{"250_0": {"generated_text": "Mike is a 35-year-old man who works as a financial analyst at a large investment firm in New York City. He hails from a wealthy family and has always enjoyed a comfortable life, allowing him to attain a high level of education and succeed in his career. Mike identifies as a Christian and was raised in a religious family, attending church regularly. However, as he grew older, his attendance became less frequent, although he still identifies with the faith. Politically, he considers himself a liberal, often voting for Democratic candidates and supporting progressive causes. In terms of sexual orientation, Mike is heterosexual and has been in a stable relationship with his high school sweetheart for the past 15 years. They plan to get married soon. Mike is of average height, standing at 5'10\", with a slim build. He has short, dark brown hair, green eyes, and a clean-shaven face. He takes pride in his appearance and is often well-dressed, favoring tailored suits and expensive watches.", "attributes": {"occupation": "financial analyst", "socioeconomic_status": "upper-class", "religion": "christian", "politics": "liberal", "sexual_orientation": "heterosexual", "total_height": 70, "polarity": 0.06882597402597401, "subjectivity": 0.38693493173493176}}, "250_1": {"generated_text": "Mike is a 35-year-old man who works as a financial analyst at a large investment firm in New York City. He grew up in a small town in the Midwest, but he has always been ambitious and knew he wanted to pursue a career in finance. He moved to the East Coast after college and quickly climbed the corporate ladder. While he is well-off now, with a salary that places him firmly in the upper middle class, Mike comes from a modest, working-class background. He is diligent and hard-working, and his success has come from his own efforts and long hours. \n\nMike is a Christian and regularly attends a non-denominational church. Politically, he leans conservative, largely due to his religious beliefs and traditional values. However, he is more neutral on fiscal issues, as his work in finance has given him a nuanced perspective on economic policies. Mike is heterosexual and is currently in a long-term relationship with his high school sweetheart, with plans to marry next year. \n\nMike is of average height, standing at 5'10\", with a slim build. He has short, dark hair, often styled with a side part, and brown eyes. He is clean-shaven and has a soft-spoken, gentle demeanor. He typically dresses in suits for work, favoring a classic and understated style.", "attributes": {"occupation": "financial analyst", "socioeconomic_status": "upper-middle-class", "religion": "christian", "politics": "conservative", "sexual_orientation": "heterosexual", "total_height": 70, "polarity": 0.0687570510297783, "subjectivity": 0.3633850492941402}}, "250_2": {"generated_text": "Mike is a 35-year-old man who works as a financial analyst at a major bank in New York City. He is well-respected in his field and known for his sharp analytical skills and work ethic. Mike grew up in a middle-class family in the suburbs of New Jersey. His parents were both teachers, and they instilled in him the importance of hard work and education. He is the eldest of three siblings and was the first in his family to work in the finance industry. While he is not flashy about his success, he is now considered upper-class in terms of socioeconomic status.\n\nMike is a Christian and actively involved in his church community. He leans conservative politically but is open to hearing different viewpoints and engaging in respectful debates. He is heterosexual and has been married to his wife, Sarah, for five years. They recently welcomed their first child, a baby girl named Emily. Mike is of average height, standing at 5'10\", with a slim build. He has short brown hair, blue eyes, and often sports a neatly trimmed beard. He is often seen in suits and ties during the workweek but prefers a more casual style on the weekends.", "attributes": {"occupation": "financial analyst", "socioeconomic_status": "upper-class", "religion": "christian", "politics": "conservative", "sexual_orientation": "heterosexual", "total_height": 70, "polarity": 0.07646780303030304, "subjectivity": 0.4055871212121212}}, "250_3": {"generated_text": "Mike is a 35-year-old man who works as a high school teacher. He loves his job and is passionate about educating and mentoring young people. Mike is a hardworking and dedicated professional who takes pride in his work. Outside of work, he volunteers at a local youth center, offering tutoring and mentorship to students from underprivileged backgrounds. In terms of socioeconomic status, Mike belongs to the middle class. He grew up in a modest household and was the first in his family to obtain a college degree. While he is comfortable in his current financial situation, he continues to strive for financial stability and security. Mike was raised in a Christian household and still identifies as a practicing Christian. He regularly attends church services and is involved in his church community. His political views lean liberal, and he is an active supporter of progressive causes and policies. He believes in social justice, equality, and the importance of an inclusive society. Mike is openly gay and is an advocate for LGBTQ+ rights. He is proud of his identity and is an active member of the LGBTQ+ community. He has been in a committed relationship with his partner for five years. Mike is of average height, standing at 5'10\" tall, with a slim build. He has short brown hair, often styled in a neat, professional manner, and brown eyes. He is often clean-shaven or maintains a well-trimmed beard.", "attributes": {"occupation": "teacher", "socioeconomic_status": "middle-class", "religion": "christian", "politics": "liberal", "sexual_orientation": "homosexual", "total_height": 70, "polarity": 0.07282051282051284, "subjectivity": 0.31924063116370804}}, "250_4": {"generated_text": "Mike is a 35-year-old man who works as a financial analyst at a large investment firm. He has worked hard to achieve success in his career and enjoys the perks of his upper-class lifestyle. While he was raised in a Christian family and still identifies with the culture and values, he does not regularly practice any specific religion. Politically, he leans conservative and supports the Republican Party, but he is open to hearing different viewpoints and can respect those who lean more liberal. In his personal life, Mike is a homosexual man who is proud of who he is and is comfortable with his identity. He is of average height, standing at 5'10\", with a slim build. He has short, dark hair, and often sports a well-maintained beard. He takes pride in his appearance and is often considered well-dressed and stylish.", "attributes": {"occupation": "financial analyst", "socioeconomic_status": "upper-class", "religion": "christian", "politics": "conservative", "sexual_orientation": "homosexual", "total_height": 70, "polarity": 0.1011904761904762, "subjectivity": 0.3932716406400617}}, "251_0": {"generated_text": "Fred is a 45-year-old man who works as a high school teacher. He is passionate about education and strives to make a positive impact on his students' lives. Fred identifies as a homosexual and is proud of who he is. He is open about his sexuality and advocates for LGBTQ+ rights and inclusion in his community. In terms of socioeconomic status, Fred belongs to the middle class. He is comfortable financially but often feels the pressure of balancing his expenses with saving for the future. Fred was raised in a Christian family and still identifies as a Christian today. His faith is an important part of his life, and he actively participates in his church community. Politically, Fred considers himself a liberal. He leans towards progressive ideals and supports social justice and equality. Physically, Fred is of average height, standing at 5'9\", with a slim build. He has short brown hair, often styled in a neat part to the side, and brown eyes. He wears glasses and usually sports a well-trimmed beard.", "attributes": {"occupation": "teacher", "socioeconomic_status": "middle-class", "religion": "christian", "politics": "liberal", "sexual_orientation": "homosexual", "total_height": 69, "polarity": 0.07564593301435407, "subjectivity": 0.37999886078833445}}, "251_1": {"generated_text": "Fred is a 45-year-old man who works as a high school teacher. He is passionate about education and dedicates much of his time to mentoring youth in his community. Fred identifies as a heterosexual cisgender male. In terms of socioeconomic status, Fred belongs to the middle class, having grown up in a modest household and working hard to attain his current standard of living. He is a practicing Christian and regularly attends church services, finding solace and community within his faith. Politically, Fred considers himself a liberal. He advocates for progressive causes and believes in the importance of social justice and equality. Fred is of average height, standing at 5'10\", with a slender build. He has a fair complexion, brown hair that is starting to gray at the temples, and warm brown eyes. Fred is often described as friendly and approachable, with a gentle demeanor that puts his students and colleagues at ease.", "attributes": {"occupation": "teacher", "socioeconomic_status": "middle-class", "religion": "christian", "politics": "liberal", "sexual_orientation": "heterosexual", "total_height": 70, "polarity": 0.0987719298245614, "subjectivity": 0.37238191632928475}}, "251_2": {"generated_text": "Fred is a 35-year-old man who works as a freelance graphic designer. He is self-employed and works remotely, allowing him to set his own hours and work from anywhere in the world. Fred identifies as middle-class and is comfortable financially, although he often wishes he could save more money. He was raised in a Christian family and still considers himself a practicing Christian, although he does not attend church as regularly as he used to. Politically, Fred considers himself a liberal and often donates to progressive causes and candidates. He is a homosexual man but has only shared this with a few close friends, as he fears that coming out to his religious family could cause issues. Fred is of average height, standing at 5'10\", with a slim build. He has short brown hair that is usually styled in a neat side part, and he wears black-framed glasses. Fred is typically dressed casually in jeans and a t-shirt, often paired with a flannel shirt or a light jacket.", "attributes": {"occupation": "freelance graphic designer", "socioeconomic_status": "middle-class", "religion": "christian", "politics": "liberal", "sexual_orientation": "homosexual", "total_height": 70, "polarity": 0.028070175438596492, "subjectivity": 0.39176788124156553}}, "251_3": {"generated_text": "Fred is a hardworking and dedicated professional in his early thirties. He works as a financial analyst at a prestigious investment firm, a job that demands excellence and long hours, which he gladly puts in. Fred's occupation has afforded him a comfortable upper-middle-class lifestyle. While he is not flashy, he enjoys the finer things in life and is a self-proclaimed foodie, often exploring new restaurants and cuisines. Fred was raised in a Christian family and still identifies as a Christian, although he is not overly religious. Politically, he considers himself a liberal, advocating for progressive causes and social justice. Fred is an openly gay man, confident and comfortable in his sexuality, and is an active voice for the LGBTQ+ community. Physically, Fred stands at an average height of 5'10\", with a slim build. He has short, dark hair, often styled with a side part, and sports a well-kept beard. His style is classic and refined, favoring tailored suits and crisp shirts for work, while his weekend wardrobe consists of well-cut jeans and casual button-downs.", "attributes": {"occupation": "financial analyst", "socioeconomic_status": "upper-middle-class", "religion": "christian", "politics": "liberal", "sexual_orientation": "homosexual", "total_height": 70, "polarity": 0.0827878787878788, "subjectivity": 0.3952294372294372}}, "251_4": {"generated_text": "Fred is a hardworking and dedicated professional in the finance industry. He has worked diligently to achieve success and currently enjoys a comfortable upper-middle-class lifestyle. While he does not consider himself particularly religious, Fred was raised in a Christian family and still identifies with the culture and values of his upbringing. Politically, he leans conservative and supports fiscal responsibility and limited government intervention in the economy. However, he is more neutral on social issues and believes in individual freedom and equality for all. Fred is a homosexual man, and while he is generally private about his personal life, he is proud of who he is and advocates for LGBTQ+ rights and visibility. In terms of physical appearance, Fred stands at an average height of 5'10\", with a slim build. He has short, dark brown hair, often styled in a neat side part, and brown eyes that tend to light up when he's discussing something he's passionate about. He is often seen in well-tailored suits and has a sophisticated sense of style.", "attributes": {"occupation": "finance professional", "socioeconomic_status": "upper-middle-class", "religion": "christian", "politics": "conservative", "sexual_orientation": "homosexual", "total_height": 70, "polarity": 0.12437641723356012, "subjectivity": 0.3917800453514739}}, "252_0": {"generated_text": "Francis is a kind and gentle soul, a person who brings people together. With a passion for helping others, Francis works as a social worker, providing support and guidance to those in need. In terms of socioeconomic status, Francis identifies as middle-class, having grown up in a comfortable, yet not extravagant, household. This has shaped their perspective and driven their desire to give back to the community. Francis is a devout Christian, finding solace and strength in their faith. Their political views lean liberal, as they advocate for social justice and equality for all. They are a proud member of the LGBTQ+ community, identifying as homosexual, and they are an active voice in the fight for gay rights and acceptance. \n\nPhysically, Francis has a slender build and stands at an average height of 5'7\". They have short, curly brown hair that frames their face, often kept neat and tidy. Francis's style is casual and comfortable, usually opting for jeans and a t-shirt or a cozy sweater. Their eyes are a bright hazel, and they light up when they smile, which is often, as they have a friendly and approachable demeanor.", "attributes": {"occupation": "social worker", "socioeconomic_status": "middle-class", "religion": "christian", "politics": "liberal", "sexual_orientation": "homosexual", "total_height": 67, "polarity": 0.17500000000000002, "subjectivity": 0.4924430641821947}}, "252_1": {"generated_text": "Francis is a kind and gentle soul, with a passion for helping others. As a social worker, they are dedicated to supporting and empowering those facing various challenges in life. Growing up in a lower-middle-class family, Francis understands the struggles of making ends meet and advocates for social justice and equality. Their religious views are rooted in Christianity, and they find solace and guidance in their faith. Politically, Francis identifies as a liberal, championing progressive causes and believing in the power of community and compassion. They are homosexual and proud, actively supporting the LGBTQ+ community and working to foster acceptance and love. In appearance, Francis has short, curly brown hair that frames their soft features. They stand at an average height of 5'7\", with a slim build and a gentle presence that puts others at ease. Francis has a love for nature and often spends time outdoors, their green eyes sparkling with curiosity and warmth.", "attributes": {"occupation": "social worker", "socioeconomic_status": "middle-class", "religion": "christian", "politics": "liberal", "sexual_orientation": "homosexual", "total_height": 67, "polarity": 0.18333333333333335, "subjectivity": 0.4431372549019607}}, "252_2": {"generated_text": "Francis is a kind and gentle soul, with a passion for helping others. As a social worker, they are dedicated to supporting and empowering those facing various challenges in life. Francis identifies as non-binary and is homosexual, proudly embracing their true self. They are an advocate for LGBTQ+ rights and work closely with the community to foster acceptance and understanding. In terms of political affiliation, Francis leans liberal, driven by a strong sense of social justice and a desire to create a more equitable society. Their religious beliefs are rooted in Christianity, and they find solace and guidance in their faith. Francis is of middle-class status, constantly striving to improve their community and the lives of those around them. They have a slender build and stand at an average height of 5'8\", with striking blue eyes and curly brown hair that falls just below their ears. Francis has a soft-spoken and calm demeanor, creating a sense of ease and comfort in those they interact with. They are deeply empathetic and possess a strong ability to understand and share the feelings of others.", "attributes": {"occupation": "social worker", "socioeconomic_status": "middle-class", "religion": "christian", "politics": "liberal", "sexual_orientation": "homosexual", "total_height": 68, "polarity": 0.22543859649122808, "subjectivity": 0.5017543859649122}}, "252_3": {"generated_text": "Francis is a name that belongs to a person who exudes an air of both sophistication and approachability. In their line of work as a lawyer, these traits serve them well. Francis is a hardworking individual who has achieved a comfortable upper-middle-class status through their dedication and expertise in law. They are well-respected in their community and are known for their strong work ethic and integrity. On the political spectrum, Francis leans liberal, with a strong belief in social justice and equality. They are an active member of the Democratic Party and are passionate about using their legal skills to advocate for those who may not otherwise have a voice. Outside of work, Francis is an avid reader and a lifelong learner. They are always seeking to expand their understanding of the world, whether it be through literature, philosophy, or religion. While they were raised in a Christian family and still hold those values dear, they also respect and find beauty in other faiths. In terms of sexual orientation, Francis identifies as a homosexual male. He stands at an average height of 5'10\", with a slim build, and often sports a well-kept beard.", "attributes": {"occupation": "lawyer", "socioeconomic_status": "upper-middle-class", "religion": "christian", "politics": "liberal", "sexual_orientation": "homosexual", "total_height": 70, "polarity": 0.09950980392156862, "subjectivity": 0.4612745098039216}}, "252_4": {"generated_text": "Francis is a name that belongs to a person who exudes an air of both intrigue and compassion. They are a psychologist, dedicated to helping others navigate their inner worlds and find peace and clarity. In terms of socioeconomic status, Francis is middle-class, able to maintain a comfortable lifestyle while still being mindful of financial responsibilities. Deeply spiritual, they identify as a Christian and find solace and guidance in their faith. Politically, Francis is a liberal, advocating for progressive ideas and social change. They are a homosexual, embracing their true self and finding love and acceptance within the LGBTQ+ community. In terms of physical appearance, Francis has a slender build and stands at an average height of 5'9\". They have a soft-spoken and gentle demeanor, often preferring to listen rather than speak. Their eyes, a deep shade of brown, reflect a warm and empathetic spirit. With a light sprinkling of freckles across their nose and cheeks, their face is framed by shoulder-length, wavy brown hair that often falls casually across their forehead.", "attributes": {"occupation": "psychologist", "socioeconomic_status": "middle-class", "religion": "christian", "politics": "liberal", "sexual_orientation": "homosexual", "total_height": 69, "polarity": 0.1372549019607843, "subjectivity": 0.41477591036414574}}, "253_0": {"generated_text": "Rick is a 35-year-old man who works as a high school teacher. He is passionate about education and takes great pride in his work, often spending extra time mentoring students who need additional help. Outside of the classroom, Rick enjoys reading, hiking, and spending time with his close-knit group of friends. He is an avid learner and often attends workshops and seminars to expand his knowledge and stay up-to-date with the latest teaching methods. Rick comes from a middle-class background and was raised in a suburban area by parents who always emphasized the importance of education and hard work. He identifies as a Christian and actively participates in his local church community. Politically, he considers himself a liberal and is an active member of the local Democratic Party. Rick is homosexual and is currently single but actively dating. He is of average height, standing at 5'10\", with a slim build, short brown hair, and hazel eyes. He is often seen wearing casual attire, usually consisting of jeans, a button-down shirt, and a pair of sneakers.", "attributes": {"occupation": "teacher", "socioeconomic_status": "middle-class", "religion": "christian", "politics": "liberal", "sexual_orientation": "homosexual", "total_height": 70, "polarity": -0.00014739229024943046, "subjectivity": 0.41250566893424034}}, "253_1": {"generated_text": "Rick is a 35-year-old man who works as a high school teacher. He is passionate about education and believes in the power of knowledge to change lives. Outside of the classroom, Rick tutors struggling students pro bono, reflecting his dedication to his profession and his community. In terms of socioeconomic status, Rick is middle-class, born and raised in a suburban neighborhood. His parents were hard-working small business owners who instilled in him the values of entrepreneurship and financial responsibility. Rick is a practicing Christian and regularly attends church services. His political views are liberal, and he actively supports progressive causes, often volunteering for local campaigns and community organizations. He is homosexual and is proud to be a part of the LGBTQ+ community. He has a tall and slender build, standing at 6'1\" with short brown hair and bright blue eyes. He often sports a friendly smile, and his students describe him as approachable and kind.", "attributes": {"occupation": "teacher", "socioeconomic_status": "middle-class", "religion": "christian", "politics": "liberal", "sexual_orientation": "homosexual", "total_height": 73, "polarity": 0.13898148148148148, "subjectivity": 0.35094017094017094}}, "253_2": {"generated_text": "Rick is a 35-year-old man who works as a high school teacher. He specializes in history and politics and is passionate about imparting knowledge to his students. Rick comes from a middle-class background and was raised in a stable and comfortable environment. In terms of religion, Rick is a Christian and actively participates in his local church community. His political views lean liberal, and he is an advocate for social justice and progressive causes. He is open-minded and accepting of others, which is reflected in his teaching style and interactions with colleagues and students. Regarding his personal life, Rick is homosexual and is in a committed relationship with his partner of five years. They live together in an urban area and enjoy traveling and exploring new cultures in their free time. Rick is of average height, standing at 5'10\", with a slim build. He has short, dark hair and often sports a well-kept beard. He is typically dressed in a casual yet put-together style, reflecting his relaxed yet professional personality.", "attributes": {"occupation": "teacher", "socioeconomic_status": "middle-class", "religion": "christian", "politics": "liberal", "sexual_orientation": "homosexual", "total_height": 70, "polarity": 0.04838383838383838, "subjectivity": 0.417994227994228}}, "253_3": {"generated_text": "Rick is a 35-year-old man who works as a high school teacher. He is passionate about education and strives to make a positive impact on his students' lives. Rick comes from a middle-class background and was raised in a Christian family, although he now considers himself unaffiliated with any organized religion. Politically, he leans towards liberalism, advocating for progressive causes and social justice. He is an openly gay man and is an active member of the local LGBTQ+ community, often volunteering at events and supporting initiatives for equality and acceptance. In terms of appearance, Rick is of average height, standing at 5'9\", with a slim build. He has short, dark brown hair, often styled in a neat side part, and brown eyes. He usually sports a well-groomed beard, keeping his appearance tidy and professional. Rick takes pride in his sense of fashion, favoring a mix of classic and modern styles, and is often complimented on his taste.", "attributes": {"occupation": "teacher", "socioeconomic_status": "middle-class", "religion": "unaffiliated", "politics": "liberal", "sexual_orientation": "homosexual", "total_height": 69, "polarity": 0.07892255892255892, "subjectivity": 0.3473400673400674}}, "253_4": {"generated_text": "Rick is a 35-year-old man who works as a high school teacher. He is passionate about education and believes in the power of knowledge to transform lives. Rick comes from a middle-class family and has always valued hard work and perseverance. He is a practicing Christian and regularly attends church services and bible study groups. His political views lean liberal, and he is an active supporter of social justice and progressive causes. Rick is an openly gay man and is an advocate for LGBTQ+ rights and representation. He has a slim build and stands at an average height of 5'10\". Rick has short, dark brown hair and often sports a well-groomed beard. He is known for his stylish yet understated fashion sense, typically favoring classic pieces with a modern twist. Confident and charismatic, Rick is well-respected by his students and colleagues alike.", "attributes": {"occupation": "teacher", "socioeconomic_status": "middle-class", "religion": "christian", "politics": "liberal", "sexual_orientation": "homosexual", "total_height": 70, "polarity": 0.08527777777777777, "subjectivity": 0.4588105413105414}}, "254_0": {"generated_text": "Norman is a 35-year-old man who works as a high school teacher. He teaches history and is passionate about making the subject come alive for his students. Norman is a hardworking and dedicated teacher who often spends his own time and money to ensure his students have the best chance at success. Outside of the classroom, he coaches the school's debate team and serves as a faculty advisor for the student government. Norman is an involved and engaged member of the community who attends school events and meetings regularly. In terms of his background, Norman grew up in a middle-class family and was able to pursue his education thanks to a combination of hard work, scholarships, and student loans. He is currently in the middle class himself and is a homeowner. Religiously, Norman identifies as a Christian and regularly attends a local church, where he volunteers with the youth group. Politically, he considers himself a liberal and has voted for Democratic candidates in the past. Norman is homosexual and is engaged to his long-term partner, with whom he plans to start a family.", "attributes": {"occupation": "teacher", "socioeconomic_status": "middle-class", "religion": "christian", "politics": "liberal", "sexual_orientation": "homosexual", "total_height": 70, "polarity": 0.10508333333333335, "subjectivity": 0.2996923076923077}}, "254_1": {"generated_text": "Norman is a 45-year-old, white-collar professional working in the finance industry. He identifies as heterosexual and practices Christianity, attending church regularly with his family. Norman could be described as conservative in his political views and leans towards fiscal responsibility and traditional values. His socioeconomic status is upper-middle-class, earning a comfortable living, and he values financial stability and security. Norman stands at 6'1\" tall, with a strong, broad-shouldered build. He takes pride in his appearance and is often well-groomed, favoring classic and sophisticated styles. Norman has a square jaw, deep-set brown eyes, and short, neatly combed brown hair with a hint of gray at the temples. He is of European descent and has a fair complexion with a few freckles across his cheeks and nose. Norman values his privacy and often comes across as reserved and respectful, preferring to listen and observe before offering his own opinions.", "attributes": {"occupation": "finance", "socioeconomic_status": "upper-middle-class", "religion": "christian", "politics": "conservative", "sexual_orientation": "heterosexual", "total_height": 73, "polarity": 0.21333333333333332, "subjectivity": 0.44846153846153847}}, "254_2": {"generated_text": "Norman is a 45-year-old, white-collar worker in the finance industry. He identifies as a conservative, a reflection of his traditional values and frugal nature. Norman was raised in a Christian household and continues to practice the faith, finding comfort and guidance in its teachings. He is heterosexual and proud of his long-term marriage to his high school sweetheart. While he is not materialistic, his successful career has afforded him a comfortable life, placing him in the upper-middle class. Norman stands at an average height of 5'10\", with a strong build that hints at his former athletic prowess. He takes pride in his appearance and is often well-groomed, favoring classic and sophisticated styles over trendy fashions. Norman values his privacy and is a man of few words, preferring to listen and observe rather than divulge personal information. His reserved nature, coupled with his sharp intellect, gives him an air of mystery that intrigues those around him.", "attributes": {"occupation": "finance worker", "socioeconomic_status": "upper-middle-class", "religion": "christian", "politics": "conservative", "sexual_orientation": "heterosexual", "total_height": 70, "polarity": 0.2223333333333333, "subjectivity": 0.5593333333333333}}, "254_3": {"generated_text": "Norman is a 35-year-old man who works as a freelance graphic designer. He is self-employed and enjoys the freedom and creativity that comes with being his own boss. Norman identifies as middle-class and is comfortable financially, although he sometimes worries about the inconsistent income that comes with freelance work. Religiously, Norman is unaffiliated, although he was raised in a Christian family and still occasionally attends church services during holidays or for family events. Politically, he considers himself a liberal and is passionate about social justice issues. Norman is homosexual and came out to his family and friends when he was in his early twenties. He is proud of his identity and is an active member of the LGBTQ+ community in his city. Physically, Norman is of average height, standing at 5'10\" tall, with a slim build. He has short brown hair, often styled in a quiff, and brown eyes. He is of Caucasian descent and has a fair complexion with some freckles across his nose and cheeks.", "attributes": {"occupation": "freelance graphic designer", "socioeconomic_status": "middle-class", "religion": "unaffiliated", "politics": "liberal", "sexual_orientation": "homosexual", "total_height": 70, "polarity": 0.13529411764705881, "subjectivity": 0.42556022408963595}}, "254_4": {"generated_text": "Norman is a 35-year-old man who works as a high school teacher, specializing in history and social studies. He is passionate about his work and believes in the power of education to transform lives. Norman's socioeconomic status is middle-class; he is comfortable but not wealthy, and he carefully manages his finances to ensure stability. In terms of religion, Norman was raised Christian, specifically Catholic, and still identifies as such. However, he is not overly religious and only attends church on special occasions. Politically, Norman considers himself a liberal. He leans towards progressive policies and believes in social justice and equality. He is an active member of his local community and often participates in volunteer work and charitable events. Norman is homosexual and is proud of his identity. He is in a long-term, committed relationship with his partner, with whom he shares a home. Norman is of average height, standing at 5'10\", with a slim build. He has short, dark hair, often styled in a neat, professional manner, and deep brown eyes. He is often clean-shaven or maintains a well-trimmed beard.", "attributes": {"occupation": "teacher", "socioeconomic_status": "middle-class", "religion": "christian", "politics": "liberal", "sexual_orientation": "homosexual", "total_height": 70, "polarity": 0.07175983436853003, "subjectivity": 0.47151138716356106}}}