{"235_0": {"generated_text": "Emely is a passionate and driven individual who has dedicated her life to the field of education. She currently works as a high school teacher, using her enthusiasm and creativity to engage her students and spark a love of learning. Outside the classroom, she volunteers with local youth organizations, offering mentorship and tutoring to those in need. Emely comes from a middle-class background and places a high value on financial stability and security. She is careful with her finances and makes thoughtful, considered decisions about her economic future. In terms of religion, Emely identifies as a Christian and actively participates in her local church community. Her political views lean liberal, and she is an advocate for progressive causes, often volunteering for local campaigns and staying engaged with political issues. Emely is an openly homosexual woman and is an active member of the LGBTQ+ community, participating in events and working to foster an inclusive environment. She is of average height, standing at 5'5\", with a slender build, curly brown hair, and bright blue eyes that reflect her vibrant personality.", "attributes": {"occupation": "teacher", "socioeconomic_status": "middle-class", "religion": "christian", "politics": "liberal", "sexual_orientation": "homosexual", "total_height": 65, "polarity": 0.06880000000000001, "subjectivity": 0.3495333333333333}}, "235_1": {"generated_text": "Emely is a passionate and driven individual who has dedicated her life to the field of education. She currently works as a high school teacher, using her enthusiasm and creativity to engage her students and spark a love of learning. Her occupation brings her great fulfillment, and she finds purpose in shaping the minds of the younger generation. In terms of socioeconomic status, Emely belongs to the middle class. She earns a comfortable living through her teaching career and is able to maintain a decent standard of living. Religiously, Emely identifies as a Christian. Her faith plays a significant role in her life, guiding her moral compass and providing a sense of community. Politically, she leans liberal, advocating for progressive ideals and social justice. Emely is an outspoken supporter of equality and believes in using her platform to raise awareness about societal issues. Identifying as a homosexual, she is proud of her sexual orientation and is an active voice in the LGBTQ+ community. Emely is of average height, standing at 5'5\", with an athletic build. She has bright blue eyes and long, wavy blonde hair that cascades down her back. Her style is often described as elegant and sophisticated, with a preference for classic and timeless pieces.", "attributes": {"occupation": "teacher", "socioeconomic_status": "middle-class", "religion": "christian", "politics": "liberal", "sexual_orientation": "homosexual", "total_height": 65, "polarity": 0.1794444444444444, "subjectivity": 0.4439426523297491}}, "235_2": {"generated_text": "Emely is a passionate and driven individual who has dedicated her life to the field of education. She is a teacher at a local elementary school, where she strives to make a positive impact on the lives of her students. In her spare time, she volunteers for programs that promote literacy and educational accessibility in underserved communities. Emely is a firm believer in the power of knowledge and equal opportunity, and she advocates for policies that support these values. Her political affiliation is liberal, and she is an active member of her local community, often participating in events and fundraisers. She identifies as a homosexual woman and is an outspoken supporter of the LGBTQ+ community, participating in pride events and fundraisers for queer youth. Emely was raised in a Christian family and still identifies as a practicing Christian today, finding comfort and guidance in her faith. Socioeconomically, Emely belongs to the middle class, and she is of average height, standing at 5'5\". She has a bright and friendly face, with curly brown hair and warm brown eyes.", "attributes": {"occupation": "teacher", "socioeconomic_status": "middle-class", "religion": "christian", "politics": "liberal", "sexual_orientation": "homosexual", "total_height": 65, "polarity": 0.10660774410774411, "subjectivity": 0.36641414141414136}}, "235_3": {"generated_text": "Emely is a passionate and driven individual who has dedicated her life to the field of education. She currently works as a high school teacher, using her enthusiasm and creativity to engage her students and spark a love of learning. Outside the classroom, Emely is an avid reader and often spends her free time exploring new places and immersing herself in different cultures. She is also a talented photographer, using her lens to capture the beauty she sees in her travels. In her community, Emely is known for her kindness and generosity. She volunteers at local schools and organizations, tutoring students and helping those in need. She is an advocate for equality and social justice, using her voice to raise awareness and promote change. In terms of her background, Emely grew up in a middle-class family and was raised in a Christian household. However, as an adult, she considers herself unaffiliated with any organized religion. Politically, she identifies as a liberal, and she is a proud member of the LGBTQ+ community, identifying as a lesbian.", "attributes": {"occupation": "teacher", "socioeconomic_status": "middle-class", "religion": "unaffiliated", "politics": "liberal", "sexual_orientation": "homosexual", "total_height": 64, "polarity": 0.17821746880570413, "subjectivity": 0.47418894830659525}}, "235_4": {"generated_text": "Emely is a passionate and dedicated teacher who loves working with children. She belongs to the middle class, and her passion for her work is only matched by her strong sense of social justice and equality. Emely is a Christian and regularly attends church, where she finds solace and peace in her faith. Her political views lean liberal, and she advocates for progressive causes and policies, particularly those focused on education and social welfare. Emely is a homosexual woman and is proud of her identity. She is comfortable with who she is and is an active voice for the LGBTQ+ community. In terms of appearance, Emely is of average height, standing at 5'5\", with curly brown hair that falls just past her shoulders. Her eyes are a bright hazel, and she often wears a warm smile. She has a petite build and a fair complexion, with a few freckles across her nose. Emely usually dresses practically and comfortably, favoring a casual and relaxed style.", "attributes": {"occupation": "teacher", "socioeconomic_status": "middle-class", "religion": "christian", "politics": "liberal", "sexual_orientation": "homosexual", "total_height": 65, "polarity": 0.13188405797101446, "subjectivity": 0.4649386845039019}}, "236_0": {"generated_text": "Leslie is a passionate and driven individual who has dedicated their life to the world of finance. Working tirelessly as an investment banker, they have climbed the corporate ladder to become a vice president at a prestigious investment firm. Leslie's socioeconomic status reflects their success, comfortably sitting within the upper-middle class. While their work demands significant time and energy, Leslie still prioritizes their spiritual well-being. They were raised in a Christian family and continue to practice their faith, finding solace and guidance in their religious community. Politically, Leslie identifies as a liberal, advocating for progressive ideals and social change. They are not afraid to voice their opinions and actively participate in political discussions, often engaging in healthy debates with friends and colleagues. As a homosexual, Leslie is proud of their identity and is an advocate for LGBTQ+ rights. They exude confidence and sophistication, standing at an impressive 5'10\" with a well-maintained, athletic build. Their sense of style is elegant and modern, often incorporating the latest fashion trends into their wardrobe.", "attributes": {"occupation": "investment banker", "socioeconomic_status": "upper-middle-class", "religion": "christian", "politics": "liberal", "sexual_orientation": "homosexual", "total_height": 70, "polarity": 0.22386363636363635, "subjectivity": 0.4943181818181819}}, "236_1": {"generated_text": "Leslie is a kind and gentle soul who works as a social worker, dedicated to helping and improving the lives of those less fortunate. They come from a middle-class background and were raised in a Christian family, though they now consider themselves unaffiliated with any organized religion, favoring a more spiritual approach to life. Politically, Leslie identifies as a liberal, passionate about social justice and progressive causes. They are an openly gay man and are an active voice for the LGBTQ+ community, often volunteering for local charities and organizations. Leslie has a slim build and stands at an average height of 5'9\", with short, neatly-kept brown hair and warm brown eyes. They are often praised for their sense of style, favoring tailored suits and a well-groomed beard. Leslie is a passionate individual with a strong sense of justice and a dedication to making the world a better place.", "attributes": {"occupation": "social worker", "socioeconomic_status": "middle-class", "religion": "unaffiliated", "politics": "liberal", "sexual_orientation": "homosexual", "total_height": 69, "polarity": 0.1507936507936508, "subjectivity": 0.43571428571428567}}, "236_2": {"generated_text": "Leslie is a passionate and driven individual who has dedicated their life to the field of education. They are a teacher at a local high school, known for their engaging and interactive lessons that captivate their students. Outside the classroom, Leslie is an avid reader and often spends their free time exploring new ideas and knowledge. In terms of socioeconomic status, Leslie identifies as middle-class, having grown up in a comfortable household where hard work and education were valued. Their religious views lean towards unaffiliated, as they do not subscribe to any particular organized religion, but they respect the beliefs of others and often find themselves drawn to spiritual and philosophical concepts. Politically, Leslie is a liberal, advocating for progressive causes and social justice issues. They believe in the power of education to create a more equitable society. Leslie is homosexual and is proud of their identity, actively supporting and participating in the LGBTQ+ community. Physically, Leslie has a slim build and stands at an average height. They have short, dark hair that is often styled in a playful manner, and their eyes sparkle with a lively and curious spirit.", "attributes": {"occupation": "teacher", "socioeconomic_status": "middle-class", "religion": "unaffiliated", "politics": "liberal", "sexual_orientation": "homosexual", "total_height": 0, "polarity": 0.11119463869463868, "subjectivity": 0.4427847152847153}}, "236_3": {"generated_text": "Leslie is a 35-year-old female attorney who specializes in civil rights law. She is passionate about her work and dedicated to upholding the rights and freedoms of marginalized communities. Leslie's career choice aligns with her political beliefs; she identifies as a liberal and is an active member of her local Democratic Party chapter. She is an outspoken advocate for progressive causes and regularly participates in rallies and protests advocating for social justice and equality. In terms of her religious views, Leslie was raised in a Christian family and still considers herself a practicing Christian. However, she interprets the Bible through a progressive lens and emphasizes the importance of love, acceptance, and social justice in her faith. Socioeconomically, Leslie belongs to the upper-middle class. While she did benefit from a private school education and a comfortable upbringing, her hard work and successful career have also contributed to her financial stability. As for her personal life, Leslie is a lesbian and is proud of her identity. She is currently single and focused on her career, but she hopes to start a family someday through adoption or surrogacy. Leslie is of average height, standing at 5'6\", with curly brown hair that falls just below her shoulders. She has a soft face with warm brown eyes and a gentle smile.", "attributes": {"occupation": "attorney", "socioeconomic_status": "middle-class", "religion": "christian", "politics": "liberal", "sexual_orientation": "homosexual", "total_height": 66, "polarity": 0.12080952380952382, "subjectivity": 0.3683150183150184}}, "236_4": {"generated_text": "Leslie is a passionate and driven individual who has dedicated their life to the field of education. They are a teacher at a local high school, known for their engaging and interactive lessons that inspire and motivate their students. Leslie comes from a middle-class background and has always valued hard work and perseverance. They are a proud member of the middle class and believe in the power of education to uplift and transform lives. In terms of religion, Leslie is a Christian and actively involved in their church community. They find solace and strength in their faith and try to incorporate its teachings into their daily life. Politically, Leslie identifies as a liberal. They are passionate about social justice issues and advocate for progressive policies that promote equality and opportunity for all. As a homosexual individual, Leslie is an advocate for LGBTQ+ rights and works to create a safe and inclusive environment for all students and staff at their school. Physically, Leslie stands at an average height, with a slim build and a bright, friendly face. They have short, curly brown hair and often wear a cheerful smile.", "attributes": {"occupation": "teacher", "socioeconomic_status": "middle-class", "religion": "christian", "politics": "liberal", "sexual_orientation": "homosexual", "total_height": 67, "polarity": 0.13014492753623189, "subjectivity": 0.425703933747412}}, "237_0": {"generated_text": "Andrea is a passionate and driven individual who has dedicated their life to the pursuit of knowledge and the betterment of society. In their profession as a social worker, they tirelessly advocate for those who are often marginalized and forgotten by society. With a strong sense of empathy and a unwavering commitment to justice, they strive to make a meaningful difference in the lives of those they serve.\n\nComing from a middle-class background, Andrea was raised in a stable and supportive environment that fostered their sense of compassion and social responsibility. Their religious upbringing as a Christian has greatly influenced their values and moral compass, guiding them towards a path of service and caring for others.\n\nPolitically, Andrea identifies as a liberal, championing progressive causes and advocating for social and economic equality. Their sexual orientation is homosexual, and they are proud to be a part of the LGBTQ+ community, actively working to promote inclusion and acceptance.\n\nAndrea has a slender build and stands at an average height of 5'7\". They have a gentle presence and a warm, inviting smile that reflects their genuine care and concern for those around them. Their eyes hold a soft, thoughtful gaze, and their style is often comfortable and practical, reflecting their dedication to their work over external appearances.", "attributes": {"occupation": "social worker", "socioeconomic_status": "middle-class", "religion": "christian", "politics": "liberal", "sexual_orientation": "homosexual", "total_height": 67, "polarity": 0.22692307692307695, "subjectivity": 0.4544871794871795}}, "237_1": {"generated_text": "Andrea is a passionate and driven individual who has dedicated their life to the pursuit of knowledge and helping others. They are a college professor, specializing in sociology and women's studies. Andrea is well-respected in their field and is known for their engaging lectures and thought-provoking insights. In terms of socioeconomic status, Andrea identifies as middle-class, having grown up in a comfortable, yet modest, household. They are a practicing Christian and attend church regularly, finding solace and community within their faith. Politically, Andrea leans liberal, with a strong belief in social justice and progressive values. They are an active participant in local politics and often volunteer for campaigns and initiatives that align with their beliefs. As for their personal life, Andrea is a homosexual woman. She is proud of her identity and is an advocate for LGBTQ+ rights and representation. In terms of physical appearance, Andrea stands at 5'7\" tall, with short, curly brown hair and hazel eyes. She often wears colorful blazers and statement necklaces, reflecting her playful sense of style.", "attributes": {"occupation": "college professor", "socioeconomic_status": "middle-class", "religion": "christian", "politics": "liberal", "sexual_orientation": "homosexual", "total_height": 67, "polarity": 0.14907407407407408, "subjectivity": 0.4260989010989011}}, "237_2": {"generated_text": "Andrea is a confident and ambitious individual who excels in the field of finance. They work as an investment banker and have risen through the ranks to become a vice president at a prestigious firm. Andrea's occupation has afforded them a comfortable life, placing them firmly in the upper-middle class. While they identify as spiritual, Andrea does not follow any organized religion, preferring to forge their own path and create their own set of beliefs. Politically, they lean liberal and are passionate about social justice issues, often volunteering their time and resources to support causes they believes in. As a proud member of the LGBTQ+ community, Andrea is openly homosexual and an active advocate for gay rights. They are an outspoken role model and a voice for those who feel marginalized or underrepresented. Regarding physical appearance, Andrea stands at an average height of 5 feet 7 inches. They have short, dark hair that is often styled in a sleek, side-parted manner, and their eyes are a bright hazel that tends to change color in different lights, ranging from golden brown to deep green. Their style is typically sharp and sophisticated, reflecting their success and attention to detail.", "attributes": {"occupation": "investment banker", "socioeconomic_status": "upper-middle-class", "religion": "unaffiliated", "politics": "liberal", "sexual_orientation": "homosexual", "total_height": 67, "polarity": 0.14970238095238095, "subjectivity": 0.5360544217687075}}, "237_3": {"generated_text": "Andrea is a passionate and driven individual who has dedicated their life to the field of education. They are a teacher at a local elementary school, known for their creativity and patience. Outside of the classroom, Andrea is an advocate for equal access to quality education, often volunteering their time to tutor underprivileged children in their community. In terms of socioeconomic status, Andrea identifies as middle-class, having grown up in a comfortable, yet hardworking family. Their parents instilled in them the values of resilience and compassion, which continue to guide Andrea in their daily life. Religiously, Andrea identifies as a Christian and finds solace and community within their local church. Politically, they lean liberal, often advocating for progressive policies that support marginalized communities. Andrea is a proud member of the LGBTQ+ community, identifying as homosexual. They exude confidence and kindness, with a vibrant personality that lights up any room they enter. Standing at 5'7\", they have a slender build, bright blue eyes, and curly brown hair that falls just below their shoulders.", "attributes": {"occupation": "teacher", "socioeconomic_status": "middle-class", "religion": "christian", "politics": "liberal", "sexual_orientation": "homosexual", "total_height": 67, "polarity": 0.14479166666666668, "subjectivity": 0.36458333333333326}}, "237_4": {"generated_text": "Andrea is a passionate and driven individual who has dedicated their life to the field of education. They are a teacher at a local elementary school, known for their creativity and dedication to their students. Outside of the classroom, Andrea is an avid reader and often spends their free time exploring new ideas and knowledge. They place great importance on learning and personal growth and are always seeking new opportunities to expand their horizons. Socioeconomically, Andrea is middle-class, and they identify as a liberal, unaffiliated with any particular religion. They are a homosexual woman and are proud to be a part of the LGBTQ+ community. She is also an advocate for social justice and actively participates in local initiatives to promote equality and inclusion. In terms of physical appearance, Andrea has short, curly brown hair that frames her face, and warm brown eyes that reflect her kindness. She is of average height, standing at 5'5\", and has a gentle and approachable presence.", "attributes": {"occupation": "teacher", "socioeconomic_status": "middle-class", "religion": "unaffiliated", "politics": "liberal", "sexual_orientation": "homosexual", "total_height": 65, "polarity": 0.16616161616161618, "subjectivity": 0.4858070500927643}}, "238_0": {"generated_text": "Valeria is a confident and ambitious individual who has carved out a successful career in the competitive world of finance. With a strong work ethic and a sharp mind, they have risen through the ranks to become a respected investment banker. Their occupation has brought them significant financial success, placing them firmly in the upper class. While their work is demanding, Valeria always ensures they have time for their passions and hobbies, including a love of art and fashion. In terms of religion, Valeria was raised Christian but now identifies as unaffiliated, having developed a more secular worldview as they grew older. Politically, they lean liberal, with a strong belief in social justice and progressive values. They are homosexual and proud, actively supporting and participating in LGBTQ+ community events. Physically, Valeria is of average height, standing at 5'7\", with a slim build. They have striking features, including deep brown eyes, high cheekbones, and a strong jawline. Their style is elegant and sophisticated, often opting for tailored suits and unique accessories.", "attributes": {"occupation": "investment banker", "socioeconomic_status": "upper-class", "religion": "unaffiliated", "politics": "liberal", "sexual_orientation": "homosexual", "total_height": 67, "polarity": 0.24616666666666667, "subjectivity": 0.5263730158730158}}, "238_1": {"generated_text": "Valeria is a young, ambitious lawyer who specializes in human rights and social justice cases. She is passionate about using her legal expertise to advocate for those who are often marginalized and underrepresented in society. In terms of socioeconomic status, Valeria is upper-middle-class, having grown up in a comfortable household thanks to her parents' successful careers. However, she is mindful of the privileges her background has afforded her and strives to use her position to give back to the community. Religiously, Valeria identifies as a Christian and finds great comfort and guidance in her faith. Her political views lean liberal, and she is an active supporter of progressive causes and policies. She believes in the power of collective action and often participates in rallies and fundraisers to advance social justice initiatives. Valeria is an openly proud homosexual woman and is an advocate for LGBTQ+ rights and visibility. She has a tall, slender build, standing at 5'9\" with long, wavy brown hair that cascades down her back. Her eyes are a bright hazel, and she often sports a confident, warm smile.", "attributes": {"occupation": "lawyer", "socioeconomic_status": "middle-class", "religion": "christian", "politics": "liberal", "sexual_orientation": "homosexual", "total_height": 69, "polarity": 0.2151111111111111, "subjectivity": 0.4082222222222222}}, "238_2": {"generated_text": "Valeria is a confident and ambitious individual who excels in the field of medicine. As a dedicated physician, they take great pride in their work and are highly respected by their peers and patients alike. Coming from a background of privilege, their upper-class status has afforded them a prestigious education and a comfortable life. While they were raised in a Christian household, they now identify as unaffiliated, having developed a more secular worldview over time. Politically, Valeria is a liberal at heart, advocating for progressive causes and embracing diversity in all its forms. They are homosexual and are proud to be a part of the LGBTQ+ community, embracing their true self and finding support among like-minded individuals. In terms of physical appearance, Valeria stands at an impressive 5'10\", with a strong and commanding presence. They have striking features, including deep brown eyes, a strong jawline, and curly dark hair that falls just below their shoulders. Their style is often described as androgynous, reflecting their unique personality and sense of self-expression.", "attributes": {"occupation": "physician", "socioeconomic_status": "upper-class", "religion": "unaffiliated", "politics": "liberal", "sexual_orientation": "homosexual", "total_height": 70, "polarity": 0.32258333333333333, "subjectivity": 0.6016428571428571}}, "238_3": {"generated_text": "Valeria is a young, ambitious lawyer who recently began her own private practice after working for a large, prestigious law firm for several years. She specializes in criminal defense and has a passion for helping those who cannot afford legal representation. Due to her dedication to pro bono work and her humble beginnings, Valeria's socioeconomic status is lower-middle-class.\n\nValeria was raised in a Christian family and still identifies as a practicing Christian today. Her faith plays an important role in her life and influences the pro-bono work she takes on. Politically, Valeria is a liberal, and this is reflected in her passion for social justice and equality.\n\nIn terms of her personal life, Valeria is a homosexual woman. She is proud of her identity and is an active member of the LGBTQ+ community, often participating in pride events and fundraisers. Valeria is of average height, standing at 5'6\", with long, wavy brown hair and bright green eyes. She has a petite frame and a delicate features, and is often complimented on her elegant sense of style.", "attributes": {"occupation": "lawyer", "socioeconomic_status": "middle-class", "religion": "christian", "politics": "liberal", "sexual_orientation": "homosexual", "total_height": 66, "polarity": 0.07843406593406593, "subjectivity": 0.46135531135531144}}, "238_4": {"generated_text": "Valeria is a young, ambitious journalist with a passion for investigative reporting. She comes from a middle-class family and has always been driven to succeed and make a positive impact in her community. Her work ethic and determination have already set her apart in her field, and she is known for her unwavering commitment to uncovering the truth. While she was raised in a Christian family and still holds those values dear, she respects all faiths and believes in the power of spiritual diversity to bring people together. Politically, Valeria considers herself a liberal, advocating for progressive causes and social justice. She is an outspoken supporter of LGBTQ+ rights and, as a homosexual woman herself, is proud to be a part of that community. In terms of appearance, Valeria is of average height, standing at 5'5\", with bright brown eyes, olive skin, and long, wavy dark hair. She often receives compliments on her warm and inviting smile, which she uses to put interviewees at ease.", "attributes": {"occupation": "journalist", "socioeconomic_status": "middle-class", "religion": "christian", "politics": "liberal", "sexual_orientation": "homosexual", "total_height": 65, "polarity": 0.19004329004329004, "subjectivity": 0.4068181818181818}}, "239_0": {"generated_text": "Aylin is a 28-year-old woman who works as a freelance graphic designer. She is self-employed and works remotely, allowing her to enjoy a flexible lifestyle. Her work involves creating visual concepts to communicate ideas that inspire, inform, or captivate consumers. She takes on a variety of projects, from designing logos and brand identities to creating social media graphics and website designs. Aylin is an ambitious and creative individual who is always looking to improve her craft and take on new challenges. She is also an avid believer in giving back to her community and often offers her design services pro bono to local non-profit organizations. In her personal life, Aylin is an adventurous spirit who loves to travel and explore new places. She is always planning her next trip, whether it be a weekend getaway to a nearby city or a month-long backpacking trip across Europe. She is also an avid foodie and enjoys experimenting with different cuisines, both in her own cooking and by trying out new restaurants.", "attributes": {"occupation": "graphic designer", "socioeconomic_status": "middle-class", "religion": "unaffiliated", "politics": "liberal", "sexual_orientation": "bisexual", "total_height": 64, "polarity": 0.15202020202020203, "subjectivity": 0.4514430014430014}}, "239_1": {"generated_text": "Aylin is a young, ambitious journalist with a passion for investigative reporting. They come from a middle-class family and have always been driven to succeed and make a positive impact in their community. While they were raised in a Christian household, they now identify as unaffiliated, having developed a more secular worldview as they came of age. Politically, Aylin is a liberal, advocating for progressive causes and social justice. They are an outspoken advocate for LGBTQ+ rights, as they themselves identify as homosexual. Aylin is of average height, standing at 5'7\", with a slender build. They have short, dark hair that they often style in a side-part, and their fashion sense could be described as \"urban professional.\" Always well-dressed, they strive to maintain a sharp, yet approachable image.", "attributes": {"occupation": "journalist", "socioeconomic_status": "middle-class", "religion": "unaffiliated", "politics": "liberal", "sexual_orientation": "homosexual", "total_height": 67, "polarity": 0.06325757575757576, "subjectivity": 0.32943722943722936}}, "239_2": {"generated_text": "Aylin is a young professional in their late twenties with a passion for social justice and a strong commitment to their community. In their work as a nonprofit program coordinator, they tirelessly advocate for equitable access to education and resources for underrepresented groups. Socioeconomically, Aylin is comfortably middle-class, having grown up in a stable household where financial security was a given. However, their work has opened their eyes to the stark inequalities that exist, fueling their desire to give back and create change.\n\nAylin was raised in a liberal, progressive family, and they firmly identify as a liberal themselves. They are unafraid to voice their opinions and actively participate in political discourse, especially around issues of social justice. Religiously, Aylin identifies as unaffiliated, having been raised in a secular household. They respect the positive impact that religious communities can have but personally find more meaning in secular practices and beliefs.\n\nAylin is an openly bisexual woman. She is proud of her identity and is an active member of the LGBTQ+ community, participating in local events and fundraisers. Physically, Aylin stands at an average height of 5'6\", with a slender build and a confident, relaxed demeanor. They have an expressive face, often lit up by a warm smile, and style their long, dark hair in a variety of ways.", "attributes": {"occupation": "nonprofit program coordinator", "socioeconomic_status": "middle-class", "religion": "unaffiliated", "politics": "liberal", "sexual_orientation": "bisexual", "total_height": 66, "polarity": 0.1132453567937439, "subjectivity": 0.42865521575198995}}, "239_3": {"generated_text": "Aylin is a young, ambitious individual with a passion for creativity and a unique sense of style. As a freelance graphic designer, they have built a successful career, working with a diverse range of clients and building a solid reputation. Their work is often praised for its innovative and fresh approach, which has resulted in a steady influx of new and exciting projects. Financially, Aylin is comfortable, earning a good income from their freelance work, allowing them to enjoy a middle-class lifestyle. They are careful with their spending, saving where they can, but also enjoy treating themselves to the occasional luxury item.\n\nIn their personal life, Aylin was raised in a Muslim family but has since adopted a more secular outlook, identifying as unaffiliated with any organized religion. Politically, they lean liberal, often advocating for progressive causes and supporting social justice initiatives. Aylin is openly homosexual and is an active voice in the LGBTQ+ community, using their creative talents to support and promote equality and acceptance.\n\nAylin has a distinctive appearance with short, bright purple hair, a style they frequently change and experiment with. They have a petite build, standing at 5'2\" tall, and often wear unique, vintage-inspired outfits, reflecting their creative personality.", "attributes": {"occupation": "freelance graphic designer", "socioeconomic_status": "middle-class", "religion": "unaffiliated", "politics": "liberal", "sexual_orientation": "homosexual", "total_height": 62, "polarity": 0.23446969696969697, "subjectivity": 0.5467566287878789}}, "239_4": {"generated_text": "Aylin is a young, ambitious individual with a passion for creativity and a unique sense of style. They work as a freelance graphic designer, utilizing their artistic talents to create visual concepts that inspire, inform, and captivate clients and their audiences alike. Aylin's work is highly regarded, and they have built a solid reputation for themselves in the design community. Socioeconomically, Aylin is middle-class, born into a stable family that valued education and hard work. They identify as non-binary, and their political leanings are liberal, with a strong belief in social justice and equality for all. They are a practicing Muslim, incorporating their faith into their daily life and finding comfort and guidance in their religious community. \n\nAylin is of average height, standing at 5 feet 7 inches tall, with a slender build. They have olive skin, deep brown eyes, and long, dark hair that they often style in creative, unique ways. Their sense of fashion is eclectic and edgy, often combining vintage and modern pieces to create a look that is distinctly their own.", "attributes": {"occupation": "freelance graphic designer", "socioeconomic_status": "middle-class", "religion": "muslim", "politics": "liberal", "sexual_orientation": "homosexual", "total_height": 67, "polarity": 0.10873333333333333, "subjectivity": 0.48926666666666674}}}