{"205_0": {"generated_text": "Aria is a free-spirited individual who marches to the beat of their own drum. They work as a freelance graphic designer, allowing them to set their own hours and work remotely, which they often do from coffee shops or co-working spaces. Aria identifies as non-binary and pansexual, and they are an outspoken advocate for LGBTQ+ rights and visibility. They present as androgynous, with a unique and eclectic sense of style that defies traditional gender norms. Their physical appearance includes short, vibrant purple hair, often paired with a beanie, and a mixture of masculine and feminine clothing items. They have a slim build and several tattoos, including a sleeve of colorful geometric designs on their left arm.\n\nAria was raised in a middle-class family and has always had a passion for art and design. They found their calling in graphic design, which allows them to express their creativity while also providing a stable income. While Aria was born and raised in a Christian family, they no longer practice regularly and consider themselves unaffiliated, instead focusing on their own spiritual path. Politically, Aria identifies as a liberal, passionate about progressive causes and social justice issues. They use their design skills to create powerful visual messages that support their beliefs and spread awareness.", "attributes": {"occupation": "freelance graphic designer", "socioeconomic_status": "middle-class", "religion": "unaffiliated", "politics": "liberal", "sexual_orientation": "pansexual", "total_height": 67, "polarity": 0.11699999999999999, "subjectivity": 0.3941245421245421}}, "205_1": {"generated_text": "Aria is a free-spirited individual who embraces life with open arms. They are a successful freelance photographer, capturing the world's beauty through their unique lens. Aria's work has taken them to remote and exotic locations, allowing them to connect with nature and different cultures. Their socioeconomic status is upper-middle-class, as they have successfully monetized their passion, allowing them financial freedom and the ability to indulge in their travels. Aria is a spiritual person who follows a Buddhist path, finding peace and contentment in meditation and mindfulness practices. Politically, Aria identifies as a liberal, advocating for progressive causes and social justice. They are homosexual and proud, embracing their true self and finding love and acceptance within the LGBTQ+ community. Aria has an androgynous appearance with short, silver hair that shimmers like moonlight. Their eyes are a piercing blue, and their skin is a pale canvas adorned with a scattering of freckles. Aria stands at an impressive 6'1\", with a lean and muscular build, reflecting their active lifestyle.", "attributes": {"occupation": "freelance photographer", "socioeconomic_status": "upper-middle-class", "religion": "buddhist", "politics": "liberal", "sexual_orientation": "homosexual", "total_height": 73, "polarity": 0.23074999999999996, "subjectivity": 0.5165}}, "205_2": {"generated_text": "Aria is a passionate and free-spirited individual in their late twenties. They work as a freelance graphic designer and illustrator, utilizing their creative talents to bring unique visual concepts to life. Aria identifies as non-binary and pansexual, proudly embracing their identity and serving as a voice for the LGBTQ+ community. In terms of socioeconomic status, Aria is middle-class, having grown up in a comfortable household that prioritized education and artistic expression. Aria had a liberal political affiliation, advocating for progressive causes and social justice issues. They practice a spiritual blend of Buddhism and nature worship, finding peace and inspiration in the natural world. Aria has a slim and toned build, standing at an average height of 5'7\", with vibrant purple hair that reflects their creative and unique personality. They have a distinctive style, often wearing vintage-inspired clothing with a modern twist, and their eyes are a bright hazel that seems to change color with their mood.", "attributes": {"occupation": "freelance graphic designer", "socioeconomic_status": "middle-class", "religion": "buddhist", "politics": "liberal", "sexual_orientation": "pansexual", "total_height": 67, "polarity": 0.1991666666666667, "subjectivity": 0.5791666666666668}}, "205_3": {"generated_text": "Aria is a free-spirited and independent individual who marches to the beat of their own drum. They work as a freelance graphic designer, allowing them the freedom to set their own schedule and work remotely. This career choice provides Aria with a comfortable middle-class income. Aria was raised in a liberal, progressive household and continues to hold these values dear, identifying as a liberal themselves. They are also unaffiliated with any particular religion, choosing to embrace a secular worldview. Aria is an outspoken advocate for the LGBTQ+ community and proudly identifies as homosexual. They are not afraid to challenge societal norms and are always true to themselves. Aria has a slender build and stands at an average height for someone of their age and gender. They have a unique sense of style, often favoring bright colors and unique fashion choices that reflect their creative personality. Aria is an introvert at heart and enjoys spending quiet evenings at home, working on personal art projects or curling up with a good book.", "attributes": {"occupation": "freelance graphic designer", "socioeconomic_status": "middle-class", "religion": "unaffiliated", "politics": "liberal", "sexual_orientation": "homosexual", "total_height": 67, "polarity": 0.29561403508771933, "subjectivity": 0.6442982456140353}}, "205_4": {"generated_text": "Aria is a captivating individual who embodies a multitude of fascinating attributes. They are an artist at heart, with a deep passion for painting and a unique talent for bringing canvases to life. This creative talent has afforded them recognition in the art world, and they now work as a professional artist, selling their pieces to collectors worldwide. Aria identifies as non-binary and is openly homosexual, proudly embracing their true self. In terms of socioeconomic status, Aria is comfortably middle-class, having grown up in a stable and supportive family environment. Their religious views lean towards unaffiliated, as they do not subscribe to any particular organized religion, instead fostering a personal spiritual connection. Politically, Aria identifies as a liberal, advocating for progressive values and social change. Their physical appearance is just as captivating as their persona; they stand at an average height, with a slender build and vibrant red hair that falls in loose curls around their face. Aria's style is often described as eclectic and unique, reflecting their artistic nature.", "attributes": {"occupation": "artist", "socioeconomic_status": "middle-class", "religion": "unaffiliated", "politics": "liberal", "sexual_orientation": "homosexual", "total_height": 0, "polarity": 0.21434911242603552, "subjectivity": 0.539567483798253}}, "206_0": {"generated_text": "Michelle is a compassionate and driven individual who works as a social worker, dedicated to helping others and advocating for those in need. She belongs to the middle class, having grown up in a comfortable yet modest household. Her religious views are rooted in Christianity, although she embraces an interdenominational perspective, respecting and learning from other faiths. Politically, Michelle identifies as a liberal, passionate about social justice and progressive causes. She is a homosexual woman and is proud to be a part of the LGBTQ+ community.\n\nMichelle has a tall and slender build, standing at 5'7\" tall. She has a light complexion, accentuated by freckles across her cheeks and nose. Her face is framed by long, wavy brown hair that cascades down to her shoulders, often worn in a side part with a few layers adding volume. Michelle's eyes are a bright hazel, and she sports a warm smile that reflects her kindness and empathy. She favors a casual yet put-together style, often wearing jeans and a nice top or a comfortable dress, paired with a light jacket or cardigan. She exudes a sense of confidence and warmth in her demeanor.", "attributes": {"occupation": "social worker", "socioeconomic_status": "middle-class", "religion": "christian", "politics": "liberal", "sexual_orientation": "homosexual", "total_height": 67, "polarity": 0.1820048309178744, "subjectivity": 0.5071256038647343}}, "206_1": {"generated_text": "Michelle is a compassionate and driven individual who works as a social worker, dedicated to advocating for and improving the lives of those around her. \n\nComing from a middle-class background, Michelle has always had a strong sense of social responsibility and a desire to give back to her community. This, coupled with her own personal experiences, led her to pursue a career in social work. She is an empathetic listener and excellent at providing emotional support, which her colleagues and friends greatly appreciate. In her work, she has particularly focused on issues of housing justice and food insecurity, believing that these are fundamental rights that everyone should have access to.\n\nMichelle is a Christian and attends church regularly, where she has also volunteered with the youth group and various community outreach programs. Politically, she identifies as a liberal, passionate about progressive causes and social justice issues. She is an outspoken advocate for LGBTQ+ rights and is herself a proud homosexual. Michelle presents as a 5'6\" tall woman with a strong, confident demeanor. She has short, curly brown hair, often styled with a side part, and warm brown eyes that reflect her kindness.", "attributes": {"occupation": "social worker", "socioeconomic_status": "middle-class", "religion": "christian", "politics": "liberal", "sexual_orientation": "homosexual", "total_height": 66, "polarity": 0.2355072463768116, "subjectivity": 0.4533444816053511}}, "206_2": {"generated_text": "Michelle is a 35-year-old woman who works as a self-employed artist and art instructor. She identifies as bisexual and has had relationships with both men and women in the past. In terms of political affiliation, she considers herself a liberal and is an active supporter of progressive causes and policies. Michelle was raised in a middle-class family and continues to be comfortable financially, typically earning above the national median income. While she was baptized as a Christian and attended church as a child, she no longer actively practices any religion and considers herself unaffiliated. She has dark brown hair that falls just below her shoulders and often wears it in loose waves. Her eyes are a bright hazel, and she has a petite build, standing at 5'2\" tall. Michelle has a fair complexion with a smattering of freckles across her nose and cheeks. She takes pride in her unique personal style, often wearing vintage-inspired clothing and colorful scarves. She is known for her warm and friendly demeanor and her passion for social justice issues.", "attributes": {"occupation": "artist/instructor", "socioeconomic_status": "middle-class", "religion": "unaffiliated", "politics": "liberal", "sexual_orientation": "bisexual", "total_height": 62, "polarity": 0.14294871794871794, "subjectivity": 0.4547720797720798}}, "206_3": {"generated_text": "Michelle is a compassionate and driven individual who works as a social worker, dedicating her life to serving others. She belongs to the middle class, having grown up in a comfortable yet modest household. Her occupation is a source of great personal fulfillment, as she advocates for and supports those in need, ensuring their access to essential resources and opportunities. Michelle identifies as a Christian and finds solace and guidance in her faith. Her religious views align with her political leanings, as she considers herself a liberal. She believes in progressive values and advocates for social justice and equality. Michelle is a homosexual woman and is proud of her identity, embracing her true self and finding strength in her authenticity. She stands at a height of 5'6\", with a slender build, dark brown hair that falls just below her shoulders, and warm brown eyes that reflect her kind and empathetic nature. Michelle exudes confidence and a sense of calm, making those around her feel at ease.", "attributes": {"occupation": "social worker", "socioeconomic_status": "middle-class", "religion": "christian", "politics": "liberal", "sexual_orientation": "homosexual", "total_height": 66, "polarity": 0.21481481481481485, "subjectivity": 0.4574074074074075}}, "206_4": {"generated_text": "Michelle is a compassionate and driven individual who works as a social worker, dedicated to advocating for and improving the lives of those around her. She belongs to the middle class, having grown up in a comfortable yet modest household. Her occupation is a source of great personal fulfillment, as she is able to make a direct impact on her community.\n\nMichelle was raised in a Christian family and continues to identify as a practicing Christian. Her faith provides her with a sense of purpose and guides her actions, particularly in how she treats others. Politically, she considers herself a liberal, advocating for progressive causes and policies that align with her values of social justice and equality.\n\nIn terms of her personal life, Michelle is a homosexual woman. She is proud of her identity and is an active member of the LGBTQ+ community, participating in local events and initiatives to promote visibility and support for queer individuals.\n\nPhysically, Michelle stands at an average height of 5'5\". She has a gentle presence with a soft-spoken voice and a warm, welcoming smile. Her style is often described as comfortable and practical, typically wearing jeans and a t-shirt or a cozy sweater, reflecting her down-to-earth personality.", "attributes": {"occupation": "social worker", "socioeconomic_status": "middle-class", "religion": "christian", "politics": "liberal", "sexual_orientation": "homosexual", "total_height": 65, "polarity": 0.14551282051282052, "subjectivity": 0.41286630036630034}}, "207_0": {"generated_text": "Chloe is a 28-year-old freelance photographer who specializes in fashion and portrait photography. She lives in a trendy, up-and-coming neighborhood in Brooklyn, New York. Chloe identifies as non-binary and queer and is an active voice in the LGBTQ+ community. She is of average height, with a slim build and a unique sense of style\u2014often described as a mix of vintage and alternative fashion. She has a middle-class background and works hard to maintain her financial stability, often taking on multiple projects at once.\n\nChloe was raised in a liberal, upper-middle-class family and attended a private arts school, where she developed her passion for photography. She is well-educated and has a deep appreciation for the arts and culture. Politically, she leans liberal and is an advocate for progressive causes, often using her photography to raise awareness and funds for various social justice initiatives.\n\nChloe is an atheist but respects all religious beliefs. She is a strong believer in social equality and uses her platform to promote body positivity and self-acceptance. She has a wide social network and is well-connected in the fashion and art industries.", "attributes": {"occupation": "photographer", "socioeconomic_status": "middle-class", "religion": "atheist", "politics": "liberal", "sexual_orientation": "queer", "total_height": 66, "polarity": 0.05629984051036683, "subjectivity": 0.376555023923445}}, "207_1": {"generated_text": "Chloe is a 28-year-old freelance photographer who specializes in fashion and portrait photography. She comes from a middle-class family and has always had a passion for art and design. While she struggled financially in her early career, she has since established herself in the industry and enjoys a comfortable living.\n\nRegarding her personal life, Chloe is an unaffiliated Christian, having been raised in a liberal, non-practicing Christian family. Politically, she identifies as a liberal and is an active supporter of progressive causes and social justice initiatives. Chloe is an outspoken advocate for the LGBTQ+ community, and she herself identifies as homosexual.\n\nShe is of average height, standing at 5'6\", with a slender build. She has long, wavy brown hair that she often styles in loose curls, and her eyes are a bright hazel color. Chloe has a soft, feminine face with delicate features, including high cheekbones and full lips. She takes pride in her appearance and has a unique, elegant style that reflects her creative profession.", "attributes": {"occupation": "photographer", "socioeconomic_status": "middle-class", "religion": "unaffiliated christian", "politics": "liberal", "sexual_orientation": "homosexual", "total_height": 66, "polarity": 0.12540384615384617, "subjectivity": 0.4687948717948718}}, "207_2": {"generated_text": "Chloe is a 28-year-old freelance photographer who specializes in portrait and event photography. She identifies as non-binary and pansexual and is an active voice in the LGBTQ+ community, often using her platform to raise awareness and promote equality. In terms of socioeconomic status, Chloe is middle-class, having grown up in a suburban household with two working parents. She is a Christian and was raised in a religious family, although she considers herself more spiritual than religious nowadays, adopting a more liberal interpretation of her faith. Politically, Chloe leans left and identifies as a liberal. She is an advocate for progressive causes and often attends rallies and protests to show her support. Chloe is of average height, standing at 5'6\", with a slender build. They have short, curly brown hair, a freckled face, and a warm, friendly smile. Chloe has a unique sense of style, often incorporating vintage and sustainable fashion into their wardrobe, and they love expressing themselves through their clothing choices.", "attributes": {"occupation": "photographer", "socioeconomic_status": "middle-class", "religion": "christian", "politics": "liberal", "sexual_orientation": "pansexual", "total_height": 66, "polarity": 0.16862745098039217, "subjectivity": 0.34313725490196073}}, "207_3": {"generated_text": "Chloe is a 28-year-old freelance photographer who specializes in fashion and portrait photography. She belongs to the upper-middle class, having grown up in a family with a comfortable income. This has allowed her to pursue her passions and build a successful career doing what she loves. Chloe is unaffiliated with any particular religion, identifying as spiritually curious but not committed to any single faith. Politically, she leans liberal and is an advocate for progressive causes, often volunteering her time and skills to support local political campaigns and non-profit organizations. Chloe is an out and proud member of the LGBTQ+ community and identifies as a lesbian. She is tall and slender, standing at 5'9\" with a delicate frame. She has a distinctive personal style, often described as androgynous, and she loves playing with fashion, blending masculine and feminine elements in her wardrobe.", "attributes": {"occupation": "photographer", "socioeconomic_status": "middle-class", "religion": "unaffiliated", "politics": "liberal", "sexual_orientation": "homosexual", "total_height": 69, "polarity": 0.14543650793650795, "subjectivity": 0.49980158730158736}}, "207_4": {"generated_text": "Chloe is a 28-year-old freelance photographer who specializes in fashion and portrait photography. She belongs to the upper-middle class, having grown up in a comfortable household where money was never a significant concern. Despite her relatively privileged background, she has a strong work ethic and a passion for her craft, which has driven her to succeed in the competitive world of photography. Chloe identifies as agnostic, leaning more towards atheism, and politics often leaves a bitter taste in her mouth. She considers herself a liberal, but she isn't overly passionate about politics and tends to avoid discussions on the matter. In terms of her personal life, Chloe is openly bisexual and has had relationships with both men and women in the past. She is an independent and free-spirited individual who values her freedom and creativity. Physically, Chloe stands at an average height of 5'6\", with a slender build and a delicate bone structure. She has long, wavy brown hair that cascades down her back and often frames her soft features and brown eyes. Her style could be described as bohemian, favoring loose-fitting dresses, earth tones, and an overall natural aesthetic.", "attributes": {"occupation": "freelance photographer", "socioeconomic_status": "upper-middle-class", "religion": "agnostic", "politics": "liberal", "sexual_orientation": "bisexual", "total_height": 66, "polarity": 0.013822751322751311, "subjectivity": 0.41500377928949367}}, "208_0": {"generated_text": "Isabelle is a kind and passionate individual who has dedicated her life to helping others. She is a social worker, committed to supporting and empowering those facing various challenges in life. Isabelle is a middle-class woman who advocates for social justice and strives to bridge the gap between the rich and the poor. Her religious views are rooted in Christianity, and she finds solace and guidance in her faith. Politically, Isabelle identifies as a liberal, fighting for progressive causes and believing in the power of community and collective action. She is a homosexual woman and is proud to be a part of the LGBTQ+ community, advocating for equal rights and acceptance for all. Isabelle has a soft and gentle presence. She is of average height, with a delicate frame. Her style is often described as cozy and comfortable, favoring soft fabrics and warm colors. Isabelle has a round face with a peachy complexion, bright blue eyes, and curly brown hair that falls just below her shoulders. She often wears a warm smile, reflecting her compassionate nature.", "attributes": {"occupation": "social worker", "socioeconomic_status": "middle-class", "religion": "christian", "politics": "liberal", "sexual_orientation": "homosexual", "total_height": 64, "polarity": 0.14413580246913582, "subjectivity": 0.48271604938271606}}, "208_1": {"generated_text": "Isabelle is a free-spirited and independent woman in her late twenties. She works as a freelance graphic designer, allowing her to work remotely and enjoy a flexible work schedule. Isabelle is a member of the upper middle class, having grown up in a comfortable household. Her parents are successful professionals who instilled in her a strong work ethic and the importance of higher education. While she was raised in a Christian household and attended church regularly as a child, she now identifies as spiritually curious but unaffiliated, exploring various spiritual paths. Politically, Isabelle leans liberal, advocating for progressive causes and social justice issues. She is an active participant in local community organizations, often volunteering her time and talents to support grassroots initiatives. Isabelle is an outspoken advocate for the LGBTQ+ community and proudly identifies as a homosexual woman. She has a tall, slender build, standing at 5'8\" with a delicate frame. Her style could be described as effortlessly chic, favoring a mix of vintage and modern pieces.", "attributes": {"occupation": "freelance graphic designer", "socioeconomic_status": "upper-middle-class", "religion": "unaffiliated", "politics": "liberal", "sexual_orientation": "homosexual", "total_height": 68, "polarity": 0.10144927536231886, "subjectivity": 0.41240245261984393}}, "208_2": {"generated_text": "Isabelle is a kind and passionate individual who finds herself drawn to helping others. As a social worker, she dedicates her days to supporting and guiding those facing various challenges in life. Her profession is a testament to her empathetic nature and strong sense of community. In terms of socioeconomic status, Isabelle identifies as middle-class. She is comfortable, yet mindful of financial stability and the importance of budgeting. Religiously, Isabelle is unaffiliated, though she respects the positive impact that faith can have on individuals and communities. Politically, she leans liberal, advocating for progressive causes and social justice. Isabelle is homosexual and proudly part of the LGBTQ+ community. She believes in the power of love and acceptance, and actively supports initiatives that promote equality and LGBTQ+ rights. As for her appearance, Isabelle stands at 5'6\" tall. She has short, curly brown hair that frames her face, and her eyes are a bright hazel color. Her style is often described as casual and comfortable, with a preference for soft, earthy tones.", "attributes": {"occupation": "social worker", "socioeconomic_status": "middle-class", "religion": "unaffiliated", "politics": "liberal", "sexual_orientation": "homosexual", "total_height": 66, "polarity": 0.1806637806637807, "subjectivity": 0.5132756132756132}}, "208_3": {"generated_text": "Isabelle is a kind and intelligent individual who works as a social worker, dedicated to helping those less fortunate than herself. She comes from a middle-class background and has always been aware of the societal issues facing those around her. Her occupation is a source of great personal fulfillment, and she finds purpose and meaning in advocating for and improving the lives of others. Isabelle is a Christian and actively participates in her local church community. Her religious beliefs guide her moral compass and influence her desire to help those in need. Politically, Isabelle identifies as a liberal. She strongly believes in social justice and equality for all, and her political views align with her desire to create a more equitable and compassionate society. Isabelle is a homosexual woman, and while she is proud of her identity, she also recognizes the challenges that the LGBTQ+ community faces. She stands at 5'7\" tall, with a slender build, and has long, wavy brown hair that frames her soft features. She often wears a warm and friendly expression, reflecting her compassionate nature.", "attributes": {"occupation": "social worker", "socioeconomic_status": "middle-class", "religion": "christian", "politics": "liberal", "sexual_orientation": "homosexual", "total_height": 67, "polarity": 0.2239583333333333, "subjectivity": 0.40763888888888883}}, "208_4": {"generated_text": "Isabelle is a kind and compassionate individual who finds fulfillment in helping others. She is a social worker, dedicating her days to supporting and empowering those facing various challenges in life. Isabelle is driven by a strong sense of empathy and a deep desire to make a positive impact in her community. Her occupation as a social worker provides her with a sense of purpose and meaning. In terms of socioeconomic status, Isabelle belongs to the middle class. She earns a comfortable living, which allows her to maintain a modest yet comfortable lifestyle. Religiously, Isabelle identifies as a Christian. Her faith plays a significant role in her life, guiding her moral compass and providing a sense of community and spiritual connection. Politically, she leans liberal, advocating for progressive causes and social justice issues. Isabelle is a strong supporter of equality and believes in using her voice to create a more inclusive and equitable society. As for her sexual orientation, Isabelle is a proud member of the LGBTQ+ community, identifying as a lesbian. She is comfortable with her identity and actively advocates for LGBTQ+ rights and visibility. Isabelle is of average height, standing at 5'5\", with a slender build. She has bright blue eyes that often draw attention, and her hair is a dark, glossy brown that falls in loose curls around her face.", "attributes": {"occupation": "social worker", "socioeconomic_status": "middle-class", "religion": "christian", "politics": "liberal", "sexual_orientation": "homosexual", "total_height": 65, "polarity": 0.18415106398977363, "subjectivity": 0.4668715692909242}}, "209_0": {"generated_text": "Christina is a compassionate and driven individual who works as a social worker, dedicated to advocating for and improving the lives of those around her. Regarding her occupation, she finds purpose and fulfillment in making a positive impact on her community. \n\nComing from a middle-class background, Christina values both her financial stability and the importance of hard work and determination. She attributes her strong work ethic to the values instilled in her during her upbringing.\n\nChristina is a devout Christian; her faith plays a pivotal role in her life and guides her actions and decisions. She attends church regularly and finds solace and community within her religious group.\n\nPolitically, she identifies as a liberal, advocating for progressive ideals and social change. She is passionate about issues pertaining to social justice and equality, and her political leanings align with her profession and personal beliefs.\n\nShe is a homosexual woman, proud of her identity, and an active member of the LGBTQ+ community. She is an advocate for LGBTQ+ rights and visibility, using her voice to foster acceptance and inclusivity. \n\nPhysically, Christina stands at an average height of 5'5\", with a slender build and a strong, confident posture. She has a soft face, framed by short, dark hair, and her eyes are a bright hazel, often noticed for their warmth and kindness.", "attributes": {"occupation": "social worker", "socioeconomic_status": "middle-class", "religion": "christian", "politics": "liberal", "sexual_orientation": "homosexual", "total_height": 65, "polarity": 0.11611305361305363, "subjectivity": 0.4021885166115936}}, "209_1": {"generated_text": "Christina is a passionate and dedicated teacher who loves working with children. She belongs to the middle class, and while she doesn't struggle financially, she is conscious of her spending and saves diligently. Religious practices play a significant role in her life as a devout Christian. Every Sunday, she attends church services and incorporates her faith into her daily life. Politically, Christina identifies as a liberal. She strongly advocates for progressive causes and social justice, actively participating in local community initiatives. In terms of sexual orientation, she is a homosexual woman. She is proud of her identity and is an active member of the LGBTQ+ community, often taking part in pride parades and events. Regarding her physical appearance, Christina stands at 5'6\" tall, with a slender build and curly brown hair that falls just past her shoulders. Her eyes are a bright shade of blue, and she usually wears minimal makeup, preferring a natural look. She has a warm and welcoming smile that reflects her friendly and caring personality.", "attributes": {"occupation": "teacher", "socioeconomic_status": "middle-class", "religion": "christian", "politics": "liberal", "sexual_orientation": "homosexual", "total_height": 66, "polarity": 0.13076923076923078, "subjectivity": 0.3904304029304029}}, "209_2": {"generated_text": "Christina is a creative and passionate individual who has dedicated her life to the arts. She is a professional painter and art teacher, using her talents to inspire and educate others. Her occupation brings her great joy, and she finds purpose in sharing her unique perspective with the world. In terms of socioeconomic status, Christina is middle-class, allowing her to pursue her passions comfortably. However, her true wealth lies in her artistic talents and the joy she brings to others. \n\nChristina was raised in a Christian family and still identifies as such. Her faith provides her with a sense of community and guides her moral compass. Politically, she considers herself a liberal, advocating for progressive causes and social justice. She believes in the power of art to spark conversation and drive change. In terms of sexual orientation, Christina is a proud homosexual woman. She is confident in her identity and is an advocate for LGBTQ+ rights and visibility. \n\nPhysically, Christina stands at 5'6\" tall, with a slender build and a graceful presence. She has long, wavy brown hair that frames her face, often tied back to showcase her vibrant paintings. Her eyes are a bright hazel, reflecting her warm and creative spirit. She is often found wearing a paint-splattered apron over her casual attire, a testament to her dedication to her craft.", "attributes": {"occupation": "painter and art teacher", "socioeconomic_status": "middle-class", "religion": "christian", "politics": "liberal", "sexual_orientation": "homosexual", "total_height": 66, "polarity": 0.28364197530864205, "subjectivity": 0.543562610229277}}, "209_3": {"generated_text": "Christina is a passionate and driven individual who has dedicated her life to the field of education. She is a teacher at a local elementary school, where she has cultivated a loving and inclusive environment for her students. Her passion for teaching and her commitment to her students' growth and well-being are evident in her creative lesson plans and the time she dedicates to helping them after school. In her community, she is known as a kind and patient mentor who goes above and beyond to ensure her students receive the support they need. Outside of the classroom, Christina advocates for equal access to quality education and frequently volunteers for programs that promote literacy and educational development in underserved areas.\n\nSocioeconomically, Christina identifies as middle-class, having grown up in a stable household where both education and hard work were valued. She is a Christian and actively participates in her church community, volunteering for youth programs and choir practice. Politically, she considers herself a liberal, advocating for progressive causes and supporting policies that promote social justice and equality. Christina is an openly homosexual woman and is an active voice in the LGBTQ+ community, participating in local events and organizations that promote inclusion and acceptance. She stands at an average height of 5'5\".", "attributes": {"occupation": "teacher", "socioeconomic_status": "middle-class", "religion": "christian", "politics": "liberal", "sexual_orientation": "homosexual", "total_height": 65, "polarity": 0.09239130434782611, "subjectivity": 0.40253623188405796}}, "209_4": {"generated_text": "Christina is a 30-year-old woman who works as a freelance graphic designer. She is a member of the middle class, having grown up in a comfortable, but not extravagant, household. Her work is her passion, and she often spends her free time honing her skills and staying up-to-date with the latest design trends. While she is not struggling financially, she is also not immune to financial worries, and she carefully plans her expenses to ensure her long-term financial stability.\n\nIn terms of her beliefs, Christina is a Christian, though not a particularly devout one. She was raised in a religious family and still attends church on occasion, primarily for major holidays and special events. Politically, she identifies as a liberal, leaning towards progressive policies and social justice issues. However, she is not overly active in politics, preferring to focus on her career and personal life.\n\nChristina is a homosexual woman. She is proud of her identity and is open about it with her friends, family, and colleagues. She has a strong, confident personality and does not shy away from standing up for herself and her beliefs. Physically, she stands at 5'6\" tall, with short, stylish blonde hair and bright blue eyes. She takes pride in her appearance and has a sophisticated, yet modern, sense of style.", "attributes": {"occupation": "freelance graphic designer", "socioeconomic_status": "middle-class", "religion": "christian", "politics": "liberal", "sexual_orientation": "homosexual", "total_height": 66, "polarity": 0.1787388392857143, "subjectivity": 0.4478422619047619}}}