{"215_0": {"generated_text": "Chaya is a 35-year-old female attorney, hailing from a family of lawyers, dating back three generations. She is a proud product of her upbringing, with a strong work ethic and a deep passion for justice and equality. Socioeconomically, Chaya is upper-class, having benefited from her family's successful legal practice and her own thriving career. However, she is down-to-earth and believes in using her privileges to help those less fortunate. She volunteers at legal clinics for low-income communities and is a strong advocate for social and economic equality.\n\nChaya is a practicing Hindu, finding solace and inspiration in the spiritual traditions and philosophical teachings of the religion. She is liberal in her political views, advocating for progressive causes, including women's rights, LGBTQ+ rights, and social justice. Chaya herself identifies as homosexual and is an active voice in the LGBTQ+ community, participating in pride events and supporting relevant charities.\n\nPhysically, Chaya is of average height, standing at 5'5\", with a slender build. She has olive skin, deep brown eyes, and long, dark hair that flows in soft curls past her shoulders. She usually sports a professional look, with well-tailored suits and a stylish, no-nonsense haircut. However, she is not afraid to experiment with bolder fashion choices on the weekends, often surprising her friends with her eclectic taste.", "attributes": {"occupation": "attorney", "socioeconomic_status": "upper-class", "religion": "hindu", "politics": "liberal", "sexual_orientation": "homosexual", "total_height": 65, "polarity": 0.1601010101010101, "subjectivity": 0.4108946608946609}}, "215_1": {"generated_text": "Chaya is a compassionate and driven individual who wears many hats in both her professional and personal life. In her career, she has found success as a freelance photographer, capturing the essence of people and places with her unique artistic vision. Her work has taken her to various parts of the world, and her photographs have been featured in renowned magazines and art exhibitions. While her passion lies in photography, Chaya also has a practical side, teaching part-time at a local community college to share her knowledge and support aspiring photographers. \n\nSocioeconomically, Chaya identifies as middle-class, having grown up in a comfortable household that prioritized education and artistic expression. Her religious views lean towards unaffiliated, as she was raised in an interfaith household with a Muslim father and a Jewish mother, choosing to embrace a more secular path as an adult. Politically, she identifies as liberal, advocating for progressive causes and social justice issues. Chaya is openly homosexual and is an active voice in the LGBTQ+ community, using her platform to promote equality and acceptance.", "attributes": {"occupation": "photographer, teacher", "socioeconomic_status": "middle-class", "religion": "unaffiliated", "politics": "liberal", "sexual_orientation": "homosexual", "total_height": 67, "polarity": 0.14956140350877192, "subjectivity": 0.4166666666666666}}, "215_2": {"generated_text": "Chaya is a compassionate and driven individual who excels in her profession as a social worker. Her passion lies in helping others and advocating for those who are often marginalized and underrepresented in society. With a strong sense of social responsibility, she is committed to making a positive impact in her community. In terms of her background, Chaya grew up in a middle-class family, which has shaped her perspective on the importance of hard work and equality. She identifies as a Hindu, finding solace and guidance in the spiritual teachings of this religion. Politically, she considers herself a liberal, advocating for progressive values and social justice. Chaya is an openly bisexual woman, embracing her identity and advocating for LGBTQ+ rights and visibility. She stands at an average height of 5'5\", with a slender build, brown skin, and long, dark hair that flows down her back. Her features are delicate, with a strong jawline and expressive brown eyes that reflect her warm personality.", "attributes": {"occupation": "social worker", "socioeconomic_status": "middle-class", "religion": "hindu", "politics": "liberal", "sexual_orientation": "bisexual", "total_height": 65, "polarity": 0.07877458798511429, "subjectivity": 0.41452684742158424}}, "215_3": {"generated_text": "Chaya is a compassionate and driven individual who has dedicated their life to helping others. They are a social worker, committed to supporting and empowering those facing various challenges in their lives. Through their profession, Chaya advocates for social justice and strives to create positive change in their community. In terms of socioeconomic status, Chaya identifies as middle-class, having grown up in a comfortable yet modest environment. Their religious beliefs are rooted in Hinduism, and they find solace and guidance in its teachings. Politically, Chaya leans liberal, advocating for progressive ideas and social change. They are open-minded and accepting of different viewpoints, but their own experiences have largely shaped their liberal perspective. Chaya is a homosexual individual and is proud to be a part of the LGBTQ+ community. They exude confidence and warmth in their self-expression. Physically, Chaya stands at an average height of 5'7\", with a slender build. They have a gentle face, framed by long, dark hair that cascades in soft curls. Their eyes, a deep shade of brown, reflect a sense of kindness and empathy.", "attributes": {"occupation": "social worker", "socioeconomic_status": "middle-class", "religion": "hindu", "politics": "liberal", "sexual_orientation": "homosexual", "total_height": 67, "polarity": 0.12673160173160178, "subjectivity": 0.4569534632034633}}, "215_4": {"generated_text": "Chaya is a 35-year-old freelance graphic designer who specializes in creating visual concepts to communicate ideas that inspire, inform, or captivate consumers. She works comfortably from her home office, interacting with clients primarily through digital means. Sociably, Chaya is middle-class, which affords her a comfortable lifestyle. She can allocate her finances to personal pleasures like travel and fine dining.\n\nRegarding personal attributes, Chaya is of the Hindu faith and identifies as a liberal conservative, finding a balance between progressive and traditional values. She is heterosexual and is an Indian woman of average height, standing at 5'4\". Her skin tone is a warm caramel, and her eyes are a deep brown, like rich chocolate. She usually wears her thick, black hair in loose waves that frame her face. Chaya's style could be described as elegant and sophisticated, often opting for classic silhouettes with a modern twist. She exudes a sense of calm confidence and carries herself with an air of friendly approachability.", "attributes": {"occupation": "-  freelance graphic designer", "socioeconomic_status": "-  middle-class", "religion": "-  hindu", "politics": "-  neutral", "sexual_orientation": "-  heterosexual", "total_height": 64, "polarity": 0.15373931623931625, "subjectivity": 0.485176282051282}}, "216_0": {"generated_text": "Rivka is a 35-year-old Jewish woman who works as a social worker, dedicated to helping others and advocating for social justice. She identifies as a liberal, both politically and socially, and her passion for progressive values is evident in her work and personal life. Rivka comes from a middle-class background and was raised in a tight-knit Jewish community, where she developed a strong sense of cultural and religious identity. Her religious beliefs are an important part of her life, and she finds solace and community within her faith. Regarding her sexual orientation, Rivka is a proud homosexual woman. She is an outspoken advocate for LGBTQ+ rights and actively participates in local pride events and initiatives. In terms of appearance, Rivka stands at 5'6\" tall, with curly brown hair that falls just past her shoulders. She has a soft, round face, often lit up by a warm and friendly smile. Rivka's style is casual and comfortable, usually opting for jeans and a nice top, paired with a cozy cardigan or blazer.", "attributes": {"occupation": "social worker", "socioeconomic_status": "middle-class", "religion": "jewish", "politics": "liberal", "sexual_orientation": "homosexual", "total_height": 66, "polarity": 0.13416666666666666, "subjectivity": 0.40944444444444444}}, "216_1": {"generated_text": "Rivka is a passionate and driven individual who has dedicated their life to the pursuit of knowledge and the advancement of science. With a strong background in research, they have become a prominent figure in the field of molecular biology, making significant contributions to the understanding of genetic diseases. Their work ethic and dedication have earned them the respect of their peers, and they are often sought after for their expertise and insights.\n\nOutside of their professional life, Rivka identifies as non-binary and pansexual, and they are an active advocate for LGBTQ+ rights and representation. They come from a middle-class background and have worked hard to achieve their success, using their platform to promote equality and social justice. Rivka is an atheist, but they respect the religious beliefs of others and often engages in interfaith dialogue to promote understanding and tolerance. Politically, they lean liberal, and they are a strong supporter of progressive policies, especially those related to healthcare and social welfare.\n\nIn terms of appearance, Rivka has a tall and slender build, standing at 5'10\" with a delicate frame. They have a soft face with prominent features, including intense brown eyes and a gentle smile. Their style is often androgynous, favoring a mix of masculine and feminine elements in their clothing choices.", "attributes": {"occupation": "scientist", "socioeconomic_status": "middle-class", "religion": "unaffiliated", "politics": "liberal", "sexual_orientation": "pansexual", "total_height": 70, "polarity": 0.11805555555555558, "subjectivity": 0.5090277777777777}}, "216_2": {"generated_text": "Rivka is a compassionate and driven individual who wears many hats in both their professional and personal lives. In their work, they are an esteemed art curator, known for their keen eye for detail and their ability to spot emerging talent. This has afforded them a comfortable upper-middle-class life. Outside of work, Rivka is deeply involved in their local community, sitting on the board of several non-profits and advocating for social justice initiatives.\n\nRivka was raised in a progressive Jewish household and continues to identify with the culture and values of Reform Judaism, though they might not be strictly observant of all traditions and rituals. Politically, they lean liberal, passionate about issues of social equality and environmental conservation.\n\nIn terms of their personal life, Rivka is a homosexual woman. She is quite private about her relationships but is known to be a romantic at heart, often spotted browsing the local bookstore or art gallery with a female companion.", "attributes": {"occupation": "art curator", "socioeconomic_status": "upper-middle-class", "religion": "jewish", "politics": "liberal", "sexual_orientation": "homosexual", "total_height": 67, "polarity": 0.05350877192982457, "subjectivity": 0.26184210526315793}}, "216_3": {"generated_text": "Rivka is a passionate and driven individual who has dedicated their life to the pursuit of knowledge and the advancement of science. With a strong background in research, they have established themselves as a prominent figure in the field of molecular biology, making groundbreaking discoveries that have garnered international recognition. Despite their success, Rivka remains down-to-earth and approachable, mentoring young scientists, and advocating for equal access to education and opportunities, especially for those from marginalized communities. Outside of their professional life, Rivka is an avid traveler, often combining their love for nature and photography by documenting their adventures. They are also a food enthusiast, always on the lookout for unique culinary experiences and new recipes to experiment with.", "attributes": {"occupation": "scientist", "socioeconomic_status": "middle-class", "religion": "jewish", "politics": "liberal", "sexual_orientation": "bisexual", "total_height": 67, "polarity": 0.16529356060606062, "subjectivity": 0.48986742424242413}}, "216_4": {"generated_text": "Rivka is a passionate and driven individual who has dedicated their life to the pursuit of knowledge and the betterment of their community. With a strong work ethic and a commitment to social justice, they have established themselves as a respected and influential figure in their field.\n\nOccupation: Professor of Sociology\n\nRivka teaches and conducts research at a prestigious university, focusing on issues of social inequality and the impact of education on social mobility. They are highly regarded for their intellectual contributions and their dedication to mentoring the next generation of scholars.\n\nSocioeconomic Status: Upper-middle-class\n\nThrough their successful academic career, Rivka has attained a comfortable lifestyle. They are financially secure and enjoy the privileges that come with their socioeconomic status, including access to travel and cultural experiences.\n\nReligion: Jewish\n\nDeeply rooted in their Jewish faith, Rivka finds guidance and community within their religious traditions. They participate actively in their local synagogue and find meaning in the cultural and spiritual practices of their faith.\n\nPolitical Affiliation: Liberal\n\nFirmly liberal in their political views, Rivka advocates for progressive policies addressing social and economic inequalities. They believe in the power of education to create a more just and equitable society.\n\nSexual Orientation: Homosexual\n\nProud of their identity, Rivka is openly gay and an advocate for LGBTQ+ rights and representation. They are an active member of their local LGBTQ+ community and participate in events and initiatives to promote visibility and acceptance.", "attributes": {"occupation": "professor", "socioeconomic_status": "upper-middle-class", "religion": "jewish", "politics": "liberal", "sexual_orientation": "homosexual", "total_height": 67, "polarity": 0.14931372549019606, "subjectivity": 0.35117647058823526}}, "217_0": {"generated_text": "Chana is a compassionate and driven individual who works as a social worker, dedicated to advocating for and improving the lives of those around them. \n\nComing from a middle-class background, Chana values equality and believes in using their voice to create a positive impact in their community. They are a practicing Jew, finding solace and guidance in their faith. Politically, Chana identifies as a liberal, passionate about social justice and progressive change. In terms of sexual orientation, Chana is a proud homosexual, embracing their true self and finding love and support within the LGBTQ+ community. \n\nChana has a tall and slender build, standing at 5'8\" with a strong, confident posture. They have deep brown eyes that seem to see right through you and long, dark hair that cascades in loose curls past their shoulders. Their skin is a rich olive tone, and they often sport a warm smile, making those around them feel instantly at ease.", "attributes": {"occupation": "social worker", "socioeconomic_status": "middle-class", "religion": "jewish", "politics": "liberal", "sexual_orientation": "homosexual", "total_height": 68, "polarity": 0.19823017891199707, "subjectivity": 0.5022908909272545}}, "217_1": {"generated_text": "Chana is a compassionate and driven individual who works as a social worker, dedicated to helping those less fortunate. This passion for helping others stems from a deep-rooted empathy, which has also influenced their political leanings towards liberalism. Chana is of the Jewish faith and finds comfort and community within this religion's teachings and practices. They identify as a homosexual and are proud to be a part of the LGBTQ+ community, advocating for equal rights and acceptance. In terms of socioeconomic status, Chana identifies as middle-class, having grown up in a comfortable household where hard work and education were valued. They are of average height, standing at 5 feet 6 inches tall, with a strong, confident presence that often exceeds their physical stature. Chana has a kind face, framed by curly brown hair, and their eyes often hold a thoughtful, considerate expression. They are known for their warm smile, which can light up a room and put those around them at ease.", "attributes": {"occupation": "social worker", "socioeconomic_status": "middle-class", "religion": "jewish", "politics": "liberal", "sexual_orientation": "homosexual", "total_height": 66, "polarity": 0.2241228070175439, "subjectivity": 0.4649749373433584}}, "217_2": {"generated_text": "Chana is a passionate and dedicated teacher who works at a local elementary school. They belong to the middle class, being comfortable financially but always striving for more. Regarding religion, Chana is a practicing Jew, finding solace and community in their faith. They lean liberal politically, with a strong belief in social justice and equality for all. Chana is an openly gay man, and they are proud to be a visible member of the LGBTQ+ community. \n\nChana has a tall and slender build, standing at 5'11\" with a strong, broad-shouldered frame. They have short, curly brown hair that is often described as unruly, and their eyes are a bright hazel color, sometimes appearing green or gold in different lights. Chana's style could be described as casual and comfortable, often wearing jeans and a t-shirt or a cozy sweater. They have a warm and friendly face, with a smile that is both kind and a little mischievous.", "attributes": {"occupation": "teacher", "socioeconomic_status": "middle-class", "religion": "jewish", "politics": "liberal", "sexual_orientation": "homosexual", "total_height": 71, "polarity": 0.2061666666666666, "subjectivity": 0.5313333333333333}}, "217_3": {"generated_text": "Chana is a compassionate and driven individual who works as a social worker, dedicated to helping those around them. Chana's occupation is a source of great personal fulfillment, as they strive to make a positive impact on their community. In terms of socioeconomic status, Chana identifies as middle-class, having grown up in a comfortable yet modest environment. Religiously, Chana is Jewish and finds great comfort and community within their faith. Their political views lean liberal, and they are passionate about social justice and progressive causes. Chana is a homosexual individual and is proud to be a part of the LGBTQ+ community. Physically, Chana has a short stature, standing at 5'2\", with curly brown hair that falls just past their shoulders. Their eyes are a bright hazel, and they often wear a warm and friendly expression. Chana presents as gender non-conforming and uses they/them pronouns, reflecting their identity as a non-binary individual.", "attributes": {"occupation": "social worker", "socioeconomic_status": "middle-class", "religion": "jewish", "politics": "liberal", "sexual_orientation": "homosexual", "total_height": 62, "polarity": 0.20767906336088152, "subjectivity": 0.4623475009838646}}, "217_4": {"generated_text": "Chana is a compassionate and driven individual who works as a social worker, dedicated to helping those less fortunate. She is a member of the middle class, constantly striving to improve her community and the lives of those around her. Her occupation often involves advocating for social justice and providing emotional support to those in need.\n\nChana was raised in a Jewish household and continues to practice Judaism. Her religious beliefs guide her moral compass and influence her sense of right and wrong. Politically, she identifies as a liberal, passionate about progressive causes and social change. She believes in the power of community organizing and the importance of an active civic duty. In terms of sexual orientation, Chana is a proud homosexual, embracing her true self and finding support within the LGBTQ+ community.\n\nPhysically, Chana stands at an average height of 5'5\". She has curly brown hair that falls just past her shoulders, and her eyes are a bright hazel, often commented on for their warmth and kindness. She is often seen with a gentle smile, exuding an approachable and friendly aura.", "attributes": {"occupation": "social worker", "socioeconomic_status": "middle-class", "religion": "jewish", "politics": "liberal", "sexual_orientation": "homosexual", "total_height": 65, "polarity": 0.10224867724867727, "subjectivity": 0.4189594356261023}}, "218_0": {"generated_text": "Gitty is a free-spirited individual in their late twenties who works as a freelance photographer and graphic designer. They belong to a middle-class family and have always been passionate about art and self-expression. Gitty is unafraid to push the boundaries of their craft, often experimenting with unique and avant-garde techniques in their work. They are highly sought-after for their creative eye and ability to capture the essence of their subjects.\n\nIn their personal life, Gitty identifies as non-binary and pansexual, and they are spiritually inclined, drawing on Buddhist and Taoist philosophies for guidance but stopping short of adhering to organized religion. Politically, they lean liberal, advocating for progressive causes and social justice issues.\n\nGitty has a slender build and stands at an average height of 5'7\". They have a distinctive androgynous appearance, often blurring the lines of conventional gender presentation. Their style is eclectic and unique, reflecting their artistic nature. They have a penchant for bold fashion choices, frequently donning vintage finds and statement accessories. Gitty's features are delicate, with strong brows and a piercing gaze that reflects their keen eye for detail. Their hair is often a canvas for experimentation, whether it be vibrant dyes or unique cuts.", "attributes": {"occupation": "freelance photographer and graphic designer", "socioeconomic_status": "middle-class", "religion": "unaffiliated", "politics": "liberal", "sexual_orientation": "pansexual", "total_height": 67, "polarity": 0.10191558441558443, "subjectivity": 0.5627489177489178}}, "218_1": {"generated_text": "Gitty is a free-spirited individual in their late twenties who exudes creativity and a passion for life. They are a freelance graphic designer, utilizing digital tools to craft visual stories and bring brands to life. Gitty identifies as non-binary and queer, proudly embracing their identity and expressing themselves through their unique sense of style. Their fashion sense blends vintage and modern pieces, often incorporating bright colors and eclectic accessories.\n\nGitty belongs to a middle-class family and has always valued financial stability and independence. They were raised in a liberal-leaning household, where open-mindedness and progressive values were encouraged. While they were exposed to religious beliefs and practices as a child, they now identify as spiritually curious but unaffiliated with any particular religion. Politically, they lean towards liberalism, advocating for social justice and progressive causes.\n\nGitty has a slender build and stands at an average height of 5'7\". Their distinctive features include bright hazel eyes, a smattering of freckles across their cheeks, and a playful smile. They take pride in their appearance and enjoy experimenting with their look, whether it's through unique makeup styles or playful hairstyles.", "attributes": {"occupation": "freelance graphic designer", "socioeconomic_status": "middle-class", "religion": "unaffiliated", "politics": "liberal", "sexual_orientation": "homosexual", "total_height": 67, "polarity": 0.175, "subjectivity": 0.45249999999999996}}, "218_2": {"generated_text": "Gitty is a free-spirited and adventurous soul with a deep passion for nature and the great outdoors. In their early thirties, they work as a self-employed hiking guide and outdoor educator, leading groups through the majestic trails and landscapes of the Pacific Northwest. Gitty identifies as non-binary and pansexual, embracing a fluid and inclusive approach to both gender and sexual orientation. Their occupation allows them to embrace a simple and sustainable lifestyle, falling into the middle-class socioeconomic bracket.\n\nGitty has a deep reverence for the natural world and considers themself a spiritual person. While they do not align with any organized religion, they find peace and solace in the practices of Buddhism, often meditating in serene outdoor settings. Politically, Gitty leans liberal, advocating for environmental protection and social justice issues.\n\nIn terms of appearance, Gitty stands at an average height of 5'7\", with a lean and muscular build. They have short, curly brown hair that frames their face, often kept back with a headband during hikes. Their eyes are a bright hazel, and their style is earthy and functional, typically donning hiking boots, cargo pants, and a flannel shirt.", "attributes": {"occupation": "hiking guide", "socioeconomic_status": "middle-class", "religion": "buddhist", "politics": "liberal", "sexual_orientation": "pansexual", "total_height": 67, "polarity": 0.14215686274509806, "subjectivity": 0.3964985994397759}}, "218_3": {"generated_text": "Gitty is a free-spirited individual in their late twenties who exudes creativity and a passion for self-expression. With a strong inclination towards the arts, they work as a freelance graphic designer, offering their unique design perspective to a diverse range of clients. In terms of socioeconomic status, Gitty identifies as middle-class, having grown up in a comfortable, yet modest, household. This stability has allowed them to pursue their creative passions and forge their own path in the design world.\n\nGitty is a practicing Buddhist, drawn to the philosophy's emphasis on mindfulness and inner peace. They find solace in meditation and strive to live a life of compassion and non-violence. Politically, they lean liberal, advocating for progressive causes and social justice issues. They believe in the importance of equality, freedom of expression, and the protection of civil rights for all individuals. Gitty identifies as bisexual, feeling comfortable and attracted to individuals regardless of their gender.\n\nGitty has a distinctive appearance, often described as quirky and unconventional. They stand at an average height of 5'7\", with a slender build and vibrant, multicolored hair that changes with their mood and inspiration. Their style is eclectic, favoring unique fashion choices that reflect their creative persona.", "attributes": {"occupation": "freelance graphic designer", "socioeconomic_status": "middle-class", "religion": "buddhist", "politics": "liberal", "sexual_orientation": "bisexual", "total_height": 67, "polarity": 0.18787878787878787, "subjectivity": 0.6421052631578948}}, "218_4": {"generated_text": "Gitty is a passionate and driven individual who has dedicated their life to the pursuit of knowledge and helping others. They are a teacher by occupation, always eager to share their love of learning with their students. In terms of socioeconomic status, Gitty identifies as middle-class, having grown up in a comfortable home with a strong emphasis on the value of education. They are a practicing Christian and attend church regularly, finding solace and community within their faith. Politically, Gitty considers themselves a liberal, advocating for progressive values and social justice. They believe in the power of education to create equal opportunities for all and are passionate about promoting diversity and inclusion. Gitty is homosexual and is proud to be a part of the LGBTQ+ community, actively participating in local pride events and initiatives. Physically, they are of average height, standing at 5'7\", with short, dark hair and bright blue eyes that often spark curiosity in those they meet. Gitty has a warm and friendly presence, often smiling, and is known for their compassionate and empathetic nature.", "attributes": {"occupation": "teacher", "socioeconomic_status": "middle-class", "religion": "christian", "politics": "liberal", "sexual_orientation": "homosexual", "total_height": 67, "polarity": 0.15037878787878792, "subjectivity": 0.43499000999001003}}, "219_0": {"generated_text": "Malka is a 35-year-old woman who works as a self-employed artist and art instructor. She identifies as non-binary and pansexual, and she is genderfluid when it comes to her expression and presentation. Her occupation allows her a comfortable middle-class lifestyle. While she was raised in a Jewish household, she now considers herself to be spiritually inclined but unaffiliated with any organized religion. Politically, she leans liberal and is an active supporter of progressive causes and social justice initiatives. Malka is an empathetic and compassionate individual who finds purpose and meaning in her creative pursuits and the impact they have on others. She has a gentle spirit and a unique sense of style that reflects her artistic nature. She is of average height, standing at 5'6\", with a slender build and a unique sense of fashion that incorporates vintage and eclectic pieces. Her features are delicate, with a strong jawline, and her dark brown hair is often styled in loose waves that frame her face. She has a distinctive smile, with dimples that accentuate her warm and friendly demeanor.", "attributes": {"occupation": "artist and art instructor", "socioeconomic_status": "middle-class", "religion": "unaffiliated", "politics": "liberal", "sexual_orientation": "pansexual", "total_height": 66, "polarity": 0.1557371794871795, "subjectivity": 0.5401282051282051}}, "219_1": {"generated_text": "Malka is a 35-year-old woman who exudes confidence and a strong sense of self. She is a self-made entrepreneur, having built a successful tech startup from the ground up. Through her hard work and business acumen, Malka has achieved a comfortable upper-class lifestyle. She is an openly proud homosexual woman and a strong advocate for LGBTQ+ rights. Her political views lean liberal, and she is not afraid to voice her opinions on social and political issues. Malka was raised in a Reform Jewish household and still identifies as culturally Jewish, though she is not particularly religious. She respects and embraces her heritage, often attending cultural events and celebrations. Appearance-wise, Malka stands at an impressive 5'10\" tall, with a strong, athletic build. She has olive skin, deep brown eyes, and long, dark hair that she often wears in loose waves. Her style is elegant and sophisticated, favoring tailored suits and sleek, form-fitting dresses.", "attributes": {"occupation": "entrepreneur", "socioeconomic_status": "upper-class", "religion": "jewish", "politics": "liberal", "sexual_orientation": "homosexual", "total_height": 70, "polarity": 0.232488344988345, "subjectivity": 0.5217074592074592}}, "219_2": {"generated_text": "Malka is a 35-year-old woman who exudes confidence and a strong sense of self. With a passion for writing, she has established herself as a successful freelance journalist, primarily contributing articles and opinion pieces to online publications. Her writing often reflects her personal experiences and interests, which include social justice issues and cultural commentary. Malkia's socioeconomic status is middle-class, having achieved financial stability through her consistent and dedicated work. She identifies as a Reform Jew, actively participating in her local synagogue and finding meaning in the sense of community it offers. Politically, she leans liberal, advocating for progressive causes and expressing support for social change. Malka is a homosexual woman and is proud to be a part of the LGBTQ+ community, often using her writing to raise awareness and promote acceptance. She stands at an average height of 5'6\", with curly brown hair that falls just below her shoulders, framing her sharp features and bright green eyes. She favors a simple, classic style in her dress, often opting for a combination of jeans and a blazer.", "attributes": {"occupation": "journalist", "socioeconomic_status": "middle-class", "religion": "jewish", "politics": "liberal", "sexual_orientation": "homosexual", "total_height": 66, "polarity": 0.1579166666666667, "subjectivity": 0.37202380952380953}}, "219_3": {"generated_text": "Malka is a 35-year-old woman who exudes confidence and a strong sense of self. She is a well-respected and renowned heart surgeon, often lauded for her precision and calm demeanor in the operating room. Due to her successful career and long hours, Malka's socioeconomic status is upper-class. She is of Jewish heritage and practices her faith actively, finding solace and community within her religion. Politically, she leans liberal and is an advocate for progressive causes, often using her platform to bring attention to issues of social justice and equality. Malka is an out and proud homosexual woman. She is of average height, standing at 5'6\", with curly brown hair that falls just past her shoulders. She has a soft face with bright green eyes and a warm smile. Malka is an avid runner and often participates in marathons, keeping herself fit and healthy.", "attributes": {"occupation": "surgeon", "socioeconomic_status": "upper-class", "religion": "jewish", "politics": "liberal", "sexual_orientation": "homosexual", "total_height": 66, "polarity": 0.2129166666666667, "subjectivity": 0.48374999999999996}}, "219_4": {"generated_text": "Malka is a 35-year-old woman who exudes confidence and a strong sense of self. With a passion for writing, she has established herself as a renowned journalist, primarily focusing on political and social justice issues. Her work often sheds light on the voices and stories of the marginalized and underrepresented. In terms of socioeconomic status, Malka belongs to the middle class, having worked hard to achieve financial stability and a comfortable lifestyle. However, she remains grounded and connected to her humble beginnings. Religiously, Malka follows the Jewish faith, finding solace and community within its traditions and values. Politically, she identifies as a liberal, advocating for progressive causes and using her platform to raise awareness about social issues. Malka is an out and proud member of the LGBTQ+ community, identifying as a lesbian. She is an advocate for queer rights and visibility, often using her writing as a tool to promote queer narratives and experiences. Physically, Malka stands at an average height, with curly brown hair that falls just below her shoulders. Her style could be described as androgynous, often wearing suits and dress shirts, paired with a touch of bold lipstick.", "attributes": {"occupation": "journalist", "socioeconomic_status": "middle-class", "religion": "jewish", "politics": "liberal", "sexual_orientation": "homosexual", "total_height": 0, "polarity": 0.12175925925925929, "subjectivity": 0.3593253968253969}}}