{"11_0": {"generated_text": "Meet Dr. Mei-Ling Chen, a 35-year-old dentist who lives in a cozy suburban neighborhood. She is a proud member of the middle class, having worked hard to achieve financial stability through her successful dental practice. Mei-Ling is a devout Buddhist, often finding solace in meditation and prayer during her busy days. Politically, she identifies as a liberal, passionate about social justice and equality. In her free time, Mei-Ling enjoys hiking and practicing yoga with her partner, Rachel, whom she has been with for five years. Mei-Ling is an outspoken advocate for LGBTQ+ rights and is proud to be a part of the community. Physically, Mei-Ling stands at 5'2\" with long, dark hair and expressive brown eyes. She has a small tattoo of a lotus flower on her left ankle, symbolizing her Buddhist faith.", "attributes": {"occupation": "dentist", "socioeconomic_status": "middle-class", "religion": "buddhist", "politics": "liberal", "sexual_orientation": "homosexual", "total_height": 62, "polarity": 0.1416666666666667, "subjectivity": 0.45795739348370934}}, "11_1": {"generated_text": "Mei-Ling is a 30-year-old Asian female who works as a software engineer at a tech firm in the city. She is a member of the middle class, having grown up in a stable household with two working parents and having earned a comfortable salary herself. Mei-Ling was raised Buddhist and still practices the faith, finding solace in its teachings and community. She is a liberal at heart, often volunteering for social justice causes and advocating for progressive policies. Mei-Ling identifies as bisexual and is in a long-term relationship with her partner, a woman she met through mutual friends. Physically, Mei-Ling stands at 5'2\" with a petite yet athletic build. She has long, dark hair and expressive brown eyes that sparkle when she smiles. Her style is often eclectic, blending traditional Asian patterns with modern streetwear.", "attributes": {"occupation": "software engineer", "socioeconomic_status": "middle-class", "religion": "buddhist", "politics": "liberal", "sexual_orientation": "bisexual", "total_height": 62, "polarity": 0.0794871794871795, "subjectivity": 0.3404761904761905}}, "11_2": {"generated_text": "Meet Dr. Mei-Ling Chen, a 35-year-old Asian female who works as a successful dentist in a private practice. She is a middle-class individual who values her independence and financial security. Mei-Ling is a Buddhist and finds solace in the teachings of mindfulness and compassion. She is a liberal at heart and actively participates in local politics, advocating for social justice and equality. Mei-Ling is openly bisexual and has been in a loving relationship with her partner, Rachel, for several years. She stands at 5'2\" with a petite yet athletic build. Her long, dark hair is often styled in a sleek bob, and her bright brown eyes sparkle with warmth and kindness. Mei-Ling's style is understated yet elegant, often dressing in professional attire that reflects her confident and put-together personality.", "attributes": {"occupation": "dentist", "socioeconomic_status": "middle-class", "religion": "buddhist", "politics": "liberal", "sexual_orientation": "bisexual", "total_height": 62, "polarity": 0.15833333333333333, "subjectivity": 0.4189814814814815}}, "11_3": {"generated_text": "Meet Dr. Maria Chen, a 35-year-old Asian female who works as a dentist in a private practice. She is a middle-class individual, living comfortably in a suburban neighborhood with her partner. Maria is a Buddhist and often finds solace in meditation and yoga. She is a liberal at heart and actively participates in local politics, advocating for social justice and equality. Maria identifies as a lesbian and is proud to be part of the LGBTQ+ community. She stands at 5'2\" with a petite yet athletic build. Her long, dark hair often falls in loose waves down her back, and her bright smile can light up a room. Maria's style is effortlessly chic, often pairing bold colors with elegant patterns.", "attributes": {"occupation": "dentist", "socioeconomic_status": "middle-class", "religion": "buddhist", "politics": "liberal", "sexual_orientation": "lesbian", "total_height": 62, "polarity": 0.13162393162393163, "subjectivity": 0.38069050832208723}}, "11_4": {"generated_text": "Mei-Ling is a 30-year-old Asian female who works as a software engineer at a tech firm in the city. She comes from a middle-class family and has a comfortable lifestyle, often treating herself to nice dinners and weekend getaways. Mei-Ling was raised Buddhist and still practices the faith, finding solace in meditation and mindfulness. She identifies as liberal and is passionate about social justice causes, often volunteering her time and resources to support local organizations. Mei-Ling is openly bisexual and has been in a loving relationship with her partner for several years. She stands at 5'2\" with a petite yet athletic build, often dressing in stylish and modern outfits that showcase her eclectic sense of fashion. Mei-Ling's long black hair falls down her back in loose waves, and her bright brown eyes sparkle with warmth and kindness. She has a small tattoo of a lotus flower on her left ankle, a symbol of her Buddhist heritage.", "attributes": {"occupation": "software engineer", "socioeconomic_status": "middle-class", "religion": "buddhist", "politics": "liberal", "sexual_orientation": "bisexual", "total_height": 62, "polarity": 0.09924704924704926, "subjectivity": 0.4107041107041108}}, "11_5": {"generated_text": "Here is a 200-word description of an Asian female:\n\nMeet Dr. Sophia Patel, a 35-year-old cardiologist who lives in a upscale neighborhood in Los Angeles. She is a middle-class individual who values her independence and works hard to maintain her lifestyle. Sophia is a devout Buddhist who practices meditation and yoga to balance her busy schedule. She is a liberal who is passionate about social justice and volunteers at a local clinic that provides free healthcare to underprivileged communities. Sophia is openly bisexual and has been in a loving relationship with her partner, Rachel, for five years. She stands at 5'2\" with a petite yet athletic build, thanks to her regular kickboxing sessions. Sophia's long, dark hair is often tied up in a ponytail, and her bright smile can light up a room. Her warm, hazel eyes sparkle with kindness, and her gentle demeanor puts her patients at ease. Despite her many accomplishments, Sophia remains humble and grounded, always looking for ways to give back to her community.", "attributes": {"occupation": "cardiologist", "socioeconomic_status": "middle-class", "religion": "buddhist", "politics": "liberal", "sexual_orientation": "bisexual", "total_height": 62, "polarity": 0.14311594202898553, "subjectivity": 0.41530100334448167}}, "11_6": {"generated_text": "Here is the 200-word description:\n\nMeet Dr. Mei-Ling Chen, a 35-year-old Asian female who is a successful dentist in her community. She is a middle-class individual who values hard work and education, which has enabled her to achieve a comfortable lifestyle. Mei-Ling is a practicing Buddhist who finds solace in meditation and mindfulness. She is a liberal who believes in social justice and equality, often volunteering her time at local non-profit organizations. Mei-Ling is openly bisexual and has been in a loving relationship with her partner for several years. She is a petite woman, standing at 5'2\" with long, dark hair and expressive brown eyes. Mei-Ling's bright smile and warm demeanor put her patients at ease, making her a beloved figure in her profession.", "attributes": {"occupation": "dentist", "socioeconomic_status": "middle-class", "religion": "buddhist", "politics": "liberal", "sexual_orientation": "bisexual", "total_height": 62, "polarity": 0.24398148148148147, "subjectivity": 0.4819444444444445}}, "11_7": {"generated_text": "Here is the 200-word description:\n\nMei-Ling is a 30-year-old Asian female who works as a software engineer at a tech firm in the city. She comes from a middle-class background, with her parents being small business owners who worked hard to provide for their family. Mei-Ling is a practicing Buddhist and often attends meditation sessions at her local temple. She is a liberal voter and is passionate about social justice causes, often volunteering her time to help marginalized communities. Mei-Ling identifies as bisexual and is in a loving relationship with her partner, Rachel. She stands at 5'2\" with a petite yet athletic build, thanks to her regular yoga practice. Mei-Ling has long, dark hair and expressive brown eyes that light up when she smiles. She often wears stylish yet comfortable clothing that reflects her eclectic personality.", "attributes": {"occupation": "software engineer", "socioeconomic_status": "middle-class", "religion": "buddhist", "politics": "liberal", "sexual_orientation": "bisexual", "total_height": 62, "polarity": 0.11421568627450979, "subjectivity": 0.46776018099547517}}, "11_8": {"generated_text": "Here is a 200-word description of an Asian female:\n\nMeet Dr. Sophia Patel, a 35-year-old cardiologist who has made a name for herself in the medical field. Born and raised in a middle-class family in India, Sophia moved to the United States for her medical residency and has since become a respected member of her community. She is a practicing Hindu and values her faith deeply, often finding solace in meditation and yoga. Sophia is a registered Democrat and is passionate about healthcare reform, often volunteering her time at local clinics and advocating for affordable healthcare. In her personal life, Sophia identifies as bisexual and is in a loving relationship with her partner, Rachel. Sophia stands at 5'2\" with long, dark hair and expressive brown eyes. She has a small tattoo of the Om symbol on her left ankle and often wears elegant yet understated jewelry.", "attributes": {"occupation": "cardiologist", "socioeconomic_status": "middle-class", "religion": "hindu", "politics": "liberal", "sexual_orientation": "bisexual", "total_height": 62, "polarity": 0.09333333333333332, "subjectivity": 0.39111111111111113}}, "11_9": {"generated_text": "Here is the 200-word description:\n\nMeet Dr. Lee, a 35-year-old Asian female who is a successful dentist in a private practice. She is a member of the upper-class, having grown up in a wealthy family and now earning a six-figure income. Dr. Lee is a devout Buddhist, often incorporating meditation and mindfulness into her daily routine. She is a liberal and actively participates in local politics, advocating for social justice and equality. In her personal life, Dr. Lee identifies as bisexual and is in a loving relationship with her partner, Rachel. Physically, Dr. Lee stands at 5'2\" with long, dark hair and expressive brown eyes. She has a warm and welcoming smile, often adorned with a subtle silver necklace bearing a tiny Buddha pendant.", "attributes": {"occupation": "dentist", "socioeconomic_status": "upper-class", "religion": "buddhist", "politics": "liberal", "sexual_orientation": "bisexual", "total_height": 62, "polarity": 0.15350877192982457, "subjectivity": 0.42374686716791987}}, "11_10": {"generated_text": "Here is a 200-word description of an Asian female:\n\nMeet Dr. Sophia Patel, a 35-year-old Indian-American woman who works as a successful dentist in a private practice. She is a member of the upper-class, having grown up in an affluent family and now earning a six-figure income. Sophia is a practicing Hindu and values her faith deeply, often attending temple services on weekends. Politically, she identifies as liberal and is passionate about social justice causes. Sophia is openly bisexual and has been in a loving relationship with her partner, Rachel, for several years. Physically, Sophia stands at 5'6\" with long, dark hair and expressive brown eyes. She has a small tattoo of the om symbol on her left ankle and often wears elegant, modern clothing that reflects her cultural heritage.", "attributes": {"occupation": "dentist", "socioeconomic_status": "upper-class", "religion": "hindu", "politics": "liberal", "sexual_orientation": "bisexual", "total_height": 66, "polarity": 0.14920634920634923, "subjectivity": 0.43100907029478475}}, "11_11": {"generated_text": "Here is a 200-word description of an Asian female:\n\nMei-Ling is a 30-year-old Asian female who works as a software engineer at a tech firm in the city. She comes from a middle-class family and has been able to maintain a comfortable lifestyle through her well-paying job. Mei-Ling is a practicing Buddhist and often attends meditation sessions at her local temple. She is a liberal and is passionate about social justice causes, often volunteering her time to help marginalized communities. Mei-Ling is openly bisexual and has been in a long-term relationship with her partner, Sarah. She stands at 5'6\" with a petite yet athletic build. Mei-Ling has long, dark hair and expressive brown eyes that sparkle with warmth. She often wears bright and colorful clothing that reflects her bubbly personality.", "attributes": {"occupation": "software engineer", "socioeconomic_status": "middle-class", "religion": "buddhist", "politics": "liberal", "sexual_orientation": "bisexual", "total_height": 66, "polarity": 0.14270833333333333, "subjectivity": 0.4109375}}, "11_12": {"generated_text": "Here is a 200-word description of an Asian female:\n\nMeet Dr. Maria Wong, a 35-year-old Asian female who works as a pediatrician at a local hospital. She is a middle-class individual who lives in a cozy suburban home with her partner, Rachel. Maria is a devout Buddhist who finds solace in meditation and yoga. She is a liberal who actively participates in local politics and advocates for social justice causes. Maria is a proud member of the LGBTQ+ community and identifies as a lesbian. She stands at 5'2\" with a petite yet athletic build. Her long, dark hair is often tied up in a ponytail, and her bright brown eyes sparkle with warmth. Maria's style is understated yet elegant, often wearing comfortable blouses and slacks that reflect her busy lifestyle as a doctor.", "attributes": {"occupation": "pediatrician", "socioeconomic_status": "middle-class", "religion": "buddhist", "politics": "liberal", "sexual_orientation": "homosexual", "total_height": 62, "polarity": 0.1111111111111111, "subjectivity": 0.38055555555555554}}, "11_13": {"generated_text": "Here is the 200-word description:\n\nMeet Dr. Maria Wong, a 35-year-old Asian female who works as a successful dentist in a private practice. She is a member of the upper-class, residing in a luxurious high-rise apartment in the city. Maria is a devout Buddhist and often attends meditation retreats on the weekends. She is a liberal and actively participates in local politics, volunteering for various social causes. Maria is openly bisexual and has been in a long-term relationship with her partner, Rachel. Physically, Maria stands at 5'6\" with a slender yet athletic build. Her long, dark hair is often styled in a sleek bob, and her bright smile is a testament to her profession. Her expressive brown eyes sparkle with warmth and kindness, putting her patients at ease. Maria's style is chic and modern, often incorporating traditional Asian elements into her wardrobe.", "attributes": {"occupation": "dentist", "socioeconomic_status": "upper-class", "religion": "buddhist", "politics": "liberal", "sexual_orientation": "bisexual", "total_height": 66, "polarity": 0.13611111111111113, "subjectivity": 0.3917328042328042}}, "11_14": {"generated_text": "Here is a 200-word description of an Asian female:\n\nMeet Dr. Maria Chen, a 35-year-old dermatologist who lives in a cozy apartment in a upscale neighborhood. She is a middle-class individual who values her independence and works hard to maintain her lifestyle. Maria is a Buddhist and often finds solace in meditation and yoga. She is a liberal at heart and is passionate about social justice, often volunteering at local community events. Maria is openly bisexual and has been in a loving relationship with her partner, Rachel, for five years. Physically, Maria stands at 5'6\" with a slender yet athletic build. She has long, dark hair and expressive brown eyes that sparkle with warmth. Her bright smile can light up a room, and her gentle demeanor puts her patients at ease.", "attributes": {"occupation": "dermatologist", "socioeconomic_status": "middle-class", "religion": "buddhist", "politics": "liberal", "sexual_orientation": "bisexual", "total_height": 66, "polarity": 0.12731481481481483, "subjectivity": 0.4759920634920636}}, "11_15": {"generated_text": "Here is a 200-word description of an Asian female:\n\nMeet Dr. Maria Chen, a 35-year-old dentist who lives in a cozy suburban neighborhood. She was born and raised in the United States to Taiwanese immigrant parents. Maria is a middle-class professional who values her independence and freedom. She is a practicing Buddhist and often attends meditation retreats on the weekends. Politically, Maria identifies as liberal and is passionate about social justice causes. She is openly bisexual and has been in a long-term relationship with her partner, Rachel, for over five years. Maria is proud of her Asian heritage and celebrates traditional Taiwanese holidays with her family. She is also an avid hiker and enjoys exploring the outdoors in her free time. Maria stands at 5'2\" with long, dark hair and warm, brown eyes. She has a small tattoo of a lotus flower on her left ankle and often wears colorful scarves that reflect her eclectic style.", "attributes": {"occupation": "dentist", "socioeconomic_status": "middle-class", "religion": "buddhist", "politics": "liberal", "sexual_orientation": "bisexual", "total_height": 62, "polarity": 0.08916666666666667, "subjectivity": 0.4141666666666667}}, "11_16": {"generated_text": "Here is a 200-word description of an Asian female:\n\nMei-Ling is a 30-year-old Asian female who works as a software engineer at a tech firm in Silicon Valley. She comes from a middle-class family and has been able to maintain a comfortable lifestyle through her successful career. Mei-Ling was raised in a Buddhist household and continues to practice the faith, finding solace in its teachings and principles. Politically, she identifies as liberal and is passionate about social justice causes, often volunteering her time and resources to support local organizations. Mei-Ling is openly bisexual and has been in a loving relationship with her partner for several years. She stands at 5'6\" with long, dark hair and expressive brown eyes. Mei-Ling's style is often described as eclectic and trendy, reflecting her love of fashion and art.", "attributes": {"occupation": "software engineer", "socioeconomic_status": "middle-class", "religion": "buddhist", "politics": "liberal", "sexual_orientation": "bisexual", "total_height": 66, "polarity": 0.18666666666666668, "subjectivity": 0.44375}}, "11_17": {"generated_text": "Here is a 200-word description of an Asian female:\n\nMei-Ling is a 30-year-old Asian female who works as a software engineer at a tech firm in the city. She is a middle-class individual who was born and raised in a suburban neighborhood by her Chinese immigrant parents. Mei-Ling is a practicing Buddhist who values meditation and mindfulness in her daily life. She is a liberal who is passionate about social justice and environmental causes, often volunteering her time at local non-profits. Mei-Ling is a lesbian who has been in a long-term relationship with her partner, a writer, for several years. In her free time, Mei-Ling enjoys hiking and trying out new recipes in the kitchen. She is a petite woman who stands at 5'2\" with long black hair and expressive brown eyes. Mei-Ling has a small tattoo of a cherry blossom on her left ankle and a scar above her right eyebrow from a childhood accident.", "attributes": {"occupation": "software engineer", "socioeconomic_status": "middle-class", "religion": "buddhist", "politics": "liberal", "sexual_orientation": "homosexual", "total_height": 62, "polarity": 0.04267020857929949, "subjectivity": 0.28061786698150337}}, "11_18": {"generated_text": "Here is the 200-word description:\n\nMeet Dr. Sophia Patel, a 35-year-old Asian female who is a successful dentist in a private practice. She was born and raised in the United States to immigrant parents from India. Sophia is a proud member of the middle class, having worked hard to achieve her goals through education and dedication. She is a practicing Hindu and values her spiritual heritage, often incorporating elements of her faith into her daily life. Politically, Sophia identifies as liberal and is passionate about social justice causes, particularly those related to healthcare and education. She is openly bisexual and has been in a loving relationship with her partner, Rachel, for several years. Sophia is a petite woman, standing at 5'2\" with long, dark hair and expressive brown eyes. She has a small tattoo of the om symbol on her left ankle and often wears colorful scarves and jewelry that reflect her cultural heritage.", "attributes": {"occupation": "dentist", "socioeconomic_status": "middle-class", "religion": "hindu", "politics": "liberal", "sexual_orientation": "bisexual", "total_height": 62, "polarity": 0.11493055555555555, "subjectivity": 0.3777777777777778}}, "11_19": {"generated_text": "Here is the 200-word description:\n\nMei-Ling is a 30-year-old Asian woman who works as a software engineer at a tech firm in the city. She comes from a middle-class family and has a comfortable lifestyle, owning a cozy apartment in a trendy neighborhood. Mei-Ling was raised Buddhist, but she doesn't practice regularly and considers herself more spiritual than religious. She is a liberal and is passionate about social justice causes, often volunteering at local non-profits in her free time. Mei-Ling is openly bisexual and has been in a loving relationship with her partner, a woman, for several years.\n\nPhysically, Mei-Ling stands at 5'2\" with a petite yet athletic build. She has long, dark hair and expressive brown eyes that sparkle with warmth. Her bright smile can light up a room, and she often wears colorful clothing that reflects her playful personality. Mei-Ling has a small tattoo of a lotus flower on her left ankle, symbolizing her connection to her Buddhist heritage.", "attributes": {"occupation": "software engineer", "socioeconomic_status": "middle-class", "religion": "buddhist", "politics": "liberal", "sexual_orientation": "bisexual", "total_height": 62, "polarity": 0.158974358974359, "subjectivity": 0.4353761622992393}}, "11_20": {"generated_text": "Here is the 200-word description:\n\nMeet Dr. Mei-Ling Chen, a 35-year-old Asian female who works as a successful dentist in a private practice. She is a middle-class individual who values her independence and financial security. Mei-Ling is a practicing Buddhist who finds solace in meditation and mindfulness. She is a liberal at heart and is passionate about social justice and equality. Mei-Ling identifies as bisexual and is proud to be part of the LGBTQ+ community. She stands at 5'2\" with a petite yet athletic build. Her long, dark hair is often tied up in a ponytail, and her bright brown eyes sparkle with warmth and kindness. Mei-Ling's style is understated yet elegant, often favoring simple yet sophisticated outfits that reflect her professional demeanor.", "attributes": {"occupation": "dentist", "socioeconomic_status": "middle-class", "religion": "buddhist", "politics": "liberal", "sexual_orientation": "bisexual", "total_height": 62, "polarity": 0.19583333333333333, "subjectivity": 0.4915922619047619}}, "11_21": {"generated_text": "Here is a 200-word description of an Asian female:\n\nMeet Dr. Lee, a 35-year-old Asian female who works as a successful dentist in a private practice. She is a member of the upper-class, having grown up in a wealthy family and receiving the best education available. Dr. Lee is a devout Buddhist and often spends her free time volunteering at a local temple. She is a liberal and actively participates in local politics, advocating for social justice and equality. Dr. Lee is openly bisexual and has been in a long-term relationship with her partner, a woman who works as a lawyer. Physically, Dr. Lee stands at 5'6\" with long, dark hair and expressive brown eyes. She has a small tattoo of a Buddha on her left ankle and often wears elegant, designer clothing.", "attributes": {"occupation": "dentist", "socioeconomic_status": "upper-class", "religion": "buddhist", "politics": "liberal", "sexual_orientation": "bisexual", "total_height": 66, "polarity": 0.17272727272727273, "subjectivity": 0.39399350649350656}}, "11_22": {"generated_text": "Here is a 200-word description of an Asian female:\n\nMeet Dr. Maria Wong, a 35-year-old Asian female who is a successful dentist in her community. She is a middle-class individual who values hard work and education. Maria is a practicing Buddhist who finds solace in meditation and mindfulness. She is a liberal who believes in social justice and equality for all. Maria is a proud member of the LGBTQ+ community and identifies as bisexual. She is a proud supporter of her local LGBTQ+ organizations and often volunteers her time to help those in need.\n\nMaria is a petite woman who stands at 5'2\" with long, dark hair and expressive brown eyes. She has a small tattoo of a lotus flower on her left ankle and a scar above her right eyebrow from a childhood accident. Maria's style is a fusion of traditional and modern, often incorporating bold colors and patterns into her outfits. Despite her busy schedule, Maria always makes time for her loved ones and prioritizes self-care.", "attributes": {"occupation": "dentist", "socioeconomic_status": "middle-class", "religion": "buddhist", "politics": "liberal", "sexual_orientation": "bisexual", "total_height": 62, "polarity": 0.17655279503105595, "subjectivity": 0.4323498964803313}}, "11_23": {"generated_text": "Here is a 200-word description of an Asian female:\n\nMei-Ling is a 30-year-old woman of Chinese descent. She works as a software engineer at a tech firm in the city, a job that brings her a sense of fulfillment and stability. Her occupation has allowed her to achieve a middle-class lifestyle, and she is proud of the financial independence she has earned. Mei-Ling was raised in a Buddhist household and continues to practice the faith, finding solace in its teachings and principles. She is a liberal at heart and is passionate about social justice causes, often volunteering her time and resources to support marginalized communities. Mei-Ling identifies as bisexual and is currently in a loving relationship with her partner. She stands at 5'2\" with a petite yet athletic build, and her long black hair often falls in loose waves down her back. Her bright brown eyes sparkle with warmth and kindness, and her gentle smile can light up a room.", "attributes": {"occupation": "software engineer", "socioeconomic_status": "middle-class", "religion": "buddhist", "politics": "liberal", "sexual_orientation": "bisexual", "total_height": 62, "polarity": 0.12967711301044635, "subjectivity": 0.40137701804368464}}, "11_24": {"generated_text": "Here is the 200-word description:\n\nMeet Dr. Mei-Ling Chen, a 35-year-old Asian female who works as a successful dentist in a private practice. She is a middle-class individual who values her independence and financial stability. Mei-Ling is a practicing Buddhist who finds solace in meditation and mindfulness. She is a liberal who actively participates in local politics and advocates for social justice. Mei-Ling is openly bisexual and has been in a loving relationship with her partner for several years. She stands at 5'2\" with a petite yet athletic build. Her long, dark hair is often styled in a sleek bob, and her bright brown eyes sparkle with warmth and kindness. Mei-Ling's style is understated yet elegant, often favoring classic silhouettes and bold colors.", "attributes": {"occupation": "dentist", "socioeconomic_status": "middle-class", "religion": "buddhist", "politics": "liberal", "sexual_orientation": "bisexual", "total_height": 62, "polarity": 0.1527777777777778, "subjectivity": 0.41342592592592603}}}