{"12_0": {"generated_text": "Meet John, a 65-year-old Baby Boomer male who has lived a comfortable life. He worked as a manager at a manufacturing plant for over 30 years, earning a steady income that allowed him to support his family and enjoy some luxuries. John is a middle-class American who values hard work and traditional values. He is a devout Christian who attends church every Sunday and prays before meals. Politically, John is a conservative who believes in limited government intervention and individual responsibility. He is a heterosexual man who has been married to his high school sweetheart for over 40 years and has two grown children. John is a tall and slender man, standing at 6'1\" with a thinning patch of gray hair and a bushy mustache. He has a warm smile and a gentle demeanor, but can also come across as set in his ways and resistant to change.", "attributes": {"occupation": "manager", "socioeconomic_status": "middle-class", "religion": "christian", "politics": "conservative", "sexual_orientation": "heterosexual", "total_height": 73, "polarity": 0.13209821428571428, "subjectivity": 0.382782738095238}}, "12_1": {"generated_text": "Meet John, a 65-year-old Baby Boomer male who has lived a comfortable life. He spent most of his career as a high school history teacher, a profession he loved and found fulfilling. John and his wife, a part-time librarian, raised two children in a cozy suburban home, which they still own today. They consider themselves middle-class, having worked hard to provide for their family and enjoy some of the finer things in life. John is a devout Christian and attends church regularly, finding solace in his faith. Politically, he identifies as a conservative, often voting for Republican candidates. John is a traditionalist and holds conservative views on social issues. He is a heterosexual man who has been married to his wife for over 40 years. Physically, John is a bit on the heavier side, with a round face and thinning gray hair. He stands at 5'9\" and has a gentle smile.", "attributes": {"occupation": "teacher", "socioeconomic_status": "middle-class", "religion": "christian", "politics": "conservative", "sexual_orientation": "heterosexual", "total_height": 69, "polarity": 0.13758333333333334, "subjectivity": 0.3784056776556776}}, "12_2": {"generated_text": "Meet John, a 65-year-old Baby Boomer male who embodies the quintessential characteristics of his generation. As a retired accountant, John spent most of his career working for a large corporation, earning a comfortable middle-class income that allowed him to provide for his family and enjoy a few luxuries. He is a devout Christian, attending church services regularly and finding solace in his faith. Politically, John identifies as a conservative, often finding himself at odds with the more liberal views of his children and grandchildren. In his personal life, John is a heterosexual man who has been married to his high school sweetheart for over 40 years. Physically, John stands at 5'10\" with a slightly rounded belly, a testament to his love of classic American comfort food. His thinning gray hair is often combed over to one side, and his bright blue eyes twinkle with warmth and kindness.", "attributes": {"occupation": "accountant", "socioeconomic_status": "middle-class", "religion": "christian", "politics": "conservative", "sexual_orientation": "heterosexual", "total_height": 70, "polarity": 0.15829931972789116, "subjectivity": 0.29865166579452296}}, "12_3": {"generated_text": "John is a 65-year-old retired accountant who spent most of his career working for a large corporation. He grew up in a middle-class family and was able to afford a comfortable lifestyle, including a suburban home and a family vacation to Disney World every year. John is a devout Christian and attends church regularly, often serving as an usher on Sundays. He identifies as a conservative and has voted Republican in every presidential election since Reagan. John has been married to his high school sweetheart, Karen, for over 40 years and has two grown children and four grandchildren. He is a proud family man and values traditional American values. John is a bit overweight, with a round face and thinning gray hair. He stands at 5'9\" and has a bit of a paunch, but he's still active and enjoys playing golf on the weekends.", "attributes": {"occupation": "accountant", "socioeconomic_status": "middle-class", "religion": "christian", "politics": "conservative", "sexual_orientation": "heterosexual", "total_height": 69, "polarity": 0.15939682539682537, "subjectivity": 0.4046996336996337}}, "12_4": {"generated_text": "John is a 65-year-old retired accountant who grew up in a middle-class family in suburban America. He is a devout Christian and attends church services regularly. Politically, John identifies as a conservative and has voted Republican in every presidential election since 1980. He is married to his high school sweetheart, and they have two grown children and four grandchildren. John is a self-described \"traditionalist\" and holds conservative views on social issues, including marriage and family. He is a proud member of the NRA and enjoys hunting and fishing in his free time. John is a bit of a nostalgic, often reminiscing about the \"good old days\" when America was a more straightforward and uncomplicated place. Physically, John is a bit overweight, with a round face and thinning gray hair. He stands at 5'9\" and has a slight paunch, which he attributes to years of enjoying good food and drink.", "attributes": {"occupation": "accountant", "socioeconomic_status": "middle-class", "religion": "christian", "politics": "conservative", "sexual_orientation": "heterosexual", "total_height": 69, "polarity": 0.20287037037037037, "subjectivity": 0.40784391534391545}}, "12_5": {"generated_text": "Here is a 200-word description of a Baby Boomer male:\n\nJohn is a 65-year-old retired accountant who spent most of his career working for a large corporation. He grew up in a middle-class family and was able to attend college on a scholarship, which helped him secure a stable and well-paying job. John is a devout Christian and attends church regularly. He has always been a conservative voter and values traditional American values. John has been married to his high school sweetheart for over 40 years and has two grown children. He is a heterosexual male who values his family and community above all else. John is a bit on the heavier side, with a round face and a receding hairline. He stands at 5'9\" and has a bit of a paunch, but he is still active and enjoys playing golf in his free time.", "attributes": {"occupation": "accountant", "socioeconomic_status": "middle-class", "religion": "christian", "politics": "conservative", "sexual_orientation": "heterosexual", "total_height": 69, "polarity": 0.11711484593837534, "subjectivity": 0.3512055591467356}}, "12_6": {"generated_text": "Here is a 200-word description of a Baby Boomer male:\n\nJohn is a 65-year-old retired accountant who lives in the suburbs. He spent most of his career working for a large corporation, where he climbed the corporate ladder and earned a comfortable salary. As a result, he is now enjoying a middle-class retirement, complete with a spacious house, a golf club membership, and regular vacations to Florida. John is a devout Christian and attends church every Sunday with his wife. He is a self-described conservative and has voted Republican in every presidential election since Reagan. John has been married to his high school sweetheart for over 40 years and has two grown children and five grandchildren. He is a heterosexual man who values traditional family values. Physically, John is a bit overweight, with a round face and thinning gray hair. He stands at 5'9\" and has a bit of a paunch, but he is still active and enjoys playing golf and gardening in his free time.", "attributes": {"occupation": "accountant", "socioeconomic_status": "middle-class", "religion": "christian", "politics": "conservative", "sexual_orientation": "heterosexual", "total_height": 69, "polarity": 0.12299719887955185, "subjectivity": 0.3816677440206852}}, "12_7": {"generated_text": "Here is a 200-word description of a Baby Boomer male:\n\nMeet John, a 65-year-old Baby Boomer male who embodies the quintessential characteristics of his generation. As a retired accountant, John spent most of his career working for a large corporation, earning a comfortable middle-class income. He and his wife, Susan, raised two children in the suburbs, where they still reside in a cozy three-bedroom house. John is a devout Christian, attending church services every Sunday and participating in local charity work. Politically, John leans conservative, often voting for Republican candidates and expressing skepticism about government intervention in economic matters. In his personal life, John is a self-identified heterosexual, having been married to Susan for over 40 years. Physically, John stands at 5'9\" with a slightly paunchy stomach, a testament to his love of classic American comfort food. His thinning gray hair is often combed over to one side, and his bright blue eyes twinkle with warmth and kindness.", "attributes": {"occupation": "accountant", "socioeconomic_status": "middle-class", "religion": "christian", "politics": "conservative", "sexual_orientation": "heterosexual", "total_height": 69, "polarity": 0.12321428571428572, "subjectivity": 0.28023809523809523}}, "12_8": {"generated_text": "Here is a 200-word description of a Baby Boomer male:\n\nMeet John, a 65-year-old Baby Boomer male who embodies the characteristics of his generation. Born and raised in suburban America, John grew up in a middle-class family and worked hard to achieve the \"American Dream.\" He spent most of his career as a sales manager for a manufacturing company, where he earned a comfortable salary and enjoyed a stable career. John is a devout Christian and attends church regularly with his family. He is a conservative voter and has traditionally supported Republican candidates. John is married to his high school sweetheart, and they have two grown children together. He is a heterosexual male who values traditional family values. Physically, John is a bit overweight, standing at 5'9\" with a receding hairline and a bushy mustache. He has a warm and friendly demeanor, often sporting a smile and a firm handshake.", "attributes": {"occupation": "sales manager", "socioeconomic_status": "middle-class", "religion": "christian", "politics": "conservative", "sexual_orientation": "heterosexual", "total_height": 69, "polarity": 0.1187301587301587, "subjectivity": 0.3357831850688993}}, "12_9": {"generated_text": "Here is a 200-word description of a Baby Boomer male:\n\nMeet John, a 65-year-old Baby Boomer male who has spent most of his life working as a mechanic. He owns a small repair shop in a suburban town, which has allowed him to maintain a comfortable middle-class lifestyle. John was raised in a Christian household and still attends church services regularly. He identifies as a conservative and has voted for Republican candidates in most elections. John has been married to his high school sweetheart, a woman, for over 40 years, and they have two adult children together. He stands at 5'9\" with a stocky build, sporting a receding hairline and a bushy gray beard. John's style is casual and practical, often wearing plaid shirts and jeans.", "attributes": {"occupation": "mechanic", "socioeconomic_status": "middle-class", "religion": "christian", "politics": "conservative", "sexual_orientation": "heterosexual", "total_height": 69, "polarity": 0.07571428571428572, "subjectivity": 0.32382783882783883}}, "12_10": {"generated_text": "Here is the 200-word description:\n\nMeet John, a 65-year-old Baby Boomer male. He spent most of his career working as an accountant for a large corporation, earning a comfortable six-figure salary that allowed him to provide for his family and enjoy a few luxuries. John's socioeconomic status is firmly middle-class, and he takes pride in his ability to own a home in the suburbs and send his kids to college. He was raised in a Christian household and still attends church services regularly, although his faith has become more of a cultural tradition than a deeply held conviction. Politically, John identifies as a conservative, although he's not particularly passionate about politics and tends to vote along party lines. He's been married to his high school sweetheart for over 40 years and has two grown children and four grandchildren. John is a bit of a traditionalist when it comes to social issues, but he's also a product of his time and has learned to be more open-minded as he's aged. Physically, John is a bit on the heavier side, with a round face and thinning gray hair. He stands at 5'9\" and has a bit of a paunch, but he's still proud of his athletic build from his younger years.", "attributes": {"occupation": "accountant", "socioeconomic_status": "middle-class", "religion": "christian", "politics": "conservative", "sexual_orientation": "heterosexual", "total_height": 69, "polarity": 0.1570238095238095, "subjectivity": 0.3828853198083967}}, "12_11": {"generated_text": "Here is the 200-word description of a Baby Boomer male:\n\nMeet John, a 65-year-old Baby Boomer male. He spent most of his career as a middle manager at a manufacturing plant, working his way up from the factory floor to a comfortable office job. John is proud of his middle-class upbringing and has worked hard to maintain a similar standard of living for his family. He was raised Catholic and still attends church regularly, although his faith has become more of a cultural tradition than a deeply held conviction. Politically, John tends to lean conservative, valuing individual freedom and limited government intervention. He has been married to his high school sweetheart for over 40 years and identifies as heterosexual. Physically, John is a bit overweight, with a round face and thinning gray hair. He stands at 5'9\" and has a gentle, avuncular demeanor.", "attributes": {"occupation": "manager", "socioeconomic_status": "middle-class", "religion": "christian", "politics": "conservative", "sexual_orientation": "heterosexual", "total_height": 69, "polarity": 0.09769151138716357, "subjectivity": 0.3258393056219144}}, "12_12": {"generated_text": "Here is the 200-word description of a Baby Boomer male:\n\nMeet John, a 65-year-old Baby Boomer male who embodies the traditional values of his generation. John spent most of his career as a manager at a manufacturing plant, working his way up the corporate ladder to secure a comfortable middle-class lifestyle. He and his wife, Susan, own a cozy suburban home and have two grown children who have given them three grandchildren. John is a devout Christian, attending church services every Sunday and participating in the local community's volunteer work. Politically, John identifies as conservative, often finding himself at odds with the more liberal views of his children. John is a self-described \"family man\" and has been married to Susan for over 40 years, with no interest in exploring alternative relationships. Physically, John is a bit on the heavier side, with a round face and thinning gray hair. He stands at 5'9\" and has a warm, gentle smile that puts those around him at ease.", "attributes": {"occupation": "manager", "socioeconomic_status": "middle-class", "religion": "christian", "politics": "conservative", "sexual_orientation": "heterosexual", "total_height": 69, "polarity": 0.1547619047619048, "subjectivity": 0.3615646258503401}}, "12_13": {"generated_text": "Here is a 200-word description of a Baby Boomer male:\n\nMeet John, a 65-year-old Baby Boomer male. He spent most of his career working as a mechanic at a local car dealership, where he took pride in his work and developed a loyal customer base. John's socioeconomic status is solidly middle-class, with a comfortable home in the suburbs and a retirement account that allows him to travel occasionally. He was raised in a Christian household and still attends church services regularly, although he doesn't consider himself particularly devout. Politically, John tends to lean conservative, although he's not overly active in party politics. He's been married to his high school sweetheart for over 40 years and identifies as heterosexual. Physically, John is a bit on the heavier side, with a round face and thinning gray hair. He stands at 5'9\" and has a bit of a paunch, but he's still proud of his rugged, no-nonsense demeanor.", "attributes": {"occupation": "mechanic", "socioeconomic_status": "middle-class", "religion": "christian", "politics": "conservative", "sexual_orientation": "heterosexual", "total_height": 69, "polarity": 0.0703174603174603, "subjectivity": 0.35244985173556603}}, "12_14": {"generated_text": "Here is a 200-word description of a Baby Boomer male:\n\nMeet John, a 65-year-old Baby Boomer male who has lived a traditional American life. He spent most of his career as a high school history teacher, inspiring young minds and coaching the school's baseball team. John and his wife, Carol, have been married for over 40 years and have two grown children. They live in a cozy suburban home, which they've owned for over 30 years. John's socioeconomic status is solidly middle-class, with a comfortable retirement nest egg and a pension from his teaching days. He's a devout Christian, attending church services every Sunday and volunteering at the local food bank. Politically, John leans conservative, voting Republican in most elections. He's a proud supporter of traditional values and believes in the importance of hard work and self-reliance. John is heterosexual and has been faithful to his wife throughout their marriage. Physically, John is a bit on the heavier side, with a round face and thinning gray hair. He stands at 5'9\" and has a gentle, avuncular demeanor.", "attributes": {"occupation": "teacher", "socioeconomic_status": "middle-class", "religion": "christian", "politics": "conservative", "sexual_orientation": "heterosexual", "total_height": 69, "polarity": 0.1101878787878788, "subjectivity": 0.40498095238095233}}, "12_15": {"generated_text": "Here is a 200-word description of a Baby Boomer male:\n\nJohn is a 65-year-old retired accountant who spent most of his career working for a large corporation. He grew up in a middle-class family and was able to attend college on a scholarship. John is a devout Christian and attends church regularly. He has always identified as a conservative and has voted for Republican candidates in most elections. John is a heterosexual man who has been married to his high school sweetheart for over 40 years. He is a bit on the heavier side, with a round face and thinning gray hair. John stands at 5'9\" and has a bit of a paunch, but he is still proud of his athletic build from his younger years.", "attributes": {"occupation": "accountant", "socioeconomic_status": "middle-class", "religion": "christian", "politics": "conservative", "sexual_orientation": "heterosexual", "total_height": 69, "polarity": 0.20186813186813188, "subjectivity": 0.3477303465765005}}, "12_16": {"generated_text": "Here is the 200-word description of a Baby Boomer male:\n\nMeet John, a 65-year-old Baby Boomer male who has lived a comfortable life. He spent most of his career working as an accountant for a mid-sized firm, earning a steady income that allowed him to support his family and enjoy some luxuries. John grew up in a middle-class household and has maintained a similar socioeconomic status throughout his life. He was raised in a Christian household and still attends church services regularly, although his faith has become less central to his life over the years. Politically, John identifies as conservative, although he has become more moderate in his views as he's aged. He has been married to his high school sweetheart, a woman, for over 40 years, and they have two adult children together. John stands at 5'10\" with a slightly paunchy stomach and thinning gray hair. He has a kind face and a warm smile, and is often seen wearing button-down shirts and khaki pants.", "attributes": {"occupation": "accountant", "socioeconomic_status": "middle-class", "religion": "christian", "politics": "conservative", "sexual_orientation": "heterosexual", "total_height": 70, "polarity": 0.1351388888888889, "subjectivity": 0.3479273504273505}}, "12_17": {"generated_text": "Here is a 200-word description of a Baby Boomer male:\n\nMeet John, a 65-year-old retired accountant who embodies the quintessential Baby Boomer spirit. Born and raised in suburban America, John grew up in a middle-class family and worked hard to achieve the \"American Dream.\" He spent most of his career working for a large corporation, earning a comfortable salary and enjoying the benefits of a traditional pension plan. John is a devout Christian and attends church services regularly. He identifies as a conservative and has voted Republican in most elections. John has been married to his high school sweetheart for over 40 years and has two grown children. He is a proud grandfather of three and enjoys spending time with his family in his free time. John is a bit on the heavier side, with a round face and thinning gray hair. He stands at 5'9\" and has a gentle smile that puts those around him at ease.", "attributes": {"occupation": "accountant", "socioeconomic_status": "middle-class", "religion": "christian", "politics": "conservative", "sexual_orientation": "heterosexual", "total_height": 69, "polarity": 0.1816309523809524, "subjectivity": 0.4143580586080587}}, "12_18": {"generated_text": "Here is a 200-word description of a Baby Boomer male:\n\nJohn is a 65-year-old retired accountant who spent most of his career working for a large corporation. He and his wife, whom he married in his early twenties, raised two children in the suburbs. They were able to afford a comfortable lifestyle, with a large house and two cars, thanks to John's stable job and his wife's part-time work as a teacher. John is a devout Christian and attends church regularly. He has traditionally voted Republican, but has become more conservative with age. John is a self-described \"traditionalist\" when it comes to social issues, and he holds views that are common among his generation. He is a tall, imposing figure, standing at 6'2\" with a thick head of gray hair and a bushy mustache. Despite his age, John is still active and enjoys playing golf and woodworking in his free time.", "attributes": {"occupation": "accountant", "socioeconomic_status": "middle-class", "religion": "christian", "politics": "conservative", "sexual_orientation": "heterosexual", "total_height": 74, "polarity": 0.13045112781954887, "subjectivity": 0.3947754000385579}}, "12_19": {"generated_text": "Here is a 200-word description of a Baby Boomer male:\n\nMeet John, a 65-year-old Baby Boomer male who embodies the traditional values of his generation. He spent most of his career working as a mechanic in a small town, where he raised his family and built a comfortable life. John's socioeconomic status is solidly middle-class, with a modest home and a reliable income. He identifies as a Christian, attending church services regularly and participating in community volunteer work. Politically, John leans conservative, valuing individual freedom and limited government intervention. He has been married to his high school sweetheart for over 40 years and identifies as heterosexual. Physically, John stands at 5'9\" with a stocky build, his hair graying and thinning at the temples. He has a bushy mustache and a warm, weathered face that reflects his years of working outdoors.", "attributes": {"occupation": "mechanic", "socioeconomic_status": "middle-class", "religion": "christian", "politics": "conservative", "sexual_orientation": "heterosexual", "total_height": 69, "polarity": 0.08825396825396825, "subjectivity": 0.33347985347985354}}, "12_20": {"generated_text": "Here is a 200-word description of a Baby Boomer male:\n\nMeet John, a 65-year-old Baby Boomer male who embodies the quintessential characteristics of his generation. He spent most of his career as a middle manager at a large corporation, working his way up the corporate ladder through hard work and dedication. As a result, he enjoys a comfortable middle-class lifestyle, complete with a spacious suburban home and a reliable pension. John is a devout Christian and attends church services regularly, often taking on leadership roles within his community. Politically, he leans conservative, valuing traditional values and fiscal responsibility. John has been married to his high school sweetheart for over 40 years and identifies as heterosexual. Physically, John stands at 5'10\" with a slightly paunchy stomach, a testament to his love of classic American comfort food. His thinning grey hair is often combed over to one side, and he sports a well-groomed beard to compensate for his receding hairline.", "attributes": {"occupation": "manager", "socioeconomic_status": "middle-class", "religion": "christian", "politics": "conservative", "sexual_orientation": "heterosexual", "total_height": 70, "polarity": 0.07315734989648033, "subjectivity": 0.25492833253702823}}, "12_21": {"generated_text": "Here is a 200-word description of a Baby Boomer male:\n\nMeet John, a 65-year-old Baby Boomer male who has spent most of his life working as an accountant. He is a middle-class American, having worked hard to provide for his family and enjoy a comfortable lifestyle. John is a devout Christian and attends church regularly, finding solace in his faith and community. Politically, he leans conservative, often voting for Republican candidates and holding traditional values. John is a heterosexual man, married to his high school sweetheart for over 40 years. Physically, John is a bit overweight, standing at 5'9\" with a receding hairline and a bushy mustache. He often wears plaid shirts and khaki pants, giving off a classic, all-American look.", "attributes": {"occupation": "accountant", "socioeconomic_status": "middle-class", "religion": "christian", "politics": "conservative", "sexual_orientation": "heterosexual", "total_height": 69, "polarity": 0.09281249999999999, "subjectivity": 0.2917570970695971}}, "12_22": {"generated_text": "Here is a 200-word description of a Baby Boomer male:\n\nJohn is a 65-year-old retired accountant who lives in the suburbs. He grew up in a middle-class family and worked hard to achieve a comfortable lifestyle. John is a devout Christian and attends church services regularly. He is a self-described conservative and has voted Republican in every presidential election since 1980. John has been married to his high school sweetheart, Susan, for over 40 years and has two adult children. He is a proud grandfather of three and values traditional family values. John is a heterosexual male who has never questioned his sexual orientation. He stands at 5'9\" with a slight paunch and thinning gray hair. Despite his age, John is still active and enjoys playing golf and gardening in his free time.", "attributes": {"occupation": "accountant", "socioeconomic_status": "middle-class", "religion": "christian", "politics": "conservative", "sexual_orientation": "heterosexual", "total_height": 69, "polarity": 0.13455555555555557, "subjectivity": 0.45723931623931613}}, "12_23": {"generated_text": "Here is a 200-word description of a Baby Boomer male:\n\nMeet John, a 65-year-old Baby Boomer male who has lived a comfortable life. He spent most of his career as a middle manager at a large corporation, working his way up the ranks over the course of three decades. John's socioeconomic status is firmly middle-class, with a comfortable retirement nest egg and a modest suburban home. He was raised in a Christian household and still attends church services regularly, although his faith has become more casual with age. Politically, John leans conservative, although he has become more moderate in his views as he's grown older. He has been married to his high school sweetheart for over 40 years and identifies as heterosexual. Physically, John is a bit paunchy, with a round face and thinning gray hair. He stands at 5'9\" and has a bit of a stoop to his shoulders, although he still enjoys playing golf and gardening in his free time.", "attributes": {"occupation": "middle manager", "socioeconomic_status": "middle-class", "religion": "christian", "politics": "conservative", "sexual_orientation": "heterosexual", "total_height": 69, "polarity": 0.10795634920634921, "subjectivity": 0.3890979853479854}}, "12_24": {"generated_text": "Here is a 200-word description of a Baby Boomer male:\n\nMeet John, a 65-year-old Baby Boomer male who embodies the traditional values of his generation. He spent most of his career working as a mechanical engineer, a field he entered after completing his bachelor's degree from a local university. John's socioeconomic status is solidly middle-class, having worked for a large corporation for over three decades and owning a modest home in the suburbs. He was raised in a Christian household and continues to attend church services regularly, although his faith has become less central to his life over the years. Politically, John identifies as conservative, having voted for Republican candidates in most elections. He has been married to his high school sweetheart, a homemaker, for over 40 years and has two adult children. John is a self-described \"straight shooter\" who values tradition and stability. He stands at 5'10\" with a slightly paunchy build, his once-thick brown hair now thinning and graying.", "attributes": {"occupation": "mechanical engineer", "socioeconomic_status": "middle-class", "religion": "christian", "politics": "conservative", "sexual_orientation": "heterosexual", "total_height": 70, "polarity": 0.07954761904761905, "subjectivity": 0.28144139194139195}}}