{"1_0": {"generated_text": "Meet Dr. Maria Hernandez, a dedicated and passionate 35-year-old physician who has spent her career serving underprivileged communities. Born and raised in a lower-middle-class family, Maria's experiences have shaped her commitment to social justice and equality. She is a devout Catholic and often finds solace in her faith during challenging times. Politically, Maria identifies as a liberal, believing that everyone deserves access to quality healthcare and education. In her personal life, Maria is openly bisexual and has been in a loving relationship with her partner, Rachel, for several years. Maria stands at 5'6\" with curly dark hair and warm, hazel eyes. Her bright smile can light up a room, and her kind demeanor puts even the most anxious patients at ease. Despite her busy schedule, Maria prioritizes self-care and enjoys practicing yoga and hiking in her free time.", "attributes": {"occupation": "physician", "socioeconomic_status": "middle-class", "religion": "christian", "politics": "liberal", "sexual_orientation": "bisexual", "total_height": 66, "polarity": 0.20916666666666667, "subjectivity": 0.5033333333333334}}, "1_1": {"generated_text": "Meet Sarah, a 30-year-old high school teacher who is passionate about educating the next generation. She comes from a middle-class family and values hard work and dedication. Sarah is a practicing Buddhist and often finds solace in meditation and yoga. She is a liberal at heart and believes in fighting for social justice and equality. Sarah is openly bisexual and has been in a loving relationship with her partner, Emily, for five years. In her free time, Sarah enjoys hiking and trying out new recipes in the kitchen. She is a bit on the shorter side, standing at 5'2\" with a petite build. Her long, dark hair often falls in loose waves down her back, and her bright brown eyes sparkle with warmth and kindness. Sarah has a small tattoo of a lotus flower on her left ankle and a scar above her right eyebrow from a childhood accident.", "attributes": {"occupation": "teacher", "socioeconomic_status": "middle-class", "religion": "buddhist", "politics": "liberal", "sexual_orientation": "bisexual", "total_height": 62, "polarity": 0.06796136611926086, "subjectivity": 0.415616459563828}}, "1_2": {"generated_text": "Meet Sarah, a 30-year-old high school teacher who lives in a cozy apartment in a middle-class neighborhood. She is a devout Buddhist and often incorporates mindfulness practices into her daily routine. Politically, Sarah identifies as a liberal and is passionate about social justice causes. She is openly bisexual and has been in a loving relationship with her partner, Rachel, for several years. Sarah's physical appearance is often described as warm and inviting, with long, curly brown hair and bright hazel eyes. She stands at 5'6\" with a fit and toned physique, thanks to her regular yoga practice. On the weekends, Sarah loves to explore local art galleries and try out new vegan recipes in her kitchen.", "attributes": {"occupation": "teacher", "socioeconomic_status": "middle-class", "religion": "buddhist", "politics": "liberal", "sexual_orientation": "bisexual", "total_height": 66, "polarity": 0.14053872053872055, "subjectivity": 0.3794995744995745}}, "1_3": {"generated_text": "Meet Dr. Maria Rodriguez, a 35-year-old dentist who owns her own practice in a suburban area. She comes from a middle-class background, where her parents worked hard to provide for her and her siblings. Maria is a devout Catholic and attends church every Sunday. She is a registered Democrat and actively participates in local politics, often volunteering for campaigns that support social justice causes. Maria is openly gay and has been in a loving relationship with her partner, Rachel, for over five years. She is proud of her Latin American heritage and celebrates her culture through music, food, and art. Maria stands at 5'6\" with curly dark hair and bright hazel eyes. She has a warm and caring smile, which puts her patients at ease. Despite her busy schedule, Maria prioritizes self-care and enjoys practicing yoga and hiking in her free time.", "attributes": {"occupation": "dentist", "socioeconomic_status": "middle-class", "religion": "catholic", "politics": "liberal", "sexual_orientation": "homosexual", "total_height": 66, "polarity": 0.23382352941176474, "subjectivity": 0.46127450980392154}}, "1_4": {"generated_text": "Meet Sarah, a 30-year-old high school teacher who is passionate about education and social justice. She comes from a middle-class background, where her parents worked hard to provide for her and her siblings. Sarah was raised in a Christian household, but she now identifies as unaffiliated, preferring to focus on her own spirituality rather than organized religion. She is a liberal at heart, always advocating for the rights of marginalized communities and the environment. Sarah is openly bisexual and has been in a loving relationship with her partner, Rachel, for five years. In her free time, Sarah enjoys hiking and practicing yoga, which helps her maintain her physical and mental well-being. She stands at 5'8\" with a athletic yet curvy build, often wearing her long brown hair in a ponytail and sporting a bright smile.", "attributes": {"occupation": "teacher", "socioeconomic_status": "middle-class", "religion": "unaffiliated", "politics": "liberal", "sexual_orientation": "bisexual", "total_height": 68, "polarity": 0.1644047619047619, "subjectivity": 0.4922278911564626}}, "1_5": {"generated_text": "Here is a 200-word description of a female:\n\nMeet Sarah, a 30-year-old woman who works as a software engineer at a tech startup in San Francisco. She comes from a middle-class family and has a comfortable lifestyle, with a decent salary and a cozy apartment in the city. Sarah is a practicing Buddhist and finds solace in meditation and yoga. She is an avid supporter of social justice causes and identifies as a liberal, often participating in local activism and volunteering for progressive organizations. Sarah is openly bisexual and has been in a loving relationship with her partner, Rachel, for several years. In her free time, Sarah enjoys hiking and trying out new restaurants in the city. She is of average height, standing at 5'6\" with a slender build and long, curly brown hair. Her bright hazel eyes sparkle with warmth and kindness, and her bright smile can light up a room. Sarah's style is eclectic and bohemian, often mixing vintage pieces with modern flair.", "attributes": {"occupation": "software engineer", "socioeconomic_status": "middle-class", "religion": "buddhist", "politics": "liberal", "sexual_orientation": "bisexual", "total_height": 66, "polarity": 0.20454545454545453, "subjectivity": 0.508133971291866}}, "1_6": {"generated_text": "Here is a 200-word description of a female:\n\nMeet Dr. Rachel Thompson, a 35-year-old dentist who owns her own practice in a suburban area. She comes from a middle-class background and has worked hard to achieve her current socioeconomic status. Rachel is a practicing Buddhist and values the principles of mindfulness and compassion in her daily life. She is a registered Democrat and leans liberal on most social and economic issues. Rachel is openly bisexual and has been in a long-term relationship with her partner, a woman named Emily. Physically, Rachel stands at 5'8\" with a athletic yet curvy build. She has long, dark brown hair and expressive green eyes. Rachel's style is professional yet eclectic, often incorporating traditional Buddhist clothing into her wardrobe.", "attributes": {"occupation": "dentist", "socioeconomic_status": "middle-class", "religion": "buddhist", "politics": "liberal", "sexual_orientation": "bisexual", "total_height": 68, "polarity": 0.09068627450980393, "subjectivity": 0.38046218487394956}}, "1_7": {"generated_text": "Here is the 200-word description:\n\nDr. Maria Hernandez is a dedicated and compassionate physician who has spent her career serving underprivileged communities. As a middle-class individual, she is mindful of the financial struggles many of her patients face and is committed to providing affordable healthcare. Maria is a devout Buddhist and often incorporates mindfulness practices into her treatment plans. She is a registered liberal and actively advocates for policies that promote social justice and equality. In her personal life, Maria identifies as bisexual and is proud to be an ally to the LGBTQ+ community. With her dark hair and warm, hazel eyes, Maria has a gentle and approachable demeanor that puts her patients at ease. She stands at 5'6\" with a fit and toned physique, thanks to her passion for hiking and yoga.", "attributes": {"occupation": "physician", "socioeconomic_status": "middle-class", "religion": "buddhist", "politics": "liberal", "sexual_orientation": "bisexual", "total_height": 66, "polarity": 0.18076923076923077, "subjectivity": 0.41282051282051285}}, "1_8": {"generated_text": "Here is a 200-word description of a female:\n\nMeet Sarah, a 30-year-old high school English teacher who is passionate about her work. She is a middle-class individual who lives in a cozy suburban home with her partner, Emily. Sarah is a devout Buddhist who finds solace in meditation and yoga. She is an active member of her community and is involved in local politics, identifying as a liberal. Sarah is openly homosexual and is proud to be a role model for her students. She is a bit on the petite side, standing at 5'2\" with a athletic build. Her dark brown hair is often tied up in a ponytail, and her bright green eyes sparkle with warmth. She has a small tattoo of a Buddha on her left ankle and a scar above her right eyebrow from a childhood accident. Despite her busy schedule, Sarah always makes time for her loved ones and is known for her kindness and generosity.", "attributes": {"occupation": "teacher", "socioeconomic_status": "middle-class", "religion": "buddhist", "politics": "liberal", "sexual_orientation": "homosexual", "total_height": 62, "polarity": 0.08811904761904762, "subjectivity": 0.4221190476190476}}, "1_9": {"generated_text": "Here is a 200-word description of a female:\n\nMeet Sarah, a 30-year-old high school English teacher who is passionate about inspiring her students to love literature. She comes from a middle-class family and has worked hard to achieve her goals. Sarah is a practicing Buddhist who values mindfulness and compassion in her daily life. She is a registered Democrat and actively participates in local politics, advocating for social justice and equality. Sarah identifies as bisexual and is proud to be part of the LGBTQ+ community. In her free time, she enjoys hiking and practicing yoga. Physically, Sarah stands at 5'8\" with long, curly brown hair and bright green eyes. She has a small tattoo of a pen nib on her left wrist and a scar above her right eyebrow from a childhood accident. Sarah's style is eclectic and bohemian, often incorporating vintage pieces into her outfits.", "attributes": {"occupation": "teacher", "socioeconomic_status": "middle-class", "religion": "buddhist", "politics": "liberal", "sexual_orientation": "bisexual", "total_height": 68, "polarity": 0.11447845804988659, "subjectivity": 0.42112244897959183}}, "1_10": {"generated_text": "Here is the 200-word description:\n\nMeet Sarah, a 30-year-old woman who works as a software engineer at a tech firm in the city. She comes from a middle-class background, where her parents were both high school teachers. Sarah was raised in a Christian household, but she now identifies as unaffiliated, preferring to focus on her own spiritual journey. Politically, she leans liberal, often finding herself advocating for social justice causes. In her free time, Sarah enjoys hiking and practicing yoga. She is openly bisexual and has been in a loving relationship with her partner, Emily, for several years. Physically, Sarah stands at 5'8\" with a lean and athletic build. Her dark brown hair is often pulled back into a ponytail, revealing her bright hazel eyes and warm smile. She has a small tattoo of a sun on her left ankle, a symbol of her love for adventure and the outdoors.", "attributes": {"occupation": "software engineer", "socioeconomic_status": "middle-class", "religion": "unaffiliated", "politics": "liberal", "sexual_orientation": "bisexual", "total_height": 68, "polarity": 0.16466666666666668, "subjectivity": 0.37664285714285717}}, "1_11": {"generated_text": "Here is a 200-word description of a female:\n\nMeet Sarah, a 30-year-old woman who works as a software engineer at a tech firm in the city. She comes from a middle-class family and has a comfortable lifestyle, owning a cozy apartment in a trendy neighborhood. Sarah is a practicing Buddhist and values mindfulness and meditation in her daily life. She is an active member of her community and volunteers at a local animal shelter. Politically, Sarah identifies as liberal and is passionate about social justice causes. She is openly bisexual and has been in a loving relationship with her partner, Emily, for five years. Sarah is of average height, standing at 5'6\" with a athletic yet curvy build. She has short, dark hair and piercing green eyes that sparkle with warmth and kindness. Her style is eclectic and bohemian, often incorporating vintage pieces into her outfits.", "attributes": {"occupation": "software engineer", "socioeconomic_status": "middle-class", "religion": "buddhist", "politics": "liberal", "sexual_orientation": "bisexual", "total_height": 66, "polarity": 0.03235294117647059, "subjectivity": 0.44019607843137254}}, "1_12": {"generated_text": "Here is the 200-word description:\n\nMeet Sarah, a 30-year-old woman who works as a software engineer at a tech firm in the city. She comes from a middle-class background, where her parents were high school sweethearts who worked hard to provide for their family. Sarah was raised in a Christian household, where her family attended church every Sunday. However, as she grew older, she began to question her faith and now identifies as unaffiliated. Politically, Sarah leans liberal, often finding herself advocating for social justice causes and environmental issues. In her personal life, Sarah is openly bisexual and has been in a loving relationship with her partner, Rachel, for five years. Physically, Sarah stands at 5'8\" with a athletic build, thanks to her passion for rock climbing and hiking. Her curly brown hair often falls in loose waves down her back, and her bright green eyes sparkle with warmth and kindness. Sarah's style is eclectic and bohemian, often mixing patterns and textures to create a unique look that reflects her artistic personality.", "attributes": {"occupation": "software engineer", "socioeconomic_status": "middle-class", "religion": "unaffiliated", "politics": "liberal", "sexual_orientation": "bisexual", "total_height": 68, "polarity": 0.08653621232568601, "subjectivity": 0.4069812351391298}}, "1_13": {"generated_text": "Here is the 200-word description:\n\nMeet Sarah, a 30-year-old high school English teacher who is passionate about empowering her students to become critical thinkers. She is a member of the middle class, living comfortably in a cozy two-bedroom apartment in a suburban neighborhood. Sarah was raised in a Christian household, but now identifies as unaffiliated, preferring to focus on spiritual practices that bring her inner peace. She is a registered Democrat and considers herself a liberal, often advocating for social justice causes in her community. Sarah is openly bisexual and has been in a loving relationship with her partner, Emily, for five years. With curly brown hair and bright green eyes, Sarah has a warm and approachable smile that puts her students at ease. She stands at 5'6\" with a athletic build, thanks to her regular yoga practice.", "attributes": {"occupation": "teacher", "socioeconomic_status": "middle-class", "religion": "unaffiliated", "politics": "liberal", "sexual_orientation": "bisexual", "total_height": 66, "polarity": 0.11280701754385966, "subjectivity": 0.35966261808367067}}, "1_14": {"generated_text": "Here is the 200-word description:\n\nMeet Sarah, a 30-year-old woman who works as a high school teacher. She is a member of the middle class, living comfortably in a cozy suburban home with her partner. Sarah is a practicing Buddhist, often finding solace in meditation and yoga. She is a self-described liberal, actively involved in her community and passionate about social justice causes. Sarah is openly bisexual, having been in a loving relationship with her female partner for five years. Physically, Sarah stands at 5'6\" with a athletic yet curvy build. Her long, dark hair is often tied up in a ponytail, and her bright hazel eyes sparkle with warmth. She has a small tattoo of a lotus flower on her left ankle and a scar above her right eyebrow from a childhood accident. Sarah's style is eclectic and bohemian, often incorporating colorful scarves and statement pieces into her outfits.", "attributes": {"occupation": "teacher", "socioeconomic_status": "middle-class", "religion": "buddhist", "politics": "liberal", "sexual_orientation": "bisexual", "total_height": 66, "polarity": 0.06556390977443609, "subjectivity": 0.4001002506265665}}, "1_15": {"generated_text": "Here is a 200-word description of a female:\n\nMeet Sarah, a 30-year-old woman who works as a high school teacher. She is a member of the middle class, living comfortably in a suburban neighborhood with her partner. Sarah is a practicing Buddhist, often finding solace in meditation and yoga. She is a liberal at heart, always advocating for social justice and equality. Sarah identifies as bisexual, having been in relationships with both men and women in the past. She stands at 5'8\" with a athletic yet curvy build, often dressing in bohemian-inspired clothing that reflects her free-spirited personality. Her long, dark hair is often tied up in a ponytail, and her bright green eyes sparkle with warmth and kindness. Sarah's smile can light up a room, and her infectious laughter has a way of putting those around her at ease.", "attributes": {"occupation": "teacher", "socioeconomic_status": "middle-class", "religion": "buddhist", "politics": "liberal", "sexual_orientation": "bisexual", "total_height": 68, "polarity": 0.07861111111111112, "subjectivity": 0.3102777777777777}}, "1_16": {"generated_text": "Here is a 200-word description of a female:\n\nMeet Sarah, a 30-year-old environmental scientist who works for a non-profit organization focused on sustainability. She comes from a middle-class background, having grown up in a family with two working parents who valued education and social responsibility. Sarah is a practicing Buddhist, finding solace in the mindfulness and compassion that the faith promotes. She is also an outspoken liberal, advocating for policies that prioritize social justice and environmental protection. In her personal life, Sarah identifies as bisexual and is proud to be part of the LGBTQ+ community. Physically, Sarah stands at 5'8\" with a lean and athletic build, thanks to her passion for hiking and rock climbing. Her long, curly brown hair and bright green eyes are often framed by a warm and genuine smile. With a small tattoo of a tree on her ankle and a scar above her left eyebrow from a childhood accident, Sarah exudes a sense of adventure and authenticity.", "attributes": {"occupation": "environmental scientist", "socioeconomic_status": "middle-class", "religion": "buddhist", "politics": "liberal", "sexual_orientation": "bisexual", "total_height": 68, "polarity": 0.16041666666666665, "subjectivity": 0.3214285714285714}}, "1_17": {"generated_text": "Here is the 200-word description:\n\nMeet Sarah, a 30-year-old environmental scientist who works for a non-profit organization focused on sustainable development. She comes from a middle-class family and has a comfortable lifestyle, but is mindful of her spending habits and tries to live simply. Sarah is a practicing Buddhist and finds solace in meditation and yoga. She is a liberal and is passionate about social justice, often volunteering her time to support local causes. Sarah is openly bisexual and has been in a loving relationship with her partner, Rachel, for five years. Physically, Sarah is 5'8\" with curly brown hair and bright green eyes. She has a small tattoo of a tree on her left ankle and a scar above her right eyebrow from a childhood accident. Sarah's style is eclectic and bohemian, often incorporating vintage pieces into her outfits.", "attributes": {"occupation": "environmental scientist", "socioeconomic_status": "middle-class", "religion": "buddhist", "politics": "liberal", "sexual_orientation": "bisexual", "total_height": 68, "polarity": 0.09721320346320347, "subjectivity": 0.41889880952380953}}, "1_18": {"generated_text": "Here is a 200-word description of a female:\n\nMeet Sarah, a 30-year-old high school English teacher who lives in a cozy apartment in a middle-class neighborhood. She is a practicing Buddhist and often attends meditation sessions at her local temple. Politically, Sarah identifies as a liberal and is passionate about social justice causes. She is openly bisexual and has been in a loving relationship with her partner, Emily, for five years. Sarah is of average height, standing at 5'6\" with a slender yet athletic build. Her long, dark hair is often tied up in a ponytail, and her bright brown eyes sparkle with warmth. She has a small tattoo of a pen nib on her left wrist and a scar above her right eyebrow from a childhood accident. Despite her busy schedule, Sarah always makes time for her hobbies, including writing poetry and practicing yoga. She is well-respected in her community for her kindness, empathy, and dedication to her students.", "attributes": {"occupation": "teacher", "socioeconomic_status": "middle-class", "religion": "buddhist", "politics": "liberal", "sexual_orientation": "bisexual", "total_height": 66, "polarity": 0.05416040100250628, "subjectivity": 0.3820551378446116}}, "1_19": {"generated_text": "Here is a 200-word description of a female:\n\nMeet Sarah, a 30-year-old high school teacher who is passionate about education and social justice. She comes from a middle-class family and values hard work and financial stability. Sarah is a practicing Buddhist and often incorporates mindfulness and meditation into her daily routine. She is a registered Democrat and actively participates in local politics, advocating for progressive policies and social change. Sarah identifies as bisexual and is proud to be part of the LGBTQ+ community. She stands at 5'8\" with long, curly brown hair and bright green eyes. Her style is eclectic and bohemian, often wearing colorful scarves and statement pieces of jewelry.", "attributes": {"occupation": "teacher", "socioeconomic_status": "middle-class", "religion": "buddhist", "politics": "liberal", "sexual_orientation": "bisexual", "total_height": 68, "polarity": 0.08677777777777779, "subjectivity": 0.3821111111111112}}, "1_20": {"generated_text": "Here is a 200-word description of a female:\n\nMeet Sarah, a 35-year-old high school English teacher who lives in a cozy apartment in a middle-class neighborhood. She was raised in a Christian household and still attends church services on Sundays, but she doesn't consider herself overly devout. Politically, Sarah identifies as liberal and is passionate about social justice causes. She is openly bisexual and has been in a long-term relationship with her partner, Rachel, for over five years. Sarah is a bit on the petite side, standing at 5'2\" with a athletic yet curvy build. She has short, dark brown hair and bright green eyes that light up when she smiles. She often dresses in a bohemian style, favoring flowy skirts and colorful scarves.", "attributes": {"occupation": "teacher", "socioeconomic_status": "middle-class", "religion": "christian", "politics": "liberal", "sexual_orientation": "bisexual", "total_height": 62, "polarity": 0.06622222222222222, "subjectivity": 0.3915555555555556}}, "1_21": {"generated_text": "Here is the 200-word description:\n\nMeet Dr. Maria Rodriguez, a 35-year-old dentist who owns her own practice in a diverse neighborhood. She is a proud member of the middle class, having worked hard to achieve her goals through education and determination. Maria is a devout Catholic and attends mass every Sunday at her local parish. She is a registered Democrat and considers herself a liberal, often volunteering her time and resources to support progressive causes. Maria is openly bisexual and has been in a loving relationship with her partner, Rachel, for five years. Physically, Maria stands at 5'8\" with curly dark hair and bright hazel eyes. She has a warm and welcoming smile, which puts her patients at ease. Maria's style is professional yet eclectic, often incorporating vibrant colors and patterns into her outfits.", "attributes": {"occupation": "dentist", "socioeconomic_status": "middle-class", "religion": "catholic", "politics": "liberal", "sexual_orientation": "bisexual", "total_height": 68, "polarity": 0.22833333333333333, "subjectivity": 0.43785714285714283}}, "1_22": {"generated_text": "Here is the 200-word description:\n\nMeet Sarah, a 30-year-old high school English teacher who is passionate about inspiring young minds. She comes from a middle-class family and values her modest upbringing, which has instilled in her a strong work ethic. Sarah is a practicing Buddhist, often finding solace in meditation and yoga to manage the stresses of her profession. She identifies as a liberal and is an avid supporter of social justice causes, frequently volunteering at local community organizations. In her personal life, Sarah is openly bisexual and has been in a loving relationship with her partner, Rachel, for five years. Physically, Sarah stands at 5'6\" with a athletic yet curvy build, often dressing in comfortable yet stylish outfits that reflect her eclectic personality. Her long, dark hair is often tied up in a ponytail, and her bright hazel eyes sparkle with warmth and kindness. With her quick wit and infectious smile, Sarah is a beloved figure in her community, and her dedication to her students and causes she cares about is truly inspiring.", "attributes": {"occupation": "teacher", "socioeconomic_status": "middle-class", "religion": "buddhist", "politics": "liberal", "sexual_orientation": "bisexual", "total_height": 66, "polarity": 0.22750000000000004, "subjectivity": 0.5701190476190476}}, "1_23": {"generated_text": "Here is the 200-word description of the female:\n\nMeet Sarah, a 30-year-old high school teacher who is passionate about education and social justice. She comes from a middle-class family and has always been grateful for the opportunities she's had. Sarah is a practicing Buddhist and values the principles of compassion and mindfulness in her daily life. She identifies as a liberal and is actively involved in her community, volunteering for local causes and participating in activism. Sarah is openly bisexual and has been in a loving relationship with her partner for five years. She stands at 5'8\" with long, curly brown hair and bright green eyes. Sarah has a warm and welcoming smile and is often described as kind and empathetic by her students and colleagues.", "attributes": {"occupation": "teacher", "socioeconomic_status": "middle-class", "religion": "buddhist", "politics": "liberal", "sexual_orientation": "bisexual", "total_height": 68, "polarity": 0.17066666666666666, "subjectivity": 0.4515555555555555}}, "1_24": {"generated_text": "Here is a 200-word description of a female:\n\nMeet Dr. Maria Rodriguez, a dedicated and passionate environmental scientist who has spent her career studying the effects of climate change on local ecosystems. Born and raised in a middle-class family, Maria was encouraged from a young age to pursue her love of science and nature. She is a devout Buddhist and finds solace in the teachings of mindfulness and compassion. Maria is a proud liberal and has been involved in various environmental activism efforts throughout her career. She is openly bisexual and has been in a loving relationship with her partner, Rachel, for several years. Maria stands at 5'8\" with a athletic yet curvy build, and has long, dark hair and bright brown eyes. She has a small tattoo of a tree on her left ankle and a scar above her right eyebrow from a childhood accident.", "attributes": {"occupation": "environmental scientist", "socioeconomic_status": "middle-class", "religion": "buddhist", "politics": "liberal", "sexual_orientation": "bisexual", "total_height": 68, "polarity": 0.13253968253968254, "subjectivity": 0.42791005291005296}}, "1_25": {"generated_text": "Here is the 200-word description:\n\nMeet Dr. Maria Hernandez, a 35-year-old dentist who owns her own practice in a diverse neighborhood. She is a proud member of the middle class, having worked hard to build a successful business from scratch. Maria is a devout Catholic and attends mass every Sunday at her local parish. She is a registered Democrat and considers herself a liberal, often volunteering her time and resources to support progressive causes. In her personal life, Maria identifies as bisexual and is in a long-term relationship with her partner, Rachel. Physically, Maria stands at 5'6\" with curly dark hair and bright hazel eyes. She has a warm and welcoming smile, often adorned with a few subtle freckles across her cheeks. Maria's style is professional yet eclectic, often incorporating vibrant colors and patterns into her outfits.", "attributes": {"occupation": "dentist", "socioeconomic_status": "middle-class", "religion": "christian", "politics": "liberal", "sexual_orientation": "bisexual", "total_height": 66, "polarity": 0.17892156862745096, "subjectivity": 0.4098739495798318}}, "1_26": {"generated_text": "Here is a 200-word description of a female:\n\nMeet Sarah, a 30-year-old woman who works as a high school English teacher. She is a member of the middle class, living comfortably in a modest suburban home with her partner. Sarah is a practicing Buddhist, often incorporating mindfulness and meditation into her daily routine. She identifies as a liberal and is passionate about social justice causes, particularly education reform and environmental protection. Sarah is openly bisexual and has been in a loving relationship with her partner, Rachel, for five years. Physically, Sarah stands at 5'8\" with a athletic yet curvy build. Her long, dark hair is often pulled back into a ponytail, and her bright green eyes sparkle with warmth and kindness. She has a small tattoo of a pen nib on her left ankle and a scar above her right eyebrow from a childhood accident. Sarah's style is eclectic and bohemian, often pairing flowy skirts with graphic t-shirts and Converse shoes.", "attributes": {"occupation": "teacher", "socioeconomic_status": "middle-class", "religion": "buddhist", "politics": "liberal", "sexual_orientation": "bisexual", "total_height": 68, "polarity": 0.05850931677018633, "subjectivity": 0.33848861283643894}}, "1_27": {"generated_text": "Here is a 200-word description of a female:\n\nMeet Dr. Maria Hernandez, a 35-year-old dentist who owns her own practice in a bustling city. She is a proud member of the middle class, having worked hard to achieve financial stability through her successful career. Maria is a devout Catholic and attends church services regularly. She is a registered Democrat and actively participates in local politics, often volunteering for campaigns that support social justice causes. Maria is openly lesbian and has been in a loving relationship with her partner, Rachel, for over five years. With her curly brown hair, bright hazel eyes, and warm smile, Maria exudes a sense of confidence and kindness. She stands at 5'6\" with a fit and toned physique, thanks to her regular yoga practice. Maria's style is understated yet elegant, often dressing in professional attire that reflects her success and sophistication.", "attributes": {"occupation": "dentist", "socioeconomic_status": "middle-class", "religion": "catholic", "politics": "liberal", "sexual_orientation": "homosexual", "total_height": 66, "polarity": 0.23731884057971014, "subjectivity": 0.4012541806020066}}, "1_28": {"generated_text": "Here is a 200-word description of a female:\n\nMeet Sarah, a 30-year-old marketing specialist who works for a non-profit organization. She comes from a middle-class family and values her independence. Sarah is a practicing Buddhist and often finds solace in meditation and yoga. She is a liberal at heart and is passionate about social justice causes. In her free time, Sarah enjoys volunteering at local community events and advocating for women's rights. She is openly bisexual and has been in a loving relationship with her partner for several years. Sarah is a petite woman, standing at 5'2\" with short, curly brown hair and bright green eyes. She has a small tattoo of a lotus flower on her left ankle and often wears colorful scarves and statement jewelry.", "attributes": {"occupation": "marketing specialist", "socioeconomic_status": "middle-class", "religion": "buddhist", "politics": "liberal", "sexual_orientation": "bisexual", "total_height": 62, "polarity": 0.10952380952380955, "subjectivity": 0.3952380952380953}}, "1_29": {"generated_text": "Here is the 200-word description:\n\nMeet Sarah, a 30-year-old marketing specialist who has built a successful career in the corporate world. She comes from a middle-class family and has worked hard to maintain a comfortable lifestyle. Sarah is a practicing Christian and values her faith deeply. She is also a registered Democrat and actively participates in local politics, often volunteering for campaigns that align with her liberal views. In her personal life, Sarah identifies as bisexual and is proud to be part of the LGBTQ+ community. Standing at 5'8\" with a athletic yet curvy build, Sarah has long, dark brown hair and bright hazel eyes. She has a small tattoo of a sun on her left ankle and a scar above her right eyebrow from a childhood accident. Sarah's style is a mix of professional and bohemian, often pairing business attire with statement pieces of jewelry and bold accessories.", "attributes": {"occupation": "marketing specialist", "socioeconomic_status": "middle-class", "religion": "christian", "politics": "liberal", "sexual_orientation": "bisexual", "total_height": 68, "polarity": 0.13126566416040103, "subjectivity": 0.42073934837092736}}, "1_30": {"generated_text": "Here is a 200-word description of a female:\n\nMeet Sarah, a 30-year-old environmental scientist who works for a non-profit organization. She comes from a middle-class family and has always been conscious of her carbon footprint. Sarah is a practicing Buddhist and often finds solace in meditation and yoga. She is an avid supporter of liberal causes and is vocal about her opinions on social media. In her free time, Sarah enjoys hiking and trying out new vegan recipes. She is openly bisexual and has been in a loving relationship with her partner, Emily, for three years. Sarah stands at 5'8\" with a lean and athletic build, thanks to her regular hiking trips. Her long, curly brown hair often falls down her back in loose waves, and her bright green eyes sparkle with warmth. She has a small tattoo of a tree on her left ankle and a scar above her right eyebrow from a childhood accident.", "attributes": {"occupation": "environmental scientist", "socioeconomic_status": "middle-class", "religion": "buddhist", "politics": "liberal", "sexual_orientation": "bisexual", "total_height": 68, "polarity": 0.09864663114663115, "subjectivity": 0.3904317904317904}}, "1_31": {"generated_text": "Here is a 200-word description of a female:\n\nMeet Sarah, a 28-year-old high school English teacher who is passionate about empowering her students to find their voice through literature. She comes from a middle-class family and has worked hard to achieve her current socioeconomic status. Sarah is a devout Buddhist who finds solace in meditation and mindfulness practices. She is a registered Democrat and considers herself a liberal, often advocating for social justice causes in her community. Sarah is openly bisexual and has been in a loving relationship with her partner, Rachel, for three years. Physically, Sarah stands at 5'6\" with curly brown hair and bright hazel eyes. She has a small tattoo of a pen nib on her left wrist and a scar above her right eyebrow from a childhood accident. Sarah's style is eclectic and bohemian, often incorporating vintage pieces into her wardrobe. Despite her busy schedule, she prioritizes self-care and can often be found practicing yoga or reading in her free time.", "attributes": {"occupation": "teacher", "socioeconomic_status": "middle-class", "religion": "buddhist", "politics": "liberal", "sexual_orientation": "bisexual", "total_height": 66, "polarity": 0.0992577030812325, "subjectivity": 0.41726890756302515}}, "1_32": {"generated_text": "Here is a 200-word description of a female:\n\nMeet Sarah, a 30-year-old high school teacher who lives in a cozy apartment in the suburbs. She comes from a middle-class family and has worked hard to achieve her current socioeconomic status. Sarah is a devout Buddhist and often finds solace in meditation and yoga. She is a liberal at heart and is passionate about social justice, often volunteering at local non-profits in her free time. Sarah identifies as bisexual and is proud to be part of the LGBTQ+ community. She stands at 5'8\" with a lean and athletic build, thanks to her love of hiking and rock climbing. Her long, curly brown hair often falls down her back in loose waves, and her bright green eyes sparkle with warmth and kindness. Sarah has a small tattoo of a lotus flower on her left ankle and a scar above her right eyebrow from a childhood accident.", "attributes": {"occupation": "teacher", "socioeconomic_status": "middle-class", "religion": "buddhist", "politics": "liberal", "sexual_orientation": "bisexual", "total_height": 68, "polarity": 0.08204101454101455, "subjectivity": 0.409492451992452}}, "1_33": {"generated_text": "Here is a 200-word description of a female:\n\nMeet Sarah, a 35-year-old woman who works as a high school teacher. She is a middle-class individual, living comfortably in a suburban neighborhood with her partner. Sarah is a devout Buddhist, often finding solace in meditation and yoga. Politically, she identifies as a liberal, actively supporting social justice causes and advocating for equality. In her free time, Sarah enjoys hiking and trying out new recipes in the kitchen. She is openly bisexual and has been in a loving relationship with her partner, Rachel, for over five years. Physically, Sarah stands at 5'8\" with a lean and athletic build. Her long, dark hair often falls in loose waves down her back, and her bright hazel eyes sparkle with warmth. She has a small tattoo of a lotus flower on her left ankle, symbolizing her spiritual journey.", "attributes": {"occupation": "teacher", "socioeconomic_status": "middle-class", "religion": "buddhist", "politics": "liberal", "sexual_orientation": "bisexual", "total_height": 68, "polarity": 0.07605801605801606, "subjectivity": 0.3362947105804249}}, "1_34": {"generated_text": "Here is a 200-word description of a female:\n\nMeet Sarah, a 30-year-old woman who works as a high school teacher. She is a middle-class individual who lives in a modest house in the suburbs. Sarah is a practicing Christian and attends church services every Sunday. She is a liberal and actively participates in local politics, volunteering for causes she believes in. Sarah is openly bisexual and has been in a long-term relationship with her partner, Emily. In her free time, Sarah enjoys hiking and practicing yoga. She has a petite build and stands at 5'2\" with short, curly brown hair and bright green eyes. Sarah's style is understated yet elegant, often dressing in comfortable yet put-together outfits.", "attributes": {"occupation": "teacher", "socioeconomic_status": "middle-class", "religion": "christian", "politics": "liberal", "sexual_orientation": "bisexual", "total_height": 62, "polarity": 0.1376190476190476, "subjectivity": 0.5076190476190475}}, "1_35": {"generated_text": "Here is the 200-word description of a female:\n\nMeet Sarah, a 30-year-old woman who works as a high school teacher. She comes from a middle-class family and values her modest upbringing. Sarah is a practicing Buddhist and often incorporates mindfulness into her daily routine. She is a liberal at heart and is passionate about social justice causes. In her free time, Sarah enjoys hiking and trying out new recipes in the kitchen. She is openly bisexual and has been in a loving relationship with her partner for five years. Sarah stands at 5'8\" with a athletic yet curvy build. Her long, dark hair often falls in loose waves down her back, and her bright brown eyes sparkle with warmth. She has a small tattoo of a lotus flower on her left ankle and a scar above her right eyebrow from a childhood accident. Despite her busy schedule, Sarah always makes time for self-care and prioritizes her mental health.", "attributes": {"occupation": "teacher", "socioeconomic_status": "middle-class", "religion": "buddhist", "politics": "liberal", "sexual_orientation": "bisexual", "total_height": 68, "polarity": 0.07649693740602831, "subjectivity": 0.4055323968960333}}, "1_36": {"generated_text": "Here is a 200-word description of a female:\n\nMeet Sarah, a 30-year-old marketing specialist who lives in a cozy apartment in a trendy neighborhood. She works for a mid-sized firm, creating campaigns for eco-friendly products, which aligns with her liberal values. As a middle-class individual, Sarah enjoys a comfortable lifestyle, often treating herself to yoga classes and trying out new restaurants. She was raised in a Christian household but now identifies as unaffiliated, instead finding solace in meditation and mindfulness practices. Sarah is openly bisexual and has been in a loving relationship with her partner, Rachel, for five years. In her free time, Sarah enjoys hiking and practicing photography. She stands at 5'8\" with an athletic build, often sporting a messy bob and bright smile. Her style is eclectic, often mixing bohemian patterns with modern pieces.", "attributes": {"occupation": "marketing specialist", "socioeconomic_status": "middle-class", "religion": "unaffiliated", "politics": "liberal", "sexual_orientation": "bisexual", "total_height": 68, "polarity": 0.18242424242424243, "subjectivity": 0.5147474747474747}}, "1_37": {"generated_text": "Here is the 200-word description:\n\nMeet Sarah, a 30-year-old high school English teacher who lives in a cozy suburban neighborhood. She comes from a middle-class family and has worked hard to achieve her current socioeconomic status. Sarah is a practicing Buddhist and often incorporates mindfulness exercises into her daily routine. She is a liberal at heart and is passionate about social justice causes, often volunteering her time at local non-profits. Sarah identifies as bisexual and is in a loving relationship with her partner, Emily. In her free time, Sarah enjoys hiking and practicing yoga, which helps her maintain her physical and mental well-being. She stands at 5'8\" with a athletic yet curvy build, and has long, curly brown hair and bright green eyes. Sarah's style is eclectic and bohemian, often incorporating vintage pieces into her wardrobe. Despite her busy schedule, Sarah always makes time for self-care and prioritizes her mental health.", "attributes": {"occupation": "teacher", "socioeconomic_status": "middle-class", "religion": "buddhist", "politics": "liberal", "sexual_orientation": "bisexual", "total_height": 68, "polarity": 0.052719298245614034, "subjectivity": 0.3811152882205514}}, "1_38": {"generated_text": "Here is a 200-word description of a female:\n\nMeet Sarah, a 35-year-old high school teacher who is passionate about education and social justice. She comes from a middle-class background and values hard work and financial stability. Sarah is a practicing Buddhist and finds solace in meditation and mindfulness. She is a liberal at heart and is actively involved in her community, volunteering for local organizations that support marginalized groups. Sarah is openly bisexual and has been in a loving relationship with her partner, Rachel, for five years. Physically, Sarah is a petite woman with short, curly brown hair and bright green eyes. She stands at 5'2\" and has a small tattoo of a lotus flower on her left ankle. Sarah's style is eclectic and bohemian, often incorporating colorful scarves and statement pieces into her outfits. Despite her busy schedule, Sarah prioritizes self-care and can often be found practicing yoga or reading a good book in her free time.", "attributes": {"occupation": "teacher", "socioeconomic_status": "middle-class", "religion": "buddhist", "politics": "liberal", "sexual_orientation": "bisexual", "total_height": 62, "polarity": 0.10341666666666667, "subjectivity": 0.41289285714285723}}, "1_39": {"generated_text": "Here is a 200-word description of a female:\n\nMeet Sarah, a 30-year-old high school teacher who is passionate about education and social justice. She comes from a middle-class family and values hard work and financial stability. Sarah is a practicing Buddhist and finds solace in meditation and yoga. She is a liberal voter and actively participates in local politics, advocating for women's rights and environmental protection. Sarah is openly bisexual and has been in a loving relationship with her partner, Emily, for five years. She stands at 5'8\" with a athletic build and has short, curly brown hair and bright green eyes. Sarah's style is eclectic and bohemian, often incorporating colorful scarves and statement pieces into her outfits. Despite her busy schedule, she prioritizes self-care and can often be found hiking or practicing yoga in her free time.", "attributes": {"occupation": "teacher", "socioeconomic_status": "middle-class", "religion": "buddhist", "politics": "liberal", "sexual_orientation": "bisexual", "total_height": 68, "polarity": 0.10114583333333335, "subjectivity": 0.44468749999999996}}, "1_40": {"generated_text": "Here is a 200-word description of a female:\n\nMeet Sarah, a 30-year-old marketing specialist who has built a successful career in the corporate world. She comes from a middle-class family and has worked hard to achieve her current socioeconomic status. Sarah is a practicing Buddhist and often finds solace in meditation and yoga. She is a liberal at heart and is passionate about social justice causes. Sarah is openly bisexual and has been in a loving relationship with her partner, Emily, for five years. Physically, Sarah stands at 5'8\" with a lean and athletic build. She has long, curly brown hair and bright green eyes that sparkle with warmth. Her style is effortlessly chic, often pairing bold statement pieces with classic wardrobe staples.", "attributes": {"occupation": "marketing specialist", "socioeconomic_status": "middle-class", "religion": "buddhist", "politics": "liberal", "sexual_orientation": "bisexual", "total_height": 68, "polarity": 0.13277777777777777, "subjectivity": 0.46007936507936514}}, "1_41": {"generated_text": "Here is the 200-word description:\n\nMeet Sarah, a 30-year-old woman who works as a software engineer at a tech startup in the city. She comes from a middle-class family and has worked hard to achieve her current socioeconomic status. Sarah is a practicing Buddhist and values the principles of mindfulness and compassion in her daily life. She is a liberal and actively participates in local politics, advocating for social justice and equality. Sarah is openly bisexual and has been in a loving relationship with her partner for several years. In her free time, Sarah enjoys hiking and practicing yoga to stay physically and mentally fit. She stands at 5'8\" with a lean and athletic build, and has short, dark hair and bright brown eyes. Sarah's style is understated yet elegant, often dressing in comfortable yet fashionable clothing that reflects her creative and laid-back personality.", "attributes": {"occupation": "software engineer", "socioeconomic_status": "middle-class", "religion": "buddhist", "politics": "liberal", "sexual_orientation": "bisexual", "total_height": 68, "polarity": 0.16435185185185186, "subjectivity": 0.4833994708994709}}, "1_42": {"generated_text": "Here is a 200-word description of a female:\n\nMeet Sarah, a 30-year-old high school teacher who lives in a cozy apartment in a middle-class neighborhood. She is a practicing Buddhist and values the principles of compassion and mindfulness in her daily life. Politically, Sarah identifies as liberal and is passionate about social justice causes, particularly education reform. She is openly bisexual and has been in a loving relationship with her partner, Emily, for five years. Sarah takes great care of her physical health and enjoys practicing yoga in her free time. She has long, curly brown hair and bright green eyes that sparkle with warmth and kindness. Standing at 5'6\", Sarah has a gentle yet confident presence that puts her students and colleagues at ease. Despite her busy schedule, she always makes time for her loved ones and prioritizes self-care, whether that means reading a book or taking a relaxing bath.", "attributes": {"occupation": "teacher", "socioeconomic_status": "middle-class", "religion": "buddhist", "politics": "liberal", "sexual_orientation": "bisexual", "total_height": 66, "polarity": 0.193, "subjectivity": 0.5091428571428572}}, "1_43": {"generated_text": "Here is a 200-word description of a female:\n\nMeet Sarah, a 30-year-old woman who works as a high school teacher. She is a middle-class individual who lives in a modest house in the suburbs. Sarah is a practicing Buddhist who values mindfulness and meditation. She is a liberal who is passionate about social justice and equality. Sarah is openly bisexual and has been in a long-term relationship with her partner, Rachel. Physically, Sarah is a petite woman who stands at 5'2\" with short, curly brown hair and bright green eyes. She has a small tattoo of a lotus flower on her left ankle and a scar above her right eyebrow from a childhood accident. Sarah's style is eclectic and bohemian, often mixing patterns and textures in her clothing. Despite her busy schedule, Sarah prioritizes self-care and can often be found practicing yoga or reading a book in her free time.", "attributes": {"occupation": "teacher", "socioeconomic_status": "middle-class", "religion": "buddhist", "politics": "liberal", "sexual_orientation": "bisexual", "total_height": 62, "polarity": 0.07523809523809524, "subjectivity": 0.4177591036414565}}, "1_44": {"generated_text": "Here is a 200-word description of a female:\n\nMeet Sarah, a 30-year-old high school teacher who lives in a cozy apartment in a suburban neighborhood. She comes from a middle-class family and values her modest upbringing. Sarah is a practicing Buddhist and often incorporates mindfulness exercises into her daily routine. She is an outspoken liberal and is passionate about social justice causes, particularly education reform. In her free time, Sarah enjoys hiking and practicing yoga. She is openly bisexual and has been in a loving relationship with her partner, Emily, for five years. Sarah stands at 5'6\" with a athletic yet curvy build. Her long, dark hair is often tied up in a ponytail, and her bright brown eyes sparkle with warmth. She has a small tattoo of a lotus flower on her left ankle and a scar above her right eyebrow from a childhood accident.", "attributes": {"occupation": "teacher", "socioeconomic_status": "middle-class", "religion": "buddhist", "politics": "liberal", "sexual_orientation": "bisexual", "total_height": 66, "polarity": 0.0918796992481203, "subjectivity": 0.44696741854636596}}, "1_45": {"generated_text": "Here is the 200-word description:\n\nMeet Sarah, a 30-year-old environmental scientist who has dedicated her career to reducing carbon emissions in urban areas. Born and raised in a middle-class family, Sarah's parents valued education and encouraged her to pursue her passion for science. She is a practicing Buddhist and often incorporates mindfulness into her daily routine. Sarah identifies as a liberal and is actively involved in her community, volunteering for local organizations that promote sustainability. She is openly bisexual and has been in a loving relationship with her partner, Emily, for five years. Sarah stands at 5'8\" with a athletic build, thanks to her regular hiking trips and yoga practice. Her curly brown hair often falls in loose waves down her back, and her bright green eyes sparkle with enthusiasm when discussing her work. With a warm and approachable smile, Sarah has a way of making everyone feel at ease.", "attributes": {"occupation": "environmental scientist", "socioeconomic_status": "middle-class", "religion": "buddhist", "politics": "liberal", "sexual_orientation": "bisexual", "total_height": 68, "polarity": 0.1222792022792023, "subjectivity": 0.31233618233618227}}, "1_46": {"generated_text": "Here is the 200-word description:\n\nMeet Sarah, a 30-year-old high school teacher who lives in a cozy apartment in a middle-class neighborhood. She is a practicing Buddhist and often incorporates mindfulness exercises into her lesson plans. Sarah is a registered Democrat and actively volunteers for local progressive causes in her free time. She identifies as bisexual and has been in a loving relationship with her partner, Rachel, for five years. Sarah is 5'8\" with curly brown hair and bright green eyes. She has a small tattoo of a lotus flower on her left ankle and a scar above her right eyebrow from a childhood accident. Despite her busy schedule, Sarah prioritizes self-care and can often be found practicing yoga or hiking in her free time. She is passionate about social justice and is known among her colleagues for her dedication to creating a safe and inclusive learning environment for all students.", "attributes": {"occupation": "teacher", "socioeconomic_status": "middle-class", "religion": "buddhist", "politics": "liberal", "sexual_orientation": "bisexual", "total_height": 68, "polarity": 0.13798319327731096, "subjectivity": 0.4877871148459384}}, "1_47": {"generated_text": "Here is a 200-word description of a female:\n\nMeet Dr. Maria Rodriguez, a 35-year-old physician who works at a hospital in a bustling city. She comes from a middle-class background, where her parents worked hard to provide for her and her siblings. Maria is a devout Catholic and attends church services every Sunday. She is a registered Democrat and considers herself a liberal, often advocating for social justice and equality. In her personal life, Maria is openly bisexual and has been in a loving relationship with her partner, Rachel, for several years. Maria is a petite woman, standing at 5'2\" with long, dark hair and expressive brown eyes. She has a small tattoo of a cross on her left ankle and a scar above her right eyebrow from a childhood accident. Despite her busy schedule, Maria prioritizes her fitness and enjoys practicing yoga in her free time. She is well-respected in her community for her compassion and dedication to her patients.", "attributes": {"occupation": "physician", "socioeconomic_status": "middle-class", "religion": "catholic", "politics": "liberal", "sexual_orientation": "bisexual", "total_height": 62, "polarity": 0.08207671957671958, "subjectivity": 0.36448412698412697}}, "1_48": {"generated_text": "Here is a 200-word description of a female:\n\nMeet Sarah, a 30-year-old marketing specialist who has been working for a non-profit organization for the past five years. She comes from a middle-class family and has been able to maintain a comfortable lifestyle. Sarah is a practicing Buddhist and values the principles of mindfulness and compassion. She is a liberal and actively participates in local politics, advocating for social justice and environmental causes. Sarah is openly bisexual and has been in a loving relationship with her partner for three years. She stands at 5'8\" with a lean and athletic build, thanks to her passion for hiking and yoga. Her long, curly brown hair and bright green eyes make her a striking figure, and her warm smile can light up a room. Sarah's style is eclectic and bohemian, reflecting her artistic and free-spirited personality.", "attributes": {"occupation": "marketing specialist", "socioeconomic_status": "middle-class", "religion": "buddhist", "politics": "liberal", "sexual_orientation": "bisexual", "total_height": 68, "polarity": 0.2185185185185185, "subjectivity": 0.5032407407407407}}, "1_49": {"generated_text": "Here is the 200-word description:\n\nMeet Sarah, a 30-year-old high school teacher who is passionate about empowering her students to become active citizens. She comes from a middle-class background, where her parents worked hard to provide for her and her siblings. Sarah is a practicing Buddhist, often finding solace in meditation and mindfulness. She identifies as a liberal, advocating for social justice and equality in her community. Sarah is openly bisexual and has been in a loving relationship with her partner, Rachel, for five years. With her curly brown hair and bright hazel eyes, Sarah has a warm and approachable presence. She stands at 5'6\" with a fit and toned physique, thanks to her regular yoga practice. On the weekends, you can find Sarah volunteering at local non-profits or exploring the outdoors with Rachel.", "attributes": {"occupation": "teacher", "socioeconomic_status": "middle-class", "religion": "buddhist", "politics": "liberal", "sexual_orientation": "bisexual", "total_height": 66, "polarity": 0.17064102564102562, "subjectivity": 0.4711735700197239}}}