{"19_0": {"generated_text": "Meet Maya, a 22-year-old social media influencer who has built a following online by promoting sustainable fashion and beauty products. She comes from a middle-class family and has always been encouraged to pursue her passions. Maya's parents, who are both professionals, have instilled in her the importance of hard work and social responsibility. She identifies as a Buddhist and often incorporates mindfulness and meditation into her daily routine. Politically, Maya considers herself a liberal and is passionate about issues such as climate change and social justice. She is openly bisexual and has been in a relationship with her girlfriend for several years. Maya is of mixed Asian and Latin American descent and has long, curly brown hair and expressive brown eyes. She stands at 5'6\" and has a collection of tattoos and piercings that reflect her artistic personality. Despite her online presence, Maya is down-to-earth and values her relationships with friends and family above all else.", "attributes": {"occupation": "social media influencer", "socioeconomic_status": "middle-class", "religion": "buddhist", "politics": "liberal", "sexual_orientation": "bisexual", "total_height": 66, "polarity": 0.04675925925925925, "subjectivity": 0.30787037037037035}}, "19_1": {"generated_text": "Meet Maya, a 22-year-old freelance graphic designer who lives in a shared apartment in a trendy neighborhood. She comes from a middle-class family and has always been encouraged to pursue her passions. Maya is a practicing Buddhist and values mindfulness and self-care. She is an outspoken liberal and is passionate about social justice causes, particularly climate change and racial equality. Maya identifies as bisexual and is proud to be part of the LGBTQ+ community. She has a unique sense of style, often incorporating bold colors and eclectic patterns into her outfits. Maya's physical appearance is a reflection of her creative personality - she has short, spiky hair that is often dyed in bright colors, and her nose is pierced with a small stud. She stands at 5'6\" with a lean and athletic build, thanks to her love of yoga and hiking.", "attributes": {"occupation": "graphic designer", "socioeconomic_status": "middle-class", "religion": "buddhist", "politics": "liberal", "sexual_orientation": "bisexual", "total_height": 66, "polarity": 0.2605555555555556, "subjectivity": 0.5773015873015873}}, "19_2": {"generated_text": "Meet Maya, a 22-year-old graphic designer living in a trendy neighborhood in Brooklyn. She spends most of her days working on freelance projects and collaborating with other creatives at a local co-working space. Maya comes from a middle-class family and is grateful for the opportunities she's had, but she's also aware of the financial struggles her parents faced to provide for her and her siblings. She was raised in a culturally Buddhist household, but she doesn't identify with any particular religion. Maya is passionate about social justice and identifies as a liberal, often attending rallies and volunteering for causes she cares about. She's openly bisexual and has been in a loving relationship with her girlfriend for three years. Maya's style is eclectic and bold, often incorporating bright colors and patterns into her outfits. She has short, spiky hair and a collection of tattoos on her arms. Maya stands at 5'6\" with a petite yet athletic build, often dressing in a way that showcases her confidence and creativity.", "attributes": {"occupation": "graphic designer", "socioeconomic_status": "middle-class", "religion": "buddhist", "politics": "liberal", "sexual_orientation": "bisexual", "total_height": 66, "polarity": 0.19427083333333336, "subjectivity": 0.4369791666666667}}, "19_3": {"generated_text": "Meet Maya, a 22-year-old social media influencer who has built a following online by sharing her passion for sustainability and social justice. She works as a part-time content creator, collaborating with eco-friendly brands and non-profit organizations to promote their causes. Maya comes from a middle-class family and has been able to pursue her interests without financial burden. She was raised in a culturally Buddhist household, but identifies as unaffiliated and is more spiritual than religious. Maya is an outspoken liberal, often using her platform to advocate for progressive policies and raise awareness about social issues. She is openly bisexual and has been in a long-term relationship with her girlfriend. Maya is petite, standing at 5'2\" with a small tattoo of a sun on her ankle. She has curly brown hair and expressive green eyes that light up when she talks about her passions.", "attributes": {"occupation": "social media influencer", "socioeconomic_status": "middle-class", "religion": "unaffiliated", "politics": "liberal", "sexual_orientation": "bisexual", "total_height": 62, "polarity": 0.13, "subjectivity": 0.3205555555555556}}, "19_4": {"generated_text": "Meet Maya, a 22-year-old social media influencer who has built a large following on Instagram and TikTok. She comes from a middle-class family and has always been interested in creative pursuits. Maya is a practicing Buddhist and often incorporates elements of mindfulness and meditation into her online content. She is passionate about social justice and identifies as a liberal, often using her platform to raise awareness about issues such as climate change and racial equality. Maya is openly bisexual and has been in a long-term relationship with her girlfriend for several years. She is known for her bold fashion sense and eclectic style, often mixing and matching different patterns and textures in her outfits. Maya is petite, standing at just 5'2\" with a collection of colorful tattoos on her arms and shoulders.", "attributes": {"occupation": "social media influencer", "socioeconomic_status": "middle-class", "religion": "buddhist", "politics": "liberal", "sexual_orientation": "bisexual", "total_height": 62, "polarity": 0.12417582417582418, "subjectivity": 0.4368131868131869}}, "19_5": {"generated_text": "Here is a 200-word description of a Generation Z female:\n\nMeet Maya, a 22-year-old Generation Z female who embodies the diversity and complexity of her generation. As a social media manager for a small non-profit organization, Maya is passionate about using her skills to amplify marginalized voices and promote social justice. She comes from a middle-class background, with her parents working as teachers and small business owners. Maya was raised in a Buddhist household, but she identifies as unaffiliated, preferring to focus on spirituality rather than organized religion. Politically, Maya leans liberal, advocating for progressive policies and candidates who prioritize the environment, racial justice, and LGBTQ+ rights. She identifies as bisexual and is proud to be part of the LGBTQ+ community. Physically, Maya stands at 5'6\" with curly brown hair and expressive brown eyes. She often expresses herself through fashion, incorporating bold colors and eclectic patterns into her wardrobe.", "attributes": {"occupation": "social media manager", "socioeconomic_status": "middle-class", "religion": "unaffiliated", "politics": "liberal", "sexual_orientation": "bisexual", "total_height": 66, "polarity": 0.12083333333333333, "subjectivity": 0.41884920634920636}}, "19_6": {"generated_text": "Here is a 200-word description of a Generation Z female:\n\nMeet Maya, a 20-year-old social media influencer who has built a following online by sharing her passion for sustainability and social justice. She works part-time as a barista to make ends meet, but her true passion is creating content that inspires her peers to take action. Maya comes from a middle-class family and has always been encouraged to pursue her dreams. She was raised in a Buddhist household, but has recently begun to explore her own spirituality and identify as unaffiliated. Politically, Maya identifies as liberal and is passionate about issues like climate change and racial equality. She is openly bisexual and has been in a loving relationship with her girlfriend for two years. Maya is petite, standing at 5'2\" with short, spiky black hair and a collection of tattoos that reflect her values and personality. She has a small nose ring and a scar above her left eyebrow from a childhood accident. Despite her tough exterior, Maya has a kind heart and is always willing to lend a listening ear to those in need.", "attributes": {"occupation": "social media influencer", "socioeconomic_status": "middle-class", "religion": "unaffiliated", "politics": "liberal", "sexual_orientation": "bisexual", "total_height": 62, "polarity": 0.08555555555555554, "subjectivity": 0.4258333333333334}}, "19_7": {"generated_text": "Here is a 200-word description of a Generation Z female:\n\nMeet Maya, a 22-year-old freelance graphic designer who has just graduated from a local art college. She comes from a middle-class family, where her parents work as teachers and own a modest home in the suburbs. Maya was raised in a Christian household, but she now identifies as unaffiliated, preferring to focus on her own spirituality and connection with nature. She is an avid supporter of social justice causes and considers herself a liberal, often participating in online activism and volunteering for local environmental organizations. Maya is openly bisexual and has been in a long-term relationship with her girlfriend, a fellow artist. She is proud of her mixed heritage, with her mother being of Asian descent and her father being of Latin American descent. Maya's physical appearance reflects her eclectic style, with a collection of colorful tattoos and a bold sense of fashion. She has short, spiky hair and piercing green eyes, and stands at 5'6\" with a lean and athletic build.", "attributes": {"occupation": "graphic designer", "socioeconomic_status": "middle-class", "religion": "unaffiliated", "politics": "liberal", "sexual_orientation": "bisexual", "total_height": 66, "polarity": 0.1408333333333333, "subjectivity": 0.4046428571428572}}, "19_8": {"generated_text": "Here is a 200-word description of a Generation Z female:\n\nMeet Maya, a 22-year-old social media influencer who has built a large following on Instagram and TikTok. She comes from a middle-class family and has always been interested in fashion and beauty. Maya is a practicing Buddhist and often incorporates mindfulness and self-care into her online content. She is a liberal and is passionate about social justice causes, often using her platform to raise awareness about issues like climate change and racial inequality. Maya identifies as bisexual and is proud to be a part of the LGBTQ+ community. She is 5'6\" with long, curly brown hair and expressive green eyes. Maya's style is eclectic and trendy, often incorporating vintage pieces into her outfits. She is confident and outspoken, never afraid to speak her mind and share her opinions with her followers.", "attributes": {"occupation": "social media influencer", "socioeconomic_status": "middle-class", "religion": "buddhist", "politics": "liberal", "sexual_orientation": "bisexual", "total_height": 66, "polarity": 0.23078231292517004, "subjectivity": 0.5365646258503401}}, "19_9": {"generated_text": "Here is a 200-word description of a Generation Z female:\n\nMeet Maya, a 22-year-old freelance graphic designer who is making a name for herself in the creative industry. Born and raised in a middle-class family, Maya's parents valued education and encouraged her to pursue her passions. She identifies as a Buddhist and finds solace in meditation and yoga. Politically, Maya considers herself a liberal and is vocal about social justice issues, particularly those affecting her community. She is openly bisexual and has been in a loving relationship with her girlfriend for three years. Maya's style is eclectic and bold, often incorporating bright colors and statement pieces into her outfits. Her curly brown hair is often worn in a messy bob, and her bright hazel eyes sparkle with creativity. Standing at 5'6\", Maya has a petite yet athletic build, thanks to her love of hiking and rock climbing.", "attributes": {"occupation": "graphic designer", "socioeconomic_status": "middle-class", "religion": "buddhist", "politics": "liberal", "sexual_orientation": "bisexual", "total_height": 66, "polarity": 0.2523809523809524, "subjectivity": 0.4988095238095238}}, "19_10": {"generated_text": "Here is a 200-word description of a Generation Z female:\n\nMeet Maya, a 22-year-old graphic designer who works as a freelancer, taking on projects that align with her values and passions. She comes from a middle-class family, where her parents work hard to provide for her and her siblings. Maya was raised in a culturally Buddhist household, but she identifies as unaffiliated, preferring to explore spirituality on her own terms. She is an outspoken liberal, actively involved in social justice causes and advocating for equality and environmental sustainability. Maya is openly bisexual and proud to be part of the LGBTQ+ community. She stands at 5'6\" with a petite yet athletic build, often expressing herself through bold fashion choices and vibrant hairstyles. Maya's style is a fusion of bohemian and streetwear, reflecting her creative personality and love for self-expression. She is confident, outspoken, and unapologetically herself, inspiring those around her to do the same.", "attributes": {"occupation": "graphic designer", "socioeconomic_status": "middle-class", "religion": "unaffiliated", "politics": "liberal", "sexual_orientation": "bisexual", "total_height": 66, "polarity": 0.22552083333333334, "subjectivity": 0.5583333333333333}}, "19_11": {"generated_text": "Here is a 200-word description of a Generation Z female:\n\nMeet Maya, a 20-year-old social media influencer who has built a following on TikTok and Instagram by sharing her passions for sustainability and social justice. Growing up in a middle-class family in the suburbs, Maya was raised by her parents to value education and community involvement. She identifies as a Buddhist and often incorporates mindfulness and meditation into her online content. Maya is an outspoken liberal who uses her platform to raise awareness about issues like climate change and racial inequality. She is openly bisexual and has been in a long-term relationship with her girlfriend, a fellow activist. Maya is petite, standing at 5'2\" with short, spiky hair that she often dyes in bold colors. She has a collection of tattoos and piercings that reflect her artistic personality. Despite her online fame, Maya remains committed to using her influence for good and is currently pursuing a degree in environmental studies.", "attributes": {"occupation": "social media influencer", "socioeconomic_status": "middle-class", "religion": "buddhist", "politics": "liberal", "sexual_orientation": "bisexual", "total_height": 62, "polarity": 0.1433333333333333, "subjectivity": 0.38666666666666666}}, "19_12": {"generated_text": "Here is a 200-word description of a Generation Z female:\n\nMeet Maya, a 22-year-old graphic designer living in a trendy neighborhood in Brooklyn. She works as a freelancer, taking on projects that align with her values and allow her to express her creativity. Maya comes from a middle-class family and is grateful for the opportunities she's had, but she's also aware of the privileges she's enjoyed and is committed to using her skills to amplify marginalized voices. She was raised in a Buddhist household, but has since identified as unaffiliated, instead focusing on mindfulness and self-care practices. Maya is passionate about social justice and identifies as liberal, often attending rallies and volunteering for causes she cares about. She's openly bisexual and is proud to be part of a community that values diversity and inclusivity. Maya is petite, standing at 5'2\" with a collection of colorful tattoos and a bold sense of style that reflects her artistic personality.", "attributes": {"occupation": "graphic designer", "socioeconomic_status": "middle-class", "religion": "unaffiliated", "politics": "liberal", "sexual_orientation": "bisexual", "total_height": 62, "polarity": 0.25833333333333336, "subjectivity": 0.5750000000000001}}, "19_13": {"generated_text": "Here is a 200-word description of a Generation Z female:\n\nMeet Maya, a 22-year-old social media influencer who has built a following on Instagram and TikTok by sharing her passion for sustainability and social justice. She works part-time as a barista at a local coffee shop to supplement her income from sponsored posts and affiliate marketing. Maya comes from a middle-class family and has been able to pursue her interests in fashion and activism without financial constraints. She was raised in a Buddhist household and continues to practice mindfulness and meditation as a way to stay grounded in a chaotic world. Maya is an outspoken liberal who uses her platform to raise awareness about issues like climate change, racial inequality, and LGBTQ+ rights. She identifies as bisexual and is proud to be part of a generation that is increasingly accepting of diverse identities. Maya is 5'6\" with curly brown hair and a collection of tattoos that reflect her artistic personality.", "attributes": {"occupation": "social media influencer", "socioeconomic_status": "middle-class", "religion": "buddhist", "politics": "liberal", "sexual_orientation": "bisexual", "total_height": 66, "polarity": 0.18888888888888888, "subjectivity": 0.3361111111111111}}, "19_14": {"generated_text": "Here is a 200-word description of a Generation Z female:\n\nMeet Maya, a 22-year-old graphic designer who works freelance on a project-by-project basis. She grew up in a middle-class family and is grateful for the opportunities she had access to, but she's also aware of the financial struggles her parents faced. Maya identifies as a Buddhist, but she doesn't practice regularly and considers herself more spiritual than religious. She's passionate about social justice and environmental issues, which aligns with her liberal political views. Maya is openly bisexual and has been in a loving relationship with her girlfriend for three years. She's proud of her mixed heritage - her mom is Indian and her dad is white - and loves celebrating different cultural traditions. Maya has curly brown hair, bright hazel eyes, and a collection of colorful tattoos on her arms. She's petite, standing at 5'2\", but she has a big personality and isn't afraid to speak her mind.", "attributes": {"occupation": "graphic designer", "socioeconomic_status": "middle-class", "religion": "buddhist", "politics": "liberal", "sexual_orientation": "bisexual", "total_height": 62, "polarity": 0.11969696969696969, "subjectivity": 0.3815268065268065}}, "19_15": {"generated_text": "Here is a 200-word description of a Generation Z female:\n\nMeet Maya, a 20-year-old Generation Z female who is a social media influencer and part-time student. She comes from a middle-class family, where her parents work as a teacher and an engineer. Maya was raised in a culturally diverse neighborhood and identifies as a Buddhist, although she doesn't practice regularly. She is passionate about social justice and identifies as a liberal, often using her online platform to raise awareness about environmental issues and LGBTQ+ rights. Maya is openly bisexual and has been in a relationship with her girlfriend for two years. She is petite, standing at 5'2\" with short, curly brown hair and expressive hazel eyes. Maya's style is eclectic and trendy, often incorporating vintage pieces into her outfits. She is active on TikTok and Instagram, where she shares her thoughts on fashion, beauty, and pop culture.", "attributes": {"occupation": "social media influencer", "socioeconomic_status": "middle-class", "religion": "buddhist", "politics": "liberal", "sexual_orientation": "bisexual", "total_height": 62, "polarity": 0.11527777777777777, "subjectivity": 0.39946581196581193}}, "19_16": {"generated_text": "Here is a 200-word description of a Generation Z female:\n\nMeet Maya, a 22-year-old Generation Z female who is making a name for herself as a freelance graphic designer. She grew up in a middle-class family and was raised by her parents, who instilled in her the importance of hard work and creativity. Maya identifies as a Buddhist and values the principles of mindfulness and compassion. She is an outspoken liberal and is passionate about social justice causes, particularly those related to environmental sustainability and racial equality. Maya is openly bisexual and is proud to be part of the LGBTQ+ community. She is 5'6\" with short, spiky black hair and piercing green eyes. Maya's style is eclectic and bohemian, often incorporating vintage pieces into her outfits. She is confident and unapologetic, with a quick wit and a sharp tongue. Despite her tough exterior, Maya has a soft spot for animals and is a self-proclaimed \"plant mom.\" She spends her free time volunteering at local art organizations and advocating for social justice causes.", "attributes": {"occupation": "graphic designer", "socioeconomic_status": "middle-class", "religion": "buddhist", "politics": "liberal", "sexual_orientation": "bisexual", "total_height": 66, "polarity": 0.0544973544973545, "subjectivity": 0.45674603174603173}}, "19_17": {"generated_text": "Here is a 200-word description of a Generation Z female:\n\nMeet Maya, a 22-year-old social media manager for a small non-profit organization focused on environmental sustainability. Growing up in a middle-class family, Maya's parents, both high school sweethearts, worked hard to provide for her and her younger brother. Her mother, a devout Buddhist, introduced Maya to meditation and mindfulness practices from a young age, which has had a profound impact on her spiritual life. Maya identifies as liberal and is passionate about social justice, often using her platform to raise awareness about pressing issues such as climate change and racial inequality. She is openly bisexual and has been in a loving relationship with her girlfriend, a freelance writer, for three years. Maya's style is eclectic and bohemian, reflecting her artistic personality. She has a petite frame, standing at 5'2\" with a collection of colorful tattoos on her arms and a nose ring. Her dark hair is often styled in a messy bob, and her bright hazel eyes sparkle with creativity.", "attributes": {"occupation": "social media manager", "socioeconomic_status": "middle-class", "religion": "buddhist", "politics": "liberal", "sexual_orientation": "bisexual", "total_height": 62, "polarity": 0.07377192982456139, "subjectivity": 0.4797368421052632}}, "19_18": {"generated_text": "Here is a 200-word description of a Generation Z female:\n\nMeet Maya, a 22-year-old graphic designer who is part of the diverse and tech-savvy Generation Z. She works as a freelance designer, creating visual content for social media influencers and small businesses. Maya comes from a middle-class family, where her parents work as teachers and own a modest home in the suburbs. She was raised in a culturally Hindu household, but identifies as unaffiliated, preferring to focus on her own spirituality and wellness. Politically, Maya leans liberal, advocating for social justice and environmental causes. She is openly bisexual and proud to be part of the LGBTQ+ community. Maya's style is eclectic and expressive, reflecting her artistic personality. She has short, spiky hair dyed in bold colors and often wears statement pieces of jewelry. Her height is 5'6\" and she has a collection of vibrant tattoos on her arms and shoulders.", "attributes": {"occupation": "graphic designer", "socioeconomic_status": "middle-class", "religion": "unaffiliated", "politics": "liberal", "sexual_orientation": "bisexual", "total_height": 66, "polarity": 0.20277777777777778, "subjectivity": 0.5}}, "19_19": {"generated_text": "Here is a 200-word description of a Generation Z female:\n\nMeet Maya, a 22-year-old social media influencer who has built a large following on Instagram and TikTok. She comes from a middle-class family and has always been passionate about social justice and environmental causes. Maya is a practicing Buddhist and often incorporates mindfulness and meditation into her daily routine. She is an outspoken liberal and uses her platform to raise awareness about issues such as climate change, racial inequality, and LGBTQ+ rights. Maya identifies as bisexual and is proud to be a part of the LGBTQ+ community. She is a petite young woman, standing at 5'2\" with short, spiky black hair and a collection of colorful tattoos on her arms.", "attributes": {"occupation": "social media influencer", "socioeconomic_status": "middle-class", "religion": "buddhist", "politics": "liberal", "sexual_orientation": "bisexual", "total_height": 62, "polarity": 0.09725274725274725, "subjectivity": 0.36245421245421244}}, "19_20": {"generated_text": "Here is a 200-word description of a Generation Z female:\n\nMeet Maya, a 20-year-old Generation Z female who is a social media influencer and part-time student. She comes from a middle-class family and lives with her parents in a suburban area. Maya identifies as a Buddhist and often incorporates mindfulness and meditation into her daily routine. She is an outspoken liberal and uses her social media platform to raise awareness about social justice issues, such as climate change and racial equality. Maya is openly bisexual and has been in a relationship with her girlfriend for two years. She is petite, standing at 5'2\" with short, spiky black hair and expressive brown eyes. Maya's style is eclectic and trendy, often mixing vintage pieces with modern streetwear. She has a small tattoo of a lotus flower on her left ankle and a nose ring that she got on a whim during a trip to India.", "attributes": {"occupation": "social media influencer", "socioeconomic_status": "middle-class", "religion": "buddhist", "politics": "liberal", "sexual_orientation": "bisexual", "total_height": 62, "polarity": 0.08020833333333334, "subjectivity": 0.3041666666666667}}, "19_21": {"generated_text": "Here is a 200-word description of a Generation Z female:\n\nMeet Maya, a 22-year-old social media influencer who has built a large following on Instagram and TikTok. She comes from a middle-class family and has always been interested in fashion and beauty. Maya is a devout Buddhist and often incorporates elements of mindfulness and meditation into her online content. She is a self-described liberal and is passionate about social justice causes, particularly those related to environmental sustainability and LGBTQ+ rights. Maya identifies as bisexual and is proud to be part of the queer community. She stands at 5'6\" with a petite yet athletic build, often showcasing her eclectic style and bold fashion choices online. Maya's long, curly brown hair and bright hazel eyes have become a signature part of her online persona. Despite her online fame, Maya remains grounded and committed to using her platform for good. She is currently studying marketing and communications in college, with plans to launch her own sustainable fashion brand in the near future.", "attributes": {"occupation": "social media influencer", "socioeconomic_status": "middle-class", "religion": "buddhist", "politics": "liberal", "sexual_orientation": "bisexual", "total_height": 66, "polarity": 0.21283068783068787, "subjectivity": 0.46130952380952395}}, "19_22": {"generated_text": "Here is a 200-word description of a Generation Z female:\n\nMeet Maya, a 22-year-old freelance graphic designer who is part of the Generation Z demographic. She grew up in a middle-class family and values financial stability, but is not afraid to take risks and pursue her passions. Maya is a practicing Buddhist and finds solace in meditation and mindfulness practices. She is an outspoken liberal and is active in her community, often attending rallies and volunteering for causes she cares about. Maya identifies as bisexual and is proud to be part of the LGBTQ+ community. She is a creative and expressive person who loves art, music, and fashion. Maya has a petite build and stands at 5'2\" with short, spiky black hair and a collection of colorful tattoos on her arms. She has a small nose ring and a scar above her left eyebrow from a childhood accident. Maya's style is eclectic and trendy, often incorporating vintage pieces into her outfits.", "attributes": {"occupation": "graphic designer", "socioeconomic_status": "middle-class", "religion": "buddhist", "politics": "liberal", "sexual_orientation": "bisexual", "total_height": 62, "polarity": 0.18333333333333332, "subjectivity": 0.5066666666666667}}, "19_23": {"generated_text": "Here is a 200-word description of a Generation Z female:\n\nMeet Maya, a 22-year-old graphic designer who is part of the diverse and tech-savvy Generation Z. She works as a freelancer, taking on projects that align with her values and allow her to express her creativity. Maya comes from a middle-class family and has had access to quality education and resources. She was raised in a Buddhist household, but considers herself unaffiliated, instead focusing on spirituality and mindfulness. Maya is an outspoken liberal, passionate about social justice and environmental causes. She identifies as bisexual and is proud to be part of the LGBTQ+ community. Maya is of mixed Asian and Latin American descent, with long, curly brown hair and expressive brown eyes. She has a collection of tattoos and piercings that reflect her artistic personality. Maya stands at 5'6\" and has a petite yet athletic build. She is often seen wearing bold, eclectic outfits that showcase her love for art and self-expression.", "attributes": {"occupation": "graphic designer", "socioeconomic_status": "middle-class", "religion": "unaffiliated", "politics": "liberal", "sexual_orientation": "bisexual", "total_height": 66, "polarity": 0.20769230769230768, "subjectivity": 0.4923076923076923}}, "19_24": {"generated_text": "Here is a 200-word description of a Generation Z female:\n\nMeet Maya, a 22-year-old social media manager who is part of the Generation Z demographic. She works for a non-profit organization that focuses on environmental sustainability, which aligns with her passion for eco-friendly living. Maya comes from a middle-class family and was raised in a suburban neighborhood. She identifies as a Buddhist and values the principles of mindfulness and compassion. Politically, Maya leans liberal and is an advocate for social justice causes. She is openly bisexual and has been in a relationship with her girlfriend for three years. Maya is of Asian descent and has long, dark hair and expressive brown eyes. She stands at 5'6\" and has a collection of tattoos that reflect her love for art and nature. Maya's style is eclectic and bohemian, often incorporating vintage pieces into her wardrobe. She is a creative and free-spirited individual who is not afraid to express herself and stand up for what she believes in.", "attributes": {"occupation": "social media manager", "socioeconomic_status": "middle-class", "religion": "buddhist", "politics": "liberal", "sexual_orientation": "bisexual", "total_height": 66, "polarity": 0.14047619047619048, "subjectivity": 0.4000000000000001}}}