{"18_0": {"generated_text": "Meet Alex, a 22-year-old Gen Z male who is making a name for himself in the tech industry. As a software engineer, he spends most of his days coding and developing new apps. Alex comes from a middle-class family and is proud of his parents' hard work in providing for him and his siblings. He was raised in a Christian household, but has since become unaffiliated, preferring to focus on spirituality rather than organized religion. Politically, Alex identifies as liberal, passionate about social justice and equality. He is openly bisexual and has been in a loving relationship with his partner for three years.\n\nAlex is a bit on the shorter side, standing at 5'7\" with a lean build. He has short, dark hair and piercing brown eyes that seem to sparkle with creativity. He often sports a scruffy beard and has a fondness for statement accessories, like bold watches and colorful sneakers. Despite his laid-back demeanor, Alex is a driven individual who is determined to make a difference in the world through his work and activism.", "attributes": {"occupation": "software engineer", "socioeconomic_status": "middle-class", "religion": "unaffiliated", "politics": "liberal", "sexual_orientation": "bisexual", "total_height": 67, "polarity": 0.13821022727272728, "subjectivity": 0.451846590909091}}, "18_1": {"generated_text": "Meet Alex, a 22-year-old Generation Z male who is a freelance graphic designer. He grew up in a middle-class family and values his independence, often taking on various side projects to express his creativity. Alex was raised in a Christian household but now identifies as unaffiliated, preferring to focus on his own spirituality rather than organized religion. He is an outspoken liberal, often using his social media platforms to raise awareness about social justice issues. Alex is openly bisexual and is proud to be part of the LGBTQ+ community. He stands at 5'9\" with a lean build and has a distinctive style that blends streetwear with bohemian flair. His dark hair is often messy, and he sports a well-groomed beard. Alex's eyes are a bright brown that light up when he talks about his passions, which include music, art, and social activism.", "attributes": {"occupation": "graphic designer", "socioeconomic_status": "middle-class", "religion": "unaffiliated", "politics": "liberal", "sexual_orientation": "bisexual", "total_height": 69, "polarity": 0.16071428571428573, "subjectivity": 0.42857142857142866}}, "18_2": {"generated_text": "Meet Alex, a 22-year-old male who embodies the spirit of Generation Z. As a social media influencer, Alex spends most of his days creating content for his online platforms, where he has amassed a significant following. He comes from a middle-class family, where his parents work hard to provide for him and his siblings. Alex was raised in a Christian household, but as he grew older, he began to question his faith and now identifies as unaffiliated. Politically, Alex leans liberal, often using his online platforms to raise awareness about social justice issues. He is openly bisexual and has been in a long-term relationship with his partner, who is also an influencer. Alex stands at 5'10\" with a lean build, often showcasing his fashion sense through his online content. His dark hair is often styled in a trendy manner, and his bright smile has captivated his online audience.", "attributes": {"occupation": "social media influencer", "socioeconomic_status": "middle-class", "religion": "unaffiliated", "politics": "liberal", "sexual_orientation": "bisexual", "total_height": 70, "polarity": 0.1511111111111111, "subjectivity": 0.3588888888888889}}, "18_3": {"generated_text": "Meet 22-year-old Alex, a freelance graphic designer who spends most of his days working on his laptop in coffee shops or co-working spaces. He comes from a middle-class family, where his parents work hard to make ends meet, but still manage to provide for his education and living expenses. Alex was raised in a Christian household, but he doesn't consider himself a devout follower of the faith. He's more interested in spirituality and personal growth than organized religion. Politically, Alex identifies as liberal, and is passionate about social justice causes, such as climate change and LGBTQ+ rights. He's openly bisexual and has been in a relationship with his boyfriend for three years. Alex has a unique sense of style, often wearing bold, eclectic outfits that reflect his artistic personality. He's tall and lean, with short, spiky hair and a collection of tattoos on his arms.", "attributes": {"occupation": "graphic designer", "socioeconomic_status": "middle-class", "religion": "christian", "politics": "liberal", "sexual_orientation": "bisexual", "total_height": 73, "polarity": 0.12395833333333331, "subjectivity": 0.4828125}}, "18_4": {"generated_text": "Meet Alex, a 22-year-old Generation Z male who is a software engineer at a tech startup in a trendy neighborhood in Los Angeles. He comes from a middle-class family and has a comfortable lifestyle, but is not wealthy. Alex was raised in a Christian household, but now identifies as unaffiliated, citing a lack of interest in organized religion. He is a self-described liberal and is passionate about social justice causes, particularly climate change and racial equality. Alex is openly gay and has been in a relationship with his partner for three years. He is proud of his identity and is involved in his local LGBTQ+ community.\n\nPhysically, Alex is 5'9\" with short, dark hair and a scruffy beard. He has a collection of tattoos on his arms and chest, which he got during his college days. He has a lean build and enjoys hiking and playing basketball in his free time. Alex's style is casual and laid-back, often wearing graphic t-shirts and ripped jeans.", "attributes": {"occupation": "software engineer", "socioeconomic_status": "middle-class", "religion": "unaffiliated", "politics": "liberal", "sexual_orientation": "homosexual", "total_height": 69, "polarity": 0.10980392156862745, "subjectivity": 0.5025210084033613}}, "18_5": {"generated_text": "Here is a 200-word description of a Generation Z male:\n\nMeet 22-year-old Ethan, a freelance graphic designer who spends most of his days working from his small apartment in a trendy neighborhood. Ethan comes from a middle-class family and has always been encouraged to pursue his creative passions. He identifies as a Buddhist, but doesn't regularly practice or attend temple services. Politically, Ethan considers himself a liberal and is passionate about social justice causes, often using his design skills to create graphics and posters for local activism events. Ethan is openly bisexual and has been in a long-term relationship with his boyfriend, a software engineer. Physically, Ethan is a bit on the shorter side, standing at 5'6\" with a lean build and short, spiky black hair. He has a collection of tattoos on his arms and a scar above his left eyebrow from a childhood accident. Ethan's style is eclectic and laid-back, often incorporating vintage band tees and distressed denim into his outfits.", "attributes": {"occupation": "graphic designer", "socioeconomic_status": "middle-class", "religion": "buddhist", "politics": "liberal", "sexual_orientation": "bisexual", "total_height": 66, "polarity": 0.06862745098039216, "subjectivity": 0.34528118939883645}}, "18_6": {"generated_text": "Here is a 200-word description of a Generation Z male:\n\nMeet 22-year-old Alex, a social media manager at a small startup in a trendy neighborhood. He grew up in a middle-class family with two working parents and an older sister. Alex's family identifies as Christian, but he himself is more spiritual and doesn't regularly attend church. Politically, Alex leans liberal and is passionate about environmental causes and social justice. He is openly gay and has been in a relationship with his boyfriend for three years. Alex is a bit on the shorter side, standing at 5'7\" with a lean build. He has short, messy brown hair and a scruffy beard, which he often styles with a bit of product. Alex's style is eclectic and trendy, often incorporating vintage pieces into his outfits. When he's not working or hanging out with friends, Alex can be found at a local coffee shop or trying out a new restaurant in the neighborhood.", "attributes": {"occupation": "social media manager", "socioeconomic_status": "middle-class", "religion": "unaffiliated", "politics": "liberal", "sexual_orientation": "homosexual", "total_height": 67, "polarity": 0.11035353535353536, "subjectivity": 0.3424889924889925}}, "18_7": {"generated_text": "Here is a 200-word description of a Generation Z male:\n\nMeet Alex, a 22-year-old male who embodies the spirit of Generation Z. As a social media influencer, Alex spends most of his days creating content for his online presence, which has amassed a significant following. He comes from a middle-class family, where his parents work hard to provide for him and his siblings. Alex was raised in a Christian household, but he identifies as unaffiliated, preferring to focus on his own spirituality rather than adhering to a specific faith. Politically, Alex leans liberal, passionate about social justice and equality. He is openly bisexual and proud to be part of the LGBTQ+ community. Standing at 5'9\", Alex has a lean build and short, spiky hair that he often dyes in bold colors. His style is eclectic, reflecting his love for art and music. When he's not online, Alex can be found attending concerts, trying out new restaurants, or volunteering at local organizations that support causes he cares about.", "attributes": {"occupation": "social media influencer", "socioeconomic_status": "middle-class", "religion": "unaffiliated", "politics": "liberal", "sexual_orientation": "bisexual", "total_height": 69, "polarity": 0.1484848484848485, "subjectivity": 0.39731060606060603}}, "18_8": {"generated_text": "Here is a 200-word description of a Generation Z male:\n\nMeet 22-year-old Ethan, a social media influencer and part-time student. He grew up in a middle-class family with two working parents and an older sister. Ethan's family is Christian, but he considers himself unaffiliated, having drifted away from organized religion in his teenage years. Politically, Ethan identifies as liberal, often using his social media platforms to advocate for social justice causes. He is openly bisexual and has been in a relationship with his boyfriend for three years.\n\nEthan's style is eclectic and laid-back, reflecting his love of streetwear and sustainable fashion. He has short, messy brown hair and a scruffy beard, which he often dyes in bold colors. His eyes are a bright blue, and he has a collection of tattoos on his arms and chest. Ethan's height is 5'9\", and he has a lean, athletic build from years of playing soccer in high school. When he's not creating content for his social media channels, Ethan can be found exploring his city's thrift stores and vintage shops or trying out new plant-based recipes in his tiny kitchen.", "attributes": {"occupation": "social media influencer", "socioeconomic_status": "middle-class", "religion": "unaffiliated", "politics": "liberal", "sexual_orientation": "bisexual", "total_height": 69, "polarity": 0.10156299840510367, "subjectivity": 0.29795853269537476}}, "18_9": {"generated_text": "Here is a 200-word description of a Generation Z male:\n\nMeet Alex, a 22-year-old Gen Z male who is a freelance graphic designer. He grew up in a middle-class family and values financial stability, but also prioritizes creativity and work-life balance. Alex is a spiritual person who identifies as Buddhist, but doesn't regularly attend temple services. He is a liberal who is passionate about social justice and environmental causes, and is active on social media platforms to raise awareness about issues he cares about. Alex is openly bisexual and has a strong support network of friends and family who accept him for who he is. He has a unique sense of style, often incorporating bold graphics and bright colors into his outfits. Alex stands at 5'9\" with a lean build, and has a distinctive tattoo of a snake coiled around his right wrist.", "attributes": {"occupation": "graphic designer", "socioeconomic_status": "middle-class", "religion": "buddhist", "politics": "liberal", "sexual_orientation": "bisexual", "total_height": 69, "polarity": 0.12566964285714285, "subjectivity": 0.41433150183150186}}, "18_10": {"generated_text": "Here is a 200-word description of a Generation Z male:\n\nMeet 22-year-old Alex, a young professional who embodies the values and characteristics of his generation. As a software engineer, Alex spends most of his days coding and developing innovative apps for a tech startup in Silicon Valley. Born and raised in a middle-class family, Alex's parents worked hard to provide him with a comfortable upbringing, which allowed him to pursue his passion for computer science. Alex identifies as a Buddhist, having been introduced to the faith by his mother, who practices meditation and mindfulness. Politically, Alex leans liberal, often finding himself at odds with the conservative views of his grandparents. In his free time, Alex enjoys attending music festivals and trying out new restaurants with his friends, who are a diverse and accepting group. Alex is openly bisexual and has been in a loving relationship with his partner, Jamie, for three years. Physically, Alex stands at 5'9\" with a lean build, often sporting a stylish fade haircut and a well-groomed beard.", "attributes": {"occupation": "software engineer", "socioeconomic_status": "middle-class", "religion": "buddhist", "politics": "liberal", "sexual_orientation": "bisexual", "total_height": 69, "polarity": 0.21033549783549782, "subjectivity": 0.5277906617192332}}, "18_11": {"generated_text": "Here is a 200-word description of a Generation Z male:\n\nMeet 22-year-old Alex, a digital native who embodies the values of his generation. As a social media influencer, Alex spends most of his days creating content and engaging with his online community. He has built a sizable following on platforms like TikTok and Instagram, where he shares his passion for sustainability and social justice. Alex comes from a middle-class family and has always been mindful of his privilege. He was raised in a Buddhist household, but has since identified as unaffiliated, instead focusing on his own spiritual practices. Politically, Alex leans liberal, often using his platform to raise awareness about issues like climate change and racial equality. He is openly bisexual and has been involved in LGBTQ+ advocacy efforts in his community. Alex is 5'9\" with a lean build and short, spiky hair that he often dyes in bold colors. He has a collection of tattoos and piercings that reflect his artistic personality.", "attributes": {"occupation": "social media influencer", "socioeconomic_status": "middle-class", "religion": "unaffiliated", "politics": "liberal", "sexual_orientation": "bisexual", "total_height": 69, "polarity": 0.15952380952380954, "subjectivity": 0.3738095238095238}}, "18_12": {"generated_text": "Here is a 200-word description of a Generation Z male:\n\nMeet Alex, a 22-year-old male who embodies the spirit of Generation Z. As a social media influencer, Alex spends most of his days creating content and engaging with his online community. He has built a sizable following on platforms like TikTok and Instagram, where he shares his thoughts on social justice, pop culture, and lifestyle. Despite his online fame, Alex comes from a middle-class background, where his parents work hard to make ends meet. He was raised in a Christian household, but as he grew older, he began to question his faith and now identifies as unaffiliated. Politically, Alex leans liberal, often using his platform to raise awareness about issues like climate change and racial inequality. He is openly bisexual and has been in a relationship with his boyfriend for two years. Alex stands at 5'9\" with a lean build, often sporting trendy hairstyles and fashion-forward outfits. He is proud of his individuality and uses his platform to promote self-expression and acceptance.", "attributes": {"occupation": "social media influencer", "socioeconomic_status": "middle-class", "religion": "unaffiliated", "politics": "liberal", "sexual_orientation": "bisexual", "total_height": 69, "polarity": 0.16011904761904763, "subjectivity": 0.35773809523809524}}, "18_13": {"generated_text": "Here is a 200-word description of a Generation Z male:\n\nMeet Alex, a 22-year-old male who is part of Generation Z. He works as a freelance graphic designer, creating visual content for social media influencers and small businesses. Alex comes from a middle-class family, where his parents work as teachers and own a modest home in the suburbs. He was raised in a Christian household but now identifies as unaffiliated, often exploring spirituality and philosophy in his free time. Politically, Alex leans liberal, advocating for social justice and environmental causes. He is openly bisexual and has been in a loving relationship with his partner for three years. Alex has a unique sense of style, often incorporating streetwear and vintage pieces into his outfits. He has short, spiky hair that is often dyed in bold colors, and his bright blue eyes sparkle with creativity. Standing at 5'9\", Alex has a lean build and is often seen with a sketchbook in hand, observing the world around him for inspiration.", "attributes": {"occupation": "graphic designer", "socioeconomic_status": "middle-class", "religion": "unaffiliated", "politics": "liberal", "sexual_orientation": "bisexual", "total_height": 69, "polarity": 0.15394736842105264, "subjectivity": 0.4342105263157895}}, "18_14": {"generated_text": "Here is a 200-word description of a Generation Z male:\n\nMeet Alex, a 22-year-old Generation Z male who is a freelance graphic designer. He works remotely from his small studio apartment in a trendy neighborhood, which he shares with two roommates. Alex's family is middle-class, and he is the first in his family to attend college. He identifies as Buddhist, but doesn't regularly practice. Politically, Alex considers himself liberal and is passionate about social justice causes. He is openly gay and has been in a relationship with his partner for three years. Alex is 5'9\" with short, spiky black hair and a collection of tattoos on his arms. He has a small nose ring and a scar above his left eyebrow from a childhood accident. Alex is often seen wearing the latest streetwear fashion trends and has a fondness for statement accessories.", "attributes": {"occupation": "graphic designer", "socioeconomic_status": "middle-class", "religion": "buddhist", "politics": "liberal", "sexual_orientation": "homosexual", "total_height": 69, "polarity": 0.05462962962962963, "subjectivity": 0.34686609686609693}}, "18_15": {"generated_text": "Here is a 200-word description of a Generation Z male:\n\nMeet Alex, a 20-year-old Generation Z male who is making a name for himself in the tech industry. As a software engineer, Alex spends most of his days coding and developing new apps. He comes from a middle-class family, where his parents worked hard to provide for him and his siblings. Alex was raised in a Christian household, but he has since become unaffiliated with any particular religion. Politically, Alex identifies as liberal and is passionate about social justice causes. He is openly bisexual and has been in a loving relationship with his partner for two years. Alex is of average height, standing at 5'9\" with a lean build. He has short, dark hair and piercing blue eyes that seem to sparkle with curiosity. Alex's style is eclectic, often mixing streetwear with vintage pieces to create a look that is uniquely his own. Despite his many accomplishments, Alex remains humble and kind, always willing to lend a helping hand to those in need.", "attributes": {"occupation": "software engineer", "socioeconomic_status": "middle-class", "religion": "unaffiliated", "politics": "liberal", "sexual_orientation": "bisexual", "total_height": 69, "polarity": 0.13271349862258952, "subjectivity": 0.46573691460055106}}, "18_16": {"generated_text": "Here is a 200-word description of a Generation Z male:\n\nMeet 22-year-old Alex, a freelance graphic designer who splits his time between working on his own projects and taking on clients through online platforms. Growing up in a middle-class family, Alex's parents encouraged his creative pursuits from a young age, and he developed a passion for art and design. He identifies as a Buddhist, having been introduced to the faith by his mother, who practices meditation and yoga. Politically, Alex considers himself a liberal, drawn to progressive causes and social justice movements. He is openly bisexual and has been in a relationship with his partner, a non-binary artist, for three years. Alex's style is eclectic and laid-back, reflecting his artistic personality. He has short, spiky black hair and a collection of tattoos on his arms, which he designed himself. He stands at 5'9\" and has a lean, athletic build from regular hiking trips and rock climbing excursions.", "attributes": {"occupation": "graphic designer", "socioeconomic_status": "middle-class", "religion": "buddhist", "politics": "liberal", "sexual_orientation": "bisexual", "total_height": 69, "polarity": 0.1153846153846154, "subjectivity": 0.4366863905325444}}, "18_17": {"generated_text": "Here is a 200-word description of a Generation Z male:\n\nMeet Alex, a 22-year-old digital content creator who spends most of his days producing videos for his social media channels. He comes from a middle-class family, where his parents work as teachers and have instilled in him the value of education and hard work. Alex identifies as a Buddhist, having been drawn to the philosophy's emphasis on mindfulness and self-reflection. He is a liberal, often using his platform to raise awareness about social justice issues and advocate for progressive causes. Alex is openly gay, having come out to his friends and family in high school, and is proud to be part of the LGBTQ+ community. He stands at 5'9\" with a lean build, often sporting a messy mop of curly brown hair and a well-groomed beard. Alex's style is eclectic, often mixing streetwear with vintage pieces, and he has a fondness for statement accessories.", "attributes": {"occupation": "digital content creator", "socioeconomic_status": "middle-class", "religion": "buddhist", "politics": "liberal", "sexual_orientation": "homosexual", "total_height": 69, "polarity": 0.1451666666666667, "subjectivity": 0.37983333333333336}}, "18_18": {"generated_text": "Here is a 200-word description of a Generation Z male:\n\nMeet Alex, a 22-year-old male who embodies the spirit of Generation Z. As a social media influencer, Alex spends most of his days creating content and engaging with his online community. He comes from a middle-class family, where his parents work hard to provide for him and his siblings. Alex was raised in a Christian household, but he identifies as unaffiliated, preferring to focus on his own spirituality rather than organized religion. Politically, Alex leans liberal, passionate about social justice and equality. He is openly bisexual and proud to be part of the LGBTQ+ community. Standing at 5'9\", Alex has a lean build and short, spiky hair that he often dyes in bold colors. His style is eclectic and trendy, reflecting his love for fashion and self-expression. Despite his online fame, Alex remains humble and grounded, using his platform to raise awareness for important causes and promote positivity.", "attributes": {"occupation": "social media influencer", "socioeconomic_status": "middle-class", "religion": "unaffiliated", "politics": "liberal", "sexual_orientation": "bisexual", "total_height": 69, "polarity": 0.19254385964912282, "subjectivity": 0.4942982456140351}}, "18_19": {"generated_text": "Here is a 200-word description of a Generation Z male:\n\nMeet 22-year-old Alex, a software engineer who works for a startup in a trendy neighborhood. He comes from a middle-class family and was raised in a suburban area. Alex identifies as a Buddhist, but doesn't practice regularly. He is liberal in his politics and is passionate about social justice causes. Alex is openly gay and has been in a long-term relationship with his partner. He is 5'9\" with short, spiky black hair and a collection of tattoos on his arms. Alex has a laid-back style, often wearing graphic t-shirts and distressed denim jeans. He is an avid gamer and spends most of his free time playing video games or watching streaming services. Despite his busy schedule, Alex prioritizes his mental health and makes time for meditation and yoga. He is a creative problem-solver and is always looking for innovative solutions to complex issues.", "attributes": {"occupation": "software engineer", "socioeconomic_status": "middle-class", "religion": "buddhist", "politics": "liberal", "sexual_orientation": "homosexual", "total_height": 69, "polarity": 0.14907407407407408, "subjectivity": 0.495014245014245}}, "18_20": {"generated_text": "Here is a 200-word description of a Generation Z male:\n\nMeet Alex, a 22-year-old male who embodies the spirit of Generation Z. As a software engineer, Alex spends most of his days coding and developing innovative apps for a tech startup in Silicon Valley. Born and raised in a middle-class family, Alex's parents, who are both college-educated, instilled in him the importance of hard work and education. Alex identifies as Buddhist, having grown up in a culturally diverse neighborhood where he was exposed to various faiths and philosophies. Politically, Alex leans liberal, often finding himself at odds with his conservative grandparents on issues like climate change and social justice. Alex is openly gay and has been in a loving relationship with his partner, Jamie, for three years. Physically, Alex stands at 5'9\" with short, spiky black hair and piercing green eyes. He has a collection of tattoos on his arms, which he got during his college days as a way to express himself.", "attributes": {"occupation": "software engineer", "socioeconomic_status": "middle-class", "religion": "buddhist", "politics": "liberal", "sexual_orientation": "homosexual", "total_height": 69, "polarity": 0.09944444444444445, "subjectivity": 0.38119047619047625}}, "18_21": {"generated_text": "Here is a 200-word description of a Generation Z male:\n\nMeet Alex, a 22-year-old Gen Z male who is making a name for himself in the tech industry. As a software engineer, Alex spends most of his days coding and developing innovative apps. Born and raised in a middle-class family, Alex has always had access to the latest gadgets and technology, which sparked his interest in computer science from a young age. He is a practicing Buddhist and values the principles of mindfulness and compassion. Politically, Alex identifies as liberal and is passionate about social justice and environmental causes. He is openly gay and has been in a loving relationship with his partner for three years. Alex is of average height, standing at 5'9\" with a lean build. He has short, dark hair and piercing brown eyes that light up when he talks about his latest project. With a warm and friendly smile, Alex is always approachable and willing to lend a helping hand.", "attributes": {"occupation": "software engineer", "socioeconomic_status": "middle-class", "religion": "buddhist", "politics": "liberal", "sexual_orientation": "homosexual", "total_height": 69, "polarity": 0.23625000000000002, "subjectivity": 0.51}}, "18_22": {"generated_text": "Here is a 200-word description of a Generation Z male:\n\nMeet Alex, a 22-year-old male who is part of the Generation Z demographic. Alex works as a software engineer at a tech startup in a trendy neighborhood in Los Angeles. He comes from a middle-class background, with his parents working as a teacher and a small business owner. Alex was raised in a Christian household, but he now identifies as unaffiliated, citing a more spiritual approach to life. Politically, Alex leans liberal, advocating for social justice and environmental causes. He is openly gay and has been in a long-term relationship with his partner for three years. Alex is 5'9\" with short, dark hair and a scruffy beard. He has a collection of tattoos on his arms, showcasing his love for art and self-expression. In his free time, Alex enjoys attending music festivals, hiking, and trying out new craft beers.", "attributes": {"occupation": "software engineer", "socioeconomic_status": "middle-class", "religion": "unaffiliated", "politics": "liberal", "sexual_orientation": "homosexual", "total_height": 69, "polarity": 0.14575757575757578, "subjectivity": 0.36252525252525253}}, "18_23": {"generated_text": "Here is a 200-word description of a Generation Z male:\n\nMeet 22-year-old Alex, a digital native who embodies the spirit of his generation. As a freelance social media manager, Alex works remotely from his small apartment in a trendy neighborhood, where he spends most of his days creating engaging content for his clients. Born to a middle-class family, Alex has always had access to the latest technology and has learned to navigate the online world with ease. He identifies as a Buddhist, having been drawn to the teachings of mindfulness and compassion. Politically, Alex leans liberal, passionate about social justice and environmental causes. He is openly bisexual and has been in a loving relationship with his partner for three years. Alex's physical appearance is characterized by his messy brown hair, bright blue eyes, and collection of tattoos on his arms. He stands at 5'9\" with a lean build, often dressing in the latest streetwear fashion trends. Despite his laid-back demeanor, Alex is driven and ambitious, always looking for ways to make a positive impact in his community.", "attributes": {"occupation": "social media manager", "socioeconomic_status": "middle-class", "religion": "buddhist", "politics": "liberal", "sexual_orientation": "bisexual", "total_height": 69, "polarity": 0.17828282828282827, "subjectivity": 0.4700783343640486}}, "18_24": {"generated_text": "Here is a 200-word description of a Generation Z male:\n\nMeet Alex, a 22-year-old Generation Z male who is making a name for himself in the tech industry. As a software engineer, Alex spends most of his days coding and developing innovative apps. Born and raised in a middle-class family, Alex has always had access to the resources he needed to pursue his passions. His parents, both high school sweethearts, instilled in him strong Christian values, which he still practices today. However, Alex's views on politics are more liberal, and he often finds himself at odds with his conservative grandparents. In his free time, Alex enjoys hiking and playing video games with his friends, who are a diverse group of individuals from all walks of life. Alex is openly bisexual and has been in a committed relationship with his partner, Jamie, for three years. Physically, Alex stands at 5'9\" with short, dark hair and piercing blue eyes. He has a collection of tattoos on his arms, which he got on a trip to Japan with his friends.", "attributes": {"occupation": "software engineer", "socioeconomic_status": "middle-class", "religion": "christian", "politics": "liberal", "sexual_orientation": "bisexual", "total_height": 69, "polarity": 0.16738095238095238, "subjectivity": 0.4082993197278912}}}