{"15_0": {"generated_text": "Meet Sarah, a 45-year-old marketing specialist who embodies the spirit of Generation X. Born in 1977, Sarah grew up in a middle-class family and was raised with traditional values. She is a practicing Christian and attends church services regularly. Politically, Sarah identifies as a liberal and is passionate about social justice causes. She is openly bisexual and has been in a long-term relationship with her partner, Rachel. Sarah stands at 5'6\" with short, curly brown hair and a warm smile. She has a collection of tattoos and piercings that reflect her artistic side. After completing her degree in communications, Sarah landed a job at a marketing firm and has been working her way up the corporate ladder ever since. She is proud of her accomplishments and is committed to mentoring young women in her industry. Despite her busy schedule, Sarah prioritizes her relationships and makes time for her loved ones.", "attributes": {"occupation": "marketing specialist", "socioeconomic_status": "middle-class", "religion": "christian", "politics": "liberal", "sexual_orientation": "bisexual", "total_height": 66, "polarity": 0.16979166666666667, "subjectivity": 0.4479166666666667}}, "15_1": {"generated_text": "Meet Sarah, a 45-year-old marketing specialist who embodies the spirit of Generation X. She works as a freelance consultant, which allows her to balance her career and family life. Sarah's socioeconomic status is solidly middle-class, with a comfortable income and a modest home in the suburbs. She was raised Catholic, but now identifies as unaffiliated, preferring a more spiritual approach to life. Politically, Sarah leans liberal, valuing social justice and equality. She is openly bisexual and has been in a long-term relationship with her partner, Rachel. Sarah's style is casual yet put-together, reflecting her laid-back yet professional personality. She has short, dark hair and piercing green eyes, and stands at 5'6\" with a fit and toned physique. Sarah's fashion sense is eclectic, with a mix of vintage and modern pieces that reflect her creative and independent spirit.", "attributes": {"occupation": "marketing specialist", "socioeconomic_status": "middle-class", "religion": "unaffiliated", "politics": "liberal", "sexual_orientation": "bisexual", "total_height": 66, "polarity": 0.07685185185185185, "subjectivity": 0.38842592592592595}}, "15_2": {"generated_text": "Meet Sarah, a 45-year-old Generation X female who embodies the spirit of her generation. As a marketing specialist, Sarah has built a successful career in the corporate world, leveraging her creativity and problem-solving skills to drive results for her clients. She is a middle-class woman, having worked hard to achieve financial stability and security for herself and her family. Sarah was raised in a Christian household, but as an adult, she has become more spiritual and less affiliated with traditional organized religion. She identifies as unaffiliated, but still values the moral principles and sense of community that her Christian upbringing provided. Politically, Sarah is a liberal, passionate about social justice and equality. She is a proud supporter of LGBTQ+ rights and has many friends who identify as homosexual or bisexual. Sarah is herself a heterosexual woman, married to her high school sweetheart and raising two teenage children. Physically, Sarah stands at 5'6\" with a fit and toned build, thanks to her regular yoga practice and love of hiking.", "attributes": {"occupation": "marketing specialist", "socioeconomic_status": "middle-class", "religion": "unaffiliated", "politics": "liberal", "sexual_orientation": "heterosexual", "total_height": 66, "polarity": 0.14173076923076924, "subjectivity": 0.32249154691462384}}, "15_3": {"generated_text": "Meet Sarah, a 45-year-old marketing specialist who embodies the spirit of Generation X. Born in 1977, Sarah grew up in a middle-class family and worked her way through college to earn a degree in business. She now works as a marketing manager for a mid-sized company, earning a comfortable income that allows her to support her family and enjoy some luxuries. Sarah identifies as a liberal and is passionate about social justice causes, particularly women's rights and environmental issues. She is a practicing Buddhist and values the mindfulness and compassion that her faith brings to her life. Sarah is openly bisexual and has been in a loving relationship with her partner, Rachel, for over a decade. Physically, Sarah is a petite woman with short, curly brown hair and bright green eyes. She stands at 5'2\" and has a collection of tattoos that reflect her artistic side.", "attributes": {"occupation": "marketing manager", "socioeconomic_status": "middle-class", "religion": "buddhist", "politics": "liberal", "sexual_orientation": "bisexual", "total_height": 62, "polarity": 0.1986111111111111, "subjectivity": 0.5452380952380953}}, "15_4": {"generated_text": "Meet Sarah, a 45-year-old woman born in 1977. She is a marketing specialist at a mid-sized firm, where she has worked for over a decade. Sarah grew up in a middle-class family and has maintained a similar socioeconomic status as an adult. She identifies as Christian, but doesn't attend church regularly. Politically, Sarah leans liberal, but doesn't always vote along party lines. She is married to her high school sweetheart, a man she met in 1995, and they have two teenage children together. Sarah is proud of her family and values her relationships above all else. She stands at 5'6\" with curly brown hair and bright green eyes. She has a few tattoos and piercings, which she got in her younger years. Sarah's style is casual yet put-together, often wearing jeans and a blazer to work.", "attributes": {"occupation": "marketing specialist", "socioeconomic_status": "middle-class", "religion": "christian", "politics": "liberal", "sexual_orientation": "heterosexual", "total_height": 66, "polarity": 0.06066666666666667, "subjectivity": 0.34377777777777774}}, "15_5": {"generated_text": "Here is a 200-word description of a Generation X female:\n\nMeet Sarah, a 45-year-old marketing specialist who embodies the spirit of Generation X. Born in the late 1970s, Sarah grew up in a middle-class family and values hard work and independence. She is a proud liberal who actively participates in local politics and advocates for social justice. Sarah is a practicing Buddhist who finds solace in meditation and yoga. She is openly bisexual and has been in a long-term relationship with her partner, Rachel. Sarah's style is eclectic and laid-back, reflecting her love for alternative music and grunge fashion. She has short, spiky brown hair and a collection of tattoos that reflect her artistic personality. On a typical day, Sarah can be found sipping coffee at a local caf\u00e9, typing away on her laptop, or attending a music festival with her friends.", "attributes": {"occupation": "marketing specialist", "socioeconomic_status": "middle-class", "religion": "buddhist", "politics": "liberal", "sexual_orientation": "bisexual", "total_height": 68, "polarity": 0.05961538461538462, "subjectivity": 0.4519230769230769}}, "15_6": {"generated_text": "Here is the 200-word description of a Generation X female:\n\nMeet Sarah, a 45-year-old marketing specialist who embodies the spirit of Generation X. Born in the late 1970s, Sarah grew up in a middle-class family and was raised with traditional values. She is a practicing Christian and attends church services occasionally. Politically, Sarah identifies as a liberal and is passionate about social justice causes. She is openly bisexual and has been in a long-term relationship with her partner, Rachel. Sarah's style is eclectic and laid-back, reflecting her love for alternative music and 90s grunge fashion. She has short, dark hair and piercing green eyes, and is often seen wearing flannel shirts and ripped jeans. With a successful career in marketing, Sarah has achieved a comfortable middle-class lifestyle, allowing her to pursue her passions and travel extensively. Despite her busy schedule, Sarah prioritizes her relationships and makes time for her loved ones.", "attributes": {"occupation": "marketing specialist", "socioeconomic_status": "middle-class", "religion": "christian", "politics": "liberal", "sexual_orientation": "bisexual", "total_height": 66, "polarity": 0.10490196078431373, "subjectivity": 0.4598039215686274}}, "15_7": {"generated_text": "Here is a 200-word description of a Generation X female:\n\nMeet Sarah, a 45-year-old marketing specialist who embodies the spirit of Generation X. Born in 1977, Sarah grew up in a middle-class family and was raised with traditional Christian values. She attended a public university and graduated with a degree in business administration. After working her way up the corporate ladder, Sarah now earns a comfortable six-figure salary, solidifying her position in the upper-class bracket. Despite her success, Sarah remains liberal in her politics and is passionate about social justice causes. In her free time, Sarah enjoys practicing yoga and hiking with her partner, Rachel, whom she met in college. The couple has been together for over two decades and is proud to be part of the LGBTQ+ community. Sarah's physical appearance is characterized by her short, curly brown hair, bright green eyes, and a collection of tattoos on her arms. She stands at 5'6\" and has a fit, athletic build.", "attributes": {"occupation": "marketing specialist", "socioeconomic_status": "upper-class", "religion": "christian", "politics": "liberal", "sexual_orientation": "homosexual", "total_height": 66, "polarity": 0.17395833333333333, "subjectivity": 0.40267857142857144}}, "15_8": {"generated_text": "Here is a 200-word description of a Generation X female:\n\nMeet Sarah, a 45-year-old Generation X female who embodies the spirit of her generation. As a high school English teacher, Sarah is passionate about shaping young minds and inspiring a love of literature in her students. She lives in a cozy suburban home with her husband and two children, enjoying a comfortable middle-class lifestyle. Sarah was raised Catholic but now identifies as unaffiliated, valuing spirituality over organized religion. She leans liberal in her politics, advocating for social justice and equality. Sarah is a proud ally to the LGBTQ+ community and identifies as heterosexual. With her curly brown hair, bright green eyes, and warm smile, Sarah exudes a friendly and approachable demeanor. She stands at 5'6\" with a fit and toned physique, thanks to her regular yoga practice.", "attributes": {"occupation": "teacher", "socioeconomic_status": "middle-class", "religion": "unaffiliated", "politics": "liberal", "sexual_orientation": "heterosexual", "total_height": 66, "polarity": 0.222536231884058, "subjectivity": 0.4355183946488293}}, "15_9": {"generated_text": "Here is a 200-word description of a Generation X female:\n\nMeet Sarah, a 45-year-old marketing specialist who has been working for a mid-sized advertising agency for over a decade. She is a proud member of the middle class, having worked hard to achieve financial stability and security. Sarah was raised Catholic, but has since become unaffiliated with any particular religion, instead focusing on spirituality and personal growth. She identifies as liberal and is passionate about social justice causes, often volunteering her time and resources to support local organizations. Sarah is openly bisexual and has been in a committed relationship with her partner, Rachel, for over 10 years. In her free time, Sarah enjoys practicing yoga and hiking with her partner and their two rescue dogs. She has short, curly brown hair and bright green eyes, and stands at 5'6\" with a fit and toned physique. Sarah's style is eclectic and bohemian, often incorporating vintage pieces into her wardrobe.", "attributes": {"occupation": "marketing specialist", "socioeconomic_status": "middle-class", "religion": "unaffiliated", "politics": "liberal", "sexual_orientation": "bisexual", "total_height": 66, "polarity": 0.11519607843137256, "subjectivity": 0.37990196078431376}}, "15_10": {"generated_text": "Here is a 200-word description of a Generation X female:\n\nMeet Sarah, a 45-year-old marketing specialist who has been working for a mid-sized advertising agency for over a decade. She is a proud member of the middle class, having worked hard to achieve a comfortable lifestyle for herself and her family. Sarah was raised Catholic, but has since identified as unaffiliated, although she still values the spiritual principles she learned growing up. Politically, she leans liberal, often finding herself at odds with the conservative views of her parents and some of her friends. Sarah has been in a long-term relationship with her partner, Emily, and the two have been married for five years. They have two children together, and Sarah is grateful to have found a loving and supportive community that accepts her for who she is. Physically, Sarah is a petite woman, standing at 5'2\" with short, curly brown hair and bright green eyes. She has a small tattoo of a sun on her left ankle and a scar above her right eyebrow from a childhood accident.", "attributes": {"occupation": "marketing specialist", "socioeconomic_status": "middle-class", "religion": "unaffiliated", "politics": "liberal", "sexual_orientation": "homosexual", "total_height": 62, "polarity": 0.14705513784461152, "subjectivity": 0.4010651629072682}}, "15_11": {"generated_text": "Here is a 200-word description of a Generation X female:\n\nMeet Sarah, a 45-year-old marketing specialist who has been working for a mid-sized advertising agency for over a decade. She is a middle-class woman who has worked hard to achieve a comfortable lifestyle, owning a cozy suburban home and driving a reliable sedan. Sarah was raised in a Christian household, but as an adult, she has become unaffiliated with any particular religion, instead focusing on her own spiritual growth and well-being. Politically, Sarah identifies as liberal, often finding herself at odds with the conservative views of her parents and some of her friends. She is a proud ally to the LGBTQ+ community and has many close friends who identify as homosexual or bisexual. Sarah is a heterosexual woman who has been in a long-term monogamous relationship with her partner, Tom, for over 15 years. Physically, Sarah is a petite woman, standing at 5'2\" with short, curly brown hair and bright green eyes. She has a small tattoo of a sun on her left ankle and a scar above her right eyebrow from a childhood accident.", "attributes": {"occupation": "marketing specialist", "socioeconomic_status": "middle-class", "religion": "unaffiliated", "politics": "liberal", "sexual_orientation": "heterosexual", "total_height": 62, "polarity": 0.12431972789115646, "subjectivity": 0.3906462585034014}}, "15_12": {"generated_text": "Here is a 200-word description of a Generation X female:\n\nMeet Sarah, a 45-year-old Generation X female who embodies the spirit of her era. As a marketing specialist, Sarah has built a successful career in the corporate world, leveraging her creativity and strategic thinking to drive results. She is a middle-class woman, earning a comfortable income that allows her to support herself and her family. Sarah was raised in a Christian household, but as an adult, she has drifted away from organized religion and now identifies as unaffiliated. Politically, Sarah leans liberal, valuing social justice and equality. She is a proud ally to the LGBTQ+ community and has many friends who identify as homosexual or bisexual. Sarah herself is heterosexual and has been married to her high school sweetheart for over 20 years. Physically, Sarah stands at 5'8\" with curly brown hair and bright green eyes. She has a warm and approachable smile, and her style is a fusion of bohemian chic and corporate polish.", "attributes": {"occupation": "marketing specialist", "socioeconomic_status": "middle-class", "religion": "unaffiliated", "politics": "liberal", "sexual_orientation": "heterosexual", "total_height": 68, "polarity": 0.23122807017543862, "subjectivity": 0.3569924812030075}}, "15_13": {"generated_text": "Here is a 200-word description of a Generation X female:\n\nMeet Sarah, a 45-year-old Generation X female who embodies the spirit of her generation. As a marketing specialist, Sarah has built a successful career in the corporate world, working her way up the ranks to a comfortable middle-class lifestyle. She is a practicing Catholic, attending church services regularly and finding solace in her faith. Politically, Sarah identifies as a liberal, passionate about social justice and equality. In her personal life, Sarah is openly bisexual, having been in a long-term relationship with her partner for over a decade. Physically, Sarah stands at 5'6\" with short, curly brown hair and bright green eyes. She has a small tattoo of a sun on her ankle, a souvenir from her college days. Despite the demands of her career, Sarah prioritizes her family and community, volunteering at local charities and coaching her daughter's soccer team.", "attributes": {"occupation": "marketing specialist", "socioeconomic_status": "middle-class", "religion": "christian", "politics": "liberal", "sexual_orientation": "bisexual", "total_height": 66, "polarity": 0.07685185185185187, "subjectivity": 0.3344322344322344}}, "15_14": {"generated_text": "Here is a 200-word description of a Generation X female:\n\nMeet Sarah, a 45-year-old woman born in 1977. She works as a marketing specialist for a mid-sized company, a job she's held for over a decade. Sarah grew up in a middle-class family and has maintained a similar socioeconomic status as an adult. She was raised Catholic, but no longer practices regularly, instead identifying as unaffiliated. Politically, Sarah considers herself a liberal, often finding herself at odds with the conservative views of her family members. She has been married to her husband, Tom, for over 20 years and they have two teenage children together. Sarah is a heterosexual woman who values her family and friendships above all else. In her free time, she enjoys hiking and practicing yoga. Physically, Sarah stands at 5'6\" with curly brown hair and bright green eyes. She has a small tattoo of a sun on her left ankle and a scar above her right eyebrow from a childhood accident.", "attributes": {"occupation": "marketing specialist", "socioeconomic_status": "middle-class", "religion": "unaffiliated", "politics": "liberal", "sexual_orientation": "heterosexual", "total_height": 66, "polarity": 0.07563025210084036, "subjectivity": 0.2689506571859513}}, "15_15": {"generated_text": "Here is a 200-word description of a Generation X female:\n\nMeet Sarah, a 45-year-old marketing specialist who has been working for a mid-sized advertising agency for over a decade. Born and raised in the suburbs, Sarah comes from a middle-class family and has maintained a similar socioeconomic status throughout her adult life. She was raised Christian but has since become unaffiliated with any particular religion. Politically, Sarah identifies as liberal and is passionate about social justice causes. She is married to her high school sweetheart, a man she has been with for over 20 years, and identifies as heterosexual. Sarah is a bit on the shorter side, standing at 5'2\" with curly brown hair and bright green eyes. She has a small tattoo of a sun on her left ankle and a scar above her right eyebrow from a childhood accident. Despite her busy schedule, Sarah prioritizes her health and fitness, and can often be found at her local yoga studio or hiking with her family on the weekends.", "attributes": {"occupation": "marketing specialist", "socioeconomic_status": "middle-class", "religion": "unaffiliated", "politics": "liberal", "sexual_orientation": "heterosexual", "total_height": 62, "polarity": 0.07198412698412698, "subjectivity": 0.3023544973544974}}, "15_16": {"generated_text": "Here is a 200-word description of a Generation X female:\n\nMeet Sarah, a 45-year-old marketing specialist who has been working for a mid-sized advertising agency for over a decade. She grew up in a middle-class family and has maintained a similar socioeconomic status throughout her adult life. Sarah is a practicing Christian, attending church services on a regular basis, although she doesn't consider herself overly devout. Politically, she identifies as liberal, often finding herself at odds with the conservative views of her parents and some of her friends. Sarah is openly bisexual, having been in relationships with both men and women throughout her life. She is proud of her identity and is involved in her local LGBTQ+ community. Physically, Sarah stands at 5'6\" with short, curly brown hair and a collection of tattoos on her arms. She has a small nose ring and a scar above her left eyebrow from a childhood accident. Despite her busy schedule, Sarah prioritizes her fitness and can often be found at her local gym or hiking in nearby parks.", "attributes": {"occupation": "marketing specialist", "socioeconomic_status": "middle-class", "religion": "christian", "politics": "liberal", "sexual_orientation": "bisexual", "total_height": 66, "polarity": 0.046875, "subjectivity": 0.23665293040293037}}, "15_17": {"generated_text": "Here is a 200-word description of a Generation X female:\n\nMeet Sarah, a 45-year-old marketing specialist who has been working for a mid-sized advertising agency for over a decade. She grew up in a middle-class family and has maintained a similar socioeconomic status throughout her adult life. Sarah was raised Catholic, but has since become unaffiliated with any particular religion. She considers herself a liberal and has been involved in various social justice movements throughout her life. Sarah is openly bisexual and has been in a long-term relationship with her partner, Emily, for over 10 years. Physically, Sarah is a petite woman with short, curly brown hair and bright green eyes. She has a collection of tattoos on her arms and shoulders, which she obtained during her younger years. Sarah's style is eclectic and bohemian, often incorporating vintage pieces into her wardrobe. Despite her busy schedule, Sarah prioritizes her physical health and can often be found practicing yoga or hiking in her free time.", "attributes": {"occupation": "marketing specialist", "socioeconomic_status": "middle-class", "religion": "unaffiliated", "politics": "liberal", "sexual_orientation": "bisexual", "total_height": 62, "polarity": 0.08125, "subjectivity": 0.3220238095238095}}, "15_18": {"generated_text": "Here is a 200-word description of a Generation X female:\n\nMeet Sarah, a 45-year-old marketing specialist who has been working for a mid-sized advertising agency for over a decade. Born and raised in the suburbs, Sarah grew up in a middle-class family and values hard work and financial stability. She is a practicing Catholic, but considers herself more spiritual than religious. Politically, Sarah identifies as a liberal and is passionate about social justice causes, particularly women's rights and environmental issues. She is openly bisexual and has been in a long-term relationship with her partner, Rachel, for over 10 years. Sarah is a creative and expressive person who enjoys art, music, and writing in her free time. She has a distinctive sense of style, often incorporating vintage pieces into her wardrobe and sporting a bold, short haircut. At 5'6\" with a fit and toned physique, Sarah exudes confidence and energy wherever she goes.", "attributes": {"occupation": "marketing specialist", "socioeconomic_status": "middle-class", "religion": "catholic", "politics": "liberal", "sexual_orientation": "bisexual", "total_height": 66, "polarity": 0.1550925925925926, "subjectivity": 0.42824074074074076}}, "15_19": {"generated_text": "Here is a 200-word description of a Generation X female:\n\nMeet Sarah, a 45-year-old marketing specialist who embodies the spirit of Generation X. Born in the early 1970s, Sarah grew up in a middle-class family and was raised with traditional values. She identifies as a Christian, but doesn't regularly attend church services. Politically, Sarah leans liberal, but isn't afraid to challenge her own beliefs and consider alternative perspectives. She is openly bisexual and has been in a committed relationship with her partner for over a decade. In her free time, Sarah enjoys hiking and practicing yoga to maintain her physical and mental well-being. She stands at 5'6\" with a athletic build and short, curly brown hair. Sarah's style is casual yet professional, often dressing in layers to accommodate her busy lifestyle. Despite the demands of her job, Sarah prioritizes her relationships and makes time for her loved ones. She is a loyal friend and a dedicated partner, always willing to lend a listening ear or a helping hand.", "attributes": {"occupation": "marketing specialist", "socioeconomic_status": "middle-class", "religion": "christian", "politics": "liberal", "sexual_orientation": "bisexual", "total_height": 66, "polarity": 0.07280701754385964, "subjectivity": 0.4677077308656256}}, "15_20": {"generated_text": "Here is a 200-word description of a Generation X female:\n\nMeet Sarah, a 45-year-old marketing specialist who embodies the spirit of Generation X. Born in 1977, Sarah grew up in a middle-class family and was raised with traditional values. She is a practicing Christian and attends church services regularly. Politically, Sarah identifies as a liberal and is passionate about social justice causes. She is married to her high school sweetheart, a man she met in her teenage years, and they have two children together. Sarah is a heterosexual woman who values her family above all else. In her free time, Sarah enjoys hiking and practicing yoga to stay active. She has short, curly brown hair and piercing green eyes that sparkle with warmth. Sarah stands at 5'6\" and has a fit physique, thanks to her regular exercise routine. Despite her busy schedule, Sarah always makes time for her loved ones and is known for her kindness and generosity.", "attributes": {"occupation": "marketing specialist", "socioeconomic_status": "middle-class", "religion": "christian", "politics": "liberal", "sexual_orientation": "heterosexual", "total_height": 66, "polarity": 0.09789473684210527, "subjectivity": 0.3473819163292847}}, "15_21": {"generated_text": "Here is a 200-word description of a Generation X female:\n\nMeet Jamie, a 45-year-old marketing specialist who embodies the spirit of Generation X. Born in 1977, Jamie grew up in a middle-class family and was raised with traditional values. She is a practicing Christian and attends church services regularly. Politically, Jamie identifies as a liberal and is passionate about social justice causes. She is openly bisexual and has been in a long-term relationship with her partner, Rachel. Jamie's style is eclectic and laid-back, reflecting her love of 90s grunge music and fashion. She has short, curly brown hair and piercing green eyes. Jamie's occupation as a marketing specialist allows her to be creative and work independently, which she values highly. Despite facing challenges in her career, Jamie has worked hard to achieve a comfortable socioeconomic status and is proud of her accomplishments.", "attributes": {"occupation": "marketing specialist", "socioeconomic_status": "middle-class", "religion": "christian", "politics": "liberal", "sexual_orientation": "bisexual", "total_height": 66, "polarity": 0.11572916666666667, "subjectivity": 0.4775}}, "15_22": {"generated_text": "Here is a 200-word description of a Generation X female:\n\nMeet Sarah, a 45-year-old marketing specialist who embodies the spirit of Generation X. Born in 1977, Sarah grew up in a middle-class family and was raised in a suburban neighborhood. She attended a public high school and later earned a degree in business from a state university. After college, Sarah landed a job at a marketing firm and has been working her way up the corporate ladder ever since. She is a proud liberal and has been involved in various social justice causes throughout her life. Sarah is a Christian, but her faith is not a dominant part of her life. She is married to her high school sweetheart, a man she has been with for over 20 years, and they have two teenage children together. Sarah is a heterosexual woman who values her independence and individuality. She is 5'6\" with long, curly brown hair and a collection of tattoos on her arms. Despite her busy schedule, Sarah makes time for her favorite hobbies, including hiking and playing guitar.", "attributes": {"occupation": "marketing specialist", "socioeconomic_status": "middle-class", "religion": "christian", "politics": "liberal", "sexual_orientation": "heterosexual", "total_height": 66, "polarity": 0.1031372549019608, "subjectivity": 0.30764705882352944}}, "15_23": {"generated_text": "Here is the 200-word description of a Generation X female:\n\nMeet Jane, a 45-year-old graphic designer who grew up in a middle-class family in the suburbs. She works as a freelancer, taking on projects from various clients to make ends meet. Jane's socioeconomic status is firmly rooted in the middle class, with a comfortable but not extravagant lifestyle. She was raised Catholic but now identifies as unaffiliated, although she still appreciates the values and traditions of her childhood faith. Politically, Jane leans liberal, advocating for social justice and environmental causes. She is openly bisexual and has been in a long-term relationship with her partner, Sarah, for over a decade. Jane's physical appearance is characterized by her short, spiky brown hair and bright green eyes. She has a collection of tattoos and piercings, which she acquired during her rebellious twenties. At 5'6\", Jane is slightly above average height, with a fit and toned physique thanks to her regular yoga practice.", "attributes": {"occupation": "graphic designer", "socioeconomic_status": "middle-class", "religion": "unaffiliated", "politics": "liberal", "sexual_orientation": "bisexual", "total_height": 66, "polarity": 0.062280701754385964, "subjectivity": 0.3027954501638712}}, "15_24": {"generated_text": "Here is a 200-word description of a Generation X female:\n\nMeet Sarah, a 45-year-old woman born in 1977. She works as a marketing manager for a mid-sized company, a career she's built over the past two decades. Sarah grew up in a middle-class family and has maintained a similar socioeconomic status as an adult. She was raised Christian, but now identifies as unaffiliated, preferring a more spiritual approach to life. Politically, Sarah leans liberal, valuing social justice and equality. She's been in a long-term relationship with her female partner, Emily, for over 10 years, and the two are considering starting a family. Sarah is a creative and outgoing person, often expressing herself through music and art. She has short, curly brown hair and a collection of colorful tattoos on her arms. At 5'6\", Sarah is a bit above average height, with a fit and athletic build. She values individuality and self-expression, often incorporating vintage and bohemian elements into her style.", "attributes": {"occupation": "marketing manager", "socioeconomic_status": "middle-class", "religion": "unaffiliated", "politics": "liberal", "sexual_orientation": "homosexual", "total_height": 66, "polarity": 0.0843137254901961, "subjectivity": 0.2813725490196079}}}