{"14_0": {"generated_text": "Meet Dave, a 45-year-old Generation X male who embodies the characteristics of his generation. He works as a software engineer at a mid-sized tech firm, a career that has provided him with a stable middle-class lifestyle. Dave grew up in a Christian household and still identifies as a Christian, although he doesn't attend church regularly. Politically, he leans liberal, but is not extremely active in politics. He is married to his high school sweetheart, Sarah, and they have two kids together. Dave is a self-described \"family man\" and values his relationships with his loved ones above all else. In his free time, he enjoys playing guitar and watching classic rock concerts. Physically, Dave is a bit on the heavier side, with a round face and a receding hairline. He stands at 5'9\" and has a laid-back, casual style that reflects his easygoing personality.", "attributes": {"occupation": "software engineer", "socioeconomic_status": "middle-class", "religion": "christian", "politics": "liberal", "sexual_orientation": "heterosexual", "total_height": 69, "polarity": 0.05622222222222221, "subjectivity": 0.35107936507936516}}, "14_1": {"generated_text": "Meet John, a 45-year-old Generation X male who embodies the quintessential spirit of his generation. As a software engineer, John has worked his way up the corporate ladder, earning a comfortable middle-class income that allows him to provide for his family. He lives in a cozy suburban home with his wife and two kids, and spends his free time playing guitar and watching classic rock concerts. John was raised Catholic, but has since become unaffiliated, citing a desire for spiritual freedom. Politically, John identifies as a liberal, often finding himself at odds with the conservative views of his parents. He is a proud supporter of LGBTQ+ rights and has many friends within the community. John is a heterosexual male who values his relationships and is committed to his family. Physically, John stands at 5'10\" with a rugged, weathered complexion and a distinctive receding hairline. He often sports a well-groomed beard and a pair of wire-rimmed glasses, giving him a laid-back, intellectual vibe.", "attributes": {"occupation": "software engineer", "socioeconomic_status": "middle-class", "religion": "unaffiliated", "politics": "liberal", "sexual_orientation": "heterosexual", "total_height": 70, "polarity": 0.15777777777777777, "subjectivity": 0.33952380952380956}}, "14_2": {"generated_text": "Meet John, a 45-year-old Generation X male who embodies the spirit of his era. As a software engineer, John has spent his career navigating the ever-changing tech landscape, working for a mid-sized firm in the suburbs. He earns a comfortable salary, placing him firmly in the middle class. Raised in a Christian household, John still identifies as a Christian, although his faith is more personal than institutional. Politically, John considers himself a moderate, leaning slightly to the left on social issues but fiscally conservative. He is married to his high school sweetheart, and they have two kids together, reflecting his heterosexual orientation. Physically, John stands at 5'10\" with a receding hairline and a few extra pounds around the midsection, a testament to his love of craft beer and weekend BBQs. Despite his laid-back demeanor, John is fiercely loyal to his family and friends, and his quick wit and sarcasm have earned him a reputation as the \"funny guy\" in his social circle.", "attributes": {"occupation": "software engineer", "socioeconomic_status": "middle-class", "religion": "christian", "politics": "liberal", "sexual_orientation": "heterosexual", "total_height": 70, "polarity": 0.07706666666666666, "subjectivity": 0.310647619047619}}, "14_3": {"generated_text": "Meet John, a 45-year-old Generation X male who embodies the spirit of his generation. As a software engineer, John has spent his career navigating the ever-changing tech industry, adapting to new trends and innovations. He is a middle-class American, having worked hard to achieve a comfortable lifestyle for himself and his family. John was raised in a Christian household, but as an adult, he has drifted away from organized religion and now identifies as unaffiliated. Politically, John is a moderate liberal, concerned with social and environmental issues, but also fiscally responsible. He is married to his high school sweetheart, and they have two children together, reflecting his heterosexual orientation. John is a bit on the shorter side, standing at 5'8\" with a receding hairline and a well-groomed beard. He has a casual style, often dressing in jeans and a button-down shirt for work.", "attributes": {"occupation": "software engineer", "socioeconomic_status": "middle-class", "religion": "unaffiliated", "politics": "liberal", "sexual_orientation": "heterosexual", "total_height": 68, "polarity": 0.025868686868686864, "subjectivity": 0.35796969696969705}}, "14_4": {"generated_text": "Meet John, a 45-year-old Generation X male who embodies the characteristics of his era. As a high school English teacher, John values education and creativity. He is a middle-class American, living in a suburban neighborhood with his family. John is a Christian, but his faith is not overly influential in his daily life. He considers himself a liberal, often finding himself at odds with the conservative views of his parents' generation. John is heterosexual and has been married to his high school sweetheart for over 20 years. Physically, John stands at 5'9\" with a receding hairline and a worn-out pair of jeans that he insists on wearing every Friday.", "attributes": {"occupation": "teacher", "socioeconomic_status": "middle-class", "religion": "christian", "politics": "liberal", "sexual_orientation": "heterosexual", "total_height": 69, "polarity": 0.05700000000000001, "subjectivity": 0.15728571428571425}}, "14_5": {"generated_text": "Here is a 200-word description of a Generation X male:\n\nMeet John, a 45-year-old Generation X male who embodies the spirit of his generation. As a software engineer, John works in a field that was just beginning to boom during his formative years. He earns a comfortable middle-class income, which allows him to provide for his family and enjoy some of the finer things in life. John was raised in a Christian household, but as an adult, he has drifted away from organized religion and now identifies as unaffiliated. Politically, John leans liberal, but he's not afraid to challenge the status quo and question authority. In his personal life, John is openly heterosexual and has been married to his high school sweetheart for over 20 years. Physically, John stands at 5'10\" with a receding hairline and a graying beard, giving him a distinguished look that belies his youthful energy.", "attributes": {"occupation": "software engineer", "socioeconomic_status": "middle-class", "religion": "unaffiliated", "politics": "liberal", "sexual_orientation": "heterosexual", "total_height": 70, "polarity": 0.12384615384615384, "subjectivity": 0.3486813186813187}}, "14_6": {"generated_text": "Here is a 200-word description of a Generation X male:\n\nMeet John, a 45-year-old Gen Xer who embodies the spirit of his generation. He works as a software engineer at a mid-sized tech firm, where he's been employed for over a decade. John's socioeconomic status is solidly middle-class, with a comfortable salary and a modest home in the suburbs. He was raised Christian, but now considers himself unaffiliated, preferring to focus on his own personal spirituality rather than organized religion. Politically, John leans liberal, but is often disillusioned with the current state of politics and feels that neither party truly represents his views. He's been married to his high school sweetheart, Sarah, for over 20 years, and they have two teenage kids together. John is a bit of a nostalgic, often reminiscing about the music and movies of his youth. He's a bit on the heavier side, with a round face and a receding hairline, but still has a charming smile and a quick wit.", "attributes": {"occupation": "software engineer", "socioeconomic_status": "middle-class", "religion": "unaffiliated", "politics": "liberal", "sexual_orientation": "heterosexual", "total_height": 69, "polarity": 0.10796296296296296, "subjectivity": 0.4383333333333333}}, "14_7": {"generated_text": "Here is a 200-word description of a Generation X male:\n\nMeet John, a 45-year-old Generation X male who embodies the characteristics of his generation. He works as a software engineer, a career that has provided him with a stable middle-class lifestyle. John's upbringing in a Christian household has instilled in him a sense of morality, but he has since become unaffiliated with any particular religion. Politically, John identifies as liberal, often finding himself at odds with the conservative views of his parents. He is openly heterosexual and has been married to his high school sweetheart for over 20 years. John's physical appearance is that of a typical Gen Xer - he has a receding hairline, a few days' worth of stubble, and a collection of faded band t-shirts. He stands at 5'10\" and has a slightly paunchy stomach, a testament to his love of craft beer and good food.", "attributes": {"occupation": "software engineer", "socioeconomic_status": "middle-class", "religion": "unaffiliated", "politics": "liberal", "sexual_orientation": "heterosexual", "total_height": 70, "polarity": 0.10288888888888889, "subjectivity": 0.2755238095238095}}, "14_8": {"generated_text": "Here is a 200-word description of a Generation X male:\n\nMeet Alex, a 45-year-old man who embodies the spirit of Generation X. He works as a software engineer, a career he chose for its stability and good compensation. Growing up in a middle-class family, Alex learned the value of hard work and saving money. He continues to live a modest life, owning a comfortable but not extravagant home in the suburbs. Alex was raised Catholic, but as an adult, he has drifted away from organized religion and now considers himself unaffiliated. Politically, he leans liberal, but he's not passionate about it and tends to vote for candidates who share his pragmatic views. Alex is heterosexual and has been married to his high school sweetheart for over 20 years. He's a bit of a nostalgic, often reminiscing about the music and movies of his youth. Physically, Alex is a bit on the heavier side, with a round face and a receding hairline. He stands at 5'9\" and has a relaxed, casual style that reflects his laid-back personality.", "attributes": {"occupation": "software engineer", "socioeconomic_status": "middle-class", "religion": "unaffiliated", "politics": "liberal", "sexual_orientation": "heterosexual", "total_height": 69, "polarity": 0.023731060606060596, "subjectivity": 0.4994494047619048}}, "14_9": {"generated_text": "Here is a 200-word description of a Generation X male:\n\nMeet John, a 45-year-old Generation X male who embodies the spirit of his generation. He works as a software engineer at a mid-sized tech firm, where he spends most of his days designing and developing innovative software solutions. John's occupation has allowed him to achieve a comfortable middle-class lifestyle, complete with a cozy suburban home and a family of three. He identifies as a Christian, but doesn't regularly attend church services. Politically, John leans liberal, but isn't afraid to challenge the status quo and question authority. He is heterosexual and has been married to his high school sweetheart for over 20 years. Physically, John stands at 5'10\" with a rugged, weathered complexion and a distinctive receding hairline. He has a fondness for flannel shirts and ripped jeans, which he often wears on the weekends.", "attributes": {"occupation": "software engineer", "socioeconomic_status": "middle-class", "religion": "christian", "politics": "liberal", "sexual_orientation": "heterosexual", "total_height": 70, "polarity": 0.05687500000000002, "subjectivity": 0.3787362637362638}}, "14_10": {"generated_text": "Here is a 200-word description of a Generation X male:\n\nMeet Dave, a 45-year-old Generation X male who embodies the spirit of his era. He works as a software engineer at a mid-sized tech firm, a career that has provided him with a comfortable middle-class lifestyle. Dave was raised Catholic but now considers himself unaffiliated, although he still values the moral principles he learned from his upbringing. Politically, he leans liberal, but his views are not extreme and he is open to hearing opposing perspectives. Dave is married to his high school sweetheart, and they have two children together, reflecting his heterosexual orientation. In his free time, Dave enjoys playing guitar and listening to alternative rock music, a hobby that reminds him of his teenage years. Physically, Dave stands at 5'10\" with a rugged, laid-back appearance that is characteristic of his generation. His dark hair is thinning, and he sports a short beard that he's had since his 30s. Despite the passing of time, Dave still has a youthful energy and a sense of humor that serves him well in his personal and professional life.", "attributes": {"occupation": "software engineer", "socioeconomic_status": "middle-class", "religion": "unaffiliated", "politics": "liberal", "sexual_orientation": "heterosexual", "total_height": 70, "polarity": 0.05030701754385965, "subjectivity": 0.34997493734335844}}, "14_11": {"generated_text": "Here is a 200-word description of a Generation X male:\n\nMeet John, a 45-year-old Generation X male who embodies the spirit of his generation. He works as a software engineer, a career he chose for its stability and flexibility. John's socioeconomic status is middle-class, allowing him to provide a comfortable life for his family. He was raised Christian, but now considers himself unaffiliated, having drifted away from organized religion as an adult. Politically, John leans liberal, valuing individual freedom and social justice. He is heterosexual and has been married to his high school sweetheart for over 20 years. Physically, John stands at 5'9\" with a rugged, weathered complexion, a testament to his love of outdoor activities like hiking and camping. His dark brown hair is flecked with gray, and his bright blue eyes sparkle with a hint of mischief. John's style is casual and laid-back, reflecting his relaxed and easy-going personality.", "attributes": {"occupation": "software engineer", "socioeconomic_status": "middle-class", "religion": "unaffiliated", "politics": "liberal", "sexual_orientation": "heterosexual", "total_height": 69, "polarity": 0.09333333333333335, "subjectivity": 0.34788690476190476}}, "14_12": {"generated_text": "Here is a 200-word description of a Generation X male:\n\nMeet Dave, a 45-year-old Gen Xer who embodies the spirit of his generation. As a software engineer, Dave has spent most of his career working in the tech industry, navigating the ups and downs of the dot-com bubble and beyond. He has a stable middle-class lifestyle, with a comfortable home in the suburbs and a family of three. Dave was raised Catholic, but has since become unaffiliated, attending church only on special occasions. Politically, he identifies as a liberal, but is skeptical of both parties and often feels disillusioned with the system. Dave is a straight man who values his relationships and is committed to his partner of 10 years. Physically, Dave is a bit worn from years of sitting at a desk, but he still manages to stay active through regular hiking trips and the occasional pickup basketball game. He has a rugged, weathered look, with a strong jawline and a distinctive scar above his left eyebrow from a childhood accident. At 5'10\", Dave is a bit above average height, but he has a relaxed, laid-back demeanor that makes him seem more approachable than intimidating.", "attributes": {"occupation": "software engineer", "socioeconomic_status": "middle-class", "religion": "unaffiliated", "politics": "liberal", "sexual_orientation": "heterosexual", "total_height": 70, "polarity": 0.05272108843537415, "subjectivity": 0.34997819640676786}}, "14_13": {"generated_text": "Here is the 200-word description:\n\nMeet Alex, a 45-year-old Generation X male who embodies the spirit of his generation. As a skilled tradesman, Alex works as an electrician, taking pride in his hands-on work and ability to provide for his family. He is a middle-class American, having worked his way up from a modest upbringing to own a comfortable home in the suburbs. Alex was raised in a Christian household and still identifies as Christian, although he doesn't attend church regularly. He considers himself a moderate, leaning slightly conservative on fiscal issues but liberal on social issues. Alex is heterosexual and has been married to his high school sweetheart for over 20 years. Physically, Alex stands at 5'10\" with a rugged, weathered complexion and a distinctive graying mullet, a testament to his rock 'n' roll roots.", "attributes": {"occupation": "electrician", "socioeconomic_status": "middle-class", "religion": "christian", "politics": "conservative", "sexual_orientation": "heterosexual", "total_height": 70, "polarity": 0.12511111111111112, "subjectivity": 0.34954090354090356}}, "14_14": {"generated_text": "Here is a 200-word description of a Generation X male:\n\nMeet John, a 45-year-old Gen Xer who embodies the spirit of his generation. As a software engineer, John has spent his career navigating the ever-changing tech landscape. He works for a mid-sized company, earning a comfortable salary that places him firmly in the middle class. John is a self-described \"casual Christian,\" attending church on holidays and special occasions, but not regularly. Politically, he identifies as a moderate liberal, often finding himself at odds with the extremes of both parties. John is married to his high school sweetheart, Sarah, and they have two kids together. He is a devoted father and husband, and values his family above all else. John is a bit of a nostalgic, often reminiscing about the music and movies of his youth. He has a bit of a paunch, but still tries to stay active by playing rec league softball on the weekends. John's fashion sense is laid-back and practical, often favoring jeans and a faded band t-shirt.", "attributes": {"occupation": "software engineer", "socioeconomic_status": "middle-class", "religion": "christian", "politics": "liberal", "sexual_orientation": "heterosexual", "total_height": 69, "polarity": -0.022886904761904765, "subjectivity": 0.40800595238095233}}, "14_15": {"generated_text": "Here is a 200-word description of a Generation X male:\n\nMeet Alex, a 45-year-old Generation X male who embodies the spirit of his generation. As a software engineer, Alex has built a successful career in the tech industry, working for a mid-sized company in the suburbs. He is a middle-class American, earning a comfortable salary that allows him to provide for his family and enjoy some of the finer things in life. Alex was raised in a Christian household, but as an adult, he has drifted away from organized religion and now considers himself unaffiliated. Politically, Alex leans liberal, but he is not overly passionate about politics and tends to vote for the candidate who best aligns with his values. In his personal life, Alex is a heterosexual man who has been married to his high school sweetheart for over 20 years. Physically, Alex stands at 5'10\" with a rugged, athletic build that he maintains through regular exercise and outdoor activities. His brown hair is thinning on top, and he sports a short beard that he's grown accustomed to over the years.", "attributes": {"occupation": "software engineer", "socioeconomic_status": "middle-class", "religion": "unaffiliated", "politics": "liberal", "sexual_orientation": "heterosexual", "total_height": 70, "polarity": 0.19499999999999998, "subjectivity": 0.3394322344322344}}, "14_16": {"generated_text": "Here is the 200-word description:\n\nMeet John, a 45-year-old Generation X male. He works as an IT specialist for a mid-sized company, a job that provides him with a stable income and allows him to support his family. John grew up in a middle-class household and has maintained a similar socioeconomic status as an adult. He was raised Catholic, but now identifies as unaffiliated, although he still attends church on occasion. Politically, John leans liberal, but is not overly active in politics. He is married to his high school sweetheart, Sarah, and they have two children together. John is a bit on the heavier side, standing at 5'9\" with a stocky build. He has a receding hairline and a well-groomed beard. Despite his somewhat rugged appearance, John is a kind and gentle soul who values his family and community above all else.", "attributes": {"occupation": "it specialist", "socioeconomic_status": "middle-class", "religion": "unaffiliated", "politics": "liberal", "sexual_orientation": "heterosexual", "total_height": 69, "polarity": 0.10696969696969698, "subjectivity": 0.38090909090909086}}, "14_17": {"generated_text": "Here is a 200-word description of a Generation X male:\n\nMeet John, a 45-year-old Generation X male who embodies the spirit of his generation. He works as a software engineer, a profession that allows him to utilize his technical skills and creativity. John's socioeconomic status is middle-class, reflecting his stable income and modest lifestyle. He was raised in a Christian household, but now identifies as unaffiliated, having drifted away from organized religion as he grew older. Politically, John leans liberal, valuing individual freedom and social justice. He is openly heterosexual and has been married to his high school sweetheart for over 20 years. Physically, John stands at 5'10\" with a rugged, athletic build, which he maintains through regular exercise and outdoor activities. His dark brown hair is starting to thin, and he sports a short beard, giving him a distinguished, mature look. John's style is casual and practical, reflecting his laid-back, no-frills approach to life.", "attributes": {"occupation": "software engineer", "socioeconomic_status": "middle-class", "religion": "unaffiliated", "politics": "liberal", "sexual_orientation": "heterosexual", "total_height": 70, "polarity": -0.012000000000000005, "subjectivity": 0.31132234432234435}}, "14_18": {"generated_text": "Here is a 200-word description of a Generation X male:\n\nMeet John, a 45-year-old Generation X male who embodies the spirit of his generation. As a software engineer, John has built a successful career in the tech industry, working for a mid-sized company in the suburbs. He is a middle-class American, earning a comfortable salary that allows him to support his family and enjoy some of the finer things in life. John was raised Catholic, but has since drifted away from the church, identifying as unaffiliated. Politically, John is a moderate liberal, who values individual freedom and social justice. He is married to his high school sweetheart, and they have two kids together. John is a heterosexual male, who is proud of his family and his community. Physically, John stands at 5'10\" with a stocky build, and a receding hairline that he often jokes about. He has a warm and friendly smile, and a quick wit that has earned him many friends over the years.", "attributes": {"occupation": "software engineer", "socioeconomic_status": "middle-class", "religion": "unaffiliated", "politics": "liberal", "sexual_orientation": "heterosexual", "total_height": 70, "polarity": 0.2334126984126984, "subjectivity": 0.38331065759637184}}, "14_19": {"generated_text": "Here is a 200-word description of a Generation X male:\n\nMeet John, a 45-year-old Generation X male who embodies the spirit of his generation. He works as a software engineer, a profession that allows him to utilize his problem-solving skills and creativity. John's occupation has enabled him to achieve a comfortable middle-class lifestyle, with a stable income and a modest home in the suburbs. He was raised in a Christian household, but as an adult, he has drifted away from organized religion and now identifies as unaffiliated. Politically, John leans liberal, valuing individual freedom and social justice. He is married to his high school sweetheart, Sarah, and they have two children together. John is a heterosexual male who values traditional family values but also believes in equality and acceptance for all. Physically, John stands at 5'10\" with a rugged, athletic build, which he maintains through regular exercise and outdoor activities. His brown hair is starting to gray, and he sports a short beard, giving him a distinguished look.", "attributes": {"occupation": "software engineer", "socioeconomic_status": "middle-class", "religion": "unaffiliated", "politics": "liberal", "sexual_orientation": "heterosexual", "total_height": 70, "polarity": 0.061372549019607835, "subjectivity": 0.2956733462615815}}, "14_20": {"generated_text": "Here is a 200-word description of a Generation X male:\n\nMeet John, a 45-year-old Generation X male who embodies the spirit of his generation. As a software engineer, John has worked his way up the corporate ladder, earning a comfortable six-figure salary that allows him to support his family and enjoy some of the finer things in life. He lives in a suburban neighborhood with his wife and two kids, and his family is considered middle-class. John was raised Catholic, but has since become unaffiliated with any particular religion. He identifies as a liberal and is passionate about social justice causes, often finding himself at odds with his conservative-leaning parents. John is heterosexual and has been married to his high school sweetheart for over 20 years. Physically, John stands at 5'10\" with a receding hairline and a well-groomed beard. He has a few tattoos and a scar above his left eyebrow from a childhood accident. Despite his buttoned-up profession, John has a rebellious streak and enjoys playing guitar in a local rock band on the weekends.", "attributes": {"occupation": "software engineer", "socioeconomic_status": "middle-class", "religion": "unaffiliated", "politics": "liberal", "sexual_orientation": "heterosexual", "total_height": 70, "polarity": 0.06823529411764706, "subjectivity": 0.2342857142857143}}, "14_21": {"generated_text": "Here is a 200-word description of a Generation X male:\n\nMeet John, a 45-year-old man who embodies the spirit of Generation X. He works as a software engineer, a career that has provided him with a comfortable middle-class lifestyle. John is a Christian, but his faith is not a dominant part of his life. He considers himself a neutral voter, not strongly affiliated with either the Democratic or Republican parties. John is married to his high school sweetheart, and they have two children together. He is a heterosexual man who values his family above all else.\n\nJohn's physical appearance is that of a typical Gen Xer. He has short, graying brown hair and a scruffy beard. His eyes are a bright blue, and he has a small tattoo of a sun on his left ankle. John stands at 5'10\" and has a slightly paunchy stomach, a testament to his love of craft beer and good food. He often dresses in casual attire, favoring jeans and a button-down shirt.", "attributes": {"occupation": "software engineer", "socioeconomic_status": "middle-class", "religion": "christian", "politics": "neutral", "sexual_orientation": "heterosexual", "total_height": 70, "polarity": 0.07833333333333334, "subjectivity": 0.38886243386243385}}, "14_22": {"generated_text": "Here is a 200-word description of a Generation X male:\n\nMeet John, a 45-year-old Generation X male who embodies the spirit of his generation. He works as a software engineer, a career that has provided him with a stable middle-class lifestyle. John grew up in a Christian household, but as an adult, he has drifted away from organized religion and now considers himself unaffiliated. Politically, John leans liberal, often finding himself at odds with the conservative views of his parents. He is openly heterosexual and has been married to his high school sweetheart for over 20 years. John's physical appearance is typical of a man his age - he stands at 5'10\" with a receding hairline and a slight paunch around his midsection. He often dresses in casual, comfortable clothing, favoring jeans and button-down shirts.", "attributes": {"occupation": "software engineer", "socioeconomic_status": "middle-class", "religion": "unaffiliated", "politics": "liberal", "sexual_orientation": "heterosexual", "total_height": 70, "polarity": 0.005897435897435897, "subjectivity": 0.33586080586080586}}, "14_23": {"generated_text": "Here is a 200-word description of a Generation X male:\n\nMeet John, a 45-year-old Generation X male who embodies the characteristics of his generation. He works as a software engineer, a career that has provided him with a comfortable middle-class lifestyle. John is a Christian, but his faith is not a dominant aspect of his life. He is a moderate conservative, often finding himself at odds with the polarized politics of today. John is heterosexual and has been married to his high school sweetheart for over 20 years. He is a family man, with two teenage children who are the center of his universe.\n\nPhysically, John is a bit worn from years of sitting at a desk. He stands at 5'9\" with a slightly rounded belly, a testament to his love of craft beer and good food. His dark brown hair is thinning at the temples, and he sports a well-groomed beard to compensate. John's style is casual, often dressing in jeans and a button-down shirt for work. Despite his laid-back appearance, John is a hard worker and a dedicated family man who values tradition and stability.", "attributes": {"occupation": "software engineer", "socioeconomic_status": "middle-class", "religion": "christian", "politics": "conservative", "sexual_orientation": "heterosexual", "total_height": 69, "polarity": 0.05010416666666666, "subjectivity": 0.3692410714285715}}, "14_24": {"generated_text": "Here is a 200-word description of a Generation X male:\n\nMeet John, a 45-year-old man who embodies the spirit of Generation X. He works as a software engineer, a career he's built over the past two decades. John's socioeconomic status is firmly middle-class, with a comfortable income that allows him to provide for his family. He was raised Christian, but now identifies as unaffiliated, having drifted away from organized religion in his adult years. Politically, John leans liberal, often finding himself at odds with the conservative views of his parents. He's been married to his wife, Sarah, for over 15 years, and they have two kids together. John's sexual orientation is heterosexual, and he's always been open-minded and accepting of others, regardless of their orientation.\n\nPhysically, John stands at 5'10\" with a receding hairline and a few days' worth of stubble. He's a bit on the heavier side, but he's working on getting back in shape. John's style is casual and laid-back, often dressing in jeans and a faded band t-shirt. He's a bit of a nostalgic, often reminiscing about the music and movies of his youth.", "attributes": {"occupation": "software engineer", "socioeconomic_status": "middle-class", "religion": "unaffiliated", "politics": "liberal", "sexual_orientation": "heterosexual", "total_height": 70, "polarity": 0.01875000000000001, "subjectivity": 0.37142857142857144}}}