{"17_0": {"generated_text": "Meet Emma, a 28-year-old marketing specialist who lives in a trendy neighborhood in a major city. She works for a mid-sized firm, creating social media campaigns for clients in the tech industry. Emma is a middle-class individual, earning a comfortable salary that allows her to enjoy her favorite hobbies, such as yoga and trying out new restaurants. She was raised in a Christian household, but now identifies as unaffiliated, preferring to focus on her own spirituality rather than organized religion. Emma is a liberal voter, passionate about social justice causes and environmental issues. She is openly bisexual and has been in a long-term relationship with her partner, Rachel, for several years. Emma is a petite woman, standing at 5'2\" with a athletic build. She has short, dark hair and piercing green eyes, often accentuated with bold makeup looks. Emma's style is eclectic and bohemian, reflecting her artistic personality and love of self-expression.", "attributes": {"occupation": "marketing specialist", "socioeconomic_status": "middle-class", "religion": "unaffiliated", "politics": "liberal", "sexual_orientation": "bisexual", "total_height": 62, "polarity": 0.15146349862258954, "subjectivity": 0.5092975206611571}}, "17_1": {"generated_text": "Meet Emma, a 28-year-old marketing specialist who lives in a trendy neighborhood in Brooklyn. She works for a mid-sized startup, creating social media campaigns for clients in the fashion industry. Emma is a proud member of the middle class, having grown up in a comfortable suburban home and now earning a decent salary to support her lifestyle. She identifies as a Buddhist, having explored various spiritual practices in her early twenties. Emma is a liberal at heart, passionate about social justice and equality, and often participates in local activism events. She is openly bisexual and has been in a loving relationship with her partner, Rachel, for three years. Emma takes care of her physical health, practicing yoga and hiking on the weekends. She stands at 5'6\" with a fit and toned physique, often dressing in bohemian chic attire that reflects her creative personality.", "attributes": {"occupation": "marketing specialist", "socioeconomic_status": "middle-class", "religion": "buddhist", "politics": "liberal", "sexual_orientation": "bisexual", "total_height": 66, "polarity": 0.19907407407407407, "subjectivity": 0.45978835978835986}}, "17_2": {"generated_text": "Meet Emma, a 28-year-old marketing specialist who works for a non-profit organization in a urban city. She comes from a middle-class family and has a stable income, which allows her to enjoy a comfortable lifestyle. Emma was raised in a Christian household, but she identifies as unaffiliated and considers herself spiritual rather than religious. She is an avid supporter of social justice causes and leans liberal in her political views. Emma is openly bisexual and has been in a long-term relationship with her partner, Rachel. In her free time, Emma enjoys practicing yoga and hiking with her friends. She has a small tattoo of a sun on her ankle and a nose ring, which reflects her eclectic and bohemian style. Emma's physical appearance is characterized by her curly brown hair, bright green eyes, and petite frame. She stands at 5'2\" and has a collection of colorful scarves and statement pieces that add to her unique sense of fashion.", "attributes": {"occupation": "marketing specialist", "socioeconomic_status": "middle-class", "religion": "unaffiliated", "politics": "liberal", "sexual_orientation": "bisexual", "total_height": 62, "polarity": 0.1416666666666667, "subjectivity": 0.42310924369747904}}, "17_3": {"generated_text": "Meet Emma, a 28-year-old marketing specialist who lives in a trendy neighborhood in a major city. She works for a mid-sized tech firm, creating social media campaigns for a living. Emma comes from a middle-class family and has a stable income, which allows her to enjoy a comfortable lifestyle. She identifies as a spiritual person, but doesn't affiliate with any particular religion, having grown up in a non-practicing Christian household. Politically, Emma considers herself a liberal, actively advocating for social justice causes and voting for progressive candidates. She is openly bisexual and has been in a loving relationship with her partner, Rachel, for three years. Emma is a fashion-conscious individual who takes pride in her appearance. She has short, curly brown hair and piercing green eyes. She stands at 5'6\" with a fit and toned physique, which she maintains through regular yoga practice and hiking trips.", "attributes": {"occupation": "marketing specialist", "socioeconomic_status": "middle-class", "religion": "unaffiliated", "politics": "liberal", "sexual_orientation": "bisexual", "total_height": 66, "polarity": 0.11381578947368425, "subjectivity": 0.3856275303643725}}, "17_4": {"generated_text": "Meet Emily, a 28-year-old marketing specialist living in a trendy neighborhood in Brooklyn. She works for a mid-sized advertising agency, where she spends most of her days brainstorming social media campaigns and sipping cold brew coffee. Emily is a proud member of the middle class, having grown up in a comfortable suburban home and now enjoying a decent salary and benefits. She identifies as a Buddhist, having discovered the teachings of mindfulness and meditation in college. Politically, Emily leans liberal, often finding herself passionate about social justice causes and advocating for women's rights. She is openly bisexual and has been in a loving relationship with her girlfriend for three years. Emily stands at 5'6\" with a petite yet athletic build, often dressing in the latest athleisure wear trends. Her long, curly brown hair and bright hazel eyes make her a stunning presence in any room.", "attributes": {"occupation": "marketing specialist", "socioeconomic_status": "middle-class", "religion": "buddhist", "politics": "liberal", "sexual_orientation": "bisexual", "total_height": 66, "polarity": 0.24385964912280703, "subjectivity": 0.5842105263157894}}, "17_5": {"generated_text": "Here is a 200-word description of a Millennial female:\n\nMeet Emma, a 28-year-old marketing specialist who works for a trendy startup in a bustling city. She grew up in a middle-class family and was able to attend a private university, where she studied business and psychology. Emma is a spiritual person who identifies as Buddhist, but doesn't regularly attend temple services. She's a self-described liberal who is passionate about social justice and environmental causes. In her free time, Emma enjoys hiking and practicing yoga. She's been in a long-term relationship with her girlfriend, Rachel, for five years. Emma has a unique sense of style, often mixing bohemian and minimalist pieces. She has curly brown hair and bright green eyes, and stands at around 5'6\" with a collection of colorful tattoos on her arms.", "attributes": {"occupation": "marketing specialist", "socioeconomic_status": "middle-class", "religion": "buddhist", "politics": "liberal", "sexual_orientation": "homosexual", "total_height": 66, "polarity": 0.20448717948717948, "subjectivity": 0.4995069033530572}}, "17_6": {"generated_text": "Here is a 200-word description of a Millennial female:\n\nMeet Emily, a 28-year-old marketing specialist who lives in a trendy neighborhood in a urban city. She works for a mid-sized startup, creating social media campaigns for a living. Emily comes from a middle-class background, with parents who are both college-educated professionals. She was raised in a Christian household, but has since identified as unaffiliated, preferring to focus on her own spiritual journey. Politically, Emily leans liberal, often finding herself at odds with the conservative views of her family members. She is openly bisexual and has been in a long-term relationship with her girlfriend, Rachel, for three years. Emily takes pride in her eclectic style, often mixing vintage pieces with modern trends. She has short, dark hair and piercing green eyes, and stands at 5'6\" with a collection of colorful tattoos on her arms.", "attributes": {"occupation": "marketing specialist", "socioeconomic_status": "middle-class", "religion": "unaffiliated", "politics": "liberal", "sexual_orientation": "bisexual", "total_height": 66, "polarity": 0.09880952380952382, "subjectivity": 0.3261904761904762}}, "17_7": {"generated_text": "Here is a 200-word description of a Millennial female:\n\nMeet Emily, a 28-year-old marketing specialist who lives in a trendy neighborhood in Brooklyn. She works for a mid-sized startup, creating social media campaigns for clients in the fashion industry. Emily's parents were both college-educated professionals, and she grew up in a comfortable middle-class household. She was raised Catholic, but has since identified as unaffiliated, preferring to focus on spirituality rather than organized religion. Emily is a self-described liberal, passionate about social justice and environmental causes. She is openly bisexual and has been in a long-term relationship with her girlfriend, Rachel, for three years. Emily is petite, standing at 5'2\" with a collection of colorful tattoos on her arms and a nose ring. She has curly brown hair and bright green eyes, often dressing in eclectic outfits that showcase her love of vintage fashion.", "attributes": {"occupation": "marketing specialist", "socioeconomic_status": "middle-class", "religion": "unaffiliated", "politics": "liberal", "sexual_orientation": "bisexual", "total_height": 62, "polarity": 0.19305555555555554, "subjectivity": 0.46249999999999997}}, "17_8": {"generated_text": "Here is a 200-word description of a Millennial female:\n\nMeet Emily, a 28-year-old marketing specialist who lives in a trendy neighborhood in Brooklyn. She works for a small startup, creating social media campaigns for eco-friendly brands. Emily comes from a middle-class family and has a comfortable income, which allows her to enjoy her favorite hobbies, such as yoga and trying out new restaurants. She was raised Catholic, but now identifies as unaffiliated, although she still appreciates the spiritual aspects of her upbringing. Emily is a liberal voter and is passionate about social justice causes, particularly feminism and LGBTQ+ rights. She is openly bisexual and has been in a loving relationship with her partner, Rachel, for three years. Emily is petite, standing at 5'2\" with curly brown hair and bright green eyes. She has a collection of tattoos and piercings, which she sees as a form of self-expression. Despite her busy schedule, Emily prioritizes her physical and mental health, and can often be found practicing yoga or meditating in her free time.", "attributes": {"occupation": "marketing specialist", "socioeconomic_status": "middle-class", "religion": "unaffiliated", "politics": "liberal", "sexual_orientation": "bisexual", "total_height": 62, "polarity": 0.15771349862258954, "subjectivity": 0.4665486029122393}}, "17_9": {"generated_text": "Here is a 200-word description of a Millennial female:\n\nMeet Emily, a 28-year-old marketing specialist living in a trendy neighborhood in Brooklyn. She works for a mid-sized startup, creating social media campaigns for a variety of clients. Emily is a middle-class individual, earning a comfortable salary that allows her to enjoy the city's cultural attractions and travel occasionally. She was raised in a Christian household but now identifies as unaffiliated, preferring to focus on spirituality rather than organized religion. Politically, Emily considers herself a liberal, passionate about social justice and environmental causes. She is openly bisexual and has been in a long-term relationship with her girlfriend, a freelance writer. Emily is a petite woman, standing at 5'2\" with short, curly brown hair and bright green eyes. She has a collection of tattoos and piercings, which she obtained during her college days. Emily's style is eclectic and bohemian, often mixing vintage pieces with modern streetwear.", "attributes": {"occupation": "marketing specialist", "socioeconomic_status": "middle-class", "religion": "unaffiliated", "politics": "liberal", "sexual_orientation": "bisexual", "total_height": 62, "polarity": 0.1303921568627451, "subjectivity": 0.36911764705882344}}, "17_10": {"generated_text": "Here is a 200-word description of a Millennial female:\n\nMeet Sarah, a 28-year-old marketing specialist living in a trendy neighborhood in Brooklyn. She works for a small startup, creating social media campaigns for eco-friendly brands. Sarah comes from a middle-class family and has a comfortable lifestyle, but she's not afraid to splurge on the latest wellness trends. She identifies as a Buddhist, but doesn't practice regularly, and considers herself spiritual rather than religious. Politically, Sarah leans liberal and is passionate about social justice causes, often attending rallies and donating to progressive organizations. She's been in a long-term relationship with her girlfriend, Rachel, for five years, and the two are considering starting a family soon. Sarah has a petite build, standing at 5'2\" with a collection of colorful tattoos on her arms. Her curly brown hair is often styled in a messy bob, and she favors statement pieces of jewelry that reflect her quirky personality.", "attributes": {"occupation": "marketing specialist", "socioeconomic_status": "middle-class", "religion": "buddhist", "politics": "liberal", "sexual_orientation": "homosexual", "total_height": 62, "polarity": 0.09803921568627451, "subjectivity": 0.44177978883861235}}, "17_11": {"generated_text": "Here is a 200-word description of a Millennial female:\n\nMeet Emily, a 28-year-old marketing specialist who lives in a trendy neighborhood in a major city. She works for a mid-sized startup, where she earns a comfortable salary that allows her to enjoy her favorite hobbies, such as yoga and trying out new restaurants. Emily grew up in a middle-class family and values her independence, often prioritizing her career and personal growth over traditional expectations. She was raised Catholic but no longer practices, instead identifying as spiritually unaffiliated. Emily is an avid follower of social justice causes and identifies as a liberal, often participating in local activism and volunteering for progressive organizations. In her free time, Emily enjoys attending music festivals and trying out new craft beers with her friends, who are a diverse and eclectic group. Emily is openly bisexual and has been in a loving relationship with her partner, Rachel, for several years. Physically, Emily stands at 5'6\" with a petite yet athletic build, often dressing in the latest fashion trends and sporting a bold, eclectic sense of style.", "attributes": {"occupation": "marketing specialist", "socioeconomic_status": "middle-class", "religion": "unaffiliated", "politics": "liberal", "sexual_orientation": "bisexual", "total_height": 66, "polarity": 0.1892127799736495, "subjectivity": 0.5037078863165819}}, "17_12": {"generated_text": "Here is a 200-word description of a Millennial female:\n\nMeet Emily, a 28-year-old marketing specialist who lives in a trendy neighborhood in a urban city. She works for a mid-sized startup, creating social media campaigns for clients in the tech industry. Emily is a middle-class individual, having grown up in a suburban household with two working parents. She identifies as a Buddhist, having explored various spiritual practices in her early twenties. Politically, Emily considers herself a liberal, actively advocating for social justice causes and environmental sustainability. She is openly bisexual and has been in a long-term relationship with her partner, Rachel. Emily is a creative and expressive person, often showcasing her style through bold fashion choices and vibrant hairstyles. She stands at 5'6\" with a petite yet athletic build, often wearing bright colors and statement pieces that reflect her eclectic personality.", "attributes": {"occupation": "marketing specialist", "socioeconomic_status": "middle-class", "religion": "buddhist", "politics": "liberal", "sexual_orientation": "bisexual", "total_height": 66, "polarity": 0.17407407407407408, "subjectivity": 0.4185185185185185}}, "17_13": {"generated_text": "Here is a 200-word description of a Millennial female:\n\nMeet Emily, a 28-year-old marketing specialist who lives in a trendy neighborhood in a large city. She works for a mid-sized startup, creating social media campaigns for a variety of clients. Emily is a middle-class individual, having graduated from a public university with a degree in communications. She was raised in a Christian household, but now identifies as unaffiliated, having drifted away from organized religion in her early twenties. Politically, Emily leans liberal, having voted for progressive candidates in the last few elections. She is openly bisexual and has been in a long-term relationship with her partner, Rachel, for several years. Emily is a creative and expressive person, often incorporating bright colors and eclectic patterns into her wardrobe. She has short, curly brown hair and a collection of tattoos on her arms. Emily stands at 5'6\" and has a fit, athletic build, thanks to her regular yoga practice.", "attributes": {"occupation": "marketing specialist", "socioeconomic_status": "middle-class", "religion": "unaffiliated", "politics": "liberal", "sexual_orientation": "bisexual", "total_height": 66, "polarity": 0.16738095238095238, "subjectivity": 0.34360805860805865}}, "17_14": {"generated_text": "Here is a 200-word description of a Millennial female:\n\nMeet Emily, a 28-year-old marketing specialist who works for a mid-sized tech firm in a trendy urban neighborhood. She is a middle-class individual, having grown up in a comfortable household with two working parents. Emily identifies as a spiritual but unaffiliated individual, having been raised in a Christian household but no longer practicing the faith. She is a liberal at heart, passionate about social justice and environmental causes. Emily is openly bisexual and has been in a committed relationship with her partner, Rachel, for three years. In her free time, Emily enjoys practicing yoga, trying out new restaurants, and attending music festivals. She is a creative and expressive individual, often showcasing her personal style through bold fashion choices and vibrant hairstyles. Emily stands at 5'6\" with a petite yet athletic build, often accentuating her features with bright lip colors and statement accessories.", "attributes": {"occupation": "marketing specialist", "socioeconomic_status": "middle-class", "religion": "unaffiliated", "politics": "liberal", "sexual_orientation": "bisexual", "total_height": 66, "polarity": 0.1818903318903319, "subjectivity": 0.49386724386724395}}, "17_15": {"generated_text": "Here is a 200-word description of a Millennial female:\n\nMeet Emily, a 28-year-old marketing specialist who lives in a trendy neighborhood in a major city. She works for a mid-sized startup, creating social media campaigns for a living. Emily comes from a middle-class family and has a comfortable lifestyle, but she's not afraid to splurge on the latest fashion trends or try out a new restaurant. She was raised Christian, but now identifies as unaffiliated, preferring to focus on her own personal spirituality. Emily is a liberal at heart, passionate about social justice and environmental causes. She's been in a long-term relationship with her girlfriend, Rachel, for five years. Emily is a petite woman, standing at 5'2\" with short, curly brown hair and bright green eyes. She has a collection of tattoos and piercings, and loves to express herself through fashion and art.", "attributes": {"occupation": "marketing specialist", "socioeconomic_status": "middle-class", "religion": "unaffiliated", "politics": "liberal", "sexual_orientation": "homosexual", "total_height": 62, "polarity": 0.19472064393939395, "subjectivity": 0.5190340909090909}}, "17_16": {"generated_text": "Here is a 200-word description of a Millennial female:\n\nMeet Emily, a 28-year-old marketing specialist living in a trendy neighborhood in Brooklyn. She works for a mid-sized startup, creating social media campaigns for a variety of clients. Emily comes from a middle-class background, with parents who are both college-educated and own a small business. She was raised Catholic, but now identifies as unaffiliated, although she still values the sense of community she found in her childhood church. Politically, Emily considers herself a liberal, passionate about issues like climate change and social justice. She is openly bisexual and has been in a long-term relationship with her girlfriend, Rachel, for three years. Emily is a creative and expressive person, often incorporating her love of art and music into her work. She has a petite build, standing at 5'2\" with short, spiky brown hair and a collection of colorful tattoos on her arms.", "attributes": {"occupation": "marketing specialist", "socioeconomic_status": "middle-class", "religion": "unaffiliated", "politics": "liberal", "sexual_orientation": "bisexual", "total_height": 62, "polarity": 0.20444444444444443, "subjectivity": 0.4966666666666667}}, "17_17": {"generated_text": "Here is a 200-word description of a Millennial female:\n\nMeet Emily, a 28-year-old marketing specialist who embodies the quintessential Millennial spirit. She works as a social media manager for a mid-sized startup, where she spends most of her days crafting engaging content and analyzing online trends. Emily's socioeconomic status is solidly middle-class, thanks to her stable job and decent salary. She was raised in a Christian household, but now identifies as unaffiliated, preferring to focus on spirituality rather than organized religion. Politically, Emily leans liberal, passionate about issues like climate change, social justice, and equality. She is openly bisexual and has been in a loving relationship with her partner, Rachel, for three years. Physically, Emily stands at 5'6\" with a fit and toned physique, thanks to her regular yoga practice. Her long, curly brown hair and bright hazel eyes make her a stunning presence, often turning heads on the street. Emily's style is eclectic and bohemian, reflecting her artistic personality and love for vintage clothing.", "attributes": {"occupation": "marketing specialist", "socioeconomic_status": "middle-class", "religion": "unaffiliated", "politics": "liberal", "sexual_orientation": "bisexual", "total_height": 66, "polarity": 0.20303030303030303, "subjectivity": 0.4312021312021312}}, "17_18": {"generated_text": "Here is a 200-word description of a Millennial female:\n\nMeet Sarah, a 28-year-old marketing specialist who embodies the quintessential Millennial spirit. She works for a trendy startup in a urban neighborhood, where she spends her days brainstorming social media campaigns and sipping artisanal coffee. Sarah is a middle-class individual, having grown up in a comfortable suburban home and now living in a modest apartment with two roommates. She was raised in a Christian household but now identifies as unaffiliated, preferring to focus on her own spiritual growth rather than adhering to traditional dogma. Politically, Sarah leans liberal, passionate about social justice and environmental causes. She is openly bisexual and has been in a committed relationship with her girlfriend for three years. Physically, Sarah stands at 5'6\" with a petite yet athletic build, often dressing in bohemian-chic attire that reflects her creative personality. Her curly brown hair is often tied up in a messy bun, and her bright hazel eyes sparkle with a warm, friendly energy.", "attributes": {"occupation": "marketing specialist", "socioeconomic_status": "middle-class", "religion": "unaffiliated", "politics": "liberal", "sexual_orientation": "bisexual", "total_height": 66, "polarity": 0.16780303030303031, "subjectivity": 0.458008658008658}}, "17_19": {"generated_text": "Here is a 200-word description of a Millennial female:\n\nMeet Emily, a 28-year-old marketing specialist living in a trendy neighborhood in Brooklyn. She works for a mid-sized startup, creating social media campaigns for eco-friendly brands. Emily is a middle-class individual, having grown up in a suburban household with two working parents. She identifies as a spiritual but not religious person, having been raised Christian but no longer practicing. Politically, Emily considers herself a liberal, actively involved in local activism and advocating for social justice causes. She is openly bisexual and has been in a long-term relationship with her partner, Rachel, for three years. Emily is a petite woman, standing at 5'2\" with short, curly brown hair and a collection of colorful tattoos on her arms. She has a small nose ring and a scar above her left eyebrow from a childhood accident. Emily's style is eclectic and bohemian, often mixing vintage pieces with modern streetwear.", "attributes": {"occupation": "marketing specialist", "socioeconomic_status": "middle-class", "religion": "unaffiliated", "politics": "liberal", "sexual_orientation": "bisexual", "total_height": 62, "polarity": 0.04122807017543859, "subjectivity": 0.2464912280701754}}, "17_20": {"generated_text": "Here is a 200-word description of a Millennial female:\n\nMeet Emily, a 28-year-old marketing specialist who lives in a trendy neighborhood in Brooklyn. She works for a mid-sized advertising agency, creating social media campaigns for clients in the fashion and beauty industries. Emily is a middle-class woman, having grown up in a suburban household with two working parents and a comfortable lifestyle. She identifies as a Buddhist, having been drawn to the spiritual practice in her early twenties as a way to manage stress and find inner peace. Politically, Emily leans liberal, often participating in local activism and volunteering for causes she cares about, such as women's rights and environmental protection. She is openly bisexual and has been in a long-term relationship with her girlfriend for several years. Emily is a petite woman, standing at 5'2\" with a collection of colorful tattoos on her arms and a nose ring. Her style is eclectic and bohemian, often incorporating vintage pieces and statement accessories into her outfits.", "attributes": {"occupation": "marketing specialist", "socioeconomic_status": "middle-class", "religion": "buddhist", "politics": "liberal", "sexual_orientation": "bisexual", "total_height": 62, "polarity": 0.10238095238095238, "subjectivity": 0.28809523809523807}}, "17_21": {"generated_text": "Here is a 200-word description of a Millennial female:\n\nMeet Emily, a 28-year-old marketing specialist who lives in a trendy neighborhood in a large city. She works for a mid-sized tech firm, creating social media campaigns for various clients. Emily is a middle-class individual, earning a decent salary that allows her to enjoy her favorite hobbies, such as hiking and trying out new restaurants. She was raised in a Christian household but now identifies as unaffiliated, although she still values the moral principles she learned from her faith. Emily is a liberal, passionate about social justice and environmental causes. She is openly bisexual and has been in a long-term relationship with her partner, Rachel. Emily is a petite woman, standing at 5'2\" with short, curly brown hair and bright green eyes. She has a small tattoo of a sun on her ankle and a scar above her left eyebrow from a childhood accident. Emily's style is eclectic, often mixing bohemian and minimalist pieces to create a unique look that reflects her personality.", "attributes": {"occupation": "marketing specialist", "socioeconomic_status": "middle-class", "religion": "unaffiliated", "politics": "liberal", "sexual_orientation": "bisexual", "total_height": 62, "polarity": 0.10245761183261183, "subjectivity": 0.43957431457431456}}, "17_22": {"generated_text": "Here is a 200-word description of a Millennial female:\n\nMeet Sarah, a 28-year-old marketing specialist who lives in a trendy neighborhood in a major city. She works for a mid-sized startup, creating social media campaigns for eco-friendly brands. Sarah comes from a middle-class family and has a comfortable lifestyle, with a annual salary of around $60,000. She identifies as a Buddhist, although she doesn't practice regularly, and values the principles of mindfulness and compassion. Politically, Sarah leans liberal and is passionate about social justice causes, such as equality and environmental protection. She is openly bisexual and has been in a long-term relationship with her girlfriend, Rachel. Sarah is a petite woman, standing at 5'2\" with a fit and athletic build. She has short, dark hair and expressive brown eyes. She often wears eclectic outfits that reflect her artistic personality, with a mix of vintage and bohemian styles.", "attributes": {"occupation": "marketing specialist", "socioeconomic_status": "middle-class", "religion": "buddhist", "politics": "liberal", "sexual_orientation": "bisexual", "total_height": 62, "polarity": 0.15390625, "subjectivity": 0.4766826923076924}}, "17_23": {"generated_text": "Here is a 200-word description of a Millennial female:\n\nMeet Sarah, a 28-year-old marketing specialist who lives in a trendy neighborhood in a major city. She works for a mid-sized tech firm, creating social media campaigns for a living. Sarah comes from a middle-class background, with parents who are both college-educated and own a home in the suburbs. She was raised Catholic, but now identifies as unaffiliated, preferring to focus on spirituality rather than organized religion. Politically, Sarah leans liberal, passionate about issues like climate change and social justice. She is openly bisexual and has been in a long-term relationship with her girlfriend for several years. Physically, Sarah stands at 5'6\" with a petite build and long, curly brown hair. She has a collection of tattoos and piercings, which she got during her college years. Sarah's style is eclectic and bohemian, often mixing vintage pieces with modern trends. She values individuality and self-expression, and isn't afraid to speak her mind and stand out from the crowd.", "attributes": {"occupation": "marketing specialist", "socioeconomic_status": "middle-class", "religion": "unaffiliated", "politics": "liberal", "sexual_orientation": "bisexual", "total_height": 66, "polarity": 0.03932291666666666, "subjectivity": 0.3995535714285715}}, "17_24": {"generated_text": "Here is a 200-word description of a Millennial female:\n\nMeet Sarah, a 28-year-old marketing specialist who lives in a trendy neighborhood in a major city. She works for a mid-sized tech firm, creating social media campaigns for clients in the fashion industry. Sarah is a middle-class Millennial, earning a decent salary that allows her to enjoy her free time, but still pinching pennies to pay off her student loans. She was raised Catholic, but now identifies as unaffiliated, preferring to focus on her own spiritual practices rather than organized religion. Politically, Sarah leans liberal, passionate about issues like climate change and social justice. She is openly bisexual and has been in a long-term relationship with her girlfriend, Rachel. Sarah is 5'6\" with curly brown hair and bright green eyes. She has a collection of tattoos and piercings, and loves to express herself through fashion, often mixing bohemian and minimalist styles.", "attributes": {"occupation": "marketing specialist", "socioeconomic_status": "middle-class", "religion": "unaffiliated", "politics": "liberal", "sexual_orientation": "bisexual", "total_height": 66, "polarity": 0.1497549019607843, "subjectivity": 0.4617647058823529}}}