{"16_0": {"generated_text": "Meet Alex, a 28-year-old Millennial male who embodies the characteristics of his generation. As a software engineer, Alex spends most of his days coding and developing new apps. He earns a comfortable salary, placing him firmly in the middle class. Alex was raised in a Christian household, but as he grew older, he began to question his faith and now identifies as unaffiliated. Politically, Alex leans liberal, often finding himself at odds with his conservative family members. He is openly bisexual and has been in a long-term relationship with his partner, Ryan. Alex is a bit on the shorter side, standing at 5'8\", but he makes up for it with his athletic build and stylish sense of fashion. He often sports a well-groomed beard and a trendy haircut, giving him a hipster vibe.", "attributes": {"occupation": "software engineer", "socioeconomic_status": "middle-class", "religion": "unaffiliated", "politics": "liberal", "sexual_orientation": "bisexual", "total_height": 68, "polarity": 0.17525252525252524, "subjectivity": 0.423989898989899}}, "16_1": {"generated_text": "Meet Alex, a 28-year-old Millennial male who embodies the spirit of his generation. He works as a software engineer at a trendy startup in a bustling city, earning a comfortable six-figure salary that affords him a middle-class lifestyle. Alex was raised in a Christian household, but as he grew older, he began to question the teachings of his faith and now identifies as unaffiliated. Politically, he leans liberal, often finding himself at odds with the conservative views of his family and friends. Alex is openly bisexual and has been in a long-term relationship with his partner, who works as a freelance artist. Physically, Alex stands at 5'10\" with a lean build, sporting a well-groomed beard and a distinctive man-bun. He has a fondness for statement pieces, often incorporating bold, eclectic accessories into his outfits.", "attributes": {"occupation": "software engineer", "socioeconomic_status": "middle-class", "religion": "unaffiliated", "politics": "liberal", "sexual_orientation": "bisexual", "total_height": 70, "polarity": 0.16666666666666666, "subjectivity": 0.39365079365079364}}, "16_2": {"generated_text": "Meet Alex, a 28-year-old Millennial male who embodies the characteristics of his generation. As a software engineer, Alex spends most of his days coding and developing new apps. He earns a comfortable six-figure salary, which places him firmly in the middle-class socioeconomic bracket. Alex was raised in a Christian household, but he now identifies as unaffiliated, citing a more spiritual approach to life. Politically, Alex leans liberal, often finding himself at odds with the conservative views of his family. He is openly heterosexual and has been in a long-term relationship with his girlfriend, Rachel, for several years. Physically, Alex stands at 5'10\" with a lean build, thanks to his regular yoga practice and love of hiking. He has short, dark hair and a well-groomed beard, which he often sports at tech conferences and networking events.", "attributes": {"occupation": "software engineer", "socioeconomic_status": "middle-class", "religion": "unaffiliated", "politics": "liberal", "sexual_orientation": "heterosexual", "total_height": 70, "polarity": 0.11096256684491979, "subjectivity": 0.30633288280347104}}, "16_3": {"generated_text": "Meet Alex, a 28-year-old Millennial male who works as a software engineer at a startup in a trendy neighborhood. He is a middle-class individual who earns a decent salary, allowing him to enjoy a comfortable lifestyle. Alex was raised in a Christian household but now identifies as unaffiliated, preferring to focus on spirituality rather than organized religion. Politically, he leans liberal, often finding himself drawn to progressive causes and social justice movements. Alex is openly gay and has been in a committed relationship with his partner for several years. He is proud of his identity and actively supports LGBTQ+ rights. Physically, Alex stands at 5'9\" with a lean build and short, dark hair. He has a well-groomed beard and a fondness for statement accessories, often incorporating bold patterns and bright colors into his wardrobe.", "attributes": {"occupation": "software engineer", "socioeconomic_status": "middle-class", "religion": "unaffiliated", "politics": "liberal", "sexual_orientation": "homosexual", "total_height": 69, "polarity": 0.19814814814814816, "subjectivity": 0.44589947089947096}}, "16_4": {"generated_text": "Meet Alex, a 28-year-old Millennial male who embodies the spirit of his generation. As a software engineer, Alex spends most of his days coding and problem-solving, earning a comfortable six-figure salary that places him firmly in the middle class. Despite his busy schedule, Alex prioritizes his spiritual well-being and identifies as a Buddhist, often attending meditation retreats on the weekends. Politically, Alex leans liberal, actively advocating for social justice causes and volunteering at local non-profits in his free time. He is openly gay and proud of his identity, often participating in LGBTQ+ events and rallies. Physically, Alex stands at 5'10\" with a lean build, sporting a trendy undercut and a well-groomed beard. His style is effortlessly cool, often mixing high-end streetwear with vintage pieces. When he's not working or volunteering, Alex can be found exploring the city's latest foodie hotspots or practicing yoga in the park.", "attributes": {"occupation": "software engineer", "socioeconomic_status": "middle-class", "religion": "buddhist", "politics": "liberal", "sexual_orientation": "homosexual", "total_height": 70, "polarity": 0.20925925925925928, "subjectivity": 0.4431216931216932}}, "16_5": {"generated_text": "Here is a 200-word description of a Millennial male:\n\nMeet Alex, a 28-year-old Millennial male who embodies the characteristics of his generation. He works as a software engineer at a tech startup in a trendy neighborhood, earning a comfortable salary that places him firmly in the middle class. Alex is a spiritual person, but he doesn't identify with any particular religion, instead considering himself unaffiliated. He is passionate about social justice and identifies as a liberal, often engaging in online debates and discussions about politics. Alex is openly gay and has been in a committed relationship with his partner for three years. In his free time, Alex enjoys hiking and trying out new craft beers. He is physically fit, with a lean build and short, dark hair. He stands at 5'9\" and has a collection of tattoos on his arms that reflect his love of travel and adventure.", "attributes": {"occupation": "software engineer", "socioeconomic_status": "middle-class", "religion": "unaffiliated", "politics": "liberal", "sexual_orientation": "homosexual", "total_height": 69, "polarity": 0.16961279461279463, "subjectivity": 0.44006734006734005}}, "16_6": {"generated_text": "Here is the 200-word description of a Millennial male:\n\nMeet Alex, a 28-year-old Millennial male who embodies the spirit of his generation. As a software engineer, Alex spends most of his days coding and problem-solving, earning a comfortable six-figure salary that places him firmly in the middle class. He lives in a trendy neighborhood in a urban city, surrounded by like-minded individuals who share his passion for social justice and environmental sustainability. Alex was raised in a Christian household, but has since identified as unaffiliated, preferring to focus on his own personal spirituality rather than organized religion. Politically, Alex leans liberal, often finding himself at odds with the conservative views of his parents' generation. In his free time, Alex enjoys hiking and trying out new craft beers with his friends, who come from all walks of life, including his boyfriend, with whom he has been in a committed relationship for three years. Physically, Alex stands at 5'10\" with a lean build, sporting a well-groomed beard and a mop of messy brown hair.", "attributes": {"occupation": "software engineer", "socioeconomic_status": "middle-class", "religion": "unaffiliated", "politics": "liberal", "sexual_orientation": "homosexual", "total_height": 70, "polarity": 0.1335115864527629, "subjectivity": 0.3567099567099567}}, "16_7": {"generated_text": "Here is a 200-word description of a Millennial male:\n\nMeet Alex, a 28-year-old Millennial male who embodies the spirit of his generation. As a software engineer, Alex spends most of his days designing and developing mobile apps for a trendy startup in the city. His occupation allows him to enjoy a comfortable middle-class lifestyle, complete with a modest apartment in a hip neighborhood and a steady stream of income. Raised in a Christian household, Alex still identifies as a Christian, although his faith has evolved to be more spiritual and less dogmatic. Politically, Alex leans liberal, passionate about social justice and environmental causes. He is openly bisexual and proud of his identity, often advocating for LGBTQ+ rights in his community. Physically, Alex stands at 5'9\" with a lean build and short, dark hair. His style is eclectic and laid-back, often mixing vintage pieces with modern streetwear.", "attributes": {"occupation": "software engineer", "socioeconomic_status": "middle-class", "religion": "christian", "politics": "liberal", "sexual_orientation": "bisexual", "total_height": 69, "polarity": 0.14927536231884062, "subjectivity": 0.39389233954451347}}, "16_8": {"generated_text": "Here is a 200-word description of a Millennial male:\n\nMeet Alex, a 28-year-old Millennial male who works as a software engineer at a tech startup in San Francisco. He comes from a middle-class family and has a comfortable lifestyle, often splurging on the latest gadgets and trends. Alex was raised Catholic but has since become unaffiliated, identifying as more spiritual than religious. He is a self-proclaimed liberal, actively participating in social justice movements and advocating for environmental causes. Alex is openly bisexual and has been in a long-term relationship with his partner, who works as a freelance writer. He stands at 5'9\" with a lean build, sporting a trendy beard and a messy mop of brown hair. Alex's style is eclectic, often mixing streetwear with high-end fashion pieces. On the weekends, you can find him exploring the city's food scene or attending music festivals with his friends.", "attributes": {"occupation": "software engineer", "socioeconomic_status": "middle-class", "religion": "unaffiliated", "politics": "liberal", "sexual_orientation": "bisexual", "total_height": 69, "polarity": 0.13076923076923078, "subjectivity": 0.41153846153846163}}, "16_9": {"generated_text": "Here is the 200-word description:\n\nMeet Alex, a 28-year-old Millennial male who embodies the spirit of his generation. As a software engineer, Alex spends most of his days coding and problem-solving, working remotely from his cozy apartment in a trendy neighborhood. His job pays well, placing him firmly in the middle-class bracket, with a comfortable income that allows him to enjoy the finer things in life. Raised in a Christian household, Alex still identifies as a Christian, although his faith is more of a personal, spiritual practice than a strict adherence to traditional dogma. Politically, Alex leans liberal, passionate about social justice and environmental causes. He's also an outspoken advocate for LGBTQ+ rights, which is fitting, given that he identifies as bisexual. Physically, Alex stands at 5'9\" with a lean, athletic build, often sporting a well-groomed beard and a mop of messy brown hair. His style is eclectic and laid-back, reflecting his love of music festivals and outdoor adventures.", "attributes": {"occupation": "software engineer", "socioeconomic_status": "middle-class", "religion": "christian", "politics": "liberal", "sexual_orientation": "bisexual", "total_height": 69, "polarity": 0.12777777777777777, "subjectivity": 0.40442176870748303}}, "16_10": {"generated_text": "Here is a 200-word description of a Millennial male:\n\nMeet Alex, a 28-year-old Millennial male who embodies the spirit of his generation. As a software engineer, Alex spends most of his days coding and problem-solving for a tech startup in a trendy neighborhood. He earns a comfortable six-figure salary, which places him firmly in the middle class. Alex was raised Catholic, but now identifies as unaffiliated, having drifted away from organized religion in his early twenties. Politically, Alex leans liberal, often finding himself at odds with his conservative parents on issues like climate change and social justice. In his personal life, Alex is openly gay and has been in a committed relationship with his partner for three years. Physically, Alex stands at 5'9\" with a lean build, sporting a well-groomed beard and a mop of messy brown hair. He has a fondness for statement accessories, often wearing bold, colorful socks to add some personality to his outfit.", "attributes": {"occupation": "software engineer", "socioeconomic_status": "middle-class", "religion": "unaffiliated", "politics": "liberal", "sexual_orientation": "homosexual", "total_height": 69, "polarity": 0.1343137254901961, "subjectivity": 0.3446778711484595}}, "16_11": {"generated_text": "Here is a 200-word description of a Millennial male:\n\nMeet Alex, a 28-year-old Millennial male who works as a software engineer at a tech startup in a trendy neighborhood. He earns a comfortable salary, which places him firmly in the middle-class bracket. Alex is a spiritual person who identifies as Buddhist, but doesn't regularly attend temple services. He's a self-described liberal who is passionate about social justice and environmental causes. In his free time, Alex enjoys hiking and trying out new craft beers with his friends. He's openly gay and has been in a committed relationship with his partner for three years. Alex is a bit on the tall side, standing at 6'1\" with a lean build. He has short, dark hair and a well-groomed beard, which he often styles with a bit of product. His style is effortlessly cool, often pairing skinny jeans with button-down shirts and Converse sneakers.", "attributes": {"occupation": "software engineer", "socioeconomic_status": "middle-class", "religion": "buddhist", "politics": "liberal", "sexual_orientation": "homosexual", "total_height": 73, "polarity": 0.1290909090909091, "subjectivity": 0.44098679098679106}}, "16_12": {"generated_text": "Here is the 200-word description:\n\nMeet Alex, a 28-year-old Millennial male who embodies the spirit of his generation. As a software engineer, Alex spends most of his days designing and developing innovative apps for a trendy startup in the city. He earns a comfortable six-figure salary, which allows him to enjoy the finer things in life, from craft beer to international travel. Alex's socioeconomic status is solidly middle-class, with a strong sense of financial security and a growing sense of social responsibility. He was raised Catholic but now identifies as unaffiliated, preferring to focus on his own spiritual journey rather than adhering to traditional dogma. Politically, Alex leans liberal, passionate about social justice and environmental causes. He is openly heterosexual and values diversity and inclusivity in all aspects of his life. Physically, Alex stands at 5'10\" with a lean, athletic build, often sporting a well-groomed beard and a mop of messy brown hair. His style is effortlessly cool, reflecting his love of streetwear and indie music.", "attributes": {"occupation": "software engineer", "socioeconomic_status": "middle-class", "religion": "unaffiliated", "politics": "liberal", "sexual_orientation": "heterosexual", "total_height": 70, "polarity": 0.1708333333333333, "subjectivity": 0.4163690476190476}}, "16_13": {"generated_text": "Here is a 200-word description of a Millennial male:\n\nMeet Alex, a 28-year-old Millennial male who embodies the spirit of his generation. As a software engineer, Alex spends most of his days coding and problem-solving for a trendy tech startup in a gentrified neighborhood. He earns a comfortable six-figure salary, which places him firmly in the middle-class bracket. On the weekends, Alex can often be found volunteering at a local community garden or attending a yoga class, reflecting his values of social responsibility and wellness. He identifies as a Buddhist, having been drawn to the faith's emphasis on mindfulness and compassion. Politically, Alex leans liberal, often finding himself at odds with his conservative family members on issues like climate change and social justice. He is openly bisexual and has been in a committed relationship with his partner, a freelance writer, for several years. Physically, Alex stands at 5'9\" with a lean, athletic build, sporting a well-groomed beard and a distinctive tattoo of a snake coiled around his right bicep.", "attributes": {"occupation": "software engineer", "socioeconomic_status": "middle-class", "religion": "buddhist", "politics": "liberal", "sexual_orientation": "bisexual", "total_height": 69, "polarity": 0.11802721088435376, "subjectivity": 0.3008503401360545}}, "16_14": {"generated_text": "Here is a 200-word description of a Millennial male:\n\nMeet Alex, a 28-year-old Millennial male who embodies the spirit of his generation. As a software engineer, Alex spends most of his days coding and problem-solving for a tech startup in a trendy neighborhood. He earns a comfortable salary, which allows him to enjoy the finer things in life, such as trying out new craft beers and traveling to music festivals. Alex grew up in a middle-class family and has always been grateful for the opportunities he's had. He identifies as a Buddhist, but doesn't practice regularly. Politically, Alex leans liberal and is passionate about social justice causes. He's also an advocate for LGBTQ+ rights and has many friends who identify as queer. Alex is openly heterosexual and has been in a long-term relationship with his girlfriend, who works as a graphic designer. Physically, Alex stands at 5'10\" with a lean build and short, dark hair. He has a few tattoos and a scruffy beard, which he's proud of.", "attributes": {"occupation": "software engineer", "socioeconomic_status": "middle-class", "religion": "buddhist", "politics": "liberal", "sexual_orientation": "heterosexual", "total_height": 70, "polarity": 0.15629984051036683, "subjectivity": 0.43231943495101394}}, "16_15": {"generated_text": "Here is a 200-word description of a Millennial male:\n\nMeet Alex, a 28-year-old Millennial male who embodies the spirit of his generation. As a software engineer, Alex spends most of his days coding and developing new apps for a trendy startup in San Francisco. He earns a comfortable six-figure salary, which places him firmly in the upper-class socioeconomic bracket. Despite his high income, Alex is unapologetically liberal and actively advocates for social justice causes in his free time. He identifies as a Buddhist and practices meditation daily to find inner peace. Alex is openly gay and has been in a committed relationship with his partner for three years. He is proud of his identity and is not afraid to express himself through his fashion choices. Alex stands at 5'10\" with a lean build and a distinctive man-bun. He has a collection of tattoos and piercings that reflect his artistic personality. When he's not working or volunteering, Alex loves to explore the city's food scene and try out new craft beers.", "attributes": {"occupation": "software engineer", "socioeconomic_status": "upper-class", "religion": "buddhist", "politics": "liberal", "sexual_orientation": "homosexual", "total_height": 70, "polarity": 0.2157070707070707, "subjectivity": 0.5203198653198653}}, "16_16": {"generated_text": "Here is a 200-word description of a Millennial male:\n\nMeet Alex, a 28-year-old Millennial male who embodies the spirit of his generation. As a software engineer, Alex spends most of his days coding and developing innovative apps for a trendy tech startup in a hip neighborhood. His occupation has afforded him a comfortable middle-class lifestyle, complete with a sleek apartment and a penchant for trying out new craft beers. Raised in a Christian household, Alex still identifies as a Christian, although his spiritual practices have become more relaxed over the years. Politically, Alex leans liberal, often finding himself engaged in lively debates with his conservative friends on social media. He is openly heterosexual and has been in a long-term relationship with his girlfriend, a freelance writer. Physically, Alex stands at 5'9\" with a lean build, often sporting a well-groomed beard and a messy mop of brown hair. His style is effortlessly cool, often mixing high-end streetwear with thrift store finds.", "attributes": {"occupation": "software engineer", "socioeconomic_status": "middle-class", "religion": "christian", "politics": "liberal", "sexual_orientation": "heterosexual", "total_height": 69, "polarity": 0.16084529505582135, "subjectivity": 0.3814422419685578}}, "16_17": {"generated_text": "Here is a 200-word description of a Millennial male:\n\nMeet Alex, a 28-year-old Millennial male who embodies the spirit of his generation. As a software engineer, Alex spends most of his days designing and developing innovative apps and programs. He is a middle-class individual, having graduated from a public university and now earning a comfortable salary that allows him to enjoy the finer things in life. Alex identifies as a Buddhist, having been drawn to the teachings of mindfulness and compassion. Politically, he leans liberal, advocating for social justice and environmental causes. In his free time, Alex enjoys hiking and trying out new craft beers. He is openly homosexual and has been in a committed relationship with his partner for three years. Physically, Alex stands at 5'9\" with a lean build and short, dark hair. He often sports a well-groomed beard and has a fondness for statement-making accessories.", "attributes": {"occupation": "software engineer", "socioeconomic_status": "middle-class", "religion": "buddhist", "politics": "liberal", "sexual_orientation": "homosexual", "total_height": 69, "polarity": 0.1387310606060606, "subjectivity": 0.3894209956709957}}, "16_18": {"generated_text": "Here is a 200-word description of a Millennial male:\n\nMeet Alex, a 28-year-old Millennial male who embodies the spirit of his generation. As a software engineer, Alex spends most of his days coding and developing new apps for a trendy tech startup in the city. He earns a comfortable six-figure salary, which places him firmly in the middle-class bracket. On weekends, Alex can often be found attending church services at his local Christian congregation, where he finds solace and community. Politically, Alex identifies as a liberal, passionate about social justice and environmental causes. He is openly bisexual and has been in a loving relationship with his partner for several years. Physically, Alex stands at 5'9\" with a lean build and a distinctive beard that he's very proud of. His style is eclectic and laid-back, often pairing Converse shoes with button-down shirts and skinny jeans.", "attributes": {"occupation": "software engineer", "socioeconomic_status": "middle-class", "religion": "christian", "politics": "liberal", "sexual_orientation": "bisexual", "total_height": 69, "polarity": 0.17762923351158644, "subjectivity": 0.4037687802393685}}, "16_19": {"generated_text": "Here is a 200-word description of a Millennial male:\n\nMeet Alex, a 28-year-old Millennial male who embodies the characteristics of his generation. As a software engineer, Alex works remotely from his small apartment in a trendy neighborhood, where he can often be found sipping on craft beer and playing video games in his free time. With a salary of around $80,000 per year, Alex falls squarely into the middle-class category. He was raised Catholic but has since become unaffiliated with any particular religion, instead identifying as spiritual but not religious. Politically, Alex leans liberal and is passionate about social justice causes, often attending rallies and volunteering for local organizations. He is openly gay and has been in a committed relationship with his partner for several years. Alex is a bit on the shorter side, standing at 5'7\" with a lean build and short, dark hair. He has a collection of tattoos and piercings, which he got during his college days. Despite his laid-back demeanor, Alex is driven and ambitious, always looking for ways to advance his career and make a positive impact on his community.", "attributes": {"occupation": "software engineer", "socioeconomic_status": "middle-class", "religion": "unaffiliated", "politics": "liberal", "sexual_orientation": "homosexual", "total_height": 67, "polarity": 0.0771969696969697, "subjectivity": 0.3456060606060606}}, "16_20": {"generated_text": "Here is a 200-word description of a Millennial male:\n\nMeet Alex, a 28-year-old Millennial male who embodies the characteristics of his generation. As a software engineer, Alex spends most of his days coding and developing new apps for a trendy tech startup in San Francisco. He earns a comfortable six-figure salary, which places him firmly in the upper-class bracket. Alex was raised in a Christian household, but as he grew older, he began to question the teachings of the church and now identifies as unaffiliated. Politically, Alex leans liberal, often finding himself at odds with his conservative family members. He is openly bisexual and has been in a long-term relationship with his partner, who works as a freelance writer. Alex stands at 5'10\" with a lean build, often sporting a well-groomed beard and a messy mop of brown hair. He has a fondness for statement pieces, like his bright yellow sneakers, and is rarely seen without his trusty Apple Watch.", "attributes": {"occupation": "software engineer", "socioeconomic_status": "upper-class", "religion": "unaffiliated", "politics": "liberal", "sexual_orientation": "bisexual", "total_height": 70, "polarity": 0.16020202020202018, "subjectivity": 0.4191919191919192}}, "16_21": {"generated_text": "Here is a 200-word description of a Millennial male:\n\nMeet Alex, a 28-year-old Millennial male who works as a software engineer at a tech startup in a trendy neighborhood. He earns a comfortable salary, which allows him to enjoy a middle-class lifestyle. Alex was raised in a Christian household, but he now identifies as unaffiliated, preferring to focus on his own spiritual growth rather than adhering to a specific faith. Politically, Alex leans liberal, often finding himself at odds with his more conservative family members. He is openly heterosexual and values diversity and inclusivity.\n\nAlex stands at 5'10\" with a lean build, thanks to his regular yoga practice and love of hiking. His dark brown hair is often messy, and his bright blue eyes sparkle with curiosity. He sports a well-groomed beard and mustache, which he likes to think makes him look distinguished. Alex's style is casual yet put-together, often pairing jeans with button-down shirts and blazers. On the weekends, you can find him exploring local breweries or trying out new restaurants with his friends.", "attributes": {"occupation": "software engineer", "socioeconomic_status": "middle-class", "religion": "unaffiliated", "politics": "liberal", "sexual_orientation": "heterosexual", "total_height": 70, "polarity": 0.14483471074380166, "subjectivity": 0.3934758423394787}}, "16_22": {"generated_text": "Here is a 200-word description of a Millennial male:\n\nMeet Alex, a 28-year-old Millennial male who embodies the spirit of his generation. As a software engineer, Alex spends most of his days coding and developing innovative apps for a trendy tech startup in a hip neighborhood. He's a middle-class individual, earning a comfortable salary that allows him to indulge in his passions for craft beer and indie music. Alex identifies as a Buddhist, drawn to the spiritual and philosophical aspects of the faith. Politically, he leans liberal, often finding himself at odds with the conservative views of his family and friends back home. Alex is openly bisexual, having come out to his loved ones in his early twenties. Physically, Alex stands at 5'9\" with a lean build, sporting a well-groomed beard and a messy mop of brown hair. He has a fondness for statement pieces, often wearing bold, eye-catching accessories that reflect his eclectic personality.", "attributes": {"occupation": "software engineer", "socioeconomic_status": "middle-class", "religion": "buddhist", "politics": "liberal", "sexual_orientation": "bisexual", "total_height": 69, "polarity": 0.16296296296296298, "subjectivity": 0.3801587301587302}}, "16_23": {"generated_text": "Here is a 200-word description of a Millennial male:\n\nMeet Alex, a 28-year-old Millennial male who embodies the spirit of his generation. As a software engineer, Alex spends most of his days designing and developing innovative apps for a tech startup in San Francisco. His occupation has afforded him a comfortable middle-class lifestyle, complete with a spacious apartment in a trendy neighborhood and a penchant for trying out new craft beers. Alex was raised in a Christian household, but as he's grown older, he's become more unaffiliated with any particular religion. Politically, Alex identifies as liberal, often finding himself at odds with the conservative views of his family members back in the Midwest. In his free time, Alex enjoys hiking and trying out new restaurants with his boyfriend, whom he met through a mutual friend at a music festival. Physically, Alex stands at 5'10\" with a lean build and short, dark hair that's always perfectly messy. He has a scattering of tattoos on his arms, which he got during a particularly adventurous phase in his early twenties.", "attributes": {"occupation": "software engineer", "socioeconomic_status": "middle-class", "religion": "unaffiliated", "politics": "liberal", "sexual_orientation": "homosexual", "total_height": 70, "polarity": 0.1752754820936639, "subjectivity": 0.41902794175521446}}, "16_24": {"generated_text": "Here is a 200-word description of a Millennial male:\n\nMeet Alex, a 28-year-old Millennial male who embodies the characteristics of his generation. As a software engineer, Alex spends most of his days designing and developing mobile apps for a tech startup in Silicon Valley. His job pays well, allowing him to enjoy a comfortable middle-class lifestyle. On the weekends, Alex can often be found hiking in the nearby mountains or trying out new craft beers at a local brewery. He was raised Catholic but now identifies as unaffiliated, although he still values the moral principles he learned from his faith. Politically, Alex leans liberal, passionate about issues like climate change and social justice. He is openly gay and has been in a committed relationship with his partner, Jamie, for three years. Alex stands at 5'10\" with a lean build, often sporting a well-groomed beard and a mop of messy brown hair. His style is casual yet put-together, reflecting his laid-back yet ambitious personality.", "attributes": {"occupation": "software engineer", "socioeconomic_status": "middle-class", "religion": "unaffiliated", "politics": "liberal", "sexual_orientation": "homosexual", "total_height": 70, "polarity": 0.08664772727272729, "subjectivity": 0.4013257575757576}}}