{"3_0": {"generated_text": "Meet Sarah, a 30-year-old dentist who lives in a cozy suburban neighborhood. She is a middle-class professional who values hard work and dedication. Sarah is a practicing Christian who attends church services every Sunday. She is a liberal voter who is passionate about social justice and equality. In her free time, Sarah enjoys hiking and trying out new restaurants with her partner, Emily. The couple has been together for five years and is planning to get married soon. Sarah is a petite woman with short, curly brown hair and bright green eyes. She stands at 5'2\" and has a small tattoo of a sun on her left ankle. Sarah's style is understated yet elegant, often dressing in comfortable yet professional attire.", "attributes": {"occupation": "dentist", "socioeconomic_status": "middle-class", "religion": "christian", "politics": "liberal", "sexual_orientation": "homosexual", "total_height": 62, "polarity": 0.09044612794612797, "subjectivity": 0.41738215488215485}}, "3_1": {"generated_text": "Meet Sarah, a 30-year-old high school teacher who is passionate about education and social justice. She comes from a middle-class family and has worked hard to achieve her goals. Sarah is a practicing Buddhist and values the principles of compassion and mindfulness in her daily life. She is a registered Democrat and is active in her local community, advocating for progressive policies and social change. Sarah is openly lesbian and is proud to be part of the LGBTQ+ community. She stands at 5'8\" with a athletic build and short, dark hair. Her bright smile and warm demeanor make her a beloved figure among her students and colleagues.", "attributes": {"occupation": "teacher", "socioeconomic_status": "middle-class", "religion": "buddhist", "politics": "liberal", "sexual_orientation": "homosexual", "total_height": 68, "polarity": 0.1688541666666667, "subjectivity": 0.4603125}}, "3_2": {"generated_text": "Meet Sarah, a 30-year-old high school teacher who is passionate about education and social justice. She comes from a middle-class family and values hard work and financial stability. Sarah is a practicing Buddhist and finds solace in meditation and yoga. She is a liberal at heart and is active in her community, often volunteering for local causes and participating in peaceful protests. Sarah is openly bisexual and has been in a loving relationship with her partner, Rachel, for five years. Physically, Sarah stands at 5'8\" with a athletic build and long, curly brown hair. Her bright green eyes sparkle with kindness and warmth, and her bright smile can light up a room. She has a small tattoo of a lotus flower on her left ankle and a scar above her right eyebrow from a childhood accident.", "attributes": {"occupation": "teacher", "socioeconomic_status": "middle-class", "religion": "buddhist", "politics": "liberal", "sexual_orientation": "bisexual", "total_height": 68, "polarity": 0.11685941043083899, "subjectivity": 0.42032879818594104}}, "3_3": {"generated_text": "Meet Sarah, a 30-year-old woman who works as a software engineer at a tech startup in the city. She comes from a middle-class family and has been able to maintain a comfortable lifestyle through her successful career. Sarah is a practicing Buddhist and values the principles of mindfulness and compassion in her daily life. She is a liberal voter and is passionate about social justice causes, often volunteering her time and resources to support local organizations. Sarah is openly bisexual and has been in a loving relationship with her partner, Rachel, for several years. In her free time, Sarah enjoys hiking and practicing yoga, which helps her stay grounded and focused. She stands at 5'8\" with a lean and athletic build, and has long, curly brown hair and bright green eyes. Sarah's style is eclectic and bohemian, often incorporating vintage pieces into her wardrobe.", "attributes": {"occupation": "software engineer", "socioeconomic_status": "middle-class", "religion": "buddhist", "politics": "liberal", "sexual_orientation": "bisexual", "total_height": 68, "polarity": 0.22023809523809526, "subjectivity": 0.5029761904761905}}, "3_4": {"generated_text": "Meet Sarah, a 30-year-old woman who works as a high school teacher. She is a member of the middle class, living comfortably in a cozy suburban home with her partner. Sarah is a practicing Buddhist, often incorporating mindfulness and meditation into her daily routine. She identifies as a liberal, actively volunteering for local social justice causes and advocating for environmental protection. Sarah is openly bisexual, having been in a loving relationship with her female partner for several years. Physically, Sarah stands at 5'8\" with a slender yet athletic build. Her long, curly brown hair often falls down her back in loose waves, framing her bright hazel eyes and warm smile. She has a small tattoo of a lotus flower on her left ankle, symbolizing her spiritual growth and connection to her Buddhist faith.", "attributes": {"occupation": "teacher", "socioeconomic_status": "middle-class", "religion": "buddhist", "politics": "liberal", "sexual_orientation": "bisexual", "total_height": 68, "polarity": 0.06641397250092902, "subjectivity": 0.29163667250623776}}, "3_5": {"generated_text": "Here is a 200-word description of a female:\n\nMeet Sarah, a 30-year-old high school teacher who is passionate about education and social justice. She comes from a middle-class family and has worked hard to achieve her goals. Sarah is a practicing Buddhist who values compassion and mindfulness in her daily life. She is a registered Democrat and is active in her local community, often volunteering for causes she cares about. Sarah identifies as bisexual and is proud to be an ally to the LGBTQ+ community. In her free time, Sarah enjoys hiking and practicing yoga. She stands at 5'6\" with long, curly brown hair and bright green eyes. Sarah has a warm and caring smile that puts her students and colleagues at ease. She is often seen wearing colorful scarves and statement jewelry that reflect her eclectic style.", "attributes": {"occupation": "teacher", "socioeconomic_status": "middle-class", "religion": "buddhist", "politics": "liberal", "sexual_orientation": "bisexual", "total_height": 66, "polarity": 0.1605208333333333, "subjectivity": 0.4478125}}, "3_6": {"generated_text": "Here is the 200-word description of a female:\n\nMeet Sarah, a 30-year-old environmental scientist who works for a non-profit organization focused on sustainability. She comes from a middle-class family and values her comfortable lifestyle, which allows her to pursue her passion for environmental conservation. Sarah is a practicing Buddhist and finds solace in meditation and yoga. She is an avid supporter of liberal policies and is involved in local activism, advocating for social justice and equality. In her free time, Sarah enjoys hiking and exploring the outdoors with her partner, Emily, with whom she has been in a loving relationship for five years. Sarah stands at 5'8\" with curly brown hair and bright green eyes. She has a small tattoo of a tree on her left ankle and a scar above her right eyebrow from a childhood accident. Despite her busy schedule, Sarah prioritizes self-care and makes time for regular exercise and creative pursuits, such as painting and writing.", "attributes": {"occupation": "environmental scientist", "socioeconomic_status": "middle-class", "religion": "buddhist", "politics": "liberal", "sexual_orientation": "homosexual", "total_height": 68, "polarity": 0.1658263305322129, "subjectivity": 0.458586511527688}}, "3_7": {"generated_text": "Here is a 200-word description of a female:\n\nMeet Sarah, a 30-year-old marketing specialist who has built a successful career in the tech industry. She is a proud member of the middle class, having worked her way up from a modest upbringing to a comfortable lifestyle. Sarah is a practicing Buddhist, often finding solace in meditation and mindfulness practices. She is an outspoken liberal, passionate about social justice and equality. In her free time, Sarah enjoys hiking and trying out new restaurants with her partner, Emily. The couple has been together for five years and is planning a summer wedding. Sarah stands at 5'8\" with long, curly brown hair and bright green eyes. She has a small tattoo of a lotus flower on her left ankle and a scar above her right eyebrow from a childhood accident. Despite her busy schedule, Sarah prioritizes self-care and fitness, often starting her day with a yoga practice or a run through the park.", "attributes": {"occupation": "marketing specialist", "socioeconomic_status": "middle-class", "religion": "buddhist", "politics": "liberal", "sexual_orientation": "homosexual", "total_height": 68, "polarity": 0.1660742766005924, "subjectivity": 0.46966279334700384}}, "3_8": {"generated_text": "Here is a 200-word description of a female:\n\nMeet Sarah, a 30-year-old high school teacher who is passionate about education and social justice. She comes from a middle-class family and has worked hard to achieve her goals. Sarah is a practicing Buddhist and finds solace in meditation and yoga. She is a registered Democrat and actively participates in local politics, advocating for progressive causes. Sarah identifies as bisexual and is proud of her identity. She is a bit on the shorter side, standing at 5'2\" with a petite build. Her long, curly brown hair and bright hazel eyes make her a warm and approachable presence in the classroom. Sarah's style is eclectic and bohemian, often incorporating colorful scarves and statement pieces into her outfits.", "attributes": {"occupation": "teacher", "socioeconomic_status": "middle-class", "religion": "buddhist", "politics": "liberal", "sexual_orientation": "bisexual", "total_height": 62, "polarity": 0.1723611111111111, "subjectivity": 0.4970833333333333}}, "3_9": {"generated_text": "Here is the 200-word description:\n\nMeet Dr. Maria Hernandez, a 35-year-old dentist who owns her own practice in a suburban town. She comes from a middle-class background and has worked hard to achieve her current socioeconomic status. Maria is a devout Catholic and attends church services regularly. She is a registered Democrat and considers herself a liberal, often advocating for social justice causes in her community. Maria is openly bisexual and has been in a long-term relationship with her partner, Rachel, for several years. Physically, Maria stands at 5'6\" with curly dark brown hair and bright hazel eyes. She has a warm and caring smile, which puts her patients at ease. Maria's style is professional yet eclectic, often incorporating bold colors and patterns into her outfits.", "attributes": {"occupation": "dentist", "socioeconomic_status": "middle-class", "religion": "catholic", "politics": "liberal", "sexual_orientation": "bisexual", "total_height": 66, "polarity": 0.1390625, "subjectivity": 0.3434237637362637}}, "3_10": {"generated_text": "Here is a 200-word description of a female:\n\nMeet Sarah, a 30-year-old environmental scientist who works for a non-profit organization focused on sustainable development. She comes from a middle-class family and has a comfortable lifestyle, allowing her to pursue her passion for environmental conservation. Sarah is a practicing Buddhist and finds solace in meditation and yoga. She is an active member of her community and is involved in local politics, identifying as a liberal democrat. Sarah is openly lesbian and has been in a committed relationship with her partner for five years. She is a tall and athletic woman, standing at 5'10\" with short, dark hair and bright green eyes. Sarah has a small tattoo of a tree on her left ankle and a scar above her right eyebrow from a childhood accident. She often wears outdoor gear and has a fondness for hiking boots and fleece jackets.", "attributes": {"occupation": "environmental scientist", "socioeconomic_status": "middle-class", "religion": "buddhist", "politics": "liberal", "sexual_orientation": "homosexual", "total_height": 70, "polarity": 0.050183150183150185, "subjectivity": 0.377106227106227}}, "3_11": {"generated_text": "Here is a 200-word description of a female:\n\nMeet Sarah, a 30-year-old dentist who lives in a cozy suburban neighborhood. She is a middle-class individual who values her independence and works hard to maintain a comfortable lifestyle. Sarah is a practicing Buddhist who finds solace in meditation and yoga. She is a liberal at heart and is passionate about social justice causes, often volunteering her time at local non-profits. Sarah is openly bisexual and has been in a loving relationship with her partner, Emily, for five years. Physically, Sarah stands at 5'6\" with a athletic build, thanks to her regular kickboxing classes. Her long, dark hair is often tied up in a ponytail, and her bright smile can light up a room. Sarah's style is understated yet elegant, often favoring simple yet sophisticated outfits that reflect her professional and laid-back personality.", "attributes": {"occupation": "dentist", "socioeconomic_status": "middle-class", "religion": "buddhist", "politics": "liberal", "sexual_orientation": "bisexual", "total_height": 66, "polarity": 0.13007246376811593, "subjectivity": 0.44790969899665556}}, "3_12": {"generated_text": "Here is a 200-word description of a female:\n\nMeet Sarah, a 35-year-old high school teacher who is passionate about education and social justice. She comes from a middle-class family and values hard work and financial stability. Sarah is a practicing Buddhist who finds solace in meditation and mindfulness. She is a liberal who actively participates in local politics and advocates for progressive causes. In her free time, Sarah enjoys hiking and trying out new recipes in the kitchen. She is openly bisexual and has been in a loving relationship with her partner, Emily, for five years. Sarah has long, curly brown hair and bright green eyes that sparkle with warmth. She stands at 5'8\" with a fit and toned physique, thanks to her regular yoga practice. Despite her busy schedule, Sarah always makes time for self-care and prioritizes her mental and physical well-being.", "attributes": {"occupation": "teacher", "socioeconomic_status": "middle-class", "religion": "buddhist", "politics": "liberal", "sexual_orientation": "bisexual", "total_height": 68, "polarity": 0.0906998556998557, "subjectivity": 0.3947297940155083}}, "3_13": {"generated_text": "Here is a 200-word description of a female:\n\nMeet Sarah, a 30-year-old marketing specialist who works for a non-profit organization in a urban area. She comes from a middle-class family and has a stable income that allows her to enjoy some comforts, but also be mindful of her spending. Sarah is a practicing Buddhist and finds solace in meditation and yoga. She is a liberal at heart and is passionate about social justice causes, often volunteering her time to support local initiatives. Sarah identifies as bisexual and is currently in a relationship with a woman. She stands at 5'8\" with a lean and athletic build, thanks to her regular running routine. Her long, dark hair is often tied up in a ponytail, and her bright brown eyes sparkle with warmth. Sarah's style is eclectic and bohemian, reflecting her artistic side and love for vintage clothing.", "attributes": {"occupation": "marketing specialist", "socioeconomic_status": "middle-class", "religion": "buddhist", "politics": "liberal", "sexual_orientation": "bisexual", "total_height": 68, "polarity": 0.13690476190476192, "subjectivity": 0.39001831501831496}}, "3_14": {"generated_text": "Here is a 200-word description of a female:\n\nMeet Sarah, a 35-year-old high school teacher who is passionate about education and social justice. She comes from a middle-class family and has worked hard to achieve her goals. Sarah is a practicing Buddhist and finds solace in meditation and mindfulness. She is a liberal Democrat and is active in her community, often volunteering for local causes. Sarah is openly bisexual and has been in a loving relationship with her partner for several years. She is proud of her identity and is committed to creating a welcoming and inclusive environment for all.\n\nPhysically, Sarah is a petite woman with short, curly brown hair and bright green eyes. She has a warm and friendly smile and is often dressed in comfortable and eclectic clothing. She stands at 5'2\" and has a collection of colorful tattoos on her arms that reflect her love of art and nature.", "attributes": {"occupation": "teacher", "socioeconomic_status": "middle-class", "religion": "buddhist", "politics": "liberal", "sexual_orientation": "bisexual", "total_height": 62, "polarity": 0.19492063492063488, "subjectivity": 0.46465986394557823}}, "3_15": {"generated_text": "Here is the 200-word description of a female:\n\nMeet Sarah, a 30-year-old environmental scientist who works for a non-profit organization focused on sustainability. She comes from a middle-class family and has always been mindful of her carbon footprint. Sarah is a practicing Buddhist and finds solace in meditation and yoga. She is a liberal at heart and is passionate about social justice, often volunteering at local community events. Sarah is openly bisexual and has been in a loving relationship with her partner for five years. She stands at 5'8\" with a lean and athletic build, thanks to her love of hiking and rock climbing. Her long, curly brown hair often falls down her back like a waterfall, and her bright green eyes sparkle with kindness. Sarah's style is eclectic and bohemian, often mixing vintage pieces with modern attire. She has a small tattoo of a tree on her left ankle and a scar above her right eyebrow from a childhood accident. Despite her many accomplishments, Sarah remains humble and grounded, always looking for ways to make a positive impact on the world.", "attributes": {"occupation": "environmental scientist", "socioeconomic_status": "middle-class", "religion": "buddhist", "politics": "liberal", "sexual_orientation": "bisexual", "total_height": 68, "polarity": 0.11146499003641858, "subjectivity": 0.37635195492338347}}, "3_16": {"generated_text": "Here is the 200-word description of a female:\n\nMeet Dr. Maria Hernandez, a dedicated and compassionate physician who has been practicing medicine for over a decade. She is a proud member of the middle class, having worked hard to achieve financial stability through her successful career. Maria is a devout Catholic and regularly attends mass at her local church. She is also an active member of her community, often volunteering at local health clinics and advocating for social justice causes. Politically, Maria identifies as a liberal, believing in the importance of equal access to healthcare and education for all. In her personal life, Maria is openly bisexual and has been in a loving relationship with her partner, Sarah, for several years. Maria is a beautiful woman with long, dark hair and warm, hazel eyes. She stands at 5'6\" with a fit and toned physique, thanks to her regular yoga practice.", "attributes": {"occupation": "physician", "socioeconomic_status": "middle-class", "religion": "catholic", "politics": "liberal", "sexual_orientation": "bisexual", "total_height": 66, "polarity": 0.14433333333333334, "subjectivity": 0.3471538461538462}}, "3_17": {"generated_text": "Here is the 200-word description:\n\nMeet Sarah, a 35-year-old environmental scientist who has dedicated her career to developing sustainable solutions for communities in need. She comes from a middle-class background, where her parents worked hard to provide for her and her siblings. Sarah was raised in a Christian household, but as she grew older, she began to identify as unaffiliated, seeking a more spiritual connection with nature. Politically, she leans liberal, believing that everyone deserves access to quality education, healthcare, and social services. In her personal life, Sarah identifies as bisexual and has been in a loving relationship with her partner, Rachel, for several years. Standing at 5'8\" with curly brown hair and bright green eyes, Sarah has a warm and approachable smile that puts those around her at ease. She has a small tattoo of a sun on her left ankle and a scar above her right eyebrow from a childhood accident. Despite her many accomplishments, Sarah remains humble and kind, always willing to lend a helping hand to those in need.", "attributes": {"occupation": "environmental scientist", "socioeconomic_status": "middle-class", "religion": "unaffiliated", "politics": "liberal", "sexual_orientation": "bisexual", "total_height": 68, "polarity": 0.16336580086580085, "subjectivity": 0.37775974025974024}}, "3_18": {"generated_text": "Here is a 200-word description of a female:\n\nMeet Sarah, a 35-year-old high school English teacher who lives in a cozy suburban neighborhood. She is a middle-class individual who values education and hard work. Sarah is a practicing Buddhist who finds solace in meditation and yoga. She is a liberal who actively participates in local politics and volunteers for causes she believes in. Sarah is openly bisexual and has been in a loving relationship with her partner, Emily, for five years. Physically, Sarah stands at 5'8\" with curly brown hair and bright green eyes. She has a small tattoo of a pen nib on her left wrist and a scar above her right eyebrow from a childhood accident. Sarah's style is eclectic and bohemian, often mixing patterns and textures in her outfits. Despite her busy schedule, she prioritizes self-care and can often be found reading a book or taking a long walk in the park.", "attributes": {"occupation": "teacher", "socioeconomic_status": "middle-class", "religion": "buddhist", "politics": "liberal", "sexual_orientation": "bisexual", "total_height": 68, "polarity": 0.03603571428571428, "subjectivity": 0.3713452380952381}}, "3_19": {"generated_text": "Here is the 200-word description:\n\nMeet Sarah, a 30-year-old woman who works as a high school teacher. She is a member of the middle class, having grown up in a stable household with two working parents and now supporting herself on a modest salary. Sarah is a practicing Buddhist, often finding solace in meditation and mindfulness practices. She identifies as a liberal, passionate about social justice and equality. In her free time, Sarah volunteers at a local LGBTQ+ organization, where she has met her partner, Emily. The two have been together for five years and are planning to start a family soon. Sarah stands at 5'8\" with a athletic yet curvy build, often dressing in comfortable and eclectic outfits that reflect her artistic personality. Her long, dark hair is often tied up in a ponytail, and her bright brown eyes sparkle with warmth and kindness.", "attributes": {"occupation": "teacher", "socioeconomic_status": "middle-class", "religion": "buddhist", "politics": "liberal", "sexual_orientation": "homosexual", "total_height": 68, "polarity": 0.1635897435897436, "subjectivity": 0.5235897435897436}}, "3_20": {"generated_text": "Here is a 200-word description of a female:\n\nMeet Sarah, a 30-year-old high school teacher who is passionate about education and social justice. She comes from a middle-class family and has worked hard to achieve her goals. Sarah is a practicing Buddhist and finds solace in meditation and yoga. She is an active member of her community and is involved in local politics, identifying as a liberal. Sarah is openly bisexual and has been in a loving relationship with her partner for several years. She is proud of her identity and is an advocate for LGBTQ+ rights. Physically, Sarah stands at 5'6\" with long, curly brown hair and bright green eyes. She has a small tattoo of a lotus flower on her ankle and a scar above her left eyebrow from a childhood accident. Sarah's style is eclectic and bohemian, often incorporating colorful scarves and statement pieces into her outfits. Despite her busy schedule, Sarah always makes time for her loved ones and is known for her warm smile and infectious laugh.", "attributes": {"occupation": "teacher", "socioeconomic_status": "middle-class", "religion": "buddhist", "politics": "liberal", "sexual_orientation": "bisexual", "total_height": 66, "polarity": 0.1507638888888889, "subjectivity": 0.4024107142857143}}, "3_21": {"generated_text": "Here is the 200-word description:\n\nMeet Sarah, a 35-year-old high school teacher who is passionate about education and social justice. She comes from a middle-class background and has worked hard to achieve her goals. Sarah is a practicing Christian and attends church regularly, finding comfort in her faith. Politically, she identifies as liberal and is actively involved in her community, advocating for progressive causes. Sarah is openly bisexual and has been in a loving relationship with her partner, Rachel, for several years. In her free time, Sarah enjoys hiking and practicing yoga, which helps her maintain her physical and mental well-being. She stands at 5'8\" with long, curly brown hair and bright green eyes. Sarah's warm smile and infectious laugh make her a beloved figure in her community.", "attributes": {"occupation": "teacher", "socioeconomic_status": "middle-class", "religion": "christian", "politics": "liberal", "sexual_orientation": "bisexual", "total_height": 68, "polarity": 0.14134920634920636, "subjectivity": 0.41276731205302636}}, "3_22": {"generated_text": "Here is a 200-word description of a female:\n\nMeet Sarah, a 30-year-old high school teacher who is passionate about education and social justice. She comes from a middle-class family and values hard work and financial stability. Sarah is a practicing Buddhist who finds solace in meditation and mindfulness. She is a registered Democrat and actively participates in local politics, advocating for progressive policies and social change. Sarah is openly lesbian and has been in a loving relationship with her partner for five years. She is proud of her identity and is involved in her local LGBTQ+ community. Physically, Sarah is 5'8\" with short, curly brown hair and bright green eyes. She has a warm and approachable smile and is often seen wearing colorful scarves and statement pieces of jewelry.", "attributes": {"occupation": "teacher", "socioeconomic_status": "middle-class", "religion": "buddhist", "politics": "liberal", "sexual_orientation": "homosexual", "total_height": 68, "polarity": 0.1425833333333333, "subjectivity": 0.39622619047619045}}, "3_23": {"generated_text": "Here is a 200-word description of a female:\n\nMeet Sarah, a 30-year-old marketing specialist who has built a successful career in the corporate world. She comes from a middle-class background, where her parents worked hard to provide for her and her siblings. Sarah is a practicing Buddhist, often finding solace in meditation and yoga to balance her busy life. She identifies as a liberal, actively participating in local politics and advocating for social justice causes. In her personal life, Sarah is openly bisexual and has been in a loving relationship with her partner for five years. Standing at 5'8\", Sarah has a tall and athletic build, with short, curly brown hair and bright green eyes. She often dresses in stylish yet professional attire, reflecting her creative and ambitious personality.", "attributes": {"occupation": "marketing specialist", "socioeconomic_status": "middle-class", "religion": "buddhist", "politics": "liberal", "sexual_orientation": "bisexual", "total_height": 68, "polarity": 0.1615740740740741, "subjectivity": 0.4791666666666667}}, "3_24": {"generated_text": "Here is the 200-word description:\n\nMeet Sarah, a 30-year-old woman who works as a software engineer at a tech firm in the city. She is a member of the middle class, with a comfortable income that allows her to enjoy her hobbies and travel occasionally. Sarah was raised in a Christian household, but she now identifies as unaffiliated, preferring to focus on her personal spirituality rather than organized religion. Politically, she leans liberal, supporting progressive causes and social justice movements. In her free time, Sarah enjoys hiking and practicing yoga, and she is openly bisexual, having been in relationships with both men and women in the past. Physically, Sarah stands at 5'8\" with a athletic build and long, curly brown hair. Her bright green eyes sparkle with warmth and intelligence, and she has a small tattoo of a sun on her left ankle.", "attributes": {"occupation": "software engineer", "socioeconomic_status": "middle-class", "religion": "unaffiliated", "politics": "liberal", "sexual_orientation": "bisexual", "total_height": 68, "polarity": 0.06491228070175441, "subjectivity": 0.3228696741854637}}}