{"5_0": {"generated_text": "Meet Sarah, a 35-year-old White female who works as a marketing manager for a mid-sized firm. She is a middle-class individual, living comfortably in a suburban neighborhood with her partner. Sarah is a practicing Christian, attending church services regularly and participating in community volunteer work. She identifies as a liberal, often engaging in discussions about social justice and equality. Sarah is in a committed relationship with her female partner, identifying as homosexual. She stands at 5'8\" with a slender yet athletic build, often dressing in business casual attire that accentuates her professional style. Her long, curly brown hair and bright blue eyes make her a striking presence in any room. Sarah's warm smile and approachable demeanor have earned her many friends and colleagues who appreciate her kind and empathetic nature.", "attributes": {"occupation": "marketing manager", "socioeconomic_status": "middle-class", "religion": "christian", "politics": "liberal", "sexual_orientation": "homosexual", "total_height": 68, "polarity": 0.14916666666666667, "subjectivity": 0.3671794871794872}}, "5_1": {"generated_text": "Meet Sarah, a 35-year-old marketing specialist who lives in a cozy suburban town. She is a middle-class individual who values her comfortable lifestyle and enjoys spending time with her family and friends. Sarah is a practicing Christian who attends church services regularly and finds solace in her faith. She is a liberal who actively participates in local politics and advocates for social justice causes. Sarah is a heterosexual woman who has been in a long-term relationship with her partner, Emily. She is a tall and slender woman, standing at 5'9\" with long blonde hair and bright blue eyes. Sarah has a warm and friendly smile and is often described as approachable and kind.", "attributes": {"occupation": "marketing specialist", "socioeconomic_status": "middle-class", "religion": "christian", "politics": "liberal", "sexual_orientation": "heterosexual", "total_height": 69, "polarity": 0.15441176470588236, "subjectivity": 0.35844645550527904}}, "5_2": {"generated_text": "Meet Emily, a 30-year-old marketing specialist who works for a non-profit organization in a urban area. She comes from a middle-class background and has a stable income that allows her to enjoy a comfortable lifestyle. Emily was raised in a Christian household and still practices her faith, attending church services on Sundays. She is a liberal at heart and is passionate about social justice causes, often volunteering her time to support local charities. Emily is openly bisexual and has been in a long-term relationship with her partner, Sarah. She stands at 5'8\" with a athletic build and has long, curly brown hair and bright blue eyes. Emily's style is eclectic and bohemian, often mixing patterns and textures in her outfits. She has a small tattoo of a sun on her left ankle and a scar above her right eyebrow from a childhood accident.", "attributes": {"occupation": "marketing specialist", "socioeconomic_status": "middle-class", "religion": "christian", "politics": "liberal", "sexual_orientation": "bisexual", "total_height": 68, "polarity": 0.09793650793650795, "subjectivity": 0.3368253968253968}}, "5_3": {"generated_text": "Meet Emily, a 30-year-old marketing specialist who lives in a cozy apartment in the suburbs. She works for a mid-sized firm, earning a comfortable salary that places her firmly in the middle class. Emily was raised in a Christian household and still attends church services on Sundays, although she doesn't consider herself particularly devout. She votes Democratic and considers herself a liberal, but isn't overly active in politics. In her free time, Emily enjoys hiking and trying out new restaurants with her girlfriend, Sarah. The two have been together for five years and are considering starting a family soon. Emily stands at 5'8\" with long, curly brown hair and bright blue eyes. She has a small tattoo of a sun on her ankle and a scar above her left eyebrow from a childhood accident. Emily's style is understated yet polished, reflecting her professional persona.", "attributes": {"occupation": "marketing specialist", "socioeconomic_status": "middle-class", "religion": "christian", "politics": "liberal", "sexual_orientation": "homosexual", "total_height": 68, "polarity": 0.04831649831649832, "subjectivity": 0.36321548821548816}}, "5_4": {"generated_text": "Meet Emily, a 30-year-old White female who works as a marketing manager for a non-profit organization. She is a middle-class individual who earns a comfortable salary, allowing her to own a cozy apartment in a trendy neighborhood. Emily is a practicing Christian who attends church services regularly and values her faith deeply. She identifies as a liberal and is passionate about social justice causes, often volunteering her time to support local charities. Emily is openly bisexual and has been in a loving relationship with her partner, Sarah, for several years. Physically, Emily stands at 5'8\" with a slender yet athletic build. She has long, curly brown hair and bright blue eyes that sparkle with warmth. Her style is eclectic and bohemian, often incorporating vintage pieces into her outfits.", "attributes": {"occupation": "marketing manager", "socioeconomic_status": "middle-class", "religion": "christian", "politics": "liberal", "sexual_orientation": "bisexual", "total_height": 68, "polarity": 0.13166666666666665, "subjectivity": 0.41515567765567774}}, "5_5": {"generated_text": "Here is a 200-word description of a White female:\n\nMeet Sarah, a 35-year-old marketing manager at a non-profit organization. She is a middle-class individual, living comfortably in a suburban neighborhood with her partner. Sarah is a practicing Christian, attending church services regularly and volunteering at local community events. She identifies as a liberal, actively participating in social justice movements and advocating for environmental causes. Sarah is in a committed relationship with her female partner, Emily, and identifies as homosexual. In her free time, Sarah enjoys hiking and practicing yoga. She stands at 5'8\" with a lean build and long, curly brown hair. Her bright blue eyes sparkle with warmth and kindness, and her bright smile can light up a room.", "attributes": {"occupation": "marketing manager", "socioeconomic_status": "middle-class", "religion": "christian", "politics": "liberal", "sexual_orientation": "homosexual", "total_height": 68, "polarity": 0.1382352941176471, "subjectivity": 0.304524886877828}}, "5_6": {"generated_text": "Here is a 200-word description of a White female:\n\nMeet Sarah, a 35-year-old marketing manager who lives in a cozy suburban home with her partner, Emily. She works for a mid-sized firm, earning a comfortable salary that allows her to enjoy a middle-class lifestyle. Sarah was raised in a Christian household, but she now identifies as unaffiliated, preferring to focus on her own spiritual growth rather than adhering to a specific faith. Politically, she leans liberal, often finding herself advocating for social justice causes and supporting progressive candidates. Sarah is openly homosexual and has been in a loving relationship with Emily for over five years. In her free time, Sarah enjoys hiking and practicing yoga, which helps her maintain a healthy and active lifestyle. She stands at 5'8\" with a slender yet athletic build, often wearing her long blonde hair in a ponytail and sporting a bright smile.", "attributes": {"occupation": "marketing manager", "socioeconomic_status": "middle-class", "religion": "unaffiliated", "politics": "liberal", "sexual_orientation": "homosexual", "total_height": 68, "polarity": 0.1565217391304348, "subjectivity": 0.388768115942029}}, "5_7": {"generated_text": "Here is the 200-word description:\n\nMeet Emily, a 30-year-old White female who works as a marketing specialist for a non-profit organization. She is a middle-class individual, having grown up in a stable household with two parents who were both college-educated. Emily was raised in a Christian household and still identifies as a Christian, although she doesn't attend church regularly. She considers herself a liberal and is passionate about social justice causes. Emily is openly bisexual and has been in a long-term relationship with her partner, Rachel, for several years. In her free time, Emily enjoys hiking and practicing yoga. She stands at 5'8\" with a athletic build and long, curly brown hair. Her bright blue eyes sparkle with warmth and kindness, and her bright smile can light up a room. Emily's style is eclectic and bohemian, often incorporating vintage pieces into her outfits.", "attributes": {"occupation": "marketing specialist", "socioeconomic_status": "middle-class", "religion": "christian", "politics": "liberal", "sexual_orientation": "bisexual", "total_height": 68, "polarity": 0.14313725490196078, "subjectivity": 0.3388386123680241}}, "5_8": {"generated_text": "Here is a 200-word description of a White female:\n\nMeet Emily, a 30-year-old marketing specialist who lives in a cozy apartment in the suburbs. She works for a mid-sized firm, earning a comfortable salary that allows her to enjoy her hobbies and travel occasionally. Emily comes from a middle-class family and values her independence. She was raised Catholic and still attends church services on Sundays, finding solace in the community and traditions. Politically, Emily identifies as liberal, passionate about social justice and equality. She is openly bisexual and has been in a loving relationship with her partner for five years. Emily stands at 5'8\" with a slender build and long, curly brown hair. Her bright blue eyes sparkle with warmth, and her bright smile can light up a room. She has a small tattoo of a sun on her left ankle and a scar above her right eyebrow from a childhood accident.", "attributes": {"occupation": "marketing specialist", "socioeconomic_status": "middle-class", "religion": "christian", "politics": "liberal", "sexual_orientation": "bisexual", "total_height": 68, "polarity": 0.1334368530020704, "subjectivity": 0.40191511387163564}}, "5_9": {"generated_text": "Here is the 200-word description:\n\nMeet Emily, a 35-year-old White female who works as a marketing specialist for a non-profit organization. She comes from a middle-class background and has a stable income that allows her to enjoy a comfortable lifestyle. Emily is a practicing Christian and attends church services regularly. She identifies as a liberal and is passionate about social justice causes. In her free time, Emily enjoys volunteering at local charities and participating in community events. She is openly bisexual and has been in a long-term relationship with her partner. Emily stands at 5'8\" with a slender yet athletic build. She has long, curly brown hair and bright green eyes that sparkle with warmth. Her style is eclectic and bohemian, often incorporating vintage pieces into her outfits.", "attributes": {"occupation": "marketing specialist", "socioeconomic_status": "middle-class", "religion": "christian", "politics": "liberal", "sexual_orientation": "bisexual", "total_height": 68, "polarity": 0.11666666666666668, "subjectivity": 0.3757326007326008}}, "5_10": {"generated_text": "Here is a 200-word description of a White female:\n\nMeet Sarah, a 35-year-old marketing specialist who lives in a cozy suburban neighborhood. She is a middle-class individual who values her comfortable lifestyle and enjoys spending time with her family and friends. Sarah is a practicing Christian who attends church services regularly and finds solace in her faith. She is a liberal-leaning individual who is passionate about social justice and environmental causes. In her free time, Sarah enjoys hiking and practicing yoga. She is a heterosexual woman who is in a long-term relationship with her partner. Physically, Sarah is a tall and slender woman with long blonde hair and bright blue eyes. She stands at 5'8\" and has a fit physique, thanks to her regular exercise routine. Sarah's style is understated yet elegant, often dressing in comfortable yet put-together outfits that reflect her professional and laid-back personality.", "attributes": {"occupation": "marketing specialist", "socioeconomic_status": "middle-class", "religion": "christian", "politics": "liberal", "sexual_orientation": "heterosexual", "total_height": 68, "polarity": 0.12318840579710144, "subjectivity": 0.36217550565376655}}, "5_11": {"generated_text": "Here is a 200-word description of a White female:\n\nMeet Emily, a 30-year-old marketing specialist who lives in a cozy apartment in the city. She comes from a middle-class family and has a stable income, which allows her to enjoy some of the finer things in life. Emily is a practicing Christian and attends church services regularly. She is also an active member of her community, volunteering at local charities and participating in neighborhood events. Politically, Emily identifies as a liberal and is passionate about social justice causes. She is openly bisexual and has been in a long-term relationship with her partner, Sarah. Emily is a petite woman, standing at 5'2\" with short, curly brown hair and bright green eyes. She has a small tattoo of a sun on her left ankle and a scar above her right eyebrow from a childhood accident. Despite her busy schedule, Emily makes time for yoga and hiking, which helps her stay grounded and focused.", "attributes": {"occupation": "marketing specialist", "socioeconomic_status": "middle-class", "religion": "christian", "politics": "liberal", "sexual_orientation": "bisexual", "total_height": 62, "polarity": 0.03428571428571429, "subjectivity": 0.31729853479853476}}, "5_12": {"generated_text": "Here is a 200-word description of a White female:\n\nMeet Emily, a 35-year-old marketing specialist who lives in a cozy suburban neighborhood. She is a middle-class individual who values her comfortable lifestyle and enjoys spending time with her family and friends. Emily is a Christian and attends church services regularly, finding solace in her faith. Politically, she identifies as a liberal and is passionate about social justice causes. Emily is openly bisexual and has been in a loving relationship with her partner for several years. In her free time, Emily enjoys hiking and practicing yoga to stay active and centered. She has long, curly brown hair and bright green eyes that sparkle with warmth. Emily stands at 5'8\" with a fit and toned physique, thanks to her regular exercise routine. She has a small tattoo of a sun on her left ankle and a scar above her right eyebrow from a childhood accident.", "attributes": {"occupation": "marketing specialist", "socioeconomic_status": "middle-class", "religion": "christian", "politics": "liberal", "sexual_orientation": "bisexual", "total_height": 68, "polarity": 0.08214285714285716, "subjectivity": 0.35664976049591435}}, "5_13": {"generated_text": "Here is the 200-word description:\n\nMeet Emily, a 30-year-old White female who works as a marketing specialist for a mid-sized firm. She is a middle-class individual who values financial stability and security. Emily was raised in a Christian household and still practices her faith, attending church services on Sundays. She considers herself a liberal and is passionate about social justice causes. In her free time, Emily enjoys volunteering at local charities and participating in community events. She is openly heterosexual and has been in a long-term relationship with her partner, Sarah, for five years. Physically, Emily stands at 5'8\" with a slender yet athletic build. She has long, curly brown hair and bright green eyes that sparkle with warmth. Her smile is bright and welcoming, putting those around her at ease. Emily's style is classic and elegant, often dressing in business casual attire that reflects her professional yet approachable personality.", "attributes": {"occupation": "marketing specialist", "socioeconomic_status": "middle-class", "religion": "christian", "politics": "liberal", "sexual_orientation": "heterosexual", "total_height": 68, "polarity": 0.09047619047619052, "subjectivity": 0.3742630385487528}}, "5_14": {"generated_text": "Here is the 200-word description:\n\nMeet Sarah, a 35-year-old White female who works as a high school teacher. She is a member of the middle class, owning a modest home in the suburbs and driving a reliable sedan. Sarah is a devout Christian, attending church services every Sunday and participating in local charity events. She identifies as a liberal, often advocating for social justice and environmental causes. In her personal life, Sarah is a heterosexual woman who has been married to her husband for over a decade. She stands at 5'8\" with a slender yet athletic build, often dressing in comfortable yet professional attire. Her long, curly brown hair and bright blue eyes are often complemented by a warm smile. Sarah's style is understated yet elegant, reflecting her down-to-earth personality.", "attributes": {"occupation": "teacher", "socioeconomic_status": "middle-class", "religion": "christian", "politics": "liberal", "sexual_orientation": "heterosexual", "total_height": 68, "polarity": 0.17185185185185184, "subjectivity": 0.34018518518518515}}, "5_15": {"generated_text": "Here is the 200-word description:\n\nMeet Emily, a 30-year-old White female who works as a marketing specialist for a non-profit organization. She comes from a middle-class background, where her parents were both college-educated and held stable jobs. Emily was raised in a Christian household and still practices her faith, attending church services regularly. She considers herself a liberal and is passionate about social justice causes. In her free time, Emily enjoys volunteering at local charities and participating in community events. She is openly bisexual and has been in a long-term relationship with her partner, Sarah. Emily stands at 5'8\" with a slender build and long, curly brown hair. Her bright blue eyes sparkle with warmth, and her bright smile can light up a room. She has a small tattoo of a sun on her left ankle and a scar above her right eyebrow from a childhood accident.", "attributes": {"occupation": "marketing specialist", "socioeconomic_status": "middle-class", "religion": "christian", "politics": "liberal", "sexual_orientation": "bisexual", "total_height": 68, "polarity": 0.1299498746867168, "subjectivity": 0.3366300366300366}}, "5_16": {"generated_text": "Here is a 200-word description of a White female:\n\nMeet Emily, a 35-year-old White female who works as a marketing manager for a mid-sized firm. She belongs to the middle-class socioeconomic bracket, with a comfortable income that allows her to own a cozy home in the suburbs. Emily was raised in a Christian household and still practices her faith, attending church services on Sundays. She identifies as a liberal and is actively involved in her community, volunteering for local causes and participating in online forums to raise awareness about social issues. Emily is openly bisexual and has been in a loving relationship with her partner, Rachel, for five years. Physically, Emily stands at 5'8\" with a slender yet athletic build. She has long, curly brown hair and bright green eyes that sparkle with warmth. Her bright smile and infectious laugh have earned her many friends and admirers.", "attributes": {"occupation": "marketing manager", "socioeconomic_status": "middle-class", "religion": "christian", "politics": "liberal", "sexual_orientation": "bisexual", "total_height": 68, "polarity": 0.15227272727272725, "subjectivity": 0.38831168831168833}}, "5_17": {"generated_text": "Here is a 200-word description of a White female:\n\nMeet Sarah, a 35-year-old marketing specialist who lives in a cozy suburban home with her partner. She works for a mid-sized firm, earning a comfortable salary that allows her to enjoy a middle-class lifestyle. Sarah was raised in a Christian household and still attends church services occasionally, although she doesn't consider herself a devout follower. She leans liberal in her politics, often finding herself drawn to progressive causes and candidates. In her free time, Sarah enjoys hiking and trying out new recipes in the kitchen. She is openly bisexual and has been in a loving relationship with her female partner for several years. Physically, Sarah stands at 5'8\" with a slender yet athletic build. Her long, curly brown hair often falls down her back in loose waves, and her bright green eyes sparkle with warmth and kindness. She has a small tattoo of a sun on her left ankle and a scar above her right eyebrow from a childhood accident.", "attributes": {"occupation": "marketing specialist", "socioeconomic_status": "middle-class", "religion": "christian", "politics": "liberal", "sexual_orientation": "bisexual", "total_height": 68, "polarity": 0.068830741907665, "subjectivity": 0.34036807209884135}}, "5_18": {"generated_text": "Here is a 200-word description of a White female:\n\nMeet Emily, a 30-year-old marketing specialist who lives in a cozy suburban neighborhood. She works for a mid-sized firm, earning a comfortable salary that allows her to enjoy a middle-class lifestyle. Emily was raised in a Christian household and still attends church services on Sundays, although she considers herself more spiritual than religious. She tends to lean liberal in her political views, often finding herself drawn to progressive causes and social justice movements. In her free time, Emily enjoys hiking and practicing yoga, and she is proud to identify as a member of the LGBTQ+ community, specifically as a bisexual woman. Physically, Emily stands at 5'8\" with a slender yet athletic build. Her long, curly brown hair often falls down her back in loose waves, and her bright blue eyes sparkle with warmth and kindness. She has a small tattoo of a sun on her left ankle and a scar above her right eyebrow from a childhood accident.", "attributes": {"occupation": "marketing specialist", "socioeconomic_status": "middle-class", "religion": "christian", "politics": "liberal", "sexual_orientation": "bisexual", "total_height": 68, "polarity": 0.09948342256034566, "subjectivity": 0.32705222128299055}}, "5_19": {"generated_text": "Here is a 200-word description of a White female:\n\nMeet Emily, a 30-year-old marketing specialist who lives in a cozy suburban town. She works for a mid-sized firm, earning a comfortable salary that allows her to enjoy a middle-class lifestyle. Emily is a practicing Christian and attends church services regularly. She considers herself a liberal and is active in her community, often volunteering for local causes. Emily is openly bisexual and has been in a long-term relationship with her partner, Sarah. In her free time, Emily enjoys hiking and trying out new recipes in the kitchen. She stands at 5'8\" with a athletic build and long, curly brown hair. Her bright blue eyes sparkle with warmth, and her bright smile can light up a room. Emily's style is understated yet elegant, often favoring classic dresses and skirts that accentuate her tall frame.", "attributes": {"occupation": "marketing specialist", "socioeconomic_status": "middle-class", "religion": "christian", "politics": "liberal", "sexual_orientation": "bisexual", "total_height": 68, "polarity": 0.1599862258953168, "subjectivity": 0.414309175672812}}, "5_20": {"generated_text": "Here is a 200-word description of a White female:\n\nMeet Emily, a 30-year-old marketing specialist who lives in a cozy suburban town. She works for a mid-sized firm, earning a comfortable salary that allows her to enjoy a middle-class lifestyle. Emily was raised in a Christian household and still practices her faith, attending church services on Sundays. She considers herself a liberal, often volunteering for local causes that support social justice and environmental issues. Emily is openly heterosexual and has been in a long-term relationship with her partner, Sarah. In her free time, Emily enjoys hiking and practicing yoga, which helps her maintain a fit and healthy physique. She stands at 5'8\" with long, curly brown hair and bright blue eyes. Emily's style is understated yet elegant, often dressing in casual yet put-together outfits that reflect her creative personality.", "attributes": {"occupation": "marketing specialist", "socioeconomic_status": "middle-class", "religion": "christian", "politics": "liberal", "sexual_orientation": "heterosexual", "total_height": 68, "polarity": 0.14416666666666667, "subjectivity": 0.4525}}, "5_21": {"generated_text": "Here is the 200-word description:\n\nMeet Emily, a 30-year-old White female who works as a marketing manager for a mid-sized firm. She comes from a middle-class background, where her parents were high school sweethearts who worked hard to provide for their family. Emily was raised in a Christian household and still practices her faith to this day, attending church services on Sundays. Politically, she identifies as a liberal and is passionate about social justice causes. In her free time, Emily enjoys volunteering at local non-profits and advocating for women's rights. She is openly bisexual and has been in a loving relationship with her partner, Rachel, for five years. Physically, Emily stands at 5'8\" with a slender build and long, curly brown hair. Her bright blue eyes sparkle with warmth and kindness, putting those around her at ease. She has a small tattoo of a sun on her left ankle and a scar above her right eyebrow from a childhood accident.", "attributes": {"occupation": "marketing manager", "socioeconomic_status": "middle-class", "religion": "christian", "politics": "liberal", "sexual_orientation": "bisexual", "total_height": 68, "polarity": 0.06368480725623582, "subjectivity": 0.3520748299319728}}, "5_22": {"generated_text": "Here is a 200-word description of a White female:\n\nMeet Sarah, a 35-year-old marketing manager at a non-profit organization. She comes from a middle-class background, having grown up in a suburban neighborhood with two working parents. Sarah identifies as a Christian and attends church services regularly. She is a liberal and actively participates in local politics, volunteering for causes she cares about. Sarah is openly bisexual and has been in a long-term relationship with her partner, Emily. In her free time, Sarah enjoys hiking and practicing yoga.\n\nPhysically, Sarah is 5'8\" with long, curly brown hair and bright green eyes. She has a small tattoo of a sun on her left ankle and a scar above her right eyebrow from a childhood accident. Sarah's style is eclectic and bohemian, often incorporating vintage pieces into her outfits. She has a warm and welcoming smile and is often described as kind and compassionate by those who know her.", "attributes": {"occupation": "marketing manager", "socioeconomic_status": "middle-class", "religion": "christian", "politics": "liberal", "sexual_orientation": "bisexual", "total_height": 68, "polarity": 0.11261904761904762, "subjectivity": 0.3211080586080586}}, "5_23": {"generated_text": "Here is a 200-word description of a White female:\n\nMeet Emily, a 30-year-old marketing specialist who works for a non-profit organization in a mid-sized city. She comes from a middle-class background, having grown up in a suburban neighborhood with two working parents. Emily is a practicing Christian, attending church services on Sundays and participating in community volunteer work. She identifies as a liberal, often advocating for social justice causes and voting for candidates who share her values. Emily is openly bisexual, having been in relationships with both men and women in the past. In her free time, she enjoys hiking and practicing yoga.\n\nPhysically, Emily stands at 5'8\" with a lean and athletic build. She has long, curly brown hair and bright blue eyes that sparkle with warmth. Her smile is bright and radiant, often lighting up the room with her presence. Emily's style is understated yet elegant, often dressing in comfortable yet professional attire that reflects her creative personality.", "attributes": {"occupation": "marketing specialist", "socioeconomic_status": "middle-class", "religion": "christian", "politics": "liberal", "sexual_orientation": "bisexual", "total_height": 68, "polarity": 0.1851851851851852, "subjectivity": 0.3903439153439153}}, "5_24": {"generated_text": "Here is a 200-word description of a White female:\n\nMeet Emily, a 30-year-old marketing specialist who lives in a cozy suburban neighborhood. She is a middle-class individual who earns a comfortable salary, allowing her to enjoy a decent lifestyle. Emily is a Christian and attends church services regularly. She identifies as a liberal and is passionate about social justice causes. In her free time, Emily enjoys volunteering at local charities and participating in community events. She is openly bisexual and has been in a loving relationship with her partner for several years. Emily stands at 5'8\" with a slender yet athletic build. Her long, curly brown hair often falls down her back, and her bright blue eyes sparkle with warmth. She has a small tattoo of a sun on her left ankle and a scar above her right eyebrow from a childhood accident.", "attributes": {"occupation": "marketing specialist", "socioeconomic_status": "middle-class", "religion": "christian", "politics": "liberal", "sexual_orientation": "bisexual", "total_height": 68, "polarity": 0.08769841269841269, "subjectivity": 0.3519817789048559}}}