{"245_0": {"generated_text": "Tenzin is a 30-year-old Buddhist monk who lives in a small monastery in the Himalayas. As a monk, Tenzin's occupation is focused on spiritual development and serving the community. Despite the monastery's simple living conditions, Tenzin's socioeconomic status is relatively stable, as the monastery is supported by donations from the local community. Tenzin's days are filled with meditation, prayer, and study, as well as helping with daily chores and teaching young monks. In his free time, Tenzin enjoys hiking and reading about philosophy and politics. He is a liberal thinker who values social justice and equality. Tenzin is openly gay and has found acceptance within his community. He stands at 5'8\" with a lean build and has a shaved head, which is a traditional style for Buddhist monks. His bright brown eyes sparkle with kindness, and his warm smile puts everyone at ease.", "attributes": {"occupation": "monk", "socioeconomic_status": "middle-class", "religion": "buddhist", "politics": "liberal", "sexual_orientation": "homosexual", "total_height": 68, "polarity": 0.18000000000000002, "subjectivity": 0.39269841269841266}}, "245_1": {"generated_text": "Tenzin is a 30-year-old Buddhist monk who lives in a small monastery in the Himalayas. As a monk, Tenzin's occupation is to study and teach Buddhist scriptures, as well as to perform various rituals and ceremonies for the local community. Despite the monastery's modest means, Tenzin's socioeconomic status is relatively stable, as the monastery is supported by donations from wealthy patrons. Tenzin's days are filled with meditation, study, and physical labor, and they take great joy in serving others. In their free time, Tenzin enjoys hiking and reading about philosophy and politics. While Tenzin is not actively involved in politics, they lean towards liberal ideologies that promote social justice and equality. Tenzin is openly gay and has found a sense of acceptance and community within the monastery. Physically, Tenzin is of average height, with a shaved head and a warm, gentle smile. They have a small tattoo of the Buddhist wheel of dharma on their left ankle.", "attributes": {"occupation": "monk", "socioeconomic_status": "middle-class", "religion": "buddhist", "politics": "liberal", "sexual_orientation": "homosexual", "total_height": 68, "polarity": 0.18888888888888888, "subjectivity": 0.44217687074829926}}, "245_2": {"generated_text": "Tenzin is a 30-year-old monk who lives in a small monastery in the Himalayas. As a monk, Tenzin's occupation is centered around spiritual growth and community service. Despite the simple living arrangements, Tenzin's socioeconomic status is middle-class due to the monastery's modest but stable income from donations and agriculture. Tenzin is a devout Buddhist, and their daily routine is filled with meditation, prayer, and study of sacred texts. Politically, Tenzin leans towards a neutral stance, focusing on inner peace and compassion rather than worldly affairs. In their personal life, Tenzin identifies as homosexual, although this aspect of their identity is not publicly disclosed due to the conservative nature of their community. Physically, Tenzin stands at 5'8\" with a lean and athletic build, honed from years of hiking and physical labor. Their dark hair is shaved close to the head, and their bright brown eyes sparkle with warmth and kindness.", "attributes": {"occupation": "monk", "socioeconomic_status": "middle-class", "religion": "buddhist", "politics": "neutral", "sexual_orientation": "homosexual", "total_height": 68, "polarity": 0.034375, "subjectivity": 0.34747023809523814}}, "245_3": {"generated_text": "Tenzin is a 30-year-old monk who resides in a small monastery in the Himalayas. As a member of the monastic community, Tenzin's occupation is that of a spiritual leader and teacher. They spend their days studying ancient scriptures, meditating, and guiding fellow monks on their spiritual journeys. Tenzin's socioeconomic status is modest, as they have taken a vow of poverty and rely on donations from the community to sustain themselves. They are a devout Buddhist, and their faith plays a central role in their daily life. Politically, Tenzin is neutral, focusing more on spiritual matters than worldly politics. They identify as homosexual, although this aspect of their identity is not widely known or discussed within the monastic community. Physically, Tenzin stands at 5'8\" with a lean and athletic build, developed from years of hiking and manual labor. Their dark hair is shaved close to the head, and their eyes are a deep, piercing brown that seem to see right through to the soul.", "attributes": {"occupation": "monk", "socioeconomic_status": "lower-class", "religion": "buddhist", "politics": "neutral", "sexual_orientation": "homosexual", "total_height": 68, "polarity": 0.04238095238095238, "subjectivity": 0.31523809523809526}}, "245_4": {"generated_text": "Tenzin is a 30-year-old Buddhist monk who lives in a small monastery in the Himalayas. As a monk, Tenzin's occupation is to study and teach Buddhist scriptures, as well as to perform various rituals and ceremonies. Despite living a simple life, Tenzin comes from a middle-class family and has access to basic amenities. Tenzin's family has been Buddhist for generations, and he was ordained as a monk at a young age. Politically, Tenzin is neutral and focuses on spiritual pursuits rather than worldly affairs. In his free time, Tenzin enjoys hiking and meditation. He is openly gay and has found acceptance within his monastic community. Physically, Tenzin is of average height, standing at 5'8\" with a lean build. He has short, shaved hair and piercing brown eyes that seem to see right through to the soul.", "attributes": {"occupation": "monk", "socioeconomic_status": "middle-class", "religion": "buddhist", "politics": "neutral", "sexual_orientation": "homosexual", "total_height": 68, "polarity": 0.061721611721611724, "subjectivity": 0.3674908424908425}}, "246_0": {"generated_text": "Selina is a 30-year-old freelance graphic designer who has built a successful career working with clients from all over the world. She is a middle-class individual who values financial stability and independence. Selina was raised in a Christian household, but she identifies as unaffiliated and doesn't practice any particular religion. She is a liberal at heart and is passionate about social justice and human rights. Selina is openly bisexual and has been in a loving relationship with her partner for several years. She is a creative and expressive person who loves art, music, and fashion. Selina stands at 5'8\" with a lean and athletic build. She has short, spiky black hair and piercing green eyes that seem to sparkle with creativity. She often wears bold and eclectic outfits that reflect her artistic personality.", "attributes": {"occupation": "graphic designer", "socioeconomic_status": "middle-class", "religion": "unaffiliated", "politics": "liberal", "sexual_orientation": "bisexual", "total_height": 68, "polarity": 0.1631578947368421, "subjectivity": 0.4868421052631579}}, "246_1": {"generated_text": "Selina is a 30-year-old graphic designer who has built a successful career in the creative industry. She comes from a middle-class family and has always been grateful for the opportunities she has had. Selina is a practicing Buddhist and values the principles of mindfulness and compassion that guide her faith. She is also an active member of her community, volunteering at local art programs and advocating for social justice causes. Politically, Selina identifies as a liberal and is passionate about issues related to equality and environmental sustainability. In her personal life, Selina is openly bisexual and has been in a loving relationship with her partner for several years. Physically, Selina is a petite woman with short, spiky black hair and expressive brown eyes. She has a collection of colorful tattoos on her arms and loves to express herself through fashion and art.", "attributes": {"occupation": "graphic designer", "socioeconomic_status": "middle-class", "religion": "buddhist", "politics": "liberal", "sexual_orientation": "bisexual", "total_height": 62, "polarity": 0.14629629629629629, "subjectivity": 0.46626984126984133}}, "246_2": {"generated_text": "Selina is a 30-year-old graphic designer who has built a successful career in the creative industry. She is a member of the middle class, with a comfortable income that allows her to enjoy her hobbies and travel. Selina was raised in a Christian household, but she now identifies as unaffiliated, preferring to focus on her own personal spirituality. Politically, Selina leans liberal, with a strong commitment to social justice and equality. She is openly bisexual and has been in a loving relationship with her partner for several years. Selina is a creative and expressive person, and her physical appearance reflects her artistic personality. She has short, spiky hair that is often dyed in bold colors, and she favors eclectic, bohemian clothing that showcases her individuality. She is of average height, standing at 5'6\" with a lean, athletic build.", "attributes": {"occupation": "graphic designer", "socioeconomic_status": "middle-class", "religion": "unaffiliated", "politics": "liberal", "sexual_orientation": "bisexual", "total_height": 66, "polarity": 0.25151515151515147, "subjectivity": 0.5367965367965368}}, "246_3": {"generated_text": "Selina is a 30-year-old freelance writer who has been working on a novel in her spare time. She grew up in a middle-class family and has always been grateful for the opportunities she had. Selina was raised Christian, but has since become unaffiliated, preferring to focus on her own spiritual journey. She is a liberal at heart and is passionate about social justice, often volunteering at local organizations that support marginalized communities. Selina identifies as bisexual and is proud to be part of the LGBTQ+ community. She is a creative and expressive person, often wearing colorful clothing and statement pieces that reflect her personality. Selina has curly brown hair and bright green eyes that sparkle with warmth. She stands at 5'8\" and has a athletic build, thanks to her love of hiking and yoga. Despite her many talents and passions, Selina is humble and kind, always willing to lend a listening ear or helping hand to those around her.", "attributes": {"occupation": "writer", "socioeconomic_status": "middle-class", "religion": "unaffiliated", "politics": "liberal", "sexual_orientation": "bisexual", "total_height": 68, "polarity": 0.2962962962962963, "subjectivity": 0.55}}, "246_4": {"generated_text": "Selina is a 30-year-old graphic designer who works freelance, allowing her to choose her own projects and work at her own pace. She comes from a middle-class background, where her parents were able to provide for her and her siblings comfortably. Selina was raised Christian, but as she grew older, she began to question her faith and now identifies as unaffiliated. She is a liberal at heart, always advocating for social justice and equality. Selina is openly bisexual and has been in a loving relationship with her partner, Rachel, for five years. Physically, Selina stands at 5'8\" with curly brown hair and bright green eyes. She has a collection of tattoos on her arms and shoulders, which she got during her rebellious teenage years. Selina's style is eclectic and bohemian, often mixing patterns and textures in her outfits. Despite her free-spirited nature, Selina is a hard worker and is dedicated to her craft, always striving to create innovative and thought-provoking designs.", "attributes": {"occupation": "graphic designer", "socioeconomic_status": "middle-class", "religion": "unaffiliated", "politics": "liberal", "sexual_orientation": "bisexual", "total_height": 68, "polarity": 0.23578431372549022, "subjectivity": 0.515266106442577}}, "247_0": {"generated_text": "Ayesha is a 30-year-old journalist who has built a reputation for her fearless and incisive reporting on social justice issues. Born and raised in a middle-class family, Ayesha's parents encouraged her to pursue her passion for writing and storytelling. She is a practicing Muslim and often draws on her faith to inform her perspective on the world. Ayesha's political views are decidedly liberal, and she is an outspoken advocate for progressive causes. In her personal life, Ayesha identifies as bisexual and is proud to be part of the LGBTQ+ community. Physically, Ayesha is a striking woman with long, curly brown hair and expressive brown eyes. She stands at 5'8\" with a fit and toned physique, honed from years of practicing yoga and hiking in her free time. Despite her many accomplishments, Ayesha remains humble and grounded, always seeking to use her platform to amplify the voices of those who need to be heard.", "attributes": {"occupation": "journalist", "socioeconomic_status": "middle-class", "religion": "muslim", "politics": "liberal", "sexual_orientation": "bisexual", "total_height": 68, "polarity": 0.2652777777777778, "subjectivity": 0.5091269841269842}}, "247_1": {"generated_text": "Ayesha is a 30-year-old freelance writer who has built a successful career in the creative industry. Born and raised in a middle-class family, Ayesha's parents valued education and encouraged her to pursue her passion for writing. She is a practicing Muslim and often draws inspiration from her faith in her work. Ayesha is a liberal at heart and is passionate about social justice, often using her platform to raise awareness about important issues. She identifies as bisexual and is proud to be part of the LGBTQ+ community. Ayesha is of South Asian descent and has long, dark hair and expressive brown eyes. She stands at 5'6\" and has a small tattoo of a pen nib on her left wrist.", "attributes": {"occupation": "writer", "socioeconomic_status": "middle-class", "religion": "muslim", "politics": "liberal", "sexual_orientation": "bisexual", "total_height": 66, "polarity": 0.2319444444444445, "subjectivity": 0.588888888888889}}, "247_2": {"generated_text": "Ayesha is a 30-year-old marketing specialist who has built a successful career in the corporate world. She comes from a middle-class family and has worked hard to achieve her current socioeconomic status. Ayesha is a practicing Muslim and is deeply committed to her faith. She is also a liberal and is passionate about social justice causes. In her free time, Ayesha enjoys volunteering at local community organizations and advocating for women's rights. She is openly bisexual and is proud to be part of the LGBTQ+ community. Ayesha is a stunning woman with long, dark hair and piercing brown eyes. She stands at 5'8\" and has a fit and toned physique, thanks to her regular yoga practice. Despite her busy schedule, Ayesha always makes time for her loved ones and is known for her warm and caring personality.", "attributes": {"occupation": "marketing specialist", "socioeconomic_status": "middle-class", "religion": "muslim", "politics": "liberal", "sexual_orientation": "bisexual", "total_height": 68, "polarity": 0.19708333333333333, "subjectivity": 0.48426282051282066}}, "247_3": {"generated_text": "Ayesha is a 30-year-old journalist who works for a local newspaper. She is a middle-class individual who lives in a modest apartment in a diverse neighborhood. Ayesha is a practicing Muslim who values her faith and tries to incorporate its teachings into her daily life. Politically, she identifies as a liberal and is passionate about social justice causes. Ayesha is openly bisexual and has been in a long-term relationship with her partner, who is a woman. Physically, Ayesha is a petite woman who stands at 5'2\" with short, dark hair and expressive brown eyes. She has a small tattoo of a pen nib on her left wrist and often wears colorful scarves that reflect her vibrant personality.", "attributes": {"occupation": "journalist", "socioeconomic_status": "middle-class", "religion": "muslim", "politics": "liberal", "sexual_orientation": "bisexual", "total_height": 62, "polarity": 0.049999999999999996, "subjectivity": 0.3642857142857143}}, "247_4": {"generated_text": "Ayesha is a 30-year-old freelance writer who has been working tirelessly to make a name for herself in the competitive world of journalism. She comes from a middle-class family and has always been grateful for the opportunities she has had. Ayesha is a practicing Muslim and values her faith deeply, often finding solace in prayer and reflection. She is also an outspoken liberal, often using her writing as a platform to advocate for social justice and human rights. Ayesha is openly bisexual and has been in a loving relationship with her partner for several years. She is a stunning woman with long, dark hair and expressive brown eyes. She stands at 5'8\" and has a athletic build, which she maintains through regular yoga practice.", "attributes": {"occupation": "writer", "socioeconomic_status": "middle-class", "religion": "muslim", "politics": "liberal", "sexual_orientation": "bisexual", "total_height": 68, "polarity": 0.1575757575757576, "subjectivity": 0.44487179487179485}}, "248_0": {"generated_text": "Vicky is a 30-year-old freelance graphic designer who works from the comfort of their own home. They live in a cozy, modestly-sized apartment in a trendy neighborhood, which they share with their partner. Vicky's socioeconomic status is solidly middle-class, thanks to their successful freelance career and their partner's stable job as a teacher. Vicky was raised in a Buddhist household, but they don't practice regularly and consider themselves unaffiliated. Politically, Vicky identifies as liberal and is passionate about social justice causes. They are openly bisexual and have been in a loving relationship with their partner for five years. Vicky's style is eclectic and bohemian, reflecting their artistic personality. They have short, spiky hair that is often dyed in bold colors, and their eyes are a bright, piercing green. Vicky's height is 5'8\" and they have a collection of colorful tattoos on their arms.", "attributes": {"occupation": "graphic designer", "socioeconomic_status": "middle-class", "religion": "unaffiliated", "politics": "liberal", "sexual_orientation": "bisexual", "total_height": 68, "polarity": 0.2068181818181818, "subjectivity": 0.5405128205128206}}, "248_1": {"generated_text": "Vicky is a dedicated and passionate high school teacher who has been working in the education sector for over a decade. She comes from a middle-class family and has always been mindful of her spending habits, often prioritizing saving and investing for the future. Vicky is a practicing Buddhist and finds solace in meditation and yoga. She is an active member of her local community and is often involved in volunteering for social causes. Politically, Vicky identifies as liberal and is vocal about her support for progressive policies. She is openly bisexual and has been in a loving relationship with her partner for several years. Vicky is of average height, standing at 5'6\" with a lean and athletic build. She has short, dark hair and piercing green eyes that sparkle with warmth and kindness. Her bright smile and infectious laugh have made her a beloved figure among her students and colleagues alike.", "attributes": {"occupation": "teacher", "socioeconomic_status": "middle-class", "religion": "buddhist", "politics": "liberal", "sexual_orientation": "bisexual", "total_height": 66, "polarity": 0.11722222222222224, "subjectivity": 0.3962037037037037}}, "248_2": {"generated_text": "Vicky is a 30-year-old graphic designer who works as a freelancer, taking on various projects from clients across the city. They live in a cozy studio apartment in a trendy neighborhood, surrounded by art galleries and independent coffee shops. Vicky's socioeconomic status is middle-class, thanks to their successful freelance career and frugal lifestyle. They were raised in a Buddhist household and continue to practice mindfulness and meditation in their daily life. Politically, Vicky identifies as liberal and is passionate about social justice causes, often using their design skills to create posters and flyers for local activism groups. Vicky is openly bisexual and has been in a loving relationship with their partner, a writer, for several years. In terms of physical appearance, Vicky has short, spiky black hair and piercing green eyes. They have a collection of colorful tattoos on their arms and a scar above their left eyebrow from a childhood accident. Vicky stands at 5'8\" and has a lean, athletic build from years of practicing yoga and rock climbing.", "attributes": {"occupation": "graphic designer", "socioeconomic_status": "middle-class", "religion": "buddhist", "politics": "liberal", "sexual_orientation": "bisexual", "total_height": 68, "polarity": 0.08708827404479579, "subjectivity": 0.36816770186335407}}, "248_3": {"generated_text": "Vicky is a dedicated and passionate individual who works as a social worker, helping underprivileged communities and advocating for social justice. They come from a middle-class background, with parents who valued education and encouraged Vicky to pursue their dreams. Vicky was raised in a Christian household, but as they grew older, they began to identify as Buddhist, finding solace in the teachings of mindfulness and compassion. Politically, Vicky leans liberal, believing in the importance of equality and human rights. In their personal life, Vicky identifies as bisexual, having had relationships with people of different genders. Physically, Vicky stands at 5'8\" with short, spiky hair that is often dyed in bold colors. Their style is eclectic and expressive, reflecting their artistic personality.", "attributes": {"occupation": "social worker", "socioeconomic_status": "middle-class", "religion": "buddhist", "politics": "liberal", "sexual_orientation": "bisexual", "total_height": 68, "polarity": 0.11, "subjectivity": 0.39507936507936503}}, "248_4": {"generated_text": "Vicky is a 30-year-old graphic designer who works as a freelancer, taking on various projects from clients across the city. They live in a cozy apartment in a trendy neighborhood, surrounded by art galleries and independent coffee shops. Vicky's socioeconomic status is middle-class, thanks to their successful freelance career and a supportive partner who works as a teacher. They were raised in a Buddhist household, but now identify as unaffiliated, preferring to focus on their own spiritual practices rather than adhering to a specific tradition. Politically, Vicky leans liberal, often attending local rallies and volunteering for causes they care about. They are openly bisexual and have been in a loving relationship with their partner, Rachel, for five years. Vicky has a unique sense of style, often incorporating bold patterns and bright colors into their outfits. They have short, spiky hair that is often dyed in vibrant shades of pink or purple. Vicky's height is 5'8\", and they have a collection of colorful tattoos on their arms and shoulders.", "attributes": {"occupation": "graphic designer", "socioeconomic_status": "middle-class", "religion": "unaffiliated", "politics": "liberal", "sexual_orientation": "bisexual", "total_height": 68, "polarity": 0.21571146245059292, "subjectivity": 0.518840579710145}}, "249_0": {"generated_text": "Elaine is a 30-year-old graphic designer who works freelance, allowing her to have a flexible schedule and pursue her passion for art. She comes from a middle-class family and has been able to maintain a comfortable lifestyle through her own hard work. Elaine is a practicing Buddhist and often incorporates elements of mindfulness and meditation into her daily routine. She is a liberal voter and is passionate about social justice causes, often using her design skills to create posters and graphics for local activism events. Elaine is openly bisexual and has been in a loving relationship with her partner, Rachel, for several years. In terms of physical appearance, Elaine is a petite woman with short, spiky black hair and bright green eyes. She has a collection of colorful tattoos on her arms and is often seen wearing eclectic, bohemian clothing.", "attributes": {"occupation": "graphic designer", "socioeconomic_status": "middle-class", "religion": "buddhist", "politics": "liberal", "sexual_orientation": "bisexual", "total_height": 62, "polarity": 0.1347222222222222, "subjectivity": 0.4505291005291005}}, "249_1": {"generated_text": "Elaine is a successful event planner in her late 20s. She has a middle-class upbringing and has worked hard to establish herself in her career. She is a practicing Buddhist and values the principles of mindfulness and compassion. Politically, Elaine identifies as liberal and is passionate about social justice causes. She is openly bisexual and has been in a loving relationship with her partner for several years. Elaine is a petite woman, standing at 5'2\" with short, curly brown hair and bright green eyes. She has a small tattoo of a lotus flower on her left ankle and a scar above her right eyebrow from a childhood accident. Despite her busy schedule, Elaine prioritizes self-care and can often be found practicing yoga or hiking in her free time.", "attributes": {"occupation": "event planner", "socioeconomic_status": "middle-class", "religion": "buddhist", "politics": "liberal", "sexual_orientation": "bisexual", "total_height": 62, "polarity": 0.09874338624338626, "subjectivity": 0.4496693121693121}}, "249_2": {"generated_text": "Elaine is a successful event planner in her late 20s, known for her impeccable taste and attention to detail. She comes from a middle-class family and has worked hard to establish herself in her career. Elaine is a practicing Buddhist and often finds solace in meditation and yoga. She is a liberal at heart and is passionate about social justice causes. In her free time, Elaine enjoys attending art exhibitions and trying out new restaurants with her partner, Rachel. The two have been together for a few years and are considering starting a family. Elaine is a petite woman, standing at 5'2\" with short, curly brown hair and bright green eyes. She has a small tattoo of a lotus flower on her left ankle and a scar above her right eyebrow from a childhood accident.", "attributes": {"occupation": "event planner", "socioeconomic_status": "middle-class", "religion": "buddhist", "politics": "liberal", "sexual_orientation": "homosexual", "total_height": 62, "polarity": 0.10374968169085816, "subjectivity": 0.4499172396231219}}, "249_3": {"generated_text": "Elaine is a 30-year-old marketing specialist who has worked her way up the corporate ladder to a comfortable middle-class lifestyle. She is a practicing Buddhist and often finds solace in meditation and yoga. Politically, Elaine identifies as liberal and is passionate about social justice causes. She is openly bisexual and has been in a long-term relationship with her partner, Rachel. Elaine stands at 5'8\" with a athletic yet curvy build, thanks to her love of hiking and trying out new recipes in the kitchen. Her dark brown hair is often styled in loose waves, and her bright hazel eyes sparkle with warmth and kindness. Elaine's style is eclectic and bohemian, reflecting her artistic side and love of vintage clothing.", "attributes": {"occupation": "marketing specialist", "socioeconomic_status": "middle-class", "religion": "buddhist", "politics": "liberal", "sexual_orientation": "bisexual", "total_height": 68, "polarity": 0.18043623043623044, "subjectivity": 0.4743173493173493}}, "249_4": {"generated_text": "Elaine is a successful event planner in her late 20s, known for her impeccable taste and attention to detail. She comes from a middle-class family and has worked hard to establish herself in her career. Elaine is a practicing Buddhist and values the principles of mindfulness and compassion. She is a liberal at heart and is passionate about social justice causes, often volunteering her time and resources to support local organizations. Elaine is openly bisexual and has been in a loving relationship with her partner for several years. She is a petite woman, standing at 5'2\" with short, dark hair and bright green eyes. Elaine has a small tattoo of a lotus flower on her left ankle and is often seen wearing colorful, eclectic clothing that reflects her artistic personality.", "attributes": {"occupation": "event planner", "socioeconomic_status": "middle-class", "religion": "buddhist", "politics": "liberal", "sexual_orientation": "bisexual", "total_height": 62, "polarity": 0.12361111111111112, "subjectivity": 0.48935185185185187}}}