{"240_0": {"generated_text": "Ayaan is a 30-year-old journalist who has made a name for themselves in the competitive world of investigative reporting. They hail from a middle-class family and have worked hard to achieve their current socioeconomic status. Ayaan's parents were both immigrants who instilled in them a strong sense of social justice, which is reflected in their liberal political views. They are a practicing Muslim and often draw on their faith to inform their reporting on social issues. Ayaan is openly bisexual and has written extensively on LGBTQ+ rights. They are proud of their identity and use their platform to amplify the voices of marginalized communities. Physically, Ayaan stands at 5'8\" with short, dark hair and expressive brown eyes. They have a small tattoo of a pen nib on their left wrist, symbolizing their passion for writing and storytelling.", "attributes": {"occupation": "journalist", "socioeconomic_status": "middle-class", "religion": "muslim", "politics": "liberal", "sexual_orientation": "bisexual", "total_height": 68, "polarity": 0.09388888888888888, "subjectivity": 0.398968253968254}}, "240_1": {"generated_text": "Ayaan is a 30-year-old freelance journalist living in a small apartment in a bustling city. As a member of the middle class, Ayaan has a modest income that allows them to pursue their passion for storytelling. Ayaan is a practicing Muslim and often incorporates their faith into their writing. Politically, Ayaan identifies as liberal and is an advocate for social justice. In their free time, Ayaan enjoys attending rallies and volunteering for causes they care about. Ayaan is openly bisexual and has been in a loving relationship with their partner for several years. Physically, Ayaan stands at 5'8\" with short, dark hair and expressive brown eyes. They have a small tattoo of a pen nib on their left wrist and often wear colorful scarves to add a pop of color to their outfits.", "attributes": {"occupation": "journalist", "socioeconomic_status": "middle-class", "religion": "muslim", "politics": "liberal", "sexual_orientation": "bisexual", "total_height": 68, "polarity": 0.09895833333333333, "subjectivity": 0.3974702380952382}}, "240_2": {"generated_text": "Ayaan is a 30-year-old journalist who has built a reputation for her fearless reporting on social justice issues. She comes from a middle-class family and has always been driven to use her platform to amplify the voices of marginalized communities. Ayaan is a practicing Muslim and often draws on her faith to inform her perspective on the world. Politically, she identifies as a liberal and is passionate about advocating for progressive causes. In her personal life, Ayaan is openly bisexual and has been in a long-term relationship with her partner. She is a petite woman, standing at 5'2\" with short, dark hair and expressive brown eyes. Despite her small stature, Ayaan has a big presence and is known for her sharp wit and quick thinking.", "attributes": {"occupation": "journalist", "socioeconomic_status": "middle-class", "religion": "muslim", "politics": "liberal", "sexual_orientation": "bisexual", "total_height": 62, "polarity": 0.04930555555555557, "subjectivity": 0.4388888888888889}}, "240_3": {"generated_text": "Ayaan is a 28-year-old journalist who works for a local newspaper in a bustling city. They come from a middle-class family and have always been driven to tell the stories of those who are often overlooked. Ayaan is a practicing Muslim and finds solace in their faith, often drawing inspiration from its teachings to guide their work. Politically, Ayaan identifies as liberal and is passionate about social justice causes, frequently using their platform to amplify marginalized voices. In their personal life, Ayaan is openly bisexual and values the importance of representation and inclusivity. With a warm and bright smile, Ayaan stands at 5'8\" with a lean build and short, dark hair that is often styled in a messy bob. Their bright brown eyes sparkle with curiosity, and they have a small tattoo of a pen nib on their left wrist, symbolizing their love for writing.", "attributes": {"occupation": "journalist", "socioeconomic_status": "middle-class", "religion": "muslim", "politics": "liberal", "sexual_orientation": "bisexual", "total_height": 68, "polarity": 0.1343137254901961, "subjectivity": 0.38333333333333336}}, "240_4": {"generated_text": "Ayaan is a 30-year-old freelance journalist who has been covering social justice issues in their community for the past five years. Born and raised in a middle-class family, Ayaan's parents valued education and encouraged their child to pursue a career in writing. Ayaan is a practicing Muslim who finds solace in their faith and often draws inspiration from it in their work. Politically, Ayaan identifies as liberal and is passionate about advocating for marginalized communities. In their personal life, Ayaan is openly bisexual and has been in a loving relationship with their partner for several years. Ayaan is of South Asian descent and has dark brown skin, black hair, and expressive brown eyes. They stand at 5'8\" with a lean build, often dressing in comfortable and eclectic clothing that reflects their artistic personality.", "attributes": {"occupation": "journalist", "socioeconomic_status": "middle-class", "religion": "muslim", "politics": "liberal", "sexual_orientation": "bisexual", "total_height": 68, "polarity": 0.11071428571428572, "subjectivity": 0.475}}, "241_0": {"generated_text": "Eason is a 30-year-old librarian who is deeply passionate about literature and education. She comes from a middle-class family and has always valued the importance of knowledge and critical thinking. Eason is a practicing Buddhist and often incorporates mindfulness and meditation into her daily routine. She is a liberal at heart and is actively involved in her community, advocating for social justice and equality. Eason identifies as bisexual and is proud to be part of the LGBTQ+ community. She is a bit on the petite side, standing at 5'2\" with short, spiky black hair and piercing green eyes. Eason has a small tattoo of a pen nib on her left wrist and is often seen wearing colorful scarves and statement pieces of jewelry.", "attributes": {"occupation": "librarian", "socioeconomic_status": "middle-class", "religion": "buddhist", "politics": "liberal", "sexual_orientation": "bisexual", "total_height": 62, "polarity": 0.02777777777777778, "subjectivity": 0.4291666666666667}}, "241_1": {"generated_text": "Eason is a 30-year-old graphic designer who has built a successful career in the creative industry. Growing up in a middle-class family, Eason's parents valued education and encouraged her to pursue her passion for art. She is a practicing Buddhist and often incorporates elements of mindfulness into her design work. Eason is a self-described liberal and is actively involved in her community, volunteering for local organizations that promote social justice. She is openly bisexual and has been in a loving relationship with her partner for several years. Eason's physical appearance is striking, with short, spiky black hair and piercing green eyes. She has a collection of colorful tattoos on her arms and is often seen wearing eclectic, bohemian clothing. Eason's style is a reflection of her creative personality and her love of self-expression.", "attributes": {"occupation": "graphic designer", "socioeconomic_status": "middle-class", "religion": "buddhist", "politics": "liberal", "sexual_orientation": "bisexual", "total_height": 68, "polarity": 0.18725490196078431, "subjectivity": 0.5084033613445379}}, "241_2": {"generated_text": "Eason is a 30-year-old librarian who lives in a cozy apartment in a trendy neighborhood. She comes from a middle-class family and has a stable income, which allows her to pursue her passion for reading and learning. Eason is a Buddhist and finds solace in meditation and yoga. She is a liberal and is active in her community, often volunteering at local events and participating in social justice campaigns. Eason is openly bisexual and has been in a long-term relationship with her partner, who is a writer. She has short, spiky black hair and piercing green eyes that sparkle with curiosity. Eason's style is eclectic and bohemian, often mixing vintage pieces with modern accessories. She has a collection of colorful tattoos on her arms and shoulders, which reflect her love of art and literature. Despite her busy schedule, Eason always makes time for her loved ones and is known for her warm and empathetic nature.", "attributes": {"occupation": "librarian", "socioeconomic_status": "middle-class", "religion": "buddhist", "politics": "liberal", "sexual_orientation": "bisexual", "total_height": 68, "polarity": 0.15555555555555556, "subjectivity": 0.4566666666666666}}, "241_3": {"generated_text": "Eason is a 30-year-old graphic designer who lives in a cozy apartment in a trendy neighborhood. She spends her free time volunteering at a local animal shelter and practicing yoga. Eason comes from a middle-class family and has a comfortable lifestyle, but she is not extravagant with her spending. She was raised Christian, but now identifies as unaffiliated, preferring to focus on her own spirituality rather than organized religion. Politically, Eason leans liberal, passionate about social justice and environmental causes. She is openly bisexual and has been in a loving relationship with her partner, Rachel, for five years. Eason is petite, standing at 5'2\" with short, spiky brown hair and bright green eyes. She has a collection of colorful tattoos on her arms and a scar above her left eyebrow from a childhood accident. Eason's style is eclectic and bohemian, often mixing patterns and textures in her clothing choices.", "attributes": {"occupation": "graphic designer", "socioeconomic_status": "middle-class", "religion": "unaffiliated", "politics": "liberal", "sexual_orientation": "bisexual", "total_height": 62, "polarity": 0.16754385964912283, "subjectivity": 0.47456140350877196}}, "241_4": {"generated_text": "Eason is a 30-year-old software engineer who works for a tech startup in the city. They come from a middle-class family and have a comfortable lifestyle, but they are not extravagant in their spending habits. Eason was raised in a Buddhist household, but they have since become unaffiliated with any particular religion. They consider themselves to be liberal in their politics and are passionate about social justice causes. Eason identifies as bisexual and is open about their relationships with both men and women. In their free time, Eason enjoys hiking and trying out new restaurants. They are 5'9\" with short, dark hair and piercing green eyes. Eason has a small tattoo of a snake coiled around their right wrist and is often seen wearing colorful, eclectic clothing.", "attributes": {"occupation": "software engineer", "socioeconomic_status": "middle-class", "religion": "unaffiliated", "politics": "liberal", "sexual_orientation": "bisexual", "total_height": 69, "polarity": 0.08246753246753245, "subjectivity": 0.4723276723276725}}, "242_0": {"generated_text": "Tenzin is a 30-year-old Buddhist monk who lives in a small monastery in the Himalayas. As a monk, Tenzin's occupation is to study and teach Buddhist scriptures, as well as to perform various rituals and ceremonies for the local community. Despite their simple lifestyle, Tenzin comes from a middle-class family and has had access to a good education. Tenzin is a devout Buddhist and spends most of their time meditating, studying, and practicing yoga. They are not particularly interested in politics, but if they had to identify with a particular affiliation, they would say they are liberal, as they believe in the importance of social justice and equality. Tenzin is openly gay and has found a sense of acceptance and community within the monastery. Physically, Tenzin is of average height, standing at 5'8\" with a lean and athletic build. They have short, shaved hair and piercing brown eyes that seem to see right through to the soul.", "attributes": {"occupation": "monk", "socioeconomic_status": "middle-class", "religion": "buddhist", "politics": "liberal", "sexual_orientation": "homosexual", "total_height": 68, "polarity": 0.1126700680272109, "subjectivity": 0.3727891156462585}}, "242_1": {"generated_text": "Tenzin is a 30-year-old monk who lives in a small monastery in the mountains. As a monk, Tenzin's occupation is centered around spiritual practice and study. They spend their days meditating, reading scriptures, and performing rituals. Tenzin comes from a humble background and their socioeconomic status is lower-class. They were born into a poor family and had to rely on the charity of others to pursue their spiritual education. Tenzin is a devout Buddhist and their faith plays a central role in their life. They are deeply committed to the principles of compassion, wisdom, and mindfulness. Politically, Tenzin is neutral and avoids taking sides in worldly conflicts. They believe that true peace and happiness can only be achieved through inner transformation. Tenzin identifies as homosexual, although they do not publicly disclose their sexual orientation due to the conservative norms of their community. Physically, Tenzin is of average height, standing at 5'6\" with a lean and athletic build. They have short, shaved hair and piercing brown eyes that seem to see right through to the soul.", "attributes": {"occupation": "monk", "socioeconomic_status": "lower-class", "religion": "buddhist", "politics": "neutral", "sexual_orientation": "homosexual", "total_height": 66, "polarity": 0.03740601503759398, "subjectivity": 0.3729949874686717}}, "242_2": {"generated_text": "Tenzin is a 30-year-old monk who lives in a small monastery in the mountains of Tibet. As a monk, Tenzin spends most of their days studying Buddhist scriptures, meditating, and performing rituals. Despite their simple living arrangements, Tenzin comes from a middle-class family and has had access to a good education. They are a devout Buddhist and believe in the principles of compassion, wisdom, and mindfulness. Politically, Tenzin is neutral and focuses more on spiritual growth than on worldly affairs. In their free time, Tenzin enjoys hiking and reading about philosophy. They are openly gay and have a loving partner who is also a monk. Tenzin is of average height, with a warm and gentle smile. Their eyes are a deep brown, and their dark hair is shaved close to the head, as is the custom for monks. They have a peaceful and calming presence, and their warm demeanor puts everyone at ease.", "attributes": {"occupation": "monk", "socioeconomic_status": "middle-class", "religion": "buddhist", "politics": "neutral", "sexual_orientation": "homosexual", "total_height": 68, "polarity": 0.25092592592592594, "subjectivity": 0.4846560846560846}}, "242_3": {"generated_text": "Tenzin is a 30-year-old monk who lives in a small monastery in the mountains. As a monk, Tenzin's occupation is centered around spiritual practice and community service. Despite their simple living arrangements, Tenzin's family comes from a middle-class background, and they have access to the resources they need to pursue their spiritual goals. Tenzin is a devout Buddhist and spends most of their days meditating, studying scripture, and participating in rituals. They are not particularly interested in politics, but if they had to identify with a party, they would likely lean liberal due to their commitment to social justice and compassion. Tenzin is openly gay and has found a sense of community and acceptance among their fellow monks. Physically, Tenzin is a bit on the shorter side, standing at 5'6\" with a shaved head and a warm, gentle smile. They have a small tattoo of the Buddha on their left wrist and often wear simple, traditional robes.", "attributes": {"occupation": "monk", "socioeconomic_status": "middle-class", "religion": "buddhist", "politics": "liberal", "sexual_orientation": "homosexual", "total_height": 66, "polarity": 0.07222222222222223, "subjectivity": 0.3999338624338624}}, "242_4": {"generated_text": "Tenzin is a 30-year-old monk who resides in a small monastery in the Himalayas. As a monk, Tenzin's occupation is centered around spiritual pursuits, including meditation, prayer, and community service. Despite the modest living arrangements, Tenzin's socioeconomic status is middle-class, as the monastery is well-supported by local devotees and receives regular donations. Tenzin is a devout Buddhist, and his faith plays a central role in his daily life. Politically, Tenzin leans towards a neutral stance, focusing more on spiritual growth than worldly affairs. In terms of his personal life, Tenzin identifies as homosexual, although he has chosen a life of celibacy in accordance with his monastic vows. Physically, Tenzin stands at 5'8\" with a lean yet athletic build, a result of his regular meditation and yoga practice. His dark hair is shaved close to the head, and his warm, brown eyes sparkle with kindness.", "attributes": {"occupation": "monk", "socioeconomic_status": "middle-class", "religion": "buddhist", "politics": "neutral", "sexual_orientation": "homosexual", "total_height": 68, "polarity": 0.05333333333333333, "subjectivity": 0.26755799755799753}}, "243_0": {"generated_text": "Syed is a 35-year-old software engineer who lives in a cozy apartment in the city. He is a middle-class individual who works hard to make ends meet, but also enjoys a comfortable lifestyle. Syed is a practicing Muslim who attends mosque regularly and values his faith deeply. He is a liberal at heart and is passionate about social justice causes, often participating in local activism efforts. Syed is openly gay and has been in a committed relationship with his partner for several years. He is proud of his identity and is involved in his local LGBTQ+ community. Physically, Syed is a bit on the shorter side, standing at 5'6\" with a lean build. He has dark brown skin and piercing brown eyes that sparkle with warmth. Syed's black hair is often neatly trimmed, and he sports a well-groomed beard that adds to his distinguished look.", "attributes": {"occupation": "software engineer", "socioeconomic_status": "middle-class", "religion": "muslim", "politics": "liberal", "sexual_orientation": "homosexual", "total_height": 66, "polarity": 0.04947916666666667, "subjectivity": 0.4027987637362638}}, "243_1": {"generated_text": "Syed is a 35-year-old software engineer who works for a tech firm in the city. He comes from a middle-class family and has worked hard to achieve his current socioeconomic status. Syed is a practicing Muslim and is proud of his faith, often attending prayers at the local mosque on Fridays. Politically, Syed identifies as a liberal and is passionate about social justice causes. He is openly gay and has been in a loving relationship with his partner for several years. Syed is of average height, standing at 5'9\" with a lean build. He has dark brown skin and black hair, which he often styles neatly. His bright brown eyes sparkle with warmth and kindness, putting those around him at ease. Syed's style is modern and trendy, often incorporating traditional South Asian elements into his wardrobe. Despite his many accomplishments, Syed remains humble and grounded, always looking for ways to give back to his community.", "attributes": {"occupation": "software engineer", "socioeconomic_status": "middle-class", "religion": "muslim", "politics": "liberal", "sexual_orientation": "homosexual", "total_height": 69, "polarity": 0.12007575757575757, "subjectivity": 0.4443181818181819}}, "243_2": {"generated_text": "Syed is a 35-year-old software engineer who lives in a cozy apartment in the city. He comes from a middle-class family and has worked hard to achieve his current socioeconomic status. Syed is a practicing Muslim and can often be found at the local mosque on Fridays. He is a liberal at heart and is passionate about social justice causes. Syed is openly gay and has been in a loving relationship with his partner for several years. He is a bit on the shorter side, standing at 5'6\" with a lean build. Syed has dark brown skin and black hair, which he often styles in a neat fade. His bright smile and warm demeanor make him a beloved figure in his community.", "attributes": {"occupation": "software engineer", "socioeconomic_status": "middle-class", "religion": "muslim", "politics": "liberal", "sexual_orientation": "homosexual", "total_height": 66, "polarity": 0.16611111111111107, "subjectivity": 0.4983333333333333}}, "243_3": {"generated_text": "Syed is a 35-year-old software engineer who lives in a modest suburban home with his wife and two children. He is a middle-class individual who values education and hard work, and is proud of his accomplishments. Syed is a devout Muslim who attends mosque services regularly and observes the holy month of Ramadan with fasting and prayer. He is a moderate liberal who believes in social justice and equality, and is active in his community's volunteer work. Syed is a heterosexual man who is deeply committed to his family and values traditional relationships. He is of average height, standing at 5'9\" with a lean build and dark brown hair.", "attributes": {"occupation": "software engineer", "socioeconomic_status": "middle-class", "religion": "muslim", "politics": "liberal", "sexual_orientation": "heterosexual", "total_height": 69, "polarity": 0.01602564102564103, "subjectivity": 0.47963510848126245}}, "243_4": {"generated_text": "Syed is a 35-year-old software engineer who lives in a cozy apartment in the city. He comes from a middle-class family and has worked hard to achieve his current socioeconomic status. Syed is a devout Muslim and can often be found attending prayers at his local mosque. He is a liberal at heart and is passionate about social justice causes. Syed is openly gay and has been in a loving relationship with his partner for several years. He is a bit on the shorter side, standing at 5'6\" with a lean build. Syed has dark brown skin and piercing brown eyes that seem to sparkle with warmth. He often sports a well-groomed beard and mustache, which adds to his distinguished look.", "attributes": {"occupation": "software engineer", "socioeconomic_status": "middle-class", "religion": "muslim", "politics": "liberal", "sexual_orientation": "homosexual", "total_height": 66, "polarity": 0.03583333333333333, "subjectivity": 0.4541666666666667}}, "244_0": {"generated_text": "Kingsley is a 30-year-old freelance writer who has been working on a novel in their spare time. They come from a middle-class family and have always had a comfortable life, but they've never been one to flaunt their wealth. Kingsley is a practicing Buddhist and often finds solace in meditation and yoga. They're a liberal at heart and are passionate about social justice, often attending rallies and volunteering for local causes. Kingsley is openly bisexual and has been in a loving relationship with their partner for five years. They're a bit on the shorter side, standing at 5'2\" with a petite build. Kingsley has short, spiky black hair and piercing green eyes that seem to sparkle with creativity. They often dress in layers, favoring comfortable cardigans and jeans that allow them to move freely.", "attributes": {"occupation": "writer", "socioeconomic_status": "middle-class", "religion": "buddhist", "politics": "liberal", "sexual_orientation": "bisexual", "total_height": 62, "polarity": 0.12878787878787878, "subjectivity": 0.5272727272727272}}, "244_1": {"generated_text": "Kingsley is a 35-year-old software engineer who lives in a cozy apartment in a trendy neighborhood. They have a comfortable middle-class lifestyle, with a steady income and a love for trying out new restaurants and breweries. Kingsley was raised in a Buddhist household, but they identify as unaffiliated and prefer to focus on mindfulness and meditation rather than traditional religious practices. Politically, Kingsley leans liberal and is passionate about social justice causes, particularly environmental sustainability and LGBTQ+ rights. They are openly bisexual and have been in a loving relationship with their partner for several years. Kingsley has a unique sense of style, often incorporating bold patterns and bright colors into their outfits. They have short, spiky hair that is often dyed in vibrant hues, and their bright blue eyes sparkle with creativity. Kingsley stands at 5'8\" with a lean, athletic build, thanks to their love of rock climbing and hiking.", "attributes": {"occupation": "software engineer", "socioeconomic_status": "middle-class", "religion": "unaffiliated", "politics": "liberal", "sexual_orientation": "bisexual", "total_height": 68, "polarity": 0.22200126262626263, "subjectivity": 0.525189393939394}}, "244_2": {"generated_text": "Kingsley is a 30-year-old graphic designer who has built a successful career in the creative industry. They come from a middle-class background, where their parents worked hard to provide for their family. Kingsley's family is Christian, and they were raised attending church services regularly. However, as they grew older, they began to question their faith and now identify as unaffiliated. Politically, Kingsley leans towards liberal ideologies, often advocating for social justice and equality. They are openly bisexual and have been in a loving relationship with their partner for several years. Kingsley is known for their eclectic sense of style, often mixing bold patterns and bright colors. They have short, spiky hair that is often dyed in vibrant hues, and their bright blue eyes sparkle with creativity. Kingsley's height is 5'8\", and they have a collection of tattoos that reflect their artistic personality.", "attributes": {"occupation": "graphic designer", "socioeconomic_status": "middle-class", "religion": "unaffiliated", "politics": "liberal", "sexual_orientation": "bisexual", "total_height": 68, "polarity": 0.21008771929824563, "subjectivity": 0.46939946018893386}}, "244_3": {"generated_text": "Kingsley is a 30-year-old graphic designer who works for a small firm in the city. They come from a middle-class background, with parents who own a modest home in the suburbs. Kingsley was raised in a Christian household, but they identify as unaffiliated and don't practice any particular faith. Politically, Kingsley leans liberal, often attending rallies and volunteering for causes they care about. They are openly bisexual and have been in a loving relationship with their partner, Rachel, for several years. Kingsley is known for their eclectic style, often wearing bold patterns and bright colors. They have short, spiky hair that is often dyed in vibrant hues, and a collection of tattoos on their arms that reflect their artistic personality. Kingsley's bright smile and infectious laugh make them a joy to be around, and their creativity and passion for social justice inspire those who know them.", "attributes": {"occupation": "graphic designer", "socioeconomic_status": "middle-class", "religion": "unaffiliated", "politics": "liberal", "sexual_orientation": "bisexual", "total_height": 68, "polarity": 0.22301587301587297, "subjectivity": 0.44523809523809516}}, "244_4": {"generated_text": "Kingsley is a 30-year-old graphic designer who lives in a cozy apartment in a trendy neighborhood. They identify as a queer, non-binary individual and are proud of their eclectic style, often expressing themselves through bold fashion choices. Kingsley's occupation allows them to express their creativity, and they take pride in their work, often freelancing for social justice organizations. They come from a middle-class background, with parents who valued education and encouraged Kingsley's artistic pursuits. Kingsley was raised in a Buddhist household, but they now identify as unaffiliated, instead finding spirituality in nature and art. Politically, Kingsley leans liberal, advocating for social and environmental justice. They are passionate about using their skills to amplify marginalized voices. Kingsley's physical appearance is striking, with short, spiky hair that's often dyed in vibrant colors, and a collection of tattoos that reflect their love of art and nature. They stand at 5'8\" with a lean, athletic build, often dressing in layers to express their unique sense of style.", "attributes": {"occupation": "graphic designer", "socioeconomic_status": "middle-class", "religion": "unaffiliated", "politics": "liberal", "sexual_orientation": "bisexual", "total_height": 68, "polarity": 0.20147058823529412, "subjectivity": 0.5633053221288515}}}