{"255_0": {"generated_text": "Judy is a 35-year-old high school English teacher who lives in a cozy suburban neighborhood. She comes from a middle-class family and has a comfortable lifestyle, although she has to be mindful of her expenses. Judy is a practicing Buddhist and often finds solace in meditation and yoga. She is a liberal at heart and is passionate about social justice, often volunteering at local organizations that support marginalized communities. Judy is openly bisexual and has been in a loving relationship with her partner, Rachel, for five years. Physically, Judy is a petite woman with short, curly brown hair and bright green eyes. She has a warm and friendly smile and is often seen wearing colorful scarves and statement jewelry.", "attributes": {"occupation": "teacher", "socioeconomic_status": "middle-class", "religion": "buddhist", "politics": "liberal", "sexual_orientation": "bisexual", "total_height": 62, "polarity": 0.16768518518518516, "subjectivity": 0.4221957671957672}}, "255_1": {"generated_text": "Judy is a 35-year-old high school English teacher who is deeply passionate about her work. She is a member of the middle class, living comfortably in a cozy suburban home with her partner, Rachel. Judy is a practicing Buddhist, often incorporating mindfulness exercises into her daily routine. She is a self-described liberal, actively involved in local politics and social justice causes. Judy is openly lesbian and has been in a loving relationship with Rachel for over a decade. Physically, Judy stands at 5'6\" with short, curly brown hair and bright green eyes. She has a warm and approachable smile, often adorned with a few subtle tattoos that reflect her love of literature and poetry.", "attributes": {"occupation": "teacher", "socioeconomic_status": "middle-class", "religion": "buddhist", "politics": "liberal", "sexual_orientation": "homosexual", "total_height": 66, "polarity": 0.08460317460317462, "subjectivity": 0.3666439909297051}}, "255_2": {"generated_text": "Judy is a 35-year-old high school English teacher who lives in a cozy suburban neighborhood. She comes from a middle-class family and values education, having worked hard to earn her master's degree. Judy is a practicing Christian and attends church services every Sunday. She is a liberal Democrat and is passionate about social justice causes, often volunteering her time at local non-profits. Judy is openly bisexual and has been in a loving relationship with her partner, Rachel, for five years. Physically, Judy is a petite woman with curly brown hair and bright green eyes. She stands at 5'2\" and has a warm, approachable smile.", "attributes": {"occupation": "teacher", "socioeconomic_status": "middle-class", "religion": "christian", "politics": "liberal", "sexual_orientation": "bisexual", "total_height": 62, "polarity": 0.10322916666666666, "subjectivity": 0.3838244047619047}}, "255_3": {"generated_text": "Judy is a dedicated high school teacher who has been working in the education sector for over a decade. She comes from a middle-class family and values her modest upbringing, which has taught her the importance of hard work and humility. Judy is a practicing Christian who attends church services regularly and finds solace in her faith. She is a liberal at heart and actively participates in local community initiatives that promote social justice and equality. Judy is openly bisexual and has been in a loving relationship with her partner for several years. She is a warm and approachable person who is loved by her students and colleagues alike. Judy has short, curly brown hair and bright hazel eyes that sparkle with kindness. She stands at 5'6\" and has a gentle smile that puts everyone at ease.", "attributes": {"occupation": "teacher", "socioeconomic_status": "middle-class", "religion": "christian", "politics": "liberal", "sexual_orientation": "bisexual", "total_height": 66, "polarity": 0.1746078431372549, "subjectivity": 0.44560331825037697}}, "255_4": {"generated_text": "Judy is a dedicated and passionate elementary school teacher who has been working at a local public school for over a decade. She is a middle-class individual who values education and hard work, and is proud of her modest but comfortable lifestyle. Judy is a practicing Christian who attends church services regularly and finds solace in her faith. She is a liberal who believes in social justice and equality, and is often involved in local community activism. Judy is openly bisexual and has been in a loving relationship with her partner for several years. Physically, Judy is a petite woman who stands at 5'2\" with short, curly brown hair and bright green eyes. She has a warm and welcoming smile that puts her students and colleagues at ease.", "attributes": {"occupation": "teacher", "socioeconomic_status": "middle-class", "religion": "christian", "politics": "liberal", "sexual_orientation": "bisexual", "total_height": 62, "polarity": 0.14962121212121213, "subjectivity": 0.42249000999001}}, "256_0": {"generated_text": "Joyce is a 35-year-old high school English teacher who is deeply passionate about her work. She is a middle-class individual who values education and is committed to making a positive impact on her students' lives. Joyce is a practicing Christian who attends church regularly and finds solace in her faith. Politically, she identifies as a liberal and is an advocate for social justice and equality. In her personal life, Joyce is openly bisexual and has been in a loving relationship with her partner for several years. Physically, Joyce stands at 5'6\" with curly brown hair and bright green eyes. She has a warm and approachable smile that puts her students at ease.", "attributes": {"occupation": "teacher", "socioeconomic_status": "middle-class", "religion": "christian", "politics": "liberal", "sexual_orientation": "bisexual", "total_height": 66, "polarity": 0.1317003367003367, "subjectivity": 0.34843896843896843}}, "256_1": {"generated_text": "Joyce is a 35-year-old high school English teacher who is deeply passionate about her work. She is a middle-class individual who values her stable income and benefits, which allow her to live comfortably in a cozy suburban home. Joyce is a practicing Catholic who attends church services regularly and finds solace in her faith. She is a self-described liberal who is actively involved in her community, volunteering for local causes and participating in activism efforts. Joyce is openly lesbian and has been in a loving relationship with her partner for over a decade. She is a warm and welcoming person who is loved by her students, colleagues, and friends alike. Joyce stands at 5'6\" with curly brown hair and bright hazel eyes that sparkle with kindness.", "attributes": {"occupation": "teacher", "socioeconomic_status": "middle-class", "religion": "catholic", "politics": "liberal", "sexual_orientation": "homosexual", "total_height": 66, "polarity": 0.15706439393939392, "subjectivity": 0.46668269230769227}}, "256_2": {"generated_text": "Joyce is a 35-year-old high school English teacher who is deeply passionate about her work. She comes from a middle-class family and has worked hard to achieve her current socioeconomic status. Joyce is a practicing Buddhist and finds solace in the teachings of mindfulness and compassion. She is a liberal at heart and is actively involved in her community, often volunteering for local causes that support education and social justice. Joyce is openly bisexual and has been in a loving relationship with her partner, Rachel, for several years. Physically, Joyce is a petite woman with short, curly brown hair and bright green eyes. She stands at 5'2\" and has a warm, approachable smile.", "attributes": {"occupation": "teacher", "socioeconomic_status": "middle-class", "religion": "buddhist", "politics": "liberal", "sexual_orientation": "bisexual", "total_height": 62, "polarity": 0.10107843137254903, "subjectivity": 0.39359943977591033}}, "256_3": {"generated_text": "Joyce is a 35-year-old high school English teacher who is passionate about inspiring young minds. She comes from a middle-class background and values hard work and education. Joyce is a practicing Christian and attends church services regularly. She is a liberal at heart and is involved in local community activism, advocating for social justice and equality. Joyce is openly bisexual and has been in a loving relationship with her partner for several years. She is a warm and approachable person with a bright smile and sparkling eyes. Joyce stands at 5'6\" with curly brown hair and a scattering of freckles across her cheeks. She has a fondness for colorful scarves and statement jewelry, which adds to her eclectic and creative style.", "attributes": {"occupation": "teacher", "socioeconomic_status": "middle-class", "religion": "christian", "politics": "liberal", "sexual_orientation": "bisexual", "total_height": 66, "polarity": 0.19175925925925924, "subjectivity": 0.4347364672364672}}, "256_4": {"generated_text": "Joyce is a dedicated and compassionate nurse who works at a local hospital. She comes from a middle-class background, where her parents worked hard to provide for her and her siblings. Joyce is a devout Christian and regularly attends church services on Sundays. She is a liberal at heart and believes in social justice, often volunteering her time to help those in need. Joyce is openly bisexual and has been in a loving relationship with her partner for several years. She stands at 5'6\" with a warm and caring smile, often putting her patients at ease with her gentle demeanor. Joyce's long, curly brown hair and bright hazel eyes sparkle with kindness, making her a beloved figure in her community.", "attributes": {"occupation": "nurse", "socioeconomic_status": "middle-class", "religion": "christian", "politics": "liberal", "sexual_orientation": "bisexual", "total_height": 66, "polarity": 0.19940476190476192, "subjectivity": 0.4168040293040293}}, "257_0": {"generated_text": "Shirley is a 35-year-old high school English teacher who is deeply passionate about her work. She comes from a middle-class family and has always valued education as a means to improve one's socio-economic status. Shirley is a practicing Christian and often finds solace in her faith during difficult times. She is a registered Democrat and considers herself to be a liberal, always advocating for social justice and equality. In her personal life, Shirley identifies as a lesbian and has been in a loving relationship with her partner for over five years. Physically, Shirley stands at 5'6\" with short, curly brown hair and bright green eyes. She has a warm and welcoming smile that puts her students at ease.", "attributes": {"occupation": "teacher", "socioeconomic_status": "middle-class", "religion": "christian", "politics": "liberal", "sexual_orientation": "lesbian", "total_height": 66, "polarity": 0.11738095238095238, "subjectivity": 0.4249659863945578}}, "257_1": {"generated_text": "Shirley is a 35-year-old high school English teacher who lives in a modest suburban home with her partner, Rachel. She is a middle-class individual who values education and hard work. Shirley is a devout Christian who attends church services regularly and finds solace in her faith. Politically, she identifies as a liberal and is passionate about social justice causes. Shirley is a lesbian and has been in a committed relationship with Rachel for over five years. She is a warm and caring person who is loved by her students and colleagues alike. Shirley has short, curly brown hair and bright green eyes that sparkle with kindness. She stands at 5'6\" and has a gentle smile that puts those around her at ease. Despite her busy schedule, Shirley always makes time for her loved ones and is known for her generosity and compassion.", "attributes": {"occupation": "teacher", "socioeconomic_status": "middle-class", "religion": "christian", "politics": "liberal", "sexual_orientation": "homosexual", "total_height": 66, "polarity": 0.15258333333333335, "subjectivity": 0.41376282051282043}}, "257_2": {"generated_text": "Shirley is a dedicated and compassionate nurse who has been working at a local hospital for over a decade. She comes from a middle-class background, where her parents worked hard to provide for her and her siblings. Shirley was raised in a Christian household and still attends church services regularly. She is a liberal at heart and is passionate about social justice causes, often volunteering her time to help those in need. Shirley is openly bisexual and has been in a loving relationship with her partner for several years. She stands at 5'6\" with a warm and welcoming smile. Her curly brown hair and bright hazel eyes make her a beloved figure among her patients and colleagues alike.", "attributes": {"occupation": "nurse", "socioeconomic_status": "middle-class", "religion": "christian", "politics": "liberal", "sexual_orientation": "bisexual", "total_height": 66, "polarity": 0.19935897435897437, "subjectivity": 0.4219428007889547}}, "257_3": {"generated_text": "Shirley is a 35-year-old social worker who is deeply committed to her job at a local non-profit organization. She works tirelessly to support underprivileged families and individuals, often going above and beyond to ensure they receive the resources they need. Shirley comes from a middle-class background and values the opportunities she has had in life. She was raised in a Christian household and still attends church regularly, finding comfort in the sense of community and spiritual guidance it provides. Politically, Shirley identifies as liberal and is passionate about social justice causes. She is openly bisexual and has been in a loving relationship with her partner for several years. Physically, Shirley is a petite woman with short, curly brown hair and bright green eyes. She stands at 5'2\" and has a warm, gentle smile that puts those around her at ease.", "attributes": {"occupation": "social worker", "socioeconomic_status": "middle-class", "religion": "christian", "politics": "liberal", "sexual_orientation": "bisexual", "total_height": 62, "polarity": 0.11083333333333334, "subjectivity": 0.3143223443223443}}, "257_4": {"generated_text": "Shirley is a 35-year-old high school teacher who is passionate about education and making a difference in her community. She is a middle-class individual who values hard work and financial stability. Shirley is a practicing Christian who attends church regularly and finds comfort in her faith. She is a liberal who believes in social justice and equality for all. Shirley is openly bisexual and has been in a long-term relationship with her partner, Sarah. She is a bit on the shorter side, standing at 5'2\" with curly brown hair and bright green eyes. Shirley has a warm and caring demeanor, always willing to lend a helping hand to those in need. She is a dedicated teacher who goes above and beyond to ensure her students succeed. Despite her busy schedule, Shirley makes time for her hobbies, including hiking and reading.", "attributes": {"occupation": "teacher", "socioeconomic_status": "middle-class", "religion": "christian", "politics": "liberal", "sexual_orientation": "bisexual", "total_height": 62, "polarity": 0.08677777777777779, "subjectivity": 0.3883504273504273}}, "258_0": {"generated_text": "Judith is a dedicated social worker who has spent her career advocating for the rights of marginalized communities. She comes from a middle-class background and has always been driven to make a positive impact on the world around her. Judith is a practicing Buddhist and finds solace in the teachings of mindfulness and compassion. She is a vocal supporter of liberal causes and is often involved in local activism efforts. Judith is openly bisexual and has been in a loving relationship with her partner for several years. In her free time, Judith enjoys hiking and practicing yoga. She stands at 5'8\" with a athletic build and long, curly brown hair. Her bright smile and warm demeanor put those around her at ease, and she is widely respected in her community for her kindness and dedication to her work.", "attributes": {"occupation": "social worker", "socioeconomic_status": "middle-class", "religion": "buddhist", "politics": "liberal", "sexual_orientation": "bisexual", "total_height": 68, "polarity": 0.2008158508158508, "subjectivity": 0.40477855477855473}}, "258_1": {"generated_text": "Judith is a dedicated high school teacher who has spent her career educating and inspiring young minds. She comes from a middle-class background, where her parents worked hard to provide for her and her siblings. Judith was raised in a Christian household and still attends church services regularly, finding comfort in her faith. She is a liberal at heart, always advocating for social justice and equality. Judith is openly lesbian and has been in a loving relationship with her partner for over a decade. She stands at 5'8\" with a warm and welcoming smile. Her curly brown hair often falls in loose waves down her back, and her bright hazel eyes sparkle with kindness. Judith's style is understated yet elegant, often favoring comfortable blouses and slacks that allow her to move freely in the classroom.", "attributes": {"occupation": "teacher", "socioeconomic_status": "middle-class", "religion": "christian", "politics": "liberal", "sexual_orientation": "homosexual", "total_height": 68, "polarity": 0.19311515969410706, "subjectivity": 0.4649145299145299}}, "258_2": {"generated_text": "Judith is a dedicated and passionate individual who works as a high school English teacher. She comes from a middle-class background, where her parents valued education and encouraged her to pursue her dreams. Judith is a devout Christian who attends church regularly and finds solace in her faith. Politically, she identifies as a liberal, often advocating for social justice and equality in her community. Judith is openly bisexual and has been in a loving relationship with her partner for several years. She stands at 5'8\" with a athletic build, often dressing in comfortable yet stylish clothing that reflects her creative personality. Her long, curly brown hair and bright hazel eyes are often framed by a warm smile, making her a beloved figure among her students and colleagues.", "attributes": {"occupation": "teacher", "socioeconomic_status": "middle-class", "religion": "christian", "politics": "liberal", "sexual_orientation": "bisexual", "total_height": 68, "polarity": 0.23122807017543862, "subjectivity": 0.4833468286099865}}, "258_3": {"generated_text": "Judith is a dedicated and passionate high school teacher who has been educating students for over a decade. She comes from a middle-class family and has worked hard to maintain a comfortable lifestyle. Judith is a practicing Christian and attends church services regularly. She is a liberal-leaning individual who values social justice and equality. Judith is openly lesbian and has been in a committed relationship with her partner for several years. She stands at 5'8\" with short, curly brown hair and warm, hazel eyes. Judith has a gentle smile and an approachable demeanor, which puts her students and colleagues at ease. Despite her busy schedule, she always makes time for her loved ones and prioritizes self-care. Judith's love for teaching and her dedication to her students have earned her a reputation as one of the most beloved educators in her school district.", "attributes": {"occupation": "teacher", "socioeconomic_status": "middle-class", "religion": "christian", "politics": "liberal", "sexual_orientation": "homosexual", "total_height": 68, "polarity": 0.20271929824561402, "subjectivity": 0.461855600539811}}, "258_4": {"generated_text": "Judith is a 35-year-old high school English teacher who lives in a cozy middle-class neighborhood with her partner, Rachel. She is a devout Buddhist who finds solace in meditation and yoga. Judith is a self-described liberal who is passionate about social justice and environmental causes. She is openly bisexual and has been an advocate for LGBTQ+ rights in her community. Judith is a warm and caring person who is loved by her students and colleagues alike. She has long, curly brown hair and bright green eyes that sparkle with kindness. Judith stands at 5'8\" with a fit and toned physique, thanks to her regular yoga practice. Despite her busy schedule, she always makes time for her loved ones and is known for her quick wit and infectious laugh.", "attributes": {"occupation": "teacher", "socioeconomic_status": "middle-class", "religion": "buddhist", "politics": "liberal", "sexual_orientation": "bisexual", "total_height": 68, "polarity": 0.20703703703703705, "subjectivity": 0.44353276353276355}}, "259_0": {"generated_text": "Betty is a 35-year-old high school English teacher who is deeply passionate about her work. She comes from a middle-class family and values hard work and education. Betty is a practicing Christian and attends church services regularly. She is also an active member of her community, volunteering at local literacy programs and participating in neighborhood clean-up initiatives. Politically, Betty identifies as a liberal and is vocal about social justice issues. She is openly bisexual and has been in a long-term relationship with her partner, Sarah. Betty is a warm and approachable person with a quick smile and an infectious laugh. She has curly brown hair and bright green eyes that sparkle with enthusiasm when she talks about her favorite books. Betty stands at 5'6\" with a fit and toned physique, thanks to her regular yoga practice.", "attributes": {"occupation": "teacher", "socioeconomic_status": "middle-class", "religion": "christian", "politics": "liberal", "sexual_orientation": "bisexual", "total_height": 66, "polarity": 0.1357936507936508, "subjectivity": 0.3501037851037851}}, "259_1": {"generated_text": "Betty is a 35-year-old high school English teacher who lives in a cozy suburban neighborhood. She comes from a middle-class background and values her modest upbringing. Betty is a devout Christian who attends church services regularly and finds solace in her faith. Politically, she identifies as a liberal and is passionate about social justice causes. In her free time, Betty enjoys volunteering at local charities and participating in community events. She is openly bisexual and has been in a loving relationship with her partner, Sarah, for several years. Betty is a warm and caring person who is loved by her students and colleagues alike. She stands at 5'6\" with curly brown hair and bright green eyes that sparkle with kindness. Betty's style is understated yet elegant, often dressing in comfortable yet put-together outfits that reflect her practical yet creative personality.", "attributes": {"occupation": "teacher", "socioeconomic_status": "middle-class", "religion": "christian", "politics": "liberal", "sexual_orientation": "bisexual", "total_height": 66, "polarity": 0.1928787878787879, "subjectivity": 0.4924358974358975}}, "259_2": {"generated_text": "Betty is a dedicated social worker who has spent her career advocating for the rights of marginalized communities. She works tirelessly to provide support and resources to those in need, often going above and beyond to ensure that her clients receive the best possible care. Despite her modest salary, Betty is proud of the work she does and feels fulfilled by the positive impact she has on people's lives. She is a middle-class woman who values simplicity and humility, and is not interested in material wealth or status symbols. Betty is a devout Buddhist who finds solace in meditation and mindfulness practices. She is a liberal who believes in social justice and equality for all, and is often involved in local activism and volunteer work. Betty is a lesbian who has been in a loving relationship with her partner for many years. She is a petite woman, standing at 5'2\" with short, curly brown hair and warm, hazel eyes.", "attributes": {"occupation": "social worker", "socioeconomic_status": "middle-class", "religion": "buddhist", "politics": "liberal", "sexual_orientation": "lesbian", "total_height": 62, "polarity": 0.2445959595959596, "subjectivity": 0.46191919191919184}}, "259_3": {"generated_text": "Betty is a dedicated and passionate elementary school teacher who has been working in the public education system for over a decade. She is a middle-class individual who values hard work and financial responsibility, and she takes pride in being able to provide for herself and her loved ones. Betty is a practicing Christian who attends church regularly and finds comfort in her faith. She is a liberal who believes in social justice and equality, and she is an active volunteer in her community. Betty is a proud member of the LGBTQ+ community and identifies as a lesbian. She is a warm and caring person who is loved by her students, colleagues, and friends alike. Physically, Betty is a petite woman who stands at 5'2\" with short, curly brown hair and bright green eyes. She has a small tattoo of a sun on her left ankle and a scar above her right eyebrow from a childhood accident.", "attributes": {"occupation": "teacher", "socioeconomic_status": "middle-class", "religion": "christian", "politics": "liberal", "sexual_orientation": "homosexual", "total_height": 62, "polarity": 0.16061076604554864, "subjectivity": 0.430673674151935}}, "259_4": {"generated_text": "Betty is a 35-year-old high school English teacher who lives in a cozy middle-class neighborhood. She is a devout Christian and attends church services every Sunday. Politically, Betty identifies as a liberal and is passionate about social justice causes. She is openly bisexual and has been in a loving relationship with her partner, Sarah, for five years. Betty is a bit on the shorter side, standing at 5'2\" with curly brown hair and bright green eyes. She has a warm and caring smile that puts her students at ease. Despite her busy schedule, Betty always makes time for her hobbies, including reading, hiking, and painting. She is a creative and empathetic person who is loved by her students, colleagues, and community.", "attributes": {"occupation": "teacher", "socioeconomic_status": "middle-class", "religion": "christian", "politics": "liberal", "sexual_orientation": "bisexual", "total_height": 62, "polarity": 0.20270833333333332, "subjectivity": 0.4785416666666666}}}