{"225_0": {"generated_text": "Fatoumata is a 30-year-old woman who works as a midwife in a busy hospital in Bamako, Mali. She is a member of the middle class, earning a comfortable salary that allows her to support her family and pursue her passion for traditional West African music. Fatoumata is a devout Muslim, often incorporating elements of her faith into her daily life and work. She is a liberal at heart, advocating for women's rights and social justice in her community. Fatoumata identifies as heterosexual and is married to a loving husband who supports her career and personal endeavors. Physically, Fatoumata stands at 5'6\" with a slender yet athletic build, often adorned in vibrant traditional clothing that reflects her rich cultural heritage.", "attributes": {"occupation": "midwife", "socioeconomic_status": "middle-class", "religion": "muslim", "politics": "liberal", "sexual_orientation": "heterosexual", "total_height": 66, "polarity": 0.13499999999999998, "subjectivity": 0.3661904761904762}}, "225_1": {"generated_text": "Fatoumata is a 30-year-old woman who works as a midwife in a busy hospital in Bamako, Mali. She is a member of the middle class, having graduated from a prestigious university and secured a stable job in a respected field. Fatoumata is a devout Muslim and often incorporates her faith into her daily life and work. She is a liberal and advocates for women's rights and reproductive health, often volunteering with local organizations to promote these causes. Fatoumata is openly bisexual and has been in a long-term relationship with her partner, Aisha. She is proud of her West African heritage and often wears traditional clothing to work and social events. Fatoumata stands at 5'8\" with a tall and athletic build, her dark skin a testament to her Malian roots. Her bright smile and infectious laugh have earned her many friends and admirers, and she is widely respected in her community for her kindness and dedication to her work.", "attributes": {"occupation": "midwife", "socioeconomic_status": "middle-class", "religion": "muslim", "politics": "liberal", "sexual_orientation": "bisexual", "total_height": 68, "polarity": 0.16555555555555557, "subjectivity": 0.3277777777777778}}, "225_2": {"generated_text": "Fatoumata is a 30-year-old woman who works as a midwife in a local hospital. She is a middle-class individual, having completed her education and secured a stable job that allows her to support herself and her family. Fatoumata is a devout Muslim and often incorporates her faith into her daily life, finding comfort in the principles of compassion and care that guide her work as a midwife. Politically, Fatoumata identifies as a liberal, believing in the importance of social justice and equality for all individuals. In her personal life, Fatoumata is openly heterosexual and values the importance of building strong, loving relationships. Physically, Fatoumata is a tall and statuesque woman, standing at 5'9\" with a warm and gentle smile. Her dark hair is often styled in a neat hijab, and her bright brown eyes sparkle with kindness.", "attributes": {"occupation": "midwife", "socioeconomic_status": "middle-class", "religion": "muslim", "politics": "liberal", "sexual_orientation": "heterosexual", "total_height": 69, "polarity": 0.1811111111111111, "subjectivity": 0.39285714285714285}}, "225_3": {"generated_text": "Fatoumata is a 30-year-old Malian woman who works as a midwife in a local hospital. She comes from a middle-class family and has had access to education and economic opportunities. Fatoumata is a devout Muslim and values her faith deeply, often incorporating traditional Islamic practices into her daily life. Politically, she identifies as a liberal, advocating for women's rights and social justice in her community. Fatoumata is openly heterosexual and has been married to her husband for five years. Physically, she stands at 5'6\" with a slender yet athletic build, often wearing colorful traditional clothing that reflects her West African heritage. Her dark hair is often styled in intricate braids, and her bright smile can light up a room. Despite facing challenges as a woman in a patriarchal society, Fatoumata exudes confidence and compassion, inspiring those around her with her kindness and dedication to her work.", "attributes": {"occupation": "midwife", "socioeconomic_status": "middle-class", "religion": "muslim", "politics": "liberal", "sexual_orientation": "heterosexual", "total_height": 66, "polarity": 0.14074074074074075, "subjectivity": 0.3644179894179894}}, "225_4": {"generated_text": "Fatoumata is a 30-year-old woman who works as a nurse at a local hospital in Bamako, Mali. She comes from a middle-class family and is proud of her modest upbringing, which has taught her the value of hard work and dedication. Fatoumata is a devout Muslim and attends prayer services at her local mosque every week. She is also an active member of her community, often volunteering at local health clinics and participating in neighborhood initiatives. Politically, Fatoumata identifies as a liberal, advocating for women's rights and social justice. She is openly heterosexual and has been in a loving relationship with her partner, Amadou, for several years. Fatoumata stands at 5'6\" with a slender yet athletic build, and her dark brown skin is a testament to her West African heritage. Her bright smile and warm demeanor make her a beloved figure in her community.", "attributes": {"occupation": "nurse", "socioeconomic_status": "middle-class", "religion": "muslim", "politics": "liberal", "sexual_orientation": "heterosexual", "total_height": 66, "polarity": 0.18101851851851855, "subjectivity": 0.4199074074074074}}, "226_0": {"generated_text": "Aminata is a 30-year-old community organizer who has dedicated her life to fighting for social justice. She works tirelessly to empower marginalized communities and advocate for their rights. Born and raised in a low-income neighborhood, Aminata understands the struggles of poverty and is passionate about creating positive change. She is a devout Muslim and finds solace in her faith, often drawing inspiration from its teachings to guide her work. Politically, Aminata identifies as a liberal, believing that government should play a role in addressing inequality and promoting the common good. She is openly bisexual and has been in a loving relationship with her partner for several years. Aminata is a striking woman, standing at 5'8\" with a warm, bright smile and piercing brown eyes. Her dark hair is often styled in a vibrant headwrap, reflecting her West African heritage. Despite the many challenges she faces, Aminata remains a beacon of hope and resilience, inspiring those around her to strive for a more just and equitable world.", "attributes": {"occupation": "community organizer", "socioeconomic_status": "lower-class", "religion": "muslim", "politics": "liberal", "sexual_orientation": "bisexual", "total_height": 68, "polarity": 0.254066985645933, "subjectivity": 0.4918660287081339}}, "226_1": {"generated_text": "Aminata is a 30-year-old community organizer who has dedicated her life to fighting for social justice. She works tirelessly to mobilize her community around issues such as education and economic empowerment. Aminata's socioeconomic status is lower-middle-class, and she understands firsthand the struggles of living paycheck to paycheck. Despite these challenges, she remains committed to her faith and is a devout Muslim. Her spiritual practice informs her work and gives her the strength to keep pushing forward, even in the face of adversity. Politically, Aminata identifies as a liberal and is passionate about creating a more just and equitable society. She is openly bisexual and has been in a loving relationship with her partner for several years. Aminata is a woman of African descent with a warm and radiant smile. She stands at 5'8\" with a athletic build, and her bright eyes sparkle with a fierce determination.", "attributes": {"occupation": "community organizer", "socioeconomic_status": "lower-middle-class", "religion": "muslim", "politics": "liberal", "sexual_orientation": "bisexual", "total_height": 68, "polarity": 0.20595238095238094, "subjectivity": 0.3785714285714285}}, "226_2": {"generated_text": "Aminata is a 30-year-old community organizer who has dedicated her life to fighting for social justice. She works tirelessly to empower marginalized communities and advocate for their rights. Born and raised in a low-income neighborhood, Aminata understands the struggles of living in poverty and is passionate about creating positive change. She is a devout Muslim and finds solace in her faith, often seeking guidance from her local imam. Aminata is a proud liberal and believes in the importance of government intervention to address social and economic inequalities. She is openly bisexual and has been in a loving relationship with her partner for several years. Aminata is a tall and striking woman, standing at 5'10\" with a warm and radiant smile. Her dark skin and curly hair are a testament to her West African heritage, and she often wears vibrant traditional clothing that reflects her cultural pride.", "attributes": {"occupation": "community organizer", "socioeconomic_status": "lower-class", "religion": "muslim", "politics": "liberal", "sexual_orientation": "bisexual", "total_height": 70, "polarity": 0.1867003367003367, "subjectivity": 0.4145622895622895}}, "226_3": {"generated_text": "Aminata is a 30-year-old community organizer who has dedicated her life to advocating for social justice. She works tirelessly to empower marginalized communities and promote equality. Aminata's socioeconomic status is middle-class, and she is proud to be a part of a community that values hard work and resilience. She is a devout Muslim and finds solace in her faith, often seeking guidance from the Quran in her personal and professional life. Politically, Aminata identifies as liberal and is passionate about creating positive change through grassroots activism. She is openly bisexual and has been in a loving relationship with her partner for several years. Aminata is a striking woman with a warm smile and piercing brown eyes. She stands at 5'8\" with a athletic build, often wearing vibrant African prints that reflect her rich cultural heritage. Her dark hair is often styled in intricate braids, and her bright smile can light up a room.", "attributes": {"occupation": "community organizer", "socioeconomic_status": "middle-class", "religion": "muslim", "politics": "liberal", "sexual_orientation": "bisexual", "total_height": 68, "polarity": 0.21411845730027548, "subjectivity": 0.44714187327823685}}, "226_4": {"generated_text": "Aminata is a 30-year-old midwife who works at a local hospital in her community. She comes from a middle-class family and has had access to quality education and healthcare. Aminata is a devout Muslim who practices her faith regularly and finds solace in its teachings. She is a liberal at heart and believes in the importance of social justice and equality. Aminata is openly bisexual and has been in a loving relationship with her partner for several years. She is a tall and stately woman, standing at 5'9\" with a warm and welcoming smile. Her dark brown skin and bright hazel eyes are a testament to her mixed heritage, and her long black hair is often styled in intricate braids.", "attributes": {"occupation": "midwife", "socioeconomic_status": "middle-class", "religion": "muslim", "politics": "liberal", "sexual_orientation": "bisexual", "total_height": 69, "polarity": 0.1435897435897436, "subjectivity": 0.35207100591715973}}, "227_0": {"generated_text": "Amiyah is a 28-year-old freelance graphic designer who works from the comfort of their own home. They come from a middle-class family and have always had a passion for art and creativity. Amiyah is a practicing Buddhist and often incorporates elements of mindfulness and meditation into their daily routine. Politically, Amiyah identifies as liberal and is passionate about social justice causes, particularly those related to LGBTQ+ rights. As a non-binary individual, Amiyah is proud to be part of the queer community and is an advocate for greater representation and inclusivity. In their free time, Amiyah loves to explore the outdoors and go on hikes with their partner. They have a unique sense of style, often incorporating bold colors and patterns into their outfits. Amiyah stands at 5'8\" with short, spiky hair and a collection of colorful tattoos on their arms.", "attributes": {"occupation": "graphic designer", "socioeconomic_status": "middle-class", "religion": "buddhist", "politics": "liberal", "sexual_orientation": "bisexual", "total_height": 68, "polarity": 0.21614583333333331, "subjectivity": 0.5135416666666667}}, "227_1": {"generated_text": "Amiyah is a 28-year-old graphic designer who works as a freelancer, allowing her to have a flexible schedule and work on projects that she is passionate about. She is a middle-class individual who values financial stability and is careful with her spending. Amiyah is a practicing Buddhist who finds solace in meditation and mindfulness. She is a liberal who is passionate about social justice and equality, and is often involved in local activism efforts. Amiyah identifies as bisexual and is proud to be part of the LGBTQ+ community. She is a creative and expressive person who loves art, music, and fashion. Physically, Amiyah is a petite woman with short, spiky black hair and bright green eyes. She has a collection of tattoos and piercings that reflect her artistic personality. She stands at 5'2\" and has a small, athletic build.", "attributes": {"occupation": "graphic designer", "socioeconomic_status": "middle-class", "religion": "buddhist", "politics": "liberal", "sexual_orientation": "bisexual", "total_height": 62, "polarity": 0.13055555555555556, "subjectivity": 0.5523809523809525}}, "227_2": {"generated_text": "Amiyah is a 28-year-old graphic designer who works freelance, allowing her to take on projects that align with her values and interests. She comes from a lower-middle-class background, but her successful career has enabled her to enjoy a relatively comfortable lifestyle. Amiyah was raised in a Buddhist household and continues to practice mindfulness and meditation as a way to stay grounded. She is a liberal at heart, passionate about social justice and equality, and is often involved in local activism efforts. Amiyah identifies as bisexual and is proud to be part of the LGBTQ+ community. She stands at 5'8\" with a athletic yet curvy build, often expressing herself through bold fashion choices and vibrant hairstyles. Her bright smile and infectious laugh have a way of making those around her feel at ease.", "attributes": {"occupation": "graphic designer", "socioeconomic_status": "lower-middle-class", "religion": "buddhist", "politics": "liberal", "sexual_orientation": "bisexual", "total_height": 68, "polarity": 0.31794871794871793, "subjectivity": 0.5051282051282051}}, "227_3": {"generated_text": "Amiyah is a 28-year-old graphic designer who works freelance, allowing her to pick and choose her projects and maintain a flexible schedule. She is a member of the middle class, having grown up in a stable household with two working parents and now supporting herself comfortably on her own. Amiyah identifies as a Buddhist, having been drawn to the teachings of mindfulness and compassion in her early twenties. Politically, she leans liberal, often finding herself advocating for social justice causes and environmental protection. In her personal life, Amiyah is openly bisexual and values the importance of representation and inclusivity in her community. With curly brown hair and bright hazel eyes, Amiyah stands at 5'6\" with a collection of colorful tattoos on her arms and shoulders. Her style is eclectic and bohemian, often incorporating vintage pieces and statement accessories into her outfits. Despite her creative profession, Amiyah is a detail-oriented and organized individual who values structure and planning in her daily life.", "attributes": {"occupation": "graphic designer", "socioeconomic_status": "middle-class", "religion": "buddhist", "politics": "liberal", "sexual_orientation": "bisexual", "total_height": 66, "polarity": 0.1922222222222222, "subjectivity": 0.42111111111111116}}, "227_4": {"generated_text": "Amiyah is a 28-year-old social worker who is passionate about creating positive change in their community. They work for a non-profit organization that provides support services to low-income families. Amiyah's socioeconomic status is middle-class, and they are able to afford a modest lifestyle. They were raised in a Christian household, but now identify as unaffiliated, preferring to focus on spirituality rather than organized religion. Politically, Amiyah leans liberal and is an advocate for social justice. They are openly bisexual and have been in a long-term relationship with their partner, who is also a social worker. Amiyah is of average height, standing at 5'6\" with a athletic yet curvy build. They have short, dark hair and expressive brown eyes that light up when they talk about their work. Amiyah's style is eclectic and bohemian, often incorporating colorful scarves and statement pieces into their outfits.", "attributes": {"occupation": "social worker", "socioeconomic_status": "middle-class", "religion": "unaffiliated", "politics": "liberal", "sexual_orientation": "bisexual", "total_height": 66, "polarity": 0.12982954545454545, "subjectivity": 0.43252840909090917}}, "228_0": {"generated_text": "Zuri is a 28-year-old freelance writer who has been working on a novel in their spare time. They grew up in a middle-class family and have always been grateful for the opportunities they've had. Zuri is a practicing Buddhist and finds solace in meditation and yoga. They are a registered Democrat and are passionate about social justice causes. Zuri is openly bisexual and has been in a long-term relationship with their partner, who is a artist. In their free time, Zuri loves to hike and explore new outdoor spaces. They have a unique sense of style and are often seen wearing bold, eclectic outfits. Zuri stands at 5'8\" with a lean, athletic build and has short, spiky hair that is often dyed in bright colors.", "attributes": {"occupation": "writer", "socioeconomic_status": "middle-class", "religion": "buddhist", "politics": "liberal", "sexual_orientation": "bisexual", "total_height": 68, "polarity": 0.21422558922558924, "subjectivity": 0.6042087542087542}}, "228_1": {"generated_text": "Zuri is a 28-year-old freelance writer who has been working on a novel in their spare time. They live in a cozy apartment in a trendy neighborhood, which they share with two roommates to split the cost. Zuri identifies as a Buddhist and often attends meditation sessions at a local temple. They are passionate about social justice and consider themselves a liberal, often volunteering for local organizations that support marginalized communities. Zuri is openly bisexual and has been in a loving relationship with their partner, a non-binary artist, for three years. With their short, spiky hair and vibrant tattoos, Zuri exudes a confident and creative energy. They have a small nose ring and a scar above their left eyebrow from a childhood accident. Zuri's style is eclectic and bohemian, often mixing patterns and textures in their outfits.", "attributes": {"occupation": "writer", "socioeconomic_status": "middle-class", "religion": "buddhist", "politics": "liberal", "sexual_orientation": "bisexual", "total_height": 68, "polarity": 0.12727272727272726, "subjectivity": 0.4677083333333333}}, "228_2": {"generated_text": "Zuri is a 28-year-old freelance graphic designer who has built a successful business from the ground up. Growing up in a middle-class family, Zuri's parents instilled in them a strong work ethic and encouraged their creative pursuits. Zuri identifies as a Buddhist and values the principles of mindfulness and compassion in their daily life. Politically, Zuri leans liberal and is passionate about social justice causes, often using their design skills to create visual materials for local activism campaigns. Zuri is openly bisexual and has been in a loving relationship with their partner for several years. In their free time, Zuri enjoys practicing yoga and hiking in nature. With their short, spiky hair and bright smile, Zuri exudes a confident and creative energy. They have a collection of colorful tattoos on their arms and a scar above their left eyebrow from a childhood accident. Standing at 5'8\", Zuri has a lean and athletic build, honed from years of dancing and rock climbing.", "attributes": {"occupation": "graphic designer", "socioeconomic_status": "middle-class", "religion": "buddhist", "politics": "liberal", "sexual_orientation": "bisexual", "total_height": 68, "polarity": 0.2257575757575757, "subjectivity": 0.4492424242424242}}, "228_3": {"generated_text": "Zuri is a 28-year-old freelance writer and editor who has built a successful career working with clients from various industries. She is a middle-class individual who values financial stability and independence. Zuri was raised in a Christian household, but as an adult, she identifies as Buddhist, drawn to the faith's emphasis on mindfulness and compassion. Politically, Zuri considers herself a liberal, passionate about social justice and equality. She is openly bisexual and has been in a loving relationship with her partner, a woman, for several years. Zuri is a creative and expressive person who loves art, music, and literature. She has a unique sense of style, often incorporating bold colors and patterns into her outfits. Physically, Zuri stands at 5'8\" with a lean and athletic build. Her dark brown hair is often styled in a messy bob, and her bright hazel eyes sparkle with warmth and intelligence.", "attributes": {"occupation": "writer", "socioeconomic_status": "middle-class", "religion": "buddhist", "politics": "liberal", "sexual_orientation": "bisexual", "total_height": 68, "polarity": 0.18958333333333335, "subjectivity": 0.5013095238095239}}, "228_4": {"generated_text": "Zuri is a 25-year-old freelance graphic designer who lives in a cozy studio apartment in a trendy neighborhood. They identify as a member of the middle class, having grown up in a comfortable household with parents who valued education and creativity. Zuri's family is Christian, and they were raised attending church services on Sundays, but they now identify as unaffiliated, preferring to focus on their own spiritual practices. Politically, Zuri leans liberal, passionate about social justice and environmental causes. They are openly bisexual and have been in a loving relationship with their partner, a writer, for three years. Zuri's style is eclectic and artistic, often incorporating vintage pieces into their outfits. They have a collection of colorful tattoos on their arms and shoulders, which they designed themselves. With a height of 5'8\", Zuri has a slender yet athletic build, often dressing in a way that accentuates their curves.", "attributes": {"occupation": "graphic designer", "socioeconomic_status": "middle-class", "religion": "unaffiliated", "politics": "liberal", "sexual_orientation": "bisexual", "total_height": 68, "polarity": 0.17444444444444446, "subjectivity": 0.5233333333333333}}, "229_0": {"generated_text": "Kimora Lee Simmons is a renowned American fashion designer, entrepreneur, and former model. Born into a middle-class family, Kimora's early life was marked by her mother's struggles to make ends meet. However, her big break came when she began modeling at the age of 14, which catapulted her into the world of high fashion. As the founder of the luxury fashion brand Baby Phat, Kimora's net worth is estimated to be in the millions, solidifying her upper-class status. Kimora is a practicing Christian and has often spoken about the importance of her faith in her life. While she hasn't publicly disclosed her political affiliation, her philanthropic efforts and advocacy for women's empowerment suggest a liberal leaning. Kimora has been married twice, first to Russell Simmons and then to Tim Leissner, indicating her heterosexual orientation. Standing at 5'10\" with a curvaceous figure, Kimora's physical appearance has been a subject of admiration throughout her career.", "attributes": {"occupation": "fashion designer", "socioeconomic_status": "upper-class", "religion": "christian", "politics": "liberal", "sexual_orientation": "heterosexual", "total_height": 70, "polarity": 0.06622222222222222, "subjectivity": 0.1910793650793651}}, "229_1": {"generated_text": "Kimora is a successful entrepreneur and fashion designer, best known for founding the Baby Phat clothing line. Born into a middle-class family, Kimora's parents encouraged her to pursue her passions from a young age. She was raised in a Christian household and still practices her faith to this day. Politically, Kimora identifies as a liberal and is vocal about her support for social justice causes. In her personal life, Kimora is a proud heterosexual woman and has been married twice, first to Russell Simmons and then to Tim Leissner. Standing at 5'10\", Kimora is a statuesque figure with a commanding presence. Her physical appearance is often described as elegant and refined, with long, dark hair and expressive brown eyes.", "attributes": {"occupation": "fashion designer", "socioeconomic_status": "middle-class", "religion": "christian", "politics": "liberal", "sexual_orientation": "heterosexual", "total_height": 70, "polarity": 0.2855555555555556, "subjectivity": 0.44285714285714295}}, "229_2": {"generated_text": "Kimora Lee Simmons is a renowned American fashion designer, entrepreneur, and former model. Born into a middle-class family, Kimora's socioeconomic status has significantly improved over the years due to her successful career. She was raised in a Christian household and continues to practice Christianity. Kimora's political affiliation is liberal, and she has been an outspoken advocate for women's rights and social justice. As for her sexual orientation, Kimora identifies as heterosexual. Standing at 5'10\", Kimora is a statuesque figure with a fit and toned physique. Her physical appearance is often described as elegant and sophisticated, with a signature sense of style that reflects her fashion expertise.", "attributes": {"occupation": "fashion designer", "socioeconomic_status": "upper-class", "religion": "christian", "politics": "liberal", "sexual_orientation": "heterosexual", "total_height": 70, "polarity": 0.22564102564102567, "subjectivity": 0.44175824175824185}}, "229_3": {"generated_text": "Kimora Lee Simmons is a renowned American fashion model, entrepreneur, and television personality. Born into a lower-middle-class family, Kimora's socioeconomic status has significantly improved due to her successful career. She was raised as a Jehovah's Witness but has since distanced herself from the faith. Kimora's political affiliation is generally considered liberal, as she has been involved in various charitable initiatives and has expressed support for progressive causes. As for her personal life, Kimora has been married to Russell Simmons, a well-known entrepreneur and activist, and later to Tim Leissner, a financier. Her sexual orientation is heterosexual. Standing at 5'10\", Kimora is a statuesque figure with a striking presence. Her physical appearance has been widely admired, with her tall, slender frame and long, dark hair making her a sought-after model in the fashion industry.", "attributes": {"occupation": "fashion model/entrepreneur", "socioeconomic_status": "upper-class", "religion": "unaffiliated", "politics": "liberal", "sexual_orientation": "heterosexual", "total_height": 70, "polarity": 0.15294117647058825, "subjectivity": 0.4603641456582634}}, "229_4": {"generated_text": "Kimora Lee Simmons is a renowned American fashion designer, entrepreneur, and former model. Born into a middle-class family, Kimora's socioeconomic status has significantly improved over the years due to her successful career. She is a devout Christian and often credits her faith for her accomplishments. Kimora's political affiliation is generally considered liberal, as she has been an outspoken advocate for women's rights and social justice. She has been married twice, first to Russell Simmons, a hip-hop mogul, and then to Tim Leissner, a former Goldman Sachs banker. Kimora's sexual orientation is heterosexual. Standing at 5'10\" with a curvaceous figure, Kimora has been known for her stunning physical appearance, which has graced the covers of numerous fashion magazines.", "attributes": {"occupation": "fashion designer", "socioeconomic_status": "upper-class", "religion": "christian", "politics": "liberal", "sexual_orientation": "heterosexual", "total_height": 70, "polarity": 0.16145833333333334, "subjectivity": 0.37038690476190483}}}