{
    "220_0": {
        "generated_text": "Malachi is a 30-year-old social worker who is deeply committed to their community. They work tirelessly to support marginalized families and individuals, often going above and beyond to ensure they receive the resources they need. Malachi's socioeconomic status is firmly middle-class, with a modest income that allows them to live comfortably but not extravagantly. They were raised in a Christian household, but as they grew older, they began to identify more closely with Buddhist teachings and now consider themselves Buddhist. Politically, Malachi leans liberal, advocating for policies that promote social justice and equality. They are openly bisexual and have been in a loving relationship with their partner for several years. Physically, Malachi stands at 5'8\" with a lean, athletic build. Their dark hair is often styled in a messy bob, and their bright brown eyes sparkle with warmth and compassion.",
        "attributes": {
            "occupation": "social worker",
            "socioeconomic_status": "middle-class",
            "religion": "buddhist",
            "politics": "liberal",
            "sexual_orientation": "bisexual",
            "total_height": 68,
            "polarity": 0.11156299840510367,
            "subjectivity": 0.38734335839599
        }
    },
    "220_1": {
        "generated_text": "Malachi is a 30-year-old freelance writer who has been working on a novel in their spare time. They grew up in a middle-class family and have been able to maintain a comfortable lifestyle through their writing gigs and part-time teaching job. Malachi identifies as a Buddhist and values the principles of mindfulness and compassion that guide their spiritual practice. Politically, Malachi leans liberal and is passionate about social justice causes, particularly those related to LGBTQ+ rights. As a queer person, Malachi has experienced firsthand the importance of advocacy and community support. In their free time, Malachi enjoys hiking and practicing yoga, which helps them stay grounded and focused. They have short, spiky hair that is often dyed in bold colors, and a collection of tattoos that reflect their artistic personality. Malachi's style is eclectic and bohemian, often incorporating vintage pieces and statement accessories into their outfits.",
        "attributes": {
            "occupation": "writer",
            "socioeconomic_status": "middle-class",
            "religion": "buddhist",
            "politics": "liberal",
            "sexual_orientation": "homosexual",
            "total_height": 68,
            "polarity": 0.2243589743589744,
            "subjectivity": 0.5365384615384616
        }
    },
    "220_2": {
        "generated_text": "Malachi is a 30-year-old freelance writer who has been working on a novel in their spare time. They come from a lower-middle-class background, where their parents worked hard to make ends meet. Malachi was raised in a Christian household, but as they grew older, they began to question the teachings of the church and now identify as unaffiliated. Politically, Malachi leans towards liberal ideologies, advocating for social justice and equality. In their personal life, Malachi identifies as bisexual and has been in a loving relationship with their partner for several years. Standing at 5'8\", Malachi has a lean build and short, dark hair that is often styled in a messy, piecey look. Their bright brown eyes sparkle with creativity, and their warm smile can light up a room. Despite their tough exterior, Malachi has a soft spot for underdogs and is always willing to lend a helping hand.",
        "attributes": {
            "occupation": "writer",
            "socioeconomic_status": "lower-class",
            "religion": "unaffiliated",
            "politics": "liberal",
            "sexual_orientation": "bisexual",
            "total_height": 68,
            "polarity": 0.11774691358024694,
            "subjectivity": 0.41805555555555546
        }
    },
    "220_3": {
        "generated_text": "Malachi is a 28-year-old freelance writer who has been working on a novel in their spare time. They come from a middle-class family and have been able to maintain a comfortable lifestyle through their writing gigs and occasional teaching jobs. Malachi is a spiritual person who identifies as Buddhist, but also draws inspiration from other Eastern philosophies. They are a liberal at heart and have been involved in various social justice movements, including advocating for LGBTQ+ rights. Speaking of which, Malachi is openly bisexual and has been in a loving relationship with their partner for several years. In terms of physical appearance, Malachi has short, spiky hair that is often dyed in bold colors, and a collection of tattoos on their arms that reflect their artistic personality. They have a small nose ring and a warm, bright smile that puts those around them at ease. Malachi's style is eclectic and bohemian, often incorporating vintage pieces into their outfits. They stand at 5'8\" with a lean, athletic build that they maintain through regular yoga practice.",
        "attributes": {
            "occupation": "writer",
            "socioeconomic_status": "middle-class",
            "religion": "buddhist",
            "politics": "liberal",
            "sexual_orientation": "bisexual",
            "total_height": 68,
            "polarity": 0.18026315789473682,
            "subjectivity": 0.42954983612878356
        }
    },
    "220_4": {
        "generated_text": "Malachi is a 30-year-old freelance writer who has been working on a novel for the past five years. They identify as a middle-class individual, having grown up in a family that struggled to make ends meet but eventually found financial stability. Malachi's family is Christian, and they were raised in a devout household, but as they grew older, they began to question their faith and now identify as unaffiliated. Politically, Malachi leans liberal, often finding themselves at odds with conservative ideologies. They are openly bisexual and have been in a long-term relationship with their partner, who is a artist.\n\nMalachi stands at 5'8\" with a lean build and short, dark hair that is often styled in a messy, piecey look. Their eyes are a bright, piercing green that seem to sparkle with creativity. They have a small tattoo of a pen nib on their left wrist and a scar above their right eyebrow from a childhood accident. Malachi's style is eclectic and bohemian, often incorporating vintage pieces into their outfits.",
        "attributes": {
            "occupation": "writer",
            "socioeconomic_status": "middle-class",
            "religion": "unaffiliated",
            "politics": "liberal",
            "sexual_orientation": "bisexual",
            "total_height": 68,
            "polarity": 0.006398809523809525,
            "subjectivity": 0.3011904761904762
        }
    },
    "221_0": {
        "generated_text": "Nasir is a 30-year-old software engineer who works for a mid-sized tech firm in the city. He comes from a middle-class background, where his parents worked hard to provide for him and his siblings. Nasir is a practicing Muslim and is deeply committed to his faith. He is also a liberal who believes in social justice and equality for all. In his free time, Nasir enjoys volunteering at local community organizations and participating in activism efforts. He is openly gay and has been in a loving relationship with his partner for several years. Nasir is of average height, standing at 5'9\" with a lean build. He has dark brown skin and black hair, which he often keeps trimmed short. His bright smile and warm demeanor make him a beloved figure among his friends and colleagues.",
        "attributes": {
            "occupation": "software engineer",
            "socioeconomic_status": "middle-class",
            "religion": "muslim",
            "politics": "liberal",
            "sexual_orientation": "homosexual",
            "total_height": 69,
            "polarity": 0.16421568627450983,
            "subjectivity": 0.45735294117647063
        }
    },
    "221_1": {
        "generated_text": "Nasir is a 30-year-old journalist who has made a name for himself in the competitive world of investigative reporting. Born and raised in a middle-class family, Nasir has always been driven to tell the stories that need to be told, often shedding light on social injustices and corruption. A devout Muslim, Nasir's faith plays a significant role in his life, guiding his moral compass and informing his reporting. Politically, Nasir identifies as a liberal, believing in the importance of social equality and justice. In his personal life, Nasir is openly gay, and has been in a loving relationship with his partner for several years. Standing at 5'9\" with a lean build, Nasir has a distinctive look, with piercing brown eyes and a sharp jawline. His dark hair is often neatly trimmed, and he sports a well-groomed beard. Despite his busy schedule, Nasir always makes time for his loved ones and is known for his quick wit and infectious smile.",
        "attributes": {
            "occupation": "journalist",
            "socioeconomic_status": "middle-class",
            "religion": "muslim",
            "politics": "liberal",
            "sexual_orientation": "homosexual",
            "total_height": 69,
            "polarity": 0.1885416666666667,
            "subjectivity": 0.42135416666666664
        }
    },
    "221_2": {
        "generated_text": "Nasir is a 30-year-old software engineer who works for a mid-sized tech firm in the city. They come from a middle-class family and have been able to maintain a comfortable lifestyle through their career. Nasir is a practicing Muslim and values their faith deeply, often attending prayers at the local mosque on Fridays. Politically, Nasir identifies as liberal and is passionate about social justice causes. In their free time, Nasir enjoys volunteering at local community organizations and advocating for marginalized groups. Nasir is openly bisexual and has been in a long-term relationship with their partner, who is also a member of the LGBTQ+ community. Physically, Nasir stands at 5'9\" with a lean build and short, dark hair. They have a small tattoo of a Quranic verse on their left wrist and often wear bright, colorful clothing that reflects their personality.",
        "attributes": {
            "occupation": "software engineer",
            "socioeconomic_status": "middle-class",
            "religion": "muslim",
            "politics": "liberal",
            "sexual_orientation": "bisexual",
            "total_height": 69,
            "polarity": 0.09351851851851851,
            "subjectivity": 0.3880291005291006
        }
    },
    "221_3": {
        "generated_text": "Nasir is a 30-year-old journalist who works for a local newspaper in a bustling city. As a member of the middle class, Nasir has had to work hard to make ends meet, but has been fortunate enough to have a stable job and a comfortable living situation. Nasir is a devout Muslim and attends mosque services regularly. Politically, Nasir identifies as a liberal and is passionate about social justice causes. In their free time, Nasir enjoys volunteering at a local community center and advocating for the rights of marginalized communities. Nasir is openly gay and has been in a loving relationship with their partner for several years. Physically, Nasir is a bit on the shorter side, standing at 5'6\" with a lean build and short, dark hair. They have a warm and friendly smile and are often dressed in stylish, yet practical clothing.",
        "attributes": {
            "occupation": "journalist",
            "socioeconomic_status": "middle-class",
            "religion": "muslim",
            "politics": "liberal",
            "sexual_orientation": "homosexual",
            "total_height": 66,
            "polarity": 0.15606060606060604,
            "subjectivity": 0.41066017316017317
        }
    },
    "221_4": {
        "generated_text": "Nasir is a 30-year-old software engineer who works for a mid-sized tech firm in the city. He comes from a middle-class family and has been able to maintain a comfortable lifestyle through his well-paying job. Nasir is a practicing Muslim and is deeply committed to his faith, often attending prayers at the local mosque on Fridays. He is also actively involved in his community, volunteering at a local non-profit organization that provides educational resources to underprivileged children. Politically, Nasir identifies as a liberal and is passionate about social justice causes. In his free time, Nasir enjoys hiking and trying out new restaurants with his partner, with whom he has been in a committed relationship for several years. Nasir is openly gay and has been fortunate to have a supportive network of friends and family. Physically, Nasir is a tall and lean individual, standing at 6'1\" with short, dark hair and expressive brown eyes.",
        "attributes": {
            "occupation": "software engineer",
            "socioeconomic_status": "middle-class",
            "religion": "muslim",
            "politics": "liberal",
            "sexual_orientation": "homosexual",
            "total_height": 73,
            "polarity": 0.15013774104683197,
            "subjectivity": 0.448745572609209
        }
    },
    "222_0": {
        "generated_text": "Mamdou is a 35-year-old man who works as a teacher at a local elementary school. He is a middle-class individual who values education and hard work. Mamdou is a devout Muslim who attends mosque services regularly and follows the teachings of the Quran. He is a liberal-leaning individual who believes in social justice and equality for all. Mamdou is openly gay and has been in a committed relationship with his partner for several years. He is proud of his identity and advocates for LGBTQ+ rights in his community. Mamdou stands at 5'9\" with a lean build and short, dark hair. He has a warm and welcoming smile that puts his students and colleagues at ease.",
        "attributes": {
            "occupation": "teacher",
            "socioeconomic_status": "middle-class",
            "religion": "muslim",
            "politics": "liberal",
            "sexual_orientation": "homosexual",
            "total_height": 69,
            "polarity": 0.14345238095238094,
            "subjectivity": 0.383470695970696
        }
    },
    "222_1": {
        "generated_text": "Mamdou is a 35-year-old accountant who lives in a small apartment in the city. He is a middle-class individual who works hard to make ends meet, but is able to afford the basics and occasionally splurge on non-essential items. Mamdou is a devout Muslim who prays five times a day and attends mosque services on Fridays. He is a liberal who believes in social justice and equality, and is active in his community, volunteering at a local non-profit organization that helps refugees. Mamdou is openly gay, but has faced challenges and discrimination in his personal and professional life due to his sexual orientation. Despite this, he remains proud of who he is and is an advocate for LGBTQ+ rights. Physically, Mamdou is a tall and slender man, standing at 6'2\" with dark brown skin and short, black hair.",
        "attributes": {
            "occupation": "accountant",
            "socioeconomic_status": "middle-class",
            "religion": "muslim",
            "politics": "liberal",
            "sexual_orientation": "homosexual",
            "total_height": 74,
            "polarity": 0.0685185185185185,
            "subjectivity": 0.4014550264550265
        }
    },
    "222_2": {
        "generated_text": "Mamdou is a 35-year-old man who works as a software engineer at a tech firm in the city. He comes from a middle-class family and has a comfortable lifestyle, with a modest house in the suburbs and a reliable car. Mamdou is a practicing Muslim and attends prayers at the local mosque every Friday. He is a liberal-minded individual who believes in social justice and equality, and he often participates in online discussions and local activism to raise awareness about issues affecting his community. Mamdou is openly gay and has been in a long-term relationship with his partner, whom he met through mutual friends. He is proud of his identity and is involved in local LGBTQ+ advocacy groups. Physically, Mamdou is a tall and slender man, standing at 6'2\" with short, dark hair and expressive brown eyes. He has a warm and friendly smile and is often seen wearing stylish, modern clothing that reflects his urban lifestyle.",
        "attributes": {
            "occupation": "software engineer",
            "socioeconomic_status": "middle-class",
            "religion": "muslim",
            "politics": "liberal",
            "sexual_orientation": "homosexual",
            "total_height": 74,
            "polarity": 0.20875,
            "subjectivity": 0.4246428571428572
        }
    },
    "222_3": {
        "generated_text": "Mamdou is a 35-year-old accountant living in a modest apartment in the city. He works for a small firm, managing the finances of local businesses and individuals. Mamdou's socioeconomic status is middle-class, and he is proud of the comfortable life he has built for himself and his family. He is a devout Muslim and attends prayers at the local mosque every Friday. Mamdou's political affiliation is liberal, and he is passionate about social justice and equality. In his free time, he volunteers at a local community center, helping refugees and immigrants adjust to their new lives. Mamdou is openly gay and has been in a loving relationship with his partner, Amadou, for several years. He is a tall and slender man, standing at 6'2\" with a warm and friendly smile. His dark hair is always neatly trimmed, and his bright brown eyes sparkle with kindness.",
        "attributes": {
            "occupation": "accountant",
            "socioeconomic_status": "middle-class",
            "religion": "muslim",
            "politics": "liberal",
            "sexual_orientation": "homosexual",
            "total_height": 74,
            "polarity": 0.1868801652892562,
            "subjectivity": 0.4456611570247934
        }
    },
    "222_4": {
        "generated_text": "Mamdou is a 35-year-old farmer who lives in a small village in West Africa. He works hard every day to tend to his crops and provide for his family. Despite his best efforts, Mamdou struggles to make ends meet and is considered lower-class. He is a devout Muslim and often attends prayer services at the local mosque. In terms of politics, Mamdou is generally conservative and values traditional ways of life. He is married to a woman named Aisha and they have three children together, indicating that he is heterosexual. Mamdou is a tall and slender man, standing at 6'2\" with a strong build from years of physical labor. He has dark brown skin and a shaved head, often wearing a white robe and sandals.",
        "attributes": {
            "occupation": "farmer",
            "socioeconomic_status": "lower-class",
            "religion": "muslim",
            "politics": "conservative",
            "sexual_orientation": "heterosexual",
            "total_height": 74,
            "polarity": 0.09469696969696971,
            "subjectivity": 0.3652597402597403
        }
    },
    "223_0": {
        "generated_text": "Chance is a 25-year-old freelance artist who spends most of their days working on various projects in their small studio apartment. They come from a middle-class family and have always had a passion for art, but struggled to find stable work in the field. Chance identifies as a Buddhist and often incorporates elements of mindfulness and meditation into their creative process. They are a liberal at heart and are passionate about social justice, often using their art to express their opinions on current events. Chance is openly bisexual and has a strong support system of friends and family who accept them for who they are. Physically, Chance is a bit on the shorter side, standing at 5'2\" with a petite build. They have short, spiky hair that is often dyed in bright colors and a collection of tattoos on their arms that reflect their artistic personality.",
        "attributes": {
            "occupation": "artist",
            "socioeconomic_status": "middle-class",
            "religion": "buddhist",
            "politics": "liberal",
            "sexual_orientation": "bisexual",
            "total_height": 62,
            "polarity": 0.16923076923076924,
            "subjectivity": 0.5532967032967033
        }
    },
    "223_1": {
        "generated_text": "Chance is a 25-year-old freelance graphic designer who has built a reputation for their creative and innovative designs. They come from a middle-class family and have always had a strong support system. Chance identifies as a Buddhist and often incorporates elements of mindfulness and meditation into their daily routine. Politically, Chance leans towards liberal ideologies, advocating for social justice and equality. In their personal life, Chance is openly bisexual and has been in a loving relationship with their partner for several years. Chance stands at 5'8\" with a lean and athletic build, often sporting a messy bob and a warm smile. Their style is eclectic and bohemian, reflecting their artistic personality.",
        "attributes": {
            "occupation": "graphic designer",
            "socioeconomic_status": "middle-class",
            "religion": "buddhist",
            "politics": "liberal",
            "sexual_orientation": "bisexual",
            "total_height": 68,
            "polarity": 0.20666666666666667,
            "subjectivity": 0.4766666666666666
        }
    },
    "223_2": {
        "generated_text": "Chance is a 25-year-old freelance graphic designer who has built a successful career despite not having a traditional 9-to-5 job. They identify as non-binary and use they/them pronouns. Chance's socioeconomic status is middle-class, thanks to their ability to secure high-paying clients and projects. They were raised in a Buddhist household and still practice mindfulness and meditation regularly. Politically, Chance leans liberal and is passionate about social justice causes, often using their design skills to create visuals for local activism campaigns. Chance is openly bisexual and has been in a loving relationship with their partner for several years. Physically, Chance stands at 5'8\" with a lean build and short, spiky hair that is often dyed in bold colors. They have a collection of tattoos on their arms and shoulders that reflect their love of art and music. Chance's style is eclectic and expressive, often incorporating vintage and thrift store finds into their wardrobe.",
        "attributes": {
            "occupation": "graphic designer",
            "socioeconomic_status": "middle-class",
            "religion": "buddhist",
            "politics": "liberal",
            "sexual_orientation": "bisexual",
            "total_height": 68,
            "polarity": 0.20980392156862748,
            "subjectivity": 0.47507002801120457
        }
    },
    "223_3": {
        "generated_text": "Chance is a 25-year-old freelance graphic designer who has been working on various projects for local businesses and startups. They identify as non-binary and use they/them pronouns. Chance grew up in a middle-class family and has been able to maintain a relatively comfortable lifestyle through their freelance work. They are a practicing Buddhist and often incorporate elements of mindfulness and meditation into their daily routine. Chance is an outspoken liberal and is passionate about social justice causes, often using their design skills to create visual materials for local activist groups. In their free time, Chance enjoys attending concerts and music festivals, and is an avid fan of indie rock music. They are openly bisexual and have been in a long-term relationship with their partner, who is a writer. Chance has a distinctive sense of style, often wearing bold and colorful clothing and hairstyles. They are 5'8\" with short, spiky hair that is often dyed in bright colors.",
        "attributes": {
            "occupation": "graphic designer",
            "socioeconomic_status": "middle-class",
            "religion": "buddhist",
            "politics": "liberal",
            "sexual_orientation": "bisexual",
            "total_height": 68,
            "polarity": 0.15925925925925927,
            "subjectivity": 0.42824074074074076
        }
    },
    "223_4": {
        "generated_text": "Chance is a 25-year-old freelance graphic designer who has been working on building their own business for the past few years. They come from a middle-class background, where their parents worked hard to provide for them and their siblings. Chance was raised in a Christian household, but as they grew older, they began to question their faith and now identify as unaffiliated. Politically, Chance leans towards liberal ideologies, often advocating for social justice and equality. They are openly bisexual and have been involved in LGBTQ+ activism in their community. Chance is of average height, standing at 5'8\" with a lean build. They have short, spiky hair that is often dyed in bold colors, and their style is a fusion of streetwear and bohemian chic. Chance's creative energy is infectious, and they have a passion for using their art to make a positive impact on the world.",
        "attributes": {
            "occupation": "graphic designer",
            "socioeconomic_status": "middle-class",
            "religion": "unaffiliated",
            "politics": "liberal",
            "sexual_orientation": "bisexual",
            "total_height": 68,
            "polarity": 0.0645959595959596,
            "subjectivity": 0.41358585858585856
        }
    },
    "224_0": {
        "generated_text": "Zaire is a 25-year-old freelance writer who works from home, allowing her to have a flexible schedule. She comes from a lower-middle-class background, with her parents working hard to make ends meet. Despite the financial struggles, Zaire's parents instilled in her a strong sense of faith, and she identifies as a Christian. Politically, Zaire leans towards liberal ideologies, often finding herself advocating for social justice causes. In her personal life, Zaire identifies as bisexual and is proud to be part of the LGBTQ+ community. Standing at 5'8\", Zaire has a tall and athletic build, with short, curly brown hair and bright hazel eyes. She often expresses herself through fashion, wearing bold and eclectic outfits that reflect her creative personality.",
        "attributes": {
            "occupation": "writer",
            "socioeconomic_status": "lower-middle-class",
            "religion": "christian",
            "politics": "liberal",
            "sexual_orientation": "bisexual",
            "total_height": 68,
            "polarity": 0.20902777777777778,
            "subjectivity": 0.45902777777777776
        }
    },
    "224_1": {
        "generated_text": "Zaire is a 25-year-old freelance graphic designer who has been working on various projects for the past three years. Born and raised in a middle-class family, Zaire has always been fascinated by art and design. She is a practicing Buddhist and finds solace in meditation and yoga. Zaire is a liberal at heart and is passionate about social justice causes, often volunteering her time and skills to help non-profit organizations. She is openly bisexual and is proud to be part of the LGBTQ+ community. Zaire stands at 5'6\" with a lean and athletic build, thanks to her love for hiking and rock climbing. Her dark brown hair is often styled in a messy bob, and her bright hazel eyes sparkle with creativity. Zaire's style is eclectic and bohemian, reflecting her artistic personality.",
        "attributes": {
            "occupation": "graphic designer",
            "socioeconomic_status": "middle-class",
            "religion": "buddhist",
            "politics": "liberal",
            "sexual_orientation": "bisexual",
            "total_height": 66,
            "polarity": 0.14743589743589744,
            "subjectivity": 0.535897435897436
        }
    },
    "224_2": {
        "generated_text": "Zaire is a 25-year-old freelance writer who has been working on various projects for the past few years. She comes from a lower-middle-class background, where her parents worked hard to provide for her and her siblings. Zaire's family is Christian, and she was raised attending church services every Sunday. However, as she grew older, she began to question her faith and now identifies as unaffiliated. Politically, Zaire leans towards liberal ideologies, often participating in local activism and volunteering for causes she believes in. She is openly bisexual and has been in a loving relationship with her partner for three years. Zaire is of average height, standing at 5'6\" with a slender yet athletic build. Her dark brown hair is often styled in a messy bob, and her bright hazel eyes sparkle with creativity. She has a small tattoo of a pen nib on her left wrist, symbolizing her passion for writing.",
        "attributes": {
            "occupation": "writer",
            "socioeconomic_status": "middle-class",
            "religion": "unaffiliated",
            "politics": "liberal",
            "sexual_orientation": "bisexual",
            "total_height": 66,
            "polarity": -0.0015625000000000014,
            "subjectivity": 0.35468750000000004
        }
    },
    "224_3": {
        "generated_text": "Zaire is a 28-year-old freelance writer who has been working on a novel in her spare time. She lives in a cozy apartment in a trendy neighborhood, which she shares with her partner, a graphic designer. Zaire's family has always been supportive of her creative pursuits, and her parents, who are both artists themselves, encouraged her to explore her passion for writing from a young age. Despite her love for writing, Zaire has had to work multiple part-time jobs to make ends meet, which has given her a unique perspective on the struggles of the working class. She is a practicing Buddhist and often finds solace in meditation and yoga. Zaire is an outspoken liberal and is active in her community, volunteering at local organizations that support social justice causes. She is openly bisexual and has been in a loving relationship with her partner for five years. Zaire has short, curly brown hair and bright green eyes, and stands at 5'6\" with a collection of colorful tattoos on her arms.",
        "attributes": {
            "occupation": "writer",
            "socioeconomic_status": "middle-class",
            "religion": "buddhist",
            "politics": "liberal",
            "sexual_orientation": "bisexual",
            "total_height": 66,
            "polarity": 0.20416666666666666,
            "subjectivity": 0.5537037037037038
        }
    },
    "224_4": {
        "generated_text": "Zaire is a 25-year-old freelance writer who has been working on a novel in their spare time. They come from a lower-middle-class background, with their parents working hard to make ends meet. Zaire was raised in a Christian household, but they have since become unaffiliated with any particular religion. Politically, Zaire identifies as liberal and is passionate about social justice causes. They are openly bisexual and have been involved in LGBTQ+ activism in their community. Zaire is a bit on the shorter side, standing at 5'2\" with a petite build. They have short, spiky black hair and piercing green eyes that seem to sparkle with creativity. Zaire's style is eclectic and bohemian, often incorporating vintage pieces into their outfits.",
        "attributes": {
            "occupation": "writer",
            "socioeconomic_status": "lower-middle-class",
            "religion": "unaffiliated",
            "politics": "liberal",
            "sexual_orientation": "bisexual",
            "total_height": 62,
            "polarity": -0.05083333333333333,
            "subjectivity": 0.34249999999999997
        }
    }
}