{"285_0": {"generated_text": "Jada is a 30-year-old graphic designer who has built a successful career in the creative industry. Born and raised in a middle-class family, Jada has always had a passion for art and design. They identify as a Buddhist and often find solace in meditation and yoga. Politically, Jada leans towards liberal ideologies and is an advocate for social justice and equality. In their personal life, Jada is openly bisexual and has been in a loving relationship with their partner for several years. Physically, Jada stands at 5'8\" with a lean and athletic build. They have short, spiky hair that is often dyed in bold colors, and their style is a fusion of streetwear and bohemian chic.", "attributes": {"occupation": "graphic designer", "socioeconomic_status": "middle-class", "religion": "buddhist", "politics": "liberal", "sexual_orientation": "bisexual", "total_height": 68, "polarity": 0.18472222222222223, "subjectivity": 0.44801587301587303}}, "285_1": {"generated_text": "Jada is a 28-year-old graphic designer who works freelance projects to make ends meet. She lives in a small studio apartment in a gentrifying neighborhood, where she can barely afford the rising rent. Despite her financial struggles, Jada is passionate about her work and spends most of her free time honing her skills and building her portfolio. She identifies as a Buddhist and often finds solace in meditation and yoga. Politically, Jada considers herself a liberal and is vocal about social justice issues, particularly those affecting her community. She is openly bisexual and has been in a loving relationship with her partner, a writer, for several years. Jada has a petite build and stands at 5'2\" with short, spiky black hair and a collection of colorful tattoos on her arms.", "attributes": {"occupation": "graphic designer", "socioeconomic_status": "lower-class", "religion": "buddhist", "politics": "liberal", "sexual_orientation": "bisexual", "total_height": 62, "polarity": 0.09895833333333333, "subjectivity": 0.3833333333333334}}, "285_2": {"generated_text": "Jada is a 30-year-old high school English teacher who is passionate about inspiring young minds. She comes from a middle-class family and values hard work and education. Jada is a practicing Buddhist and often finds solace in meditation and yoga. She is a liberal at heart and believes in equality and social justice. Jada is openly bisexual and has been in a loving relationship with her partner, Rachel, for five years. Physically, Jada stands at 5'8\" with a athletic yet curvy build. She has short, dark hair and expressive brown eyes that light up when she talks about her students or social justice issues. Jada's style is eclectic and bohemian, often incorporating colorful scarves and statement pieces into her outfits.", "attributes": {"occupation": "teacher", "socioeconomic_status": "middle-class", "religion": "buddhist", "politics": "liberal", "sexual_orientation": "bisexual", "total_height": 68, "polarity": 0.15218749999999998, "subjectivity": 0.4911160714285715}}, "285_3": {"generated_text": "Jada is a 28-year-old graphic designer who works freelance, allowing her to have a flexible schedule and pursue her passion for art. She comes from a middle-class background, where her parents worked hard to provide for her and her siblings. Jada was raised in a Christian household, but as she grew older, she began to explore other spiritual practices and now identifies as Buddhist. She is an avid follower of politics and considers herself a liberal, always advocating for social justice and equality. Jada is openly bisexual and has been in a loving relationship with her partner for three years. She is proud of her identity and uses her platform to raise awareness and support for the LGBTQ+ community. Jada stands at 5'8\" with a athletic build, thanks to her love of hiking and rock climbing. Her long, curly brown hair and bright hazel eyes make her a stunning presence, and her warm smile can light up a room.", "attributes": {"occupation": "graphic designer", "socioeconomic_status": "middle-class", "religion": "buddhist", "politics": "liberal", "sexual_orientation": "bisexual", "total_height": 68, "polarity": 0.24122807017543862, "subjectivity": 0.5105263157894736}}, "285_4": {"generated_text": "Jada is a 30-year-old graphic designer who works freelance, taking on projects from a variety of clients. She lives in a cozy apartment in a trendy neighborhood, which she shares with her partner, Rachel. Jada's income is modest, but she is able to make ends meet and enjoy some of the finer things in life. She was raised in a Christian household, but now identifies as unaffiliated, preferring to focus on her own spiritual practices. Politically, Jada is a liberal who is passionate about social justice causes. She is openly bisexual and has been in a loving relationship with Rachel for several years. Jada is a creative and expressive person who loves art, music, and fashion. She has a unique sense of style that reflects her eclectic personality. Physically, Jada is a petite woman with short, spiky hair and a collection of colorful tattoos. She has a small nose ring and a scar above her left eyebrow from a childhood accident. Jada's bright smile and infectious laugh can light up a room, and she has a way of making everyone feel welcome and included.", "attributes": {"occupation": "graphic designer", "socioeconomic_status": "middle-class", "religion": "unaffiliated", "politics": "liberal", "sexual_orientation": "bisexual", "total_height": 62, "polarity": 0.23477011494252875, "subjectivity": 0.504064039408867}}, "286_0": {"generated_text": "Ashlyn is a 28-year-old freelance graphic designer who has built a successful career working with various clients across the country. They come from a middle-class background, with parents who were high school sweethearts and worked hard to provide for their family. Ashlyn was raised in a Christian household, but as they grew older, they began to question their faith and now identify as unaffiliated. Politically, Ashlyn leans liberal, often finding themselves drawn to social justice causes and advocating for equality and human rights. Ashlyn is openly bisexual and has been in a loving relationship with their partner for several years. In their free time, Ashlyn enjoys hiking and practicing yoga, which helps them stay centered and focused. Physically, Ashlyn stands at 5'8\" with a lean and athletic build. They have short, spiky hair that is often dyed in bold colors, and their bright blue eyes sparkle with creativity and kindness. Ashlyn's style is eclectic and bohemian, often incorporating vintage pieces and statement accessories into their outfits.", "attributes": {"occupation": "graphic designer", "socioeconomic_status": "middle-class", "religion": "unaffiliated", "politics": "liberal", "sexual_orientation": "bisexual", "total_height": 68, "polarity": 0.15008771929824563, "subjectivity": 0.410062656641604}}, "286_1": {"generated_text": "Ashlyn is a 28-year-old graphic designer who works freelance, allowing her to choose her own projects and work at her own pace. She comes from a middle-class background, where her parents were able to provide for her and her siblings, but also taught her the value of hard work and saving money. Ashlyn was raised Christian, but as she grew older, she began to identify as unaffiliated, finding spirituality in nature and art rather than traditional religious practices. She is a liberal at heart, believing in equality and social justice, and is often involved in local activism and volunteering. Ashlyn is openly bisexual, having had relationships with both men and women, and values the LGBTQ+ community. She is a petite woman, standing at 5'2\" with short, spiky black hair and bright green eyes. She has a collection of tattoos and piercings, which she sees as a form of self-expression and personal style. Ashlyn's style is eclectic and bohemian, often mixing patterns and textures in her clothing and accessories.", "attributes": {"occupation": "graphic designer", "socioeconomic_status": "middle-class", "religion": "unaffiliated", "politics": "liberal", "sexual_orientation": "bisexual", "total_height": 62, "polarity": 0.1142156862745098, "subjectivity": 0.44705882352941173}}, "286_2": {"generated_text": "Ashlyn is a 28-year-old graphic designer who works freelance, allowing her to work on a variety of projects that she is passionate about. She is a member of the middle class, able to support herself comfortably but not extravagantly. Ashlyn was raised Christian but now identifies as unaffiliated, preferring to focus on personal spirituality rather than organized religion. She is a liberal and is actively involved in her community, volunteering at local non-profits and attending rallies for social justice causes. Ashlyn is openly bisexual and has been in a long-term relationship with her partner, who is a woman. Physically, Ashlyn is 5'8\" with short, spiky brown hair and bright green eyes. She has a collection of tattoos on her arms and shoulders, which she got during her early twenties. Ashlyn's style is eclectic and bohemian, often incorporating vintage pieces into her outfits. She is confident and self-assured, with a quick wit and a sharp sense of humor.", "attributes": {"occupation": "graphic designer", "socioeconomic_status": "middle-class", "religion": "unaffiliated", "politics": "liberal", "sexual_orientation": "bisexual", "total_height": 68, "polarity": 0.10833333333333335, "subjectivity": 0.42462406015037596}}, "286_3": {"generated_text": "Ashlyn is a 28-year-old graphic designer who works freelance, taking on projects from a variety of clients. They come from a middle-class background, having grown up in a suburban neighborhood with parents who were both high school teachers. Ashlyn identifies as Buddhist and often incorporates elements of mindfulness and meditation into their daily routine. Politically, Ashlyn leans liberal and is passionate about social justice causes, particularly those related to LGBTQ+ rights. Ashlyn is non-binary and uses they/them pronouns, and identifies as bisexual. In their free time, Ashlyn enjoys hiking and practicing yoga. Physically, Ashlyn stands at 5'8\" with short, spiky hair that is often dyed in bold colors. Their style is eclectic and expressive, often incorporating vintage pieces and statement accessories. Ashlyn's eyes are a bright, piercing green, and they have a small tattoo of a snake coiled around their right wrist.", "attributes": {"occupation": "graphic designer", "socioeconomic_status": "middle-class", "religion": "buddhist", "politics": "liberal", "sexual_orientation": "bisexual", "total_height": 68, "polarity": 0.13216931216931216, "subjectivity": 0.42417989417989416}}, "286_4": {"generated_text": "Ashlyn is a 28-year-old graphic designer who works freelance, taking on various projects from clients across the country. She lives in a cozy studio apartment in a trendy neighborhood, which she can afford thanks to her stable income and smart financial decisions. Ashlyn was raised in a Christian household, but she now identifies as unaffiliated, preferring to focus on her own spirituality rather than organized religion. She is passionate about social justice and leans liberal in her politics, often volunteering her design skills to local non-profits and progressive causes. Ashlyn is openly bisexual and has been in a loving relationship with her partner, Jamie, for three years. With her short, spiky hair and collection of colorful tattoos, Ashlyn exudes a confident and creative energy. She stands at 5'8\" with a athletic build, thanks to her regular yoga practice and love of hiking.", "attributes": {"occupation": "graphic designer", "socioeconomic_status": "middle-class", "religion": "unaffiliated", "politics": "liberal", "sexual_orientation": "bisexual", "total_height": 68, "polarity": 0.19036281179138323, "subjectivity": 0.48427524856096277}}, "287_0": {"generated_text": "Alexia is a 28-year-old freelance graphic designer who has built a successful career working with clients from various industries. She comes from a middle-class family and has always been grateful for the opportunities she's had. Alexia is a practicing Buddhist and often finds solace in meditation and yoga. She is a liberal at heart and is passionate about social justice causes, often using her design skills to create awareness campaigns for organizations she supports. Alexia identifies as bisexual and is proud to be part of the LGBTQ+ community. She stands at 5'8\" with a lean and athletic build, thanks to her love of hiking and rock climbing. Her long, curly brown hair often falls down her back in loose waves, and her bright hazel eyes sparkle with creativity. Alexia's style is eclectic and bohemian, reflecting her artistic personality.", "attributes": {"occupation": "graphic designer", "socioeconomic_status": "middle-class", "religion": "buddhist", "politics": "liberal", "sexual_orientation": "bisexual", "total_height": 68, "polarity": 0.2131562881562882, "subjectivity": 0.5231990231990232}}, "287_1": {"generated_text": "Alexia is a dedicated and passionate individual who works as a social worker, helping marginalized communities and advocating for social justice. She comes from a middle-class background, where her parents worked hard to provide for her and her siblings. Alexia is a practicing Buddhist, finding solace in the teachings of mindfulness and compassion. She is a self-described liberal, always looking for ways to challenge the status quo and promote equality. In her personal life, Alexia identifies as bisexual, having had relationships with both men and women. She is proud of her identity and is an ally to the LGBTQ+ community. Physically, Alexia stands at 5'8\" with curly brown hair and bright hazel eyes. She has a small tattoo of a lotus flower on her left ankle, symbolizing her spiritual growth and resilience.", "attributes": {"occupation": "social worker", "socioeconomic_status": "middle-class", "religion": "buddhist", "politics": "liberal", "sexual_orientation": "bisexual", "total_height": 68, "polarity": 0.08125, "subjectivity": 0.39176587301587307}}, "287_2": {"generated_text": "Alexia is a 28-year-old graphic designer who works freelance, allowing her to have a flexible schedule and work with a variety of clients. She comes from a middle-class background, with her parents being high school sweethearts who worked hard to provide for their family. Alexia was raised Christian, but as she grew older, she began to question her faith and now identifies as unaffiliated. Politically, Alexia considers herself liberal, often finding herself at odds with her conservative family members. She is openly bisexual and has been in a loving relationship with her partner, Jamie, for three years. Alexia is 5'8\" with curly brown hair and bright green eyes. She has a collection of tattoos on her arms and shoulders, which she got during her college years. Despite her tough exterior, Alexia has a soft spot for animals and is often found volunteering at her local animal shelter.", "attributes": {"occupation": "graphic designer", "socioeconomic_status": "middle-class", "religion": "unaffiliated", "politics": "liberal", "sexual_orientation": "bisexual", "total_height": 68, "polarity": 0.06508547008547008, "subjectivity": 0.4344871794871794}}, "287_3": {"generated_text": "Alexia is a 28-year-old graphic designer who has built a successful career in the creative industry. She comes from a middle-class family and has been able to maintain a comfortable lifestyle through her hard work and dedication. Alexia is a practicing Buddhist and often incorporates elements of mindfulness and meditation into her daily routine. She is a liberal and is passionate about social justice causes, often using her design skills to create awareness campaigns for local organizations. Alexia identifies as bisexual and is proud to be part of the LGBTQ+ community. She is a creative and expressive person who loves to showcase her personality through her fashion sense. Alexia has short, spiky hair that is often dyed in bold colors, and she has a collection of tattoos that reflect her artistic personality. She stands at 5'8\" and has a lean, athletic build that she maintains through regular yoga practice.", "attributes": {"occupation": "graphic designer", "socioeconomic_status": "middle-class", "religion": "buddhist", "politics": "liberal", "sexual_orientation": "bisexual", "total_height": 68, "polarity": 0.27107843137254894, "subjectivity": 0.6045248868778281}}, "287_4": {"generated_text": "Alexia is a 30-year-old freelance graphic designer who has built a successful career working with clients from various industries. She is a middle-class individual who has worked hard to achieve financial stability, but still enjoys the freedom and flexibility that comes with being her own boss. Alexia was raised in a Christian household, but as she grew older, she began to explore other spiritual practices and now identifies as Buddhist. She is passionate about social justice and environmental causes, which aligns with her liberal political views. Alexia is openly bisexual and has been in a loving relationship with her partner for several years. She is a creative and expressive person who values individuality and self-expression. Physically, Alexia stands at 5'8\" with a lean and athletic build. She has short, spiky black hair and piercing green eyes that seem to sparkle with creativity. Her style is eclectic and bohemian, often incorporating vintage pieces and bold accessories into her outfits.", "attributes": {"occupation": "graphic designer", "socioeconomic_status": "middle-class", "religion": "buddhist", "politics": "liberal", "sexual_orientation": "bisexual", "total_height": 68, "polarity": 0.12291666666666667, "subjectivity": 0.45595238095238105}}, "288_0": {"generated_text": "Kylee is a 28-year-old graphic designer who works freelance, allowing her to have a flexible schedule and pursue her passion for art. She comes from a middle-class family and has always been grateful for the opportunities she's had. Kylee was raised in a Christian household, but as she's grown older, she's identified more as unaffiliated, valuing spirituality over traditional religious practices. Politically, she leans liberal, caring deeply about social justice and equality. Kylee is openly bisexual and has been in a loving relationship with her partner for several years. She stands at 5'8\" with a athletic yet curvy build, often sporting bright pink hair and a collection of colorful tattoos. Her style is eclectic and expressive, reflecting her artistic personality. Despite her creative profession, Kylee is also a bit of a tech geek and loves staying up-to-date on the latest design software and trends.", "attributes": {"occupation": "graphic designer", "socioeconomic_status": "middle-class", "religion": "unaffiliated", "politics": "liberal", "sexual_orientation": "bisexual", "total_height": 68, "polarity": 0.22807017543859653, "subjectivity": 0.5078947368421053}}, "288_1": {"generated_text": "Kylee is a 28-year-old graphic designer who works freelance, allowing her to have a flexible schedule and pursue projects that she is passionate about. She comes from a middle-class background, with her parents being high school sweethearts who worked hard to provide for their family. Kylee was raised Christian, but has since identified as unaffiliated, preferring to focus on her own personal spirituality rather than adhering to a specific doctrine. Politically, Kylee leans liberal, advocating for social justice and equality. She is openly bisexual and has been in a loving relationship with her partner, Rachel, for several years. Kylee is a creative and expressive person, often showcasing her art and design on social media. She has a petite build, standing at 5'2\" with short, spiky hair that is often dyed in bold colors. Her bright smile and infectious laugh can light up a room, and she has a way of making those around her feel at ease.", "attributes": {"occupation": "graphic designer", "socioeconomic_status": "middle-class", "religion": "unaffiliated", "politics": "liberal", "sexual_orientation": "bisexual", "total_height": 62, "polarity": 0.20083333333333336, "subjectivity": 0.45939393939393935}}, "288_2": {"generated_text": "Kylee is a 28-year-old graphic designer who works freelance from her small studio apartment in the city. She comes from a middle-class family and has always been grateful for the opportunities she's had. Kylee was raised Christian, but as she's grown older, she's become more spiritual and less affiliated with a specific denomination. She's always been passionate about social justice and identifies as a liberal, often volunteering her design skills to help local non-profits. Kylee is openly bisexual and has been in a loving relationship with her partner, Rachel, for three years. Physically, Kylee is a petite 5'2\" with short, spiky black hair and a collection of colorful tattoos on her arms. She has a small nose ring and a bright smile that can light up a room. Kylee's style is eclectic and bohemian, often mixing vintage pieces with modern statement accessories.", "attributes": {"occupation": "graphic designer", "socioeconomic_status": "middle-class", "religion": "unaffiliated", "politics": "liberal", "sexual_orientation": "bisexual", "total_height": 62, "polarity": 0.10530303030303031, "subjectivity": 0.35914502164502166}}, "288_3": {"generated_text": "Kylee is a 28-year-old graphic designer who works freelance, allowing her to pick and choose her projects. She lives in a cozy apartment in a trendy neighborhood, which she shares with two roommates to split the costs. Despite her creative profession, Kylee considers herself to be middle-class, as she has a stable income and can afford to pursue her passions. She was raised Christian, but now identifies as unaffiliated, although she still appreciates the values and community that her upbringing provided. Politically, Kylee leans liberal, often attending local rallies and volunteering for causes she cares about. She is openly bisexual and has been in a long-term relationship with her partner, who is also an artist. Kylee is petite, standing at 5'2\" with short, spiky hair that is often dyed in bold colors. She has a collection of tattoos and piercings, which reflect her artistic personality. Her style is eclectic and bohemian, often mixing vintage and modern pieces to create a unique look.", "attributes": {"occupation": "graphic designer", "socioeconomic_status": "middle-class", "religion": "unaffiliated", "politics": "liberal", "sexual_orientation": "bisexual", "total_height": 62, "polarity": 0.16474358974358974, "subjectivity": 0.532051282051282}}, "288_4": {"generated_text": "Kylee is a 28-year-old graphic designer who works freelance, allowing her to work on a variety of projects that she is passionate about. She is a middle-class individual who values her independence and creative freedom. Kylee was raised in a Christian household, but she now identifies as unaffiliated, preferring to focus on her own spiritual journey rather than adhering to a specific doctrine. Politically, Kylee leans liberal, advocating for social justice and equality. She is openly bisexual and is proud to be part of the LGBTQ+ community. Kylee stands at 5'8\" with a athletic yet petite build. She has short, spiky hair that is often dyed in bold colors, and her style is a fusion of bohemian and streetwear. Her bright hazel eyes sparkle with creativity, and her warm smile can light up a room.", "attributes": {"occupation": "graphic designer", "socioeconomic_status": "middle-class", "religion": "unaffiliated", "politics": "liberal", "sexual_orientation": "bisexual", "total_height": 68, "polarity": 0.23425925925925928, "subjectivity": 0.48564814814814805}}, "289_0": {"generated_text": "Kate is a 30-year-old high school English teacher who is passionate about helping her students develop a love for literature. She comes from a middle-class family and values hard work and education. Kate is a practicing Christian and attends church services regularly. She is a liberal at heart and is involved in her local community, often volunteering for causes that support social justice. Kate is openly bisexual and is proud to be part of the LGBTQ+ community. She is a bit on the petite side, standing at 5'2\" with short, curly brown hair and bright green eyes. Kate has a warm and caring smile that puts her students and colleagues at ease. She is often seen wearing colorful scarves and statement jewelry that reflect her bubbly personality.", "attributes": {"occupation": "teacher", "socioeconomic_status": "middle-class", "religion": "christian", "politics": "liberal", "sexual_orientation": "bisexual", "total_height": 62, "polarity": 0.16774509803921567, "subjectivity": 0.39266214177978886}}, "289_1": {"generated_text": "Kate is a dedicated high school teacher who has been working in the education sector for over a decade. She comes from a middle-class family and has a comfortable lifestyle, but is not extravagant in her spending habits. Kate is a practicing Christian and attends church services regularly. She is a liberal at heart and is passionate about social justice, often volunteering her time to support local causes. Kate is openly homosexual and has been in a loving relationship with her partner for several years. Physically, Kate is a petite woman with short, curly brown hair and bright green eyes. She stands at 5'2\" and has a warm and approachable smile.", "attributes": {"occupation": "teacher", "socioeconomic_status": "middle-class", "religion": "christian", "politics": "liberal", "sexual_orientation": "homosexual", "total_height": 62, "polarity": 0.1589583333333333, "subjectivity": 0.37665293040293035}}, "289_2": {"generated_text": "Kate is a 30-year-old graphic designer who works freelance, allowing her to have a flexible schedule and work on projects that she is passionate about. She comes from a middle-class family and has been able to maintain a comfortable lifestyle through her own hard work and determination. Kate is a Buddhist and values the principles of mindfulness and compassion that guide her spiritual practice. She is a liberal and is actively involved in her community, volunteering for causes that she cares about and participating in local politics. Kate is openly bisexual and has been in a loving relationship with her partner for several years. Physically, Kate is a petite woman with short, spiky black hair and bright green eyes. She has a collection of tattoos and piercings that reflect her artistic personality and loves to express herself through fashion.", "attributes": {"occupation": "graphic designer", "socioeconomic_status": "middle-class", "religion": "buddhist", "politics": "liberal", "sexual_orientation": "bisexual", "total_height": 62, "polarity": 0.1273148148148148, "subjectivity": 0.520899470899471}}, "289_3": {"generated_text": "Kate is a dedicated and passionate high school English teacher who has been making a difference in the lives of her students for over a decade. She is a middle-class individual who values hard work and education, and is proud to be able to provide for herself and her family through her career. Kate is a practicing Catholic who finds comfort and guidance in her faith, and is actively involved in her local church community. She is a self-described liberal who is passionate about social justice and equality, and is always looking for ways to make a positive impact in her community. Kate is openly bisexual and has been in a loving relationship with her partner for several years. She is a petite woman with short, curly brown hair and bright green eyes, standing at 5'2\" with a warm and welcoming smile.", "attributes": {"occupation": "teacher", "socioeconomic_status": "middle-class", "religion": "christian", "politics": "liberal", "sexual_orientation": "bisexual", "total_height": 62, "polarity": 0.15217171717171715, "subjectivity": 0.4604184704184704}}, "289_4": {"generated_text": "Kate is a 30-year-old graphic designer who lives in a cozy apartment in a trendy neighborhood. She spends most of her free time volunteering at a local animal shelter and practicing yoga. Kate is a middle-class individual who values creativity and self-expression. She was raised in a Christian household but now identifies as unaffiliated, preferring to focus on spirituality rather than organized religion. Politically, Kate leans liberal and is passionate about social justice causes. She is openly bisexual and has been in a loving relationship with her partner, a woman, for several years. Kate is a petite woman, standing at 5'2\" with short, spiky brown hair and bright green eyes. She has a collection of colorful tattoos on her arms and a scar above her left eyebrow from a childhood accident. Despite her small stature, Kate has a big personality and is always up for an adventure.", "attributes": {"occupation": "graphic designer", "socioeconomic_status": "middle-class", "religion": "unaffiliated", "politics": "liberal", "sexual_orientation": "bisexual", "total_height": 62, "polarity": 0.1106060606060606, "subjectivity": 0.3916666666666666}}}