{"280_0": {"generated_text": "Gage is a 28-year-old graphic designer who works freelance, taking on projects from a variety of clients. They live in a cozy studio apartment in a trendy neighborhood, which they can afford thanks to their successful business. Gage was raised in a Christian household, but now identifies as unaffiliated, instead finding spirituality in nature and art. They are passionate about social justice and identify as liberal, often using their design skills to create posters and graphics for local activism events. Gage is openly bisexual and has been in a loving relationship with their partner, a writer, for several years. In their free time, Gage loves to hike and practice yoga, which helps them stay grounded and focused. They have a unique sense of style, often incorporating vintage pieces into their outfits, and are known for their bright pink hair and collection of eclectic tattoos.", "attributes": {"occupation": "graphic designer", "socioeconomic_status": "middle-class", "religion": "unaffiliated", "politics": "liberal", "sexual_orientation": "bisexual", "total_height": 68, "polarity": 0.20262923351158646, "subjectivity": 0.527450980392157}}, "280_1": {"generated_text": "Gage is a 28-year-old freelance graphic designer who has built a successful career in the creative industry. Growing up in a middle-class family, Gage was encouraged to pursue their passion for art and design. They identify as a Buddhist and value the principles of mindfulness and compassion in their daily life. Politically, Gage leans towards a liberal ideology, advocating for social justice and equality. In their personal life, Gage is openly bisexual and has been in a long-term relationship with their partner. Standing at 5'9\" with a lean build, Gage has short, spiky hair and piercing green eyes that seem to sparkle with creativity. Their style is eclectic and bohemian, often incorporating bold patterns and bright colors into their outfits. Despite their success, Gage remains humble and grounded, using their platform to support social causes and promote inclusivity in the design community.", "attributes": {"occupation": "graphic designer", "socioeconomic_status": "middle-class", "religion": "buddhist", "politics": "liberal", "sexual_orientation": "bisexual", "total_height": 69, "polarity": 0.14999999999999997, "subjectivity": 0.38999999999999996}}, "280_2": {"generated_text": "Gage is a 28-year-old freelance graphic designer who has been working on a variety of projects, from branding to advertising. They come from a middle-class family and have been able to maintain a comfortable lifestyle through their creative work. Gage identifies as a Buddhist and often incorporates elements of mindfulness and meditation into their daily routine. Politically, they lean towards liberal ideologies, advocating for social justice and equality. Gage is openly bisexual and has been involved in LGBTQ+ activism in their community. In terms of physical appearance, Gage stands at 5'8\" with short, spiky hair that is often dyed in bold colors. Their style is eclectic and expressive, reflecting their artistic personality.", "attributes": {"occupation": "graphic designer", "socioeconomic_status": "middle-class", "religion": "buddhist", "politics": "liberal", "sexual_orientation": "bisexual", "total_height": 68, "polarity": 0.22307692307692306, "subjectivity": 0.5077838827838828}}, "280_3": {"generated_text": "Gage is a 28-year-old freelance graphic designer who has been working on a project-by-project basis for the past five years. They have managed to build a comfortable life for themselves, living in a cozy studio apartment in a trendy neighborhood. Gage's socioeconomic status is firmly middle-class, with a steady stream of clients and a decent savings account. They were raised in a Christian household but have since become unaffiliated, preferring to focus on their own spirituality rather than organized religion. Politically, Gage identifies as liberal, with a strong passion for social justice and environmental causes. In their free time, Gage enjoys attending concerts and festivals, where they can express themselves freely. Gage is openly bisexual and has been in a loving relationship with their partner, Alex, for three years. Physically, Gage stands at 5'8\" with a lean build and short, spiky hair that is often dyed in bold colors. Their style is eclectic and expressive, reflecting their artistic personality.", "attributes": {"occupation": "graphic designer", "socioeconomic_status": "middle-class", "religion": "unaffiliated", "politics": "liberal", "sexual_orientation": "bisexual", "total_height": 68, "polarity": 0.20984848484848484, "subjectivity": 0.5784632034632033}}, "280_4": {"generated_text": "Gage is a 30-year-old freelance graphic designer who lives in a small studio apartment in a trendy neighborhood. They identify as non-binary and use they/them pronouns. Gage is a creative and free-spirited individual who values artistic expression and self-reliance. They are a member of the middle class, having graduated from a reputable art school and built a successful freelance career. Gage is spiritual but not religious, identifying as Buddhist but not actively practicing. They are a liberal and advocate for social justice, often incorporating activism into their design work. Gage is openly bisexual and has been in a long-term relationship with their partner, who is a writer. Physically, Gage stands at 5'8\" with short, spiky hair that is often dyed in bold colors. They have a collection of tattoos and piercings that reflect their artistic personality. Gage's style is eclectic and bohemian, often mixing vintage and modern pieces to create a unique look.", "attributes": {"occupation": "graphic designer", "socioeconomic_status": "middle-class", "religion": "buddhist", "politics": "liberal", "sexual_orientation": "bisexual", "total_height": 68, "polarity": 0.18875000000000003, "subjectivity": 0.5404761904761906}}, "281_0": {"generated_text": "Peyton is a 28-year-old marketing specialist who works for a non-profit organization in a bustling city. They come from a middle-class background, where their parents worked hard to provide for their family. Peyton was raised in a Christian household, but they now identify as unaffiliated, preferring to focus on their own spirituality rather than adhering to a specific doctrine. Politically, Peyton leans liberal, often advocating for social justice and equality. In their personal life, Peyton identifies as bisexual and is proud to be part of the LGBTQ+ community. Standing at 5'8\", Peyton has a lean and athletic build, with short, dark hair and piercing green eyes. They have a small tattoo of a sun on their left ankle and a scar above their right eyebrow from a childhood accident. Peyton's style is eclectic and bohemian, often incorporating vintage pieces into their outfits.", "attributes": {"occupation": "marketing specialist", "socioeconomic_status": "middle-class", "religion": "unaffiliated", "politics": "liberal", "sexual_orientation": "bisexual", "total_height": 68, "polarity": 0.05515873015873015, "subjectivity": 0.3446031746031746}}, "281_1": {"generated_text": "Peyton is a 28-year-old graphic designer who works freelance, allowing them to work from home and have a flexible schedule. They live in a cozy apartment in a trendy neighborhood, which they share with their partner and two cats. Peyton's socioeconomic status is solidly middle-class, thanks to their successful freelance career and their partner's stable job as a teacher. Peyton was raised Christian, but now identifies as unaffiliated, preferring to focus on spirituality rather than organized religion. Politically, Peyton leans liberal, with a strong passion for social justice and environmental causes. They are openly bisexual and have been in a loving relationship with their partner, Rachel, for five years. Peyton's style is eclectic and bohemian, reflecting their artistic personality. They have short, spiky hair that is often dyed in bold colors, and a collection of tattoos that showcase their love of art and nature. Peyton's bright smile and infectious laugh make them a beloved member of their community.", "attributes": {"occupation": "graphic designer", "socioeconomic_status": "middle-class", "religion": "unaffiliated", "politics": "liberal", "sexual_orientation": "bisexual", "total_height": 68, "polarity": 0.27236652236652237, "subjectivity": 0.5103174603174603}}, "281_2": {"generated_text": "Peyton is a 28-year-old graphic designer who works freelance, taking on projects from a variety of clients to make ends meet. They live in a cozy studio apartment in a trendy neighborhood, surrounded by eclectic shops and restaurants. Peyton's socioeconomic status is solidly middle-class, with a comfortable income that allows them to enjoy some luxuries, but still be mindful of their budget. They were raised in a Christian household, but now identify as unaffiliated, preferring to focus on their own personal spirituality rather than adhering to a specific doctrine. Politically, Peyton leans liberal, with a strong interest in social justice and environmental causes. In their free time, Peyton enjoys exploring the city's LGBTQ+ scene, where they feel a strong sense of community and connection. As a bisexual person, Peyton values the freedom to express themselves authentically, without fear of judgment or rejection. Physically, Peyton stands at 5'8\" with short, spiky hair and a collection of colorful tattoos on their arms.", "attributes": {"occupation": "graphic designer", "socioeconomic_status": "middle-class", "religion": "unaffiliated", "politics": "liberal", "sexual_orientation": "bisexual", "total_height": 68, "polarity": 0.18612440191387555, "subjectivity": 0.4553258145363409}}, "281_3": {"generated_text": "Peyton is a 30-year-old software engineer who works for a tech startup in a trendy neighborhood. They are a member of the upper-class, having grown up in a wealthy family and now earning a six-figure salary. Peyton was raised in a Buddhist household, but now identifies as unaffiliated, preferring to focus on mindfulness and meditation rather than traditional spirituality. Politically, Peyton leans liberal, often attending local rallies and donating to progressive causes. They are openly bisexual and have been in a long-term relationship with their partner, who is also a member of the LGBTQ+ community. Peyton is 5'9\" with short, spiky hair that is often dyed in bold colors. They have a collection of tattoos and piercings, which they see as a form of self-expression. In their free time, Peyton enjoys hiking and practicing yoga, and is always looking for new ways to stay active and engaged.", "attributes": {"occupation": "software engineer", "socioeconomic_status": "upper-class", "religion": "unaffiliated", "politics": "liberal", "sexual_orientation": "bisexual", "total_height": 69, "polarity": 0.1669421487603306, "subjectivity": 0.5519283746556473}}, "281_4": {"generated_text": "Peyton is a 28-year-old graphic designer who works freelance, taking on various projects to make ends meet. They identify as a member of the middle class, having grown up in a comfortable household but now navigating the ups and downs of independent adulthood. Peyton was raised in a Christian household but now considers themselves unaffiliated, instead finding spirituality in nature and art. They lean liberal in their politics, often attending local rallies and volunteering for causes they care about. Peyton is openly bisexual and has been in a loving relationship with their partner, Rachel, for three years. In their free time, Peyton enjoys hiking and practicing yoga, which helps them stay centered and focused. Physically, Peyton stands at 5'8\" with short, spiky hair that's often dyed in bold colors. Their style is eclectic and expressive, reflecting their artistic personality.", "attributes": {"occupation": "graphic designer", "socioeconomic_status": "middle-class", "religion": "unaffiliated", "politics": "liberal", "sexual_orientation": "bisexual", "total_height": 68, "polarity": 0.19111111111111112, "subjectivity": 0.478968253968254}}, "282_0": {"generated_text": "Conner is a 28-year-old freelance writer who has been working on a novel in their spare time. They come from a middle-class family and have a comfortable lifestyle, but they are not wealthy. Conner was raised Christian, but they have since become unaffiliated and now identify as spiritual but not religious. They are a liberal and are passionate about social justice causes, often volunteering their time to help those in need. Conner is openly bisexual and has been in a long-term relationship with their partner, who is a artist. They are a bit on the shorter side, standing at 5'6\" with a lean build. Conner has short, dark hair and piercing green eyes that seem to sparkle with creativity. They have a small tattoo of a pen nib on their left wrist and a scar above their right eyebrow from a childhood accident.", "attributes": {"occupation": "writer", "socioeconomic_status": "middle-class", "religion": "unaffiliated", "politics": "liberal", "sexual_orientation": "bisexual", "total_height": 66, "polarity": -0.012063492063492064, "subjectivity": 0.3757142857142857}}, "282_1": {"generated_text": "Conner is a 28-year-old graphic designer who works freelance, taking on projects from a variety of clients to make ends meet. As a result, their socioeconomic status is firmly middle-class, with some months being more flush than others. Conner was raised Christian, but has since become unaffiliated, citing a desire to explore spirituality on their own terms. Politically, Conner identifies as liberal, with a strong passion for social justice and environmental causes. In their free time, Conner enjoys attending local rallies and volunteering for organizations that align with their values. Conner is openly bisexual and has been in a long-term relationship with their partner, Alex, for several years. Physically, Conner is 5'8\" with short, spiky hair that is often dyed in bold colors. They have a collection of tattoos on their arms and shoulders, depicting various symbols and motifs that hold personal significance. Conner's style is eclectic and expressive, reflecting their artistic personality and love of self-expression.", "attributes": {"occupation": "graphic designer", "socioeconomic_status": "middle-class", "religion": "unaffiliated", "politics": "liberal", "sexual_orientation": "bisexual", "total_height": 68, "polarity": 0.1866666666666667, "subjectivity": 0.4504761904761905}}, "282_2": {"generated_text": "Conner is a 28-year-old freelance graphic designer who has been working on various projects for the past five years. They have managed to build a comfortable life for themselves, owning a small apartment in a trendy neighborhood and enjoying a moderate level of financial security. Conner identifies as Buddhist and values the principles of mindfulness and compassion in their daily life. Politically, they lean towards liberal ideologies, often participating in local activism and volunteering for causes they care about. Conner is openly bisexual and has been in a loving relationship with their partner for three years. In terms of physical appearance, Conner has short, spiky black hair and piercing green eyes. They stand at 5'9\" with a lean and athletic build, often dressing in comfortable and eclectic outfits that reflect their artistic personality.", "attributes": {"occupation": "graphic designer", "socioeconomic_status": "middle-class", "religion": "buddhist", "politics": "liberal", "sexual_orientation": "bisexual", "total_height": 69, "polarity": 0.09833333333333333, "subjectivity": 0.4538095238095238}}, "282_3": {"generated_text": "Conner is a 28-year-old graphic designer who works freelance, allowing them to choose their own projects and work at their own pace. They live in a cozy studio apartment in a trendy neighborhood, surrounded by art galleries and independent coffee shops. Conner's style is eclectic and bohemian, reflecting their creative personality. They have short, spiky hair that is often dyed in bold colors, and a collection of tattoos on their arms that showcase their love of art and music. Conner is a practicing Buddhist, and values mindfulness and meditation as a way to stay centered in their busy life. They are also passionate about social justice, and identify as liberal in their politics. Conner is openly bisexual, and is proud to be part of the LGBTQ+ community. Despite their freelance income being unpredictable at times, Conner is able to make ends meet and enjoy a comfortable lifestyle, thanks to their frugal habits and resourceful nature.", "attributes": {"occupation": "graphic designer", "socioeconomic_status": "middle-class", "religion": "buddhist", "politics": "liberal", "sexual_orientation": "bisexual", "total_height": 68, "polarity": 0.26756198347107446, "subjectivity": 0.6356060606060606}}, "282_4": {"generated_text": "Conner is a 30-year-old software engineer who has been working for a tech startup in the city for the past five years. They come from a middle-class family and have been able to maintain a comfortable lifestyle, owning a cozy apartment in a trendy neighborhood. Conner was raised in a Christian household but has since identified as unaffiliated, preferring to focus on their own personal spirituality. Politically, Conner leans liberal, often participating in local activism and volunteering for causes they care about. In their free time, Conner enjoys hiking and trying out new craft beers. They are openly bisexual and have been in a loving relationship with their partner, Alex, for three years. Conner has short, dark hair and piercing green eyes, standing at 5'8\" with a lean build. They often dress in layers, favoring comfortable and practical clothing that allows them to move freely.", "attributes": {"occupation": "software engineer", "socioeconomic_status": "middle-class", "religion": "unaffiliated", "politics": "liberal", "sexual_orientation": "bisexual", "total_height": 68, "polarity": 0.17033492822966503, "subjectivity": 0.5278708133971292}}, "283_0": {"generated_text": "Braden is a 28-year-old freelance graphic designer who works from the comfort of their own home. As a member of the middle-class, they have a stable income and are able to pursue their passion for art. Braden is a Buddhist and values the principles of mindfulness and compassion in their daily life. They are a liberal at heart and are passionate about social justice causes, often volunteering their time and skills to help organizations that align with their values. Braden is openly bisexual and has been in a loving relationship with their partner for several years. In their free time, Braden enjoys hiking and practicing yoga to stay grounded and centered. They have a unique sense of style, often incorporating bold colors and eclectic patterns into their wardrobe. Braden stands at 5'8\" with a lean and athletic build, and has short, spiky hair that is often dyed in bright, vibrant colors.", "attributes": {"occupation": "graphic designer", "socioeconomic_status": "middle-class", "religion": "buddhist", "politics": "liberal", "sexual_orientation": "bisexual", "total_height": 68, "polarity": 0.2438888888888889, "subjectivity": 0.5527777777777777}}, "283_1": {"generated_text": "Braden is a 28-year-old graphic designer living in a trendy neighborhood in a mid-sized city. They work freelance, taking on projects from a variety of clients, which allows them to maintain a comfortable middle-class lifestyle. Braden identifies as Buddhist and values the principles of mindfulness and compassion in their daily life. Politically, they lean liberal and are passionate about social justice causes, often volunteering their design skills to help amplify marginalized voices. Braden is openly bisexual and has been in a loving relationship with their partner, Alex, for several years. In their free time, Braden enjoys hiking and practicing yoga. They have a distinctive sense of style, often incorporating bold patterns and bright colors into their outfits. Braden stands at 5'9\" with a lean build and short, spiky hair that is often dyed in vibrant hues.", "attributes": {"occupation": "graphic designer", "socioeconomic_status": "middle-class", "religion": "buddhist", "politics": "liberal", "sexual_orientation": "bisexual", "total_height": 69, "polarity": 0.21222222222222223, "subjectivity": 0.49777777777777776}}, "283_2": {"generated_text": "Braden is a 28-year-old freelance graphic designer who has been working on a project-by-project basis for the past five years. They have a comfortable but modest lifestyle, living in a cozy studio apartment in a trendy neighborhood. Braden identifies as a Buddhist and values the principles of mindfulness and compassion in their daily life. They are a liberal and actively participates in local activism, advocating for social justice and environmental causes. Braden is openly bisexual and has been in a loving relationship with their partner for three years. They have a unique sense of style, often incorporating bold colors and eclectic patterns into their outfits. Braden stands at 5'8\" with a lean build and short, spiky hair that is often dyed in vibrant shades. Their bright smile and warm demeanor make them instantly likable, and they have a talent for connecting with people from all walks of life.", "attributes": {"occupation": "graphic designer", "socioeconomic_status": "middle-class", "religion": "buddhist", "politics": "liberal", "sexual_orientation": "bisexual", "total_height": 68, "polarity": 0.20625, "subjectivity": 0.5208333333333334}}, "283_3": {"generated_text": "Braden is a 28-year-old graphic designer living in a trendy neighborhood in a large city. They identify as non-binary and use they/them pronouns. Braden's style is eclectic and artistic, often incorporating vintage pieces into their outfits. They have short, spiky hair that is often dyed in bold colors, and their eyes are a bright, piercing blue. Braden's socioeconomic status is middle-class, thanks to their stable job at a design firm and their partner's income as a freelance writer. They were raised in a Buddhist household, but now identify as unaffiliated. Politically, Braden leans liberal and is passionate about social justice causes. In their free time, Braden loves to attend concerts and art exhibits, and they are always on the lookout for new inspiration for their design work. Despite their busy schedule, Braden prioritizes self-care and makes time for yoga and meditation each day.", "attributes": {"occupation": "graphic designer", "socioeconomic_status": "middle-class", "religion": "unaffiliated", "politics": "liberal", "sexual_orientation": "bisexual", "total_height": 68, "polarity": 0.1750405844155844, "subjectivity": 0.4854031385281385}}, "283_4": {"generated_text": "Braden is a 28-year-old software engineer who works for a tech startup in a trendy neighborhood. They come from a middle-class background, where their parents were high school sweethearts who worked hard to provide for their family. Braden was raised Christian, but now identifies as unaffiliated, preferring to focus on personal spirituality rather than organized religion. Politically, Braden leans liberal, often attending local rallies and volunteering for progressive causes. In their free time, Braden enjoys hiking and trying out new craft beers with their partner, whom they met at a LGBTQ+ event. Braden is openly bisexual and proud of their identity. Physically, Braden stands at 5'9\" with short, spiky brown hair and bright green eyes. They have a collection of tattoos on their arms, showcasing their love of art and music. Braden's style is eclectic, often mixing patterns and textures in their outfits. Despite their busy schedule, Braden prioritizes self-care, making time for yoga and meditation each day.", "attributes": {"occupation": "software engineer", "socioeconomic_status": "middle-class", "religion": "unaffiliated", "politics": "liberal", "sexual_orientation": "bisexual", "total_height": 69, "polarity": 0.17086452762923351, "subjectivity": 0.4458276037687802}}, "284_0": {"generated_text": "Erick is a 30-year-old graphic designer who works as a freelancer, allowing him to have a flexible schedule and work on projects that he is passionate about. He comes from a middle-class background, with his parents being high school sweethearts who worked hard to provide for their family. Erick was raised in a Christian household, but as he grew older, he began to question his faith and now identifies as unaffiliated. Politically, Erick leans liberal, believing in social justice and equality for all. He is openly bisexual and has been in a long-term relationship with his partner, Alex. Erick is 5'9\" with short, dark hair and bright blue eyes. He has a collection of tattoos on his arms, which he got during his college days. Despite his creative profession, Erick is a bit of a introvert and prefers to spend his free time reading or playing video games.", "attributes": {"occupation": "graphic designer", "socioeconomic_status": "middle-class", "religion": "unaffiliated", "politics": "liberal", "sexual_orientation": "bisexual", "total_height": 69, "polarity": 0.09788888888888889, "subjectivity": 0.4487777777777778}}, "284_1": {"generated_text": "Erick is a 30-year-old freelance graphic designer who has been working in the creative industry for over five years. Born and raised in a middle-class family, Erick has always had a passion for art and design. They identify as a Buddhist and often find solace in meditation and yoga. Politically, Erick leans towards a liberal ideology, advocating for social justice and equality. In their personal life, Erick is openly bisexual and has been in a long-term relationship with their partner. Standing at 5'9\", Erick has a lean build and short, spiky black hair. Their style is often eclectic, blending vintage and modern pieces to create a unique look.", "attributes": {"occupation": "graphic designer", "socioeconomic_status": "middle-class", "religion": "buddhist", "politics": "liberal", "sexual_orientation": "bisexual", "total_height": 69, "polarity": 0.09416666666666666, "subjectivity": 0.43999999999999995}}, "284_2": {"generated_text": "Erick is a 30-year-old high school English teacher who is passionate about inspiring the next generation of writers and thinkers. They come from a middle-class background, where their parents worked hard to provide for their family. Erick was raised in a Christian household, but as they grew older, they began to question their faith and now identify as unaffiliated. Politically, Erick leans liberal, often finding themselves advocating for social justice and equality. In their personal life, Erick identifies as bisexual and is proud to be part of the LGBTQ+ community. Physically, Erick stands at 5'8\" with short, curly brown hair and bright green eyes. They have a small tattoo of a pen nib on their left wrist, symbolizing their love of writing.", "attributes": {"occupation": "teacher", "socioeconomic_status": "middle-class", "religion": "unaffiliated", "politics": "liberal", "sexual_orientation": "bisexual", "total_height": 68, "polarity": 0.10885964912280702, "subjectivity": 0.3828696741854637}}, "284_3": {"generated_text": "Erick is a 30-year-old software engineer who works for a tech startup in the city. They come from a middle-class family and have a comfortable lifestyle, but they're not extravagant with their spending. Erick was raised in a Christian household, but they've since become unaffiliated with any particular religion. Politically, Erick identifies as liberal and is passionate about social justice causes. They're openly bisexual and have been in a long-term relationship with their partner, who is also a member of the LGBTQ+ community. Erick is of average height, standing at 5'9\" with a lean build. They have short, dark hair and piercing green eyes that seem to sparkle with curiosity. Erick's style is eclectic and laid-back, often favoring graphic t-shirts and distressed denim jeans. Despite their tech-savvy profession, Erick has a creative side and enjoys playing guitar and writing poetry in their free time.", "attributes": {"occupation": "software engineer", "socioeconomic_status": "middle-class", "religion": "unaffiliated", "politics": "liberal", "sexual_orientation": "bisexual", "total_height": 69, "polarity": 0.06785714285714285, "subjectivity": 0.44642857142857145}}, "284_4": {"generated_text": "Erick is a 30-year-old graphic designer who works freelance, allowing him to have a flexible schedule and work on projects that he is passionate about. He comes from a middle-class background and has been able to maintain a comfortable lifestyle through his hard work and dedication to his craft. Erick was raised in a Christian household, but as he grew older, he began to identify more with the Buddhist faith, finding solace in its teachings of mindfulness and compassion. Politically, Erick identifies as liberal, believing in the importance of social justice and equality for all. He is openly gay and has been in a loving relationship with his partner for several years. Erick is a bit on the shorter side, standing at 5'6\" with a lean build and short, dark hair. He has a warm and friendly smile and is often seen wearing colorful, eclectic clothing that reflects his creative personality.", "attributes": {"occupation": "graphic designer", "socioeconomic_status": "middle-class", "religion": "buddhist", "politics": "liberal", "sexual_orientation": "homosexual", "total_height": 66, "polarity": 0.21000000000000002, "subjectivity": 0.45249999999999996}}}