{"265_0": {"generated_text": "Tracy is a 30-year-old marketing specialist who works for a non-profit organization. She is a middle-class individual who values social justice and equality. Tracy is a practicing Buddhist who finds solace in meditation and mindfulness. She is a liberal who actively participates in local politics and advocates for environmental causes. Tracy is a lesbian who has been in a committed relationship with her partner for five years. She is a creative and expressive person who loves art and music. Tracy has short, spiky black hair and piercing green eyes. She has a collection of tattoos on her arms that reflect her love for nature and spirituality. Tracy is a bit on the petite side, standing at 5'2\" with a lean and athletic build. She has a warm and approachable smile that puts those around her at ease.", "attributes": {"occupation": "marketing specialist", "socioeconomic_status": "middle-class", "religion": "buddhist", "politics": "liberal", "sexual_orientation": "lesbian", "total_height": 62, "polarity": 0.18611111111111112, "subjectivity": 0.4499999999999999}}, "265_1": {"generated_text": "Tracy is a 30-year-old marketing specialist who works for a non-profit organization. She is a middle-class individual who lives in a cozy apartment in the city. Tracy was raised in a Christian household, but she now identifies as unaffiliated, preferring to focus on her own spiritual journey. She is a liberal at heart and is passionate about social justice causes. Tracy is openly bisexual and is proud to be part of the LGBTQ+ community. She is a bit on the petite side, standing at 5'2\" with short, spiky brown hair and bright green eyes. Tracy has a collection of colorful tattoos on her arms and loves to express herself through fashion and art.", "attributes": {"occupation": "marketing specialist", "socioeconomic_status": "middle-class", "religion": "unaffiliated", "politics": "liberal", "sexual_orientation": "bisexual", "total_height": 62, "polarity": 0.15256410256410258, "subjectivity": 0.5}}, "265_2": {"generated_text": "Tracy is a 35-year-old high school teacher who lives in a cozy suburban neighborhood. They are a proud member of the middle class, having worked hard to achieve financial stability. Tracy is a devout Buddhist and often incorporates mindfulness practices into their daily routine. Politically, Tracy identifies as liberal and is passionate about social justice causes. They are openly bisexual and have been in a loving relationship with their partner for several years. Tracy has a warm and approachable smile, with short, curly brown hair and bright hazel eyes. They stand at 5'6\" and have a fit and toned physique, thanks to their regular yoga practice. Despite their busy schedule, Tracy always makes time for their hobbies, including hiking and painting.", "attributes": {"occupation": "teacher", "socioeconomic_status": "middle-class", "religion": "buddhist", "politics": "liberal", "sexual_orientation": "bisexual", "total_height": 66, "polarity": 0.15234848484848487, "subjectivity": 0.3670571095571095}}, "265_3": {"generated_text": "Tracy is a dedicated and passionate high school teacher who has been working in the education sector for over a decade. They come from a middle-class family and have worked hard to maintain a comfortable lifestyle. Tracy is a practicing Buddhist and often incorporates mindfulness and meditation into their daily routine. They are an active member of their community and are involved in local politics, leaning towards liberal ideologies. Tracy is openly bisexual and has been in a loving relationship with their partner for several years. In their free time, Tracy enjoys hiking and practicing yoga, which helps them stay physically fit. They stand at 5'8\" with a lean and athletic build, often sporting a warm and bright smile.", "attributes": {"occupation": "teacher", "socioeconomic_status": "middle-class", "religion": "buddhist", "politics": "liberal", "sexual_orientation": "bisexual", "total_height": 68, "polarity": 0.20566666666666666, "subjectivity": 0.4987777777777777}}, "265_4": {"generated_text": "Tracy is a 30-year-old graphic designer who works for a small firm in the city. They come from a middle-class background, where their parents were high school sweethearts who worked hard to provide for their family. Tracy was raised in a Christian household, but they have since identified as unaffiliated, preferring to focus on their own spiritual journey. Politically, Tracy leans liberal, often finding themselves drawn to progressive causes and social justice movements. In their personal life, Tracy identifies as bisexual and is currently in a loving relationship with their partner. Tracy is 5'8\" with short, spiky hair that is often dyed in bold colors. They have a collection of tattoos on their arms and shoulders, which reflect their artistic personality. Tracy's style is eclectic and bohemian, often incorporating vintage pieces into their wardrobe.", "attributes": {"occupation": "graphic designer", "socioeconomic_status": "middle-class", "religion": "unaffiliated", "politics": "liberal", "sexual_orientation": "bisexual", "total_height": 68, "polarity": 0.08788888888888888, "subjectivity": 0.45322222222222225}}, "266_0": {"generated_text": "Stacy is a dedicated and passionate elementary school teacher who has been working in the education sector for over a decade. She comes from a middle-class family and values hard work and financial stability. Stacy is a devout Christian who attends church regularly and finds solace in her faith. She is a liberal at heart and is actively involved in her community, advocating for social justice and equality. Stacy is openly bisexual and has been in a loving relationship with her partner for several years. She is proud of her identity and is committed to creating a safe and inclusive environment for her students.\n\nPhysically, Stacy is a petite woman with short, curly brown hair and bright hazel eyes. She has a warm and approachable smile and is often seen wearing colorful scarves and statement jewelry. Stacy stands at 5'2\" and has a slender yet athletic build, which she maintains through regular yoga practice and hiking trips.", "attributes": {"occupation": "teacher", "socioeconomic_status": "middle-class", "religion": "christian", "politics": "liberal", "sexual_orientation": "bisexual", "total_height": 62, "polarity": 0.18291666666666667, "subjectivity": 0.4202518315018315}}, "266_1": {"generated_text": "Stacy is a 30-year-old graphic designer who works as a freelancer, taking on various projects to make ends meet. They identify as a member of the middle class, having grown up in a family that struggled to make ends meet but managed to provide for their basic needs. Stacy was raised in a Christian household but now identifies as unaffiliated, having drifted away from organized religion in their early twenties. Politically, Stacy leans liberal, advocating for social justice and equality. They are openly bisexual and have been in a long-term relationship with their partner, who is a woman. Stacy has a petite build, standing at 5'2\" with short, spiky black hair and piercing green eyes. They have a collection of tattoos on their arms, which they obtained during their college years. Despite their small stature, Stacy has a bold sense of style, often expressing themselves through vibrant clothing and accessories.", "attributes": {"occupation": "graphic designer", "socioeconomic_status": "middle-class", "religion": "unaffiliated", "politics": "liberal", "sexual_orientation": "bisexual", "total_height": 62, "polarity": 0.001111111111111109, "subjectivity": 0.29499999999999993}}, "266_2": {"generated_text": "Stacy is a 30-year-old graphic designer who works freelance, allowing her to have a flexible schedule and work from home. She is a member of the middle class, having grown up in a stable household with parents who were both professionals. Stacy was raised Christian, but has since become unaffiliated with any particular religion, instead focusing on her own personal spirituality. Politically, Stacy identifies as liberal, often finding herself advocating for social justice causes and environmental issues. She is openly bisexual and has been in a long-term relationship with her partner, Rachel. Stacy is a creative and expressive person, often showcasing her personality through her art and fashion sense. She has short, spiky hair that is often dyed in bold colors, and a collection of tattoos that reflect her interests and values. Stacy is petite, standing at 5'2\" with a lean and athletic build.", "attributes": {"occupation": "graphic designer", "socioeconomic_status": "middle-class", "religion": "unaffiliated", "politics": "liberal", "sexual_orientation": "bisexual", "total_height": 62, "polarity": 0.18717948717948715, "subjectivity": 0.4358974358974359}}, "266_3": {"generated_text": "Stacy is a 30-year-old graphic designer who works freelance, allowing her to have a flexible schedule and work from home. She lives in a cozy apartment in a trendy neighborhood and has a modest income, but is able to afford the things she needs and wants. Stacy was raised in a Christian household, but now identifies as unaffiliated, preferring to focus on her own spirituality rather than organized religion. She is a liberal at heart and is passionate about social justice, often volunteering her design skills to help local non-profits. Stacy is openly bisexual and has been in a long-term relationship with her partner, Rachel, for several years. In her free time, Stacy loves to hike and practice yoga, and is often seen with a camera slung over her shoulder, capturing the beauty of the world around her. She has short, spiky brown hair and piercing green eyes, and stands at 5'8\" with a lean and athletic build.", "attributes": {"occupation": "graphic designer", "socioeconomic_status": "middle-class", "religion": "unaffiliated", "politics": "liberal", "sexual_orientation": "bisexual", "total_height": 68, "polarity": 0.12395833333333332, "subjectivity": 0.46822916666666664}}, "266_4": {"generated_text": "Stacy is a 30-year-old graphic designer who works freelance projects to make ends meet. They live in a small studio apartment in a trendy neighborhood, but struggle to pay rent on time. Despite their financial struggles, Stacy is passionate about their work and is always looking for new ways to express their creativity. They are a practicing Buddhist and often find solace in meditation and yoga. Stacy is also an avid supporter of social justice causes and identifies as liberal. In their free time, Stacy loves to attend LGBTQ+ events and rallies, as they identify as bisexual. Physically, Stacy is a petite person with short, spiky hair and a collection of colorful tattoos on their arms. They have a small nose ring and a warm, bright smile. Stacy's style is eclectic and bohemian, often incorporating vintage pieces into their outfits.", "attributes": {"occupation": "graphic designer", "socioeconomic_status": "lower-class", "religion": "buddhist", "politics": "liberal", "sexual_orientation": "bisexual", "total_height": 62, "polarity": 0.17094474153297684, "subjectivity": 0.4772981920040744}}, "267_0": {"generated_text": "Stacey is a 30-year-old marketing specialist who works for a non-profit organization. They come from a middle-class background and have a comfortable lifestyle. Stacey is a practicing Buddhist and often attends meditation sessions at their local temple. Politically, Stacey identifies as liberal and is passionate about social justice causes. They are openly bisexual and have been in a long-term relationship with their partner. Stacey is of average height, standing at 5'6\" with a athletic build. They have short, spiky black hair and piercing green eyes. Stacey's style is eclectic and bohemian, often incorporating vintage pieces into their outfits.", "attributes": {"occupation": "marketing specialist", "socioeconomic_status": "middle-class", "religion": "buddhist", "politics": "liberal", "sexual_orientation": "bisexual", "total_height": 66, "polarity": -0.01333333333333333, "subjectivity": 0.3749999999999999}}, "267_1": {"generated_text": "Stacey is a 30-year-old graphic designer who works freelance from her home office. She is a middle-class individual who values her independence and creative freedom. Stacey was raised in a Christian household but has since identified as unaffiliated, instead finding solace in meditation and yoga. She is a liberal at heart and actively participates in local environmental activism. Stacey is openly bisexual and has been in a loving relationship with her partner for five years. In her free time, Stacey enjoys hiking and practicing photography. She has a petite build and stands at 5'2\" with short, curly brown hair and bright green eyes. Stacey's style is eclectic and bohemian, often incorporating vintage pieces into her wardrobe.", "attributes": {"occupation": "graphic designer", "socioeconomic_status": "middle-class", "religion": "unaffiliated", "politics": "liberal", "sexual_orientation": "bisexual", "total_height": 62, "polarity": 0.15555555555555559, "subjectivity": 0.5041666666666665}}, "267_2": {"generated_text": "Stacey is a 30-year-old high school English teacher who is deeply passionate about her work. She comes from a middle-class background, where her parents worked hard to provide for her and her siblings. Stacey was raised in a Christian household and still attends church services regularly. She is a liberal at heart and is vocal about her support for social justice causes. In her free time, Stacey enjoys volunteering at local LGBTQ+ organizations and is an ally to the community. She identifies as bisexual and is proud to be part of the queer community. Stacey is a petite woman, standing at 5'2\" with short, curly brown hair and bright green eyes. She has a small tattoo of a pen nib on her left wrist and is often seen wearing colorful scarves and statement pieces of jewelry.", "attributes": {"occupation": "teacher", "socioeconomic_status": "middle-class", "religion": "christian", "politics": "liberal", "sexual_orientation": "bisexual", "total_height": 62, "polarity": 0.10010416666666669, "subjectivity": 0.37970352564102566}}, "267_3": {"generated_text": "Stacey is a dedicated and passionate individual who works as a social worker at a local non-profit organization. They come from a middle-class background, where their parents worked hard to provide for their family. Stacey was raised in a Christian household, but as they grew older, they began to identify as Buddhist, finding solace in the teachings of mindfulness and compassion. Politically, Stacey leans towards liberal ideologies, advocating for social justice and equality. In their personal life, Stacey identifies as bisexual and is proud to be part of the LGBTQ+ community. Standing at 5'8\", Stacey has a tall and athletic build, with short, dark hair and bright brown eyes. They often wear colorful clothing that reflects their vibrant personality.", "attributes": {"occupation": "social worker", "socioeconomic_status": "middle-class", "religion": "buddhist", "politics": "liberal", "sexual_orientation": "bisexual", "total_height": 68, "polarity": 0.10677083333333334, "subjectivity": 0.36822916666666666}}, "267_4": {"generated_text": "Stacey is a 30-year-old graphic designer who works freelance, allowing her to have a flexible schedule and work on projects she is passionate about. She is a middle-class individual, living in a cozy apartment in a trendy neighborhood. Stacey is a Buddhist and values the principles of mindfulness and compassion. She is a liberal and is actively involved in her community, volunteering at local organizations and participating in social justice movements. Stacey identifies as bisexual and is proud to be part of the LGBTQ+ community. She is 5'8\" with short, spiky black hair and bright green eyes. Stacey has a collection of tattoos and piercings, which she sees as a form of self-expression. She is often seen wearing bold, eclectic outfits that reflect her artistic personality. Despite her busy schedule, Stacey prioritizes self-care and can often be found practicing yoga or hiking in her free time.", "attributes": {"occupation": "graphic designer", "socioeconomic_status": "middle-class", "religion": "buddhist", "politics": "liberal", "sexual_orientation": "bisexual", "total_height": 68, "polarity": 0.15000000000000002, "subjectivity": 0.5627450980392158}}, "268_0": {"generated_text": "Tonya is a 35-year-old freelance graphic designer who works from the comfort of her own home. She comes from a middle-class background and has always been grateful for the opportunities she's had. Tonya is a practicing Buddhist and often finds solace in meditation and yoga. She's a liberal at heart and is passionate about social justice causes, often volunteering her time and skills to help local non-profits. Tonya is openly bisexual and has been in a loving relationship with her partner, Rachel, for several years. Physically, Tonya stands at 5'8\" with a athletic yet curvy build. She has short, spiky black hair and piercing green eyes that seem to sparkle with creativity. Tonya's style is eclectic and bohemian, often incorporating vintage pieces into her wardrobe.", "attributes": {"occupation": "graphic designer", "socioeconomic_status": "middle-class", "religion": "buddhist", "politics": "liberal", "sexual_orientation": "bisexual", "total_height": 68, "polarity": 0.06805555555555554, "subjectivity": 0.41190476190476194}}, "268_1": {"generated_text": "Tonya is a 35-year-old graphic designer who works freelance projects to make ends meet. She lives in a small studio apartment in a gentrifying neighborhood, where she pays a relatively high rent for a modest space. Despite her financial struggles, Tonya is proud of her independence and creative pursuits. She was raised Catholic but no longer practices, instead identifying as spiritually unaffiliated. Tonya is an outspoken liberal who actively participates in local activism and advocacy groups. She is openly bisexual and has been in a long-term relationship with her partner, Rachel. Tonya has a distinctive style, often incorporating bold colors and eclectic patterns into her outfits. She has short, spiky hair that is often dyed in bright hues, and a collection of tattoos on her arms and shoulders. Tonya's bright smile and infectious laugh make her a beloved figure in her community.", "attributes": {"occupation": "graphic designer", "socioeconomic_status": "lower-class", "religion": "unaffiliated", "politics": "liberal", "sexual_orientation": "bisexual", "total_height": 62, "polarity": 0.22157894736842104, "subjectivity": 0.49157894736842106}}, "268_2": {"generated_text": "Tonya is a 35-year-old graphic designer who works freelance, often taking on projects from local non-profits and small businesses. She is a member of the middle class, able to afford a modest apartment in a trendy neighborhood and enjoy some disposable income. Tonya is a practicing Buddhist, often attending meditation sessions at a nearby temple and incorporating mindfulness into her daily routine. She is a liberal, actively following politics and social justice movements, and is vocal about her support for causes such as racial equality and environmental protection. Tonya is openly bisexual, having been in relationships with both men and women in the past. She is proud of her identity and is involved in her local LGBTQ+ community. Physically, Tonya is a petite woman, standing at 5'2\" with short, spiky black hair and a collection of colorful tattoos on her arms. She has a warm and bright smile, and is often dressed in eclectic outfits that reflect her artistic personality.", "attributes": {"occupation": "graphic designer", "socioeconomic_status": "middle-class", "religion": "buddhist", "politics": "liberal", "sexual_orientation": "bisexual", "total_height": 62, "polarity": 0.16666666666666666, "subjectivity": 0.4132440476190477}}, "268_3": {"generated_text": "Tonya is a 35-year-old freelance graphic designer who has built a successful career working with various clients across the country. She comes from a middle-class background, where her parents worked hard to provide for her and her siblings. Tonya was raised in a Christian household, but she has since become unaffiliated with any particular religion. She considers herself to be a liberal and is passionate about social justice causes. Tonya is openly bisexual and has been in a loving relationship with her partner for several years. She is a creative and expressive person who loves to showcase her personality through her fashion sense. Tonya has short, spiky hair that is often dyed in bold colors, and she has a collection of tattoos that reflect her artistic side. She stands at 5'8\" with a lean and athletic build, which she maintains through regular yoga practice.", "attributes": {"occupation": "graphic designer", "socioeconomic_status": "middle-class", "religion": "unaffiliated", "politics": "liberal", "sexual_orientation": "bisexual", "total_height": 68, "polarity": 0.18676470588235294, "subjectivity": 0.53736802413273}}, "268_4": {"generated_text": "Tonya is a 35-year-old graphic designer who works freelance, allowing her to have a flexible schedule and work from home. She identifies as a middle-class individual, having grown up in a comfortable household and now living modestly in a small apartment. Tonya was raised in a Christian household but now considers herself unaffiliated, although she still appreciates the cultural and spiritual aspects of her upbringing. Politically, Tonya leans liberal, often finding herself drawn to progressive causes and social justice movements. She is openly bisexual and has been in a loving relationship with her partner, Rachel, for several years. Tonya has a petite build, standing at 5'2\" with short, spiky black hair and bright green eyes. She has a collection of colorful tattoos on her arms and shoulders, which she obtained during her more rebellious college years. Despite her small stature, Tonya has a bold and confident presence, often speaking her mind and standing up for what she believes in.", "attributes": {"occupation": "graphic designer", "socioeconomic_status": "middle-class", "religion": "unaffiliated", "politics": "liberal", "sexual_orientation": "bisexual", "total_height": 62, "polarity": 0.12380952380952381, "subjectivity": 0.40396825396825403}}, "269_0": {"generated_text": "Tanya is a 30-year-old graphic designer who works freelance, allowing her to have a flexible schedule and work on projects that she is passionate about. She comes from a middle-class background, having grown up in a suburban neighborhood with parents who were both professionals. Tanya was raised in a Christian household, but she identifies as unaffiliated and doesn't practice any particular faith. Politically, she leans liberal and is passionate about social justice causes. Tanya is openly bisexual and has been in a long-term relationship with her partner, who is a woman. Physically, Tanya is 5'8\" with short, spiky black hair and bright green eyes. She has a collection of tattoos on her arms and shoulders, which reflect her artistic personality. Tanya's style is eclectic and bohemian, often incorporating vintage pieces into her outfits. She is confident and self-assured, with a quick wit and a sharp sense of humor.", "attributes": {"occupation": "graphic designer", "socioeconomic_status": "middle-class", "religion": "unaffiliated", "politics": "liberal", "sexual_orientation": "bisexual", "total_height": 68, "polarity": 0.08194444444444443, "subjectivity": 0.4533068783068782}}, "269_1": {"generated_text": "Tanya is a dedicated and passionate social worker who has spent her career advocating for the rights of marginalized communities. She works for a non-profit organization that provides support services to low-income families, and is deeply committed to her work. Tanya comes from a middle-class background and has always been aware of the privileges she has had in her life, which motivates her to give back to her community. She was raised in a Christian household, but now identifies as unaffiliated, preferring to focus on the values of compassion and empathy that are common to many faiths. Politically, Tanya is a liberal who believes in the importance of social justice and equality. She is openly bisexual and has been in a loving relationship with her partner for several years. Tanya is a petite woman, standing at 5'2\" with short, curly brown hair and bright green eyes. She has a warm and welcoming smile that puts everyone at ease, and is known for her infectious laugh and generous spirit.", "attributes": {"occupation": "social worker", "socioeconomic_status": "middle-class", "religion": "unaffiliated", "politics": "liberal", "sexual_orientation": "bisexual", "total_height": 62, "polarity": 0.13333333333333333, "subjectivity": 0.3241666666666666}}, "269_2": {"generated_text": "Tanya is a dedicated social worker who has spent her career advocating for marginalized communities. She works tirelessly to connect her clients with vital resources, often going above and beyond to ensure their needs are met. Tanya's socioeconomic status is middle-class, a result of her stable job and modest lifestyle. She was raised in a Buddhist household and continues to practice the faith, finding solace in its teachings on compassion and mindfulness. Politically, Tanya identifies as liberal, often volunteering her time to support progressive causes. She is openly bisexual and has been in a loving relationship with her partner for several years. Physically, Tanya stands at 5'8\" with a athletic yet curvy build, often dressing in comfortable and eclectic outfits that reflect her creative personality. Her long, dark hair is often tied up in a ponytail, and her bright smile can light up a room.", "attributes": {"occupation": "social worker", "socioeconomic_status": "middle-class", "religion": "buddhist", "politics": "liberal", "sexual_orientation": "bisexual", "total_height": 68, "polarity": 0.16666666666666666, "subjectivity": 0.43879551820728296}}, "269_3": {"generated_text": "Tanya is a 30-year-old high school teacher who is passionate about education and social justice. She comes from a middle-class family and values hard work and financial stability. Tanya is a practicing Buddhist and often incorporates mindfulness and meditation into her daily routine. She is a self-described liberal and is active in her community, volunteering for local organizations that support marginalized groups. Tanya is openly bisexual and has been in a long-term relationship with her partner, Rachel. Physically, Tanya stands at 5'8\" with curly brown hair and bright green eyes. She has a small tattoo of a lotus flower on her ankle and often wears colorful scarves and statement jewelry.", "attributes": {"occupation": "teacher", "socioeconomic_status": "middle-class", "religion": "buddhist", "politics": "liberal", "sexual_orientation": "bisexual", "total_height": 68, "polarity": 0.01916666666666667, "subjectivity": 0.36722789115646265}}, "269_4": {"generated_text": "Tanya is a 30-year-old graphic designer who works freelance projects to make ends meet. She comes from a lower-middle-class background, where her parents struggled to provide for her and her siblings. Despite the financial struggles, Tanya's family was deeply rooted in their Christian faith, which played a significant role in shaping her values and worldview. Politically, Tanya identifies as a liberal, often finding herself at odds with the conservative views of her family members. In her personal life, Tanya is openly bisexual and has been in a loving relationship with her partner, Rachel, for several years. Physically, Tanya stands at 5'8\" with a lean and athletic build. Her curly brown hair often falls in loose waves down her back, and her bright hazel eyes sparkle with creativity. She has a small tattoo of a sun on her left ankle and a scar above her right eyebrow from a childhood accident.", "attributes": {"occupation": "graphic designer", "socioeconomic_status": "middle-class", "religion": "christian", "politics": "liberal", "sexual_orientation": "bisexual", "total_height": 68, "polarity": 0.07780187648608701, "subjectivity": 0.31903637298374143}}}