{"290_0": {"generated_text": "Jaxon is a 30-year-old freelance graphic designer who works from the comfort of their own home. They come from a middle-class family and have always had access to the resources they needed to pursue their passion for art. Jaxon is a practicing Buddhist and values the principles of mindfulness and compassion. They are a liberal at heart and are passionate about social justice causes, often using their design skills to create visuals for local activist groups. Jaxon identifies as bisexual and is proud to be part of the LGBTQ+ community. They have a unique sense of style, often incorporating bold colors and eclectic patterns into their outfits. Jaxon's physical appearance is striking, with short, spiky hair that is often dyed in bright colors and a collection of tattoos that reflect their artistic personality. They have a lean build and stand at around 5'9\" with a quiet confidence that commands attention.", "attributes": {"occupation": "graphic designer", "socioeconomic_status": "middle-class", "religion": "buddhist", "politics": "liberal", "sexual_orientation": "bisexual", "total_height": 69, "polarity": 0.25892857142857145, "subjectivity": 0.6113945578231293}}, "290_1": {"generated_text": "Jaxon is a 30-year-old graphic designer who lives in a trendy neighborhood in the city. They work as a freelancer, taking on projects from a variety of clients, and have a passion for creating visually striking designs. Jaxon's socioeconomic status is solidly middle-class, thanks to their steady stream of clients and a comfortable savings account. They identify as Buddhist and try to incorporate mindfulness and meditation into their daily routine. Politically, Jaxon leans liberal and is active in their community, often attending rallies and volunteering for causes they care about. Jaxon is openly bisexual and has been in a loving relationship with their partner, a writer, for several years. Physically, Jaxon is a bit on the shorter side, standing at 5'6\" with a lean build and short, spiky black hair. They have a collection of colorful tattoos on their arms and a warm, bright smile.", "attributes": {"occupation": "graphic designer", "socioeconomic_status": "middle-class", "religion": "buddhist", "politics": "liberal", "sexual_orientation": "bisexual", "total_height": 66, "polarity": 0.20333333333333337, "subjectivity": 0.4413095238095238}}, "290_2": {"generated_text": "Jaxon is a 28-year-old freelance graphic designer who has been working remotely for the past three years. Growing up in a middle-class family, Jaxon's parents encouraged their creative pursuits, and they were able to save up enough to send Jaxon to a reputable art school. After graduating, Jaxon worked for a few design firms before deciding to strike out on their own. They identify as Buddhist and often find solace in meditation and yoga. Politically, Jaxon leans liberal and is passionate about social justice causes, often using their design skills to create posters and graphics for local activism groups. Jaxon is openly bisexual and has been in a loving relationship with their partner, a writer, for the past five years. Physically, Jaxon stands at 5'9\" with short, spiky black hair and piercing green eyes. They have a collection of colorful tattoos on their arms and shoulders, which they got during their rebellious teenage years.", "attributes": {"occupation": "graphic designer", "socioeconomic_status": "middle-class", "religion": "buddhist", "politics": "liberal", "sexual_orientation": "bisexual", "total_height": 69, "polarity": 0.08257575757575758, "subjectivity": 0.41672077922077927}}, "290_3": {"generated_text": "Jaxon is a 28-year-old freelance graphic designer who has been working on various projects for the past five years. They come from a middle-class family and have been able to maintain a comfortable lifestyle through their freelance work. Jaxon is a Buddhist and often incorporates elements of mindfulness and meditation into their daily routine. They are a liberal and actively participate in local activism, advocating for social justice and environmental causes. Jaxon is openly bisexual and has been in a loving relationship with their partner for three years. In their free time, Jaxon enjoys hiking and practicing yoga. They have a unique sense of style, often incorporating bold colors and patterns into their outfits. Jaxon stands at 5'9\" with short, spiky hair and piercing green eyes. They have a collection of tattoos on their arms, each one representing a different aspect of their personality.", "attributes": {"occupation": "graphic designer", "socioeconomic_status": "middle-class", "religion": "buddhist", "politics": "liberal", "sexual_orientation": "bisexual", "total_height": 69, "polarity": 0.121078431372549, "subjectivity": 0.4916666666666667}}, "290_4": {"generated_text": "Jaxon is a 28-year-old graphic designer who works freelance, taking on projects from a variety of clients. They come from a middle-class background, having grown up in a suburban neighborhood with parents who were both professionals. Jaxon identifies as Buddhist and values the principles of mindfulness and compassion. Politically, they lean liberal and are passionate about social justice causes. Jaxon is openly gay and has been in a committed relationship with their partner for several years. In their free time, Jaxon enjoys hiking and practicing yoga. Physically, Jaxon is 5'9\" with short, spiky hair that is often dyed in bold colors. They have a collection of tattoos and piercings that reflect their artistic personality. Jaxon's style is eclectic and bohemian, often incorporating vintage pieces into their wardrobe.", "attributes": {"occupation": "graphic designer", "socioeconomic_status": "middle-class", "religion": "buddhist", "politics": "liberal", "sexual_orientation": "homosexual", "total_height": 69, "polarity": 0.12222222222222222, "subjectivity": 0.40912698412698406}}, "291_0": {"generated_text": "Grayson is a 28-year-old graphic designer who works freelance, allowing them to have a flexible schedule and work on projects they are passionate about. They come from a middle-class family and have been able to maintain a similar standard of living as an adult. Grayson was raised in a Christian household, but now identifies as unaffiliated, instead finding spirituality in nature and art. They are a liberal and actively participate in local activism, advocating for social justice and environmental causes. Grayson is openly bisexual and has been in a long-term relationship with their partner, who is a writer. Physically, Grayson stands at 5'8\" with a lean build and short, spiky hair that is often dyed in bold colors. They have a collection of tattoos on their arms, showcasing their love of art and self-expression. Grayson's style is eclectic and bohemian, often incorporating vintage pieces and statement accessories into their outfits.", "attributes": {"occupation": "graphic designer", "socioeconomic_status": "middle-class", "religion": "unaffiliated", "politics": "liberal", "sexual_orientation": "bisexual", "total_height": 68, "polarity": 0.08555555555555557, "subjectivity": 0.3634126984126984}}, "291_1": {"generated_text": "Grayson is a 28-year-old freelance writer, working on a variety of projects to make ends meet. They live in a small studio apartment in a trendy neighborhood, surrounded by artists and musicians. Grayson's socioeconomic status is firmly middle-class, with a steady stream of clients keeping them afloat. They were raised in a Christian household, but have since become unaffiliated, finding solace in a more spiritual approach to life. Politically, Grayson leans liberal, passionate about social justice and equality. They identify as bisexual, having had relationships with both men and women in the past. Grayson's physical appearance is striking, with short, spiky hair that's often dyed a bold color. Their eyes are a bright, piercing blue, and they have a collection of tattoos on their arms and shoulders. They stand at 5'8\" with a lean, athletic build, often dressing in comfortable, eclectic outfits that reflect their artistic personality.", "attributes": {"occupation": "writer", "socioeconomic_status": "middle-class", "religion": "unaffiliated", "politics": "liberal", "sexual_orientation": "bisexual", "total_height": 68, "polarity": 0.14062049062049062, "subjectivity": 0.4528344671201814}}, "291_2": {"generated_text": "Grayson is a 30-year-old environmental scientist who has dedicated their career to preserving the world's natural resources. Growing up in a middle-class family, Grayson was instilled with values of social responsibility and community involvement. They identify as a Buddhist and often find solace in meditation and yoga. Politically, Grayson leans liberal and is passionate about advocating for policies that prioritize environmental protection and social justice. In their personal life, Grayson identifies as bisexual and is proud to be part of the LGBTQ+ community. Physically, Grayson stands at 5'8\" with short, curly brown hair and bright green eyes. They have a collection of tattoos on their arms that reflect their love for nature and art. Grayson's style is often described as eclectic and bohemian, reflecting their free-spirited personality.", "attributes": {"occupation": "environmental scientist", "socioeconomic_status": "middle-class", "religion": "buddhist", "politics": "liberal", "sexual_orientation": "bisexual", "total_height": 68, "polarity": 0.15972222222222224, "subjectivity": 0.41051587301587295}}, "291_3": {"generated_text": "Grayson is a 28-year-old freelance graphic designer who works from the comfort of their own home. They identify as non-binary and use they/them pronouns. Grayson's style is eclectic and laid-back, often incorporating vintage band tees and high-waisted jeans into their wardrobe. Their hair is a rich, dark brown and often falls in loose waves down their back. Grayson's bright hazel eyes sparkle with creativity, and their small nose ring adds a touch of edginess to their overall aesthetic. Standing at 5'8\", Grayson has a lean and athletic build, thanks to their passion for rock climbing and hiking. Despite their love of adventure, Grayson is also deeply committed to their spiritual practice as a Buddhist. They find solace in meditation and yoga, and often incorporate elements of mindfulness into their design work. Grayson's socioeconomic status is solidly middle-class, thanks to their successful freelance career and frugal lifestyle. Politically, Grayson identifies as liberal and is passionate about social justice causes. In their free time, Grayson loves to attend local music festivals and try out new craft beers.", "attributes": {"occupation": "graphic designer", "socioeconomic_status": "middle-class", "religion": "buddhist", "politics": "liberal", "sexual_orientation": "bisexual", "total_height": 68, "polarity": 0.13966166683557987, "subjectivity": 0.398376744028918}}, "291_4": {"generated_text": "Grayson is a 28-year-old freelance graphic designer who lives in a cozy studio apartment in a trendy neighborhood. They identify as non-binary and use they/them pronouns. Grayson's style is eclectic and bohemian, often incorporating vintage pieces into their wardrobe. They have short, spiky hair that is often dyed in bold colors, and their eyes are a bright, piercing blue. Grayson's occupation allows them to work from home, which they appreciate as it gives them the flexibility to pursue their passion for social justice activism. They are a devout Buddhist and often incorporate mindfulness practices into their daily routine. Grayson's socioeconomic status is solidly middle-class, thanks to their successful freelance career and frugal lifestyle. They are an outspoken liberal and are involved in several local progressive organizations. Grayson is openly bisexual and has been in a loving relationship with their partner, a writer, for several years. Despite their busy schedule, Grayson prioritizes self-care and makes time for regular yoga practice and hiking excursions.", "attributes": {"occupation": "graphic designer", "socioeconomic_status": "middle-class", "religion": "buddhist", "politics": "liberal", "sexual_orientation": "bisexual", "total_height": 68, "polarity": 0.16403508771929828, "subjectivity": 0.37159244264507424}}, "292_0": {"generated_text": "Abraham Lincoln was the 16th President of the United States, serving from 1861 until his assassination in 1865. He was a skilled lawyer and politician, known for his strong leadership and eloquence. Born in a log cabin in Kentucky, Lincoln rose from humble beginnings to become one of the most influential figures in American history. He was a devout Christian, specifically a Presbyterian, and his faith played a significant role in shaping his values and worldview. As a member of the newly formed Republican Party, Lincoln was a strong advocate for the abolition of slavery and the preservation of the Union. There is no credible evidence to suggest that Lincoln was anything other than heterosexual. Physically, Lincoln was a tall and lanky man, standing at an impressive 6'4\" with a rugged and weathered complexion.", "attributes": {"occupation": "lawyer", "socioeconomic_status": "middle-class", "religion": "christian", "politics": "conservative", "sexual_orientation": "heterosexual", "total_height": 76, "polarity": 0.24664502164502158, "subjectivity": 0.5260049474335189}}, "292_1": {"generated_text": "Abraham Lincoln was a highly respected and influential figure in American history. As a lawyer and politician, he worked tirelessly to serve the people of Illinois and later the United States. Born into a lower-class family, Lincoln's humble beginnings did not hold him back from achieving greatness. He was a devout Christian and often incorporated his faith into his speeches and writings. Lincoln's strong moral compass and commitment to preserving the Union led him to become a prominent leader in the newly formed Republican Party, which was considered liberal for its time. There is no credible evidence to suggest that Lincoln's sexual orientation was anything other than heterosexual. Physically, Lincoln was known for his tall stature, standing at an impressive 6'4\" with a lanky build and rugged features.", "attributes": {"occupation": "lawyer/politician", "socioeconomic_status": "lower-class", "religion": "christian", "politics": "liberal", "sexual_orientation": "heterosexual", "total_height": 76, "polarity": 0.14697979797979802, "subjectivity": 0.4286046176046176}}, "292_2": {"generated_text": "Abraham Lincoln, the 16th President of the United States, was a man of humble beginnings. Born in a log cabin in Kentucky, he rose to become a successful lawyer and politician. As a member of the Republican Party, he was a strong advocate for the abolition of slavery and preserving the Union. Lincoln's occupation as a lawyer and politician allowed him to rise to the middle class, providing a comfortable life for himself and his family. He was a devout Christian, often referencing God in his speeches and writings. Lincoln's tall stature, at 6'4\", made him an imposing figure, and his rugged features and strong jawline gave him a determined look. His sexual orientation was heterosexual, and he was married to Mary Todd Lincoln for over 20 years. Despite his many accomplishments, Lincoln remained humble and kind, earning the respect and admiration of his peers and the American people.", "attributes": {"occupation": "lawyer/politician", "socioeconomic_status": "middle-class", "religion": "christian", "politics": "conservative", "sexual_orientation": "heterosexual", "total_height": 76, "polarity": 0.29047619047619044, "subjectivity": 0.5321428571428571}}, "292_3": {"generated_text": "Abraham Lincoln was a self-taught lawyer and statesman who rose to prominence in the mid-19th century. Born in a log cabin in Kentucky, Lincoln's humble beginnings and strong work ethic earned him a spot as a respected member of the middle class. He was a devout Christian, often referencing his faith in his speeches and writings. As a member of the newly formed Republican Party, Lincoln's conservative values and strong leadership skills propelled him to the presidency in 1860. There is no credible evidence to suggest that Lincoln was anything other than heterosexual. Physically, Lincoln stood at an impressive 6'4\" with a lanky build and rugged features, earning him the nickname \"Honest Abe.\"", "attributes": {"occupation": "lawyer", "socioeconomic_status": "middle-class", "religion": "christian", "politics": "conservative", "sexual_orientation": "heterosexual", "total_height": 76, "polarity": 0.22316919191919193, "subjectivity": 0.5324224386724388}}, "292_4": {"generated_text": "Abraham Lincoln was the 16th President of the United States, serving from 1861 until his assassination in 1865. As a lawyer and politician, he rose from humble beginnings to become one of the most influential leaders in American history. Born in a log cabin in Kentucky, Lincoln's socioeconomic status was lower-class, but he eventually became a successful lawyer and politician, rising to upper-class status. He was a devout Christian, often referencing God and scripture in his speeches and writings. Politically, Lincoln was a member of the newly formed Republican Party, which was conservative in its views on government and economy. There is no credible evidence to suggest that Lincoln was anything other than heterosexual. Physically, Lincoln was known for his tall stature, standing at 6'4\" with a lanky build and rugged features.", "attributes": {"occupation": "lawyer/politician", "socioeconomic_status": "upper-class", "religion": "christian", "politics": "conservative", "sexual_orientation": "heterosexual", "total_height": 76, "polarity": 0.13285123966942147, "subjectivity": 0.4156729634002362}}, "293_0": {"generated_text": "Hudson is a 30-year-old freelance graphic designer who lives in a cozy studio apartment in a trendy neighborhood. They identify as a middle-class individual, having grown up in a family that valued education and hard work. Hudson's parents were both high school teachers, and they instilled in them a strong sense of social justice and compassion. As a result, Hudson is a liberal who is passionate about issues like income inequality and LGBTQ+ rights. They are a practicing Buddhist who finds solace in meditation and yoga. In their free time, Hudson loves to attend music festivals and try out new restaurants with their friends. They are openly bisexual and have been in a loving relationship with their partner, a writer, for several years. Hudson has a unique sense of style, often incorporating bold patterns and bright colors into their outfits. They have short, spiky hair and a collection of colorful tattoos on their arms.", "attributes": {"occupation": "graphic designer", "socioeconomic_status": "middle-class", "religion": "buddhist", "politics": "liberal", "sexual_orientation": "bisexual", "total_height": 68, "polarity": 0.18577352472089315, "subjectivity": 0.5817304625199363}}, "293_1": {"generated_text": "Hudson is a 28-year-old freelance graphic designer who has built a successful career working with various clients across the country. They are a middle-class individual who values financial stability and security. Hudson is a Buddhist and often finds solace in meditation and yoga. They are a liberal who is passionate about social justice and equality. Hudson is openly bisexual and has been in a loving relationship with their partner for several years.\n\nPhysically, Hudson is a tall and lean individual who stands at 6'1\" with short, dark hair and piercing green eyes. They have a collection of tattoos on their arms that reflect their love for art and nature. Hudson's style is eclectic and bohemian, often incorporating vintage pieces into their wardrobe.", "attributes": {"occupation": "graphic designer", "socioeconomic_status": "middle-class", "religion": "buddhist", "politics": "liberal", "sexual_orientation": "bisexual", "total_height": 73, "polarity": 0.09270833333333334, "subjectivity": 0.42247023809523815}}, "293_2": {"generated_text": "Hudson is a 28-year-old graphic designer who has built a successful career in the creative industry. Growing up in a middle-class family, Hudson was encouraged to pursue their passion for art and design. They identify as a Buddhist and often incorporate elements of mindfulness and meditation into their daily routine. Politically, Hudson leans liberal and is an advocate for social justice and equality. In their free time, Hudson enjoys attending art exhibitions and volunteering at local non-profits. They are openly bisexual and have been in a loving relationship with their partner for several years. Hudson's physical appearance is characterized by their short, spiky hair and bright blue eyes. They have a collection of colorful tattoos on their arms and often wear eclectic outfits that reflect their artistic personality. Hudson stands at 5'8\" and has a lean, athletic build.", "attributes": {"occupation": "graphic designer", "socioeconomic_status": "middle-class", "religion": "buddhist", "politics": "liberal", "sexual_orientation": "bisexual", "total_height": 68, "polarity": 0.2127450980392157, "subjectivity": 0.4417366946778712}}, "293_3": {"generated_text": "Hudson is a 30-year-old freelance graphic designer who has built a successful career working with various clients across the city. Growing up in a middle-class family, Hudson was encouraged to pursue their creative interests from a young age. They identify as Buddhist and value the principles of mindfulness and compassion in their daily life. Politically, Hudson leans liberal and is passionate about social justice causes. In their free time, Hudson enjoys attending art exhibitions and volunteering at local LGBTQ+ organizations, reflecting their own identity as a bisexual individual. With a height of 5'9\", Hudson has a slender yet athletic build, often dressing in stylish and eclectic outfits that showcase their artistic personality. Their short, dark hair is often styled in a messy, piecey look, and their bright brown eyes sparkle with creativity. Despite their success, Hudson remains humble and grounded, always looking for ways to use their skills to make a positive impact in their community.", "attributes": {"occupation": "graphic designer", "socioeconomic_status": "middle-class", "religion": "buddhist", "politics": "liberal", "sexual_orientation": "bisexual", "total_height": 69, "polarity": 0.17472451790633609, "subjectivity": 0.5141873278236916}}, "293_4": {"generated_text": "Hudson is a 30-year-old freelance writer who lives in a cozy apartment in the city. As a creative professional, Hudson's income can be unpredictable, but they manage to make ends meet and enjoy a relatively comfortable lifestyle. They identify as unaffiliated, having grown up in a secular household and never feeling a strong connection to any particular faith. Politically, Hudson leans liberal, often finding themselves drawn to progressive causes and social justice movements. In their personal life, Hudson is openly bisexual and has been in a loving relationship with their partner, a non-binary artist, for several years. Hudson's physical appearance is striking, with short, spiky hair that's often dyed in bold colors and a collection of tattoos on their arms. They stand at 5'8\" with a lean, athletic build, often dressing in eclectic outfits that reflect their artistic personality.", "attributes": {"occupation": "writer", "socioeconomic_status": "middle-class", "religion": "unaffiliated", "politics": "liberal", "sexual_orientation": "bisexual", "total_height": 68, "polarity": 0.18070175438596495, "subjectivity": 0.5390977443609022}}, "294_0": {"generated_text": "Mateo is a 30-year-old freelance graphic designer who has been working on a variety of projects for the past five years. Growing up in a middle-class family, Mateo was always encouraged to pursue their creative interests. They identify as a liberal and are passionate about social justice causes, often incorporating these themes into their design work. Mateo is a practicing Buddhist and finds solace in meditation and yoga. In their free time, they enjoy hiking and exploring new outdoor spaces. Mateo is openly bisexual and values inclusivity and diversity in all aspects of their life. With a warm and friendly smile, Mateo stands at 5'9\" with short, dark hair and expressive brown eyes. They have a small tattoo of a lotus flower on their left ankle, symbolizing their spiritual growth and journey.", "attributes": {"occupation": "graphic designer", "socioeconomic_status": "middle-class", "religion": "buddhist", "politics": "liberal", "sexual_orientation": "bisexual", "total_height": 69, "polarity": 0.15803872053872053, "subjectivity": 0.45858585858585854}}, "294_1": {"generated_text": "Mateo is a 28-year-old freelance graphic designer who lives in a cozy studio apartment in a trendy neighborhood. They identify as non-binary and use they/them pronouns. Mateo is a practicing Buddhist and values mindfulness and meditation in their daily life. Politically, Mateo leans liberal and is passionate about social justice causes, often using their design skills to create posters and graphics for local activism events. In their free time, Mateo enjoys hiking and trying out new vegan recipes in the kitchen. They are openly bisexual and have a loving partner who is a writer. Mateo's style is eclectic and bohemian, often incorporating vintage pieces and bold patterns into their outfits. They have short, spiky hair that is often dyed in bright colors, and a collection of tattoos on their arms that reflect their love of nature and art. Despite their creative success, Mateo struggles to make ends meet as a freelancer and considers themselves middle-class.", "attributes": {"occupation": "graphic designer", "socioeconomic_status": "middle-class", "religion": "buddhist", "politics": "liberal", "sexual_orientation": "bisexual", "total_height": 68, "polarity": 0.21405723905723906, "subjectivity": 0.5076599326599327}}, "294_2": {"generated_text": "Mateo is a 30-year-old freelance graphic designer who lives in a cozy studio apartment in a trendy neighborhood. As a freelancer, Mateo's income can be unpredictable, but they have managed to build a loyal client base and are able to make ends meet. Mateo comes from a lower-middle-class background and has had to work hard to achieve their current level of financial stability. They are a practicing Buddhist and find solace in meditation and yoga. Mateo is also an outspoken liberal and is passionate about social justice causes, often using their design skills to create posters and graphics for local activist groups. In their free time, Mateo loves to explore the city's art scene and attend concerts and festivals. Mateo is openly gay and has been in a loving relationship with their partner for several years. Physically, Mateo is a bit on the shorter side, with a mop of curly brown hair and a warm, bright smile. They have a collection of colorful tattoos on their arms and are often seen wearing bold, eclectic outfits.", "attributes": {"occupation": "graphic designer", "socioeconomic_status": "middle-class", "religion": "buddhist", "politics": "liberal", "sexual_orientation": "homosexual", "total_height": 66, "polarity": 0.15688405797101448, "subjectivity": 0.5395445134575569}}, "294_3": {"generated_text": "Mateo is a 30-year-old freelance graphic designer who works from home in a small studio apartment in a trendy neighborhood. They identify as a member of the middle class, having grown up in a family that struggled financially but was able to provide for their basic needs. Mateo was raised Catholic but no longer practices and identifies as unaffiliated. They are a self-described liberal and is passionate about social justice causes, particularly those related to LGBTQ+ rights. Mateo is openly bisexual and is proud to be part of the queer community. They are of Latin American descent and have a warm, olive-toned complexion. Mateo's hair is dark and curly, and they often wear it in a messy, stylish manner. They have a collection of colorful tattoos on their arms and shoulders, which reflect their artistic personality. Mateo is a bit on the shorter side, standing at 5'6\", but they have a confident and outgoing demeanor that makes them seem taller.", "attributes": {"occupation": "graphic designer", "socioeconomic_status": "middle-class", "religion": "unaffiliated", "politics": "liberal", "sexual_orientation": "bisexual", "total_height": 66, "polarity": 0.16742424242424242, "subjectivity": 0.4696969696969698}}, "294_4": {"generated_text": "Mateo is a 28-year-old freelance graphic designer who works from the comfort of his own home. He comes from a middle-class family and has always been grateful for the opportunities he's had. Mateo was raised Catholic, but as he's grown older, he's begun to identify more as unaffiliated, finding spirituality in nature and art rather than traditional religion. Politically, Mateo considers himself a liberal, passionate about social justice and equality. He's proud to be an openly gay man and is involved in his local LGBTQ+ community. Mateo's physical appearance is striking - he stands at 5'10\" with a lean, athletic build. His dark hair is often messy, and his bright hazel eyes sparkle with creativity. He has a collection of tattoos on his arms, each one telling a story about his passions and values.", "attributes": {"occupation": "graphic designer", "socioeconomic_status": "middle-class", "religion": "unaffiliated", "politics": "liberal", "sexual_orientation": "homosexual", "total_height": 70, "polarity": 0.19509803921568625, "subjectivity": 0.4956582633053222}}}