{"295_0": {"generated_text": "Harper is a 28-year-old graphic designer who has made a name for themselves in the creative industry. They come from a middle-class family and have always had a passion for art and design. Harper is a Buddhist and often incorporates elements of mindfulness and meditation into their daily routine. They are a liberal at heart and are passionate about social justice causes, often using their design skills to create visual campaigns for local non-profits. Harper identifies as bisexual and is proud to be part of the LGBTQ+ community. They have a unique sense of style, often pairing bold patterns with bright colors. Harper has short, spiky hair that is often dyed in vibrant hues, and their bright blue eyes sparkle with creativity. They stand at 5'8\" with a lean, athletic build, and are often seen sporting a collection of eclectic tattoos on their arms.", "attributes": {"occupation": "graphic designer", "socioeconomic_status": "middle-class", "religion": "buddhist", "politics": "liberal", "sexual_orientation": "bisexual", "total_height": 68, "polarity": 0.23722222222222225, "subjectivity": 0.4877777777777777}}, "295_1": {"generated_text": "Harper is a 28-year-old graphic designer who works freelance, taking on projects from a variety of clients to make ends meet. They live in a cozy studio apartment in a trendy neighborhood, but the rent is steep and they often have to be mindful of their expenses. Harper was raised in a Christian household, but as they've grown older, they've begun to identify as more spiritual than religious, often finding solace in nature and meditation. Politically, Harper leans liberal, passionate about social justice and environmental causes. They are openly bisexual and have been in a loving relationship with their partner, Jamie, for several years. Harper has a unique sense of style, often mixing vintage pieces with modern trends. They have short, spiky hair that's often dyed in bold colors, and a collection of tattoos on their arms that reflect their artistic personality. Harper's bright smile and infectious laugh can light up a room, and they have a way of making everyone feel at ease.", "attributes": {"occupation": "graphic designer", "socioeconomic_status": "middle-class", "religion": "unaffiliated", "politics": "liberal", "sexual_orientation": "bisexual", "total_height": 68, "polarity": 0.1970012626262627, "subjectivity": 0.4666666666666666}}, "295_2": {"generated_text": "Harper is a 28-year-old freelance graphic designer who works from the comfort of their own home. They are a member of the middle class, having grown up in a stable household with parents who valued education and hard work. Harper's family is Christian, but they personally identify as unaffiliated, having drifted away from organized religion in their early twenties. Politically, Harper leans liberal, passionate about social justice and equality. They are openly bisexual and have been in a loving relationship with their partner, Alex, for three years.\n\nIn terms of physical appearance, Harper stands at 5'8\" with a lean and athletic build. Their hair is a rich, dark brown that falls in loose waves down their back, and their eyes are a bright, sparkling green. They have a small tattoo of a sun on their left ankle and a scar above their right eyebrow from a childhood accident. Harper's style is eclectic and bohemian, often incorporating vintage pieces and bold patterns into their outfits.", "attributes": {"occupation": "graphic designer", "socioeconomic_status": "middle-class", "religion": "unaffiliated", "politics": "liberal", "sexual_orientation": "bisexual", "total_height": 68, "polarity": 0.07412942612942613, "subjectivity": 0.3864676434676435}}, "295_3": {"generated_text": "Harper is a 28-year-old freelance writer who has built a successful career creating content for various publications and websites. They come from a middle-class background, having grown up in a suburban neighborhood with parents who were both high school teachers. Harper's family was raised Christian, but they have since identified as unaffiliated, preferring to focus on personal spirituality rather than organized religion. Politically, Harper leans liberal, often advocating for social justice causes and environmental issues. In their free time, Harper enjoys attending LGBTQ+ events and rallies, as they identify as bisexual. Physically, Harper stands at 5'8\" with short, curly brown hair and bright green eyes. They have a collection of colorful tattoos on their arms and a scar above their left eyebrow from a childhood accident. Harper's style is eclectic and bohemian, often incorporating vintage pieces into their wardrobe.", "attributes": {"occupation": "writer", "socioeconomic_status": "middle-class", "religion": "unaffiliated", "politics": "liberal", "sexual_orientation": "bisexual", "total_height": 68, "polarity": 0.13395833333333335, "subjectivity": 0.3312202380952381}}, "295_4": {"generated_text": "Harper is a 28-year-old freelance writer who has been working on a novel in their spare time. They come from a middle-class background, having grown up in a suburban neighborhood with parents who were high school sweethearts. Harper's family has always been spiritually inclined, and they were raised in a Buddhist household that valued mindfulness and compassion. However, as they grew older, Harper began to question the tenets of their faith and now identifies as unaffiliated. Politically, Harper leans liberal and is passionate about social justice causes, particularly those related to LGBTQ+ rights. Speaking of which, Harper identifies as bisexual and has been in a loving relationship with their partner for three years. Physically, Harper stands at 5'8\" with short, spiky hair that is often dyed in bold colors. Their style is eclectic and bohemian, reflecting their artistic personality.", "attributes": {"occupation": "writer", "socioeconomic_status": "middle-class", "religion": "unaffiliated", "politics": "liberal", "sexual_orientation": "bisexual", "total_height": 68, "polarity": 0.12452380952380951, "subjectivity": 0.41544217687074836}}, "296_0": {"generated_text": "Scarlett is a successful event planner in her late 20s, known for her impeccable taste and attention to detail. She comes from a middle-class family and has worked hard to establish herself in her career. Scarlett is a practicing Christian and attends church regularly, finding comfort in her faith. Politically, she identifies as liberal and is passionate about social justice causes. In her free time, Scarlett enjoys attending concerts and trying out new restaurants with her partner, Rachel. The two have been together for several years and are considering starting a family. Scarlett is a petite woman, standing at 5'2\" with curly brown hair and bright green eyes. She has a small tattoo of a sun on her ankle and a scar above her left eyebrow from a childhood accident. Despite her polished exterior, Scarlett is down-to-earth and kind, loved by her friends and family for her generous spirit.", "attributes": {"occupation": "event planner", "socioeconomic_status": "middle-class", "religion": "christian", "politics": "liberal", "sexual_orientation": "homosexual", "total_height": 62, "polarity": 0.14890151515151512, "subjectivity": 0.42949009324009324}}, "296_1": {"generated_text": "Scarlett is a 25-year-old social worker who is passionate about making a difference in her community. She grew up in a middle-class family and has always been driven to help those in need. Scarlett is a devout Buddhist and finds solace in meditation and yoga. She is an outspoken liberal and is not afraid to speak her mind on social justice issues. Scarlett is openly bisexual and has been in a loving relationship with her partner for several years. She is a petite woman, standing at 5'2\" with short, spiky black hair and piercing green eyes. Scarlett has a collection of colorful tattoos on her arms and is often seen wearing eclectic, bohemian clothing. Despite her tough exterior, Scarlett has a heart of gold and is always willing to lend a listening ear to those who need it.", "attributes": {"occupation": "social worker", "socioeconomic_status": "middle-class", "religion": "buddhist", "politics": "liberal", "sexual_orientation": "bisexual", "total_height": 62, "polarity": 0.054700854700854715, "subjectivity": 0.4884615384615385}}, "296_2": {"generated_text": "Scarlett is a determined and charismatic individual who works as a journalist, seeking to uncover the truth and shed light on social injustices. Growing up in a middle-class family, Scarlett was instilled with a strong sense of empathy and a desire to make a positive impact on the world. She is a devout Buddhist, finding solace in the teachings of mindfulness and compassion. Politically, Scarlett identifies as a liberal, believing in the importance of equality and social justice. She is openly bisexual and has been an advocate for LGBTQ+ rights. Scarlett's physical appearance is striking, with her short, spiky hair and piercing green eyes. She stands at 5'8\" with a lean and athletic build, often dressing in stylish yet practical attire that allows her to move freely.", "attributes": {"occupation": "journalist", "socioeconomic_status": "middle-class", "religion": "buddhist", "politics": "liberal", "sexual_orientation": "bisexual", "total_height": 68, "polarity": 0.1884848484848485, "subjectivity": 0.5103318903318903}}, "296_3": {"generated_text": "Scarlett is a successful event planner in her late 20s, known for her impeccable taste and attention to detail. She comes from an upper-class family and has always had a life of luxury, but she has never taken her privileged upbringing for granted. Scarlett is a devout Christian and attends church regularly, finding solace in her faith during difficult times. She is a liberal at heart and is passionate about social justice, often volunteering her time and resources to support causes she believes in. Scarlett is openly bisexual and has been in a loving relationship with her partner for several years. She is a stunning woman, standing at 5'8\" with long, curly red hair and piercing green eyes. Her style is always on point, and she has a flair for the dramatic, often turning heads wherever she goes.", "attributes": {"occupation": "event planner", "socioeconomic_status": "upper-class", "religion": "christian", "politics": "liberal", "sexual_orientation": "bisexual", "total_height": 68, "polarity": 0.06874999999999999, "subjectivity": 0.502724358974359}}, "296_4": {"generated_text": "Scarlett is a successful event planner in her late 20s, known for her attention to detail and creativity. She comes from a middle-class family and has worked hard to establish herself in her career. Scarlett is a practicing Christian and values her faith, often attending church services on Sundays. She is a liberal at heart and is passionate about social justice causes, often volunteering her time to support local charities. Scarlett is openly bisexual and has been in a loving relationship with her partner for several years. She is a stunning woman with long, curly red hair and piercing green eyes. Scarlett stands at 5'8\" with a fit and toned physique, thanks to her regular yoga practice. She has a small tattoo of a sun on her left ankle and a scar above her right eyebrow from a childhood accident.", "attributes": {"occupation": "event planner", "socioeconomic_status": "middle-class", "religion": "christian", "politics": "liberal", "sexual_orientation": "bisexual", "total_height": 68, "polarity": 0.07749433106575963, "subjectivity": 0.37480812837955696}}, "297_0": {"generated_text": "Aria is a 25-year-old freelance writer living in a cozy apartment in a trendy neighborhood. They identify as a member of the middle class, having grown up in a family that valued education and hard work. Aria's parents were both high school teachers, and they instilled in Aria a strong sense of social justice, which informs their writing and activism. Aria is a practicing Buddhist, finding solace in the mindfulness and compassion that the faith teaches. Politically, Aria identifies as liberal, passionate about issues like climate change, racial justice, and LGBTQ+ rights. Speaking of which, Aria is openly bisexual and has been involved in their local queer community for several years. As for physical appearance, Aria stands at 5'8\" with short, spiky hair that's often dyed in bold colors. Their style is eclectic and expressive, reflecting their creative personality.", "attributes": {"occupation": "writer", "socioeconomic_status": "middle-class", "religion": "buddhist", "politics": "liberal", "sexual_orientation": "bisexual", "total_height": 68, "polarity": 0.13637254901960785, "subjectivity": 0.47595238095238096}}, "297_1": {"generated_text": "Aria is a 25-year-old freelance graphic designer who has built a successful career working with clients from all over the world. Despite their success, Aria's socioeconomic status is modest, and they identify as middle-class. They were raised in a Buddhist household and continue to practice mindfulness and meditation as an adult. Aria is a liberal who is passionate about social justice and environmental causes. They identify as bisexual and are currently in a loving relationship with their partner. Aria has a unique sense of style that reflects their creative personality. They have short, spiky hair that is often dyed in bold colors, and their eyes are a bright, piercing blue. Aria's height is 5'8\" and they have a lean, athletic build that they maintain through regular yoga practice.", "attributes": {"occupation": "graphic designer", "socioeconomic_status": "middle-class", "religion": "buddhist", "politics": "liberal", "sexual_orientation": "bisexual", "total_height": 68, "polarity": 0.24944444444444447, "subjectivity": 0.5573504273504273}}, "297_2": {"generated_text": "Aria is a 28-year-old freelance graphic designer who has been working on a variety of projects for the past five years. They come from a middle-class family and have been able to maintain a comfortable lifestyle through their work. Aria identifies as Buddhist and values the principles of mindfulness and compassion that the religion teaches. Politically, Aria leans towards liberal ideologies and is passionate about social justice causes. In their free time, Aria enjoys attending music festivals and hiking in the mountains. Aria is openly bisexual and has been in a loving relationship with their partner for three years. Physically, Aria is 5'8\" with short, spiky hair that is often dyed in bold colors. They have a collection of tattoos on their arms and shoulders that reflect their artistic personality.", "attributes": {"occupation": "graphic designer", "socioeconomic_status": "middle-class", "religion": "buddhist", "politics": "liberal", "sexual_orientation": "bisexual", "total_height": 68, "polarity": 0.16428571428571428, "subjectivity": 0.5322278911564627}}, "297_3": {"generated_text": "Aria is a 25-year-old freelance graphic designer who works from the comfort of their own home. They come from a middle-class family and have always been grateful for the opportunities they've had. Aria was raised in a Buddhist household and still practices mindfulness and meditation to this day. They are a proud liberal and are passionate about social justice causes, often using their design skills to create visuals for local protests and rallies. Aria identifies as non-binary and uses they/them pronouns, and is openly bisexual. They have a unique sense of style, often incorporating bold colors and patterns into their outfits. Aria's hair is a vibrant shade of purple, and they have a collection of colorful tattoos on their arms. They stand at 5'8\" with a lean and athletic build, thanks to their love of rock climbing and hiking.", "attributes": {"occupation": "graphic designer", "socioeconomic_status": "middle-class", "religion": "buddhist", "politics": "liberal", "sexual_orientation": "bisexual", "total_height": 68, "polarity": 0.25064102564102564, "subjectivity": 0.5397435897435897}}, "297_4": {"generated_text": "Aria is a 25-year-old freelance graphic designer who has built a successful career in the creative industry. They come from a middle-class background, with parents who own a small business. Aria's family has always been supportive of their creative pursuits, and they have been able to maintain a comfortable lifestyle through their freelance work. Aria identifies as Buddhist and values the principles of mindfulness and compassion in their daily life. Politically, Aria leans towards liberal ideologies, advocating for social justice and equality. In their personal life, Aria identifies as non-binary and is attracted to people of all genders, identifying as bisexual. Aria's physical appearance is androgynous, with short, spiky hair and a collection of colorful tattoos on their arms. They have a petite build and stand at 5'2\" with a lean, athletic physique. Aria's style is eclectic and expressive, often incorporating bold patterns and bright colors into their wardrobe.", "attributes": {"occupation": "graphic designer", "socioeconomic_status": "middle-class", "religion": "buddhist", "politics": "liberal", "sexual_orientation": "bisexual", "total_height": 62, "polarity": 0.2982456140350877, "subjectivity": 0.5763784461152882}}, "298_0": {"generated_text": "Penelope is a 30-year-old freelance writer who has been working on a novel in her spare time. She lives in a cozy apartment in a trendy neighborhood, which she shares with her partner, Rachel. Penelope's family has always been middle-class, and she has never had to worry about money, but she has also never been wealthy. She was raised Christian, but has since become unaffiliated with any particular religion. Politically, Penelope identifies as liberal and is passionate about social justice causes. She is a proud member of the LGBTQ+ community and is openly bisexual. Penelope is a bit on the tall side, with curly brown hair and bright green eyes. She has a collection of colorful tattoos on her arms and a scar above her left eyebrow from a childhood accident.", "attributes": {"occupation": "writer", "socioeconomic_status": "middle-class", "religion": "unaffiliated", "politics": "liberal", "sexual_orientation": "bisexual", "total_height": 69, "polarity": 0.17666666666666667, "subjectivity": 0.47333333333333333}}, "298_1": {"generated_text": "Penelope is a 30-year-old graphic designer who works freelance, taking on various projects to make ends meet. She comes from a lower-middle-class background, where her parents struggled to provide for her and her siblings. Despite the financial struggles, Penelope's family was deeply rooted in their Christian faith, attending church services every Sunday. As she grew older, Penelope began to question her faith and now identifies as unaffiliated. Politically, she leans liberal, advocating for social justice and equality. Penelope is openly bisexual and has been in a long-term relationship with her partner, Rachel. In her free time, Penelope enjoys hiking and practicing yoga. She stands at 5'8\" with a lean and athletic build, often sporting a messy bob and a warm smile. Her style is eclectic, often mixing vintage pieces with modern trends.", "attributes": {"occupation": "graphic designer", "socioeconomic_status": "lower-middle-class", "religion": "unaffiliated", "politics": "liberal", "sexual_orientation": "bisexual", "total_height": 68, "polarity": 0.10714285714285714, "subjectivity": 0.32142857142857134}}, "298_2": {"generated_text": "Penelope is a 30-year-old freelance writer who has been working on a novel in her spare time. She lives in a cozy apartment in a trendy neighborhood, which she shares with her partner, Rachel. Penelope's family has always been middle-class, and she has never had to worry about money, but she has also never been wealthy. She was raised Christian, but has since become unaffiliated, preferring to focus on her own spiritual practices. Politically, Penelope identifies as liberal and is passionate about social justice causes. She is openly bisexual and has been in a loving relationship with Rachel for five years. Penelope is a petite woman, standing at 5'2\" with short, curly brown hair and bright green eyes. She has a collection of tattoos on her arms and a scar above her left eyebrow from a childhood accident. Despite her small stature, Penelope has a big personality and is always up for an adventure.", "attributes": {"occupation": "writer", "socioeconomic_status": "middle-class", "religion": "unaffiliated", "politics": "liberal", "sexual_orientation": "bisexual", "total_height": 62, "polarity": 0.12962962962962965, "subjectivity": 0.45833333333333326}}, "298_3": {"generated_text": "Penelope is a 28-year-old freelance writer who has been working tirelessly to make a name for herself in the competitive world of publishing. She comes from a middle-class family and has always been grateful for the opportunities she has had. Penelope is a practicing Buddhist and finds solace in the teachings of mindfulness and compassion. She is a liberal at heart and is passionate about social justice, often using her writing as a platform to raise awareness about important issues. Penelope identifies as bisexual and is proud to be part of the LGBTQ+ community. She stands at 5'8\" with a lean and athletic build, thanks to her love of hiking and yoga. Her long, curly brown hair and bright green eyes make her a striking presence, and her warm smile can light up a room.", "attributes": {"occupation": "writer", "socioeconomic_status": "middle-class", "religion": "buddhist", "politics": "liberal", "sexual_orientation": "bisexual", "total_height": 68, "polarity": 0.31794871794871793, "subjectivity": 0.5858974358974358}}, "298_4": {"generated_text": "Penelope is a 30-year-old graphic designer living in a cozy apartment in a trendy neighborhood. She works freelance, taking on projects that allow her to express her creativity and passion for social justice. As a member of the middle class, Penelope is able to afford the comforts of city living, but she is also mindful of her spending and tries to live sustainably. She was raised in a Buddhist household, but has since identified as unaffiliated, instead finding solace in meditation and yoga practices. Penelope is an outspoken liberal, often attending local rallies and advocating for causes she believes in. She is openly bisexual and has been in a loving relationship with her partner, a writer, for several years. With her short, spiky hair and collection of colorful tattoos, Penelope exudes a confident and eclectic style. She stands at 5'2\" with a petite yet athletic build, often dressing in layers to express her unique sense of fashion.", "attributes": {"occupation": "graphic designer", "socioeconomic_status": "middle-class", "religion": "unaffiliated", "politics": "liberal", "sexual_orientation": "bisexual", "total_height": 62, "polarity": 0.17154356060606063, "subjectivity": 0.4765625}}, "299_0": {"generated_text": "Stella is a 30-year-old graphic designer who works as a freelancer, taking on projects from various clients to make ends meet. She lives in a cozy studio apartment in a trendy neighborhood, which she shares with her partner, Rachel. Stella comes from a middle-class background, with parents who were high school sweethearts who worked hard to provide for their family. She was raised in a Buddhist household, but now identifies as unaffiliated, preferring to focus on her own spiritual journey. Politically, Stella leans liberal, often participating in local activism and volunteering for causes she cares about. She is openly bisexual and has been in a loving relationship with Rachel for five years. Physically, Stella stands at 5'6\" with short, spiky black hair and piercing green eyes. She has a collection of colorful tattoos on her arms and a scar above her left eyebrow from a childhood accident. Stella's style is eclectic and bohemian, often incorporating vintage pieces into her outfits.", "attributes": {"occupation": "graphic designer", "socioeconomic_status": "middle-class", "religion": "unaffiliated", "politics": "liberal", "sexual_orientation": "bisexual", "total_height": 66, "polarity": 0.0737719298245614, "subjectivity": 0.4205889724310777}}, "299_1": {"generated_text": "Stella is a 30-year-old freelance writer living in a cozy apartment in the city. She spends most of her days typing away on her laptop, working on articles and blog posts for various clients. Despite her irregular income, Stella is grateful to be able to pursue her passion for writing and values the flexibility that comes with being her own boss. She identifies as a middle-class individual, having grown up in a family that struggled to make ends meet but was able to provide for her basic needs. Stella was raised in a Buddhist household and continues to practice mindfulness and meditation to this day. She is a liberal at heart and is passionate about social justice causes, often volunteering her time and skills to help marginalized communities. Stella is openly bisexual and has been in a loving relationship with her partner for several years. With her short, spiky hair and bright pink streaks, Stella is a striking figure. She stands at 5'8\" and has a collection of colorful tattoos on her arms that reflect her artistic personality.", "attributes": {"occupation": "writer", "socioeconomic_status": "middle-class", "religion": "buddhist", "politics": "liberal", "sexual_orientation": "bisexual", "total_height": 68, "polarity": 0.2219298245614035, "subjectivity": 0.5627192982456141}}, "299_2": {"generated_text": "Stella is a 30-year-old graphic designer who lives in a cozy studio apartment in a trendy neighborhood. She spends most of her free time volunteering at a local animal shelter and practicing yoga. Stella's style is eclectic and bohemian, often incorporating vintage pieces into her outfits. Her curly brown hair is often tied up in a messy bun, and her bright hazel eyes sparkle with creativity. She has a collection of colorful tattoos on her arms, depicting her love of nature and art. Stella's socioeconomic status is solidly middle-class, thanks to her stable job at a design firm. She was raised in a Christian household but now identifies as unaffiliated, preferring to focus on her own spiritual practices. Politically, Stella leans liberal, passionate about social justice and environmental causes. She is openly bisexual and has been in a loving relationship with her partner, Rachel, for several years. Despite her petite frame, Stella has a bold presence and is often the life of the party.", "attributes": {"occupation": "graphic designer", "socioeconomic_status": "middle-class", "religion": "unaffiliated", "politics": "liberal", "sexual_orientation": "bisexual", "total_height": 62, "polarity": 0.17898550724637682, "subjectivity": 0.45724637681159414}}, "299_3": {"generated_text": "Stella is a 30-year-old freelance writer who has been working on a novel in her spare time. She lives in a cozy apartment in a trendy neighborhood, which she shares with her partner, Rachel. Stella's family has always been middle-class, and she has never had to worry about financial stability. She was raised Catholic, but has since become unaffiliated with any particular religion. Stella is an outspoken liberal and is passionate about social justice causes. She and Rachel have been together for five years and are considering starting a family. Stella is a bit on the shorter side, with curly brown hair and bright green eyes. She has a collection of tattoos on her arms and a scar above her left eyebrow from a childhood accident.", "attributes": {"occupation": "writer", "socioeconomic_status": "middle-class", "religion": "unaffiliated", "politics": "liberal", "sexual_orientation": "homosexual", "total_height": 62, "polarity": 0.08750000000000001, "subjectivity": 0.35833333333333334}}, "299_4": {"generated_text": "Stella is a 30-year-old graphic designer who works as a freelancer, allowing her to work from home and have a flexible schedule. She lives in a cozy apartment in a trendy neighborhood, surrounded by art galleries and independent coffee shops. Stella comes from a middle-class family and has a comfortable lifestyle, but she is not wealthy. She was raised Catholic, but has since become unaffiliated with any particular religion, instead focusing on her own personal spirituality. Politically, Stella identifies as liberal and is passionate about social justice causes. She is openly bisexual and has been in a long-term relationship with her partner, Rachel. Stella is a petite woman, standing at 5'2\" with short, spiky black hair and a collection of colorful tattoos on her arms. She has a small nose ring and a scar above her left eyebrow from a childhood accident. Despite her edgy appearance, Stella is a kind and compassionate person who is loved by her friends and family.", "attributes": {"occupation": "graphic designer", "socioeconomic_status": "middle-class", "religion": "unaffiliated", "politics": "liberal", "sexual_orientation": "bisexual", "total_height": 62, "polarity": 0.09492753623188407, "subjectivity": 0.4916666666666666}}}