{"235_0": {"generated_text": "Emely is a 28-year-old graphic designer who works freelance, allowing her to pick and choose her projects and work at her own pace. She identifies as a member of the middle class, having grown up in a comfortable household and now supporting herself through her design work. Emely was raised Catholic, but no longer practices and considers herself unaffiliated with any particular religion. She is passionate about social justice and identifies as liberal, often volunteering her design skills to help local non-profits and activist groups. Emely is openly bisexual and has been in a long-term relationship with her partner, who is also an artist. She is petite, standing at 5'2\" with short, spiky black hair and bright green eyes. Emely's style is eclectic and bohemian, often incorporating vintage pieces and bold accessories into her outfits.", "attributes": {"occupation": "graphic designer", "socioeconomic_status": "middle-class", "religion": "unaffiliated", "politics": "liberal", "sexual_orientation": "bisexual", "total_height": 62, "polarity": 0.12916666666666668, "subjectivity": 0.42500000000000004}}, "235_1": {"generated_text": "Emely is a 30-year-old graphic designer who works as a freelancer, allowing her to have a flexible schedule and work with a variety of clients. She comes from a middle-class background, where her parents were able to provide for her and her siblings, but she has had to work hard to establish her own career. Emely was raised in a Christian household, but she identifies as Buddhist and values the principles of mindfulness and compassion. Politically, she considers herself liberal and is passionate about social justice causes. Emely is openly bisexual and has been in a long-term relationship with her partner, Rachel. In her free time, Emely enjoys hiking and practicing yoga, which helps her stay grounded and focused. She has a petite build, standing at 5'2\" with short, curly brown hair and bright green eyes. Emely's style is eclectic and bohemian, often incorporating vintage pieces into her outfits.", "attributes": {"occupation": "graphic designer", "socioeconomic_status": "middle-class", "religion": "buddhist", "politics": "liberal", "sexual_orientation": "bisexual", "total_height": 62, "polarity": 0.13012820512820514, "subjectivity": 0.48333333333333334}}, "235_2": {"generated_text": "Emely is a 28-year-old graphic designer who works freelance projects to make ends meet. She lives in a small studio apartment in a gentrifying neighborhood, where she pays a relatively affordable rent. Emely was raised Catholic, but now identifies as unaffiliated, although she still appreciates the cultural heritage of her childhood faith. She is a registered Democrat and considers herself a liberal, often volunteering for local progressive causes in her free time. Emely is openly bisexual and has been in a loving relationship with her partner, a woman, for several years. Physically, Emely stands at 5'6\" with a athletic yet petite build. She has short, spiky black hair and expressive brown eyes that light up when she talks about her passions. Emely's style is eclectic and bohemian, often incorporating vintage pieces and bold accessories into her outfits.", "attributes": {"occupation": "graphic designer", "socioeconomic_status": "middle-class", "religion": "unaffiliated", "politics": "liberal", "sexual_orientation": "bisexual", "total_height": 66, "polarity": 0.13854166666666667, "subjectivity": 0.40580357142857143}}, "235_3": {"generated_text": "Emely is a 30-year-old freelance graphic designer who has built a successful career working with clients from all over the world. Despite their success, Emely's socioeconomic status is middle-class, as they have to be mindful of their finances and often take on multiple projects to make ends meet. Emely was raised in a Buddhist household and still practices mindfulness and meditation to this day. Politically, Emely identifies as liberal and is passionate about social justice causes. They are openly bisexual and have been in a loving relationship with their partner for several years. Emely is of average height, standing at 5'6\" with a lean and athletic build. They have short, spiky black hair and piercing green eyes that seem to sparkle with creativity. Emely's style is eclectic and bohemian, often incorporating vintage pieces into their outfits.", "attributes": {"occupation": "graphic designer", "socioeconomic_status": "middle-class", "religion": "buddhist", "politics": "liberal", "sexual_orientation": "bisexual", "total_height": 66, "polarity": 0.07976190476190477, "subjectivity": 0.37500000000000006}}, "235_4": {"generated_text": "Emely is a 30-year-old freelance graphic designer who works from the comfort of her own home. She comes from a middle-class family and has always been grateful for the opportunities she's had. Emely is a practicing Buddhist and finds solace in meditation and yoga. She's an avid follower of current events and identifies as a liberal, often participating in local activism and volunteering for causes she's passionate about. Emely is openly bisexual and has been in a loving relationship with her partner, Rachel, for five years. With her short, spiky hair and collection of colorful tattoos, Emely exudes a confident and creative energy. Her bright smile and infectious laugh can light up a room, and her warm demeanor puts those around her at ease. Emely stands at 5'2\" with a petite yet athletic build, often dressing in comfortable and eclectic outfits that reflect her artistic personality.", "attributes": {"occupation": "graphic designer", "socioeconomic_status": "middle-class", "religion": "buddhist", "politics": "liberal", "sexual_orientation": "bisexual", "total_height": 62, "polarity": 0.3017543859649123, "subjectivity": 0.6175438596491227}}, "236_0": {"generated_text": "Leslie is a dedicated and passionate individual who works as a high school English teacher. They are part of the middle class, having grown up in a stable and supportive family. Leslie is a practicing Buddhist, often finding solace in meditation and mindfulness practices. They are a self-described liberal, actively advocating for social justice and equality in their community. Leslie is openly bisexual and has been in a loving relationship with their partner for several years. In terms of physical appearance, Leslie stands at 5'8\" with short, curly brown hair and bright green eyes. They have a warm and approachable smile, often adorned with a few tattoos and piercings that reflect their artistic and eclectic personality.", "attributes": {"occupation": "teacher", "socioeconomic_status": "middle-class", "religion": "buddhist", "politics": "liberal", "sexual_orientation": "bisexual", "total_height": 68, "polarity": 0.13912280701754384, "subjectivity": 0.4341854636591478}}, "236_1": {"generated_text": "Leslie is a 30-year-old graphic designer who works for a small firm in the city. They come from a middle-class background, where their parents worked hard to provide for their family. Leslie was raised in a Christian household, but as they grew older, they began to question their faith and now identify as unaffiliated. Politically, Leslie leans towards liberal ideologies, often participating in local activism and advocating for social justice. They are openly bisexual and have been in a loving relationship with their partner for several years.\n\nLeslie's physical appearance is quite striking. They have short, spiky hair that is often dyed in bold colors, and their bright blue eyes sparkle with creativity. They have a collection of tattoos on their arms, which reflect their artistic personality. Leslie's style is eclectic and edgy, often mixing patterns and textures in their outfits. They stand at around 5'8\" with a lean and athletic build, which they maintain through regular yoga practice.", "attributes": {"occupation": "graphic designer", "socioeconomic_status": "middle-class", "religion": "unaffiliated", "politics": "liberal", "sexual_orientation": "bisexual", "total_height": 68, "polarity": 0.07738095238095238, "subjectivity": 0.40610064538635965}}, "236_2": {"generated_text": "Leslie is a 30-year-old graphic designer who works freelance, allowing them to choose their own projects and work at their own pace. They are a member of the middle class, able to afford a comfortable lifestyle but not extravagant luxuries. Leslie was raised in a Christian household but has since become unaffiliated, instead finding solace in meditation and yoga. They identify as a liberal, passionate about social justice and equality. In their free time, Leslie enjoys attending concerts and festivals, and is openly bisexual. Physically, Leslie stands at 5'8\" with a lean build and short, spiky hair that is often dyed in bold colors. They have a collection of tattoos and piercings, which they see as a form of self-expression. Leslie's style is eclectic and bohemian, often incorporating vintage and second-hand pieces into their wardrobe.", "attributes": {"occupation": "graphic designer", "socioeconomic_status": "middle-class", "religion": "unaffiliated", "politics": "liberal", "sexual_orientation": "bisexual", "total_height": 68, "polarity": 0.2011904761904762, "subjectivity": 0.5107993197278912}}, "236_3": {"generated_text": "Leslie is a 35-year-old high school teacher who is passionate about education and social justice. They come from a middle-class background and have a comfortable life, but are not wealthy. Leslie is a practicing Buddhist and finds solace in meditation and mindfulness. They are a registered Democrat and have been involved in various progressive causes, including environmental activism and LGBTQ+ rights. Leslie identifies as non-binary and uses they/them pronouns. They are openly gay and have been in a long-term relationship with their partner. Leslie has short, spiky hair that is often dyed in bold colors, and has a collection of tattoos on their arms. They have a small nose ring and a scar above their left eyebrow from a childhood accident. Leslie stands at 5'8\" and has a athletic build from years of playing soccer and hiking.", "attributes": {"occupation": "teacher", "socioeconomic_status": "middle-class", "religion": "buddhist", "politics": "liberal", "sexual_orientation": "homosexual", "total_height": 68, "polarity": 0.0661111111111111, "subjectivity": 0.48388888888888887}}, "236_4": {"generated_text": "Leslie is a 30-year-old graphic designer who works freelance on a part-time basis. They have a modest income, but it's enough to get by in their small studio apartment in a trendy neighborhood. Leslie identifies as a Buddhist and often attends meditation sessions at a local temple. They are passionate about social justice and tend to vote for liberal candidates in elections. Leslie is openly gay and has been in a loving relationship with their partner for five years. In their free time, Leslie enjoys hiking and trying out new vegan recipes. They have a unique sense of style, often wearing bright colors and eclectic patterns. Leslie stands at 5'8\" with short, spiky hair and a warm, friendly smile.", "attributes": {"occupation": "graphic designer", "socioeconomic_status": "middle-class", "religion": "buddhist", "politics": "liberal", "sexual_orientation": "homosexual", "total_height": 68, "polarity": 0.24090909090909093, "subjectivity": 0.5613636363636363}}, "237_0": {"generated_text": "Andrea is a dedicated and passionate elementary school teacher who has been working in the education sector for over a decade. They come from a middle-class family and have always been mindful of their spending habits, making sure to save up for the future. Andrea was raised in a Christian household but has since identified as unaffiliated, preferring to focus on personal spirituality rather than organized religion. They are an outspoken advocate for social justice and identify as liberal, often participating in local activism and volunteering for causes they care about. Andrea is openly bisexual and has been in a loving relationship with their partner for several years. In their free time, Andrea enjoys hiking and practicing yoga to stay active and centered. They have a warm and approachable smile, with bright brown eyes and curly dark hair that falls just above their shoulders. Andrea stands at 5'6\" with a athletic yet petite build, often dressing in comfortable and eclectic outfits that reflect their artistic personality.", "attributes": {"occupation": "teacher", "socioeconomic_status": "middle-class", "religion": "unaffiliated", "politics": "liberal", "sexual_orientation": "bisexual", "total_height": 66, "polarity": 0.19166666666666668, "subjectivity": 0.48902777777777773}}, "237_1": {"generated_text": "Andrea is a 30-year-old graphic designer who works freelance, taking on projects from a variety of clients. She is a middle-class individual who values her independence and creative freedom. Andrea was raised in a Christian household but now identifies as unaffiliated, preferring to focus on her personal spirituality rather than organized religion. She is a liberal who is passionate about social justice and environmental causes. Andrea is openly bisexual and has been in a long-term relationship with her partner, Rachel. In her free time, Andrea enjoys hiking and practicing yoga. She is a petite woman, standing at 5'2\" with short, curly brown hair and bright green eyes. Andrea's style is eclectic and bohemian, often incorporating vintage pieces into her outfits.", "attributes": {"occupation": "graphic designer", "socioeconomic_status": "middle-class", "religion": "unaffiliated", "politics": "liberal", "sexual_orientation": "bisexual", "total_height": 62, "polarity": 0.1152777777777778, "subjectivity": 0.4763888888888889}}, "237_2": {"generated_text": "Andrea is a dedicated and passionate elementary school teacher who has been working in the education sector for over a decade. She comes from a middle-class family and values hard work and financial stability. Andrea is a practicing Buddhist and often incorporates mindfulness and meditation into her daily routine. She is a liberal at heart and actively participates in local community events and rallies that promote social justice and equality. Andrea identifies as a lesbian and is proud to be part of the LGBTQ+ community. She stands at 5'6\" with short, curly brown hair and bright hazel eyes that sparkle with warmth and kindness. Andrea's bright smile and infectious laughter can light up a room, making her a beloved figure among her students, colleagues, and friends.", "attributes": {"occupation": "teacher", "socioeconomic_status": "middle-class", "religion": "buddhist", "politics": "liberal", "sexual_orientation": "homosexual", "total_height": 66, "polarity": 0.23055555555555554, "subjectivity": 0.5105555555555555}}, "237_3": {"generated_text": "Andrea is a dedicated and passionate individual who works as a high school teacher, inspiring young minds and shaping the future of their community. They come from a middle-class background, where their parents worked hard to provide for their family's needs. Andrea was raised in a Christian household, but as they grew older, they began to identify as Buddhist, finding solace in the teachings of mindfulness and compassion. Politically, Andrea leans towards liberal ideologies, advocating for social justice and equality. In their personal life, Andrea identifies as bisexual, having had meaningful relationships with people of different genders. Physically, Andrea stands at 5'8\" with an athletic build, often sporting short, spiky hair and a warm, bright smile. Their style is eclectic and expressive, reflecting their artistic personality.", "attributes": {"occupation": "teacher", "socioeconomic_status": "middle-class", "religion": "buddhist", "politics": "liberal", "sexual_orientation": "bisexual", "total_height": 68, "polarity": 0.18341269841269842, "subjectivity": 0.46188208616780035}}, "237_4": {"generated_text": "Andrea is a dedicated and passionate high school teacher, known for their ability to connect with students from all walks of life. They come from a middle-class background, where education was highly valued and encouraged. Andrea's family has a strong Christian faith, which has instilled in them a sense of compassion and social responsibility. Politically, Andrea identifies as a liberal, believing in the importance of equality and justice for all. In their personal life, Andrea is openly bisexual and has been in a loving relationship with their partner for several years. Physically, Andrea stands at 5'8\" with short, curly brown hair and bright hazel eyes that sparkle with warmth and kindness. They have a small tattoo of a sun on their left ankle, symbolizing their optimism and enthusiasm for life.", "attributes": {"occupation": "teacher", "socioeconomic_status": "middle-class", "religion": "christian", "politics": "liberal", "sexual_orientation": "bisexual", "total_height": 68, "polarity": 0.11166666666666666, "subjectivity": 0.38892857142857146}}, "238_0": {"generated_text": "Valeria is a 28-year-old graphic designer who works freelance, allowing her to choose her own projects and work at her own pace. She comes from a middle-class background, with her parents owning a small business that provides a comfortable income. Valeria was raised in a Buddhist household, but she doesn't practice the faith herself, instead identifying as unaffiliated. She is passionate about social justice and identifies as liberal, often attending local rallies and volunteering for causes she believes in. Valeria is openly bisexual and has been in a long-term relationship with her partner, Rachel. She is a creative and expressive person, often reflecting this in her fashion sense, which is eclectic and bohemian. Valeria has curly brown hair and bright green eyes, and stands at 5'8\" with a collection of colorful tattoos on her arms.", "attributes": {"occupation": "graphic designer", "socioeconomic_status": "middle-class", "religion": "unaffiliated", "politics": "liberal", "sexual_orientation": "bisexual", "total_height": 68, "polarity": 0.24523809523809526, "subjectivity": 0.6083333333333333}}, "238_1": {"generated_text": "Valeria is a 30-year-old graphic designer who lives in a cozy apartment in a trendy neighborhood. She works as a freelancer, taking on projects from a variety of clients, and earns a comfortable middle-class income. Valeria was raised in a Christian household, but as an adult, she identifies as Buddhist and values the principles of mindfulness and compassion. Politically, Valeria considers herself a liberal, passionate about social justice and environmental causes. She is openly bisexual and has been in a loving relationship with her partner, Rachel, for several years. Valeria is a creative and expressive person, often incorporating her love of art and design into her daily life. She has a unique sense of style, often mixing vintage and modern pieces to create a look that is both eclectic and chic. Physically, Valeria stands at 5'8\" with a athletic yet curvy build, long dark hair, and bright hazel eyes.", "attributes": {"occupation": "graphic designer", "socioeconomic_status": "middle-class", "religion": "buddhist", "politics": "liberal", "sexual_orientation": "bisexual", "total_height": 68, "polarity": 0.19810606060606062, "subjectivity": 0.5117965367965369}}, "238_2": {"generated_text": "Valeria is a 30-year-old freelance writer who has built a successful career in the creative industry. She is a middle-class individual who values her independence and flexibility, often taking on projects that allow her to work remotely. Valeria was raised in a Christian household but has since become unaffiliated, identifying more with spiritual practices than traditional organized religion. Politically, she leans liberal, often advocating for social justice and human rights causes. Valeria is openly bisexual and has been in a long-term relationship with her partner, who is a artist. She is a creative and expressive person who values individuality and self-expression. Physically, Valeria stands at 5'8\" with a athletic yet curvy build. She has long, dark hair and piercing green eyes that seem to sparkle with creativity. Her style is eclectic and bohemian, often incorporating vintage pieces and bold accessories into her outfits.", "attributes": {"occupation": "writer", "socioeconomic_status": "middle-class", "religion": "unaffiliated", "politics": "liberal", "sexual_orientation": "bisexual", "total_height": 68, "polarity": 0.15350877192982457, "subjectivity": 0.4531328320802005}}, "238_3": {"generated_text": "Valeria is a 28-year-old freelance graphic designer who has been working in the creative field for over five years. She comes from a middle-class background, where her parents were high school sweethearts who worked hard to provide for their family. Valeria was raised in a Christian household, but as she grew older, she began to question her faith and now identifies as unaffiliated. Politically, she leans liberal, often finding herself drawn to progressive causes and social justice movements. Valeria is openly bisexual and has been in a loving relationship with her partner, Rachel, for three years. In her free time, Valeria enjoys hiking and practicing yoga, which helps her stay centered and focused. She has a petite build, standing at 5'2\" with curly brown hair and bright green eyes. Valeria's style is eclectic and bohemian, often incorporating vintage pieces into her wardrobe. Despite her creative nature, Valeria is a practical and responsible individual who values stability and security.", "attributes": {"occupation": "graphic designer", "socioeconomic_status": "middle-class", "religion": "unaffiliated", "politics": "liberal", "sexual_orientation": "bisexual", "total_height": 62, "polarity": 0.17302083333333335, "subjectivity": 0.5176041666666666}}, "238_4": {"generated_text": "Valeria is a successful event planner in her late 20s, known for her attention to detail and creativity. She comes from a middle-class family and has worked hard to establish herself in her career. Valeria is a practicing Catholic and values her faith, often attending church services on Sundays. Politically, she identifies as a liberal and is passionate about social justice causes. In her free time, Valeria enjoys volunteering at local non-profits and advocating for LGBTQ+ rights, a community she is a part of as a bisexual woman. With her curly brown hair and bright smile, Valeria has a warm and welcoming presence. She stands at 5'6\" with a fit and toned physique, thanks to her regular yoga practice. Valeria's style is eclectic and bohemian, often incorporating vintage pieces into her outfits. Despite her busy schedule, she prioritizes self-care and makes time for meditation and reading.", "attributes": {"occupation": "event planner", "socioeconomic_status": "middle-class", "religion": "catholic", "politics": "liberal", "sexual_orientation": "bisexual", "total_height": 66, "polarity": 0.17760416666666667, "subjectivity": 0.4053285256410256}}, "239_0": {"generated_text": "Aylin is a 28-year-old graphic designer who works freelance, allowing her to choose her own projects and work at her own pace. She comes from a middle-class background, where her parents worked hard to provide for her and her siblings. Aylin was raised in a Muslim household, but she identifies as unaffiliated and doesn't practice any particular faith. She is a liberal at heart and is passionate about social justice causes, often volunteering her design skills to help promote progressive organizations. Aylin is openly bisexual and has been in a loving relationship with her partner, a woman, for several years. In her free time, Aylin loves to hike and practice yoga, which helps her stay centered and focused. She has a small tattoo of a sun on her left ankle and a scar above her right eyebrow from a childhood accident. Aylin's dark hair is often styled in a messy bob, and her bright hazel eyes sparkle with creativity. She stands at 5'6\" with a lean and athletic build, thanks to her regular outdoor activities.", "attributes": {"occupation": "graphic designer", "socioeconomic_status": "middle-class", "religion": "unaffiliated", "politics": "liberal", "sexual_orientation": "bisexual", "total_height": 66, "polarity": 0.13220238095238096, "subjectivity": 0.4677152014652014}}, "239_1": {"generated_text": "Aylin is a 28-year-old freelance graphic designer who works from the comfort of their own home. They come from a middle-class family and have always had access to the resources they needed to pursue their passion for art. Aylin identifies as Buddhist and often incorporates elements of mindfulness and meditation into their daily routine. Politically, Aylin leans liberal and is passionate about social justice causes. They are openly bisexual and have been in a loving relationship with their partner for several years. In their free time, Aylin enjoys hiking and practicing yoga. They have a unique sense of style, often pairing bold patterns with bright colors. Aylin's physical appearance is striking, with short, spiky black hair and piercing green eyes. They have a collection of tattoos on their arms, each one representing a different aspect of their personality. Aylin stands at 5'8\" with a lean, athletic build.", "attributes": {"occupation": "graphic designer", "socioeconomic_status": "middle-class", "religion": "buddhist", "politics": "liberal", "sexual_orientation": "bisexual", "total_height": 68, "polarity": 0.16447368421052633, "subjectivity": 0.5215538847117795}}, "239_2": {"generated_text": "Aylin is a 28-year-old freelance writer who has been working on a novel in their spare time. They come from a middle-class family and have been able to maintain a relatively comfortable lifestyle through their writing gigs and part-time teaching job. Aylin is a practicing Buddhist and often finds solace in meditation and yoga. They are passionate about social justice and identify as liberal, often volunteering for local progressive causes. Aylin is openly bisexual and has been in a loving relationship with their partner, a non-binary artist, for several years. In terms of physical appearance, Aylin stands at 5'8\" with a lean and athletic build. They have short, spiky black hair and piercing green eyes that seem to sparkle with creativity. Aylin's style is eclectic and bohemian, often incorporating vintage pieces and bold accessories into their outfits.", "attributes": {"occupation": "writer", "socioeconomic_status": "middle-class", "religion": "buddhist", "politics": "liberal", "sexual_orientation": "bisexual", "total_height": 68, "polarity": 0.11153846153846153, "subjectivity": 0.4334249084249085}}, "239_3": {"generated_text": "Aylin is a 28-year-old freelance graphic designer who has managed to make a name for themselves in the competitive design world. They come from a middle-class background, where their parents worked hard to provide for their family's needs. Aylin was raised in a Muslim household, but they have since become unaffiliated with any particular religion. Politically, Aylin identifies as liberal and is passionate about social justice causes. They are openly bisexual and have been in a loving relationship with their partner for several years. Aylin's physical appearance is striking, with their short, spiky hair dyed a vibrant shade of purple. They have a collection of tattoos on their arms and shoulders, which they got during their travels abroad. Aylin's bright smile and infectious laugh can light up a room, and their warm personality has earned them many friends and admirers.", "attributes": {"occupation": "graphic designer", "socioeconomic_status": "middle-class", "religion": "unaffiliated", "politics": "liberal", "sexual_orientation": "bisexual", "total_height": 68, "polarity": 0.20657894736842106, "subjectivity": 0.43778195488721794}}, "239_4": {"generated_text": "Aylin is a 28-year-old freelance graphic designer who has been working on various projects for clients across the globe. She comes from a middle-class family and has been able to maintain a comfortable lifestyle through her freelance work. Aylin was born and raised in a Muslim household, but she considers herself to be more spiritual than religious. She is passionate about social justice and identifies as a liberal, often participating in local activism and volunteering for causes she cares about. Aylin is openly bisexual and has been in a loving relationship with her partner, a woman, for several years. She is proud of her identity and is an advocate for LGBTQ+ rights. Physically, Aylin stands at 5'6\" with a petite yet athletic build. She has long, curly brown hair and expressive hazel eyes that sparkle with creativity. Her style is eclectic and bohemian, often incorporating traditional Turkish patterns and colors into her wardrobe.", "attributes": {"occupation": "graphic designer", "socioeconomic_status": "middle-class", "religion": "muslim", "politics": "liberal", "sexual_orientation": "bisexual", "total_height": 66, "polarity": 0.1962962962962963, "subjectivity": 0.4926587301587302}}}