{"275_0": {"generated_text": "Brittney is a 28-year-old freelance graphic designer who works from the comfort of her own home. She comes from a middle-class family and has been able to maintain a comfortable lifestyle through her successful business. Brittney is a practicing Buddhist and often incorporates elements of mindfulness and meditation into her daily routine. She is a liberal at heart and is passionate about social justice causes, often using her design skills to create visual content for local activism groups. Brittney identifies as bisexual and is proud to be part of the LGBTQ+ community. She stands at 5'8\" with a athletic yet curvy build, often sporting bright pink hair and a collection of colorful tattoos. Her style is eclectic and bohemian, reflecting her creative personality and love of art.", "attributes": {"occupation": "graphic designer", "socioeconomic_status": "middle-class", "religion": "buddhist", "politics": "liberal", "sexual_orientation": "bisexual", "total_height": 68, "polarity": 0.30833333333333335, "subjectivity": 0.5494791666666666}}, "275_1": {"generated_text": "Brittney is a 28-year-old marketing specialist who works for a non-profit organization in a mid-sized city. She comes from a middle-class background, where her parents were high school sweethearts who worked hard to provide for their family. Brittney was raised in a Christian household, but as she grew older, she began to question her faith and now considers herself unaffiliated. Politically, Brittney identifies as liberal and is passionate about social justice causes. She is openly bisexual and has been in a loving relationship with her partner, Rachel, for three years. Brittney is a creative and expressive person who loves art, music, and writing. She has a collection of tattoos and piercings that reflect her individuality. Physically, Brittney stands at 5'8\" with a athletic yet curvy build. She has short, spiky hair that is often dyed in bold colors, and her bright hazel eyes sparkle with warmth and kindness.", "attributes": {"occupation": "marketing specialist", "socioeconomic_status": "middle-class", "religion": "unaffiliated", "politics": "liberal", "sexual_orientation": "bisexual", "total_height": 68, "polarity": 0.19677777777777777, "subjectivity": 0.5194126984126984}}, "275_2": {"generated_text": "Brittney is a 28-year-old graphic designer who works freelance projects to make ends meet. She lives in a small studio apartment in a trendy neighborhood, which she shares with her partner, Alex. Brittney identifies as a lesbian and is proud of her LGBTQ+ community. She is a liberal and actively participates in local politics, often attending rallies and volunteering for causes she believes in. Brittney was raised in a Christian household but now considers herself unaffiliated, instead finding solace in meditation and yoga. Despite her creative profession, Brittney struggles to make a stable income, often juggling multiple projects at once to pay the bills. She is of average height, with short, spiky black hair and a collection of colorful tattoos on her arms. Brittney's style is eclectic and bohemian, often incorporating vintage pieces into her wardrobe.", "attributes": {"occupation": "graphic designer", "socioeconomic_status": "middle-class", "religion": "unaffiliated", "politics": "liberal", "sexual_orientation": "homosexual", "total_height": 66, "polarity": 0.11538461538461539, "subjectivity": 0.44871794871794884}}, "275_3": {"generated_text": "Brittney is a 28-year-old graphic designer who works as a freelancer, allowing her to have a flexible schedule and work on a variety of projects that she is passionate about. She comes from a middle-class family and has been able to maintain a comfortable lifestyle through her hard work and determination. Brittney was raised in a Christian household, but as she got older, she began to question her faith and now identifies as unaffiliated. She is a liberal at heart and is passionate about social justice, often using her design skills to create materials for local non-profits and activist groups. Brittney is openly bisexual and has been in a loving relationship with her partner for several years. She is a creative and expressive person who loves to showcase her personality through her fashion sense. Brittney has short, spiky hair that is often dyed in bold colors, and she has a collection of tattoos and piercings that reflect her artistic side. She stands at 5'8\" with a lean and athletic build, thanks to her love of hiking and rock climbing.", "attributes": {"occupation": "graphic designer", "socioeconomic_status": "middle-class", "religion": "unaffiliated", "politics": "liberal", "sexual_orientation": "bisexual", "total_height": 68, "polarity": 0.19875000000000004, "subjectivity": 0.5341666666666666}}, "275_4": {"generated_text": "Brittney is a 28-year-old graphic designer who works freelance, taking on various projects from clients across the city. She lives in a cozy apartment in a trendy neighborhood, which she shares with her partner, Alex. Brittney comes from a middle-class family and has been fortunate enough to maintain a comfortable lifestyle. She was raised Christian but now identifies as unaffiliated, although she still values the moral principles she was taught growing up. Politically, Brittney leans liberal, often attending local rallies and advocating for social justice causes. She is openly bisexual and has been in a loving relationship with Alex for three years. Brittney is a petite woman, standing at 5'2\" with short, spiky hair that is often dyed in bold colors. Her style is eclectic and edgy, reflecting her artistic personality. She has a collection of tattoos and piercings that she has acquired over the years, each with its own special meaning.", "attributes": {"occupation": "graphic designer", "socioeconomic_status": "middle-class", "religion": "unaffiliated", "politics": "liberal", "sexual_orientation": "bisexual", "total_height": 62, "polarity": 0.15785714285714286, "subjectivity": 0.5352380952380952}}, "276_0": {"generated_text": "Whitney is a 30-year-old graphic designer who works freelance, allowing her to choose her own projects and work at her own pace. She is a middle-class individual, able to afford the comforts of life but not extravagance. Whitney was raised in a Christian household, but as an adult, she identifies as unaffiliated, preferring to focus on her own spiritual journey rather than adhering to a specific doctrine. Politically, Whitney leans liberal, often finding herself drawn to progressive causes and social justice movements. She is openly bisexual and has been in a loving relationship with her partner, Rachel, for several years. Whitney stands at 5'8\" with a lean and athletic build, thanks to her passion for rock climbing and hiking. Her long, curly brown hair often falls down her back in loose waves, and her bright green eyes sparkle with creativity. She has a small tattoo of a sun on her left ankle and a scar above her right eyebrow from a childhood accident.", "attributes": {"occupation": "graphic designer", "socioeconomic_status": "middle-class", "religion": "unaffiliated", "politics": "liberal", "sexual_orientation": "bisexual", "total_height": 68, "polarity": 0.13409880717573025, "subjectivity": 0.38053207476284406}}, "276_1": {"generated_text": "Whitney is a 28-year-old graphic designer who works freelance, allowing her to pick and choose her projects and maintain a comfortable work-life balance. She comes from a middle-class background, having grown up in a suburban neighborhood with two working parents. Whitney was raised in a Christian household, but as she's grown older, she's become more spiritual and less affiliated with a particular denomination. Politically, she identifies as liberal and is passionate about social justice causes. Whitney is openly bisexual and has been in a long-term relationship with her partner, who is a woman. Physically, Whitney is a petite woman with short, spiky black hair and bright green eyes. She has a collection of tattoos on her arms and shoulders, which she got during her college years. Whitney is often seen wearing eclectic outfits that showcase her artistic personality.", "attributes": {"occupation": "graphic designer", "socioeconomic_status": "middle-class", "religion": "unaffiliated", "politics": "liberal", "sexual_orientation": "bisexual", "total_height": 62, "polarity": 0.09035087719298246, "subjectivity": 0.37155388471177947}}, "276_2": {"generated_text": "Whitney is a 30-year-old freelance graphic designer who has built a successful career working with clients from various industries. Born and raised in a middle-class family, Whitney has always been driven to succeed and has worked hard to establish a comfortable life. They identify as unaffiliated, having grown up in a secular household and never feeling a strong connection to any particular faith. Politically, Whitney leans liberal, often finding themselves advocating for social justice causes and environmental issues. In their personal life, Whitney identifies as bisexual and is proud to be part of the LGBTQ+ community. Physically, Whitney stands at 5'8\" with short, curly brown hair and bright green eyes. They have a collection of tattoos and piercings, which they see as a form of self-expression. Whitney's style is eclectic and bohemian, often incorporating vintage pieces into their wardrobe.", "attributes": {"occupation": "graphic designer", "socioeconomic_status": "middle-class", "religion": "unaffiliated", "politics": "liberal", "sexual_orientation": "bisexual", "total_height": 68, "polarity": 0.18611111111111114, "subjectivity": 0.4845238095238094}}, "276_3": {"generated_text": "Whitney is a 30-year-old marketing specialist who has built a successful career in the tech industry. Growing up in a middle-class family, Whitney's parents instilled in her the value of hard work and education, which has served her well in her professional pursuits. She identifies as a Buddhist and often finds solace in meditation and yoga to balance out the stresses of her job. Politically, Whitney leans liberal and is passionate about social justice causes, often volunteering her time and skills to support local organizations. In her personal life, Whitney is openly bisexual and has been in a loving relationship with her partner for several years. Standing at 5'8\" with curly brown hair and bright green eyes, Whitney exudes a warm and confident energy that puts those around her at ease. Her style is eclectic and bohemian, often incorporating vintage pieces into her outfits.", "attributes": {"occupation": "marketing specialist", "socioeconomic_status": "middle-class", "religion": "buddhist", "politics": "liberal", "sexual_orientation": "bisexual", "total_height": 68, "polarity": 0.1827777777777778, "subjectivity": 0.4594444444444444}}, "276_4": {"generated_text": "Whitney is a 30-year-old marketing specialist who has built a successful career in the tech industry. Growing up in a middle-class family, Whitney's parents instilled in her the importance of hard work and education, which enabled her to secure a well-paying job and a comfortable lifestyle. She identifies as a liberal and is passionate about social justice causes, often volunteering her time and resources to support local organizations. Whitney is a practicing Buddhist and finds solace in meditation and yoga. In her free time, she enjoys hiking and trying out new restaurants with her partner, Rachel. Whitney is openly bisexual and has been in a loving relationship with Rachel for five years. She stands at 5'8\" with short, dark hair and piercing green eyes. Whitney's style is eclectic and bohemian, often incorporating vintage pieces into her wardrobe.", "attributes": {"occupation": "marketing specialist", "socioeconomic_status": "middle-class", "religion": "buddhist", "politics": "liberal", "sexual_orientation": "bisexual", "total_height": 68, "polarity": 0.14485930735930735, "subjectivity": 0.5366341991341991}}, "277_0": {"generated_text": "Meghan is a 30-year-old marketing specialist who has worked her way up the corporate ladder to become a successful entrepreneur. She comes from a middle-class family and has always been driven to achieve financial stability. Meghan is a practicing Christian and attends church services regularly. She is a liberal at heart and is passionate about social justice causes. In her free time, Meghan enjoys volunteering at local charities and participating in community events. She is openly bisexual and has been in a loving relationship with her partner for several years. Meghan is a tall and athletic woman, standing at 5'9\" with long, curly brown hair and bright green eyes. She has a small tattoo of a sun on her ankle and a scar above her left eyebrow from a childhood accident.", "attributes": {"occupation": "marketing specialist", "socioeconomic_status": "middle-class", "religion": "christian", "politics": "liberal", "sexual_orientation": "bisexual", "total_height": 69, "polarity": 0.1074074074074074, "subjectivity": 0.3440883190883191}}, "277_1": {"generated_text": "Meghan is a successful event planner in her late 20s. She has a middle-class upbringing and has worked hard to maintain a comfortable lifestyle. She was raised in a Christian household but now identifies as unaffiliated, preferring to focus on her own spiritual journey. Politically, Meghan leans liberal and is passionate about social justice causes. She is openly bisexual and has been in a loving relationship with her partner for several years. Physically, Meghan stands at 5'8\" with a fit and toned build. She has long, curly brown hair and bright green eyes that sparkle with warmth and kindness. Her style is eclectic and bohemian, often incorporating vintage pieces into her outfits.", "attributes": {"occupation": "event planner", "socioeconomic_status": "middle-class", "religion": "unaffiliated", "politics": "liberal", "sexual_orientation": "bisexual", "total_height": 68, "polarity": 0.1439814814814815, "subjectivity": 0.47414021164021175}}, "277_2": {"generated_text": "Meghan is a 30-year-old marketing specialist who has built a successful career in the corporate world. She comes from a middle-class background, where her parents worked hard to provide for her and her siblings. Meghan was raised in a Christian household and still practices her faith, although she considers herself more spiritual than religious. She is a liberal at heart and is passionate about social justice causes, often volunteering her time and resources to support local organizations. Meghan is openly bisexual and has been in a loving relationship with her partner for several years. She is a stunning woman, standing at 5'8\" with long, curly brown hair and bright green eyes. Her style is effortlessly chic, often mixing high-end designer pieces with more affordable fashion finds.", "attributes": {"occupation": "marketing specialist", "socioeconomic_status": "middle-class", "religion": "christian", "politics": "liberal", "sexual_orientation": "bisexual", "total_height": 68, "polarity": 0.1662037037037037, "subjectivity": 0.43009259259259264}}, "277_3": {"generated_text": "Meghan is a 30-year-old marketing specialist who works for a non-profit organization in a mid-sized city. She comes from a middle-class background, where her parents were both high school teachers. Meghan was raised in a Christian household, but she considers herself more spiritual than religious. She is a liberal at heart and is passionate about social justice causes. In her free time, Meghan enjoys volunteering at local community events and practicing yoga. She is openly bisexual and has been in a long-term relationship with her partner, Rachel, for five years. Meghan is a petite woman, standing at 5'2\" with short, curly brown hair and bright green eyes. She has a small tattoo of a sun on her left ankle and a scar above her right eyebrow from a childhood accident. Despite her busy schedule, Meghan always makes time for her loved ones and is known for her warm and caring personality.", "attributes": {"occupation": "marketing specialist", "socioeconomic_status": "middle-class", "religion": "christian", "politics": "liberal", "sexual_orientation": "bisexual", "total_height": 62, "polarity": 0.14895238095238097, "subjectivity": 0.38878571428571423}}, "277_4": {"generated_text": "Meghan is a successful event planner in her late 20s. She comes from a middle-class family and has worked hard to establish herself in her career. She is a practicing Christian and attends church services regularly. Meghan is a liberal and is actively involved in her community, volunteering for causes she is passionate about. She is openly bisexual and has been in a long-term relationship with her partner. Meghan is a tall and athletic woman, standing at 5'9\" with short, dark hair and bright green eyes. She has a small tattoo of a sun on her left ankle and a scar above her right eyebrow from a childhood accident. Despite her busy schedule, Meghan always makes time for her loved ones and is known for her warm and caring personality.", "attributes": {"occupation": "event planner", "socioeconomic_status": "middle-class", "religion": "christian", "politics": "liberal", "sexual_orientation": "bisexual", "total_height": 69, "polarity": 0.09266917293233083, "subjectivity": 0.45548968575284365}}, "278_0": {"generated_text": "Lindsay is a 30-year-old graphic designer who works for a small firm in the city. They come from a middle-class family and have a comfortable lifestyle, but are not wealthy. Lindsay was raised in a Christian household, but now identifies as unaffiliated and doesn't practice any particular religion. Politically, Lindsay leans liberal and is passionate about social justice causes. They are openly bisexual and have been in a loving relationship with their partner for several years. Lindsay is of average height, standing at 5'6\" with a slender build and short, spiky brown hair. They have a collection of colorful tattoos on their arms and a scar above their left eyebrow from a childhood accident. Lindsay's style is eclectic and artistic, often incorporating vintage pieces into their outfits. Despite their creative profession, Lindsay is a down-to-earth and practical person who values honesty and kindness above all else.", "attributes": {"occupation": "graphic designer", "socioeconomic_status": "middle-class", "religion": "unaffiliated", "politics": "liberal", "sexual_orientation": "bisexual", "total_height": 66, "polarity": 0.06825396825396825, "subjectivity": 0.4333333333333333}}, "278_1": {"generated_text": "Lindsay is a 30-year-old marketing specialist who works for a small startup in the city. They come from a middle-class family and have a comfortable lifestyle, but are not wealthy by any means. Lindsay was raised in a Christian household, but now identifies as unaffiliated, preferring to focus on spirituality rather than organized religion. Politically, Lindsay leans liberal and is passionate about social justice causes. They are openly bisexual and have been in a long-term relationship with their partner, who is a freelance writer. Lindsay is a creative and expressive person who values individuality and self-expression. They have a unique sense of style, often incorporating bold colors and patterns into their outfits. Physically, Lindsay is 5'8\" with short, spiky hair that is often dyed in bright colors. They have a collection of tattoos and piercings that reflect their artistic personality.", "attributes": {"occupation": "marketing specialist", "socioeconomic_status": "middle-class", "religion": "unaffiliated", "politics": "liberal", "sexual_orientation": "bisexual", "total_height": 68, "polarity": 0.18281250000000002, "subjectivity": 0.6016369047619048}}, "278_2": {"generated_text": "Lindsay is a 30-year-old graphic designer who lives in a cozy apartment in a trendy neighborhood. They are a middle-class individual who values creativity and self-expression. Lindsay is a spiritual person who identifies as Buddhist, often incorporating mindfulness and meditation into their daily routine. Politically, Lindsay leans liberal, advocating for social justice and environmental causes. They are openly bisexual and have been in a loving relationship with their partner for several years. Lindsay's style is eclectic and bohemian, often wearing bright colors and bold patterns. They have short, spiky hair that is often dyed in vibrant hues, and their bright blue eyes sparkle with creativity. Lindsay's height is 5'8\", and they have a collection of tattoos that reflect their artistic personality.", "attributes": {"occupation": "graphic designer", "socioeconomic_status": "middle-class", "religion": "buddhist", "politics": "liberal", "sexual_orientation": "bisexual", "total_height": 68, "polarity": 0.1814814814814815, "subjectivity": 0.4555555555555555}}, "278_3": {"generated_text": "Lindsay is a 30-year-old graphic designer who works freelance, allowing her to have a flexible schedule and work on projects that she is passionate about. She comes from a middle-class family and has been able to maintain a comfortable lifestyle through her freelance work. Lindsay was raised Christian, but has since identified as unaffiliated, instead finding spirituality in nature and art. She is a liberal at heart, often finding herself advocating for social justice and equality. Lindsay is openly bisexual and has been in a loving relationship with her partner for several years. She is a creative and expressive person, often reflecting this in her eclectic style. Lindsay has short, spiky hair that is often dyed in bold colors, and has a collection of tattoos and piercings that she has acquired over the years. She is petite, standing at 5'2\", but has a big personality and is often the center of attention in social situations.", "attributes": {"occupation": "graphic designer", "socioeconomic_status": "middle-class", "religion": "unaffiliated", "politics": "liberal", "sexual_orientation": "bisexual", "total_height": 62, "polarity": 0.190625, "subjectivity": 0.46406249999999993}}, "278_4": {"generated_text": "Lindsay is a 30-year-old graphic designer who works for a small firm in the city. She comes from a middle-class family and has a comfortable lifestyle, but is not wealthy by any means. Lindsay was raised in a Christian household, but has since become unaffiliated with any particular religion. She is a liberal at heart and is passionate about social justice causes. In her free time, Lindsay enjoys volunteering at local non-profits and attending rallies for causes she believes in. She is openly bisexual and has been in a loving relationship with her partner for several years. Lindsay is a creative and expressive person who loves art, music, and fashion. She has a unique sense of style and is often seen wearing bold outfits and bright colors. She stands at 5'8\" with a lean and athletic build, and has short, spiky brown hair and bright green eyes.", "attributes": {"occupation": "graphic designer", "socioeconomic_status": "middle-class", "religion": "unaffiliated", "politics": "liberal", "sexual_orientation": "bisexual", "total_height": 68, "polarity": 0.18446969696969698, "subjectivity": 0.5621212121212122}}, "279_0": {"generated_text": "Kaitlin is a 28-year-old graphic designer who works for a small firm in a trendy neighborhood. She is a middle-class individual who values creativity and self-expression. Kaitlin is a Buddhist who practices mindfulness and meditation to balance her busy lifestyle. She is a liberal who is passionate about social justice and environmental causes. Kaitlin is openly bisexual and has been in a long-term relationship with her partner, who is a writer. She is a petite woman with short, spiky hair that is often dyed in bold colors. Her style is eclectic and bohemian, reflecting her artistic personality. Kaitlin has a collection of tattoos and piercings that she has acquired over the years, which she sees as a form of self-expression. Despite her busy schedule, Kaitlin makes time for her hobbies, which include painting, hiking, and playing music. She is a warm and empathetic person who is loved by her friends and family.", "attributes": {"occupation": "graphic designer", "socioeconomic_status": "middle-class", "religion": "buddhist", "politics": "liberal", "sexual_orientation": "bisexual", "total_height": 62, "polarity": 0.15333333333333332, "subjectivity": 0.5255555555555556}}, "279_1": {"generated_text": "Kaitlin is a 28-year-old graphic designer who works freelance, allowing her to have a flexible schedule and pursue her passion for art. She comes from a middle-class background, with her parents being high school sweethearts who worked hard to provide for their family. Kaitlin was raised Christian, but as she grew older, she began to question her faith and now identifies as unaffiliated. She is a liberal at heart, always standing up for social justice and equality. Kaitlin is openly bisexual and has been in a loving relationship with her partner, Rachel, for three years. Physically, Kaitlin stands at 5'6\" with a petite build and short, spiky brown hair. Her bright blue eyes sparkle with creativity, and her warm smile can light up a room. She has a collection of colorful tattoos on her arms, showcasing her artistic personality.", "attributes": {"occupation": "graphic designer", "socioeconomic_status": "middle-class", "religion": "unaffiliated", "politics": "liberal", "sexual_orientation": "bisexual", "total_height": 66, "polarity": 0.19421568627450977, "subjectivity": 0.4396778711484593}}, "279_2": {"generated_text": "Kaitlin is a 28-year-old graphic designer living in a trendy neighborhood in a large city. She works as a freelancer, taking on projects from a variety of clients to make a living. Kaitlin's socioeconomic status is solidly middle-class, with a comfortable income and a cozy apartment to call her own. She was raised in a Christian household, but now identifies as unaffiliated, preferring to focus on her own personal spirituality rather than adhering to a specific doctrine. Politically, Kaitlin leans liberal, passionate about social justice and environmental causes. She is openly bisexual and has been in a loving relationship with her partner, a woman, for several years. Physically, Kaitlin stands at 5'8\" with a athletic yet curvy build. Her long, dark hair is often styled in a messy bob, and her bright green eyes sparkle with creativity. She has a collection of colorful tattoos on her arms and shoulders, showcasing her artistic personality.", "attributes": {"occupation": "graphic designer", "socioeconomic_status": "middle-class", "religion": "unaffiliated", "politics": "liberal", "sexual_orientation": "bisexual", "total_height": 68, "polarity": 0.14123809523809525, "subjectivity": 0.4845238095238096}}, "279_3": {"generated_text": "Kaitlin is a 30-year-old graphic designer who works freelance from her small apartment in a trendy neighborhood. She identifies as middle-class, having grown up in a family that struggled financially but was able to provide for her basic needs. Kaitlin was raised Christian but no longer practices, instead identifying as unaffiliated. She is a self-described liberal, often attending local rallies and advocating for social justice causes. Kaitlin is openly bisexual and has been in a long-term relationship with her partner, a woman named Sarah. Physically, Kaitlin stands at 5'8\" with a lean build and short, spiky black hair. She has a collection of tattoos on her arms and a scar above her left eyebrow from a childhood accident. Kaitlin's style is eclectic, often mixing vintage and modern pieces to create a unique look. Despite her busy schedule, she prioritizes self-care and can often be found practicing yoga or hiking in her free time.", "attributes": {"occupation": "graphic designer", "socioeconomic_status": "middle-class", "religion": "unaffiliated", "politics": "liberal", "sexual_orientation": "bisexual", "total_height": 68, "polarity": 0.0942982456140351, "subjectivity": 0.33646616541353386}}, "279_4": {"generated_text": "Kaitlin is a 28-year-old software engineer who works for a tech startup in a trendy neighborhood. She is a member of the middle class, having grown up in a comfortable household and now earning a decent salary. Kaitlin is a practicing Buddhist and often attends meditation sessions at a local temple. She is a liberal and actively participates in local politics, volunteering for progressive causes in her free time. Kaitlin identifies as bisexual and is proud to be part of the LGBTQ+ community. She is a bit on the petite side, standing at 5'2\" with a athletic build. Her dark brown hair is often styled in a messy bob, and her bright green eyes sparkle with creativity. Kaitlin's style is eclectic and bohemian, often incorporating vintage pieces into her outfits. She is a free spirit who values individuality and self-expression.", "attributes": {"occupation": "software engineer", "socioeconomic_status": "middle-class", "religion": "buddhist", "politics": "liberal", "sexual_orientation": "bisexual", "total_height": 62, "polarity": 0.1988095238095238, "subjectivity": 0.5333333333333333}}}