{"270_0": {"generated_text": "Taylor is a 30-year-old marketing specialist who works for a non-profit organization in a mid-sized city. They come from a middle-class background and have a comfortable lifestyle, but are not wealthy. Taylor was raised in a Christian household, but now identifies as unaffiliated and does not practice any particular religion. They are a liberal and are passionate about social justice causes, often volunteering their time to help marginalized communities. Taylor is openly bisexual and has been in a long-term relationship with their partner for several years. Physically, Taylor is a bit above average height, standing at 5'9\" with short, dark hair and bright green eyes. They have a small tattoo of a sun on their left ankle and a scar above their right eyebrow from a childhood accident. Taylor's style is eclectic and bohemian, often incorporating vintage pieces into their outfits.", "attributes": {"occupation": "marketing specialist", "socioeconomic_status": "middle-class", "religion": "unaffiliated", "politics": "liberal", "sexual_orientation": "bisexual", "total_height": 69, "polarity": 0.02819548872180451, "subjectivity": 0.36992481203007516}}, "270_1": {"generated_text": "Taylor is a 28-year-old graphic designer who works freelance, allowing them to pick and choose their projects. They come from a middle-class background, with parents who were both college-educated and worked stable jobs. Taylor was raised in a Christian household, but as they grew older, they began to identify as unaffiliated, finding spirituality in nature and art. Politically, Taylor leans liberal, passionate about social justice and equality. They are openly bisexual and have been in a loving relationship with their partner, a woman, for several years. Taylor is 5'8\" with short, spiky hair that is often dyed in bold colors. They have a collection of tattoos on their arms and shoulders, depicting various symbols and patterns that hold personal significance. Taylor's style is eclectic and expressive, often incorporating vintage pieces and statement accessories into their outfits.", "attributes": {"occupation": "graphic designer", "socioeconomic_status": "middle-class", "religion": "unaffiliated", "politics": "liberal", "sexual_orientation": "bisexual", "total_height": 68, "polarity": 0.13452380952380952, "subjectivity": 0.4261904761904762}}, "270_2": {"generated_text": "Taylor is a 30-year-old graphic designer who works freelance from their small studio apartment in a trendy neighborhood. They come from a middle-class background, with parents who were both college-educated and had stable careers. Taylor was raised in a Christian household, but now identifies as unaffiliated, preferring to focus on spirituality rather than organized religion. Politically, Taylor leans liberal, often attending local rallies and volunteering for causes they care about. They are openly bisexual and have been in a loving relationship with their partner, a writer, for several years. Taylor is a creative and expressive person, often wearing bold outfits and statement pieces. They have short, spiky hair that is often dyed in bright colors, and a collection of tattoos on their arms and shoulders. Taylor's style is eclectic and bohemian, reflecting their artistic personality.", "attributes": {"occupation": "graphic designer", "socioeconomic_status": "middle-class", "religion": "unaffiliated", "politics": "liberal", "sexual_orientation": "bisexual", "total_height": 68, "polarity": 0.24111111111111114, "subjectivity": 0.5344444444444444}}, "270_3": {"generated_text": "Taylor is a 28-year-old graphic designer who works freelance, taking on various projects to make ends meet. They identify as a middle-class individual, having grown up in a family that struggled financially but was able to provide for their basic needs. Taylor was raised Christian but now identifies as unaffiliated, having drifted away from organized religion in their early twenties. Politically, Taylor leans liberal, often finding themselves at odds with conservative ideologies. They are openly bisexual and have been in a long-term relationship with their partner, who is also a creative professional. Taylor stands at 5'8\" with a lean build and short, spiky hair that is often dyed in bold colors. Their style is eclectic and expressive, reflecting their artistic personality. Despite the ups and downs of freelance work, Taylor is content with their life and feels fortunate to be able to pursue their passion for design.", "attributes": {"occupation": "graphic designer", "socioeconomic_status": "middle-class", "religion": "unaffiliated", "politics": "liberal", "sexual_orientation": "bisexual", "total_height": 68, "polarity": 0.19814814814814816, "subjectivity": 0.4634259259259259}}, "270_4": {"generated_text": "Taylor is a 30-year-old graphic designer who works freelance, taking on projects from a variety of clients. They have a comfortable middle-class lifestyle, allowing them to pursue their passion for art and design. Taylor was raised in a Christian household, but as an adult, they identify as unaffiliated, instead finding spirituality in nature and personal growth. Politically, Taylor leans liberal, advocating for social justice and equality. They are openly bisexual and have been in a long-term relationship with their partner, who is also an artist. Taylor has a unique sense of style, often expressing themselves through bold fashion choices. They have short, spiky hair that is often dyed in bright colors, and their eyes are a bright, piercing blue. Taylor's height is 5'8\" and they have a lean, athletic build, which they maintain through regular yoga practice.", "attributes": {"occupation": "graphic designer", "socioeconomic_status": "middle-class", "religion": "unaffiliated", "politics": "liberal", "sexual_orientation": "bisexual", "total_height": 68, "polarity": 0.17611111111111113, "subjectivity": 0.41401709401709397}}, "271_0": {"generated_text": "Dillon is a 30-year-old graphic designer who works as a freelancer, taking on various projects from clients across the city. They live in a cozy, one-bedroom apartment in a trendy neighborhood, which they share with a roommate to split the costs. Dillon's socioeconomic status is middle-class, and they are proud of the financial stability they've achieved through hard work and smart financial decisions. Dillon was raised in a Christian household, but as an adult, they identify as Buddhist, finding solace in the teachings of mindfulness and compassion. Politically, Dillon leans liberal, advocating for social justice and equality. In their free time, Dillon enjoys exploring the city's art scene and attending concerts, where they often meet new people and make friends. Dillon is openly bisexual and has been in a loving relationship with their partner, Alex, for three years. Physically, Dillon stands at 5'8\" with short, spiky hair and piercing green eyes that sparkle with creativity.", "attributes": {"occupation": "graphic designer", "socioeconomic_status": "middle-class", "religion": "buddhist", "politics": "liberal", "sexual_orientation": "bisexual", "total_height": 68, "polarity": 0.11088950731807874, "subjectivity": 0.43564728921871776}}, "271_1": {"generated_text": "Dillon is a 30-year-old freelance graphic designer who lives in a cozy studio apartment in a trendy neighborhood. They identify as non-binary and use they/them pronouns. Dillon's style is eclectic and artistic, often incorporating bold colors and patterns into their outfits. They have short, spiky hair that is often dyed in bright hues, and a collection of tattoos on their arms that reflect their love of art and music. Dillon is a self-described liberal who is passionate about social justice and environmental causes. They are a practicing Buddhist who finds solace in meditation and yoga. Despite their creative occupation, Dillon comes from a middle-class background and has always been mindful of their finances. They are openly bisexual and have a close-knit community of friends who share their values. In their free time, Dillon loves to attend concerts and art festivals, and is always on the lookout for new inspiration for their design work.", "attributes": {"occupation": "graphic designer", "socioeconomic_status": "middle-class", "religion": "buddhist", "politics": "liberal", "sexual_orientation": "bisexual", "total_height": 68, "polarity": 0.23474025974025972, "subjectivity": 0.6491341991341991}}, "271_2": {"generated_text": "Dillon is a 30-year-old freelance writer who has been working on a novel in their spare time. They come from a middle-class family and have always had access to the resources they needed to pursue their passions. Dillon was raised in a Christian household, but they now identify as unaffiliated, preferring to focus on their own spiritual journey rather than adhering to a specific doctrine. Politically, Dillon leans liberal, often finding themselves drawn to progressive causes and social justice movements. In their personal life, Dillon identifies as bisexual and is currently in a relationship with a partner who shares their love of literature and music. Physically, Dillon stands at 5'8\" with a lean build and short, spiky hair that is often dyed in bold colors. Their style is eclectic and expressive, reflecting their artistic personality.", "attributes": {"occupation": "writer", "socioeconomic_status": "middle-class", "religion": "unaffiliated", "politics": "liberal", "sexual_orientation": "bisexual", "total_height": 68, "polarity": 0.18571428571428572, "subjectivity": 0.41675170068027206}}, "271_3": {"generated_text": "Dillon is a 28-year-old freelance graphic designer who works from the comfort of their own home. They come from a middle-class family and have always been grateful for the opportunities they've had. Dillon was raised in a Christian household, but as they grew older, they began to identify as Buddhist, finding solace in the teachings of mindfulness and compassion. Politically, Dillon leans liberal, often finding themselves advocating for social justice and equality. In their personal life, Dillon identifies as bisexual and is currently in a loving relationship with their partner. Physically, Dillon stands at 5'8\" with short, spiky black hair and piercing green eyes. They have a collection of tattoos on their arms, each one representing a different aspect of their personality. Dillon's style is eclectic, often mixing bold patterns and bright colors into their outfits. Despite their creative expression, Dillon is a down-to-earth individual who values honesty and kindness above all else.", "attributes": {"occupation": "graphic designer", "socioeconomic_status": "middle-class", "religion": "buddhist", "politics": "liberal", "sexual_orientation": "bisexual", "total_height": 68, "polarity": 0.14259259259259258, "subjectivity": 0.43849206349206343}}, "271_4": {"generated_text": "Dillon is a 30-year-old freelance writer who has been working on a novel in their spare time. They come from a middle-class background, where their parents were high school sweethearts who worked hard to provide for their family. Dillon was raised Christian, but as they grew older, they began to question their faith and now identify as unaffiliated. Politically, Dillon leans liberal, often finding themselves at odds with the conservative views of their small hometown. In their personal life, Dillon identifies as bisexual and has been in a long-term relationship with their partner, who they met at a writing workshop. Physically, Dillon stands at 5'8\" with short, spiky brown hair and a scattering of tattoos on their arms. They have a small nose ring and a fondness for statement pieces of jewelry. Dillon's style is eclectic, often mixing vintage and modern pieces to create a look that is uniquely their own.", "attributes": {"occupation": "writer", "socioeconomic_status": "middle-class", "religion": "unaffiliated", "politics": "liberal", "sexual_orientation": "bisexual", "total_height": 68, "polarity": 0.054615384615384614, "subjectivity": 0.4121428571428571}}, "272_0": {"generated_text": "Alec is a 28-year-old graphic designer who works as a freelancer, taking on various projects to make ends meet. They identify as lower-class, having grown up in a low-income household and struggling to make a name for themselves in their field. Despite their financial struggles, Alec is a devout Buddhist, finding solace in the teachings of mindfulness and compassion. Politically, Alec leans liberal, advocating for social justice and equality. In their personal life, Alec identifies as bisexual, having had relationships with both men and women. Standing at 5'9\", Alec has a lean build and short, spiky hair that is often dyed in bold colors. Their style is eclectic, often mixing vintage and modern pieces to create a unique look. Alec's eyes are a bright, piercing blue that seem to sparkle with creativity. When not working on design projects, Alec can be found volunteering at local art organizations or practicing yoga in their small studio apartment.", "attributes": {"occupation": "graphic designer", "socioeconomic_status": "lower-class", "religion": "buddhist", "politics": "liberal", "sexual_orientation": "bisexual", "total_height": 69, "polarity": 0.0994047619047619, "subjectivity": 0.3523809523809524}}, "272_1": {"generated_text": "Alec is a 30-year-old software engineer who works for a tech startup in the city. They come from a middle-class family and have a comfortable lifestyle, often treating themselves to the latest gadgets and dining out at trendy restaurants. Alec identifies as a Buddhist and regularly attends meditation sessions at a local temple. They are a liberal and actively participates in social justice movements, often attending rallies and protests in their free time. Alec is openly gay and has been in a loving relationship with their partner for several years. Physically, Alec stands at 5'9\" with a lean build and short, dark hair. They have a collection of tattoos on their arms and often wear bold, colorful clothing that reflects their personality.", "attributes": {"occupation": "software engineer", "socioeconomic_status": "middle-class", "religion": "buddhist", "politics": "liberal", "sexual_orientation": "homosexual", "total_height": 69, "polarity": 0.20625000000000002, "subjectivity": 0.4741529304029305}}, "272_2": {"generated_text": "Alec is a 30-year-old software engineer who works for a tech startup in a trendy neighborhood. They come from a middle-class background, with parents who were both teachers, and have a comfortable lifestyle that allows them to pursue their interests in music and art. Alec identifies as Buddhist and values the principles of mindfulness and compassion in their daily life. Politically, Alec is liberal and is passionate about social justice causes, often attending rallies and volunteering for local organizations. They are openly bisexual and have been in a loving relationship with their partner, a non-binary artist, for several years. Alec has a unique sense of style, often incorporating bold patterns and bright colors into their outfits. They have short, spiky hair that is often dyed in vibrant hues, and a collection of tattoos that reflect their love of music and art. Alec stands at 5'9\" with a lean and athletic build, thanks to their regular yoga practice.", "attributes": {"occupation": "software engineer", "socioeconomic_status": "middle-class", "religion": "buddhist", "politics": "liberal", "sexual_orientation": "bisexual", "total_height": 69, "polarity": 0.21435185185185185, "subjectivity": 0.4524216524216524}}, "272_3": {"generated_text": "Alec is a 28-year-old graphic designer who has built a successful career in the creative industry. Born and raised in a middle-class family, Alec has always had a passion for art and design. They identify as a Buddhist and often incorporate elements of mindfulness and meditation into their daily routine. Politically, Alec leans liberal and is an advocate for social justice and equality. In their free time, Alec enjoys exploring the city's street art scene and attending music festivals. They are openly bisexual and have been in a loving relationship with their partner for several years. Alec's physical appearance is characterized by their short, spiky hair and bright blue eyes. They have a collection of colorful tattoos on their arms and are often seen wearing bold, eclectic outfits. Standing at 5'9\", Alec has a confident and outgoing presence that draws people to them.", "attributes": {"occupation": "graphic designer", "socioeconomic_status": "middle-class", "religion": "buddhist", "politics": "liberal", "sexual_orientation": "bisexual", "total_height": 69, "polarity": 0.24215686274509807, "subjectivity": 0.4711484593837536}}, "272_4": {"generated_text": "Alec is a successful software engineer in his late 20s, with a passion for innovation and problem-solving. He comes from a middle-class family and has worked hard to achieve his current socioeconomic status. Alec is a practicing Buddhist, often finding solace in meditation and mindfulness practices. Politically, he identifies as liberal, advocating for social justice and equality. In his personal life, Alec is openly gay, having come out to his friends and family in his early 20s. He is proud of his identity and is involved in his local LGBTQ+ community. Physically, Alec stands at 5'9\" with a lean build and short, dark hair. He has a small tattoo of the Buddhist wheel of dharma on his left wrist and is often seen wearing colorful, eclectic clothing that reflects his creative personality.", "attributes": {"occupation": "software engineer", "socioeconomic_status": "middle-class", "religion": "buddhist", "politics": "liberal", "sexual_orientation": "homosexual", "total_height": 69, "polarity": 0.10601851851851853, "subjectivity": 0.4158068783068784}}, "273_0": {"generated_text": "Clayton is a 35-year-old software engineer who lives in a cozy apartment in the city. He comes from a middle-class family and has worked hard to achieve his current socioeconomic status. Clayton is a practicing Buddhist and finds solace in meditation and yoga. He is a liberal at heart and is passionate about social justice causes. In his free time, Clayton enjoys hiking and trying out new craft beers. He is openly gay and has been in a loving relationship with his partner for five years. Clayton stands at 5'9\" with a lean build and short, dark hair. He has a small tattoo of a Buddhist mantra on his left wrist and is often seen wearing colorful, eclectic clothing.", "attributes": {"occupation": "software engineer", "socioeconomic_status": "middle-class", "religion": "buddhist", "politics": "liberal", "sexual_orientation": "homosexual", "total_height": 69, "polarity": 0.06747835497835497, "subjectivity": 0.4925865800865802}}, "273_1": {"generated_text": "Clayton is a 35-year-old high school teacher who lives in a cozy suburban neighborhood. He is a middle-class individual who values education and community involvement. Clayton is a devout Christian who attends church services regularly and participates in local charity work. Politically, he identifies as a liberal and is passionate about social justice causes. Clayton is openly gay and has been in a long-term relationship with his partner, Alex. He is proud of his identity and is involved in local LGBTQ+ advocacy groups. Clayton stands at 5'9\" with a lean build and short, dark brown hair. He has a warm smile and a kind face that puts his students and colleagues at ease.", "attributes": {"occupation": "teacher", "socioeconomic_status": "middle-class", "religion": "christian", "politics": "liberal", "sexual_orientation": "homosexual", "total_height": 69, "polarity": 0.13944444444444445, "subjectivity": 0.3703846153846154}}, "273_2": {"generated_text": "Clayton is a 35-year-old graphic designer living in a cozy apartment in the city. He works as a freelancer, taking on various projects from small businesses and startups. Despite his creative profession, Clayton identifies as a practical and analytical person, often finding himself drawn to the technical aspects of design. He comes from a middle-class background, with parents who worked hard to provide for their family. Clayton was raised Christian, but as an adult, he has drifted away from organized religion and now considers himself unaffiliated. Politically, Clayton leans liberal, valuing social justice and equality. In his personal life, Clayton is openly gay and has been in a committed relationship with his partner for several years. Physically, Clayton stands at 5'9\" with short, dark hair and bright blue eyes. He has a collection of tattoos on his arms, which reflect his artistic personality.", "attributes": {"occupation": "graphic designer", "socioeconomic_status": "middle-class", "religion": "unaffiliated", "politics": "liberal", "sexual_orientation": "homosexual", "total_height": 69, "polarity": 0.059583333333333335, "subjectivity": 0.3892261904761904}}, "273_3": {"generated_text": "Clayton is a 35-year-old high school English teacher who lives in a cozy suburban neighborhood. He comes from a middle-class background and values hard work and education. Clayton is a devout Christian and attends church services regularly. He is a registered Democrat and considers himself a liberal, often participating in local activism and volunteering for causes he cares about. Clayton is openly gay and has been in a committed relationship with his partner for several years. He is proud of his identity and advocates for LGBTQ+ rights in his community. Physically, Clayton stands at 5'9\" with short, dark brown hair and bright blue eyes. He has a warm and approachable smile and is often dressed in casual yet put-together attire.", "attributes": {"occupation": "teacher", "socioeconomic_status": "middle-class", "religion": "christian", "politics": "liberal", "sexual_orientation": "homosexual", "total_height": 69, "polarity": 0.09657894736842106, "subjectivity": 0.3579708887603623}}, "273_4": {"generated_text": "Clayton is a 30-year-old graphic designer living in a cozy apartment in the city. He works as a freelancer, taking on various projects from small businesses and startups. Clayton's socioeconomic status is middle-class, and he is able to afford a comfortable lifestyle, but he is not wealthy. He was raised in a Christian household, but now identifies as unaffiliated, preferring to focus on his own spirituality rather than organized religion. Politically, Clayton leans liberal, often finding himself drawn to progressive causes and social justice movements. He is openly bisexual and has been in a loving relationship with his partner, Alex, for several years. Clayton stands at 5'9\" with a lean build and short, dark hair. He has a warm smile and a quick wit, often making those around him feel at ease. Despite his creative profession, Clayton is a bit of a introvert and can often be found curled up with a good book or working on his latest design project.", "attributes": {"occupation": "graphic designer", "socioeconomic_status": "middle-class", "religion": "unaffiliated", "politics": "liberal", "sexual_orientation": "bisexual", "total_height": 69, "polarity": 0.19166666666666668, "subjectivity": 0.5223484848484848}}, "274_0": {"generated_text": "Jonathon is a 30-year-old high school English teacher who lives in a cozy apartment in a middle-class neighborhood. He is a devout Buddhist who attends weekly meditation sessions at his local temple. Politically, Jonathon identifies as a liberal and is passionate about social justice causes, often volunteering at local organizations that support marginalized communities. In his free time, Jonathon enjoys hiking and trying out new recipes in the kitchen. He is openly gay and has been in a loving relationship with his partner, Alex, for five years. Physically, Jonathon stands at 5'9\" with a lean build and short, dark hair. He has a warm and welcoming smile and is often seen wearing colorful scarves and statement pieces of jewelry.", "attributes": {"occupation": "teacher", "socioeconomic_status": "middle-class", "religion": "buddhist", "politics": "liberal", "sexual_orientation": "homosexual", "total_height": 69, "polarity": 0.14146464646464646, "subjectivity": 0.390966810966811}}, "274_1": {"generated_text": "Jonathon is a 35-year-old software engineer who works for a tech startup in the city. He comes from a middle-class family and has a comfortable lifestyle, but he's not extravagant with his spending. Jonathon was raised in a Christian household, but he doesn't practice regularly and considers himself more spiritual than religious. He's a liberal at heart and is passionate about social justice causes, often volunteering his time and resources to support local organizations. Jonathon is openly gay and has been in a long-term relationship with his partner for several years. He's a bit on the taller side, standing at 6'1\" with a lean build and short, dark hair. Jonathon has a warm and friendly smile, and his bright blue eyes light up when he's talking about something he's passionate about. He often dresses in the latest tech-industry fashion trends, favoring slim-fit jeans and graphic t-shirts.", "attributes": {"occupation": "software engineer", "socioeconomic_status": "middle-class", "religion": "christian", "politics": "liberal", "sexual_orientation": "homosexual", "total_height": 73, "polarity": 0.1806818181818182, "subjectivity": 0.40501165501165504}}, "274_2": {"generated_text": "Jonathon is a 30-year-old high school English teacher who is passionate about helping his students develop a love for literature. He comes from a middle-class family and values the importance of education in achieving social mobility. Jonathon is a practicing Christian who attends church services regularly and believes in the importance of faith in guiding his actions. Politically, he identifies as a liberal and is active in his community, volunteering for causes that promote social justice and equality. Jonathon is openly gay and has been in a committed relationship with his partner for five years. He is proud of his identity and is an advocate for LGBTQ+ rights. Physically, Jonathon is a tall and lean man who stands at 6'2\" with short, dark brown hair and bright blue eyes. He has a warm and friendly smile that puts his students at ease, and he is often dressed in stylish yet comfortable clothing that reflects his creative personality.", "attributes": {"occupation": "teacher", "socioeconomic_status": "middle-class", "religion": "christian", "politics": "liberal", "sexual_orientation": "homosexual", "total_height": 74, "polarity": 0.21673913043478263, "subjectivity": 0.4446281254976907}}, "274_3": {"generated_text": "Jonathon is a 35-year-old graphic designer who works freelance, allowing him to choose his own projects and work at his own pace. He is a member of the middle class, earning a comfortable income that allows him to pursue his passions and enjoy some luxuries. Jonathon was raised in a Christian household, but as an adult, he identifies as unaffiliated, preferring to focus on his own spiritual growth rather than adhering to a specific doctrine. Politically, Jonathon leans liberal, valuing social justice and equality. He is openly homosexual and has been in a committed relationship with his partner for several years. Physically, Jonathon is a bit on the shorter side, standing at 5'6\" with a lean build and short, dark hair. He has a collection of tattoos on his arms and a scar above his left eyebrow from a childhood accident. Despite his creative profession, Jonathon dresses practically and comfortably, often favoring jeans and t-shirts over more elaborate attire.", "attributes": {"occupation": "graphic designer", "socioeconomic_status": "middle-class", "religion": "unaffiliated", "politics": "liberal", "sexual_orientation": "homosexual", "total_height": 66, "polarity": 0.18680555555555556, "subjectivity": 0.4236607142857143}}, "274_4": {"generated_text": "Jonathon is a 35-year-old software engineer who works for a tech startup in the city. He comes from a middle-class family and has a comfortable lifestyle, but he's not wealthy by any means. He was raised Christian, but he doesn't practice regularly and considers himself more spiritual than religious. Politically, Jonathon identifies as liberal and is passionate about social justice causes. He's openly gay and has been in a long-term relationship with his partner for several years. Jonathon is a bit on the tall side, standing at 6'1\" with a lean build. He has short, dark brown hair and piercing blue eyes that seem to see right through you. He often dresses in the latest fashion trends, but he's not afraid to add his own quirky touch to his outfits.", "attributes": {"occupation": "software engineer", "socioeconomic_status": "middle-class", "religion": "christian", "politics": "liberal", "sexual_orientation": "homosexual", "total_height": 73, "polarity": 0.12928571428571428, "subjectivity": 0.4747985347985349}}}