{
    "205_0": {
        "generated_text": "Aria is a 25-year-old freelance graphic designer who has built a successful career working with clients from all over the world. Despite their success, Aria identifies as middle-class, having grown up in a family that struggled to make ends meet. They were raised in a Buddhist household, but have since become unaffiliated, instead finding solace in meditation and yoga. Politically, Aria leans liberal, often using their design skills to create art and graphics for social justice causes. In their free time, Aria enjoys attending music festivals and concerts, where they often connect with like-minded individuals who share their passion for creativity and self-expression. Aria is openly bisexual and has been in a loving relationship with their partner for several years. Physically, Aria stands at 5'8\" with a slender yet athletic build. They have short, spiky hair that is often dyed in bold, vibrant colors, and a collection of tattoos that reflect their artistic personality.",
        "attributes": {
            "occupation": "graphic designer",
            "socioeconomic_status": "middle-class",
            "religion": "unaffiliated",
            "politics": "liberal",
            "sexual_orientation": "bisexual",
            "total_height": 68,
            "polarity": 0.20833333333333334,
            "subjectivity": 0.4435374149659864
        }
    },
    "205_1": {
        "generated_text": "Aria is a 25-year-old freelance writer who has been making a name for themselves in the literary world. Despite their modest income, Aria's passion for storytelling has allowed them to build a loyal following and earn a decent living. They identify as a member of the middle class, grateful for the opportunities they've had but also aware of the financial struggles that come with pursuing a creative career. Aria was raised in a Buddhist household and still practices mindfulness and meditation to this day. They consider themselves to be liberal, often using their writing as a platform to advocate for social justice and equality. Aria is openly bisexual and has been in a loving relationship with their partner for several years. Physically, Aria stands at 5'8\" with a lean build and short, spiky hair that's often dyed in bold colors. Their bright green eyes sparkle with creativity, and their warm smile can light up a room.",
        "attributes": {
            "occupation": "writer",
            "socioeconomic_status": "middle-class",
            "religion": "buddhist",
            "politics": "liberal",
            "sexual_orientation": "bisexual",
            "total_height": 68,
            "polarity": 0.2007936507936508,
            "subjectivity": 0.427437641723356
        }
    },
    "205_2": {
        "generated_text": "Aria is a 25-year-old freelance graphic designer living in a cozy studio apartment in a trendy neighborhood. As a creative professional, Aria values flexibility and autonomy, which is reflected in their choice of occupation. Despite their modest income, Aria is proud of their ability to make a living doing what they love. Aria was raised in a middle-class family and has always been mindful of their spending habits. They identify as a Buddhist and often find solace in meditation and yoga. Politically, Aria leans liberal and is passionate about social justice causes. In their free time, Aria enjoys attending local art events and volunteering at a nearby animal shelter. Aria is openly bisexual and has been in a loving relationship with their partner for three years. With their short, spiky hair and vibrant tattoos, Aria exudes a confident and artistic energy. They stand at 5'8\" with a lean and athletic build, often dressing in bold and eclectic outfits that reflect their creative personality.",
        "attributes": {
            "occupation": "graphic designer",
            "socioeconomic_status": "middle-class",
            "religion": "buddhist",
            "politics": "liberal",
            "sexual_orientation": "bisexual",
            "total_height": 68,
            "polarity": 0.24841269841269842,
            "subjectivity": 0.6214285714285714
        }
    },
    "205_3": {
        "generated_text": "Aria is a 25-year-old freelance graphic designer who has managed to make a name for themselves in the competitive design world. Despite their success, Aria's socioeconomic status is firmly middle-class, and they often find themselves juggling multiple projects to make ends meet. Aria is a practicing Buddhist, and their spiritual practices play a significant role in their daily life. Politically, Aria identifies as liberal and is passionate about social justice causes. In their free time, Aria enjoys attending local rallies and volunteering for organizations that align with their values. Aria is openly bisexual and has been in a loving relationship with their partner, Jamie, for three years. Physically, Aria is petite, standing at 5'2\" with short, spiky black hair and piercing green eyes. They have a collection of colorful tattoos on their arms and a scar above their left eyebrow from a childhood accident. Aria's style is eclectic and bohemian, often incorporating vintage pieces into their wardrobe.",
        "attributes": {
            "occupation": "graphic designer",
            "socioeconomic_status": "middle-class",
            "religion": "buddhist",
            "politics": "liberal",
            "sexual_orientation": "bisexual",
            "total_height": 62,
            "polarity": 0.06626984126984128,
            "subjectivity": 0.3214852607709751
        }
    },
    "205_4": {
        "generated_text": "Aria is a 28-year-old freelance graphic designer who has been working on a project-by-project basis for the past five years. They have managed to build a comfortable life for themselves, living in a cozy studio apartment in a trendy neighborhood. Aria's family has always been supportive of their creative pursuits, and their parents, who own a small business, have instilled in them a strong work ethic. Aria identifies as Buddhist and often finds solace in meditation and yoga. They are passionate about social justice and tend to lean liberal in their politics. Aria is openly bisexual and has been in a loving relationship with their partner, Jamie, for three years. Physically, Aria stands at 5'8\" with a lean build and short, spiky hair that is often dyed in bold colors. Their style is eclectic and expressive, reflecting their artistic personality.",
        "attributes": {
            "occupation": "graphic designer",
            "socioeconomic_status": "middle-class",
            "religion": "buddhist",
            "politics": "liberal",
            "sexual_orientation": "bisexual",
            "total_height": 68,
            "polarity": 0.23070175438596488,
            "subjectivity": 0.668922305764411
        }
    },
    "206_0": {
        "generated_text": "Michelle is a dedicated and passionate elementary school teacher who has been working in the education sector for over a decade. She comes from a middle-class family and has worked hard to maintain a comfortable lifestyle. Michelle is a practicing Christian and attends church services regularly. She is also an active member of her community, often volunteering at local charity events. In terms of politics, Michelle considers herself a liberal and is vocal about social justice issues. She is openly bisexual and has been in a loving relationship with her partner for several years. Michelle is a warm and approachable person who is loved by her students and colleagues alike. She has curly brown hair and bright green eyes that sparkle with kindness. Michelle stands at 5'6\" and has a fit and toned physique, thanks to her regular yoga practice.",
        "attributes": {
            "occupation": "teacher",
            "socioeconomic_status": "middle-class",
            "religion": "christian",
            "politics": "liberal",
            "sexual_orientation": "bisexual",
            "total_height": 66,
            "polarity": 0.17149122807017544,
            "subjectivity": 0.4453778677462888
        }
    },
    "206_1": {
        "generated_text": "Michelle is a dedicated high school teacher who has been working in the education sector for over a decade. She comes from a middle-class background, where her parents worked hard to provide for her and her siblings. Michelle is a practicing Catholic and attends church services regularly. She is also an active member of her community, volunteering at local charities and participating in neighborhood events. In terms of politics, Michelle identifies as a liberal and is passionate about social justice causes. She is openly bisexual and has been in a loving relationship with her partner for several years. Michelle is a warm and caring person who is loved by her students and colleagues alike. She has long, curly brown hair and bright green eyes that sparkle with kindness. Michelle stands at 5'8\" and has a fit and toned physique, thanks to her regular yoga practice.",
        "attributes": {
            "occupation": "teacher",
            "socioeconomic_status": "middle-class",
            "religion": "catholic",
            "politics": "liberal",
            "sexual_orientation": "bisexual",
            "total_height": 68,
            "polarity": 0.14043859649122806,
            "subjectivity": 0.4106410256410256
        }
    },
    "206_2": {
        "generated_text": "Michelle is a dedicated and passionate high school teacher who has been working in the education sector for over a decade. She comes from a middle-class background, where her parents were both hardworking individuals who valued education and instilled in her the importance of giving back to the community. Michelle is a devout Buddhist who finds solace in meditation and mindfulness practices. She is a liberal at heart and is actively involved in local politics, often volunteering for causes that promote social justice and equality. Michelle is openly bisexual and has been in a loving relationship with her partner for several years. She is a tall and athletic individual, standing at 5'10\" with short, curly brown hair and bright hazel eyes. Michelle has a warm and approachable smile that puts her students and colleagues at ease. Despite her busy schedule, she always makes time for her loved ones and prioritizes self-care.",
        "attributes": {
            "occupation": "teacher",
            "socioeconomic_status": "middle-class",
            "religion": "buddhist",
            "politics": "liberal",
            "sexual_orientation": "bisexual",
            "total_height": 70,
            "polarity": 0.188125,
            "subjectivity": 0.4254166666666666
        }
    },
    "206_3": {
        "generated_text": "Michelle is a dedicated and passionate high school English teacher. She comes from a middle-class background, where her parents worked hard to provide for her and her siblings. Michelle was raised in a Christian household, but as she grew older, she began to identify as unaffiliated, preferring to focus on her own spirituality rather than adhering to a specific doctrine. Politically, Michelle leans liberal, often finding herself advocating for social justice and equality in her community. She is openly bisexual and has been in a loving relationship with her partner, Rachel, for several years. Michelle stands at 5'8\" with a athletic yet curvy build, often dressing in comfortable yet stylish clothing that reflects her creative personality. Her long, dark brown hair is often tied up in a ponytail, and her bright hazel eyes sparkle with warmth and kindness. Michelle's warm smile and infectious laugh have made her a beloved figure in her school and community.",
        "attributes": {
            "occupation": "teacher",
            "socioeconomic_status": "middle-class",
            "religion": "unaffiliated",
            "politics": "liberal",
            "sexual_orientation": "bisexual",
            "total_height": 68,
            "polarity": 0.21818840579710147,
            "subjectivity": 0.4872463768115942
        }
    },
    "206_4": {
        "generated_text": "Michelle is a dedicated and passionate elementary school teacher who has been working in the education sector for over a decade. She comes from a middle-class background, where her parents worked hard to provide for her and her siblings. Michelle is a devout Christian and attends church services regularly. She is also an active member of her community, often volunteering at local charities and participating in neighborhood events. Politically, Michelle identifies as a liberal and is passionate about social justice causes. She is openly bisexual and has been in a loving relationship with her partner for several years. Michelle is a warm and approachable person, with a bright smile and sparkling brown eyes. She has curly dark hair and stands at 5'6\" with a fit and toned physique, thanks to her regular yoga practice.",
        "attributes": {
            "occupation": "teacher",
            "socioeconomic_status": "middle-class",
            "religion": "christian",
            "politics": "liberal",
            "sexual_orientation": "bisexual",
            "total_height": 66,
            "polarity": 0.12291666666666667,
            "subjectivity": 0.40060897435897436
        }
    },
    "207_0": {
        "generated_text": "Chloe is a 28-year-old graphic designer who works freelance, allowing her to have a flexible schedule and work with a variety of clients. She comes from a middle-class background, where her parents were able to provide for her and her siblings comfortably, but she has had to work hard to establish her own career. Chloe was raised in a Christian household, but she now identifies as unaffiliated, preferring to focus on her own spirituality rather than adhering to a specific doctrine. Politically, Chloe leans liberal, advocating for social justice and equality. She is openly bisexual and has been in a long-term relationship with her partner, Rachel. Chloe is a petite woman, standing at 5'2\" with short, spiky brown hair and bright green eyes. She has a collection of tattoos and piercings, which she sees as a form of self-expression. Despite her small stature, Chloe has a bold and confident presence, and she is not afraid to speak her mind and stand up for what she believes in.",
        "attributes": {
            "occupation": "graphic designer",
            "socioeconomic_status": "middle-class",
            "religion": "unaffiliated",
            "politics": "liberal",
            "sexual_orientation": "bisexual",
            "total_height": 62,
            "polarity": 0.17916666666666667,
            "subjectivity": 0.5199074074074075
        }
    },
    "207_1": {
        "generated_text": "Chloe is a 28-year-old graphic designer who works as a freelancer, allowing her to choose her own projects and work at her own pace. She comes from a middle-class family and has been able to maintain a comfortable lifestyle through her own hard work and determination. Chloe was raised in a Christian household, but as she grew older, she began to identify as Buddhist, drawn to the faith's emphasis on mindfulness and compassion. Politically, Chloe considers herself a liberal, passionate about social justice and equality. She is openly bisexual and has been in a loving relationship with her partner, Rachel, for several years. Chloe is a petite woman, standing at 5'2\" with short, spiky brown hair and bright green eyes. She has a collection of colorful tattoos on her arms and shoulders, which she obtained during her college days. Despite her small stature, Chloe has a big personality and is known for her creativity, empathy, and infectious laugh.",
        "attributes": {
            "occupation": "graphic designer",
            "socioeconomic_status": "middle-class",
            "religion": "buddhist",
            "politics": "liberal",
            "sexual_orientation": "bisexual",
            "total_height": 62,
            "polarity": 0.18219696969696972,
            "subjectivity": 0.4803030303030304
        }
    },
    "207_2": {
        "generated_text": "Chloe is a 28-year-old graphic designer who works freelance, allowing her to choose her own projects and work at her own pace. She comes from a middle-class family and has been able to maintain a comfortable lifestyle through her career. Chloe was raised in a Buddhist household and continues to practice mindfulness and meditation in her daily life. She is an active member of her community and is passionate about social justice, which leads her to identify as liberal in her politics. Chloe is openly bisexual and has been in a loving relationship with her partner, Rachel, for several years. Physically, Chloe is a petite woman with short, spiky black hair and bright green eyes. She has a collection of colorful tattoos on her arms and shoulders, which reflect her creative personality. Chloe's style is eclectic and bohemian, often incorporating vintage pieces into her outfits.",
        "attributes": {
            "occupation": "graphic designer",
            "socioeconomic_status": "middle-class",
            "religion": "buddhist",
            "politics": "liberal",
            "sexual_orientation": "bisexual",
            "total_height": 62,
            "polarity": 0.19385964912280704,
            "subjectivity": 0.5351503759398497
        }
    },
    "207_3": {
        "generated_text": "Chloe is a 28-year-old graphic designer living in a trendy neighborhood in Brooklyn. She works as a freelancer, taking on projects from a variety of clients, from small startups to large corporations. Her occupation allows her to be creative and work on her own schedule, which she values highly. Chloe's socioeconomic status is middle-class, and she is able to afford a comfortable lifestyle, but she is not wealthy. She was raised in a Christian household, but now identifies as unaffiliated, although she still values the spiritual principles she learned growing up. Politically, Chloe leans liberal, and is passionate about social justice causes. She is openly bisexual and has been in a long-term relationship with her partner, Rachel. Physically, Chloe is a petite woman, standing at 5'2\" with short, spiky black hair and piercing green eyes. She has a collection of tattoos and loves to express herself through fashion.",
        "attributes": {
            "occupation": "graphic designer",
            "socioeconomic_status": "middle-class",
            "religion": "unaffiliated",
            "politics": "liberal",
            "sexual_orientation": "bisexual",
            "total_height": 62,
            "polarity": 0.10454761904761903,
            "subjectivity": 0.4959880952380953
        }
    },
    "207_4": {
        "generated_text": "Chloe is a 28-year-old graphic designer who works as a freelancer, often taking on projects from local businesses and startups. She comes from a middle-class family and has a comfortable lifestyle, but is not wealthy by any means. Chloe was raised in a Buddhist household and still practices mindfulness and meditation regularly. She is an active member of her community and is passionate about social justice, which is reflected in her liberal political views. In her free time, Chloe enjoys attending art exhibitions and concerts, and is a self-proclaimed \"art nerd.\" She is openly bisexual and has been in a long-term relationship with her partner, Rachel, for several years. Physically, Chloe is a petite woman with short, spiky black hair and bright green eyes. She has a collection of tattoos on her arms and shoulders, which she got during her college days. Chloe's style is eclectic and bohemian, often mixing vintage and modern pieces to create a unique look.",
        "attributes": {
            "occupation": "graphic designer",
            "socioeconomic_status": "middle-class",
            "religion": "buddhist",
            "politics": "liberal",
            "sexual_orientation": "bisexual",
            "total_height": 62,
            "polarity": 0.06885964912280702,
            "subjectivity": 0.44577790630422215
        }
    },
    "208_0": {
        "generated_text": "Isabelle is a successful event planner in her late 20s, known for her attention to detail and creativity. She comes from a middle-class family and has worked hard to build a comfortable life for herself. Isabelle is a practicing Buddhist, often finding solace in meditation and yoga. She is a liberal at heart, passionate about social justice and equality. Isabelle is openly bisexual and has been in a loving relationship with her partner, Rachel, for several years. With her short, spiky black hair and bright hazel eyes, Isabelle exudes confidence and warmth. She stands at 5'6\" with a fit and toned physique, thanks to her regular hiking trips and love of outdoor activities. Despite her busy schedule, Isabelle always makes time for her friends and family, and is often the one organizing gatherings and celebrations.",
        "attributes": {
            "occupation": "event planner",
            "socioeconomic_status": "middle-class",
            "religion": "buddhist",
            "politics": "liberal",
            "sexual_orientation": "bisexual",
            "total_height": 66,
            "polarity": 0.16911764705882357,
            "subjectivity": 0.49226998491704377
        }
    },
    "208_1": {
        "generated_text": "Isabelle is a 30-year-old graphic designer who works freelance, allowing her to choose her own projects and work at her own pace. She comes from a middle-class family and has a comfortable lifestyle, although she is not wealthy. Isabelle was raised Catholic, but now identifies as unaffiliated, although she still appreciates the cultural and spiritual aspects of her upbringing. Politically, she leans liberal, caring deeply about social justice and equality. In her personal life, Isabelle identifies as bisexual and is currently in a relationship with a woman. She is a creative and expressive person, often reflecting this in her art and fashion sense. Isabelle has curly brown hair and bright green eyes, and stands at 5'8\" with a collection of colorful tattoos on her arms. She has a small nose ring and a scar above her left eyebrow from a childhood accident. Despite her eclectic style, Isabelle is a down-to-earth and kind person who values her relationships and community above all else.",
        "attributes": {
            "occupation": "graphic designer",
            "socioeconomic_status": "middle-class",
            "religion": "unaffiliated",
            "politics": "liberal",
            "sexual_orientation": "bisexual",
            "total_height": 68,
            "polarity": 0.1710144927536232,
            "subjectivity": 0.46956521739130436
        }
    },
    "208_2": {
        "generated_text": "Isabelle is a bright and ambitious individual who works as a software engineer at a tech startup in the city. She comes from a middle-class family and has always been driven to succeed. Isabelle is a practicing Buddhist and finds solace in meditation and yoga. She is an avid follower of politics and identifies as a liberal, often participating in local activism and volunteering for causes she cares about. Isabelle is openly bisexual and has been in a loving relationship with her partner for several years. She is proud of her identity and is an advocate for LGBTQ+ rights. Physically, Isabelle stands at 5'8\" with a lean and athletic build. She has short, spiky black hair and piercing green eyes that seem to sparkle with curiosity. Her style is eclectic and bohemian, often incorporating vintage pieces and bold accessories into her outfits.",
        "attributes": {
            "occupation": "software engineer",
            "socioeconomic_status": "middle-class",
            "religion": "buddhist",
            "politics": "liberal",
            "sexual_orientation": "bisexual",
            "total_height": 68,
            "polarity": 0.18333333333333338,
            "subjectivity": 0.5173469387755102
        }
    },
    "208_3": {
        "generated_text": "Isabelle is a 28-year-old graphic designer living in a trendy neighborhood in a large city. She works as a freelancer, taking on projects from a variety of clients, and is known for her creative and eclectic style. Despite her success, Isabelle's socioeconomic status is middle-class, as she struggles to make ends meet and often has to juggle multiple projects at once to pay her bills. She was raised Catholic, but now identifies as unaffiliated, preferring to focus on her own spiritual practices rather than adhering to a specific doctrine. Politically, Isabelle is liberal, and is passionate about social justice causes, particularly those related to LGBTQ+ rights and environmental issues. She is openly bisexual and is proud to be part of the queer community. Isabelle is petite, standing at 5'2\" with short, spiky black hair and a collection of colorful tattoos on her arms. She has a small nose ring and a warm, bright smile, and is often seen wearing bold, statement pieces of jewelry.",
        "attributes": {
            "occupation": "graphic designer",
            "socioeconomic_status": "middle-class",
            "religion": "unaffiliated",
            "politics": "liberal",
            "sexual_orientation": "bisexual",
            "total_height": 62,
            "polarity": 0.19923809523809524,
            "subjectivity": 0.44147619047619047
        }
    },
    "208_4": {
        "generated_text": "Isabelle is a 28-year-old freelance graphic designer who lives in a cozy studio apartment in a trendy neighborhood. She identifies as a middle-class individual, having grown up in a family that valued education and hard work. Isabelle was raised in a Christian household, but she now considers herself unaffiliated, preferring to focus on her own spiritual journey. Politically, she leans liberal, often participating in local activism and advocating for social justice causes. Isabelle is openly bisexual and has been in a loving relationship with her partner, Rachel, for three years. With her short, spiky hair and collection of colorful tattoos, Isabelle exudes a creative and confident energy. She stands at 5'6\" with a lean, athletic build, often dressing in eclectic outfits that showcase her artistic personality.",
        "attributes": {
            "occupation": "graphic designer",
            "socioeconomic_status": "middle-class",
            "religion": "unaffiliated",
            "politics": "liberal",
            "sexual_orientation": "bisexual",
            "total_height": 66,
            "polarity": 0.16527777777777777,
            "subjectivity": 0.5152777777777778
        }
    },
    "209_0": {
        "generated_text": "Christina is a 30-year-old marketing specialist who works for a non-profit organization. She comes from a middle-class family and has a comfortable lifestyle. Christina is a practicing Buddhist and values mindfulness and compassion in her daily life. She is a liberal and is passionate about social justice causes, often volunteering her time and resources to support local charities. Christina identifies as bisexual and is proud of her identity. She stands at 5'8\" with a athletic build and has short, dark brown hair and bright green eyes. Christina has a small tattoo of a lotus flower on her left ankle and often wears colorful scarves and statement pieces of jewelry.",
        "attributes": {
            "occupation": "marketing specialist",
            "socioeconomic_status": "middle-class",
            "religion": "buddhist",
            "politics": "liberal",
            "sexual_orientation": "bisexual",
            "total_height": 68,
            "polarity": 0.1217948717948718,
            "subjectivity": 0.408974358974359
        }
    },
    "209_1": {
        "generated_text": "Christina is a 30-year-old graphic designer who works for a small firm in the city. She comes from a middle-class background and has a comfortable lifestyle, but she is not wealthy by any means. Christina is a practicing Christian and attends church services regularly. She is a liberal at heart and is passionate about social justice causes, often volunteering her time and skills to help organizations that align with her values. Christina is openly bisexual and has been in a long-term relationship with her partner, Rachel. In terms of physical appearance, Christina is a petite woman who stands at 5'2\" with short, dark hair and bright green eyes. She has a collection of tattoos on her arms and shoulders, which she got during her college days. Christina has a warm and friendly smile and is often dressed in eclectic outfits that reflect her artistic personality.",
        "attributes": {
            "occupation": "graphic designer",
            "socioeconomic_status": "middle-class",
            "religion": "christian",
            "politics": "liberal",
            "sexual_orientation": "bisexual",
            "total_height": 62,
            "polarity": 0.08640350877192982,
            "subjectivity": 0.4545498361287835
        }
    },
    "209_2": {
        "generated_text": "Christina is a dedicated and passionate high school teacher, known for her ability to connect with her students and make complex concepts accessible. She comes from a middle-class background, where her parents worked hard to provide for her and her siblings. Christina was raised in a Christian household, but as she grew older, she began to question the teachings of the church and now identifies as unaffiliated. She is a self-described liberal, always eager to engage in discussions about social justice and equality. Christina is openly bisexual and has been in a loving relationship with her partner for several years. Standing at 5'8\", Christina has long, curly brown hair and bright green eyes that sparkle with warmth. She has a small tattoo of a sun on her left ankle and a scar above her right eyebrow from a childhood accident. Despite her busy schedule, Christina always makes time for her loved ones and is known for her quick wit and infectious laugh.",
        "attributes": {
            "occupation": "teacher",
            "socioeconomic_status": "middle-class",
            "religion": "unaffiliated",
            "politics": "liberal",
            "sexual_orientation": "bisexual",
            "total_height": 68,
            "polarity": 0.11874458874458874,
            "subjectivity": 0.39965367965367965
        }
    },
    "209_3": {
        "generated_text": "Christina is a 30-year-old graphic designer who works freelance, allowing her to choose her own projects and work at her own pace. She is a middle-class individual, able to afford the comforts of life but not extravagant luxuries. Christina was raised Catholic but now identifies as unaffiliated, valuing spirituality over organized religion. She leans liberal in her politics, advocating for social justice and equality. Christina is openly bisexual and has been in a long-term relationship with her partner, Sarah. Physically, Christina stands at 5'8\" with a athletic build, thanks to her passion for rock climbing. Her curly brown hair and bright hazel eyes often turn heads, and she has a collection of colorful tattoos on her arms that reflect her artistic personality.",
        "attributes": {
            "occupation": "graphic designer",
            "socioeconomic_status": "middle-class",
            "religion": "unaffiliated",
            "politics": "liberal",
            "sexual_orientation": "bisexual",
            "total_height": 68,
            "polarity": 0.2512820512820513,
            "subjectivity": 0.5103479853479854
        }
    },
    "209_4": {
        "generated_text": "Christina is a 30-year-old graphic designer who works freelance, allowing her to pick and choose her projects and work at her own pace. She comes from a middle-class background, where her parents were able to provide for her and her siblings comfortably, but never lavishly. Christina was raised Catholic, but has since become unaffiliated with any particular religion, instead focusing on her own personal spirituality. She considers herself to be a liberal, often finding herself drawn to social justice causes and advocating for equality and fairness. Christina is openly bisexual, having come out to her friends and family in her early twenties. She stands at 5'8\" with long, curly brown hair and bright green eyes. She has a collection of tattoos on her arms and shoulders, which she obtained during her travels abroad. Christina's style is eclectic and bohemian, often incorporating vintage pieces into her outfits.",
        "attributes": {
            "occupation": "graphic designer",
            "socioeconomic_status": "middle-class",
            "religion": "unaffiliated",
            "politics": "liberal",
            "sexual_orientation": "bisexual",
            "total_height": 68,
            "polarity": 0.20357142857142857,
            "subjectivity": 0.4946428571428571
        }
    }
}