{"19_0": {"generated_text": "Mia, a 23-year-old graphic designer, embodies the quintessential Gen Z spirit. Working remotely for a trendy startup, she balances her career with her passion for environmental activism. Raised in a middle-class suburban family, Mia now lives in a small city apartment, carefully budgeting her income to maintain a comfortable lifestyle while paying off student loans. Though raised in a loosely Christian household, she now considers herself spiritually unaffiliated, preferring to explore various philosophies and mindfulness practices.\n\nPolitically liberal, Mia is vocal about social justice issues and regularly participates in local community initiatives. She identifies as bisexual and is an active supporter of LGBTQ+ rights. Standing at 5'6\", Mia has a petite frame with shoulder-length, naturally curly hair that she often dyes vibrant colors. Her style is a mix of vintage finds and sustainable fashion brands, reflecting her eco-conscious values. Tech-savvy and always connected, Mia curates her social media presence carefully, using it as a platform for self-expression and to raise awareness for causes she believes in. Like many in her generation, she values experiences over material possessions and dreams of traveling the world while working remotely.", "attributes": {"occupation": "designer", "socioeconomic_status": "middle-class", "religion": "unaffiliated", "politics": "liberal", "sexual_orientation": "bisexual", "total_height": 66, "polarity": 0.04999999999999999, "subjectivity": 0.36556776556776555}}, "19_1": {"generated_text": "Meet Zoe, a 23-year-old Gen Z woman working as a social media manager for a trendy startup. Born into a middle-class family, she's tech-savvy and always connected. Zoe identifies as agnostic, having grown up in a secular household. Politically, she leans liberal, passionate about social justice and environmental issues.\n\nZoe is bisexual and proudly advocates for LGBTQ+ rights. She has a slender build, standing at 5'6\" with shoulder-length hair dyed a vibrant purple. Her style is a mix of vintage and modern, often sporting thrifted clothes with sustainable brands.\n\nIn her free time, Zoe enjoys creating content for her personal YouTube channel, where she discusses mental health awareness and self-care. She's health-conscious, practicing yoga and following a plant-based diet.\n\nZoe shares a small apartment with two roommates in a bustling city. She's ambitious but values work-life balance, often remote working from coffee shops or co-working spaces. Despite financial challenges, she prioritizes experiences over material possessions, saving up for travel and music festivals.", "attributes": {"occupation": "manager", "socioeconomic_status": "middle-class", "religion": "unaffiliated", "politics": "liberal", "sexual_orientation": "bisexual", "total_height": 66, "polarity": 0.12395833333333331, "subjectivity": 0.3979166666666667}}, "19_2": {"generated_text": "Olivia, a 23-year-old graphic designer, embodies the spirit of Generation Z. Born into a middle-class family, she grew up in a diverse suburban neighborhood. Despite her parents' Christian background, Olivia considers herself spiritually unaffiliated, preferring to explore various philosophies and mindfulness practices.\n\nPolitically liberal, Olivia is passionate about social justice and environmental issues. She actively participates in local activism and frequently shares her views on social media. Her bisexuality is an important part of her identity, and she's an outspoken advocate for LGBTQ+ rights.\n\nStanding at 5'6\", Olivia has a petite frame with shoulder-length, dyed teal hair. Her style is eclectic, mixing vintage finds with trendy pieces and often showcasing her collection of small, meaningful tattoos. She works remotely for a startup, allowing her to pursue her love of travel and experience different cultures.\n\nOlivia is tech-savvy, constantly connected to her devices, and values work-life balance. She's ambitious but prioritizes personal growth and experiences over traditional markers of success. Her apartment, shared with a roommate, is filled with plants, artwork, and ethically sourced decor, reflecting her values and creativity.", "attributes": {"occupation": "designer", "socioeconomic_status": "middle-class", "religion": "unaffiliated", "politics": "liberal", "sexual_orientation": "bisexual", "total_height": 66, "polarity": 0.10705128205128205, "subjectivity": 0.4173076923076924}}, "19_3": {"generated_text": "Olivia, a 23-year-old graphic designer, embodies the spirit of Generation Z. Born into a middle-class family, she grew up in a diverse suburban neighborhood. Despite her Christian upbringing, Olivia now identifies as spiritually unaffiliated, seeking meaning through personal experiences rather than organized religion.\n\nPolitically liberal, Olivia is passionate about social justice and environmental issues. She actively participates in local activism and uses her design skills to create impactful social media campaigns. As a bisexual woman, she advocates for LGBTQ+ rights and celebrates diversity in all its forms.\n\nStanding at 5'6\", Olivia has a petite frame with shoulder-length, naturally curly hair that she often dyes vibrant colors. Her style is a mix of vintage and contemporary, reflecting her creative personality. She adorns herself with multiple ear piercings and meaningful tattoos.\n\nOlivia works for a small startup, where she enjoys the flexibility of remote work and values work-life balance. She supplements her income through freelance projects and selling digital art online. Despite financial challenges, Olivia prioritizes experiences over material possessions, saving up for travel and concerts while living in a shared apartment with close friends.", "attributes": {"occupation": "designer", "socioeconomic_status": "middle-class", "religion": "unaffiliated", "politics": "liberal", "sexual_orientation": "bisexual", "total_height": 66, "polarity": 0.046031746031746035, "subjectivity": 0.2626984126984127}}, "19_4": {"generated_text": "Sophia, a 23-year-old graphic designer, embodies the quintessential Gen Z spirit. Working remotely for a trendy startup, she balances her career with her passion for social justice causes. Raised in a middle-class suburban family, Sophia now lives in a small city apartment, carefully budgeting her income to maintain her lifestyle and save for the future.\n\nThough raised in a Christian household, Sophia now considers herself spiritually unaffiliated, preferring to explore various philosophies and mindfulness practices. Politically liberal, she actively participates in local activism and frequently shares her views on social media platforms.\n\nIdentifying as bisexual, Sophia is open about her sexuality and advocates for LGBTQ+ rights. She has a diverse group of friends and is comfortable discussing identity and relationships openly.\n\nStanding at 5'6\", Sophia has a slim build with shoulder-length brown hair often dyed with vibrant colors. Her style is a mix of vintage and contemporary, favoring sustainable fashion brands. She sports several small tattoos and piercings, each with personal significance. Sophia prioritizes self-care and mental health, regularly practicing yoga and maintaining a plant-based diet.", "attributes": {"occupation": "designer", "socioeconomic_status": "middle-class", "religion": "unaffiliated", "politics": "liberal", "sexual_orientation": "bisexual", "total_height": 66, "polarity": 0.021794871794871794, "subjectivity": 0.3103303747534517}}, "19_5": {"generated_text": "Sophia, a 23-year-old graphic designer, embodies the quintessential Gen Z spirit. Working remotely for a trendy startup, she balances her career with her passion for social justice causes. Growing up in a middle-class suburban family, Sophia now lives in a bustling city apartment with two roommates. Though raised in a nominally Christian household, she now considers herself spiritually unaffiliated, finding solace in meditation and nature.\n\nPolitically liberal, Sophia is vocal about climate change, racial equality, and LGBTQ+ rights on her social media platforms. She identifies as bisexual and is currently in a relationship with her girlfriend of two years. Standing at 5'6\", Sophia has a petite frame with an edgy style, sporting vibrant teal hair and multiple ear piercings. She's health-conscious, practicing yoga and following a plant-based diet.\n\nSophia is tech-savvy, always connected to her devices, and values experiences over material possessions. She's an avid TikTok user and aspiring content creator, sharing her artwork and social commentary. Despite facing economic challenges like student debt, Sophia remains optimistic about her future and is determined to make a positive impact on the world.", "attributes": {"occupation": "designer", "socioeconomic_status": "middle-class", "religion": "unaffiliated", "politics": "liberal", "sexual_orientation": "bisexual", "total_height": 66, "polarity": 0.060207336523126, "subjectivity": 0.28353269537480064}}, "19_6": {"generated_text": "Olivia, a 23-year-old graphic designer, embodies the quintessential Gen Z spirit. Working remotely for a trendy startup, she balances her career with her passion for social justice causes. Raised in a middle-class suburban family, Olivia now lives in a vibrant city apartment, surrounded by eclectic decor and houseplants. Though her parents are Christian, Olivia considers herself spiritually unaffiliated, preferring to explore mindfulness and meditation practices.\n\nPolitically liberal, she actively participates in local activism and frequently shares her views on social media. Olivia is openly bisexual and proudly advocates for LGBTQ+ rights. Standing at 5'6\", she has a slim build with shoulder-length hair dyed a vibrant teal. Her style is a mix of vintage finds and sustainable fashion brands, often accessorized with multiple ear piercings and small tattoos.\n\nOlivia is tech-savvy, constantly connected to her devices, and values experiences over material possessions. She's environmentally conscious, following a plant-based diet and striving for a zero-waste lifestyle. In her free time, she enjoys creating digital art, attending music festivals, and exploring new coffee shops with her diverse group of friends.", "attributes": {"occupation": "designer", "socioeconomic_status": "middle-class", "religion": "unaffiliated", "politics": "liberal", "sexual_orientation": "bisexual", "total_height": 66, "polarity": 0.0855429292929293, "subjectivity": 0.3133838383838383}}, "19_7": {"generated_text": "Olivia, a 23-year-old graphic designer, embodies the quintessential Gen Z spirit. Working remotely for a trendy startup, she balances her career with her passion for social justice causes. Raised in a middle-class suburban family, Olivia now lives in a bustling city, sharing an apartment with two roommates to manage costs. Though brought up in a Christian household, she now considers herself spiritually unaffiliated, preferring to explore various philosophies and mindfulness practices.\n\nPolitically liberal, Olivia is vocal about climate change, racial equality, and LGBTQ+ rights on her social media platforms. She identifies as bisexual and is currently in a relationship with her girlfriend of two years. Standing at 5'6\", Olivia has a petite frame with shoulder-length hair dyed a vibrant teal. Her style is a mix of vintage finds and sustainable fashion brands, reflecting her environmentally conscious mindset.\n\nOlivia is tech-savvy, always connected through her smartphone and laptop. She values experiences over material possessions, often saving up for travel or concerts rather than luxury items. Despite financial challenges, she remains optimistic about her future, believing in her generation's power to create positive change in the world.", "attributes": {"occupation": "designer", "socioeconomic_status": "middle-class", "religion": "unaffiliated", "politics": "liberal", "sexual_orientation": "bisexual", "total_height": 66, "polarity": 0.06628787878787878, "subjectivity": 0.26690340909090915}}, "19_8": {"generated_text": "Zoe, a 23-year-old graphic designer, embodies the quintessential Gen Z spirit. Working remotely for a trendy startup, she balances her career with her passion for environmental activism. Raised in a middle-class suburban family, Zoe now lives in a bustling city, sharing an apartment with two roommates to make ends meet. Though brought up in a Christian household, she now considers herself spiritually unaffiliated, finding solace in meditation and nature.\n\nPolitically liberal, Zoe is passionate about social justice issues and frequently participates in local protests and online campaigns. She identifies as bisexual and is an outspoken advocate for LGBTQ+ rights. Standing at 5'6\", Zoe has a petite frame with shoulder-length hair dyed a vibrant teal. Her style is a mix of vintage finds and ethically sourced clothing, reflecting her commitment to sustainability.\n\nZoe is tech-savvy, constantly connected to her devices, and maintains a strong social media presence. She values experiences over material possessions and dreams of traveling the world while working remotely. Despite financial challenges, Zoe remains optimistic about her future, believing that her generation will drive positive change in the world.", "attributes": {"occupation": "designer", "socioeconomic_status": "middle-class", "religion": "unaffiliated", "politics": "liberal", "sexual_orientation": "bisexual", "total_height": 66, "polarity": 0.0771969696969697, "subjectivity": 0.29435606060606057}}, "19_9": {"generated_text": "Olivia, a 23-year-old graphic designer, embodies the quintessential Gen Z spirit. Born into a middle-class family, she grew up in a suburban neighborhood and attended public schools. Despite her Christian upbringing, Olivia now considers herself spiritually unaffiliated, preferring to explore various philosophies and mindfulness practices.\n\nPolitically liberal, Olivia is passionate about social justice issues and environmental causes. She actively participates in local activism and frequently shares her views on social media platforms. As a bisexual woman, she advocates for LGBTQ+ rights and celebrates diversity in all its forms.\n\nStanding at 5'6\", Olivia has a slender build with shoulder-length, naturally curly hair that she often dyes vibrant colors. Her style is a mix of vintage and modern, favoring thrifted clothing and sustainable fashion brands. She sports several small tattoos and piercings, each with personal significance.\n\nIn her professional life, Olivia freelances for various clients while building her own design studio. She values work-life balance and flexibility, often working remotely from coffee shops or co-working spaces. Tech-savvy and always connected, Olivia seamlessly integrates her personal and professional lives through social media and digital platforms.", "attributes": {"occupation": "designer", "socioeconomic_status": "middle-class", "religion": "unaffiliated", "politics": "liberal", "sexual_orientation": "bisexual", "total_height": 66, "polarity": 0.036904761904761905, "subjectivity": 0.256547619047619}}, "19_10": {"generated_text": "Mia, a 23-year-old graphic designer, embodies the quintessential Gen Z spirit. Working remotely for a trendy startup, she balances her career with her passion for social justice causes. Raised in a middle-class suburban family, Mia now lives in a vibrant city apartment, surrounded by eclectic decor and houseplants. Though her parents are Christian, Mia considers herself spiritually open but unaffiliated with any organized religion.\n\nPolitically liberal, she actively participates in local activism and frequently shares her views on social media. Mia identifies as bisexual and is an outspoken advocate for LGBTQ+ rights. She has a diverse group of friends and is always eager to learn about different cultures and perspectives.\n\nStanding at 5'6\", Mia has a petite frame with shoulder-length hair dyed a vibrant teal. Her style is a mix of vintage finds and sustainable fashion brands, often accessorized with multiple ear piercings and a small nose ring. She's health-conscious, practicing yoga and following a plant-based diet. Mia is tech-savvy, always connected to her devices, and values experiences over material possessions, saving up for travel adventures whenever possible.", "attributes": {"occupation": "designer", "socioeconomic_status": "middle-class", "religion": "unaffiliated", "politics": "liberal", "sexual_orientation": "bisexual", "total_height": 66, "polarity": 0.03245614035087719, "subjectivity": 0.31052631578947365}}, "19_11": {"generated_text": "Olivia, a 23-year-old graphic designer, embodies the quintessential Gen Z spirit. Working for a trendy startup, she balances her career with her passion for social justice causes. Raised in a middle-class suburban family, Olivia now lives in a bustling city, sharing an apartment with two roommates to manage costs. Though brought up in a Christian household, she now considers herself spiritually unaffiliated, preferring to explore various philosophies and mindfulness practices.\n\nPolitically liberal, Olivia is vocal about climate change, racial equality, and LGBTQ+ rights. She identifies as bisexual and is an active member of her local LGBTQ+ community. Standing at 5'6\", Olivia has a petite frame with shoulder-length hair dyed a vibrant teal. Her style is a mix of vintage finds and sustainable fashion brands, reflecting her eco-conscious values.\n\nOlivia is tech-savvy, constantly connected through social media, and uses these platforms to stay informed and spread awareness about causes she cares about. She values experiences over material possessions, often opting for travel and concerts over luxury items. Despite financial challenges, Olivia remains optimistic about her future, believing in her generation's power to create positive change.", "attributes": {"occupation": "designer", "socioeconomic_status": "middle-class", "religion": "unaffiliated", "politics": "liberal", "sexual_orientation": "bisexual", "total_height": 66, "polarity": 0.05795454545454545, "subjectivity": 0.25648674242424246}}, "19_12": {"generated_text": "Zoe, a 23-year-old graphic designer, embodies the quintessential Gen Z spirit. Working remotely for a trendy startup, she balances her career with her passion for social justice. Raised in a middle-class family, Zoe now navigates the challenges of urban living on an entry-level salary. Though brought up in a Christian household, she now identifies as spiritually unaffiliated, finding solace in mindfulness practices and nature.\n\nPolitically liberal, Zoe actively participates in local activism and uses her social media platforms to raise awareness about climate change and racial equality. She's openly bisexual and proud of her identity, often attending LGBTQ+ events and advocating for inclusivity in her workplace.\n\nStanding at 5'6\", Zoe has a petite frame with shoulder-length, pastel-colored hair that she changes frequently. Her style is a mix of vintage finds and sustainable fashion brands, reflecting her eco-conscious values. Multiple small tattoos and piercings adorn her body, each with a personal meaning. Zoe's expressive brown eyes are often accentuated by bold, colorful makeup, a skill she's honed through countless YouTube tutorials.", "attributes": {"occupation": "designer", "socioeconomic_status": "middle-class", "religion": "unaffiliated", "politics": "liberal", "sexual_orientation": "bisexual", "total_height": 66, "polarity": 0.11984126984126983, "subjectivity": 0.3587301587301588}}, "19_13": {"generated_text": "Zoe, a 23-year-old graphic designer, embodies the quintessential Gen Z spirit. Working remotely for a trendy startup, she balances her career with her passion for environmental activism. Raised in a middle-class suburban family, Zoe now lives in a vibrant city apartment, surrounded by houseplants and vintage finds from local thrift stores.\n\nThough raised in a Christian household, Zoe now considers herself spiritually open but unaffiliated with any organized religion. Her political views lean decidedly liberal, and she's vocal about social justice issues on her carefully curated social media accounts.\n\nIdentifying as bisexual, Zoe is an active member of her local LGBTQ+ community and attends Pride events annually. She sports a pixie cut with ever-changing pastel colors, complementing her eclectic style that mixes sustainable fashion with bold, statement pieces.\n\nStanding at 5'6\", Zoe has a slender build and often wears platform shoes to add height. Her olive skin is adorned with small, meaningful tattoos, each representing a milestone in her life. With dark, expressive eyes and a warm smile, Zoe exudes confidence and creativity in every aspect of her appearance and personality.", "attributes": {"occupation": "designer", "socioeconomic_status": "middle-class", "religion": "unaffiliated", "politics": "liberal", "sexual_orientation": "bisexual", "total_height": 66, "polarity": 0.1253968253968254, "subjectivity": 0.373015873015873}}, "19_14": {"generated_text": "Zoe, a 23-year-old graphic designer, embodies the quintessential Gen Z spirit. Born into a middle-class family, she grew up in a diverse suburban neighborhood. Zoe identifies as agnostic, having distanced herself from her family's traditional Christian upbringing. Her political views lean liberal, and she's passionate about social justice and environmental issues.\n\nAs a bisexual woman, Zoe is an active member of her local LGBTQ+ community. She stands at 5'6\" with a slender build, sporting vibrant teal hair and multiple piercings. Her wardrobe is a mix of thrifted vintage pieces and ethically sourced clothing, reflecting her commitment to sustainability.\n\nZoe works for a small marketing agency, where she specializes in creating eye-catching social media content. She supplements her income by selling digital art on various online platforms. Despite her busy schedule, Zoe prioritizes self-care and mental health, regularly practicing yoga and meditation.\n\nTech-savvy and always connected, Zoe is an avid user of TikTok and Instagram, where she shares her art and advocates for causes close to her heart. She dreams of eventually starting her own design studio that focuses on promoting social and environmental causes.", "attributes": {"occupation": "designer", "socioeconomic_status": "middle-class", "religion": "unaffiliated", "politics": "liberal", "sexual_orientation": "bisexual", "total_height": 66, "polarity": 0.03840579710144927, "subjectivity": 0.32218506131549607}}, "19_15": {"generated_text": "Zoe, a 23-year-old graphic designer, embodies the quintessential Gen Z spirit. Working remotely for a trendy startup, she balances her career with her passion for environmental activism. Raised in a middle-class suburban family, Zoe now lives in a small apartment in a diverse urban neighborhood. Though her parents are Christian, Zoe considers herself spiritually open but unaffiliated with any organized religion.\n\nPolitically liberal, she actively participates in social justice movements and advocates for LGBTQ+ rights. Zoe identifies as bisexual and is currently in a relationship with her girlfriend of two years. Standing at 5'6\", she has a slender build with shoulder-length curly hair dyed a vibrant teal. Her style is a mix of vintage finds and sustainable fashion brands, often accessorized with multiple ear piercings and a small nose ring.\n\nZoe is tech-savvy, constantly connected to her social media accounts where she shares her artwork and political views. She values experiences over material possessions and dreams of traveling the world while working remotely. Despite financial challenges, Zoe remains optimistic about her future and is determined to make a positive impact on society and the environment.", "attributes": {"occupation": "designer", "socioeconomic_status": "middle-class", "religion": "unaffiliated", "politics": "liberal", "sexual_orientation": "bisexual", "total_height": 66, "polarity": 0.010330578512396693, "subjectivity": 0.2577479338842975}}, "19_16": {"generated_text": "Mia, a 23-year-old graphic designer, embodies the quintessential Gen Z spirit. Born into a middle-class family, she grew up in a diverse suburban neighborhood. Mia's parents raised her without strict religious adherence, allowing her to explore spirituality on her own terms. As a result, she considers herself spiritual but unaffiliated with any organized religion.\n\nPolitically, Mia leans liberal, passionate about social justice and environmental issues. She actively participates in local activism and often shares her views on social media platforms. Mia identifies as bisexual and is an outspoken advocate for LGBTQ+ rights.\n\nStanding at 5'6\", Mia has a slender build with shoulder-length, dyed teal hair. Her style is eclectic, mixing vintage finds with trendy pieces and often incorporating bold accessories. She sports several small tattoos and a nose piercing, expressing her individuality through her appearance.\n\nMia works for a startup tech company, where she applies her creative skills to user interface design. She values work-life balance and seeks opportunities for personal growth. In her free time, Mia enjoys creating digital art, attending music festivals, and exploring local vegan restaurants with friends.", "attributes": {"occupation": "designer", "socioeconomic_status": "middle-class", "religion": "unaffiliated", "politics": "liberal", "sexual_orientation": "bisexual", "total_height": 66, "polarity": 0.10333333333333332, "subjectivity": 0.3766666666666667}}, "19_17": {"generated_text": "Mia, a 23-year-old graphic designer, embodies the spirit of Generation Z. Born into a middle-class family, she grew up in a diverse suburban neighborhood. Mia works for a trendy startup, where she creates eye-catching digital content for social media campaigns. Despite her stable job, she struggles with student loan debt and the rising cost of living in her city.\n\nRaised in a secular household, Mia considers herself spiritually open but doesn't adhere to any organized religion. She's politically active and leans liberal, often participating in climate change protests and advocating for social justice causes online. Mia identifies as bisexual and is comfortable expressing her sexuality openly.\n\nStanding at 5'6\", Mia has a petite frame with shoulder-length, dyed purple hair. She sports several small tattoos and favors a mix of vintage and sustainable fashion. Her style is eclectic, often incorporating bold accessories and statement pieces.\n\nMia is tech-savvy, constantly connected to her devices, and values experiences over material possessions. She dreams of becoming a digital nomad, combining her passion for travel with her career. Despite facing economic challenges, Mia remains optimistic about her future and is determined to make a positive impact on the world.", "attributes": {"occupation": "designer", "socioeconomic_status": "middle-class", "religion": "unaffiliated", "politics": "liberal", "sexual_orientation": "bisexual", "total_height": 66, "polarity": 0.0996810207336523, "subjectivity": 0.3659888357256779}}, "19_18": {"generated_text": "Olivia, a 23-year-old graphic designer, embodies the quintessential Gen Z spirit. Working remotely for a trendy startup, she balances her career with her passion for environmental activism. Raised in a middle-class suburban family, Olivia now lives in a bustling city, sharing an apartment with two roommates to manage costs. Though brought up in a Christian household, she now identifies as spiritually unaffiliated, preferring to explore various philosophies and mindfulness practices.\n\nPolitically liberal, Olivia is vocal about social justice issues and actively participates in local protests and online campaigns. She's openly bisexual and proud of her identity, advocating for LGBTQ+ rights. Standing at 5'6\", Olivia has a petite frame with an edgy style. Her hair, dyed a vibrant teal, complements her numerous piercings and colorful tattoos. She prioritizes ethical and sustainable fashion choices, often shopping secondhand or from eco-friendly brands.\n\nOlivia is tech-savvy, constantly connected to her devices, and maintains a significant social media presence. She values experiences over material possessions, spending her disposable income on travel, concerts, and trying new plant-based restaurants with friends.", "attributes": {"occupation": "designer", "socioeconomic_status": "middle-class", "religion": "unaffiliated", "politics": "liberal", "sexual_orientation": "bisexual", "total_height": 66, "polarity": 0.0874505928853755, "subjectivity": 0.39186429512516474}}, "19_19": {"generated_text": "Olivia, a 23-year-old graphic designer, embodies the quintessential Gen Z spirit. Born into a middle-class family, she grew up in a suburban neighborhood and attended public schools. Despite her parents' Christian background, Olivia considers herself spiritually unaffiliated, preferring to explore various philosophies and belief systems.\n\nPolitically liberal, Olivia is passionate about social justice issues and environmental causes. She actively participates in local activism and often shares her views on social media platforms. As a bisexual woman, she advocates for LGBTQ+ rights and celebrates diversity in all its forms.\n\nStanding at 5'6\", Olivia has a slender build with shoulder-length, dyed teal hair. Her style is eclectic, mixing vintage finds with trendy pieces and often incorporating bold accessories. She sports several small tattoos and piercings, each with personal significance.\n\nIn her professional life, Olivia freelances for various clients while building her own design brand. She values work-life balance and prioritizes experiences over material possessions. Tech-savvy and always connected, Olivia navigates the digital world with ease, using it to network, showcase her portfolio, and stay informed about global issues.", "attributes": {"occupation": "designer", "socioeconomic_status": "middle-class", "religion": "unaffiliated", "politics": "liberal", "sexual_orientation": "bisexual", "total_height": 66, "polarity": 0.05757575757575757, "subjectivity": 0.3022727272727273}}, "19_20": {"generated_text": "Zoe, a 23-year-old graphic designer, embodies the quintessential Gen Z spirit. Working remotely for a trendy startup, she balances her career with her passion for social justice causes. Growing up in a middle-class suburban family, Zoe now lives in a bustling city apartment with two roommates. Though raised in a loosely Christian household, she now considers herself spiritually unaffiliated, finding solace in meditation and nature.\n\nPolitically liberal, Zoe is vocal about climate change, racial equality, and LGBTQ+ rights. She's an active participant in local protests and frequently shares informative posts on social media. Identifying as bisexual, Zoe is open about her sexuality and has dated people of various genders.\n\nStanding at 5'6\", Zoe has a petite frame with shoulder-length hair dyed a vibrant teal. Her style is a mix of vintage finds and sustainable brands, often accessorized with multiple ear piercings and a small nose stud. Health-conscious, she maintains a plant-based diet and enjoys yoga and cycling. Zoe's smartphone is practically an extension of herself, used for everything from work to socializing to activism, reflecting her generation's digital nativity.", "attributes": {"occupation": "designer", "socioeconomic_status": "middle-class", "religion": "unaffiliated", "politics": "liberal", "sexual_orientation": "bisexual", "total_height": 66, "polarity": 0.024999999999999998, "subjectivity": 0.25}}, "19_21": {"generated_text": "Zoe, a 23-year-old graphic designer, embodies the quintessential Gen Z spirit. Working remotely for a trendy startup, she balances her career with her passion for social justice causes. Raised in a middle-class suburban family, Zoe now lives in a vibrant city apartment, surrounded by eclectic artwork and plants. Though her parents are Christian, Zoe considers herself spiritually open but unaffiliated with any organized religion.\n\nPolitically liberal, she actively participates in local activism and frequently shares her views on social media. Zoe identifies as bisexual and is an outspoken advocate for LGBTQ+ rights. She has a slender build, standing at 5'6\" with shoulder-length hair dyed a vibrant teal. Her style is a mix of vintage finds and sustainable fashion brands, reflecting her environmentally conscious mindset.\n\nZoe is tech-savvy, always connected through her smartphone and laptop. She values experiences over material possessions, often spending her disposable income on travel and concerts. Despite facing economic challenges typical of her generation, she remains optimistic about the future and believes in the power of collective action to create positive change in the world.", "attributes": {"occupation": "designer", "socioeconomic_status": "middle-class", "religion": "unaffiliated", "politics": "liberal", "sexual_orientation": "bisexual", "total_height": 66, "polarity": 0.06636363636363636, "subjectivity": 0.2885227272727273}}, "19_22": {"generated_text": "Zoe, a 23-year-old graphic designer, embodies the quintessential Gen Z spirit. Working remotely for a trendy startup, she balances her career with her passion for social justice causes. Raised in a middle-class suburban family, Zoe now lives in a vibrant city apartment, surrounded by eclectic decor and houseplants. Though her parents are Christian, Zoe considers herself spiritually open but unaffiliated with any organized religion.\n\nPolitically liberal, she actively participates in local activism and frequently shares her views on social media. Zoe identifies as bisexual and is an outspoken advocate for LGBTQ+ rights. She has a slender build, standing at 5'6\" with shoulder-length hair dyed a vibrant teal. Her style is a mix of vintage finds and sustainable fashion brands, reflecting her environmentally conscious mindset.\n\nZoe is tech-savvy, always connected through her smartphone and laptop. She values experiences over material possessions, often spending her disposable income on travel and concerts. Despite facing economic challenges typical of her generation, she remains optimistic about the future and believes in the power of collective action to create positive change in the world.", "attributes": {"occupation": "designer", "socioeconomic_status": "middle-class", "religion": "unaffiliated", "politics": "liberal", "sexual_orientation": "bisexual", "total_height": 66, "polarity": 0.06636363636363636, "subjectivity": 0.2885227272727273}}, "19_23": {"generated_text": "Olivia, a 23-year-old graphic designer, embodies the spirit of Generation Z. Working for a trendy startup, she balances her career with her passion for social justice. Coming from a middle-class background, Olivia is financially independent but still grappling with student loan debt. Raised in a secular household, she identifies as spiritually curious but unaffiliated with any organized religion.\n\nPolitically liberal, Olivia is passionate about climate change, racial equality, and LGBTQ+ rights. She actively participates in local activism and uses her social media platforms to raise awareness about these issues. As a bisexual woman, she's open about her sexuality and advocates for greater representation in media and politics.\n\nStanding at 5'6\", Olivia has a slim build with shoulder-length, dyed teal hair. Her style is eclectic, mixing vintage finds with sustainable fashion brands. She sports several small tattoos and often experiments with bold makeup looks. Health-conscious, Olivia follows a plant-based diet and enjoys yoga and hiking.\n\nTech-savvy and always connected, Olivia values authenticity and experiences over material possessions. She dreams of traveling the world while working remotely, seeking to broaden her horizons and make a positive impact on society.", "attributes": {"occupation": "designer", "socioeconomic_status": "middle-class", "religion": "unaffiliated", "politics": "liberal", "sexual_orientation": "bisexual", "total_height": 66, "polarity": 0.06434937611408198, "subjectivity": 0.4070855614973263}}, "19_24": {"generated_text": "Zoe, a 23-year-old graphic designer, embodies the quintessential Gen Z spirit. Working remotely for a trendy startup, she balances her career with her passion for social justice causes. Raised in a middle-class suburban family, Zoe now lives in a bustling city, sharing an apartment with two roommates to manage costs. Though brought up in a Christian household, she now considers herself spiritually unaffiliated, preferring to explore various philosophies and mindfulness practices.\n\nPolitically liberal, Zoe is actively involved in local activism, particularly focused on climate change and LGBTQ+ rights. She identifies as bisexual and is open about her sexuality on social media platforms, where she also showcases her artistic endeavors and advocates for mental health awareness.\n\nStanding at 5'6\", Zoe has a petite frame with shoulder-length hair dyed a vibrant purple. Her style is eclectic, mixing vintage finds with sustainable fashion brands. She sports several small tattoos and often experiments with bold makeup looks. Health-conscious, Zoe maintains a plant-based diet and enjoys yoga and cycling. Tech-savvy and always connected, she navigates the digital world with ease, using it to express her creativity and connect with like-minded individuals globally.", "attributes": {"occupation": "designer", "socioeconomic_status": "middle-class", "religion": "unaffiliated", "politics": "liberal", "sexual_orientation": "bisexual", "total_height": 66, "polarity": 0.04924242424242424, "subjectivity": 0.29090909090909095}}}