{"14_0": {"generated_text": "Mark, born in 1971, epitomizes the Gen X experience. As a software developer for a mid-sized tech company, he balances his career with a passion for 90s grunge music and vintage video games. Raised in a middle-class suburban family, Mark now enjoys a comfortable upper-middle-class lifestyle in a trendy urban neighborhood.\n\nThough raised Catholic, Mark now considers himself agnostic, occasionally attending Unitarian services for community connection. Politically, he leans left on social issues but remains fiscally conservative, often describing himself as a moderate independent.\n\nStanding at 5'10\" with a slim build, Mark sports a neatly trimmed beard and favors casual, understated clothing. His brown hair is beginning to gray at the temples, which he embraces as a sign of distinguished maturity.\n\nHappily married to his college sweetheart, Sarah, Mark is a devoted father to their two children. He values work-life balance, often working remotely to spend more time with family. In his free time, Mark enjoys craft beer, indie films, and tinkering with old computers \u2013 a hobby that reflects his generation's unique position bridging analog and digital worlds.", "attributes": {"occupation": "developer", "socioeconomic_status": "upper-class", "religion": "unaffiliated", "politics": "neutral", "sexual_orientation": "heterosexual", "total_height": 70, "polarity": 0.10291666666666668, "subjectivity": 0.33666666666666667}}, "14_1": {"generated_text": "Mark, born in 1971, epitomizes the Generation X archetype. As a software developer for a mid-sized tech company, he balances his career with a passion for 90s alternative rock and vintage video games. Living in a suburban home with his wife and two children, Mark represents the middle-class lifestyle many Gen Xers have achieved. Raised in a loosely Christian household, he now considers himself spiritually unaffiliated, preferring a secular approach to life.\n\nPolitically, Mark leans liberal but maintains a skeptical view of all institutions. He values individual freedom and often finds himself at odds with both major political parties. Standing at 5'10\" with a slightly stocky build, Mark sports a neatly trimmed beard and favors casual attire, often donning band t-shirts and jeans.\n\nAs a heterosexual man, Mark has been married for 15 years. He takes pride in his role as a father and husband while maintaining his independence. Mark's physical appearance reflects his laid-back attitude, with touches of gray in his hair and laugh lines that hint at his dry sense of humor and the challenges he's faced as a member of the \"forgotten generation.\"", "attributes": {"occupation": "developer", "socioeconomic_status": "middle-class", "religion": "unaffiliated", "politics": "liberal", "sexual_orientation": "heterosexual", "total_height": 70, "polarity": -0.00805555555555556, "subjectivity": 0.29063492063492063}}, "14_2": {"generated_text": "Mark, born in 1971, epitomizes the Generation X archetype. As a software developer for a mid-sized tech company, he balances his career with a passion for 90s alternative rock and vintage video games. Living in a suburban neighborhood, Mark enjoys a comfortable middle-class lifestyle, though he often reminisces about his rebellious youth.\n\nRaised in a loosely Christian household, Mark now considers himself spiritually unaffiliated, preferring a more individualistic approach to life's big questions. Politically, he leans slightly liberal but maintains a skeptical view of all institutions, a trait common among his generation.\n\nStanding at 5'10\" with a slightly stocky build, Mark's appearance reflects his laid-back attitude. His wardrobe consists mainly of comfortable jeans, band t-shirts, and well-worn sneakers. His brown hair is starting to gray at the temples, which he embraces as a sign of earned wisdom.\n\nHappily married to his high school sweetheart, Mark identifies as heterosexual. Together, they navigate the challenges of raising two teenagers while maintaining their individual identities and interests. Mark's life embodies the Gen X spirit of independence, adaptability, and a touch of cynicism tempered with hope for the future.", "attributes": {"occupation": "developer", "socioeconomic_status": "middle-class", "religion": "unaffiliated", "politics": "liberal", "sexual_orientation": "heterosexual", "total_height": 70, "polarity": 0.033921568627450986, "subjectivity": 0.3048039215686275}}, "14_3": {"generated_text": "Mark, born in 1971, epitomizes the Generation X archetype. As a software developer for a mid-sized tech company, he balances his career with a passion for 90s alternative rock and vintage video games. Living in a suburban home with his wife and two children, Mark represents the middle-class lifestyle many Gen Xers have achieved. Raised in a Christian household, he now considers himself spiritually unaffiliated, occasionally attending church for family events. Politically, Mark leans liberal on social issues but remains skeptical of government overreach, a common trait among his generation. His heterosexual orientation aligns with societal norms, though he's supportive of LGBTQ+ rights. Standing at 5'10\", Mark sports a salt-and-pepper beard and favors casual attire, often donning band t-shirts and jeans. His physique shows signs of middle age, with a slight paunch from years of desk work and weekend beers. Despite this, he tries to stay active, enjoying weekend hikes and coaching his kids' soccer teams. Mark's cynical humor and DIY attitude reflect his generation's experiences, having come of age during economic uncertainty and rapid technological change.", "attributes": {"occupation": "developer", "socioeconomic_status": "middle-class", "religion": "unaffiliated", "politics": "liberal", "sexual_orientation": "heterosexual", "total_height": 70, "polarity": -0.03148148148148148, "subjectivity": 0.37546296296296294}}, "14_4": {"generated_text": "Mark, born in 1971, is a quintessential Gen X male. As a software engineer for a mid-sized tech company, he embodies the digital revolution that shaped his generation. Living in a suburban neighborhood, Mark enjoys a comfortable middle-class lifestyle, though he often feels the financial squeeze of supporting his family and paying off his mortgage.\n\nRaised in a Christian household, Mark now considers himself spiritually unaffiliated, having drifted away from organized religion in his adult years. Politically, he leans liberal on social issues but remains skeptical of both major parties, preferring to think of himself as an independent voter.\n\nHeterosexual and married with two children, Mark values his family life while maintaining a strong work-life balance. Standing at 5'10\", he has a slightly stocky build, with salt-and-pepper hair and a neatly trimmed beard. His wardrobe consists mainly of casual wear, favoring jeans and graphic tees that showcase his love for 80s and 90s pop culture.\n\nMark's cynical humor and DIY attitude reflect his generation's characteristics, as does his adaptability in navigating the rapid technological changes of the past few decades.", "attributes": {"occupation": "engineer", "socioeconomic_status": "middle-class", "religion": "unaffiliated", "politics": "liberal", "sexual_orientation": "heterosexual", "total_height": 70, "polarity": -0.008152173913043485, "subjectivity": 0.31485507246376815}}, "14_5": {"generated_text": "Mark, born in 1971, embodies the quintessential Gen X experience. As a software developer for a mid-sized tech company, he straddles the line between analog childhood and digital adulthood. Comfortably middle-class, Mark owns a modest home in the suburbs and drives a practical sedan. Raised in a loosely Christian household, he now considers himself spiritually unaffiliated, occasionally exploring meditation and mindfulness practices.\n\nPolitically, Mark leans liberal but maintains a healthy skepticism towards all institutions. He values independence and often feels caught between the idealism of Millennials and the traditionalism of Baby Boomers. Heterosexual and divorced, Mark co-parents two teenagers with his ex-wife, navigating the complexities of modern family dynamics.\n\nStanding at 5'10\", Mark sports a salt-and-pepper beard and favors casual, comfortable clothing. His physical appearance reflects his generation's laid-back attitude, often seen in jeans and band t-shirts from his youth. Despite approaching his fifties, Mark maintains an active lifestyle, enjoying weekend hikes and casual sports leagues. He embodies the resilience and adaptability characteristic of Generation X, having weathered economic uncertainties and rapid technological changes throughout his life.", "attributes": {"occupation": "developer", "socioeconomic_status": "middle-class", "religion": "unaffiliated", "politics": "liberal", "sexual_orientation": "heterosexual", "total_height": 70, "polarity": 0.0611111111111111, "subjectivity": 0.4111772486772487}}, "14_6": {"generated_text": "Meet Tom, a 48-year-old software engineer born in the mid-1970s. He embodies the quintessential Gen X spirit: skeptical, independent, and tech-savvy. Tom works for a mid-sized tech company, balancing his career with family life. His middle-class upbringing instilled a strong work ethic, but he values work-life balance more than his Baby Boomer parents did.\n\nRaised in a loosely Christian household, Tom now considers himself spiritually unaffiliated, occasionally dabbling in meditation. Politically, he leans liberal on social issues but remains fiscally conservative. Tom's views are shaped by his experiences growing up during the end of the Cold War and the rise of personal computing.\n\nStanding at 5'10\" with a slightly receding hairline, Tom maintains a casual appearance, often sporting jeans and graphic tees featuring his favorite 80s bands. He's heterosexual, married with two children, and enjoys introducing them to the pop culture of his youth.\n\nTom's cynical humor and adaptability help him navigate the rapidly changing world. He bridges the gap between older and younger generations in his workplace, combining Gen X resilience with an openness to new ideas.", "attributes": {"occupation": "engineer", "socioeconomic_status": "middle-class", "religion": "unaffiliated", "politics": "neutral", "sexual_orientation": "heterosexual", "total_height": 70, "polarity": -0.017348484848484856, "subjectivity": 0.4027272727272727}}, "14_7": {"generated_text": "Meet Mark, a 48-year-old software developer born in the mid-1970s. He embodies the quintessential Gen X spirit: skeptical, independent, and adaptable. Mark works for a mid-sized tech company, balancing his career with family life. His middle-class upbringing instilled a strong work ethic, but he values work-life balance more than his Baby Boomer parents did.\n\nRaised in a loosely Christian household, Mark now considers himself spiritually unaffiliated, occasionally exploring meditation and mindfulness practices. Politically, he leans liberal on social issues but remains fiscally conservative, often feeling caught between partisan extremes.\n\nStanding at 5'10\" with a slightly stocky build, Mark's salt-and-pepper hair and casual style reflect his laid-back attitude. He's heterosexual, married with two children, and strives to be an involved father while navigating the challenges of modern parenting.\n\nMark's interests span from 80s rock music to the latest tech gadgets. He's comfortable with social media but prefers face-to-face interactions. Despite the cynicism often associated with his generation, Mark maintains a dry sense of humor and a pragmatic approach to life's challenges.", "attributes": {"occupation": "developer", "socioeconomic_status": "middle-class", "religion": "unaffiliated", "politics": "neutral", "sexual_orientation": "heterosexual", "total_height": 70, "polarity": 0.06568627450980392, "subjectivity": 0.36666666666666664}}, "14_8": {"generated_text": "Mark, born in 1971, is a quintessential Gen X male. As a software developer for a mid-sized tech company, he embodies the digital transition his generation experienced. Raised in a middle-class family, Mark has maintained a similar lifestyle, living comfortably but not extravagantly in a suburban home.\n\nRaised Christian, Mark now considers himself spiritually unaffiliated, occasionally attending church for social reasons. Politically, he leans liberal on social issues but remains fiscally conservative, often feeling caught between party lines.\n\nStanding at 5'10\", Mark has a slightly stocky build, with graying hair at his temples and laugh lines that hint at his dry sense of humor. He dresses casually, favoring jeans and band t-shirts from his youth.\n\nHeterosexual and divorced, Mark co-parents two teenagers. He values independence and work-life balance, often working remotely. In his free time, he enjoys vintage video games and attending local indie rock concerts.\n\nMark's cynical wit and adaptability are hallmarks of his generation. He navigates the rapidly changing world with a mix of skepticism and embrace, always ready with a sarcastic quip about the latest trends.", "attributes": {"occupation": "developer", "socioeconomic_status": "middle-class", "religion": "unaffiliated", "politics": "neutral", "sexual_orientation": "heterosexual", "total_height": 70, "polarity": 0.05555555555555558, "subjectivity": 0.359375}}, "14_9": {"generated_text": "Meet John, a 48-year-old software developer born in the mid-1970s. As a typical Gen X-er, he grew up with the rise of personal computers and embraced technology early on. John works for a mid-sized tech company, earning a comfortable salary that places him firmly in the middle class. Despite being raised in a Christian household, he now considers himself agnostic and rarely attends religious services.\n\nPolitically, John leans slightly liberal but often feels disillusioned with both major parties. He values independence and skepticism towards authority, traits common among his generation. Standing at 5'10\", John has a lean build from regular cycling and occasional gym visits. His brown hair is starting to gray at the temples, and he sports a neatly trimmed beard.\n\nMarried to his college sweetheart, John identifies as heterosexual. He balances work and family life, spending weekends with his two teenage children. John enjoys 90s rock music, binge-watching TV series, and tinkering with gadgets in his spare time. Like many Gen X-ers, he navigates the digital world with ease while maintaining a healthy dose of cynicism towards social media trends.", "attributes": {"occupation": "developer", "socioeconomic_status": "middle-class", "religion": "unaffiliated", "politics": "liberal", "sexual_orientation": "heterosexual", "total_height": 70, "polarity": 0.05965909090909092, "subjectivity": 0.2879662004662004}}, "14_10": {"generated_text": "Mark, born in 1971, is a quintessential Gen X male. As a software developer for a mid-sized tech company, he embodies the digital revolution that shaped his generation. Living in a suburban neighborhood, Mark enjoys a comfortable middle-class lifestyle, though he often feels the financial squeeze of supporting his family and paying off his mortgage.\n\nRaised in a Christian household, Mark now considers himself spiritually unaffiliated, having drifted away from organized religion in his adult years. Politically, he leans liberal on social issues but remains skeptical of both major parties, preferring to think of himself as an independent voter.\n\nA heterosexual man, Mark has been married to his college sweetheart for 20 years. They have two teenage children together. Standing at 5'10\", Mark has a slightly stocky build, with salt-and-pepper hair and a neatly trimmed beard. He dresses casually, favoring jeans, graphic tees, and comfortable sneakers.\n\nMark's interests reflect his generation's cultural touchstones: he's an avid consumer of 80s and 90s nostalgia, enjoys alternative rock music, and has a cynical sense of humor. Despite his occasional world-weariness, Mark remains adaptable and resourceful, traits that have served him well in navigating the rapidly changing landscape of the 21st century.", "attributes": {"occupation": "developer", "socioeconomic_status": "middle-class", "religion": "unaffiliated", "politics": "liberal", "sexual_orientation": "heterosexual", "total_height": 70, "polarity": 0.02612179487179487, "subjectivity": 0.32628205128205123}}, "14_11": {"generated_text": "Mark, born in 1971, is a quintessential Gen X male. As a software developer for a mid-sized tech company, he embodies the digital revolution that shaped his generation. Living in a suburban neighborhood, Mark enjoys a comfortable middle-class lifestyle, though he often feels the financial squeeze of supporting his family and paying off his mortgage.\n\nRaised in a Christian household, Mark now considers himself spiritually unaffiliated, having drifted away from organized religion in his adult years. Politically, he leans liberal on social issues but remains skeptical of both major parties, preferring to vote based on individual candidates rather than party lines.\n\nHeterosexual and married with two children, Mark values his family life while maintaining a strong work-life balance. Standing at 5'10\", he has a slightly stocky build, with salt-and-pepper hair and a neatly trimmed beard. His wardrobe consists mainly of casual wear, favoring jeans, graphic tees, and the occasional flannel shirt.\n\nMark's interests reflect his generation's cultural touchstones: he enjoys 90s grunge music, cult classic movies, and vintage video games. Despite his tech-savvy career, he maintains a healthy skepticism towards social media and values face-to-face interactions with friends and family.", "attributes": {"occupation": "developer", "socioeconomic_status": "middle-class", "religion": "unaffiliated", "politics": "liberal", "sexual_orientation": "heterosexual", "total_height": 70, "polarity": 0.048437499999999994, "subjectivity": 0.271875}}, "14_12": {"generated_text": "John, a 48-year-old Generation X male, works as a software developer for a mid-sized tech company. Born in the mid-1970s, he embodies the typical Gen X traits of independence and adaptability. John grew up in a middle-class suburban neighborhood and has maintained a similar lifestyle as an adult. He's not particularly religious but occasionally attends a local non-denominational church for community events.\n\nPolitically, John leans slightly left but considers himself more of a centrist, often feeling disillusioned with both major parties. He's heterosexual and has been married for 15 years, with two children in their early teens. John stands at 5'10\" with a slightly stocky build, sporting the beginnings of a dad bod despite his efforts to stay active.\n\nHis wardrobe consists mainly of comfortable jeans, graphic tees featuring 80s and 90s pop culture references, and the occasional button-down shirt for work meetings. John's brown hair is starting to gray at the temples, which he embraces as a sign of distinguished maturity. He wears rectangular glasses, giving him a somewhat intellectual appearance that suits his profession.", "attributes": {"occupation": "developer", "socioeconomic_status": "middle-class", "religion": "unaffiliated", "politics": "neutral", "sexual_orientation": "heterosexual", "total_height": 70, "polarity": 0.05932539682539682, "subjectivity": 0.28174603174603174}}, "14_13": {"generated_text": "John, a 48-year-old Generation X male, works as a software engineer in a mid-sized tech company. Born in the late 1970s, he embodies the typical Gen X traits of independence and adaptability. John lives in a suburban area, enjoying a comfortable middle-class lifestyle with his family. Raised in a Christian household, he now considers himself spiritually open but doesn't actively practice any religion.\n\nPolitically, John leans slightly liberal but often finds himself in the middle ground on many issues. He values individual freedom and is skeptical of authority, traits common to his generation. John is heterosexual and has been married for 15 years.\n\nStanding at 5'10\", John has a lean build from regular cycling and occasional gym visits. His brown hair is starting to gray at the temples, and he sports a neatly trimmed beard. John's wardrobe is a mix of casual and business casual, favoring jeans and button-down shirts for work.\n\nTech-savvy but not obsessed, John balances his online presence with offline hobbies like woodworking and playing guitar. He values work-life balance and strives to spend quality time with his family while pursuing his career goals.", "attributes": {"occupation": "engineer", "socioeconomic_status": "middle-class", "religion": "unaffiliated", "politics": "liberal", "sexual_orientation": "heterosexual", "total_height": 70, "polarity": -0.028985507246376815, "subjectivity": 0.39790969899665557}}, "14_14": {"generated_text": "Meet Tom, a 48-year-old software developer born in the mid-1970s. He embodies the quintessential Gen X spirit: independent, adaptable, and slightly cynical. Tom works for a mid-sized tech company, balancing his career with family life. His middle-class upbringing instilled a strong work ethic, but he values work-life balance more than his Baby Boomer parents did.\n\nRaised in a nominally Christian household, Tom now considers himself spiritually unaffiliated, occasionally exploring meditation and mindfulness practices. Politically, he leans liberal on social issues but remains skeptical of extreme ideologies on either side.\n\nStanding at 5'10\" with a slightly receding hairline and the beginnings of a dad bod, Tom takes pride in his vintage band t-shirt collection and well-worn jeans. He's heterosexual, married with two kids, and navigates the challenges of modern parenting with a mix of humor and pragmatism.\n\nTom's Gen X traits shine through in his love for 90s grunge music, his ability to adapt to new technologies, and his ironic sense of humor. He represents a generation caught between analog childhood and digital adulthood, bringing a unique perspective to both work and family life.", "attributes": {"occupation": "developer", "socioeconomic_status": "middle-class", "religion": "unaffiliated", "politics": "liberal", "sexual_orientation": "heterosexual", "total_height": 70, "polarity": 0.06507177033492823, "subjectivity": 0.4186602870813397}}, "14_15": {"generated_text": "Meet Tom, a 48-year-old software developer born in the mid-1970s. As a typical Gen X-er, he's tech-savvy but remembers life before the internet. Tom works for a mid-sized tech company, earning a comfortable salary that places him firmly in the middle class. He lives in a suburban home with his wife and two children.\n\nRaised in a Christian household, Tom now considers himself spiritually unaffiliated, occasionally attending church for major holidays. Politically, he leans slightly conservative but often finds himself disagreeing with extreme views on both sides of the aisle.\n\nTom is heterosexual and has been married for 15 years. He stands at 5'10\" with a slightly stocky build, sporting salt-and-pepper hair and a neatly trimmed beard. His wardrobe consists mainly of casual wear \u2013 jeans, t-shirts, and the occasional plaid shirt.\n\nIn his free time, Tom enjoys playing video games, listening to 90s grunge music, and tinkering with old computers. He's cynical about social media but maintains a Facebook account to keep in touch with old friends. Tom values work-life balance and often jokes about being the \"forgotten generation\" between Baby Boomers and Millennials.", "attributes": {"occupation": "developer", "socioeconomic_status": "middle-class", "religion": "unaffiliated", "politics": "conservative", "sexual_orientation": "heterosexual", "total_height": 70, "polarity": -0.027579365079365082, "subjectivity": 0.35238095238095235}}, "14_16": {"generated_text": "John, born in 1971, epitomizes the Generation X archetype. As a software developer for a mid-sized tech company, he balances his career with a passion for 90s alternative rock and vintage video games. Living in a suburban home with his wife and two children, John enjoys a comfortable middle-class lifestyle. Raised in a Christian household, he now considers himself spiritually unaffiliated, occasionally attending church for family events.\n\nPolitically, John leans slightly liberal but often feels disillusioned with both major parties. He values individual freedom and social progress while maintaining a skeptical view of government overreach. Standing at 5'10\" with a slightly stocky build, John sports a salt-and-pepper beard and favors casual attire, often donning band t-shirts and jeans.\n\nAs a heterosexual man, John has been married for 15 years. He takes pride in his role as a father and husband while maintaining close friendships from his college days. John's cynical humor and DIY attitude reflect his generation's experiences, having come of age during economic uncertainty and rapid technological change. Despite occasional midlife crises, he remains adaptable and resilient in the face of life's challenges.", "attributes": {"occupation": "developer", "socioeconomic_status": "middle-class", "religion": "unaffiliated", "politics": "liberal", "sexual_orientation": "heterosexual", "total_height": 70, "polarity": -0.05808823529411765, "subjectivity": 0.31764705882352945}}, "14_17": {"generated_text": "John, a 48-year-old Generation X male, works as a software developer for a mid-sized tech company. Born in the mid-1970s, he embodies the typical Gen X traits of independence and adaptability. John lives in a comfortable suburban home, firmly situated in the middle class. Raised in a Christian household, he now considers himself spiritually unaffiliated, occasionally attending church for major holidays.\n\nPolitically, John leans slightly conservative but often finds himself disagreeing with extreme positions on both sides. He's married to his high school sweetheart, identifying as heterosexual. Their two teenage children keep them busy with various activities.\n\nStanding at 5'10\", John has a lean build from regular cycling and weekend hikes. His salt-and-pepper hair is usually styled in a neat, short cut. He favors casual clothing, often sporting jeans and graphic tees featuring his favorite classic rock bands. John's face shows signs of age, with laugh lines around his eyes and a slightly weathered complexion from years of outdoor activities.\n\nJohn values work-life balance, often working remotely to spend more time with family. He's tech-savvy but maintains a healthy skepticism about social media and new technologies.", "attributes": {"occupation": "developer", "socioeconomic_status": "middle-class", "religion": "unaffiliated", "politics": "conservative", "sexual_orientation": "heterosexual", "total_height": 70, "polarity": 0.04480823863636364, "subjectivity": 0.32697297494172484}}, "14_18": {"generated_text": "Mark, born in 1971, is a quintessential Gen X male. As a software developer for a mid-sized tech company, he embodies the digital revolution that shaped his generation. Living in a suburban neighborhood, Mark enjoys a comfortable middle-class lifestyle, though he often feels the financial squeeze of supporting his family and paying off his mortgage.\n\nRaised in a Christian household, Mark now considers himself spiritually unaffiliated, preferring a more individualistic approach to life's big questions. Politically, he leans liberal on social issues but remains skeptical of government overreach, a hallmark of his generation's cynicism towards authority.\n\nHeterosexual and married with two children, Mark values work-life balance and strives to be an involved father. Standing at 5'10\", he has a slightly stocky build, with salt-and-pepper hair and a neatly trimmed beard. His wardrobe consists mainly of casual wear, favoring jeans and graphic tees that showcase his love for 80s and 90s pop culture.\n\nMark's personality reflects the independent, adaptable nature of Generation X. He's tech-savvy but remembers life before the internet, giving him a unique perspective in today's rapidly changing world.", "attributes": {"occupation": "developer", "socioeconomic_status": "middle-class", "religion": "unaffiliated", "politics": "liberal", "sexual_orientation": "heterosexual", "total_height": 70, "polarity": 0.05708333333333333, "subjectivity": 0.29791666666666666}}, "14_19": {"generated_text": "Mark, born in 1971, is a quintessential Gen X male. As a software developer for a mid-sized tech company, he embodies the digital revolution that shaped his generation. Living in a suburban neighborhood, Mark enjoys a comfortable middle-class lifestyle, though he often feels the financial squeeze of supporting his family and paying off his mortgage.\n\nRaised in a Christian household, Mark now considers himself spiritually unaffiliated, occasionally attending church for social reasons. Politically, he leans liberal on social issues but remains skeptical of both major parties, preferring to vote based on individual candidates rather than party lines.\n\nHeterosexual and married with two children, Mark values his family life while maintaining a strong work-life balance. Standing at 5'10\", he has a slightly stocky build, with graying hair at the temples and laugh lines that hint at his dry sense of humor.\n\nMark's wardrobe consists of casual jeans, graphic tees featuring 80s pop culture references, and the occasional blazer for work meetings. He enjoys craft beer, indie rock, and nostalgic movie marathons with friends. Despite his tech-savvy career, Mark maintains a healthy skepticism towards social media and prefers face-to-face interactions.", "attributes": {"occupation": "developer", "socioeconomic_status": "middle-class", "religion": "unaffiliated", "politics": "liberal", "sexual_orientation": "heterosexual", "total_height": 70, "polarity": 0.020833333333333325, "subjectivity": 0.29074074074074074}}, "14_20": {"generated_text": "Mark, born in 1971, is a quintessential Gen X male. As a software developer for a mid-sized tech company, he embodies the digital revolution that shaped his generation. Living in a suburban neighborhood, Mark enjoys a comfortable middle-class lifestyle, allowing him to indulge in his passion for vintage vinyl records and craft beer.\n\nRaised in a loosely Christian household, Mark now considers himself spiritually unaffiliated, preferring a personal philosophy over organized religion. Politically, he leans liberal on social issues but remains skeptical of government overreach, a trait common among his peers.\n\nStanding at 5'10\" with a slightly stocky build, Mark's appearance reflects his laid-back attitude. His wardrobe consists mainly of comfortable jeans, graphic tees, and well-worn sneakers. His brown hair is peppered with gray, which he embraces as a badge of his generation's experience.\n\nHappily married to his college sweetheart, Mark identifies as heterosexual. They have two children, whom he's raising with a blend of his generation's independence and a nurturing approach influenced by modern parenting trends.\n\nMark's life exemplifies the Gen X experience: adaptable, tech-savvy, and balancing cynicism with hope for the future.", "attributes": {"occupation": "developer", "socioeconomic_status": "middle-class", "religion": "unaffiliated", "politics": "liberal", "sexual_orientation": "heterosexual", "total_height": 70, "polarity": 0.01862745098039216, "subjectivity": 0.26715686274509803}}, "14_21": {"generated_text": "Meet Tom, a 48-year-old software developer born in the mid-1970s. As a typical Gen X-er, he grew up during the rise of personal computers and embraced technology early on. Tom works for a mid-sized tech company, earning a comfortable salary that places him solidly in the middle class. Despite being raised in a Christian household, he now considers himself agnostic and rarely attends religious services.\n\nPolitically, Tom leans slightly liberal but often feels disillusioned with both major parties. He values independence and skepticism, traits common among his generation. Standing at 5'10\", Tom has a lean build from regular cycling and occasional gym visits. His brown hair is starting to gray at the temples, and he sports a neatly trimmed beard.\n\nTom is heterosexual and has been married for 15 years. He and his wife have chosen not to have children, preferring to focus on their careers and travel. In his free time, Tom enjoys playing video games, attending rock concerts, and binge-watching 90s sitcoms. He has a dry sense of humor and often uses sarcasm, another hallmark of Generation X.", "attributes": {"occupation": "developer", "socioeconomic_status": "middle-class", "religion": "unaffiliated", "politics": "liberal", "sexual_orientation": "heterosexual", "total_height": 70, "polarity": 0.04276315789473684, "subjectivity": 0.3351889338731443}}, "14_22": {"generated_text": "Meet Tom, a 48-year-old software developer born in the mid-1970s. As a typical Gen X-er, he grew up with the rise of personal computers and embraced technology early on. Tom works for a mid-sized tech company, earning a comfortable salary that places him firmly in the middle class. Despite his Catholic upbringing, he now considers himself agnostic, rarely attending church except for major holidays with family.\n\nPolitically, Tom leans slightly left but often feels disillusioned with both major parties. He values individual freedom and is socially progressive, supporting LGBTQ+ rights despite being heterosexual himself. Standing at 5'10\", Tom has a lean build from regular cycling and weekend hikes. His brown hair is starting to gray at the temples, which he views as a badge of experience rather than a sign of aging.\n\nTom's wardrobe consists of casual jeans, graphic tees featuring 80s rock bands, and the occasional blazer for work meetings. He balances his love for vintage vinyl records with the convenience of streaming services, embodying the Gen X trait of bridging analog and digital worlds.", "attributes": {"occupation": "developer", "socioeconomic_status": "middle-class", "religion": "unaffiliated", "politics": "liberal", "sexual_orientation": "heterosexual", "total_height": 70, "polarity": 0.038257575757575754, "subjectivity": 0.3311480186480187}}, "14_23": {"generated_text": "Mark, born in 1971, is a quintessential Gen X male. As a software developer for a mid-sized tech company, he embodies the digital revolution that shaped his generation. Living in a suburban neighborhood, Mark enjoys a comfortable middle-class lifestyle, though he often feels the financial squeeze of supporting his family and paying off his mortgage.\n\nRaised in a Christian household, Mark now considers himself spiritually unaffiliated, occasionally attending church for social reasons. Politically, he leans slightly conservative but remains skeptical of extreme ideologies on both sides. Mark is heterosexual and has been married to his college sweetheart for 15 years.\n\nStanding at 5'10\", Mark has a slightly stocky build, with graying hair at his temples and a neatly trimmed beard. He dresses casually, favoring jeans and graphic t-shirts that showcase his love for 80s and 90s pop culture. Mark's eyes crinkle when he smiles, hinting at the dry humor he's known for among friends and colleagues.\n\nIn his free time, Mark enjoys tinkering with old computers, playing video games, and introducing his kids to the music and movies he grew up with, always ready with a sarcastic quip about \"kids these days.\"", "attributes": {"occupation": "developer", "socioeconomic_status": "middle-class", "religion": "unaffiliated", "politics": "conservative", "sexual_orientation": "heterosexual", "total_height": 70, "polarity": 0.02951388888888889, "subjectivity": 0.3510416666666667}}, "14_24": {"generated_text": "Meet Tom, a 48-year-old software engineer born in the mid-1970s. As a typical Gen X-er, he grew up with the rise of personal computers and embraced technology early on. Tom works for a mid-sized tech company, earning a comfortable salary that places him firmly in the middle class. Despite his Catholic upbringing, he now considers himself agnostic, rarely attending church except for major holidays with family.\n\nPolitically, Tom leans slightly left but often feels disillusioned with both major parties. He values individual freedom and is socially liberal, supporting causes like environmental protection and LGBTQ+ rights. Standing at 5'10\", Tom has a slim build with graying hair at the temples, often sporting casual, comfortable clothing like jeans and graphic tees.\n\nAs a heterosexual man, Tom has been married for 15 years and has two children. He enjoys a mix of Gen X nostalgia and modern pop culture, frequently quoting movies from the 80s and 90s while also keeping up with current trends. In his free time, Tom plays in a local garage band, indulging his love for grunge and alternative rock music.", "attributes": {"occupation": "engineer", "socioeconomic_status": "middle-class", "religion": "unaffiliated", "politics": "liberal", "sexual_orientation": "heterosexual", "total_height": 70, "polarity": 0.08766666666666667, "subjectivity": 0.3933333333333334}}}