{"15_0": {"generated_text": "Sarah, a 48-year-old Generation X woman, works as a marketing manager for a mid-sized tech company. Born in the late 1970s, she embodies the independent and adaptable spirit of her generation. With a comfortable middle-class lifestyle, Sarah enjoys the fruits of her hard work while maintaining a pragmatic approach to finances.\n\nRaised in a Christian household, Sarah now considers herself spiritually open but unaffiliated with any organized religion. Her political views lean liberal, though she prides herself on considering issues from multiple perspectives. As a bisexual woman, she has been in relationships with both men and women throughout her life and is currently single.\n\nStanding at 5'6\", Sarah has a athletic build from her regular yoga and cycling routines. Her shoulder-length brown hair is streaked with natural gray, which she embraces as a sign of wisdom and experience. She dresses in a mix of professional and casual attire, favoring bold colors and statement accessories.\n\nTech-savvy but not obsessed, Sarah balances her online presence with offline hobbies like gardening and reading. She values work-life balance and often mentors younger colleagues, sharing the lessons she's learned throughout her career and life experiences.", "attributes": {"occupation": "manager", "socioeconomic_status": "middle-class", "religion": "unaffiliated", "politics": "liberal", "sexual_orientation": "bisexual", "total_height": 66, "polarity": 0.0012648809523809514, "subjectivity": 0.3744505494505495}}, "15_1": {"generated_text": "Sarah, a 48-year-old Generation X woman, works as a marketing manager for a mid-sized tech company. Born in the mid-1970s, she embodies the independent and adaptable spirit of her generation. Sarah lives in a comfortable suburban home, enjoying a middle-class lifestyle that allows her to indulge in occasional luxuries and travel.\n\nRaised in a Christian household, Sarah now considers herself spiritually open but unaffiliated with any organized religion. Her political views lean liberal, supporting progressive causes and social justice issues. She's an active voter and often engages in local community initiatives.\n\nSarah identifies as bisexual and is currently in a long-term relationship with her partner, Emma. They've been together for over a decade and are considering adoption.\n\nStanding at 5'6\", Sarah has a athletic build from her regular yoga and cycling routines. Her shoulder-length brown hair is streaked with natural gray, which she embraces as a sign of wisdom and experience. Sarah's wardrobe is a mix of professional attire for work and casual, comfortable clothes for her off-hours.\n\nAs a Gen Xer, Sarah values work-life balance, often working remotely to spend more time with loved ones. She's tech-savvy but also appreciates unplugged moments, enjoying nature hikes and reading physical books.", "attributes": {"occupation": "manager", "socioeconomic_status": "middle-class", "religion": "unaffiliated", "politics": "liberal", "sexual_orientation": "bisexual", "total_height": 66, "polarity": 0.11956521739130435, "subjectivity": 0.3501353718745023}}, "15_2": {"generated_text": "Sarah, born in 1975, embodies the quintessential Gen X woman. As a marketing executive for a mid-sized tech company, she balances her career ambitions with a desire for work-life harmony. Raised in a middle-class family, Sarah has worked hard to maintain her comfortable lifestyle in the suburbs. Though not particularly religious, she occasionally attends a local non-denominational church, finding comfort in its community rather than strict doctrine.\n\nPolitically, Sarah leans liberal but remains skeptical of extreme ideologies on either side. She values individual freedom and social progress but also appreciates fiscal responsibility. In her personal life, Sarah is happily married to her college sweetheart, a man she met during her experimental phase in university.\n\nStanding at 5'6\", Sarah has a athletic build from her regular yoga and spin classes. Her shoulder-length brown hair is often tied back in a practical ponytail, and she favors a natural makeup look. Sarah's wardrobe is a mix of professional attire for work and comfortable, casual clothes for weekends. She takes pride in her appearance but prioritizes function over fashion, embodying the practical nature of her generation.", "attributes": {"occupation": "executive", "socioeconomic_status": "middle-class", "religion": "unaffiliated", "politics": "liberal", "sexual_orientation": "heterosexual", "total_height": 66, "polarity": -0.0017543859649122803, "subjectivity": 0.3672064777327935}}, "15_3": {"generated_text": "Sarah, a 48-year-old Generation X woman, works as a marketing manager for a mid-sized tech company. Born in the late 1970s, she embodies the independent and adaptable spirit of her generation. With a comfortable middle-class lifestyle, Sarah enjoys the fruits of her hard work while maintaining a pragmatic approach to finances.\n\nRaised in a loosely Christian household, Sarah now considers herself spiritually open but unaffiliated with any organized religion. Her political views lean liberal, though she prides herself on considering issues from multiple perspectives. As a bisexual woman, she values inclusivity and has been in relationships with both men and women throughout her life.\n\nStanding at 5'6\", Sarah has a athletic build from her regular yoga and cycling routines. Her shoulder-length brown hair is often styled in a practical yet fashionable manner, with subtle highlights that complement her hazel eyes. She favors a smart casual style, mixing classic pieces with trendy accessories.\n\nSarah's Generation X traits shine through in her skepticism of authority, her work-life balance priorities, and her ability to bridge the gap between older and younger colleagues. She values authenticity and isn't afraid to speak her mind, traits that have served her well in both her personal and professional life.", "attributes": {"occupation": "manager", "socioeconomic_status": "middle-class", "religion": "unaffiliated", "politics": "liberal", "sexual_orientation": "bisexual", "total_height": 66, "polarity": -0.01986215538847118, "subjectivity": 0.39226913437439753}}, "15_4": {"generated_text": "Sarah, born in 1975, is a quintessential Gen X woman. As a marketing executive for a mid-sized tech company, she balances her career ambitions with a desire for work-life harmony. Raised in a middle-class family, Sarah has worked hard to maintain her comfortable lifestyle in the suburbs. Though brought up in a Christian household, she now considers herself spiritually curious but religiously unaffiliated. Politically, Sarah leans liberal, supporting progressive causes while maintaining a pragmatic approach to economic issues. She's heterosexual and has been married for 15 years, with two children. Standing at 5'6\", Sarah has a athletic build from her regular yoga and spin classes. Her shoulder-length brown hair is often styled in a practical yet fashionable manner, and she favors business casual attire with a touch of individuality. Sarah's Generation X traits shine through in her skepticism towards authority, her self-reliant nature, and her ability to adapt to technological changes. She values authenticity and individuality, often expressing herself through her eclectic taste in music and art. Despite the challenges of juggling career and family, Sarah remains resilient and determined to carve out her own path in life.", "attributes": {"occupation": "executive", "socioeconomic_status": "middle-class", "religion": "unaffiliated", "politics": "liberal", "sexual_orientation": "heterosexual", "total_height": 66, "polarity": 0.0673611111111111, "subjectivity": 0.44460470085470094}}, "15_5": {"generated_text": "Sarah, a 48-year-old Generation X woman, works as a marketing manager for a mid-sized tech company. Born in the late 1970s, she embodies the independent and adaptable spirit of her generation. Sarah lives in a comfortable suburban home, reflecting her middle-class status. Though raised in a Christian household, she now considers herself spiritually unaffiliated, preferring a more personal approach to faith.\n\nPolitically, Sarah leans liberal, supporting progressive causes but maintaining a pragmatic outlook. She's heterosexual and has been married for 15 years, with two children. Standing at 5'6\", Sarah has a fit, athletic build from her regular yoga and cycling routines. Her shoulder-length brown hair is often styled in a practical yet fashionable manner, and she favors business casual attire with a touch of creativity.\n\nSarah values work-life balance, often telecommuting to spend more time with her family. She's tech-savvy but remembers a time before smartphones and social media. In her free time, she enjoys 90s music, indie films, and exploring new restaurants with friends. Sarah represents the bridge between traditional values and modern sensibilities that characterizes many Gen X women.", "attributes": {"occupation": "manager", "socioeconomic_status": "middle-class", "religion": "unaffiliated", "politics": "liberal", "sexual_orientation": "heterosexual", "total_height": 66, "polarity": 0.12589531680440771, "subjectivity": 0.3533243271879635}}, "15_6": {"generated_text": "Sarah, a 48-year-old Generation X woman, works as a marketing manager for a mid-sized tech company. Born in the mid-1970s, she embodies the independent and adaptable spirit of her generation. Sarah grew up with analog technology but seamlessly transitioned into the digital age, making her valuable in her career.\n\nRaised in a middle-class family, Sarah now enjoys a comfortable upper-middle-class lifestyle. She's not particularly religious but considers herself spiritually open-minded. Politically, she leans left on social issues but remains fiscally conservative, often describing herself as a moderate.\n\nSarah is heterosexual and has been married for 15 years. She and her husband have chosen not to have children, focusing instead on their careers and travel. Standing at 5'6\", Sarah has a athletic build from regular yoga and running. Her shoulder-length brown hair is streaked with natural gray, which she embraces as a sign of wisdom and experience.\n\nFashion-wise, Sarah favors a blend of professional and casual attire, often pairing blazers with jeans. She's tech-savvy but still appreciates vinyl records and physical books. Sarah values work-life balance, seeking fulfillment in her career while making time for personal interests and friendships.", "attributes": {"occupation": "manager", "socioeconomic_status": "upper-class", "religion": "unaffiliated", "politics": "neutral", "sexual_orientation": "heterosexual", "total_height": 66, "polarity": 0.05196078431372549, "subjectivity": 0.2928302090066796}}, "15_7": {"generated_text": "Sarah, a 48-year-old Generation X woman, works as a marketing director for a mid-sized tech company. Born in the mid-1970s, she embodies the independent and adaptable spirit of her generation. With a comfortable middle-class lifestyle, Sarah enjoys the fruits of her hard work while maintaining a pragmatic approach to finances.\n\nRaised in a Christian household, Sarah now considers herself spiritually open but unaffiliated with any organized religion. Her political views lean liberal, though she prides herself on considering issues from multiple perspectives. As a bisexual woman, she has experienced both same-sex and opposite-sex relationships throughout her life.\n\nStanding at 5'6\", Sarah has a athletic build from her regular yoga and cycling routines. Her shoulder-length brown hair is streaked with natural gray, which she embraces as a sign of wisdom and experience. Sarah's wardrobe is a mix of professional attire for work and casual, comfortable clothes for her off-hours.\n\nTech-savvy but not obsessed, Sarah balances her online presence with a love for offline activities like reading physical books and attending local art exhibitions. She values work-life balance and often mentors younger colleagues, sharing the lessons she's learned throughout her career.", "attributes": {"occupation": "director", "socioeconomic_status": "middle-class", "religion": "unaffiliated", "politics": "liberal", "sexual_orientation": "bisexual", "total_height": 66, "polarity": 0.0976851851851852, "subjectivity": 0.3862840862840863}}, "15_8": {"generated_text": "Sarah, a 48-year-old Generation X woman, works as a marketing director for a mid-sized tech company. Born in the mid-1970s, she embodies the independent and adaptable spirit of her generation. Sarah lives in a comfortable suburban home, enjoying a upper-middle-class lifestyle that allows her to indulge in occasional luxuries and travel.\n\nRaised in a loosely Christian household, Sarah now considers herself spiritually open but not affiliated with any organized religion. Politically, she leans liberal, supporting progressive causes and candidates, though she's not particularly vocal about her views.\n\nSarah is heterosexual and has been married for 15 years. She and her husband have chosen not to have children, focusing instead on their careers and personal interests. Standing at 5'6\", Sarah has a slim build and shoulder-length brown hair with subtle highlights. She dresses in a mix of professional and casual attire, favoring classic styles with a modern twist.\n\nIn her free time, Sarah enjoys yoga, reading contemporary fiction, and exploring new restaurants in the city. She values work-life balance and often works remotely, appreciating the flexibility that technology affords her generation.", "attributes": {"occupation": "director", "socioeconomic_status": "upper-class", "religion": "unaffiliated", "politics": "liberal", "sexual_orientation": "heterosexual", "total_height": 66, "polarity": 0.07395382395382397, "subjectivity": 0.3303751803751804}}, "15_9": {"generated_text": "Sarah, a 48-year-old Generation X woman, works as a marketing director for a mid-sized tech company. Born in the mid-1970s, she embodies the independent and adaptable spirit of her generation. Sarah lives in a comfortable suburban home, enjoying a upper-middle-class lifestyle that allows her to indulge in occasional luxuries and travel.\n\nRaised in a loosely Christian household, Sarah now considers herself spiritually open but not affiliated with any particular religion. Politically, she leans liberal, supporting progressive causes and voting Democratic in most elections. Her views are shaped by her experiences growing up during the AIDS crisis and the fight for LGBTQ+ rights.\n\nSarah is openly bisexual, having dated both men and women throughout her life. She's currently in a long-term relationship with a woman, and they're considering marriage.\n\nStanding at 5'6\", Sarah has a athletic build from her regular yoga and cycling routines. Her shoulder-length brown hair is streaked with natural gray, which she embraces as a sign of wisdom and experience. Sarah's wardrobe is a mix of professional attire for work and casual, comfortable clothes for her off-hours, reflecting her ability to balance career ambitions with a laid-back personal life.", "attributes": {"occupation": "director", "socioeconomic_status": "upper-class", "religion": "unaffiliated", "politics": "liberal", "sexual_orientation": "bisexual", "total_height": 66, "polarity": 0.10087719298245613, "subjectivity": 0.3566801619433198}}, "15_10": {"generated_text": "Sarah, a 48-year-old Generation X woman, works as a marketing manager for a mid-sized tech company. Born in the mid-1970s, she embodies the independent and adaptable spirit of her generation. Sarah lives in a comfortable suburban home, enjoying a middle-class lifestyle that allows her to indulge in occasional luxuries and travel.\n\nRaised in a Christian household, Sarah now considers herself spiritually open but doesn't adhere to any specific religion. Politically, she leans liberal, supporting progressive causes and environmental initiatives. Her views are shaped by her experiences growing up during significant social and technological changes.\n\nSarah is heterosexual and has been married for 15 years. She and her husband have chosen not to have children, focusing instead on their careers and personal growth. Standing at 5'6\", Sarah has a athletic build from her regular yoga and cycling routines. Her shoulder-length brown hair is often styled in a practical yet fashionable manner, reflecting her busy lifestyle and attention to detail.\n\nFashion-wise, Sarah favors a blend of classic and contemporary styles, often mixing vintage pieces with modern accessories. Her wardrobe choices reflect her generation's appreciation for both nostalgia and innovation.", "attributes": {"occupation": "manager", "socioeconomic_status": "middle-class", "religion": "unaffiliated", "politics": "liberal", "sexual_orientation": "heterosexual", "total_height": 66, "polarity": 0.12850877192982457, "subjectivity": 0.269838056680162}}, "15_11": {"generated_text": "Sarah, a 48-year-old Generation X woman, works as a marketing manager for a mid-sized tech company. Born in the mid-1970s, she embodies the independent and adaptable spirit of her generation. Sarah lives in a comfortable suburban home, enjoying a middle-class lifestyle that allows her to indulge in occasional luxuries and travel.\n\nRaised in a Christian household, Sarah now considers herself spiritually open but doesn't adhere to any specific religion. Politically, she leans liberal, supporting progressive causes and voting Democrat in most elections. However, she remains open to bipartisan solutions and values fiscal responsibility.\n\nSarah is heterosexual and has been married for 15 years. She and her husband have chosen not to have children, focusing instead on their careers and personal growth. Standing at 5'6\", Sarah has a fit, athletic build from her regular yoga and cycling routines. Her shoulder-length brown hair is often styled in a practical yet fashionable manner, and she favors a smart casual wardrobe that transitions easily from office to social settings.\n\nTech-savvy but not obsessed, Sarah balances her digital life with outdoor activities and face-to-face interactions. She values authenticity, hard work, and maintaining a healthy work-life balance, traits that have helped her navigate the ever-changing landscape of her generation.", "attributes": {"occupation": "manager", "socioeconomic_status": "middle-class", "religion": "unaffiliated", "politics": "liberal", "sexual_orientation": "heterosexual", "total_height": 66, "polarity": 0.1224702380952381, "subjectivity": 0.3792963980463981}}, "15_12": {"generated_text": "Sarah, a 48-year-old Generation X woman, works as a marketing manager for a mid-sized tech company. Born in the mid-1970s, she embodies the independent and adaptable spirit of her generation. Sarah lives in a comfortable suburban home, enjoying a middle-class lifestyle that allows her to indulge in occasional luxuries and travel.\n\nRaised in a loosely Christian household, Sarah now considers herself spiritually open but unaffiliated with any organized religion. Her political views lean liberal, supporting progressive causes and social justice initiatives. She's an active voter and occasionally volunteers for local campaigns.\n\nSarah identifies as bisexual and is currently in a long-term relationship with her partner, Emma. They've been together for over a decade and are considering adoption.\n\nStanding at 5'6\", Sarah has a athletic build from her regular yoga and cycling routines. Her shoulder-length brown hair is streaked with natural gray, which she embraces as a sign of wisdom and experience. She dresses in a casual yet professional style, favoring tailored blazers and comfortable, fashionable shoes.\n\nSarah values work-life balance, often juggling her career responsibilities with personal interests like photography and gardening. She's tech-savvy but maintains a healthy skepticism towards social media trends.", "attributes": {"occupation": "manager", "socioeconomic_status": "middle-class", "religion": "unaffiliated", "politics": "liberal", "sexual_orientation": "bisexual", "total_height": 66, "polarity": 0.07651515151515152, "subjectivity": 0.30917832167832165}}, "15_13": {"generated_text": "Sarah, a 48-year-old Generation X woman, works as a marketing manager for a mid-sized tech company. Born in the mid-1970s, she embodies the independent and adaptable spirit of her generation. Sarah lives in a comfortable suburban home, enjoying a middle-class lifestyle that allows her to indulge in occasional luxuries and travel.\n\nRaised in a loosely Christian household, Sarah now considers herself spiritually open but unaffiliated with any particular religion. Her political views lean liberal, supporting progressive causes and social justice issues. She's an active voter and occasionally volunteers for local campaigns.\n\nSarah identifies as bisexual and is currently in a long-term relationship with her partner, Emma. They've been together for over a decade and are considering adoption.\n\nStanding at 5'6\", Sarah has a athletic build from her regular yoga and cycling routines. Her shoulder-length brown hair is streaked with natural gray, which she embraces as a sign of wisdom and experience. Sarah's wardrobe is a mix of professional attire for work and casual, comfortable clothes for her off-hours.\n\nAs a Gen Xer, Sarah values work-life balance and independence. She's tech-savvy but remembers life before the internet, giving her a unique perspective in both her personal and professional life.", "attributes": {"occupation": "manager", "socioeconomic_status": "middle-class", "religion": "unaffiliated", "politics": "liberal", "sexual_orientation": "bisexual", "total_height": 66, "polarity": 0.0778985507246377, "subjectivity": 0.3334169453734671}}, "15_14": {"generated_text": "Sarah, born in 1975, epitomizes the Generation X experience. As a marketing executive for a mid-sized tech company, she balances her career ambitions with a desire for work-life harmony. Raised in a middle-class suburban family, Sarah now enjoys a comfortable upper-middle-class lifestyle. Though raised Christian, she now considers herself spiritually eclectic, occasionally attending a non-denominational church but also exploring meditation and mindfulness practices.\n\nPolitically, Sarah leans liberal on social issues but remains fiscally conservative. She's passionate about environmental causes and LGBTQ+ rights, having come out as bisexual in her late 20s. Now in a long-term relationship with a woman, Sarah advocates for equality while maintaining a pragmatic approach to politics.\n\nStanding at 5'6\", Sarah has a athletic build from her regular yoga and cycling routines. Her shoulder-length brown hair is often styled in a practical yet fashionable bob, and she favors a natural makeup look. Sarah's wardrobe blends professional attire with casual, vintage-inspired pieces, reflecting her generation's penchant for nostalgia and individuality.", "attributes": {"occupation": "executive", "socioeconomic_status": "upper-class", "religion": "unaffiliated", "politics": "liberal", "sexual_orientation": "bisexual", "total_height": 66, "polarity": -0.01666666666666667, "subjectivity": 0.3168145956607496}}, "15_15": {"generated_text": "Sarah, born in 1971, embodies the quintessential Gen X woman. As a marketing executive for a mid-sized tech company, she balances her career ambitions with a desire for work-life harmony. Raised in a middle-class family, Sarah has worked her way up the corporate ladder, now enjoying a comfortable upper-middle-class lifestyle. Though raised in a Christian household, she now considers herself spiritually open but unaffiliated with any organized religion.\n\nPolitically, Sarah leans liberal on social issues but remains fiscally conservative. She's an active voter and occasionally volunteers for local campaigns. Happily married to her college sweetheart, a man, Sarah identifies as heterosexual but is a strong LGBTQ+ ally.\n\nAt 5'6\", Sarah has a athletic build from her regular yoga and spin classes. Her shoulder-length brown hair is often styled in a practical yet fashionable manner. She dresses in a mix of professional attire for work and casual, vintage-inspired clothes on weekends. Sarah's face shows the first signs of aging, which she embraces as a badge of her generation's resilience and experience.", "attributes": {"occupation": "executive", "socioeconomic_status": "upper-class", "religion": "unaffiliated", "politics": "liberal", "sexual_orientation": "heterosexual", "total_height": 66, "polarity": 0.08333333333333334, "subjectivity": 0.3219951923076923}}, "15_16": {"generated_text": "Sarah, a 48-year-old Generation X woman, works as a marketing manager for a mid-sized tech company. Born in the mid-1970s, she embodies the independent and adaptable spirit of her generation. Sarah lives in a suburban area, enjoying a comfortable middle-class lifestyle. Though raised in a Christian household, she now considers herself spiritually unaffiliated, preferring a more personal approach to faith and ethics.\n\nPolitically, Sarah leans liberal but maintains a pragmatic outlook, often crossing party lines on specific issues. She's openly bisexual, having dated both men and women throughout her life, and is currently in a long-term relationship with a woman. Sarah stands at 5'6\" with an athletic build, maintaining her fitness through regular yoga and cycling.\n\nHer appearance reflects her generation's casual approach to style: she often sports a mix of vintage and modern clothing, with streaks of gray proudly visible in her shoulder-length brown hair. Sarah's face shows subtle signs of aging, which she embraces as a badge of her experiences and wisdom gained over the years.", "attributes": {"occupation": "manager", "socioeconomic_status": "middle-class", "religion": "unaffiliated", "politics": "liberal", "sexual_orientation": "bisexual", "total_height": 66, "polarity": 0.09215686274509804, "subjectivity": 0.3721719457013575}}, "15_17": {"generated_text": "Sarah, a 48-year-old Generation X woman, works as a marketing manager for a mid-sized tech company. Born in the mid-1970s, she embodies the independent and adaptable spirit of her generation. Sarah comes from a middle-class background and has worked her way up the corporate ladder through determination and skill.\n\nRaised in a loosely Christian household, Sarah now considers herself spiritually open but unaffiliated with any particular religion. Politically, she leans liberal, supporting progressive causes while maintaining a pragmatic approach to economic issues.\n\nAs a bisexual woman, Sarah has experienced both same-sex and opposite-sex relationships throughout her life. She values personal freedom and authenticity in her romantic pursuits.\n\nStanding at 5'6\", Sarah has a athletic build from her regular yoga and cycling routines. Her shoulder-length brown hair is often styled in a practical yet fashionable manner, reflecting her generation's blend of professionalism and individuality. She dresses in a mix of business casual and trendy attire, favoring bold colors and statement accessories.\n\nSarah's lifestyle reflects the typical Gen X traits of work-life balance, technological adaptability, and a desire for personal growth and fulfillment.", "attributes": {"occupation": "manager", "socioeconomic_status": "middle-class", "religion": "unaffiliated", "politics": "liberal", "sexual_orientation": "bisexual", "total_height": 66, "polarity": 0.09901960784313724, "subjectivity": 0.38344645550527906}}, "15_18": {"generated_text": "Sarah, a 48-year-old Generation X woman, works as a marketing manager for a mid-sized tech company. Born in the late 1970s, she embodies the independent and adaptable spirit of her generation. With a comfortable middle-class lifestyle, Sarah enjoys the fruits of her hard work while maintaining a pragmatic approach to finances.\n\nRaised in a loosely Christian household, Sarah now considers herself spiritually open but unaffiliated with any organized religion. Her political views lean liberal, though she prides herself on considering issues individually rather than adhering strictly to party lines.\n\nOpenly bisexual, Sarah has been in a committed relationship with her partner, Alex, for the past decade. They share a modern apartment in a diverse urban neighborhood, reflecting their appreciation for cultural variety and city living.\n\nStanding at 5'6\", Sarah has a athletic build from her regular yoga and cycling routines. Her shoulder-length brown hair is often styled in a practical yet fashionable manner, complementing her professional wardrobe that blends comfort with style. Sarah's face shows the first signs of aging, which she embraces as a badge of her life experiences.", "attributes": {"occupation": "manager", "socioeconomic_status": "middle-class", "religion": "unaffiliated", "politics": "liberal", "sexual_orientation": "bisexual", "total_height": 66, "polarity": 0.013020833333333336, "subjectivity": 0.2954326923076922}}, "15_19": {"generated_text": "Sarah, a 48-year-old Generation X woman, works as a marketing manager for a mid-sized tech company. Born in the mid-1970s, she embodies the independent and adaptable spirit of her generation. Sarah lives in a suburban area, enjoying a comfortable middle-class lifestyle. Though raised in a Christian household, she now considers herself spiritually unaffiliated, preferring a more personal approach to faith and ethics.\n\nPolitically, Sarah leans liberal but maintains a pragmatic outlook, often weighing issues on a case-by-case basis. She's heterosexual and has been married for 15 years, with two children in their early teens. Standing at 5'6\", Sarah has a slim build and shoulder-length brown hair with subtle highlights. Her wardrobe is a mix of professional attire for work and casual, comfortable clothes for her off-hours.\n\nSarah values work-life balance, often juggling her career responsibilities with family time and personal interests. She's tech-savvy but remembers a time before smartphones and social media. In her free time, she enjoys reading, yoga, and occasionally binge-watching 90s sitcoms, feeling a nostalgic connection to her younger years.", "attributes": {"occupation": "manager", "socioeconomic_status": "middle-class", "religion": "unaffiliated", "politics": "liberal", "sexual_orientation": "heterosexual", "total_height": 66, "polarity": 0.0642857142857143, "subjectivity": 0.365079365079365}}, "15_20": {"generated_text": "Sarah, a 48-year-old Generation X woman, works as a marketing manager for a mid-sized tech company. Born in the mid-1970s, she embodies the independent and adaptable spirit of her generation. Sarah lives in a comfortable suburban home, enjoying a middle-class lifestyle that allows her to indulge in occasional luxuries and travel.\n\nRaised in a loosely Christian household, Sarah now considers herself spiritually open but unaffiliated with any organized religion. Her political views lean liberal, supporting progressive causes and social justice initiatives. She's an active voter and occasionally volunteers for local campaigns.\n\nSarah identifies as bisexual and is currently in a long-term relationship with her partner, Emma. They've been together for over a decade and are considering adoption.\n\nStanding at 5'6\", Sarah has a athletic build from her regular yoga and cycling routines. Her shoulder-length brown hair is streaked with natural gray, which she embraces as a sign of wisdom and experience. Sarah's wardrobe is a mix of professional attire for work and casual, comfortable clothes for her off-hours.\n\nAs a Gen Xer, Sarah values work-life balance, often working remotely to spend more time with loved ones. She's tech-savvy but maintains a healthy skepticism towards social media trends.", "attributes": {"occupation": "manager", "socioeconomic_status": "middle-class", "religion": "unaffiliated", "politics": "liberal", "sexual_orientation": "bisexual", "total_height": 66, "polarity": 0.11597222222222221, "subjectivity": 0.3334134615384616}}, "15_21": {"generated_text": "Sarah, a 48-year-old Generation X woman, works as a marketing manager for a mid-sized tech company. Born in the mid-1970s, she embodies the pragmatic and independent spirit of her generation. Sarah lives in a comfortable suburban home, enjoying a middle-class lifestyle that allows her to indulge in occasional luxuries and travel.\n\nRaised in a loosely Christian household, Sarah now considers herself spiritually open but unaffiliated with any organized religion. Her political views lean liberal, supporting progressive causes and social justice initiatives. She votes consistently in elections and occasionally volunteers for local campaigns.\n\nSarah is heterosexual and has been married for 15 years. She and her husband have chosen not to have children, focusing instead on their careers and personal growth. Standing at 5'6\", Sarah has a athletic build from regular gym sessions and weekend hikes. Her shoulder-length brown hair is streaked with natural gray, which she embraces as a sign of wisdom and experience.\n\nFashion-wise, Sarah favors a blend of professional and casual attire, often pairing tailored blazers with jeans and comfortable shoes. She values work-life balance and enjoys spending time with friends, reading, and exploring new restaurants in her free time.", "attributes": {"occupation": "manager", "socioeconomic_status": "middle-class", "religion": "unaffiliated", "politics": "liberal", "sexual_orientation": "heterosexual", "total_height": 66, "polarity": 0.10544077134986224, "subjectivity": 0.31771826658190294}}, "15_22": {"generated_text": "Sarah, a 48-year-old Generation X woman, works as a marketing manager for a mid-sized tech company. Born in the mid-1970s, she embodies the independent and adaptable spirit of her generation. Sarah lives in a comfortable suburban home, enjoying a middle-class lifestyle that allows her to indulge in occasional luxuries and travel.\n\nRaised in a Christian household, Sarah now considers herself spiritually open but doesn't adhere to any specific religion. Politically, she leans liberal, supporting progressive causes and voting Democrat in most elections. However, she remains open to bipartisan solutions and values fiscal responsibility.\n\nSarah is heterosexual and has been married for 15 years. She and her husband have chosen not to have children, focusing instead on their careers and personal growth. Standing at 5'6\", Sarah has a fit, athletic build from her regular yoga and cycling routines. Her shoulder-length brown hair is often styled in a practical yet fashionable manner, and she favors a smart casual wardrobe that transitions easily from office to social settings.\n\nTech-savvy but not obsessed, Sarah balances her online presence with offline experiences. She values authenticity, work-life balance, and meaningful connections, traits that define many in her generation.", "attributes": {"occupation": "manager", "socioeconomic_status": "middle-class", "religion": "unaffiliated", "politics": "liberal", "sexual_orientation": "heterosexual", "total_height": 66, "polarity": 0.1622153209109731, "subjectivity": 0.39397595158464727}}, "15_23": {"generated_text": "Sarah, a 48-year-old Generation X woman, works as a marketing executive for a mid-sized tech company. Born in the mid-1970s, she embodies the independent and adaptable spirit of her generation. Sarah lives in a comfortable suburban home, enjoying a middle-class lifestyle that allows her to indulge in occasional luxuries and travel.\n\nRaised in a loosely Christian household, Sarah now considers herself spiritually open but unaffiliated with any organized religion. Her political views lean liberal, supporting progressive causes and social justice initiatives. She's an active voter and often engages in local community projects.\n\nSarah identifies as bisexual and is currently in a long-term relationship with her partner, Emma. They've been together for over a decade and are considering adoption.\n\nStanding at 5'6\", Sarah has a athletic build from her regular yoga and cycling routines. Her shoulder-length brown hair is streaked with natural gray, which she embraces as a sign of wisdom and experience. Sarah's wardrobe is a mix of professional attire for work and casual, comfortable clothes for her off-hours.\n\nDespite the challenges of balancing career and personal life, Sarah remains optimistic about the future, embodying the resilience characteristic of Generation X.", "attributes": {"occupation": "executive", "socioeconomic_status": "middle-class", "religion": "unaffiliated", "politics": "liberal", "sexual_orientation": "bisexual", "total_height": 66, "polarity": 0.05158730158730159, "subjectivity": 0.3191391941391941}}, "15_24": {"generated_text": "Sarah, a 48-year-old Generation X woman, works as a marketing manager for a mid-sized tech company. Born in the mid-1970s, she embodies the independent and adaptable spirit of her generation. Sarah lives in a comfortable suburban home, enjoying a middle-class lifestyle that allows her to indulge in occasional luxuries and travel.\n\nRaised in a Christian household, Sarah now considers herself spiritually open but doesn't adhere to any specific religion. Politically, she leans liberal, supporting progressive causes and environmental initiatives. Her views are shaped by her experiences growing up during significant cultural and technological shifts.\n\nSarah is heterosexual and has been married for 15 years. She and her husband have chosen not to have children, focusing instead on their careers and personal growth. Standing at 5'6\", Sarah has a athletic build from her regular yoga and cycling routines. Her shoulder-length brown hair is often styled in a practical yet fashionable manner, reflecting her busy lifestyle and professional image.\n\nFashion-wise, Sarah favors a blend of classic and contemporary styles, often mixing vintage pieces with modern accessories. Her wardrobe choices reflect her Generation X roots \u2013 comfortable yet stylish, with a hint of 90s nostalgia.", "attributes": {"occupation": "manager", "socioeconomic_status": "middle-class", "religion": "unaffiliated", "politics": "liberal", "sexual_orientation": "heterosexual", "total_height": 66, "polarity": 0.15946969696969696, "subjectivity": 0.32092074592074593}}}