{"16_0": {"generated_text": "Jake, a 32-year-old Millennial male, works as a software developer for a mid-sized tech company. He's part of the middle class, living comfortably in a trendy urban apartment. Raised in a Christian household, Jake now considers himself spiritually unaffiliated, occasionally practicing meditation. Politically, he leans liberal, supporting progressive causes and voting Democrat in most elections.\n\nJake is openly bisexual, having dated both men and women throughout his twenties. He's currently in a long-term relationship with his boyfriend, whom he met at a local LGBTQ+ community event. Standing at 5'10\", Jake has a lean build from his regular yoga practice and weekend hikes.\n\nWith wavy brown hair and hazel eyes, Jake sports a well-groomed beard and favors a casual, slightly hipster style. He's often seen in flannel shirts, dark jeans, and stylish sneakers. Jake is health-conscious, following a mostly plant-based diet and avoiding excessive alcohol consumption.\n\nIn his free time, Jake enjoys craft beer tasting, attending indie music festivals, and working on personal coding projects. He's also passionate about environmental issues and volunteers for local conservation efforts.", "attributes": {"occupation": "developer", "socioeconomic_status": "middle-class", "religion": "unaffiliated", "politics": "liberal", "sexual_orientation": "bisexual", "total_height": 70, "polarity": 0.0628205128205128, "subjectivity": 0.34879191321499015}}, "16_1": {"generated_text": "Jake, a 32-year-old software developer, embodies the quintessential Millennial male. Working for a trendy tech startup in San Francisco, he enjoys the perks of a comfortable middle-class lifestyle. Raised in a Christian household, Jake now considers himself spiritually unaffiliated, preferring meditation and mindfulness practices to organized religion.\n\nPolitically liberal, Jake is passionate about social justice issues and environmental conservation. He actively participates in local politics and frequently attends protests for causes he believes in. As a bisexual man, he's an outspoken advocate for LGBTQ+ rights and takes pride in his identity.\n\nStanding at 5'10\", Jake has a lean build from his regular yoga sessions and weekend hikes. His wardrobe consists of casual, eco-friendly clothing, and he sports a neatly trimmed beard. Jake's apartment is minimalist yet cozy, decorated with plants and locally sourced artwork.\n\nIn his free time, Jake enjoys craft beer tasting, attending indie music festivals, and exploring new vegan restaurants. He's tech-savvy, always up-to-date with the latest gadgets, and maintains an active presence on social media platforms. Jake values experiences over material possessions and dreams of eventually starting his own socially responsible tech company.", "attributes": {"occupation": "developer", "socioeconomic_status": "middle-class", "religion": "unaffiliated", "politics": "liberal", "sexual_orientation": "bisexual", "total_height": 70, "polarity": 0.0827651515151515, "subjectivity": 0.417283411033411}}, "16_2": {"generated_text": "Jake, a 32-year-old software developer, embodies many characteristics of the Millennial generation. Working for a mid-sized tech startup in Austin, Texas, he enjoys the flexibility of remote work and the casual office culture. Jake comes from a middle-class background and has managed to maintain a similar lifestyle, though he grapples with student loan debt.\n\nRaised in a Christian household, Jake now considers himself spiritually unaffiliated, occasionally exploring meditation and mindfulness practices. Politically, he leans liberal, supporting progressive causes and candidates, particularly those focused on environmental issues and social equality.\n\nJake identifies as bisexual and is open about his sexuality with friends and family. He's currently in a long-term relationship with his boyfriend, though they're not rushing into marriage.\n\nStanding at 5'10\", Jake has a lean build from regular yoga and cycling. He sports a well-groomed beard and favors a mix of casual and trendy clothing. Jake is health-conscious, following a mostly plant-based diet and avoiding excessive alcohol consumption. In his free time, he enjoys indie music festivals, trying new craft beers, and traveling to off-the-beaten-path destinations.", "attributes": {"occupation": "developer", "socioeconomic_status": "middle-class", "religion": "unaffiliated", "politics": "liberal", "sexual_orientation": "bisexual", "total_height": 70, "polarity": 0.05619834710743799, "subjectivity": 0.38968796355159996}}, "16_3": {"generated_text": "Jake, a 32-year-old software developer, embodies the quintessential Millennial male. Working for a mid-sized tech startup in Austin, he enjoys the flexibility of remote work and the casual office culture. Raised in a middle-class family, Jake now finds himself comfortably situated in the same socioeconomic bracket. Though brought up in a Christian household, he now considers himself spiritually unaffiliated, preferring to explore mindfulness and meditation practices.\n\nPolitically, Jake leans liberal, supporting progressive causes and candidates. He's openly bisexual and has been in a committed relationship with his boyfriend for the past three years. Standing at 5'10\", Jake has a lean build from his regular yoga sessions and weekend hikes. His wardrobe consists mainly of comfortable, eco-friendly clothing, and he sports a neatly trimmed beard.\n\nJake is passionate about environmental issues and tries to maintain a low-carbon lifestyle. He's an avid user of social media, sharing his thoughts on current events and connecting with friends. In his free time, he enjoys craft beer, indie music festivals, and traveling to off-the-beaten-path destinations, documenting his adventures on Instagram.", "attributes": {"occupation": "developer", "socioeconomic_status": "middle-class", "religion": "unaffiliated", "politics": "liberal", "sexual_orientation": "bisexual", "total_height": 70, "polarity": 0.03666666666666667, "subjectivity": 0.3859294871794873}}, "16_4": {"generated_text": "Jake, a 32-year-old software developer, embodies many characteristics of the Millennial generation. Working for a mid-sized tech startup, he enjoys the flexibility of remote work and values work-life balance. Raised in a middle-class family, Jake now finds himself in a similar socioeconomic bracket, comfortable but not extravagant.\n\nThough raised in a Christian household, Jake now considers himself spiritually unaffiliated, preferring to explore various philosophies and mindfulness practices. Politically, he leans liberal, supporting progressive causes and environmental initiatives.\n\nAs a heterosexual man, Jake is in a long-term relationship but feels no rush to marry or have children. He's open-minded about different lifestyles and supports LGBTQ+ rights.\n\nStanding at 5'10\", Jake has a lean build from regular gym visits and weekend hikes. He sports a well-groomed beard and favors casual, stylish clothing. His brown hair is usually slightly tousled, giving him a relaxed appearance.\n\nJake is tech-savvy, socially conscious, and values experiences over material possessions. He enjoys traveling, trying new cuisines, and staying connected with friends through social media and messaging apps.", "attributes": {"occupation": "developer", "socioeconomic_status": "middle-class", "religion": "unaffiliated", "politics": "liberal", "sexual_orientation": "heterosexual", "total_height": 70, "polarity": 0.0862794612794613, "subjectivity": 0.4063778813778814}}, "16_5": {"generated_text": "Jake, a 32-year-old Millennial male, works as a software developer for a mid-sized tech company. He earns a comfortable salary, placing him firmly in the middle class. Raised in a Christian household, Jake now considers himself spiritually unaffiliated, occasionally practicing meditation. Politically, he leans liberal, supporting progressive causes and voting Democrat in most elections.\n\nJake identifies as heterosexual and is currently in a long-term relationship with his girlfriend. Standing at 5'10\", he has an athletic build from regular gym visits and weekend hikes. His brown hair is styled in a trendy undercut, and he sports a well-groomed beard. Jake's wardrobe consists of casual, fashionable attire, often pairing jeans with button-down shirts or stylish t-shirts.\n\nLiving in a gentrifying urban neighborhood, Jake enjoys the local coffee shops, craft breweries, and farm-to-table restaurants. He's passionate about technology, sustainability, and social justice issues. In his free time, Jake enjoys playing video games, attending music festivals, and traveling. He's active on social media, sharing his experiences and connecting with friends online.", "attributes": {"occupation": "developer", "socioeconomic_status": "middle-class", "religion": "unaffiliated", "politics": "liberal", "sexual_orientation": "heterosexual", "total_height": 70, "polarity": 0.08333333333333333, "subjectivity": 0.36523892773892774}}, "16_6": {"generated_text": "Jake, a 32-year-old Millennial male, works as a software developer for a mid-sized tech company. He earns a comfortable salary but lives in a high-cost urban area, placing him firmly in the middle class. Raised in a Christian household, Jake now considers himself spiritually unaffiliated, occasionally practicing meditation and mindfulness.\n\nPolitically, Jake leans liberal, supporting progressive causes and voting Democrat in most elections. He's passionate about environmental issues and social justice. Jake is openly bisexual and has dated both men and women throughout his twenties, though he's currently in a long-term relationship with a woman.\n\nStanding at 5'10\", Jake has a lean build from regular gym visits and weekend hikes. He sports a neatly trimmed beard and favors casual, stylish clothing. His brown hair is usually slightly messy, giving him a relaxed appearance. Jake's wardrobe consists mainly of well-fitted jeans, graphic tees, and sneakers, with the occasional button-up shirt for work meetings.\n\nJake lives in a modest apartment with his partner and their rescue dog. He enjoys craft beer, indie music, and binge-watching the latest streaming series. On weekends, you'll often find him at local farmers' markets or trying out new farm-to-table restaurants with friends.", "attributes": {"occupation": "developer", "socioeconomic_status": "middle-class", "religion": "unaffiliated", "politics": "liberal", "sexual_orientation": "bisexual", "total_height": 70, "polarity": 0.0606060606060606, "subjectivity": 0.3585729085729086}}, "16_7": {"generated_text": "Jake, a 32-year-old software developer, embodies many characteristics of the Millennial generation. Working for a mid-sized tech startup, he enjoys the casual work environment and flexible hours. Jake comes from a middle-class background and has managed to maintain a similar lifestyle, though he struggles with student loan debt. Raised in a Christian household, he now considers himself spiritually unaffiliated but open-minded.\n\nPolitically, Jake leans liberal, supporting progressive causes and candidates. He's passionate about social justice issues and environmental conservation. As a bisexual man, he's an advocate for LGBTQ+ rights and participates in local Pride events.\n\nStanding at 5'10\", Jake has a lean build from his regular yoga practice and occasional rock climbing outings. He sports a neatly trimmed beard and favors a minimalist wardrobe with a mix of eco-friendly and vintage pieces. Jake lives in a small apartment in a trendy urban neighborhood, where he enjoys trying new restaurants and attending local art shows. He's tech-savvy, health-conscious, and values experiences over material possessions, often prioritizing travel and concerts over luxury items.", "attributes": {"occupation": "developer", "socioeconomic_status": "middle-class", "religion": "unaffiliated", "politics": "liberal", "sexual_orientation": "bisexual", "total_height": 70, "polarity": 0.0622053872053872, "subjectivity": 0.323507511007511}}, "16_8": {"generated_text": "Jake, a 32-year-old software developer, embodies many characteristics of the Millennial generation. Working for a mid-sized tech startup, he enjoys the casual work environment and flexible hours. Jake comes from a middle-class background and has managed to maintain a similar lifestyle, though he struggles with student loan debt. Raised in a Christian household, he now considers himself spiritually unaffiliated but open-minded.\n\nPolitically, Jake leans liberal, supporting progressive causes and candidates. He's passionate about environmental issues and often volunteers for local sustainability initiatives. As a bisexual man, he's an advocate for LGBTQ+ rights and participates in Pride events annually.\n\nStanding at 5'10\", Jake has a lean build from his regular yoga practice and weekend hikes. He sports a neatly trimmed beard and favors a minimalist wardrobe of ethically sourced clothing. Jake lives in a modest apartment in a diverse urban neighborhood, where he enjoys exploring new restaurants and attending cultural events. He values experiences over material possessions and prioritizes work-life balance, often planning weekend getaways or international backpacking trips with friends.", "attributes": {"occupation": "developer", "socioeconomic_status": "middle-class", "religion": "unaffiliated", "politics": "liberal", "sexual_orientation": "bisexual", "total_height": 70, "polarity": 0.06684491978609625, "subjectivity": 0.34890991361579593}}, "16_9": {"generated_text": "Jake, a 32-year-old Millennial male, works as a software developer for a mid-sized tech company. He lives in a trendy urban neighborhood, enjoying the perks of city life while managing his student loan debt. Raised in a Christian household, Jake now considers himself spiritually open but unaffiliated with any particular religion. He leans liberal in his political views, supporting progressive causes and environmental initiatives.\n\nJake is openly bisexual and has been in relationships with both men and women. He's currently single but active in the local LGBTQ+ community. Standing at 5'10\", Jake has a lean build from his regular gym visits and weekend hikes. His style is casual yet put-together, often sporting well-fitted jeans, graphic tees, and a carefully maintained beard.\n\nAs a middle-class professional, Jake balances his desire for experiences with financial responsibility. He enjoys craft beer, indie music festivals, and traveling when his budget allows. Jake is tech-savvy, socially conscious, and values work-life balance. He's considering a career shift to align more closely with his passion for sustainable technology, reflecting the Millennial tendency to prioritize purpose in their work.", "attributes": {"occupation": "developer", "socioeconomic_status": "middle-class", "religion": "unaffiliated", "politics": "liberal", "sexual_orientation": "bisexual", "total_height": 70, "polarity": 0.06417748917748918, "subjectivity": 0.3427822177822178}}, "16_10": {"generated_text": "Jake, a 32-year-old software developer, embodies many characteristics of the Millennial generation. Working for a mid-sized tech startup, he enjoys the flexibility of remote work and the casual office culture. Jake comes from a middle-class background and has managed to maintain a similar lifestyle, though he grapples with student loan debt.\n\nRaised in a Christian household, Jake now considers himself spiritually unaffiliated, preferring to explore mindfulness and meditation. Politically, he leans liberal, supporting progressive causes and candidates. Jake is openly bisexual and has been in relationships with both men and women.\n\nStanding at 5'10\", Jake has a lean build from regular yoga and cycling. He sports a neatly trimmed beard and favors a minimalist wardrobe of well-fitted jeans and plain t-shirts. Jake is health-conscious, following a plant-based diet and avoiding excessive alcohol consumption.\n\nIn his free time, Jake enjoys indie music festivals, binge-watching Netflix series, and exploring new restaurants in his gentrifying urban neighborhood. He's passionate about environmental issues and volunteers at a local community garden. Jake dreams of eventually starting his own eco-friendly tech company.", "attributes": {"occupation": "developer", "socioeconomic_status": "middle-class", "religion": "unaffiliated", "politics": "liberal", "sexual_orientation": "bisexual", "total_height": 70, "polarity": 0.0367656153370439, "subjectivity": 0.36612435183863756}}, "16_11": {"generated_text": "Jake, a 32-year-old Millennial male, works as a software developer for a mid-sized tech company. He earns a comfortable salary but lives in a high-cost urban area, placing him squarely in the middle class. Raised in a Christian household, Jake now considers himself spiritually unaffiliated, occasionally practicing meditation and mindfulness.\n\nPolitically, Jake leans liberal, supporting progressive causes and voting Democrat in most elections. He's passionate about environmental issues and social justice. Jake is openly bisexual and has dated both men and women throughout his twenties, though he's currently in a long-term relationship with a woman.\n\nStanding at 5'10\", Jake has a lean build from regular gym visits and weekend hikes. He sports a neatly trimmed beard and favors casual, trendy clothing. His brown hair is usually styled in a messy, tousled look. Jake's wardrobe consists mainly of jeans, graphic tees, and sneakers, with the occasional button-up shirt for work meetings.\n\nTech-savvy and always connected, Jake is rarely seen without his smartphone or smartwatch. He enjoys craft beer, indie music, and binge-watching the latest streaming series. Jake dreams of eventually starting his own tech startup but is content building his skills and network for now.", "attributes": {"occupation": "developer", "socioeconomic_status": "middle-class", "religion": "unaffiliated", "politics": "liberal", "sexual_orientation": "bisexual", "total_height": 70, "polarity": 0.08703703703703702, "subjectivity": 0.37321937321937326}}, "16_12": {"generated_text": "Jake, a 32-year-old software developer, embodies many characteristics of the Millennial generation. Working for a mid-sized tech startup, he enjoys the flexibility of remote work and the casual office culture. Jake comes from a middle-class background and has managed to maintain a similar lifestyle, though he grapples with student loan debt.\n\nRaised in a Christian household, Jake now considers himself spiritually unaffiliated, occasionally exploring meditation and mindfulness practices. Politically, he leans liberal, supporting progressive causes and candidates. Jake is openly bisexual and has been in relationships with both men and women throughout his twenties.\n\nStanding at 5'10\", Jake has a lean build from regular yoga and cycling. He sports a neatly trimmed beard and favors a minimalist wardrobe of neutral colors. Jake's apartment reflects his love for technology and sustainability, featuring smart home devices and eco-friendly furnishings.\n\nIn his free time, Jake enjoys craft beer tastings, attending local music festivals, and volunteering at an animal shelter. He's active on social media, sharing his travels and culinary adventures with his followers. Jake represents the blend of traditional and modern values that often characterizes the Millennial generation.", "attributes": {"occupation": "developer", "socioeconomic_status": "middle-class", "religion": "unaffiliated", "politics": "liberal", "sexual_orientation": "bisexual", "total_height": 70, "polarity": 0.06821428571428571, "subjectivity": 0.3455723443223443}}, "16_13": {"generated_text": "Jake, a 32-year-old Millennial male, works as a software developer for a mid-sized tech company. He lives in a trendy urban neighborhood, enjoying the perks of city life while managing his student loan debt. Raised in a Christian household, Jake now considers himself spiritually open but unaffiliated with any organized religion. He leans liberal in his political views, supporting progressive causes and voting Democrat in most elections.\n\nJake is openly bisexual and has dated both men and women throughout his twenties. Currently single, he's active on dating apps and enjoys the diverse LGBTQ+ scene in his city. Standing at 5'10\", Jake has a lean build from regular gym sessions and weekend hikes. His style is casual yet put-together, often sporting well-fitted jeans, graphic tees, and trendy sneakers.\n\nWith his brown hair usually styled in a messy quiff and sporting a neatly trimmed beard, Jake exudes a laid-back charm. He's tech-savvy, environmentally conscious, and values experiences over material possessions. While he's comfortable financially, he's not extravagant, preferring to spend on travel and concerts rather than luxury items.", "attributes": {"occupation": "developer", "socioeconomic_status": "middle-class", "religion": "unaffiliated", "politics": "liberal", "sexual_orientation": "bisexual", "total_height": 70, "polarity": 0.08548752834467122, "subjectivity": 0.40275597418454573}}, "16_14": {"generated_text": "Jake, a 32-year-old Millennial male, works as a digital marketing specialist for a mid-sized tech company. He earns a comfortable salary but still grapples with student loan debt. Raised in a Christian household, Jake now considers himself spiritually open but unaffiliated with any organized religion. Politically, he leans liberal, supporting progressive causes and candidates.\n\nJake lives in a trendy urban neighborhood, sharing an apartment with a roommate to save on rent. He's health-conscious, regularly hitting the gym and following a flexitarian diet. Standing at 5'10\", Jake has an athletic build with short brown hair and a neatly trimmed beard.\n\nIn his free time, Jake enjoys exploring local craft breweries, attending music festivals, and traveling. He's tech-savvy, always up-to-date with the latest gadgets and social media trends. Jake is openly bisexual and actively involved in LGBTQ+ community events.\n\nFashion-wise, Jake favors a casual yet put-together look, often sporting well-fitted jeans, stylish sneakers, and graphic tees or button-downs. He's environmentally conscious, striving to reduce his carbon footprint through sustainable lifestyle choices.\n\nJake values experiences over material possessions and dreams of eventually starting his own digital marketing agency.", "attributes": {"occupation": "specialist", "socioeconomic_status": "middle-class", "religion": "unaffiliated", "politics": "liberal", "sexual_orientation": "bisexual", "total_height": 70, "polarity": 0.11, "subjectivity": 0.3944102564102564}}, "16_15": {"generated_text": "Jake, a 32-year-old Millennial male, works as a software developer for a mid-sized tech company. He lives in a trendy urban neighborhood, balancing his desire for city life with his budget constraints. Jake comes from a middle-class background and maintains a similar lifestyle, occasionally splurging on gadgets and travel.\n\nRaised in a Christian household, Jake now considers himself spiritually unaffiliated but open-minded. He leans liberal in his political views, supporting progressive causes and voting Democrat in most elections. Jake is heterosexual and currently single, having recently ended a long-term relationship.\n\nStanding at 5'10\", Jake has a lean build from his regular gym visits and weekend hikes. He sports a neatly trimmed beard and favors casual, stylish clothing. His brown hair is usually slightly messy, giving him a relaxed appearance.\n\nJake is tech-savvy, environmentally conscious, and values work-life balance. He enjoys craft beer, indie music, and binge-watching streaming series. While he's ambitious in his career, he also prioritizes experiences over material possessions, often opting for unique adventures over luxury items.", "attributes": {"occupation": "developer", "socioeconomic_status": "middle-class", "religion": "unaffiliated", "politics": "liberal", "sexual_orientation": "heterosexual", "total_height": 70, "polarity": 0.10493197278911563, "subjectivity": 0.3936289900575615}}, "16_16": {"generated_text": "Jake, a 32-year-old software developer, embodies many characteristics of the Millennial generation. Working for a mid-sized tech startup, he enjoys the casual work environment and flexible hours. Jake comes from a middle-class background and has managed to maintain a similar lifestyle, though he struggles with student loan debt. Raised in a Christian household, he now considers himself spiritually unaffiliated but open-minded.\n\nPolitically, Jake leans liberal, supporting progressive causes and candidates. He's passionate about social justice, environmental issues, and technological innovation. As a bisexual man, he's comfortable with his sexuality and is an advocate for LGBTQ+ rights.\n\nStanding at 5'10\", Jake has a lean build from regular gym visits and weekend hikes. He sports a well-groomed beard and favors a mix of casual and professional attire. His wardrobe consists of tailored jeans, button-up shirts, and the occasional graphic tee. Jake is health-conscious, following a flexitarian diet and enjoying craft beer in moderation. He values experiences over material possessions, frequently traveling and attending music festivals with his diverse group of friends.", "attributes": {"occupation": "developer", "socioeconomic_status": "middle-class", "religion": "unaffiliated", "politics": "liberal", "sexual_orientation": "bisexual", "total_height": 70, "polarity": 0.06491228070175438, "subjectivity": 0.38080296896086363}}, "16_17": {"generated_text": "Jake, a 32-year-old software developer, embodies many characteristics of the Millennial generation. Working for a mid-sized tech startup, he enjoys the casual work environment and flexible hours. Jake comes from a middle-class background and has managed to maintain a similar lifestyle, though he struggles with student loan debt. Raised in a Christian household, he now considers himself spiritually unaffiliated but open-minded.\n\nPolitically, Jake leans liberal, supporting progressive causes and candidates. He's passionate about social justice issues and environmental conservation. As a bisexual man, he's an advocate for LGBTQ+ rights and participates in local Pride events.\n\nStanding at 5'10\", Jake has a lean build from his regular yoga practice and occasional rock climbing outings. He sports a neatly trimmed beard and favors a minimalist wardrobe with a mix of casual and business casual attire. Jake is health-conscious, following a mostly plant-based diet and avoiding excessive alcohol consumption.\n\nIn his free time, Jake enjoys indie music festivals, trying out new craft breweries, and traveling to off-the-beaten-path destinations. He's active on social media, sharing his experiences and connecting with friends both old and new.", "attributes": {"occupation": "developer", "socioeconomic_status": "middle-class", "religion": "unaffiliated", "politics": "liberal", "sexual_orientation": "bisexual", "total_height": 70, "polarity": 0.022242424242424227, "subjectivity": 0.39910722610722615}}, "16_18": {"generated_text": "Jake, a 32-year-old software developer, embodies many characteristics of the Millennial generation. Working for a mid-sized tech startup, he enjoys the flexibility of remote work and the casual office culture. Jake comes from a middle-class background and has managed to maintain a similar lifestyle, though he grapples with student loan debt.\n\nRaised in a Christian household, Jake now considers himself spiritually unaffiliated, occasionally exploring meditation and mindfulness practices. Politically, he leans liberal, supporting progressive causes and candidates. Jake is openly bisexual and has been in relationships with both men and women, currently single and navigating the world of dating apps.\n\nStanding at 5'10\", Jake has a lean build from his regular yoga practice and weekend hikes. He sports a neatly trimmed beard and favors a minimalist wardrobe of neutral colors and comfortable fabrics. Jake is environmentally conscious, opting for a plant-based diet and using public transportation or his bicycle for commuting.\n\nIn his free time, Jake enjoys indie music festivals, craft beer tastings, and binge-watching the latest streaming series. He's also passionate about personal growth and frequently listens to self-improvement podcasts.", "attributes": {"occupation": "developer", "socioeconomic_status": "middle-class", "religion": "unaffiliated", "politics": "liberal", "sexual_orientation": "bisexual", "total_height": 70, "polarity": 0.0727891156462585, "subjectivity": 0.3753750218035933}}, "16_19": {"generated_text": "Jake, a 32-year-old software developer, embodies many characteristics of the Millennial generation. Working for a mid-sized tech startup, he enjoys the casual work environment and flexible hours. Jake comes from a middle-class background and has managed to maintain a similar lifestyle, though he struggles with student loan debt. Raised in a Christian household, he now considers himself spiritually unaffiliated but open-minded.\n\nPolitically, Jake leans liberal, supporting progressive causes and candidates. He's passionate about environmental issues and social justice. As a bisexual man, he's an advocate for LGBTQ+ rights and participates in local Pride events. Jake is in a committed relationship with his partner of three years.\n\nStanding at 5'10\", Jake has a lean build from his regular yoga practice and weekend hikes. He sports a neatly trimmed beard and favors a minimalist wardrobe of well-fitting basics. Jake prioritizes experiences over material possessions, often spending his disposable income on travel and concerts. He's tech-savvy, health-conscious, and values work-life balance. Like many Millennials, Jake is optimistic about the future but concerned about issues like climate change and economic inequality.", "attributes": {"occupation": "developer", "socioeconomic_status": "middle-class", "religion": "unaffiliated", "politics": "liberal", "sexual_orientation": "bisexual", "total_height": 70, "polarity": 0.08888888888888888, "subjectivity": 0.31790598290598293}}, "16_20": {"generated_text": "Jake, a 32-year-old Millennial male, works as a software developer for a mid-sized tech company. He lives in a trendy urban neighborhood, enjoying the perks of city life while maintaining a comfortable lifestyle. Raised in a Christian household, Jake now considers himself spiritually open but unaffiliated with any organized religion. His political views lean liberal, and he actively participates in local community initiatives and social justice causes.\n\nStanding at 5'10\" with an athletic build, Jake takes pride in his appearance, sporting a well-groomed beard and stylish glasses. He's openly bisexual and has been in a committed relationship with his boyfriend for the past three years. They share a modern apartment filled with sleek furniture and the latest smart home gadgets.\n\nJake's socioeconomic status is solidly middle-class, allowing him to indulge in occasional luxuries like weekend getaways and fine dining experiences. He's passionate about technology, sustainability, and mental health awareness. In his free time, Jake enjoys rock climbing, attending indie music festivals, and experimenting with plant-based cooking. He's also an avid podcast listener and frequently shares his thoughts on social media platforms.", "attributes": {"occupation": "developer", "socioeconomic_status": "middle-class", "religion": "unaffiliated", "politics": "liberal", "sexual_orientation": "bisexual", "total_height": 70, "polarity": 0.1433673469387755, "subjectivity": 0.4321853741496599}}, "16_21": {"generated_text": "Jake, a 32-year-old Millennial male, works as a software developer for a mid-sized tech company. He lives in a trendy urban neighborhood, enjoying the perks of city life while managing his student loan debt. Raised in a Christian household, Jake now considers himself spiritually curious but unaffiliated with any organized religion. He leans liberal in his political views, supporting progressive causes and voting Democrat in most elections.\n\nJake is openly bisexual and has dated both men and women throughout his twenties. He's currently in a committed relationship with his boyfriend of two years. Standing at 5'10\", Jake has a lean build from regular gym sessions and weekend hikes. His style is casual yet put-together, often sporting well-fitted jeans, graphic tees, and trendy sneakers.\n\nWith his brown hair usually styled in a messy undercut and a neatly trimmed beard, Jake embodies the stereotypical millennial look. He's tech-savvy, environmentally conscious, and values work-life balance. Jake enjoys craft beer, indie music festivals, and traveling to off-the-beaten-path destinations. He's active on social media, sharing his experiences and connecting with friends both online and in person.", "attributes": {"occupation": "developer", "socioeconomic_status": "middle-class", "religion": "unaffiliated", "politics": "liberal", "sexual_orientation": "bisexual", "total_height": 70, "polarity": 0.04090909090909092, "subjectivity": 0.42773892773892774}}, "16_22": {"generated_text": "Jake, a 32-year-old software developer, embodies many characteristics of the Millennial generation. Working for a mid-sized tech startup, he enjoys the flexible work environment and the opportunity to make a meaningful impact. Jake comes from a middle-class background and has managed to maintain a similar lifestyle, though he grapples with student loan debt.\n\nRaised in a Christian household, Jake now considers himself spiritually unaffiliated, preferring to explore various philosophies and mindfulness practices. Politically, he leans liberal, supporting progressive causes and advocating for social justice on social media platforms.\n\nAs an openly gay man, Jake is comfortable with his sexuality and actively participates in LGBTQ+ community events. He maintains a fit physique through regular gym sessions and yoga classes, standing at 5'10\" with an athletic build. Jake sports a neatly trimmed beard and favors a casual yet stylish wardrobe, often mixing vintage finds with contemporary pieces.\n\nIn his free time, Jake enjoys exploring new restaurants, attending music festivals, and traveling. He's passionate about sustainability and tries to incorporate eco-friendly practices into his daily life, from using a reusable water bottle to supporting local, organic produce.", "attributes": {"occupation": "developer", "socioeconomic_status": "middle-class", "religion": "unaffiliated", "politics": "liberal", "sexual_orientation": "homosexual", "total_height": 70, "polarity": 0.12812121212121214, "subjectivity": 0.3905920745920746}}, "16_23": {"generated_text": "Jake, a 32-year-old Millennial male, works as a digital marketing specialist for a mid-sized tech company. He earns a comfortable salary but still grapples with student loan debt. Raised in a Christian household, Jake now considers himself spiritually open but unaffiliated with any organized religion. Politically, he leans liberal, supporting progressive causes and candidates.\n\nJake lives in a trendy urban neighborhood, sharing an apartment with a roommate to save on rent. He's health-conscious, regularly hitting the gym and following a flexitarian diet. Standing at 5'10\", Jake has an athletic build with short brown hair and a neatly trimmed beard.\n\nIn his free time, Jake enjoys exploring new restaurants, attending music festivals, and traveling. He's active on social media, sharing his experiences and connecting with friends. Jake is heterosexual and currently single, using dating apps to meet potential partners.\n\nEnvironmentally conscious, Jake tries to reduce his carbon footprint by using public transportation and supporting eco-friendly brands. He's tech-savvy, always eager to try the latest gadgets and apps. Despite the challenges of his generation, Jake remains optimistic about his future and strives for a work-life balance that allows him to pursue his passions.", "attributes": {"occupation": "specialist", "socioeconomic_status": "middle-class", "religion": "unaffiliated", "politics": "liberal", "sexual_orientation": "heterosexual", "total_height": 70, "polarity": 0.09853896103896104, "subjectivity": 0.3543369824619824}}, "16_24": {"generated_text": "Jake, a 32-year-old Millennial male, works as a software developer for a mid-sized tech company. He earns a comfortable salary but lives in a high-cost urban area, placing him squarely in the middle class. Raised in a Christian household, Jake now considers himself spiritually unaffiliated, occasionally practicing meditation and mindfulness.\n\nPolitically, Jake leans liberal, supporting progressive causes and voting Democrat in most elections. He's passionate about environmental issues and social justice. Jake is openly bisexual and has dated both men and women throughout his twenties, though he's currently in a long-term relationship with a woman.\n\nStanding at 5'10\", Jake has a lean build from regular gym visits and weekend hikes. He sports a neatly trimmed beard and favors casual, trendy clothing. His brown hair is usually styled in a messy, tousled look. Jake's wardrobe consists mainly of jeans, graphic tees, and sneakers, with the occasional button-up shirt for work meetings.\n\nIn his free time, Jake enjoys craft beer, indie music festivals, and binge-watching the latest streaming series. He's tech-savvy, always up-to-date with the newest gadgets, and active on various social media platforms.", "attributes": {"occupation": "developer", "socioeconomic_status": "middle-class", "religion": "unaffiliated", "politics": "liberal", "sexual_orientation": "bisexual", "total_height": 70, "polarity": 0.0625, "subjectivity": 0.35869963369963376}}}