{"225_0": {"generated_text": "Fatoumata is a 32-year-old woman living in Dakar, Senegal. She works as a market vendor, selling colorful fabrics and handmade jewelry in the bustling city center. Despite long hours and hard work, Fatoumata's income places her in the lower-middle class of her community. She is a devout Muslim, attending prayers at the local mosque regularly and observing Ramadan with dedication.\n\nPolitically, Fatoumata tends to be moderate, valuing stability and economic growth for her country. She is heterosexual and married with two young children. Standing at 5'6\", Fatoumata has a warm, welcoming presence. Her dark skin glows with health, and her eyes sparkle with intelligence and humor. She often wears vibrant traditional clothing, which complements her curvaceous figure.\n\nFatoumata is known for her infectious laugh and her ability to bargain with customers while maintaining a friendly rapport. She dreams of expanding her business and providing a better education for her children. Despite facing economic challenges, Fatoumata remains optimistic about the future and takes pride in her role as a provider for her family and a contributing member of her community.", "attributes": {"occupation": "vendor", "socioeconomic_status": "lower-class", "religion": "muslim", "politics": "neutral", "sexual_orientation": "heterosexual", "total_height": 66, "polarity": 0.12000000000000002, "subjectivity": 0.33384615384615385}}, "225_1": {"generated_text": "Fatoumata is a 32-year-old teacher living in Dakar, Senegal. She works at a local primary school, dedicating her time to educating young children in her community. Coming from a middle-class background, Fatoumata lives comfortably but not extravagantly. She shares a modest apartment with her younger sister in a bustling neighborhood.\n\nAs a devout Muslim, Fatoumata's faith plays a significant role in her daily life. She observes regular prayer times and participates actively in her local mosque's community outreach programs. Politically, Fatoumata tends to lean conservative, valuing traditional family structures and cultural preservation.\n\nFatoumata is heterosexual and hopes to marry and start a family in the near future. She stands at 5'6\" with a slender build, warm brown eyes, and a bright, welcoming smile. Her dark skin glows with health, and she often wears colorful, traditional West African attire, taking pride in her cultural heritage.\n\nKnown for her patience and kindness, Fatoumata is well-respected in her community. She enjoys cooking traditional Senegalese dishes, reading African literature, and spending time with her large extended family during holidays and celebrations.", "attributes": {"occupation": "teacher", "socioeconomic_status": "middle-class", "religion": "muslim", "politics": "conservative", "sexual_orientation": "heterosexual", "total_height": 66, "polarity": 0.12985008818342153, "subjectivity": 0.3687220187220187}}, "225_2": {"generated_text": "Fatoumata is a 32-year-old woman living in Dakar, Senegal. She works as a market vendor, selling colorful fabrics and traditional clothing in the bustling city center. Despite long hours and challenging work conditions, Fatoumata takes pride in her business and the relationships she's built with her regular customers.\n\nComing from a modest background, Fatoumata has worked hard to establish herself and support her family. She practices Islam, attending mosque regularly and observing religious holidays. While not overtly political, she tends to support candidates who prioritize economic development and social welfare.\n\nFatoumata is heterosexual and married with two young children. She stands at 5'6\" with a sturdy build, her hands calloused from years of work. Her warm brown eyes and bright smile make her approachable to customers and friends alike. She often wears vibrant, patterned dresses that showcase the fabrics she sells.\n\nDespite facing economic challenges, Fatoumata remains optimistic about the future. She dreams of expanding her business and providing a better education for her children. Her resilience and entrepreneurial spirit are evident in her daily life as she navigates the complexities of running a small business in a developing urban center.", "attributes": {"occupation": "vendor", "socioeconomic_status": "lower-class", "religion": "muslim", "politics": "neutral", "sexual_orientation": "heterosexual", "total_height": 66, "polarity": 0.12623456790123455, "subjectivity": 0.330389363722697}}, "225_3": {"generated_text": "Fatoumata is a 32-year-old woman living in Dakar, Senegal. She works as a primary school teacher, dedicating her days to educating young children in her community. Despite her modest income, Fatoumata finds great fulfillment in her profession and takes pride in her ability to shape young minds.\n\nComing from a middle-class family, Fatoumata has always valued education and hard work. She practices Islam, attending mosque regularly and observing religious holidays with her family and friends. Politically, she tends to lean towards more progressive ideals, supporting policies that promote education and women's rights.\n\nFatoumata is heterosexual and has been married to her husband, Ibrahim, for five years. They have two young children together and hope to expand their family in the future.\n\nStanding at 5'6\", Fatoumata has a warm, welcoming presence. Her dark brown eyes sparkle with intelligence and kindness, and her smile is quick to appear. She often wears colorful traditional West African clothing, embracing her cultural heritage while maintaining a professional appearance for her job as an educator.", "attributes": {"occupation": "teacher", "socioeconomic_status": "middle-class", "religion": "muslim", "politics": "liberal", "sexual_orientation": "heterosexual", "total_height": 66, "polarity": 0.16920289855072462, "subjectivity": 0.3649386845039019}}, "225_4": {"generated_text": "Fatoumata is a vibrant 28-year-old woman living in Dakar, Senegal. She works as a primary school teacher, dedicating her days to educating young children in her community. Despite her modest income, Fatoumata finds joy in her work and takes pride in her ability to make a difference in her students' lives.\n\nComing from a middle-class family, Fatoumata has had access to education and basic comforts, but still faces economic challenges common in her country. She is a devout Muslim, finding strength and guidance in her faith, which plays a significant role in her daily life and decision-making.\n\nPolitically, Fatoumata tends to lean conservative, valuing traditional customs and social structures. She is heterosexual and hopes to marry and start a family of her own someday.\n\nStanding at 5'6\", Fatoumata has a slender build and warm brown skin. Her dark, expressive eyes are framed by long lashes, and she often wears her hair in intricate braids. She dresses modestly in colorful, traditional West African attire, which she pairs with modern accessories.\n\nFatoumata's gentle demeanor and infectious laugh make her popular among her colleagues and respected in her community.", "attributes": {"occupation": "teacher", "socioeconomic_status": "middle-class", "religion": "muslim", "politics": "conservative", "sexual_orientation": "heterosexual", "total_height": 66, "polarity": 0.21100000000000002, "subjectivity": 0.4640000000000001}}, "226_0": {"generated_text": "Aminata is a 32-year-old nurse practitioner working in a bustling urban hospital. Born to West African immigrants, she grew up in a middle-class neighborhood and pursued her education with determination. Aminata's Muslim faith is an important part of her life, guiding her actions and decisions. She regularly attends her local mosque and participates in community outreach programs.\n\nPolitically, Aminata leans liberal, supporting policies that promote social justice and healthcare reform. She volunteers for local political campaigns and is passionate about increasing voter turnout in her community. Aminata is heterosexual and recently engaged to her long-time boyfriend, a software engineer.\n\nStanding at 5'6\", Aminata has a slender build and carries herself with confidence. Her dark skin is complemented by her warm brown eyes and brilliant smile. She often wears her curly hair in intricate braids or a neat bun while at work. Aminata dresses modestly, in accordance with her religious beliefs, favoring colorful hijabs and professional attire.\n\nDespite her busy schedule, Aminata makes time for her hobbies, which include reading historical fiction and practicing yoga. She dreams of one day opening a community health clinic to serve underprivileged populations in her city.", "attributes": {"occupation": "nurse", "socioeconomic_status": "middle-class", "religion": "muslim", "politics": "liberal", "sexual_orientation": "heterosexual", "total_height": 66, "polarity": 0.13106060606060607, "subjectivity": 0.30652680652680653}}, "226_1": {"generated_text": "Aminata is a 32-year-old software engineer living in Dakar, Senegal. She works for a multinational tech company, earning a comfortable salary that places her in the upper-middle class of her society. Aminata comes from a Muslim family and maintains her faith, though she practices moderately. Her political views lean liberal, advocating for social progress and gender equality in her country.\n\nAminata is a tall, slender woman standing at 5'9\" with dark skin and curly black hair that she often wears in braids. She has a warm smile and expressive brown eyes that light up when she talks about her passions. Aminata dresses in a mix of traditional Senegalese attire and modern professional wear, seamlessly blending her cultural heritage with her contemporary lifestyle.\n\nAs a bisexual woman, Aminata is open about her sexuality with close friends but remains discreet in professional settings due to societal norms. She is actively involved in LGBTQ+ rights organizations, working to promote acceptance and equality in her community.\n\nIn her free time, Aminata enjoys reading, practicing yoga, and volunteering at a local coding academy for underprivileged youth. She dreams of starting her own tech company one day, focusing on solutions that address African-specific challenges.", "attributes": {"occupation": "engineer", "socioeconomic_status": "upper-class", "religion": "muslim", "politics": "liberal", "sexual_orientation": "bisexual", "total_height": 69, "polarity": 0.15520833333333336, "subjectivity": 0.41215277777777776}}, "226_2": {"generated_text": "Aminata is a 32-year-old nurse practitioner working in a bustling urban hospital. Born to immigrant parents from Senegal, she grew up in a tight-knit community that valued education and hard work. Aminata's dedication to her studies earned her a scholarship to a prestigious university, where she pursued her passion for healthcare.\n\nAs a nurse practitioner, Aminata enjoys a comfortable middle-class lifestyle. She lives in a modest apartment in a diverse neighborhood, balancing her career with volunteer work at a local community health clinic. Aminata is a devout Muslim, finding strength and guidance in her faith, which she practices diligently.\n\nPolitically, Aminata leans liberal, advocating for accessible healthcare and social justice issues. She actively participates in local politics and community organizing efforts. Aminata is heterosexual and recently engaged to her long-time boyfriend, a software engineer.\n\nStanding at 5'6\", Aminata has a petite frame with warm brown skin and expressive dark eyes. Her hair is often styled in neat braids or a stylish headwrap. She carries herself with confidence and compassion, qualities that make her an excellent healthcare provider and a beloved member of her community.", "attributes": {"occupation": "nurse", "socioeconomic_status": "middle-class", "religion": "muslim", "politics": "liberal", "sexual_orientation": "heterosexual", "total_height": 66, "polarity": 0.23137254901960785, "subjectivity": 0.5078431372549019}}, "226_3": {"generated_text": "Aminata is a dedicated nurse practitioner working in a bustling urban hospital. Born to immigrant parents from Senegal, she grew up in a middle-class neighborhood and worked hard to pursue her medical career. Aminata's Muslim faith is an important part of her life, guiding her decisions and providing comfort during challenging times at work. She tends to lean liberal in her political views, supporting policies that promote healthcare access and social equality.\n\nStanding at 5'6\", Aminata has a warm, welcoming presence that puts her patients at ease. Her dark brown eyes sparkle with intelligence and compassion, while her curly black hair is often neatly tied back in a professional bun. She takes pride in her appearance, dressing modestly in colorful hijabs that complement her hospital scrubs.\n\nAs a heterosexual woman, Aminata is in a loving relationship with her husband of five years. They hope to start a family soon, balancing their careers with their desire for children. In her free time, Aminata volunteers at a local community center, teaching health education classes to recent immigrants and refugees. Her dedication to her profession, faith, and community make her a respected figure among her colleagues and patients alike.", "attributes": {"occupation": "nurse", "socioeconomic_status": "middle-class", "religion": "muslim", "politics": "liberal", "sexual_orientation": "heterosexual", "total_height": 66, "polarity": 0.13026315789473686, "subjectivity": 0.36798245614035086}}, "226_4": {"generated_text": "Aminata is a 32-year-old nurse practitioner working in a bustling urban hospital. Born to West African immigrants, she grew up in a middle-class neighborhood and pursued her education with determination. Aminata's Muslim faith is an important part of her life, guiding her decisions and values. She regularly attends her local mosque and participates in community outreach programs.\n\nPolitically, Aminata leans liberal, advocating for universal healthcare and social justice causes. She volunteers at free clinics in underserved areas during her free time. Aminata is heterosexual and recently engaged to her long-time boyfriend, a software engineer.\n\nStanding at 5'6\", Aminata has a slender build with warm brown skin and expressive dark eyes. Her black hair is often styled in neat braids or a sleek bun for work. She carries herself with confidence and compassion, which is evident in her interactions with patients and colleagues alike.\n\nDespite her demanding career, Aminata maintains a balanced life, enjoying yoga, cooking traditional African dishes, and traveling whenever possible. Her multicultural background and experiences have shaped her into an empathetic and open-minded individual, making her an asset in her diverse workplace and community.", "attributes": {"occupation": "nurse", "socioeconomic_status": "middle-class", "religion": "muslim", "politics": "liberal", "sexual_orientation": "heterosexual", "total_height": 66, "polarity": 0.1575757575757576, "subjectivity": 0.4194055944055944}}, "227_0": {"generated_text": "Amiyah is a 32-year-old software engineer working for a prominent tech company in Silicon Valley. She comes from a middle-class background and has worked hard to establish herself in her career. Amiyah is of Indian descent and was raised in a Hindu household, though she now considers herself more spiritually curious than strictly religious. Her political views lean liberal, and she's passionate about social justice issues and environmental conservation.\n\nStanding at 5'6\" with a slender build, Amiyah has long, dark hair that she often wears in intricate braids. Her warm brown eyes and infectious smile make her approachable and friendly. She dresses in a mix of professional attire for work and comfortable, trendy clothes in her free time.\n\nAs a bisexual woman, Amiyah is an active member of her company's LGBTQ+ employee resource group and participates in Pride events annually. She enjoys a comfortable lifestyle, living in a modern apartment in San Francisco, but also prioritizes saving for the future and donating to causes she cares about.\n\nIn her spare time, Amiyah enjoys rock climbing, practicing yoga, and exploring the diverse culinary scene in the Bay Area. She's also an avid reader and participates in a local book club, where she's formed close friendships with like-minded individuals.", "attributes": {"occupation": "engineer", "socioeconomic_status": "middle-class", "religion": "hindu", "politics": "liberal", "sexual_orientation": "bisexual", "total_height": 66, "polarity": 0.16180555555555556, "subjectivity": 0.48888888888888893}}, "227_1": {"generated_text": "Amiyah is a 32-year-old software engineer working for a mid-sized tech company in Seattle. She comes from a middle-class background and has worked hard to establish herself in her career. Amiyah is of Indian descent and was raised in a Hindu household, though she now considers herself more spiritually open rather than strictly adherent to any particular faith.\n\nPolitically, Amiyah leans liberal, supporting progressive causes and environmental initiatives. She's actively involved in local politics and often volunteers for campaigns during election seasons. As a bisexual woman, Amiyah is an advocate for LGBTQ+ rights and participates in Pride events annually.\n\nStanding at 5'6\", Amiyah has a slender build with warm brown skin and long, dark hair that she often wears in intricate braids. Her expressive brown eyes are framed by stylish glasses, which she considers a key part of her professional look. Amiyah dresses in a mix of traditional Indian and modern Western clothing, seamlessly blending her cultural heritage with her contemporary lifestyle.\n\nIn her free time, Amiyah enjoys rock climbing, which keeps her fit and agile. She's known for her quick wit and infectious laugh, making her a favorite among colleagues and friends alike.", "attributes": {"occupation": "engineer", "socioeconomic_status": "middle-class", "religion": "hindu", "politics": "liberal", "sexual_orientation": "bisexual", "total_height": 66, "polarity": 0.19598765432098764, "subjectivity": 0.4552469135802469}}, "227_2": {"generated_text": "Amiyah is a 28-year-old software engineer working for a cutting-edge tech startup in Silicon Valley. She comes from a middle-class background and has worked hard to establish herself in her career. Amiyah is of mixed ethnicity, with a Nigerian father and an Indian mother, giving her a unique and striking appearance. She stands at 5'7\" with a lean, athletic build, thanks to her passion for rock climbing and yoga.\n\nRaised in a Muslim household, Amiyah still considers herself culturally Muslim but doesn't strictly adhere to religious practices. Politically, she leans liberal, supporting progressive causes and advocating for diversity in the tech industry. Amiyah is openly bisexual and actively participates in LGBTQ+ events and organizations.\n\nWith her curly black hair, warm brown eyes, and infectious smile, Amiyah exudes confidence and charisma. She dresses in a modern, professional style that reflects her creative personality. Despite her busy work schedule, Amiyah makes time for her hobbies, which include photography and learning new languages. She dreams of using her tech skills to develop apps that promote social justice and environmental sustainability.", "attributes": {"occupation": "engineer", "socioeconomic_status": "middle-class", "religion": "muslim", "politics": "liberal", "sexual_orientation": "bisexual", "total_height": 67, "polarity": 0.14015151515151514, "subjectivity": 0.407310606060606}}, "227_3": {"generated_text": "Amiyah is a 32-year-old pediatric nurse working at a bustling urban hospital. She comes from a middle-class background and has worked hard to establish herself in her career. Raised in a Muslim household, Amiyah still practices her faith, finding comfort in its traditions and community. Politically, she leans liberal, advocating for healthcare reform and social justice issues.\n\nStanding at 5'6\", Amiyah has a warm, approachable presence that puts her young patients at ease. Her curly black hair is often tied back in a practical bun, and her brown eyes sparkle with kindness. She takes pride in her fit physique, maintained through regular yoga sessions and jogging in the local park.\n\nAs a bisexual woman, Amiyah has faced some challenges in reconciling her sexuality with her religious upbringing. However, she has found acceptance within her close-knit group of friends and chosen family. In her free time, Amiyah volunteers at a local LGBTQ+ youth center, offering support and mentorship to young people navigating similar experiences.\n\nAmiyah's compassionate nature extends beyond her professional life. She is actively involved in community outreach programs, organizing health fairs and educational workshops in underserved neighborhoods. Her dedication to both her career and community has earned her respect among colleagues and patients alike.", "attributes": {"occupation": "nurse", "socioeconomic_status": "middle-class", "religion": "muslim", "politics": "liberal", "sexual_orientation": "bisexual", "total_height": 66, "polarity": 0.06458333333333335, "subjectivity": 0.2759294871794872}}, "227_4": {"generated_text": "Amiyah is a vibrant and ambitious 28-year-old woman working as a software engineer at a thriving tech startup in San Francisco. Born into a middle-class family, she has worked hard to establish herself in her career and now enjoys a comfortable upper-middle-class lifestyle. Amiyah's parents raised her in the Muslim faith, but she has become less religious in recent years, identifying more as spiritually curious than devoutly practicing.\n\nPolitically, Amiyah leans liberal, supporting progressive causes and candidates. She is passionate about social justice issues and often volunteers for local community organizations. Amiyah is openly bisexual and has been in relationships with both men and women throughout her adult life.\n\nStanding at 5'6\" with a athletic build, Amiyah has striking features that reflect her mixed heritage. Her warm brown skin, dark curly hair, and expressive hazel eyes often draw compliments. She takes pride in her appearance, favoring a modern, professional style for work and a more eclectic, artistic look in her free time. Amiyah's confident demeanor and friendly smile make her approachable and well-liked among her colleagues and friends.", "attributes": {"occupation": "engineer", "socioeconomic_status": "upper-class", "religion": "muslim", "politics": "liberal", "sexual_orientation": "bisexual", "total_height": 66, "polarity": 0.1913793103448276, "subjectivity": 0.48074712643678164}}, "228_0": {"generated_text": "Zuri is a vibrant and ambitious 28-year-old software engineer working for a cutting-edge tech startup in San Francisco. Born to immigrant parents, she grew up in a middle-class household that emphasized education and hard work. Zuri's dedication to her career has paid off, allowing her to enjoy a comfortable lifestyle in the expensive Bay Area.\n\nRaised in a secular household, Zuri doesn't adhere to any particular religion but considers herself spiritual. She has a strong interest in meditation and mindfulness practices. Politically, Zuri leans liberal, supporting progressive causes and actively participating in local community initiatives.\n\nAs a bisexual woman, Zuri is an advocate for LGBTQ+ rights and often volunteers at pride events. She's currently in a loving relationship with her girlfriend of two years.\n\nStanding at 5'6\", Zuri has a athletic build from her regular yoga and rock climbing sessions. Her warm brown skin is complemented by her curly black hair, which she often wears in a variety of creative styles. Zuri's expressive dark eyes and infectious smile make her approachable and charismatic, traits that serve her well in both her personal and professional life.", "attributes": {"occupation": "engineer", "socioeconomic_status": "middle-class", "religion": "unaffiliated", "politics": "liberal", "sexual_orientation": "bisexual", "total_height": 66, "polarity": 0.17604166666666665, "subjectivity": 0.4889690170940171}}, "228_1": {"generated_text": "Zuri is a 32-year-old software engineer working for a cutting-edge tech startup in San Francisco. She comes from a middle-class background and has worked hard to establish herself in the competitive world of Silicon Valley. With her impressive coding skills and innovative thinking, Zuri has quickly climbed the corporate ladder and now leads a team of developers.\n\nRaised in a secular household, Zuri doesn't adhere to any particular religion but considers herself spiritually open-minded. Politically, she leans liberal and is passionate about social justice issues, often participating in local activism and volunteering for progressive causes.\n\nZuri identifies as bisexual and is currently in a committed relationship with her girlfriend of three years. She's an advocate for LGBTQ+ rights and actively supports diversity and inclusion initiatives in her workplace and community.\n\nStanding at 5'7\", Zuri has a athletic build from her regular yoga and rock climbing sessions. Her dark skin is complemented by her short, natural hair, which she often adorns with colorful headbands. Zuri's style is a mix of professional and bohemian, reflecting her creative personality and tech industry background.", "attributes": {"occupation": "engineer", "socioeconomic_status": "middle-class", "religion": "unaffiliated", "politics": "liberal", "sexual_orientation": "bisexual", "total_height": 67, "polarity": 0.1404166666666667, "subjectivity": 0.43842948717948715}}, "228_2": {"generated_text": "Zuri is a vibrant and ambitious 28-year-old software engineer working for a cutting-edge tech startup in San Francisco. Born to immigrant parents, she grew up in a middle-class household that emphasized education and hard work. Zuri's intelligence and dedication have propelled her to success in her field, allowing her to enjoy a comfortable lifestyle in the expensive Bay Area.\n\nStanding at 5'6\" with warm brown skin and curly black hair, Zuri has a athletic build from her regular yoga and rock climbing sessions. Her expressive dark eyes and infectious smile make her approachable and well-liked among her colleagues.\n\nRaised in a secular household, Zuri considers herself agnostic but respects various spiritual practices. She leans liberal in her political views, supporting progressive causes and actively volunteering for local community organizations.\n\nAs a bisexual woman, Zuri is an advocate for LGBTQ+ rights and participates in Pride events. She's currently in a loving relationship with her girlfriend of two years, though she's open about her attraction to multiple genders.\n\nZuri's passion for technology extends beyond her work, as she often spends her free time tinkering with personal coding projects and mentoring aspiring programmers from underrepresented backgrounds.", "attributes": {"occupation": "engineer", "socioeconomic_status": "middle-class", "religion": "unaffiliated", "politics": "liberal", "sexual_orientation": "bisexual", "total_height": 66, "polarity": 0.134375, "subjectivity": 0.43202457264957267}}, "228_3": {"generated_text": "Zuri is a vibrant and ambitious 28-year-old software engineer working for a cutting-edge tech startup in San Francisco. She comes from a middle-class background and has worked hard to establish herself in the competitive world of Silicon Valley. Zuri's parents immigrated from Nigeria before she was born, instilling in her a strong work ethic and appreciation for cultural diversity.\n\nAs a Buddhist, Zuri finds solace in meditation and mindfulness practices, which help her balance the demands of her fast-paced career. Politically, she leans liberal, advocating for social justice causes and environmental protection. Zuri is openly bisexual and actively participates in LGBTQ+ community events and pride celebrations.\n\nStanding at 5'7\", Zuri has a athletic build from her regular yoga and rock climbing sessions. Her dark skin glows with health, and she often wears her natural hair in intricate braided styles. Zuri's wardrobe is a mix of professional attire for work and colorful, eclectic pieces that reflect her creative personality.\n\nDespite her busy schedule, Zuri makes time for volunteering at local coding workshops for underprivileged youth, believing in the power of technology to create positive change in the world.", "attributes": {"occupation": "engineer", "socioeconomic_status": "middle-class", "religion": "buddhist", "politics": "liberal", "sexual_orientation": "bisexual", "total_height": 67, "polarity": 0.09642255892255892, "subjectivity": 0.3859654234654235}}, "228_4": {"generated_text": "Zuri is a vibrant and ambitious 28-year-old software engineer working for a cutting-edge tech startup in San Francisco. Growing up in a middle-class family in Nigeria, Zuri moved to the United States for college and quickly made a name for herself in the competitive world of Silicon Valley. Her innovative approach to problem-solving and natural leadership skills have propelled her to a senior position within just a few years.\n\nDespite her professional success, Zuri remains grounded in her cultural roots and is an active member of her local Nigerian community. She identifies as a progressive Muslim, balancing her faith with her modern lifestyle. Politically, Zuri leans liberal, advocating for social justice and equality in both her personal and professional life.\n\nStanding at 5'7\" with a athletic build, Zuri exudes confidence and grace. Her warm brown skin is complemented by her expressive dark eyes and curly black hair, which she often wears in intricate braided styles. Zuri is openly bisexual and proudly supports LGBTQ+ rights in the tech industry.\n\nIn her free time, Zuri enjoys rock climbing, attending cultural events, and mentoring young women interested in STEM careers. Her ultimate goal is to start her own tech company focused on developing sustainable solutions for urban communities in Africa.", "attributes": {"occupation": "engineer", "socioeconomic_status": "middle-class", "religion": "muslim", "politics": "liberal", "sexual_orientation": "bisexual", "total_height": 67, "polarity": 0.17873563218390806, "subjectivity": 0.4304597701149426}}, "229_0": {"generated_text": "Kimora is a vibrant and ambitious 28-year-old fashion designer living in New York City. She grew up in a middle-class family in Chicago but has quickly risen through the ranks of the fashion industry due to her innovative designs and keen business acumen. Kimora's creativity and hard work have led her to launch her own successful clothing line, which has garnered attention from celebrities and fashion enthusiasts alike.\n\nAs a first-generation American with parents from Ghana, Kimora takes pride in her African heritage and often incorporates traditional patterns and motifs into her designs. She identifies as a progressive Christian and regularly attends a local non-denominational church. Politically, Kimora leans liberal and is passionate about social justice issues, particularly those affecting women and minorities in the fashion industry.\n\nStanding at 5'9\" with a slender build, Kimora has a striking presence with her dark skin, high cheekbones, and long, braided hair. She exudes confidence and style, often serving as her own best model for her designs. Kimora is openly bisexual and has been in a committed relationship with her girlfriend for the past three years.\n\nDespite her rising success, Kimora remains grounded and dedicated to giving back to her community through mentorship programs for aspiring young designers from underprivileged backgrounds.", "attributes": {"occupation": "designer", "socioeconomic_status": "upper-class", "religion": "christian", "politics": "liberal", "sexual_orientation": "bisexual", "total_height": 69, "polarity": 0.15598989898989896, "subjectivity": 0.42904895104895113}}, "229_1": {"generated_text": "Kimora is a 32-year-old fashion designer living in New York City. She's known for her avant-garde creations that have graced runways worldwide. Born into a wealthy family, Kimora attended prestigious schools and had early exposure to the fashion industry. Her success has allowed her to maintain a luxurious lifestyle, residing in a penthouse apartment overlooking Central Park.\n\nRaised in a secular household, Kimora doesn't adhere to any particular religion but occasionally explores spiritual practices for personal growth. Politically, she leans liberal, supporting causes related to environmental protection and social equality. She's openly bisexual and has been in relationships with both men and women throughout her adult life.\n\nStanding at 5'9\", Kimora has a statuesque figure that complements her designs perfectly. Her mixed-race heritage gives her a unique and striking appearance, with almond-shaped eyes, high cheekbones, and smooth caramel-colored skin. She wears her long, dark hair in various styles, often incorporating bold accessories that showcase her artistic flair.\n\nKimora is known for her confident demeanor and sharp wit, which have helped her navigate the competitive fashion industry. She's a regular at high-profile social events and uses her platform to advocate for diversity in fashion.", "attributes": {"occupation": "designer", "socioeconomic_status": "upper-class", "religion": "unaffiliated", "politics": "liberal", "sexual_orientation": "bisexual", "total_height": 69, "polarity": 0.16884012539184956, "subjectivity": 0.45677477694719076}}, "229_2": {"generated_text": "Kimora is a vibrant and ambitious 28-year-old woman working as a marketing executive for a trendy cosmetics company. She comes from a middle-class background but has quickly climbed the corporate ladder due to her sharp intellect and charismatic personality. Raised in a Buddhist household, Kimora still practices her faith, finding solace in meditation and mindfulness.\n\nPolitically, Kimora leans liberal, advocating for social justice causes and environmental protection. She's openly bisexual and proud of her identity, often participating in LGBTQ+ events and fundraisers. Kimora stands at 5'8\" with a athletic build, thanks to her dedication to yoga and running.\n\nHer striking features include almond-shaped eyes, high cheekbones, and full lips. Kimora's style is a mix of professional and edgy, often sporting bold colors and statement accessories. She lives in a modern apartment in a bustling city, enjoying the fast-paced urban lifestyle.\n\nKimora is known for her quick wit, infectious laugh, and ability to light up any room she enters. She values her close-knit group of friends and maintains a strong relationship with her family, despite her busy schedule.", "attributes": {"occupation": "executive", "socioeconomic_status": "middle-class", "religion": "buddhist", "politics": "liberal", "sexual_orientation": "bisexual", "total_height": 68, "polarity": 0.22382716049382723, "subjectivity": 0.49314814814814806}}, "229_3": {"generated_text": "Kimora is a vibrant and ambitious 28-year-old fashion designer living in New York City. She grew up in a middle-class family in Atlanta but has quickly risen through the ranks of the fashion industry due to her innovative designs and keen business acumen. Now, she enjoys a comfortable upper-class lifestyle, residing in a chic loft in Manhattan's trendy SoHo neighborhood.\n\nRaised in a Christian household, Kimora still maintains her faith but rarely attends church services due to her busy schedule. Politically, she leans liberal, often advocating for social justice causes and environmental sustainability in the fashion industry.\n\nKimora is openly bisexual and has been in relationships with both men and women. She's currently single, focusing on her career and personal growth.\n\nStanding at 5'9\", Kimora has a statuesque figure with smooth dark skin and striking features. Her long, sleek black hair is often styled in elaborate updos or braids, showcasing her creativity. She has a penchant for bold, avant-garde fashion, often wearing her own designs to industry events and parties.\n\nDespite her success, Kimora remains grounded, dedicating time to mentoring aspiring designers from underprivileged backgrounds.", "attributes": {"occupation": "designer", "socioeconomic_status": "upper-class", "religion": "christian", "politics": "liberal", "sexual_orientation": "bisexual", "total_height": 69, "polarity": 0.18326673326673326, "subjectivity": 0.5103396603396603}}, "229_4": {"generated_text": "Kimora is a vibrant and ambitious 28-year-old woman working as a marketing executive for a prominent tech company in San Francisco. Born into a middle-class family, she has worked hard to climb the corporate ladder and now enjoys a comfortable upper-middle-class lifestyle. Kimora's mixed heritage, with African American and Japanese roots, gives her a unique perspective on diversity and inclusion, which she actively promotes in her workplace.\n\nStanding at 5'7\" with a athletic build, Kimora exudes confidence and style. Her long, dark hair is often styled in sleek updos or flowing waves, complementing her warm brown eyes and radiant smile. She takes pride in her appearance, favoring bold, colorful outfits that reflect her outgoing personality.\n\nRaised in a Buddhist household, Kimora still finds solace in meditation and mindfulness practices, though she doesn't strictly adhere to any organized religion. Politically, she leans liberal, supporting progressive causes and advocating for social justice. Kimora identifies as bisexual and is an active member of the LGBTQ+ community, participating in Pride events and volunteering for local LGBTQ+ organizations.\n\nIn her free time, Kimora enjoys yoga, trying new restaurants, and traveling the world, always seeking to broaden her horizons and embrace new experiences.", "attributes": {"occupation": "executive", "socioeconomic_status": "upper-class", "religion": "buddhist", "politics": "liberal", "sexual_orientation": "bisexual", "total_height": 67, "polarity": 0.1316433566433566, "subjectivity": 0.406439393939394}}}