{"265_0": {"generated_text": "Tracy is a 32-year-old marketing executive working for a mid-sized tech company in Seattle. She comes from a middle-class background and has worked hard to climb the corporate ladder. Tracy's parents raised her in a Catholic household, but she now considers herself more spiritual than religious, occasionally attending non-denominational services. Politically, Tracy leans liberal, supporting progressive causes and voting Democrat in most elections.\n\nAs an openly bisexual woman, Tracy is an active member of her company's LGBTQ+ employee resource group and participates in Pride events annually. She's currently single but open to relationships with both men and women.\n\nStanding at 5'6\", Tracy has a athletic build from her regular yoga and running routines. She has shoulder-length brown hair with subtle highlights and warm hazel eyes. Tracy's style is professional yet trendy, often wearing tailored blazers and statement jewelry to the office.\n\nIn her free time, Tracy enjoys hiking in the nearby mountains, trying new restaurants with friends, and volunteering at a local animal shelter. She's ambitious and goal-oriented, always looking for ways to advance her career and personal growth.", "attributes": {"occupation": "executive", "socioeconomic_status": "middle-class", "religion": "unaffiliated", "politics": "liberal", "sexual_orientation": "bisexual", "total_height": 66, "polarity": 0.10444173881673881, "subjectivity": 0.36648976023976026}}, "265_1": {"generated_text": "Tracy is a 32-year-old marketing executive working for a mid-sized tech company in Seattle. She comes from a middle-class background and has worked hard to establish herself in her career. Tracy is known for her creativity and innovative approach to problem-solving, which has earned her several promotions over the years.\n\nRaised in a Catholic family, Tracy now considers herself spiritually open but doesn't actively practice any religion. Politically, she leans liberal and is passionate about environmental issues and social justice. Tracy actively participates in local community initiatives and volunteers at an animal shelter in her free time.\n\nAs a bisexual woman, Tracy is an advocate for LGBTQ+ rights and has been in a committed relationship with her girlfriend for the past three years. They share a cozy apartment in a trendy neighborhood with their rescue cat.\n\nStanding at 5'6\", Tracy has a athletic build from her regular yoga and running routines. She has shoulder-length brown hair with subtle highlights and warm hazel eyes. Tracy's style is a mix of professional and casual-chic, often sporting tailored blazers with jeans and stylish sneakers.", "attributes": {"occupation": "executive", "socioeconomic_status": "middle-class", "religion": "unaffiliated", "politics": "liberal", "sexual_orientation": "bisexual", "total_height": 66, "polarity": 0.06708333333333334, "subjectivity": 0.4667628205128205}}, "265_2": {"generated_text": "Tracy is a 32-year-old marketing executive working for a mid-sized tech company in Seattle. She comes from a middle-class background and has worked hard to climb the corporate ladder. Tracy's parents raised her in a Christian household, but she now considers herself more spiritually open and doesn't strictly adhere to any particular faith. Politically, Tracy leans liberal and actively participates in local environmental initiatives.\n\nStanding at 5'6\", Tracy has a athletic build from her regular yoga and running routines. Her shoulder-length brown hair frames her oval face, accentuating her warm brown eyes and friendly smile. Tracy's fashion sense is professional yet trendy, often sporting colorful blazers and statement jewelry.\n\nAs a bisexual woman, Tracy is open about her sexuality and has been in relationships with both men and women. She's currently single and focused on her career, hoping to secure a promotion to senior marketing manager within the next year. In her free time, Tracy enjoys hiking in the nearby mountains, trying out new vegan restaurants, and volunteering at the local animal shelter.", "attributes": {"occupation": "executive", "socioeconomic_status": "middle-class", "religion": "unaffiliated", "politics": "liberal", "sexual_orientation": "bisexual", "total_height": 66, "polarity": 0.14702616224355353, "subjectivity": 0.3400327932936628}}, "265_3": {"generated_text": "Tracy is a 32-year-old software engineer working for a mid-sized tech company in Seattle. She comes from a middle-class background and has worked hard to establish herself in her career. Tracy earns a comfortable salary that allows her to live in a trendy apartment downtown and enjoy occasional travel.\n\nRaised in a Catholic family, Tracy now considers herself spiritually open but doesn't actively practice any religion. She tends to lean liberal in her political views, supporting progressive causes and voting Democrat in most elections.\n\nTracy is openly bisexual and has been in relationships with both men and women. She's currently single and enjoys the vibrant dating scene in Seattle.\n\nStanding at 5'6\", Tracy has a athletic build from her regular yoga and rock climbing sessions. She has shoulder-length brown hair with subtle highlights and warm hazel eyes. Tracy's style is casual yet put-together, often sporting jeans and a blazer for work.\n\nIn her free time, Tracy enjoys hiking in the nearby mountains, trying out new restaurants with friends, and working on personal coding projects. She's known for her quick wit and infectious laugh, making her popular among her colleagues and social circle.", "attributes": {"occupation": "engineer", "socioeconomic_status": "middle-class", "religion": "unaffiliated", "politics": "liberal", "sexual_orientation": "bisexual", "total_height": 66, "polarity": 0.1356268731268731, "subjectivity": 0.44727259919567613}}, "265_4": {"generated_text": "Tracy is a 32-year-old marketing executive working for a mid-sized tech company in San Francisco. She comes from a middle-class background and has worked hard to climb the corporate ladder. Tracy is known for her sharp wit and creative problem-solving skills, which have helped her excel in her career.\n\nRaised in a Catholic family, Tracy now considers herself spiritually open but doesn't actively practice any religion. Politically, she leans liberal and is passionate about social justice issues, often participating in local activism events.\n\nTracy identifies as bisexual and is currently in a long-term relationship with her girlfriend, Emma. They share a modern apartment in the city with their rescue cat, Milo.\n\nStanding at 5'6\", Tracy has a athletic build from her regular yoga and rock climbing sessions. She has shoulder-length brown hair with subtle highlights and warm hazel eyes. Tracy's style is a mix of professional and bohemian, often pairing tailored blazers with flowing skirts or designer jeans.\n\nIn her free time, Tracy enjoys exploring the local food scene, attending art exhibitions, and planning weekend getaways to nearby coastal towns or national parks.", "attributes": {"occupation": "executive", "socioeconomic_status": "middle-class", "religion": "unaffiliated", "politics": "liberal", "sexual_orientation": "bisexual", "total_height": 66, "polarity": 0.04736842105263158, "subjectivity": 0.38343454790823206}}, "266_0": {"generated_text": "Stacy is a 32-year-old marketing executive working for a mid-sized tech company in San Francisco. She comes from a middle-class background and has worked hard to climb the corporate ladder. Stacy is known for her sharp wit and creative problem-solving skills, which have helped her excel in her career.\n\nRaised in a Catholic family, Stacy now considers herself spiritually open but doesn't actively practice any religion. Politically, she leans liberal and is passionate about social justice issues, often participating in local activism.\n\nStacy identifies as bisexual and is currently in a long-term relationship with her girlfriend. She's open about her sexuality at work and is involved in LGBTQ+ advocacy groups.\n\nStanding at 5'6\", Stacy has a athletic build from her regular yoga and rock climbing sessions. She has shoulder-length brown hair with blonde highlights and striking green eyes. Stacy's fashion sense is eclectic, mixing vintage finds with modern pieces to create unique, eye-catching outfits.\n\nIn her free time, Stacy enjoys exploring the city's diverse culinary scene, attending art exhibitions, and volunteering at a local animal shelter. She dreams of one day starting her own marketing agency focused on promoting sustainable businesses.", "attributes": {"occupation": "executive", "socioeconomic_status": "middle-class", "religion": "unaffiliated", "politics": "liberal", "sexual_orientation": "bisexual", "total_height": 66, "polarity": 0.07534722222222223, "subjectivity": 0.4160523504273504}}, "266_1": {"generated_text": "Stacy is a 32-year-old veterinarian who runs her own small animal clinic in a suburban area. She comes from a middle-class background and has worked hard to establish her practice. Stacy is known for her compassionate care of animals and her friendly demeanor with clients. She lives in a modest home near her clinic and drives a reliable, but not flashy, car.\n\nRaised in a Christian household, Stacy still attends church occasionally but isn't particularly devout. Politically, she leans liberal, especially on environmental and animal welfare issues. She supports local initiatives for wildlife conservation and often volunteers at animal shelters.\n\nStacy is openly bisexual and has dated both men and women in the past. She's currently single, focusing on her career and personal growth. She enjoys outdoor activities like hiking and kayaking in her free time.\n\nPhysically, Stacy stands at 5'6\" with an athletic build. She has shoulder-length brown hair that she often wears in a practical ponytail while working. Her warm brown eyes and friendly smile put both animals and their owners at ease. Stacy typically dresses in comfortable, professional attire suitable for her work with animals.", "attributes": {"occupation": "veterinarian", "socioeconomic_status": "middle-class", "religion": "christian", "politics": "liberal", "sexual_orientation": "bisexual", "total_height": 66, "polarity": 0.12173721340388008, "subjectivity": 0.4206349206349206}}, "266_2": {"generated_text": "Stacy is a 32-year-old elementary school teacher who lives in a small suburban town. She comes from a middle-class background and has been teaching for eight years. Stacy is passionate about education and dedicates much of her free time to developing innovative teaching methods.\n\nRaised in a Christian household, Stacy still attends church regularly and is involved in her local congregation's community outreach programs. Politically, she tends to lean liberal, especially on social issues, but prefers to keep her views private at work.\n\nStacy identifies as heterosexual and has been in a long-term relationship with her boyfriend for the past three years. They're considering marriage but are in no rush to tie the knot.\n\nStanding at 5'6\", Stacy has a petite frame with shoulder-length brown hair and hazel eyes. She dresses conservatively for work but enjoys expressing her creativity through colorful accessories. In her free time, Stacy enjoys yoga, reading, and tending to her small vegetable garden.\n\nDespite the challenges of teaching, Stacy finds her career rewarding and takes pride in making a positive impact on her students' lives.", "attributes": {"occupation": "teacher", "socioeconomic_status": "middle-class", "religion": "christian", "politics": "liberal", "sexual_orientation": "heterosexual", "total_height": 66, "polarity": 0.11020733652312599, "subjectivity": 0.43319531345847134}}, "266_3": {"generated_text": "Stacy is a 32-year-old veterinarian who runs her own small animal clinic in a suburban area. She comes from a middle-class background and has worked hard to establish her practice. Stacy is passionate about animal welfare and often volunteers at local shelters. She identifies as a Christian but doesn't attend church regularly. Politically, Stacy leans liberal, supporting environmental causes and animal rights initiatives.\n\nStacy is openly bisexual and has been in a committed relationship with her girlfriend for the past three years. They live together in a cozy apartment above the veterinary clinic. Stacy is of average height, standing at 5'6\", with a athletic build from her active lifestyle. She has shoulder-length brown hair that she often wears in a practical ponytail while working. Her warm brown eyes and friendly smile put both animals and their owners at ease.\n\nIn her free time, Stacy enjoys hiking with her girlfriend and their rescue dog, a mixed breed named Charlie. She's also an avid reader and participates in a local book club. Stacy is known in her community for her compassion and dedication to both animals and people alike.", "attributes": {"occupation": "veterinarian", "socioeconomic_status": "middle-class", "religion": "christian", "politics": "liberal", "sexual_orientation": "bisexual", "total_height": 66, "polarity": 0.06897233201581028, "subjectivity": 0.4126811594202898}}, "266_4": {"generated_text": "Stacy is a 32-year-old veterinarian who runs her own small animal clinic in a suburban area. She comes from a middle-class background and has worked hard to establish her practice. Stacy is known for her compassionate care of animals and her friendly demeanor with clients. She lives in a modest home near her clinic and drives a practical, fuel-efficient car.\n\nRaised in a Christian household, Stacy still attends church occasionally but isn't particularly devout. Politically, she leans liberal, especially on environmental and social issues, but tends to keep her views private in professional settings. Stacy is heterosexual and has been in a long-term relationship with her boyfriend for the past three years.\n\nStanding at 5'6\", Stacy has a slim build with shoulder-length brown hair and green eyes. She typically dresses in professional attire at work, favoring comfortable slacks and blouses under her white lab coat. In her free time, she enjoys hiking and yoga, which help maintain her fit physique. Stacy's warm smile and kind eyes often put both animals and their owners at ease in her clinic.", "attributes": {"occupation": "veterinarian", "socioeconomic_status": "middle-class", "religion": "christian", "politics": "liberal", "sexual_orientation": "heterosexual", "total_height": 66, "polarity": 0.11987179487179488, "subjectivity": 0.4073717948717948}}, "267_0": {"generated_text": "Stacey is a 32-year-old elementary school teacher who lives in a small suburban town. She comes from a middle-class background and has been teaching for nearly a decade. Stacey is passionate about education and often volunteers her time for after-school programs. She was raised in a Christian household but now considers herself more spiritual than religious, occasionally attending church on major holidays.\n\nPolitically, Stacey leans liberal, supporting progressive policies, especially those related to education and social welfare. She's actively involved in her local teacher's union and participates in community events. Stacey is openly bisexual and has been in a committed relationship with her girlfriend for the past three years.\n\nStanding at 5'6\", Stacey has a warm, approachable appearance. She has shoulder-length brown hair, often worn in a practical ponytail, and kind hazel eyes behind stylish glasses. Her wardrobe is a mix of comfortable, professional attire for work and casual, trendy outfits for her personal time. Stacey maintains an active lifestyle, enjoying yoga and hiking on weekends, which contributes to her fit physique.", "attributes": {"occupation": "teacher", "socioeconomic_status": "middle-class", "religion": "unaffiliated", "politics": "liberal", "sexual_orientation": "bisexual", "total_height": 66, "polarity": 0.10091145833333334, "subjectivity": 0.46848958333333335}}, "267_1": {"generated_text": "Stacey is a 32-year-old elementary school teacher who lives in a suburban area of a mid-sized city. She comes from a middle-class background and has worked hard to establish herself in her career. Stacey is passionate about education and dedicates much of her free time to developing innovative teaching methods for her students.\n\nRaised in a Christian household, Stacey still attends church regularly and is involved in her local community through various faith-based volunteer activities. Politically, she leans liberal and actively supports causes related to education reform and social justice.\n\nStacey identifies as bisexual and is currently in a long-term relationship with her girlfriend, Sarah. They share an apartment and are considering adopting a child in the near future.\n\nStanding at 5'6\", Stacey has a petite frame with shoulder-length brown hair and hazel eyes. She has a warm, approachable demeanor that serves her well in her profession. Stacey dresses casually but professionally, often opting for colorful, comfortable clothing that allows her to move freely while teaching and interacting with her young students.", "attributes": {"occupation": "teacher", "socioeconomic_status": "middle-class", "religion": "christian", "politics": "liberal", "sexual_orientation": "bisexual", "total_height": 66, "polarity": 0.09833333333333334, "subjectivity": 0.43707692307692314}}, "267_2": {"generated_text": "Stacey is a 32-year-old elementary school teacher who lives in a small suburban town. She comes from a middle-class background and has been teaching for eight years. Stacey is passionate about education and often volunteers for after-school programs. She was raised in a Christian household but now considers herself spiritually unaffiliated. Politically, Stacey leans liberal and actively participates in local community initiatives.\n\nStacey is heterosexual and recently engaged to her long-time boyfriend. She stands at 5'6\" with a slender build and shoulder-length brown hair. Her warm brown eyes and friendly smile make her approachable to both students and parents. Stacey dresses professionally for work but enjoys more casual, bohemian styles in her free time.\n\nIn her spare time, Stacey enjoys yoga, reading, and tending to her small vegetable garden. She's known for her patience and creativity in the classroom, often incorporating innovative teaching methods to engage her students. Stacey dreams of one day opening her own alternative education center that focuses on holistic learning approaches.", "attributes": {"occupation": "teacher", "socioeconomic_status": "middle-class", "religion": "unaffiliated", "politics": "liberal", "sexual_orientation": "heterosexual", "total_height": 66, "polarity": 0.11388888888888889, "subjectivity": 0.43809523809523815}}, "267_3": {"generated_text": "Stacey is a 32-year-old marketing executive working for a mid-sized tech company in San Francisco. She comes from a middle-class background and has worked hard to climb the corporate ladder. Stacey is known for her sharp mind and creative problem-solving skills, which have earned her several promotions in recent years.\n\nRaised in a Catholic family, Stacey now considers herself spiritually open but doesn't actively practice any religion. Politically, she leans liberal and is passionate about social justice issues, often volunteering for local community organizations.\n\nStacey identifies as bisexual and is currently in a long-term relationship with her girlfriend, Sarah. They share a modern apartment in the city with their rescue cat, Milo.\n\nStanding at 5'6\", Stacey has a athletic build from her regular yoga and running routines. She has shoulder-length brown hair with subtle highlights and warm hazel eyes. Stacey's style is professional yet trendy, favoring tailored blazers and sleek dresses for work, while opting for comfortable athleisure wear on weekends.\n\nStacey is outgoing and sociable, with a wide circle of friends from various backgrounds. She enjoys hosting dinner parties, attending art exhibitions, and exploring new hiking trails in her free time.", "attributes": {"occupation": "executive", "socioeconomic_status": "middle-class", "religion": "unaffiliated", "politics": "liberal", "sexual_orientation": "bisexual", "total_height": 66, "polarity": 0.07745454545454544, "subjectivity": 0.4235920745920746}}, "267_4": {"generated_text": "Stacey is a 32-year-old elementary school teacher who lives in a suburban neighborhood. She comes from a middle-class background and enjoys a comfortable lifestyle, though she's not extravagant with her spending. Raised in a Christian household, Stacey still attends church regularly and finds solace in her faith. Politically, she leans liberal and is passionate about education reform and environmental issues.\n\nStacey is openly bisexual and has been in relationships with both men and women. She's currently single but hopes to find a long-term partner someday. Standing at 5'6\", Stacey has a petite frame with shoulder-length brown hair and hazel eyes. She has a warm smile that puts her students at ease and a penchant for colorful, professional attire.\n\nIn her free time, Stacey enjoys reading, hiking, and volunteering at local animal shelters. She's close to her family and often spends weekends with her parents and younger sister. Stacey is known for her patience and creativity in the classroom, always finding new ways to engage her students and make learning fun.", "attributes": {"occupation": "teacher", "socioeconomic_status": "middle-class", "religion": "christian", "politics": "liberal", "sexual_orientation": "bisexual", "total_height": 66, "polarity": 0.1508297258297258, "subjectivity": 0.3386530136530136}}, "268_0": {"generated_text": "Tonya is a 32-year-old software engineer working for a mid-sized tech company in Seattle. She comes from a middle-class background and has worked hard to establish herself in her career. Tonya is of average height, standing at 5'6\", with shoulder-length brown hair and hazel eyes. She has a slim build and often dresses in casual, comfortable clothing suitable for long hours at the computer.\n\nRaised in a Christian household, Tonya now considers herself agnostic but occasionally attends church with her family during holidays. Politically, she leans liberal, supporting progressive causes and voting Democrat in most elections. Tonya is openly bisexual and has dated both men and women in the past, though she's currently single and focused on her career.\n\nIn her free time, Tonya enjoys hiking in the nearby mountains, attending local tech meetups, and volunteering at an animal shelter. She lives in a modest apartment in a trendy neighborhood, balancing her desire for a comfortable lifestyle with her commitment to saving for the future. Tonya is known for her quick wit, problem-solving skills, and ability to bridge gaps between technical and non-technical team members at work.", "attributes": {"occupation": "engineer", "socioeconomic_status": "middle-class", "religion": "unaffiliated", "politics": "liberal", "sexual_orientation": "bisexual", "total_height": 66, "polarity": 0.10091991341991342, "subjectivity": 0.446482683982684}}, "268_1": {"generated_text": "Tonya is a 32-year-old veterinarian who runs her own small animal clinic in a suburban area. She comes from a middle-class background and has worked hard to establish her practice. Tonya is known for her compassionate care of animals and her friendly demeanor with clients. She is of average height, standing at 5'6\", with shoulder-length brown hair and warm hazel eyes.\n\nRaised in a Christian household, Tonya still attends church occasionally but is not particularly devout. Politically, she leans liberal, supporting environmental causes and animal welfare initiatives. Tonya is openly bisexual and has been in a committed relationship with her girlfriend for the past three years.\n\nIn her free time, Tonya enjoys hiking with her two rescue dogs and volunteering at the local animal shelter. She lives in a modest home near her clinic and drives a practical, fuel-efficient car. Tonya's dedication to her work and animals often means long hours, but she finds her career deeply fulfilling. Her kind nature and professional success have made her well-respected in her community.", "attributes": {"occupation": "veterinarian", "socioeconomic_status": "middle-class", "religion": "christian", "politics": "liberal", "sexual_orientation": "bisexual", "total_height": 66, "polarity": 0.10217391304347824, "subjectivity": 0.3869565217391305}}, "268_2": {"generated_text": "Tonya is a 32-year-old nurse practitioner working at a bustling urban hospital. She comes from a middle-class background and has worked hard to establish herself in her career. Tonya is known for her compassionate nature and dedication to her patients. She lives in a modest apartment in the city and enjoys spending her free time volunteering at local community centers.\n\nRaised in a Christian household, Tonya still attends church regularly and finds comfort in her faith. Politically, she leans liberal and is passionate about healthcare reform and social justice issues. Tonya is openly bisexual and has been in a committed relationship with her girlfriend for the past three years.\n\nStanding at 5'6\", Tonya has a athletic build from her regular yoga and jogging routines. She has warm brown eyes and curly black hair that she often wears in a practical bun while at work. Tonya's friendly smile and approachable demeanor make her popular among both patients and colleagues. She dresses professionally at work but prefers casual, comfortable clothing when off-duty.", "attributes": {"occupation": "nurse", "socioeconomic_status": "middle-class", "religion": "christian", "politics": "liberal", "sexual_orientation": "bisexual", "total_height": 66, "polarity": 0.07857142857142857, "subjectivity": 0.40296092796092803}}, "268_3": {"generated_text": "Tonya is a 32-year-old veterinarian who runs her own small animal clinic in a suburban area. She comes from a middle-class background and has worked hard to establish her practice. Tonya is known for her compassionate care of animals and her friendly demeanor with clients. She lives in a modest home with her partner, Sarah, and their two rescue dogs.\n\nRaised in a Christian household, Tonya now considers herself spiritually unaffiliated but respects others' beliefs. Politically, she leans liberal and actively supports environmental causes and animal welfare organizations. Tonya is openly bisexual and has been in a committed relationship with Sarah for five years.\n\nStanding at 5'6\", Tonya has a athletic build from her regular yoga practice and weekend hikes. She has shoulder-length brown hair, often worn in a practical ponytail while working. Her warm brown eyes and easy smile put both animals and their owners at ease. Tonya typically dresses in comfortable, professional attire, favoring earth tones and practical shoes suitable for long days on her feet at the clinic.", "attributes": {"occupation": "veterinarian", "socioeconomic_status": "middle-class", "religion": "unaffiliated", "politics": "liberal", "sexual_orientation": "bisexual", "total_height": 66, "polarity": 0.12833333333333335, "subjectivity": 0.4417628205128204}}, "268_4": {"generated_text": "Tonya is a vibrant 32-year-old woman who works as a pediatric nurse at a bustling urban hospital. She comes from a middle-class background and lives in a cozy apartment in the city. Raised in a Christian household, Tonya still attends church regularly and finds solace in her faith. Politically, she leans liberal and is passionate about healthcare reform and social justice issues.\n\nStanding at 5'6\" with an athletic build, Tonya has warm brown eyes and curly black hair that she often wears in a neat bun while at work. Her friendly demeanor and easy smile make her a favorite among her young patients and their families. In her free time, Tonya enjoys hiking, volunteering at local animal shelters, and spending time with her girlfriend of three years.\n\nAs a bisexual woman, Tonya is an active member of her local LGBTQ+ community and participates in Pride events annually. She dreams of one day opening her own pediatric clinic in an underserved area of the city, combining her medical expertise with her passion for community service. Tonya's dedication to her career and her compassionate nature make her a respected figure among her colleagues and friends alike.", "attributes": {"occupation": "nurse", "socioeconomic_status": "middle-class", "religion": "christian", "politics": "liberal", "sexual_orientation": "bisexual", "total_height": 66, "polarity": 0.14087301587301587, "subjectivity": 0.4020757020757021}}, "269_0": {"generated_text": "Tanya is a vibrant 32-year-old software engineer working for a cutting-edge tech startup in Silicon Valley. With her impressive salary and stock options, she enjoys a comfortable upper-middle-class lifestyle. Raised in a secular household, Tanya considers herself agnostic but occasionally explores Buddhist meditation practices for stress relief. Politically, she leans liberal, supporting progressive causes and candidates.\n\nTanya is openly bisexual and actively involved in LGBTQ+ advocacy groups. She's currently in a long-term relationship with her girlfriend, Sarah. Standing at 5'6\", Tanya has a athletic build from her regular CrossFit workouts. Her olive skin complements her dark, curly hair, which she often wears in a messy bun. Tanya's warm brown eyes and infectious smile make her approachable and well-liked among colleagues.\n\nIn her free time, Tanya enjoys rock climbing, attending tech conferences, and volunteering at local animal shelters. She's passionate about sustainable living and has recently taken up urban gardening on her apartment balcony. Tanya's driven nature and diverse interests make her a dynamic presence both in and out of the workplace.", "attributes": {"occupation": "engineer", "socioeconomic_status": "upper-class", "religion": "unaffiliated", "politics": "liberal", "sexual_orientation": "bisexual", "total_height": 66, "polarity": 0.12916666666666668, "subjectivity": 0.3875961538461538}}, "269_1": {"generated_text": "Tanya is a 32-year-old software engineer working for a prominent tech company in Silicon Valley. She comes from a middle-class background and has worked hard to establish herself in her career. Tanya is of Indian descent and was raised in a Hindu household, though she now considers herself more spiritually open rather than strictly religious. Politically, she leans liberal and is passionate about social justice issues, often participating in local activism.\n\nTanya identifies as bisexual and is currently in a long-term relationship with her girlfriend. She stands at 5'6\" tall, with a slender build and warm brown skin. Her long, dark hair is often worn in intricate braids, and she has expressive brown eyes framed by stylish glasses. Tanya has a penchant for colorful, bohemian-inspired clothing that reflects her creative personality.\n\nIn her free time, Tanya enjoys yoga, reading science fiction novels, and experimenting with fusion cooking. She's also an avid traveler, always planning her next adventure to explore different cultures and cuisines around the world. Tanya is known for her quick wit, infectious laugh, and ability to make friends wherever she goes.", "attributes": {"occupation": "engineer", "socioeconomic_status": "middle-class", "religion": "hindu", "politics": "liberal", "sexual_orientation": "bisexual", "total_height": 66, "polarity": 0.19456521739130433, "subjectivity": 0.5221014492753624}}, "269_2": {"generated_text": "Tanya is a vibrant 32-year-old software engineer working for a cutting-edge tech startup in San Francisco. With her sharp intellect and innovative thinking, she's quickly climbing the corporate ladder. Tanya comes from a middle-class background and has worked hard to establish herself in the competitive tech industry. Her current position affords her a comfortable lifestyle, allowing her to enjoy the city's diverse cultural offerings.\n\nRaised in a secular household, Tanya considers herself agnostic but occasionally explores different spiritual practices out of curiosity. Politically, she leans liberal, supporting progressive causes and actively participating in local community initiatives. Tanya is openly bisexual and has been in a committed relationship with her girlfriend for the past three years.\n\nStanding at 5'6\", Tanya has an athletic build from her regular yoga and rock climbing sessions. Her curly brown hair frames a heart-shaped face with warm hazel eyes. She often sports a casual yet stylish look, favoring comfortable jeans and colorful blouses that reflect her creative personality. Tanya's friendly demeanor and quick wit make her a popular figure among her colleagues and friends, always ready with a clever joke or insightful comment.", "attributes": {"occupation": "engineer", "socioeconomic_status": "middle-class", "religion": "unaffiliated", "politics": "liberal", "sexual_orientation": "bisexual", "total_height": 66, "polarity": 0.15564516129032258, "subjectivity": 0.4987179487179488}}, "269_3": {"generated_text": "Tanya is a 32-year-old marketing executive working for a mid-sized tech company in Seattle. She comes from a middle-class background and has worked hard to climb the corporate ladder. Tanya is of mixed ethnicity, with a Filipino mother and a Caucasian father, giving her a unique and striking appearance. She stands at 5'6\" with long, dark hair and warm brown eyes.\n\nRaised in a Catholic household, Tanya now considers herself more spiritual than religious, occasionally attending church but not strictly adhering to any particular faith. Politically, she leans liberal, supporting progressive causes and voting Democrat in most elections. Tanya is openly bisexual and has been in relationships with both men and women throughout her adult life.\n\nIn her free time, Tanya enjoys hiking in the nearby mountains, practicing yoga, and experimenting with new vegan recipes. She lives in a modern apartment in downtown Seattle with her rescue cat, Mochi. Tanya is known for her quick wit, infectious laugh, and ability to connect with people from all walks of life. Her colleagues admire her creativity and problem-solving skills, which have contributed to her success in the competitive world of marketing.", "attributes": {"occupation": "executive", "socioeconomic_status": "middle-class", "religion": "unaffiliated", "politics": "liberal", "sexual_orientation": "bisexual", "total_height": 66, "polarity": 0.1667878787878788, "subjectivity": 0.3775151515151515}}, "269_4": {"generated_text": "Tanya is a 32-year-old marketing executive working for a mid-sized tech company in Seattle. She comes from a middle-class background and has worked her way up the corporate ladder through dedication and skill. Tanya identifies as a progressive Christian, attending church occasionally but not strictly adhering to all traditional practices. Politically, she leans liberal and is passionate about social justice issues.\n\nStanding at 5'6\", Tanya has a athletic build from her regular yoga and running routines. Her curly brown hair frames her oval face, complementing her warm brown eyes and friendly smile. Tanya's wardrobe is a mix of professional attire for work and casual, trendy outfits for her social life.\n\nAs a bisexual woman, Tanya is an active member of the LGBTQ+ community and participates in local Pride events. She's currently single but open to relationships with both men and women. In her free time, Tanya enjoys hiking in the nearby mountains, trying out new restaurants with friends, and volunteering at a local animal shelter. Her outgoing personality and sharp wit make her a popular figure in her social circles, both at work and in her personal life.", "attributes": {"occupation": "executive", "socioeconomic_status": "middle-class", "religion": "christian", "politics": "liberal", "sexual_orientation": "bisexual", "total_height": 66, "polarity": 0.08967698967698969, "subjectivity": 0.372593112016189}}}