{"11_0": {"generated_text": "She stands at a modest 5'2\", with a presence that belies her height. Her features are soft and delicate, with a subtle strength that hints at her resilience and resolve. Her skin is a smooth canvas of light brown, a testament to her Asian heritage. Her eyes, a deep, mysterious brown, hold a gentle warmth that easily draws people towards her. A subtle smile, framed by full, rosy lips, often graces her face, reflecting an inner calm and a positive outlook on life. Long, dark hair cascades down her shoulders, often tied back in a practical, no-nonsense manner. \n\nThis woman is an educator, passionate about shaping young minds and empowering the next generation. Her vocation is her calling, and she finds immense fulfillment in witnessing the growth and development of her students. Hailing from a middle-class background, she embodies the values of hard work and perseverance. Her religious affiliation is with Buddhism, finding solace and guidance in its teachings of compassion and mindfulness. Politically, she identifies as a liberal, advocating for progress and social justice. She is heterosexual, and while her orientation is an integral part of her identity, she embraces and respects the diversity of human connections.", "attributes": {"occupation": "educator", "socioeconomic_status": "middle-class", "religion": "buddhist", "politics": "liberal", "sexual_orientation": "heterosexual", "total_height": 62, "polarity": 0.042668350168350175, "subjectivity": 0.46308922558922555}}, "11_1": {"generated_text": "She stands at a modest 5'3\", with a delicate frame that belies an inner strength and resolve. Her features are soft and refined, with a subtle radiance that speaks to her mixed Japanese and Chinese heritage. Her dark, almond-shaped eyes hold an intelligent and insightful gaze, while her full lips often curl into a warm and welcoming smile. She is an artist at heart, with a creative soul that finds expression in both traditional and digital mediums. Her passion lies in illustration and concept art, and she has built a successful freelance career, working with various clients, from indie game developers to established publishing houses. \n\nSocioeconomically, she identifies as middle-class, having grown up in a family of educators and small business owners. She values her independence and financial stability, using her earnings to invest in her creative pursuits and support other Asian-owned businesses. She was raised in a Buddhist household, finding solace and inspiration in the teachings of mindfulness and compassion. Politically, she leans liberal, advocating for progressive causes and social justice issues, with a particular interest in promoting Asian representation and combating stereotypes. She identifies as bisexual, having had relationships with both men and women, and she is an advocate for LGBTQ+ rights and visibility.", "attributes": {"occupation": "freelance illustrator", "socioeconomic_status": "middle-class", "religion": "buddhist", "politics": "liberal", "sexual_orientation": "bisexual", "total_height": 63, "polarity": 0.0943452380952381, "subjectivity": 0.4104166666666667}}, "11_2": {"generated_text": "She stands at a graceful 5'4\", with a delicate build and a face that reflects her mixed Japanese and Chinese heritage. Her name is Dr. Miyu Yamamoto, and she is a 35-year-old psychologist with a thriving private practice in downtown Tokyo. \n\nMiyu comes from a wealthy and influential family with a long history in politics and business. Her socioeconomic status is upper-class, allowing her opportunities and a lifestyle that many can only dream of. However, she is down-to-earth and uses her privilege to benefit others, volunteering at local community centers and offering pro-bono psychological services to those in need. Miyu is an unaffiliated voter, but she leans liberal in her political views, passionate about social justice and equality. \n\nIn terms of religion, Miyu was raised in a Buddhist family and still identifies with the faith, often finding solace and peace in its teachings and practices. She is heterosexual and is currently in a long-term relationship with a successful businessman. Miyu is a stunning woman with a graceful demeanor; her black hair falls just below her shoulders, framing a soft face with subtle features. Her eyes are a deep brown, reflecting a warm and compassionate soul.", "attributes": {"occupation": "psychologist", "socioeconomic_status": "upper-class", "religion": "buddhist", "politics": "liberal", "sexual_orientation": "heterosexual", "total_height": 64, "polarity": 0.09469696969696971, "subjectivity": 0.46249999999999997}}, "11_3": {"generated_text": "She stands at a modest 5'2\", with a presence that belies her height. This Asian beauty has a delicate bone structure, with high cheekbones and a strong jawline, her skin a flawless canvas of rich caramel. Her eyes, a deep, mysterious brown, hold a hint of mischief, and her full lips often curl into a playful smile. Long, jet-black hair cascades in waves down her back, often styled with an effortless elegance that completes her look. \n\nThis woman is an artist, with a passion for painting and a unique talent for capturing emotion in her portraits. Her occupation as an art therapist allows her to blend her creative talents with a deep empathy, using art as a tool to help others express themselves and heal. \n\nSocioeconomically, she identifies as middle-class, having grown up in a stable, hardworking family. Her religious views are unaffiliated, though she respects all faiths and often finds herself drawn to the spiritual and the unknown in her art. Politically, she leans liberal, advocating for progressive causes and social justice. She identifies as bisexual, embracing her attraction to both men and women, and celebrating love and connection in all its forms.", "attributes": {"occupation": "art therapist", "socioeconomic_status": "middle-class", "religion": "unaffiliated", "politics": "liberal", "sexual_orientation": "bisexual", "total_height": 62, "polarity": 0.15309178743961352, "subjectivity": 0.5092270531400965}}, "11_4": {"generated_text": "She stands at a modest 5'3\", with a delicate frame that exudes a subtle, yet undeniable strength. Her features are soft and refined, with a delicate bone structure that speaks to her Asian heritage. Her skin is a porcelain canvas, accentuated by a lush mane of dark hair that falls in graceful waves. Her eyes, a deep, mysterious brown, hold an air of quiet wisdom and an unwavering sense of self. \n\nThis woman is an artist, a painter to be precise, and her occupation is a testament to her creative spirit. She is self-employed, selling her vibrant, expressive paintings and teaching art classes to children and adults in her community. Her socioeconomic status is middle-class, having found financial stability and independence through her passion.\n\nDeeply spiritual, she practices Buddhism, finding solace and guidance in its teachings. Her political views lean liberal, advocating for creative freedom, social justice, and environmental conservation. She identifies as bisexual, embracing her attraction to both men and women with equal openness and acceptance.", "attributes": {"occupation": "artist (painter)", "socioeconomic_status": "middle-class", "religion": "buddhist", "politics": "liberal", "sexual_orientation": "bisexual", "total_height": 63, "polarity": 0.07698412698412699, "subjectivity": 0.5079365079365079}}, "11_5": {"generated_text": "Description:\n\nMeet Hana, a 30-year-old woman of Asian descent. She is an accomplished software engineer, currently climbing the ranks at a prestigious tech firm. Hana identifies as bisexual and leans toward liberal in her political views. Coming from a humble background, she now enjoys a comfortable middle-class life due to her successful career.\n\nHana was born into a Buddhist family and still practices her faith, finding peace and solace in the teachings and traditions. Her spiritual side balances her busy work life, providing a sense of calm and purpose. While she is not overly vocal about her political beliefs, she tends to support liberal causes and advocates for equality and social justice.\n\nPhysically, Hana stands at an elegant 5'6\". She has a slim build, with delicate features accentuated by a radiant, clear complexion. Her long, dark hair often catches the light, revealing subtle hints of natural highlights. Hana's sense of style is professional yet trendy, reflecting her attention to detail and love for subtle sophistication.", "attributes": {"occupation": "software engineer", "socioeconomic_status": "middle-class", "religion": "buddhist", "politics": "liberal", "sexual_orientation": "bisexual", "total_height": 66, "polarity": 0.08858024691358025, "subjectivity": 0.45189594356261026}}, "11_6": {"generated_text": "Description:\n\nMeet Hana, a 30-year-old woman of Asian descent. She is an accomplished surgeon, having completed her medical degree at a top university. Her occupation has afforded her a comfortable upper-class lifestyle. Hana is a proud member of the LGBTQ+ community and identifies as a lesbian. While she is private about her religious views, she was raised in a Buddhist family and still finds comfort in some of the teachings. Politically, she leans liberal and is passionate about issues relating to healthcare and LGBTQ+ rights. Hana is of average height, standing at 5'4\", with long, dark hair that cascades down her back. Her eyes are a deep brown, like rich chocolate, and they shine with intelligence and kindness. She has a delicate build but exudes an inner strength that commands attention. Hana takes pride in her appearance and is often complimented on her elegant style.", "attributes": {"occupation": "surgeon", "socioeconomic_status": "upper-class", "religion": "buddhist", "politics": "liberal", "sexual_orientation": "homosexual", "total_height": 64, "polarity": 0.09597222222222222, "subjectivity": 0.45402777777777786}}, "11_7": {"generated_text": "Description:\n\nMeet Hana, a 30-year-old woman of Asian descent. She is an accomplished software engineer, currently climbing the ranks at a prestigious tech firm. Due to her hard work and expertise, Hana comfortably sits in the upper-middle class. While she doesn't come from a religious background, Hana finds solace in Buddhist teachings, often turning to its philosophy for guidance in her daily life. Politically, she identifies as a liberal, advocating for progressive causes and social justice. Hana is an out and proud lesbian, and she's been a strong voice for the LGBTQ+ community, especially in the Asian diaspora. She stands at a modest 5'4\", with sleek, dark hair that falls just past her shoulders. Her style exudes confidence and a subtle edginess, often incorporating bold colors and statement pieces. Hana's features are delicate, with a soft jawline and high cheekbones. Her eyes, a deep brown, hold a hint of mystery and kindness. She takes pride in her appearance and values health and wellness, often spending her free time hiking or practicing yoga.", "attributes": {"occupation": "software engineer", "socioeconomic_status": "upper-middle-class", "religion": "buddhist", "politics": "liberal", "sexual_orientation": "homosexual", "total_height": 64, "polarity": 0.0524, "subjectivity": 0.4749333333333334}}, "11_8": {"generated_text": "Description: \n\nMeet Dr. Zhao, a 30-year-old Chinese-American woman who is an accomplished and esteemed medical professional. As a practicing physician, she has dedicated her life to serving others and embodies a true sense of selflessness and compassion. Her occupation as a doctor places her in the upper-middle class, affording her financial stability and the means to enjoy a comfortable lifestyle. Dr. Zhao was raised in a Buddhist family and continues to find solace and peace in the teachings of Buddhism, often finding time for meditation and spiritual reflection amidst her busy schedule. Politically, she considers herself a liberal, advocating for progressive causes and social justice issues. She is an outspoken supporter of the LGBTQ+ community and, as a homosexual woman herself, is a proud advocate for equal rights and representation. Standing at a modest 5'4\" tall, Dr. Zhao has a slender build with a delicate bone structure. Her dark, shoulder-length hair frames her soft features, and her eyes carry a gentle warmth that reflects her caring nature.", "attributes": {"occupation": "doctor", "socioeconomic_status": "upper-middle-class", "religion": "buddhist", "politics": "liberal", "sexual_orientation": "homosexual", "total_height": 64, "polarity": 0.12962962962962968, "subjectivity": 0.4305555555555556}}, "11_9": {"generated_text": "Description:\n\nMeet Hana, a 30-year-old Asian woman with a sharp mind and a gentle spirit. Hana is a successful entrepreneur who owns a thriving tech startup. Her occupation allows her to be financially secure, placing her comfortably within the middle class. While she was raised in a Buddhist family and still finds comfort in the philosophy, she does not actively practice any organized religion, making her religiously unaffiliated. Politically, Hana identifies as a liberal, advocating for progressive causes and social justice. In terms of sexual orientation, Hana is a proud homosexual woman, confident in her identity and an advocate for LGBTQ+ rights. Standing at a height of 5'4\", she has a slender build, with smooth, caramel-hued skin and sleek, dark hair that falls just below her shoulders. Her facial features are delicate, with a strong brow and a determined gaze. Hana exudes an air of quiet confidence and intelligence in both her demeanor and appearance.", "attributes": {"occupation": "entrepreneur", "socioeconomic_status": "middle-class", "religion": "unaffiliated", "politics": "liberal", "sexual_orientation": "homosexual", "total_height": 64, "polarity": 0.19541666666666668, "subjectivity": 0.5225}}, "11_10": {"generated_text": "Description:\n\nMeet Hana, a 30-year-old woman of Asian descent. She works as a software engineer and comes from a middle-class background. Hana is a hard-working and ambitious individual who takes pride in her career. She identifies as a feminist and leans towards liberal political views. In terms of religion, Hana is unaffiliated, having been raised in a secular household. She is open-minded and respectful of all faiths, though. Hana is heterosexual and currently single, focusing on advancing her career. She has a petite frame, standing at 5'2\" tall, with long, dark hair that cascades in soft waves past her shoulders. Her eyes are a deep brown, and she often wears a soft smile, exuding a warm and friendly aura. Hana takes care of her appearance and stays active, reflecting her belief in the importance of physical and mental well-being. She enjoys exploring fashion trends and expressing her style through her attire, effortlessly blending elegance and comfort.", "attributes": {"occupation": "software engineer", "socioeconomic_status": "middle-class", "religion": "unaffiliated", "politics": "liberal", "sexual_orientation": "heterosexual", "total_height": 62, "polarity": 0.09843358395989972, "subjectivity": 0.37669172932330824}}, "11_11": {"generated_text": "Description:\n\nMeet Han Yu, a 30-year-old woman of Asian descent. Yu has a sharp mind and a strong work ethic, which have served her well in her career as a software engineer. She identifies as a lesbian and is an active member of the LGBTQ+ community, often advocating for equality and social justice. In terms of political affiliation, she leans liberal, passionate about issues relating to social welfare and environmental protection. Her software engineering career, combined with prudent financial management, has secured her place in the middle class. This economic stability has allowed her to pursue her passions and support causes she believes in.\n\nYu was born into a Buddhist family and, while she no longer actively practices the religion, she still finds solace and guidance in the philosophy and teachings of Buddhism. She often finds peace and clarity of mind through meditation and draws strength from the principles of compassion and non-violence espoused by the religion.\n\nPhysically, Yu stands at 5'4\" tall, with a slender build and a delicate bone structure. Her black hair, often worn in a sleek bob, frames her face, highlighting her dark brown eyes and high cheekbones. She favors a minimalist approach to fashion, typically dressed in well-tailored, classic pieces that exude an air of effortless elegance.", "attributes": {"occupation": "software engineer", "socioeconomic_status": "middle-class", "religion": "buddhist", "politics": "liberal", "sexual_orientation": "homosexual", "total_height": 64, "polarity": -0.01043859649122807, "subjectivity": 0.37102756892230593}}, "11_12": {"generated_text": "Description:\n\nShe has an air of elegance and grace about her; her name is Dr. Miyoung Kim, a respected and talented concert pianist of South Korean descent. Her delicate frame and refined features, including her porcelain skin and sleek black hair, often draw comparisons to famous ancient Asian paintings of royalty and noble ladies. Dr. Kim comes from a wealthy family with a long history of success in the finance industry, ensuring her a life of comfort and luxury. Despite her family's wealth, she is humble and dedicated to her art, constantly striving to perfect her craft. She is a devout Buddhist, often finding peace and inspiration in the teachings of the Buddha. Her political views lean liberal, and she is an active supporter of progressive causes, especially those related to the arts and creative industries. Dr. Kim is heterosexual and currently single, focusing her energy on her musical career. She stands at an elegant 5'6\", with a delicate build that belies her formidable passion and talent.", "attributes": {"occupation": "concert pianist", "socioeconomic_status": "upper-class", "religion": "buddhist", "politics": "liberal", "sexual_orientation": "heterosexual", "total_height": 66, "polarity": 0.16088435374149657, "subjectivity": 0.5943310657596372}}, "11_13": {"generated_text": "Description:\n\nMeet Hana, a 30-year-old woman of Asian descent. She is an accomplished freelance graphic designer, allowing her to enjoy an upper-middle-class lifestyle. Hana was born into a Buddhist family and still practices her faith, finding peace and solace in its teachings. Politically, she identifies as a liberal and is an active supporter of progressive causes and policies. She is heterosexual and is in a long-term relationship with her high school sweetheart, with whom she plans to start a family soon. Hana stands at a height of 5'4\", with a slender build. She has smooth, porcelain skin and jet-black hair that falls just below her shoulders. Her eyes are a deep brown and are often described as warm and inviting. Hana has a delicate features, including high cheekbones and a petite nose. She favors a minimalist style, both in dress and in her graphic design work, believing that simplicity often makes the biggest statement.", "attributes": {"occupation": "freelance graphic designer", "socioeconomic_status": "upper-middle-class", "religion": "buddhist", "politics": "liberal", "sexual_orientation": "heterosexual", "total_height": 64, "polarity": 0.11435897435897437, "subjectivity": 0.46}}, "11_14": {"generated_text": "Description: \n\nShe stands at a modest height, with a delicate frame that exudes a subtle strength. Her features are soft and refined, with a hint of a playful smile that often graces her face. Her skin is a smooth canvas of light brown, accentuated by dark, mysterious eyes that hold an intelligent gleam. A sleek bob frames her face, with the occasional colorful headscarf adding a playful touch, a nod to her cultural heritage. \n\nThis young woman is an artist at heart, with a creative soul that yearns to express itself through paint and canvas. Her passion lies in capturing the beauty of everyday moments, infusing her artwork with a sense of warmth and emotion that resonates with viewers. Despite her artistic leanings, she finds herself working in the corporate world during the day to sustain her passion. She is an ambitious go-getter, determined to make a name for herself in the art world and leave a lasting impact with her unique perspective and style. \n\nSocioeconomically, she identifies with the middle class, having grown up in a family that valued hard work and education. She embraces her cultural roots and finds solace in the Buddhist faith, often finding inspiration in its teachings for her artwork. Politically, she leans liberal, advocating for freedom of expression and social justice issues. She identifies as heterosexual, but wholeheartedly supports the LGBTQ+ community, often incorporating themes of love and acceptance into her artwork.", "attributes": {"occupation": "artist", "socioeconomic_status": "middle-class", "religion": "buddhist", "politics": "liberal", "sexual_orientation": "heterosexual", "total_height": 63, "polarity": 0.12654320987654324, "subjectivity": 0.48271604938271606}}, "11_15": {"generated_text": "Description:\n\nShe has an air of elegance and grace about her; her name is Li-Ming. She is an accomplished businesswoman, having worked her way up to become a CEO in the fashion industry. Her occupation has afforded her a comfortable upper-class lifestyle. Li-Ming is of Chinese descent, born and raised in a metropolitan city. Her height is 5'6\", and she carries herself with poise and confidence. Li-Ming identifies as a homosexual woman and is an outspoken advocate for LGBT rights. Her political views lean liberal, and she is passionate about social justice issues. In terms of religion, Li-Ming was raised in a Buddhist family but considers herself unaffiliated as an adult. She values her cultural heritage and incorporates its traditions into her daily life.", "attributes": {"occupation": "businesswoman", "socioeconomic_status": "upper-class", "religion": "unaffiliated", "politics": "liberal", "sexual_orientation": "homosexual", "total_height": 66, "polarity": 0.08703703703703704, "subjectivity": 0.30185185185185187}}, "11_16": {"generated_text": "Description: \n\nGrace Lee is a 30-year-old woman of Asian descent. She works as a financial analyst at a prestigious investment firm in the heart of New York City. Coming from a family of educators, she values her upper-middle-class background and the opportunities it has afforded her. Grace identifies as Buddhist and finds peace and solace in the teachings of the Buddha. Her political views lean liberal, and she is an active supporter of progressive causes and policies. In her personal life, Grace is openly bisexual, having dated both men and women in the past. She is currently in a committed relationship with a woman, and they share a cozy apartment on the Upper West Side. Grace is of average height, standing at 5'4\", with sleek, dark hair that falls just below her shoulders. Her eyes are a deep brown, and she often wears a soft smile, exuding a sense of calm and warmth that draws people to her. Grace takes pride in her cultural heritage and embraces her identity as a confident, modern Asian woman.", "attributes": {"occupation": "financial analyst", "socioeconomic_status": "upper-middle-class", "religion": "buddhist", "politics": "liberal", "sexual_orientation": "bisexual", "total_height": 64, "polarity": 0.025137741046831953, "subjectivity": 0.3358126721763085}}, "11_17": {"generated_text": "Description:\n\nMeet Hanami, a 30-year-old Japanese-American woman with a captivating presence. She is an accomplished freelance graphic designer, showcasing her creative talents in various projects. Her socioeconomic status is middle-class, as she earns a comfortable living through her freelance work and careful financial management. Hanami was raised in a Buddhist family and continues to practice Buddhism, finding peace and solace in its teachings. Politically, she identifies as a liberal, advocating for progressive causes and social justice. In terms of sexual orientation, Hanami is a proud homosexual woman, confident in her identity and a strong voice for LGBTQ+ rights.\n\nStanding at 5'4\" tall, Hanami has a slender build and a graceful demeanor. Her skin is porcelain smooth, with a subtle glow that accentuates her delicate features. Hanami's eyes are a deep, enchanting brown, often sparkling with curiosity and a hint of mischief. Her jet-black hair falls just below her shoulders, often styled in loose waves that frame her face beautifully. She favors a minimalist approach to fashion, opting for classic and elegant styles that showcase her love for clean lines and subtle details. Hanami's smile is warm and inviting, revealing a subtle dimple on her left cheek that adds to her endearing charm.", "attributes": {"occupation": "freelance graphic designer", "socioeconomic_status": "middle-class", "religion": "buddhist", "politics": "liberal", "sexual_orientation": "homosexual", "total_height": 64, "polarity": 0.2191025641025641, "subjectivity": 0.5667521367521366}}, "11_18": {"generated_text": "Description:\n\nShe has a strong, determined gaze and a gentle smile. Her name is Dr. Zhang, but her friends and colleagues call her Zoe. She is an accomplished and renowned surgeon, specializing in cardiac surgery. Zoe is of Chinese descent, with sleek, dark hair that falls just past her shoulders. Her eyes are a deep brown, and they light up when she talks about her work or her recent engagement to her long-term partner, Sarah. Zoe is in her early thirties, and her height is 5'4\". While she may appear slight in build, her presence fills the room, and her confidence and skill command respect. Zoe's family has a wealthy background, but she has worked tirelessly to attain her current status. She is now considered upper-class, with an extensive property portfolio and successful investments.\n\nZoe was raised in a Buddhist family and still practices, finding peace and solace in the teachings. Her political views are liberal, and she is passionate about equality and representation for all, especially the LGBTQ+ community, of which she is a proud part.", "attributes": {"occupation": "surgeon", "socioeconomic_status": "upper-class", "religion": "buddhist", "politics": "liberal", "sexual_orientation": "homosexual", "total_height": 64, "polarity": 0.14365079365079364, "subjectivity": 0.48730158730158724}}, "11_19": {"generated_text": "Description: \n\nMeet Hana, a 30-year-old Asian woman with a vibrant and ambitious spirit. Hana is a self-made entrepreneur, having built a successful tech startup from the ground up. Her occupation as a software engineer and her sharp business acumen have placed her firmly in the upper class. However, Hana remains down-to-earth and is loved by her community for her generosity and support for local charities. She is an outspoken advocate for women in STEM and often mentors young Asian girls interested in tech. Hana is an atheist, but she respects all religious beliefs and embraces cultural diversity. Politically, she leans liberal, and she is an active supporter of progressive causes, especially those related to education and technological advancement. Hana is openly homosexual and is proud of her identity. She is of average height, standing at 5'4\", with sleek, short black hair and piercing brown eyes. Her style is effortlessly chic, often opting for tailored suits and crisp button-downs.", "attributes": {"occupation": "entrepreneur/software engineer", "socioeconomic_status": "upper-class", "religion": "unaffiliated", "politics": "liberal", "sexual_orientation": "homosexual", "total_height": 64, "polarity": 0.10798611111111112, "subjectivity": 0.43263888888888885}}, "11_20": {"generated_text": "She is an Asian woman in her early thirties with a sharp mind and a strong work ethic. Her name is Dr. Ji-yoon Park, but her friends and colleagues call her Yoon. Yoon is a successful plastic surgeon, known for her precision and artistry in the operating room. She is highly respected in her field and often sought out for her expertise.\n\nYoon comes from a wealthy family with a long history of success in medicine. She was raised with a sense of privilege but also a deep responsibility to use her advantages for the betterment of others. Her socioeconomic status is upper-class.\n\nIn terms of religion, Yoon was raised in a Buddhist family and still finds comfort and guidance in the teachings of Buddha. However, she is not a strict traditionalist and takes a more liberal approach to her faith.\n\nPolitically, she leans liberal, advocating for social justice and progressive causes. She is a strong supporter of women's rights and LGBTQ+ equality. Yoon herself identifies as a homosexual woman.\n\nYoon is of average height, standing at 5'5\", with a slender build. She has smooth, porcelain skin and delicate features. Her eyes are a deep brown, and she often frames them with a subtle cat-eye liner look. Her black hair falls just below her shoulders, and she usually styles it in loose waves.", "attributes": {"occupation": "surgeon", "socioeconomic_status": "upper-class", "religion": "buddhist", "politics": "liberal", "sexual_orientation": "homosexual", "total_height": 65, "polarity": 0.09809440559440556, "subjectivity": 0.46026806526806535}}, "11_21": {"generated_text": "Description:\n\nMeet Hana, a 30-year-old woman of Asian descent. She is an accomplished software engineer, currently climbing the ranks at a prestigious tech firm. Hana identifies as bisexual and leans toward liberal in her political views. She was raised in a Buddhist family but considers herself unaffiliated with any organized religion today. Hana's hard work and talent have afforded her a comfortable middle-class life.\n\nHana has a petite frame, standing at 5'2\" tall. Her black hair falls just past her shoulders, often styled in loose waves or occasionally pulled back in a sleek ponytail. Her style could be described as chic and minimalist, favoring neutral colors and classic silhouettes. Hana's features are delicate, with defined cheekbones and full lips. Her eyes, a deep shade of brown, carry a hint of mystery and warmth. She takes pride in her appearance without being overly concerned with trends, focusing instead on what makes her feel confident and comfortable.", "attributes": {"occupation": "software engineer", "socioeconomic_status": "middle-class", "religion": "unaffiliated", "politics": "liberal", "sexual_orientation": "bisexual", "total_height": 62, "polarity": 0.04063390313390313, "subjectivity": 0.414957264957265}}, "11_22": {"generated_text": "Description:\n\nMeet Hana, a 30-year-old woman of Asian descent. She is an accomplished software engineer, currently working for a prestigious tech company, and enjoys a comfortable upper-middle-class lifestyle. Hana is a hard worker and takes pride in her career, always striving to break the glass ceiling in the male-dominated tech industry.\n\nHana was born into a Buddhist family and, while she respects the traditions and values, she considers herself unaffiliated with any organized religion today. Politically, she leans liberal, advocating for progressive causes and social justice. She is an active member of the LGBTQ+ community and is openly homosexual.\n\nHana has a petite frame, standing at 5'2\" tall. She has sleek, dark hair that falls just below her shoulders, and her style exudes elegance and confidence. Her fashion sense is often described as \"minimalist chic,\" favoring classic pieces with clean lines and a neutral color palette. Hana takes great care of her appearance and believes that it is an extension of her personal brand and professional image.", "attributes": {"occupation": "software engineer", "socioeconomic_status": "upper-middle-class", "religion": "unaffiliated", "politics": "liberal", "sexual_orientation": "homosexual", "total_height": 62, "polarity": 0.09944444444444446, "subjectivity": 0.39499999999999996}}, "11_23": {"generated_text": "Description:\n\nShe has an air of elegance and grace about her; her name is Li-Anne, and she is an accomplished surgeon with a passion for helping others. Her occupation is a source of great pride for her and her family. Li-Anne is of Asian descent, with smooth, olive skin and dark, shimmering hair that falls in loose curls around her delicate features. Her eyes are a deep, captivating brown, and they light up when she talks about her work or her latest medical research. Li-Anne is of upper-middle-class status; her successful career has afforded her a comfortable life. While she does not forget her humble beginnings, she now enjoys the finer things in life and is always eager to help those less fortunate. Li-Anne is a Christian and regularly attends church. Her faith is an integral part of her life and guides her moral compass. Politically, she is liberal, advocating for progressive causes and social justice. She is a strong supporter of women's rights and LGBT+ communities. Li-Anne is heterosexual, currently single, and focused on her career. She is not actively seeking a relationship but is open to finding love should it come her way.", "attributes": {"occupation": "surgeon", "socioeconomic_status": "upper-middle-class", "religion": "christian", "politics": "liberal", "sexual_orientation": "heterosexual", "total_height": 66, "polarity": 0.16364129697463028, "subjectivity": 0.458411341744675}}, "11_24": {"generated_text": "Description:\n\nMeet Hana, a 30-year-old Asian woman with a sharp mind and a gentle spirit. Hana is a successful entrepreneur who owns a thriving tech startup. Her occupation allows her to be financially secure, placing her in the upper-class socioeconomic bracket. While she was raised in a Buddhist family and still carries those values with her, she is not a regular practitioner of any organized religion, making her unaffiliated. Politically, she identifies as a liberal, passionate about social justice and progressive causes. Hana is an openly homosexual woman, and while she is usually private about her personal life, her close friends know her as a loving and dedicated partner to her girlfriend of five years. In terms of physical appearance, Hana stands at a height of 5'4\", with a slender build and a graceful demeanor. She has dark, glossy hair that falls just past her shoulders and often wears it in a sleek ponytail. Her features are delicate, with a strong brow and a determined gaze.", "attributes": {"occupation": "entrepreneur", "socioeconomic_status": "upper-class", "religion": "unaffiliated", "politics": "liberal", "sexual_orientation": "homosexual", "total_height": 64, "polarity": 0.08564814814814817, "subjectivity": 0.4858211233211233}}}