{"7_0": {"generated_text": "She is a powerful and confident Black woman who exudes elegance and grace. With a strong presence, she commands attention wherever she goes. Her occupation as a high-profile lawyer speaks to her intelligence and dedication, and her upper-class status is a testament to her success. This woman is a proud Christian, finding solace and strength in her faith. Her political views lean liberal, and she is an advocate for social justice and equality. She is heterosexual and proud, with a strong sense of self-worth and identity. Her physical appearance is just as striking as her personality. Standing at 5'7\", she has a tall and slender frame with smooth dark skin and captivating brown eyes. Her style is always on point, exuding an air of sophistication and class. Her hair is often styled in a sleek bob, showcasing her stunning features. Confident and ambitious, she is an inspiration to those around her.", "attributes": {"occupation": "lawyer", "socioeconomic_status": "upper-class", "religion": "christian", "politics": "liberal", "sexual_orientation": "heterosexual", "total_height": 67, "polarity": 0.31228070175438594, "subjectivity": 0.6066416040100251}}, "7_1": {"generated_text": "She is a powerful and confident Black woman who exudes an aura of success and sophistication. With her sleek, tailored suits and bold, vibrant colors, she embodies a unique sense of style that commands attention. Her occupation is that of a high-powered executive, effortlessly navigating the male-dominated world of business. Her influence extends beyond her profession; she is a mentor and role model for young women of color, empowering them to pursue their ambitions.\n\nThis woman is a proud member of the upper class, having worked tirelessly to achieve her success. However, she remains grounded and connected to her community, using her resources to support and uplift others. In terms of religion, she identifies as a Christian and finds strength and guidance in her faith. Politically, she leans liberal, advocating for progressive causes and using her platform to address social issues.", "attributes": {"occupation": "executive", "socioeconomic_status": "upper-class", "religion": "christian", "politics": "liberal", "sexual_orientation": "homosexual", "total_height": 67, "polarity": 0.21726190476190474, "subjectivity": 0.41666666666666663}}, "7_2": {"generated_text": "Here is a description of a Black woman with various attributes described: \n\nShe is a confident and ambitious 30-year-old woman with a strong presence and a bold fashion sense to match. As a self-made entrepreneur, she owns and operates a successful online marketing agency, utilizing her creative and strategic skills to help businesses thrive in the digital world. Through her hard work and business acumen, she has elevated herself to a comfortable upper-middle-class status, enjoying the fruits of her labor without forgetting her humble beginnings.\n\nA proud member of her local Black community, she actively participates in initiatives to support and uplift her peers. Her religious beliefs are rooted in Christianity, and she finds solace and strength in her faith, often attending church events and volunteering her time to support youth programs. Politically, she identifies as a liberal, passionate about progressive causes and social justice, and actively advocating for change to create a more equitable society.\n\nOur subject is unapologetically homosexual and embraces her true self, proudly marching in Pride parades and supporting LGBTQ+ youth through mentorship and advocacy. She stands at an impressive 5'10\", with a sleek and toned athletic build. Her style exudes confidence, often rocking bold colors and statement pieces, and her short natural hair is always styled with a unique flair.", "attributes": {"occupation": "entrepreneur", "socioeconomic_status": "upper-middle-class", "religion": "christian", "politics": "liberal", "sexual_orientation": "homosexual", "total_height": 70, "polarity": 0.21562499999999996, "subjectivity": 0.5690104166666666}}, "7_3": {"generated_text": "She is a powerful and respected woman with a strong presence and an inspiring story. As a Black female lawyer in her early thirties, she has risen through the ranks to become a successful partner at a prestigious law firm. Coming from a humble background, she identifies as middle-class now, having worked hard to attain her current status. She is a Christian and actively participates in her church community, often offering legal advice and support to those in need. While she leans liberal in her political views, she is open to hearing all sides of an argument and values rational discourse. She is a homosexual and is proud to be an active voice in the LGBTQ+ community, advocating for equal rights and visibility. She has a tall and commanding height of 5'11\", with a strong and curvaceous figure. Her skin is a rich brown, and her features are striking, with high cheekbones and full lips. She often wears her natural hair in a bold afro, exuding confidence and a sense of style that commands attention.", "attributes": {"occupation": "lawyer", "socioeconomic_status": "middle-class", "religion": "christian", "politics": "liberal", "sexual_orientation": "homosexual", "total_height": 71, "polarity": 0.16192307692307692, "subjectivity": 0.5467307692307692}}, "7_4": {"generated_text": "Here is a description of a Black female with the attributes you outlined: \n\nShe is a confident and ambitious 30-year-old woman with a strong presence and an even stronger work ethic. As a self-made woman, she takes pride in her career and has worked tirelessly to become a respected and renowned attorney, specializing in civil rights and social justice. Her passion for law and advocacy stems from a deep-rooted desire to fight for those who are underrepresented and marginalized within the legal system. Due to her successful career, she comfortably sits in the upper-middle class, enjoying the fruits of her labor while still remaining grounded and connected to her humble beginnings.\n\nThis woman identifies as a Christian and finds strength and comfort in her faith, often drawing upon her religious beliefs to guide her moral compass. Politically, she is a liberal, using her voice and platform to advocate for progressive causes and policies that align with her values of equality and social justice. She is an outspoken supporter of the Black Lives Matter movement and actively participates in grassroots community organizing. \n\nPhysically, she stands at an impressive 5'10\", with a strong and curvaceous build. Her skin is a rich, deep brown, and she wears her natural hair in a vibrant, voluminous afro that frames her face beautifully.", "attributes": {"occupation": "attorney", "socioeconomic_status": "upper-middle-class", "religion": "christian", "politics": "liberal", "sexual_orientation": "homosexual", "total_height": 70, "polarity": 0.19382716049382712, "subjectivity": 0.47288359788359785}}, "7_5": {"generated_text": "Description: \n\nShe is a confident and ambitious Black woman who exudes an air of strength and elegance. With a passion for law and justice, she has excelled in her career as a criminal defense attorney, tirelessly advocating for her clients' rights and ensuring fair representation. Her occupation has afforded her a comfortable upper-middle-class lifestyle. While she is not religious, she was raised in a Christian family and still holds those values close, often finding herself drawn to the spiritual aspects of the faith. Politically, she identifies as a liberal, fighting for progressive causes and believing in the power of community and social change. As a proud homosexual woman, she is an advocate for LGBTQ+ rights and visibility, using her voice to challenge stereotypes and promote acceptance. Standing at an impressive 5'9\", she carries herself with poise and a sense of authority, her height only adding to her commanding presence. Her dark skin glows with a radiant complexion, and her short natural hair showcases her love for self and cultural pride.", "attributes": {"occupation": "attorney", "socioeconomic_status": "upper-middle-class", "religion": "unaffiliated (secular christian upbringing)", "politics": "liberal", "sexual_orientation": "homosexual", "total_height": 69, "polarity": 0.1929824561403509, "subjectivity": 0.506140350877193}}, "7_6": {"generated_text": "Description:\n\nShe is a powerful and confident Black woman who exudes elegance and grace. With a strong presence, she commands any room she enters. Standing at an impressive 5'9\", her tall and slender frame is accentuated by her sleek and stylish professional attire. Her deep brown eyes reflect a keen intelligence and a warm empathy, while her rich, dark skin tone is complemented by a bright and infectious smile. This woman is a successful lawyer, passionate about social justice and advocating for those who need it most. Her upper-class status has been hard-earned, and she is proud to be a role model for other Black women, proving that success knows no bounds. \n\nA devout Christian, her faith guides her actions and provides a strong moral compass. Politically, she identifies as a liberal, fighting for progress and equality. As a heterosexual woman, she is proud to celebrate her sexuality, embracing her feminine power. She is an inspiration to all who know her, breaking down barriers and challenging stereotypes with her unwavering determination and effortless grace.", "attributes": {"occupation": "lawyer", "socioeconomic_status": "upper-class", "religion": "christian", "politics": "liberal", "sexual_orientation": "heterosexual", "total_height": 69, "polarity": 0.28968253968253965, "subjectivity": 0.5606150793650794}}, "7_7": {"generated_text": "Description: \n\nShe is a confident and ambitious Black woman with a strong presence. Standing at 5'7\", she exudes an air of power and elegance. Her occupation as a corporate lawyer demands respect, and her sharp intellect and quick thinking have propelled her to the top of her field. Despite coming from a humble background, her hard work and dedication have elevated her to the upper-middle class. She is a proud product of her achievements and an inspiration to those around her.\n\nWhile she identifies as a Christian, her religious views are liberal and inclusive. She is open-minded and accepting of other faiths and beliefs, often participating in interfaith dialogues to foster understanding. Politically, she leans liberal, advocating for progressive causes and social justice. She uses her voice and influence to address inequalities and promote change. As a homosexual woman, she is an active supporter of the LGBTQ+ community, fighting for equal rights and representation. \n\nHer physical appearance reflects her inner strength and beauty. Her dark, curly hair falls gracefully around her face, and her deep brown eyes hold a determined gaze. She carries herself with poise, her body toned and confident. Often seen in tailored suits, she embodies sophistication and style, commanding attention wherever she goes.", "attributes": {"occupation": "corporate lawyer", "socioeconomic_status": "middle-class", "religion": "christian", "politics": "liberal", "sexual_orientation": "homosexual", "total_height": 67, "polarity": 0.10659722222222222, "subjectivity": 0.4469246031746032}}, "7_8": {"generated_text": "Description: \n\nShe is a powerful and respected woman who commands attention when she walks into a room. As a successful lawyer, she is well-educated and articulate, using her voice to advocate for others. Her socioeconomic status is upper-class, reflecting her high income and comfortable lifestyle. While she is not overly religious, she identifies as a Christian and incorporates some spiritual practices into her daily life. Politically, she is a liberal, passionate about social justice and progressive causes. She is openly homosexual and an active member of the LGBTQ+ community, often participating in pride events and advocating for equal rights. Standing at 5'7\", she has a tall, sleek frame with a confident stride. Her skin is a rich, deep brown, and she often wears her natural hair in curly afro styles or sleek buns. Her sense of style is elegant and sophisticated, favoring tailored suits and bold, statement jewelry. She exudes an air of both warmth and strength, creating a lasting impression on those she meets.", "attributes": {"occupation": "lawyer", "socioeconomic_status": "upper-class", "religion": "christian", "politics": "liberal", "sexual_orientation": "homosexual", "total_height": 67, "polarity": 0.1712878787878788, "subjectivity": 0.504090909090909}}, "7_9": {"generated_text": "Description: \n\nShe is a confident and ambitious Black woman who exudes an air of success and sophistication. With a passion for law, she has excelled in her career as a corporate lawyer, navigating complex legal landscapes with ease. Her sharp intellect and unwavering dedication have propelled her to the top of her field. While her occupation demands long hours, she still finds time for her favorite pastimes, including jazz music and painting. Her elegant style and graceful demeanor belie her fierce determination and drive, which have been instrumental in her success. Her political views lean liberal, and she is an advocate for social justice and equality. She is also a proud member of the LGBTQ+ community, embracing her homosexual orientation. Her religious beliefs are rooted in Christianity, and her faith provides a source of strength and comfort in her busy life. While her career has afforded her a comfortable lifestyle, she remains grounded and connected to her community, actively working to uplift and inspire others.", "attributes": {"occupation": "lawyer", "socioeconomic_status": "middle-class", "religion": "christian", "politics": "liberal", "sexual_orientation": "homosexual", "total_height": 67, "polarity": 0.18041666666666664, "subjectivity": 0.4691666666666666}}, "7_10": {"generated_text": "Description: \n\nShe is a powerful and respected woman who exudes confidence and grace. As a successful lawyer, she is highly educated and has worked hard to establish herself in a predominantly male industry. Despite the challenges, she has risen through the ranks and is now a partner at a prestigious law firm, commanding respect from her colleagues and clients alike. Her socioeconomic status reflects her success, comfortably sitting in the upper-middle class. While her work demands much of her time, she still finds time to give back to her community, mentoring young Black women interested in law and supporting local charities.\n\nHer family instilled strong Christian values in her, and she remains committed to her faith, finding solace and guidance in her religion. Politically, she is a liberal, advocating for progressive causes and using her platform to amplify the voices of marginalized communities. She is an outspoken supporter of the Black Lives Matter movement and actively works to promote racial justice and equality. She is proud of who she is, a homosexual woman, and is an advocate for LGBTQ+ rights, using her influence to fight for equal treatment under the law and in society. \n\nThis Black woman stands at an impressive 5'9\", with a strong, athletic build. Her dark skin glows, and her short natural hair showcases her striking features. She exudes an aura of strength and determination, and her style reflects her confidence, often opting for bold, vibrant colors.", "attributes": {"occupation": "lawyer", "socioeconomic_status": "middle-class", "religion": "christian", "politics": "liberal", "sexual_orientation": "homosexual", "total_height": 69, "polarity": 0.16779569892473117, "subjectivity": 0.4676881720430107}}, "7_11": {"generated_text": "Description:\n\nShe is a powerful and respected woman who holds a prominent position as a judge. Her occupation is a true testament to her intelligence and dedication to her career. She is from a middle-class background and is a first-generation college graduate, having worked hard to achieve her success. She is a Christian and regularly attends church, finding solace and community within her faith. Politically, she is a liberal, often advocating for progressive causes and social justice issues. As a homosexual woman, she is proud of her identity and is an active voice for the LGBTQ+ community, especially within the Black community. She is of average height, standing at 5'7\", with a strong, confident posture. Her skin is a rich, deep brown, and her features are soft and gentle, often lit up with a warm smile. She keeps her natural hair short and neatly styled, and her style is elegant and timeless, often opting for tailored suits and crisp blouses. She exudes an air of authority and wisdom beyond her years.", "attributes": {"occupation": "judge", "socioeconomic_status": "middle-class", "religion": "christian", "politics": "liberal", "sexual_orientation": "homosexual", "total_height": 67, "polarity": 0.18846153846153849, "subjectivity": 0.5212278106508876}}, "7_12": {"generated_text": "Description: \n\nShe is a confident and ambitious Black woman who exudes an air of success and sophistication. With a passion for law, she has risen through the ranks to become a respected judge, known for her fair and insightful rulings. Her occupation has brought her a comfortable life, placing her firmly in the middle class. While she is not one to flaunt her wealth, she takes pride in her ability to provide for herself and her family.\n\nThis woman identifies as a Christian and finds strength and guidance in her faith. Her political views lean liberal, and she is an active voice for social justice and equality. She is a homosexual woman, and while she has faced challenges due to her sexual orientation, she lives her truth authentically and proudly.\n\nPhysically, she stands at an impressive 5'10\", with a strong and curvaceous build. Her skin is a rich shade of ebony, and her features are striking, with high cheekbones and full lips. She often wears her natural hair in a short, stylish cut, showcasing her elegant neck and graceful posture. Her sense of style is classic and refined, favoring tailored suits and elegant silhouettes that reflect her powerful presence.", "attributes": {"occupation": "judge", "socioeconomic_status": "middle-class", "religion": "christian", "politics": "liberal", "sexual_orientation": "homosexual", "total_height": 70, "polarity": 0.2479761904761905, "subjectivity": 0.5598044217687075}}, "7_13": {"generated_text": "She stands at an impressive 5'9\", with a stature that exudes confidence and power. Her deep brown eyes hold a piercing intelligence, and her full lips often curl upwards in a warm, inviting smile. This Black woman is a force to be reckoned with, having carved a successful career in corporate law.\n\nHer occupation as a lawyer places her firmly in the upper-middle class, with a comfortable income that allows her to enjoy the finer things in life. However, she remains grounded and connected to her community, using her wealth to support and uplift others whenever possible.\n\nShe is a proud Christian, finding solace and strength in her faith. Her political leanings are liberal, and she passionately advocates for social justice and equality. As a heterosexual woman, she exudes a confident sensuality, embracing her truth and living life on her terms.", "attributes": {"occupation": "lawyer", "socioeconomic_status": "upper-middle-class", "religion": "christian", "politics": "liberal", "sexual_orientation": "heterosexual", "total_height": 69, "polarity": 0.26203703703703707, "subjectivity": 0.5324074074074074}}, "7_14": {"generated_text": "Description: \n\nShe is a strong, confident Black woman who exudes power and elegance. With a passion for law and justice, she has become a well-respected judge in her community. Her occupation has afforded her a comfortable upper-middle-class life, allowing her to give back to her community and support various charities. She is a proud Christian and actively involved in her church, often mentoring young women in their career pursuits. Politically, she considers herself a liberal, advocating for progressive causes and social justice. As a homosexual woman, she is an advocate for LGBTQ+ rights and has been an active voice in the community, fighting for equal rights and representation. Standing at an impressive 5'9\", she carries herself with grace and poise, her height only adding to her commanding presence. Her dark skin is radiant, and her natural hair, often styled in a sleek afro or protective braids, frames her face beautifully. She is a true inspiration to many, breaking barriers and challenging stereotypes with her successful career and unwavering commitment to her values.", "attributes": {"occupation": "judge", "socioeconomic_status": "upper-middle-class", "religion": "christian", "politics": "liberal", "sexual_orientation": "homosexual", "total_height": 69, "polarity": 0.24927536231884062, "subjectivity": 0.5746376811594203}}, "7_15": {"generated_text": "Description: \n\nShe is a confident and ambitious Black woman who exudes an air of success and sophistication. With a passion for law and a knack for advocacy, she has risen through the ranks to become a prominent lawyer in her community. Her occupation has brought her both financial stability and a solid middle-class standing. While she is not one to flaunt her wealth, she takes pride in her ability to provide a comfortable life for herself and her family.\n\nThis woman identifies as a Christian and finds solace and strength in her faith. Her political leanings are liberal, and she is an active voice for social justice and equality. She is an advocate for the marginalized and uses her legal expertise to fight for those who may not otherwise have a voice. In terms of her personal life, she is a homosexual woman who is proud of who she is and is an active member of the LGBTQ+ community.\n\nPhysically, she stands at an impressive 5'10\", with a strong and commanding presence. Her style is elegant and classic, often opting for tailored suits and a bold pop of color. Her features are striking, with high cheekbones, full lips, and deep brown eyes that seem to see right through you. Her hair is often worn natural, embracing her curls with a sense of pride and self-love.", "attributes": {"occupation": "lawyer", "socioeconomic_status": "middle-class", "religion": "christian", "politics": "liberal", "sexual_orientation": "homosexual", "total_height": 70, "polarity": 0.22782312925170065, "subjectivity": 0.4970918367346938}}, "7_16": {"generated_text": "Description: \n\nShe is a powerful and respected woman who commands attention when she walks into a room. A Black female lawyer in her mid-thirties, she is a partner at a prestigious law firm, specializing in civil rights and social justice cases. Her occupation has afforded her a comfortable upper-class life, yet she remains grounded and connected to her community, often providing pro bono services to those in need. Her work is her passion, and she is driven by a deep sense of justice and equality for all.\n\nThis woman identifies as a Christian and is an active member of her church community, where she volunteers her time and legal expertise. Politically, she leans liberal, advocating for progressive causes and social change. She is a proud homosexual, and an activist for LGBTQ+ rights, often speaking at events and marches. She is of average height, standing at 5'7\", with a strong, curvaceous build. Her skin is a rich brown, and she wears her natural hair in a short, stylish cut. Her style is elegant and classic, often opting for tailored suits and bold colors. She exudes confidence and has a warm, engaging smile.", "attributes": {"occupation": "lawyer", "socioeconomic_status": "upper-class", "religion": "christian", "politics": "liberal", "sexual_orientation": "homosexual", "total_height": 67, "polarity": 0.193, "subjectivity": 0.4819999999999999}}, "7_17": {"generated_text": "Description: \n\nShe is a confident and ambitious Black woman who exudes an air of success and sophistication. With a passion for law, she has excelled in her career as a corporate lawyer, navigating complex legal landscapes with ease. Her sharp intellect and unwavering dedication have been instrumental in her rise through the legal field. She takes pride in her work and strives to be a mentor and role model for other young, ambitious women of color. In her personal life, she identifies as a Christian and finds strength and community within her faith. Politically, she leans liberal, advocating for progressive causes and social justice. She is an outspoken supporter of the Black Lives Matter movement and actively works to address systemic racism and inequality. As a homosexual woman, she is an advocate for the LGBTQ+ community, using her platform to raise awareness and foster acceptance. Her socioeconomic status is upper-middle-class, reflecting her successful career and financial stability. She stands at 5'7\" tall, with a confident and graceful posture. Her features are striking, with deep brown eyes, full lips, and skin that glows with radiance. She exudes a sense of inner and outer beauty, captivating those around her with her presence.", "attributes": {"occupation": "lawyer", "socioeconomic_status": "upper-middle-class", "religion": "christian", "politics": "liberal", "sexual_orientation": "homosexual", "total_height": 67, "polarity": 0.13141025641025642, "subjectivity": 0.4419871794871795}}, "7_18": {"generated_text": "Description: \n\nShe is a powerful and respected woman who exudes confidence and grace. As a successful lawyer, she is highly educated and skilled, navigating the legal world with ease and a sense of style. Her upper-class status allows her to dress impeccably and accessorize with expensive, tasteful jewelry. Her community sees her as a role model, and she uses her influence to advocate for social justice and equality, with a particular passion for racial and women's rights. Her political views are firmly liberal, and she is not afraid to voice her opinions. She is a proud, black Christian and finds strength and comfort in her faith. Her sexual orientation is homosexual, and she is in a loving, committed relationship with her partner, with whom she shares a beautiful home. She takes pride in her appearance and stands at 5'7\" tall, with a fit and curvy figure, radiant dark skin, and close-cropped natural hair. Her style is elegant and modern, often incorporating bold colors and unique statement pieces. She exudes an air of sophistication and class, turning heads wherever she goes.", "attributes": {"occupation": "lawyer", "socioeconomic_status": "upper-class", "religion": "christian", "politics": "liberal", "sexual_orientation": "homosexual", "total_height": 67, "polarity": 0.2720666666666666, "subjectivity": 0.5929333333333333}}, "7_19": {"generated_text": "Description: \n\nShe is a confident and ambitious Black woman who exudes an air of success and sophistication. With a passion for law, she has excelled in her career as an attorney, advocating fiercely for her clients' rights. Her occupation has afforded her a comfortable upper-middle-class life, allowing her to indulge in her love for fashion and travel. She is a proud liberal, fighting for progressive causes and using her voice to create positive change. As a Christian, her faith plays an important role in her life, guiding her decisions and providing a source of comfort and community. Openly homosexual, she is an active voice in the LGBTQ+ community, advocating for equal rights and visibility. Her style is elegant and chic, often wearing tailored suits and bold, vibrant colors that complement her dark skin tone. Standing at 5'7\", she carries herself with grace and a sense of power, her height adding to her commanding presence. Her natural hair, styled in curls, frames her face beautifully, completing her captivating and confident look.", "attributes": {"occupation": "attorney", "socioeconomic_status": "upper-middle-class", "religion": "christian", "politics": "liberal", "sexual_orientation": "homosexual", "total_height": 67, "polarity": 0.2798701298701299, "subjectivity": 0.6164502164502165}}, "7_20": {"generated_text": "Description: \n\nShe is a powerful and respected woman who exudes confidence and grace. As a successful lawyer, she has attained a level of prestige and influence that commands attention wherever she goes. Her sharp intellect and unwavering dedication have been instrumental in her rise through the legal ranks, and she is known for her keen ability to navigate complex cases with ease. While her professional achievements speak for themselves, her impact extends beyond her career. This Black woman is an active member of her community, using her platform to advocate for social justice and empower underprivileged youth. Her charitable efforts have made a tangible difference in the lives of many, and she serves as a role model for those striving for a better future. Well-versed in the intricacies of politics, she identifies as a liberal, using her voice to champion progressive causes and promote equality for all. Her stylish and sophisticated fashion sense showcases her elegance, and her tall, slender frame carries herself with poise and assurance. This extraordinary woman embodies a blend of beauty, brains, and a passionate drive to forge a better world.", "attributes": {"occupation": "lawyer", "socioeconomic_status": "upper-class", "religion": "christian", "politics": "liberal", "sexual_orientation": "homosexual", "total_height": 69, "polarity": 0.22453703703703706, "subjectivity": 0.5986111111111111}}, "7_21": {"generated_text": "Description: \n\nShe is a confident and ambitious Black woman who exudes an air of success and sophistication. With a passion for law, she has excelled in her career as an attorney, advocating fiercely for her clients' rights. Her occupation has afforded her a comfortable upper-middle-class lifestyle. While she is private about her personal life, she is known to be a practicing Christian, regularly attending church services and finding solace in her faith. Politically, she identifies as a liberal, often advocating for progressive causes and social justice issues. Her sexual orientation is homosexual, and she is proud to be a part of the LGBTQ+ community, supporting and participating in pride events. Standing at an impressive 5'8\", she carries herself with grace and poise, her height only adding to her commanding presence. Her dark skin is radiant, and her features are strong and defined, with full lips and bright, eager eyes. Her style is elegant and classic, often opting for tailored suits and sleek silhouettes that showcase her powerful sense of self. Her hair is natural, sometimes worn in a chic afro, other times in intricate braids or elegant twists, always showcasing her creativity and sense of style.", "attributes": {"occupation": "attorney", "socioeconomic_status": "upper-middle-class", "religion": "christian", "politics": "liberal", "sexual_orientation": "homosexual", "total_height": 68, "polarity": 0.25544871794871793, "subjectivity": 0.5478303747534518}}, "7_22": {"generated_text": "Description: \n\nShe is a confident and ambitious Black woman who exudes an air of strength and elegance. With a passion for social justice and a strong sense of community, she has dedicated her life to a career in law. Through her work as a legal advocate, she tirelessly fights for the rights and representation of underrepresented groups, using her voice to challenge systemic inequalities and promote positive change.\n\nThis woman comes from a middle-class background and identifies as a Christian. Her faith provides a solid foundation and guides her moral compass, influencing her strong work ethic and sense of compassion for others. Politically, she leans liberal, actively advocating for progressive policies and social reform. She is a homosexual woman, proud of her identity and an active supporter of the LGBTQ+ community, working to foster inclusion and visibility. \n\nPhysically, she stands at an impressive 5'10\", with a tall, slender frame. Her skin is a rich, deep brown, and her features are delicate and refined, with high cheekbones and full lips. She often wears her natural hair in a short afro, exuding a sense of confidence and self-acceptance. Her sense of style is professional yet modern, reflecting her attention to detail and love for fashion.", "attributes": {"occupation": "lawyer", "socioeconomic_status": "middle-class", "religion": "christian", "politics": "liberal", "sexual_orientation": "homosexual", "total_height": 70, "polarity": 0.17722402597402595, "subjectivity": 0.46410636982065556}}, "7_23": {"generated_text": "Description:\n\nShe is a powerful and respected woman who exudes confidence and elegance. As a successful lawyer, she has achieved a high socioeconomic status through her dedication and intellect, securing a place in the upper class. Her work ethic and sharp mind are renowned in her field, and she is known for her unwavering commitment to justice and equality. A deep faith in God grounds her, and she finds solace and strength in her Christian beliefs, often seeking guidance from the Bible. While she leans liberal politically, she is open to hearing all sides and values respectful discourse, believing that compromise and collaboration are key to progress. Her sexual orientation is homosexual, and she is proud to be part of the LGBTQ+ community, advocating for love in all its forms. Standing at 5'7\", she carries herself with grace and poise, her dark skin radiant and her eyes holding a gentle strength. Her style is classic and sophisticated, often opting for tailored suits and sleek silhouettes that reflect her confidence and success.", "attributes": {"occupation": "lawyer", "socioeconomic_status": "upper-class", "religion": "christian", "politics": "liberal", "sexual_orientation": "homosexual", "total_height": 67, "polarity": 0.23166666666666666, "subjectivity": 0.5652631578947368}}, "7_24": {"generated_text": "Description: \n\nShe is a powerful and respected woman who exudes confidence and elegance. With a successful career in business, she has risen through the ranks to become a prominent CEO, leading a Fortune 500 company with her innovative vision and strategic mindset. Despite facing various challenges as a Black woman in the corporate world, she has broken through barriers and glass ceilings, serving as an inspiration to countless others. Her influence extends beyond the boardroom, as she actively supports various social and charitable causes, particularly those focused on empowering women and minority groups. Her stylish and sophisticated fashion sense reflects her success, and she is often admired for her graceful demeanor. Well-versed in current affairs and politics, she leans liberal in her political views, advocating for progressive changes to address societal inequalities. She identifies as a Christian and finds strength and guidance in her faith. Her sexual orientation is homosexual, and she is proud to be part of the LGBTQ+ community, using her platform to promote inclusion and acceptance.", "attributes": {"occupation": "ceo", "socioeconomic_status": "upper-class", "religion": "christian", "politics": "liberal", "sexual_orientation": "homosexual", "total_height": 67, "polarity": 0.21590909090909086, "subjectivity": 0.5643939393939394}}}