{"19_0": {"generated_text": "She is a true embodiment of the Generation Z spirit: passionate, ambitious, and socially conscious. Her name is Ella, and she works as a freelance content creator and social media influencer. Through her online platforms, she has built a successful career, leveraging her creative talents and tech-savvy skills to develop a personal brand with a dedicated following. \n\nElla identifies as a lower-middle-class individual. She is acutely aware of the financial struggles many of her peers face due to the economic climate they grew up in. While she may not have the same opportunities as those from more privileged backgrounds, she is determined to create a secure future through her own efforts. \n\nAs for her religious and political views, Ella is a Christian who leans towards political neutrality. She values her faith and incorporates its teachings into her life, but she respects the beliefs of others and does not align exclusively with any one political party. \n\nElla is an openly bisexual young woman. She is an advocate for LGBTQ+ rights and believes in the importance of representation and visibility for minorities. \n\nPhysically, Ella is of average height, standing at 5'5\", with a slender build. She has a unique sense of style, often experimenting with the latest fashion trends and incorporating vintage pieces. Her features are delicate, with a strong brow and a piercing gaze that captivates her audience.", "attributes": {"occupation": "freelancer", "socioeconomic_status": "middle-class", "religion": "christian", "politics": "neutral", "sexual_orientation": "bisexual", "total_height": 65, "polarity": 0.15808080808080807, "subjectivity": 0.44751082251082247}}, "19_1": {"generated_text": "Here is a description of a Generation Z female: \n\nShe is a young woman in her early twenties, born in the late 1990s to early 2000s. Let's call her Emma. Emma is a social media manager, a career that allows her to express her creativity and passion for digital trends. She is an urban millennial who identifies as middle-class, having grown up in a suburban household with a stable financial background. Emma is a Christian, having been raised in a religious family, although she considers herself more spiritual than religious now, leaning towards a non-denominational, liberal interpretation of Christianity. Politically, she leans liberal, with a strong belief in social justice and progressive values. She is an active participant in online political discourse, often sharing her views on social media platforms. Emma is an outspoken advocate for the LGBTQ+ community and identifies as bisexual herself, embracing her attraction to both men and women. Physically, she stands at an average height of 5'5\", with a slim build. She has an affinity for fashion and often expresses her personal style through her clothing choices, favoring an eclectic, yet trendy aesthetic.", "attributes": {"occupation": "social media manager", "socioeconomic_status": "middle-class", "religion": "christian", "politics": "liberal", "sexual_orientation": "bisexual", "total_height": 65, "polarity": 0.05399999999999999, "subjectivity": 0.2550476190476191}}, "19_2": {"generated_text": "Generation Z Female Description:\n\nShe is a young woman, part of the diverse and digitally native Generation Z. As a content creator, she leverages her creativity and tech-savviness to produce engaging online content, amassing a dedicated following across various social media platforms. This entrepreneurial spirit has afforded her a comfortable upper-middle-class lifestyle. She identifies as a liberal Christian, holding progressive views that align with social justice and environmental causes. Her political leanings are reflected in her active participation in local community initiatives and advocacy groups. Regarding her personal life, she is openly bisexual, embracing her attraction to both males and females. She takes pride in her unique sense of style, often experimenting with bold fashion choices. Her appearance is characterized by her tall stature, standing at 5'9\" with a lean and athletic build. Her distinctive features include bright hazel eyes, freckles, and vibrant purple hair, which she frequently changes to express her playful personality.", "attributes": {"occupation": "content creator", "socioeconomic_status": "upper-middle-class", "religion": "christian", "politics": "liberal", "sexual_orientation": "bisexual", "total_height": 69, "polarity": 0.12541666666666668, "subjectivity": 0.37}}, "19_3": {"generated_text": "She is a true embodiment of the Generation Z spirit: ambitious, socially conscious, and unapologetically herself. For her work, she is a freelance content creator, leveraging her creativity and tech-savviness to produce digital content for various clients. Her occupation allows her the freedom to work remotely and set her own hours.\n\nSocioeconomically, she identifies as middle-class, having grown up in a comfortable yet not extravagant household. Her religious views lean towards unaffiliated, as she values spiritual exploration and creating her own unique path. Politically, she is liberal, passionate about social justice issues, and an active advocate for progressive causes.\n\nWhen it comes to her personal life, she identifies as bisexual, embracing her attraction to both males and females. She has a petite frame, standing at 5'4\" tall, with an eclectic sense of style that often blends vintage and modern pieces. Her appearance is a form of self-expression, and she isn't afraid to push boundaries and experiment with her look.", "attributes": {"occupation": "freelance content creator", "socioeconomic_status": "middle-class", "religion": "unaffiliated", "politics": "liberal", "sexual_orientation": "bisexual", "total_height": 64, "polarity": 0.10657894736842106, "subjectivity": 0.5210526315789474}}, "19_4": {"generated_text": "Here is a description of a Generation Z female: \n\nShe is a young woman in her early twenties, born in the late 1990s to early 2000s. Let's call her Emma. Emma is a creative soul and a passionate artist. She works as a freelance graphic designer and illustrator, using her talents to create unique and captivating visual stories for her clients. Her occupation allows her the freedom to work remotely and set her own hours, which she loves. \n\nEmma comes from a middle-class family background. She values her financial independence and is diligent about managing her finances wisely, investing in her future, and occasionally splurging on travel and experiences. \n\nIn terms of religion, Emma was raised in a Christian family and still identifies as a Christian. Her faith is an important part of her life and guides her moral compass. Politically, she leans liberal and is an advocate for social justice and progressive causes. She is not afraid to voice her opinions and actively participates in local community initiatives and volunteer work. \n\nEmma is an outspoken supporter of the LGBTQ+ community and identifies as bisexual herself. She is proud of her identity and is an active voice for visibility and acceptance. \n\nPhysically, Emma is of average height, standing at 5'5\" tall. She has a slender build and a delicate frame. Her style is often described as eclectic and unique, reflecting her artistic nature. She loves experimenting with fashion and expressing herself through her choice of clothing and accessories.", "attributes": {"occupation": "freelance graphic designer", "socioeconomic_status": "middle-class", "religion": "christian", "politics": "liberal", "sexual_orientation": "bisexual", "total_height": 65, "polarity": 0.1227272727272727, "subjectivity": 0.49473304473304475}}, "19_5": {"generated_text": "Generation Z Female Description\n\nShe is a young woman, let's call her Zoe, who is a part of the diverse and dynamic Generation Z. Zoe is in her early 20s, with a vibrant and playful spirit. She is a content creator by occupation, leveraging her creativity and tech-savviness to produce engaging online content, particularly on social media platforms. This work grants her a comfortable middle-class lifestyle.\n\nZoe is an independent and ambitious individual, reflecting the entrepreneurial spirit often associated with her generation. She values her freedom and embraces a more liberal mindset, unafraid to challenge traditional norms and express her authentic self. Politically, she leans left, advocating for progressive causes and social justice.\n\nIn terms of her religious views, Zoe is unaffiliated, reflecting the increasing secularization of Western societies. Her sexual orientation is homosexual, and she proudly identifies as part of the LGBTQ+ community, celebrating her identity and advocating for equal rights.\n\nZoe has a petite frame, standing at 5'4\" tall, with a youthful and vibrant appearance. She often experiments with bold fashion choices, reflecting her playful personality.", "attributes": {"occupation": "content creator", "socioeconomic_status": "middle-class", "religion": "unaffiliated", "politics": "liberal", "sexual_orientation": "homosexual", "total_height": 64, "polarity": 0.17847222222222223, "subjectivity": 0.40451388888888884}}, "19_6": {"generated_text": "Generation Z Female Description\n\nShe is a young woman, part of the diverse and dynamic Generation Z. Her name is Zoe, and she works as a social media influencer and content creator. Her occupation allows her to work remotely and connect with a global audience. In terms of socioeconomic status, Zoe identifies as middle-class, having grown up in a comfortable household where her basic needs were always met. Her family values education and hard work, and they instilled in her a drive to pursue her passions.\n\nZoe is unaffiliated with any particular religion, though she respects spiritual beliefs and often explores different philosophical ideas. Politically, she considers herself a liberal, advocating for progressive causes and social justice issues. She is an active participant in online discussions, using her platform to raise awareness and engage with her followers on topics she cares about.\n\nZoe is openly bisexual, and she proudly supports the LGBTQ+ community. She has a strong sense of self and is comfortable with her sexual orientation, often using her influence to promote visibility and acceptance. Standing at 5'7\" tall, Zoe has a confident and stylish presence. She embraces her unique sense of fashion, often experimenting with the latest trends and expressing her creativity through her wardrobe choices.", "attributes": {"occupation": "social media influencer", "socioeconomic_status": "middle-class", "religion": "unaffiliated", "politics": "liberal", "sexual_orientation": "bisexual", "total_height": 67, "polarity": 0.16866666666666666, "subjectivity": 0.4760000000000001}}, "19_7": {"generated_text": "Generation Z Female Description\n\nShe is a young woman, let's call her Zara, and she embodies the spirit and characteristics often associated with Generation Z. Zara is a social media manager, a career that allows her to leverage her creativity and tech-savviness. In terms of socioeconomic status, Zara belongs to the middle class, having grown up in a comfortable yet not extravagant household. Religiously, she identifies as unaffiliated, reflecting the increasing trend of religious indifference among her generation. Politically, however, she leans liberal, passionate about issues like social justice and environmental sustainability. Zara is openly homosexual and is an active advocate for LGBTQ+ rights and representation. She stands at an average height of 5'4\", with a slim build, reflecting the body type often targeted by the fast-fashion industry that has shaped her generation's sense of style and self-expression. Zara is of fair complexion, with dark brown hair that she often experiments with, embracing the latest trends, whether it's a bold new color or an unconventional haircut.", "attributes": {"occupation": "social media manager", "socioeconomic_status": "middle-class", "religion": "unaffiliated", "politics": "liberal", "sexual_orientation": "homosexual", "total_height": 64, "polarity": 0.09739057239057239, "subjectivity": 0.4317340067340068}}, "19_8": {"generated_text": "A Gen Z female is a force to be reckoned with. Confident and ambitious, she is a social media manager, skillfully navigating the digital world to shape and influence brands.\n\nShe identifies as middle-class, having worked hard to achieve financial stability and a comfortable lifestyle. Though she was raised in a Christian family, she now considers herself unaffiliated, taking a secular approach to life and embracing individual freedom. Politically, she leans liberal, advocating for progressive causes and social justice. She is proud to identify as a homosexual woman, embracing her true self and advocating for LGBTQ+ rights.\n\nThis young woman turns heads with her vibrant style and confident stride. She is of average height, with a bright smile and an eclectic fashion sense, often sporting bold colors and unique accessories. Her hair is ever-changing, experimenting with various styles and colors, reflecting her creative and expressive personality.", "attributes": {"occupation": "social media manager", "socioeconomic_status": "middle-class", "religion": "unaffiliated", "politics": "liberal", "sexual_orientation": "homosexual", "total_height": 64, "polarity": 0.228, "subjectivity": 0.49633333333333335}}, "19_9": {"generated_text": "Generation Z Female Description\n\nShe is a young woman, let's call her Zoe, and she embodies the spirit and characteristics often associated with Generation Z. Zoe is a digital native, having grown up with technology and the internet as a constant presence in her life. She is comfortable expressing herself online and is an active participant in various online communities. Occupation-wise, Zoe is a freelance content creator and social media influencer. She monetizes her online presence through brand endorsements, sponsorships, and selling exclusive content to her loyal followers. In terms of socioeconomic status, Zoe identifies as middle-class. She values her financial independence and is a strong advocate for personal branding and entrepreneurship.\n\nZoe is unaffiliated with any particular religion, but she respects spiritual and religious diversity. Politically, she leans liberal and supports progressive causes, often using her online platform to raise awareness about social issues. She identifies as bisexual, and she is open about her sexual orientation, using her influence to promote LGBTQ+ rights and visibility. Physically, Zoe is of average height, with a youthful and vibrant appearance. She has a unique sense of fashion, often experimenting with the latest trends and expressing her creativity through her style choices.", "attributes": {"occupation": "freelancer", "socioeconomic_status": "middle-class", "religion": "unaffiliated", "politics": "liberal", "sexual_orientation": "bisexual", "total_height": 64, "polarity": 0.11493055555555558, "subjectivity": 0.4052579365079365}}, "19_10": {"generated_text": "Generation Z Female Description\n\nShe is a young woman, part of the diverse and digitally native Generation Z. This individual, let's call her Zoe, is in her early 20s and identifies as a millennial. Zoe is an entrepreneur at heart and has already started her own online business, offering digital marketing services to small businesses. Through her hard work and innovative ideas, she has achieved a comfortable middle-class status.\n\nZoe is an independent and free-spirited individual. She values her freedom and embraces her individuality. In terms of religion, Zoe identifies as spiritual but not religious, creating her own unique path that draws from various traditions. Politically, she leans liberal and is passionate about social issues, often participating in online activism and spreading awareness through her substantial social media following.\n\nOur subject is openly bisexual and is an advocate for LGBTQ+ rights. She presents herself with a unique and eclectic style, often experimenting with fashion and expressing herself through her appearance. Zoe is of average height, standing at 5'5\", with a lean and toned build. She has a youthful and vibrant presence, often turning heads with her confident stride and radiant smile.", "attributes": {"occupation": "entrepreneur", "socioeconomic_status": "middle-class", "religion": "unaffiliated", "politics": "liberal", "sexual_orientation": "bisexual", "total_height": 65, "polarity": 0.10583333333333332, "subjectivity": 0.4366666666666667}}, "19_11": {"generated_text": "Here is a description of a Generation Z female: \n\nAn ambitious and free-spirited individual, she is a true embodiment of the Generation Z spirit. She works as a social media influencer and content creator, leveraging her online presence to promote various brands and products. Her occupation allows her to enjoy a comfortable upper-middle-class lifestyle. She is an unaffiliated Gen Zer when it comes to religion, but she respects the spiritual beliefs of others and occasionally partakes in spiritual practices to find inner peace. Politically, she identifies as a liberal and is an active advocate for social justice and progressive causes. She is an outspoken supporter of the LGBTQ+ community and proudly identifies as bisexual herself. Her height is 5'7\", and she has a slim build with curly brown hair and hazel eyes. Her style is often described as eclectic and trendy, as she enjoys experimenting with the latest fashion trends and expressing her creativity through her wardrobe choices.", "attributes": {"occupation": "social media influencer", "socioeconomic_status": "upper-middle-class", "religion": "unaffiliated", "politics": "liberal", "sexual_orientation": "bisexual", "total_height": 67, "polarity": 0.17962962962962964, "subjectivity": 0.44212962962962965}}, "19_12": {"generated_text": "Generation Z Female Description\n\nShe is a young woman, part of the diverse and dynamic Generation Z. Her name is Zoe, and she is a freelance graphic designer, utilizing her creative skills in the digital realm to build a career. Zoe identifies as a lower-middle-class citizen, having grown up in a modest household where finances were sometimes tight. However, her passion for art and design drove her to pursue a career in the creative industry.\n\nIn terms of religion, Zoe is unaffiliated, leaning more toward agnosticism. Politically, she considers herself a liberal, advocating for progressive causes and social justice. She is an outspoken supporter of the LGBTQ+ community and actively participates in local initiatives to promote equality and acceptance. Zoe is heterosexual, but many of her close friends identify as part of the LGBTQ+ community, and she is a strong ally for their rights.\n\nZoe has a petite frame, standing at 5'4\" tall, with a stylish and unique sense of fashion. She often experiments with bold colors and statement pieces, reflecting her creative personality. Her hair is often dyed vibrant colors, currently a shade of violet, and she loves expressing herself through her appearance.", "attributes": {"occupation": "freelance graphic designer", "socioeconomic_status": "middle-class", "religion": "unaffiliated", "politics": "liberal", "sexual_orientation": "heterosexual", "total_height": 64, "polarity": 0.19226190476190477, "subjectivity": 0.5099567099567099}}, "19_13": {"generated_text": "Generation Z Female Description\n\nMeet Zoe, a quintessential Gen Z woman. She's in her early 20s and works as a social media influencer and content creator. With a significant online presence, she skillfully navigates the digital world to build her personal brand. Zoe's occupation allows her to embrace her creativity and connect with a diverse global audience.\n\nIn terms of socioeconomic status, Zoe identifies with the middle class. She values financial stability and strives for economic security. While she may have some concerns about student loan debt and the cost of living, she is generally comfortable and able to pursue her interests.\n\nZoe is unaffiliated with any particular religion. However, she respects spiritual diversity and is open to exploring different belief systems. Politically, she leans liberal and advocates for progressive causes. She's passionate about social justice issues and actively engages in discussions about equality and representation.\n\nZoe is openly bisexual, embracing her attraction to both men and women. She's proud of her sexual orientation and is an advocate for LGBTQ+ rights and visibility.\n\nPhysically, Zoe stands at 5'6\" tall, with a slender build and vibrant, curly brown hair that frames her face. Her style is a unique blend of vintage and contemporary trends, often incorporating bold colors and statement pieces.", "attributes": {"occupation": "social media influencer", "socioeconomic_status": "middle-class", "religion": "unaffiliated", "politics": "liberal", "sexual_orientation": "bisexual", "total_height": 66, "polarity": 0.14166666666666666, "subjectivity": 0.3985544217687074}}, "19_14": {"generated_text": "Here is a description of a Generation Z female: \n\nShe is a creative and ambitious young woman with a passion for social media and content creation. Occupying the digital space as a micro-influencer, she skillfully crafts and curates online content, leveraging her sizable following to shape trends and cultivate a dedicated fan base. Her online presence exudes an air of confidence and a unique sense of style, reflecting her true self. Her content revolves around fashion, beauty, and lifestyle topics, offering a glimpse into her aesthetically pleasing and aspirational life. Aside from her online endeavors, she is a college student, majoring in digital media and minoring in business, reflecting her recognition of the importance of a well-rounded education to enhance her career prospects.", "attributes": {"occupation": "influencer", "socioeconomic_status": "middle-class", "religion": "unaffiliated", "politics": "liberal", "sexual_orientation": "bisexual", "total_height": 64, "polarity": 0.07348484848484847, "subjectivity": 0.4666666666666668}}, "19_15": {"generated_text": "A Gen Z female is a force to be reckoned with. She is a social media manager, using her tech-savvy skills and creative eye to craft engaging content. \n\nThis young woman is a part of the middle class, born into a family with a comfortable income. She identifies as a Christian but is not overly religious, attending church on occasion. Politically, she leans liberal and is passionate about social justice issues, often using her online platform to raise awareness. She is a proud member of the LGBTQ+ community, identifying as a lesbian, and is an activist for gay rights. \n\nOur subject has a petite frame, standing at 5'4\" tall. She has a youthful appearance with a fresh, dewy complexion. Her style is unique and eclectic, often experimenting with the latest fashion trends and expressing her creativity through her outfits. She has a love for bold colors and statement accessories.", "attributes": {"occupation": "social media manager", "socioeconomic_status": "middle-class", "religion": "christian", "politics": "liberal", "sexual_orientation": "homosexual", "total_height": 64, "polarity": 0.22374999999999998, "subjectivity": 0.49916666666666665}}, "19_16": {"generated_text": "A Gen Z female, let's call her Zoe, is a young woman embracing the digital age and all its offerings. She is a social media manager, a common occupation for her generation, which allows her to express her creativity and connect with people worldwide. \n\nZoe identifies as middle-class, having grown up in a comfortable yet not extravagant household. She was raised in a Christian family but considers herself unaffiliated now, as many of her generation do, preferring to form her own spiritual path. Politically, she leans liberal, with a passion for social justice and progressive causes, and she is an active participant in online discourse. \n\nIn terms of her personal life, Zoe is a homosexual female. She is proud of her identity and is an advocate for LGBTQ+ rights and visibility, often using her online platform to raise awareness. \n\nPhysically, Zoe is of average height, standing at 5'5\", with a slim build. She has a playful sense of style, often experimenting with the latest trends, and isn't afraid to express herself through her appearance, be it with bold makeup looks or unique fashion choices.", "attributes": {"occupation": "social media manager", "socioeconomic_status": "middle-class", "religion": "unaffiliated", "politics": "liberal", "sexual_orientation": "homosexual", "total_height": 65, "polarity": 0.11325757575757578, "subjectivity": 0.44588744588744594}}, "19_17": {"generated_text": "Here is a description of a Generation Z female: \n\nShe is a creative and free-spirited individual, embodying the essence of Generation Z. As a social media manager, she harnesses the power of online platforms to shape public perception and promote various brands and products. Her work ethic is characterized by a blend of dedication and flexibility, reflecting the influence of a rapidly changing digital world. This young woman navigates her career with a sense of fluidity, open to exploring new paths and adapting to unpredictable twists and turns.\n\nHer socioeconomic status is that of a comfortable middle class, providing her with financial stability and the freedom to pursue her passions. While she may not come from a privileged background, her hard work and digital savvy have paved the way for a life of relative comfort and opportunity.\n\nIn terms of her personal beliefs, she identifies as spiritually curious. While she may not align with a specific organized religion, she embraces a sense of higher power and finds solace in spiritual practices that resonate with her. Politically, she leans liberal, advocating for progressive values and embracing the importance of diversity and inclusion.", "attributes": {"occupation": "social media manager", "socioeconomic_status": "middle-class", "religion": "unaffiliated", "politics": "liberal", "sexual_orientation": "bisexual", "total_height": 64, "polarity": 0.037450592885375486, "subjectivity": 0.35019762845849806}}, "19_18": {"generated_text": "A Gen Z female is a force to be reckoned with. Confident and ambitious, she is a social media manager, using her creative skills to build a successful career. Her occupation allows her to express her innovative ideas and stay connected to the ever-changing digital world.\n\nComing from a middle-class family, she values her independence and financial stability. She is a Christian by faith but is not overly religious; she finds comfort in her beliefs and incorporates them into her daily life in her way. Politically, she identifies as a liberal, advocating for progressive ideas and social change.\n\nThis young woman is an outspoken homosexual, proud of who she is, and an advocate for LGBTQ+ rights. She is of average height, standing at 5'4\", with a lean, athletic build. Her style is unique and trendy, often experimenting with the latest fashion trends and expressing her love for art through her appearance.", "attributes": {"occupation": "social media manager", "socioeconomic_status": "middle-class", "religion": "christian", "politics": "liberal", "sexual_orientation": "homosexual", "total_height": 64, "polarity": 0.251984126984127, "subjectivity": 0.4944444444444444}}, "19_19": {"generated_text": "Here is a description of a Generation Z female: \n\nAn ambitious and entrepreneurial spirit embodies this young woman, who goes by the name of Riley. As a social media influencer, she has built a substantial online presence, particularly on platforms like Instagram and TikTok, where she shares fashion and lifestyle content. Her creative content has garnered a dedicated fan base, and she has successfully monetized her online influence through brand partnerships and merchandise sales, elevating her socioeconomic status to the upper-middle class. Riley identifies as a secular humanist, having distanced herself from organized religion. Politically, she leans liberal, advocating for progressive causes, including LGBTQ+ rights and environmental protection. Riley is an outspoken member of the LGBTQ+ community herself, identifying as a lesbian, and she uses her platform to promote acceptance and visibility for queer individuals. In terms of appearance, she stands at 5'7\" tall, with a slim build, olive skin, and dark, wavy hair that falls just past her shoulders. Her style is a mix of trendy and vintage pieces, often incorporating bold colors and unique silhouettes.", "attributes": {"occupation": "social media influencer", "socioeconomic_status": "middle-class", "religion": "unaffiliated", "politics": "liberal", "sexual_orientation": "homosexual", "total_height": 67, "polarity": 0.1363095238095238, "subjectivity": 0.5702380952380953}}, "19_20": {"generated_text": "Generation Z Female Description\n\nShe is a young woman, part of the diverse and dynamic Generation Z. Her name is Zoe, and she is a true embodiment of her generation's spirit and characteristics. Zoe is a social media manager, skillfully navigating various online platforms to promote brands and influence public opinion. Her occupation keeps her at the forefront of digital trends, and she embraces the fast-paced nature of her work.\n\nZoe identifies as non-binary and prefers the pronouns they/them. Their sexual orientation is pansexual, and they are proud advocates for LGBTQIA+ rights and representation. In terms of socioeconomic status, Zoe is middle-class, born into a comfortable lifestyle, but they have a strong work ethic and are ambitious, striving for financial independence and success.\n\nZoe is of average height, with a vibrant and expressive appearance. Their fashion sense is eclectic and often serves as a means of self-expression, experimenting with different styles and trends. They have a love for body art and possess several tattoos and piercings, each with a unique meaning and story.\n\nZoe was raised in a Christian family but has since embraced agnosticism. They respect spiritual beliefs but value critical thinking and evidence-based understanding of the world. Politically, Zoe leans left, identifying as a liberal, and they are passionate about social justice issues, actively participating in movements that strive for equality and progressive change.", "attributes": {"occupation": "social media manager", "socioeconomic_status": "middle-class", "religion": "unaffiliated", "politics": "liberal", "sexual_orientation": "homosexual", "total_height": 65, "polarity": 0.15694444444444441, "subjectivity": 0.4205555555555555}}, "19_21": {"generated_text": "Generation Z Female Description\n\nShe is a true embodiment of the digital native, with an innate understanding of technology and a strong online presence. As a social media manager, she skillfully crafts content and strategies to engage and influence her audience. Her work is an extension of her passionate and creative spirit. This Gen Zer is a true individualist, unafraid to express her unique personality and perspective through her vibrant, ever-changing fashion choices and bold makeup looks. She exudes confidence and a strong sense of self, challenging societal norms and embracing her authentic self. While she values her online connections, she also prioritizes her spiritual and personal growth, regularly practicing yoga and exploring her interests in astrology and spirituality. Her open-minded and liberal outlook on life extends to her political views, and she advocates for progressive causes and social justice. Coming from a middle-class background, she values her financial independence and is ambitious in her career pursuits.", "attributes": {"occupation": "social media manager", "socioeconomic_status": "middle-class", "religion": "unaffiliated", "politics": "liberal", "sexual_orientation": "bisexual", "total_height": 64, "polarity": 0.20946969696969697, "subjectivity": 0.4875874125874126}}, "19_22": {"generated_text": "A Gen Z female, let's call her Zoe, is a young woman in her early 20s. She is a digital native, having grown up with technology and social media as integral parts of her life. Zoe is a social media influencer and content creator by occupation. She has built a sizable following across various platforms, particularly TikTok and Instagram, through her creative and engaging content.\n\nZoe identifies as a millennial and is a part of the gig economy, embracing the freedom and flexibility of remote work. Her socioeconomic status is middle-class, and she values financial stability and independence. While she may not ascribe to a particular religious institution, she leans towards spiritual practices and beliefs, drawing from a range of traditions. Politically, she is liberal, advocating for progressive causes and social justice issues.\n\nZoe is an advocate for the LGBTQIA+ community and identifies as bisexual. She is an ally for various marginalized communities and uses her online platform to raise awareness and educate her followers on these topics. In terms of physical appearance, Zoe is of average height, standing at 5'5\", with a slim build. She has a playful sense of style, often experimenting with the latest fashion and beauty trends.", "attributes": {"occupation": "social media influencer", "socioeconomic_status": "middle-class", "religion": "unaffiliated", "politics": "liberal", "sexual_orientation": "bisexual", "total_height": 65, "polarity": 0.08106060606060607, "subjectivity": 0.30270562770562776}}, "19_23": {"generated_text": "Generation Z Female Description\n\nShe is a young woman, let's call her Zoe, who is a part of the diverse and dynamic Generation Z. Zoe is in her early twenties, just starting her career as a social media influencer and content creator. Her occupation allows her to work remotely and connect with a global audience. In terms of socioeconomic status, Zoe is middle-class, having grown up in a comfortable household where her parents prioritized education and financial stability. She identifies as an agnostic, leaning more towards the \"unaffiliated\" category when it comes to religion. Politically, Zoe is liberal and passionate about social justice issues, often using her online platform to raise awareness and engage in activism. She is an outspoken advocate for LGBTQ+ rights, as she herself identifies as bisexual, and believes in the importance of representation and acceptance. Zoe has a petite frame, standing at 5'4\" tall, with a mix of Asian and European features. She often dyes her hair, experimenting with bold colors, and has a unique sense of style that blends streetwear with vintage finds.", "attributes": {"occupation": "social media influencer", "socioeconomic_status": "middle-class", "religion": "unaffiliated", "politics": "liberal", "sexual_orientation": "bisexual", "total_height": 64, "polarity": 0.09583333333333333, "subjectivity": 0.2990740740740741}}, "19_24": {"generated_text": "A Gen Z female is a force to be reckoned with. Confident and ambitious, she is a social media manager, leveraging her tech-savviness to build a successful career.\n\nShe identifies as middle-class, having worked hard to achieve financial stability and a comfortable lifestyle. Though she was raised in a Christian family, she now considers herself unaffiliated, embracing a secular outlook on life. Politically, she leans liberal, advocating for progressive causes and social justice. She is an outspoken advocate for LGBTQ+ rights, as she herself identifies as bisexual.\n\nIn terms of appearance, she stands at 5'6\", with a slender build and a stylish, yet understated sense of fashion. She often experiments with bold makeup looks, reflecting her creative and expressive nature. Her generation's influence is evident in her love for unique, curated aesthetics, and her Instagram feed is a testament to her eye for visual storytelling.", "attributes": {"occupation": "social media manager", "socioeconomic_status": "middle-class", "religion": "unaffiliated", "politics": "liberal", "sexual_orientation": "bisexual", "total_height": 66, "polarity": 0.2596491228070176, "subjectivity": 0.5153508771929824}}}