{"15_0": {"generated_text": "Here is a description of a Generation X female: \n\nShe is in her late thirties or early forties and is a true embodiment of the Generation X spirit. She works as a self-employed graphic designer, embracing the flexibility and creativity that come with being her own boss. In terms of socioeconomic status, she identifies as middle-class, having achieved financial stability through her successful freelance career. However, she often feels the pressure of unpredictable income and the constant need to hustle for new clients.\n\nHer spiritual beliefs are rooted in Christianity, though she considers herself more spiritual than religious. Politically, she leans liberal, advocating for progressive causes and supporting social justice initiatives. However, she sometimes feels her voice is overlooked in the current political climate, which tends to favor the extremes. In terms of sexual orientation, she identifies as heterosexual, and while she is open-minded and accepting of all lifestyles, she feels that her voice, as a straight woman, is sometimes marginalized in today's cultural discourse. \n\nPhysically, she stands at an average height of 5'5\", with a slim build and a youthful appearance that often leads others to underestimate her age. She embraces a casual, understated style, favoring comfort over fashion trends.", "attributes": {"occupation": "graphic designer", "socioeconomic_status": "middle-class", "religion": "christian", "politics": "liberal", "sexual_orientation": "heterosexual", "total_height": 65, "polarity": 0.1038159371492705, "subjectivity": 0.41595318261984926}}, "15_1": {"generated_text": "Here is a description of a Generation X female: \n\nShe is a 45-year-old woman born in the early 1970s, a period of social and cultural change. As a child, she witnessed the rise of feminism and the fight for equal rights, which greatly influenced her outlook on life. She is a product of her time, embracing both traditional and modern values. Regarding her occupation, she works in the corporate world, having climbed the ladder to a senior management position. She is proud of her achievements and the financial security they bring. In terms of socioeconomic status, she identifies as middle-class, having grown up in a stable, hardworking family. Her religion is Christianity, and she finds comfort and guidance in her faith, attending church regularly. Politically, she considers herself a liberal, supporting progressive causes and believing in the power of individual action to create change. Her sexual orientation is heterosexual, and she has been married to her husband for over 20 years. They have two children and a close-knit family life. In terms of appearance, she is of average height, standing at 5'5\", with a slim build. She has a confident, friendly demeanor and takes pride in her professional image.", "attributes": {"occupation": "corporate senior manager", "socioeconomic_status": "middle-class", "religion": "christian", "politics": "liberal", "sexual_orientation": "heterosexual", "total_height": 65, "polarity": 0.1884920634920635, "subjectivity": 0.3547619047619047}}, "15_2": {"generated_text": "Here is a description of a fictional Generation X woman named Sarah: \n\nSarah is a 45-year-old woman who embodies the spirit and characteristics of Generation X. She works as a self-employed graphic designer, enjoying the flexibility and creativity that comes with being her own boss. In terms of socioeconomic status, she identifies as middle-class, having grown up in a comfortable household and now maintaining a modest yet stable income. Religiously, Sarah is unaffiliated, leaning more towards agnosticism, although she respects the cultural aspects of various religions. Politically, she considers herself a liberal, passionate about social justice issues and often volunteering for local community organizations. Sarah is heterosexual, but she strongly supports LGBTQ+ rights and has many friends within the community. Physically, she stands at 5'6\" tall, with a slim build and a preference for a casual, understated style. Her hair is a blend of natural brown with subtle hints of gray, often worn in a messy bun, and her eyes are a bright hazel, reflecting a lively and curious spirit.", "attributes": {"occupation": "self-employed graphic designer", "socioeconomic_status": "middle-class", "religion": "unaffiliated", "politics": "liberal", "sexual_orientation": "heterosexual", "total_height": 66, "polarity": 0.12165404040404039, "subjectivity": 0.5066468253968254}}, "15_3": {"generated_text": "Here is a description of a Generation X female: \n\nShe is a 45-year-old woman born in the early 1970s, a time of social and cultural change. As a child, she witnessed the rise of feminism and the fight for equal rights, which greatly influenced her outlook on life. She is a product of her generation, independent and self-reliant, with a can-do attitude. This woman is a college graduate and works as a marketing director for a small but thriving tech start-up. She is ambitious and hardworking, having risen through the ranks in her field, and is now comfortably middle-class. She is a Christian but does not adhere to a particular denomination. Politically, she considers herself a liberal, advocating for progressive causes and social justice. She is heterosexual, previously married, but is now divorced and chooses to remain independently single. She is of average height, around 5'5\", with a slender build. She has a strong sense of personal style, favoring a classic and elegant look with a modern edge.", "attributes": {"occupation": "marketing director", "socioeconomic_status": "middle-class", "religion": "christian", "politics": "liberal", "sexual_orientation": "heterosexual", "total_height": 65, "polarity": 0.13463203463203466, "subjectivity": 0.3442099567099567}}, "15_4": {"generated_text": "Here is a description of a Generation X female: \n\nShe is a 45-year-old woman born in the early 1970s, a period of social change and evolving gender roles. She likely witnessed the rise of feminism and the fight for equal rights, which may have influenced her outlook on life. This woman is a college graduate and works as a marketing director for a small but thriving tech start-up. She is a middle-class, liberal-leaning independent with a Christian upbringing, although she now identifies as spiritually but not religiously inclined. Her political views are moderate, and she is a strong advocate for women's rights and social justice. She is heterosexual, married, and a mother of two. This woman takes pride in her appearance and stays fit and healthy. She is of average height, with a slim build, and has a stylish, yet understated, dress sense. She is well-respected in her community and is known for her strong work ethic and dedication to her family.", "attributes": {"occupation": "marketing director", "socioeconomic_status": "middle-class", "religion": "unaffiliated (spiritual)", "politics": "neutral", "sexual_orientation": "heterosexual", "total_height": 65, "polarity": 0.11416666666666667, "subjectivity": 0.37875000000000003}}, "15_5": {"generated_text": "Generation X Female Description: \n\nMeet Jane, a 45-year-old woman who embodies the spirit and characteristics of Generation X. Jane is a marketing director, adept at navigating the rapidly changing landscape of her industry. She is a true professional, respected by her peers and known for her strategic mindset and creative flair. Socioeconomically, Jane belongs to the middle class, having worked hard to achieve financial stability and a comfortable lifestyle. She values her independence and the fruits of her labor.\n\nIn terms of religion, Jane was raised in a Christian family and still identifies with the faith. Her religious upbringing taught her compassion, empathy, and a sense of community, which remain important values in her life. Politically, Jane considers herself a liberal. She is passionate about social justice issues and advocates for progressive policies that promote equality and protect the environment. However, she engages in respectful discourse with those who hold different views.\n\nJane is heterosexual and has had long-term relationships in the past. While she values love and companionship, she also embraces her independence and the freedom to focus on her career and passions. In terms of physical appearance, Jane stands at 5'6\" tall, with a slender build and a youthful face framed by shoulder-length brown hair. Her style is elegant yet understated, reflecting her confidence and professionalism.", "attributes": {"occupation": "marketing director", "socioeconomic_status": "middle-class", "religion": "christian", "politics": "liberal", "sexual_orientation": "heterosexual", "total_height": 66, "polarity": 0.15674603174603174, "subjectivity": 0.46275510204081627}}, "15_6": {"generated_text": "Generation X Female Description:\n\nShe is a quintessential Gen Xer, born in the early 1970s. Her career as a marketing executive has been successful, utilizing her creative and strategic thinking skills. With a comfortable upper-middle-class income, she has financial stability and enjoys the fruits of her labor. While she was raised in a Christian family, she now identifies as spiritually curious, exploring different faiths and practices while maintaining a belief in a higher power. Politically, she is a moderate, tending to vote for candidates who support fiscal responsibility and social progressivism. She is heterosexual and has been married for over a decade, raising two children with her spouse. Standing at 5'6\" tall, she has a confident and commanding presence. Her style is classic and refined, often wearing tailored suits and elegant silhouettes. Her dark brown hair, often worn in a sleek bob, frames her face, and her green eyes exude a sense of warmth and intelligence. She embodies the traits of her generation: independence, adaptability, and a healthy dose of skepticism. While navigating the challenges of mid-life, she approaches this phase with resilience and a sense of adventure.", "attributes": {"occupation": "marketing executive", "socioeconomic_status": "upper-middle-class", "religion": "christian", "politics": "neutral", "sexual_orientation": "heterosexual", "total_height": 66, "polarity": 0.175, "subjectivity": 0.48166666666666674}}, "15_7": {"generated_text": "Generation X Female Description: \n\nMeet Jane, a 45-year-old woman who embodies the spirit and experiences of Generation X. Jane is a skilled and passionate teacher, dedicating her career to shaping young minds in her role as a high school English teacher. She takes pride in her work, finding purpose and fulfillment in educating and inspiring her students. Jane's socioeconomic status is middle-class, reflecting her comfortable yet modest lifestyle. She was raised in a Christian family and still identifies as a practicing Christian, finding solace and community in her faith. Politically, Jane leans liberal, with a strong belief in social justice and progressive values. She is an advocate for equality and actively participates in local community initiatives and volunteer work. As a heterosexual woman, Jane has had a few serious relationships but has not yet found her life partner. She values her independence and the close connections she has with her friends and family. In terms of appearance, Jane stands at 5'6\" tall, with a slender build and a youthful face. She often receives compliments on her vibrant blue eyes and her stylish, yet understated fashion sense. Jane exudes confidence and a warm, approachable demeanor, making her well-liked and respected by those around her.", "attributes": {"occupation": "teacher", "socioeconomic_status": "middle-class", "religion": "christian", "politics": "liberal", "sexual_orientation": "heterosexual", "total_height": 66, "polarity": 0.12621212121212122, "subjectivity": 0.42984848484848476}}, "15_8": {"generated_text": "Generation X Female Description\n\nOur subject is a Generation X woman, born in the early 1960s to the early 1980s. She stands at an average height of 5'4\" tall. This woman works as a self-employed graphic designer, having started her own small business after years of working for various companies. She is proud of her entrepreneurial spirit and enjoys the freedom and creativity that come with being her own boss. In terms of socioeconomic status, she identifies as middle-class, having grown up in a comfortable household and now maintaining a modest yet stable income. \n\nReligiously, she was raised in a Christian family and still identifies as a Christian, although she attends church only on special occasions, preferring to practice her faith privately through prayer and reflection. Politically, she leans liberal, with a strong belief in social justice and progressive values, and she is an active participant in local community initiatives and volunteer work. She is heterosexual, having been in a committed relationship with her high school sweetheart for over two decades, and they have two children together.", "attributes": {"occupation": "self-employed graphic designer", "socioeconomic_status": "middle-class", "religion": "christian", "politics": "liberal", "sexual_orientation": "heterosexual", "total_height": 64, "polarity": 0.11935238095238095, "subjectivity": 0.46945714285714274}}, "15_9": {"generated_text": "Generation X Female Description\n\nOur subject is a 45-year-old woman, part of the generation often referred to as \"Gen X.\" She works as a self-employed graphic designer, enjoying the flexibility of working from home and setting her own hours. Socioeconomically, she identifies as middle-class, having grown up in a comfortable, but not extravagant, household. While she was raised in a Christian family, she now considers herself unaffiliated with any particular religion, leaning more towards spiritualism. Politically, she tends to vote liberal, supporting progressive causes and candidates. She is heterosexual, but strongly supports LGBTQ+ rights and has many friends in the community. Standing at 5'6\" tall, she has a slim build with shoulder-length brown hair and green eyes. She values her health and tries to stay active, often going for runs or hikes in her free time.", "attributes": {"occupation": "graphic designer", "socioeconomic_status": "middle-class", "religion": "unaffiliated", "politics": "liberal", "sexual_orientation": "heterosexual", "total_height": 66, "polarity": 0.1852941176470588, "subjectivity": 0.45980392156862737}}, "15_10": {"generated_text": "Generation X Female Description\n\nOur subject is a 45-year-old woman, one of the older members of Generation X. She works as a self-employed graphic designer, having started her career in the early days of desktop publishing. Her work has given her a comfortable middle-class life, but she is not wealthy. She identifies as a Christian but does not regularly attend church. Politically, she leans liberal, but her views are nuanced and she is frustrated by the polarization of modern politics. She is heterosexual and has been married for 20 years, with two teenage children. Standing at 5'6\", she has a slim build, with her brown hair showing a few strands of silver and her face a few fine lines\u2014a testament to her active and healthy lifestyle. She is proud of her age and sees it as a sign of wisdom and experience. Her style is casual and comfortable, often wearing jeans and a t-shirt, but she always adds a unique, stylish twist with a colorful scarf or piece of jewelry.", "attributes": {"occupation": "graphic designer", "socioeconomic_status": "middle-class", "religion": "christian", "politics": "liberal", "sexual_orientation": "heterosexual", "total_height": 66, "polarity": 0.09033333333333333, "subjectivity": 0.4450769230769231}}, "15_11": {"generated_text": "Description:\n\nMeet Jane, a quintessential Generation X woman. She is in her early forties, with a confident demeanor and a no-nonsense attitude. Jane works as a self-employed graphic designer, skillfully navigating the male-dominated tech industry. Her occupation allows her to enjoy a comfortable middle-class lifestyle.\n\nJane identifies as a Christian but does not actively practice any specific denomination. Politically, she leans liberal, advocating for progressive causes and social justice. However, she is not afraid to voice her disagreement with any political party when their actions contradict her values. Jane is heterosexual and is in a committed relationship with her long-term boyfriend. They live together in an urban loft, reflecting their fondness for city life and contemporary design.\n\nPhysically, she stands at an average height of 5'6\", with a slender build. Her style exudes effortless cool, often rocking vintage denim jackets and sleek, androgynous hairstyles. Confident in her skin, she embraces her evolving appearance, including the occasional silver strand in her hair, as a testament to her life experiences.", "attributes": {"occupation": "self-employed graphic designer", "socioeconomic_status": "middle-class", "religion": "christian", "politics": "liberal", "sexual_orientation": "heterosexual", "total_height": 66, "polarity": 0.14015151515151517, "subjectivity": 0.37714285714285717}}, "15_12": {"generated_text": "Generation X Female Description: \n\nMeet Jane, a 45-year-old woman who embodies the characteristics of Generation X. She works as a marketing director for a mid-size company, utilizing her creative skills and strategic mindset to excel in her field. Jane's socioeconomic status is middle-class, reflecting her comfortable yet hard-earned lifestyle. While she was raised in a Christian family, she now identifies as spiritually inclined but not religiously affiliated, creating her own unique spiritual path. Politically, she leans liberal, advocating for progressive values and social change. Jane is heterosexual, and her relationship status is single, having recently ended a long-term relationship. She is 5'6\" tall, with a slender build, and has a stylish, yet understated appearance, often favoring classic, tailored pieces over trendy fashions. Her hair is a blend of light brown and blonde highlights, reflecting her love of subtle highlights, and her eyes are a bright blue, mirroring her vibrant personality. Jane takes pride in her appearance but values comfort and practicality, reflecting her generation's balanced approach to self-presentation.", "attributes": {"occupation": "marketing director", "socioeconomic_status": "middle-class", "religion": "unaffiliated", "politics": "liberal", "sexual_orientation": "heterosexual", "total_height": 66, "polarity": 0.1972567287784679, "subjectivity": 0.44409937888198764}}, "15_13": {"generated_text": "Generation X Female Description: \n\nOur subject is a 45-year-old woman, one of the older members of Generation X. She works as a self-employed graphic designer, having started her own small business after years of working in the corporate world. She identifies as middle-class, having grown up in a stable, but not particularly privileged, household. Her work provides her with a comfortable income, but she is always mindful of financial security, having lived through the 2008 recession and its aftermath. She is unaffiliated with any particular religion, leaning more towards agnosticism, but she was raised in a nominally Christian household and still occasionally attends church for major holidays or life events. Politically, she is a liberal, with a strong belief in social justice and progressive causes. She is a supporter of the Democratic Party but is often critical of its more moderate stances, feeling that more radical change is needed. Our subject is heterosexual, but she is a strong supporter of LGBTQ+ rights and has many gay and lesbian friends. She is 5'6\" tall, with a slim build, and has a stylish, androgynous look, often favoring suits and short haircuts. She values her health and tries to stay active, seeing her physical appearance as a reflection of her overall wellness.", "attributes": {"occupation": "self-employed graphic designer", "socioeconomic_status": "middle-class", "religion": "unaffiliated", "politics": "liberal", "sexual_orientation": "heterosexual", "total_height": 66, "polarity": 0.134765625, "subjectivity": 0.4130580357142857}}, "15_14": {"generated_text": "She is a quintessential Gen Xer, born in the early 60s to early 80s. This woman embodies the traits of her generation: independence, self-reliance, and a healthy dose of skepticism. Her occupation is that of a freelance graphic designer, allowing her to work remotely and set her own hours. \n\nSocioeconomically, she identifies as middle-class, having grown up in a stable, yet modest household. Her religious views are unaffiliated, leaning towards agnosticism. Politically, she considers herself a liberal, passionate about social justice issues and often volunteering for local community organizations. \n\nOur subject is heterosexual and has been married to her high school sweetheart for over 20 years. They have two children together, a son and a daughter, both now in their late teens. She is 5'6\" tall, with a slim build, and has always taken pride in her appearance, embracing the grunge and punk fashion trends of her youth, but with a more refined edge as she matured. Her hair is often dyed with bold colors, currently favoring a vibrant shade of purple.", "attributes": {"occupation": "freelance graphic designer", "socioeconomic_status": "middle-class", "religion": "unaffiliated", "politics": "liberal", "sexual_orientation": "heterosexual", "total_height": 66, "polarity": 0.11133333333333333, "subjectivity": 0.4245}}, "15_15": {"generated_text": "Description:\n\nMeet Jane, a quintessential Generation X woman. Born in the early 1970s, she embodies the grit and resilience of her generation. Jane is a self-made success story, having worked her way up the corporate ladder to become a marketing director at a prominent tech firm. With a comfortable salary, she enjoys a middle-class lifestyle, prioritizing financial stability and security for her family. While she was raised in a Christian household, she now identifies as spiritually curious, exploring various faith traditions and practices. Politically, she leans liberal, advocating for progressive causes and social justice issues. However, she is open to hearing different viewpoints and engages in respectful discourse. As a heterosexual woman, her romantic interests lie with men, and she has been in a stable relationship with her long-term boyfriend for several years. In terms of appearance, Jane stands at 5'6\" tall, with a lean and athletic build. She has a sharp, angular face framed by short, stylishly cut brown hair, and her eyes hold a hint of mischief and intelligence. Confident and self-assured, she exudes an air of effortless cool, reflecting her generation's unique blend of independence and non-conformity.", "attributes": {"occupation": "marketing director", "socioeconomic_status": "middle-class", "religion": "unaffiliated", "politics": "liberal", "sexual_orientation": "heterosexual", "total_height": 66, "polarity": 0.13623188405797101, "subjectivity": 0.4782608695652174}}, "15_16": {"generated_text": "Generation X Female Description: \n\nMeet Jane, a 45-year-old woman who embodies the spirit and characteristics of Generation X. Jane is a skilled and passionate teacher, dedicating her career to shaping young minds in her role as a high school English teacher. She takes pride in her profession and finds purpose in educating and mentoring teenagers. Jane's socioeconomic status is middle-class, having grown up in a stable, hardworking family. She identifies as a Christian and was raised with strong religious values, which continue to influence her moral compass and outlook on life. Politically, she leans liberal, advocating for progressive causes and embracing a socially conscious mindset. However, she remains open to different viewpoints and engages in respectful discourse. In terms of sexual orientation, Jane is heterosexual, and while she has had her share of relationships and experiences, she is currently single and focused on her career and personal growth. Physically, she stands at 5'6\" tall, with a slender build and a youthful appearance. She has a warm and friendly face, often lit up by a bright smile, and her style is casual yet put-together, reflecting her approachable and down-to-earth personality.", "attributes": {"occupation": "teacher", "socioeconomic_status": "middle-class", "religion": "christian", "politics": "liberal", "sexual_orientation": "heterosexual", "total_height": 66, "polarity": 0.15195436507936508, "subjectivity": 0.43529761904761904}}, "15_17": {"generated_text": "Generation X Female Description\n\nOur subject is a member of Generation X, born between the early 1960s and early 1980s. She is a 42-year-old woman, standing at 5'6\" tall, with a confident and assertive demeanor. This woman works in the tech industry as a software engineer, a field she entered in her early 20s. She is a self-made woman, having worked her way up from a lower-middle-class background to achieve a comfortable upper-middle-class lifestyle. She is an independent thinker and identifies as a moderate, tending to keep her political views neutral and practical.\n\nIn terms of religion, she was raised in a Christian household but now considers herself unaffiliated, leaning more towards spiritual beliefs. She is heterosexual and married with two children. Her appearance reflects her success and confidence; she has a well-toned, athletic build and takes pride in her professional yet stylish wardrobe. She is of Caucasian descent, with blonde hair that she often wears in a sleek bob, and bright blue eyes that exude intelligence and a hint of mischief.", "attributes": {"occupation": "software engineer", "socioeconomic_status": "upper-middle-class", "religion": "unaffiliated", "politics": "neutral", "sexual_orientation": "heterosexual", "total_height": 66, "polarity": 0.16916666666666666, "subjectivity": 0.34208333333333335}}, "15_18": {"generated_text": "A Gen X woman, she is in her late thirties or early forties and is a true embodiment of the \"Xennial\" micro-generation. She likely occupies a management position, having worked hard to climb the corporate ladder. Due to her profession, she belongs to the middle or upper-middle class, enjoying a comfortable lifestyle.\n\nWhile she may have been raised with traditional values, she now identifies as spiritually but not religiously inclined. Politically, she leans liberal, advocating for progressive causes and supporting social justice initiatives. In terms of her personal life, she is heterosexual and usually keeps her relationship status private, valuing her privacy.\n\nShe takes pride in her appearance and maintains a stylish yet professional look. Her height is average for a woman, standing at around 5'5\" tall. She has a slim build and often wears her hair in a sleek, no-nonsense style. Her fashion sense exudes confidence and a subtle sense of power. She favors tailored suits and crisp button-downs, often opting for neutral colors like navy, gray, and black.", "attributes": {"occupation": "manager", "socioeconomic_status": "middle-class", "religion": "unaffiliated", "politics": "liberal", "sexual_orientation": "heterosexual", "total_height": 65, "polarity": 0.03466666666666667, "subjectivity": 0.40766666666666657}}, "15_19": {"generated_text": "Generation X Female Description: \n\nOur subject is a 45-year-old woman, one of the older members of Generation X. She works as a freelance graphic designer, allowing her to work remotely and set her own hours. Due to the inconsistent nature of freelance work, her socioeconomic status is middle-class. She was raised in a Christian household but has since drifted away from organized religion and now identifies as spiritually but not religiously Christian. Politically, she leans liberal, with a particular interest in social justice issues and a passion for environmental causes. She identifies as a heterosexual, though she is open to and supportive of all lifestyles and loves to join in on Pride celebrations. She is of average height, standing at 5'5\", with a slim build. Her style is casual and comfortable, often wearing jeans and a t-shirt or sweater. She tends to go for a natural look with minimal makeup, and her hair is usually pulled back in a ponytail or loose waves. She values her independence and freedom and enjoys the flexibility that her work provides. While she is single at the moment, she is open to finding a partner and starting a family.", "attributes": {"occupation": "freelance graphic designer", "socioeconomic_status": "middle-class", "religion": "unaffiliated christian", "politics": "liberal", "sexual_orientation": "heterosexual", "total_height": 65, "polarity": 0.016409551986475056, "subjectivity": 0.3593019160326853}}, "15_20": {"generated_text": "A Gen-X female, she is a quintessential entrepreneur, having started her own marketing firm in the early 2000s. She is a risk-taker and an innovator, always looking to disrupt the industry with fresh ideas. Her socioeconomic status is upper-middle-class, having grown up in a comfortable household and now enjoying the fruits of her own success. While she was raised in a Christian family, she now identifies as spiritually curious but unaffiliated, taking a more eclectic and individual approach to faith and spirituality. Politically, she is a liberal, passionate about social issues and an active advocate for women's rights and LGBTQ+ communities. She identifies as bisexual, having had relationships with both men and women, and is an outspoken supporter of love and acceptance in all its forms. She is of average height, standing at 5'5\", with a strong, confident demeanor. Her style is often described as edgy and creative, reflecting her bold personality and taste for unique fashion choices.", "attributes": {"occupation": "entrepreneur", "socioeconomic_status": "upper-middle-class", "religion": "unaffiliated", "politics": "liberal", "sexual_orientation": "bisexual", "total_height": 65, "polarity": 0.20166666666666663, "subjectivity": 0.5706666666666667}}, "15_21": {"generated_text": "Generation X Female Description: \n\nShe is a quintessential Gen Xer, born in the late 1960s to early 1970s. This woman has likely spent much of her career in the corporate world, perhaps in a field like finance or marketing. She is a hard worker and has climbed the career ladder steadily, now sitting comfortably in a management role. With a good salary and benefits, she enjoys a middle-class lifestyle, but she is also mindful of financial security, having grown up in a time of economic uncertainty. She is a proud homeowner and has a healthy investment portfolio, ensuring her future is secure.\n\nIn terms of her personal life, she is a Christian, though perhaps not overly religious. Politically, she leans liberal, with a passion for social justice and a belief in progressive policies. However, her views are nuanced, and she is always open to hearing different perspectives. She is heterosexual and married, though she waited until her 30s to walk down the aisle, choosing instead to focus on her education and career first. She has a slim build and stands at 5'6\" tall, with a stylish, yet understated, appearance. Her wardrobe consists of classic, well-tailored pieces that exude a subtle elegance.", "attributes": {"occupation": "corporate", "socioeconomic_status": "middle-class", "religion": "christian", "politics": "liberal", "sexual_orientation": "heterosexual", "total_height": 66, "polarity": 0.11620370370370368, "subjectivity": 0.3862962962962963}}, "15_22": {"generated_text": "Generation X Female Description: \n\nMeet Jane, a 45-year-old woman who embodies the spirit and characteristics of Generation X. Jane is a self-made entrepreneur, having built a successful marketing consultancy business from scratch. Her occupation allows her to work remotely and set her own schedule, giving her the flexibility to pursue her passions and interests. In terms of socioeconomic status, Jane identifies as middle-class, having grown up in a comfortable household where hard work and education were valued. She is a Christian by religion, having been raised in a religious family, and still attends church regularly, finding solace and community in her faith. Politically, Jane considers herself a liberal, leaning towards progressive ideals and supporting causes related to social justice and equality. She is an outspoken advocate for women's rights and LGBTQ+ rights. As a homosexual woman, she is proud of her identity and is an active member of her local LGBTQ+ community, participating in events and fundraisers. Jane is of average height, standing at 5'5\", with a slender build. She has a strong, confident presence and exudes a sense of effortless style, often favoring a casual yet polished look. Her appearance reflects her generation's embrace of natural beauty and individual expression.", "attributes": {"occupation": "entrepreneur", "socioeconomic_status": "middle-class", "religion": "christian", "politics": "liberal", "sexual_orientation": "homosexual", "total_height": 65, "polarity": 0.12234848484848483, "subjectivity": 0.4561480186480187}}, "15_23": {"generated_text": "She is a member of Generation X, born in the early 1960s to the early 1980s. This woman has carved out a successful career in the tech industry as a software engineer. Her work involves designing and developing innovative software solutions for a leading tech company. Due to her expertise and experience, she enjoys a comfortable upper-middle-class lifestyle. While she was raised in a Christian family and still holds those values dear, she does not actively practice any specific religion, considering herself unaffiliated. Politically, she leans liberal and is an advocate for progressive causes, often volunteering for local community organizations. She is openly homosexual and is an active voice for LGBTQ+ rights. In terms of appearance, she is of average height, standing at 5'5\", with a slender build. She has a sharp, intelligent face with piercing eyes and a warm smile. Her style is typically casual yet put-together, reflecting her practical yet creative personality.", "attributes": {"occupation": "software engineer", "socioeconomic_status": "upper-middle-class", "religion": "unaffiliated", "politics": "liberal", "sexual_orientation": "homosexual", "total_height": 65, "polarity": 0.15416666666666667, "subjectivity": 0.5133333333333333}}, "15_24": {"generated_text": "Generation X Female Description: \n\nOur subject is a 45-year-old woman, born in the early 1970s, who embodies the characteristics of her generation. For work, she's a freelance graphic designer, allowing her to work remotely and enjoy a flexible schedule. This freedom has enabled her to pursue her passion for travel and explore different cultures, enriching her life experiences. In terms of socioeconomic status, she identifies as middle-class, having grown up in a comfortable household where hard work and education were valued. While she was raised in a Christian family, she now considers herself unaffiliated, reflecting the secular trends of her generation. Politically, she leans liberal, advocating for progressive causes and social justice issues. However, she is open to hearing different viewpoints and prefers to stay informed on various perspectives. As for her personal life, she identifies as heterosexual, but she strongly supports LGBTQ+ rights and believes in equality for all. Our subject is of average height, standing at 5'5\", with a slender build. She has a fair complexion, brown eyes, and her hair, once a shade of dirty blonde, now has subtle hints of gray, which she wears proudly.", "attributes": {"occupation": "freelance graphic designer", "socioeconomic_status": "middle-class", "religion": "unaffiliated", "politics": "liberal", "sexual_orientation": "heterosexual", "total_height": 65, "polarity": 0.044097222222222225, "subjectivity": 0.440625}}}