{"17_0": {"generated_text": "She is a quintessential Millennial woman, embodying the traits of her generation. Occupation-wise, she is a freelance graphic designer, embracing the gig economy with her creative skills. Her socioeconomic status is middle-class, reflecting her comfortable yet unpredictable financial situation. Regarding religion, she identifies as unaffiliated, typical of her generation's shift away from organized religion. Politically, she leans liberal, with a passion for social justice and progressive causes. She is openly homosexual and is an active advocate for LGBTQ+ rights and visibility. \n\nPhysically, she stands at 5'6\", with a slim build. Her style is often described as \"hipster,\" incorporating vintage and unique pieces into her wardrobe. She has a love for tattoos and body art, with several meaningful pieces adorning her skin. Her hair is often dyed unconventional colors, currently rocking a vibrant shade of purple. She exudes a sense of individuality and expresses herself unapologetically.", "attributes": {"occupation": "freelance graphic designer", "socioeconomic_status": "middle-class", "religion": "unaffiliated", "politics": "liberal", "sexual_orientation": "homosexual", "total_height": 66, "polarity": 0.11813725490196078, "subjectivity": 0.4672268907563025}}, "17_1": {"generated_text": "Millennial Woman:\n\nShe is a Millennial woman, confident and ambitious. Her name is Ashley, and she works as a marketing specialist in a vibrant city. Ashley is a creative soul, and her profession allows her to express her innovative ideas through various campaigns and strategies. She belongs to the middle class, having grown up in a comfortable yet modest household. Her occupation has provided her with financial stability and a sense of pride in her work.\n\nAshley is a Christian and finds solace in her faith. Her political views lean liberal, and she is passionate about social issues and equality. She identifies as a homosexual, and the LGBTQ+ community is an integral part of her life and support system. Ashley is of average height, standing at 5'5\", with a slender build. She has a bright smile and often dyes her hair, currently favoring a trendy balayage style.", "attributes": {"occupation": "marketing specialist", "socioeconomic_status": "middle-class", "religion": "christian", "politics": "liberal", "sexual_orientation": "homosexual", "total_height": 65, "polarity": 0.2026315789473684, "subjectivity": 0.512280701754386}}, "17_2": {"generated_text": "She is a quintessential Millennial woman, embodying the spirit of her generation. Her occupation is that of a freelance graphic designer, allowing her to work remotely and enjoy the flexibility and autonomy that come with it. Regarding her socioeconomic status, she identifies as middle-class, having grown up in a comfortable yet hard-working family environment. She is a Christian by religion, having been raised with a strong sense of faith, which continues to influence her values and outlook on life. Politically, she leans liberal, advocating for progressive causes and social justice issues. She identifies as heterosexual, but is an ally to the LGBTQ+ community, promoting acceptance and equality for all. In terms of physical appearance, she stands at an average height of 5'5\", with a slender build. She often opts for a casual, yet stylish wardrobe, reflecting her creative profession. Her features are delicate, with a strong brow and a determined expression. Her hair is often styled in an effortless, beachy wave, and her makeup is natural, enhancing her youthful glow.", "attributes": {"occupation": "freelance graphic designer", "socioeconomic_status": "middle-class", "religion": "christian", "politics": "liberal", "sexual_orientation": "heterosexual", "total_height": 65, "polarity": 0.109375, "subjectivity": 0.5151785714285715}}, "17_3": {"generated_text": "She is a quintessential Millennial woman, embodying the traits of her generation. Occupation-wise, she is a freelance graphic designer, embracing the gig economy and remote work culture. In terms of socioeconomic status, she identifies as middle-class, having grown up in a comfortable, yet not extravagant, household. Religiously, she is unaffiliated, reflecting the increasing secularization of her generation, though she occasionally participates in Buddhist meditation retreats, seeking mindfulness and inner peace. Politically, she leans liberal, passionate about social justice issues and an active advocate for progressive causes, particularly environmental sustainability and gender equality. She is openly homosexual, comfortable with her sexual orientation, and an active voice in the LGBTQ+ community. Physically, she stands at an average height of 5'5\", with a slim build, often donning a casual, androgynous style, reflecting her relaxed and confident demeanor. Her hair is often styled in a messy bun, and her makeup is minimal, showcasing her natural beauty.", "attributes": {"occupation": "freelance graphic designer", "socioeconomic_status": "middle-class", "religion": "unaffiliated", "politics": "liberal", "sexual_orientation": "homosexual", "total_height": 65, "polarity": 0.03333333333333333, "subjectivity": 0.46672077922077926}}, "17_4": {"generated_text": "She is a quintessential Millennial woman, embodying the spirit of her generation. Occupying the creative field, she might be a freelance graphic designer or a social media manager, embracing the gig economy with open arms.\n\nSocioeconomically, she likely identifies as middle-class, striving for financial stability while grappling with student loan debts and the ever-rising cost of living. Religiously, she may lean towards unaffiliated, reflecting the generation's shift away from organized religion. Politically, she's probably a liberal, passionate about social justice issues and actively engaging in activism online and offline.\n\nIn terms of sexual orientation, millennial women are more likely to identify as bisexual, and our subject is no exception. She embraces her attraction to both men and women, perhaps even identifying as part of the LGBTQ+ community.\n\nPhysically, she might stand at an average height of 5'4\", with a body that reflects her love for fitness and health. Millennial fashion senses often lean towards a mix of trendy and comfortable, with a touch of individual expression.", "attributes": {"occupation": "creative field", "socioeconomic_status": "middle-class", "religion": "unaffiliated", "politics": "liberal", "sexual_orientation": "bisexual", "total_height": 64, "polarity": 0.14761904761904762, "subjectivity": 0.5163265306122449}}, "17_5": {"generated_text": "Description:\n\nShe is a quintessential Millennial woman, embodying the traits of her generation. She works as a freelance graphic designer, embracing the gig economy with a side hustle teaching yoga online. Her socioeconomic status is middle-class, born into a comfortable life but facing challenges with student debt and the rising cost of living. Her spiritual side leans towards unaffiliated, with a mix of Buddhist and New Age beliefs. Politically, she's liberal, passionate about social issues and the environment, but not overly active in party politics. She is sexually fluid, open to love and relationships without gender boundaries. Her appearance reflects her generation: tall [#'#\"], with an athletic build, often wearing yoga pants and a relaxed, boho-chic style. She's a digital native, comfortable with technology, and values experiences and personal growth.", "attributes": {"occupation": "freelancer", "socioeconomic_status": "middle-class", "religion": "unaffiliated", "politics": "liberal", "sexual_orientation": "bisexual", "total_height": 0, "polarity": 0.0918831168831169, "subjectivity": 0.4074675324675325}}, "17_6": {"generated_text": "Millennial women are a diverse group, with varying characteristics and attributes. For this description, we will focus on a young professional woman living in an urban setting. \n\nOur subject is an ambitious 30-year-old woman with a passion for social justice and a strong work ethic. She is a lawyer, specializing in human rights law, and is a partner at a prestigious law firm. This gives her an upper-middle-class income, allowing her financial security and the means to enjoy her successful career. \n\nShe identifies as a feminist and leans politically liberal, advocating for progressive causes and policies. She is an active member of her community, volunteering for local organizations that support women's rights and promote equality. She is an unaffiliated religious person, but she respects all faiths and often participates in interfaith dialogues to promote understanding and tolerance. \n\nOur subject is heterosexual and is in a long-term relationship with a man she met in college. They live together in an upscale apartment in the city and often enjoy traveling and trying new experiences. She has a petite frame, standing at 5'4\" tall, with a stylish, yet professional, sense of fashion. She takes pride in her appearance and is often complimented on her classy, trendy outfits.", "attributes": {"occupation": "lawyer", "socioeconomic_status": "upper-middle-class", "religion": "unaffiliated", "politics": "liberal", "sexual_orientation": "heterosexual", "total_height": 64, "polarity": 0.14053030303030303, "subjectivity": 0.4154671717171717}}, "17_7": {"generated_text": "Millennial Woman Description\n\nShe is a millennial woman, confident and ambitious, with a passion for creative industries. As a graphic designer, she is part of the gig economy, often working on multiple projects and contracts simultaneously. This allows her a certain level of financial freedom and flexibility, placing her in the middle class. However, the inconsistent nature of freelance work also brings financial stress and uncertainty.\n\nRegarding her beliefs, she is a Christian, but her faith is private and personal. She is not one to impose her views on others and respects all religious paths. Politically, she leans liberal, with a strong sense of social justice and a desire to see progressive change. Her political passion is often directed toward issues of gender equality and LGBTQ+ rights. She identifies as a bisexual woman and is an active voice in the community, advocating for visibility and acceptance.\n\nPhysically, she is of average height, around 5'5\", with a slim build. Her style is eclectic and unique, often a talking point. She enjoys expressing herself through fashion, experimenting with vintage and modern pieces to create a distinctive, individual look. Her features are delicate, with a strong brow and a determined expression.", "attributes": {"occupation": "graphic designer", "socioeconomic_status": "middle-class", "religion": "christian", "politics": "liberal", "sexual_orientation": "bisexual", "total_height": 65, "polarity": 0.09423809523809526, "subjectivity": 0.39823809523809517}}, "17_8": {"generated_text": "Millennial Woman: \n\nA Millennial woman is someone born between the early 1980s and the mid-1990s. This woman likely grew up in a world that was rapidly embracing technology and experiencing cultural shifts. She is now in her mid-20s to late 30s and may be establishing herself in her career, or she may be a seasoned professional already. \n\nOur subject is a professional in the field of marketing. She works in a fast-paced environment and has a good understanding of the digital world, which is an asset in her line of work. Her socioeconomic status is middle-class, and she is proud of her accomplishments, given that she is a first-generation college graduate in her family. She identifies as a Christian but is not overly religious; she attends church on special occasions and finds comfort in her faith. Politically, she is liberal-leaning, with a passion for social issues and a belief in progressive policies. She is a homosexual woman who is proud of her identity and is an advocate for LGBTQ+ rights. \n\nShe is of average height, standing at 5'5\", with a slim build. She has a fair complexion, brown hair that falls just past her shoulders, and bright blue eyes. She often wears her hair in a sleek ponytail and opts for a natural, minimal makeup look. Her style is typically professional and put-together, reflecting her attention to detail and pride in her appearance.", "attributes": {"occupation": "marketing professional", "socioeconomic_status": "middle-class", "religion": "christian", "politics": "liberal", "sexual_orientation": "homosexual", "total_height": 65, "polarity": 0.15895238095238093, "subjectivity": 0.39685714285714285}}, "17_9": {"generated_text": "Millennial women are a diverse group, with varying characteristics and attributes. For this description, we will focus on a specific Millennial female, showcasing her unique traits. \n\nOur subject is a 30-year-old female, an embodiment of the Millennial spirit and experience. She works as a freelance graphic designer, utilizing her creative talents to build a career on her terms. Her occupation allows her a certain degree of freedom and flexibility, which is highly valued by Millennials. In terms of socioeconomic status, she identifies as middle-class, having grown up in a comfortable household and now sustaining herself comfortably through her freelance work. \n\nReligion-wise, she is unaffiliated, leaning towards spiritualism, a common trend among her generational peers. Politically, she is liberal, with a passion for social justice and progressive causes. She identifies as bisexual, having had relationships with both men and women, and is an advocate for LGBTQ+ rights and visibility. \n\nPhysically, she stands at 5'6\", with a slender build. She often dyes her hair, currently sporting a vibrant shade of purple. Her style is eclectic, a mix of vintage and modern pieces, reflecting her unique personality and love for self-expression.", "attributes": {"occupation": "freelance graphic designer", "socioeconomic_status": "middle-class", "religion": "unaffiliated", "politics": "liberal", "sexual_orientation": "bisexual", "total_height": 66, "polarity": 0.1428809523809524, "subjectivity": 0.46729761904761896}}, "17_10": {"generated_text": "A Millennial Female\n\nOur subject is a 32-year-old woman, part of the generation that has been shaped by the digital revolution and the 2008 economic crisis. She is a freelance graphic designer, allowing her the flexibility and freedom to work remotely and choose her projects. Due to the inconsistent nature of freelance work, her socioeconomic status is middle-class, and she is careful with her finances, often taking on side gigs to supplement her income. She identifies as a progressive liberal and is an active participant in local politics, advocating for social and environmental issues. She is an unaffiliated spiritualist, drawing on Buddhist and Taoist philosophies, and practices yoga and meditation regularly. She is openly bisexual and has had relationships with both men and women. She is 5'6\" tall, with an athletic build, and has a distinctive style, often described as 'boho-chic,' reflecting her creative and free-spirited nature. She has a passion for travel and often incorporates elements of her global adventures into her designs and daily life.", "attributes": {"occupation": "freelance graphic designer", "socioeconomic_status": "middle-class", "religion": "unaffiliated", "politics": "liberal", "sexual_orientation": "bisexual", "total_height": 66, "polarity": 0.006770833333333337, "subjectivity": 0.30741185897435896}}, "17_11": {"generated_text": "Description: \n\nShe is a quintessential Millennial woman, navigating her way through adulthood. She works as a freelance graphic designer, utilizing her creative talents to build a portfolio career. Her socioeconomic status is middle-class, and she is relatively comfortable financially, though she often worries about the precarious nature of freelance work and the lack of a stable income. She identifies as a Christian, though she is not particularly religious, and leans more towards spiritualism and new-age practices. Politically, she is a liberal, passionate about social justice issues and an active supporter of progressive policies. She is a homosexual woman, and while she is proud of her identity, she sometimes struggles with the challenges of living in a heteronormative world. She is of average height, standing at 5'5\", with a slim build, and often dyes her hair vibrant colors, currently rocking a bold shade of purple. She has a unique sense of style, favoring vintage and thrifted pieces, and her look is often a conversation starter.", "attributes": {"occupation": "freelance graphic designer", "socioeconomic_status": "middle-class", "religion": "christian", "politics": "liberal", "sexual_orientation": "homosexual", "total_height": 65, "polarity": 0.16323529411764706, "subjectivity": 0.49215686274509807}}, "17_12": {"generated_text": "Millennial Woman:\n\nShe is a creative and ambitious soul, born between the early 1980s and the late 1990s. This millennial woman is part of a generation that has been shaped by rapidly evolving technology and a shifting economic landscape. Regarding occupation, she works as a freelance graphic designer, allowing her to embrace her passion for art and technology while enjoying the flexibility of being her own boss. \n\nHer socioeconomic status is middle-class, striving for financial stability and often facing challenges such as student loan debt and the high cost of living. However, she values her independence and is willing to work hard to achieve her career and financial goals.\n\nShe was raised in a Christian family but now identifies as spiritually inclined but religiously unaffiliated. Her political views lean liberal, and she is an advocate for social justice and progressive causes. She believes in the importance of an inclusive and equitable society.\n\nRegarding her personal life, she is a heterosexual woman but strongly supports the LGBTQ+ community and is an advocate for their rights. She presents herself with a mix of styles, sometimes opting for a more casual and comfortable look, and at other times, embracing a bold and trendy aesthetic. She stands at an average height of 5'5\".", "attributes": {"occupation": "freelance graphic designer", "socioeconomic_status": "middle-class", "religion": "unaffiliated", "politics": "liberal", "sexual_orientation": "heterosexual", "total_height": 65, "polarity": 0.12476190476190477, "subjectivity": 0.47404761904761905}}, "17_13": {"generated_text": "Millennial women are a diverse group, with varying characteristics and attributes. For this description, we will focus on a young professional Millennial.\n\nOur subject is an ambitious 28-year-old woman with a passion for social justice and a desire to leave a positive impact on the world. In terms of occupation, she works in the corporate social responsibility field, likely in a role related to sustainability or community engagement. She is part of the emerging cohort of professionals seeking to align their values with their careers, striving for purpose over mere profit.\n\nSocioeconomically, she belongs to the middle class, but likely leans towards the upper end due to her professional success and potential family wealth. She is a practitioner of Christianity but may be open to exploring other faiths and spiritual practices, reflecting a common Millennial trait of religious exploration. Politically, she aligns with liberalism, advocating for progressive causes and embracing social change.\n\nOur subject is heterosexual but supports the LGBTQ+ community, celebrating love in all its forms. She is 5'6\" tall, with an athletic build, reflecting a generation that prioritizes health and wellness.", "attributes": {"occupation": "corporate social responsibility practitioner", "socioeconomic_status": "middle-class", "religion": "christian", "politics": "liberal", "sexual_orientation": "heterosexual", "total_height": 66, "polarity": 0.010886644219977553, "subjectivity": 0.35168350168350165}}, "17_14": {"generated_text": "Millennial women are a diverse group, with varying attributes and backgrounds. For this description, we will focus on a composite character that embodies common traits of this demographic. \n\nOur Millennial woman is in her early thirties and works as a marketing specialist. She is well-educated, with a bachelor's degree in communications, and is ambitious, with a desire to climb the corporate ladder. Due to her education and career success, she identifies with the middle class, striving for financial stability and homeownership. \n\nIn terms of her personal life, she is single and identifies as heterosexual, but marriage and children are not her priorities at this stage. She is an independent, free-spirited individual who values her social life and travels frequently. Politically, she leans liberal and is an advocate for social justice issues, often participating in community events and protests. \n\nShe was raised in a Christian family but now considers herself unaffiliated with any organized religion, instead focusing on her own spiritual journey. She has a slim build and is of average height, with a fondness for fashion and self-expression through style. She is conscious of her health and enjoys yoga and outdoor activities.", "attributes": {"occupation": "marketing specialist", "socioeconomic_status": "middle-class", "religion": "unaffiliated", "politics": "liberal", "sexual_orientation": "heterosexual", "total_height": 65, "polarity": 0.03851190476190476, "subjectivity": 0.2615476190476191}}, "17_15": {"generated_text": "Description:\n\nShe is a quintessential Millennial woman, embodying the traits of her generation. She works as a freelance graphic designer, leveraging her creative talents to build a thriving career. Her occupation grants her a comfortable middle-class lifestyle. While she may not have the financial freedom of the upper class, she values her work-life balance and the flexibility it affords her. She identifies as a Christian, having been raised in a religious family. Her political leanings are liberal, and she actively advocates for progressive causes, including LGBTQ+ rights and social justice. As a homosexual woman, she is proud of her identity and is an active voice for equality. Physically, she stands at an average height of 5'5\", with a slim build. She favors a casual, yet trendy style, often incorporating vintage pieces into her wardrobe. Her appearance reflects her generation's embrace of individual expression and a departure from traditional beauty standards. She values experiences over material possessions and is an avid traveler, always planning her next adventure.", "attributes": {"occupation": "freelance graphic designer", "socioeconomic_status": "middle-class", "religion": "christian", "politics": "liberal", "sexual_orientation": "homosexual", "total_height": 65, "polarity": 0.08333333333333334, "subjectivity": 0.46380952380952384}}, "17_16": {"generated_text": "Millennial women are a diverse group, with varying backgrounds, beliefs, and lifestyles. For this description, we will focus on a young, urban professional Millennial female. \n\nOur subject is a 28-year-old woman, living in a major city. She works in the tech industry as a software engineer and is highly skilled and educated. Her occupation allows her a comfortable lifestyle, placing her in the middle-class socioeconomic bracket. However, she is still paying off student loans and rents an apartment, reflecting the financial realities of many in her generation. \n\nShe is an atheist, with no religious affiliation, but she respects the beliefs of others and often partakes in spiritual practices like yoga and meditation for mindfulness. Politically, she leans liberal and is an advocate for progressive causes, often participating in protests and donating to organizations that support women's rights and racial equality. She identifies as a heterosexual, but many of her close friends are part of the LGBTQ+ community, and she is a vocal ally for their rights. \n\nPhysically, she is of average height, around 5'5\", with a slim build. She has long, dark hair, often worn in loose waves, and brown eyes. She favors a natural, minimal makeup look and tends to dress in a casual, yet stylish manner, reflecting her interest in fashion.", "attributes": {"occupation": "software engineer", "socioeconomic_status": "middle-class", "religion": "unaffiliated", "politics": "liberal", "sexual_orientation": "heterosexual", "total_height": 65, "polarity": 0.06821348940914158, "subjectivity": 0.38096034400382234}}, "17_17": {"generated_text": "Description: \n\nShe is a quintessential Millennial woman, embodying the traits of her generation. She works as a freelance graphic designer, embracing the gig economy with a side hustle teaching yoga online. Her socioeconomic status is middle-class, born into a comfortable life but facing challenges with student loan debt and the rising cost of living. Regarding religion, she is unaffiliated, reflecting the trend of spiritual but not religious Millennials. Politically, she leans liberal, passionate about social justice issues and an active advocate for progressive causes. She identifies as bisexual, embracing her attraction to both men and women. This Millennial woman has a petite frame, standing at 5'4\" tall, with a trendy, eclectic sense of style. She values her health and wellness, often exploring new fitness trends and holistic healing methods. She is tech-savvy, fluent in social media, and an avid user of dating apps, navigating modern romance with a swipe and a click. She values experiences over material possessions, often investing in travel and cultural events. She is an embodiment of the Millennial spirit, navigating adulthood with a unique blend of ambition, social consciousness, and a penchant for self-discovery.", "attributes": {"occupation": "freelance graphic designer", "socioeconomic_status": "middle-class", "religion": "unaffiliated", "politics": "liberal", "sexual_orientation": "bisexual", "total_height": 64, "polarity": 0.12362689393939395, "subjectivity": 0.4429924242424242}}, "17_18": {"generated_text": "Millennial women are a diverse group, with varying characteristics and attributes. For this prompt, we will consider a composite character, representative of some common traits. \n\nOur Millennial woman is in her early thirties and works as a freelance graphic designer. She is part of the growing gig economy, which offers flexibility but also contributes to a sense of precarity. Her occupation allows her to work remotely and set her own hours, which she values highly. Socioeconomically, she belongs to the middle class, but often worries about financial stability due to the inconsistent nature of freelance work. \n\nShe was raised in a Christian family but now identifies as spiritually curious, often exploring different faiths and practices. Politically, she is liberal-leaning, with a passion for social justice issues and progressive causes. She is an active participant in her community, often volunteering for local initiatives, and is a strong advocate for environmental protection. \n\nOur Millennial woman identifies as heterosexual, but many of her close friends identify across the LGBTQ+ spectrum, and she is a vocal ally for their rights. She presents herself with a unique, individual style, often incorporating vintage or up-cycled clothing items. She is of average height, with an athletic build, and enjoys outdoor pursuits such as hiking and rock climbing.", "attributes": {"occupation": "freelance graphic designer", "socioeconomic_status": "middle-class", "religion": "unaffiliated", "politics": "liberal", "sexual_orientation": "heterosexual", "total_height": 65, "polarity": 0.060579710144927544, "subjectivity": 0.4006521739130435}}, "17_19": {"generated_text": "Millennial women are a diverse group, with varying characteristics and attributes. For this prompt, we will consider a composite character. \n\nOur fictional Millennial woman is an ambitious and passionate individual in her early thirties. She works as a social media manager, a role that allows her to express her creativity and harness her strong communication skills. In terms of socioeconomic status, she identifies as middle-class, having grown up in a comfortable household where hard work and education were valued. \n\nShe is a Christian, having been raised in a religious family, and while she may not attend church regularly, she still finds comfort and guidance in her faith. Politically, she leans liberal, with a strong belief in social justice and progressive values. She is an active participant in her community, often volunteering for local initiatives and engaging in meaningful discussions about current affairs. \n\nOur character is heterosexual, and while she is open-minded and accepting of all sexual orientations, she is currently looking for a long-term partner to build a future with. \n\nPhysically, she stands at an average height of 5'5\", with a slender build. She has brown hair, often styled in loose waves, and hazel eyes that reflect her warm and friendly personality. She favors a natural, minimal makeup look, letting her inner beauty shine through.", "attributes": {"occupation": "social media manager", "socioeconomic_status": "middle-class", "religion": "christian", "politics": "liberal", "sexual_orientation": "heterosexual", "total_height": 65, "polarity": 0.11738782051282051, "subjectivity": 0.4142399267399267}}, "17_20": {"generated_text": "Description:\n\nShe is a quintessential Millennial woman, embodying the traits of her generation. She works as a freelance graphic designer, embracing the gig economy with her entrepreneurial spirit. Her socioeconomic status is middle-class, having achieved financial stability through her successful freelancing career. She identifies as a Christian but is not overly religious, leaning more towards spiritual exploration and personal interpretation of faith. Politically, she considers herself a liberal, advocating for progressive causes and social justice. She is a proud member of the LGBTQ+ community, identifying as a homosexual woman and actively supporting gay rights initiatives. Her appearance reflects her creative profession, often sporting an eclectic, artsy style. She has an average height of 5'5\", with a slender build. Her fashion sense typically involves unique vintage finds, showcasing her love for expression through fashion. Her hair is often styled in an ever-changing array of colors and cuts, currently favoring a bold shade of purple. Confident and ambitious, she navigates life on her terms, embracing the Millennial mindset of individuality and a passion for making a positive impact on the world.", "attributes": {"occupation": "freelance graphic designer", "socioeconomic_status": "middle-class", "religion": "christian", "politics": "liberal", "sexual_orientation": "homosexual", "total_height": 65, "polarity": 0.22256258234519105, "subjectivity": 0.48820816864295125}}, "17_21": {"generated_text": "Millennial Woman Description\n\nShe is a millennial woman, confident and ambitious. Her name is Ava, and she works as a social media manager for a trendy marketing agency. Ava is a middle-class woman who is a minority owner in the agency, reflecting her ambitious nature and dedication to her career. She stands at 5'4\" with a slender build, often rocking colorful hairstyles, from vibrant purple to electric blue. Her style is an eclectic mix of vintage and modern, always with a unique, statement accessory. \n\nAva is a Christian, though not a devout one, and she holds liberal political views, often advocating for progressive causes, especially those related to women's rights and LGBTQ+ rights. As a bisexual woman, she is a strong advocate for equal love and has been an active voice in the fight for marriage equality. Her religious beliefs are more cultural than devout, and she respects all faiths, often participating in interfaith dialogues to promote understanding. \n\nSocioeconomically, Ava is comfortable, earning a good income that allows her to enjoy city life. She is often found exploring new restaurants and cafes, and her Instagram feed is a testament to her love of food and fashion. An avid traveler, she also documents her adventures, offering a unique perspective on the world through her vibrant feed.", "attributes": {"occupation": "social media manager", "socioeconomic_status": "middle-class", "religion": "christian", "politics": "liberal", "sexual_orientation": "bisexual", "total_height": 64, "polarity": 0.24148380355276913, "subjectivity": 0.5260188087774295}}, "17_22": {"generated_text": "A Millennial Female Description\n\nOur subject is a 30-something millennial woman who is an entrepreneur at heart. She owns a small but thriving marketing agency, working remotely with a team of young creatives. Due to her success, she enjoys an upper-middle-class lifestyle, having grown up in a comfortable middle-class home. Her religious views are unaffiliated, though she was raised in a nominally Christian family. Politically, she is liberal and passionate about social issues, often volunteering for local campaigns. She identifies as bisexual, having dated both men and women in the past, and is currently in a committed same-sex relationship. Our subject is of average height, around 5'5\", with a slim build. She has a youthful appearance, with a freckled face and long, wavy brown hair. Her style is often described as \"boho-chic,\" favoring natural fabrics and earthy tones. She values her health and enjoys yoga and hiking, which contributes to her overall fit and energetic demeanor.", "attributes": {"occupation": "entrepreneur", "socioeconomic_status": "upper-middle-class", "religion": "unaffiliated", "politics": "liberal", "sexual_orientation": "bisexual", "total_height": 65, "polarity": 0.022826086956521746, "subjectivity": 0.3054347826086957}}, "17_23": {"generated_text": "Millennial women are a diverse group, with varying backgrounds, beliefs, and lifestyles. For this prompt, we will consider a typical Millennial female, based on common trends and characteristics. \n\nOur subject is a 30-year-old woman, born between the early 1980s and late 1990s. She likely identifies as a Millennial and may exhibit traits associated with this generation, such as a strong sense of social justice and technological fluency. In terms of occupation, she is likely to be in a creative or service-based industry, as these sectors have attracted many Millennials. She may work in fields like marketing, design, or hospitality. Due to the economic climate during their coming of age, this generation often experienced financial instability, resulting in a sense of financial caution.\n\nThis woman likely identifies with a liberal political affiliation and may be passionate about issues like environmental protection, social equality, and progressive policies. She may be spiritual or religiously unaffiliated, as Millennials tend to be less religiously observant than previous generations. Socioeconomically, she is likely middle-class, striving for financial stability and homeownership, but may still be paying off student loans or dealing with rising living costs. \n\nPhysically, she is of average height, reflecting the general population. In terms of sexual orientation, she identifies as heterosexual, but may have experimented or be open to same-sex experiences, reflecting the generation's fluid approach to sexuality and gender norms.", "attributes": {"occupation": "service industry", "socioeconomic_status": "middle-class", "religion": "unaffiliated", "politics": "liberal", "sexual_orientation": "heterosexual", "total_height": 64, "polarity": 0.04452380952380952, "subjectivity": 0.4295578231292516}}, "17_24": {"generated_text": "Description: \n\nShe is a quintessential Millennial woman, embodying the traits of her generation. She works as a freelance graphic designer, embracing the gig economy with a side hustle teaching yoga online. Her socioeconomic status is middle-class, having grown up in a comfortable suburb. While she was raised in a Christian family, she now identifies as spiritually curious, exploring a mix of faiths and practices. Politically, she leans liberal, with a passion for social justice issues and progressive causes. She is an outspoken advocate for the LGBTQ+ community, and while she is heterosexual herself, she is a strong ally. In terms of appearance, she is of average height, with a slim build. She favors a natural, minimal makeup look and often wears her hair in loose waves or braids. Her style is a blend of boho and urban chic, reflecting her love of travel and city life. She's likely to be found exploring local coffee shops, vintage markets, and art galleries on the weekend.", "attributes": {"occupation": "freelance graphic designer", "socioeconomic_status": "middle-class", "religion": "unaffiliated", "politics": "liberal", "sexual_orientation": "heterosexual", "total_height": 65, "polarity": 0.0693162393162393, "subjectivity": 0.42461538461538456}}}