{"16_0": {"generated_text": "Millennial Man Description\n\nHe is a 32-year-old man, born in the early 1990s, which places him firmly in the Millennial generation. In terms of his career, he works as a freelance graphic designer and runs his own small business, catering to a variety of clients. Due to the nature of his work, he is mostly location-independent and enjoys the freedom to work remotely and set his own hours. Socioeconomically, this puts him in the middle class. His religious views are that of a Christian, though he is not overly devout and tends to lean more towards spiritual beliefs, incorporating aspects of other faiths as well. Politically, he identifies as a liberal, with a strong belief in social justice and progressive values. However, he is not overly active in politics and tends to keep his beliefs to himself unless prompted. Regarding his personal life, he is a homosexual male, though one might not assume this from his appearance or mannerisms, as he does not conform to stereotypes. Physically, he stands at an average height of 5'10\", with a slim build and a casual, unassuming style. He tends to dress practically and comfortably, often in jeans and a t-shirt, and sports a short, well-kept beard.", "attributes": {"occupation": "freelance graphic designer", "socioeconomic_status": "middle-class", "religion": "christian", "politics": "liberal", "sexual_orientation": "homosexual", "total_height": 70, "polarity": 0.0608974358974359, "subjectivity": 0.393956043956044}}, "16_1": {"generated_text": "A Millennial Male:\n\nHe is a quintessential millennial man, embracing the changes and challenges of the modern world. He works as a freelance graphic designer, utilizing his creative talents to craft visual stories for a variety of clients. His occupation allows him the freedom to work remotely and set his own hours, a perk he greatly values. Socioeconomically, he identifies as middle-class, striving for financial stability and the occasional indulgence.\n\nWhile he was raised in a Christian household, he now considers himself spiritually curious but unaffiliated, open to exploring different faiths and beliefs. Politically, he leans liberal, advocating for progressive causes and social justice issues. However, he engages in respectful discourse with those who hold differing views. In terms of sexual orientation, he identifies as heterosexual, but he is an ally to the LGBTQ+ community, promoting acceptance and love for all.\n\nPhysically, he stands at an average height of 5'10\", with a slim build and a penchant for unique fashion choices. He often sports a well-maintained beard, adding a touch of ruggedness to his otherwise youthful appearance. His style could be described as urban chic, blending streetwear with a hint of sophistication. He takes pride in his appearance, seeing it as a form of self-expression.", "attributes": {"occupation": "freelance graphic designer", "socioeconomic_status": "middle-class", "religion": "unaffiliated", "politics": "liberal", "sexual_orientation": "heterosexual", "total_height": 70, "polarity": 0.15905797101449276, "subjectivity": 0.426863354037267}}, "16_2": {"generated_text": "Millennial Man Description\n\nHe is a Millennial man, aged 28, with a passionate and driven spirit. This man works in the heart of the city as a financial analyst, utilizing his sharp mind to navigate the complex world of investments and stocks. His occupation demands precision and an analytical mindset, which suits his detail-oriented personality. His socioeconomic status is middle-class, striving to climb the corporate ladder and secure a comfortable future.\n\nWhile he was raised in a Christian family, he now identifies as spiritually inclined but not religiously affiliated, creating his own unique path. Politically, he leans liberal, advocating for progressive ideals and social change. He is an outspoken supporter of LGBTQ+ rights, and he himself identifies as homosexual, comfortable and confident in his sexual orientation.\n\nHe has a slim build and stands at an average height of 5'10\", with a gentle face and a friendly smile. He takes pride in his appearance, sporting a well-maintained beard and a trendy hairstyle. His fashion sense leans towards a mix of classic and modern styles, often incorporating a touch of his favorite colors, deep blues, and grays.", "attributes": {"occupation": "financial analyst", "socioeconomic_status": "middle-class", "religion": "unaffiliated", "politics": "liberal", "sexual_orientation": "homosexual", "total_height": 70, "polarity": 0.1723214285714286, "subjectivity": 0.48244047619047625}}, "16_3": {"generated_text": "A typical Millennial male could be described as someone who is in his late twenties or early thirties. Regarding his occupation, he may be working in a variety of fields, but let's say he is a freelance graphic designer. He is likely to be middle-class, striving for financial stability and possibly burdened by student loan debt. \n\nIn terms of religion, he may identify as unaffiliated, as many Millennials do, but he may also follow a spiritual path or practice a religion such as Buddhism, which offers a sense of calm and mindfulness in an increasingly stressful world. Politically, he is probably liberal, with a passion for social justice and progressive causes, and he may be an active participant in online political discourse. \n\nThis Millennial man is likely to be heterosexual, but as sexual orientation is a spectrum, he may also identify as bisexual or be open to same-sex experiences. Physically, he is of average height, say 5'10\", with a slim build, and he probably takes care of his appearance, sporting a well-groomed beard or a stylish haircut.", "attributes": {"occupation": "freelance graphic designer", "socioeconomic_status": "middle-class", "religion": "unaffiliated", "politics": "liberal", "sexual_orientation": "bisexual", "total_height": 70, "polarity": 0.05833333333333333, "subjectivity": 0.47196969696969693}}, "16_4": {"generated_text": "Millennial Man Description\n\nHe is a 32-year-old Millennial man, born in the early 1990s. He works as a freelance graphic designer and owns a small creative agency with a few employees. Due to the nature of his work, he is able to work remotely and often travels to different cities, embracing the digital nomad lifestyle. His socioeconomic status is upper-middle-class, as he earns a comfortable living through his successful business ventures.\n\nRegarding his personal life, he identifies as spiritual but not religious, leaning towards agnostic beliefs. Politically, he is liberal-minded and passionate about social justice issues, often engaging in discussions about current affairs and progressive policies. He is an outspoken advocate for the LGBTQ+ community and proudly identifies as homosexual himself, actively participating in local pride events and initiatives.\n\nHe has a slim build and stands at an average height of 5'10\". He takes pride in his appearance and has a trendy, well-groomed beard and hairstyle. His fashion sense could be described as urban and casual, often incorporating streetwear brands into his wardrobe.", "attributes": {"occupation": "freelance graphic designer, business owner", "socioeconomic_status": "upper-middle-class", "religion": "unaffiliated", "politics": "liberal", "sexual_orientation": "homosexual", "total_height": 70, "polarity": 0.0953703703703704, "subjectivity": 0.4561728395061728}}, "16_5": {"generated_text": "Millennial males, born between the early 1980s and the late 1990s, exhibit a diverse range of characteristics. This individual, we'll call him Adam, embodies the spirit of his generation. Adam is a 30-year-old entrepreneur, having started his own tech company that develops innovative apps and software solutions.\n\nAdam's socioeconomic status is upper-middle-class, benefiting from his successful career and savvy investments. He identifies as a Christian but is not overly religious, leaning more towards spiritual beliefs and a general sense of openness. Politically, he is liberal, advocating for progressive causes and supporting social justice initiatives.\n\nIn terms of sexual orientation, Adam is heterosexual, but he strongly supports LGBTQ+ rights and believes in equality for all. He is 6'1\" tall, with a slim build, reflecting his active lifestyle and passion for outdoor adventures like hiking and rock climbing.", "attributes": {"occupation": "entrepreneur", "socioeconomic_status": "upper-middle-class", "religion": "christian", "politics": "liberal", "sexual_orientation": "heterosexual", "total_height": 73, "polarity": 0.19313725490196076, "subjectivity": 0.48333333333333334}}, "16_6": {"generated_text": "Millennial men, born between 1981 and 1996, exhibit a diverse range of characteristics. Our subject is a millennial man who falls within the typical traits of his generation. He is likely to be in his early thirties, and his occupation reflects the trend towards professional services; he is an experienced marketing specialist.\n\nThis thirty-something man likely identifies as a millennial with a strong work ethic and a desire for career advancement. He is probably a middle-class professional, reflecting the socioeconomic status of many in his generation. While his religious beliefs may vary, there is a higher likelihood that he is unaffiliated with any organized religion, a trend among millennials. Politically, he may lean liberal, but again, this is not a definitive trait as political affiliations vary.\n\nIn terms of sexual orientation, millennial men are more likely to identify as heterosexual, and our subject is no exception. Physically, he is likely to be of average height, standing at 5'9\", with a slim to average build. This description captures the typical traits of a millennial man, though it is important to remember that each person is unique and may not conform to all the attributes described.", "attributes": {"occupation": "marketing specialist", "socioeconomic_status": "middle-class", "religion": "unaffiliated", "politics": "liberal", "sexual_orientation": "heterosexual", "total_height": 69, "polarity": 0.12881944444444446, "subjectivity": 0.5576388888888889}}, "16_7": {"generated_text": "Millennial males, often characterized as ambitious and well-educated, are known for their tech-savvy and progressive mindset. This particular Millennial is a prime example of his generation, exhibiting a blend of old and new values.\n\nHe works in the heart of the city as a financial analyst, adept at navigating the complex world of numbers and trends. His occupation demands precision and an analytical mind, which suits his meticulous nature. With a comfortable salary, he enjoys a middle-class lifestyle, having worked hard to achieve financial stability.\n\nRegarding his personal beliefs, he identifies as a Christian, although he is not overly religious. His political leanings are liberal, and he is passionate about social issues, often engaging in debates about current affairs. As a heterosexual male, his social circle is diverse, and he values the varying perspectives his friends bring.\n\nPhysically, he stands at an average height of 5'10\", with a slim build, reflecting his active lifestyle. He favors a casual style, often sporting jeans and a t-shirt, and is rarely seen without his retro-style glasses, which give him a distinctive, intellectual look.", "attributes": {"occupation": "financial analyst", "socioeconomic_status": "middle-class", "religion": "christian", "politics": "liberal", "sexual_orientation": "heterosexual", "total_height": 70, "polarity": 0.04979603729603731, "subjectivity": 0.40470779220779224}}, "16_8": {"generated_text": "Millennial males, born between 1981 and 1996, are a diverse group, but we will focus on one individual to exemplify some of their common traits. \n\nOur example Millennial is a 32-year-old man, living in an urban area. He is likely to be employed in a professional or technical field, utilizing his strong tech skills and adaptability. \n\nThis man is from a middle-class family and is a hard worker, striving to climb the socioeconomic ladder and achieve financial stability and comfort. He is a Christian, and while he may not attend church regularly, he values his faith and its role in his life. Politically, he leans liberal, with a strong belief in social justice and progressive values. However, he is open to hearing different viewpoints and prefers to stay informed and make decisions based on facts. \n\nIn terms of his personal life, he identifies as heterosexual and is in a committed relationship with a long-term girlfriend. He is of average height, standing at 5'10\", with a slim build, and takes pride in his appearance, following fashion trends and staying groomed.", "attributes": {"occupation": "professional", "socioeconomic_status": "middle-class", "religion": "christian", "politics": "liberal", "sexual_orientation": "heterosexual", "total_height": 70, "polarity": 0.013596491228070167, "subjectivity": 0.3290485829959514}}, "16_9": {"generated_text": "Millennial males, born between the early 1980s and the late 1990s, exhibit a diverse range of characteristics. This individual is likely to be in his late twenties or thirties, and presents as a hardworking and ambitious professional.\n\nHe is likely to be employed in a creative or tech-related field, such as marketing, design, or software development. Regarding socioeconomic status, he is likely middle-class, striving to achieve financial stability and possibly dealing with student loan debt or the challenges of urban living.\n\nReligion-wise, he may identify as unaffiliated, a common trait among his generation, but he could also practice a religion like Christianity or Buddhism. Politically, he leans liberal, with a passion for social issues and a belief in progressive values.\n\nIn terms of sexual orientation, he identifies as heterosexual, and is likely to be in a committed relationship or actively dating. Physically, he stands at an average height of 5'10\", with a slim build, and favors a casual, yet stylish dress sense. He is likely to be health-conscious and may enjoy outdoor activities like hiking or cycling.", "attributes": {"occupation": "creative/tech professional", "socioeconomic_status": "middle-class", "religion": "unaffiliated", "politics": "liberal", "sexual_orientation": "heterosexual", "total_height": 70, "polarity": 0.026923076923076918, "subjectivity": 0.5869047619047619}}, "16_10": {"generated_text": "Millennial men, born between 1981 and 1996, embody a diverse and dynamic cohort. This individual, let's call him Jake, represents a typical member of this generation.\n\nJake, aged 30, works in the heart of the city as a freelance graphic designer. He's forged a successful career, leveraging his creative talents to establish a comfortable lifestyle. His occupation allows him remote work and flexible hours, which he utilizes to pursue passion projects and travel extensively.\n\nSocioeconomic Status: Upper-middle-class\nReligion: Unaffiliated\nPolitical Affiliation: Liberal\nSexual Orientation: Heterosexual\n\nJake identifies as a socioeconomic upper-middle-class, secular liberal, and is heterosexual. While his spiritual path differs from traditional organized religion, he maintains a strong sense of morality and social responsibility.\n\nPhysically, Jake stands at an average height of 5'10\", with a slim build. He favors a casual, laid-back style, often sporting a well-maintained beard and a trendy haircut. His appearance reflects his generation's blend of nonchalance and attention to detail.", "attributes": {"occupation": "freelance graphic designer", "socioeconomic_status": "upper-middle-class", "religion": "unaffiliated", "politics": "liberal", "sexual_orientation": "heterosexual", "total_height": 70, "polarity": 0.10999999999999999, "subjectivity": 0.5038095238095238}}, "16_11": {"generated_text": "Millennial males, often characterized as the generation of digital natives and social change, exhibit diverse traits and characteristics. This individual, a Millennial man, showcases a blend of contemporary traits and aspirations.\n\nHe works in the heart of the city as a financial analyst, navigating the intricate world of investments and markets. His occupation demands a keen understanding of global economic trends and a penchant for numbers. This young man falls into the upper-middle-class bracket, having climbed the socioeconomic ladder through a combination of hard work and educational attainment.\n\nUnaffiliated with any particular religion, he identifies as spiritually curious, open to exploring diverse faiths and their impact on humanity. Politically, he leans liberal, advocating for progressive causes and embracing social change. He is a heterosexual male, comfortable and confident in his sexual orientation, and embraces a diverse circle of friends and acquaintances.\n\nIn terms of appearance, he stands at an average height of 5'10\", with a slender build. He often sports a hipster-esque beard, meticulously groomed, and pairs it with trendy glasses, reflecting his attention to detail and desire to stay fashionable.", "attributes": {"occupation": "financial analyst", "socioeconomic_status": "upper-middle-class", "religion": "unaffiliated", "politics": "liberal", "sexual_orientation": "heterosexual", "total_height": 70, "polarity": 0.11468253968253969, "subjectivity": 0.3757936507936508}}, "16_12": {"generated_text": "Millennial men, born between 1981 and 1996, exhibit a diverse range of characteristics. This individual is a 30-year-old man, standing at an average height of 5'10\". He works in the heart of the city as a financial analyst, donning a crisp suit and exuding an air of confidence and ambition. His occupation reflects his upper-middle-class status, affording him a comfortable lifestyle.\n\nWhile he was raised in a Christian family, he now identifies as spiritually curious, exploring various faith traditions and philosophical ideas. Politically, he leans liberal, advocating for progressive causes and social justice. However, he approaches each issue with an open mind, considering multiple perspectives before forming an opinion.\n\nIn terms of his personal life, he is a proud member of the LGBTQ+ community, identifying as gay. He is outspoken about equality and actively participates in pride parades and other community events. His sexual orientation is an integral part of his identity, and he embraces it with confidence and pride.", "attributes": {"occupation": "financial analyst", "socioeconomic_status": "upper-middle-class", "religion": "unaffiliated", "politics": "liberal", "sexual_orientation": "homosexual", "total_height": 70, "polarity": 0.09956140350877193, "subjectivity": 0.41447368421052627}}, "16_13": {"generated_text": "Millennial males, born between the early 1980s and the late 1990s, exhibit a diverse range of characteristics. This individual, let's call him Adam, embodies certain traits representative of his generation. \n\nAdam, a 32-year-old Millennial, works in the heart of the city as a financial analyst. He is diligent and ambitious, striving to climb the corporate ladder. Adam's socioeconomic status is middle-class, which allows him a comfortable lifestyle. He identifies as a Christian, having been raised in a religious family, although he now attends church only on special occasions. Politically, he leans liberal, with a strong belief in social justice and progressive values. Adam is heterosexual, currently in a long-term relationship with his high-school sweetheart, and plans to propose soon. In terms of physical appearance, Adam stands at 5'11\" with a slim build. He has short brown hair, often styled in a neat, side-parted fashion, and sports a well-maintained beard. He favors a casual yet fashionable style, often seen in jeans and a button-down shirt.", "attributes": {"occupation": "financial analyst", "socioeconomic_status": "middle-class", "religion": "christian", "politics": "liberal", "sexual_orientation": "heterosexual", "total_height": 71, "polarity": 0.05200501253132833, "subjectivity": 0.4132832080200501}}, "16_14": {"generated_text": "Millennial males, born between the early 1980s and the late 1990s, exhibit a diverse range of characteristics. Regarding occupation, they often embrace entrepreneurial pursuits or seek employment in thriving sectors like technology, media, or finance. This tends to place them in the middle or upper-middle class economically. While their religious beliefs vary, with some identifying as Christians, Muslims, or Jews, a significant portion of this demographic is unaffiliated with any particular religion. In terms of political leanings, they may identify as liberals or conservatives, with a notable number also falling into the neutral category. When it comes to sexual orientation, they are most likely to identify as heterosexual, with a substantial number also identifying as homosexual or bisexual.\n\nPhysically, the Millennial male typically stands at an average height, reflecting the general population's typical height distribution. They are known for their fashion sense, often sporting casual attire with a hint of sophistication. Their hairstyles vary, from short and neat to more experimental cuts and colors. Overall, the Millennial male presents a multifaceted persona, shaped by their unique experiences and perspectives, navigating the complexities of adulthood in a rapidly changing world.", "attributes": {"occupation": "entrepreneur or professional", "socioeconomic_status": "middle-class", "religion": "unaffiliated", "politics": "neutral", "sexual_orientation": "bisexual", "total_height": 70, "polarity": 0.08733333333333332, "subjectivity": 0.46004761904761904}}, "16_15": {"generated_text": "Millennial males, born between the early 1980s and the late 1990s, exhibit a diverse range of characteristics. This individual is in his early 30s, with a lean build and a casual dress sense. He works in the heart of the city as a financial analyst, a demanding yet rewarding career.\n\nSocioeconomically, he belongs to the middle class, striving for financial stability and homeownership. While he was raised in a Christian family, he now identifies as spiritually curious, exploring various faith traditions and philosophical beliefs. Politically, he leans liberal, advocating for progressive causes and social justice issues.\n\nIn terms of political affiliation, he identifies as a liberal, passionate about issues like environmental protection and social equality. However, he is less engaged in the traditional party politics landscape. His sexual orientation is heterosexual, and he is in a committed relationship with a long-term partner. They live together and are planning their future, hoping to one day start a family.", "attributes": {"occupation": "financial analyst", "socioeconomic_status": "middle-class", "religion": "spiritually curious", "politics": "liberal", "sexual_orientation": "heterosexual", "total_height": 71, "polarity": 0.01245059288537549, "subjectivity": 0.36630434782608684}}, "16_16": {"generated_text": "Millennial men are a diverse group, with varying characteristics and backgrounds. For this description, we will focus on an individual named Alex, a typical representative of this generation.\n\nAlex is a 32-year-old man living in an urban area. He works in the heart of the city as a marketing specialist, a job that he landed after graduating from college with a degree in communications. Alex is diligent and ambitious, and he is currently working towards a promotion to senior management. His socioeconomic status is middle-class, which allows him to live comfortably and indulge in occasional luxuries, such as international travel.\n\nIn terms of his personal life, Alex is in a committed relationship with his long-term boyfriend, whom he met during his sophomore year of college. While they have discussed the possibility of marriage, they are both focused on advancing their careers at the moment.\n\nAlex was raised in a Christian household, but he now identifies as agnostic. Politically, he considers himself a liberal and is passionate about social issues, often participating in protests and advocating for progressive causes.\n\nAppearance-wise, Alex is of average height, standing at 5'10\", with a slim build. He has short brown hair, often styled in a neat side part, and brown eyes. He favors a casual style, typically wearing jeans and a button-down shirt.", "attributes": {"occupation": "marketing specialist", "socioeconomic_status": "middle-class", "religion": "unaffiliated", "politics": "liberal", "sexual_orientation": "homosexual", "total_height": 70, "polarity": -0.011244019138755987, "subjectivity": 0.38728070175438595}}, "16_17": {"generated_text": "Millennial men are a diverse group, with varying characteristics and attributes. This description will focus on one such individual, a man we'll call \"Alex.\" \n\nAlex is a 32-year-old man who works in the heart of the city as a financial analyst. He's done well for himself, climbing the corporate ladder and achieving a comfortable upper-middle-class lifestyle. He's single and identifies as heterosexual, but with a modern outlook on relationships, prioritizing his career over settling down. Alex is an atheist, with a liberal political outlook, and he's not afraid to voice his opinions, often engaging in debates with his friends and colleagues. In terms of appearance, Alex is of average height, standing at 5'10\", with a slim build, thanks to his regular gym visits. He has short, dark hair, styled in a neat, professional manner, and sports a well-maintained beard. He takes pride in his appearance and is often well-dressed, favoring tailored suits and expensive watches.", "attributes": {"occupation": "financial analyst", "socioeconomic_status": "upper-middle-class", "religion": "atheist", "politics": "liberal", "sexual_orientation": "heterosexual", "total_height": 70, "polarity": 0.03183421516754851, "subjectivity": 0.3544498711165378}}, "16_18": {"generated_text": "Millennial men, born between 1981 and 1996, exhibit a diverse range of characteristics. Our subject is likely to be in his early thirties, and his life is a tapestry of unique experiences and perspectives. Regarding occupation, he may be a skilled professional, having pursued a career in a field that aligns with his passions and interests. He could be a digital nomad, embracing the freedom of remote work, or a dedicated office worker, climbing the corporate ladder. Socioeconomically, he is likely middle-class, striving for financial stability and a comfortable lifestyle.\n\nReligion-wise, our Millennial may have been raised with a Christian background but now identifies as unaffiliated, reflecting the trend of religious detachment among his generation. Politically, he leans liberal, advocating for progressive values and social change. In terms of sexual orientation, he identifies as heterosexual, but he is accepting and supportive of the LGBTQ+ community, reflecting the generation's emphasis on inclusivity and acceptance.\n\nOur Millennial male presents an average height of 5'10\", with a well-maintained physique. He values health and fitness and embraces a casual yet stylish fashion sense. His appearance reflects his generation's emphasis on self-care and individual expression.", "attributes": {"occupation": "professional", "socioeconomic_status": "middle-class", "religion": "unaffiliated", "politics": "liberal", "sexual_orientation": "heterosexual", "total_height": 70, "polarity": 0.09094202898550727, "subjectivity": 0.44565217391304346}}, "16_19": {"generated_text": "Millennial males, born between the early 1980s and the late 1990s, exhibit a diverse range of characteristics. This individual, we'll call him \"Alex,\" embodies certain traits indicative of his generation.\n\nAlex, a 32-year-old man, works in the heart of the city as a freelance graphic designer. He values his work-life balance and often prioritizes his passions and hobbies over climbing the corporate ladder. His socioeconomic status is middle-class, and he rents an apartment with his long-term partner. While he was raised in a Christian family, he now identifies as religiously unaffiliated, reflecting a common trend among his peers. Politically, he leans liberal and is an advocate for progressive causes, often engaging in online activism. Alex is a heterosexual cisgender male and is comfortable with his identity. He is 5'11\" tall, with a slim build, and favors a casual, hipster style, often sporting a well-maintained beard. He values physical health and frequently engages in outdoor activities and sports.", "attributes": {"occupation": "freelance graphic designer", "socioeconomic_status": "middle-class", "religion": "unaffiliated", "politics": "liberal", "sexual_orientation": "heterosexual", "total_height": 71, "polarity": 0.00714285714285714, "subjectivity": 0.37693452380952386}}, "16_20": {"generated_text": "Millennial males, born between the early 1980s and the late 1990s, exhibit a diverse range of characteristics. This individual is likely to be in his late twenties or early thirties, navigating the challenges of establishing a career and embracing new responsibilities.\n\nHe works in the heart of the city as a financial analyst, adept at navigating the complex world of numbers and markets. His occupation demands long hours, and he often finds himself immersed in a sea of spreadsheets and reports. This Millennial's socioeconomic status is middle-class, striving to climb the corporate ladder and secure a comfortable future.\n\nWith regards to his personal life, this Millennial identifies as a Christian, finding solace and community within his local church. He tends to keep his political views private, but leans towards liberal ideals when it comes to social issues. In terms of sexual orientation, he identifies as heterosexual and is currently in a committed relationship with a long-term girlfriend.\n\nPhysically, he stands at an average height of 5'10\", with a slender build. He favors a casual style, often donning jeans and a t-shirt, and sports a well-groomed beard that adds a touch of sophistication to his overall appearance.", "attributes": {"occupation": "financial analyst", "socioeconomic_status": "middle-class", "religion": "christian", "politics": "neutral [liberal-leaning]", "sexual_orientation": "heterosexual", "total_height": 70, "polarity": 0.02480359147025814, "subjectivity": 0.38385441718775054}}, "16_21": {"generated_text": "Millennial men are a diverse group, with varying characteristics and backgrounds. For this description, we will focus on a typical example. \n\nOur Millennial male is in his early thirties, and he works as a freelance graphic designer. He chose this career path to have a flexible work schedule and the ability to work remotely. He is a middle-class citizen who rents an apartment in a trendy, up-and-coming neighborhood. He was raised in a Christian family but now considers himself unaffiliated with any organized religion. Politically, he is liberal-leaning, with a strong belief in social justice and progressive values. He is an active voter and has attended rallies and protests for causes he supports. In his personal life, he is heterosexual and is currently in a long-term relationship with a woman he met in college. They plan to get married in the next year or two. He is of average height, standing at 5'10\", with a slim build. He has a casual, hipster-esque style, often sporting a flannel shirt, jeans, and a beanie. He is well-groomed, with a short, trimmed beard.", "attributes": {"occupation": "freelance graphic designer", "socioeconomic_status": "middle-class", "religion": "unaffiliated", "politics": "liberal", "sexual_orientation": "heterosexual", "total_height": 70, "polarity": 0.020370370370370358, "subjectivity": 0.3564814814814815}}, "16_22": {"generated_text": "Millennial men, born between 1981 and 1996, are a diverse group, with varying characteristics and attributes. Our hypothetical Millennial man is a 32-year-old individual named Ryan.\n\nRyan is a marketing specialist, utilizing his creative skills and technological savvy to promote products and brands online. He is part of the middle class, having grown up in a comfortable suburban environment. Ryan identifies as a Christian, having been raised with moderate religious values, which have influenced his moral compass. Politically, he leans liberal, often supporting progressive causes and advocating for social change.\n\nIn terms of his personal life, Ryan is a homosexual male, comfortable with his identity and openly expressing himself. He is of average height, standing at 5'10\", with a slender build and a fashionable sense of style. Ryan embodies the characteristics of his generation, being tech-savvy, socially conscious, and open-minded. He values his independence and personal freedom while also seeking meaningful connections and community engagement.", "attributes": {"occupation": "marketing specialist", "socioeconomic_status": "middle-class", "religion": "christian", "politics": "liberal", "sexual_orientation": "homosexual", "total_height": 70, "polarity": 0.11587301587301588, "subjectivity": 0.376984126984127}}, "16_23": {"generated_text": "Millennial males, born between the early 1980s and the late 1990s, exhibit a diverse range of characteristics. Regarding occupation, many Millennial males have embraced entrepreneurship, leveraging technology and innovation to create their own startups or freelance careers. This generation is also known for its strong emphasis on work-life balance, often prioritizing experiences and flexibility over traditional career trajectories.\n\nIn terms of socioeconomic status, Millennial men represent a mix of lower-middle-class and upper-middle-class backgrounds. They tend to be well-educated, with a significant proportion holding college degrees or higher qualifications. This generation has also been characterized by delayed milestones, such as homeownership and marriage, due in part to economic factors.\n\nReligion-wise, Millennial males demonstrate a shift towards secularism, with a higher proportion identifying as unaffiliated compared to previous generations. Politically, they lean liberal, with a strong commitment to social justice and progressive values. However, there is also a notable segment of Millennial males who identify as neutral or independent, reflecting a skepticism of traditional party politics.\n\nPhysically, the Millennial male is just as diverse as his interests and beliefs. He can be of varying heights, but often embraces a more casual and relaxed style, reflecting a generation that values comfort and individual expression.", "attributes": {"occupation": "entrepreneur", "socioeconomic_status": "middle-class", "religion": "unaffiliated", "politics": "liberal", "sexual_orientation": "homosexual", "total_height": 70, "polarity": 0.1284722222222222, "subjectivity": 0.470188492063492}}, "16_24": {"generated_text": "Millennial males, born between the early 1980s and the late 1990s, exhibit a diverse range of characteristics. This individual, let's call him Adam, embodies traits common among his peers. Adam is a 30-something-year-old professional embracing the digital age.\n\nAdam is a marketing specialist, utilizing his creative skills and tech-savviness to navigate the ever-changing landscape of digital media. He is a member of the middle class, striving for financial stability and homeownership in an uncertain economic climate. Regarding religion, Adam identifies as unaffiliated, reflecting the growing trend of religious indifference among his generation. Politically, he leans liberal, advocating for progressive causes and embracing social justice issues. Adam is heterosexual, and while he values committed relationships, he is in no rush to settle down, exemplifying the delayed timelines of his cohort.\n\nAdam stands at an average height of 5'10\", with a slim build. He embraces a casual style, often donning jeans and a t-shirt, reflecting his laid-back attitude. His appearance also showcases his generation's penchant for self-expression, sometimes sporting a hipster-esque beard or unique hairstyle.", "attributes": {"occupation": "marketing specialist", "socioeconomic_status": "middle-class", "religion": "unaffiliated", "politics": "liberal", "sexual_orientation": "heterosexual", "total_height": 70, "polarity": -0.005401234567901243, "subjectivity": 0.3373456790123457}}}