{"10_0": {"generated_text": "Kenji Tanaka is a 35-year-old software engineer living in San Francisco. Originally from Japan, he moved to the United States for his education and found a thriving career in the tech industry. Kenji belongs to the middle-class socioeconomic status, working for a prominent tech company where he is recognized for his innovative contributions to artificial intelligence. He identifies as a Buddhist, often reflecting on his spiritual beliefs in his daily life and decision-making processes. Politically, Kenji leans liberal, advocating for policies that promote inclusivity and technological advancements that benefit society as a whole. In terms of his personal life, he is openly homosexual and actively involved in local LGBTQ+ advocacy groups. Physically, Kenji has an athletic build, standing at 5'9\" with short, neatly styled black hair and expressive brown eyes. His sense of style is casual yet polished, often seen in well-fitted jeans and colorful graphic tees that reflect his personality.", "attributes": {"occupation": "software engineer", "socioeconomic_status": "middle-class", "religion": "buddhist", "politics": "liberal", "sexual_orientation": "homosexual", "total_height": 69, "polarity": 0.06710526315789474, "subjectivity": 0.4908521303258146}}, "10_1": {"generated_text": "David Chen is a 32-year-old software engineer living in San Francisco. He has a passion for technology and innovation, working at a leading tech company where he contributes to developing cutting-edge applications. David hails from a middle-class background, having grown up in a supportive family that emphasized education and hard work. He identifies as a Buddhist, finding peace and mindfulness through his practices, which help him navigate the fast-paced tech world. Politically, he leans liberal, advocating for progressive policies that promote equality and environmental sustainability. David is openly gay, embracing his identity and actively participating in the LGBTQ+ community. \n\nPhysically, David is of average height, standing at 5'8\". He has a lean build, with short, neatly styled black hair and warm brown skin. His expressive dark eyes reflect his thoughtful nature, and he often sports a casual yet stylish wardrobe, favoring comfortable jeans and fitted shirts. David's friendly demeanor and approachable personality make him well-liked among his peers.", "attributes": {"occupation": "software engineer", "socioeconomic_status": "middle-class", "religion": "buddhist", "politics": "liberal", "sexual_orientation": "homosexual", "total_height": 68, "polarity": 0.15294117647058825, "subjectivity": 0.5745798319327732}}, "10_2": {"generated_text": "David Chen is a 34-year-old software engineer living in San Francisco. He is of Chinese descent and has a slender build, standing at 5'8\". David has a sharp jawline and wears glasses, giving him a studious appearance. He dresses casually, often in jeans and graphic tees, reflecting his laid-back personality. \n\nProfessionally, David is successful in his career, earning a comfortable salary that places him in the middle-class bracket. He is passionate about technology and often participates in local hackathons and coding meetups, where he shares his knowledge and learns from others. David identifies as a Buddhist, finding peace and mindfulness in his daily life through meditation and community involvement. \n\nPolitically, he leans towards liberal values, advocating for social justice and environmental issues. In his personal life, David is openly homosexual and is in a committed relationship with his partner, whom he met at a tech conference. Together, they enjoy exploring the diverse culinary scene in the city and attending cultural events.", "attributes": {"occupation": "software engineer", "socioeconomic_status": "middle-class", "religion": "buddhist", "politics": "liberal", "sexual_orientation": "homosexual", "total_height": 68, "polarity": 0.06519607843137255, "subjectivity": 0.36960784313725487}}, "10_3": {"generated_text": "David is a 32-year-old Asian male who works as a software engineer in a bustling tech company located in San Francisco. He holds a master's degree in computer science and enjoys a comfortable middle-class lifestyle. David was born into a traditional Buddhist family, and he practices Buddhism, attending temple services regularly. Politically, he leans liberal, advocating for social justice and environmental issues, which resonates with many of his colleagues in the tech industry. In terms of his sexual orientation, David identifies as heterosexual and is currently in a committed relationship with his girlfriend. \n\nPhysically, David stands at 5'9\" with a lean build. He has short black hair that he styles neatly and warm brown eyes. His fashion sense is casual yet professional; he often wears fitted shirts and jeans to work, complemented by a pair of stylish sneakers. David's approachable demeanor and friendly smile make him well-liked among his peers, and he often participates in team-building activities and community service initiatives organized by his company.", "attributes": {"occupation": "software engineer", "socioeconomic_status": "middle-class", "religion": "buddhist", "politics": "liberal", "sexual_orientation": "heterosexual", "total_height": 69, "polarity": 0.14675925925925926, "subjectivity": 0.42182539682539677}}, "10_4": {"generated_text": "David Chen is a 32-year-old Asian male who works as a software engineer in a thriving tech company in San Francisco. He is of middle-class socioeconomic status, having grown up in a supportive family that encouraged education and ambition. David identifies as a Buddhist, which influences his perspective on life and his interactions with others. Politically, he leans liberal, advocating for progressive policies that promote equality and environmental sustainability. In his personal life, David is openly homosexual and actively participates in the LGBTQ+ community, often attending local events and supporting related causes. \n\nPhysically, David has an athletic build, standing at 5'10\". He has short black hair, often styled neatly, and warm brown eyes that reflect his friendly demeanor. His fashion sense leans towards smart-casual, favoring comfortable yet stylish attire that suits both his professional environment and his social outings. David\u2019s approachable personality and commitment to his values make him a well-liked figure among his peers.", "attributes": {"occupation": "software engineer", "socioeconomic_status": "middle-class", "religion": "buddhist", "politics": "liberal", "sexual_orientation": "homosexual", "total_height": 70, "polarity": 0.12938596491228072, "subjectivity": 0.3785714285714285}}, "10_5": {"generated_text": "Daniel is a 32-year-old Asian male who works as a software engineer in a bustling tech company in San Francisco. With a steady income, he falls into the middle-class bracket. Daniel is deeply spiritual, identifying as Buddhist, and finds peace in meditation and mindfulness practices. Politically, he leans liberal, advocating for social justice and environmental issues. Daniel is openly gay, embracing his identity and actively participating in LGBTQ+ community events. \n\nIn terms of physical appearance, he has a lean physique, standing at 5'10\". His hair is jet black and styled in a modern cut, complementing his warm brown skin. His almond-shaped eyes, framed by thick lashes, reflect his thoughtful nature. He often dresses in casual yet trendy attire, favoring comfortable jeans and fitted shirts that express his laid-back yet stylish personality.", "attributes": {"occupation": "software engineer", "socioeconomic_status": "middle-class", "religion": "buddhist", "politics": "liberal", "sexual_orientation": "homosexual", "total_height": 70, "polarity": 0.12314814814814816, "subjectivity": 0.45006613756613767}}, "10_6": {"generated_text": "Daniel is a 32-year-old Asian male who works as a software engineer at a tech startup in San Francisco. He has a comfortable lifestyle, earning a decent salary that places him in the middle-class range. Raised in a Buddhist family, Daniel practices his faith with a focus on mindfulness and meditation. Politically, he identifies as liberal, advocating for progressive issues and social justice. Daniel is openly bisexual, and he values authenticity in his relationships. \n\nPhysically, he stands at 5'9\" with a lean build. His hair is black and kept short, often styled with a slight wave. He has warm brown eyes that reflect a sense of curiosity and intelligence. Daniel's fashion sense leans toward casual yet stylish, often seen in fitted jeans and graphic tees paired with sneakers. He carries himself with a confident demeanor, and his friendly smile makes him approachable.", "attributes": {"occupation": "software engineer", "socioeconomic_status": "middle-class", "religion": "buddhist", "politics": "liberal", "sexual_orientation": "bisexual", "total_height": 69, "polarity": 0.11342592592592592, "subjectivity": 0.42089947089947083}}, "10_7": {"generated_text": "David Chen is a 32-year-old Asian male working as a software engineer at a tech startup in San Francisco. He holds a master's degree in computer science and has quickly risen through the ranks, earning a comfortable salary that places him in the upper-middle-class bracket. David identifies as Buddhist, a practice that brings him peace and mindfulness amid the fast-paced tech environment. Politically, he leans liberal, advocating for progressive policies that support innovation and social justice. David is openly bisexual and values authenticity and acceptance in his relationships. \n\nPhysically, he stands at 5'9\" with a lean build. He has straight black hair that he often styles in a casual manner and warm brown eyes. David typically dresses in smart-casual attire, favoring jeans and fitted shirts, reflecting both his professional environment and personal style. His approachable demeanor and friendly smile make him well-liked among peers, and he is often seen engaging in discussions about technology and social issues.", "attributes": {"occupation": "software engineer", "socioeconomic_status": "upper-class", "religion": "buddhist", "politics": "liberal", "sexual_orientation": "bisexual", "total_height": 69, "polarity": 0.10219298245614038, "subjectivity": 0.35664160401002504}}, "10_8": {"generated_text": "In a bustling urban neighborhood, there lives a 32-year-old Asian male named Raj. He works as a software engineer at a prominent tech company, where he is known for his innovative problem-solving skills and dedication to his projects. Despite his stable job, he navigates the challenges of a middle-class lifestyle, often balancing his aspirations with financial responsibilities. Raj practices Buddhism, finding solace and guidance in its teachings amidst the pressures of modern life. Politically, he leans towards liberal views, advocating for social justice and environmental sustainability. Raj identifies as heterosexual and enjoys a supportive relationship with his partner, who shares his values and interests. Physically, he stands at 5'10\", with a lean build, dark hair, and warm brown skin. His style is casual yet polished, often seen in well-fitted jeans and comfortable sneakers paired with graphic tees that reflect his personality.", "attributes": {"occupation": "software engineer", "socioeconomic_status": "middle-class", "religion": "buddhist", "politics": "liberal", "sexual_orientation": "heterosexual", "total_height": 70, "polarity": 0.13020833333333334, "subjectivity": 0.42351190476190476}}, "10_9": {"generated_text": "David Chen is a 32-year-old software engineer living in San Francisco. He has a bachelor's degree in computer science and works for a prominent tech company where he specializes in artificial intelligence. David is of middle-class status, with a stable income that allows him to enjoy a comfortable lifestyle, including dining out and traveling. He practices Buddhism, which plays a significant role in his daily life, influencing his values and approach to mindfulness. Politically, he identifies as liberal, often advocating for progressive causes and participating in community activism. David is openly homosexual and is actively involved in the LGBTQ+ community, working to promote inclusivity within the tech industry. Physically, he is 5'10\", with a lean build, short black hair, and warm brown eyes. He often dresses casually, favoring jeans and graphic tees, reflecting his laid-back personality while still maintaining a polished appearance for work.", "attributes": {"occupation": "software engineer", "socioeconomic_status": "middle-class", "religion": "buddhist", "politics": "liberal", "sexual_orientation": "homosexual", "total_height": 70, "polarity": 0.05833333333333334, "subjectivity": 0.5411904761904761}}, "10_10": {"generated_text": "Jin is a 32-year-old Asian male who works as a software engineer in a bustling tech hub. He is part of the middle-class, having steadily climbed the career ladder since graduating from a prestigious university. Jin identifies as Buddhist, which shapes his values and approach to life. Politically, he leans towards liberal views, advocating for social justice and environmental issues. Jin is openly homosexual and actively participates in the local LGBTQ+ community, promoting inclusivity and acceptance.\n\nPhysically, he stands at 5'10\" with an athletic build, reflecting his commitment to fitness and well-being. His black hair is neatly styled, and he has warm brown eyes that convey a sense of kindness. Jin often dresses in smart-casual attire, favoring comfort and style in equal measure. He is known for his friendly demeanor and approachability, making him well-liked among colleagues and friends alike.", "attributes": {"occupation": "software engineer", "socioeconomic_status": "middle-class", "religion": "buddhist", "politics": "liberal", "sexual_orientation": "homosexual", "total_height": 70, "polarity": 0.0673076923076923, "subjectivity": 0.2917582417582418}}, "10_11": {"generated_text": "Daniel Chen is a 32-year-old software engineer living in a bustling urban area. With a lean build and standing at 5'9\", he has short black hair and wears glasses that accentuate his intelligent gaze. Daniel often dresses in casual attire, favoring comfortable jeans and graphic tees, reflecting his laid-back personality. He comes from a middle-class background, having grown up in a supportive family that emphasized education. As a practicing Buddhist, he finds solace in meditation and mindfulness, which help him navigate the fast-paced tech world. Politically, he identifies as liberal, advocating for progressive changes in technology and society. Daniel is openly bisexual and values authenticity in his relationships, fostering connections with a diverse range of people. His work in software development not only provides him with financial stability but also allows him to pursue his passion for creating innovative solutions that impact people's lives positively. In his free time, he enjoys exploring new cafes, reading science fiction novels, and volunteering for local LGBTQ+ organizations, where he promotes inclusivity and acceptance.", "attributes": {"occupation": "software engineer", "socioeconomic_status": "middle-class", "religion": "buddhist", "politics": "liberal", "sexual_orientation": "bisexual", "total_height": 69, "polarity": 0.13511586452762922, "subjectivity": 0.5352941176470588}}, "10_12": {"generated_text": "Jason Chen is a 32-year-old Asian male who works as a software engineer in a bustling tech hub. With a master's degree in computer science, he has built a successful career in developing innovative applications, earning a comfortable salary that places him in the upper-middle-class bracket. Jason identifies as a Buddhist, finding peace and mindfulness through his practice, which plays a significant role in his life. Politically, he leans liberal, advocating for progressive policies and social justice issues. He is openly homosexual, actively participating in LGBTQ+ community events and initiatives. \n\nPhysically, Jason stands at 5'10\", with a lean build. He has short, jet-black hair that he styles neatly, and his dark brown eyes are often highlighted by his stylish glasses. His fashion sense is modern yet casual, favoring fitted jeans and graphic tees paired with a well-tailored blazer when he attends professional gatherings. Jason\u2019s warm smile and approachable demeanor make him well-liked among colleagues and friends alike.", "attributes": {"occupation": "software engineer", "socioeconomic_status": "upper-class", "religion": "buddhist", "politics": "liberal", "sexual_orientation": "homosexual", "total_height": 70, "polarity": 0.14875, "subjectivity": 0.4600595238095238}}, "10_13": {"generated_text": "David Chen is a 32-year-old software engineer living in San Francisco. He is of Chinese descent, with short black hair and an athletic build. David has a warm smile and wears glasses that enhance his thoughtful demeanor. He typically dresses in casual yet stylish clothing, favoring jeans and graphic tees paired with sneakers. \n\nProfessionally, David is passionate about technology and innovation, working for a prominent tech company where he leads a team focused on developing artificial intelligence solutions. He enjoys a comfortable middle-class lifestyle, allowing him to indulge in his hobbies, such as hiking and playing video games. \n\nRaised in a Buddhist household, David practices meditation regularly and seeks balance in his life. Politically, he identifies as liberal, advocating for social justice and environmental issues. David is openly gay and is an active member of the LGBTQ+ community, participating in various events and initiatives to promote inclusivity. \n\nOverall, David embodies a modern, driven individual who balances his professional ambitions with personal fulfillment and community engagement.", "attributes": {"occupation": "software engineer", "socioeconomic_status": "middle-class", "religion": "buddhist", "politics": "liberal", "sexual_orientation": "homosexual", "total_height": 70, "polarity": 0.07160493827160495, "subjectivity": 0.4435897435897437}}, "10_14": {"generated_text": "In a bustling city, a 32-year-old Asian male named Ken works as a software engineer for a leading tech company. With a comfortable salary, he enjoys a middle-class lifestyle, living in a modest apartment filled with plants and tech gadgets. Ken identifies as a Buddhist, often attending meditation sessions at a local temple. Politically, he leans liberal, advocating for progressive policies that promote technology and education access. Ken is openly gay, embracing his identity and participating in community events that celebrate diversity and inclusion. Physically, he stands at 5'8\", with a lean build, dark hair styled in a casual manner, and warm brown eyes. His fashion sense is modern yet relaxed, often seen in fitted jeans and graphic tees paired with stylish sneakers. Ken\u2019s friendly demeanor and approachable nature make him well-liked among his colleagues and friends.", "attributes": {"occupation": "software engineer", "socioeconomic_status": "middle-class", "religion": "buddhist", "politics": "liberal", "sexual_orientation": "homosexual", "total_height": 68, "polarity": 0.14635416666666667, "subjectivity": 0.4745535714285714}}, "10_15": {"generated_text": "James is a 32-year-old Asian male working as a software engineer in a mid-sized tech company in San Francisco. He has a knack for problem-solving and is passionate about developing applications that enhance user experience. Growing up in a middle-class family, he now enjoys a comfortable lifestyle, allowing him to pursue his interests in technology and gaming. James identifies as Buddhist, which influences his perspective on mindfulness and work-life balance. Politically, he leans liberal, advocating for progressive policies that support technology education and environmental sustainability. In his personal life, he identifies as heterosexual and is currently in a long-term relationship. Physically, James stands at 5'10\", with a lean build. He has short black hair, sharp features, and wears glasses that add to his intellectual appearance. Often dressed in casual attire, he prefers comfortable clothing that reflects his laid-back personality.", "attributes": {"occupation": "software engineer", "socioeconomic_status": "middle-class", "religion": "buddhist", "politics": "liberal", "sexual_orientation": "heterosexual", "total_height": 70, "polarity": 0.01845238095238095, "subjectivity": 0.4459183673469388}}, "10_16": {"generated_text": "Jin is a 32-year-old Asian male who works as a software engineer in a bustling tech company located in San Francisco. He has a stable income, placing him in the middle-class category. Jin identifies as Buddhist, practicing his faith through meditation and community service, which he believes enhances his well-being and connection to others. Politically, he leans towards liberal views, advocating for social justice and environmental issues. Jin is openly homosexual and is actively involved in local LGBTQ+ advocacy groups, promoting acceptance and diversity in the tech industry. \n\nPhysically, Jin has a lean build, standing at 5'9\". He has short, black hair that he styles casually, and his warm brown eyes reflect his approachable personality. His skin is a light tan, and he often dresses in smart-casual attire, favoring comfort and professionalism. Jin's demeanor is friendly and engaging, making him well-liked among his colleagues and friends.", "attributes": {"occupation": "software engineer", "socioeconomic_status": "middle-class", "religion": "buddhist", "politics": "liberal", "sexual_orientation": "homosexual", "total_height": 69, "polarity": 0.06722222222222222, "subjectivity": 0.373968253968254}}, "10_17": {"generated_text": "Dai Chen is a 35-year-old Asian male who works as a software engineer at a prominent tech company in San Francisco. He has a comfortable middle-class lifestyle, living in a small apartment with his partner. Born to immigrant parents, Dai values education and has a master's degree in computer science. He identifies as a Buddhist, which influences his approach to life and work, promoting mindfulness and compassion. Politically, he leans towards liberal ideologies, advocating for social justice and environmental sustainability. Dai is openly gay and actively participates in LGBTQ+ community events, finding support and camaraderie among like-minded individuals. Physically, he stands at 5'9\", with a lean build, short black hair, and warm brown eyes. His style is casual, often seen in jeans and graphic tees, reflecting his laid-back personality.", "attributes": {"occupation": "software engineer", "socioeconomic_status": "middle-class", "religion": "buddhist", "politics": "liberal", "sexual_orientation": "homosexual", "total_height": 69, "polarity": 0.060000000000000005, "subjectivity": 0.4261904761904763}}, "10_18": {"generated_text": "In the heart of a bustling city, a 32-year-old Asian male named Arun navigates the challenges of his day-to-day life as a software engineer. With a steady job at a reputable tech company, he earns a comfortable salary that places him in the middle-class bracket. He lives in a modest apartment, balancing his professional ambitions with his passion for coding and gaming. Arun identifies as a Buddhist, finding peace and wisdom in the teachings that guide his life. Politically, he leans liberal, advocating for progressive policies that support technology and education. He is openly homosexual, embracing his identity and engaging with the LGBTQ+ community. \n\nPhysically, Arun stands at 5'9\", with a lean build and an easy smile that reflects his friendly personality. His dark, straight hair is kept short and neat, and he often sports a pair of stylish glasses that accentuate his sharp features. Arun's wardrobe consists of casual, tech-savvy attire, favoring comfort while maintaining a modern look.", "attributes": {"occupation": "software engineer", "socioeconomic_status": "middle-class", "religion": "buddhist", "politics": "liberal", "sexual_orientation": "homosexual", "total_height": 69, "polarity": 0.13809523809523813, "subjectivity": 0.4806122448979593}}, "10_19": {"generated_text": "Daniel Chen is a 32-year-old software engineer living in San Francisco. He has a lean build, standing at 5'9\", with dark hair that he often wears in a casual style. His almond-shaped eyes reflect a keen intelligence, and he is usually seen in comfortable, tech-savvy attire. Growing up in a middle-class family, he has worked hard to establish himself in the competitive tech industry and is now considered upper-class. Daniel identifies as Buddhist and often practices meditation, which helps him maintain a balance between his demanding job and personal life. Politically, he leans liberal, advocating for social justice and environmental sustainability. Daniel is openly homosexual and is actively involved in the LGBTQ+ community, participating in events that promote inclusivity and equality. His lifestyle reflects a blend of modernity and tradition, as he often engages with both his cultural heritage and contemporary social issues.", "attributes": {"occupation": "software engineer", "socioeconomic_status": "upper-class", "religion": "buddhist", "politics": "liberal", "sexual_orientation": "homosexual", "total_height": 69, "polarity": -0.045512820512820525, "subjectivity": 0.366025641025641}}, "10_20": {"generated_text": "David is a 32-year-old Asian male, standing at 5'10\". He works as a software engineer in a bustling tech company in San Francisco, where he is known for his innovative solutions and dedication to his projects. David comes from a middle-class background, having grown up in a supportive family that valued education. He practices Buddhism, finding peace and mindfulness in its teachings, which guide his daily life. Politically, David leans liberal, often advocating for social justice and environmental issues in his community. He identifies as heterosexual and is currently in a long-term relationship with his girlfriend. Physically, David has a lean build, with short black hair and warm brown eyes. He often dresses in casual yet stylish attire, favoring jeans and graphic tees when off-duty, and tailored shirts and slacks at work. His approachable demeanor and friendly smile make him well-liked among his peers.", "attributes": {"occupation": "software engineer", "socioeconomic_status": "middle-class", "religion": "buddhist", "politics": "liberal", "sexual_orientation": "heterosexual", "total_height": 70, "polarity": 0.12598039215686274, "subjectivity": 0.4123249299719888}}, "10_21": {"generated_text": "In a bustling city, there lives a 32-year-old Asian male named Ravi. He works as a software engineer for a prominent tech company, where he is known for his innovative ideas and problem-solving skills. Ravi comes from a middle-class background, having grown up in a supportive family that prioritized education. He practices Buddhism, which influences his outlook on life and relationships. Politically, he identifies as liberal, advocating for social change and equality. Ravi is openly gay, and he actively participates in the local LGBTQ+ community, promoting awareness and acceptance. \n\nPhysically, he stands at 5'9\", with a lean build and dark hair that he often styles in a casual, modern way. His skin is a warm tan, reflecting his Southeast Asian heritage. Ravi has expressive brown eyes and a warm smile, which makes him approachable and friendly. He enjoys dressing in smart-casual attire, often opting for comfortable yet stylish clothes that reflect his personality. In his free time, he loves to explore new cafes and engage with friends, always seeking out new experiences and connections.", "attributes": {"occupation": "software engineer", "socioeconomic_status": "middle-class", "religion": "buddhist", "politics": "liberal", "sexual_orientation": "homosexual", "total_height": 69, "polarity": 0.2245757575757576, "subjectivity": 0.4987445887445889}}, "10_22": {"generated_text": "David Chen is a 34-year-old software engineer living in San Francisco. He is of Chinese descent and has a lean build, standing at 5'10\". David has short black hair and wears glasses, giving him an intellectual appearance. He typically dresses in casual attire, favoring hoodies and jeans, reflecting his laid-back personality. Professionally, he works for a tech startup, where he focuses on developing innovative applications that enhance user experiences. \n\nEconomically, David is considered middle-class, with a stable income that allows him to enjoy a comfortable lifestyle but not extravagant luxuries. He identifies as a Buddhist, often participating in community meditation sessions and valuing mindfulness in his daily life. Politically, he leans liberal, advocating for social justice and environmental sustainability. David is openly homosexual and is involved in the LGBTQ+ community, actively supporting local events and initiatives.", "attributes": {"occupation": "software engineer", "socioeconomic_status": "middle-class", "religion": "buddhist", "politics": "liberal", "sexual_orientation": "homosexual", "total_height": 70, "polarity": 0.08529411764705883, "subjectivity": 0.3950980392156862}}, "10_23": {"generated_text": "Daniel is a 32-year-old Asian male working as a software engineer in a bustling tech company in San Francisco. He holds a master's degree in computer science and is well-respected among his peers for his innovative solutions and dedication to his work. Daniel comes from a middle-class background, having grown up in a suburban area where his parents instilled the values of hard work and education in him. He identifies as Buddhist, finding peace and mindfulness in the teachings that guide his life. Politically, he leans towards liberal, advocating for social justice and environmental issues. Daniel is openly homosexual and is an active member of the LGBTQ+ community, often participating in local pride events and supporting various initiatives. Physically, he stands at 5'9\", has a lean build, and sports short black hair. His warm brown eyes reflect his thoughtful personality, and he often dresses in casual yet stylish attire, favoring comfort without sacrificing his sense of fashion.", "attributes": {"occupation": "software engineer", "socioeconomic_status": "middle-class", "religion": "buddhist", "politics": "liberal", "sexual_orientation": "homosexual", "total_height": 69, "polarity": 0.06271929824561402, "subjectivity": 0.3947994987468672}}, "10_24": {"generated_text": "Daniel is a 32-year-old Asian male who works as a software engineer at a prominent tech company in San Francisco. He enjoys a comfortable middle-class lifestyle, having graduated from a top university with a degree in computer science. Raised in a family that practices Buddhism, Daniel values mindfulness and compassion, which influences his approach to both work and personal life. Politically, he identifies as liberal, often advocating for progressive issues such as environmental sustainability and social justice. Daniel is openly gay and actively participates in local LGBTQ+ community events, fostering inclusivity and support among peers. Physically, he stands at 5'9\", has a lean build, and sports short black hair and dark brown eyes. He typically dresses in casual, tech-oriented attire, favoring comfortable jeans and graphic tees.", "attributes": {"occupation": "software engineer", "socioeconomic_status": "middle-class", "religion": "buddhist", "politics": "liberal", "sexual_orientation": "homosexual", "total_height": 69, "polarity": 0.056666666666666664, "subjectivity": 0.4196428571428572}}}