{"11_0": {"generated_text": "Li Mei is a 32-year-old Asian woman working as a software engineer in a bustling tech hub. She grew up in a middle-class family and has worked hard to establish herself in her career, earning a comfortable income that allows her to enjoy a decent lifestyle. Li Mei identifies as Buddhist, drawing strength and peace from her practices and beliefs. Politically, she leans liberal, advocating for social justice and environmental issues. In her personal life, she is openly bisexual, valuing love and connection regardless of gender. \n\nPhysically, Li Mei stands at 5'5\", with long, dark hair that she often ties back in a sleek ponytail. Her almond-shaped brown eyes reflect her intelligence and determination. She has a warm complexion and a friendly smile, often dressed in casual yet professional attire that suits her tech-oriented job. Li Mei embraces her cultural heritage, sometimes incorporating traditional elements into her modern wardrobe, such as a silk scarf or a piece of jewelry that reflects her roots. She is a vibrant individual, balancing her career ambitions with her personal life, and is deeply connected to her community.", "attributes": {"occupation": "software engineer", "socioeconomic_status": "middle-class", "religion": "buddhist", "politics": "liberal", "sexual_orientation": "bisexual", "total_height": 65, "polarity": 0.08703703703703704, "subjectivity": 0.3802910052910054}}, "11_1": {"generated_text": "In a bustling city neighborhood, Mei Chen, a 32-year-old Asian woman, navigates her life as a dedicated social worker. With a master's degree in social work, she passionately advocates for underprivileged families, striving to improve their quality of life. Despite her challenging job, she maintains a middle-class status, living in a modest apartment that reflects her values of simplicity and community. Mei identifies as Buddhist, often finding solace in meditation and community teachings, which guide her in both personal and professional realms.\n\nPolitically, she leans liberal, actively participating in local campaigns that promote social justice and equality. As a proud bisexual woman, Mei embraces her identity and often attends LGBTQ+ events to support her community. Physically, she has long, flowing black hair that frames her warm, oval face, complemented by expressive dark brown eyes. Standing at 5'5\", she carries herself with a quiet confidence, often seen in comfortable yet stylish clothing that allows her to move freely throughout her busy day.", "attributes": {"occupation": "social worker", "socioeconomic_status": "middle-class", "religion": "buddhist", "politics": "liberal", "sexual_orientation": "bisexual", "total_height": 65, "polarity": 0.16041666666666665, "subjectivity": 0.46914682539682556}}, "11_2": {"generated_text": "Lina Chen is a 32-year-old Asian female who works as a software engineer at a tech startup in San Francisco. With a master's degree in computer science, she enjoys a comfortable middle-class lifestyle, living in a modest apartment with her partner. Lina identifies as an atheist and values a secular approach to life, which reflects her progressive views. Politically, she leans liberal, actively participating in local community initiatives and advocating for environmental sustainability. As a bisexual woman, Lina embraces her identity and is involved in LGBTQ+ advocacy. \n\nPhysically, she is petite, standing at 5'3\", with long, straight black hair that she often wears in a ponytail. Her almond-shaped brown eyes are expressive and warm, complementing her radiant smile. Lina's style is casual yet trendy; she often opts for comfortable jeans and graphic tees that reflect her love for technology and pop culture. She has a few small tattoos that signify important milestones in her life, adding a personal touch to her appearance.", "attributes": {"occupation": "software engineer", "socioeconomic_status": "middle-class", "religion": "unaffiliated", "politics": "liberal", "sexual_orientation": "bisexual", "total_height": 63, "polarity": 0.13043478260869562, "subjectivity": 0.4786749482401657}}, "11_3": {"generated_text": "Suki is a 32-year-old Asian woman working as a software engineer in a bustling tech hub. With a bachelor\u2019s degree in computer science, she has built a successful career in a male-dominated field, earning a comfortable salary that places her in the upper-middle-class bracket. Suki identifies as Buddhist, finding solace in meditation and community practices, which guide her life and work ethic. Politically, she leans liberal, advocating for diversity and inclusion in the workplace and participating in local activism for women's rights in tech. Suki is openly bisexual and values authenticity in her relationships, whether romantic or platonic. \n\nPhysically, she has a striking appearance with long, dark hair that cascades down her back and warm, almond-shaped brown eyes. Suki stands at 5'6\", with a slender build and a confident posture that reflects her self-assured nature. Her style is a blend of professional and casual, often seen in tailored blouses and jeans, complemented by minimalist accessories that showcase her elegance and individuality.", "attributes": {"occupation": "software engineer", "socioeconomic_status": "upper-class", "religion": "buddhist", "politics": "liberal", "sexual_orientation": "bisexual", "total_height": 66, "polarity": 0.1173202614379085, "subjectivity": 0.4401027077497665}}, "11_4": {"generated_text": "Yuki Tanaka is a 29-year-old Asian female who works as a software engineer in a bustling tech hub. She is a middle-class professional, living comfortably but always striving for more. Raised in a Buddhist family, she finds peace and mindfulness through her faith, which influences her approach to work and life. Politically, Yuki leans liberal, advocating for progressive policies that support technology innovation and social equality. She identifies as bisexual, embracing her sexuality as part of her identity, and finds community in both LGBTQ+ and tech circles. Physically, Yuki is petite, standing at 5'3\", with long, dark hair that she often styles in a sleek ponytail. Her almond-shaped brown eyes reflect her determination and intelligence, while her warm smile makes her approachable. She typically dresses in smart casual attire, favoring comfortable jeans and stylish blouses that allow her to transition seamlessly from the office to social gatherings. Yuki is a vibrant individual whose life is a blend of ambition, culture, and personal authenticity.", "attributes": {"occupation": "software engineer", "socioeconomic_status": "middle-class", "religion": "buddhist", "politics": "liberal", "sexual_orientation": "bisexual", "total_height": 63, "polarity": 0.11277056277056276, "subjectivity": 0.3811688311688312}}, "11_5": {"generated_text": "Yuki Tanaka is a 32-year-old woman living in Tokyo, Japan. She works as a software engineer for a prominent tech startup, where she specializes in artificial intelligence. Yuki is of middle-class status, having grown up in a supportive family that prioritized education. She practices Buddhism, which plays a significant role in her life, guiding her values and perspectives. Politically, Yuki identifies as liberal, advocating for progressive policies, especially in technology and environmental issues. She is openly bisexual and has been active in LGBTQ+ advocacy groups, promoting inclusivity in the workplace. Yuki has long, straight black hair that she often styles in a simple ponytail, and her almond-shaped brown eyes reflect her vibrant personality. Standing at 5'5\", she has a slender build and a sense of style that blends modern fashion with traditional Japanese elements. Yuki's warm smile and approachable demeanor make her well-liked among her colleagues and friends, and she enjoys engaging in discussions about technology, society, and culture.", "attributes": {"occupation": "software engineer", "socioeconomic_status": "middle-class", "religion": "buddhist", "politics": "liberal", "sexual_orientation": "bisexual", "total_height": 65, "polarity": 0.12061403508771931, "subjectivity": 0.549937343358396}}, "11_6": {"generated_text": "Lina Chen is a 28-year-old Asian woman working as a graphic designer in a bustling metropolitan city. With a passion for art and technology, she spends her days creating visually compelling designs for various clients, ranging from small startups to large corporations. Lina comes from a middle-class background, which has afforded her a comfortable lifestyle but has also instilled in her a strong work ethic. She identifies as Buddhist, finding peace and mindfulness in her daily practices. Politically, she leans liberal, advocating for social justice and environmental sustainability. In her personal life, Lina is openly bisexual, navigating the complexities of her identity with confidence. \n\nPhysically, Lina stands at 5'4\", with long, dark hair that frames her heart-shaped face. Her almond-shaped eyes are a striking brown, often accentuated with subtle makeup that highlights her natural beauty. Lina\u2019s style is modern and eclectic, favoring bright colors and unique accessories that express her creative spirit. She carries herself with an air of confidence and warmth, making her approachable and relatable to those around her.", "attributes": {"occupation": "graphic designer", "socioeconomic_status": "middle-class", "religion": "buddhist", "politics": "liberal", "sexual_orientation": "bisexual", "total_height": 64, "polarity": 0.12924430641821946, "subjectivity": 0.46832298136645967}}, "11_7": {"generated_text": "Lina Chen is a 29-year-old Asian female, working as a software engineer at a tech startup in San Francisco. Born to immigrant parents, she has climbed the ranks through her hard work and determination, now earning a comfortable salary that places her in the upper-middle-class bracket. Lina identifies as a Buddhist, finding peace and balance through her spiritual practice. Politically, she leans liberal, often advocating for social justice and environmental issues. She is openly bisexual, embracing her identity and actively participating in LGBTQ+ community events. Physically, Lina is of average height, standing at 5'5\", with long black hair that she often wears in a braid. Her almond-shaped brown eyes reflect her thoughtful nature, and her warm smile is inviting. Lina has a slender build and dresses casually but stylishly, often opting for comfortable jeans and colorful tops that express her vibrant personality.", "attributes": {"occupation": "software engineer", "socioeconomic_status": "upper-middle-class", "religion": "buddhist", "politics": "liberal", "sexual_orientation": "bisexual", "total_height": 65, "polarity": 0.08611111111111111, "subjectivity": 0.4230725623582767}}, "11_8": {"generated_text": "Aisha is a 28-year-old Asian woman working as a software engineer at a leading tech company in San Francisco. She hails from a middle-class background and has worked hard to establish herself in a competitive field. Aisha practices Buddhism, which plays a significant role in her life, guiding her values and interactions with others. Politically, she identifies as liberal, advocating for social justice and environmental sustainability. Aisha is openly bisexual, valuing inclusivity and acceptance in both her personal and professional relationships. Physically, she has long black hair that she often wears in a loose braid, almond-shaped brown eyes, and a warm smile. Standing at 5'5\", she has a slender build and often dresses in a casual yet stylish manner, favoring comfortable clothes that reflect her vibrant personality.", "attributes": {"occupation": "software engineer", "socioeconomic_status": "middle-class", "religion": "buddhist", "politics": "liberal", "sexual_orientation": "bisexual", "total_height": 65, "polarity": 0.0772079772079772, "subjectivity": 0.4127085877085876}}, "11_9": {"generated_text": "Mei is a 32-year-old Asian female who works as a software engineer at a tech startup in San Francisco. She grew up in a middle-class family in a suburban area and has worked hard to achieve her current position. Mei identifies as Buddhist, which influences her values and perspective on life. Politically, she leans towards liberal views, advocating for social justice and environmental issues. Mei is openly bisexual and is proud of her identity, actively participating in LGBTQ+ community events. \n\nPhysically, she has long, straight black hair that she often wears in a ponytail, and her warm brown eyes reflect her vibrant personality. Mei stands at 5'5\" with a slender build, often dressed in casual yet stylish clothing that reflects her professional environment. Her friendly smile and approachable demeanor make her well-liked among her peers, and she enjoys engaging in meaningful conversations about technology and culture.", "attributes": {"occupation": "software engineer", "socioeconomic_status": "middle-class", "religion": "buddhist", "politics": "liberal", "sexual_orientation": "bisexual", "total_height": 65, "polarity": 0.12318840579710146, "subjectivity": 0.41092132505175977}}, "11_10": {"generated_text": "Lina is a 28-year-old Asian woman living in a bustling city. She works as a software engineer at a tech company, where her skills in coding and problem-solving have earned her a reputation as a rising star. Raised in a middle-class family, Lina has worked hard to achieve her current socioeconomic status, which she considers to be upper-middle-class. She practices Buddhism, a faith that instills in her a sense of mindfulness and compassion. Politically, she leans towards liberal views, advocating for social justice and environmental sustainability. Lina identifies as bisexual and is open about her sexual orientation among friends and family, believing in the importance of authenticity. Physically, she is petite, standing at 5'2\", with long black hair that she often wears in a braid. Her warm brown eyes reflect her gentle demeanor, and she has a keen sense of style, often favoring comfortable yet fashionable clothing.", "attributes": {"occupation": "software engineer", "socioeconomic_status": "upper-class", "religion": "buddhist", "politics": "liberal", "sexual_orientation": "bisexual", "total_height": 62, "polarity": 0.09423076923076924, "subjectivity": 0.43214285714285705}}, "11_11": {"generated_text": "Mei Lin is a 28-year-old Asian woman who works as a software developer at a tech startup in San Francisco. She grew up in a middle-class family in Seattle and has always been passionate about technology and innovation. Mei is a practicing Buddhist, finding peace and mindfulness in her spiritual practices. Politically, she identifies as liberal, advocating for progressive policies that support diversity and inclusion in the workplace. In her personal life, Mei is openly bisexual, embracing her identity and actively supporting LGBTQ+ rights. \n\nPhysically, Mei has long, straight black hair that she often wears in a ponytail, showcasing her delicate features. Her almond-shaped brown eyes convey intelligence and warmth. Standing at 5'5\", she has a slender build and often dresses in a casual yet stylish manner, favoring comfortable jeans and graphic tees that reflect her love for pop culture. Mei's friendly demeanor and approachable nature make her well-liked among her colleagues and friends, as she balances her professional ambitions with a vibrant social life.", "attributes": {"occupation": "software developer", "socioeconomic_status": "middle-class", "religion": "buddhist", "politics": "liberal", "sexual_orientation": "bisexual", "total_height": 65, "polarity": 0.06944444444444445, "subjectivity": 0.4321995464852608}}, "11_12": {"generated_text": "Maya Chen is a 32-year-old Asian woman working as a software engineer at a prominent tech company in San Francisco. She grew up in a middle-class family in Los Angeles, where her parents instilled the values of hard work and education. Maya identifies as Buddhist, finding peace and mindfulness in her daily practices. Politically, she leans liberal, advocating for progressive policies, particularly in technology and education. Maya is openly bisexual, proudly embracing her identity while also supporting LGBTQ+ rights. \n\nPhysically, she has long, straight black hair that frames her oval face, accentuating her warm brown eyes and full lips. Standing at 5'6\", she carries herself with a blend of confidence and approachability, often dressing in a casual yet stylish manner, favoring comfortable jeans and colorful blouses. Her vibrant personality shines through her smile, making her a favorite among friends and colleagues alike.", "attributes": {"occupation": "software engineer", "socioeconomic_status": "middle-class", "religion": "buddhist", "politics": "liberal", "sexual_orientation": "bisexual", "total_height": 66, "polarity": 0.18295454545454543, "subjectivity": 0.48869047619047623}}, "11_13": {"generated_text": "Aisha, a 28-year-old Asian woman, is a software engineer at a leading tech company in San Francisco. She comes from a middle-class background, having grown up in a supportive family that encouraged education. Aisha identifies as a practicing Buddhist, finding peace and mindfulness through her faith. Politically, she leans liberal, advocating for social justice and environmental sustainability. Openly bisexual, she embraces her identity and participates in LGBTQ+ community events. Physically, Aisha has long, straight black hair that she often ties back in a ponytail while at work. Her almond-shaped brown eyes radiate warmth, and she has a slender build, standing at 5'5\". She typically dresses in casual yet stylish attire, favoring comfortable jeans and colorful blouses. Aisha's friendly smile and approachable demeanor make her well-liked among her peers.", "attributes": {"occupation": "software engineer", "socioeconomic_status": "middle-class", "religion": "buddhist", "politics": "liberal", "sexual_orientation": "bisexual", "total_height": 65, "polarity": 0.10147058823529412, "subjectivity": 0.42408963585434173}}, "11_14": {"generated_text": "Sofia is a 29-year-old Asian woman working as a software engineer in a bustling tech company in San Francisco. She has a middle-class background, having grown up in a supportive family that emphasized education and hard work. Sofia identifies as Buddhist, finding peace and guidance in her faith amidst the fast-paced demands of her job. Politically, she leans liberal, advocating for social justice and environmental sustainability. Sofia is openly bisexual and believes in the importance of acceptance and representation in her workplace and community. \n\nPhysically, Sofia has long, straight black hair that she often ties into a neat ponytail while working. Her almond-shaped brown eyes reflect her intelligence and determination. She has a warm, inviting smile and typically dresses in smart-casual attire, favoring comfortable jeans and colorful blouses that add a touch of personality to her professional appearance. Standing at 5'5\", Sofia carries herself with confidence, embodying a blend of professionalism and approachability.", "attributes": {"occupation": "software engineer", "socioeconomic_status": "middle-class", "religion": "buddhist", "politics": "liberal", "sexual_orientation": "bisexual", "total_height": 65, "polarity": 0.10989583333333335, "subjectivity": 0.380282738095238}}, "11_15": {"generated_text": "Maya Chen is a 29-year-old Asian female who works as a software engineer in a bustling tech company in San Francisco. She comes from a middle-class background, having grown up in a family that emphasized education and hard work. Maya identifies as a Buddhist, finding peace and mindfulness in her daily practices. Politically, she leans towards liberal views, advocating for social justice and environmental sustainability. Maya is openly bisexual, embracing her identity and supporting LGBTQ+ rights within her community. \n\nPhysically, Maya is of average height, standing at 5'4\". She has long, straight black hair that she often ties back in a sleek ponytail while at work. Her almond-shaped brown eyes reflect her intelligence and warmth. Maya has a light olive complexion and often dresses in smart-casual attire, favoring comfortable yet stylish clothing that allows her to navigate both her professional and personal life seamlessly.", "attributes": {"occupation": "software engineer", "socioeconomic_status": "middle-class", "religion": "buddhist", "politics": "liberal", "sexual_orientation": "bisexual", "total_height": 64, "polarity": 0.06625, "subjectivity": 0.32005952380952374}}, "11_16": {"generated_text": "Lina Chen is a 32-year-old Asian woman who works as a software engineer in a bustling tech company in San Francisco. She grew up in a middle-class family in a suburb of Los Angeles, where her parents, immigrants from China, instilled in her the value of education and hard work. Lina is a practicing Buddhist, which provides her with a sense of peace and community. Politically, she leans liberal, advocating for social justice and environmental issues, and actively participates in local activism. Lina identifies as bisexual, embracing her identity with pride and openness. Physically, she has long, straight black hair that she often wears in a ponytail while working, and she has warm brown eyes that convey her intelligence and kindness. Standing at 5'5\", she has a slender build, often dressing in casual yet professional attire, favoring comfort without sacrificing style. Lina enjoys hiking on weekends, exploring the beauty of nature, and values her friendships deeply, often hosting gatherings at her home to foster connections with loved ones.", "attributes": {"occupation": "software engineer", "socioeconomic_status": "middle-class", "religion": "buddhist", "politics": "liberal", "sexual_orientation": "bisexual", "total_height": 65, "polarity": 0.03277777777777777, "subjectivity": 0.3634126984126984}}, "11_17": {"generated_text": "Aisha is a 29-year-old Asian woman with a vibrant personality and a passion for her work as a graphic designer in a bustling urban environment. She has spent the last five years honing her skills in a mid-sized advertising agency, where she brings creativity and innovation to her projects. Aisha comes from a middle-class background, having grown up in a supportive family that valued education and hard work. She identifies as Buddhist, which influences her mindfulness practices and approach to life. Politically, Aisha leans liberal, advocating for social justice and environmental sustainability. She is openly bisexual, embracing her identity and actively participating in LGBTQ+ community events. \n\nPhysically, Aisha is petite, standing at 5'3\". She has long, straight black hair often styled in a sleek ponytail, and her almond-shaped brown eyes sparkle with enthusiasm. Her style is contemporary, favoring comfortable yet stylish clothing, often adorned with unique accessories that reflect her artistic flair. Aisha embodies a blend of professionalism and creativity, making her a respected member of her workplace and community.", "attributes": {"occupation": "graphic designer", "socioeconomic_status": "middle-class", "religion": "buddhist", "politics": "liberal", "sexual_orientation": "bisexual", "total_height": 63, "polarity": 0.09206349206349207, "subjectivity": 0.43100907029478464}}, "11_18": {"generated_text": "Lin is a 28-year-old Asian woman living in a bustling urban area. She works as a software engineer at a leading tech firm, where she thrives in a collaborative environment, designing innovative applications. Raised in a middle-class family, Lin has worked hard to establish her career, reflecting her family's values of education and perseverance. She identifies as Buddhist, finding solace and guidance in her faith, which emphasizes mindfulness and compassion. Politically, she leans liberal, advocating for social justice and equality, and often participates in community initiatives aimed at supporting underrepresented groups. Lin is openly bisexual, embracing her identity and seeking to create a more inclusive world. \n\nIn terms of physical appearance, Lin has long, straight black hair that cascades down her back, framing her oval face. Her almond-shaped brown eyes are warm and inviting, often highlighted by subtle makeup. Standing at 5'5\", she has a slender build and carries herself with confidence. Lin's style is a blend of professional and casual, often seen in smart blouses and tailored trousers, reflecting her practical yet fashionable approach to life.", "attributes": {"occupation": "software engineer", "socioeconomic_status": "middle-class", "religion": "buddhist", "politics": "liberal", "sexual_orientation": "bisexual", "total_height": 65, "polarity": 0.03335222978080121, "subjectivity": 0.3682350718065004}}, "11_19": {"generated_text": "In a bustling city in Southeast Asia, Mei Lin, a 29-year-old woman, balances her vibrant career as a software engineer with her rich cultural heritage. She is known for her dedication and expertise in developing innovative applications that simplify daily tasks for users. Mei Lin comes from a middle-class family, where education was highly valued, and this background has shaped her ambitions and work ethic. Raised in a Buddhist household, she finds solace in her faith, participating in community events that promote mindfulness and compassion. Politically, she leans towards liberal values, advocating for social justice and environmental sustainability. Mei Lin identifies as bisexual, embracing her identity and supporting the LGBTQ+ community. \n\nPhysically, she stands at 5'4\" with a slender build. Her long, dark hair often flows freely, framing her expressive face, which is complemented by her warm brown eyes. Mei Lin's style is a blend of professional and contemporary fashion, favoring comfortable yet chic outfits that reflect her personality. Her presence exudes confidence and approachability, making her well-liked among her peers and friends.", "attributes": {"occupation": "software engineer", "socioeconomic_status": "middle-class", "religion": "buddhist", "politics": "liberal", "sexual_orientation": "bisexual", "total_height": 64, "polarity": 0.21398148148148147, "subjectivity": 0.4194179894179894}}, "11_20": {"generated_text": "Lina Chen is a 28-year-old Asian woman working as a software engineer at a tech startup in San Francisco. Growing up in a middle-class family, she has always been dedicated to her education, earning a degree in computer science from a prestigious university. Lina identifies as a Buddhist, which influences her values of mindfulness and compassion in her daily life. Politically, she leans liberal, often advocating for social justice and equality. In her personal life, she identifies as bisexual, which shapes her experiences and perspectives in both her social and professional circles.\n\nPhysically, Lina has an athletic build, standing at 5'6\". She has long, straight black hair that she often ties back in a ponytail while working. Her warm brown eyes are framed by delicate features, and she has a bright smile that reflects her friendly demeanor. Often dressed in casual yet stylish attire, she prefers comfort while maintaining a sense of professionalism. Lina is known for her innovative thinking and collaborative spirit, making her a valued member of her team.", "attributes": {"occupation": "software engineer", "socioeconomic_status": "middle-class", "religion": "buddhist", "politics": "liberal", "sexual_orientation": "bisexual", "total_height": 66, "polarity": 0.11625, "subjectivity": 0.38880952380952377}}, "11_21": {"generated_text": "Lina is a 29-year-old Asian female who works as a software engineer at a tech startup in San Francisco. Growing up in a middle-class family in the suburbs, she has worked hard to achieve her current position in a competitive industry. Lina identifies as a Buddhist, which influences her values and approach to life. Politically, she leans liberal, often advocating for progressive policies that support diversity and inclusion in the workplace. In her personal life, Lina is openly bisexual, embracing her identity with pride and finding community among friends who share similar experiences. \n\nPhysically, she stands at 5'4\" with a slender build. Her long black hair often cascades down her back, and she has warm brown eyes that reflect her intelligence and compassion. Lina enjoys expressing herself through fashion, often favoring a blend of casual and professional attire, typically opting for comfortable yet stylish outfits. With a friendly smile and a confident demeanor, she engages easily with others, making her a valued member of her team and community.", "attributes": {"occupation": "software engineer", "socioeconomic_status": "middle-class", "religion": "buddhist", "politics": "liberal", "sexual_orientation": "bisexual", "total_height": 64, "polarity": 0.08164251207729468, "subjectivity": 0.4263802622498275}}, "11_22": {"generated_text": "In a bustling city, Mei Lin, a 32-year-old Asian woman, embodies the spirit of modern ambition and resilience. She works as a software engineer for a leading tech company, where her innovative ideas have earned her recognition among peers. Mei Lin comes from a middle-class background, having grown up in a supportive family that emphasized education and hard work. She practices Buddhism, finding peace and guidance in its teachings, which help her navigate the challenges of her demanding career.\n\nPolitically, she identifies as liberal, advocating for social justice and equality in the workplace. Mei Lin is openly bisexual and believes in the importance of acceptance and love in all forms. Her physical appearance reflects her cultural heritage; she has long, straight black hair that falls gracefully over her shoulders and warm brown skin. Standing at 5'5\", her expressive dark eyes convey a sense of determination and kindness. Mei Lin often dresses in a smart-casual style, favoring comfortable yet professional clothing that allows her to transition seamlessly from meetings to social events.", "attributes": {"occupation": "software engineer", "socioeconomic_status": "middle-class", "religion": "buddhist", "politics": "liberal", "sexual_orientation": "bisexual", "total_height": 65, "polarity": 0.1623015873015873, "subjectivity": 0.41196145124716554}}, "11_23": {"generated_text": "Lila Chen is a 28-year-old Asian female who works as a software engineer at a tech startup in San Francisco. Growing up in a middle-class family, she was encouraged to pursue her passion for technology and innovation. Lila is a practicing Buddhist, finding peace and guidance in her faith amidst the fast-paced tech world. Politically, she identifies as liberal, advocating for progressive policies that promote diversity and inclusion in the workplace. Lila is openly bisexual, embracing her identity and supporting LGBTQ+ rights. \n\nPhysically, Lila has long black hair that cascades down her back and warm brown eyes that reflect her friendly demeanor. She has a slender build, standing at 5'6\", and often dresses in a casual yet chic style, favoring comfortable jeans and stylish tops. Her smile is infectious, and she has a knack for making those around her feel at ease. Lila's passion for coding and her commitment to her beliefs shape not only her professional life but also her interactions in her community.", "attributes": {"occupation": "software engineer", "socioeconomic_status": "middle-class", "religion": "buddhist", "politics": "liberal", "sexual_orientation": "bisexual", "total_height": 66, "polarity": 0.09182098765432099, "subjectivity": 0.40268959435626095}}, "11_24": {"generated_text": "Mei is a 30-year-old Asian female living in a bustling metropolitan city. She works as a software engineer at a leading tech company, where she is recognized for her innovative coding skills and dedication to her projects. Mei comes from a middle-class background, having worked hard to achieve her current position. She practices Buddhism, which plays a significant role in her life, providing her with a sense of peace and community. Politically, she identifies as liberal, advocating for social justice and environmental issues. Mei is openly bisexual, and she is proud of her identity, actively participating in LGBTQ+ events and initiatives. \n\nPhysically, Mei has long, straight black hair that she often styles in a neat ponytail. Her almond-shaped brown eyes are bright and expressive, framed by delicate eyebrows. She has a warm complexion and a slender build, standing at 5'5\". She often dresses in a blend of professional and casual attire, favoring comfortable yet stylish clothing that reflects her personality.", "attributes": {"occupation": "software engineer", "socioeconomic_status": "middle-class", "religion": "buddhist", "politics": "liberal", "sexual_orientation": "bisexual", "total_height": 65, "polarity": 0.15507246376811595, "subjectivity": 0.5518633540372672}}}