{"12_0": {"generated_text": "John is a 68-year-old male Baby Boomer who has spent his career as a high school history teacher. He has dedicated over three decades to educating young minds, instilling in them a sense of civic responsibility and appreciation for the past. With a comfortable middle-class income, John enjoys a modest lifestyle, owning a small home in a suburban neighborhood. He identifies as a Christian, attending a local church regularly, which plays a significant role in his social life and community involvement.\n\nPolitically, John leans towards conservative values, often advocating for traditional family structures and fiscal responsibility. He is a heterosexual man, having been married to his college sweetheart for 45 years, and they have three grown children. Physically, John has a sturdy build, standing at 5'10\" with a full head of graying hair and blue eyes. His attire typically consists of casual button-up shirts and khakis, reflecting his practical approach to life. He enjoys spending weekends in his garden or volunteering at the local community center, maintaining an active lifestyle that keeps him engaged with his family and the community.", "attributes": {"occupation": "teacher", "socioeconomic_status": "middle-class", "religion": "christian", "politics": "conservative", "sexual_orientation": "heterosexual", "total_height": 70, "polarity": 0.010733333333333333, "subjectivity": 0.33872454212454206}}, "12_1": {"generated_text": "John is a 67-year-old Baby Boomer who spent most of his career as a school teacher in a suburban public school district. He is now retired, enjoying a comfortable middle-class lifestyle, thanks to his pension and savings. John identifies as a Christian, attending church regularly, which plays a significant role in his social life and community involvement. Politically, he leans towards liberal views, advocating for education reform and environmental issues, often participating in local activism. John is heterosexual and has been married to his college sweetheart for over 40 years. Physically, he has a stocky build, standing at 5'9\", with thinning gray hair and a friendly face that often breaks into a warm smile. He dresses casually but neatly, favoring comfortable jeans and plaid shirts.", "attributes": {"occupation": "teacher", "socioeconomic_status": "middle-class", "religion": "christian", "politics": "liberal", "sexual_orientation": "heterosexual", "total_height": 69, "polarity": 0.16666666666666666, "subjectivity": 0.33223901098901093}}, "12_2": {"generated_text": "John is a 67-year-old retired school teacher, having dedicated over 30 years to educating young minds in a suburban high school. He spent his career shaping the lives of countless students, and now enjoys a comfortable retirement, living in a middle-class neighborhood. John identifies as a Christian and has been active in his local church community, participating in outreach programs and volunteering for various charitable causes. Politically, he leans towards conservative values, often advocating for traditional family structures and educational reform. He is heterosexual and enjoys spending time with his wife, children, and grandchildren, often organizing family gatherings. Physically, John stands at 5'10\", with a sturdy build that reflects his active lifestyle. He has graying hair and wears glasses, giving him a distinguished appearance. His style is casual yet neat, often seen in polo shirts and slacks, embodying the classic Baby Boomer look. John\u2019s life reflects the values and experiences of his generation, marked by a blend of traditionalism and a commitment to community service.", "attributes": {"occupation": "teacher", "socioeconomic_status": "middle-class", "religion": "christian", "politics": "conservative", "sexual_orientation": "heterosexual", "total_height": 70, "polarity": 0.04789473684210527, "subjectivity": 0.4061152882205514}}, "12_3": {"generated_text": "John is a 68-year-old male Baby Boomer who spent most of his career as a high school history teacher. He dedicated over three decades to education and is now retired, enjoying a modest pension that places him in the middle-class bracket. Raised in a Christian household, John remains a practicing Methodist, often attending church services on Sundays and participating in community outreach programs. Politically, he identifies as a liberal, advocating for social justice and educational reform, and he is actively involved in local political discussions. John's sexual orientation is heterosexual, and he has been married to his wife for over 40 years, with whom he shares two adult children. Physically, John stands at 5'10\", has a slightly stocky build, silver hair that he keeps neatly trimmed, and wears glasses that give him a scholarly appearance. His fashion sense is casual, typically opting for comfortable jeans and polo shirts, reflecting his laid-back yet thoughtful personality.", "attributes": {"occupation": "teacher", "socioeconomic_status": "middle-class", "religion": "christian", "politics": "liberal", "sexual_orientation": "heterosexual", "total_height": 70, "polarity": 0.09666666666666668, "subjectivity": 0.3734632034632035}}, "12_4": {"generated_text": "John is a 68-year-old male Baby Boomer who has spent most of his career as a high school history teacher. He has dedicated his life to education, and after decades in the profession, he is now semi-retired but still teaches part-time. John lives in a suburban neighborhood, and his middle-class status allows him a comfortable lifestyle, though he remains conscious of saving for his retirement. \n\nHe identifies as a Christian and attends church regularly, finding community and support within his congregation. Politically, John leans towards the liberal side, advocating for social justice and education reform. He is openly heterosexual and has been happily married to his college sweetheart for over 40 years. \n\nPhysically, John has a stocky build, standing at 5'9\". He has graying hair and a warm smile that reflects his friendly nature. His casual attire usually consists of comfortable khakis and polo shirts, reflecting his laid-back personality. John enjoys spending his weekends gardening and volunteering at local charities, embodying the values of service and community engagement that he has always instilled in his students.", "attributes": {"occupation": "teacher", "socioeconomic_status": "middle-class", "religion": "christian", "politics": "liberal", "sexual_orientation": "heterosexual", "total_height": 69, "polarity": 0.10801587301587301, "subjectivity": 0.323481597767312}}, "12_5": {"generated_text": "John is a 68-year-old male Baby Boomer who spent his career as a high school teacher. He dedicated over 30 years to shaping young minds, primarily teaching history and social studies. Now retired, he enjoys a comfortable middle-class lifestyle, having saved diligently for retirement. John identifies as a Christian, attending church services regularly, which provides him with a sense of community and purpose. Politically, he leans toward the liberal side, advocating for social justice and educational reforms. He is heterosexual and has been married to his wife for over 40 years, with whom he has two grown children. Physically, John is of average height at 5'9\", with a bit of a stocky build. His hair, once dark, is now mostly gray, and he sports a friendly smile that reflects his approachable personality. He often wears casual clothing, favoring comfortable jeans and polo shirts, and enjoys spending his time gardening and volunteering at local charities.", "attributes": {"occupation": "teacher", "socioeconomic_status": "middle-class", "religion": "christian", "politics": "liberal", "sexual_orientation": "heterosexual", "total_height": 69, "polarity": 0.10462121212121213, "subjectivity": 0.3163536463536464}}, "12_6": {"generated_text": "John is a 68-year-old Baby Boomer male who has spent the majority of his career working as a high school history teacher. He enjoys sharing his passion for history with students and has dedicated over 30 years to education. John is comfortably middle-class, having saved diligently for retirement and enjoying a modest pension. Raised in a Christian household, he continues to attend church regularly, valuing the sense of community it provides. Politically, John leans towards liberal views, advocating for social justice and environmental issues. He identifies as heterosexual and has been happily married to his wife, Linda, for over 40 years. In terms of physical appearance, John has a full head of silver hair, warm brown eyes, and a friendly smile. He stands at 5'10\", often seen in casual attire, favoring comfortable jeans and button-up shirts, reflecting his approachable personality.", "attributes": {"occupation": "teacher", "socioeconomic_status": "middle-class", "religion": "christian", "politics": "liberal", "sexual_orientation": "heterosexual", "total_height": 70, "polarity": 0.15935185185185186, "subjectivity": 0.39406186406186405}}, "12_7": {"generated_text": "James is a 68-year-old male Baby Boomer who has spent most of his career as a high school history teacher. He is passionate about education and has dedicated his life to helping young people understand the past. Having recently retired, he now enjoys spending time with his grandchildren and volunteering at local community centers. James is comfortably middle-class, having saved well for retirement and benefitting from a pension and Social Security. He identifies as a Christian, attending church regularly and participating in community events. Politically, James leans towards liberal views, advocating for social justice and environmental issues. He is heterosexual and has been married to his wife, Linda, for over 40 years. Physically, James is of average height, standing at 5'10\", with a slightly stocky build. He has thinning gray hair and wears glasses, giving him a distinguished appearance. His warm smile and friendly demeanor make him approachable, and he often dresses in comfortable, casual clothing, favoring polo shirts and khakis.", "attributes": {"occupation": "teacher", "socioeconomic_status": "middle-class", "religion": "christian", "politics": "liberal", "sexual_orientation": "heterosexual", "total_height": 70, "polarity": 0.080625, "subjectivity": 0.33026862026862025}}, "12_8": {"generated_text": "James, a 68-year-old Baby Boomer, is a retired school principal who dedicated over three decades to shaping young minds in his suburban community. With a comfortable middle-class lifestyle, he spent his career in education, believing in the transformative power of learning. He identifies as a Christian, attending church regularly, which has provided him a strong sense of community and support throughout his life. Politically, James leans conservative, often advocating for traditional values and educational reforms that emphasize discipline and respect. He is heterosexual and has been happily married to his college sweetheart for nearly 45 years, with whom he has three grown children. Physically, James stands at 5'10\", with a sturdy build that reflects his active lifestyle; he enjoys hiking and gardening. His salt-and-pepper hair, coupled with deep-set blue eyes, gives him a distinguished appearance. He often dresses in casual yet neat clothing, favoring polo shirts and khakis, embodying a relaxed but respectable demeanor.", "attributes": {"occupation": "retired school principal", "socioeconomic_status": "middle-class", "religion": "christian", "politics": "conservative", "sexual_orientation": "heterosexual", "total_height": 70, "polarity": 0.07647058823529411, "subjectivity": 0.35704589528118935}}, "12_9": {"generated_text": "John is a 68-year-old Baby Boomer male who has spent most of his career as a high school history teacher. He is passionate about education and has dedicated his life to shaping young minds. Financially, John is comfortably situated in the middle-class, having invested wisely in his retirement and home. He identifies as a Christian, attending church regularly and finding community and support through his faith. Politically, he leans towards liberal views, advocating for social justice and environmental issues, which often puts him at odds with his more conservative neighbors. John is heterosexual and has been happily married to his college sweetheart for over 40 years. Physically, he stands at 5'10\", with a slightly stocky build, gray hair that he keeps neatly trimmed, and warm brown eyes that reflect his kindness. His casual attire usually consists of comfortable slacks and polo shirts, embodying his laid-back personality. He enjoys gardening and reading historical novels in his spare time, often sharing his love of history with his grandchildren.", "attributes": {"occupation": "teacher", "socioeconomic_status": "middle-class", "religion": "christian", "politics": "liberal", "sexual_orientation": "heterosexual", "total_height": 70, "polarity": 0.13376811594202898, "subjectivity": 0.37433827042522694}}, "12_10": {"generated_text": "John is a 67-year-old Baby Boomer male who spent his career as a high school history teacher, passionate about educating young minds and fostering critical thinking. He has dedicated over 30 years to teaching, earning a comfortable middle-class income that allows him to live in a modest suburban home. John identifies as a Christian, attending church services regularly, which has been a cornerstone of his community involvement. Politically, he leans towards liberal views, advocating for social justice and environmental sustainability. He is heterosexual and has been married to his college sweetheart for over 40 years. Physically, John has a sturdy build, standing at 5'10\". He has thinning gray hair, often styled neatly, and wears glasses that give him a scholarly appearance. His wardrobe consists of comfortable, casual clothing, typically favoring polo shirts and khakis, reflecting his easy-going nature.", "attributes": {"occupation": "teacher", "socioeconomic_status": "middle-class", "religion": "christian", "politics": "liberal", "sexual_orientation": "heterosexual", "total_height": 70, "polarity": 0.04015948963317384, "subjectivity": 0.4101638712165028}}, "12_11": {"generated_text": "John is a 67-year-old retired school teacher who dedicated over 30 years of his life to shaping young minds. He grew up in a middle-class family and, after a fulfilling career, now enjoys a comfortable retirement with a modest pension. John is a practicing Christian who attends church regularly, finding community and solace in his faith. Politically, he identifies as a liberal, advocating for social justice and environmental issues, which aligns with the values he imparted to his students. John is heterosexual and has been married to his college sweetheart for over 40 years, with whom he shares three children. Physically, John has a sturdy build, standing at 5'10\". He has salt-and-pepper hair and often sports a friendly smile, reflecting his approachable personality. His attire typically consists of casual slacks and collared shirts, embodying his easy-going nature and comfort in his own skin.", "attributes": {"occupation": "retired teacher", "socioeconomic_status": "middle-class", "religion": "christian", "politics": "liberal", "sexual_orientation": "heterosexual", "total_height": 70, "polarity": 0.10654761904761903, "subjectivity": 0.4073652537938252}}, "12_12": {"generated_text": "John is a 68-year-old male Baby Boomer who spent most of his career as a high school history teacher. He dedicated over three decades to education, shaping the minds of young students and instilling in them a love for learning. Now retired, he lives comfortably on a pension and savings, placing him in the middle-class socioeconomic status. John identifies as a Christian and attends a local church regularly, finding solace and community in his faith. Politically, he leans towards liberal views, advocating for social justice and environmental issues. John is heterosexual and has been happily married to his wife, Linda, for 45 years. Physically, he stands at 5'10\" with a slightly stocky build, gray hair, and a warm smile that reflects his friendly nature. He enjoys spending time with his grandchildren, gardening, and volunteering at the local food bank.", "attributes": {"occupation": "teacher", "socioeconomic_status": "middle-class", "religion": "christian", "politics": "liberal", "sexual_orientation": "heterosexual", "total_height": 70, "polarity": 0.15535087719298246, "subjectivity": 0.26542702911123967}}, "12_13": {"generated_text": "John is a typical Baby Boomer male, born in the late 1950s, who has spent his life navigating the changing landscapes of America. He works as a high school history teacher, a profession he is passionate about, inspiring young minds with stories from the past. John is comfortably middle-class, having built a stable life through a combination of his teaching salary and a modest pension from his previous job in the private sector. He identifies as a Christian, attending church services regularly, which provides him with a sense of community and belonging. Politically, John leans towards the conservative side, valuing traditional values and fiscal responsibility. He is heterosexual and has been married for over 30 years, with two grown children who have started families of their own. Physically, John stands at 5'10\", with a stocky build that reflects his love for gardening and weekend hiking trips. His hair, once a vibrant brown, has turned to a distinguished gray, and he often sports a friendly smile that puts his students at ease.", "attributes": {"occupation": "teacher", "socioeconomic_status": "middle-class", "religion": "christian", "politics": "conservative", "sexual_orientation": "heterosexual", "total_height": 70, "polarity": 0.10076388888888888, "subjectivity": 0.4347825091575091}}, "12_14": {"generated_text": "John is a 68-year-old Baby Boomer male who spent his career as a high school history teacher, passionately shaping young minds for over three decades. He is now retired, enjoying a comfortable middle-class lifestyle, thanks to a modest pension and savings. Raised in a Christian household, he remains a practicing member of his local church, where he finds community and support. Politically, John leans towards the liberal side, advocating for social justice and environmental issues, reflecting the values he instilled in his students. He identifies as heterosexual and has been happily married for over 40 years. Physically, John has a sturdy build, standing at 5'10\", with salt-and-pepper hair and kind blue eyes that twinkle with warmth and humor. His casual style often consists of polo shirts and khakis, embodying a relaxed yet respectable appearance.", "attributes": {"occupation": "teacher", "socioeconomic_status": "middle-class", "religion": "christian", "politics": "liberal", "sexual_orientation": "heterosexual", "total_height": 70, "polarity": 0.11543859649122808, "subjectivity": 0.3903258145363409}}, "12_15": {"generated_text": "John is a 68-year-old retired school principal who spent over three decades shaping the minds of young students. He grew up in a middle-class household and now enjoys a comfortable retirement, thanks to a modest pension and savings. John identifies as a Christian and attends church regularly, finding solace in his faith and community. Politically, he leans towards conservative values, advocating for traditional education and family structures, though he remains open to discussions about social issues. John is heterosexual and has been happily married to his wife, Linda, for over 40 years. Physically, he has a sturdy build, standing at 5'10\", with graying hair and a friendly smile that reflects his approachable demeanor. His casual attire often consists of khakis and polo shirts, embodying his easygoing nature. John enjoys gardening and spending time with his grandchildren, cherishing family gatherings and the bonds they share.", "attributes": {"occupation": "retired school principal", "socioeconomic_status": "middle-class", "religion": "christian", "politics": "conservative", "sexual_orientation": "heterosexual", "total_height": 70, "polarity": 0.07239583333333333, "subjectivity": 0.3595695970695971}}, "12_16": {"generated_text": "John is a 68-year-old Baby Boomer who has spent his career as a high school history teacher. He is proud to have shaped the minds of many students over the years and is now enjoying a comfortable retirement. Financially, he falls into the middle-class category, having saved diligently throughout his life and invested wisely in a modest home. John identifies as a Christian, attending church regularly, which he believes provides a strong moral foundation. Politically, he leans toward liberal views, advocating for social justice and education reform. John is heterosexual and has been happily married to his wife for over 40 years. Physically, he stands at 5'10\", with a stocky build, gray hair, and warm blue eyes that reflect his friendly demeanor. His typical attire includes casual slacks and a button-down shirt, often paired with a cardigan, embodying a laid-back yet put-together style.", "attributes": {"occupation": "teacher", "socioeconomic_status": "middle-class", "religion": "christian", "politics": "liberal", "sexual_orientation": "heterosexual", "total_height": 70, "polarity": 0.1611904761904762, "subjectivity": 0.4107831850688993}}, "12_17": {"generated_text": "John is a 68-year-old Baby Boomer who has spent most of his life working as a high school history teacher. He has dedicated over 30 years to education, shaping young minds and inspiring students to appreciate the past. Now retired, John enjoys a comfortable middle-class lifestyle, having saved diligently for his retirement and benefiting from a pension. He is a practicing Christian, attending church services regularly, which provides him with a strong sense of community and purpose. Politically, John leans conservative, often advocating for traditional values and fiscal responsibility. He identifies as heterosexual and has been married to his college sweetheart for nearly 50 years. \n\nPhysically, John has a sturdy build, standing at 5'10\" with a few extra pounds around his midsection due to a more sedentary lifestyle in retirement. He has graying hair, often kept short and neat, and wears glasses that give him an intellectual appearance. His wardrobe consists of comfortable, casual clothing, often featuring plaid shirts and khakis, reflecting his laid-back yet practical nature.", "attributes": {"occupation": "teacher", "socioeconomic_status": "middle-class", "religion": "christian", "politics": "conservative", "sexual_orientation": "heterosexual", "total_height": 70, "polarity": 0.10731884057971014, "subjectivity": 0.4123817486860965}}, "12_18": {"generated_text": "George is a 67-year-old Baby Boomer who has spent the majority of his life working as a high school history teacher. He has dedicated over 30 years to education, shaping young minds and inspiring a love for learning. George lives comfortably in a suburban neighborhood, enjoying a middle-class lifestyle, with a modest home filled with books and memorabilia from his travels. He is a practicing Christian, attending services regularly and finding community in his church. Politically, George leans toward liberal views, advocating for social justice and environmental issues, often engaging in discussions about current events with friends and family. He identifies as heterosexual and has been happily married to his wife for over 40 years. Physically, George has a friendly demeanor, standing at 5'10\" with a bit of a belly that reflects his love for cooking and sharing meals with loved ones. He has salt-and-pepper hair, often sporting a neatly trimmed beard, and his warm brown eyes sparkle with kindness and humor.", "attributes": {"occupation": "teacher", "socioeconomic_status": "middle-class", "religion": "christian", "politics": "liberal", "sexual_orientation": "heterosexual", "total_height": 70, "polarity": 0.23896825396825394, "subjectivity": 0.44173556602128033}}, "12_19": {"generated_text": "John is a 68-year-old Baby Boomer male who spent most of his career as a high school history teacher, dedicating his life to educating young minds and sharing his passion for the past. Now retired, he enjoys a comfortable middle-class lifestyle, supported by his pension and savings. Raised in a Christian household, John remains active in his local church, finding community and purpose in its activities. Politically, he leans towards liberal views, advocating for social justice and environmental issues, a reflection of the changing times he has witnessed throughout his life. John identifies as heterosexual and has been married to his college sweetheart for over 40 years. Physically, he stands at 5'10\", with a slightly balding head and a warm smile that reflects his approachable nature. He is often seen wearing casual attire, favoring comfort over style, and his kind blue eyes reveal a lifetime of wisdom and experience.", "attributes": {"occupation": "teacher", "socioeconomic_status": "middle-class", "religion": "christian", "politics": "liberal", "sexual_orientation": "heterosexual", "total_height": 70, "polarity": 0.08966666666666667, "subjectivity": 0.32914285714285707}}, "12_20": {"generated_text": "John is a 67-year-old retired school teacher who spent over 30 years in the education system, passionately shaping young minds. He lives in a suburban neighborhood, enjoying a comfortable middle-class lifestyle, thanks to a solid pension and savings accumulated over his career. A lifelong Methodist, John finds solace and community in his faith, attending church regularly and participating in local charity events. Politically, he leans towards conservative values, often advocating for traditional family structures and fiscal responsibility. John identifies as heterosexual and has been married to his high school sweetheart for over four decades, cherishing their family life with children and grandchildren. Physically, he stands at 5'10\", with a sturdy build that reflects his active lifestyle. He has graying hair and a warm smile that reflects his approachable personality. His attire often consists of comfortable, casual clothing, preferring jeans and button-up shirts, embodying the quintessential retired educator who enjoys gardening and spending time with family.", "attributes": {"occupation": "teacher", "socioeconomic_status": "middle-class", "religion": "christian", "politics": "conservative", "sexual_orientation": "heterosexual", "total_height": 70, "polarity": 0.0965079365079365, "subjectivity": 0.4036403279260422}}, "12_21": {"generated_text": "John is a 68-year-old Baby Boomer who has spent his career as a high school history teacher. He is well-respected in his community and enjoys a comfortable middle-class lifestyle, having saved diligently for retirement. John identifies as a Christian, attending church regularly, which plays a significant role in his life and values. Politically, he leans conservative, often advocating for traditional family values and fiscal responsibility. John is heterosexual and has been married to his wife for over 40 years. \n\nPhysically, John stands at 5'10\", with a sturdy build that reflects his active lifestyle. He has silver hair, which he keeps neatly trimmed, and often sports a pair of wire-rimmed glasses. His wardrobe consists mainly of plaid shirts and khaki trousers, embodying a casual yet put-together appearance. John takes pride in his appearance, ensuring he looks presentable whether he is teaching, attending church, or spending time with his grandchildren.", "attributes": {"occupation": "teacher", "socioeconomic_status": "middle-class", "religion": "christian", "politics": "conservative", "sexual_orientation": "heterosexual", "total_height": 70, "polarity": 0.04756410256410256, "subjectivity": 0.4180600169061707}}, "12_22": {"generated_text": "Jack is a 68-year-old Baby Boomer who has spent his career as a high school teacher, passionately educating students in history and social studies. He retired recently, enjoying a comfortable middle-class lifestyle thanks to a solid pension and savings. Raised in a Christian household, he remains active in his local church, where he finds community and support. Politically, Jack identifies as a liberal, advocating for social justice and environmental issues, reflecting the values he instilled in his students. He is heterosexual and has been happily married to his college sweetheart for over 40 years. Jack stands at 5'10\" with a sturdy build, silver hair, and a warm smile that reflects his approachable nature. He often dresses in casual, comfortable clothing, favoring polo shirts and khakis, embodying a laid-back style typical of his generation.", "attributes": {"occupation": "teacher", "socioeconomic_status": "middle-class", "religion": "christian", "politics": "liberal", "sexual_orientation": "heterosexual", "total_height": 70, "polarity": 0.10140350877192982, "subjectivity": 0.3757894736842105}}, "12_23": {"generated_text": "John is a 67-year-old retired school teacher living in a suburban neighborhood. He spent over 30 years in the education sector, dedicated to shaping young minds and fostering a love for learning. Now enjoying his retirement, John is part of the middle-class, having saved diligently over the years and benefiting from a modest pension. He identifies as a Christian, attending church regularly and participating in community service activities. Politically, John leans conservative, often advocating for traditional values and fiscal responsibility. Throughout his life, he has been a heterosexual man, sharing a loving marriage with his wife for over four decades. \n\nPhysically, John has a sturdy build, standing at 5'10\". His hair, once dark, is now a silvery gray, and he sports a neatly trimmed beard that adds to his distinguished appearance. With warm blue eyes and a friendly smile, he has a welcoming demeanor that makes him approachable. He enjoys dressing comfortably, often seen in casual slacks and button-up shirts, embodying the relaxed style of retirement while still maintaining an air of respectability.", "attributes": {"occupation": "retired teacher", "socioeconomic_status": "middle-class", "religion": "christian", "politics": "conservative", "sexual_orientation": "heterosexual", "total_height": 70, "polarity": 0.14342105263157895, "subjectivity": 0.420339309812994}}, "12_24": {"generated_text": "John is a 67-year-old Baby Boomer who has spent his career as a high school history teacher, passionately imparting knowledge about the past to young minds. He has always been dedicated to his profession and enjoys a comfortable middle-class lifestyle, thanks to his years of teaching and a modest pension. Raised in a Christian household, he continues to attend church regularly, finding community and solace in his faith. Politically, John identifies as a liberal, advocating for social justice and educational reform, which he believes are essential for the progress of society. He is heterosexual and has been happily married to his college sweetheart for over four decades. John has a warm smile and a friendly demeanor, standing at 5'10\" with a slightly graying beard and thinning hair. He typically dresses in casual slacks and button-up shirts, reflecting his laid-back yet professional attitude. His kind blue eyes and approachable nature make him a beloved figure in his community.", "attributes": {"occupation": "teacher", "socioeconomic_status": "middle-class", "religion": "christian", "politics": "liberal", "sexual_orientation": "heterosexual", "total_height": 70, "polarity": 0.11740000000000002, "subjectivity": 0.39667692307692304}}}