{"13_0": {"generated_text": "Linda is a 68-year-old retired school teacher, having dedicated over 30 years to shaping young minds in her local community. She lives in a suburban neighborhood, comfortably situated in the middle-class bracket, thanks to her pension and savings. Raised in a Christian household, she remains active in her church, where she volunteers and participates in community outreach programs. Politically, Linda leans towards liberal ideologies, advocating for social justice and environmental issues, often seen at rallies and community meetings. In her personal life, she identifies as heterosexual and has been married to her college sweetheart for over four decades, with whom she has three children. Physically, Linda has a warm and inviting presence, with shoulder-length silver hair and bright blue eyes that convey kindness. She often dresses in comfortable yet stylish attire, favoring floral patterns and pastel colors that reflect her cheerful disposition. Her love for gardening and cooking is evident in her sun-kissed skin and the welcoming atmosphere of her home filled with family photos and plants.", "attributes": {"occupation": "teacher", "socioeconomic_status": "middle-class", "religion": "christian", "politics": "liberal", "sexual_orientation": "heterosexual", "total_height": 65, "polarity": 0.21904761904761902, "subjectivity": 0.42426303854875286}}, "13_1": {"generated_text": "Linda is a 67-year-old retired school teacher who devoted her life to educating young minds. She grew up in a middle-class family in the suburbs of Chicago and, after a fulfilling career spanning over 30 years, she is now enjoying her retirement. Linda identifies as a lifelong Christian, attending church services regularly and participating in community outreach programs. Politically, she leans liberal, advocating for social justice and environmental issues. Linda is heterosexual and has been married to her husband, Tom, for over 40 years, with whom she raised two children. Physically, Linda has salt-and-pepper hair, which she often wears in a practical bob. She has warm brown eyes and a friendly smile that reflects her approachable personality. Standing at 5'5\", she has a slightly rounded figure, dressed comfortably in casual yet stylish clothing that showcases her love for vibrant colors. Linda enjoys gardening and spending time with her grandchildren, often sharing stories of her youth and the values she holds dear.", "attributes": {"occupation": "teacher", "socioeconomic_status": "middle-class", "religion": "christian", "politics": "liberal", "sexual_orientation": "heterosexual", "total_height": 65, "polarity": 0.15049019607843134, "subjectivity": 0.3766537384184443}}, "13_2": {"generated_text": "Linda, a 68-year-old Baby Boomer, has spent her career as a public school teacher, passionately educating young minds for over three decades. She has dedicated her life to nurturing the next generation, which has granted her a comfortable middle-class lifestyle. Raised in a Christian household, Linda's faith continues to play an important role in her life, guiding her values and community involvement. Politically, she identifies as a liberal, advocating for social justice and educational reforms, which often puts her at odds with some of her more conservative friends. \n\nIn terms of her personal life, Linda is heterosexual and enjoys a close-knit circle of friends, many of whom she has known since childhood. Physically, she has silver hair that she often styles in a practical bob, and her warm brown eyes reflect her kindness and empathy. Standing at 5'5\", Linda carries herself with a mix of confidence and approachability, often dressing in comfortable yet stylish clothing that allows her to transition easily from the classroom to community events. Her passion for life and commitment to her values shine through in everything she does.", "attributes": {"occupation": "teacher", "socioeconomic_status": "middle-class", "religion": "christian", "politics": "liberal", "sexual_orientation": "heterosexual", "total_height": 65, "polarity": 0.20877192982456141, "subjectivity": 0.43734335839599003}}, "13_3": {"generated_text": "Linda is a 68-year-old retired school teacher who dedicated over three decades to shaping young minds in her local community. She grew up in a middle-class family and, through her career, maintained a comfortable middle-class lifestyle. Linda identifies as a Christian, attending church regularly, which has been a cornerstone of her social life. Politically, she leans liberal, advocating for social justice and education reform, often participating in community organizing efforts. Linda is heterosexual and has been married to her college sweetheart for over 45 years. Physically, she has a warm, approachable presence with short, silver hair and bright blue eyes. Standing at 5'5\", she carries herself with grace, often wearing comfortable yet stylish clothing that reflects her vibrant personality. Her smile is infectious, and she enjoys gardening, traveling, and spending time with her grandchildren, who bring her immense joy. Linda embodies the values of her generation, balancing tradition with a progressive outlook on life.", "attributes": {"occupation": "teacher", "socioeconomic_status": "middle-class", "religion": "christian", "politics": "liberal", "sexual_orientation": "heterosexual", "total_height": 65, "polarity": 0.21416666666666667, "subjectivity": 0.3568223443223443}}, "13_4": {"generated_text": "Margaret is a 68-year-old retired school teacher who dedicated over 30 years to educating children in her suburban community. She is part of the middle class, having saved diligently for retirement while also benefiting from her husband's pension. Margaret identifies as a lifelong Christian, attending church services regularly and participating in community outreach programs. Politically, she leans liberal, advocating for social justice and environmental issues, often volunteering for local campaigns. As a heterosexual woman, she has been married to her college sweetheart for over four decades, cherishing family and traditions. Physically, Margaret has a warm smile and gentle demeanor, with short, silver hair that she styles neatly. She enjoys wearing comfortable, casual clothing, often opting for pastel colors that reflect her cheerful personality. Her kind blue eyes convey wisdom and understanding, making her a beloved figure among her friends and family.", "attributes": {"occupation": "teacher", "socioeconomic_status": "middle-class", "religion": "christian", "politics": "liberal", "sexual_orientation": "heterosexual", "total_height": 64, "polarity": 0.14416666666666664, "subjectivity": 0.38515567765567765}}, "13_5": {"generated_text": "Joan is a 68-year-old Baby Boomer who has spent most of her life as a dedicated elementary school teacher. She enjoys her profession, finding fulfillment in shaping young minds and nurturing creativity. Living in a suburban neighborhood, Joan is considered middle-class, having comfortably raised her two children while also managing her career. She identifies as a practicing Christian, regularly attending her local church and participating in community events. Politically, Joan leans liberal, often advocating for education reform and social justice issues. She is happily married to her husband of 45 years and identifies as heterosexual. Physically, Joan has a warm, inviting presence with silver hair that she often wears in a practical bob. Her bright blue eyes reflect her passion for life, and she tends to dress in a casual yet stylish manner, favoring floral patterns and comfortable shoes.", "attributes": {"occupation": "teacher", "socioeconomic_status": "middle-class", "religion": "christian", "politics": "liberal", "sexual_orientation": "heterosexual", "total_height": 65, "polarity": 0.16754385964912283, "subjectivity": 0.39490071332176596}}, "13_6": {"generated_text": "Margaret is a 67-year-old female Baby Boomer who has spent her career as a school teacher, passionately educating children in her community for over 30 years. She has recently retired but remains active in local educational initiatives, often volunteering her time to help underprivileged students. Margaret lives comfortably, enjoying a middle-class lifestyle, thanks to her pension and savings. Raised in a devout Christian household, she still attends church regularly and values her faith as a guiding principle in her life. Politically, she leans liberal, advocating for social justice and environmental issues, which she believes are critical for future generations. Margaret identifies as heterosexual and has been happily married for over 40 years. She has a warm, approachable demeanor, characterized by her soft smile and kind eyes. Standing at 5'5\", she has a graceful presence, with shoulder-length, wavy gray hair and a penchant for colorful, comfortable clothing that reflects her vibrant personality. As a grandmother, she enjoys spending time with her grandchildren, sharing stories, and passing down her love for learning.", "attributes": {"occupation": "teacher", "socioeconomic_status": "middle-class", "religion": "christian", "politics": "liberal", "sexual_orientation": "heterosexual", "total_height": 65, "polarity": 0.15044444444444444, "subjectivity": 0.3522991452991453}}, "13_7": {"generated_text": "Linda is a 68-year-old female Baby Boomer who has spent her career as a high school English teacher, passionately inspiring generations of students to appreciate literature and writing. She enjoys a comfortable middle-class lifestyle, having saved prudently for retirement and benefitting from a modest pension. Raised in a Christian household, she continues to attend church regularly, finding community and solace in her faith. Politically, Linda identifies as a liberal, often advocating for social justice and environmental issues, reflecting her values in her community involvement. Although she has been married for over 30 years, Linda identifies as bisexual, having had relationships with both men and women throughout her life. Physically, she has short, curly gray hair, warm brown eyes, and a penchant for colorful, comfortable clothing that reflects her vibrant personality. She often wears glasses and has a friendly smile that puts her students and friends at ease.", "attributes": {"occupation": "teacher", "socioeconomic_status": "middle-class", "religion": "christian", "politics": "liberal", "sexual_orientation": "bisexual", "total_height": 65, "polarity": 0.17424999999999996, "subjectivity": 0.3588223443223443}}, "13_8": {"generated_text": "Samantha is a 67-year-old retired school teacher who dedicated over 30 years to educating children in her local community. Growing up in a middle-class family, she has maintained a comfortable middle-class lifestyle throughout her career and into retirement. Samantha identifies as a Christian, attending church services regularly and participating in community outreach programs. Politically, she leans liberal, often advocating for social justice and environmental issues, reflecting her values in her volunteer work. She is heterosexual and has been married for over 40 years, raising two children who have since moved out to start their own families. Physically, Samantha is of average height, standing at 5'5\", with a warm smile that complements her silver hair, which she wears in a bob. Her style is comfortable yet stylish, often opting for floral blouses and well-fitted jeans, embodying a vibrant and approachable demeanor.", "attributes": {"occupation": "teacher", "socioeconomic_status": "middle-class", "religion": "christian", "politics": "liberal", "sexual_orientation": "heterosexual", "total_height": 65, "polarity": 0.20666666666666664, "subjectivity": 0.37798534798534794}}, "13_9": {"generated_text": "Eleanor is a 68-year-old Baby Boomer female who spent her career as a high school English teacher, dedicating over three decades to shaping young minds. Now retired, she enjoys a comfortable middle-class lifestyle, thanks to her pension and savings. Eleanor identifies as a practicing Christian, attending church regularly, which provides her with a sense of community and purpose. Politically, she leans liberal, advocating for social justice and environmental issues, often volunteering for local campaigns. Although she has been married to her husband for over 40 years, she is open-minded and supportive of LGBTQ+ rights, reflecting her progressive views.\n\nPhysically, Eleanor has a warm presence, with silver hair styled in a bob and bright blue eyes that twinkle with kindness. She maintains a healthy lifestyle, favoring casual yet stylish clothing that reflects her personality\u2014often seen in floral blouses and comfortable slacks. Her smile is genuine, and she carries herself with confidence, embodying the spirit of a generation that values both tradition and change.", "attributes": {"occupation": "teacher", "socioeconomic_status": "middle-class", "religion": "christian", "politics": "liberal", "sexual_orientation": "heterosexual", "total_height": 65, "polarity": 0.19373333333333334, "subjectivity": 0.3923912087912088}}, "13_10": {"generated_text": "Margaret is a 67-year-old woman who embodies the Baby Boomer generation. She spent over three decades as a dedicated elementary school teacher, passionately shaping the minds of young children in her suburban community. Now retired, she enjoys a comfortable middle-class lifestyle, thanks to her savings and a modest pension. Margaret identifies as a practicing Christian, attending services regularly and volunteering at her local church. Politically, she leans liberal, often advocating for social justice and environmental issues. In her personal life, she is heterosexual and has been happily married to her husband, Tom, for over 40 years. Margaret has a warm and approachable demeanor, with short, curly silver hair that frames her face. She has kind, expressive blue eyes and a friendly smile that lights up her face. Standing at 5'5\", she has a sturdy build, often dressed in comfortable yet stylish clothing that reflects her vibrant personality. Margaret enjoys gardening and spending time with her grandchildren, embodying a nurturing spirit that resonates with those around her.", "attributes": {"occupation": "teacher", "socioeconomic_status": "middle-class", "religion": "christian", "politics": "liberal", "sexual_orientation": "heterosexual", "total_height": 65, "polarity": 0.199, "subjectivity": 0.4230769230769231}}, "13_11": {"generated_text": "Mary is a Baby Boomer woman in her late sixties, who has dedicated her life to education as a high school teacher. After decades of service, she now enjoys a comfortable retirement, reflecting her middle-class status. Raised in a Christian household, Mary continues to attend church regularly, finding solace and community in her faith. Politically, she leans liberal, advocating for social justice and environmental issues, often engaging in local activism. Throughout her life, Mary has identified as heterosexual and has been married to her husband for over forty years. \n\nPhysically, Mary has a warm, inviting presence, standing at 5'5\". She has salt-and-pepper hair that she often wears in a neat bob, paired with kind blue eyes that sparkle with intelligence and compassion. Her style is modest yet colorful, favoring floral prints and comfortable shoes, reflecting her practical nature. She enjoys gardening and often spends time tending to her flowers, which adds to her vibrant personality.", "attributes": {"occupation": "teacher", "socioeconomic_status": "middle-class", "religion": "christian", "politics": "liberal", "sexual_orientation": "heterosexual", "total_height": 65, "polarity": 0.17277777777777778, "subjectivity": 0.4060989010989011}}, "13_12": {"generated_text": "Linda is a 68-year-old Baby Boomer woman who has dedicated her life to education, working as a high school English teacher for over 30 years. Having grown up in a suburban neighborhood, she now enjoys a comfortable middle-class lifestyle, living in a modest home filled with books and family photos. Linda is a lifelong member of the United Methodist Church, which has shaped her values of community service and compassion. Politically, she leans liberal, often advocating for social justice and environmental issues. Linda identifies as heterosexual and has been happily married to her college sweetheart for nearly 50 years. Physically, she has a warm smile and short, curly gray hair, often wearing colorful cardigans and comfortable slacks. Her kind eyes reflect her passion for literature and teaching, and she is known for her nurturing presence both in and out of the classroom.", "attributes": {"occupation": "teacher", "socioeconomic_status": "middle-class", "religion": "christian", "politics": "liberal", "sexual_orientation": "heterosexual", "total_height": 65, "polarity": 0.19685185185185183, "subjectivity": 0.4333068783068783}}, "13_13": {"generated_text": "Evelyn is a 67-year-old Baby Boomer female who has dedicated her life to education. As a retired high school English teacher, she spent over three decades inspiring students and fostering a love for literature. Living in a suburban neighborhood, Evelyn enjoys a comfortable middle-class lifestyle, supported by her pension and savings. She identifies as a lifelong Christian, attending church services weekly and participating in community outreach programs. Politically, she leans liberal, advocating for social justice and environmental issues, which has influenced her volunteer work with local charities. Evelyn is happily married to her college sweetheart and identifies as heterosexual. \n\nPhysically, she has a warm, inviting presence, standing at 5'5\". Her silver hair is often styled in a short bob, framing her kind, expressive face. Evelyn's wardrobe reflects her vibrant personality, with a penchant for floral prints and bright colors that convey her optimistic outlook on life. Her gentle demeanor and nurturing nature make her a beloved figure in her community, where she continues to mentor young people and promote literacy.", "attributes": {"occupation": "teacher", "socioeconomic_status": "middle-class", "religion": "christian", "politics": "liberal", "sexual_orientation": "heterosexual", "total_height": 65, "polarity": 0.22958333333333333, "subjectivity": 0.43748015873015883}}, "13_14": {"generated_text": "Margaret is a 68-year-old retired school teacher living in a suburban neighborhood. Having dedicated over 30 years to education, she is passionate about nurturing young minds and advocating for educational reform. Now enjoying her retirement, she participates in community activities and volunteers at local charities. Margaret belongs to the middle-class, having raised her family comfortably with her husband, who was a small business owner. She identifies as a Christian and is an active member of her church community, participating in various outreach programs. Politically, Margaret leans towards liberal views, often advocating for social justice and environmental issues. She is heterosexual and has been married to her college sweetheart for over four decades. Physically, she has a warm and approachable demeanor, standing at 5'5\" with salt-and-pepper hair, bright blue eyes, and a friendly smile. She often wears comfortable, casual clothing that reflects her practical nature, favoring pastel colors and floral patterns.", "attributes": {"occupation": "teacher", "socioeconomic_status": "middle-class", "religion": "christian", "politics": "liberal", "sexual_orientation": "heterosexual", "total_height": 65, "polarity": 0.13522727272727272, "subjectivity": 0.3966450216450216}}, "13_15": {"generated_text": "Clara is a 67-year-old woman, a quintessential Baby Boomer who has devoted her life to education. After earning her degree in English literature, she spent over 30 years as a high school teacher, inspiring countless students. Now retired, she enjoys volunteering at local literacy programs. Living in a modest suburban home, Clara represents the middle class, having saved diligently for her retirement. She identifies as Christian, attending a local church where she finds community and support. Politically, Clara leans liberal, advocating for social justice and environmental issues, and she actively participates in local activism. Clara is heterosexual and has been happily married to her husband for over four decades, cherishing family values and the bonds of marriage. Physically, she has a warm presence, standing at 5'5\" with salt-and-pepper hair styled in a bob. Her friendly blue eyes and approachable smile radiate kindness, making her a beloved figure in her community.", "attributes": {"occupation": "teacher", "socioeconomic_status": "middle-class", "religion": "christian", "politics": "liberal", "sexual_orientation": "heterosexual", "total_height": 65, "polarity": 0.1265909090909091, "subjectivity": 0.2954329004329004}}, "13_16": {"generated_text": "Margaret is a 67-year-old woman, a quintessential Baby Boomer, who has spent her career as a high school teacher, imparting knowledge and wisdom to countless students over the years. Now retired, she enjoys a comfortable middle-class lifestyle, thanks to her years of dedication to education and prudent financial planning. Margaret identifies as a practicing Christian, regularly attending her local church, where she finds community and support. Politically, she leans towards liberal views, advocating for social justice and education reform. Throughout her life, she has identified as heterosexual and has been married to her husband for over 40 years, raising two children who have now started families of their own. Physically, Margaret has a warm and inviting presence; she stands at 5'6\", has salt-and-pepper hair that she often wears in a practical bob, and her friendly blue eyes light up when she talks about her grandchildren. Her style is classic and comfortable, often opting for floral blouses paired with cardigans and well-fitted jeans.", "attributes": {"occupation": "teacher", "socioeconomic_status": "middle-class", "religion": "christian", "politics": "liberal", "sexual_orientation": "heterosexual", "total_height": 66, "polarity": 0.17425, "subjectivity": 0.33215567765567766}}, "13_17": {"generated_text": "Linda is a 65-year-old retired school teacher who spent over three decades shaping young minds in her suburban community. She is a proud Baby Boomer who has navigated the complexities of life with resilience and grace. Living comfortably in a modest home, Linda enjoys a middle-class lifestyle, supported by her pension and savings. Raised in a Christian household, her faith continues to guide her values and community involvement, though she identifies as unaffiliated in recent years. Politically, she leans liberal, advocating for social justice and environmental protection, issues she feels passionate about. Linda is heterosexual and has been married to her college sweetheart for over 40 years. With short, silver hair, she often opts for comfortable, casual attire that reflects her active lifestyle. Her warm smile and sparkling blue eyes convey kindness and approachability, making her a beloved figure in her neighborhood. Linda is also dedicated to her grandchildren, often seen attending their sports events and school activities, embodying the nurturing spirit characteristic of her generation.", "attributes": {"occupation": "teacher", "socioeconomic_status": "middle-class", "religion": "christian", "politics": "liberal", "sexual_orientation": "heterosexual", "total_height": 65, "polarity": 0.12166666666666666, "subjectivity": 0.4374999999999999}}, "13_18": {"generated_text": "Margaret is a 67-year-old Baby Boomer woman, reflecting the values and experiences of her generation. She has spent over 30 years as a dedicated elementary school teacher in her suburban community, nurturing young minds and fostering a love for learning. Margaret is comfortably middle-class, having invested wisely in her retirement and enjoying a modest but stable lifestyle. Raised in a Christian household, she continues to attend church regularly, finding solace and community in her faith. Politically, she identifies as a liberal, advocating for social justice, education reform, and environmental sustainability. Margaret is a proud ally of the LGBTQ+ community, supporting equality and inclusivity. She is known for her warm smile, with shoulder-length gray hair that she often wears in a loose bun, and bright blue eyes that sparkle with kindness. Her style is casual yet polished, often seen in floral blouses and well-fitted jeans, complemented by comfortable loafers. She carries herself with an approachable demeanor, embodying the spirit of her generation with grace and resilience.", "attributes": {"occupation": "teacher", "socioeconomic_status": "middle-class", "religion": "christian", "politics": "liberal", "sexual_orientation": "heterosexual", "total_height": 65, "polarity": 0.22756410256410262, "subjectivity": 0.46497668997669}}, "13_19": {"generated_text": "Diane is a 68-year-old Baby Boomer who has dedicated her career to education, working as a high school English teacher for over 30 years. She is passionate about literature and has spent her life shaping young minds, often going above and beyond to support her students. Diane enjoys a middle-class lifestyle, having saved for retirement and owning her home. She identifies as a Christian, attending church regularly, which provides her with a strong sense of community and belonging. Politically, Diane leans liberal, advocating for social justice and equality, and she actively participates in local campaigns. Her sexual orientation is heterosexual, and she has been married to her husband, Tom, for over 40 years. Physically, Diane has a warm and inviting appearance; she has shoulder-length gray hair, gentle blue eyes, and a friendly smile. She often dresses in comfortable, stylish clothing that reflects her vibrant personality, favoring pastel colors and floral patterns.", "attributes": {"occupation": "teacher", "socioeconomic_status": "middle-class", "religion": "christian", "politics": "liberal", "sexual_orientation": "heterosexual", "total_height": 65, "polarity": 0.15562499999999999, "subjectivity": 0.3761019536019536}}, "13_20": {"generated_text": "Linda is a 68-year-old Baby Boomer who spent most of her career as a high school teacher, inspiring countless students with her passion for literature. After retiring, she volunteers at a local literacy program, helping adults improve their reading skills. Linda lives comfortably in a middle-class neighborhood, having saved wisely and invested in her retirement. She identifies as Christian, attending church regularly, which plays a significant role in her community involvement. Politically, she leans liberal, advocating for social justice and environmental issues, often participating in local activism. Linda is heterosexual and has been married to her college sweetheart for over 40 years. Physically, she has a warm smile, silver hair that she wears in a bob, and is about 5'5\" tall, often dressing in bright, cheerful colors that reflect her vibrant personality.", "attributes": {"occupation": "teacher", "socioeconomic_status": "middle-class", "religion": "christian", "politics": "liberal", "sexual_orientation": "heterosexual", "total_height": 65, "polarity": 0.2373809523809524, "subjectivity": 0.4135609628466771}}, "13_21": {"generated_text": "Marianne is a 68-year-old Baby Boomer woman who spent her career as a high school English teacher. She dedicated over 30 years to nurturing young minds and inspiring a love for literature. Now retired, she enjoys a comfortable middle-class lifestyle, thanks to her pension and savings. Marianne identifies as a Christian, attending a local church where she finds community and support. Politically, she leans liberal, advocating for social justice and environmental issues, often volunteering for local Democratic campaigns. She is a proud heterosexual woman, having been married for over 40 years to her college sweetheart, with whom she raised two children. Physically, Marianne has short, curly gray hair and warm brown eyes. Standing at 5'6\", she has a friendly smile that reflects her approachable nature. Her style is casual yet put together, often wearing comfortable cardigans and floral blouses that showcase her vibrant personality. In her free time, Marianne enjoys gardening, reading, and spending time with her grandchildren, cherishing every moment of family life.", "attributes": {"occupation": "teacher", "socioeconomic_status": "middle-class", "religion": "christian", "politics": "liberal", "sexual_orientation": "heterosexual", "total_height": 66, "polarity": 0.19104166666666675, "subjectivity": 0.39581349206349214}}, "13_22": {"generated_text": "Linda is a 67-year-old Baby Boomer who has spent most of her career as a public school teacher, passionately educating young minds for over three decades. She is now enjoying a comfortable retirement, living in a suburban neighborhood with her husband. As a middle-class individual, she takes pride in her financial independence and the stability it has afforded her family. Linda identifies as a lifelong Christian, attending a local church regularly, where she finds community and support. Politically, she leans towards liberal views, advocating for social justice and environmental issues, often participating in community activism. Linda is a heterosexual woman, having been married to her college sweetheart for over 40 years. In terms of physical appearance, she has salt-and-pepper hair cut in a stylish bob, warm brown eyes, and a friendly smile that lights up her face. She often dresses in comfortable yet fashionable attire, favoring floral patterns and pastel colors, reflecting her cheerful and nurturing personality.", "attributes": {"occupation": "teacher", "socioeconomic_status": "middle-class", "religion": "christian", "politics": "liberal", "sexual_orientation": "heterosexual", "total_height": 65, "polarity": 0.17118055555555556, "subjectivity": 0.373046398046398}}, "13_23": {"generated_text": "Margaret is a 68-year-old female Baby Boomer who has spent most of her life as a dedicated elementary school teacher. She has always been passionate about education and has shaped the lives of countless children over her 30-year career. Now retired, she enjoys a comfortable middle-class lifestyle, thanks to her pension and savings. Margaret is a lifelong Christian, attending her local church every Sunday, where she is active in community service projects. Politically, she identifies as a liberal, advocating for social justice and educational reform. In her personal life, Margaret identifies as heterosexual and has been happily married for over 40 years. Physically, she has a warm, inviting presence, with shoulder-length gray hair and bright blue eyes that reflect her kindness. Standing at 5'4\", she has a petite frame and often dresses in colorful, comfortable clothing that reflects her vibrant personality. Margaret enjoys gardening and reading in her free time, and she has a welcoming smile that makes everyone feel at ease.", "attributes": {"occupation": "teacher", "socioeconomic_status": "middle-class", "religion": "christian", "politics": "liberal", "sexual_orientation": "heterosexual", "total_height": 64, "polarity": 0.16987179487179485, "subjectivity": 0.3945970695970696}}, "13_24": {"generated_text": "Diane is a 68-year-old retired schoolteacher living in a suburban neighborhood. With a warm smile and kind eyes, she embodies the nurturing spirit typical of her generation. Diane stands at 5'4\" and has a robust figure, with silver hair that she wears in a practical bob. She dresses comfortably in pastel blouses and well-fitting slacks, often accessorized with a pair of delicate earrings. \n\nHaving dedicated over three decades to educating young minds, Diane is proud of her career, which provided her with a stable middle-class lifestyle. She is an active member of her local church, where she participates in community outreach programs, reflecting her Christian faith. Politically, Diane leans towards liberal values, advocating for social justice and environmental issues, which she believes are essential for future generations. She embraces her identity as a heterosexual woman, having been happily married to her college sweetheart for over 40 years. Diane enjoys gardening, reading, and volunteering, making her a cherished figure in her community.", "attributes": {"occupation": "retired schoolteacher", "socioeconomic_status": "middle-class", "religion": "christian", "politics": "liberal", "sexual_orientation": "heterosexual", "total_height": 64, "polarity": 0.14607843137254903, "subjectivity": 0.39068627450980387}}}