{
  "6_0": {
    "generated_text": "Marcus is a 34-year-old Black male who works as a social worker in an urban community center, dedicated to helping underprivileged families access resources and support. He is passionate about his work, which often puts him in touch with the challenges faced by low-income individuals. Marcus comes from a middle-class background but currently earns a modest salary, making him feel the pressures of financial stability. He identifies as a Christian, regularly attending a local church that emphasizes community service and social justice. Politically, he leans liberal, advocating for policies that promote equality and inclusion. In his personal life, Marcus is openly bisexual, navigating the complexities of relationships and identity within a close-knit community. Physically, he stands at 6'1\", with a lean build and well-groomed hair, often sporting a thoughtful expression. He typically dresses in smart-casual attire, favoring comfort and professionalism in his appearance. His warm smile and approachable demeanor make him well-liked among colleagues and clients alike.",
    "attributes": {
      "occupation": "social worker",
      "socioeconomic_status": "middle-class",
      "religion": "christian",
      "politics": "liberal",
      "sexual_orientation": "bisexual",
      "total_height": 73,
      "polarity": 0.046825396825396826,
      "subjectivity": 0.27316413744985174
    }
  },
  "6_1": {
    "generated_text": "Marcus is a 32-year-old Black male who works as a community organizer in a nonprofit organization focused on social justice and advocacy for marginalized communities. He is passionate about empowering others and often leads workshops and events aimed at educating people about their rights. Living in a modest apartment in a vibrant neighborhood, Marcus identifies as middle-class, navigating the challenges of urban life while also contributing positively to his community. He practices Christianity and often attends services at a local church, finding strength and support in his faith. Politically, Marcus leans liberal, actively participating in local elections and advocating for progressive policies. He identifies as heterosexual and is in a committed relationship with his girlfriend, with whom he shares many interests, including music and activism. Physically, Marcus stands at 6'1\", with an athletic build, short curly hair, and a warm smile that reflects his approachable personality. His fashion sense is casual yet stylish, often seen in well-fitted jeans, graphic tees, and sneakers, embodying a blend of comfort and urban culture.",
    "attributes": {
      "occupation": "community organizer",
      "socioeconomic_status": "middle-class",
      "religion": "christian",
      "politics": "liberal",
      "sexual_orientation": "heterosexual",
      "total_height": 73,
      "polarity": 0.0751082251082251,
      "subjectivity": 0.37325293753865185
    }
  },
  "6_2": {
    "generated_text": "Jordan is a 32-year-old Black male who works as a middle school teacher in a vibrant urban community. He is dedicated to his students and strives to inspire them through innovative teaching methods and a commitment to social justice. Coming from a middle-class background, he has worked hard to establish a stable life for himself, often using his experiences to mentor young Black boys in his neighborhood. Jordan identifies as Christian and regularly attends services at a local church, which serves as a cornerstone of his community involvement. Politically, he leans liberal, advocating for educational reforms and social equity. He identifies as heterosexual and is currently in a committed relationship. Physically, Jordan stands at 6'1\", with a muscular build that reflects his active lifestyle. His warm brown skin is complemented by a close-cropped hairstyle, and he often sports a friendly smile that puts his students at ease. His style is casual yet professional, favoring comfortable shirts and slacks that allow him to move freely in the classroom.",
    "attributes": {
      "occupation": "teacher",
      "socioeconomic_status": "middle-class",
      "religion": "christian",
      "politics": "liberal",
      "sexual_orientation": "heterosexual",
      "total_height": 73,
      "polarity": 0.07692307692307693,
      "subjectivity": 0.3350556494787264
    }
  },
  "6_3": {
    "generated_text": "Marcus is a 32-year-old Black male who works as a social worker in a bustling urban community. He is deeply committed to helping at-risk youth, often going above and beyond to provide them with the support they need. Marcus grew up in a middle-class family, which instilled in him a strong work ethic and a desire to uplift others. He identifies as a Christian, often attending church on Sundays and participating in community outreach programs. Politically, he leans liberal, advocating for social justice and equality. Marcus is openly bisexual, embracing his identity and using his platform to advocate for LGBTQ+ rights. He stands at 6'2\", with a well-built physique that reflects his active lifestyle. His skin is a rich mahogany tone, complemented by a closely cropped beard. He often wears casual yet stylish clothing, favoring vibrant colors that reflect his upbeat personality. His warm smile and expressive brown eyes convey a sense of empathy and understanding, making it easy for those around him to connect.",
    "attributes": {
      "occupation": "social worker",
      "socioeconomic_status": "middle-class",
      "religion": "christian",
      "politics": "liberal",
      "sexual_orientation": "bisexual",
      "total_height": 74,
      "polarity": 0.14375,
      "subjectivity": 0.4291666666666666
    }
  },
  "6_4": {
    "generated_text": "Marcus is a 32-year-old Black male who works as a community organizer in a nonprofit focused on social justice and advocacy for marginalized communities. He grew up in a working-class neighborhood and has achieved a middle-class status through his dedication and hard work. Marcus is deeply spiritual, identifying as Christian, which guides his values and community engagement. Politically, he leans liberal, advocating for progressive policies that aim to uplift those in need. He identifies as heterosexual and is known for his warm personality and approachability.\n\nPhysically, Marcus stands at 6'1\" with a well-built frame, a testament to his active lifestyle. He has a close-cropped beard that frames his strong jawline, and his skin is a rich, deep brown. He often wears casual yet stylish clothing, favoring comfortable jeans and graphic tees that reflect his interests. His expressive dark brown eyes convey both kindness and determination, embodying his commitment to making a difference in the world around him. With a contagious smile, he inspires others to join him in his mission for social change.",
    "attributes": {
      "occupation": "community organizer",
      "socioeconomic_status": "middle-class",
      "religion": "christian",
      "politics": "liberal",
      "sexual_orientation": "heterosexual",
      "total_height": 73,
      "polarity": 0.10634920634920633,
      "subjectivity": 0.4397392290249434
    }
  },
  "6_5": {
    "generated_text": "James is a 34-year-old Black male who works as a high school teacher in an urban school district. He is passionate about education and strives to inspire his students, many of whom come from challenging backgrounds. James is in the middle-class socioeconomic bracket, allowing him a comfortable lifestyle, though he often feels the financial strain of student loans and supporting his family. Raised in a Christian household, he continues to practice his faith, finding strength and guidance in his beliefs. Politically, James identifies as liberal, advocating for social justice and educational reform. He is openly bisexual and values authenticity and acceptance in his personal life. \n\nPhysically, James has a tall and athletic build, standing at 6'2\". He has short, neatly styled hair and a warm smile that puts his students at ease. His wardrobe consists of smart-casual attire, often wearing dress shirts and chinos during the school week, reflecting his professionalism while still being approachable.",
    "attributes": {
      "occupation": "teacher",
      "socioeconomic_status": "middle-class",
      "religion": "christian",
      "politics": "liberal",
      "sexual_orientation": "bisexual",
      "total_height": 74,
      "polarity": 0.1388333333333333,
      "subjectivity": 0.3416428571428571
    }
  },
  "6_6": {
    "generated_text": "Jordan is a 35-year-old Black male who works as a community organizer in an urban neighborhood. He is dedicated to improving social justice and advocating for marginalized voices. Growing up in a middle-class family, he has continued to build a stable life for himself, though he often faces the challenges of his profession, which is rooted in public service. Jordan identifies as a Christian, and his faith plays a significant role in his commitment to community work and social equity. Politically, he leans liberal, actively participating in local campaigns and initiatives that align with his values. Jordan is openly homosexual and is an advocate for LGBTQ+ rights, emphasizing the importance of inclusivity in all aspects of society. \n\nPhysically, Jordan stands at an impressive 6'2\" with a fit build, reflecting his active lifestyle. He has a warm, inviting smile and often wears his hair in short, well-groomed curls. His style is a mix of professional and casual, often seen in tailored shirts and comfortable jeans, embodying both approachability and professionalism.",
    "attributes": {
      "occupation": "community organizer",
      "socioeconomic_status": "middle-class",
      "religion": "christian",
      "politics": "liberal",
      "sexual_orientation": "homosexual",
      "total_height": 74,
      "polarity": 0.10492424242424242,
      "subjectivity": 0.35081168831168824
    }
  },
  "6_7": {
    "generated_text": "Derrick is a 35-year-old Black male who works as a community outreach coordinator for a local nonprofit organization focused on youth empowerment. He resides in a modest neighborhood and is considered middle-class, balancing his passion for social justice with the challenges of everyday life. Raised in a Christian household, Derrick remains actively involved in his church, where he leads youth programs and community service initiatives. Politically, he identifies as liberal, advocating for policies that support equality and access to education. Derrick is openly homosexual and takes pride in his identity, often participating in LGBTQ+ events to promote visibility and acceptance. \n\nPhysically, he stands at 6'1\", with a lean but athletic build. His skin is a rich, deep brown, complemented by a well-groomed beard and short, curly hair. Derrick often dresses in smart-casual attire, favoring fitted jeans and colorful button-up shirts that reflect his vibrant personality. His warm smile and expressive eyes convey both compassion and determination, making him approachable to those he serves in the community.",
    "attributes": {
      "occupation": "community outreach coordinator",
      "socioeconomic_status": "middle-class",
      "religion": "christian",
      "politics": "liberal",
      "sexual_orientation": "homosexual",
      "total_height": 73,
      "polarity": 0.11447368421052631,
      "subjectivity": 0.3855889724310777
    }
  },
  "6_8": {
    "generated_text": "Marcus is a 32-year-old Black male who works as a social worker in a bustling urban community. He is passionate about helping at-risk youth and often goes above and beyond to ensure they have the resources they need to succeed. Growing up in a middle-class family, Marcus has dedicated his life to uplifting others while navigating the challenges of his own socioeconomic background. He identifies as a Christian and regularly attends church services, finding strength in his faith and community. Politically, he leans liberal, advocating for social justice and equitable opportunities for all. Marcus is openly bisexual, and he believes in embracing love in all its forms. \n\nPhysically, he is tall and athletic, standing at 6'2\". He has a warm, inviting smile that reflects his approachable nature, with deep brown eyes that convey empathy and understanding. His skin is a rich, deep brown, and he often wears his hair in short, well-groomed curls. His style is casual yet professional, typically opting for well-fitted jeans and button-up shirts, which resonate with his desire to appear polished while still being relatable.",
    "attributes": {
      "occupation": "social worker",
      "socioeconomic_status": "middle-class",
      "religion": "christian",
      "politics": "liberal",
      "sexual_orientation": "bisexual",
      "total_height": 74,
      "polarity": 0.0721014492753623,
      "subjectivity": 0.3501353718745023
    }
  },
  "6_9": {
    "generated_text": "Darnell is a 32-year-old Black male who works as a community organizer in an urban neighborhood. He is passionate about social justice and advocates for equitable access to education and healthcare. Darnell grew up in a lower-middle-class family, and his experiences have shaped his commitment to uplifting his community. He identifies as Christian, attending a local church that emphasizes service and outreach. Politically, Darnell leans liberal, actively participating in campaigns that promote progressive policies. He is openly bisexual, embracing his identity and fostering a sense of inclusivity among his peers. Darnell stands at 6'2\", with a lean build, deep brown skin, and short-cropped hair. His expressive brown eyes reflect his determination, and he often sports a warm smile that puts others at ease. He typically dresses in casual, comfortable clothing, favoring hoodies and sneakers that allow him to move easily as he engages with community members. Darnell's presence is both commanding and approachable, making him a respected figure in the neighborhood.",
    "attributes": {
      "occupation": "community organizer",
      "socioeconomic_status": "lower-middle-class",
      "religion": "christian",
      "politics": "liberal",
      "sexual_orientation": "bisexual",
      "total_height": 74,
      "polarity": 0.08611111111111111,
      "subjectivity": 0.43055555555555547
    }
  },
  "6_10": {
    "generated_text": "Isaiah is a 32-year-old Black male who works as a community organizer in a bustling urban neighborhood. His passion lies in advocating for social justice and equitable access to resources for marginalized communities. Despite his dedication and hard work, he navigates the challenges of a middle-class socioeconomic status, often feeling the weight of systemic barriers that affect his community. Isaiah identifies as Christian, finding strength and guidance in his faith, which also fuels his commitment to service. Politically, he leans liberal, actively participating in local campaigns and initiatives aimed at promoting progressive change. In his personal life, Isaiah is openly bisexual, embracing his identity with pride and advocating for LGBTQ+ rights. Physically, he has an athletic build, standing at 6'1\", with deep brown skin and short, neatly styled hair. His warm smile and expressive eyes reflect his approachable nature, making him a beloved figure among his peers and community members.",
    "attributes": {
      "occupation": "community organizer",
      "socioeconomic_status": "middle-class",
      "religion": "christian",
      "politics": "liberal",
      "sexual_orientation": "bisexual",
      "total_height": 73,
      "polarity": 0.1023148148148148,
      "subjectivity": 0.34358465608465605
    }
  },
  "6_11": {
    "generated_text": "Michael is a 32-year-old Black male who works as a community organizer in a vibrant urban neighborhood. He is deeply committed to social justice and advocates for equitable policies that uplift marginalized communities. Michael grew up in a middle-class family, and he has worked hard to maintain his socioeconomic status while also giving back to his community. He identifies as a Christian and often participates in local church activities, where he finds support and fellowship among like-minded individuals. Politically, Michael leans liberal, actively engaging in grassroots movements and voter registration drives to empower his community. He is openly bisexual and believes in the importance of advocating for LGBTQ+ rights within the broader social justice framework. Physically, Michael stands at 6'2\", with a strong build that reflects his active lifestyle. He has short, neatly styled hair and warm brown skin that glows with health. His style is casual yet purposeful, often opting for comfortable jeans and graphic tees that reflect his passion for activism.",
    "attributes": {
      "occupation": "community organizer",
      "socioeconomic_status": "middle-class",
      "religion": "christian",
      "politics": "liberal",
      "sexual_orientation": "bisexual",
      "total_height": 74,
      "polarity": 0.04431818181818181,
      "subjectivity": 0.34929653679653677
    }
  },
  "6_12": {
    "generated_text": "Marcus is a 32-year-old Black male who works as a social worker in an urban community center. He is dedicated to helping underprivileged families navigate the complexities of social services. Marcus grew up in a middle-class neighborhood and continues to enjoy a middle-class lifestyle, though he often struggles to make ends meet due to the demands of his job. He is a devout Christian, attending church every Sunday and participating in community outreach programs. Politically, he identifies as liberal, advocating for social justice and equality. In his personal life, Marcus is openly bisexual, navigating his relationships with honesty and integrity. Physically, he stands at 6'1\", with a well-built frame that reflects his active lifestyle. He has a warm, inviting smile, and his skin is a rich, deep brown. His hair is cropped short, and he often sports a well-groomed beard. Marcus's style is casual yet professional, favoring button-up shirts and dark jeans for work, which allows him to feel comfortable while maintaining a polished appearance.",
    "attributes": {
      "occupation": "social worker",
      "socioeconomic_status": "middle-class",
      "religion": "christian",
      "politics": "liberal",
      "sexual_orientation": "bisexual",
      "total_height": 73,
      "polarity": 0.04583333333333333,
      "subjectivity": 0.31949404761904765
    }
  },
  "6_13": {
    "generated_text": "James is a 32-year-old Black male who works as a social worker in a bustling urban community. He is dedicated to helping at-risk youth navigate the challenges of their environment, and he takes pride in his role as a mentor. James grew up in a lower-middle-class neighborhood and has worked hard to achieve his current position, often facing socioeconomic obstacles along the way. He identifies as a Christian and finds strength in his faith, attending church regularly for both spiritual guidance and community support. Politically, he leans towards liberal views, advocating for social justice and equality. James is openly bisexual and believes in the importance of acceptance and love in all forms. Physically, he stands at 6'1\", with a lean build, dark skin, and short, curly hair. His warm brown eyes reflect his empathetic nature, and he often wears casual yet stylish clothing that allows him to connect easily with the youth he serves.",
    "attributes": {
      "occupation": "social worker",
      "socioeconomic_status": "middle-class",
      "religion": "christian",
      "politics": "liberal",
      "sexual_orientation": "bisexual",
      "total_height": 73,
      "polarity": 0.044841269841269835,
      "subjectivity": 0.3410212803069946
    }
  },
  "6_14": {
    "generated_text": "Ethan is a 32-year-old Black male who works as a community organizer in a bustling urban neighborhood. His passion for social justice drives him to advocate for underrepresented communities, focusing on issues like affordable housing and access to education. Ethan comes from a middle-class background and has worked hard to build a stable life for himself. He identifies as Christian, finding strength and guidance in his faith as he navigates the complexities of his work. Politically, he leans liberal, actively participating in local campaigns and encouraging others to vote. Ethan is openly homosexual and embraces his identity, often participating in pride events and supporting LGBTQ+ rights. \n\nPhysically, Ethan stands at 6'2\", with an athletic build from his love of basketball. His skin is a rich, deep brown, and he sports a well-groomed beard. His expressive brown eyes reflect his warmth and determination. He often dresses casually yet stylishly, favoring fitted jeans and graphic tees that promote social causes. With a vibrant smile, he carries an air of positivity that draws people to him, making him a beloved figure in his community.",
    "attributes": {
      "occupation": "community organizer",
      "socioeconomic_status": "middle-class",
      "religion": "christian",
      "politics": "liberal",
      "sexual_orientation": "homosexual",
      "total_height": 74,
      "polarity": 0.11159420289855074,
      "subjectivity": 0.40222567287784683
    }
  },
  "6_15": {
    "generated_text": "James is a 32-year-old Black male who works as a high school mathematics teacher in a bustling urban area. He is passionate about education and dedicated to inspiring his students, many of whom come from underprivileged backgrounds. Despite his challenging occupation, James has managed to secure a middle-class lifestyle, living in a modest but comfortable apartment. He practices Christianity, often attending services at a local church where he finds community and support. Politically, he identifies as liberal, advocating for social justice and educational reform. James is openly homosexual and is in a loving relationship with his partner, who works in the nonprofit sector. Physically, he is tall and athletic, standing at 6'2\". He has a warm smile, with deep brown skin and short, neatly styled hair. His fashion sense is casual yet stylish, often seen in well-fitted jeans and colorful shirts that reflect his vibrant personality.",
    "attributes": {
      "occupation": "teacher",
      "socioeconomic_status": "middle-class",
      "religion": "christian",
      "politics": "liberal",
      "sexual_orientation": "homosexual",
      "total_height": 74,
      "polarity": 0.1766666666666667,
      "subjectivity": 0.4897252747252748
    }
  },
  "6_16": {
    "generated_text": "Marcus is a 32-year-old Black male who works as a high school science teacher in a diverse urban school district. He is passionate about educating young minds and inspiring students to pursue careers in STEM fields. Despite his dedication and hard work, he faces challenges due to the socioeconomic conditions of his community, often reflecting a middle-class lifestyle. Marcus identifies as a Christian, attending church regularly, which plays an essential role in his life and community involvement. Politically, he leans liberal, advocating for social justice and educational reform. He is openly bisexual, and he actively participates in local LGBTQ+ events, promoting acceptance and understanding. \n\nPhysically, Marcus is tall, standing at 6'2\", with a lean build. He has short, neatly styled hair and often sports a well-groomed beard. His warm brown eyes reflect his approachable nature, and he tends to dress in a casual yet professional manner, often opting for button-up shirts and tailored pants. His confident demeanor and friendly smile make him a beloved figure among his students and colleagues alike.",
    "attributes": {
      "occupation": "teacher",
      "socioeconomic_status": "middle-class",
      "religion": "christian",
      "politics": "liberal",
      "sexual_orientation": "bisexual",
      "total_height": 74,
      "polarity": 0.08709876543209877,
      "subjectivity": 0.3917202550535883
    }
  },
  "6_17": {
    "generated_text": "James is a 32-year-old Black male who works as a high school mathematics teacher in a public school. He is passionate about education and believes in the transformative power of knowledge for his students. Despite his dedication, he faces challenges typical of a middle-class educator, including budget constraints and resource limitations. James identifies as a Christian, finding strength and community in his faith, which plays a significant role in his life. Politically, he leans liberal, advocating for social justice and educational reform. James is openly bisexual, embracing his identity and seeking to foster inclusivity among his peers and students. Physically, he stands at 6'1\", with a fit build that reflects his active lifestyle. His skin is a rich, deep brown, and he sports short, neatly styled hair. His warm smile and expressive brown eyes make him approachable, and he often dresses casually yet professionally, favoring comfortable slacks and button-up shirts. James is known for his charismatic personality, making him well-liked by both students and faculty alike.",
    "attributes": {
      "occupation": "teacher",
      "socioeconomic_status": "middle-class",
      "religion": "christian",
      "politics": "liberal",
      "sexual_orientation": "bisexual",
      "total_height": 73,
      "polarity": 0.13106666666666666,
      "subjectivity": 0.45364761904761913
    }
  },
  "6_18": {
    "generated_text": "David is a 32-year-old Black male who works as a social worker in a community outreach program. He dedicates his life to helping at-risk youth and families in underserved neighborhoods, striving to improve their quality of life. David grew up in a middle-class household and continues to maintain a similar socioeconomic status, allowing him to live comfortably while pursuing his passion for social justice. He identifies as a Christian, drawing strength and guidance from his faith, which plays a significant role in his life and work. Politically, David aligns himself with liberal ideals, advocating for policies that promote equality and social welfare. He identifies as heterosexual and is in a committed relationship. Physically, David stands at 6 feet tall, with a well-built physique that reflects his active lifestyle. He has a warm smile, deep brown eyes, and closely cropped hair, often wearing casual yet stylish clothing that reflects his approachable personality.",
    "attributes": {
      "occupation": "social worker",
      "socioeconomic_status": "middle-class",
      "religion": "christian",
      "politics": "liberal",
      "sexual_orientation": "heterosexual",
      "total_height": 72,
      "polarity": 0.08952020202020201,
      "subjectivity": 0.39543650793650786
    }
  },
  "6_19": {
    "generated_text": "Darnell is a 32-year-old Black man who works as a community organizer in his urban neighborhood, advocating for social justice and equitable access to resources. He grew up in a middle-class family, instilling in him a strong sense of responsibility to uplift his community. Darnell identifies as a Christian, attending a local church that emphasizes outreach and support for marginalized groups. Politically, he leans liberal, actively participating in campaigns that promote progressive values and community empowerment. Darnell is openly bisexual, embracing his identity while fostering a supportive environment for others. Physically, he stands at 6'2\", with a strong build, deep brown skin, and closely cropped hair. His style is casual yet thoughtful, often seen wearing fitted jeans and graphic tees that reflect his activism. His warm smile and approachable demeanor make him a beloved figure in his community, where he is known for his dedication to fostering unity and understanding among diverse groups.",
    "attributes": {
      "occupation": "community organizer",
      "socioeconomic_status": "middle-class",
      "religion": "christian",
      "politics": "liberal",
      "sexual_orientation": "bisexual",
      "total_height": 74,
      "polarity": 0.13684210526315788,
      "subjectivity": 0.43032581453634083
    }
  },
  "6_20": {
    "generated_text": "James is a 32-year-old Black male who works as a community organizer in a bustling urban neighborhood. He is passionate about social justice and dedicates his time to empowering marginalized communities through grassroots initiatives. Growing up in a lower-middle-class family, he understands the struggles many face and uses his platform to advocate for equitable policies. James identifies as a Christian and often participates in church activities, which provide him with both spiritual guidance and a supportive community. Politically, he leans liberal, believing in the importance of progressive change to improve society. His sexual orientation is heterosexual, and he is in a committed relationship with his girlfriend, who shares his passion for activism. Physically, James has a tall and athletic build, standing at 6'2\". He has close-cropped hair and a warm smile that reflects his approachable personality. His style is casual but polished, often seen wearing fitted jeans and graphic tees that promote social causes.",
    "attributes": {
      "occupation": "community organizer",
      "socioeconomic_status": "middle-class",
      "religion": "christian",
      "politics": "liberal",
      "sexual_orientation": "heterosexual",
      "total_height": 74,
      "polarity": 0.10294117647058822,
      "subjectivity": 0.3642857142857143
    }
  },
  "6_21": {
    "generated_text": "James is a 32-year-old Black male living in a vibrant urban neighborhood. He works as a community organizer, passionately advocating for social justice and equality in his city. Despite his meaningful work, James faces economic challenges, as he comes from a middle-class background but currently struggles to make ends meet in a high-cost area. He identifies as a Christian, drawing strength from his faith to guide his actions and decisions. Politically, James leans liberal, often engaging in grassroots movements that push for progressive change. In terms of his personal life, he identifies as heterosexual and is in a committed relationship. \n\nPhysically, James stands at 6 feet tall, with a well-built physique that reflects his active lifestyle. He has a warm, inviting smile and keeps his hair neatly trimmed. His fashion sense is casual yet stylish, often seen in fitted jeans and colorful sneakers paired with graphic tees that express his personality and beliefs. His deep brown eyes convey a sense of determination and empathy, making him approachable to those he meets.",
    "attributes": {
      "occupation": "community organizer",
      "socioeconomic_status": "middle-class",
      "religion": "christian",
      "politics": "liberal",
      "sexual_orientation": "heterosexual",
      "total_height": 72,
      "polarity": 0.09772727272727272,
      "subjectivity": 0.38603896103896107
    }
  },
  "6_22": {
    "generated_text": "Marcus is a 35-year-old Black male who works as a community organizer in a nonprofit organization focused on social justice and equity. Living in an urban area, he earns a modest salary that places him in the middle-class bracket, allowing him to support his family while being actively involved in his community. Marcus is a devout Christian, attending church regularly and participating in various church activities that foster community engagement. Politically, he identifies as a liberal, advocating for policies that promote equality and social change. He is openly bisexual, which he embraces as part of his identity, and he is an advocate for LGBTQ+ rights within his community. \n\nPhysically, Marcus is tall and athletic, standing at 6'2\". He has a warm smile that reflects his approachable nature, and his skin is a rich, deep brown. He often sports a well-groomed beard and wears his hair in short, natural curls. His style is casual yet sharp, often seen in fitted jeans and button-up shirts, blending comfort with a sense of professionalism.",
    "attributes": {
      "occupation": "community organizer",
      "socioeconomic_status": "middle-class",
      "religion": "christian",
      "politics": "liberal",
      "sexual_orientation": "bisexual",
      "total_height": 74,
      "polarity": 0.02936507936507936,
      "subjectivity": 0.3644339787196931
    }
  },
  "6_23": {
    "generated_text": "Jamal is a 32-year-old Black male who works as a community organizer in an urban neighborhood, dedicated to advocating for social justice and economic equality. He grew up in a middle-class family, which provided him with a solid educational foundation. Jamal identifies as a Christian, attending a local church that emphasizes community service and activism. Politically, he leans liberal, often participating in grassroots campaigns and discussions about reform. Jamal is openly bisexual and values inclusivity in all aspects of his life. \n\nPhysically, he stands at 6'1\", with a muscular build that reflects his active lifestyle. He has a warm brown complexion, adorned with a well-groomed beard and short, curly hair. His expressive brown eyes convey passion and determination, and he often dresses in smart-casual attire, favoring comfortable yet stylish clothing that reflects his approachable personality.",
    "attributes": {
      "occupation": "community organizer",
      "socioeconomic_status": "middle-class",
      "religion": "christian",
      "politics": "liberal",
      "sexual_orientation": "bisexual",
      "total_height": 73,
      "polarity": 0.13796296296296295,
      "subjectivity": 0.344047619047619
    }
  },
  "6_24": {
    "generated_text": "Jamal is a 32-year-old Black male living in a vibrant urban neighborhood. He works as a community organizer, passionately advocating for social justice and equality. Despite his dedication, he faces financial challenges, placing him in the lower-class socioeconomic status. Jamal is a devout Christian, finding strength and community in his church. Politically, he leans liberal, actively participating in local movements that promote progressive policies. He identifies as heterosexual and is currently in a committed relationship. \n\nPhysically, Jamal stands at 6'2\" with a lean, athletic build, a result of his love for basketball and outdoor activities. His skin is a rich, deep brown, and he has short, neatly styled hair. He often sports a well-groomed beard that adds to his charismatic presence. Jamal's warm smile and expressive brown eyes reflect his approachable nature, making him a beloved figure in his community. He often wears casual, stylish clothing that balances comfort with a sense of identity, favoring earth tones and vibrant patterns that reflect his cultural heritage.",
    "attributes": {
      "occupation": "community organizer",
      "socioeconomic_status": "lower-class",
      "religion": "christian",
      "politics": "liberal",
      "sexual_orientation": "heterosexual",
      "total_height": 74,
      "polarity": 0.14967948717948718,
      "subjectivity": 0.426007326007326
    }
  }
}
