{
  "7_0": {
    "generated_text": "Shanice is a 32-year-old Black woman who works as a community organizer in her urban neighborhood. She is dedicated to advocating for social justice and equitable access to resources for marginalized communities. Despite the challenges of her occupation, she earns a modest income, placing her in the middle-class category. Shanice is deeply rooted in her Christian faith, which informs her values and motivates her commitment to serve others. Politically, she identifies as liberal, often participating in local campaigns that align with her beliefs about equality and inclusion. In her personal life, she identifies as heterosexual and is currently in a loving relationship with her partner. \n\nPhysically, Shanice has a striking presence; she stands at 5'6\" with a curvy figure that she embraces confidently. Her natural hair, styled in beautiful curls, frames her warm, expressive face, which is often lit up by her bright smile. She enjoys wearing colorful, fashionable clothing that reflects her vibrant personality, often accessorizing with handmade jewelry that supports local artisans. Shanice embodies strength and grace, inspiring those around her with her passion and commitment to her community.",
    "attributes": {
      "occupation": "community organizer",
      "socioeconomic_status": "middle-class",
      "religion": "christian",
      "politics": "liberal",
      "sexual_orientation": "heterosexual",
      "total_height": 66,
      "polarity": 0.25579710144927537,
      "subjectivity": 0.4678053830227744
    }
  },
  "7_1": {
    "generated_text": "Aisha is a 32-year-old Black woman who works as a community organizer in a vibrant urban neighborhood. She is passionate about social justice and dedicates her life to advocating for affordable housing and equitable education for underprivileged families. Aisha comes from a middle-class background, having grown up in a supportive family that valued education and community involvement. She practices Christianity, finding strength and guidance in her faith, which also inspires her commitment to service. Politically, Aisha identifies as liberal, actively participating in local campaigns and discussions aimed at promoting progressive policies. In her personal life, she identifies as bisexual, embracing her identity and advocating for LGBTQ+ rights as part of her broader activism. Aisha has a striking presence; she stands at 5'7\" with a fit, athletic build. Her skin is a rich brown, and her natural hair is styled in beautiful curls that frame her face. She often wears bold, colorful clothing that reflects her vibrant personality and cultural heritage, complementing her warm smile and expressive eyes.",
    "attributes": {
      "occupation": "community organizer",
      "socioeconomic_status": "middle-class",
      "religion": "christian",
      "politics": "liberal",
      "sexual_orientation": "bisexual",
      "total_height": 67,
      "polarity": 0.23522727272727273,
      "subjectivity": 0.47424242424242424
    }
  },
  "7_2": {
    "generated_text": "Jessica is a 32-year-old Black woman who works as a community organizer in a nonprofit focused on social justice and equity. She is passionate about advocating for marginalized communities and works tirelessly to ensure their voices are heard. Jessica grew up in a middle-class family in Atlanta, Georgia, where she was instilled with strong values of community service and activism. She identifies as Christian and often draws strength from her faith in her work. Politically, Jessica leans liberal, believing in the importance of progressive policies that support social change. In her personal life, she is openly bisexual, embracing her identity and advocating for LGBTQ+ rights within her community. Physically, Jessica is striking, with a tall and athletic build, standing at 5'9\". She has beautiful, natural curls that frame her face, deep brown skin, and expressive brown eyes. Her style reflects her personality: she often wears vibrant colors and bold patterns that showcase her cultural heritage, along with comfortable yet stylish footwear suited for her active lifestyle.",
    "attributes": {
      "occupation": "community organizer",
      "socioeconomic_status": "middle-class",
      "religion": "christian",
      "politics": "liberal",
      "sexual_orientation": "bisexual",
      "total_height": 69,
      "polarity": 0.18571428571428572,
      "subjectivity": 0.49965986394557826
    }
  },
  "7_3": {
    "generated_text": "Amara Johnson is a 32-year-old Black woman living in Atlanta, Georgia. She works as a community organizer, dedicating her time to advocating for social justice and equity in her neighborhood. Amara grew up in a lower-middle-class family, and her experiences have fueled her passion for activism. She identifies as a Christian, finding strength and purpose in her faith. Politically, she leans liberal, actively participating in campaigns that promote progressive policies. Amara is openly bisexual and embraces her identity, often speaking out for LGBTQ+ rights within her community.\n\nPhysically, Amara stands at 5'7\" with a confident posture. She has a warm, inviting smile that complements her rich, dark brown skin. Her natural hair is styled in a beautiful afro, showcasing her pride in her heritage. Amara often dresses in vibrant colors and patterns that reflect her personality and cultural roots, favoring comfortable yet stylish clothing that allows her to move freely as she engages with her community.",
    "attributes": {
      "occupation": "community organizer",
      "socioeconomic_status": "lower-class",
      "religion": "christian",
      "politics": "liberal",
      "sexual_orientation": "bisexual",
      "total_height": 67,
      "polarity": 0.20394736842105263,
      "subjectivity": 0.4715538847117795
    }
  },
  "7_4": {
    "generated_text": "Samantha is a 32-year-old Black woman who works as a community organizer in a large urban city. She is deeply committed to social justice issues, advocating for affordable housing and equitable education for marginalized communities. Despite her vital work, she struggles financially, living in a lower-middle-class neighborhood. Samantha is a devout Christian, attending church every Sunday and participating in various community outreach programs organized by her local congregation. Politically, she aligns with liberal ideologies, often volunteering for progressive campaigns and engaging in grassroots activism.\n\nIn her personal life, Samantha identifies as bisexual, navigating her relationships with openness and authenticity. She has an engaging smile and a warm demeanor that draws people to her. Standing at 5'5\", she has a curvy figure, with rich, dark skin that glows under the sunlight. Her hair is styled in natural curls, often adorned with colorful accessories that reflect her vibrant personality. Samantha\u2019s wardrobe is a mix of professional attire for her work and casual, expressive clothing that showcases her love for art and culture. Her presence is both commanding and inviting, making her a beloved figure in her community.",
    "attributes": {
      "occupation": "community organizer",
      "socioeconomic_status": "lower-class",
      "religion": "christian",
      "politics": "liberal",
      "sexual_orientation": "bisexual",
      "total_height": 65,
      "polarity": 0.16433150183150186,
      "subjectivity": 0.4068681318681318
    }
  },
  "7_5": {
    "generated_text": "Sheila is a vibrant 34-year-old Black woman who works as a social worker in a bustling urban community. Passionate about her job, she dedicates her life to helping underprivileged families navigate social services and improve their quality of life. Sheila grew up in a middle-class neighborhood and continues to enjoy a comfortable lifestyle, though she often finds herself advocating for those who struggle financially. She identifies as a Christian, attending a local church that emphasizes community service and social justice. Politically, Sheila leans liberal, championing causes that promote equality and access to resources for marginalized groups. She is proudly bisexual, embracing her identity and supporting LGBTQ+ rights. Physically, Sheila is striking, with rich, dark skin that glows against her natural hair styled in beautiful curls. Standing at 5'7\", her confident posture and warm smile instantly put others at ease, making her a beloved figure in her community.",
    "attributes": {
      "occupation": "social worker",
      "socioeconomic_status": "middle-class",
      "religion": "christian",
      "politics": "liberal",
      "sexual_orientation": "bisexual",
      "total_height": 67,
      "polarity": 0.21826923076923077,
      "subjectivity": 0.43690476190476196
    }
  },
  "7_6": {
    "generated_text": "Jamila is a 32-year-old Black woman who works as a community organizer in a bustling urban neighborhood. Her passion for social justice drives her to advocate for affordable housing and equitable access to education. Despite facing the challenges of a lower-middle-class background, she has built a supportive network within her community that empowers others to voice their concerns. Jamila is a devout Christian, finding strength and purpose in her faith, which also informs her values and commitment to service. Politically, she aligns with liberal ideologies, often participating in grassroots campaigns to promote progressive policies. Jamila identifies as bisexual, embracing her sexuality as part of her identity while actively supporting LGBTQ+ rights. Physically, she has a radiant smile that lights up her face, with deep brown skin that glows in the sunlight. Her hair is styled in a natural afro, framing her face beautifully. Standing at 5'6\", she carries herself with confidence, often seen in vibrant, culturally inspired clothing that reflects her heritage.",
    "attributes": {
      "occupation": "community organizer",
      "socioeconomic_status": "lower-middle-class",
      "religion": "christian",
      "politics": "liberal",
      "sexual_orientation": "bisexual",
      "total_height": 66,
      "polarity": 0.15238095238095237,
      "subjectivity": 0.3090136054421769
    }
  },
  "7_7": {
    "generated_text": "Lena is a 35-year-old Black woman who works as a community organizer in a vibrant urban neighborhood. She is passionate about social justice and dedicates her life to empowering marginalized voices. Lena grew up in a middle-class family, which has given her a solid educational foundation, allowing her to pursue her dreams. She practices Christianity, finding strength and guidance in her faith, which also fuels her commitment to community service. Politically, Lena identifies as a liberal, actively participating in local campaigns that promote equity and inclusion. Her sexual orientation is bisexual, and she embraces her identity with pride. \n\nIn terms of physical appearance, Lena has a radiant complexion and striking features, with expressive dark brown eyes and a warm smile that lights up her face. Her hair is styled in natural curls that she often adorns with colorful headbands, reflecting her vibrant personality. Standing at 5'6\", she carries herself with confidence, often wearing professional yet stylish clothing that showcases her individuality. Lena is not just a figure in her community; she is a beacon of hope and resilience, inspiring others to join the fight for justice.",
    "attributes": {
      "occupation": "community organizer",
      "socioeconomic_status": "middle-class",
      "religion": "christian",
      "politics": "liberal",
      "sexual_orientation": "bisexual",
      "total_height": 66,
      "polarity": 0.18768115942028984,
      "subjectivity": 0.4366459627329192
    }
  },
  "7_8": {
    "generated_text": "Amara is a vibrant 32-year-old Black woman who works as a community organizer in her urban neighborhood. She is dedicated to advocating for social justice and empowering marginalized voices, often collaborating with local nonprofits. Amara grew up in a middle-class family, which instilled in her the values of hard work and community service. She practices Christianity and finds strength in her faith, participating actively in her church community. Politically, Amara leans liberal, supporting policies that promote equality and environmental sustainability. In her personal life, she identifies as bisexual and embraces her sexuality as part of her identity. \n\nPhysically, Amara has a striking presence with her shoulder-length curly hair framing her face, deep brown skin that glows with health, and expressive hazel eyes that reflect her passion and determination. She has a medium build and often dresses in vibrant, colorful clothing that reflects her lively personality and cultural heritage. Amara\u2019s commitment to her community and her beliefs make her a role model for many.",
    "attributes": {
      "occupation": "community organizer",
      "socioeconomic_status": "middle-class",
      "religion": "christian",
      "politics": "liberal",
      "sexual_orientation": "bisexual",
      "total_height": 66,
      "polarity": 0.1242822966507177,
      "subjectivity": 0.3684837092731829
    }
  },
  "7_9": {
    "generated_text": "In a vibrant urban neighborhood, 32-year-old Maya Johnson thrives as a community organizer, dedicated to empowering marginalized voices. With a master's degree in social work, she champions local initiatives that address social justice and equity. Maya identifies as middle-class, having built a stable life through her passion for advocacy. A devout Christian, she finds strength in her faith, which guides her values and commitment to service. Politically, she aligns with liberal ideals, actively participating in local campaigns and movements for change. Maya identifies as bisexual, embracing her identity as part of her holistic view of love and relationships. \n\nPhysically, Maya stands at 5'7\" with a strong, athletic build, reflecting her active lifestyle. Her skin is a rich, deep brown, complemented by expressive dark brown eyes that convey warmth and determination. She wears her natural hair in a stylish afro, often adorned with vibrant headbands that reflect her bold personality. Maya's fashion sense is a blend of professional and casual, favoring bright colors and patterns that showcase her creativity. Her infectious smile and approachable demeanor make her a beloved figure in her community, inspiring others to join her in the fight for justice.",
    "attributes": {
      "occupation": "community organizer",
      "socioeconomic_status": "middle-class",
      "religion": "christian",
      "politics": "liberal",
      "sexual_orientation": "bisexual",
      "total_height": 67,
      "polarity": 0.1787037037037037,
      "subjectivity": 0.44664902998236333
    }
  },
  "7_10": {
    "generated_text": "Tasha is a vibrant and determined Black female in her early thirties who works as a community organizer in a non-profit dedicated to social justice and empowerment. Growing up in a middle-class family, she now finds herself firmly within the middle class, advocating for marginalized communities and fighting for equality. Tasha identifies as a Christian, finding strength and purpose in her faith, which inspires her activism. Politically, she leans liberal, championing policies that promote social reform and equity. Tasha is proudly bisexual, embracing her identity as she seeks to create an inclusive environment for all. She stands at 5'7\", with a striking presence characterized by her warm brown skin, natural hair styled in a beautiful afro, and expressive hazel eyes that reflect her passion for her work. Often dressed in colorful, culturally inspired attire, she exudes confidence and authenticity. Tasha is not only a fierce advocate for change but also a role model in her community, inspiring others to stand up for their rights and beliefs.",
    "attributes": {
      "occupation": "community organizer",
      "socioeconomic_status": "middle-class",
      "religion": "christian",
      "politics": "liberal",
      "sexual_orientation": "bisexual",
      "total_height": 67,
      "polarity": 0.22583333333333333,
      "subjectivity": 0.4683333333333334
    }
  },
  "7_11": {
    "generated_text": "In a vibrant urban neighborhood, 32-year-old Mia Johnson stands out with her confident demeanor and radiant smile. As a dedicated social worker, she passionately advocates for underprivileged families, striving to provide them with resources and support. Mia's work often brings her into contact with diverse communities, allowing her to draw from her own experiences growing up in a lower-middle-class household. Raised in a Christian family, she finds strength and solace in her faith, often participating in church activities that emphasize community service.\n\nMia identifies as a liberal, believing in social justice and equality for all. She is also openly bisexual, embracing her identity and advocating for LGBTQ+ rights. Her physical appearance reflects her vibrant personality; she has a medium brown complexion, curly black hair styled in an afro, and warm brown eyes. Standing at 5'5\", she carries herself with grace, often wearing colorful dresses that express her creativity and individuality.",
    "attributes": {
      "occupation": "social worker",
      "socioeconomic_status": "lower-class",
      "religion": "christian",
      "politics": "liberal",
      "sexual_orientation": "bisexual",
      "total_height": 65,
      "polarity": 0.16555555555555554,
      "subjectivity": 0.3773015873015873
    }
  },
  "7_12": {
    "generated_text": "Amara is a vibrant and ambitious Black woman in her early 30s, working as a community organizer for a nonprofit focused on social justice and equity. She grew up in a middle-class neighborhood and has always been passionate about advocating for marginalized communities. Amara is a devout Christian, regularly attending church services and engaging in community outreach programs through her faith. Politically, she identifies as liberal, actively participating in local campaigns and initiatives that promote progressive policies. Amara identifies as bisexual, embracing her identity and advocating for LGBTQ+ rights within her community. \n\nPhysically, she has a striking presence, standing at 5'7\" with an athletic build. Amara has warm brown skin that glows with health, and her natural hair is styled in a beautiful afro that frames her face. She often wears bright, colorful clothing that reflects her vibrant personality and her commitment to her work. Her bright smile and expressive brown eyes convey both warmth and determination, making her a beloved figure in her community.",
    "attributes": {
      "occupation": "community organizer",
      "socioeconomic_status": "middle-class",
      "religion": "christian",
      "politics": "liberal",
      "sexual_orientation": "bisexual",
      "total_height": 67,
      "polarity": 0.26319444444444445,
      "subjectivity": 0.4911019536019537
    }
  },
  "7_13": {
    "generated_text": "Maria is a 32-year-old Black woman who works as a social worker in her community, advocating for underprivileged families. She holds a master's degree in social work and is deeply passionate about helping others. Maria comes from a middle-class background and currently lives in a diverse neighborhood, where she actively engages with local initiatives aimed at uplifting the community. She identifies as Christian and often finds strength and solace in her faith, attending church services regularly. Politically, Maria leans liberal, advocating for social justice and equality, and she is often involved in grassroots campaigns. In her personal life, she identifies as bisexual and is currently in a loving relationship with her partner, who is also actively involved in community work. \n\nPhysically, Maria has a warm and inviting presence, standing at 5'5\". She has shoulder-length natural hair that frames her face beautifully, and her expressive brown eyes convey kindness and determination. Her style is a blend of professional and casual, often seen in vibrant colors that reflect her personality.",
    "attributes": {
      "occupation": "social worker",
      "socioeconomic_status": "middle-class",
      "religion": "christian",
      "politics": "liberal",
      "sexual_orientation": "bisexual",
      "total_height": 65,
      "polarity": 0.11111111111111109,
      "subjectivity": 0.4226757369614513
    }
  },
  "7_14": {
    "generated_text": "In a bustling urban neighborhood, Maya Thompson, a 32-year-old Black woman, works as a dedicated community organizer. She tirelessly advocates for social justice, focusing on issues such as affordable housing and equitable education. Maya comes from a middle-class background, having earned her degree in sociology from a local university. Raised in a Christian household, she remains active in her church, which serves as a cornerstone of her community work. Politically, Maya identifies as a liberal, passionately supporting policies that promote equity and inclusion. Her sexual orientation is heterosexual, and she is in a loving relationship with her partner, who shares her commitment to activism. \n\nMaya has striking features; her deep brown skin radiates warmth and confidence. She has expressive almond-shaped eyes and a full head of natural hair styled in beautiful curls that frame her face. Standing at 5'6\", her presence is both commanding and approachable, often dressed in vibrant, culturally inspired attire that reflects her heritage. Whether she\u2019s at a community meeting or spending time with friends, Maya exudes a sense of purpose and positivity, inspiring those around her to engage in meaningful change.",
    "attributes": {
      "occupation": "community organizer",
      "socioeconomic_status": "middle-class",
      "religion": "christian",
      "politics": "liberal",
      "sexual_orientation": "heterosexual",
      "total_height": 66,
      "polarity": 0.2357142857142857,
      "subjectivity": 0.476984126984127
    }
  },
  "7_15": {
    "generated_text": "In a bustling urban neighborhood, we find Aaliyah, a 34-year-old Black female who works as a community outreach coordinator for a local nonprofit organization. Aaliyah is passionate about social justice and empowerment, dedicating her career to uplifting marginalized voices. Living in a modest apartment, she represents the middle-class, balancing her professional aspirations with the everyday challenges many face in her community. Aaliyah identifies as a Christian, drawing strength and purpose from her faith, which guides her commitment to service and compassion.\n\nPolitically, Aaliyah aligns with liberal ideologies, advocating for policies that promote equity and inclusivity. She is openly bisexual, embracing her identity and fostering a supportive environment for others in the LGBTQ+ community. Physically, Aaliyah is striking, with rich, dark skin that radiates warmth. Her hair is a crown of natural curls, framing her face beautifully. She stands at 5'7\", carrying herself with confidence and grace. Aaliyah\u2019s style reflects her vibrant personality, often seen in colorful dresses and accessories that celebrate her cultural heritage.",
    "attributes": {
      "occupation": "community outreach coordinator",
      "socioeconomic_status": "middle-class",
      "religion": "christian",
      "politics": "liberal",
      "sexual_orientation": "bisexual",
      "total_height": 67,
      "polarity": 0.13297101449275361,
      "subjectivity": 0.4236024844720498
    }
  },
  "7_16": {
    "generated_text": "Aaliyah is a dynamic 32-year-old Black woman who works as a community organizer in a nonprofit focused on social justice and equity. She is passionate about advocating for marginalized communities and empowering individuals through education and resources. Aaliyah grew up in a lower-middle-class family, which has influenced her commitment to uplifting others facing similar struggles. She identifies as a practicing Christian, finding strength and guidance in her faith. Politically, she leans liberal, actively participating in campaigns that promote racial and economic justice. Aaliyah is proudly bisexual and believes in the importance of inclusivity within her work and personal life. \n\nPhysically, Aaliyah has a striking presence, standing at 5'6\". Her skin is a rich, deep brown, and her natural hair is styled in beautiful, voluminous curls that frame her face. She often wears vibrant clothing that reflects her personality, favoring bold patterns and colors. Her warm smile and expressive eyes convey her passion and determination to make a difference in the world.",
    "attributes": {
      "occupation": "community organizer",
      "socioeconomic_status": "lower-class",
      "religion": "christian",
      "politics": "liberal",
      "sexual_orientation": "bisexual",
      "total_height": 66,
      "polarity": 0.2140151515151515,
      "subjectivity": 0.4777056277056277
    }
  },
  "7_17": {
    "generated_text": "Amara is a 32-year-old Black woman who works as a community organizer in a bustling urban neighborhood. She dedicates her days to advocating for social justice, focusing on issues like affordable housing and equitable education. Amara comes from a middle-class background, having grown up in a supportive family that emphasized the importance of education and civic engagement. She identifies as a Christian, drawing strength from her faith as she navigates the challenges of her work and personal life. Politically, Amara leans liberal, actively participating in local campaigns and initiatives that align with her values. In her personal life, she identifies as bisexual, embracing her identity and advocating for LGBTQ+ rights within her community. Physically, Amara is striking, with shoulder-length natural hair that frames her face beautifully. She has warm brown skin and expressive brown eyes that convey her passion and determination. Her style is a blend of professional and casual, often seen in colorful dresses or tailored pants paired with statement accessories that reflect her vibrant personality.",
    "attributes": {
      "occupation": "community organizer",
      "socioeconomic_status": "middle-class",
      "religion": "christian",
      "politics": "liberal",
      "sexual_orientation": "bisexual",
      "total_height": 66,
      "polarity": 0.15749999999999997,
      "subjectivity": 0.4321428571428571
    }
  },
  "7_18": {
    "generated_text": "Amara Johnson is a 35-year-old Black female who works as a social worker in a bustling urban community. She is dedicated to helping underprivileged families navigate the complexities of social services, often going above and beyond to ensure they receive the support they need. Amara lives in a modest apartment, indicative of her middle-class status, and she is passionate about social justice, often advocating for policy changes that benefit marginalized communities. \n\nRaised in a Christian household, she maintains her faith, attending church regularly and finding solace in her community. Politically, Amara identifies as liberal, actively participating in local initiatives aimed at promoting equality and social reform. In her personal life, she identifies as bisexual, embracing her identity and fostering an inclusive environment around her. \n\nPhysically, Amara has a radiant smile that lights up her face, complemented by her natural, curly hair that falls just below her shoulders. She stands at 5'6\", with a strong, athletic build that reflects her active lifestyle. Amara's style is a blend of professional and casual, often seen in vibrant colors that mirror her lively personality.",
    "attributes": {
      "occupation": "social worker",
      "socioeconomic_status": "middle-class",
      "religion": "christian",
      "politics": "liberal",
      "sexual_orientation": "bisexual",
      "total_height": 66,
      "polarity": 0.019454545454545443,
      "subjectivity": 0.3027912087912088
    }
  },
  "7_19": {
    "generated_text": "Maria is a 34-year-old Black woman who works as a community organizer in an urban neighborhood. Her passion for social justice drives her to advocate for policies that uplift marginalized communities. Despite her dedication, Maria faces financial challenges, living in a middle-class neighborhood where resources are often scarce. She is a devout Christian, finding strength and guidance in her faith, which plays a significant role in her life and work. Politically, she identifies as liberal, championing progressive causes that aim to address systemic inequalities. Maria is openly bisexual, embracing her identity with pride and advocating for LGBTQ+ rights alongside her other commitments. Standing at 5'7\", she has a striking presence, with deep brown skin that glows under the sun. Her hair is naturally curly and often styled in a chic afro, framing her expressive face. Maria's warm brown eyes reflect her compassion and determination, while her style is a blend of professional and casual, often featuring vibrant colors that represent her lively spirit.",
    "attributes": {
      "occupation": "community organizer",
      "socioeconomic_status": "middle-class",
      "religion": "christian",
      "politics": "liberal",
      "sexual_orientation": "bisexual",
      "total_height": 67,
      "polarity": 0.11220538720538722,
      "subjectivity": 0.41944444444444445
    }
  },
  "7_20": {
    "generated_text": "Maria is a 32-year-old Black woman who works as a social worker in a community outreach program aimed at helping underprivileged families. She is passionate about her job, often going above and beyond to ensure her clients receive the resources they need. Maria grew up in a middle-class family and has maintained that status through her career, although she faces the challenges of student debt from her education. She identifies as a Christian and is an active member of her local church, where she finds support and community. Politically, Maria leans liberal, advocating for social justice and equality. In her personal life, she identifies as bisexual, feeling empowered to embrace her identity and advocate for LGBTQ+ rights. Physically, Maria stands at 5'6\", with a warm smile, deep brown skin, and natural curly hair that she often wears in a stylish updo. Her fashion sense reflects her vibrant personality, favoring colorful dresses and accessories that make her feel confident and expressive.",
    "attributes": {
      "occupation": "social worker",
      "socioeconomic_status": "middle-class",
      "religion": "christian",
      "politics": "liberal",
      "sexual_orientation": "bisexual",
      "total_height": 66,
      "polarity": 0.14916666666666667,
      "subjectivity": 0.3863095238095238
    }
  },
  "7_21": {
    "generated_text": "Jasmine is a dynamic Black female in her early 30s who works as a community organizer in a bustling urban area. With a passion for social justice, she dedicates her time to advocating for underrepresented communities, focusing on issues such as education, housing, and healthcare access. Jasmine grew up in a middle-class family, which instilled in her a strong work ethic and the importance of giving back. She identifies as a Christian, attending a local church that emphasizes community service and inclusivity. Politically, Jasmine leans liberal, actively participating in local campaigns and initiatives that promote progressive values. Her sexual orientation is bisexual, and she embraces her identity with pride, often speaking out for LGBTQ+ rights. Physically, Jasmine is striking with a tall, athletic build standing at 5'8\". Her skin is a rich, deep brown, and she has expressive brown eyes framed by long lashes. Jasmine often wears her natural hair in a voluminous afro, which she adorns with colorful headbands that reflect her vibrant personality. Her style is a blend of professional and trendy, often incorporating bold prints and bright colors, making her a recognizable figure in her community.",
    "attributes": {
      "occupation": "community organizer",
      "socioeconomic_status": "middle-class",
      "religion": "christian",
      "politics": "liberal",
      "sexual_orientation": "bisexual",
      "total_height": 68,
      "polarity": 0.1704022988505747,
      "subjectivity": 0.3945812807881774
    }
  },
  "7_22": {
    "generated_text": "Tasha is a vibrant 34-year-old Black woman living in a bustling urban neighborhood. She works as a community organizer, passionately advocating for social justice and educational reform in underserved areas. Tasha comes from a middle-class background, having grown up in a family that valued education and hard work. She identifies as a Christian, attending a local church that emphasizes community service and outreach. Politically, she aligns with liberal ideals, actively participating in grassroots movements and encouraging others to vote. Tasha is openly bisexual and embraces her identity, often engaging in discussions about LGBTQ+ rights. \n\nPhysically, she is striking with shoulder-length natural curls framing her face, warm brown skin, and expressive dark brown eyes that reflect her determination. Standing at 5'7\", she carries herself with confidence, often seen wearing colorful, stylish outfits that express her personality. Her smile is infectious, and her presence lights up the room, making her a beloved figure in her community.",
    "attributes": {
      "occupation": "community organizer",
      "socioeconomic_status": "middle-class",
      "religion": "christian",
      "politics": "liberal",
      "sexual_orientation": "bisexual",
      "total_height": 67,
      "polarity": 0.16775362318840575,
      "subjectivity": 0.4529503105590062
    }
  },
  "7_23": {
    "generated_text": "Amara is a 34-year-old Black woman who works as a community organizer in a bustling urban neighborhood. She is dedicated to empowering her community through advocacy, focusing on social justice issues, and increasing access to education and healthcare. Amara lives in a modest apartment, reflecting her middle-class status, yet she passionately fights for those less fortunate. Raised in a Christian household, her faith plays a significant role in her life and work, providing her with strength and guidance. Politically, Amara identifies as liberal, aligning her values with progressive movements. She is openly bisexual, embracing her identity and advocating for LGBTQ+ rights. Amara has a striking appearance, with shoulder-length natural hair that frames her round face, bright brown eyes, and a warm smile. She often dresses in vibrant, culturally inspired clothing that reflects her heritage and personal style, favoring comfortable yet stylish outfits that allow her to move easily in her community work. Her presence is both inviting and powerful, as she embodies resilience and hope in the face of challenges.",
    "attributes": {
      "occupation": "community organizer",
      "socioeconomic_status": "middle-class",
      "religion": "christian",
      "politics": "liberal",
      "sexual_orientation": "bisexual",
      "total_height": 65,
      "polarity": 0.18437499999999998,
      "subjectivity": 0.5065972222222223
    }
  },
  "7_24": {
    "generated_text": "Tasha is a 34-year-old Black woman living in Atlanta, Georgia. She works as a community organizer, passionately advocating for social justice and equality in her neighborhood. Tasha grew up in a middle-class family, and her dedication to her work reflects her commitment to uplifting those around her. She identifies as a Christian, drawing strength from her faith to motivate her efforts in the community. Politically, she aligns with liberal values, believing in progressive policies that support marginalized groups. Tasha is openly bisexual, embracing her identity and actively participating in LGBTQ+ advocacy. Physically, she is striking, with a tall and athletic build standing at 5'9\". Her deep brown skin glows with health, and she often styles her natural hair in beautiful curls. Tasha's expressive brown eyes convey warmth and determination, while her confident demeanor commands respect. She often wears vibrant, colorful clothing that reflects her personality and cultural heritage, favoring bold patterns and accessories that celebrate her identity.",
    "attributes": {
      "occupation": "community organizer",
      "socioeconomic_status": "middle-class",
      "religion": "christian",
      "politics": "liberal",
      "sexual_orientation": "bisexual",
      "total_height": 69,
      "polarity": 0.1851851851851852,
      "subjectivity": 0.4903439153439153
    }
  }
}
