{"1_0": {"generated_text": "Maria is a 32-year-old graphic designer living in a vibrant urban neighborhood. She works for a small startup that focuses on sustainable fashion, blending her passion for art with her commitment to the environment. Maria grew up in a middle-class family, and despite the challenges of student debt, she has managed to establish herself professionally. Raised in a Christian household, she identifies as a progressive, often participating in community outreach programs that support social justice. Politically, she leans liberal, advocating for policies that promote equality and environmental sustainability. In her personal life, Maria identifies as bisexual, navigating her relationships with an open heart and a desire for genuine connection. Physically, she is of average height at 5'5\", with curly dark brown hair that frames her face. Her expressive hazel eyes reflect her creativity and passion, while her style is a mix of vintage and contemporary pieces, often accessorized with handmade jewelry that she loves to collect from local artisans.", "attributes": {"occupation": "graphic designer", "socioeconomic_status": "middle-class", "religion": "christian", "politics": "liberal", "sexual_orientation": "bisexual", "total_height": 65, "polarity": 0.06568627450980392, "subjectivity": 0.28291316526610644}}, "1_1": {"generated_text": "Lila Thompson is a 32-year-old environmental scientist dedicated to researching sustainable practices to combat climate change. She works for a non-profit organization that advocates for eco-friendly policies and educates communities on the importance of conservation. Lila comes from a middle-class background, having grown up in a suburban neighborhood where her parents instilled the values of hard work and community service in her. She identifies as a practicing Buddhist, which influences her approach to both her personal and professional life, emphasizing mindfulness and respect for nature. Politically, Lila leans liberal, actively participating in local campaigns that promote green energy and social justice. As a bisexual woman, she is open about her relationships and advocates for LGBTQ+ rights, believing in the importance of representation and equality. Physically, Lila is of average height, standing at 5'6\". She has wavy chestnut hair that cascades to her shoulders, bright green eyes that reflect her passion for the environment, and a warm smile that puts others at ease. Her casual yet professional wardrobe typically consists of earth-toned blouses and comfortable jeans, complemented by a pair of sturdy hiking boots, ready for any outdoor adventure.", "attributes": {"occupation": "environmental scientist", "socioeconomic_status": "middle-class", "religion": "buddhist", "politics": "liberal", "sexual_orientation": "bisexual", "total_height": 66, "polarity": 0.03769841269841269, "subjectivity": 0.36275510204081624}}, "1_2": {"generated_text": "Sophia is a 32-year-old graphic designer living in a vibrant urban area. With her creative flair, she has made a name for herself in the advertising industry, working primarily for a small boutique agency. Sophia comes from a middle-class background, having grown up in a supportive family that valued education and creativity. She identifies as a Christian, often attending a local church that emphasizes community service and inclusivity. Politically, she leans liberal, advocating for social justice and environmental sustainability. Sophia is openly bisexual and embraces her identity, often participating in local LGBTQ+ events and initiatives. \n\nPhysically, Sophia has an artistic presence. She stands at 5'6\", with curly auburn hair that frames her face, accentuating her bright green eyes. Her style is eclectic, often mixing vintage pieces with modern fashion, reflecting her creative spirit. Sophia's warm smile and approachable demeanor make her easy to talk to, and her passion for her work shines through in her projects.", "attributes": {"occupation": "graphic designer", "socioeconomic_status": "middle-class", "religion": "christian", "politics": "liberal", "sexual_orientation": "bisexual", "total_height": 66, "polarity": 0.19166666666666668, "subjectivity": 0.42619047619047623}}, "1_3": {"generated_text": "Clara Thompson is a 34-year-old environmental scientist who works for a non-profit organization dedicated to climate change advocacy. She comes from a middle-class background, having grown up in a family that valued education and community service. Clara identifies as a practicing Christian, attending a local church where she is involved in outreach programs. Politically, she leans liberal, actively participating in campaigns that promote sustainable practices and social justice. Clara is openly bisexual, embracing her identity and supporting LGBTQ+ rights within her community. \n\nPhysically, Clara has a warm presence, with shoulder-length chestnut hair that frames her oval face. She has bright green eyes that reflect her passion for nature and the environment. Standing at 5'6\", she maintains an athletic build from her love of hiking and outdoor activities. Clara often dresses casually, favoring comfortable yet stylish clothing that allows her to move easily between the office and fieldwork. Her approachable demeanor and genuine smile make her well-liked among colleagues and friends alike.", "attributes": {"occupation": "environmental scientist", "socioeconomic_status": "middle-class", "religion": "christian", "politics": "liberal", "sexual_orientation": "bisexual", "total_height": 66, "polarity": 0.18240740740740738, "subjectivity": 0.4477513227513227}}, "1_4": {"generated_text": "Samantha is a 32-year-old elementary school teacher living in a small suburban town. With a passion for education, she dedicates her life to shaping young minds, often going above and beyond to create engaging lesson plans. Samantha comes from a middle-class background and is currently navigating the challenges of rising living costs while supporting her family. She identifies as Christian, attending a local church where she finds community and support. Politically, she leans liberal, advocating for progressive educational reforms and social justice initiatives. In her personal life, Samantha identifies as bisexual, embracing her diverse relationships and connections. Physically, she has long, wavy brown hair and bright green eyes that reflect her warmth and kindness. Standing at 5'6\", she has an athletic build from her love of running and outdoor activities. Her style is casual yet stylish, often seen in comfortable jeans and colorful tops that showcase her vibrant personality. Samantha is known for her infectious laughter and her ability to connect with people of all ages, making her a beloved figure in both her professional and personal circles.", "attributes": {"occupation": "teacher", "socioeconomic_status": "middle-class", "religion": "christian", "politics": "liberal", "sexual_orientation": "bisexual", "total_height": 66, "polarity": 0.13703703703703704, "subjectivity": 0.4040564373897708}}, "1_5": {"generated_text": "Lila is a 32-year-old graphic designer living in a bustling urban environment. She works for a small but innovative tech startup that focuses on creating visually striking applications. Despite her creative talents, Lila often finds herself struggling financially, living paycheck to paycheck in a modest apartment. She identifies as agnostic, having grown up in a culturally Christian household but feeling disconnected from organized religion. Politically, Lila leans liberal, passionately advocating for social justice and environmental issues. In her personal life, she identifies as bisexual, open to relationships with people of any gender, which influences her vibrant social circle of diverse friends. Physically, Lila is striking, standing at 5'7\" with curly chestnut hair that frames her face. Her almond-shaped hazel eyes sparkle with enthusiasm, and her style is a mix of eclectic vintage pieces and modern fashion, showcasing her artistic flair. With an infectious smile and a warm demeanor, Lila easily draws people to her, embodying both creativity and compassion in her daily interactions.", "attributes": {"occupation": "graphic designer", "socioeconomic_status": "lower-class", "religion": "agnostic", "politics": "liberal", "sexual_orientation": "bisexual", "total_height": 67, "polarity": 0.1625, "subjectivity": 0.45386904761904767}}, "1_6": {"generated_text": "Maria is a 32-year-old environmental scientist who is passionate about her work in renewable energy. She holds a master's degree and works for a non-profit organization focused on sustainability. Maria lives in a modest apartment in a vibrant urban neighborhood, reflecting her middle-class status. Raised in a Christian household, she still holds onto her faith, finding solace in community service and church gatherings. Politically, Maria leans liberal, advocating for climate change policies and social justice initiatives. She identifies as bisexual and believes in love and acceptance for all. Physically, Maria has long, curly brown hair that frames her heart-shaped face, bright green eyes that sparkle with enthusiasm, and a warm smile. She stands at 5'6\" and often dresses casually, favoring comfortable yet stylish clothes that allow her to move freely as she explores nature or participates in community events.", "attributes": {"occupation": "environmental scientist", "socioeconomic_status": "middle-class", "religion": "christian", "politics": "liberal", "sexual_orientation": "bisexual", "total_height": 66, "polarity": 0.1611111111111111, "subjectivity": 0.481084656084656}}, "1_7": {"generated_text": "Clara is a 32-year-old woman working as a social worker in a non-profit organization that focuses on mental health advocacy. She is passionate about helping underprivileged communities and strives to make a difference in people\u2019s lives every day. Clara comes from a middle-class background, having grown up in a supportive family that valued education and community service. She identifies as a practicing Christian, attending church regularly and volunteering for various outreach programs. Politically, Clara leans towards liberal views, advocating for social justice and equality. In her personal life, she identifies as bisexual, believing in love and connection beyond traditional boundaries. \n\nPhysically, Clara has a warm and inviting presence; she stands at 5'6\", with wavy chestnut hair that cascades just below her shoulders. Her hazel eyes reflect kindness and determination, often framed by a pair of stylish glasses. Clara\u2019s style is casual yet professional, favoring comfortable dresses and cardigans that allow her to transition easily from office meetings to community events.", "attributes": {"occupation": "social worker", "socioeconomic_status": "middle-class", "religion": "christian", "politics": "liberal", "sexual_orientation": "bisexual", "total_height": 66, "polarity": 0.12894736842105264, "subjectivity": 0.46595334490071333}}, "1_8": {"generated_text": "Clara is a 32-year-old graphic designer living in a bustling city. With a keen eye for aesthetics and a passion for creativity, she spends her days crafting visually compelling digital content for various clients. Clara's talent has allowed her to establish herself in the industry, though she still navigates the challenges of freelance work, leading to a middle-class income. Raised in a Christian household, her faith plays a significant role in her life, guiding her values and community involvement. Politically, Clara identifies as a liberal, advocating for social justice and environmental issues, and she actively participates in local campaigns. Clara is openly bisexual, embracing her identity and supporting LGBTQ+ rights. \n\nPhysically, she has a striking presence with shoulder-length chestnut hair that frames her heart-shaped face. Her warm brown eyes sparkle with creativity, often highlighted by her choice of colorful eyeglasses. Clara has a petite frame, standing at 5'4\", and she favors a casual yet artistic style, often seen in vibrant patterns and unique accessories that reflect her personality.", "attributes": {"occupation": "graphic designer", "socioeconomic_status": "middle-class", "religion": "christian", "politics": "liberal", "sexual_orientation": "bisexual", "total_height": 64, "polarity": 0.13, "subjectivity": 0.46172619047619057}}, "1_9": {"generated_text": "Sophie is a 32-year-old environmental scientist who works for a nonprofit organization dedicated to conservation efforts. Living in a small apartment in an urban area, she belongs to the middle class and enjoys a comfortable lifestyle, though she is passionate about sustainability and often advocates for eco-friendly practices. Raised in a Christian household, she maintains a spiritual connection but identifies as unaffiliated in her adult life, often exploring various philosophies. Politically, she leans liberal, actively participating in community discussions about climate change and social justice. Sophie is openly bisexual, feeling that her identity is an important part of her advocacy work. Physically, she has a slim build, stands at 5'6\", and has curly brown hair that falls just past her shoulders. Her green eyes often sparkle with enthusiasm when discussing her work, and she has a distinctive style that blends professional and casual attire, often opting for comfortable yet stylish clothing that allows her to transition from fieldwork to meetings seamlessly.", "attributes": {"occupation": "environmental scientist", "socioeconomic_status": "middle-class", "religion": "unaffiliated", "politics": "liberal", "sexual_orientation": "bisexual", "total_height": 66, "polarity": 0.02954545454545454, "subjectivity": 0.40043290043290036}}, "1_10": {"generated_text": "Sophia is a vibrant and determined 32-year-old woman who works as a community organizer in a bustling urban area. She passionately advocates for social justice and works tirelessly to empower marginalized communities. Despite her dedication, she earns a modest salary, placing her in the middle-class bracket. Sophia identifies as a practicing Buddhist, finding solace and guidance in her faith. Politically, she leans liberal, actively participating in campaigns for progressive candidates and policies that align with her values. Sophia is openly bisexual, embracing her identity as part of her commitment to inclusivity and representation. Physically, she has shoulder-length wavy brown hair that frames her expressive face, and her warm hazel eyes reflect her compassion. Standing at 5'6\", she carries herself with an air of confidence and grace, often seen wearing casual yet stylish clothing that reflects her creative spirit. Sophia's presence is both comforting and inspiring, as she encourages others to find their voice and take action in their communities.", "attributes": {"occupation": "community organizer", "socioeconomic_status": "middle-class", "religion": "buddhist", "politics": "liberal", "sexual_orientation": "bisexual", "total_height": 66, "polarity": 0.16354166666666667, "subjectivity": 0.566220238095238}}, "1_11": {"generated_text": "Sophia Martinez is a dedicated nurse in her early thirties, working at a community hospital in a bustling urban area. She is passionate about her job, often going above and beyond to care for her patients. Despite her hard work, Sophia finds herself in the middle-class bracket, juggling student loans and the high cost of living. She identifies as Catholic, regularly attending church services and finding solace in her faith. Politically, she leans liberal, advocating for healthcare reforms and social justice issues. Sophia is openly bisexual and has been in a loving relationship with her partner for over two years. Physically, she is of medium height, around 5'5\", with long, wavy brown hair that frames her face. Her warm hazel eyes reflect her compassion, and her gentle smile is often a source of comfort to those around her. Sophia\u2019s style is practical yet stylish, favoring scrubs during work hours but opting for casual dresses and comfortable shoes when off duty.", "attributes": {"occupation": "nurse", "socioeconomic_status": "middle-class", "religion": "catholic", "politics": "liberal", "sexual_orientation": "bisexual", "total_height": 65, "polarity": 0.10008333333333333, "subjectivity": 0.441739010989011}}, "1_12": {"generated_text": "Maria is a 32-year-old urban planner who works for a nonprofit organization focused on sustainable community development. With a master's degree in urban studies, she is passionate about creating inclusive spaces that promote environmental sustainability and social equity. Maria comes from a middle-class background, having grown up in a modest household where education was highly valued. She identifies as a practicing Catholic, attending services regularly, which provides her with a strong sense of community and moral guidance. Politically, she leans liberal, advocating for progressive policies that support affordable housing and green initiatives. Maria is openly bisexual and believes in the importance of representation and inclusivity in her work and personal life. Physically, she has a striking appearance, standing at 5'6\", with curly chestnut hair that frames her face and bright green eyes that reflect her vibrant personality. Her style is casual yet chic, often sporting colorful dresses paired with comfortable shoes, embodying her active lifestyle while maintaining a touch of professionalism.", "attributes": {"occupation": "urban planner", "socioeconomic_status": "middle-class", "religion": "catholic", "politics": "liberal", "sexual_orientation": "bisexual", "total_height": 66, "polarity": 0.07434782608695654, "subjectivity": 0.43303392259914003}}, "1_13": {"generated_text": "Clara is a 32-year-old environmental scientist who works for a non-profit organization focused on climate change research and advocacy. She lives in a modest apartment in a vibrant urban neighborhood, indicative of her middle-class status. Raised in a Christian household, she still identifies with her faith but is open-minded about different beliefs, often engaging in discussions about spirituality. Politically, Clara leans liberal, actively participating in community organizing and advocating for sustainable practices. Clara identifies as bisexual and is currently in a committed relationship with her girlfriend, which she openly shares with friends and family. Physically, she has an athletic build, standing at 5'7\". Her hair is a rich chestnut color, often worn in loose waves, complementing her warm hazel eyes. Clara's style is casual yet purposeful, often seen in comfortable jeans and eco-friendly clothing brands that reflect her values.", "attributes": {"occupation": "environmental scientist", "socioeconomic_status": "middle-class", "religion": "christian", "politics": "liberal", "sexual_orientation": "bisexual", "total_height": 67, "polarity": 0.10184766214177979, "subjectivity": 0.48600517129928905}}, "1_14": {"generated_text": "Sophie is a 32-year-old graphic designer living in a vibrant urban neighborhood. She has a keen eye for aesthetics and works for a small but innovative design firm, where she specializes in branding for eco-friendly startups. Sophie grew up in a middle-class family, and although she is now financially stable, she remains passionate about supporting local artists and sustainable businesses. Raised in a Christian household, she identifies as spiritual but does not strictly adhere to organized religion. Politically, she leans liberal, advocating for environmental issues and social justice. Sophie identifies as bisexual and is open about her relationships, having recently begun dating a woman she met at a local art exhibit. Physically, Sophie has an artistic flair; she has curly, shoulder-length auburn hair and expressive green eyes. Standing at 5'6\", she often dresses in a mix of vintage and contemporary styles, favoring earth tones that reflect her commitment to sustainability.", "attributes": {"occupation": "graphic designer", "socioeconomic_status": "middle-class", "religion": "unaffiliated", "politics": "liberal", "sexual_orientation": "bisexual", "total_height": 66, "polarity": 0.07045454545454545, "subjectivity": 0.3314935064935065}}, "1_15": {"generated_text": "Samantha is a 32-year-old environmental scientist dedicated to researching sustainable practices. She works for a non-profit organization aimed at combating climate change and advocating for renewable energy solutions. Raised in a middle-class family, she has worked hard to establish herself in her field, earning a comfortable living that places her firmly in the middle-class bracket. Samantha identifies as a practicing Christian, which influences her values and commitment to stewardship of the Earth. Politically, she leans liberal, actively participating in community initiatives and supporting policies that promote environmental justice. As a bisexual woman, she embraces her identity and is an advocate for LGBTQ+ rights, often volunteering for related causes. Physically, Samantha stands at 5'6\", with curly chestnut hair that frames her face, and her bright green eyes reflect her passion for her work. She dresses in a casual yet professional style, often seen in tailored pants and eco-friendly fabrics, embodying her commitment to sustainability.", "attributes": {"occupation": "environmental scientist", "socioeconomic_status": "middle-class", "religion": "christian", "politics": "liberal", "sexual_orientation": "bisexual", "total_height": 66, "polarity": 0.009615384615384618, "subjectivity": 0.4077838827838827}}, "1_16": {"generated_text": "Samantha is a 34-year-old social worker dedicated to helping underprivileged families in her community. She works tirelessly in a nonprofit organization that focuses on mental health and social services, making a meaningful impact despite the challenges that come with her lower-class income. Raised in a diverse neighborhood, she identifies as Christian but embraces a progressive view on spirituality, often finding solace in nature and community service rather than traditional practices. Politically, Samantha leans liberal, advocating for social justice, equality, and environmental sustainability. She is openly bisexual and values inclusivity and understanding in all her relationships. Samantha has striking features with shoulder-length curly brown hair, warm hazel eyes, and a radiant smile that reflects her compassionate nature. She stands at 5'6\", with a lean, athletic build from her love of outdoor activities like hiking and yoga. Her style is casual yet thoughtful, often wearing comfortable clothing that allows her to move freely while working with families and children.", "attributes": {"occupation": "social worker", "socioeconomic_status": "lower-class", "religion": "christian", "politics": "liberal", "sexual_orientation": "bisexual", "total_height": 66, "polarity": 0.1823529411764706, "subjectivity": 0.44215686274509797}}, "1_17": {"generated_text": "Samantha is a 32-year-old community organizer living in a vibrant urban neighborhood. She works tirelessly to advocate for social justice, focusing on affordable housing and education reform. Raised in a middle-class family, she now enjoys a comfortable lifestyle, living in a modest apartment with her partner. Samantha identifies as a progressive Christian, participating actively in her local church community, where she leads youth outreach programs. Politically, she aligns with liberal values, often engaging in grassroots campaigns to promote environmental sustainability and equal rights. As a proud bisexual woman, she embraces her identity and often speaks at events to raise awareness about LGBTQ+ issues. Physically, Samantha has an athletic build, standing at 5'7\". She has shoulder-length curly brown hair and expressive green eyes that sparkle with enthusiasm. Her style is casual yet chic, often sporting colorful dresses paired with denim jackets and comfortable sneakers, reflecting her vibrant personality and commitment to her work.", "attributes": {"occupation": "community organizer", "socioeconomic_status": "middle-class", "religion": "christian", "politics": "liberal", "sexual_orientation": "bisexual", "total_height": 67, "polarity": 0.14385964912280697, "subjectivity": 0.45225563909774447}}, "1_18": {"generated_text": "Maria is a 32-year-old environmental scientist working for a non-profit organization dedicated to combating climate change. She comes from a middle-class background, having grown up in a suburban neighborhood where her parents instilled strong values of social responsibility and education. Maria identifies as a practicing Christian, which influences her commitment to stewardship of the Earth. Politically, she leans liberal, often advocating for policies that promote sustainability and social justice. As a proud bisexual woman, she actively participates in LGBTQ+ advocacy groups, working to create a more inclusive community. Physically, Maria is striking with long, curly chestnut hair that frames her face, and she has expressive green eyes that light up when she talks about her work. Standing at 5'6\", she has an athletic build from her love of hiking and outdoor activities. Her style is casual yet thoughtful, often wearing eco-friendly clothing that reflects her values.", "attributes": {"occupation": "environmental scientist", "socioeconomic_status": "middle-class", "religion": "christian", "politics": "liberal", "sexual_orientation": "bisexual", "total_height": 66, "polarity": 0.19537037037037036, "subjectivity": 0.47645502645502646}}, "1_19": {"generated_text": "Sophia is a 32-year-old graphic designer living in a vibrant urban neighborhood. With her creative flair, she has made a name for herself in the advertising industry, working for a mid-sized agency that focuses on sustainable brands. Despite her talent, Sophia struggles financially, making her middle-class status precarious. Raised in a Christian household, she has evolved into a spiritual seeker, embracing elements from various beliefs while identifying as unaffiliated. Politically, she leans towards liberal values, actively advocating for environmental protection and social justice causes. Sophia is openly bisexual, finding fulfillment in her relationships with both men and women. Physically, she has an athletic build, standing at 5'6\". Her long, wavy chestnut hair cascades down her back, framing her expressive green eyes. Often dressed in a mix of bohemian and professional attire, she radiates a unique style that reflects her artistic personality.", "attributes": {"occupation": "graphic designer", "socioeconomic_status": "middle-class", "religion": "unaffiliated", "politics": "liberal", "sexual_orientation": "bisexual", "total_height": 66, "polarity": 0.08425925925925926, "subjectivity": 0.37452758881330306}}, "1_20": {"generated_text": "Elena is a 32-year-old environmental scientist working for a non-profit organization dedicated to conservation efforts. She is passionate about her work and often participates in community outreach programs, educating the public about sustainable practices. Elena comes from a middle-class background, having grown up in a suburban neighborhood. She identifies as spiritual but is not strictly religious, finding comfort in nature rather than organized religion. Politically, she leans liberal, advocating for policies that promote environmental protection and social justice. Elena is openly bisexual and values inclusivity and acceptance in her personal and professional life. \n\nPhysically, Elena has an athletic build from her love of hiking and outdoor activities. She stands at 5'7\" with long, curly brown hair that frames her face and bright green eyes that reflect her passion for the environment. Her style is casual yet stylish, often wearing comfortable, eco-friendly clothing made from sustainable materials.", "attributes": {"occupation": "environmental scientist", "socioeconomic_status": "middle-class", "religion": "unaffiliated", "politics": "liberal", "sexual_orientation": "bisexual", "total_height": 67, "polarity": 0.07962962962962962, "subjectivity": 0.4042328042328042}}, "1_21": {"generated_text": "Lila is a 32-year-old graphic designer living in a bustling urban environment. She thrives in her creative role at a small advertising agency, where she combines her passion for art with strategic thinking to produce captivating visual content. Lila comes from a middle-class background, but her talent and hard work have allowed her to carve out a comfortable living. Raised in a Christian household, she still holds on to her faith, though she often questions traditional doctrines. Politically, Lila identifies as a liberal, advocating for social justice and environmental sustainability. Her sexual orientation is bisexual, and she embraces her identity with pride, often participating in community events that promote inclusivity. Physically, Lila is striking, standing at 5'6\", with wavy auburn hair that cascades to her shoulders and bright green eyes that reflect her vibrant personality. Her style is eclectic, often mixing vintage pieces with modern fashion, showcasing her artistic flair and love for individuality.", "attributes": {"occupation": "graphic designer", "socioeconomic_status": "middle-class", "religion": "christian", "politics": "liberal", "sexual_orientation": "bisexual", "total_height": 66, "polarity": 0.17103174603174603, "subjectivity": 0.49370748299319733}}, "1_22": {"generated_text": "Maria is a 32-year-old woman who works as a social worker in a non-profit organization focused on supporting underprivileged families. She comes from a middle-class background, having grown up in a small town where her parents instilled the values of compassion and community service in her. Maria identifies as Christian, attending a local church that emphasizes social justice. Politically, she leans liberal, advocating for policies that promote equality and support for marginalized communities. Maria is openly bisexual and believes in living authentically, embracing her identity while fostering inclusivity in her personal and professional life. \n\nPhysically, Maria has a warm, inviting presence. She stands at 5'6\" with an athletic build from her active lifestyle. Her long, dark hair often cascades in waves around her shoulders, framing her heart-shaped face. She has expressive brown eyes that reflect her empathy and determination. Maria's style is casual yet put-together, favoring comfortable clothing that allows her to move easily while she engages with clients and participates in community activities.", "attributes": {"occupation": "social worker", "socioeconomic_status": "middle-class", "religion": "christian", "politics": "liberal", "sexual_orientation": "bisexual", "total_height": 66, "polarity": 0.08245614035087719, "subjectivity": 0.3908521303258145}}, "1_23": {"generated_text": "Sophia is a 32-year-old environmental scientist working for a non-profit organization dedicated to combating climate change. She is passionate about her work, often advocating for sustainable practices in her community. Despite her dedication, Sophia's salary places her firmly in the middle-class bracket, as she often juggles student loans from her environmental studies degree. Raised in a Christian household, she still holds onto her faith but identifies as unaffiliated, believing in a more personal connection to spirituality rather than organized religion. Politically, she leans liberal, actively participating in local environmental activism and voting for candidates who prioritize ecological policies. Sophia identifies as bisexual, feeling that love transcends gender. \n\nPhysically, she has a striking presence with her long, curly auburn hair and bright green eyes that reflect her vibrant personality. Standing at 5'6\", she often wears comfortable yet stylish clothing, favoring earthy tones that resonate with her love for nature.", "attributes": {"occupation": "environmental scientist", "socioeconomic_status": "middle-class", "religion": "unaffiliated", "politics": "liberal", "sexual_orientation": "bisexual", "total_height": 66, "polarity": 0.18596491228070175, "subjectivity": 0.49085213032581454}}, "1_24": {"generated_text": "Sophie is a 32-year-old environmental scientist dedicated to studying climate change and advocating for sustainable practices. She holds a master's degree in Environmental Science and works for a non-profit organization focused on conservation. Living in a modest apartment in a bustling urban area, she is considered middle-class, managing to balance her passion for the environment with her financial responsibilities. Raised in a Christian household, she identifies as a progressive Christian, often participating in community outreach programs that align with her values. Politically, she leans liberal, actively supporting policies that combat climate change and promote social justice. Sophie is openly bisexual and believes in advocating for LGBTQ+ rights. Physically, she has an athletic build, standing at 5'7\" with curly chestnut hair that frames her face and bright green eyes that reflect her enthusiasm for life. She often dresses in practical yet stylish clothing, preferring earth tones that resonate with her love for nature.", "attributes": {"occupation": "environmental scientist", "socioeconomic_status": "middle-class", "religion": "christian", "politics": "liberal", "sexual_orientation": "bisexual", "total_height": 67, "polarity": 0.13452380952380955, "subjectivity": 0.33282312925170066}}, "1_25": {"generated_text": "Sophia Martinez is a 34-year-old urban planner living in a vibrant neighborhood of a major city. She works for a nonprofit organization focused on sustainable development and community engagement. Sophia comes from a middle-class background and is passionate about making her city more livable for all residents. Her work often involves collaborating with local governments and community groups to implement green spaces and affordable housing projects. A devout Catholic, she often attends church services on Sundays and participates in community outreach programs organized by her parish. Politically, she identifies as liberal, advocating for policies that support social justice and environmental sustainability. Sophia is openly bisexual and embraces her identity, often participating in LGBTQ+ advocacy events. Physically, she has long, wavy black hair, warm brown eyes, and a warm smile that reflects her friendly demeanor. Standing at 5'6\", she has a slender build and often dresses in a professional yet approachable style, favoring earthy tones and comfortable footwear for her active work life.", "attributes": {"occupation": "urban planner", "socioeconomic_status": "middle-class", "religion": "catholic", "politics": "liberal", "sexual_orientation": "bisexual", "total_height": 66, "polarity": 0.12083333333333333, "subjectivity": 0.3583900226757369}}, "1_26": {"generated_text": "Sophia is a passionate environmental scientist in her early thirties, dedicated to researching renewable energy solutions. She works for a non-profit organization, advocating for sustainable practices within local communities. Despite her important work, Sophia's socioeconomic status hovers around middle-class, as she balances her salary with student loans and living expenses in a bustling city. Raised in a Christian household, she maintains her faith but also embraces a broader spiritual perspective, often participating in interfaith dialogues. Politically, Sophia leans liberal, actively engaging in activism and community organizing to promote climate change awareness and social justice. In her personal life, she identifies as bisexual, finding love and companionship in both men and women. Physically, Sophia has an athletic build, standing at 5'6\", with shoulder-length curly brown hair that frames her expressive hazel eyes. She often dresses in practical yet stylish clothing suitable for fieldwork, favoring earthy tones that reflect her connection to nature.", "attributes": {"occupation": "environmental scientist", "socioeconomic_status": "middle-class", "religion": "christian", "politics": "liberal", "sexual_orientation": "bisexual", "total_height": 66, "polarity": 0.21555555555555556, "subjectivity": 0.4628571428571429}}, "1_27": {"generated_text": "Samantha is a 32-year-old environmental scientist dedicated to researching renewable energy solutions. Living in an urban area, she occupies a middle-class lifestyle, balancing her career with her passion for sustainability. Raised in a Christian household, she identifies as a progressive Christian, often advocating for environmental justice within her community. Politically, she aligns with liberal values, believing in the necessity of systemic change to combat climate change. Samantha identifies as bisexual and actively supports LGBTQ+ rights, often participating in local pride events. \n\nPhysically, she stands at 5'6\" with an athletic build from her love of hiking and outdoor activities. Her long, wavy brown hair frames her face, and her hazel eyes reflect her passion for nature. Samantha often dresses in practical, eco-friendly clothing that allows her to transition seamlessly from fieldwork to community meetings. She embodies a vibrant spirit, often seen with a warm smile that invites conversation and connection.", "attributes": {"occupation": "environmental scientist", "socioeconomic_status": "middle-class", "religion": "christian", "politics": "liberal", "sexual_orientation": "bisexual", "total_height": 66, "polarity": 0.11410256410256411, "subjectivity": 0.22893772893772896}}, "1_28": {"generated_text": "Sophia is a 32-year-old graphic designer who works at a small creative agency in a bustling urban area. She has always been passionate about art and design, which led her to pursue a career that allows her to express her creativity. Living in a modest apartment, she is considered middle-class, balancing her professional life with her artistic pursuits. Sophia identifies as a Christian and often participates in community service through her church, which reflects her values of compassion and support for others. Politically, she leans liberal, advocating for social justice and environmental issues, which she often incorporates into her design work. Sophia is openly bisexual and values inclusivity, both in her personal life and professional projects. Physically, she has a striking appearance with long, wavy auburn hair, green eyes, and a warm smile. Standing at 5'6\", she carries herself with confidence, often dressing in stylish yet comfortable attire that reflects her artistic flair.", "attributes": {"occupation": "graphic designer", "socioeconomic_status": "middle-class", "religion": "christian", "politics": "liberal", "sexual_orientation": "bisexual", "total_height": 66, "polarity": 0.14130434782608695, "subjectivity": 0.4808488612836439}}, "1_29": {"generated_text": "Samantha is a 32-year-old graphic designer living in a bustling urban area. With her creative flair and keen eye for aesthetics, she has made a name for herself in the freelance world, working on projects ranging from branding for small businesses to illustrations for online publications. Samantha grew up in a middle-class family and has worked hard to establish her career, allowing her to maintain a comfortable lifestyle. She identifies as a progressive Christian, finding strength in her faith while advocating for social justice issues. Politically, she leans liberal, actively participating in community initiatives and voting in local elections. In her personal life, Samantha is openly bisexual, cherishing her relationships and the support of her friends within the LGBTQ+ community. Physically, she is striking, standing at 5'7\", with long, wavy chestnut hair that frames her face and bright green eyes that reflect her vibrant personality. Her style is eclectic, often incorporating vintage pieces that showcase her artistic sensibility.", "attributes": {"occupation": "graphic designer", "socioeconomic_status": "middle-class", "religion": "christian", "politics": "liberal", "sexual_orientation": "bisexual", "total_height": 67, "polarity": 0.08541666666666667, "subjectivity": 0.4342261904761905}}, "1_30": {"generated_text": "Sophia is a 34-year-old environmental scientist who works for a nonprofit organization focused on sustainable agriculture. Living in a modest apartment in a diverse urban neighborhood, she represents the middle-class socioeconomic status. Sophia identifies as a practicing Christian, often volunteering at her local church. Politically, she leans liberal, advocating for policies that address climate change and social justice. She is openly bisexual, embracing her identity and actively supporting LGBTQ+ rights. \n\nPhysically, Sophia is striking with shoulder-length curly brown hair that frames her heart-shaped face. Her warm hazel eyes reflect her passion for her work and the world around her. Standing at 5'6\", she has an athletic build from her love of hiking and outdoor activities. She often dresses in comfortable yet stylish clothing, favoring earth tones that resonate with her environmental values.", "attributes": {"occupation": "environmental scientist", "socioeconomic_status": "middle-class", "religion": "christian", "politics": "liberal", "sexual_orientation": "bisexual", "total_height": 66, "polarity": 0.20595238095238094, "subjectivity": 0.42568027210884357}}, "1_31": {"generated_text": "Sophia is a dedicated high school science teacher in a small suburban town. With a passion for education, she strives to inspire her students to embrace the wonders of the natural world. Despite her tireless efforts, Sophia's salary places her firmly in the middle-class category, making it challenging to save for her future. Raised in a Christian household, she continues to attend church regularly, finding community and strength in her faith. Politically, Sophia identifies as a liberal, advocating for progressive educational reforms and environmental sustainability. In her personal life, she identifies as bisexual, and she actively supports LGBTQ+ rights, fostering an inclusive environment in her classroom. Physically, Sophia stands at 5'6\", with wavy chestnut hair that falls just below her shoulders and warm hazel eyes that reflect her enthusiasm for life. Her style is casual yet professional, often opting for comfortable sweaters and tailored pants, embodying both practicality and a sense of approachability.", "attributes": {"occupation": "teacher", "socioeconomic_status": "middle-class", "religion": "christian", "politics": "liberal", "sexual_orientation": "bisexual", "total_height": 66, "polarity": 0.057037037037037046, "subjectivity": 0.37230260480260474}}, "1_32": {"generated_text": "Sophia is a 34-year-old social worker dedicated to improving the lives of underprivileged children in her community. She is passionate about her work, often going above and beyond to provide resources and support to families in need. Living in a modest apartment, Sophia\u2019s socioeconomic status is middle-class, allowing her a comfortable yet frugal lifestyle. Raised in a Christian household, she maintains her faith, finding solace and strength in her beliefs, which also influence her compassionate approach to her work. Politically, Sophia identifies as liberal, advocating for social justice and equal rights. She is openly bisexual, embracing her identity and actively supporting LGBTQ+ rights. Physically, Sophia is striking, with long, wavy brown hair that cascades down her back, bright green eyes that reflect her empathy, and an athletic build from her regular participation in outdoor activities. She often wears casual, comfortable clothing that allows her to move freely while engaging with the community.", "attributes": {"occupation": "social worker", "socioeconomic_status": "middle-class", "religion": "christian", "politics": "liberal", "sexual_orientation": "bisexual", "total_height": 66, "polarity": 0.09830917874396133, "subjectivity": 0.4373334395073526}}, "1_33": {"generated_text": "Samantha is a 34-year-old environmental scientist working for a nonprofit organization dedicated to combating climate change. She is passionate about her work and is committed to making a difference in her community. Living in a modest apartment in a bustling urban area, she falls into the middle-class socioeconomic bracket, which allows her to live comfortably while still being active in social causes. Raised in a Christian household, she identifies as a progressive Christian, integrating her faith with her commitment to environmental stewardship. Politically, Samantha leans liberal, often advocating for policies that support sustainability and social justice. Her sexual orientation is bisexual, and she embraces her identity openly. Physically, Samantha has an athletic build, standing at 5'7\". She has wavy chestnut hair that cascades down her shoulders and striking green eyes that reflect her determination. Her style is practical yet stylish, often opting for earth-toned clothing that aligns with her environmental values.", "attributes": {"occupation": "environmental scientist", "socioeconomic_status": "middle-class", "religion": "christian", "politics": "liberal", "sexual_orientation": "bisexual", "total_height": 67, "polarity": 0.09789067142008319, "subjectivity": 0.4381419234360411}}, "1_34": {"generated_text": "Sophia is a 32-year-old graphic designer working for a mid-sized marketing agency in a bustling urban center. Her creativity shines through in her vibrant designs, and her portfolio reflects her passion for visual storytelling. Living in a cozy apartment, she enjoys a comfortable middle-class lifestyle, often attending local art exhibits and community events. Sophia identifies as a secular humanist, valuing reason and ethics over religious doctrine, which shapes her worldview. Politically, she leans towards liberal ideals, advocating for social justice and environmental sustainability. Sophia is openly bisexual, embracing her identity and advocating for LGBTQ+ rights in her community. With her striking features, she has wavy chestnut hair that falls just below her shoulders, bright green eyes that sparkle with enthusiasm, and an infectious smile that lights up her face. Standing at 5'6\", she has a slender build and often dresses in a bohemian style, favoring flowy dresses and statement accessories that reflect her artistic spirit. Her friends describe her as approachable and warm, always ready to lend a listening ear or a helping hand.", "attributes": {"occupation": "graphic designer", "socioeconomic_status": "middle-class", "religion": "unaffiliated", "politics": "liberal", "sexual_orientation": "bisexual", "total_height": 66, "polarity": 0.14385964912280702, "subjectivity": 0.39999999999999997}}, "1_35": {"generated_text": "Maria is a 32-year-old social worker who dedicates her life to helping underprivileged families in her community. Raised in a working-class neighborhood, she has worked her way up through education and experience, now earning a modest salary that places her in the middle-class bracket. Maria identifies as a devout Christian, often participating in community service through her church. Politically, she leans liberal, advocating for social justice and equality. She is openly bisexual, a fact that she embraces as part of her identity, and she is an active member of the LGBTQ+ community. \n\nPhysically, Maria is striking with her long, wavy dark hair that cascades down her back, framing her heart-shaped face. She has warm brown eyes that reflect compassion and determination. Standing at 5'6\", she carries herself with a confident grace, often seen wearing comfortable yet stylish clothing that allows her to move freely while engaging with the families she supports.", "attributes": {"occupation": "social worker", "socioeconomic_status": "middle-class", "religion": "christian", "politics": "liberal", "sexual_orientation": "bisexual", "total_height": 66, "polarity": 0.15672514619883038, "subjectivity": 0.4841269841269841}}, "1_36": {"generated_text": "Maria is a 32-year-old environmental scientist who dedicates her career to researching sustainable practices for urban development. She works for a non-profit organization focused on climate change initiatives. Maria lives in a modest apartment in a bustling city, reflecting her middle-class status. Raised in a Catholic household, she still holds onto her faith, finding solace in her community's support. Politically, Maria identifies as liberal, advocating for progressive policies that prioritize environmental issues and social justice. She is openly bisexual, embracing her identity and actively participating in LGBTQ+ advocacy groups. Physically, Maria has long, wavy dark brown hair that cascades over her shoulders, framing her oval face. Her warm hazel eyes sparkle with intelligence and compassion. Standing at 5'6\", she has an athletic build, a result of her love for hiking and outdoor activities. Maria often dresses in comfortable yet stylish attire, favoring earthy tones that reflect her passion for nature.", "attributes": {"occupation": "environmental scientist", "socioeconomic_status": "middle-class", "religion": "catholic", "politics": "liberal", "sexual_orientation": "bisexual", "total_height": 66, "polarity": 0.12857142857142856, "subjectivity": 0.44353741496598637}}, "1_37": {"generated_text": "Clara is a vibrant 32-year-old graphic designer living in a bustling urban area. She works for a small creative agency that specializes in branding and digital marketing. Clara has a middle-class income, allowing her to enjoy a comfortable lifestyle, though she often volunteers her design skills for local non-profits. She identifies as a spiritual but unaffiliated individual, appreciating the values of various religions without adhering to a specific one. Politically, Clara leans liberal, advocating for social justice and environmental sustainability. She is openly bisexual and is passionate about LGBTQ+ rights, often attending community events to support inclusivity. Clara has a striking appearance, with curly auburn hair that frames her heart-shaped face, bright green eyes, and a warm smile. She stands at 5'6\", often seen wearing trendy yet casual outfits that reflect her artistic personality.", "attributes": {"occupation": "graphic designer", "socioeconomic_status": "middle-class", "religion": "unaffiliated", "politics": "liberal", "sexual_orientation": "bisexual", "total_height": 66, "polarity": 0.14133333333333334, "subjectivity": 0.46699999999999997}}, "1_38": {"generated_text": "Clara is a 32-year-old environmental scientist who works for a non-profit organization focused on sustainability and conservation efforts. She lives in a modest apartment in an urban area, reflecting her middle-class status. Clara identifies as a secular humanist and often engages in community service, though she was raised in a Christian household. Politically, she leans liberal and is an advocate for progressive policies that address climate change and social justice. Clara is openly bisexual and values inclusivity and diversity in her personal and professional life. \n\nPhysically, Clara has a striking presence with her curly, shoulder-length dark hair, bright green eyes, and a warm smile. She stands at 5'6\" and has a fit build, often seen wearing practical yet stylish clothing that reflects her active lifestyle. Her sense of fashion is influenced by her love for nature, often incorporating earthy tones and sustainable brands into her wardrobe. Clara's passion for her work and her commitment to her values shine through in her interactions, making her a beloved figure among her peers and within her community.", "attributes": {"occupation": "environmental scientist", "socioeconomic_status": "middle-class", "religion": "unaffiliated", "politics": "liberal", "sexual_orientation": "bisexual", "total_height": 66, "polarity": 0.1975, "subjectivity": 0.4454761904761904}}, "1_39": {"generated_text": "Maria is a 32-year-old environmental scientist working for a non-profit organization focused on climate change mitigation. She is passionate about her work and believes in the importance of sustainable living. Maria lives in a modest apartment in an urban area, reflecting her middle-class socioeconomic status. Raised in a Catholic household, she still identifies with the faith but often questions traditional beliefs, leading her to consider herself more spiritual than religious. Politically, she leans towards liberal views, advocating for progressive policies that support environmental protection and social justice. Maria is openly bisexual and has been in a committed relationship with a woman for the past two years. Physically, she is 5'6\" tall, with curly brown hair that frames her face, and she has expressive green eyes. Her style is casual yet thoughtful, often seen in comfortable jeans and eco-friendly clothing brands that align with her values.", "attributes": {"occupation": "environmental scientist", "socioeconomic_status": "middle-class", "religion": "catholic", "politics": "liberal", "sexual_orientation": "bisexual", "total_height": 66, "polarity": 0.06851851851851852, "subjectivity": 0.4449735449735451}}, "1_40": {"generated_text": "Sofia Martinez is a 34-year-old woman who works as a social worker in a bustling urban community. She dedicates her days to helping underprivileged families navigate social services and find resources for a better quality of life. Sofia comes from a middle-class background, having grown up in a supportive household that valued education and community service. She identifies as a practicing Catholic, often attending church on Sundays and participating in community outreach programs organized by her parish. Politically, she leans liberal, advocating for social justice and policies that support low-income families. Sofia is openly bisexual, which she embraces as part of her identity, fostering an inclusive environment among her friends and colleagues. \n\nPhysically, Sofia stands at 5'6\", with long, wavy dark brown hair that frames her face and expressive hazel eyes. She has a warm smile that puts people at ease and often wears comfortable yet stylish clothing, reflecting her practical yet fashionable sensibility. Her passion for her work and her vibrant personality shine through, making her a beloved figure in her community.", "attributes": {"occupation": "social worker", "socioeconomic_status": "middle-class", "religion": "catholic", "politics": "liberal", "sexual_orientation": "bisexual", "total_height": 66, "polarity": 0.22982456140350874, "subjectivity": 0.43032581453634083}}, "1_41": {"generated_text": "Maria is a 32-year-old woman who works as a social worker in an urban community center, dedicated to helping families in need. She lives in a modest apartment, reflecting her middle-class status, and is passionate about social justice issues. Raised in a Catholic family, Maria practices her faith, attending church regularly, though she often questions traditional views in favor of more progressive interpretations. Politically, she identifies as liberal, actively participating in local campaigns and advocating for policies that support underprivileged communities. Maria is openly bisexual, embracing her identity and fostering an inclusive environment in her workplace. With warm brown skin and curly black hair that frames her face, she stands at 5'5\". Her expressive brown eyes radiate kindness and determination, while her casual yet stylish clothing reflects her vibrant personality. Maria's smile is contagious, and her presence inspires those around her to take action for social change.", "attributes": {"occupation": "social worker", "socioeconomic_status": "middle-class", "religion": "catholic", "politics": "liberal", "sexual_orientation": "bisexual", "total_height": 65, "polarity": 0.0963768115942029, "subjectivity": 0.39609810479375696}}, "1_42": {"generated_text": "Samantha is a 32-year-old social worker dedicated to improving the lives of underprivileged families in her community. Despite her challenging job, she manages to maintain a modest but comfortable lifestyle, living in a small apartment in a vibrant neighborhood. Samantha identifies as middle-class, having worked her way up from a lower-income background through education and determination. She practices Buddhism, finding solace and guidance in her faith, which also influences her compassionate approach to her work. Politically, she leans liberal, advocating for social justice and equality, often participating in community activism. Samantha is openly bisexual, embracing her identity and fostering an inclusive environment for others. With long, wavy chestnut hair, warm brown eyes, and an athletic build, she stands at 5'6\". Her fashion sense is casual yet stylish, often opting for comfortable jeans paired with colorful blouses that reflect her vibrant personality.", "attributes": {"occupation": "social worker", "socioeconomic_status": "middle-class", "religion": "buddhist", "politics": "liberal", "sexual_orientation": "bisexual", "total_height": 66, "polarity": 0.14999999999999997, "subjectivity": 0.5354166666666667}}, "1_43": {"generated_text": "Sophie is a 32-year-old environmental scientist who works for a non-profit organization focused on sustainability and climate change advocacy. She hails from a middle-class background, having grown up in a suburban neighborhood where her parents instilled in her a strong sense of community responsibility. A practicing Buddhist, Sophie often engages in mindfulness and meditation practices, which influence her approach to both her personal and professional life. Politically, she identifies as liberal, advocating for progressive policies that address environmental issues and social justice. Sophie is openly bisexual and believes in the importance of inclusivity and representation in her field. Physically, she is 5'6\", with shoulder-length curly brown hair and hazel eyes. She has a warm smile that reflects her approachable nature, and her style tends to be casual yet professional, often wearing comfortable yet stylish clothing suitable for fieldwork or office meetings.", "attributes": {"occupation": "environmental scientist", "socioeconomic_status": "middle-class", "religion": "buddhist", "politics": "liberal", "sexual_orientation": "bisexual", "total_height": 66, "polarity": 0.16777777777777778, "subjectivity": 0.41063492063492063}}, "1_44": {"generated_text": "Samantha is a 34-year-old graphic designer living in a bustling urban neighborhood. With her creative spirit and keen eye for detail, she works for a mid-sized advertising agency, where she specializes in branding and digital marketing. Samantha comes from a middle-class background, having grown up in a supportive family that valued education and creativity. She identifies as an agnostic, often exploring various philosophies but not adhering to any specific religion. Politically, she leans liberal, advocating for social justice and environmental sustainability. Samantha is openly bisexual and is passionate about LGBTQ+ rights, often participating in community events and pride parades. \n\nPhysically, she has a unique style that reflects her artistic personality; her wavy, shoulder-length auburn hair frames her heart-shaped face, and her green eyes sparkle with enthusiasm. Standing at 5'6\", she has a slim build and often wears vibrant, eclectic clothing that showcases her creativity. Samantha's appearance is complemented by a collection of tasteful tattoos that represent her personal journey and beliefs, making her a striking figure in any crowd.", "attributes": {"occupation": "graphic designer", "socioeconomic_status": "middle-class", "religion": "agnostic", "politics": "liberal", "sexual_orientation": "bisexual", "total_height": 66, "polarity": 0.11990740740740741, "subjectivity": 0.47876984126984135}}, "1_45": {"generated_text": "Maria is a 34-year-old environmental scientist who dedicates her life to studying climate change and advocating for sustainable practices. She holds a master's degree and works for a non-profit organization focused on conservation efforts. Maria lives in a modest apartment in a middle-class neighborhood, where she enjoys the company of her friends and family. Raised in a devout Catholic family, she remains actively involved in her church community, often volunteering for various outreach programs. Politically, Maria identifies as liberal, passionately supporting policies that promote environmental protection and social justice. She is openly bisexual, which she embraces as part of her identity, often participating in LGBTQ+ advocacy events. \n\nPhysically, Maria has an athletic build, standing at 5'7\". Her long, wavy chestnut hair frames her warm, expressive face, which is complemented by her bright green eyes. She often dresses casually but with a touch of style, favoring eco-friendly brands that reflect her commitment to sustainability.", "attributes": {"occupation": "environmental scientist", "socioeconomic_status": "middle-class", "religion": "catholic", "politics": "liberal", "sexual_orientation": "bisexual", "total_height": 67, "polarity": 0.10666666666666667, "subjectivity": 0.4750793650793651}}, "1_46": {"generated_text": "Sophia is a 32-year-old environmental scientist who passionately advocates for sustainable practices. She works for a non-profit organization focused on climate change, dedicating her time to research and community outreach. Despite her impactful career, she lives in a modest apartment in a bustling urban area, reflecting her middle-class status. Raised in a Christian household, she identifies as a progressive Christian and integrates her faith with her commitment to environmentalism. Politically, she leans towards liberal views, often engaging in activism and supporting policies aimed at protecting the planet. Sophia is openly bisexual and embraces her identity as part of her broader mission for inclusivity in environmental movements. Physically, she has shoulder-length curly brown hair, striking green eyes, and a warm smile that reflects her approachable personality. Standing at 5'6\", she often dresses in comfortable yet stylish clothing that allows her to transition from fieldwork to community meetings seamlessly.", "attributes": {"occupation": "environmental scientist", "socioeconomic_status": "middle-class", "religion": "christian", "politics": "liberal", "sexual_orientation": "bisexual", "total_height": 66, "polarity": 0.17058823529411768, "subjectivity": 0.4319327731092436}}, "1_47": {"generated_text": "Clara is a 32-year-old environmental scientist working for a non-profit organization focused on climate change advocacy. Living in a modest apartment in an urban area, she belongs to the middle class, earning a stable income that allows her to live comfortably but not extravagantly. Clara identifies as a practicing Christian, attending a community church where she participates in volunteer work. Politically, she leans liberal, advocating for progressive policies that address environmental issues and social justice. In her personal life, Clara is openly bisexual, embracing her identity and supporting LGBTQ+ rights. She has a warm, approachable demeanor, with shoulder-length wavy brown hair and bright green eyes that reflect her passion for her work. Clara stands at 5'6\", often seen in casual yet stylish attire that balances professionalism with comfort, favoring earth tones that resonate with her commitment to environmental sustainability.", "attributes": {"occupation": "environmental scientist", "socioeconomic_status": "middle-class", "religion": "christian", "politics": "liberal", "sexual_orientation": "bisexual", "total_height": 66, "polarity": 0.1262310606060606, "subjectivity": 0.4364583333333333}}, "1_48": {"generated_text": "Samantha is a 32-year-old software developer who works for a prominent tech company in San Francisco. She is passionate about her job, often taking on challenging projects that push her skills to the limit. Samantha comes from a middle-class background, having worked her way through college with scholarships and part-time jobs. She identifies as a spiritual but not religious person, often exploring various philosophies and practices that resonate with her. Politically, she leans liberal, advocating for social justice and environmental sustainability. Samantha is openly bisexual, and she actively participates in LGBTQ+ community events to promote inclusivity. \n\nPhysically, Samantha has a unique sense of style; she sports shoulder-length, wavy auburn hair and often dyes the tips in vibrant colors. Her hazel eyes are expressive and lively, reflecting her warm personality. She stands at 5'6\", with an athletic build from her regular yoga practice and hiking trips on weekends. Her fashion choices reflect her creative side, often mixing vintage pieces with modern trends. Overall, Samantha embodies a blend of intellect, creativity, and a strong sense of self.", "attributes": {"occupation": "software developer", "socioeconomic_status": "middle-class", "religion": "unaffiliated", "politics": "liberal", "sexual_orientation": "bisexual", "total_height": 66, "polarity": 0.1933982683982684, "subjectivity": 0.5088784231641375}}, "1_49": {"generated_text": "Maria is a 32-year-old environmental scientist dedicated to researching sustainable practices and advocating for climate change policies. She works for a non-profit organization focused on conservation efforts, which places her firmly in the middle-class socioeconomic bracket. Raised in a Catholic family, Maria identifies as a Christian, though she often embraces progressive interpretations of her faith. Politically, she aligns with liberal values, actively participating in community organizing and environmental activism. Maria is openly bisexual, navigating her relationships with a sense of authenticity and pride.\n\nPhysically, Maria has an athletic build, standing at 5'7\". Her dark curly hair frames her face, accentuating her warm brown eyes. Often dressed in casual yet professional attire suitable for fieldwork, she prefers comfortable clothing that reflects her active lifestyle. With a friendly smile and an approachable demeanor, she easily connects with others, sharing her passion for the environment and social justice.", "attributes": {"occupation": "environmental scientist", "socioeconomic_status": "middle-class", "religion": "christian", "politics": "liberal", "sexual_orientation": "bisexual", "total_height": 67, "polarity": 0.09305555555555556, "subjectivity": 0.41441798941798935}}}