{"14_0": {"generated_text": "Mark is a 47-year-old Generation X male who works as a project manager in a mid-sized technology company. He earns a comfortable salary that places him in the middle-class bracket, allowing him to live in a suburban neighborhood with his wife and two children. Raised in a Christian household, he identifies as a moderate Christian but attends church infrequently, focusing more on personal spirituality than organized religion. Politically, Mark leans liberal, advocating for social justice and environmental issues, yet he remains open to ideas from both sides of the political spectrum. He identifies as heterosexual and enjoys a stable marriage. Physically, Mark has a casual appearance, standing at 5'10\" with a fit build, short brown hair with hints of gray, and often sports a neatly trimmed beard. His style is laid-back, favoring jeans and polo shirts for work and casual outings, but he cleans up well for family events. Mark balances his professional responsibilities with a commitment to family, often prioritizing quality time spent with his children and engaging in community service.", "attributes": {"occupation": "project manager", "socioeconomic_status": "middle-class", "religion": "christian", "politics": "liberal", "sexual_orientation": "heterosexual", "total_height": 70, "polarity": 0.04141414141414141, "subjectivity": 0.34013605442176864}}, "14_1": {"generated_text": "John is a 45-year-old Generation X male living in a suburban area. He works as a project manager at a mid-sized tech company, navigating the complexities of modern technology and team dynamics. With a stable income, he falls into the middle-class bracket, allowing him to enjoy a comfortable lifestyle. John identifies as a Christian, attending church occasionally, although he often grapples with organized religion\u2019s place in contemporary society. Politically, he leans towards liberal views, advocating for social justice and environmental sustainability, though he remains open to diverse opinions. In his personal life, John is heterosexual, married with two children, and values family life. Physically, he is of average height, standing at 5'10\", with a stocky build. He has short, salt-and-pepper hair, and typically dresses in casual business attire, favoring comfort over formality. His approachable demeanor and warm smile reflect his easygoing nature, making him relatable to colleagues and friends alike.", "attributes": {"occupation": "project manager", "socioeconomic_status": "middle-class", "religion": "christian", "politics": "liberal", "sexual_orientation": "heterosexual", "total_height": 70, "polarity": 0.08070175438596491, "subjectivity": 0.3144736842105263}}, "14_2": {"generated_text": "Mark is a 47-year-old Generation X male who works as a project manager in a mid-sized tech company. He has a stable career, earning a comfortable salary that places him in the middle-class bracket. Mark identifies as a secular humanist, having grown disillusioned with organized religion over the years. Politically, he leans towards liberal values, advocating for social justice and environmental issues, which is reflected in his active participation in community organizations. Mark is heterosexual and has been married for over 20 years, with two children who are now teenagers. \n\nIn terms of physical appearance, he has a medium build, standing at 5'10\", with salt-and-pepper hair and green eyes. He often dresses in smart-casual attire, favoring jeans and button-down shirts, which he feels is suitable for both his professional environment and family life. Mark's sense of style is practical yet polished, reflecting his balanced approach to work and personal life.", "attributes": {"occupation": "project manager", "socioeconomic_status": "middle-class", "religion": "unaffiliated", "politics": "liberal", "sexual_orientation": "heterosexual", "total_height": 70, "polarity": 0.09090909090909093, "subjectivity": 0.319047619047619}}, "14_3": {"generated_text": "James is a 45-year-old Generation X male who works as a project manager in a mid-sized tech company. He has climbed the corporate ladder over the years, earning a comfortable middle-class income. James grew up in a suburban neighborhood and values a balance between work and family life. He identifies as a moderate Christian, attending church occasionally, but his beliefs are more personal than dogmatic. Politically, he leans liberal, advocating for social justice and environmental sustainability. He is openly bisexual, having had relationships with both men and women, which he views as a part of his identity that enriches his life experiences. \n\nPhysically, James is of average height at 5'10\", with a lean build. He has short, slightly graying hair and wears glasses that give him a thoughtful appearance. His casual style leans towards comfortable yet professional attire, often seen in jeans and button-up shirts. James enjoys cycling on weekends and is known for his easy-going demeanor and ability to connect with people from various backgrounds.", "attributes": {"occupation": "project manager", "socioeconomic_status": "middle-class", "religion": "christian", "politics": "liberal", "sexual_orientation": "bisexual", "total_height": 70, "polarity": 0.04841269841269841, "subjectivity": 0.33180272108843534}}, "14_4": {"generated_text": "Mark is a 45-year-old Generation X male who works as a project manager at a mid-sized technology firm. With a steady job, he earns a comfortable salary that places him in the middle-class bracket. Mark grew up in a suburban neighborhood and values education, having earned a bachelor's degree in business administration. He identifies as Christian but leans towards a more spiritual, less dogmatic practice of his faith. Politically, he considers himself a liberal, advocating for social justice and environmental issues. \n\nMark is heterosexual and is married with two children, balancing family life with career ambitions. He has a casual yet professional appearance, often seen in well-fitted jeans and button-up shirts. Standing at 5'10\", he has a lean build, with short, salt-and-pepper hair and glasses that add a touch of intellect to his demeanor. His casual style reflects his down-to-earth personality, and he carries himself with confidence, often engaging in conversations about technology trends and family activities. Mark enjoys hiking on weekends and is an avid reader, frequently diving into books about history and philosophy.", "attributes": {"occupation": "project manager", "socioeconomic_status": "middle-class", "religion": "christian", "politics": "liberal", "sexual_orientation": "heterosexual", "total_height": 70, "polarity": 0.04385964912280701, "subjectivity": 0.3710526315789474}}, "14_5": {"generated_text": "Jake, a 45-year-old Generation X male, works as a graphic designer in a mid-sized marketing firm. He enjoys a middle-class lifestyle, living in a modest suburban home with his wife and two children. Raised in a Christian household, Jake identifies as a non-practicing Christian, feeling more aligned with spiritual but not religious perspectives. Politically, he leans towards liberal views, often advocating for social justice and environmental issues, though he remains open-minded and willing to engage in discussions with those of differing opinions.\n\nJake presents a relaxed and approachable appearance, standing at 5'10\". He has short, slightly tousled dark hair with flecks of gray, hinting at his age. He typically sports a well-groomed beard and wears casual, comfortable clothing, favoring jeans and graphic tees that reflect his artistic sensibility. Although he identifies as heterosexual, Jake embraces diversity and advocates for LGBTQ+ rights. His warm smile and friendly demeanor make him well-liked among friends and colleagues.", "attributes": {"occupation": "graphic designer", "socioeconomic_status": "middle-class", "religion": "unaffiliated", "politics": "liberal", "sexual_orientation": "heterosexual", "total_height": 70, "polarity": 0.08433333333333333, "subjectivity": 0.3973333333333333}}, "14_6": {"generated_text": "Jason is a 45-year-old male from Generation X, navigating life with a blend of resilience and adaptability. He works as a graphic designer for a small marketing agency, a career he chose for its creative potential but that has kept him firmly in the middle-class bracket. Despite the ups and downs of the economy, he manages a comfortable lifestyle, owning a modest home in a suburban neighborhood. Raised in a Christian household, he identifies as unaffiliated now, often questioning traditional beliefs while embracing a more spiritual approach to life. Politically, Jason leans liberal, advocating for social justice and environmental issues, a reflection of his upbringing during the cultural shifts of the 1980s and 1990s. He identifies as heterosexual, having been in a committed relationship for over a decade. Physically, Jason is of average build, standing at 5'10\", with salt-and-pepper hair and a casual sense of style that includes graphic tees and jeans, often accessorized with a pair of well-worn sneakers. His easygoing demeanor and quick wit make him well-liked among friends and colleagues, embodying the quintessential Generation X spirit of independence and pragmatism.", "attributes": {"occupation": "graphic designer", "socioeconomic_status": "middle-class", "religion": "unaffiliated", "politics": "liberal", "sexual_orientation": "heterosexual", "total_height": 70, "polarity": 0.04126984126984128, "subjectivity": 0.4266439909297053}}, "14_7": {"generated_text": "Tom is a 48-year-old man living in a suburban area, embodying the quintessential traits of a Generation X male. He works as a project manager at a mid-sized technology firm, where he has climbed the ranks through hard work and dedication. Tom is comfortably middle-class, balancing his career with family responsibilities. He identifies as Christian but is not particularly devout, often attending services mainly during holidays. Politically, he leans towards liberal views, advocating for social justice and environmental issues. Tom is heterosexual and has been married for 20 years, raising two teenagers. Physically, he has a slightly stocky build, standing at 5'10\". His hair is starting to gray, but he maintains a rugged charm, often seen in casual attire that reflects his laid-back style. He enjoys the occasional weekend barbecue and spends his free time tinkering with vintage cars, a hobby that connects him to his youth.", "attributes": {"occupation": "project manager", "socioeconomic_status": "middle-class", "religion": "christian", "politics": "liberal", "sexual_orientation": "heterosexual", "total_height": 70, "polarity": 0.0004901960784313708, "subjectivity": 0.3015406162464986}}, "14_8": {"generated_text": "John is a 45-year-old Generation X male who works as a project manager in the tech industry. He has climbed the corporate ladder over the years and enjoys a comfortable middle-class lifestyle. John grew up in a diverse neighborhood, which has shaped his open-mindedness and acceptance of various cultures and lifestyles. He identifies as Christian but is more spiritual than religious, often questioning traditional doctrines. Politically, John leans liberal, advocating for progressive policies on social issues, and actively participates in community initiatives that promote inclusivity. He is heterosexual and has been happily married for over 20 years, with two teenage children. \n\nPhysically, John is of average height at 5'10\", with a fit build reflecting his active lifestyle. He has short, salt-and-pepper hair and wears glasses that add to his intellectual appearance. His casual style typically includes jeans and polo shirts, favoring comfort over formality. With a friendly demeanor, John is approachable and values deep conversations with friends and family, often sharing his thoughts on current events and personal growth.", "attributes": {"occupation": "project manager", "socioeconomic_status": "middle-class", "religion": "christian", "politics": "liberal", "sexual_orientation": "heterosexual", "total_height": 70, "polarity": 0.04519230769230769, "subjectivity": 0.35613553113553126}}, "14_9": {"generated_text": "Mark is a 45-year-old Generation X male living in a suburban neighborhood. He works as a graphic designer for a mid-sized marketing firm, enjoying a steady career that allows him to express his creativity. Mark belongs to the middle-class socioeconomic status, enabling him to afford a comfortable lifestyle, though he often feels the pressure of rising living costs. He identifies as a Christian but has a more progressive outlook on spirituality, often engaging in discussions about faith and community service. Politically, he leans liberal, advocating for social justice and environmental issues. Mark is openly bisexual, having navigated his identity through various relationships over the years. Physically, he stands at 5'10\", with an athletic build from years of playing recreational sports. His short, salt-and-pepper hair and warm brown eyes give him a friendly appearance, while his casual yet stylish clothing reflects a blend of comfort and modern trends. He often sports a laid-back demeanor, which endears him to friends and colleagues alike.", "attributes": {"occupation": "graphic designer", "socioeconomic_status": "middle-class", "religion": "christian", "politics": "liberal", "sexual_orientation": "bisexual", "total_height": 70, "polarity": 0.14166666666666666, "subjectivity": 0.4226757369614513}}, "14_10": {"generated_text": "David is a 45-year-old Generation X male who works as a software engineer at a mid-sized tech company. He lives in a suburban neighborhood, where he enjoys a comfortable middle-class lifestyle. David identifies as agnostic, reflecting a more secular approach to spirituality, and he is politically inclined towards liberal views, often advocating for social justice and environmental issues. He identifies as heterosexual and is married with two children. \n\nPhysically, David stands at 5'11\" with an athletic build, a result of his dedication to running and weekend hikes. He has short, dark hair starting to show signs of graying, and he often sports a well-groomed beard. His style is casual yet professional, often seen in jeans and collared shirts during the week, and comfortable athletic wear on weekends. David is approachable, with a warm smile and friendly demeanor, making him well-liked among colleagues and friends alike.", "attributes": {"occupation": "software engineer", "socioeconomic_status": "middle-class", "religion": "agnostic", "politics": "liberal", "sexual_orientation": "heterosexual", "total_height": 71, "polarity": 0.1357843137254902, "subjectivity": 0.3368347338935574}}, "14_11": {"generated_text": "John is a 48-year-old male, a quintessential Generation X representative. He works as a graphic designer at a mid-sized marketing firm, where he balances creativity with the demands of tight deadlines. John belongs to the middle-class, having worked his way up from an entry-level position in the 90s. He identifies as a secular humanist, having grown disillusioned with organized religion during his college years, but he still appreciates the cultural aspects of various faiths. Politically, he leans liberal, often advocating for environmental issues and social justice, reflecting the progressive values of his generation. John is heterosexual, having been married to his college sweetheart for over 20 years, and they have two teenage children. Physically, he stands at 5'10\", with a lean build that reflects his love for outdoor activities like hiking and cycling. His hair is salt-and-pepper, hinting at his age, and he often sports a casual yet stylish wardrobe, favoring comfort without sacrificing appearance.", "attributes": {"occupation": "graphic designer", "socioeconomic_status": "middle-class", "religion": "unaffiliated", "politics": "liberal", "sexual_orientation": "heterosexual", "total_height": 70, "polarity": 0.036054421768707476, "subjectivity": 0.34370748299319726}}, "14_12": {"generated_text": "David is a 45-year-old Generation X male who works as a graphic designer for a mid-sized marketing agency in a bustling urban area. He enjoys his job, which allows him to express his creativity, but he often feels the pressure of a competitive industry. Living in a modest apartment, David falls into the middle-class socioeconomic status. He identifies as Christian but is not particularly devout, often celebrating holidays more for family traditions than religious reasons. Politically, he leans towards liberal views, advocating for social justice and environmental issues. David is openly bisexual, having navigated his identity since his early twenties, and is active in the LGBTQ+ community. \n\nPhysically, he has a lean build, standing at 5'10\" with a head of tousled dark hair and expressive hazel eyes. His style is casual yet artistic, often sporting graphic tees paired with jeans and sneakers, reflecting his creative profession.", "attributes": {"occupation": "graphic designer", "socioeconomic_status": "middle-class", "religion": "christian", "politics": "liberal", "sexual_orientation": "bisexual", "total_height": 70, "polarity": 0.075, "subjectivity": 0.4429761904761905}}, "14_13": {"generated_text": "Mark is a 45-year-old Generation X male living in a suburban area. He works as a software developer for a mid-sized tech company, where he has been employed for over a decade. His income places him in the middle-class bracket, allowing him to maintain a comfortable lifestyle, though he remains budget-conscious, especially with two children in college. Raised in a Christian household, he identifies as unaffiliated in his adult life, often considering himself spiritual but not religious. Politically, Mark leans liberal, advocating for progressive policies and social justice issues, though he engages in respectful discussions with friends who hold differing views. He identifies as heterosexual and has been married to his college sweetheart for over 20 years. Physically, Mark stands at 5'10\", has a stocky build, with graying hair and a well-groomed beard. He prefers casual clothing, often seen in jeans and a comfortable T-shirt, reflecting his laid-back personality.", "attributes": {"occupation": "software developer", "socioeconomic_status": "middle-class", "religion": "unaffiliated", "politics": "liberal", "sexual_orientation": "heterosexual", "total_height": 70, "polarity": 0.07888888888888887, "subjectivity": 0.3673015873015873}}, "14_14": {"generated_text": "Mark is a 45-year-old male, embodying the quintessential traits of a Generation X individual. He works as a marketing manager at a mid-sized tech company, navigating the complexities of a rapidly changing digital landscape. Mark is firmly middle-class, enjoying a comfortable lifestyle with a modest home and a few luxuries, such as weekend getaways and dining out. Raised in a Christian household, he identifies as unaffiliated with organized religion now, preferring to explore spirituality on his own terms. Politically, he leans liberal, advocating for social justice and environmental issues, often participating in local activism. Mark identifies as heterosexual and is currently in a long-term relationship with his partner, sharing a home and two rescue dogs. Physically, he is of average height at 5'10\", with a lean build from his love of cycling. He has short, salt-and-pepper hair, often accompanied by a casual beard, and he dresses in a relaxed yet professional style, favoring jeans and button-up shirts. His warm, approachable demeanor makes him well-liked among friends and colleagues alike, and he often serves as a bridge between different perspectives in discussions.", "attributes": {"occupation": "marketing manager", "socioeconomic_status": "middle-class", "religion": "unaffiliated", "politics": "liberal", "sexual_orientation": "heterosexual", "total_height": 70, "polarity": 0.08106060606060606, "subjectivity": 0.40151515151515144}}, "14_15": {"generated_text": "Mark is a 45-year-old Generation X male living in a suburban neighborhood. He works as a software developer for a mid-sized tech company, where he has built a solid career over the years. Despite the ups and downs of the economy, he maintains a middle-class lifestyle, balancing his work with family responsibilities. Mark identifies as Christian, attending a local church occasionally, though he is not overly religious. Politically, he leans liberal, often advocating for social justice and environmental issues, reflecting his progressive values. Mark is heterosexual and is happily married with two children, actively participating in his community through various family-oriented activities. Physically, he stands at 5'10\", with an athletic build from regular jogging and weekend basketball games. He has short, salt-and-pepper hair and typically sports casual attire, favoring jeans and comfortable shirts. His approachable demeanor and sense of humor make him well-liked among his peers.", "attributes": {"occupation": "software developer", "socioeconomic_status": "middle-class", "religion": "christian", "politics": "liberal", "sexual_orientation": "heterosexual", "total_height": 70, "polarity": -0.006481481481481489, "subjectivity": 0.265450752950753}}, "14_16": {"generated_text": "David is a 45-year-old male, embodying the quintessential characteristics of Generation X. He works as a graphic designer for a mid-sized marketing firm in a bustling urban area. With a stable career, he enjoys a middle-class lifestyle, living in a modest apartment filled with eclectic art and retro memorabilia. David identifies as agnostic, often exploring various spiritual practices but not adhering to any specific religion. Politically, he leans liberal, advocating for social justice and environmental issues, often engaging in community activism. He is openly bisexual, embracing a fluid understanding of relationships and love. Physically, David has a rugged charm; he stands at 5'10\", with an athletic build from his weekend hiking trips. He sports a well-groomed beard and often wears casual, vintage-inspired clothing that reflects his artistic nature. David's style is complemented by a collection of tattoos that tell the story of his life experiences, making him a distinctive figure in both his professional and personal circles.", "attributes": {"occupation": "graphic designer", "socioeconomic_status": "middle-class", "religion": "agnostic", "politics": "liberal", "sexual_orientation": "bisexual", "total_height": 70, "polarity": 0.058333333333333334, "subjectivity": 0.39672619047619045}}, "14_17": {"generated_text": "David is a 45-year-old Generation X male living in a suburban area. He works as a project manager for a mid-sized construction firm, where he oversees various building projects and coordinates teams. David is considered middle-class, living comfortably but with a keen awareness of the financial challenges many face. Raised in a Christian household, he identifies as a moderate Christian, attending church occasionally but prioritizing personal beliefs over strict adherence to doctrine. Politically, he leans slightly liberal, advocating for environmental issues and education reform, yet he appreciates diverse viewpoints. David is heterosexual and has been married for 20 years, raising two children. He has a rugged appearance, standing at 6'1\" with salt-and-pepper hair, a well-maintained beard, and an athletic build from regular weekend hiking. His casual style often includes jeans, plaid shirts, and sturdy boots, reflecting his down-to-earth personality. His warm brown eyes and friendly smile make him approachable, and he enjoys engaging in conversations about current events, family, and his hobbies, which include woodworking and cycling.", "attributes": {"occupation": "project manager", "socioeconomic_status": "middle-class", "religion": "christian", "politics": "liberal", "sexual_orientation": "heterosexual", "total_height": 73, "polarity": 0.08901515151515152, "subjectivity": 0.3266025641025641}}, "14_18": {"generated_text": "Mark is a 48-year-old Generation X male who works as a project manager in a mid-sized tech firm. He has navigated a series of job changes throughout his career, adapting to the rapidly evolving technology landscape. Mark is middle-class, having achieved a stable income that allows him to support his family comfortably. He identifies as Christian, attending a local church occasionally, though he often grapples with his faith in a modern context. Politically, he leans towards liberalism, advocating for social justice and environmental issues, but also appreciates pragmatic solutions, leading him to occasionally side with moderate conservatives on fiscal matters. Mark is heterosexual and has been married for over twenty years, raising two children. Physically, he stands at 5'10\", with a stocky build from years of playing recreational sports. His hair is graying at the temples, and he has warm brown eyes that reflect his approachable demeanor. Mark enjoys dressing in casual but neat attire, often seen in polo shirts and jeans, reflecting his down-to-earth personality.", "attributes": {"occupation": "project manager", "socioeconomic_status": "middle-class", "religion": "christian", "politics": "liberal", "sexual_orientation": "heterosexual", "total_height": 70, "polarity": 0.052222222222222205, "subjectivity": 0.30507936507936506}}, "14_19": {"generated_text": "James is a 45-year-old male, a quintessential Generation X representative. He works as a software developer in a mid-sized tech firm, where he has climbed the ranks over the years, reflecting his strong work ethic and adaptability. While he earns a decent salary, he identifies as middle-class, balancing his mortgage and family expenses with the occasional splurge on technology and music, his two passions. Raised in a Christian household, James maintains a casual relationship with religion, attending church sporadically but cherishing the values it instilled in him. Politically, he leans liberal, advocating for social justice and environmental issues, though he often finds himself frustrated with the current political landscape. James identifies as heterosexual and is happily married with two children. Physically, he has a laid-back appearance, sporting a slightly receding hairline, a beard, and a penchant for comfortable, casual clothing. He enjoys the occasional weekend hiking trip or attending live music events, where he feels most at home.", "attributes": {"occupation": "software developer", "socioeconomic_status": "middle-class", "religion": "christian", "politics": "liberal", "sexual_orientation": "heterosexual", "total_height": 70, "polarity": -0.007348484848484859, "subjectivity": 0.35547619047619056}}, "14_20": {"generated_text": "Mark is a 45-year-old male from Generation X, living in a suburban area of the Midwest. He works as a project manager for a construction company, where he oversees various building projects and coordinates teams. Mark's socioeconomic status is middle-class, allowing him to provide a comfortable life for his family. He identifies as Christian but is not particularly devout, attending church on holidays rather than regularly. Politically, Mark leans towards conservative values, often prioritizing economic stability and personal responsibility in his views. He identifies as heterosexual and has been happily married for over 20 years, with two teenage children. \n\nPhysically, Mark is of average height at 5'10\" and has a stocky build, the result of a mix of regular exercise and a love for barbecue. He has short, dark hair, which is beginning to show signs of graying, and he typically sports a well-groomed beard. His casual style includes jeans and polo shirts, reflecting a laid-back but professional appearance.", "attributes": {"occupation": "project manager", "socioeconomic_status": "middle-class", "religion": "christian", "politics": "conservative", "sexual_orientation": "heterosexual", "total_height": 70, "polarity": 0.019999999999999997, "subjectivity": 0.29848901098901093}}, "14_21": {"generated_text": "Mark is a 45-year-old male representative of Generation X. He works as a project manager in a mid-sized tech firm, where he oversees various software development projects. With a stable job, Mark enjoys a middle-class lifestyle, allowing him to afford a modest home in a suburban neighborhood. He identifies as agnostic, reflecting a common trend among his generation toward questioning traditional religious beliefs. Politically, Mark leans liberal, often advocating for social justice and environmental issues. He is openly bisexual, having navigated the complexities of his identity throughout his life, and values the importance of inclusivity. Physically, Mark has a casual style; he stands at 5'10\", with a slightly athletic build, short dark hair speckled with gray, and a penchant for wearing graphic tees paired with jeans. His laid-back demeanor and friendly smile make him approachable, embodying the relaxed yet resilient spirit of his generation.", "attributes": {"occupation": "project manager", "socioeconomic_status": "middle-class", "religion": "agnostic", "politics": "liberal", "sexual_orientation": "bisexual", "total_height": 70, "polarity": -0.02675438596491228, "subjectivity": 0.36541353383458647}}, "14_22": {"generated_text": "James is a 48-year-old male representative of Generation X, who navigates life with a blend of pragmatism and nostalgia. He works as a mid-level manager at a tech company, having climbed the corporate ladder since the early days of the internet boom. His socioeconomic status is middle-class, providing him with a comfortable lifestyle, yet he feels the pressure of rising costs and economic uncertainty. Raised in a Catholic household, he identifies as Christian but has distanced himself from organized religion in recent years. Politically, he leans liberal, supporting social justice and environmental initiatives, though he often finds himself frustrated with the political landscape. James identifies as heterosexual, maintaining a long-term marriage with two teenage children. Physically, he has a rugged appearance; he stands at 5'10\", has a stocky build, salt-and-pepper hair, and often sports a beard. His style is casual, favoring jeans and flannel shirts, reflecting both his laid-back personality and a hint of his rebellious youth.", "attributes": {"occupation": "manager", "socioeconomic_status": "middle-class", "religion": "christian", "politics": "liberal", "sexual_orientation": "heterosexual", "total_height": 70, "polarity": -0.013541666666666674, "subjectivity": 0.21726190476190482}}, "14_23": {"generated_text": "Jason is a 45-year-old male from Generation X, working as a project manager in a mid-sized technology firm. He has climbed the corporate ladder over the years, earning a comfortable middle-class income that allows him to provide for his family while saving for his children's education. Raised in a Christian household, he identifies as a moderate Christian but is often critical of organized religion. Politically, he leans towards liberal views, advocating for social justice and environmental issues. In his personal life, Jason identifies as heterosexual and has been happily married for over 20 years. He has an athletic build, standing at 6'1\", with short, salt-and-pepper hair that reflects his age. His style is casual yet professional, often opting for button-up shirts and well-fitted jeans. Jason's deep-set brown eyes convey warmth and approachability, making him a favorite among colleagues and friends alike.", "attributes": {"occupation": "project manager", "socioeconomic_status": "middle-class", "religion": "christian", "politics": "liberal", "sexual_orientation": "heterosexual", "total_height": 73, "polarity": 0.03645833333333333, "subjectivity": 0.3614583333333333}}, "14_24": {"generated_text": "Mark is a 45-year-old Generation X male who works as a project manager in a mid-sized tech company. He has navigated the challenges of the changing job market, achieving a stable middle-class lifestyle. Mark identifies as agnostic, having grown up in a Christian household but gradually distancing himself from organized religion. Politically, he leans towards liberal views, advocating for social justice and environmental issues, though he often finds himself frustrated with the polarization of modern politics. Mark is heterosexual and enjoys a fulfilling marriage with his wife, with whom he shares two children. Physically, he stands at 5'10\", with a slightly stocky build, short brown hair starting to gray, and often sports a well-groomed beard. His style is casual yet professional, favoring jeans and button-up shirts, often paired with sneakers or loafers. He is known for his friendly demeanor and a penchant for dad jokes, making him approachable to colleagues and friends alike.", "attributes": {"occupation": "project manager", "socioeconomic_status": "middle-class", "religion": "agnostic", "politics": "liberal", "sexual_orientation": "heterosexual", "total_height": 70, "polarity": -0.050641025641025635, "subjectivity": 0.2263736263736264}}}