{"19_0": {"generated_text": "Sophia is a 24-year-old Generation Z female who works as a social media manager for a non-profit organization focused on climate change advocacy. She graduated from a state university with a degree in communications and carries student debt, placing her in the middle-class socioeconomic bracket. Raised in a progressive household, Sophia identifies as agnostic but respects various belief systems. Politically, she aligns with liberal values, actively participating in local activism and voting for candidates who prioritize environmental policies and social justice.\n\nSophia is openly bisexual, embracing her identity and advocating for LGBTQ+ rights within her community. Her physical appearance reflects her vibrant personality; she has shoulder-length, wavy teal hair, expressive brown eyes, and often sports a mix of vintage and contemporary fashion, favoring thrifted pieces. Standing at 5'6\", she has a slim build, frequently accessorizing with colorful jewelry that showcases her artistic flair. Sophia is passionate about using her skills to create positive change, and her online presence is filled with messages of empowerment and sustainability.", "attributes": {"occupation": "social media manager", "socioeconomic_status": "middle-class", "religion": "agnostic", "politics": "liberal", "sexual_orientation": "bisexual", "total_height": 66, "polarity": 0.1320707070707071, "subjectivity": 0.42435064935064937}}, "19_1": {"generated_text": "Sophia is a 24-year-old Generation Z female who works as a social media manager for a non-profit organization focused on climate change awareness. She is passionate about her job, utilizing her digital skills to engage a younger audience and promote sustainable practices. Coming from a middle-class background, Sophia has always been driven to make a difference in the world around her. She identifies as agnostic, reflecting a trend among her peers who often question traditional religious beliefs. Politically, she leans liberal, advocating for social justice and environmental policies, and actively participates in local activism. Sophia is openly bisexual, embracing her identity and supporting LGBTQ+ rights. With a vibrant sense of style, she sports shoulder-length dyed pink hair, often paired with vintage band tees and high-waisted jeans. Her expressive tattoos, which tell stories of her life and passions, peek out from under her sleeves. Standing at 5'6\", she has a slim build and carries herself with confidence, embodying the values of authenticity and individuality that resonate with her generation.", "attributes": {"occupation": "social media manager", "socioeconomic_status": "middle-class", "religion": "agnostic", "politics": "liberal", "sexual_orientation": "bisexual", "total_height": 66, "polarity": 0.0625, "subjectivity": 0.3270833333333334}}, "19_2": {"generated_text": "Emily is a 23-year-old Generation Z female living in a bustling urban area. She works as a social media manager for a nonprofit organization focused on climate change advocacy. Growing up in a middle-class family, she values education and has a degree in communications. Emily identifies as agnostic, feeling more connected to nature than traditional religious practices. Politically, she leans liberal, often participating in local activism and advocating for social justice causes. In her personal life, she identifies as bisexual and enjoys exploring the vibrant LGBTQ+ community in her city.\n\nWith a passion for fashion, Emily\u2019s physical appearance reflects her unique style. She has shoulder-length dyed blue hair, often adorned with colorful clips. Her casual yet trendy wardrobe typically includes oversized graphic tees, high-waisted jeans, and chunky sneakers. Standing at 5'6\", she has an athletic build, a testament to her love for outdoor activities and yoga. Emily's warm hazel eyes and infectious smile make her approachable, and her tattoos, each with personal significance, tell the story of her journey and beliefs.", "attributes": {"occupation": "social media manager", "socioeconomic_status": "middle-class", "religion": "agnostic", "politics": "liberal", "sexual_orientation": "bisexual", "total_height": 66, "polarity": 0.11920289855072462, "subjectivity": 0.3670807453416149}}, "19_3": {"generated_text": "A Generation Z female named Mia is a 23-year-old graphic designer living in a bustling urban area. She grew up in a middle-class family, where her parents emphasized the importance of education and creativity. Mia identifies as agnostic, having been raised in a household that celebrated various beliefs but ultimately allowed her the freedom to explore her own spirituality. Politically, she leans liberal, actively participating in social justice movements and advocating for climate change awareness. Mia is openly bisexual, finding love and connection in diverse relationships.\n\nPhysically, Mia has an edgy style characterized by brightly colored hair and an array of tattoos that express her individuality. She stands at 5'6\", with a slender build and an energetic presence that draws people in. Mia often wears vintage clothing mixed with contemporary pieces, showcasing her unique taste. Her social media is filled with vibrant artwork, snapshots of her life, and her passionate involvement in community events. She embodies the spirit of her generation, navigating the complexities of modern life with creativity and purpose.", "attributes": {"occupation": "graphic designer", "socioeconomic_status": "middle-class", "religion": "agnostic", "politics": "liberal", "sexual_orientation": "bisexual", "total_height": 66, "polarity": 0.14756944444444445, "subjectivity": 0.4892857142857143}}, "19_4": {"generated_text": "Sophia is a 24-year-old Generation Z female who works as a social media manager for a sustainable fashion brand. Raised in a middle-class family, she has always been passionate about environmental issues and fashion, leading her to pursue a career that aligns with her values. Sophia identifies as agnostic, having grown up in a Christian household but moving away from organized religion as she sought her own beliefs. Politically, she leans liberal, advocating for climate action and social justice, and often participates in protests and community initiatives.\n\nIn terms of her personal life, Sophia identifies as bisexual and is currently in a committed relationship with her girlfriend. She embraces her individuality through her eclectic style, often mixing vintage finds with contemporary pieces. Sophia has medium-length wavy hair dyed a vibrant shade of teal, and her skin is a warm olive tone. Standing at 5'6\", she has an athletic build from her love of outdoor activities like hiking and biking. Sophia\u2019s expressive style is complemented by her collection of piercings and tattoos, each telling a story about her journey and beliefs.", "attributes": {"occupation": "social media manager", "socioeconomic_status": "middle-class", "religion": "agnostic", "politics": "liberal", "sexual_orientation": "bisexual", "total_height": 66, "polarity": 0.19666666666666668, "subjectivity": 0.38333333333333336}}, "19_5": {"generated_text": "At 24 years old, Maya is a vibrant Generation Z female navigating the complexities of modern life. She works as a social media manager for a non-profit organization focused on environmental issues, reflecting her passion for sustainability. Growing up in a middle-class family, Maya values her education, having graduated with a degree in communications. She identifies as spiritual but does not adhere to a specific religion, believing in a blend of ideas that resonate with her. Politically, she leans liberal, actively advocating for climate action and social justice. Maya is openly bisexual and embraces her identity as part of her personal narrative. \n\nIn terms of appearance, Maya has a unique style that blends vintage thrift store finds with modern trends. She sports a short, curly haircut dyed a pastel pink, and her expressive outfits often include oversized sweaters and high-waisted jeans. Her warm brown skin is complemented by a collection of eclectic accessories, including earrings made from recycled materials. Maya embodies the values of her generation, combining activism with a sense of individuality and creativity.", "attributes": {"occupation": "social media manager", "socioeconomic_status": "middle-class", "religion": "unaffiliated", "politics": "liberal", "sexual_orientation": "bisexual", "total_height": 66, "polarity": 0.125, "subjectivity": 0.3416666666666666}}, "19_6": {"generated_text": "At 24, Maya is a vibrant Generation Z female making waves in the digital marketing industry. With a degree in communications, she works as a social media manager for a startup focused on sustainable products. Living in an urban area, she enjoys a middle-class lifestyle, balancing her passion for creativity with a desire for financial independence. Maya identifies as agnostic, valuing personal spirituality over traditional religious practices. Politically, she leans liberal, actively advocating for climate change awareness and social justice through her online platforms. \n\nMaya is openly bisexual, embracing her identity and fostering inclusivity within her social circles. Her appearance reflects her artistic flair; she has shoulder-length, brightly dyed purple hair, often styled in loose waves. Standing at 5'5\", she has a slender build and a penchant for eclectic fashion\u2014often mixing thrifted vintage pieces with contemporary streetwear. Her bright green eyes and warm smile exude a welcoming energy, making her a relatable figure to her peers. Maya embodies the spirit of her generation, blending ambition with authenticity, and using her voice to inspire change.", "attributes": {"occupation": "social media manager", "socioeconomic_status": "middle-class", "religion": "agnostic", "politics": "liberal", "sexual_orientation": "bisexual", "total_height": 65, "polarity": 0.12074592074592073, "subjectivity": 0.3289044289044289}}, "19_7": {"generated_text": "Amara is a 24-year-old Generation Z woman living in a vibrant urban area. She works as a social media manager for a non-profit organization focused on climate change awareness. Amara grew up in a middle-class family and has a strong commitment to her work, believing that social media can drive real change. She identifies as spiritual but not religious, often drawing inspiration from various philosophies rather than adhering to a single religion. Politically, she leans liberal, actively participating in local activism and voting for progressive candidates. Amara is openly bisexual and values inclusivity and diversity in her personal life and work. \n\nPhysically, she has a unique style characterized by colorful hair, often dyed in shades of blue or purple, which reflects her creative personality. She has a slim build, standing at 5'6\", and frequently wears vintage clothing mixed with contemporary pieces, showcasing her love for thrift shopping and sustainability. Her piercings and tattoos tell stories of her values and experiences, making her a distinctive figure in her community.", "attributes": {"occupation": "social media manager", "socioeconomic_status": "middle-class", "religion": "unaffiliated", "politics": "liberal", "sexual_orientation": "bisexual", "total_height": 66, "polarity": 0.10848214285714286, "subjectivity": 0.3357142857142858}}, "19_8": {"generated_text": "Sophia is a 22-year-old woman who embodies the spirit of Generation Z. She works as a social media manager for a small, eco-conscious startup in her urban neighborhood. Growing up in a middle-class family, she has a strong sense of community and is passionate about sustainability and social justice. Sophia identifies as agnostic, having grown up in a Christian household but finding her own path in terms of spirituality. Politically, she leans liberal, often advocating for climate change initiatives and LGBTQ+ rights. Sophia is openly bisexual, which she embraces as part of her identity, and she uses her platform to raise awareness about LGBTQ+ issues. In terms of physical appearance, she has a unique style characterized by colorful hair, often dyed in shades of blue or lavender, and a penchant for thrifted clothing. Her expressive tattoos tell stories of her experiences and beliefs. Sophia stands at 5'6\", with a confident posture that reflects her commitment to authenticity and self-expression.", "attributes": {"occupation": "social media manager", "socioeconomic_status": "middle-class", "religion": "agnostic", "politics": "liberal", "sexual_orientation": "bisexual", "total_height": 66, "polarity": 0.1734375, "subjectivity": 0.4495535714285714}}, "19_9": {"generated_text": "Sophia is a 23-year-old Generation Z woman living in a vibrant urban area. She works as a social media manager for a nonprofit organization focused on environmental issues, reflecting her passion for sustainability and social justice. Coming from a middle-class background, she balances her work with freelance graphic design projects to support her lifestyle. Sophia identifies as agnostic, embracing a spiritual but non-religious worldview, and her political views lean strongly liberal, advocating for progressive policies and climate action. She is openly bisexual, actively participating in LGBTQ+ community events and initiatives. \n\nPhysically, Sophia has a unique style that reflects her creative personality; she has shoulder-length dyed lavender hair, often styled in loose waves. Her fashion sense is eclectic, favoring thrifted vintage pieces mixed with contemporary brands. With a height of 5'6\", she has a slender build and an expressive face adorned with freckles. Sophia's style is complemented by her love for colorful accessories and statement earrings, showcasing her individuality and artistic flair.", "attributes": {"occupation": "social media manager", "socioeconomic_status": "middle-class", "religion": "agnostic", "politics": "liberal", "sexual_orientation": "bisexual", "total_height": 66, "polarity": 0.16816239316239315, "subjectivity": 0.42200418628990055}}, "19_10": {"generated_text": "In a bustling urban environment, a Generation Z female named Mia stands out with her vibrant personality and unique sense of style. At 22 years old, she works as a social media manager for a sustainable fashion brand, a role that perfectly aligns with her passion for environmental issues and digital communication. Growing up in a middle-class family, she understands the value of hard work and is determined to make a difference in her community. Mia identifies as spiritual but not religious, often exploring various belief systems while embracing a sense of personal growth. Politically, she leans liberal, advocating for social justice, climate action, and equality. Her sexuality is fluid; she identifies as bisexual and actively supports LGBTQ+ rights. Physically, Mia is striking, with shoulder-length dyed lavender hair, a sprinkle of freckles across her nose, and an eclectic wardrobe that combines thrifted pieces with high-fashion items. Her style is a reflection of her individuality and commitment to sustainability, often accessorizing with handmade jewelry and vintage finds. With an engaging smile and a confident demeanor, Mia embodies the spirit of her generation, navigating the complexities of modern life with creativity and conviction.", "attributes": {"occupation": "social media manager", "socioeconomic_status": "middle-class", "religion": "unaffiliated", "politics": "liberal", "sexual_orientation": "bisexual", "total_height": 66, "polarity": 0.13680555555555554, "subjectivity": 0.3556051587301587}}, "19_11": {"generated_text": "At 24 years old, Mia is a vibrant Generation Z female navigating her early career as a social media manager for a popular non-profit organization focused on environmental sustainability. Growing up in a middle-class household, she learned the importance of financial stability and social responsibility from her parents, who emphasized community involvement. Mia identifies as agnostic, often expressing her belief in the importance of personal spirituality over organized religion. Politically, she leans liberal, advocating for climate action and social justice, which is reflected in her activism and online presence. Mia is openly bisexual, proudly supporting LGBTQ+ rights and inclusion. \n\nPhysically, she has a unique style characterized by colorful hair, often changing from pastel pink to electric blue, and her wardrobe is a mix of vintage thrift finds and contemporary streetwear. With a height of 5'6\", she has an athletic build, a testament to her love for outdoor activities like hiking and biking. Her bright green eyes and warm smile make her approachable, and she often uses her platform to inspire others to engage in meaningful conversations about societal issues.", "attributes": {"occupation": "social media manager", "socioeconomic_status": "middle-class", "religion": "agnostic", "politics": "liberal", "sexual_orientation": "bisexual", "total_height": 66, "polarity": 0.17532051282051284, "subjectivity": 0.3215201465201465}}, "19_12": {"generated_text": "Sophia is a 22-year-old Generation Z female living in an urban environment. She works as a social media manager for a non-profit organization focused on environmental issues. Growing up in a middle-class family, she values sustainability and community engagement, often volunteering in local clean-up initiatives. Sophia identifies as agnostic, having been raised in a Christian household but now embracing a more secular worldview. Politically, she leans liberal, advocating for climate action and social justice. Her sexual orientation is bisexual, and she feels empowered to express her identity openly within her circle of friends. \n\nSophia has a unique sense of style, often incorporating thrifted clothing into her wardrobe, which reflects her commitment to sustainability. She has shoulder-length, wavy dark hair and bright green eyes, often highlighted with colorful makeup that matches her vibrant personality. Standing at 5'5\", she carries herself with confidence and embodies the values of her generation.", "attributes": {"occupation": "social media manager", "socioeconomic_status": "middle-class", "religion": "agnostic", "politics": "liberal", "sexual_orientation": "bisexual", "total_height": 65, "polarity": 0.13872549019607844, "subjectivity": 0.32745098039215687}}, "19_13": {"generated_text": "Sophia is a 22-year-old Generation Z female who works as a social media manager for a sustainable fashion brand. She is passionate about environmental issues and uses her platform to promote ethical practices in the fashion industry. Coming from a middle-class background, Sophia is currently navigating student loans while living in a vibrant urban area. She identifies as agnostic and often engages in discussions about spirituality and self-discovery with her friends. Politically, she leans liberal and is actively involved in local activism, advocating for climate change awareness and social justice. Sophia is openly bisexual and values inclusivity in her relationships and friendships. In terms of her physical appearance, she has a unique sense of style, often combining thrifted vintage pieces with modern trends. She has shoulder-length, wavy brown hair, expressive hazel eyes, and a passion for bold accessories, often sporting colorful makeup that reflects her creative personality.", "attributes": {"occupation": "social media manager", "socioeconomic_status": "middle-class", "religion": "agnostic", "politics": "liberal", "sexual_orientation": "bisexual", "total_height": 66, "polarity": 0.14517543859649124, "subjectivity": 0.431203007518797}}, "19_14": {"generated_text": "Sophia is a 23-year-old Generation Z female who works as a social media manager for a non-profit organization focused on environmental issues. She graduated from college with a degree in communications and is currently living in a small apartment in an urban area. Sophia comes from a middle-class background, and her job allows her to live comfortably, though she is always conscious of her budget. She identifies as agnostic, having grown up in a Christian household but now embracing a more secular worldview. Politically, she leans liberal, actively participating in local activism and supporting progressive causes. Sophia is openly bisexual, and she values inclusivity and representation in all aspects of life. In terms of physical appearance, she has shoulder-length, dyed teal hair, often styled in loose waves. Her style is eclectic, mixing vintage clothing with modern accessories, and she enjoys expressing her personality through her fashion choices. Sophia\u2019s warm brown eyes and freckles give her a youthful appearance, and she often wears minimal makeup, preferring a natural look.", "attributes": {"occupation": "social media manager", "socioeconomic_status": "middle-class", "religion": "agnostic", "politics": "liberal", "sexual_orientation": "bisexual", "total_height": 65, "polarity": 0.08378288378288377, "subjectivity": 0.33787720216291645}}, "19_15": {"generated_text": "Sophia is a 24-year-old Generation Z female living in a vibrant urban area. She works as a digital marketing specialist for a tech startup, utilizing her creativity and social media expertise to engage audiences and drive brand awareness. Sophia comes from a middle-class background, with her parents supporting her education and career aspirations. She identifies as agnostic, exploring various spiritual practices but not adhering to any specific religion. Politically, she leans liberal, advocating for social justice, climate action, and inclusivity in her community. Sophia identifies as bisexual, embracing her fluid sexuality and actively participating in LGBTQ+ events and discussions. She has a unique physical appearance, with shoulder-length teal hair, expressive hazel eyes, and a penchant for eclectic fashion that combines thrifted pieces with trendy accessories. Her style reflects her personality\u2014bold, creative, and unapologetically herself.", "attributes": {"occupation": "digital marketing specialist", "socioeconomic_status": "middle-class", "religion": "agnostic", "politics": "liberal", "sexual_orientation": "bisexual", "total_height": 65, "polarity": 0.14342105263157895, "subjectivity": 0.3465538847117795}}, "19_16": {"generated_text": "Emma is a 24-year-old Generation Z female who works as a social media manager for a non-profit organization focused on environmental issues. Living in a bustling urban area, she navigates life on a middle-class salary, balancing her passion for sustainability with the need to make a living. Raised in a secular household, she identifies as unaffiliated with any particular religion, embracing a more spiritual, nature-connected belief system. Politically, Emma leans liberal, actively participating in local activism and advocating for climate change awareness. She identifies as bisexual, openly discussing her relationships and experiences with friends and online communities. Emma has a distinct sense of style that combines vintage thrift finds with contemporary pieces, often seen in high-waisted jeans, oversized graphic tees, and colorful sneakers. Her long, wavy, dyed blue hair complements her expressive hazel eyes and fair skin, while her nose ring adds an edgy touch to her overall look. Emma embodies the spirit of her generation, using her creativity and social media skills to promote causes she cares about while staying true to her authentic self.", "attributes": {"occupation": "social media manager", "socioeconomic_status": "middle-class", "religion": "unaffiliated", "politics": "liberal", "sexual_orientation": "bisexual", "total_height": 66, "polarity": 0.1463768115942029, "subjectivity": 0.3601449275362319}}, "19_17": {"generated_text": "Samantha is a 24-year-old Generation Z female who works as a digital marketing specialist for a startup in her city. She comes from a middle-class background, having been raised in a suburban neighborhood where her parents instilled the values of hard work and education in her. Samantha identifies as spiritual but is largely unaffiliated with organized religion, finding peace in nature and meditation rather than traditional practices. Politically, she leans liberal, advocating for social justice and climate change initiatives, which she often discusses on her social media platforms. Samantha identifies as bisexual, feeling empowered to express her identity in a world that is increasingly accepting of diverse sexual orientations. \n\nPhysically, she has an athletic build, standing at 5'6\" with shoulder-length, wavy brown hair that she often dyes with vibrant colors. Her style reflects her personality: a mix of vintage thrift finds and modern streetwear, adorned with unique accessories and colorful sneakers. With an infectious smile and expressive eyes, Samantha embodies the creativity and authenticity of her generation.", "attributes": {"occupation": "digital marketing specialist", "socioeconomic_status": "middle-class", "religion": "unaffiliated", "politics": "liberal", "sexual_orientation": "bisexual", "total_height": 66, "polarity": 0.1461640211640212, "subjectivity": 0.35350529100529104}}, "19_18": {"generated_text": "Lila is a 24-year-old graphic designer living in a vibrant urban environment. She grew up in a middle-class family that instilled strong values of creativity and social awareness in her. Lila identifies as a spiritual but unaffiliated person, often drawing inspiration from various philosophies but not adhering strictly to any organized religion. Politically, she leans liberal, actively participating in local environmental initiatives and advocating for social justice issues. Lila is openly bisexual and values inclusivity and representation in her work and personal life. \n\nPhysically, she has a striking appearance with shoulder-length, dyed lavender hair that reflects her artistic flair. Lila has a penchant for vintage fashion, often mixing thrifted pieces with modern streetwear to create a unique style that stands out. Her expressive tattoos tell stories of her experiences and beliefs, further enhancing her individuality. Lila is known for her warm smile and approachable demeanor, making her a beloved figure among her peers.", "attributes": {"occupation": "graphic designer", "socioeconomic_status": "middle-class", "religion": "unaffiliated", "politics": "liberal", "sexual_orientation": "bisexual", "total_height": 66, "polarity": 0.18876811594202894, "subjectivity": 0.4511387163561077}}, "19_19": {"generated_text": "Lila is a 24-year-old female who embodies the spirit of Generation Z. Recently graduated with a degree in environmental science, she works as a sustainability consultant for a non-profit organization, helping businesses reduce their carbon footprint. Lila comes from a middle-class background, having grown up in a supportive household that valued education and activism. She identifies as spiritual but not religious, embracing a blend of mindfulness practices without adhering to a specific faith. Politically, Lila leans liberal, actively participating in climate change advocacy and social justice initiatives. She is openly bisexual, believing in love and acceptance for all. Physically, Lila has a unique style, often sporting colorful hair and expressive tattoos that reflect her values and interests. She stands at 5'6\", with an athletic build from her love of outdoor activities like hiking and yoga. Lila is a vibrant representation of her generation, balancing her professional ambitions with a commitment to making the world a better place.", "attributes": {"occupation": "sustainability consultant", "socioeconomic_status": "middle-class", "religion": "unaffiliated", "politics": "liberal", "sexual_orientation": "bisexual", "total_height": 66, "polarity": 0.19166666666666665, "subjectivity": 0.41409774436090224}}, "19_20": {"generated_text": "In a vibrant urban setting, a 24-year-old Generation Z female named Maya navigates her life with a blend of ambition and authenticity. Maya works as a digital marketing specialist for a nonprofit organization focused on environmental sustainability. Coming from a middle-class background, she values social impact and often engages in community activism. Raised in a multicultural family, Maya identifies as unaffiliated with any religion, though she respects various beliefs and practices mindfulness in her daily life. Politically, she leans liberal, advocating for progressive policies that address climate change and social justice issues. Maya identifies as bisexual, embracing her fluidity in relationships and finding strength in her diverse identity. With striking teal hair and an eclectic sense of style that often includes thrifted vintage clothing, she stands at 5'6\". Her expressive tattoos tell stories of her journey and beliefs, making her a unique presence in any room she enters.", "attributes": {"occupation": "digital marketing specialist", "socioeconomic_status": "middle-class", "religion": "unaffiliated", "politics": "liberal", "sexual_orientation": "bisexual", "total_height": 66, "polarity": 0.15902777777777777, "subjectivity": 0.3527777777777778}}, "19_21": {"generated_text": "Lila is a 22-year-old Generation Z woman navigating the complexities of modern life. Recently graduated with a degree in environmental science, she works as a sustainability consultant for a non-profit organization focused on climate action. Lila comes from a middle-class background and is passionate about social justice and environmental issues, often engaging in community activism. Raised in a secular household, she identifies as unaffiliated with any religion, valuing personal spirituality over organized belief systems. Politically, she leans liberal, advocating for progressive policies that address climate change and promote equality. Lila identifies as bisexual, embracing her fluidity in relationships. With an athletic build, she stands at 5'6\" and has shoulder-length, wavy brown hair that she often styles with colorful clips. Her style reflects her creative personality, favoring vintage clothing and eco-friendly brands, often accessorized with handmade jewelry. Lila\u2019s expressive hazel eyes and warm smile draw people in, making her both approachable and inspiring in her pursuits.", "attributes": {"occupation": "sustainability consultant", "socioeconomic_status": "middle-class", "religion": "unaffiliated", "politics": "liberal", "sexual_orientation": "bisexual", "total_height": 66, "polarity": 0.2630952380952381, "subjectivity": 0.4833333333333333}}, "19_22": {"generated_text": "Meet Mia, a 24-year-old Generation Z female living in a vibrant urban area. She works as a social media manager for a sustainable fashion brand, a job that allows her to blend her passion for environmental issues with her love for creativity. Mia grew up in a middle-class household, but she is currently navigating the challenges of student debt while trying to establish her career. She identifies as agnostic, reflecting a trend among her peers who prioritize personal beliefs over organized religion. Politically, Mia leans liberal, actively participating in movements advocating for climate action and social justice. She is openly bisexual and embraces her identity, often sharing her experiences on social platforms to foster understanding and inclusivity. \n\nPhysically, Mia is striking with shoulder-length dyed blue hair, a nose ring, and a penchant for eclectic fashion, often mixing thrifted pieces with contemporary styles. Her style is a reflection of her personality\u2014bold, creative, and unafraid to stand out in a crowd.", "attributes": {"occupation": "social media manager", "socioeconomic_status": "middle-class", "religion": "agnostic", "politics": "liberal", "sexual_orientation": "bisexual", "total_height": 65, "polarity": 0.10555555555555557, "subjectivity": 0.3171957671957672}}, "19_23": {"generated_text": "Amara is a 23-year-old female from Generation Z, living in an urban area. She works as a social media manager for a nonprofit organization focused on environmental issues, a role that allows her to blend her passion for activism with her digital skills. Amara comes from a middle-class background, having been raised in a supportive family that encouraged her education and career aspirations. She identifies as agnostic, feeling more connected to nature than to organized religion. Politically, she leans liberal, often advocating for progressive policies that promote social justice and environmental sustainability. Amara is openly bisexual, embracing her identity and supporting LGBTQ+ rights. \n\nIn terms of physical appearance, she has a distinctive style, often seen with vibrant colored hair and a wardrobe that mixes vintage finds with contemporary fashion. Standing at 5'5\", Amara has an athletic build, reflecting her active lifestyle that includes yoga and hiking. Her expressive hazel eyes and freckled complexion make her stand out, and she often accessorizes with statement earrings and thrifted jewelry, showcasing her unique personality.", "attributes": {"occupation": "social media manager", "socioeconomic_status": "middle-class", "religion": "agnostic", "politics": "liberal", "sexual_orientation": "bisexual", "total_height": 65, "polarity": 0.16822916666666668, "subjectivity": 0.36830357142857145}}, "19_24": {"generated_text": "Sophie is a 24-year-old Generation Z female living in a vibrant urban area. She works as a social media manager for a nonprofit organization focused on environmental issues, reflecting her passion for activism and sustainability. Raised in a middle-class family, Sophie has been able to pursue her education, earning a degree in communications from a local university. She identifies as agnostic, often exploring different spiritual perspectives but ultimately valuing personal experience over organized religion. Politically, she leans liberal, actively participating in movements advocating for climate change action and social justice. Sophie is bisexual, feeling that her romantic interests are fluid and not confined to traditional labels. In terms of physical appearance, she has an eclectic style, often sporting colorful hair and vintage clothing, standing at 5'6\". Her expressive tattoos tell stories of her beliefs and experiences, making her a distinctive presence in her community.", "attributes": {"occupation": "social media manager", "socioeconomic_status": "middle-class", "religion": "agnostic", "politics": "liberal", "sexual_orientation": "bisexual", "total_height": 66, "polarity": 0.09, "subjectivity": 0.34922619047619047}}}