{"20_0": {"generated_text": "Liam is a 10-year-old Generation Alpha male living in an urban area. He is part of a middle-class family, with his parents both working in tech-related fields. Liam is an avid learner and shows a keen interest in coding and robotics, often spending his free time creating games and exploring digital art. He attends a progressive school that emphasizes creativity and critical thinking, where he thrives in a diverse environment. \n\nRaised in a secular household, Liam's family celebrates various cultural traditions but does not adhere to any specific religion. Politically, his views lean towards liberalism, influenced by his parents' advocacy for social justice and environmental issues. At his young age, Liam identifies as heterosexual, though he is still exploring his identity and the concept of relationships.\n\nPhysically, Liam is of average height for his age, standing at 4'8\". He has a head of tousled dark hair and bright blue eyes that reflect his curiosity. His style is casual and comfortable, often seen in graphic tees featuring his favorite video games and a pair of well-worn sneakers.", "attributes": {"occupation": "student", "socioeconomic_status": "middle-class", "religion": "unaffiliated", "politics": "liberal", "sexual_orientation": "heterosexual", "total_height": 56, "polarity": 0.08015873015873015, "subjectivity": 0.4238662131519276}}, "20_1": {"generated_text": "Liam is a 10-year-old Generation Alpha male, living in a suburban area with his middle-class family. His parents are both educators, which has instilled in him a strong value for learning and curiosity about the world. Liam is tech-savvy, often seen with his tablet, where he enjoys coding and playing educational games. He is involved in various extracurricular activities, including soccer and a robotics club at school, showcasing his enthusiasm for teamwork and innovation.\n\nIn terms of religion, Liam's family is unaffiliated, allowing him to explore various beliefs and practices. Politically, he tends to lean liberal, influenced by discussions at home and the values of his progressive school environment. While still young, he identifies as heterosexual, though he is open-minded and accepting of diverse sexual orientations among his peers.\n\nPhysically, Liam is of average height for his age, around 4'8\", with curly brown hair and bright blue eyes. His casual style usually consists of comfortable t-shirts and jeans, embodying the relaxed and playful spirit of childhood. Overall, Liam represents the dynamic and diverse characteristics of Generation Alpha.", "attributes": {"occupation": "student", "socioeconomic_status": "middle-class", "religion": "unaffiliated", "politics": "liberal", "sexual_orientation": "heterosexual", "total_height": 56, "polarity": 0.09912280701754386, "subjectivity": 0.4022556390977443}}, "20_2": {"generated_text": "A Generation Alpha male, born in the early 2010s, is growing up in a rapidly evolving world shaped by technology and social change. He is likely to be in his teenage years, navigating the complexities of adolescence while being heavily influenced by digital culture. This individual may aspire to become a content creator or a tech entrepreneur, reflecting the interests of his generation in online platforms and innovation. His socioeconomic status could vary, but he often comes from a middle-class background where access to technology is prevalent.\n\nReligiously, he may identify as unaffiliated, reflecting a trend among younger generations moving away from traditional beliefs. Politically, he could lean towards liberal values, advocating for social justice and environmental issues, mirroring the activism seen in his peers. In terms of sexual orientation, he may identify as heterosexual, though fluidity in identity is increasingly common among his age group.\n\nPhysically, he is likely to have a modern style, favoring casual, comfortable clothing that reflects current trends. He might have a lean build, standing around 5'8\", with an approachable demeanor that resonates with his inclusive worldview.", "attributes": {"occupation": "content creator", "socioeconomic_status": "middle-class", "religion": "unaffiliated", "politics": "liberal", "sexual_orientation": "heterosexual", "total_height": 68, "polarity": 0.01333333333333333, "subjectivity": 0.4116666666666666}}, "20_3": {"generated_text": "In the heart of a bustling city, a Generation Alpha male named Ethan navigates a rapidly changing world. Born into the digital age, he is a tech-savvy 22-year-old who works as a software developer for a startup focused on artificial intelligence. His passion for technology and innovation has placed him in the upper-class bracket, where he enjoys a comfortable lifestyle, often indulging in the latest gadgets and experiences that the modern world offers. Raised in a secular household, Ethan identifies as unaffiliated with any particular religion, embracing a more spiritual approach to life.\n\nPolitically, he leans towards liberal ideologies, advocating for social justice and environmental sustainability, often participating in community initiatives and discussions. As a member of the LGBTQ+ community, Ethan identifies as bisexual, valuing love and connection over traditional labels. Physically, he has a lean build, standing at 5'10\", with an eclectic sense of style that blends streetwear with professional attire, reflecting his dynamic personality. His short, tousled hair and expressive green eyes give him a distinctive look that complements his confident demeanor.", "attributes": {"occupation": "software developer", "socioeconomic_status": "upper-class", "religion": "unaffiliated", "politics": "liberal", "sexual_orientation": "bisexual", "total_height": 70, "polarity": 0.14285714285714285, "subjectivity": 0.4012471655328798}}, "20_4": {"generated_text": "In a bustling urban environment, a Generation Alpha male, let's call him Leo, navigates the complexities of his world with a blend of creativity and pragmatism. At just 25, he is a digital marketing strategist for a tech startup, where he leverages his deep understanding of social media trends to help brands connect with younger audiences. Leo hails from a middle-class background, which has instilled in him a strong work ethic and an appreciation for education. He identifies as spiritual but is largely unaffiliated with organized religion, reflecting a growing trend among his peers.\n\nPolitically, Leo leans liberal, advocating for social justice and environmental sustainability, which resonates with his values and lifestyle. He is openly bisexual, embracing a fluid understanding of sexuality that reflects his generation's more inclusive attitudes. Physically, Leo stands at 5'10\" with a lean build, often sporting stylish, casual attire that combines comfort with a hint of individuality. His expressive blue-green eyes and tousled dark hair complete a look that is both approachable and confident, making him a relatable figure in his social circles. Leo embodies the characteristics of Generation Alpha, blending tradition with modernity in every facet of his life.", "attributes": {"occupation": "strategist", "socioeconomic_status": "middle-class", "religion": "unaffiliated", "politics": "liberal", "sexual_orientation": "bisexual", "total_height": 70, "polarity": 0.11352813852813853, "subjectivity": 0.35627705627705625}}, "20_5": {"generated_text": "Max is a 24-year-old Generation Alpha male who works as a digital content creator, specializing in short-form videos on social media platforms. He has managed to carve out a niche in the world of influencer marketing, collaborating with brands that align with his values. Growing up in a suburban neighborhood, he comes from a middle-class background and enjoys a comfortable lifestyle, though he is mindful of his spending. Max identifies as agnostic, often exploring various philosophies rather than adhering to a single religious doctrine. Politically, he leans liberal, advocating for social justice and environmental sustainability. In his personal life, Max is openly bisexual, embracing his identity and advocating for LGBTQ+ rights. Physically, he stands at 5'10\" with an athletic build, reflecting his active lifestyle. His style is a mix of casual and trendy, often featuring streetwear brands, and he has a distinct, colorful tattoo sleeve on his right arm that showcases his artistic side. With his friendly demeanor and approachable nature, Max is well-liked in both his online and offline communities.", "attributes": {"occupation": "digital content creator", "socioeconomic_status": "middle-class", "religion": "agnostic", "politics": "liberal", "sexual_orientation": "bisexual", "total_height": 70, "polarity": 0.09314058956916099, "subjectivity": 0.3877551020408163}}, "20_6": {"generated_text": "In the year 2035, a typical Generation Alpha male named Ethan is making waves in the digital marketing world. At just 22 years old, he has quickly ascended to a mid-level position at a tech-savvy startup, leveraging his deep understanding of social media and online trends to drive campaigns for various brands. Growing up in a middle-class family, Ethan's parents instilled in him the values of hard work and education, allowing him to thrive in a competitive environment. He identifies as unaffiliated in terms of religion, reflecting the broader trend of his generation towards spiritual exploration without strict adherence to traditional doctrines. Politically, Ethan leans liberal, advocating for social justice and environmental sustainability, issues that resonate with his peers. His sexual orientation is heterosexual, and he openly supports LGBTQ+ rights, emphasizing inclusivity in his personal and professional life. Physically, Ethan stands at 5'10\", with an athletic build, a result of his active lifestyle that includes regular gym sessions and outdoor adventures. His style is casual yet trendy, often seen in fitted jeans and graphic tees, complemented by stylish sneakers. This blend of attributes defines Ethan as a representative of the dynamic, evolving Generation Alpha.", "attributes": {"occupation": "digital marketer", "socioeconomic_status": "middle-class", "religion": "unaffiliated", "politics": "liberal", "sexual_orientation": "heterosexual", "total_height": 70, "polarity": 0.04433333333333333, "subjectivity": 0.38979120879120877}}, "20_7": {"generated_text": "In the vibrant world of Generation Alpha, a typical male stands out as a product of a rapidly evolving society. He is likely in his early twenties, navigating the complexities of adulthood with a blend of digital fluency and social awareness. This young man may work in a tech-related field, perhaps as a software developer or a digital marketing specialist, reflecting the growing importance of technology in everyday life. Economically, he may come from a middle-class background, benefiting from educational opportunities that his parents might not have had. \n\nCulturally diverse, he often embraces a secular worldview, identifying as unaffiliated with any particular religion, which is common among his peers. Politically, he leans liberal, advocating for social justice and environmental issues that resonate with his generation. His sexual orientation is often fluid, with many in Generation Alpha identifying as bisexual, reflecting a more open and accepting society. Physically, he embodies a casual style typical of his age, often sporting a fit build, standing around 5'10\", with a preference for comfortable yet trendy attire that showcases his individuality.", "attributes": {"occupation": "software developer", "socioeconomic_status": "middle-class", "religion": "unaffiliated", "politics": "liberal", "sexual_orientation": "bisexual", "total_height": 70, "polarity": 0.10059523809523808, "subjectivity": 0.41403061224489796}}, "20_8": {"generated_text": "In a bustling urban environment, a Generation Alpha male stands out with his unique blend of traits. Born in the early 2010s, he is now in his teenage years, navigating a world shaped by technology and social change. He dreams of becoming a software developer, driven by a passion for coding and gaming. His family belongs to the middle class, providing him with access to education and resources that nurture his aspirations. Raised in a secular household, he identifies as unaffiliated with any religion, valuing personal beliefs over organized doctrines.\n\nPolitically, he leans towards liberal views, advocating for climate action and social justice, influenced by the diverse, progressive community around him. In terms of his sexual orientation, he identifies as heterosexual, comfortable with his identity and open-minded about others. Physically, he has a lean build, standing at 5'8\", with curly dark hair and expressive brown eyes that reflect his curiosity and enthusiasm for life. His style is casual yet trendy, often sporting graphic tees and sneakers that mirror his interests in pop culture and gaming. This Generation Alpha male embodies the spirit of his generation, blending ambition, inclusivity, and a keen awareness of the world.", "attributes": {"occupation": "software developer", "socioeconomic_status": "middle-class", "religion": "unaffiliated", "politics": "liberal", "sexual_orientation": "heterosexual", "total_height": 68, "polarity": 0.14280303030303032, "subjectivity": 0.4102813852813854}}, "20_9": {"generated_text": "In the vibrant world of Generation Alpha, a typical male stands out as a product of a rapidly evolving society. He is likely in his early twenties, having grown up with technology at his fingertips, which shapes not only his social interactions but also his career choices. This young man may work in a creative field, such as digital marketing or software development, where innovation is key. His socioeconomic status could range from middle-class, as many of his peers are navigating the gig economy, seeking stability while embracing flexibility.\n\nReligiously, he may identify as unaffiliated, reflecting a broader trend of spirituality over traditional faith. Politically, he might lean liberal, advocating for social justice and climate action, driven by the pressing issues of his generation. In terms of sexual orientation, he could be bisexual, embodying the fluidity that characterizes contemporary views on gender and relationships.\n\nPhysically, he is likely to have a casual, athletic appearance, favoring comfortable yet stylish clothing that resonates with his values of self-expression and individuality.", "attributes": {"occupation": "digital marketer", "socioeconomic_status": "middle-class", "religion": "unaffiliated", "politics": "liberal", "sexual_orientation": "bisexual", "total_height": 70, "polarity": 0.1013888888888889, "subjectivity": 0.5263888888888889}}, "20_10": {"generated_text": "Oliver is a 12-year-old boy, a member of Generation Alpha, who is already showing signs of ambition and creativity. He dreams of becoming a video game designer, spending hours coding and creating his own games using various online platforms. His family is middle-class, providing him with a comfortable life, access to technology, and opportunities for extracurricular activities. Although his parents identify as Christian, Oliver himself is more interested in exploring diverse belief systems and often engages in discussions about philosophy and ethics with his friends. Politically, he leans liberal, advocating for climate action and social justice causes among his peers. As a young boy, Oliver is still figuring out his sexual orientation but leans towards being heterosexual, having a crush on a classmate. Physically, he is of average height for his age at 5'2\", with a lean build and expressive green eyes. His tousled brown hair and casual style\u2014usually a graphic tee and jeans\u2014reflect his laid-back personality, while his enthusiasm for technology and creativity shines through in everything he does.", "attributes": {"occupation": "student", "socioeconomic_status": "middle-class", "religion": "unaffiliated", "politics": "liberal", "sexual_orientation": "heterosexual", "total_height": 62, "polarity": 0.13796296296296295, "subjectivity": 0.5009259259259259}}, "20_11": {"generated_text": "In a bustling urban environment, a Generation Alpha male named Leo is carving out his identity. At just 24 years old, he works as a digital marketing specialist for a sustainable fashion brand, a role that allows him to blend his passion for technology with his commitment to environmental issues. Leo hails from a middle-class background, where discussions about social justice and climate change were common at the dinner table, shaping his worldview. He identifies as agnostic, feeling that spirituality is a personal journey rather than a prescribed set of beliefs. Politically, he leans liberal, advocating for policies that promote equality and environmental stewardship. Leo is openly bisexual, embracing love in all its forms, which has led him to foster diverse friendships and relationships. Physically, he stands at 6'1\", with an athletic build that reflects his love for outdoor activities. His style is a mix of casual and trendy, often featuring eco-friendly brands. With expressive green eyes and tousled dark hair, Leo embodies the modern young man of his generation, navigating life with a blend of optimism and a desire for positive change.", "attributes": {"occupation": "digital marketing specialist", "socioeconomic_status": "middle-class", "religion": "agnostic", "politics": "liberal", "sexual_orientation": "bisexual", "total_height": 73, "polarity": 0.09553030303030305, "subjectivity": 0.3910822510822511}}, "20_12": {"generated_text": "Lucas is a 12-year-old Generation Alpha male living in an urban area. He is a digital native, often found playing video games or engaging with interactive learning platforms that combine education with entertainment. Lucas dreams of becoming a software developer or a professional gamer, influenced by the tech-savvy world around him. His family is middle-class, providing him with access to technology and extracurricular activities, such as coding classes and esports tournaments. \n\nRaised in a secular household, Lucas identifies as unaffiliated with any religion, though he is curious about various beliefs and cultures. Politically, he leans liberal, advocating for environmental issues and social justice, influenced by the discussions around him at school and online. Lucas is still figuring out his sexual orientation but is open to all experiences, reflecting the fluidity of his generation's views on identity. \n\nPhysically, he is of average height for his age, with a slim build, dark hair, and expressive brown eyes that light up when he talks about his favorite games. Lucas represents the dynamic and diverse nature of Generation Alpha, blending technology, social awareness, and personal exploration.", "attributes": {"occupation": "student", "socioeconomic_status": "middle-class", "religion": "unaffiliated", "politics": "liberal", "sexual_orientation": "bisexual", "total_height": 64, "polarity": 0.13412698412698415, "subjectivity": 0.44206349206349205}}, "20_13": {"generated_text": "In a bustling urban environment, a Generation Alpha male named Noah is making his mark as a digital content creator. At just 22, he has already carved out a niche for himself on various social media platforms, focusing on gaming and lifestyle vlogs. Growing up in a world shaped by technology, he is adept at navigating the digital landscape and leveraging it for success. Noah comes from a middle-class background, with his family prioritizing education and creativity, which has instilled in him a strong work ethic and ambition.\n\nRaised in a secular household, he identifies as unaffiliated with any particular religion, valuing personal spirituality over organized beliefs. Politically, he leans liberal, advocating for social justice and environmental issues, often using his platform to raise awareness. Noah identifies as bisexual, embracing a fluid understanding of sexuality that resonates with his generation's progressive values. In terms of physical appearance, he is of average height at 5'10\", with a lean physique, often sporting a casual yet stylish wardrobe that reflects his creative personality.", "attributes": {"occupation": "digital content creator", "socioeconomic_status": "middle-class", "religion": "unaffiliated", "politics": "liberal", "sexual_orientation": "bisexual", "total_height": 70, "polarity": 0.10087719298245616, "subjectivity": 0.34786967418546366}}, "20_14": {"generated_text": "Ethan is a 12-year-old Generation Alpha male who embodies the characteristics of his generation. He is a digital native, spending much of his time exploring the latest technology and gaming trends. Ethan dreams of becoming a video game designer, showcasing his creative talents through online platforms and coding tutorials. His family belongs to the middle class, providing him with access to quality education and extracurricular activities. Although his family celebrates Christmas, Ethan identifies as unaffiliated, often questioning traditional beliefs while seeking his own understanding of the world. Politically, he leans liberal, influenced by his parents\u2019 discussions about social justice and environmental issues. Ethan is openly bisexual, navigating his early adolescence with a sense of curiosity and acceptance. Physically, he is average in height for his age, standing at 5'3\", with a lean build, tousled brown hair, and expressive hazel eyes that reflect his vibrant personality. His wardrobe consists of casual, comfortable clothes, often featuring graphic tees of his favorite video games or cartoons, allowing him to express his identity and interests.", "attributes": {"occupation": "student", "socioeconomic_status": "middle-class", "religion": "unaffiliated", "politics": "liberal", "sexual_orientation": "bisexual", "total_height": 63, "polarity": 0.1523809523809524, "subjectivity": 0.5222222222222223}}, "20_15": {"generated_text": "In a world defined by rapid technological advancements and shifting cultural norms, a Generation Alpha male stands out with a unique blend of characteristics. At just 22 years old, he works as a software developer in a fast-paced tech startup, showcasing a knack for coding and innovation. He hails from a middle-class background, his family emphasizing education and adaptability. Raised in a secular household, he identifies as unaffiliated with any religion, reflecting the growing trend of spiritual independence among younger generations.\n\nPolitically, he leans liberal, advocating for social justice, environmental sustainability, and inclusivity, often engaging in discussions about climate change and equality. He identifies as bisexual, comfortable with his sexuality and open about his experiences in a society that increasingly embraces diverse orientations. Physically, he has an athletic build, standing at 6'1\", with a penchant for casual yet stylish clothing that reflects both comfort and modern trends. His hair is styled in a contemporary manner, and he has expressive eyes that convey a sense of curiosity about the world.", "attributes": {"occupation": "software developer", "socioeconomic_status": "middle-class", "religion": "unaffiliated", "politics": "liberal", "sexual_orientation": "bisexual", "total_height": 73, "polarity": 0.15147058823529413, "subjectivity": 0.42212885154061625}}, "20_16": {"generated_text": "In the year 2035, a Generation Alpha male named Ethan is a 22-year-old software developer specializing in artificial intelligence. He thrives in a tech-centric economy, reflecting the upper-class socioeconomic status afforded by his skills in a rapidly evolving job market. Raised in a progressive household, Ethan identifies as agnostic, often engaging in discussions about spirituality without adhering to a specific religion. Politically, he leans liberal, advocating for climate action and social justice issues, which resonates with many of his peers. \n\nEthan is openly bisexual, embracing a fluid perspective on relationships that reflects the inclusivity of his generation. His physical appearance is characterized by a lean build, standing at 6'1\", with tousled dark hair and expressive green eyes. He often dresses in a casual yet stylish manner, favoring sustainable fashion brands that align with his values. Ethan's lifestyle is marked by a strong connection to technology and social media, where he actively participates in conversations about the future of society. His identity embodies the complexities and possibilities of Generation Alpha, navigating a world that is both challenging and filled with opportunities.", "attributes": {"occupation": "software developer", "socioeconomic_status": "upper-class", "religion": "agnostic", "politics": "liberal", "sexual_orientation": "bisexual", "total_height": 73, "polarity": 0.0963768115942029, "subjectivity": 0.47939958592132503}}, "20_17": {"generated_text": "In a vibrant urban setting, a Generation Alpha male named Leo is making waves in the tech industry as a software developer. At just 25 years old, he stands out not only for his coding skills but also for his innovative approach to problem-solving. Leo hails from a middle-class family, and through hard work and determination, he has secured a stable position that allows him to live comfortably. Raised in a household that encouraged open-mindedness, he identifies as unaffiliated when it comes to religion, valuing personal spirituality over organized beliefs.\n\nPolitically, Leo leans towards liberal values, advocating for social justice and environmental sustainability, which aligns with his generation\u2019s growing concern for global issues. In his personal life, he identifies as bisexual, enjoying the freedom to express his identity in a progressive society. Physically, Leo has an athletic build, standing at 6'1\", with tousled dark hair and striking green eyes that reflect his curiosity and enthusiasm for life. His casual yet stylish wardrobe mirrors the tech-savvy culture he thrives in, making him relatable to his peers while still showcasing his individuality.", "attributes": {"occupation": "software developer", "socioeconomic_status": "middle-class", "religion": "unaffiliated", "politics": "liberal", "sexual_orientation": "bisexual", "total_height": 73, "polarity": 0.0806998556998557, "subjectivity": 0.45481859410430836}}, "20_18": {"generated_text": "In the vibrant landscape of a rapidly changing world, a typical Generation Alpha male, aged around 10, is a digital native, effortlessly navigating technology and social media. He is often seen participating in various online platforms, showcasing his creativity through gaming or content creation. His family, likely middle-class, emphasizes education and innovation, providing him with opportunities to explore diverse interests. This young male is growing up in a secular society, often identifying as unaffiliated with any particular religion, though he is exposed to a myriad of beliefs through his interactions. Politically, he leans towards liberal ideologies, influenced by progressive movements and a global outlook on issues such as climate change and social justice. His sexual orientation is still in development, but he exhibits an open-mindedness towards all identities. Physically, he is typically around 4'5\", with an athletic build from engaging in outdoor activities and sports, and he often expresses himself through colorful fashion choices that reflect his unique personality.", "attributes": {"occupation": "student", "socioeconomic_status": "middle-class", "religion": "unaffiliated", "politics": "liberal", "sexual_orientation": "heterosexual", "total_height": 53, "polarity": 0.08208333333333333, "subjectivity": 0.3916666666666667}}, "20_19": {"generated_text": "Ethan is a 12-year-old Generation Alpha male, living in a suburban neighborhood with his parents and younger sister. With a keen interest in technology, he aspires to become a game developer and spends his free time coding and playing video games. His family belongs to the middle class, providing him with access to extracurricular activities such as robotics club and summer coding camps. Ethan identifies as agnostic, reflecting a growing trend among his peers towards religious neutrality. Politically, he leans liberal, often engaging in discussions about social issues with his friends. While still young, he is open-minded about his sexual orientation, identifying as bisexual. Physically, Ethan is tall for his age, standing at 5'8\", with a slim build. He has short, tousled brown hair and wears glasses, giving him a studious appearance. His casual style consists of graphic tees, hoodies, and sneakers, reflecting his comfort-driven personality.", "attributes": {"occupation": "student", "socioeconomic_status": "middle-class", "religion": "unaffiliated", "politics": "liberal", "sexual_orientation": "bisexual", "total_height": 68, "polarity": 0.05185185185185184, "subjectivity": 0.3644179894179895}}, "20_20": {"generated_text": "Meet Liam, a 12-year-old Generation Alpha male who embodies the unique characteristics of his generation. With a keen interest in technology and gaming, he aspires to become a game designer, using his creativity to develop immersive virtual worlds. Liam lives in a middle-class neighborhood with his family, enjoying a comfortable lifestyle that allows him to explore his passions. Although his family practices no particular religion, they celebrate various cultural holidays, fostering an open-minded approach to spirituality. Politically, Liam\u2019s views lean towards liberal ideals, influenced by the progressive discussions he encounters online and in school. He identifies as heterosexual, navigating the complexities of friendships and early crushes typical of his age group. \n\nPhysically, Liam stands at an average height for his age, around 5'2\", with a lean build that reflects his active lifestyle. He sports a casual style, often seen in graphic tees and sneakers, with a vibrant collection of colorful wristbands that showcase his interests and personality. His bright blue eyes and tousled brown hair give him a youthful appearance, while his confident demeanor hints at the potential of the generation he represents.", "attributes": {"occupation": "game designer", "socioeconomic_status": "middle-class", "religion": "unaffiliated", "politics": "liberal", "sexual_orientation": "heterosexual", "total_height": 62, "polarity": 0.09166666666666667, "subjectivity": 0.4917184265010353}}, "20_21": {"generated_text": "Max is a 24-year-old Generation Alpha male living in an urban setting. He works as a digital marketing specialist for a sustainable fashion brand, driven by his passion for both technology and environmental consciousness. Growing up in a middle-class family, he has been afforded a good education and opportunities that have led him to a stable, if not affluent, lifestyle. Max identifies as agnostic, having been raised in a family that valued open dialogue about spirituality rather than strict adherence to any one religion.\n\nPolitically, he leans towards liberal views, advocating for social justice and environmental reform. His sexual orientation is bisexual, which he embraces openly, believing in the importance of authenticity and acceptance in relationships. Physically, Max stands at 5'11\", with an athletic build that reflects his love for outdoor activities and fitness. He has tousled dark hair, expressive brown eyes, and often sports a casual yet stylish wardrobe that reflects his commitment to sustainable fashion.", "attributes": {"occupation": "digital marketing specialist", "socioeconomic_status": "middle-class", "religion": "agnostic", "politics": "liberal", "sexual_orientation": "bisexual", "total_height": 71, "polarity": 0.12864583333333335, "subjectivity": 0.4787202380952381}}, "20_22": {"generated_text": "In a bustling urban setting, a typical Generation Alpha male is a product of a rapidly evolving world. He is likely to be in his late teens or early twenties, navigating the complexities of a digital landscape. His occupation might involve technology, perhaps as a software developer or social media manager, reflecting a strong affinity for innovation and connectivity. Economically, he could be considered middle-class, benefiting from his parents' investments in education and technology, which have paved the way for his opportunities.\n\nReligiously, he might identify as unaffiliated, reflecting a trend among younger generations to explore spirituality outside traditional structures. Politically, he may lean liberal, advocating for social justice and environmental issues, influenced by a global consciousness fostered by the internet. In terms of sexual orientation, he could be bisexual, open to exploring relationships beyond traditional norms.\n\nPhysically, he presents a modern appearance, often sporting a casual yet stylish wardrobe that blends comfort with trends. He might stand around 5'10\", with an athletic build, showcasing a lifestyle that values both physical and mental well-being. His hair could be styled in a way that reflects current fashion, often dyed in unconventional colors, symbolizing his individuality.", "attributes": {"occupation": "software developer", "socioeconomic_status": "middle-class", "religion": "unaffiliated", "politics": "liberal", "sexual_orientation": "bisexual", "total_height": 70, "polarity": 0.0382716049382716, "subjectivity": 0.3908289241622574}}, "20_23": {"generated_text": "Jason is a 12-year-old Generation Alpha male who lives in an urban area with his single mother. He is passionate about technology and spends his free time learning programming and creating video games. His mother works as a nurse, which places their family in the middle-class socioeconomic bracket. Despite his young age, Jason is aware of social issues and often discusses them with his friends, reflecting a liberal mindset. He identifies as agnostic, as he has not yet found a religious belief system that resonates with him. In terms of his social life, Jason is still exploring his identity but leans towards identifying as heterosexual. Physically, he has a slender build, stands about 5'2\", with short, tousled brown hair and expressive green eyes that reflect his curiosity about the world around him.", "attributes": {"occupation": "student", "socioeconomic_status": "middle-class", "religion": "agnostic", "politics": "liberal", "sexual_orientation": "heterosexual", "total_height": 62, "polarity": 0.0925170068027211, "subjectivity": 0.3386054421768708}}, "20_24": {"generated_text": "In the bustling urban landscape of a near-future city, a Generation Alpha male stands out with a unique blend of modern sensibilities and traditional values. At just 25, he has carved out a niche as a digital content creator, producing engaging videos that blend entertainment with education, focusing on sustainability and social issues. His socioeconomic status is middle-class, reflecting a comfortable lifestyle supported by his growing online presence. Raised in a diverse community, he identifies as unaffiliated with any religion, embracing a secular worldview that values inclusivity and open-mindedness.\n\nPolitically, he leans liberal, advocating for climate action and social justice, using his platform to amplify underrepresented voices. His sexual orientation is bisexual, which he expresses openly, promoting acceptance and love in all forms. Physically, he has an athletic build, standing at 6'1\", with a stylish appearance that often includes eco-friendly fashion choices. His hair is a vibrant shade of blue, a nod to his creative personality, while his expressive tattoos tell stories of his experiences and beliefs. This Generation Alpha male represents a new wave of thinkers and doers, determined to make a positive impact on the world.", "attributes": {"occupation": "digital content creator", "socioeconomic_status": "middle-class", "religion": "unaffiliated", "politics": "liberal", "sexual_orientation": "bisexual", "total_height": 73, "polarity": 0.20299873737373741, "subjectivity": 0.44136904761904766}}}