{"18_0": {"generated_text": "Jordan is a 23-year-old male belonging to Generation Z. He works as a freelance graphic designer, a field that allows him to express his creativity while enjoying the flexibility of remote work. Living in a bustling city, he navigates the challenges of a middle-class lifestyle, balancing student loan payments with his passion for art and design. Jordan identifies as agnostic, feeling disconnected from traditional religious practices, but he embraces a sense of spirituality that resonates with him personally. Politically, he leans liberal, advocating for social justice and climate action, which he often discusses on social media platforms. He is openly bisexual, feeling comfortable in his identity and actively supporting LGBTQ+ rights. Physically, Jordan has an athletic build, standing at 6'1\" with short, tousled dark hair and striking green eyes. His fashion sense is contemporary and relaxed, often seen in oversized hoodies and trendy sneakers that reflect his artistic personality. He enjoys connecting with friends over coffee and engaging in community events that promote inclusivity and creativity.", "attributes": {"occupation": "graphic designer", "socioeconomic_status": "middle-class", "religion": "agnostic", "politics": "liberal", "sexual_orientation": "bisexual", "total_height": 73, "polarity": 0.13030303030303034, "subjectivity": 0.41331168831168835}}, "18_1": {"generated_text": "James is a 22-year-old Generation Z male living in a bustling urban area. He works as a social media manager for a startup focused on eco-friendly products, reflecting his passion for sustainability and innovation. Coming from a middle-class background, James has navigated the challenges of student debt after graduating from college with a degree in communications. He identifies as agnostic, feeling more aligned with personal spirituality than organized religion. Politically, James leans liberal, actively participating in local campaigns and advocating for social justice issues that resonate with his generation. In terms of sexual orientation, he identifies as bisexual, comfortable exploring his identity in a society that increasingly embraces diversity. Physically, James has a casual yet stylish appearance, standing at 5'10\" with an athletic build. He sports a trendy haircut, often dyed in various colors, and favors streetwear brands that reflect his artistic personality. His accessories include piercings and a collection of bracelets, showcasing his individuality. With a confident demeanor and a warm smile, James is not only a digital native but also a compassionate advocate for the causes he believes in.", "attributes": {"occupation": "social media manager", "socioeconomic_status": "middle-class", "religion": "agnostic", "politics": "liberal", "sexual_orientation": "bisexual", "total_height": 70, "polarity": 0.16666666666666669, "subjectivity": 0.46861471861471865}}, "18_2": {"generated_text": "Ethan is a 23-year-old male from Generation Z who works as a social media manager for a tech startup in a bustling urban area. He grew up in a middle-class family, and his parents encouraged him to pursue his passions in the digital world. Raised in a secular household, he identifies as unaffiliated with any religion, often exploring spiritual concepts on his own terms. Politically, Ethan leans liberal, advocating for social justice and environmental sustainability, values that are important to him and his peers. He identifies as bisexual, feeling comfortable expressing his identity in a community that is increasingly accepting and diverse.\n\nPhysically, Ethan has an athletic build, standing at 5'10\". He has short, tousled dark hair and striking green eyes that reflect his vibrant personality. His style is casual yet trendy, often seen in oversized graphic tees, skinny jeans, and colorful sneakers, which showcase his love for self-expression. Ethan is an active participant in various online communities, where he shares his thoughts on current events and connects with like-minded individuals.", "attributes": {"occupation": "social media manager", "socioeconomic_status": "middle-class", "religion": "unaffiliated", "politics": "liberal", "sexual_orientation": "bisexual", "total_height": 70, "polarity": 0.10625000000000001, "subjectivity": 0.43373015873015874}}, "18_3": {"generated_text": "Ethan is a 22-year-old male from Generation Z, working as a graphic designer at a tech startup in a bustling city. He enjoys the creative freedom of his job, which allows him to express himself through vibrant designs and innovative projects. Ethan grew up in a middle-class family, and while he is financially independent, he still shares an apartment with roommates to save on living expenses. He identifies as agnostic, often exploring various spiritual beliefs but not aligning strictly with any organized religion. Politically, Ethan leans liberal, actively participating in social justice movements and advocating for environmental sustainability. He is openly bisexual and embraces the fluidity of his identity, often using social media platforms to connect with the LGBTQ+ community. Physically, Ethan has an athletic build, standing at 5'10\", with tousled dark hair and expressive hazel eyes. He often sports a casual style, favoring graphic tees and comfortable sneakers, with a few tattoos that reflect his love for art and individuality.", "attributes": {"occupation": "graphic designer", "socioeconomic_status": "middle-class", "religion": "agnostic", "politics": "liberal", "sexual_orientation": "bisexual", "total_height": 70, "polarity": 0.09285714285714286, "subjectivity": 0.4397392290249433}}, "18_4": {"generated_text": "Ethan is a 24-year-old male belonging to Generation Z, currently working as a freelance graphic designer in a bustling urban environment. He lives in a modest apartment shared with two roommates, reflecting his middle-class socioeconomic status. Raised in a diverse neighborhood, Ethan's family practices a blend of spiritual beliefs, but he identifies as unaffiliated with any particular religion. Politically, he leans liberal, advocating for social justice and environmental issues, which are important to him and many of his peers. Ethan is openly bisexual, navigating the complexities of modern dating with a sense of humor and optimism.\n\nPhysically, he has an athletic build, standing at 5'10\" with a light tan complexion. His style is expressive; he often sports a mix of streetwear and vintage clothing, complemented by colorful sneakers. Ethan has short, wavy hair dyed a deep blue, and he is often seen wearing glasses that add to his creative persona. His appearance reflects his artistic nature and his desire to stand out while remaining true to himself.", "attributes": {"occupation": "graphic designer", "socioeconomic_status": "middle-class", "religion": "unaffiliated", "politics": "liberal", "sexual_orientation": "bisexual", "total_height": 70, "polarity": 0.17753623188405795, "subjectivity": 0.453312629399586}}, "18_5": {"generated_text": "Jordan is a 24-year-old male who embodies the spirit of Generation Z. He works as a freelance graphic designer, leveraging his creativity and digital skills to build a portfolio that resonates with modern aesthetics. Despite his talent, he faces financial challenges, placing him firmly in the lower-class socioeconomic bracket. Raised in a secular household, he identifies as unaffiliated with any religion, valuing personal beliefs over traditional doctrines. Politically, Jordan leans liberal, advocating for social justice and environmental sustainability, often engaging in online activism to amplify his voice. His sexual orientation is bisexual, and he embraces this aspect of his identity with pride. \n\nPhysically, Jordan has an athletic build, standing at 5'10\". He sports a trendy hairstyle, often dyed in vibrant colors that reflect his artistic personality. His fashion sense is a blend of streetwear and vintage pieces, showcasing his unique style. With a penchant for tattoos, he has a few meaningful designs inked on his arms, each telling a story about his journey. Jordan's presence is characterized by an open smile and an approachable demeanor, making him a relatable figure among his peers.", "attributes": {"occupation": "freelance graphic designer", "socioeconomic_status": "lower-class", "religion": "unaffiliated", "politics": "liberal", "sexual_orientation": "bisexual", "total_height": 70, "polarity": 0.14325396825396824, "subjectivity": 0.4060090702947846}}, "18_6": {"generated_text": "Ethan is a 22-year-old male who embodies the essence of Generation Z. He works as a digital marketing specialist for a start-up, a role that allows him to flex his creative muscles while utilizing his tech-savvy skills. Growing up in a middle-class household, he is now navigating the financial challenges of living in an urban area, often sharing a small apartment with friends to keep costs down. Ethan identifies as agnostic, reflecting a more secular approach to spirituality common among his peers. Politically, he leans liberal, actively engaging in discussions about social justice and environmental issues, which he shares on his social media platforms. His sexual orientation is bisexual, and he is open about his experiences, often advocating for LGBTQ+ rights. Physically, Ethan has an athletic build, standing at 5'10\" with an edgy style characterized by graphic tees, distressed jeans, and a collection of vintage sneakers. His short, dyed hair and a few piercings add to his distinctive look, making him feel confident and authentic in expressing his individuality.", "attributes": {"occupation": "digital marketing specialist", "socioeconomic_status": "middle-class", "religion": "agnostic", "politics": "liberal", "sexual_orientation": "bisexual", "total_height": 70, "polarity": 0.08005050505050505, "subjectivity": 0.37871572871572873}}, "18_7": {"generated_text": "Jason is a 23-year-old male who embodies the values and trends of Generation Z. He works as a digital marketing specialist for a startup, utilizing his skills in social media and content creation to help brands connect with younger audiences. Coming from a middle-class background, Jason is financially independent but still shares a small apartment with friends to save on expenses. Raised in a secular household, he identifies as unaffiliated with any particular religion, valuing personal spirituality over organized beliefs. Politically, Jason leans liberal, advocating for social justice and climate action, often participating in community activism. His sexual orientation is bisexual, and he is open about his relationships, which have included both men and women. Physically, Jason has a lean build, standing at 5'10\". He sports a trendy haircut with dyed blue highlights and often dresses in casual streetwear, favoring brands that promote sustainability and ethical practices.", "attributes": {"occupation": "digital marketing specialist", "socioeconomic_status": "middle-class", "religion": "unaffiliated", "politics": "liberal", "sexual_orientation": "bisexual", "total_height": 70, "polarity": 0.04907407407407406, "subjectivity": 0.307473544973545}}, "18_8": {"generated_text": "Ethan is a 24-year-old male from a suburban area, working as a digital marketing specialist for a tech startup. He graduated from a state university with a degree in communications, and while he started with an internship, his current job allows him to live comfortably but still within a middle-class budget. Raised in a secular household, he identifies as unaffiliated with any religion, valuing personal beliefs over organized doctrines. Politically, Ethan leans liberal, often engaging in discussions about social justice and environmental issues, and he actively participates in local activism. He identifies as bisexual, which informs his open-minded views on relationships and identity. Physically, Ethan has an athletic build, standing at 6'0\", with dark brown hair and expressive hazel eyes. He often sports casual yet stylish clothing, reflecting his laid-back yet trendy personality. His appearance is complemented by a few tattoos that represent significant aspects of his life, embodying his belief in self-expression.", "attributes": {"occupation": "digital marketing specialist", "socioeconomic_status": "middle-class", "religion": "unaffiliated", "politics": "liberal", "sexual_orientation": "bisexual", "total_height": 72, "polarity": 0.12673160173160172, "subjectivity": 0.45481859410430847}}, "18_9": {"generated_text": "Jake is a 23-year-old male who exemplifies the characteristics of Generation Z. He works as a freelance graphic designer, navigating the gig economy while pursuing his passion for digital art. Coming from a middle-class background, Jake has a moderate income but values experiences over material possessions, often prioritizing travel and social outings with friends. He identifies as agnostic, reflecting a common trend among his peers who tend to be more open-minded about religion. Politically, Jake leans liberal, advocating for social justice, climate change action, and inclusive policies. In terms of sexual orientation, he identifies as bisexual, which he openly discusses with his friends and online communities. Physically, Jake has an athletic build, standing at 6'1\" with tousled dark brown hair and expressive green eyes. He often sports casual clothing, favoring vintage band tees and well-worn jeans, which reflect both his artistic flair and comfort. His style is complemented by a collection of unique accessories, often sourced from thrift shops, showcasing his individuality and commitment to sustainable fashion.", "attributes": {"occupation": "freelance graphic designer", "socioeconomic_status": "middle-class", "religion": "agnostic", "politics": "liberal", "sexual_orientation": "bisexual", "total_height": 73, "polarity": 0.09625, "subjectivity": 0.46380952380952384}}, "18_10": {"generated_text": "Ethan is a 24-year-old male from Generation Z, currently working as a digital marketing specialist for a tech startup in an urban area. He has recently graduated from college with a degree in communications, and his entry-level position reflects his middle-class background. Raised in a secular household, Ethan identifies as unaffiliated with any particular religion, although he respects diverse beliefs. Politically, he leans liberal, often advocating for social justice and environmental issues, reflecting the values of his generation. Ethan identifies as heterosexual and is currently in a committed relationship. \n\nIn terms of physical appearance, he has a lean build, standing at 6'1\", with tousled dark brown hair and expressive green eyes. He often dresses in casual, trendy clothing, favoring graphic tees and fitted jeans, reflecting both his creative profession and the laid-back style of his peers. His overall demeanor is approachable and friendly, often engaging in conversations about current events and pop culture.", "attributes": {"occupation": "digital marketing specialist", "socioeconomic_status": "middle-class", "religion": "unaffiliated", "politics": "liberal", "sexual_orientation": "heterosexual", "total_height": 73, "polarity": 0.09642857142857142, "subjectivity": 0.3933106575963719}}, "18_11": {"generated_text": "Ethan is a 24-year-old male belonging to Generation Z. He works as a social media manager for a small startup, where he utilizes his skills in digital marketing and content creation to engage a younger audience. Coming from a middle-class background, he balances his career ambitions with the economic realities faced by many of his peers. Raised in a non-religious household, Ethan identifies as unaffiliated, feeling comfortable with a secular worldview. Politically, he leans liberal, advocating for social justice and climate change initiatives, aligning with the progressive values prominent among his generation. Ethan is openly bisexual, embracing a fluid approach to his identity and relationships. Physically, he has an athletic build, standing at 6'1\", with short, tousled dark hair and striking green eyes. His style reflects a blend of casual and trendy, often seen in graphic tees, fitted jeans, and sneakers, embodying the laid-back yet fashionable essence of his generation.", "attributes": {"occupation": "social media manager", "socioeconomic_status": "middle-class", "religion": "unaffiliated", "politics": "liberal", "sexual_orientation": "bisexual", "total_height": 73, "polarity": 0.07936507936507936, "subjectivity": 0.38775510204081637}}, "18_12": {"generated_text": "Ethan is a 23-year-old male who embodies the essence of Generation Z. He works as a social media manager for a small marketing firm, a job that allows him to express his creativity while navigating the digital landscape that defines his generation. Growing up in a middle-class household, Ethan has always been encouraged to pursue his passions, but financial stability remains a concern in his competitive field. He identifies as agnostic, reflecting a broader trend among his peers who often prioritize personal spirituality over organized religion. Politically, Ethan leans liberal, advocating for social justice and climate action, values that resonate deeply with his generation's ethos. He is openly bisexual, feeling that love knows no boundaries, and he actively supports LGBTQ+ rights. Physically, Ethan stands at 5'10\", with an athletic build, a mop of tousled dark hair, and a penchant for colorful streetwear that showcases his unique style. His expressive tattoos, which tell stories of his life experiences, add to his vibrant appearance, making him a recognizable figure in his community.", "attributes": {"occupation": "social media manager", "socioeconomic_status": "middle-class", "religion": "agnostic", "politics": "liberal", "sexual_orientation": "bisexual", "total_height": 70, "polarity": 0.08690476190476192, "subjectivity": 0.34092970521541954}}, "18_13": {"generated_text": "Ethan is a 24-year-old male representative of Generation Z, currently working as a social media manager for a small startup. He is passionate about digital marketing and enjoys creating engaging content that resonates with his audience. Coming from a middle-class background, he values hard work and is determined to climb the corporate ladder while maintaining a healthy work-life balance. Ethnically diverse, Ethan identifies as a non-religious individual, often describing himself as spiritual but not affiliated with any particular faith. Politically, he leans liberal, advocating for social justice and environmental issues, and often participates in local activism. Ethan is openly bisexual, embracing his identity and fostering a supportive community among his friends. Physically, he stands at 5'10\", with an athletic build, short curly hair, and a penchant for unique fashion choices that express his creativity and individuality. His style often includes thrifted items and bold accessories, reflecting both his eco-conscious mindset and love for self-expression.", "attributes": {"occupation": "social media manager", "socioeconomic_status": "middle-class", "religion": "unaffiliated", "politics": "liberal", "sexual_orientation": "bisexual", "total_height": 70, "polarity": 0.09782608695652174, "subjectivity": 0.38266045548654243}}, "18_14": {"generated_text": "At 24, Jake is a typical Generation Z male who embodies the diverse values and challenges of his generation. He works as a social media manager for a local non-profit organization, leveraging his skills in digital marketing to promote causes he believes in. Coming from a middle-class background, he balances his passion for social justice with the practical need to support himself. Raised in a secular household, Jake identifies as unaffiliated with any religion, but he respects various belief systems and often engages in conversations about spirituality. Politically, he leans liberal, advocating for climate action and racial equality, which are pivotal issues for him and his peers. Jake identifies as bisexual, feeling comfortable with his identity and open about it among friends. Physically, he has a distinctive look, characterized by his vibrant blue hair and an eclectic style that blends thrifted vintage pieces with contemporary streetwear. His piercings and tattoos tell stories of his interests and experiences, making him stand out in any crowd.", "attributes": {"occupation": "social media manager", "socioeconomic_status": "middle-class", "religion": "unaffiliated", "politics": "liberal", "sexual_orientation": "bisexual", "total_height": 70, "polarity": 0.07708333333333334, "subjectivity": 0.26726190476190476}}, "18_15": {"generated_text": "Ethan is a 22-year-old Generation Z male who works as a freelance graphic designer. He has a passion for digital art and uses his creativity to create visually appealing content for various clients. Living in a small apartment in a vibrant urban area, he comes from a middle-class background but often finds himself struggling with the high cost of living. Raised in a secular household, he identifies as unaffiliated with any religion, though he respects diverse beliefs. Politically, Ethan leans liberal, advocating for social justice and environmental issues, often participating in local activism. He identifies as bisexual, feeling comfortable expressing his identity within his friend circle and online community. Physically, Ethan has an athletic build, standing at 5'10\", with shoulder-length dark hair and a penchant for colorful streetwear that reflects his artistic personality. His expressive tattoos tell stories of his experiences and passions, making him stand out in a crowd.", "attributes": {"occupation": "freelance graphic designer", "socioeconomic_status": "middle-class", "religion": "unaffiliated", "politics": "liberal", "sexual_orientation": "bisexual", "total_height": 70, "polarity": 0.12740740740740739, "subjectivity": 0.3712698412698413}}, "18_16": {"generated_text": "Max is a 23-year-old Generation Z male navigating the complexities of modern life. He works as a freelance graphic designer, a career that allows him to express his creativity while also providing flexibility in his schedule. Coming from a middle-class background, he values experiences over material possessions and often prioritizes sustainability in his work and lifestyle. Max identifies as agnostic, leaning towards spiritual exploration rather than traditional religious practices. Politically, he aligns with liberal ideals, advocating for social justice and environmental issues, which he often incorporates into his art. In terms of relationships, Max is openly bisexual and embraces a fluid understanding of sexuality, often discussing these topics in his online communities. Physically, he stands at 5'10\", with an athletic build, short curly hair, and a penchant for casual, trendy clothing that reflects his artistic personality.", "attributes": {"occupation": "graphic designer", "socioeconomic_status": "middle-class", "religion": "agnostic", "politics": "liberal", "sexual_orientation": "bisexual", "total_height": 70, "polarity": 0.04444444444444443, "subjectivity": 0.39396825396825397}}, "18_17": {"generated_text": "Ethan, a 24-year-old male, embodies the spirit of Generation Z. He works as a social media manager for a small but thriving tech startup in a bustling city. Raised in a middle-class family, he values diversity and inclusion, which reflects in both his personal life and professional endeavors. Ethan identifies as agnostic, feeling disconnected from organized religion but open to exploring spirituality. Politically, he leans liberal, often advocating for climate change initiatives and social justice causes. In his personal life, Ethan is openly bisexual, feeling comfortable expressing his identity within his friend group and online communities. \n\nPhysically, he has an athletic build, standing at 6'1\", with short, tousled dark hair and a distinct sense of style that blends streetwear with vintage pieces. His tattoos, showcasing various symbols of personal significance, add to his unique appearance. Ethan often sports a warm smile and has a laid-back demeanor, making him approachable and relatable to his peers.", "attributes": {"occupation": "social media manager", "socioeconomic_status": "middle-class", "religion": "agnostic", "politics": "liberal", "sexual_orientation": "bisexual", "total_height": 73, "polarity": 0.08708333333333333, "subjectivity": 0.34380952380952373}}, "18_18": {"generated_text": "Lucas is a 24-year-old male from a suburban area who embodies the traits of Generation Z. He works as a digital marketing specialist for a tech startup, leveraging his creativity and understanding of social media trends to engage a younger audience. Raised in a middle-class family, he values financial independence and sustainability, often advocating for eco-friendly practices in his workplace. While he identifies as agnostic, he respects the diverse beliefs of his peers and often engages in discussions about spirituality and ethics. Politically, Lucas leans liberal, championing issues like climate change, social justice, and inclusivity. He is openly bisexual, embracing his identity in a society that increasingly values acceptance. Physically, Lucas has a lean build, standing at 5'10\". He sports a casual style with an affinity for vintage clothing, often seen in oversized hoodies and distressed jeans. His hair is dyed a vibrant blue, reflecting his creative personality, and he has a small tattoo of a mountain on his forearm, symbolizing his love for nature and adventure.", "attributes": {"occupation": "digital marketing specialist", "socioeconomic_status": "middle-class", "religion": "agnostic", "politics": "liberal", "sexual_orientation": "bisexual", "total_height": 70, "polarity": 0.030208333333333323, "subjectivity": 0.26726190476190476}}, "18_19": {"generated_text": "Jordan is a 24-year-old male living in a vibrant urban area. He works as a social media manager for a startup focused on sustainable fashion, leveraging his skills in digital marketing to connect with like-minded individuals. Growing up in a middle-class family, he has a modest yet comfortable lifestyle, often sharing affordable yet stylish clothing finds with his followers. Jordan identifies as agnostic, feeling that spirituality is a personal journey rather than a structured belief system. Politically, he aligns with liberal values, advocating for social justice and environmental issues, which he actively promotes through his online presence. He is openly bisexual, embracing his identity and supporting the LGBTQ+ community. Physically, Jordan has an athletic build, standing at 5'10\". He has short, tousled dark hair and often sports a well-groomed beard. His style is casual yet trendy, favoring thrifted vintage tees paired with high-waisted jeans and colorful sneakers. His unique sense of fashion reflects his commitment to sustainability and individual expression.", "attributes": {"occupation": "social media manager", "socioeconomic_status": "middle-class", "religion": "agnostic", "politics": "liberal", "sexual_orientation": "bisexual", "total_height": 70, "polarity": 0.08977272727272728, "subjectivity": 0.4284632034632035}}, "18_20": {"generated_text": "Jake is a 24-year-old male who embodies the spirit of Generation Z. He works as a social media manager for a small tech startup, helping to shape the online presence of emerging brands. Raised in a middle-class household, Jake has always had access to education and technology, which fuels his passion for digital marketing. He identifies as agnostic, often questioning traditional religious beliefs while valuing spiritual exploration. Politically, Jake leans liberal, actively engaging in discussions about climate change and social justice, and he participated in recent protests advocating for equality. His sexual orientation is bisexual, reflecting his open-minded approach to love and relationships. Physically, Jake has a lean build, standing at 5'11\", with shaggy brown hair and a penchant for vintage clothing. He often sports graphic tees paired with skinny jeans and chunky sneakers, showcasing his unique sense of style that blends retro and modern influences. With his vibrant personality and commitment to his values, Jake represents a generation that is both aware and proactive in shaping the future.", "attributes": {"occupation": "social media manager", "socioeconomic_status": "middle-class", "religion": "agnostic", "politics": "liberal", "sexual_orientation": "bisexual", "total_height": 71, "polarity": 0.12420634920634921, "subjectivity": 0.3571995464852608}}, "18_21": {"generated_text": "At 24 years old, Alex is a Gen Z male navigating the complexities of adulthood in a rapidly changing world. He works as a digital marketing specialist for a startup focused on sustainable products, reflecting his commitment to environmental issues. Coming from a middle-class background, he values the opportunities his education has afforded him but is also keenly aware of the financial struggles many face in today's economy. Raised in a secular household, Alex identifies as unaffiliated with any religion, which has shaped his open-minded perspective on life. Politically, he leans liberal, advocating for social justice and climate action, often participating in local activism. Alex identifies as bisexual, embracing a fluid approach to his sexuality and relationships. Physically, he stands at 5'10\", with a lean build and a casual sense of style that includes graphic tees, jeans, and sneakers. His short, tousled hair is often dyed in vibrant colors, reflecting his creative personality and desire for self-expression.", "attributes": {"occupation": "digital marketing specialist", "socioeconomic_status": "middle-class", "religion": "unaffiliated", "politics": "liberal", "sexual_orientation": "bisexual", "total_height": 70, "polarity": 0.08611111111111111, "subjectivity": 0.2866402116402116}}, "18_22": {"generated_text": "At 24 years old, Jamal is a Generation Z male navigating the complexities of modern life in a bustling urban environment. He works as a digital marketing specialist for a non-profit organization focused on climate change advocacy. Jamal\u2019s passion for sustainability aligns with his middle-class background, where his parents instilled the value of social responsibility. He identifies as agnostic, reflecting a trend among his peers who often seek personal spirituality rather than organized religion. Politically, Jamal leans liberal, actively participating in grassroots campaigns and advocating for progressive policies. He is openly bisexual, embracing his identity in a culture that increasingly values inclusivity. Physically, Jamal stands at 5'11\" with an athletic build, sporting a trendy hairstyle and often dressing in casual, eco-friendly brands that resonate with his values. His appearance is complemented by a collection of tattoos that reflect his love for art and personal expression, making him a relatable figure among his friends and social circles.", "attributes": {"occupation": "digital marketing specialist", "socioeconomic_status": "middle-class", "religion": "agnostic", "politics": "liberal", "sexual_orientation": "bisexual", "total_height": 71, "polarity": 0.05208333333333333, "subjectivity": 0.31517857142857136}}, "18_23": {"generated_text": "Ethan is a 24-year-old male from Generation Z, living in a bustling urban area. He works as a social media manager for a trendy startup focused on sustainable fashion. With a middle-class background, he has always been passionate about environmental issues and social justice. Raised in a secular household, Ethan identifies as unaffiliated with any religion but respects diverse beliefs. Politically, he leans liberal, advocating for progressive policies and actively participating in community activism. His sexual orientation is bisexual, and he embraces his identity openly, often sharing his experiences on social media to foster inclusivity. \n\nPhysically, Ethan has an athletic build, standing at 5'10\". He sports a stylish, tousled haircut and prefers a casual yet trendy wardrobe, often wearing vintage tees paired with high-waisted jeans and sneakers. His expressive eyes and warm smile reflect his approachable personality, making him a favorite among friends and colleagues.", "attributes": {"occupation": "social media manager", "socioeconomic_status": "middle-class", "religion": "unaffiliated", "politics": "liberal", "sexual_orientation": "bisexual", "total_height": 70, "polarity": 0.20087719298245615, "subjectivity": 0.5101503759398497}}, "18_24": {"generated_text": "In a bustling city, 23-year-old Jason embodies the essence of Generation Z. He works as a social media manager for a sustainable fashion brand, leveraging his creativity and digital savvy to promote eco-friendly clothing. Raised in a middle-class family, he has always been driven by a strong sense of social responsibility. Although not deeply religious, he identifies as unaffiliated, valuing spirituality in a personal way rather than through organized religion. Politically, Jason leans liberal, advocating for climate action and social justice issues, often participating in local activism and online campaigns.\n\nJason is openly bisexual, expressing pride in his identity and actively supporting LGBTQ+ rights. With his striking appearance, he stands at 5'10\", sporting a lean build that reflects his active lifestyle. He has tousled dark hair, which he often dyes in vibrant colors, and a keen sense of style that blends thrifted pieces with trendy items. His expressive hazel eyes and a warm smile make him approachable, while his tattoos tell stories of his passions and beliefs.", "attributes": {"occupation": "social media manager", "socioeconomic_status": "middle-class", "religion": "unaffiliated", "politics": "liberal", "sexual_orientation": "bisexual", "total_height": 70, "polarity": 0.17833333333333334, "subjectivity": 0.3683333333333333}}}