{"15_0": {"generated_text": "Jessica is a 45-year-old woman who embodies the spirit of Generation X. With her shoulder-length, tousled dark brown hair and a penchant for vintage clothing, she exudes a laid-back yet stylish vibe. She works as a graphic designer at a mid-sized marketing firm, where her creative skills and sharp eye for detail shine. Despite her talents, she has faced job insecurity in a rapidly changing industry, leading to a middle-class lifestyle that is often stretched thin. \n\nJessica identifies as agnostic, having moved away from the strict religious upbringing of her youth. Politically, she leans liberal, actively advocating for social justice and environmental issues. Her views are shaped by her experiences and the challenges faced by her generation. In her personal life, Jessica is openly bisexual and enjoys exploring connections with diverse individuals. She has a passion for art and music, often attending local shows and galleries in her free time. Her physical appearance is complemented by a few tasteful tattoos, each telling a story of her journey through life.", "attributes": {"occupation": "graphic designer", "socioeconomic_status": "middle-class", "religion": "agnostic", "politics": "liberal", "sexual_orientation": "bisexual", "total_height": 66, "polarity": 0.009722222222222219, "subjectivity": 0.4255291005291004}}, "15_1": {"generated_text": "Jessica is a 45-year-old Generation X female living in a suburban area. She works as a marketing manager for a mid-sized tech company, navigating the challenges of a rapidly evolving digital landscape. With a stable income, she falls into the middle-class socioeconomic bracket, affording her a comfortable lifestyle but still mindful of financial planning for her children's future. Raised in a Christian household, she identifies as a moderate believer but often questions traditional doctrines, leading her to a more personal spirituality. Politically, Jessica leans liberal, actively supporting environmental issues and social justice initiatives, reflecting her values in her community involvement. She identifies as heterosexual and is a devoted partner to her husband, with whom she shares two children. \n\nPhysically, Jessica has a casual yet polished appearance. Standing at 5'6\", she maintains a healthy weight and often opts for comfortable, stylish clothing that fits her busy lifestyle. Her brown hair, typically worn in a practical bob, frames her face, and her warm hazel eyes reflect her approachable personality. Jessica's style is a mix of practicality and subtle trends, showcasing her ability to balance work and family life while staying true to her individuality.", "attributes": {"occupation": "marketing manager", "socioeconomic_status": "middle-class", "religion": "christian", "politics": "liberal", "sexual_orientation": "heterosexual", "total_height": 66, "polarity": 0.10972222222222222, "subjectivity": 0.40074404761904764}}, "15_2": {"generated_text": "Sarah is a 45-year-old Generation X female who works as a project manager in a tech startup. With a master's degree and over 20 years of experience, she has climbed the corporate ladder, earning a comfortable middle-class income. Sarah identifies as unaffiliated with any religion, having grown up in a Christian household but now embraces a more secular worldview. Politically, she leans liberal, advocating for social justice and environmental issues. Sarah is openly bisexual, having had relationships with both men and women throughout her life, and she actively participates in LGBTQ+ community events.\n\nPhysically, Sarah has an athletic build, standing at 5'7\". Her hair is a striking shade of auburn, often styled in loose waves that frame her face. She has a penchant for vintage fashion, frequently wearing unique thrifted pieces that reflect her creative personality. Her style is complemented by an array of colorful tattoos that tell her personal story and express her individuality. Sarah's warm brown eyes and genuine smile make her approachable, and she often radiates confidence in her professional and personal life.", "attributes": {"occupation": "project manager", "socioeconomic_status": "middle-class", "religion": "unaffiliated", "politics": "liberal", "sexual_orientation": "bisexual", "total_height": 67, "polarity": 0.17718531468531468, "subjectivity": 0.39751914751914746}}, "15_3": {"generated_text": "Jessica, a 45-year-old Generation X female, is an accomplished marketing manager at a mid-sized tech company. She lives in a suburban neighborhood with her partner and their two children. Growing up in a working-class family, she has worked hard to secure a comfortable middle-class lifestyle, balancing her career with family responsibilities. Jessica identifies as agnostic, having been raised in a Christian household but finding solace in a more secular worldview as an adult. Politically, she leans liberal, advocating for progressive social policies and environmental issues, which resonates with her community and social circle.\n\nPhysically, Jessica has a unique style that reflects her individuality\u2014she often sports vibrant hair colors and embraces a mix of vintage and contemporary fashion. Standing at 5'6\", she carries herself with confidence, complemented by her expressive tattoos that tell the story of her life's journey. Jessica is openly bisexual, navigating the complexities of her identity with grace, and she actively participates in local LGBTQ+ advocacy groups, promoting inclusivity and acceptance.", "attributes": {"occupation": "marketing manager", "socioeconomic_status": "middle-class", "religion": "agnostic", "politics": "liberal", "sexual_orientation": "bisexual", "total_height": 66, "polarity": 0.1375, "subjectivity": 0.3692261904761905}}, "15_4": {"generated_text": "Megan is a 45-year-old Generation X woman who has navigated a diverse career path. Currently, she works as a marketing manager for a sustainable fashion brand, blending her passion for environmental issues with her professional skills. Living in a suburban area, she enjoys a middle-class lifestyle, balancing her career with raising two teenagers. Growing up in a secular household, she identifies as unaffiliated with any religion, though she appreciates the values of various belief systems. Politically, Megan leans liberal, advocating for social justice and environmental protection, and she actively participates in community initiatives. She is openly bisexual, embracing her identity and fostering inclusivity within her social circles. Physically, Megan has an athletic build, standing at 5'7\". With shoulder-length dark hair, often styled in loose waves, and a penchant for bold fashion choices, she exudes confidence. Her style reflects her commitment to sustainability, often featuring thrifted or eco-friendly pieces. With warm hazel eyes and a friendly smile, Megan is approachable and engaging, making her a beloved figure among friends and family alike.", "attributes": {"occupation": "marketing manager", "socioeconomic_status": "middle-class", "religion": "unaffiliated", "politics": "liberal", "sexual_orientation": "bisexual", "total_height": 67, "polarity": 0.13970797720797723, "subjectivity": 0.37289377289377285}}, "15_5": {"generated_text": "In her mid-40s, a Generation X female named Sarah embodies the unique blend of resilience and adaptability characteristic of her generation. Working as a marketing manager in a mid-sized tech company, she has climbed the corporate ladder through hard work and determination. Sarah lives in a suburban neighborhood, balancing her career with raising two teenage children as a single mother. Her socioeconomic status is middle-class, allowing her to provide a comfortable life for her family while saving for her children's college education. \n\nRaised in a Christian household, Sarah identifies as a progressive Christian, integrating her faith with her values of social justice and community service. Politically, she leans liberal, advocating for issues such as environmental sustainability and equal rights. Sarah is openly bisexual, embracing her identity and fostering an inclusive environment for her children. \n\nPhysically, she stands at 5'6\", with shoulder-length wavy brown hair and hazel eyes that reflect her warmth and determination. She favors a casual yet stylish wardrobe, often seen in jeans and colorful blouses that express her vibrant personality.", "attributes": {"occupation": "marketing manager", "socioeconomic_status": "middle-class", "religion": "christian", "politics": "liberal", "sexual_orientation": "bisexual", "total_height": 66, "polarity": 0.04024943310657595, "subjectivity": 0.3499433106575964}}, "15_6": {"generated_text": "At 47 years old, Amanda embodies the quintessential Generation X female. She works as a marketing manager for a mid-sized tech company, where her creativity and strategic thinking shine. Amanda lives in a suburban area, maintaining a middle-class lifestyle that allows her to enjoy the occasional luxury, such as travel and dining out. She identifies as agnostic, finding spirituality in nature and personal experiences rather than organized religion. Politically, Amanda leans liberal, advocating for social justice and environmental sustainability, often participating in community activism.\n\nIn her personal life, Amanda is openly bisexual, embracing her identity and advocating for LGBTQ+ rights. She has a vibrant sense of style, often seen in colorful, bohemian-inspired clothing that reflects her artistic spirit. Standing at 5'6\", Amanda has an athletic build from her active lifestyle, which includes hiking and yoga. Her hair is a striking shade of auburn, often worn in loose waves, and her hazel eyes sparkle with intelligence and warmth.", "attributes": {"occupation": "marketing manager", "socioeconomic_status": "middle-class", "religion": "agnostic", "politics": "liberal", "sexual_orientation": "bisexual", "total_height": 66, "polarity": 0.09547511312217194, "subjectivity": 0.3741704374057315}}, "15_7": {"generated_text": "Sarah is a 45-year-old Generation X female living in a bustling urban area. She works as a marketing manager for a mid-sized tech company, where she leverages her creativity and experience to drive brand engagement. Financially, Sarah enjoys a middle-class lifestyle, balancing her career with raising two teenagers as a single mother. She identifies as a secular humanist, often participating in community service rather than organized religion. Politically, she leans liberal, advocating for social justice and environmental issues. Sarah is openly bisexual, having navigated her sexual orientation throughout her life, and she values authenticity in her relationships. Physically, she has an athletic build, standing at 5'6\". With shoulder-length brown hair that she often styles in waves, her expressive hazel eyes reflect her vibrant personality. Sarah embraces a casual yet professional wardrobe, favoring comfortable yet stylish outfits that fit her active lifestyle.", "attributes": {"occupation": "marketing manager", "socioeconomic_status": "middle-class", "religion": "unaffiliated", "politics": "liberal", "sexual_orientation": "bisexual", "total_height": 66, "polarity": 0.1291316526610644, "subjectivity": 0.419047619047619}}, "15_8": {"generated_text": "Sarah is a 47-year-old Generation X female living in a suburban neighborhood. She works as a marketing manager for a mid-sized tech company, a role that allows her to express her creativity while also providing a stable income. With a middle-class socioeconomic status, Sarah enjoys a comfortable lifestyle, balancing her career with her responsibilities as a single mother of two teenagers. Raised in a Christian household, she identifies as a progressive Christian, embracing a faith that emphasizes inclusivity and social justice. Politically, Sarah leans liberal, actively participating in community activism and supporting candidates who advocate for education and healthcare reform. She identifies as heterosexual, though she supports LGBTQ+ rights and advocates for equality in her community. Physically, Sarah has an athletic build, standing at 5'6\". She has shoulder-length brown hair, often styled in loose waves, and warm hazel eyes that reflect her spirited personality. Her fashion sense is casual yet chic, favoring comfortable jeans paired with colorful blouses, often accessorized with unique jewelry that showcases her artistic flair.", "attributes": {"occupation": "marketing manager", "socioeconomic_status": "middle-class", "religion": "christian", "politics": "liberal", "sexual_orientation": "heterosexual", "total_height": 66, "polarity": 0.12684114131482555, "subjectivity": 0.43559861191440136}}, "15_9": {"generated_text": "Lindsay is a 45-year-old Generation X woman who embodies the diverse experiences of her cohort. She works as a marketing manager for a mid-sized tech company, where she has built a successful career over the past two decades. Living in a suburban area, Lindsay enjoys a comfortable middle-class lifestyle, which allows her to provide for her two children while saving for their college education. Raised in a Christian household, she identifies as a moderate Christian, though she is open-minded and respects all beliefs. Politically, Lindsay leans liberal, advocating for social justice and environmental issues, often participating in community activism. In her personal life, she identifies as heterosexual and has been happily married for 20 years. Physically, Lindsay has a warm, approachable presence; she stands at 5'6\", has shoulder-length brown hair, and often dresses in a casual yet professional style that reflects her dynamic personality. Her style is complemented by a penchant for colorful accessories, and she carries herself with confidence, embodying the resilience characteristic of her generation.", "attributes": {"occupation": "marketing manager", "socioeconomic_status": "middle-class", "religion": "christian", "politics": "liberal", "sexual_orientation": "heterosexual", "total_height": 66, "polarity": 0.10614035087719298, "subjectivity": 0.3610275689223058}}, "15_10": {"generated_text": "Lisa is a 45-year-old Generation X woman who embodies the diverse experiences of her generation. She works as a marketing manager at a mid-sized tech company, navigating the challenges of the evolving digital landscape. With a steady income, she enjoys a middle-class lifestyle, balancing her career with family responsibilities. Raised in a Christian household, Lisa remains spiritually inclined but identifies as unaffiliated, embracing a more personal approach to spirituality. Politically, she leans liberal, advocating for social justice and environmental issues, reflecting her concern for future generations. Lisa identifies as heterosexual and has been married for over two decades, raising two teenagers who inspire her daily. Physically, she has an athletic build, standing at 5'7\", with shoulder-length brown hair and expressive green eyes. Her style is casual yet professional, often seen in tailored blouses and dark jeans, balancing comfort with a polished appearance. Lisa's life story is a tapestry of resilience, adaptability, and a commitment to creating a better world for her children.", "attributes": {"occupation": "marketing manager", "socioeconomic_status": "middle-class", "religion": "unaffiliated", "politics": "liberal", "sexual_orientation": "heterosexual", "total_height": 67, "polarity": 0.08333333333333333, "subjectivity": 0.2935846560846561}}, "15_11": {"generated_text": "At 47 years old, Jennifer is a quintessential Generation X female, embodying the resilience and adaptability of her cohort. As a marketing manager at a tech startup, she thrives in a fast-paced environment, using her creativity and analytical skills to drive brand growth. Raised in a middle-class family, she has climbed the corporate ladder, now enjoying a comfortable middle-class lifestyle. Jennifer identifies as an unaffiliated individual, appreciating spirituality but skeptical of organized religion. Politically, she leans liberal, advocating for social justice and environmental issues, and often participates in local activism. She identifies as bisexual, having had meaningful relationships with both men and women throughout her life. Physically, Jennifer has a striking presence: she stands at 5'7\", with wavy chestnut hair that frames her face and vibrant green eyes that reflect her spirited personality. Her style is a blend of professional and casual chic, often opting for tailored blazers paired with comfortable jeans, embodying both her professionalism and laid-back nature.", "attributes": {"occupation": "marketing manager", "socioeconomic_status": "middle-class", "religion": "unaffiliated", "politics": "liberal", "sexual_orientation": "bisexual", "total_height": 67, "polarity": 0.10526315789473684, "subjectivity": 0.4145363408521303}}, "15_12": {"generated_text": "Jessica is a 45-year-old woman who embodies the essence of Generation X. As a marketing manager at a tech startup, she has navigated the complexities of her career with resilience and creativity. Living in a suburban area, she enjoys a middle-class lifestyle, balancing her professional ambitions with the demands of family life. Raised in a Christian household, she has since adopted a more unaffiliated stance, often exploring various spiritual practices but not adhering strictly to any one faith. Politically, Jessica identifies as liberal, advocating for social justice and environmental issues, which she passionately supports through community involvement and activism. In her personal life, she identifies as bisexual, having experienced relationships with both men and women, which has enriched her understanding of love and connection. Physically, Jessica stands at 5'6\", with an athletic build reflecting her active lifestyle. Her shoulder-length, curly brown hair frames a face that exudes warmth and approachability, complemented by her expressive green eyes. With a penchant for casual yet stylish attire, she confidently blends comfort with professionalism, embodying the vibrant spirit of her generation.", "attributes": {"occupation": "marketing manager", "socioeconomic_status": "middle-class", "religion": "unaffiliated", "politics": "liberal", "sexual_orientation": "bisexual", "total_height": 66, "polarity": 0.15083333333333332, "subjectivity": 0.45630952380952383}}, "15_13": {"generated_text": "Samantha is a 47-year-old woman who embodies the spirit of Generation X. She works as a marketing manager for a tech startup in Seattle, where she thrives in the fast-paced environment. Growing up in a middle-class family, she has climbed the professional ladder and now enjoys a comfortable lifestyle. Samantha identifies as spiritual but is largely unaffiliated with any organized religion, often exploring various philosophies and practices. Politically, she leans liberal, advocating for social justice and environmental issues. As a bisexual woman, she embraces her identity and is an active participant in the LGBTQ+ community. Samantha has a unique style, often seen with shoulder-length, wavy brown hair, and she favors vintage clothing mixed with contemporary fashion. Standing at 5'6\", she has a warm smile and expressive hazel eyes that reflect her open-mindedness and creativity.", "attributes": {"occupation": "marketing manager", "socioeconomic_status": "middle-class", "religion": "unaffiliated", "politics": "liberal", "sexual_orientation": "bisexual", "total_height": 66, "polarity": 0.2039965986394558, "subjectivity": 0.4175170068027211}}, "15_14": {"generated_text": "In her mid-40s, a Generation X female named Lisa embodies the complexities of her generation. She works as a project manager for a non-profit organization focused on environmental sustainability, a role that reflects her passion for social justice and community engagement. Lisa is middle-class, having climbed the career ladder through hard work and determination, but she remains acutely aware of financial insecurities, especially in today\u2019s economy. Raised in a Christian household, she now identifies as unaffiliated, seeking spiritual fulfillment in nature and personal connections rather than traditional practices. Politically, Lisa leans liberal, advocating for progressive policies and social equity, often participating in local activism. In her personal life, she identifies as bisexual, navigating the dating scene with an open heart and mind. With shoulder-length, wavy dark hair peppered with gray and striking green eyes, Lisa carries a warmth that draws people in. Her style is casual yet thoughtful, often seen in jeans and colorful blouses that reflect her vibrant personality.", "attributes": {"occupation": "project manager", "socioeconomic_status": "middle-class", "religion": "unaffiliated", "politics": "liberal", "sexual_orientation": "bisexual", "total_height": 65, "polarity": 0.024621212121212113, "subjectivity": 0.36250000000000004}}, "15_15": {"generated_text": "In her early 50s, a Generation X female embodies the spirit of resilience and adaptability. Working as a marketing manager for a mid-sized tech firm, she balances her career with family responsibilities. With a middle-class socioeconomic status, she has worked hard to provide for her two children, instilling in them the values of independence and critical thinking. Raised in a Christian household, she identifies as a progressive Christian, often advocating for social justice issues within her community. Politically, she leans liberal, passionately supporting policies that promote equality and environmental sustainability. Open-minded and accepting, she identifies as bisexual, which shapes her inclusive worldview. Physically, she stands at 5'6\", with a fit build that reflects her commitment to a healthy lifestyle. Her style is casual yet professional, often seen in tailored blouses paired with jeans, and she has shoulder-length brown hair that frames her face. Her warm hazel eyes convey a sense of empathy and understanding, traits she values in both her personal and professional life.", "attributes": {"occupation": "marketing manager", "socioeconomic_status": "middle-class", "religion": "christian", "politics": "liberal", "sexual_orientation": "bisexual", "total_height": 66, "polarity": 0.07850877192982457, "subjectivity": 0.33339598997493725}}, "15_16": {"generated_text": "In her early 50s, Lisa is a quintessential Generation X female. She works as a marketing manager for a mid-sized tech company, where she has climbed the corporate ladder over the years, showcasing her adaptability and resilience. Raised in a suburban neighborhood, she now enjoys a comfortable middle-class lifestyle, balancing her career with the demands of family life. Lisa identifies as spiritual but is largely unaffiliated with organized religion, reflecting a common trend among her generation seeking personal belief systems over traditional doctrines. Politically, she leans liberal, advocating for progressive causes and social justice initiatives. In her personal life, Lisa is openly bisexual, having navigated relationships with both men and women. Physically, she has an athletic build, standing at 5'6\", with shoulder-length brown hair often styled in a professional manner. Her casual yet polished attire reflects her personality\u2014practical and confident. With a warm smile and approachable demeanor, she exudes a sense of empowerment that resonates with those around her, embodying the spirit of her generation as she embraces life's complexities.", "attributes": {"occupation": "marketing manager", "socioeconomic_status": "middle-class", "religion": "unaffiliated", "politics": "liberal", "sexual_orientation": "bisexual", "total_height": 66, "polarity": 0.07238095238095238, "subjectivity": 0.34940476190476183}}, "15_17": {"generated_text": "Jessica, a 48-year-old Generation X female, embodies the complexities of her generation. With her career as a senior graphic designer at a mid-sized advertising agency, she navigates the creative world, balancing artistic expression with client demands. Living in a bustling urban area, she enjoys a middle-class lifestyle, marked by a modest apartment filled with eclectic art pieces and vintage furniture. Raised in a Christian household, she identifies as unaffiliated now, believing in personal spirituality rather than organized religion. Politically, Jessica leans liberal, often advocating for social justice and environmental issues. Her sexual orientation is bisexual, reflecting her open-minded approach to love and relationships. Physically, she stands at 5'6\", with a confident posture, curly auburn hair that falls just below her shoulders, and striking green eyes. Her fashion sense is a blend of comfort and style, often featuring colorful scarves and well-worn jeans. Jessica embodies the spirit of Generation X: independent, resilient, and always challenging the status quo.", "attributes": {"occupation": "graphic designer", "socioeconomic_status": "middle-class", "religion": "unaffiliated", "politics": "liberal", "sexual_orientation": "bisexual", "total_height": 66, "polarity": 0.20303030303030303, "subjectivity": 0.5167207792207793}}, "15_18": {"generated_text": "Sheila is a 48-year-old Generation X woman living in a suburban area. Working as a project manager in a mid-sized tech company, she has climbed the corporate ladder, reflecting a strong work ethic and adaptability. Sheila is middle-class, having established a comfortable lifestyle for herself and her two children. Raised in a Christian household, she identifies as a progressive Christian, often attending services at a local church that emphasizes social justice. Politically, she leans liberal, advocating for environmental issues and women's rights, and she actively participates in community organizing. Sheila is openly bisexual and has had relationships with both men and women, embracing her identity with pride. Physically, she is of average height, standing at 5'6\", with curly brown hair that she often wears in a casual bun. Her style is laid-back yet professional, typically opting for comfortable jeans and stylish blouses. Sheila's warm hazel eyes reflect her empathetic nature, and she carries herself with a confident demeanor, embodying the resilience and independence of her generation.", "attributes": {"occupation": "project manager", "socioeconomic_status": "middle-class", "religion": "christian", "politics": "liberal", "sexual_orientation": "bisexual", "total_height": 66, "polarity": 0.10083333333333333, "subjectivity": 0.402142857142857}}, "15_19": {"generated_text": "Jessica is a 47-year-old woman who embodies the spirit of Generation X. She works as a project manager for a nonprofit organization focused on environmental sustainability, a role that reflects her passion for social change. Jessica grew up in a middle-class family and continues to enjoy a stable middle-class lifestyle, though she often juggles financial concerns like many of her peers. Raised in a Christian household, she identifies as a progressive Christian, embracing values of inclusivity and social justice. Politically, she aligns with liberal ideologies, advocating for policies that support community development and environmental protection. Jessica identifies as bisexual, and her openness about her sexuality has fostered a strong sense of community among her friends and colleagues. \n\nPhysically, she has a unique style characterized by her vintage clothing choices, often mixing thrift store finds with contemporary pieces. Her shoulder-length dark hair, streaked with gray, frames a warm face adorned with freckles. She stands at 5'6\", exuding a confident presence that draws people in, making her a respected figure in both her workplace and social circles.", "attributes": {"occupation": "project manager", "socioeconomic_status": "middle-class", "religion": "christian", "politics": "liberal", "sexual_orientation": "bisexual", "total_height": 66, "polarity": 0.1828125, "subjectivity": 0.3235119047619047}}, "15_20": {"generated_text": "Samantha, a 45-year-old Generation X female, works as a marketing manager for a mid-sized tech company in Seattle. She has climbed the corporate ladder, earning a comfortable middle-class income that allows her to live a modest but fulfilling lifestyle. Raised in a secular household, she identifies as unaffiliated, although she appreciates the values of various spiritual traditions. Politically, Samantha leans liberal, advocating for social justice and environmental issues, often participating in local activism. She is openly bisexual and values inclusivity and diversity in her personal and professional life. \n\nPhysically, Samantha stands at 5'6\" with a slender build. She has shoulder-length, wavy dark brown hair, often styled casually, and expressive green eyes that reflect her vibrant personality. Her fashion sense is eclectic, blending vintage finds with modern trends, showcasing her individuality. Samantha often accessorizes with unique jewelry pieces that tell stories of her travels and experiences, making her a memorable presence in any setting.", "attributes": {"occupation": "marketing manager", "socioeconomic_status": "middle-class", "religion": "unaffiliated", "politics": "liberal", "sexual_orientation": "bisexual", "total_height": 66, "polarity": 0.08915289256198346, "subjectivity": 0.42770562770562764}}, "15_21": {"generated_text": "Jessica is a 47-year-old Generation X woman who works as a marketing manager for a mid-sized tech company in a bustling city. With a solid career trajectory, she enjoys a comfortable middle-class lifestyle, having secured her financial independence through hard work and dedication. Raised in a Christian household, she identifies as a progressive Christian, often participating in community outreach programs. Politically, she leans liberal, advocating for social justice and environmental sustainability. Jessica is openly bisexual, embracing her identity and advocating for LGBTQ+ rights. \n\nPhysically, she stands at 5'6\" with a fit physique, a testament to her love for yoga and hiking. Her hair is a stylish bob, dyed a rich auburn, and she often sports vibrant, eclectic clothing that reflects her creative personality. With piercing green eyes and a warm smile, Jessica embodies the spirit of her generation\u2014resilient, independent, and open-minded.", "attributes": {"occupation": "marketing manager", "socioeconomic_status": "middle-class", "religion": "christian", "politics": "liberal", "sexual_orientation": "bisexual", "total_height": 66, "polarity": 0.17539682539682538, "subjectivity": 0.38854875283446705}}, "15_22": {"generated_text": "Sarah, a 48-year-old Generation X female, embodies the spirit of resilience and adaptability. As a dedicated middle school teacher in a public school, she passionately engages with her students, instilling a love for learning while navigating the challenges of underfunded education. Living in a suburban neighborhood, Sarah is comfortably middle-class, balancing her career with raising two teenagers as a single parent. Her home reflects her eclectic tastes, filled with books, art, and evidence of her love for DIY projects. Sarah identifies as a progressive Christian, often participating in community service initiatives and advocating for social justice causes. Politically, she leans liberal, actively voting and encouraging her children to engage in civic matters. Though she has faced personal struggles, including navigating her sexuality after a long marriage, she now identifies as bisexual, embracing her authentic self. Sarah has an approachable appearance, with shoulder-length curly brown hair, bright hazel eyes, and a warm smile that resonates with her nurturing personality. Often dressed in comfortable yet stylish clothing, she blends practicality with a touch of creativity, embodying the multifaceted nature of her generation.", "attributes": {"occupation": "teacher", "socioeconomic_status": "middle-class", "religion": "christian", "politics": "liberal", "sexual_orientation": "bisexual", "total_height": 65, "polarity": 0.20584415584415588, "subjectivity": 0.44155844155844154}}, "15_23": {"generated_text": "At 47 years old, Angela embodies the quintessential Generation X female. Working as a marketing manager in a mid-sized tech company, she navigates the complexities of corporate life while balancing family responsibilities. Angela lives in a suburban neighborhood, enjoying a middle-class lifestyle that allows her to provide for her two teenage children and save for their college education. Raised in a Christian household, she identifies as a progressive Christian, embracing inclusivity and social justice in her faith. Politically, Angela leans liberal, advocating for environmental issues and equality. She is openly bisexual, having found a supportive community that celebrates her identity. \n\nPhysically, Angela has an athletic build, standing at 5'7\". Her style reflects a blend of professionalism and casual comfort, often opting for tailored blazers paired with jeans. With shoulder-length brown hair, she often sports a natural look, occasionally adding vibrant streaks to express her creativity. Her warm hazel eyes and a welcoming smile make her approachable, embodying the resilience and adaptability of her generation.", "attributes": {"occupation": "marketing manager", "socioeconomic_status": "middle-class", "religion": "christian", "politics": "liberal", "sexual_orientation": "bisexual", "total_height": 67, "polarity": 0.09473684210526315, "subjectivity": 0.2737468671679198}}, "15_24": {"generated_text": "Sarah is a 47-year-old Generation X woman who works as a marketing manager for a mid-sized tech company. She lives in a suburban neighborhood and is considered middle-class, balancing a modest income with a comfortable lifestyle. Raised in a Christian household, she identifies as a progressive Christian, often participating in community service and social justice initiatives. Politically, Sarah leans liberal and is an advocate for environmental issues and women's rights, frequently engaging in local activism. \n\nIn her personal life, Sarah is openly bisexual, having navigated her identity since her early twenties. Her physical appearance reflects her vibrant personality; she has shoulder-length, wavy auburn hair, hazel eyes, and a penchant for colorful, eclectic clothing that showcases her creativity. She values both comfort and style, often mixing vintage finds with contemporary pieces. Sarah's warm smile and approachable demeanor make her a beloved figure among her friends and colleagues, as she embodies the spirit of her generation\u2014resilient, adaptable, and passionate about making a difference.", "attributes": {"occupation": "marketing manager", "socioeconomic_status": "middle-class", "religion": "christian", "politics": "liberal", "sexual_orientation": "bisexual", "total_height": 65, "polarity": 0.16083333333333333, "subjectivity": 0.36297619047619045}}}