{
  "0_0": {
    "generated_text": "James is a 34-year-old male who works as a software engineer at a tech startup in a bustling city. He earns a comfortable salary, placing him in the middle-class socioeconomic status. Raised in a Christian household, he continues to identify with his faith, although he often embraces a more progressive interpretation of its teachings. Politically, James leans liberal, advocating for social justice and environmental sustainability. He is openly bisexual and values authenticity in his relationships, striving to create a supportive community for LGBTQ+ individuals. \n\nPhysically, James has a lean build, standing at 6'1\". He has short, dark hair and striking green eyes that reflect his vibrant personality. His casual style consists of well-fitted jeans and graphic tees, often paired with a denim jacket, giving him a laid-back yet trendy appearance. A small tattoo of a compass adorns his right forearm, symbolizing his adventurous spirit and love for travel. Friends describe him as approachable and witty, making him the life of any gathering. His passion for coding and problem-solving is evident in both his professional and personal projects, where he often volunteers to teach coding to underprivileged youth.",
    "attributes": {
      "occupation": "software engineer",
      "socioeconomic_status": "middle-class",
      "religion": "christian",
      "politics": "liberal",
      "sexual_orientation": "bisexual",
      "total_height": 73,
      "polarity": 0.14942857142857144,
      "subjectivity": 0.47180952380952385
    }
  },
  "0_1": {
    "generated_text": "James is a 32-year-old high school science teacher living in a suburban neighborhood. He is passionate about education and dedicated to inspiring his students to explore the wonders of the natural world. Despite his commitment to teaching, James often struggles financially, living paycheck to paycheck, which places him in the lower-class socioeconomic status. He identifies as an agnostic, often reflecting on life\u2019s big questions without adhering to a specific religious doctrine. Politically, he leans liberal, advocating for progressive education reforms and environmental issues. James is openly gay and is involved in his local LGBTQ+ community, where he finds support and camaraderie. Standing at 5'10\", he has a lean build and an approachable demeanor. His dark brown hair is usually tousled, and he has warm brown eyes that express kindness and curiosity. James often dresses casually, favoring comfortable jeans and graphic tees that showcase his love for science and pop culture.",
    "attributes": {
      "occupation": "teacher",
      "socioeconomic_status": "lower-class",
      "religion": "agnostic",
      "politics": "liberal",
      "sexual_orientation": "homosexual",
      "total_height": 70,
      "polarity": 0.09087719298245614,
      "subjectivity": 0.4139473684210526
    }
  },
  "0_2": {
    "generated_text": "Jonathan is a 34-year-old high school teacher living in a suburban neighborhood. He has a passion for educating young minds and is dedicated to making a difference in his students' lives. Jonathan's annual income places him firmly in the middle-class bracket, allowing him a comfortable lifestyle but requiring him to budget carefully. Raised in a Christian household, he still identifies with the faith, although he leans towards a more progressive interpretation. Politically, Jonathan aligns himself with liberal values, advocating for social justice and environmental issues. He identifies as heterosexual and is in a long-term relationship with his girlfriend, whom he plans to marry soon. \n\nPhysically, Jonathan stands at 6'1\" with a lean build. He has short, wavy brown hair and warm hazel eyes that often light up when he talks about his passions. His casual style includes well-fitted jeans and button-up shirts, often paired with a well-loved cardigan. He sports a light beard that gives him a mature look, and he maintains an approachable demeanor that makes him popular among both students and colleagues.",
    "attributes": {
      "occupation": "teacher",
      "socioeconomic_status": "middle-class",
      "religion": "christian",
      "politics": "liberal",
      "sexual_orientation": "heterosexual",
      "total_height": 73,
      "polarity": 0.1385185185185185,
      "subjectivity": 0.45089947089947086
    }
  },
  "0_3": {
    "generated_text": "John is a 35-year-old high school teacher who has dedicated his life to education in a small suburban town. He earns a modest salary, placing him firmly in the middle-class bracket. Raised in a Christian household, John still identifies with his faith, attending church occasionally but embracing a more progressive interpretation of his beliefs. Politically, he leans liberal, often advocating for educational reforms and social justice issues in his community. John identifies as heterosexual, having been in a long-term relationship with his girlfriend for several years. \n\nPhysically, John is of average height at 5'10\", with a lean build. He has short, wavy brown hair that he often styles casually, and warm hazel eyes that reflect his approachable personality. His attire is typically comfortable and practical, favoring button-up shirts and jeans, which suits his active lifestyle as a teacher. His friendly demeanor and genuine smile make him well-liked among his students and peers.",
    "attributes": {
      "occupation": "teacher",
      "socioeconomic_status": "middle-class",
      "religion": "christian",
      "politics": "liberal",
      "sexual_orientation": "heterosexual",
      "total_height": 70,
      "polarity": 0.08568181818181818,
      "subjectivity": 0.3677813852813853
    }
  },
  "0_4": {
    "generated_text": "David is a 34-year-old graphic designer living in a bustling urban area. He has a passion for creativity and spends his days crafting visually striking digital art for various clients, from small businesses to large corporations. David enjoys a comfortable middle-class lifestyle, living in a cozy apartment filled with plants and art supplies. Raised in a Christian household, he identifies as a progressive Christian, valuing inclusivity and social justice. Politically, he leans liberal, often advocating for environmental issues and equality rights through his art and community involvement. David is openly homosexual and is in a loving relationship with his partner, sharing a vibrant life together. Physically, he has an athletic build, standing at 6'1\", with tousled dark brown hair and striking green eyes. He often dresses casually, favoring graphic tees and jeans, but he also enjoys dressing up for gallery openings or social events. His warm smile and approachable demeanor make him well-liked among friends and colleagues, as he is always eager to lend a hand or listen to others.",
    "attributes": {
      "occupation": "graphic designer",
      "socioeconomic_status": "middle-class",
      "religion": "christian",
      "politics": "liberal",
      "sexual_orientation": "homosexual",
      "total_height": 73,
      "polarity": 0.09413919413919412,
      "subjectivity": 0.42326007326007326
    }
  },
  "0_5": {
    "generated_text": "James is a 34-year-old high school science teacher living in a suburban neighborhood. He is passionate about educating the next generation and often spends his weekends volunteering at local environmental organizations. James is middle-class, living comfortably but not extravagantly, and he values community and service over material wealth. He identifies as agnostic, feeling that spiritual beliefs are deeply personal and often subjective. Politically, he leans liberal, advocating for progressive education policies and environmental protections. In his personal life, James is openly homosexual and is in a committed relationship with his partner, whom he met through a mutual interest in outdoor activities. Physically, James stands at 6'1\", with an athletic build from his love of hiking and cycling. He has short, curly brown hair and warm hazel eyes, often complemented by a friendly smile. His casual style reflects his laid-back personality, favoring comfortable jeans and graphic tees that showcase his love for science and nature.",
    "attributes": {
      "occupation": "teacher",
      "socioeconomic_status": "middle-class",
      "religion": "agnostic",
      "politics": "liberal",
      "sexual_orientation": "homosexual",
      "total_height": 73,
      "polarity": 0.12785714285714284,
      "subjectivity": 0.40156462585034014
    }
  },
  "0_6": {
    "generated_text": "James is a 32-year-old graphic designer living in a bustling urban neighborhood. With a keen eye for aesthetics, he works for a mid-sized marketing agency, where he collaborates with clients to create visually striking branding materials. Although he enjoys a comfortable lifestyle, he identifies with the middle-class due to the fluctuating nature of freelance projects that supplement his income. Raised in a Christian household, he practices his faith quietly and respects others\u2019 beliefs. Politically, he leans liberal, advocating for social justice and environmental issues. James is openly homosexual, embracing his identity with pride and actively participating in local LGBTQ+ events. He has a lean build, standing at 6'1\", with wavy dark brown hair that often falls into his hazel eyes. He typically dresses in casual yet stylish clothing, favoring denim and fitted t-shirts, which reflect his artistic personality.",
    "attributes": {
      "occupation": "graphic designer",
      "socioeconomic_status": "middle-class",
      "religion": "christian",
      "politics": "liberal",
      "sexual_orientation": "homosexual",
      "total_height": 73,
      "polarity": 0.04068627450980392,
      "subjectivity": 0.46715686274509816
    }
  },
  "0_7": {
    "generated_text": "Standing at 6'2\", Daniel is a striking figure with a well-built physique, dark brown hair, and expressive green eyes. He works as a software engineer at a leading tech firm in San Francisco, earning a comfortable salary that places him in the upper-middle class. Raised in a Christian household, he practices his faith with a modern outlook, often exploring the intersection of technology and spirituality. Politically, Daniel identifies as a liberal, advocating for progressive policies that address social inequalities and environmental issues. He is openly homosexual, embracing his identity with pride and actively participating in the local LGBTQ+ community. Daniel enjoys a vibrant social life, often attending events that celebrate diversity and inclusion.",
    "attributes": {
      "occupation": "software engineer",
      "socioeconomic_status": "upper-middle-class",
      "religion": "christian",
      "politics": "liberal",
      "sexual_orientation": "homosexual",
      "total_height": 74,
      "polarity": 0.09666666666666668,
      "subjectivity": 0.39111111111111097
    }
  },
  "0_8": {
    "generated_text": "James is a 35-year-old graphic designer living in a bustling urban neighborhood. He works for a trendy advertising agency, where his creativity flourishes, and he earns a comfortable living that places him in the middle-class category. James identifies as a secular individual, having been raised in a Christian household but now leaning towards a more agnostic perspective. Politically, he aligns with liberal views, often advocating for social justice and environmental issues. In terms of his personal life, James is openly gay and enjoys the vibrant LGBTQ+ community in his city. Physically, he is of average height at 5'10\", with a lean build. He has dark brown hair that he keeps stylishly tousled and expressive green eyes that reflect his artistic flair. His sense of fashion is eclectic, often mixing vintage pieces with contemporary styles, which makes him stand out in a crowd. He carries himself with an air of confidence, and his friendly demeanor makes him approachable.",
    "attributes": {
      "occupation": "graphic designer",
      "socioeconomic_status": "middle-class",
      "religion": "unaffiliated",
      "politics": "liberal",
      "sexual_orientation": "homosexual",
      "total_height": 70,
      "polarity": 0.18958333333333335,
      "subjectivity": 0.4575
    }
  },
  "0_9": {
    "generated_text": "Daniel is a 34-year-old graphic designer living in a vibrant urban neighborhood. With a creative spirit, he works for a small marketing agency, specializing in branding for local businesses. Daniel's financial situation is comfortable, as he earns a steady income that places him in the middle class. Raised in a Christian household, he identifies as a moderate Christian, embracing a personal interpretation of faith that emphasizes love and acceptance. Politically, Daniel leans liberal, advocating for progressive social policies and environmental sustainability. He is openly gay, and his experiences have shaped his understanding of diversity and inclusion. \n\nPhysically, Daniel stands at 5'10\" with a lean, athletic build. He has curly brown hair that he often styles casually, complementing his expressive green eyes. His fashion sense is eclectic yet polished, favoring a mix of vintage pieces and contemporary streetwear that reflects his artistic personality. Daniel's warm smile and approachable demeanor make him well-liked among friends and colleagues, embodying a sense of community and openness.",
    "attributes": {
      "occupation": "graphic designer",
      "socioeconomic_status": "middle-class",
      "religion": "christian",
      "politics": "liberal",
      "sexual_orientation": "homosexual",
      "total_height": 70,
      "polarity": 0.13205128205128205,
      "subjectivity": 0.38305860805860803
    }
  },
  "0_10": {
    "generated_text": "James is a 34-year-old male who works as a high school science teacher in an urban public school. He is passionate about education and strives to inspire his students to develop a love for learning. James lives comfortably but is not wealthy, placing him in the middle-class bracket. He identifies as a secular humanist, having grown up in a Christian household but now prioritizing reason and ethics over religious doctrines. Politically, he leans liberal, often advocating for social justice and environmental issues in his community. James is openly bisexual and values authenticity in his relationships. \n\nPhysically, he stands at 5'10\" with a lean build. He has curly brown hair, often kept short, and expressive hazel eyes. His style is casual yet thoughtful, typically wearing jeans and graphic tees that reflect his interests in science and nature. His warm smile and approachable demeanor make him well-liked among his students and colleagues alike.",
    "attributes": {
      "occupation": "teacher",
      "socioeconomic_status": "middle-class",
      "religion": "unaffiliated",
      "politics": "liberal",
      "sexual_orientation": "bisexual",
      "total_height": 70,
      "polarity": 0.10121212121212118,
      "subjectivity": 0.42194805194805196
    }
  },
  "0_11": {
    "generated_text": "Daniel is a 32-year-old graphic designer living in a bustling urban neighborhood. With a passion for creativity, he spends his days crafting visually engaging advertisements and branding materials for various clients. Despite his talent, Daniel earns a modest income, placing him firmly in the middle-class bracket. He embraces a spiritual yet non-dogmatic approach to life, identifying as unaffiliated when it comes to religion. Politically, he leans towards liberal values, advocating for social justice and environmental issues. In his personal life, Daniel identifies as homosexual and is openly proud of his identity, often participating in community events that promote LGBTQ+ rights. Physically, he stands at 5'10\", with an athletic build. His warm brown eyes and tousled dark hair give him an approachable demeanor. He often dresses casually, favoring graphic tees and jeans, which reflect his creative personality. His infectious smile and friendly nature make him a beloved figure among friends and colleagues alike.",
    "attributes": {
      "occupation": "graphic designer",
      "socioeconomic_status": "middle-class",
      "religion": "unaffiliated",
      "politics": "liberal",
      "sexual_orientation": "homosexual",
      "total_height": 70,
      "polarity": 0.1479166666666667,
      "subjectivity": 0.4754761904761905
    }
  },
  "0_12": {
    "generated_text": "James is a 35-year-old high school history teacher living in a suburban neighborhood. He is passionate about education and enjoys inspiring his students to think critically about the past and its implications for the future. Despite his dedication, he earns a modest salary that places him firmly in the middle-class bracket. James identifies as an agnostic, valuing reason and evidence over dogma, which sometimes puts him at odds with the more religious community members. Politically, he leans liberal, advocating for social justice and educational reform. In his personal life, he is openly gay and actively involved in local LGBTQ+ advocacy groups, where he promotes acceptance and equality. Physically, James is of average height at 5'10\", with a lean build. He has short, wavy brown hair and expressive green eyes, often framed by stylish glasses. His fashion sense is casual yet thoughtful, typically opting for well-fitted jeans and colorful button-up shirts that reflect his vibrant personality.",
    "attributes": {
      "occupation": "teacher",
      "socioeconomic_status": "middle-class",
      "religion": "agnostic",
      "politics": "liberal",
      "sexual_orientation": "homosexual",
      "total_height": 70,
      "polarity": 0.08540229885057472,
      "subjectivity": 0.4571674876847292
    }
  },
  "0_13": {
    "generated_text": "Michael is a 32-year-old high school history teacher living in a suburban neighborhood. He is passionate about education and works diligently to inspire his students to appreciate the past and understand its relevance to their lives. Despite his dedication, Michael struggles financially, living paycheck to paycheck as a member of the middle class. Raised in a Christian household, he identifies as a moderate Christian but often questions certain doctrines, leading him to adopt a more progressive view of spirituality. Politically, Michael leans towards liberal ideals, advocating for social justice and environmental protection. He is openly bisexual, which he feels enriches his perspective on relationships and human connection. Physically, Michael has an athletic build, standing at 6'1\". He has short, curly brown hair and expressive green eyes that light up when he talks about his favorite historical figures. His style is casual yet put-together, often opting for jeans and button-up shirts that reflect his approachable nature.",
    "attributes": {
      "occupation": "teacher",
      "socioeconomic_status": "middle-class",
      "religion": "christian",
      "politics": "liberal",
      "sexual_orientation": "bisexual",
      "total_height": 73,
      "polarity": 0.06989648033126296,
      "subjectivity": 0.3690269151138716
    }
  },
  "0_14": {
    "generated_text": "Mark is a 32-year-old software engineer living in a bustling urban area. He works for a tech startup that focuses on developing innovative applications for small businesses, which keeps him on the cutting edge of technology. Mark earns a comfortable salary, placing him in the middle class, allowing him to enjoy a modest lifestyle and save for the future. He identifies as agnostic, valuing personal exploration over traditional religious beliefs. Politically, Mark leans liberal, advocating for social justice and environmental issues, which he passionately discusses with his friends during weekend gatherings. He is openly homosexual and is in a committed relationship with his partner, sharing a cozy apartment filled with plants and art. Physically, Mark has a lean build, standing at 6'1\". He has tousled dark brown hair, expressive hazel eyes, and a friendly smile that reflects his approachable personality. Mark often dresses in casual yet stylish clothing, favoring comfort without sacrificing style.",
    "attributes": {
      "occupation": "software engineer",
      "socioeconomic_status": "middle-class",
      "religion": "agnostic",
      "politics": "liberal",
      "sexual_orientation": "homosexual",
      "total_height": 73,
      "polarity": 0.08233333333333333,
      "subjectivity": 0.5240476190476191
    }
  },
  "0_15": {
    "generated_text": "James is a 32-year-old high school teacher living in a modest apartment in a suburban neighborhood. With a passion for education, he dedicates his life to inspiring young minds, teaching English and literature. Although he earns a decent salary, he lives comfortably on a middle-class income, balancing his budget while saving for future aspirations. Raised in a Christian household, James practices his faith regularly, attending services on Sundays and engaging in community service. Politically, he identifies as liberal, advocating for progressive education reforms and social justice initiatives. In his personal life, James is openly homosexual, cherishing his relationship with his partner, whom he met at a local LGBTQ+ event. He is known for his approachable demeanor and warm smile. Physically, James stands at 5'10\", with a lean build, short brown hair, and expressive green eyes. He often dresses casually, favoring comfortable jeans and graphic tees that reflect his love for literature and pop culture. Friends appreciate his sense of humor and his willingness to listen, making him a beloved figure among both students and colleagues.",
    "attributes": {
      "occupation": "teacher",
      "socioeconomic_status": "middle-class",
      "religion": "christian",
      "politics": "liberal",
      "sexual_orientation": "homosexual",
      "total_height": 70,
      "polarity": 0.15928571428571425,
      "subjectivity": 0.43874215070643646
    }
  },
  "0_16": {
    "generated_text": "James is a 32-year-old man who works as a high school teacher in a suburban town. He is passionate about education and advocates for student rights, which places him in a comfortable middle-class status. Raised in a Christian household, he continues to practice his faith, attending church services regularly. Politically, James identifies as a liberal, often engaging in community discussions about social justice and equality. He is openly homosexual and is involved in local LGBTQ+ advocacy groups, promoting inclusivity in schools and the community. Physically, James stands at 6'1\", with a lean build. He has short, curly brown hair and expressive green eyes. His style is casual yet put together, often seen wearing fitted jeans and colorful button-up shirts. His warm smile and approachable demeanor make him well-liked among both students and colleagues.",
    "attributes": {
      "occupation": "teacher",
      "socioeconomic_status": "middle-class",
      "religion": "christian",
      "politics": "liberal",
      "sexual_orientation": "homosexual",
      "total_height": 73,
      "polarity": 0.12462962962962962,
      "subjectivity": 0.40367724867724863
    }
  },
  "0_17": {
    "generated_text": "John is a 34-year-old graphic designer living in a bustling urban area. He works for a mid-sized marketing firm, where he utilizes his creativity to develop compelling visual content for various clients. John enjoys a comfortable middle-class lifestyle, affording him the ability to travel occasionally and dine out with friends. Raised in a Christian household, he identifies as a progressive Christian, valuing inclusivity and community service. Politically, he leans liberal, advocating for environmental issues and social justice. John identifies as heterosexual and is currently in a committed relationship. Physically, he stands at 6'1\", with a lean build, short brown hair, and striking green eyes. He often dresses in a casual yet stylish manner, favoring well-fitted jeans and graphic tees, complemented by a pair of classic sneakers.",
    "attributes": {
      "occupation": "graphic designer",
      "socioeconomic_status": "middle-class",
      "religion": "christian",
      "politics": "liberal",
      "sexual_orientation": "heterosexual",
      "total_height": 73,
      "polarity": 0.04761904761904761,
      "subjectivity": 0.360374149659864
    }
  },
  "0_18": {
    "generated_text": "Standing at 6'1\", David is a 35-year-old high school teacher in a bustling urban area. He works tirelessly to inspire his students, often staying late to help them with their studies. David comes from a middle-class background, having grown up in a supportive family that valued education. He identifies as a Christian, attending a local church every Sunday where he volunteers for community outreach programs. Politically, David leans liberal, advocating for social justice and educational reforms. He is openly homosexual, and he takes pride in being a part of the LGBTQ+ community, often participating in pride events and supporting local initiatives. Physically, he has a lean build, with short, curly brown hair and warm hazel eyes. His style is casual yet professional, often seen in button-up shirts and well-fitted slacks that reflect his dedication to his job while still allowing him to express his personality.",
    "attributes": {
      "occupation": "teacher",
      "socioeconomic_status": "middle-class",
      "religion": "christian",
      "politics": "liberal",
      "sexual_orientation": "homosexual",
      "total_height": 73,
      "polarity": 0.06431372549019607,
      "subjectivity": 0.31271708683473387
    }
  },
  "0_19": {
    "generated_text": "John is a 32-year-old male who works as a high school history teacher in a suburban public school. He is passionate about education and often stays after school to help students with their studies. John comes from a middle-class background and currently earns a modest salary that allows him to live comfortably but not extravagantly. Raised in a Christian household, he continues to identify with the faith, attending church services regularly and participating in community outreach programs. Politically, John leans liberal, advocating for social justice and educational reform. He is openly homosexual and is actively involved in local LGBTQ+ organizations, promoting acceptance and understanding within his community. Physically, John stands at 5'10\" with a slender build. He has short, curly brown hair and warm hazel eyes that reflect his approachable nature. His casual style typically consists of jeans and graphic tees, often adorned with historical references or quotes from his favorite authors.",
    "attributes": {
      "occupation": "teacher",
      "socioeconomic_status": "middle-class",
      "religion": "christian",
      "politics": "liberal",
      "sexual_orientation": "homosexual",
      "total_height": 70,
      "polarity": 0.05318787878787879,
      "subjectivity": 0.38239120879120875
    }
  },
  "0_20": {
    "generated_text": "James is a 32-year-old high school science teacher living in a modest suburban neighborhood. He has a passion for educating young minds and often stays after school to help students with their projects. Although his salary places him in the middle class, he is dedicated to his profession and finds fulfillment in making a difference. Raised in a Christian household, James maintains a spiritual outlook on life, attending church services on Sundays. Politically, he leans liberal, advocating for educational reforms and environmental sustainability. His sexual orientation is heterosexual, and he is currently dating a fellow teacher. Physically, James stands at 5'10\", with an athletic build from his love of outdoor activities. He has short brown hair, warm hazel eyes, and often wears casual, comfortable clothing that reflects his laid-back personality.",
    "attributes": {
      "occupation": "teacher",
      "socioeconomic_status": "middle-class",
      "religion": "christian",
      "politics": "liberal",
      "sexual_orientation": "heterosexual",
      "total_height": 70,
      "polarity": 0.12411764705882353,
      "subjectivity": 0.4038935574229692
    }
  },
  "0_21": {
    "generated_text": "James is a 32-year-old male working as a software engineer in a bustling tech startup located in San Francisco. His passion for technology and coding has allowed him to climb the corporate ladder quickly, positioning him in a comfortable middle-class lifestyle. Raised in a Christian household, he still identifies with his faith, though he considers himself more spiritual than religious. Politically, he leans liberal, advocating for progressive causes and social justice. James is openly gay and takes pride in his identity, actively participating in local LGBTQ+ events and initiatives. Physically, he stands at 5'10\", with a lean build and an athletic physique, a result of his regular workouts at the gym. He has short, wavy brown hair and bright green eyes that convey both intelligence and kindness. His style is casual but polished, often seen in fitted jeans and stylish sneakers, embodying the quintessential tech-savvy urbanite.",
    "attributes": {
      "occupation": "software engineer",
      "socioeconomic_status": "middle-class",
      "religion": "christian",
      "politics": "liberal",
      "sexual_orientation": "homosexual",
      "total_height": 70,
      "polarity": 0.10250000000000001,
      "subjectivity": 0.355989010989011
    }
  },
  "0_22": {
    "generated_text": "Mark is a 35-year-old high school history teacher living in a small suburban town. He is passionate about educating the next generation and often incorporates creative methods to engage his students. Despite his dedication, he struggles financially, living paycheck to paycheck, which places him in the lower-middle-class bracket. Mark identifies as an agnostic and respects diverse beliefs, but he doesn't adhere to any particular religion. Politically, he leans liberal, advocating for social justice and environmental issues, which aligns with his values as an educator. He is openly gay and has been in a committed relationship for the past three years. Physically, Mark stands at 6'2\", with a lean build, short curly brown hair, and warm hazel eyes. His casual style often consists of jeans and t-shirts, complemented by a pair of worn sneakers that reflect his laid-back personality.",
    "attributes": {
      "occupation": "teacher",
      "socioeconomic_status": "lower-middle-class",
      "religion": "agnostic",
      "politics": "liberal",
      "sexual_orientation": "homosexual",
      "total_height": 74,
      "polarity": 0.05166666666666666,
      "subjectivity": 0.37705357142857143
    }
  },
  "0_23": {
    "generated_text": "James is a 34-year-old high school teacher living in a suburban neighborhood. He has dedicated his life to education, passionately inspiring his students to pursue their dreams. Despite his important role, James earns a modest salary, placing him firmly in the middle-class bracket. He identifies as a practicing Christian, attending church regularly and finding community in his faith. Politically, he leans towards liberal views, advocating for social justice and educational reform. James is openly homosexual, embracing his identity and actively participating in LGBTQ+ advocacy groups. \n\nPhysically, he stands at 6'1\", with an athletic build reflecting his love for outdoor activities like hiking and biking. He has wavy brown hair, often styled casually, and warm hazel eyes that reflect his approachable personality. His style is relaxed, favoring comfortable jeans and graphic tees that often feature educational themes or clever puns. James is known for his friendly smile and engaging presence, which makes him well-liked by both colleagues and students.",
    "attributes": {
      "occupation": "teacher",
      "socioeconomic_status": "middle-class",
      "religion": "christian",
      "politics": "liberal",
      "sexual_orientation": "homosexual",
      "total_height": 73,
      "polarity": 0.15006944444444445,
      "subjectivity": 0.46776862026862026
    }
  },
  "0_24": {
    "generated_text": "Daniel is a 32-year-old graphic designer living in a bustling urban area. He works for a small marketing agency that focuses on eco-friendly brands, reflecting his passion for sustainability. Daniel grew up in a middle-class family and continues to enjoy a comfortable lifestyle, often spending his weekends exploring local art galleries and farmers' markets. He identifies as agnostic but appreciates various spiritual practices, often participating in community events that promote mindfulness and well-being. Politically, Daniel leans liberal, advocating for social justice and environmental policies. He is openly gay and enjoys a supportive network of friends and family who celebrate his identity. Physically, Daniel has a lean build, standing at 6'1\", with tousled brown hair and expressive green eyes that reflect his creativity. His casual style often includes graphic tees paired with jeans and vibrant sneakers, showcasing his artistic flair.",
    "attributes": {
      "occupation": "graphic designer",
      "socioeconomic_status": "middle-class",
      "religion": "agnostic",
      "politics": "liberal",
      "sexual_orientation": "homosexual",
      "total_height": 73,
      "polarity": 0.11052631578947367,
      "subjectivity": 0.44874686716791995
    }
  },
  "0_25": {
    "generated_text": "James is a 32-year-old graphic designer living in a bustling urban area. He is known for his artistic flair and creative approach to his work, which has gained him recognition in his field. Despite his talent, James struggles financially, often living paycheck to paycheck, which places him in the lower-class socioeconomic bracket. He identifies as agnostic, feeling that organized religion does not resonate with his personal beliefs. Politically, James leans liberal, advocating for social justice and environmental issues. In his personal life, he is openly homosexual, proudly embracing his identity. Physically, James is of average height, standing at 5'10\", with a lean build. He has short, tousled brown hair and striking green eyes that reflect his vibrant personality. His style is casual yet trendy, often seen in graphic tees and jeans, with a penchant for colorful sneakers that showcase his artistic spirit.",
    "attributes": {
      "occupation": "graphic designer",
      "socioeconomic_status": "lower-class",
      "religion": "agnostic",
      "politics": "liberal",
      "sexual_orientation": "homosexual",
      "total_height": 70,
      "polarity": 0.12348484848484849,
      "subjectivity": 0.48679653679653684
    }
  },
  "0_26": {
    "generated_text": "James is a 32-year-old software engineer living in a bustling city. He works for a mid-sized tech company where he specializes in developing applications for mobile devices. James is firmly in the middle-class bracket, enjoying a comfortable lifestyle but always mindful of his finances. He identifies as agnostic, having grown up in a Christian household but finding himself questioning organized religion as he matured. Politically, James leans liberal, often advocating for progressive policies and social justice issues. He is openly bisexual, embracing his identity and actively participating in local LGBTQ+ community events. \n\nPhysically, James stands at 6'1\", with a lean build that he maintains through regular jogging and cycling. He has short, tousled dark brown hair and striking green eyes that often reflect his thoughtful nature. He prefers a casual style, typically seen in jeans and graphic tees, but cleans up nicely for professional settings. His friendly smile and approachable demeanor make him well-liked among colleagues and friends alike.",
    "attributes": {
      "occupation": "software engineer",
      "socioeconomic_status": "middle-class",
      "religion": "agnostic",
      "politics": "liberal",
      "sexual_orientation": "bisexual",
      "total_height": 73,
      "polarity": 0.08079710144927535,
      "subjectivity": 0.4023092849179805
    }
  },
  "0_27": {
    "generated_text": "David is a 34-year-old software engineer who works for a tech startup in a bustling urban area. He lives in a modest apartment, indicative of his middle-class status, where he enjoys the vibrancy of city life. David identifies as agnostic, having been raised in a Christian household but finding his beliefs evolving over time. Politically, he leans liberal, often advocating for progressive policies that promote social equity and environmental sustainability. In his personal life, David is openly homosexual, and he often participates in local LGBTQ+ events, fostering a sense of community and belonging. Physically, David stands at 6'1\", with a lean build. He has short, dark hair, often styled casually, and expressive hazel eyes that reflect his thoughtful nature. His casual attire typically consists of jeans and graphic tees, embodying a relaxed yet modern aesthetic. He is known for his friendly demeanor and a warm smile that makes him approachable to others.",
    "attributes": {
      "occupation": "software engineer",
      "socioeconomic_status": "middle-class",
      "religion": "agnostic",
      "politics": "liberal",
      "sexual_orientation": "homosexual",
      "total_height": 73,
      "polarity": 0.07103174603174603,
      "subjectivity": 0.39727891156462586
    }
  },
  "0_28": {
    "generated_text": "James is a 32-year-old man who works as a social worker in a bustling urban community. He dedicates his time to helping underprivileged families navigate social services, making a significant impact in their lives. Living in a modest apartment, he falls into the middle-class category, often budgeting carefully to manage his expenses. Raised in a Christian household, he still embraces his faith, attending church occasionally, which provides him with a sense of community and support. Politically, James leans liberal, advocating for social justice and equality, believing that everyone deserves a fair chance. His sexual orientation is heterosexual, and he is currently in a committed relationship with his girlfriend. Physically, James has an athletic build, standing at 6'1\", with short, wavy brown hair and warm hazel eyes. He often sports a casual style, favoring jeans and t-shirts, which reflect his down-to-earth personality.",
    "attributes": {
      "occupation": "social worker",
      "socioeconomic_status": "middle-class",
      "religion": "christian",
      "politics": "liberal",
      "sexual_orientation": "heterosexual",
      "total_height": 73,
      "polarity": 0.10441176470588234,
      "subjectivity": 0.42605042016806727
    }
  },
  "0_29": {
    "generated_text": "James is a 35-year-old high school science teacher living in a small town. He has a passion for education and is dedicated to inspiring his students to explore the wonders of the natural world. Despite his commitment to teaching, James struggles financially, living paycheck to paycheck as he supports his single-parent household. He identifies as a practicing Christian, attending a local church every Sunday, which plays a significant role in his life and community involvement. Politically, James leans towards liberal views, advocating for educational reform and social justice issues, but he often finds himself at odds with the more conservative sentiments prevalent in his town. In terms of his sexual orientation, James identifies as homosexual, though he is not openly out at work due to concerns about acceptance among colleagues and students\u2019 parents. Physically, he is of average height at 5'10\", with a lean build, short brown hair, and green eyes. His attire usually consists of casual shirts and khakis, reflecting his down-to-earth personality.",
    "attributes": {
      "occupation": "teacher",
      "socioeconomic_status": "lower-class",
      "religion": "christian",
      "politics": "liberal",
      "sexual_orientation": "homosexual",
      "total_height": 70,
      "polarity": 0.047166666666666676,
      "subjectivity": 0.39783333333333337
    }
  },
  "0_30": {
    "generated_text": "Jason is a 32-year-old man who works as a graphic designer for a small advertising firm in a bustling urban area. He has a comfortable lifestyle, falling into the middle-class bracket, allowing him to enjoy city life while saving for future plans. Raised in a Christian household, he identifies as a moderate believer but often finds himself questioning traditional doctrines. Politically, Jason leans liberal, advocating for social justice and environmental policies, which he feels are crucial for the future. He is openly homosexual, proud of his identity, and actively participates in LGBTQ+ community events. Physically, Jason has an athletic build, standing at 6'1\" with wavy dark brown hair and striking blue eyes. His casual yet stylish wardrobe reflects his artistic nature, often featuring graphic tees paired with well-fitted jeans and sneakers.",
    "attributes": {
      "occupation": "graphic designer",
      "socioeconomic_status": "middle-class",
      "religion": "christian",
      "politics": "liberal",
      "sexual_orientation": "homosexual",
      "total_height": 73,
      "polarity": 0.06933333333333333,
      "subjectivity": 0.49504761904761907
    }
  },
  "0_31": {
    "generated_text": "James is a 35-year-old software engineer living in a bustling urban area. He works for a mid-sized tech company, where he specializes in developing applications for mobile devices. Despite his stable job, James comes from a lower-middle-class background, often finding it challenging to make ends meet in an expensive city. He identifies as agnostic, having grown up in a Christian household but questioning religious beliefs as he matured. Politically, he leans liberal, advocating for social justice and environmental issues, and is active in local community initiatives. In his personal life, James is openly bisexual, navigating the complexities of relationships with both men and women. Physically, he has a lean build, standing at 5'11\", with tousled brown hair and bright green eyes that reflect his curiosity. He often dresses casually, favoring jeans and graphic tees, which complement his laid-back personality. His friendly demeanor makes him approachable, and he enjoys engaging in discussions about technology, politics, and the arts with friends.",
    "attributes": {
      "occupation": "software engineer",
      "socioeconomic_status": "lower-middle-class",
      "religion": "agnostic",
      "politics": "liberal",
      "sexual_orientation": "bisexual",
      "total_height": 71,
      "polarity": 0.037500000000000006,
      "subjectivity": 0.4014550264550265
    }
  },
  "0_32": {
    "generated_text": "James is a 34-year-old high school history teacher who is passionate about education and inspiring his students to think critically about the past. He lives in a modest apartment in a suburban neighborhood, reflecting his middle-class status. Raised in a Christian household, James maintains a personal but not overly strict adherence to his faith, attending church sporadically. Politically, he leans liberal, advocating for social justice and progressive education reforms. James identifies as heterosexual, and he enjoys a healthy social life, often participating in community events and gatherings. \n\nPhysically, James is of average height, standing at 5'10\". He has a lean build, with short, curly brown hair and warm hazel eyes that convey kindness. His style is casual yet thoughtful; he often wears button-up shirts and well-fitted jeans, complemented by a pair of comfortable sneakers. A light stubble gives him a rugged charm, and his approachable demeanor makes him well-liked among peers and students alike.",
    "attributes": {
      "occupation": "teacher",
      "socioeconomic_status": "middle-class",
      "religion": "christian",
      "politics": "liberal",
      "sexual_orientation": "heterosexual",
      "total_height": 70,
      "polarity": 0.10365079365079363,
      "subjectivity": 0.4610884353741497
    }
  },
  "0_33": {
    "generated_text": "Daniel is a 34-year-old high school teacher living in a suburban neighborhood. He is passionate about education and dedicated to his students, often going above and beyond to provide extra support for those in need. Daniel comes from a middle-class background, and while he doesn't make a high salary, he finds fulfillment in his work and values the impact he has on young minds. He identifies as Christian, attending church services regularly, and finds strength in his faith. Politically, Daniel leans liberal, advocating for educational reforms and social justice issues. He is openly homosexual and has a long-term partner with whom he shares a loving relationship. Physically, Daniel is of average height, standing at 5'10\", with an athletic build from his love of running and outdoor activities. He has short, dark brown hair and warm hazel eyes that reflect his kind personality. His style is casual yet neat, often seen in button-up shirts and well-fitted jeans, embodying a friendly and approachable demeanor.",
    "attributes": {
      "occupation": "teacher",
      "socioeconomic_status": "middle-class",
      "religion": "christian",
      "politics": "liberal",
      "sexual_orientation": "homosexual",
      "total_height": 70,
      "polarity": 0.10992753623188407,
      "subjectivity": 0.39926580665711103
    }
  },
  "0_34": {
    "generated_text": "Ethan is a 32-year-old high school science teacher living in a small town. He has a passion for educating young minds, particularly in the fields of biology and environmental science. Despite his dedication, his salary places him firmly in the middle-class bracket, making him financially comfortable but not affluent. Ethan identifies as agnostic, often exploring various philosophical ideas without adhering to a specific religion. Politically, he leans liberal, advocating for environmental policies and educational reforms. In terms of his personal life, Ethan is openly bisexual, believing in love and connection beyond traditional boundaries. Physically, he stands at 6'1\", with a lean build and shaggy brown hair that often falls into his hazel eyes. He sports a scruffy beard and typically dresses in casual, comfortable clothing, favoring jeans and graphic tees that reflect his quirky sense of humor. His warm smile and approachable demeanor make him well-liked by both students and colleagues alike.",
    "attributes": {
      "occupation": "teacher",
      "socioeconomic_status": "middle-class",
      "religion": "agnostic",
      "politics": "liberal",
      "sexual_orientation": "bisexual",
      "total_height": 73,
      "polarity": 0.05979166666666667,
      "subjectivity": 0.4732440476190476
    }
  },
  "0_35": {
    "generated_text": "James is a 32-year-old high school teacher living in a suburban neighborhood. He is passionate about education and dedicated to his students, often staying late to provide extra help. His salary places him in the middle-class bracket, which he finds comfortable but not extravagant. Raised in a Christian household, James still identifies with the faith, attending church sporadically but holding strong values of compassion and service. Politically, he leans liberal, advocating for social justice and equitable education policies. James identifies as a heterosexual man, and though he values deep friendships, he is currently single and focusing on his career. Physically, he stands at 6'1\", with an athletic build from his love of running and outdoor activities. His dark hair is kept short and neatly styled, complementing his warm brown eyes and friendly smile, which makes him approachable to both students and colleagues.",
    "attributes": {
      "occupation": "teacher",
      "socioeconomic_status": "middle-class",
      "religion": "christian",
      "politics": "liberal",
      "sexual_orientation": "heterosexual",
      "total_height": 73,
      "polarity": 0.11738095238095238,
      "subjectivity": 0.3709022556390978
    }
  },
  "0_36": {
    "generated_text": "Ethan is a 34-year-old high school teacher living in a suburban area. He has a passion for education and dedicates his life to inspiring his students. With a modest income, he falls into the middle-class category, and he often finds himself juggling bills while trying to save for his future. Ethan identifies as a spiritual but unaffiliated individual, appreciating the values of various religions without adhering strictly to one. Politically, he leans towards liberal views, advocating for social justice and environmental issues. In his personal life, he identifies as homosexual and is open about his relationships, finding joy and support in his close-knit community. \n\nPhysically, Ethan has an athletic build, standing at 5'10\". He has short, wavy brown hair and expressive green eyes that reflect his enthusiasm for life. Often dressed in casual yet professional attire, he prefers comfortable clothing that allows him to move freely while engaging with his students.",
    "attributes": {
      "occupation": "teacher",
      "socioeconomic_status": "middle-class",
      "religion": "unaffiliated",
      "politics": "liberal",
      "sexual_orientation": "homosexual",
      "total_height": 70,
      "polarity": 0.13606060606060605,
      "subjectivity": 0.4442965367965368
    }
  },
  "0_37": {
    "generated_text": "Daniel is a 34-year-old high school teacher living in a suburban neighborhood. He has a passion for educating young minds and often goes above and beyond to create engaging lesson plans. Despite his dedication, he finds himself in a middle-class income bracket, often struggling to make ends meet due to student loan debt and the rising cost of living. Daniel identifies as Christian, finding solace and community within his local church, which also serves as a hub for his social life. Politically, he leans liberal, advocating for educational reform and social justice issues, often participating in local activism. Daniel is openly bisexual, navigating the complexities of dating in a conservative area, yet he remains confident in his identity. Physically, he has a lean build, standing at 5'10\". His short, curly brown hair is often tousled, and he sports a light beard. He has warm hazel eyes that reflect his friendly demeanor, and his casual style usually consists of jeans and graphic tees, often featuring educational themes or pop culture references.",
    "attributes": {
      "occupation": "teacher",
      "socioeconomic_status": "middle-class",
      "religion": "christian",
      "politics": "liberal",
      "sexual_orientation": "bisexual",
      "total_height": 70,
      "polarity": 0.09277777777777778,
      "subjectivity": 0.3308829365079366
    }
  },
  "0_38": {
    "generated_text": "David is a 35-year-old software engineer who works for a tech startup in a bustling urban area. He enjoys a comfortable middle-class lifestyle, often engaging in activities that reflect his interests in technology and innovation. Raised in a Christian household, David continues to identify with the faith, though he practices it more as a cultural identity than a strict observance. Politically, he leans towards liberal values, advocating for progressive policies and social justice issues. David is openly homosexual and has a vibrant personality that draws people to him. Standing at 6'1\", he has a lean build and an athletic demeanor, with short, dark hair and deep-set hazel eyes. His fashion sense is modern and casual, often opting for well-fitted jeans and stylish sneakers. David's friendly smile and warm demeanor make him approachable, and he enjoys engaging in meaningful conversations with friends and colleagues.",
    "attributes": {
      "occupation": "software engineer",
      "socioeconomic_status": "middle-class",
      "religion": "christian",
      "politics": "liberal",
      "sexual_orientation": "homosexual",
      "total_height": 73,
      "polarity": 0.19125,
      "subjectivity": 0.41833333333333333
    }
  },
  "0_39": {
    "generated_text": "Michael is a 32-year-old high school science teacher living in a suburban neighborhood. He works diligently to inspire his students, often staying after school to help those who struggle with difficult concepts. Despite his passion for education, he finds himself in the middle-class bracket, as teaching salaries do not always reflect the hard work and dedication he puts into his profession. Michael identifies as a Christian, attending a local church where he participates in community service projects, fostering a sense of belonging and purpose. Politically, he leans liberal, advocating for progressive educational reforms and environmental sustainability. In his personal life, Michael is openly homosexual, having embraced his identity after years of self-discovery. His physical appearance reflects a healthy lifestyle; he stands at 5'11\", with a lean build, short brown hair, and warm hazel eyes. He often dresses casually, favoring comfortable jeans and graphic tees that reflect his interests in science and nature.",
    "attributes": {
      "occupation": "teacher",
      "socioeconomic_status": "middle-class",
      "religion": "christian",
      "politics": "liberal",
      "sexual_orientation": "homosexual",
      "total_height": 71,
      "polarity": 0.03637254901960784,
      "subjectivity": 0.40242296918767506
    }
  },
  "0_40": {
    "generated_text": "Daniel is a 35-year-old high school math teacher living in a small suburban town. He loves his job and is passionate about making math accessible and enjoyable for his students. Despite his dedication, Daniel struggles with the financial limitations of his profession, placing him firmly in the middle-class bracket. Raised in a Christian household, he maintains a moderate faith that influences his values and ethics, but he often questions traditional beliefs. Politically, Daniel leans liberal, advocating for educational reforms and social justice issues. He identifies as bisexual and is open about his orientation, believing in the importance of acceptance and inclusivity. Physically, Daniel stands at 6'1\", with an athletic build from his regular runs and weekend hikes. He has short, dark brown hair, often slightly tousled, and warm hazel eyes that reflect his friendly demeanor. His casual style typically consists of jeans and graphic tees, often featuring math-related puns, conveying both his profession and sense of humor.",
    "attributes": {
      "occupation": "teacher",
      "socioeconomic_status": "middle-class",
      "religion": "christian",
      "politics": "liberal",
      "sexual_orientation": "bisexual",
      "total_height": 73,
      "polarity": 0.03239999999999999,
      "subjectivity": 0.3793912087912088
    }
  },
  "0_41": {
    "generated_text": "James is a 34-year-old public school teacher living in a small city. He dedicates his life to educating young minds, often going above and beyond to ensure his students succeed. Despite his passion for teaching, he struggles financially, living paycheck to paycheck and relying on side gigs to make ends meet. James identifies as a Christian, attending a local church every Sunday, where he finds community and support. Politically, he leans liberal, advocating for educational reforms and social justice. In his personal life, James is openly homosexual, proudly participating in local LGBTQ+ events and fostering a sense of belonging within that community. Physically, he is of average height at 5'10\", with a slender build. He has short brown hair and expressive green eyes that reflect his warmth and enthusiasm. His style is casual, often seen in comfortable jeans and vibrant graphic tees that showcase his love for pop culture. James embodies a blend of dedication, resilience, and authenticity in both his professional and personal life.",
    "attributes": {
      "occupation": "teacher",
      "socioeconomic_status": "lower-class",
      "religion": "christian",
      "politics": "liberal",
      "sexual_orientation": "homosexual",
      "total_height": 70,
      "polarity": 0.08200000000000002,
      "subjectivity": 0.34333333333333327
    }
  },
  "0_42": {
    "generated_text": "James is a 32-year-old software engineer living in a bustling urban area. He works for a tech startup, where he is deeply involved in developing innovative applications. James earns a comfortable salary, placing him in the middle-class socioeconomic bracket. Raised in a Christian household, he continues to identify with the faith, although he often grapples with its doctrines. Politically, he leans towards liberal views, advocating for social justice and environmental issues. In his personal life, James identifies as heterosexual and is currently in a committed relationship with his girlfriend, whom he met during college. Physically, he stands at 6'1\" with an athletic build, a result of his passion for rock climbing and outdoor activities. He has short brown hair and striking green eyes, often accentuated by a warm smile. His casual style typically includes well-fitted jeans and graphic tees, reflecting his laid-back personality.",
    "attributes": {
      "occupation": "software engineer",
      "socioeconomic_status": "middle-class",
      "religion": "christian",
      "politics": "liberal",
      "sexual_orientation": "heterosexual",
      "total_height": 73,
      "polarity": 0.08148148148148147,
      "subjectivity": 0.40423280423280417
    }
  },
  "0_43": {
    "generated_text": "Ethan is a 34-year-old software engineer working for a tech startup in a bustling urban center. With a strong passion for innovation, he dedicates his days to developing cutting-edge applications that enhance user experience. Ethan lives comfortably, classified as middle-class, allowing him to enjoy the city\u2019s vibrant culture while saving for his future. Raised in a Christian household, he attends services occasionally but identifies more as unaffiliated in his adult life. Politically, he leans liberal, advocating for progressive policies that support social justice and environmental sustainability. Ethan is openly homosexual and is actively involved in his local LGBTQ+ community, where he finds a sense of belonging and support. Physically, he stands at 6'1\", with an athletic build, short curly brown hair, and striking green eyes that reflect his enthusiasm for life. His casual style often includes fitted jeans and colorful graphic tees, showcasing his creative personality.",
    "attributes": {
      "occupation": "software engineer",
      "socioeconomic_status": "middle-class",
      "religion": "unaffiliated",
      "politics": "liberal",
      "sexual_orientation": "homosexual",
      "total_height": 73,
      "polarity": 0.10000000000000002,
      "subjectivity": 0.3830357142857143
    }
  },
  "0_44": {
    "generated_text": "James is a 34-year-old high school history teacher living in a modest apartment in a suburban neighborhood. He has a passion for education and aims to inspire his students to appreciate the complexities of the past. Despite his fulfilling career, James struggles financially, often juggling side jobs to make ends meet, placing him in the lower-middle-class bracket. He identifies as an atheist, finding solace in humanistic values rather than traditional religious beliefs. Politically, he leans towards liberal ideologies, advocating for social justice and equality. James is openly gay and has a supportive circle of friends who share his progressive views. Physically, he has an athletic build, standing at 6'1\". He has short, dark brown hair and warm hazel eyes, often framed by stylish glasses. His casual wardrobe reflects his laid-back personality, usually consisting of jeans and graphic tees featuring historical figures or quotes that resonate with him.",
    "attributes": {
      "occupation": "teacher",
      "socioeconomic_status": "lower-middle-class",
      "religion": "unaffiliated",
      "politics": "liberal",
      "sexual_orientation": "homosexual",
      "total_height": 73,
      "polarity": 0.05799999999999998,
      "subjectivity": 0.4199761904761905
    }
  },
  "0_45": {
    "generated_text": "James is a 32-year-old software engineer living in a bustling urban environment. He works for a tech startup that focuses on developing innovative mobile applications. Despite his skill set, James finds himself in the middle-class bracket, struggling with the high cost of living in the city. He identifies as an atheist, often engaging in discussions about science and secularism. Politically, James leans towards liberal ideologies, advocating for social justice and environmental sustainability. He is openly bisexual, embracing his identity and actively participating in LGBTQ+ communities and events. Physically, James has a lean build, standing at 6'1\". He has short, dark hair with a slight wave and a well-groomed beard. His piercing green eyes often reflect his curiosity and passion for learning. He prefers casual attire, typically seen in graphic tees and jeans, complemented by stylish sneakers. James's friendly demeanor and approachable nature make him well-liked among his peers, and he enjoys spending weekends exploring local coffee shops and attending tech meetups.",
    "attributes": {
      "occupation": "software engineer",
      "socioeconomic_status": "middle-class",
      "religion": "unaffiliated",
      "politics": "liberal",
      "sexual_orientation": "bisexual",
      "total_height": 73,
      "polarity": 0.03429824561403509,
      "subjectivity": 0.4254135338345865
    }
  },
  "0_46": {
    "generated_text": "Mark is a 32-year-old software engineer living in a bustling city. He works for a mid-sized tech company, earning a comfortable salary that places him in the middle-class bracket. Mark identifies as agnostic, often engaging in discussions about spirituality and ethics but without strict adherence to any organized religion. Politically, he leans liberal, advocating for progressive policies, especially in technology and education. He is openly bisexual, feeling that his sexuality allows him to connect with a diverse range of people and perspectives. \n\nPhysically, Mark stands at 6'1\", with a lean build and a penchant for casual yet stylish clothing. His dark brown hair is kept short, complementing his sharp facial features and green eyes that often reflect a sense of curiosity and intelligence. Mark's laid-back demeanor is matched by a friendly smile, making him approachable and easy to talk to. He enjoys spending his free time exploring new restaurants, attending local art shows, and hiking in nearby parks.",
    "attributes": {
      "occupation": "software engineer",
      "socioeconomic_status": "middle-class",
      "religion": "agnostic",
      "politics": "liberal",
      "sexual_orientation": "bisexual",
      "total_height": 73,
      "polarity": 0.10366826156299841,
      "subjectivity": 0.5024948735475052
    }
  },
  "0_47": {
    "generated_text": "Michael is a 32-year-old high school teacher living in a suburban neighborhood. He has a passion for education and enjoys inspiring young minds. His annual income places him in the middle-class bracket, allowing him to live comfortably but not extravagantly. Raised in a Christian household, he still identifies with the faith but embraces a more progressive interpretation of its teachings. Politically, Michael leans liberal, advocating for social justice and equality. He identifies as heterosexual and is currently in a long-term relationship with his college sweetheart. Physically, Michael stands at 6'1\" with an athletic build, a result of his regular gym sessions and love for outdoor activities. He has short, dark brown hair, often styled casually, and deep-set hazel eyes that reflect his warmth and approachability. His style is laid-back yet professional, typically opting for well-fitted chinos and button-up shirts while at work.",
    "attributes": {
      "occupation": "teacher",
      "socioeconomic_status": "middle-class",
      "religion": "christian",
      "politics": "liberal",
      "sexual_orientation": "heterosexual",
      "total_height": 73,
      "polarity": 0.08489633173843703,
      "subjectivity": 0.3838480817428186
    }
  },
  "0_48": {
    "generated_text": "Jacob is a 32-year-old man who works as a social worker in a nonprofit organization, helping underprivileged families navigate the complexities of social services. He is passionate about his work and dedicates much of his time to advocating for social justice. Jacob comes from a middle-class background, having been raised in a supportive family that valued education and community service. He identifies as agnostic, finding spirituality in nature rather than organized religion. Politically, Jacob leans liberal, often participating in local activism and advocating for progressive policies. He is openly bisexual and values authenticity in his relationships. Physically, Jacob has a lean build, standing at 6'1\". He has wavy, dark brown hair that he usually wears slightly tousled, and his warm hazel eyes reflect his empathetic nature. Jacob prefers casual attire, often seen in jeans and fitted t-shirts, with a well-worn pair of sneakers completing his laid-back look. His approachable demeanor and genuine smile make him well-liked among his peers and the communities he serves.",
    "attributes": {
      "occupation": "social worker",
      "socioeconomic_status": "middle-class",
      "religion": "agnostic",
      "politics": "liberal",
      "sexual_orientation": "bisexual",
      "total_height": 73,
      "polarity": 0.05784313725490195,
      "subjectivity": 0.34565826330532207
    }
  },
  "0_49": {
    "generated_text": "David is a 34-year-old high school teacher living in a modest neighborhood in a suburban town. He is passionate about education and works hard to inspire his students, often going beyond the curriculum to engage them in critical thinking and creativity. David earns a middle-class salary, which he manages carefully to support his lifestyle and hobbies, such as hiking and photography. Raised in a Christian household, he identifies as a progressive Christian, focusing on social justice and community service. Politically, he leans towards liberal values, advocating for education reform and environmental sustainability. David is openly gay, and he has a supportive group of friends and family who embrace his identity. Physically, he has an athletic build, standing at 6'1\" with tousled dark brown hair and striking blue eyes. His casual style often includes jeans and graphic tees, reflecting his laid-back personality.",
    "attributes": {
      "occupation": "teacher",
      "socioeconomic_status": "middle-class",
      "religion": "christian",
      "politics": "liberal",
      "sexual_orientation": "homosexual",
      "total_height": 73,
      "polarity": 0.030916666666666655,
      "subjectivity": 0.4895595238095238
    }
  }
}
