{"17_0": {"generated_text": "Sophia is a 32-year-old Millennial woman living in a vibrant urban neighborhood. She works as a digital marketing manager for a tech startup, where she thrives in a fast-paced, creative environment. With a degree in communications and several years of experience, Sophia is well-respected in her field. She enjoys a middle-class lifestyle, balancing her career with freelance projects on the side. Raised in a secular household, she identifies as unaffiliated but appreciates various spiritual practices and philosophies.\n\nPolitically, Sophia leans liberal, advocating for social justice and environmental sustainability. She actively participates in community activism and supports progressive candidates. In her personal life, Sophia is openly bisexual, navigating her relationships with a sense of authenticity and confidence. \n\nPhysically, she has a unique style that reflects her personality; she stands at 5'6\", has shoulder-length wavy auburn hair, and often sports vintage clothing paired with contemporary accessories. Her expressive hazel eyes and warm smile draw people in, and she exudes an approachable charm that makes her friends and colleagues feel comfortable around her.", "attributes": {"occupation": "digital marketing manager", "socioeconomic_status": "middle-class", "religion": "unaffiliated", "politics": "liberal", "sexual_orientation": "bisexual", "total_height": 66, "polarity": 0.16885964912280702, "subjectivity": 0.3864661654135338}}, "17_1": {"generated_text": "Jessica is a 32-year-old Millennial woman living in a bustling urban area. She works as a digital marketing specialist for a tech startup, where she focuses on social media strategy and content creation. Her job provides her with a comfortable middle-class income, allowing her to enjoy a modest lifestyle, including renting a trendy apartment and dining out occasionally with friends. Raised in a secular household, Jessica identifies as unaffiliated but appreciates the cultural aspects of various religions. Politically, she leans liberal, advocating for social justice and environmental issues, and actively participates in community initiatives. Jessica is openly bisexual and values inclusivity and diversity in her personal and professional life. She has an athletic build, standing at 5'7\", with shoulder-length wavy brown hair and expressive hazel eyes. Her style is casual yet fashionable, often sporting vintage clothing and accessorizing with unique jewelry pieces that reflect her creative personality. With a passion for travel, she often shares her adventures on social media, connecting with like-minded individuals and fostering a sense of community among her followers.", "attributes": {"occupation": "digital marketing specialist", "socioeconomic_status": "middle-class", "religion": "unaffiliated", "politics": "liberal", "sexual_orientation": "bisexual", "total_height": 67, "polarity": 0.13531746031746034, "subjectivity": 0.45198412698412693}}, "17_2": {"generated_text": "Emily is a 32-year-old graphic designer living in a vibrant urban area. She works for a mid-sized marketing agency, where she specializes in creating visually appealing content for social media campaigns. Emily identifies as middle-class, having a stable income that allows her to afford a modest apartment and enjoy a comfortable lifestyle, though she often feels the pressures of student loan debt. Raised in a Christian household, she now identifies as unaffiliated with any particular religion, choosing instead to explore spirituality on her own terms. Politically, Emily leans liberal, actively participating in community initiatives and advocating for social justice issues. As a proud member of the LGBTQ+ community, she identifies as bisexual and is open about her relationships. Physically, Emily has an artistic flair reflected in her style; she has shoulder-length, wavy brown hair, expressive hazel eyes, and often wears colorful, vintage-inspired clothing that showcases her creativity. Her casual yet chic appearance often turns heads, and her confident demeanor allows her to navigate both her professional and social circles with ease.", "attributes": {"occupation": "graphic designer", "socioeconomic_status": "middle-class", "religion": "unaffiliated", "politics": "liberal", "sexual_orientation": "bisexual", "total_height": 66, "polarity": 0.19305555555555554, "subjectivity": 0.47956349206349214}}, "17_3": {"generated_text": "Sophia is a 32-year-old Millennial woman living in a vibrant urban area. She works as a digital marketing specialist for a tech startup, where she focuses on social media strategy and content creation. Sophia enjoys a middle-class lifestyle, which allows her to afford a modest apartment and participate in various cultural activities. Raised in a secular household, she identifies as unaffiliated with any religion but respects diverse beliefs. Politically, she leans liberal, advocating for social justice and environmental issues, often volunteering for local community initiatives. Sophia is openly bisexual and values inclusivity in her personal and professional life. With long, wavy chestnut hair and striking green eyes, she stands at 5'6\". Her style is a mix of casual and trendy, often incorporating vintage pieces that reflect her unique personality. Sophia embodies the essence of her generation\u2014tech-savvy, socially conscious, and committed to making a positive impact in her community.", "attributes": {"occupation": "digital marketing specialist", "socioeconomic_status": "middle-class", "religion": "unaffiliated", "politics": "liberal", "sexual_orientation": "bisexual", "total_height": 66, "polarity": 0.0755050505050505, "subjectivity": 0.40375180375180375}}, "17_4": {"generated_text": "Jessica is a 32-year-old marketing manager living in a vibrant urban area. With a bachelor's degree in communications, she has climbed the corporate ladder in a mid-sized tech firm. Jessica is middle-class, enjoying a comfortable lifestyle that allows her to travel and indulge in her love for art and fashion. Raised in a progressive household, she identifies as unaffiliated with any particular religion, valuing personal spirituality over organized doctrine. Politically, she leans liberal, advocating for social justice, environmental sustainability, and inclusivity. Jessica is openly bisexual and actively participates in LGBTQ+ community events, fostering a supportive network of friends and allies. \n\nPhysically, she has an athletic build, standing at 5'6\". Her style is a blend of professional and trendy, often seen in chic blouses paired with tailored pants and stylish sneakers. She has shoulder-length, wavy chestnut hair and expressive hazel eyes that reflect her passion for life. Jessica\u2019s vibrant personality draws people to her, making her a beloved figure among her peers.", "attributes": {"occupation": "marketing manager", "socioeconomic_status": "middle-class", "religion": "unaffiliated", "politics": "liberal", "sexual_orientation": "bisexual", "total_height": 66, "polarity": 0.2285714285714286, "subjectivity": 0.48140589569161}}, "17_5": {"generated_text": "Sophia is a 30-year-old Millennial woman living in a vibrant urban environment. She works as a digital marketing specialist at a tech startup, where she thrives on creativity and innovation. Earning a moderate salary, she comfortably falls into the middle-class category, enjoying a lifestyle that allows for occasional travel and dining out with friends. Raised in a Christian household, Sophia identifies as unaffiliated with any specific denomination, favoring a more personal, spiritual approach to her beliefs. Politically, she leans liberal, advocating for social justice and environmental sustainability. Sophia identifies as bisexual, embracing love and connection in various forms. With a unique sense of style, she has an eclectic wardrobe that reflects her artistic personality. Standing at 5'6\", she has long, wavy dark brown hair, expressive hazel eyes, and a warm smile. Sophia's appearance is complemented by a few tattoos that symbolize her life experiences and values, and she often wears vintage accessories that showcase her individuality.", "attributes": {"occupation": "digital marketing specialist", "socioeconomic_status": "middle-class", "religion": "unaffiliated", "politics": "liberal", "sexual_orientation": "bisexual", "total_height": 66, "polarity": 0.17118055555555556, "subjectivity": 0.3951388888888889}}, "17_6": {"generated_text": "Jessica is a 32-year-old woman living in a bustling urban environment. She works as a digital marketing specialist at a mid-sized tech company, where she thrives in a creative and collaborative atmosphere. With a salary that places her comfortably in the middle class, she enjoys a modest yet fulfilling lifestyle, often sharing her experiences on social media. Jessica identifies as agnostic, finding meaning in personal experiences rather than traditional religious practices. Politically, she leans liberal, actively participating in community initiatives and advocating for social justice causes. In her personal life, she identifies as bisexual, embracing love in all its forms. \n\nPhysically, Jessica has an athletic build, standing at 5'6\". She has long, wavy dark hair that she often styles in a messy bun, and her expressive hazel eyes reflect her vibrant personality. Her fashion sense is casual yet trendy, favoring sustainable brands and comfortable, stylish clothing that allows her to move freely throughout her busy day.", "attributes": {"occupation": "digital marketing specialist", "socioeconomic_status": "middle-class", "religion": "agnostic", "politics": "liberal", "sexual_orientation": "bisexual", "total_height": 66, "polarity": 0.12962962962962965, "subjectivity": 0.48430335097001775}}, "17_7": {"generated_text": "Samantha is a 29-year-old Millennial woman living in a vibrant urban neighborhood. She works as a digital marketing specialist for a tech startup, a role that allows her to express her creativity and passion for social media. With a steady income, she enjoys a middle-class lifestyle, balancing her career ambitions with her love for travel and exploration. Samantha identifies as agnostic, finding spirituality in nature rather than organized religion, and this perspective often shapes her worldview. Politically, she leans liberal, advocating for social justice and environmental issues, frequently participating in local activism. In her personal life, Samantha identifies as bisexual, embracing a fluid approach to relationships and love. Physically, she has an athletic build, standing at 5'6\", with long, wavy brown hair and expressive hazel eyes. Her style is a blend of casual and chic, often sporting vintage finds paired with modern accessories. Samantha embodies the Millennial spirit, navigating the complexities of her identity while striving to make a positive impact in her community.", "attributes": {"occupation": "digital marketing specialist", "socioeconomic_status": "middle-class", "religion": "agnostic", "politics": "liberal", "sexual_orientation": "bisexual", "total_height": 66, "polarity": 0.11459330143540669, "subjectivity": 0.3274550011392117}}, "17_8": {"generated_text": "Samantha is a 29-year-old Millennial woman living in a bustling urban environment. She works as a graphic designer for a tech startup, where she thrives in a creative and collaborative atmosphere. Earning a comfortable salary, she falls into the middle-class category, allowing her to enjoy a decent lifestyle while still budgeting for student loans from her art degree. Samantha identifies as unaffiliated with any particular religion, having grown up in a household that valued personal beliefs over organized faith. Politically, she leans liberal, advocating for social justice and environmental sustainability, which aligns with her values of inclusivity and progress. In her personal life, Samantha is bisexual, embracing her identity with pride and openness. \n\nPhysically, she has an athletic build, standing at 5'6\". Her long, wavy brown hair often cascades over her shoulders, complementing her green eyes. She has a casual yet stylish sense of fashion, frequently opting for comfortable yet trendy outfits that reflect her artistic personality. With a warm smile and an approachable demeanor, Samantha embodies the vibrant spirit of her generation.", "attributes": {"occupation": "graphic designer", "socioeconomic_status": "middle-class", "religion": "unaffiliated", "politics": "liberal", "sexual_orientation": "bisexual", "total_height": 66, "polarity": 0.17028985507246377, "subjectivity": 0.48737060041407865}}, "17_9": {"generated_text": "Jessica is a 32-year-old Millennial woman living in a vibrant urban neighborhood. She works as a digital marketing specialist for a tech startup, where she utilizes her creativity and analytical skills to drive online engagement. With a steady income, Jessica is comfortably situated in the middle class, enjoying a lifestyle that includes dining out, traveling, and attending cultural events. Raised in a secular household, she identifies as unaffiliated with any religion, although she appreciates the values of various spiritual traditions. Politically, she leans liberal, advocating for social justice and environmental sustainability. Jessica is openly bisexual and believes in the importance of inclusivity and representation. Physically, she has an athletic build, standing at 5'6\", with shoulder-length dark brown hair and expressive hazel eyes. She often expresses her individuality through her fashion choices, favoring a blend of vintage pieces and modern trends that showcase her unique style.", "attributes": {"occupation": "digital marketing specialist", "socioeconomic_status": "middle-class", "religion": "unaffiliated", "politics": "liberal", "sexual_orientation": "bisexual", "total_height": 66, "polarity": 0.14398148148148152, "subjectivity": 0.35978835978835977}}, "17_10": {"generated_text": "Samantha is a 32-year-old Millennial woman living in a bustling urban environment. She works as a digital marketing manager for a tech startup, leveraging her creativity and analytical skills to help businesses thrive online. Samantha earns a comfortable salary, placing her in the middle-class socioeconomic bracket, allowing her to enjoy a modest apartment and occasional travel. Raised in a secular household, she identifies as unaffiliated with any religion, although she respects diverse beliefs. Politically, she leans liberal, advocating for social justice and environmental sustainability. Samantha is openly bisexual, embracing her identity in a community that values inclusivity. Physically, she has a medium build, standing at 5'6\", with shoulder-length wavy brown hair and expressive green eyes. Her style is casual yet trendy, often mixing vintage pieces with contemporary fashion, reflecting her unique personality and love for self-expression. Her passion for social causes and commitment to her career make her a dynamic individual, embodying the values and challenges faced by many of her generation.", "attributes": {"occupation": "digital marketing manager", "socioeconomic_status": "middle-class", "religion": "unaffiliated", "politics": "liberal", "sexual_orientation": "bisexual", "total_height": 66, "polarity": 0.15277777777777776, "subjectivity": 0.43339002267573695}}, "17_11": {"generated_text": "Emily is a 30-year-old Millennial woman who works as a digital marketing specialist for a tech startup in a bustling urban area. She enjoys a middle-class lifestyle, living in a shared apartment with friends to keep expenses down. Raised in a secular household, she identifies as unaffiliated with any particular religion, embracing a more spiritual outlook on life. Politically, she leans liberal, advocating for progressive causes and environmental sustainability. In her personal life, Emily identifies as bisexual, actively participating in LGBTQ+ advocacy groups. \n\nPhysically, she has an athletic build, standing at 5'6\". She has shoulder-length wavy brown hair, often dyed with vibrant streaks of color that reflect her artistic personality. Her fashion sense is eclectic and expressive, favoring vintage finds and sustainable brands. With warm hazel eyes and a radiant smile, Emily embodies a modern woman who balances her professional ambitions with a commitment to social justice and community involvement.", "attributes": {"occupation": "digital marketing specialist", "socioeconomic_status": "middle-class", "religion": "unaffiliated", "politics": "liberal", "sexual_orientation": "bisexual", "total_height": 66, "polarity": 0.1617283950617284, "subjectivity": 0.32768959435626094}}, "17_12": {"generated_text": "Emily is a 30-year-old Millennial woman who works as a digital marketing specialist at a mid-sized tech company in a bustling urban area. She enjoys a comfortable middle-class lifestyle, often exploring the latest trends in fashion and technology. Raised in a secular household, Emily identifies as unaffiliated with any religion, embracing a more spiritual but non-dogmatic approach to life. Politically, she aligns herself with liberal ideologies, advocating for social justice and environmental sustainability. As a proud member of the LGBTQ+ community, she identifies as bisexual and actively participates in pride events and discussions surrounding equality. Emily has an expressive sense of style, often sporting vibrant hair colors and eclectic outfits that reflect her creative personality. Standing at 5'6\", she has an athletic build, a warm smile, and expressive hazel eyes that convey her passion for life. Her social media presence showcases her love for travel, art, and culinary adventures, making her an influential figure among her peers.", "attributes": {"occupation": "digital marketing specialist", "socioeconomic_status": "middle-class", "religion": "unaffiliated", "politics": "liberal", "sexual_orientation": "bisexual", "total_height": 66, "polarity": 0.30526315789473685, "subjectivity": 0.46315789473684205}}, "17_13": {"generated_text": "Jessica is a 32-year-old woman living in a vibrant urban area, working as a digital marketing specialist for a tech startup. She holds a bachelor\u2019s degree in communications and enjoys a middle-class lifestyle, renting a small apartment with her partner. Jessica identifies as agnostic, reflecting a shift away from traditional religious practices, and she often engages in discussions about spirituality and personal beliefs. Politically, she leans liberal, advocating for social justice issues, environmental sustainability, and equal rights. Jessica is openly bisexual, actively participating in LGBTQ+ communities and events, promoting inclusivity and representation. With a sense of style that reflects her creative profession, she has shoulder-length wavy brown hair, often dyed in vibrant colors. Her fashion choices are eclectic, featuring vintage finds mixed with contemporary pieces, and she embraces a natural look with minimal makeup. Jessica stands at 5'6\", with a slender build, and her expressive green eyes often light up when she discusses her passions or connects with others over shared interests.", "attributes": {"occupation": "digital marketing specialist", "socioeconomic_status": "middle-class", "religion": "agnostic", "politics": "liberal", "sexual_orientation": "bisexual", "total_height": 66, "polarity": 0.07857142857142857, "subjectivity": 0.3952380952380953}}, "17_14": {"generated_text": "Emily is a 32-year-old Millennial woman who works as a digital marketing specialist for a tech startup in a bustling city. She is passionate about her career, constantly learning new trends in social media and online advertising. With a stable income, she enjoys a middle-class lifestyle, renting a cozy apartment with her partner in a vibrant neighborhood. Emily identifies as agnostic, having grown up in a Christian household but finding her beliefs evolving over time. Politically, she leans liberal, advocating for social justice and environmental sustainability. As a bisexual woman, she embraces her identity and actively supports LGBTQ+ rights. \n\nPhysically, Emily has a unique style that reflects her personality; she has shoulder-length, wavy brown hair and expressive hazel eyes. Her wardrobe consists of a mix of vintage and contemporary pieces, often accessorized with handmade jewelry. Standing at 5'5\", she carries herself with confidence, often sporting a bright smile that reflects her optimistic outlook on life.", "attributes": {"occupation": "digital marketing specialist", "socioeconomic_status": "middle-class", "religion": "agnostic", "politics": "liberal", "sexual_orientation": "bisexual", "total_height": 65, "polarity": 0.13694295900178255, "subjectivity": 0.397886427298192}}, "17_15": {"generated_text": "Samantha is a 30-year-old Millennial female living in a vibrant urban area. She works as a digital marketing specialist for a tech startup, where she navigates the fast-paced world of social media and online advertising. Samantha is passionate about her work and enjoys the creative aspects of her job, often collaborating with diverse teams. Coming from a middle-class background, she values financial independence and has a keen interest in sustainable living. While she identifies as agnostic, Samantha respects various beliefs and enjoys exploring different philosophies. Politically, she leans liberal, advocating for social justice and environmental issues. In her personal life, she identifies as bisexual and is in a committed relationship with her girlfriend. Samantha stands at 5'6\", with an athletic build from her love of yoga and hiking. She has shoulder-length, wavy brown hair and often wears trendy outfits that reflect her artistic flair. Her warm hazel eyes and friendly smile make her approachable, and she enjoys meeting new people at local coffee shops and community events.", "attributes": {"occupation": "digital marketing specialist", "socioeconomic_status": "middle-class", "religion": "agnostic", "politics": "liberal", "sexual_orientation": "bisexual", "total_height": 66, "polarity": 0.16800144300144298, "subjectivity": 0.38751803751803754}}, "17_16": {"generated_text": "Sophia is a 29-year-old Millennial female who works as a marketing manager for a tech startup in a bustling urban area. She is passionate about her career, often working long hours, but she balances it with her love for travel and outdoor adventures. Sophia grew up in a middle-class family, and her current socioeconomic status reflects that; she is comfortably middle-class, able to afford a modest apartment and enjoy occasional luxuries. Raised in a secular household, she identifies as unaffiliated with any religion but values spirituality in a broader sense. Politically, Sophia leans liberal, advocating for social justice and environmental issues. She is openly bisexual, proud of her identity and actively supports LGBTQ+ rights. Physically, Sophia has an athletic build, standing at 5'6\" with shoulder-length curly brown hair and warm hazel eyes. Her style is casual yet trendy, often seen in high-waisted jeans and colorful sneakers, reflecting her vibrant personality.", "attributes": {"occupation": "marketing manager", "socioeconomic_status": "middle-class", "religion": "unaffiliated", "politics": "liberal", "sexual_orientation": "bisexual", "total_height": 66, "polarity": 0.16666666666666669, "subjectivity": 0.49437229437229446}}, "17_17": {"generated_text": "Emily is a 29-year-old marketing specialist living in a vibrant urban neighborhood. With a degree in communications, she has carved out a successful career in a mid-sized tech company, where she focuses on social media strategy and brand development. Emily enjoys a comfortable middle-class lifestyle, often dining out with friends and exploring new hobbies. Raised in a Christian household, she identifies as unaffiliated in her adult life, embracing a more spiritual yet non-denominational approach to her beliefs. Politically, she leans liberal, actively participating in local activism and supporting environmental causes. As a proud bisexual woman, Emily is open about her relationships, often attending LGBTQ+ events and advocating for equal rights. Physically, she has a distinctive style; her hair is a vibrant shade of purple, and she stands at 5'6\". With an eclectic fashion sense that combines thrift store finds with trendy pieces, she radiates confidence and creativity, often accessorizing with unique jewelry that reflects her personality.", "attributes": {"occupation": "marketing specialist", "socioeconomic_status": "middle-class", "religion": "unaffiliated", "politics": "liberal", "sexual_orientation": "bisexual", "total_height": 66, "polarity": 0.19736652236652236, "subjectivity": 0.4101937744794888}}, "17_18": {"generated_text": "Emily is a 29-year-old Millennial woman living in a vibrant urban neighborhood. She works as a marketing specialist for a tech startup, where she uses her creativity and digital savvy to help promote innovative products. Emily enjoys a comfortable middle-class lifestyle, allowing her to explore her passions for travel and wellness. Raised in a secular household, she identifies as unaffiliated with any religion, valuing personal spirituality over traditional beliefs. Politically, she leans liberal, advocating for social justice and environmental issues, and often participates in community activism. Emily is openly bisexual, embracing her identity and supporting LGBTQ+ rights. With a striking sense of style, she has shoulder-length brown hair, bright green eyes, and a passion for fashion that reflects her eclectic personality. Standing at 5'6\", she carries herself with confidence, often seen in trendy yet comfortable outfits that blend professionalism with a touch of casual flair.", "attributes": {"occupation": "marketing specialist", "socioeconomic_status": "middle-class", "religion": "unaffiliated", "politics": "liberal", "sexual_orientation": "bisexual", "total_height": 66, "polarity": 0.16764705882352943, "subjectivity": 0.5156862745098039}}, "17_19": {"generated_text": "Sophie is a 32-year-old Millennial woman living in a bustling urban area. She works as a digital marketing specialist for a tech startup, where she thrives in a fast-paced environment that allows her creativity to shine. Sophie enjoys a comfortable middle-class lifestyle, often balancing her career aspirations with her passion for social justice and community service. Raised in a secular household, she identifies as unaffiliated with any religion, though she respects diverse beliefs and often engages in discussions about spirituality and ethics. Politically, Sophie leans liberal, advocating for progressive policies that address climate change and equality. In her personal life, she identifies as bisexual, and she is currently in a loving relationship with her girlfriend, reflecting her open-minded approach to love and partnerships. Physically, Sophie has an athletic build, standing at 5'6\". Her style is a blend of casual and chic, often sporting vintage clothing and bold accessories that express her individuality. With short, wavy brown hair and bright green eyes, she captures attention effortlessly, embodying the spirit of her generation.", "attributes": {"occupation": "digital marketing specialist", "socioeconomic_status": "middle-class", "religion": "unaffiliated", "politics": "liberal", "sexual_orientation": "bisexual", "total_height": 66, "polarity": 0.15111111111111108, "subjectivity": 0.43952380952380954}}, "17_20": {"generated_text": "Jessica is a 32-year-old Millennial woman living in a vibrant urban area. She works as a digital marketing specialist for a tech startup, where she manages social media campaigns and content creation. With a stable income, she comfortably falls into the middle-class category. Raised in a liberal household, she identifies as unaffiliated in terms of religion, often exploring various spiritual practices but not adhering strictly to any one faith. Politically, she aligns with progressive values, actively participating in community activism and advocating for social justice issues. Jessica identifies as bisexual, feeling a strong connection to both men and women, which enriches her social experiences. \n\nPhysically, she stands at 5'6\" with a slender build. Her long, wavy brown hair frames her face, which is adorned with minimal makeup that highlights her natural beauty. She often wears casual yet stylish clothing, favoring vintage shops and sustainable brands. Her warm hazel eyes reflect her approachable personality, and she carries herself with confidence. Jessica embodies the spirit of her generation, balancing ambition with a commitment to inclusivity and authenticity.", "attributes": {"occupation": "digital marketing specialist", "socioeconomic_status": "middle-class", "religion": "unaffiliated", "politics": "liberal", "sexual_orientation": "bisexual", "total_height": 66, "polarity": 0.07982456140350877, "subjectivity": 0.3899749373433584}}, "17_21": {"generated_text": "Sophia is a 29-year-old Millennial woman living in a vibrant urban area. She works as a digital marketing specialist for a tech startup, where her creativity and tech-savvy skills help brands connect with their audience. With a middle-class background, Sophia enjoys a comfortable lifestyle but is conscious of her student loans from her time at university. Raised in a culturally diverse environment, she identifies as spiritual but unaffiliated with any specific religion, embracing a blend of beliefs that resonate with her values. Politically, Sophia leans liberal, actively participating in local activism and advocating for climate change initiatives. Her sexual orientation is bisexual, and she values inclusivity in her personal and professional life. Physically, Sophia has an athletic build, standing at 5'7\", with shoulder-length wavy brown hair and expressive hazel eyes that reflect her passion for life. Her style is a mix of casual and trendy, often seen in high-waisted jeans and colorful blouses, complemented by stylish sneakers that showcase her vibrant personality.", "attributes": {"occupation": "digital marketing specialist", "socioeconomic_status": "middle-class", "religion": "unaffiliated", "politics": "liberal", "sexual_orientation": "bisexual", "total_height": 67, "polarity": 0.1476190476190476, "subjectivity": 0.40799319727891165}}, "17_22": {"generated_text": "Emily is a 30-year-old Millennial woman living in a bustling urban area. She works as a digital marketing specialist for a tech startup, navigating the fast-paced world of social media and online branding. With a stable job, she enjoys a middle-class lifestyle, living in a cozy apartment shared with her partner. Raised in a secular household, she identifies as unaffiliated with any religion, although she values spirituality and mindfulness practices. Politically, Emily leans liberal, advocating for social justice and environmental sustainability, often participating in community activism. As a bisexual woman, she embraces her identity and is open about her experiences in both romantic and platonic relationships. Physically, Emily has shoulder-length wavy brown hair, expressive hazel eyes, and a warm smile. She stands at 5'6\", often dressing in a trendy yet comfortable style that reflects her creative personality.", "attributes": {"occupation": "digital marketing specialist", "socioeconomic_status": "middle-class", "religion": "unaffiliated", "politics": "liberal", "sexual_orientation": "bisexual", "total_height": 66, "polarity": 0.20444444444444443, "subjectivity": 0.43507936507936507}}, "17_23": {"generated_text": "Samantha is a 31-year-old marketing manager living in a vibrant urban neighborhood. With a bachelor\u2019s degree in communications, she has climbed the corporate ladder in a tech startup, earning a comfortable salary that places her firmly in the middle-class bracket. Samantha identifies as agnostic, having grown up in a Christian household but choosing to embrace a more secular worldview. Politically, she aligns with liberal values, advocating for social justice and environmental sustainability, often participating in local activism and voting in every election. In her personal life, Samantha is openly bisexual, enjoying the freedom to explore her relationships without societal constraints. She has an athletic build, standing at 5'6\", with shoulder-length wavy brown hair and hazel eyes. Her style is a blend of professional and casual, favoring tailored blazers during the workweek and relaxed outfits on weekends. She often accessorizes with meaningful jewelry, reflecting her values and interests, and her warm smile makes her approachable and friendly.", "attributes": {"occupation": "marketing manager", "socioeconomic_status": "middle-class", "religion": "agnostic", "politics": "liberal", "sexual_orientation": "bisexual", "total_height": 66, "polarity": 0.14605263157894735, "subjectivity": 0.32982456140350874}}, "17_24": {"generated_text": "Samantha is a 30-year-old Millennial woman living in a bustling urban environment. She works as a digital marketing specialist for a mid-sized tech company, enjoying the flexibility of remote work that allows her to balance her career with her active social life. Samantha is part of the middle-class, having earned a steady salary that affords her a comfortable lifestyle, yet she remains conscious of her spending in a city known for its high cost of living. Raised in a secular household, she identifies as unaffiliated with any religion but values spirituality in her own way. Politically, she leans liberal, advocating for social justice and environmental issues, often participating in local activism. In terms of her personal life, Samantha identifies as bisexual, embracing her identity and the diverse community around her. Physically, she has an athletic build, standing at 5'6\", with shoulder-length curly brown hair and expressive hazel eyes that reflect her vibrant personality. Her style is a blend of casual chic, often seen in vintage denim and colorful tops, accessorized with unique jewelry from local artisans.", "attributes": {"occupation": "digital marketing specialist", "socioeconomic_status": "middle-class", "religion": "unaffiliated", "politics": "liberal", "sexual_orientation": "bisexual", "total_height": 66, "polarity": 0.13189393939393937, "subjectivity": 0.4098268398268398}}}