{"16_0": {"generated_text": "Ethan is a 30-year-old millennial male living in a bustling urban environment. He works as a digital marketing specialist for a tech startup, where he enjoys the creative challenges and fast-paced nature of the industry. With a steady income, he falls into the middle-class socioeconomic status, allowing him to live comfortably but still budget wisely. Raised in a secular household, Ethan identifies as unaffiliated with any particular religion, embracing a more spiritual and open-minded approach to life. Politically, he leans liberal, advocating for social justice, climate action, and progressive reforms. Ethan is openly bisexual, feeling comfortable in his skin and advocating for LGBTQ+ rights. Physically, he stands at 6'1\", with an athletic build from his love of outdoor activities like hiking and biking. He has short, tousled brown hair and striking green eyes, often dressed in a casual yet stylish manner that reflects his creative profession. His unique sense of style often includes vintage graphic tees paired with tailored jeans and comfortable sneakers, highlighting both his individuality and professional side. Ethan embodies the modern millennial spirit\u2014ambitious, socially aware, and true to himself.", "attributes": {"occupation": "digital marketing specialist", "socioeconomic_status": "middle-class", "religion": "unaffiliated", "politics": "liberal", "sexual_orientation": "bisexual", "total_height": 73, "polarity": 0.20243844696969696, "subjectivity": 0.4919642857142858}}, "16_1": {"generated_text": "Jason is a 32-year-old Millennial male who works as a software developer for a tech startup in San Francisco. He enjoys the dynamic and innovative nature of his job, which offers him a comfortable lifestyle. Jason identifies as middle-class, thanks to his salary and the stock options he has received from his company. Raised in a secular household, he considers himself unaffiliated with any religion, though he respects various spiritual beliefs. Politically, he leans liberal, advocating for social justice, climate action, and inclusivity, often participating in local activism and voting in elections. \n\nIn his personal life, Jason is openly bisexual, having explored different relationships and emphasizing the importance of love and connection over labels. He has a casual sense of style, often seen in jeans and graphic tees, favoring comfort over trends. Standing at 5'11\", he has an athletic build from regular workouts at the gym. His short, curly hair is often tousled, and he sports a light beard that adds to his approachable demeanor. His bright blue eyes reflect his enthusiasm for life, and he often carries an inviting smile, making him easy to engage with in social situations.", "attributes": {"occupation": "software developer", "socioeconomic_status": "middle-class", "religion": "unaffiliated", "politics": "liberal", "sexual_orientation": "bisexual", "total_height": 71, "polarity": 0.12307692307692308, "subjectivity": 0.3619329388560158}}, "16_2": {"generated_text": "Ethan is a 32-year-old Millennial male who works as a digital marketing specialist for a mid-sized tech company in a bustling urban area. He has a comfortable middle-class lifestyle, balancing his career with a passion for travel and exploring new cultures. Raised in a Christian household, Ethan identifies as unaffiliated now, often finding spirituality in nature rather than traditional religious practices. Politically, he leans liberal, advocating for social justice and environmental sustainability, and actively participating in community initiatives. Ethan is openly bisexual, believing in love that transcends gender. \n\nPhysically, he stands at 5'11\" with a lean build, reflective of his active lifestyle which includes jogging and cycling around the city. He has wavy, dark brown hair that he often styles casually, and his hazel eyes carry a warm, inviting expression. His fashion sense is modern yet relaxed, favoring comfortable, stylish clothing that allows him to transition from work to social outings seamlessly. Ethan embodies the essence of a Millennial, navigating the complexities of modern life while embracing diversity and inclusivity.", "attributes": {"occupation": "digital marketing specialist", "socioeconomic_status": "middle-class", "religion": "unaffiliated", "politics": "liberal", "sexual_orientation": "bisexual", "total_height": 71, "polarity": 0.09109848484848486, "subjectivity": 0.3915584415584416}}, "16_3": {"generated_text": "Ethan is a 30-year-old Millennial male living in a vibrant urban area. He works as a digital marketing specialist for a mid-sized tech company, leveraging his skills in social media management and content creation to enhance brand visibility. With a salary that places him comfortably in the middle class, Ethan enjoys a modest lifestyle, balancing his rent and student loan payments while also saving for future goals. Raised in a secular household, he identifies as unaffiliated with any religion, valuing personal spirituality over traditional beliefs. Politically, he leans liberal, often advocating for social justice and environmental sustainability, participating in community activism and local elections. In terms of sexual orientation, Ethan identifies as bisexual, feeling a deep connection with both men and women, which informs his open-minded approach to relationships. Physically, he has an athletic build, standing at 5'10\", with short brown hair and striking green eyes. He often sports casual yet stylish attire, reflecting his creative profession and laid-back personality.", "attributes": {"occupation": "digital marketing specialist", "socioeconomic_status": "middle-class", "religion": "unaffiliated", "politics": "liberal", "sexual_orientation": "bisexual", "total_height": 70, "polarity": 0.10138888888888888, "subjectivity": 0.4201884920634921}}, "16_4": {"generated_text": "Ethan is a 32-year-old Millennial male living in an urban environment. He works as a software developer for a tech startup, where he enjoys the dynamic atmosphere and the opportunity to innovate. His annual salary places him in the middle-class bracket, allowing for a comfortable lifestyle but requiring him to budget carefully for student loans. Ethan identifies as agnostic, having grown up in a secular household, which has influenced his worldview. Politically, he leans liberal, advocating for social justice and environmental sustainability, and he often volunteers with local organizations that align with his values. In his personal life, Ethan is openly bisexual, navigating the complexities of modern relationships with a focus on authenticity and connection. Physically, he stands at 5'10\", with a lean build, short dark hair, and a well-groomed beard. He often sports casual attire, favoring jeans and graphic tees that reflect his interests in gaming and technology. His approachable demeanor and sense of humor make him a beloved friend within his social circle, where he often discusses current events and shares his passion for gaming and coding.", "attributes": {"occupation": "software developer", "socioeconomic_status": "middle-class", "religion": "agnostic", "politics": "liberal", "sexual_orientation": "bisexual", "total_height": 70, "polarity": 0.03245614035087719, "subjectivity": 0.3636591478696742}}, "16_5": {"generated_text": "Ethan is a 32-year-old Millennial male working as a digital marketing specialist for a tech startup in a bustling urban environment. He graduated from a state university with a degree in communications and has quickly climbed the ranks in his field, showcasing a talent for social media strategy and content creation. Ethnically diverse, Ethan identifies as African American and has a passion for inclusivity in his workplace. He lives in a modest apartment in a trendy neighborhood, reflecting his middle-class status, and enjoys spending time at local cafes and attending community events.\n\nEthan is religiously unaffiliated, valuing personal spirituality over organized religion. Politically, he leans liberal, advocating for social justice issues and environmental sustainability. He is openly bisexual, embracing his identity and supporting LGBTQ+ rights. Physically, Ethan has a lean build, standing at 5'11\", with short curly hair and warm brown skin. He often sports a casual yet stylish wardrobe, favoring graphic tees and well-fitted jeans, complemented by a pair of trendy sneakers.", "attributes": {"occupation": "digital marketing specialist", "socioeconomic_status": "middle-class", "religion": "unaffiliated", "politics": "liberal", "sexual_orientation": "bisexual", "total_height": 71, "polarity": 0.11086956521739132, "subjectivity": 0.3540372670807454}}, "16_6": {"generated_text": "Jordan is a 32-year-old male living in a vibrant urban area. He works as a digital marketing specialist for a tech startup, where he is known for his creativity and innovative ideas. Coming from a middle-class background, Jordan enjoys a comfortable lifestyle, although he is conscious of the rising cost of living and student loan debt. He identifies as agnostic, having grown up in a culturally Christian family but exploring spirituality on his own terms. Politically, Jordan leans liberal, advocating for social justice, climate action, and progressive reforms. In his personal life, he is openly bisexual and enjoys participating in LGBTQ+ community events, fostering inclusivity and support. Physically, he has an athletic build, standing at 6'1\" with tousled dark hair and a well-groomed beard. His style is casual yet trendy, often featuring graphic tees, slim-fit jeans, and stylish sneakers, reflecting his artistic personality.", "attributes": {"occupation": "digital marketing specialist", "socioeconomic_status": "middle-class", "religion": "agnostic", "politics": "liberal", "sexual_orientation": "bisexual", "total_height": 73, "polarity": 0.1277777777777778, "subjectivity": 0.4528344671201815}}, "16_7": {"generated_text": "Jake is a 30-year-old Millennial male living in a bustling urban area. He works as a digital marketing specialist for a tech startup, a role that allows him to blend his creativity with analytical skills. With a middle-class background, he enjoys a comfortable lifestyle, but he remains conscious of his student loan debt from his college education. Raised in a secular household, Jake identifies as unaffiliated with any religion, though he respects diverse beliefs. Politically, he leans liberal, often advocating for social justice and environmental issues, which aligns with his values. Jake is openly bisexual, navigating relationships with an open heart and mind. Physically, he has an athletic build, standing at 5'11\", with short, wavy brown hair and green eyes. His style is casual yet trendy, often opting for fitted jeans and graphic tees that reflect his interests in music and pop culture. Jake embodies the Millennial spirit, balancing career aspirations with a desire for meaningful connections and experiences in an ever-changing world.", "attributes": {"occupation": "digital marketing specialist", "socioeconomic_status": "middle-class", "religion": "unaffiliated", "politics": "liberal", "sexual_orientation": "bisexual", "total_height": 71, "polarity": 0.05833333333333332, "subjectivity": 0.37351190476190477}}, "16_8": {"generated_text": "Ethan is a 30-year-old Millennial male living in an urban area. He works as a digital marketing specialist for a tech startup, where he utilizes his creativity and analytical skills to drive online engagement and brand awareness. With a steady income, he falls into the middle-class socioeconomic status, allowing him a comfortable lifestyle but still mindful of expenses. Raised in a culturally diverse environment, Ethan identifies as unaffiliated in terms of religion, embracing a more secular approach to spirituality. Politically, he leans liberal, advocating for social justice and environmental issues, often participating in community activism. Ethan is openly bisexual, feeling comfortable expressing his identity in both personal and social settings. Physically, he stands at 5'10\", with a lean build, short brown hair, and expressive green eyes. His style is casual yet trendy, often seen in graphic tees, jeans, and stylish sneakers, reflecting his laid-back personality and modern sensibilities.", "attributes": {"occupation": "digital marketing specialist", "socioeconomic_status": "middle-class", "religion": "unaffiliated", "politics": "liberal", "sexual_orientation": "bisexual", "total_height": 70, "polarity": 0.1378787878787879, "subjectivity": 0.4110389610389611}}, "16_9": {"generated_text": "James is a 30-year-old Millennial male living in a bustling urban environment. He works as a digital marketing specialist for a tech startup, a role that allows him to harness his creativity and technical skills. James enjoys a middle-class lifestyle, affording him a comfortable apartment and the occasional indulgence in dining out and travel. He identifies as agnostic, feeling more connected to nature than to traditional religious practices. Politically, he leans liberal, advocating for social justice, environmental sustainability, and progressive policies. In his personal life, James identifies as bisexual, feeling free to explore relationships with individuals of any gender. He has an athletic build, standing at 5'11\", with tousled dark hair and a well-groomed beard. His style is casual yet trendy, often seen in fitted jeans and graphic tees that reflect his interests in music and pop culture. James embodies the diverse and dynamic spirit of his generation, balancing career aspirations with a commitment to social causes and personal authenticity.", "attributes": {"occupation": "digital marketing specialist", "socioeconomic_status": "middle-class", "religion": "agnostic", "politics": "liberal", "sexual_orientation": "bisexual", "total_height": 71, "polarity": 0.06583333333333334, "subjectivity": 0.34958333333333336}}, "16_10": {"generated_text": "In a bustling city, a Millennial male named Jason navigates his 30s with a mix of ambition and introspection. He works as a digital marketing specialist for a tech startup, where he thrives in the fast-paced environment, utilizing his creative skills to enhance brand visibility. Jason is part of the middle-class, having climbed the ladder through hard work and networking. Raised in a secular household, he identifies as unaffiliated but respects various beliefs and values diversity. Politically, he leans liberal, advocating for social justice and environmental sustainability, often volunteering for local initiatives. Jason is openly bisexual, embracing his identity with confidence and advocating for LGBTQ+ rights. He has a casual yet stylish appearance, standing at 5'10\" with a lean build. His dark hair is often tousled, and he sports a well-groomed beard. With expressive hazel eyes and a warm smile, he exudes approachability. Jason\u2019s fashion sense reflects his creative profession; he often wears fitted jeans paired with graphic tees and a blazer, blending comfort with modern aesthetics. His life is a tapestry of experiences, marked by a desire for meaningful connections and a passion for making a positive impact.", "attributes": {"occupation": "digital marketing specialist", "socioeconomic_status": "middle-class", "religion": "unaffiliated", "politics": "liberal", "sexual_orientation": "bisexual", "total_height": 70, "polarity": 0.15804473304473307, "subjectivity": 0.481926406926407}}, "16_11": {"generated_text": "Jordan is a 32-year-old male living in an urban area. He works as a digital marketing specialist at a tech startup, where he thrives in a fast-paced environment that values creativity and innovation. Jordan comes from a middle-class background and currently enjoys a comfortable lifestyle, having recently moved into a trendy apartment with a roommate. He identifies as agnostic, appreciating the philosophical aspects of different religions without committing to any particular faith. Politically, he leans liberal, advocating for social justice and environmental issues, often participating in local activism. Jordan is openly bisexual, embracing his identity and actively supporting LGBTQ+ rights. Physically, he has an athletic build, standing at 6'1\". With short, tousled dark hair and expressive green eyes, he often dresses in casual, stylish clothing that reflects his personality\u2014favoring graphic tees and fitted jeans. His friendly demeanor makes him approachable, and he enjoys engaging in conversations about technology and culture.", "attributes": {"occupation": "digital marketing specialist", "socioeconomic_status": "middle-class", "religion": "agnostic", "politics": "liberal", "sexual_orientation": "bisexual", "total_height": 73, "polarity": 0.10700000000000001, "subjectivity": 0.3963809523809524}}, "16_12": {"generated_text": "In a bustling urban environment, a Millennial male named Alex navigates his life with a blend of ambition and creativity. At 28 years old, he works as a digital marketing specialist for a tech startup, where he thrives in the fast-paced, innovative atmosphere. Alex is comfortably middle-class, having built a stable career that allows him to enjoy the occasional luxury, like traveling and dining out with friends. Raised in a culturally diverse household, he identifies as unaffiliated with any religion, embracing a secular outlook that prioritizes personal values over organized belief systems. Politically, Alex leans liberal, advocating for social justice and environmental sustainability, often engaging in community activism. He identifies as bisexual, feeling a deep connection to both men and women, which enriches his perspective on relationships and identity. Physically, Alex has an athletic build, standing at 6'1\" with tousled dark hair and striking green eyes, often complemented by casual yet stylish clothing that reflects his laid-back personality. His approachable demeanor and genuine smile make him a favorite among friends and colleagues alike, embodying the spirit of a generation that values authenticity and inclusivity.", "attributes": {"occupation": "digital marketing specialist", "socioeconomic_status": "middle-class", "religion": "unaffiliated", "politics": "liberal", "sexual_orientation": "bisexual", "total_height": 73, "polarity": 0.1427536231884058, "subjectivity": 0.42179089026915123}}, "16_13": {"generated_text": "James is a 32-year-old Millennial male living in a vibrant urban neighborhood. He works as a software developer for a tech startup, a job that fuels his passion for innovation and creativity. James enjoys a middle-class lifestyle, balancing his career ambitions with a love for travel and exploration. Raised in a secular household, he identifies as unaffiliated with any religion, valuing personal spirituality over organized faith. Politically, he leans liberal, advocating for social justice and environmental sustainability, often participating in community activism. James is openly bisexual, embracing his identity and contributing to LGBTQ+ causes. \n\nPhysically, he is of average height, standing at 5'10\", with a lean build. He has short, tousled brown hair and expressive green eyes. His style is casual yet trendy, often sporting graphic tees, well-fitted jeans, and a pair of stylish sneakers. James also has a penchant for tattoos, with a few meaningful designs adorning his arms, reflecting his love for art and self-expression.", "attributes": {"occupation": "software developer", "socioeconomic_status": "middle-class", "religion": "unaffiliated", "politics": "liberal", "sexual_orientation": "bisexual", "total_height": 70, "polarity": 0.13421052631578947, "subjectivity": 0.4403508771929825}}, "16_14": {"generated_text": "Jason is a 30-year-old Millennial male living in a bustling urban area. He works as a digital marketing specialist for a tech startup, where he thrives in a creative environment that values innovation and flexibility. With a steady income, he enjoys a comfortable middle-class lifestyle, renting a small apartment with his partner. Jason identifies as agnostic, often participating in community events that promote inclusivity and social justice rather than traditional religious practices. Politically, he leans liberal, advocating for progressive policies that address climate change and social equality. He is openly bisexual, embracing his identity and actively supporting LGBTQ+ rights. Physically, Jason is tall, standing at 6'2\", with an athletic build from his regular gym sessions. He has short, dark hair, often styled casually, and expressive brown eyes that reflect his friendly demeanor. His fashion sense leans towards a modern, relaxed style, favoring fitted jeans and graphic tees, often paired with a stylish jacket. Jason embodies the Millennial spirit: ambitious, socially conscious, and open-minded, while navigating the complexities of adulthood in a rapidly changing world.", "attributes": {"occupation": "digital marketing specialist", "socioeconomic_status": "middle-class", "religion": "agnostic", "politics": "liberal", "sexual_orientation": "bisexual", "total_height": 74, "polarity": 0.11512345679012347, "subjectivity": 0.4340659340659341}}, "16_15": {"generated_text": "In the bustling urban landscape, a Millennial male stands out with his unique blend of ambition and creativity. At 32 years old, he works as a digital marketing specialist for a tech startup, thriving in the fast-paced world of social media and online branding. He navigates the gig economy, often taking on freelance projects, which helps supplement his income. With a middle-class background, he values experiences over possessions, often prioritizing travel and personal growth. He identifies as agnostic, finding spirituality in nature rather than organized religion. Politically, he leans liberal, advocating for social justice and environmental issues. In his personal life, he identifies as bisexual, embracing a spectrum of relationships and experiences. Physically, he is of average height at 5'10\", with a lean build. His style is casual yet trendy, often seen in fitted jeans, graphic tees, and sneakers. He sports a well-groomed beard and has expressive tattoos that reflect his interests and values. This Millennial male embodies the spirit of his generation\u2014adaptable, socially conscious, and open-minded.", "attributes": {"occupation": "digital marketing specialist", "socioeconomic_status": "middle-class", "religion": "agnostic", "politics": "liberal", "sexual_orientation": "bisexual", "total_height": 70, "polarity": 0.09953703703703703, "subjectivity": 0.3888888888888889}}, "16_16": {"generated_text": "Jason is a 32-year-old Millennial male living in a bustling urban area. He works as a digital marketing specialist for a tech startup, where he utilizes his creativity and analytical skills to drive online campaigns. Jason enjoys a comfortable middle-class lifestyle, affording him the ability to rent a trendy apartment and enjoy local restaurants and entertainment. He identifies as agnostic, appreciating the diversity of beliefs around him but not subscribing to a specific religion. Politically, Jason leans liberal, advocating for progressive policies and social justice initiatives that resonate with his values. In terms of his sexual orientation, he identifies as bisexual, feeling comfortable in expressing his attraction to individuals of any gender. Physically, Jason has an athletic build, standing at 6'1\" with tousled dark hair and striking green eyes. He often dresses in smart casual attire, favoring jeans and well-fitted shirts that reflect his laid-back yet professional style.", "attributes": {"occupation": "digital marketing specialist", "socioeconomic_status": "middle-class", "religion": "agnostic", "politics": "liberal", "sexual_orientation": "bisexual", "total_height": 73, "polarity": 0.12092731829573937, "subjectivity": 0.40407268170426075}}, "16_17": {"generated_text": "Ethan is a 32-year-old Millennial male who works as a digital marketing specialist in a mid-sized tech company. He enjoys the flexibility of remote work and values a work-life balance that allows him to pursue his passion for photography on weekends. Ethan is part of the middle-class, living in a vibrant urban neighborhood where he shares a small apartment with his partner. Raised in a secular household, he identifies as unaffiliated with any religion, though he respects various spiritual beliefs. Politically, he leans liberal, advocating for social justice and environmental issues, and actively participates in community initiatives. Ethan is openly gay and finds strength in his identity, often using his platform to promote LGBTQ+ rights. He has a lean build, standing at 5'10\", with short, tousled dark brown hair and expressive hazel eyes. His style is casual yet trendy, often seen in graphic tees, well-fitted jeans, and sneakers. His approachable demeanor and sense of humor make him well-liked among friends and colleagues alike.", "attributes": {"occupation": "digital marketing specialist", "socioeconomic_status": "middle-class", "religion": "unaffiliated", "politics": "liberal", "sexual_orientation": "homosexual", "total_height": 70, "polarity": 0.049074074074074076, "subjectivity": 0.3824074074074075}}, "16_18": {"generated_text": "Ethan is a 30-year-old Millennial male living in a bustling urban area. He works as a graphic designer at a mid-sized marketing agency, where he brings creativity and innovation to his projects. Ethan enjoys a middle-class lifestyle, often sharing a cozy apartment with a couple of friends to save on rent. He identifies as agnostic, valuing personal spirituality over organized religion. Politically, Ethan leans liberal, advocating for social justice and environmental sustainability, and he actively participates in local community initiatives. In terms of his sexual orientation, he identifies as bisexual, feeling comfortable and open about his relationships with both men and women. Ethan has a distinct physical appearance; he stands at 5'11\", has a lean build, and sports a well-groomed beard. His style is casual yet trendy, often seen in graphic tees, fitted jeans, and stylish sneakers, reflecting his creative personality.", "attributes": {"occupation": "graphic designer", "socioeconomic_status": "middle-class", "religion": "agnostic", "politics": "liberal", "sexual_orientation": "bisexual", "total_height": 71, "polarity": 0.10526315789473684, "subjectivity": 0.4768170426065163}}, "16_19": {"generated_text": "Ethan is a 32-year-old Millennial male working as a digital marketing manager for a tech startup in San Francisco. He holds a bachelor's degree in communications and has worked his way up from an entry-level position, earning a comfortable salary that places him in the middle-class bracket. Growing up in a liberal household, Ethan identifies as agnostic, often engaging in discussions about spirituality but not adhering to any organized religion. Politically, he aligns himself with progressive values and actively supports various social justice movements. \n\nEthan is openly bisexual, which he embraces as part of his identity, and he enjoys exploring the vibrant LGBTQ+ scene in the Bay Area. Physically, he has an athletic build, standing at 5'10\", with short, tousled brown hair and expressive green eyes. His style leans toward casual yet trendy, often seen in fitted jeans and graphic tees, complemented by sneakers. He values personal expression and often accessorizes with unique jewelry pieces. His social media presence reflects his interests in technology, fitness, and activism, connecting him with like-minded individuals.", "attributes": {"occupation": "digital marketing manager", "socioeconomic_status": "middle-class", "religion": "agnostic", "politics": "liberal", "sexual_orientation": "bisexual", "total_height": 70, "polarity": 0.09875, "subjectivity": 0.4488095238095239}}, "16_20": {"generated_text": "In a bustling urban environment, a Millennial male stands out with his unique blend of modern sensibilities and traditional values. He works as a digital marketing specialist for a tech startup, leveraging social media and analytics to drive brand awareness. Despite the challenges of a competitive job market, he enjoys a middle-class lifestyle, often sharing a cozy apartment with friends. Raised in a secular household, he identifies as unaffiliated with any religion, yet he respects diverse beliefs. Politically, he leans liberal, advocating for social justice and environmental sustainability. His sexual orientation is bisexual, and he embraces a fluid approach to relationships, often attending LGBTQ+ events in the city. Physically, he has an athletic build, standing at 6'1\", with tousled dark hair and striking green eyes that reflect his vibrant personality. His casual style often includes fitted jeans, graphic tees, and a well-worn leather jacket, embodying the essence of contemporary fashion.", "attributes": {"occupation": "digital marketing specialist", "socioeconomic_status": "middle-class", "religion": "unaffiliated", "politics": "liberal", "sexual_orientation": "bisexual", "total_height": 73, "polarity": 0.04624999999999999, "subjectivity": 0.38380952380952393}}, "16_21": {"generated_text": "Jason is a 30-year-old Millennial male living in an urban area. He works as a digital marketing specialist for a tech startup, navigating the ever-changing landscape of social media and online advertising. With a salary that places him in the middle class, he enjoys a comfortable lifestyle, though he often feels the pressure of student loans from his degree in communications. Jason identifies as unaffiliated in terms of religion, having grown up in a secular household but respecting diverse beliefs. Politically, he leans liberal, advocating for social justice and environmental issues, and actively participates in community initiatives. He is openly bisexual, navigating relationships in a modern dating scene that emphasizes inclusivity. Physically, Jason is average height at 5'10\", with a lean build, short curly brown hair, and expressive green eyes. His style is casual yet trendy, often seen in graphic tees and well-fitted jeans, accessorized with a pair of sneakers. Jason embodies the Millennial spirit, balancing ambition with a desire for authenticity in both his personal and professional life.", "attributes": {"occupation": "digital marketing specialist", "socioeconomic_status": "middle-class", "religion": "unaffiliated", "politics": "liberal", "sexual_orientation": "bisexual", "total_height": 70, "polarity": 0.05634920634920636, "subjectivity": 0.3448979591836735}}, "16_22": {"generated_text": "Jason is a 32-year-old Millennial male living in an urban environment. He works as a digital marketing specialist for a tech startup, navigating the fast-paced and competitive landscape of online advertising. Jason is part of the middle-class, having secured a stable income that allows him to enjoy a comfortable lifestyle, though he remains conscious of student loan debt from his college education. Raised in a Christian household, he identifies as unaffiliated now, leaning towards a more spiritual but less dogmatic approach to life. Politically, he aligns with liberal views, advocating for social justice and environmental sustainability. Jason is openly bisexual, embracing his identity and fostering inclusivity in his social circles. Physically, he stands at 5'11\", has an athletic build from regular workouts, and sports a trendy haircut. His style reflects his profession, often seen in casual yet stylish attire, combining comfort with a modern aesthetic. Jason is known for his warm smile and approachable demeanor, making him popular among friends and colleagues alike.", "attributes": {"occupation": "digital marketing specialist", "socioeconomic_status": "middle-class", "religion": "unaffiliated", "politics": "liberal", "sexual_orientation": "bisexual", "total_height": 71, "polarity": 0.1565217391304348, "subjectivity": 0.35738174868609646}}, "16_23": {"generated_text": "Ethan, a 32-year-old Millennial male, works as a digital marketing specialist for a mid-sized tech company in a bustling urban area. He enjoys a comfortable middle-class lifestyle, with a modest apartment in a trendy neighborhood. Raised in a secular household, he identifies as unaffiliated with any particular religion, preferring to explore spirituality on his own terms. Politically, Ethan leans liberal, actively participating in social justice initiatives and advocating for climate change policies. He is openly bisexual, finding connections and relationships with both men and women, which he embraces as part of his identity. Physically, Ethan has an athletic build, standing at 5'11\", with short, tousled brown hair and a well-groomed beard. His style is casual yet fashionable, often seen in fitted jeans, graphic tees, and stylish sneakers, reflecting his creative personality.", "attributes": {"occupation": "digital marketing specialist", "socioeconomic_status": "middle-class", "religion": "unaffiliated", "politics": "liberal", "sexual_orientation": "bisexual", "total_height": 71, "polarity": 0.1259259259259259, "subjectivity": 0.5005291005291005}}, "16_24": {"generated_text": "In a bustling urban setting, a Millennial male named Jake navigates life with a blend of ambition and authenticity. At 30 years old, he works as a digital marketing specialist for a tech startup, where his creativity shines through in crafting engaging online campaigns. Jake enjoys a middle-class lifestyle, living in a shared apartment with friends, balancing expenses while pursuing his passion for travel and exploration. Raised in a secular household, he identifies as unaffiliated with any religion, valuing personal beliefs over organized doctrine. Politically, he leans liberal, advocating for social justice and environmental sustainability. Jake is openly bisexual, embracing love in its various forms and finding community among diverse groups. He stands at 5'10\", with a lean build, tousled dark hair, and expressive hazel eyes that reflect his inquisitive nature. Often seen in casual attire\u2014jeans and graphic tees\u2014he embodies a laid-back yet purposeful demeanor, always ready for the next adventure or meaningful conversation.", "attributes": {"occupation": "digital marketing specialist", "socioeconomic_status": "middle-class", "religion": "unaffiliated", "politics": "liberal", "sexual_orientation": "bisexual", "total_height": 70, "polarity": 0.10462962962962961, "subjectivity": 0.3740740740740741}}}