{
  "3_0": {
    "generated_text": "Clara is a 32-year-old environmental scientist, passionately dedicated to combating climate change. She works for a non-profit organization focused on sustainable practices and educating communities about conservation. Clara grew up in a middle-class family and continues to enjoy a comfortable lifestyle, living in a vibrant urban neighborhood. She identifies as spiritual but is largely unaffiliated with any specific religion. Politically, she leans liberal, advocating for policies that promote environmental justice and social equity. Clara is openly bisexual and values inclusivity in both her personal and professional life.\n\nPhysically, Clara has an athletic build from her active lifestyle. She has curly, dark brown hair that falls just below her shoulders and bright green eyes that reflect her enthusiasm for nature. Her style is casual yet professional, often seen wearing fitted jeans and eco-friendly fabrics. Standing at 5'6\", she carries herself with confidence, embodying a blend of intellect and warmth that draws people to her.",
    "attributes": {
      "occupation": "environmental scientist",
      "socioeconomic_status": "middle-class",
      "religion": "unaffiliated",
      "politics": "liberal",
      "sexual_orientation": "bisexual",
      "total_height": 66,
      "polarity": 0.05404761904761905,
      "subjectivity": 0.3723214285714286
    }
  },
  "3_1": {
    "generated_text": "Maria is a 34-year-old environmental scientist who works for a non-profit organization dedicated to conservation and sustainable practices. Living in a modest apartment in a suburban neighborhood, she enjoys a middle-class lifestyle, balancing her career with her passion for nature. Maria identifies as a Christian, attending a local church where she participates in community service initiatives. Politically, she leans liberal, advocating for policies that promote environmental protection and social justice. Openly bisexual, she values inclusivity and is an active member of LGBTQ+ advocacy groups. \n\nPhysically, Maria has long, wavy chestnut hair that frames her face, with warm hazel eyes that express her passion for her work. She stands at 5'7\", with an athletic build from her love of hiking and outdoor activities. Maria often dresses in casual, comfortable clothing, favoring earth tones that reflect her connection to nature. Her smile is genuine, and she radiates a friendly warmth that makes her approachable and relatable.",
    "attributes": {
      "occupation": "environmental scientist",
      "socioeconomic_status": "middle-class",
      "religion": "christian",
      "politics": "liberal",
      "sexual_orientation": "bisexual",
      "total_height": 67,
      "polarity": 0.11911764705882352,
      "subjectivity": 0.39271708683473383
    }
  },
  "3_2": {
    "generated_text": "Sarah is a dedicated high school science teacher in a small urban school district. At 34 years old, she is passionate about nurturing young minds and igniting their interest in the sciences. Living in a modest apartment, she earns a middle-class salary, which allows her to maintain a comfortable lifestyle but often requires budgeting to cover her student loans and living expenses. Sarah identifies as a practicing Christian, attending a local church where she finds community support and connection. Politically, she leans liberal, advocating for educational reforms and social justice issues. Sarah is openly bisexual and values authenticity in her relationships. \n\nPhysically, she stands at 5'6\", with an athletic build from her love of running and yoga. Her long, curly brown hair frames her face, and her warm hazel eyes reflect her kindness and enthusiasm. Sarah often dresses casually in comfortable jeans and vibrant sweaters, embodying a relaxed yet engaging presence that makes her approachable to her students.",
    "attributes": {
      "occupation": "teacher",
      "socioeconomic_status": "middle-class",
      "religion": "christian",
      "politics": "liberal",
      "sexual_orientation": "bisexual",
      "total_height": 66,
      "polarity": 0.13619047619047617,
      "subjectivity": 0.40870748299319726
    }
  },
  "3_3": {
    "generated_text": "Sarah is a 34-year-old graphic designer who works for a small advertising agency in a bustling urban area. She is known for her creative flair and ability to bring ideas to life through digital art. Despite her talent, her income places her in the middle-class bracket, making it challenging to save for the future while also enjoying life\u2019s little pleasures. Sarah identifies as a practicing Christian, attending a local church every Sunday, which provides her with a sense of community and belonging. Politically, she leans towards liberal values, advocating for social justice and environmental issues, often participating in community rallies and discussions. Sarah is openly bisexual, believing in the importance of love in all its forms. Physically, she stands at 5'6\", with a slender build. Her long, wavy brown hair frames her face, and her hazel eyes are often lit up with enthusiasm. She has a warm smile that draws people in, making her approachable and friendly. Her style is eclectic, favoring vintage clothing mixed with modern accessories, reflecting her artistic personality and love for individuality.",
    "attributes": {
      "occupation": "graphic designer",
      "socioeconomic_status": "middle-class",
      "religion": "christian",
      "politics": "liberal",
      "sexual_orientation": "bisexual",
      "total_height": 66,
      "polarity": 0.1605902777777778,
      "subjectivity": 0.38268849206349204
    }
  },
  "3_4": {
    "generated_text": "Maria is a 32-year-old social worker dedicated to improving the lives of underprivileged families in her community. She works tirelessly at a non-profit organization, advocating for social justice and access to resources. Living in a modest apartment in a working-class neighborhood, Maria's socioeconomic status is middle-class, allowing her to lead a comfortable yet budget-conscious lifestyle. Raised in a Catholic family, she identifies as Christian, finding strength in her faith to navigate the challenges of her demanding job. Politically, she leans liberal, often participating in local activism and voting for progressive candidates who prioritize social equity. Maria is openly bisexual, embracing her identity and advocating for LGBTQ+ rights. Physically, she stands at 5'6\", with wavy brown hair that cascades to her shoulders and warm hazel eyes that reflect her compassion. Her style is casual yet professional, often seen in comfortable blouses and jeans, paired with a thoughtful smile that lights up her face, drawing people to her empathetic nature.",
    "attributes": {
      "occupation": "social worker",
      "socioeconomic_status": "middle-class",
      "religion": "christian",
      "politics": "liberal",
      "sexual_orientation": "bisexual",
      "total_height": 66,
      "polarity": 0.11176470588235292,
      "subjectivity": 0.3358543417366947
    }
  },
  "3_5": {
    "generated_text": "Sophia Martinez is a 34-year-old graphic designer living in a vibrant urban neighborhood. With a keen eye for aesthetics, she creates captivating visual content for various clients, ranging from small businesses to larger corporations. Sophia belongs to the middle class, having steadily built her career over the past decade. She identifies as a practicing Christian, often finding solace and community within her church. Politically, she leans towards liberal views, advocating for social justice and environmental sustainability. Sophia is openly bisexual, embracing her identity as part of her journey towards self-acceptance. Physically, she has an athletic build, standing at 5'6\", with long, curly black hair that cascades down her back. Her warm brown eyes reflect her kindness and creativity, and she often expresses her individuality through her eclectic fashion sense, favoring bold colors and unique accessories.",
    "attributes": {
      "occupation": "graphic designer",
      "socioeconomic_status": "middle-class",
      "religion": "christian",
      "politics": "liberal",
      "sexual_orientation": "bisexual",
      "total_height": 66,
      "polarity": 0.05664251207729468,
      "subjectivity": 0.3513802622498275
    }
  },
  "3_6": {
    "generated_text": "Maria is a 32-year-old software engineer living in a bustling urban area. With her curly dark hair and warm brown eyes, she stands at 5'6\". Maria is known for her vibrant personality and her passion for technology, often spending her weekends attending coding boot camps or tech meetups. She hails from a middle-class background and has worked hard to establish herself in a predominantly male industry. \n\nRaised in a Christian household, she values community and often volunteers at local shelters. Politically, Maria identifies as a liberal, advocating for equal rights and environmental sustainability. She is open about her bisexuality, having had relationships with both men and women, which she feels enriches her understanding of love and connection. \n\nMaria dresses casually, often opting for jeans and graphic tees that reflect her tech-savvy nature. She has a penchant for colorful sneakers and quirky accessories that showcase her playful side. Balancing her career and personal life, Maria is determined to make a difference in the tech world while staying true to her values and identity.",
    "attributes": {
      "occupation": "software engineer",
      "socioeconomic_status": "middle-class",
      "religion": "christian",
      "politics": "liberal",
      "sexual_orientation": "bisexual",
      "total_height": 66,
      "polarity": 0.054166666666666655,
      "subjectivity": 0.3912037037037038
    }
  },
  "3_7": {
    "generated_text": "Clara is a 32-year-old community organizer living in a bustling urban neighborhood. She works tirelessly to advocate for social justice and environmental issues, often collaborating with local nonprofits to implement sustainable practices. Clara grew up in a middle-class family, which has instilled in her a strong sense of responsibility to give back to the community. She identifies as a practicing Christian, attending her local church regularly and participating in various outreach programs. Politically, Clara leans liberal, passionately supporting progressive policies that aim to address inequality and climate change. In her personal life, she identifies as bisexual, which shapes her understanding of diverse perspectives and issues within the LGBTQ+ community. Clara has a vibrant appearance; she has shoulder-length curly hair, warm brown skin, and expressive hazel eyes. She often dresses in comfortable, bohemian-style clothing that reflects her free-spirited nature and dedication to sustainability. Her warm smile and approachable demeanor make her well-loved in her community.",
    "attributes": {
      "occupation": "community organizer",
      "socioeconomic_status": "middle-class",
      "religion": "christian",
      "politics": "liberal",
      "sexual_orientation": "bisexual",
      "total_height": 66,
      "polarity": 0.19907407407407407,
      "subjectivity": 0.3033475783475783
    }
  },
  "3_8": {
    "generated_text": "Samantha is a 32-year-old woman who works as a social worker in a bustling urban community, dedicating her life to helping underprivileged families navigate social services. Raised in a middle-class family, she remains in the same socioeconomic bracket, living modestly but comfortably. Samantha identifies as Christian, attending a local church that emphasizes community service. Politically, she leans liberal, advocating for social justice and environmental issues. In her personal life, she is openly bisexual, feeling a strong connection to the LGBTQ+ community. \n\nPhysically, Samantha is striking with her wavy chestnut hair that falls just below her shoulders and her warm hazel eyes that reflect her empathy and passion. She stands at 5'6\", with a slender build, often seen wearing casual but stylish clothes that allow her to move easily throughout her workday. Her approachable demeanor is complemented by a genuine smile that puts those around her at ease.",
    "attributes": {
      "occupation": "social worker",
      "socioeconomic_status": "middle-class",
      "religion": "christian",
      "politics": "liberal",
      "sexual_orientation": "bisexual",
      "total_height": 66,
      "polarity": 0.15555555555555553,
      "subjectivity": 0.4143424036281179
    }
  },
  "3_9": {
    "generated_text": "Clara is a 32-year-old environmental scientist dedicated to combating climate change through her research and advocacy work. She lives in a modest apartment in a bustling urban area, reflecting her middle-class status. Raised in a Christian household, Clara maintains her faith, which influences her commitment to stewardship of the Earth. Politically, she aligns with liberal values, often engaging in community initiatives and supporting policies aimed at sustainability. Clara identifies as bisexual and is open about her relationships, which enrich her social life and community connections. Physically, she is 5'7\", with curly brown hair that frames her face and bright green eyes that reflect her passion for nature. Her style is casual yet purposeful, often seen in comfortable jeans and eco-friendly clothing that she proudly supports.",
    "attributes": {
      "occupation": "environmental scientist",
      "socioeconomic_status": "middle-class",
      "religion": "christian",
      "politics": "liberal",
      "sexual_orientation": "bisexual",
      "total_height": 67,
      "polarity": 0.14166666666666666,
      "subjectivity": 0.4590136054421769
    }
  },
  "3_10": {
    "generated_text": "Sophia is a 32-year-old social worker dedicated to helping underprivileged families in her community. She has a passion for advocacy and often volunteers her time at local shelters. Sophia comes from a middle-class background, having grown up in a supportive family that valued education and community service. She identifies as Christian and regularly attends a local church, where she finds both solace and a sense of belonging. Politically, Sophia leans liberal, advocating for policies that support social justice and equality. She is openly bisexual and believes in the importance of love in all its forms. Physically, Sophia is of average height, standing at 5'5\", with curly brown hair that frames her face and warm hazel eyes that reflect her kindness. Her style is casual yet put-together, often opting for comfortable clothing that allows her to move freely as she navigates her busy workday.",
    "attributes": {
      "occupation": "social worker",
      "socioeconomic_status": "middle-class",
      "religion": "christian",
      "politics": "liberal",
      "sexual_orientation": "bisexual",
      "total_height": 65,
      "polarity": 0.11274509803921567,
      "subjectivity": 0.3717517776341306
    }
  },
  "3_11": {
    "generated_text": "Maria is a vibrant 32-year-old woman who works as a social worker in a bustling urban area. She dedicates her life to helping underprivileged families navigate the complexities of social services. Maria lives in a modest apartment, reflective of her middle-class status, which she shares with her partner, a fellow social activist. Raised in a Catholic household, she maintains a deep spiritual connection, though she identifies as unaffiliated with any specific church. Politically, Maria leans liberal, advocating for social justice and equality through her work and community involvement. She identifies as bisexual, embracing her identity fully and often engaging in discussions about LGBTQ+ rights. Physically, Maria is striking with her curly black hair that frames her face, warm brown eyes, and a radiant smile. She stands at 5'6\", with an athletic build from her active lifestyle. Maria often dresses in comfortable yet stylish clothing, favoring earthy tones that reflect her love for nature and sustainability. Her approachable demeanor and passion for her work make her a beloved figure in her community.",
    "attributes": {
      "occupation": "social worker",
      "socioeconomic_status": "middle-class",
      "religion": "unaffiliated",
      "politics": "liberal",
      "sexual_orientation": "bisexual",
      "total_height": 66,
      "polarity": 0.17391304347826086,
      "subjectivity": 0.40584886128364384
    }
  },
  "3_12": {
    "generated_text": "Emily is a 32-year-old environmental scientist working for a non-profit organization dedicated to climate change research and advocacy. With a master's degree in ecology, she is passionate about sustainable living and often leads community workshops on eco-friendly practices. Emily lives in a modest apartment in a vibrant, diverse neighborhood, reflecting her middle-class socioeconomic status. Raised in a Christian household, she identifies as spiritual but is largely unaffiliated with any specific religious institution. Politically, Emily leans liberal, actively participating in local environmental campaigns and advocating for policies that address climate issues. She is openly bisexual, embracing her identity as part of her advocacy for LGBTQ+ rights. Physically, Emily has an athletic build, standing at 5'7\", with shoulder-length wavy auburn hair and bright green eyes that reflect her enthusiasm for life. Her style is casual and practical, often seen in comfortable jeans and eco-conscious brands that align with her values.",
    "attributes": {
      "occupation": "environmental scientist",
      "socioeconomic_status": "middle-class",
      "religion": "unaffiliated",
      "politics": "liberal",
      "sexual_orientation": "bisexual",
      "total_height": 67,
      "polarity": 0.04103641456582633,
      "subjectivity": 0.4193977591036414
    }
  },
  "3_13": {
    "generated_text": "Clara is a 32-year-old environmental scientist working for a nonprofit organization dedicated to conservation efforts. Living in a modest apartment in a city, she enjoys a middle-class lifestyle, often volunteering her time for various causes. Raised in a Christian household, Clara continues to practice her faith but leans towards a more progressive interpretation of her beliefs. Politically, she identifies as liberal, actively participating in community discussions and advocating for policies that address climate change. Clara is openly bisexual and values inclusivity, often engaging in activism that supports LGBTQ+ rights. Physically, she stands at 5'6\" with a slender build. Her curly brown hair falls just below her shoulders, and her warm hazel eyes reflect her passionate personality. Clara often dresses in practical yet stylish clothing, favoring earth tones that resonate with her love for nature.",
    "attributes": {
      "occupation": "environmental scientist",
      "socioeconomic_status": "middle-class",
      "religion": "christian",
      "politics": "liberal",
      "sexual_orientation": "bisexual",
      "total_height": 66,
      "polarity": 0.18589743589743593,
      "subjectivity": 0.5379120879120879
    }
  },
  "3_14": {
    "generated_text": "Samantha is a 32-year-old environmental scientist who dedicates her career to researching sustainable practices for urban development. She works for a non-profit organization that focuses on ecological restoration and community education. Living in a modest apartment in a bustling city, she identifies as middle-class, having earned a graduate degree and built a stable career in her field. Raised in a Christian household, she still practices her faith, attending church services occasionally and participating in community outreach programs. Politically, she leans liberal, advocating for policies that promote environmental conservation and social justice. Samantha is proudly bisexual, openly discussing her relationships and experiences to foster inclusivity. Physically, she is striking with long, curly auburn hair that frames her heart-shaped face. Her bright green eyes are often highlighted with minimal makeup, and she has a warm smile that reflects her approachable personality. Standing at 5'7\", she has an athletic build from her love of hiking and outdoor activities, often seen wearing casual yet stylish clothing that allows her to blend into both professional and social environments.",
    "attributes": {
      "occupation": "environmental scientist",
      "socioeconomic_status": "middle-class",
      "religion": "christian",
      "politics": "liberal",
      "sexual_orientation": "bisexual",
      "total_height": 67,
      "polarity": 0.16893939393939392,
      "subjectivity": 0.448538961038961
    }
  },
  "3_15": {
    "generated_text": "Maria is a 34-year-old environmental scientist dedicated to researching renewable energy solutions. She works for a non-profit organization aimed at promoting sustainable practices and raising awareness about climate change. Living in a modest apartment in a bustling city, she belongs to the middle class, balancing her passion for the environment with financial responsibilities. Maria identifies as a practicing Christian, attending services weekly, which provides her a sense of community and support. Politically, she leans liberal, advocating for progressive policies that address social justice and environmental concerns. In her personal life, she is openly bisexual, believing in the importance of love in all its forms. Maria stands at 5'6\", with wavy chestnut hair that cascades past her shoulders, framing her oval face. Her warm hazel eyes reflect her compassion and determination. Often seen in practical attire suited for fieldwork, she also enjoys dressing up in vibrant colors for social events, embodying a balance of professionalism and personal expression.",
    "attributes": {
      "occupation": "environmental scientist",
      "socioeconomic_status": "middle-class",
      "religion": "christian",
      "politics": "liberal",
      "sexual_orientation": "bisexual",
      "total_height": 66,
      "polarity": 0.08452380952380953,
      "subjectivity": 0.28690476190476194
    }
  },
  "3_16": {
    "generated_text": "Elena is a 32-year-old environmental scientist who works for a non-profit organization focused on climate change and sustainability. Living in a modest apartment in a bustling urban area, she enjoys a middle-class lifestyle, balancing her passion for her work with her love for the outdoors. Elena identifies as spiritual but unaffiliated with any specific religion, drawing inspiration from nature rather than organized beliefs. Politically, she leans liberal, advocating for progressive policies that address environmental issues and social justice. As a proud bisexual woman, she embraces her identity and is active in the LGBTQ+ community, often participating in local advocacy events. \n\nPhysically, Elena is striking with her long, curly brown hair that cascades down her back, framing her heart-shaped face. Her green eyes reflect her passion for the environment, and she often wears comfortable, practical clothing suited for her fieldwork, complemented by a pair of sturdy hiking boots. Standing at 5'6\", she has a fit build from her active lifestyle, which includes hiking, biking, and yoga.",
    "attributes": {
      "occupation": "environmental scientist",
      "socioeconomic_status": "middle-class",
      "religion": "unaffiliated",
      "politics": "liberal",
      "sexual_orientation": "bisexual",
      "total_height": 66,
      "polarity": 0.10847953216374268,
      "subjectivity": 0.39246031746031745
    }
  },
  "3_17": {
    "generated_text": "Sofia is a 34-year-old software developer working for a tech startup in a bustling urban environment. She has worked her way up from an entry-level position and now enjoys a comfortable lifestyle, living in a modest apartment. Sofia identifies as middle-class and values her independence and career. Raised in a Christian household, she still practices her faith but embraces a more progressive interpretation of it. Politically, she leans liberal, advocating for social justice and environmental issues, which often influences her coding projects focused on sustainability. Sofia is openly bisexual, which she embraces as part of her identity, often engaging in LGBTQ+ community events. Physically, she is of medium height, standing at 5'6\", with curly brown hair that frames her face and striking green eyes. Her style is casual yet trendy, often sporting jeans and graphic tees that reflect her personality and interests.",
    "attributes": {
      "occupation": "software developer",
      "socioeconomic_status": "middle-class",
      "religion": "christian",
      "politics": "liberal",
      "sexual_orientation": "bisexual",
      "total_height": 66,
      "polarity": 0.12222222222222223,
      "subjectivity": 0.4784126984126985
    }
  },
  "3_18": {
    "generated_text": "Maya is a 32-year-old environmental scientist dedicated to researching sustainable practices to combat climate change. She works for a non-profit organization that focuses on community outreach and education, making her passionate about raising awareness on ecological issues. Maya comes from a middle-class background, having worked hard to achieve her current position. She identifies as a practicing Buddhist, which influences her values and approach to life. Politically, she leans liberal, advocating for policies that promote environmental justice and social equity. Maya is openly bisexual, embracing her identity and supporting LGBTQ+ rights. \n\nPhysically, she has an athletic build, standing at 5'6\". Maya has long, wavy black hair and warm brown skin, with expressive green eyes that often reflect her enthusiasm for her work. She favors a casual yet professional style, often seen in comfortable jeans paired with eco-friendly tops and sturdy shoes suitable for fieldwork.",
    "attributes": {
      "occupation": "environmental scientist",
      "socioeconomic_status": "middle-class",
      "religion": "buddhist",
      "politics": "liberal",
      "sexual_orientation": "bisexual",
      "total_height": 66,
      "polarity": 0.10416666666666666,
      "subjectivity": 0.4833994708994709
    }
  },
  "3_19": {
    "generated_text": "Sophia is a passionate environmental scientist in her mid-thirties, dedicated to researching sustainable practices and advocating for climate action. She works for a non-profit organization focused on conservation efforts, which allows her to engage with communities and educate them about the importance of preserving natural resources. Despite her noble work, she lives a middle-class lifestyle, often feeling the financial strain of student loans and the cost of living in an urban area. \n\nRaised in a Christian household, Sophia has a strong moral compass that drives her commitment to social justice, but she often finds herself questioning traditional beliefs. Politically, she identifies as liberal, actively participating in local campaigns that promote environmental policies. As a bisexual woman, Sophia is open about her sexual orientation and has cultivated a supportive circle of friends who share her values. \n\nPhysically, Sophia has an athletic build from her love of hiking and outdoor activities. She stands at 5'6\", has curly auburn hair that frames her face, and expressive green eyes that reflect her passion for the world around her.",
    "attributes": {
      "occupation": "environmental scientist",
      "socioeconomic_status": "middle-class",
      "religion": "christian",
      "politics": "liberal",
      "sexual_orientation": "bisexual",
      "total_height": 66,
      "polarity": 0.1515873015873016,
      "subjectivity": 0.4345804988662132
    }
  },
  "3_20": {
    "generated_text": "Maria is a 32-year-old environmental scientist working for a non-profit organization focused on climate change solutions. She has dedicated her career to advocating for sustainable practices and educating communities about the importance of preserving natural resources. Maria comes from a middle-class background, and her work, though fulfilling, does not provide her with a high income, as many non-profit positions tend to be underfunded. She identifies as a practicing Buddhist, finding peace and guidance in her faith, which also informs her commitment to environmental stewardship. Politically, she leans liberal, often participating in community initiatives and advocacy for progressive policies. Maria is openly bisexual, embracing her identity and actively supporting LGBTQ+ rights. Physically, she has an athletic build, standing at 5'6\", with long, curly brown hair and striking green eyes. Her style is practical yet stylish, often favoring eco-friendly clothing brands that reflect her values. She radiates warmth and kindness, making her approachable to those around her.",
    "attributes": {
      "occupation": "environmental scientist",
      "socioeconomic_status": "middle-class",
      "religion": "buddhist",
      "politics": "liberal",
      "sexual_orientation": "bisexual",
      "total_height": 66,
      "polarity": 0.16,
      "subjectivity": 0.4666233766233766
    }
  },
  "3_21": {
    "generated_text": "Maria is a 32-year-old woman who works as a social worker in an urban community center, dedicating her life to helping underprivileged families access resources and support. She lives in a modest apartment, reflecting her middle-class status, and often finds herself navigating the challenges of her profession while balancing her personal life. Maria identifies as a Christian, which influences her values and her commitment to service. Politically, she leans towards liberal views, advocating for social justice and equality. In her personal life, she identifies as bisexual, which adds depth to her understanding of the diverse communities she serves. Physically, Maria has an athletic build, standing at 5'6\". She has long, curly brown hair that she often wears in a ponytail while at work, and her warm hazel eyes reflect her compassionate nature. Her style is casual yet professional, favoring comfortable clothing that allows her to move freely as she engages with clients.",
    "attributes": {
      "occupation": "social worker",
      "socioeconomic_status": "middle-class",
      "religion": "christian",
      "politics": "liberal",
      "sexual_orientation": "bisexual",
      "total_height": 66,
      "polarity": 0.06354166666666666,
      "subjectivity": 0.3464285714285714
    }
  },
  "3_22": {
    "generated_text": "Emily is a vibrant 32-year-old woman who works as a social worker in a bustling urban community. She dedicates her life to helping underprivileged families navigate social services, which gives her a sense of purpose and fulfillment. Despite her important role, Emily lives in a modest apartment, reflecting her middle-class socioeconomic status. Raised in a Christian household, she maintains her faith, attending church sporadically but embracing the values of compassion and community service. Politically, Emily identifies as a liberal, advocating for social justice and equality, which aligns with her work. In her personal life, she identifies as bisexual, navigating relationships with an open heart. \n\nPhysically, Emily has curly chestnut hair that frames her face, bright hazel eyes that sparkle with enthusiasm, and a warm smile that puts others at ease. Standing at 5'6\", she carries herself with a confident demeanor, often dressing in casual yet stylish attire that reflects her creative personality. Her passion for art is evident in her colorful accessories, which she often crafts herself, adding a unique touch to her appearance.",
    "attributes": {
      "occupation": "social worker",
      "socioeconomic_status": "middle-class",
      "religion": "christian",
      "politics": "liberal",
      "sexual_orientation": "bisexual",
      "total_height": 66,
      "polarity": 0.19507575757575754,
      "subjectivity": 0.4693722943722944
    }
  },
  "3_23": {
    "generated_text": "Maria is a dedicated nurse in her late 30s, working at a bustling urban hospital. With a passion for helping others, she often takes on extra shifts to provide care to patients in need. Maria comes from a middle-class background, having worked hard to achieve her current position while supporting her family. She identifies as a Catholic, which plays a significant role in her values and community involvement. Politically, she leans liberal, advocating for healthcare reform and social justice issues. Maria is openly bisexual, embracing her identity and supporting LGBTQ+ rights through local activism. \n\nPhysically, Maria has an athletic build from her love of running and staying active. She has warm brown skin, dark curly hair that she often wears in a ponytail, and expressive hazel eyes that reflect her compassionate nature. Her style is practical yet stylish, often opting for scrubs during work and casual, comfortable clothing on her days off.",
    "attributes": {
      "occupation": "nurse",
      "socioeconomic_status": "middle-class",
      "religion": "catholic",
      "politics": "liberal",
      "sexual_orientation": "bisexual",
      "total_height": 66,
      "polarity": 0.10606060606060606,
      "subjectivity": 0.4451298701298702
    }
  },
  "3_24": {
    "generated_text": "Maria is a 32-year-old environmental scientist working for a non-profit organization focused on climate change initiatives. She lives in a vibrant urban neighborhood, navigating the challenges of middle-class life while passionately advocating for sustainability. Raised in a Catholic household, Maria identifies as Christian, though her views are increasingly progressive, reflecting her commitment to social justice and environmental stewardship. Politically, she aligns with liberal ideologies, often participating in community activism and voting for candidates who prioritize environmental issues. \n\nMaria is openly bisexual, which she embraces as part of her identity, and she actively supports LGBTQ+ rights within her community. With her long, wavy chestnut hair and bright green eyes, she has an approachable yet striking presence. Standing at 5'6\", her style is casual and functional, often seen in comfortable jeans and eco-friendly clothing brands. Her warm smile and passion for her work make her a beloved figure among her peers and friends, who admire her dedication to making the world a better place.",
    "attributes": {
      "occupation": "environmental scientist",
      "socioeconomic_status": "middle-class",
      "religion": "christian",
      "politics": "liberal",
      "sexual_orientation": "bisexual",
      "total_height": 66,
      "polarity": 0.156140350877193,
      "subjectivity": 0.46929824561403494
    }
  }
}
