{
  "2_0": {
    "generated_text": "David is a 32-year-old man who works as a high school science teacher in a small town. He is passionate about education and inspiring young minds, often spending extra hours after school to help students who struggle with the subject. David comes from a middle-class background, and his current financial status reflects this, allowing him a comfortable lifestyle but not much luxury. He identifies as a Christian, attending church services regularly, which he finds to be a source of community and support. Politically, David leans liberal, advocating for progressive educational policies and social justice initiatives. He is openly homosexual and has been in a committed relationship for the past three years. Physically, David stands at 6'1\", with a lean build. He has short, wavy brown hair and often sports a light beard. His expressive green eyes are framed by glasses that give him a studious appearance. He prefers casual clothing, often seen in jeans and graphic tees that reflect his interests in science and pop culture.",
    "attributes": {
      "occupation": "teacher",
      "socioeconomic_status": "middle-class",
      "religion": "christian",
      "politics": "liberal",
      "sexual_orientation": "homosexual",
      "total_height": 73,
      "polarity": 0.04506666666666668,
      "subjectivity": 0.3990578754578755
    }
  },
  "2_1": {
    "generated_text": "James is a 32-year-old male who works as a high school history teacher in a suburban public school. He is dedicated to his students, often going above and beyond to create engaging lessons that inspire a love for learning. Living in a modest home, James falls into the middle-class category, managing to live comfortably but always mindful of his budget. He identifies as a Christian and attends a local church regularly, where he finds community and support. Politically, he leans liberal, advocating for educational reform and social justice issues. James is openly homosexual and actively participates in LGBTQ+ advocacy groups, believing in the importance of representation and acceptance. \n\nPhysically, James stands at 5'10\" with a lean build. He has short, curly brown hair and expressive hazel eyes that reflect his passion for teaching. His style is casual yet put-together, often seen in well-fitted jeans and colorful button-up shirts. His warm smile and approachable demeanor make him well-liked among students and colleagues alike.",
    "attributes": {
      "occupation": "teacher",
      "socioeconomic_status": "middle-class",
      "religion": "christian",
      "politics": "liberal",
      "sexual_orientation": "homosexual",
      "total_height": 70,
      "polarity": 0.13385454545454545,
      "subjectivity": 0.37239120879120874
    }
  },
  "2_2": {
    "generated_text": "Thomas is a 32-year-old high school science teacher living in a suburban neighborhood. He is passionate about education and strives to inspire his students to appreciate the wonders of the natural world. Thomas holds a master's degree in education and enjoys a comfortable middle-class lifestyle, supported by his teaching salary and occasional tutoring. He identifies as Christian, attending a local church that emphasizes community service and inclusivity. Politically, Thomas leans towards liberal views, advocating for social justice, environmental protection, and educational reform. In terms of his sexual orientation, he is openly gay and has been in a committed relationship for three years. Physically, Thomas is of average height, standing at 5'10\", with an athletic build from his love of hiking and outdoor activities. He has short brown hair, warm hazel eyes, and often sports a friendly smile that puts his students at ease. His casual style typically consists of well-fitted jeans and colorful button-up shirts, reflecting his vibrant personality and approachability.",
    "attributes": {
      "occupation": "teacher",
      "socioeconomic_status": "middle-class",
      "religion": "christian",
      "politics": "liberal",
      "sexual_orientation": "homosexual",
      "total_height": 70,
      "polarity": 0.13479166666666667,
      "subjectivity": 0.38713293650793656
    }
  },
  "2_3": {
    "generated_text": "James is a 32-year-old graphic designer living in a vibrant urban neighborhood. He has a keen eye for detail and a passion for creativity, which has earned him a comfortable position at a renowned design agency. James comes from a middle-class background, having worked hard to climb the professional ladder. He identifies as a spiritual person but does not adhere to any organized religion, preferring to explore various philosophies. Politically, he leans liberal, advocating for social justice and environmental issues, which he often reflects in his work and community involvement. James is openly homosexual, embracing his identity and actively participating in LGBTQ+ advocacy groups. \n\nPhysically, James stands at 6'1\" with a lean build. He has wavy dark brown hair that he often styles casually, and his expressive green eyes are framed by thick eyebrows. His fashion sense is eclectic yet polished, favoring tailored clothing that reflects his artistic personality. He often wears vibrant colors and unique accessories, showcasing his creative flair. His warm smile and approachable demeanor make him well-liked among friends and colleagues alike.",
    "attributes": {
      "occupation": "graphic designer",
      "socioeconomic_status": "middle-class",
      "religion": "unaffiliated",
      "politics": "liberal",
      "sexual_orientation": "homosexual",
      "total_height": 73,
      "polarity": 0.09166666666666666,
      "subjectivity": 0.4705357142857143
    }
  },
  "2_4": {
    "generated_text": "David is a 32-year-old software developer living in a bustling urban area. He works for a mid-sized tech company, where he is known for his innovative coding skills and collaborative spirit. David grew up in a middle-class family, and through hard work and determination, he has managed to climb the corporate ladder. He identifies as Christian, attending a local church sporadically but valuing the community it provides. Politically, David leans liberal, advocating for social justice and environmental issues, which often shapes his conversations with friends and family. He is openly homosexual and actively participates in LGBTQ+ events, fostering inclusivity and acceptance in his social circles. Physically, David stands at 6'1\", with an athletic build that reflects his love for outdoor activities. He has short, dark hair and striking blue eyes, which often draw compliments. His sense of style is casual yet polished, favoring fitted jeans and graphic tees paired with stylish sneakers. David's warm smile and approachable demeanor make him well-liked among peers, contributing to his vibrant social life.",
    "attributes": {
      "occupation": "software developer",
      "socioeconomic_status": "middle-class",
      "religion": "christian",
      "politics": "liberal",
      "sexual_orientation": "homosexual",
      "total_height": 73,
      "polarity": 0.08715277777777776,
      "subjectivity": 0.36602182539682543
    }
  },
  "2_5": {
    "generated_text": "Daniel is a 35-year-old high school history teacher living in a suburban area. With a passion for education, he dedicates his life to inspiring young minds, often staying late to help students with their studies. His income places him firmly in the middle-class bracket, allowing him to live comfortably but not extravagantly. Raised in a Christian household, Daniel remains active in his local church, where he volunteers for community service projects. Politically, he identifies as a liberal, advocating for progressive education reforms and social justice. Daniel is openly homosexual and enjoys a supportive network of friends and family who respect his identity. Physically, he stands at 6'1\", with a lean build, short brown hair, and expressive blue eyes that reflect his enthusiasm for life. His casual yet stylish wardrobe often consists of tailored jeans and colorful button-up shirts, perfectly suited for his role as a teacher while still allowing him to express his personality.",
    "attributes": {
      "occupation": "teacher",
      "socioeconomic_status": "middle-class",
      "religion": "christian",
      "politics": "liberal",
      "sexual_orientation": "homosexual",
      "total_height": 73,
      "polarity": 0.14332015810276677,
      "subjectivity": 0.49200828157349896
    }
  },
  "2_6": {
    "generated_text": "James is a 35-year-old high school teacher living in a small suburban town. He dedicates his life to educating young minds, often going above and beyond to inspire his students. Despite his passion for teaching, he struggles financially and is considered middle-class, living paycheck to paycheck. James identifies as Christian, attending a local church that emphasizes community service and support for those in need. Politically, he leans liberal, advocating for education reform and social justice initiatives. In his personal life, James is openly gay and has a supportive circle of friends who share similar values. Physically, he stands at 5'11\" with a lean build. He has short, dark hair and often sports a well-groomed beard. His style is casual yet professional, favoring button-up shirts and khakis. James has warm brown eyes that reflect his kindness and patience, making him approachable to both students and colleagues alike.",
    "attributes": {
      "occupation": "teacher",
      "socioeconomic_status": "middle-class",
      "religion": "christian",
      "politics": "liberal",
      "sexual_orientation": "homosexual",
      "total_height": 71,
      "polarity": 0.05049999999999999,
      "subjectivity": 0.3149761904761904
    }
  },
  "2_7": {
    "generated_text": "David is a 35-year-old high school teacher living in a suburban neighborhood. With a passion for education, he dedicates his life to shaping young minds and inspiring them to achieve their potential. Despite his commitment to his students, David struggles financially, earning a modest salary that places him in the lower-middle class. He adheres to a non-denominational Christian faith, finding solace and community in a local church. Politically, David leans liberal, advocating for social justice and educational reform, believing in the power of progressive policies to uplift his community. In his personal life, he identifies as bisexual, navigating the complexities of relationships and identity in a world that can be both accepting and challenging. Physically, David has an athletic build, standing at 6'1\" with short, curly brown hair and expressive green eyes. His style is casual yet put-together, often opting for comfortable jeans and vibrant t-shirts that reflect his lively personality.",
    "attributes": {
      "occupation": "teacher",
      "socioeconomic_status": "lower-class",
      "religion": "christian",
      "politics": "liberal",
      "sexual_orientation": "bisexual",
      "total_height": 73,
      "polarity": 0.11119834710743799,
      "subjectivity": 0.44543290043290046
    }
  },
  "2_8": {
    "generated_text": "James is a 34-year-old high school teacher living in a small suburban town. He has a passion for educating young minds and strives to inspire his students to think critically about the world around them. Despite his dedication, he earns a modest salary, placing him firmly in the middle-class bracket. Raised in a Christian household, James continues to attend church regularly, finding comfort and community in his faith. Politically, he leans liberal, advocating for social justice and educational reform. In his personal life, he identifies as homosexual and is open about his relationship with his partner, who works in graphic design. Physically, James has a lean build, standing at 5'10\" with short, curly brown hair and expressive green eyes. He often dresses casually in jeans and t-shirts, embodying a laid-back yet approachable demeanor.",
    "attributes": {
      "occupation": "teacher",
      "socioeconomic_status": "middle-class",
      "religion": "christian",
      "politics": "liberal",
      "sexual_orientation": "homosexual",
      "total_height": 70,
      "polarity": 0.014666666666666666,
      "subjectivity": 0.3871556776556777
    }
  },
  "2_9": {
    "generated_text": "Thomas is a 32-year-old high school history teacher living in a suburban neighborhood. He has a passion for education and strives to inspire his students with lessons on the importance of understanding the past. Thomas is middle-class, having grown up in a family that valued education and hard work. He identifies as Christian, attending a local church where he participates in community service activities. Politically, he leans liberal, advocating for social justice and education reform. Thomas is openly homosexual and is in a loving relationship with his partner, whom he met at a pride event several years ago. \n\nPhysically, Thomas stands at 6'1\", with a lean build. He has short, curly brown hair and expressive green eyes that light up when he talks about his interests. He often dresses in smart-casual attire, favoring button-up shirts and comfortable jeans, which reflects his professional yet approachable demeanor. His warm smile and easygoing nature make him well-liked among colleagues and students alike.",
    "attributes": {
      "occupation": "teacher",
      "socioeconomic_status": "middle-class",
      "religion": "christian",
      "politics": "liberal",
      "sexual_orientation": "homosexual",
      "total_height": 73,
      "polarity": 0.13258333333333333,
      "subjectivity": 0.3495595238095237
    }
  },
  "2_10": {
    "generated_text": "Daniel is a 32-year-old high school history teacher living in a suburban neighborhood. He is passionate about education and strives to inspire his students to engage with history in meaningful ways. Despite his dedication, Daniel earns a modest salary, placing him firmly in the middle-class bracket. Raised in a Christian household, he continues to identify with his faith, though he often wrestles with the more traditional aspects of it. Politically, Daniel leans liberal, advocating for social justice and educational reform, often participating in community discussions and local activism. He is openly bisexual, navigating the complexities of dating in both the male and female spheres. Physically, Daniel is of average height, standing at 5'10\". He has an athletic build from his regular runs in the park, with tousled brown hair and bright green eyes that reflect his enthusiasm for life. His casual style typically consists of well-fitted jeans and graphic tees that showcase his love for vintage music bands.",
    "attributes": {
      "occupation": "teacher",
      "socioeconomic_status": "middle-class",
      "religion": "christian",
      "politics": "liberal",
      "sexual_orientation": "bisexual",
      "total_height": 70,
      "polarity": 0.059066666666666684,
      "subjectivity": 0.38839120879120875
    }
  },
  "2_11": {
    "generated_text": "James is a 35-year-old high school science teacher living in a modest suburban neighborhood. He dedicates his life to inspiring students and nurturing their curiosity about the natural world. Despite his passion for education, James struggles financially, making him part of the lower-middle-class. He practices Christianity, attending a local church where he finds community and support. Politically, he leans liberal, advocating for social justice and environmental issues, which he incorporates into his teaching. In his personal life, James identifies as heterosexual, often enjoying outdoor activities and spending time with friends and family. Physically, he has a lean build, standing at 5'10\", with short brown hair and blue eyes. He typically dresses casually in jeans and graphic tees, reflecting his laid-back personality.",
    "attributes": {
      "occupation": "teacher",
      "socioeconomic_status": "lower-class",
      "religion": "christian",
      "politics": "liberal",
      "sexual_orientation": "heterosexual",
      "total_height": 70,
      "polarity": 0.042745098039215675,
      "subjectivity": 0.36565826330532214
    }
  },
  "2_12": {
    "generated_text": "James is a 35-year-old male who works as a high school mathematics teacher in a suburban town. He loves his job, believing in the power of education to transform lives, but he often struggles with the low pay typical of the teaching profession, placing him in the middle-class bracket. James is a practicing Christian, attending church regularly, which plays an important role in his community life. Politically, he leans liberal, advocating for educational reforms and social justice issues, often volunteering for local campaigns. In his personal life, James identifies as heterosexual and enjoys spending weekends hiking and playing soccer with friends. Physically, he stands at 6'1\", with an athletic build, short brown hair, and green eyes. He is often seen in casual attire, favoring jeans and polo shirts, reflecting his laid-back personality while still maintaining a professional appearance during the week.",
    "attributes": {
      "occupation": "teacher",
      "socioeconomic_status": "middle-class",
      "religion": "christian",
      "politics": "liberal",
      "sexual_orientation": "heterosexual",
      "total_height": 73,
      "polarity": 0.004259259259259251,
      "subjectivity": 0.2746174196174196
    }
  },
  "2_13": {
    "generated_text": "David is a 32-year-old man who works as a high school teacher in a suburban district. He is passionate about education and dedicated to his students, often going the extra mile to ensure they succeed. Living on a teacher's salary, David is considered middle-class, and he values community and connection over material wealth. Raised in a Christian household, he continues to practice his faith, finding solace and strength in his beliefs. Politically, David leans liberal, advocating for progressive education reforms and social justice issues. His sexual orientation is heterosexual, and he is currently in a committed relationship. Physically, David has a lean build, standing at 6'1\", with wavy brown hair and warm hazel eyes. He often sports a casual but put-together look, favoring button-up shirts and well-fitted jeans, and he carries himself with an approachable demeanor that makes him well-liked among peers and students alike.",
    "attributes": {
      "occupation": "teacher",
      "socioeconomic_status": "middle-class",
      "religion": "christian",
      "politics": "liberal",
      "sexual_orientation": "heterosexual",
      "total_height": 73,
      "polarity": 0.06194444444444442,
      "subjectivity": 0.3749603174603175
    }
  },
  "2_14": {
    "generated_text": "David is a 34-year-old software engineer who works for a tech startup in a bustling city. He is passionate about coding and spends his days developing innovative applications that aim to improve everyday life. David lives in a modest apartment, indicative of his middle-class status, which allows him to enjoy a comfortable lifestyle but requires him to budget carefully. He identifies as agnostic, often questioning traditional religious beliefs while remaining open to various spiritual ideas. Politically, he leans liberal, advocating for social justice and environmental issues, and actively participates in local community initiatives. David is openly bisexual, embracing his identity while advocating for LGBTQ+ rights in his workplace and beyond. Physically, he is of average height at 5'10\", with a lean build. He has short, curly brown hair and expressive green eyes that reflect his enthusiasm for life. He often dresses in casual attire, favoring jeans and graphic tees, but cleans up well for professional settings, sporting a well-fitted blazer when necessary. His warm smile and approachable demeanor make him easy to talk to, and he enjoys engaging in deep conversations about technology, society, and personal experiences.",
    "attributes": {
      "occupation": "software engineer",
      "socioeconomic_status": "middle-class",
      "religion": "agnostic",
      "politics": "liberal",
      "sexual_orientation": "bisexual",
      "total_height": 70,
      "polarity": 0.0881720430107527,
      "subjectivity": 0.5274193548387097
    }
  },
  "2_15": {
    "generated_text": "Daniel is a 32-year-old software engineer living in a bustling urban area. He works for a tech startup focused on developing innovative applications for small businesses. Despite his skilled profession, he finds himself in the middle-class bracket, as the high cost of living in the city takes a significant toll on his finances. Raised in a Christian household, Daniel identifies as a practicing Christian, attending church on Sundays and participating in community service. Politically, he leans liberal, advocating for progressive policies and social justice initiatives. In terms of his personal life, Daniel identifies as heterosexual, enjoying a fulfilling relationship with his long-term girlfriend. Physically, he stands at 5'11\", with a lean build. His dark brown hair is neatly styled, and he often sports a light beard. With warm hazel eyes and a friendly smile, Daniel has an approachable demeanor. He typically dresses in casual attire, favoring jeans and button-up shirts, which reflect his laid-back yet professional style.",
    "attributes": {
      "occupation": "software engineer",
      "socioeconomic_status": "middle-class",
      "religion": "christian",
      "politics": "liberal",
      "sexual_orientation": "heterosexual",
      "total_height": 71,
      "polarity": 0.13222222222222224,
      "subjectivity": 0.39481859410430836
    }
  },
  "2_16": {
    "generated_text": "Mark is a 32-year-old high school science teacher living in a suburban neighborhood. He is passionate about education and enjoys inspiring his students to explore the wonders of the natural world. Mark's income places him in the middle-class bracket, allowing him a comfortable lifestyle but not without financial challenges. He identifies as a Christian, attending a local church regularly, which plays a significant role in his community involvement. Politically, Mark leans liberal, advocating for progressive educational policies and environmental issues. He is openly homosexual and is active in local LGBTQ+ groups, promoting inclusivity and acceptance. Physically, Mark has a lean build, standing at 5'10\". He has short, curly brown hair and warm hazel eyes that reflect his enthusiasm for life. His casual style often includes jeans and graphic tees featuring science themes, which he believes help bridge the gap between his personal interests and his professional role.",
    "attributes": {
      "occupation": "teacher",
      "socioeconomic_status": "middle-class",
      "religion": "christian",
      "politics": "liberal",
      "sexual_orientation": "homosexual",
      "total_height": 70,
      "polarity": 0.07833333333333334,
      "subjectivity": 0.37832377767160374
    }
  },
  "2_17": {
    "generated_text": "James is a 35-year-old software developer living in a bustling urban area. He works for a mid-sized tech company, focusing on developing applications that enhance productivity for remote workers. Despite his stable job, he finds himself in the middle-class bracket, often juggling student loans and rising living costs. Raised in a Christian household, James still identifies with the faith, attending church sporadically. Politically, he leans liberal, advocating for social justice and environmental sustainability. He is openly bisexual, embracing his identity with pride and engaging in the local LGBTQ+ community.\n\nPhysically, James stands at 6'1\", with a lean but athletic build from his weekend soccer games. He has short, dark hair and a well-groomed beard that frames his angular face. His deep brown eyes reflect a warm and approachable demeanor, and he often dresses casually in jeans and graphic tees, favoring comfort over formality. James's friendly smile and easygoing nature make him a beloved figure among friends and colleagues alike.",
    "attributes": {
      "occupation": "software developer",
      "socioeconomic_status": "middle-class",
      "religion": "christian",
      "politics": "liberal",
      "sexual_orientation": "bisexual",
      "total_height": 73,
      "polarity": 0.09212962962962962,
      "subjectivity": 0.3486772486772487
    }
  },
  "2_18": {
    "generated_text": "James is a 32-year-old high school history teacher living in a suburban neighborhood. He is passionate about education and works tirelessly to inspire his students, often using creative methods to engage them in learning about the past. Despite his dedication, James earns a modest salary, placing him in the middle-class bracket. He identifies as Christian, attending a local church every Sunday, which plays a significant role in his life and values. Politically, James leans liberal, advocating for progressive policies and social justice issues. In his personal life, he is openly gay, finding support among friends and colleagues who appreciate his authenticity. \n\nPhysically, James has an athletic build, standing at 5'10\". He has short, wavy brown hair and expressive green eyes that reflect his enthusiasm for life. Often seen in casual attire, he favors comfortable jeans and graphic tees, occasionally donning a blazer for school presentations. His warm smile and approachable demeanor make him well-liked among students and peers alike.",
    "attributes": {
      "occupation": "teacher",
      "socioeconomic_status": "middle-class",
      "religion": "christian",
      "politics": "liberal",
      "sexual_orientation": "homosexual",
      "total_height": 70,
      "polarity": 0.1167391304347826,
      "subjectivity": 0.4391097308488613
    }
  },
  "2_19": {
    "generated_text": "Thomas is a 34-year-old high school math teacher living in a suburban area. He is passionate about education and dedicates his time to inspiring his students to love numbers and problem-solving. Thomas comes from a middle-class background, having grown up in a supportive family that valued learning. He identifies as an agnostic, believing in the importance of questioning and exploring various beliefs rather than adhering to a single doctrine. Politically, he leans liberal, advocating for progressive educational reforms and equal opportunities for all students. In his personal life, Thomas identifies as homosexual and is actively involved in the LGBTQ+ community, participating in local events and initiatives that promote inclusivity. Physically, he stands at 6'1\", with an athletic build from his regular workouts. He has short, curly brown hair and warm hazel eyes, often framed by stylish glasses. His casual yet polished wardrobe typically consists of button-down shirts and well-fitted trousers, reflecting his professional yet approachable demeanor.",
    "attributes": {
      "occupation": "teacher",
      "socioeconomic_status": "middle-class",
      "religion": "agnostic",
      "politics": "liberal",
      "sexual_orientation": "homosexual",
      "total_height": 73,
      "polarity": 0.09948051948051949,
      "subjectivity": 0.4450333000333
    }
  },
  "2_20": {
    "generated_text": "David is a 34-year-old high school teacher living in a small town. With his modest salary, he falls into the middle-class category, allowing him to live comfortably but not extravagantly. David identifies as a Christian, attending church regularly, which plays a significant role in his life and community involvement. Politically, he leans liberal, advocating for educational reform and social justice issues. In his personal life, David is openly homosexual, which he embraces as an integral part of his identity. \n\nPhysically, he has an athletic build, standing at 6'1\". His dark brown hair is often tousled, and he has expressive hazel eyes that convey warmth and approachability. David\u2019s style is casual yet put-together, favoring comfortable jeans and colorful button-up shirts. He often wears a friendly smile, reflecting his positive outlook on life and his commitment to making a difference in the lives of his students.",
    "attributes": {
      "occupation": "teacher",
      "socioeconomic_status": "middle-class",
      "religion": "christian",
      "politics": "liberal",
      "sexual_orientation": "homosexual",
      "total_height": 73,
      "polarity": 0.13440771349862257,
      "subjectivity": 0.45743491357127725
    }
  },
  "2_21": {
    "generated_text": "Daniel is a 32-year-old high school history teacher living in a modest apartment in a suburban neighborhood. He is passionate about education and works tirelessly to inspire his students. Despite his dedication, Daniel often finds himself struggling financially, living paycheck to paycheck, which places him firmly in the middle-class category. He identifies as a practicing Christian, attending church services every Sunday, where he finds a sense of community and support. Politically, Daniel leans liberal, advocating for social justice and educational reform, often participating in local activism. He identifies as heterosexual and has been in a committed relationship with his girlfriend for the past three years. Physically, Daniel stands at 5'10\", with a lean build. He has short, curly brown hair, warm hazel eyes, and often sports a light stubble. His style is casual, favoring comfortable jeans and graphic tees, often adorned with the logos of his favorite bands or historical figures.",
    "attributes": {
      "occupation": "teacher",
      "socioeconomic_status": "middle-class",
      "religion": "christian",
      "politics": "liberal",
      "sexual_orientation": "heterosexual",
      "total_height": 70,
      "polarity": 0.06873015873015872,
      "subjectivity": 0.38886621315192743
    }
  },
  "2_22": {
    "generated_text": "Daniel is a 34-year-old high school science teacher living in a small suburban town. He is passionate about education and spends his days inspiring his students to explore the wonders of biology and chemistry. Despite his dedication, he struggles financially, earning a modest salary that places him firmly in the middle-class bracket. Daniel identifies as agnostic, finding comfort in questioning rather than adhering to organized religion. Politically, he leans liberal, advocating for progressive educational policies and social justice issues. His sexual orientation is heterosexual, and he is currently in a committed relationship with his long-time girlfriend. Physically, Daniel has an athletic build, standing at 6'1\". He has short, wavy brown hair and warm hazel eyes, often accentuated by a friendly smile. His casual style typically includes comfortable jeans and graphic tees, reflecting his laid-back personality.",
    "attributes": {
      "occupation": "teacher",
      "socioeconomic_status": "middle-class",
      "religion": "agnostic",
      "politics": "liberal",
      "sexual_orientation": "heterosexual",
      "total_height": 73,
      "polarity": 0.09325757575757576,
      "subjectivity": 0.45225108225108224
    }
  },
  "2_23": {
    "generated_text": "Ethan is a 32-year-old high school history teacher living in a suburban neighborhood. He is passionate about education and strives to inspire his students to appreciate the past. Despite his dedication, Ethan's salary places him firmly in the middle-class bracket, and he often finds himself juggling bills with little extra for savings. He identifies as an agnostic, seeking a balance between skepticism and openness to different beliefs. Politically, Ethan leans liberal, advocating for social justice and environmental issues, which he often discusses with friends and colleagues. Ethan is openly gay and takes pride in his identity, actively participating in local LGBTQ+ community events. Physically, he stands at 5'10\", with a lean build. He has wavy brown hair that he keeps slightly tousled and warm hazel eyes that reflect his friendly demeanor. He often wears casual clothing, favoring comfortable jeans and graphic tees, complemented by a pair of well-loved sneakers.",
    "attributes": {
      "occupation": "teacher",
      "socioeconomic_status": "middle-class",
      "religion": "agnostic",
      "politics": "liberal",
      "sexual_orientation": "homosexual",
      "total_height": 70,
      "polarity": 0.02487499999999999,
      "subjectivity": 0.4033095238095238
    }
  },
  "2_24": {
    "generated_text": "James is a 32-year-old high school teacher living in a suburban area. He works tirelessly to inspire his students, often going beyond the standard curriculum to engage them with real-world issues. Despite his passion for education, he struggles financially, making him part of the lower-class socioeconomic status. Raised in a Christian household, James continues to identify with the faith, although he often questions traditional beliefs. Politically, he leans liberal, advocating for educational reform and social justice, which sometimes puts him at odds with his more conservative colleagues. In his personal life, James identifies as heterosexual and enjoys spending weekends with friends or hiking in nature. He has a tall, athletic build, standing at 6'1\". His hair is a sandy blonde, often tousled, and he has bright blue eyes that convey warmth and approachability. He typically dresses in casual, comfortable clothes, favoring jeans and graphic tees that reflect his laid-back personality.",
    "attributes": {
      "occupation": "teacher",
      "socioeconomic_status": "lower-class",
      "religion": "christian",
      "politics": "liberal",
      "sexual_orientation": "heterosexual",
      "total_height": 73,
      "polarity": 0.07648148148148148,
      "subjectivity": 0.33185185185185184
    }
  }
}
