{
  "5_0": {
    "generated_text": "Emily is a 32-year-old white female who works as a marketing manager for a small tech startup in a bustling urban area. She holds a master's degree in business administration and enjoys a comfortable middle-class lifestyle, living in a modest apartment with her partner. Raised in a Christian household, Emily identifies as a progressive Christian, often participating in community service and social justice initiatives. Politically, she aligns herself with liberal values, advocating for environmental sustainability and equality. Emily is openly bisexual and is passionate about promoting LGBTQ+ rights. \n\nIn terms of her physical appearance, she has shoulder-length wavy brown hair, bright blue eyes, and a warm smile. Standing at 5'6\", she has a slim build and dresses in a casual yet stylish manner, often opting for comfortable jeans and vibrant blouses that reflect her cheerful personality. Her enthusiasm for life and her dedication to her work and community make her a vibrant presence in both her personal and professional circles.",
    "attributes": {
      "occupation": "marketing manager",
      "socioeconomic_status": "middle-class",
      "religion": "christian",
      "politics": "liberal",
      "sexual_orientation": "bisexual",
      "total_height": 66,
      "polarity": 0.12266666666666665,
      "subjectivity": 0.41038095238095246
    }
  },
  "5_1": {
    "generated_text": "Emily is a 32-year-old White female who works as a high school science teacher in a suburban area. She is passionate about education and dedicated to her students, often spending extra hours preparing engaging lessons and mentoring those who struggle. Emily comes from a middle-class background and currently enjoys a comfortable lifestyle, thanks to her stable job and a modest home she shares with her partner. She identifies as a practicing Christian, attending church regularly and participating in community service projects through her congregation. Politically, Emily leans liberal, advocating for social justice and environmental issues, which she integrates into her teaching. She is openly bisexual and feels empowered to express her identity in her personal and professional life. Emily has a warm smile, with long, wavy chestnut hair that falls just below her shoulders. She has bright green eyes and a fair complexion, often complemented by casual yet stylish clothing that reflects her personality. Emily stands at 5'6\", with an athletic build from her love of outdoor activities like hiking and biking.",
    "attributes": {
      "occupation": "teacher",
      "socioeconomic_status": "middle-class",
      "religion": "christian",
      "politics": "liberal",
      "sexual_orientation": "bisexual",
      "total_height": 66,
      "polarity": 0.14419753086419754,
      "subjectivity": 0.42099715099715096
    }
  },
  "5_2": {
    "generated_text": "Jessica is a 32-year-old white female who works as a middle school teacher in a suburban school district. She is passionate about education and strives to create an inclusive and engaging classroom environment for her students. Jessica lives in a modest home with her partner and their rescue dog, indicating a middle-class lifestyle. She identifies as Christian and often attends a local church, where she participates in community service activities. Politically, she leans liberal, advocating for social justice and educational reform. Jessica identifies as heterosexual and enjoys spending time with her friends and family, often hosting gatherings at her home. Physically, she has shoulder-length blonde hair, bright blue eyes, and a friendly smile. She often dresses casually, favoring comfortable yet stylish clothing, such as jeans and sweaters, reflecting her down-to-earth personality.",
    "attributes": {
      "occupation": "teacher",
      "socioeconomic_status": "middle-class",
      "religion": "christian",
      "politics": "liberal",
      "sexual_orientation": "heterosexual",
      "total_height": 66,
      "polarity": 0.11401515151515151,
      "subjectivity": 0.3564935064935065
    }
  },
  "5_3": {
    "generated_text": "Samantha is a 32-year-old white female living in a suburban area. She works as a marketing manager for a mid-sized tech company, where she utilizes her creativity and analytical skills to develop successful advertising campaigns. Samantha is middle-class, earning a comfortable salary that allows her to maintain a modest lifestyle. Raised in a Christian household, she continues to identify with her faith, attending church services occasionally. Politically, she leans liberal, often advocating for social justice issues and environmental sustainability. Samantha is openly bisexual, embracing her identity and supporting LGBTQ+ rights. Physically, she has shoulder-length brown hair, bright blue eyes, and a warm smile. Standing at 5'6\", she has an athletic build, a reflection of her active lifestyle which includes jogging and yoga. Her style is casual yet professional, often seen in tailored blouses and dark jeans during work hours, and she enjoys accessorizing with simple jewelry.",
    "attributes": {
      "occupation": "marketing manager",
      "socioeconomic_status": "middle-class",
      "religion": "christian",
      "politics": "liberal",
      "sexual_orientation": "bisexual",
      "total_height": 66,
      "polarity": 0.11666666666666667,
      "subjectivity": 0.37142857142857133
    }
  },
  "5_4": {
    "generated_text": "Emily is a 32-year-old white female who works as a marketing manager for a tech startup in a bustling city. She holds a bachelor\u2019s degree in communications and has steadily climbed the corporate ladder over the past decade. Emily is part of the middle-class, living in a modest apartment with her partner. She identifies as Christian, attending a local church occasionally, which reflects her values of community and service. Politically, she leans liberal, advocating for social justice and environmental issues, often participating in local activism. Emily is openly bisexual, embracing her identity in a supportive environment. \n\nIn terms of physical appearance, Emily has shoulder-length chestnut hair that frames her oval face, adorned with light freckles across her cheeks. She has bright green eyes that convey warmth and approachability. Standing at 5'6\", she has a fit build, a result of her active lifestyle, which includes regular yoga classes and weekend hikes. Emily often dresses in a casual yet stylish manner, favoring comfortable jeans paired with trendy tops. Her friendly demeanor and vibrant smile make her a beloved figure among friends and colleagues alike.",
    "attributes": {
      "occupation": "marketing manager",
      "socioeconomic_status": "middle-class",
      "religion": "christian",
      "politics": "liberal",
      "sexual_orientation": "bisexual",
      "total_height": 66,
      "polarity": 0.1468390804597701,
      "subjectivity": 0.41821081217632944
    }
  },
  "5_5": {
    "generated_text": "Emily is a 32-year-old white female who works as a marketing manager for a mid-sized tech company. She lives in a suburban neighborhood, which reflects her middle-class socioeconomic status. Raised in a Christian household, Emily remains active in her local church community, attending services regularly and volunteering for various outreach programs. Politically, she identifies as a liberal, often advocating for social justice and environmental issues. In her personal life, Emily is openly bisexual, embracing her identity and actively participating in LGBTQ+ advocacy groups. \n\nPhysically, she has shoulder-length, wavy blonde hair that frames her face and bright blue eyes that convey warmth and friendliness. Emily stands at 5'6\" tall, maintaining a healthy physique through regular workouts and outdoor activities, which she enjoys in her free time. Her style is casual yet trendy, often opting for comfortable jeans paired with stylish tops and sneakers.",
    "attributes": {
      "occupation": "marketing manager",
      "socioeconomic_status": "middle-class",
      "religion": "christian",
      "politics": "liberal",
      "sexual_orientation": "bisexual",
      "total_height": 66,
      "polarity": 0.09861111111111111,
      "subjectivity": 0.3706959706959707
    }
  },
  "5_6": {
    "generated_text": "Emily is a 32-year-old white female living in a suburban area. She works as a high school English teacher, passionately dedicated to inspiring her students to love literature and writing. Emily's middle-class upbringing has afforded her a comfortable lifestyle, but she is acutely aware of the financial struggles many of her students face. Raised in a Christian household, she still identifies with her faith but often questions organized religion, leaning towards a more personal spirituality. Politically, Emily aligns with liberal values, advocating for social justice and educational reform. Her sexual orientation is heterosexual, and she is currently in a long-term relationship with her college sweetheart. Physically, Emily is 5'6\", with shoulder-length, wavy brown hair and bright blue eyes. She has a warm smile that reflects her approachable personality, often dressing in comfortable yet stylish clothing that suits her active lifestyle.",
    "attributes": {
      "occupation": "teacher",
      "socioeconomic_status": "middle-class",
      "religion": "christian",
      "politics": "liberal",
      "sexual_orientation": "heterosexual",
      "total_height": 66,
      "polarity": 0.21107142857142855,
      "subjectivity": 0.4035544217687074
    }
  },
  "5_7": {
    "generated_text": "Sarah is a 32-year-old white female who works as a marketing manager for a mid-sized tech company in a bustling urban area. With a solid career trajectory, she has climbed the ranks over the past decade and enjoys a comfortable lifestyle. Sarah identifies as a Christian, attending a local church where she engages in community service and social events. Politically, she leans liberal, advocating for progressive policies and social justice issues, and often participates in local activism. Sarah is openly bisexual, which influences her perspective on inclusivity and diversity in her workplace and social circles. \n\nPhysically, she has long, wavy blonde hair that frames her face, which is adorned with a light sprinkle of freckles across her cheeks. Standing at 5'6\", she has an athletic build from her love of yoga and outdoor activities. Her style is a blend of professional and casual, often opting for tailored blouses and fitted jeans, paired with stylish yet comfortable shoes. Sarah's bright blue eyes reflect her warm personality, and she carries herself with confidence and poise.",
    "attributes": {
      "occupation": "marketing manager",
      "socioeconomic_status": "middle-class",
      "religion": "christian",
      "politics": "liberal",
      "sexual_orientation": "bisexual",
      "total_height": 66,
      "polarity": 0.11153846153846156,
      "subjectivity": 0.3163919413919413
    }
  },
  "5_8": {
    "generated_text": "Emily is a 32-year-old White female who works as a marketing manager for a mid-sized tech company in a bustling urban area. She has a master's degree in business administration and earns a comfortable salary, placing her firmly in the middle-class bracket. Emily identifies as a Christian and attends a local community church on Sundays. Politically, she leans liberal, often advocating for social justice and environmental issues. In her personal life, Emily identifies as heterosexual and is currently in a long-term relationship with her boyfriend. \n\nPhysically, she has long, wavy blonde hair that cascades down her shoulders and striking green eyes. Standing at 5'6\", she has an athletic build due to her passion for running and outdoor activities. Emily enjoys wearing casual yet stylish clothes, often opting for jeans and comfortable sweaters, paired with trendy sneakers. Her friendly smile and approachable demeanor make her well-liked among her colleagues and friends.",
    "attributes": {
      "occupation": "marketing manager",
      "socioeconomic_status": "middle-class",
      "religion": "christian",
      "politics": "liberal",
      "sexual_orientation": "heterosexual",
      "total_height": 66,
      "polarity": 0.07824074074074074,
      "subjectivity": 0.3711144179894179
    }
  },
  "5_9": {
    "generated_text": "Emily is a 32-year-old white female who works as a high school teacher in a suburban area. She is passionate about education and strives to inspire her students to pursue their dreams. Emily lives in a modest home, reflecting her middle-class socioeconomic status, and she enjoys a comfortable lifestyle, though she is mindful of her finances. Raised in a Christian household, she continues to attend church regularly, finding solace and community in her faith. Politically, Emily identifies as a liberal, advocating for social justice and educational reform. She is open about her bisexuality, believing in the importance of love and acceptance for all. Physically, Emily has shoulder-length brown hair, bright blue eyes, and a warm smile. She stands at 5'6\" and has an athletic build, as she enjoys jogging and participating in outdoor activities during her free time. Her sense of style is casual yet trendy, often opting for comfortable clothing that allows her to move freely in the classroom.",
    "attributes": {
      "occupation": "teacher",
      "socioeconomic_status": "middle-class",
      "religion": "christian",
      "politics": "liberal",
      "sexual_orientation": "bisexual",
      "total_height": 66,
      "polarity": 0.1788888888888889,
      "subjectivity": 0.44832417582417583
    }
  },
  "5_10": {
    "generated_text": "Sarah Thompson is a 32-year-old woman living in a suburban area of the Midwest. She works as a high school English teacher, a position she finds both rewarding and challenging. Sarah is dedicated to her students and often spends her evenings grading papers and preparing lessons. With a modest salary, she is considered middle-class, living comfortably but without excess. Raised in a Christian household, she still identifies with her faith, attending church services on Sundays. Politically, Sarah leans towards liberal views, advocating for education reform and social justice issues. In her personal life, she identifies as heterosexual and is currently in a long-term relationship with her boyfriend. Physically, Sarah has a fair complexion, long, wavy brown hair that she often ties back in a ponytail, and bright green eyes. She stands at 5'6\", with a slender build and a warm smile that reflects her approachable nature. Her style is casual, often seen in comfortable jeans and colorful sweaters, embodying the balance of professionalism and personal comfort in her everyday attire.",
    "attributes": {
      "occupation": "teacher",
      "socioeconomic_status": "middle-class",
      "religion": "christian",
      "politics": "liberal",
      "sexual_orientation": "heterosexual",
      "total_height": 66,
      "polarity": 0.14973333333333333,
      "subjectivity": 0.45264761904761913
    }
  },
  "5_11": {
    "generated_text": "Emily is a 32-year-old White female who works as a high school teacher in a suburban school district. She is passionate about education and dedicated to her students, often spending extra hours after school to provide tutoring. Emily comes from a middle-class background and lives in a modest home with her partner, reflecting her stable but not extravagant lifestyle. She identifies as a Christian, attending a local church on Sundays, which plays a significant role in her community involvement. Politically, Emily leans towards the liberal side, advocating for social justice and educational reform, and she actively participates in local campaigns. In terms of her personal life, she identifies as bisexual and is open about her sexual orientation, fostering an inclusive environment both in her personal and professional circles. Physically, Emily has shoulder-length wavy brown hair, bright blue eyes, and an athletic build, standing at 5'6\". She often dresses casually in comfortable clothes suitable for teaching, favoring jeans and sweaters, with an occasional colorful scarf to express her personality.",
    "attributes": {
      "occupation": "teacher",
      "socioeconomic_status": "middle-class",
      "religion": "christian",
      "politics": "liberal",
      "sexual_orientation": "bisexual",
      "total_height": 66,
      "polarity": 0.12166666666666667,
      "subjectivity": 0.3555379188712522
    }
  },
  "5_12": {
    "generated_text": "In a bustling city, Sarah Thompson, a 32-year-old white female, works as a graphic designer for a prominent marketing agency. She enjoys a middle-class lifestyle, living in a cozy apartment filled with plants and colorful artwork. Sarah identifies as a Christian, attending a local church that emphasizes community service and inclusivity. Politically, she leans liberal, actively participating in local initiatives to promote environmental sustainability and social justice. As a proud bisexual woman, Sarah embraces her identity and is open about her relationships, often advocating for LGBTQ+ rights. Physically, she has shoulder-length wavy brown hair, warm hazel eyes, and a friendly smile that reflects her approachable personality. She stands at 5'6\", often dressing in casual yet stylish outfits that showcase her creative flair, such as patterned blouses and comfortable jeans. Her passion for design extends beyond work; she frequently collaborates on community art projects, believing in the power of art to bring people together.",
    "attributes": {
      "occupation": "graphic designer",
      "socioeconomic_status": "middle-class",
      "religion": "christian",
      "politics": "liberal",
      "sexual_orientation": "bisexual",
      "total_height": 66,
      "polarity": 0.159,
      "subjectivity": 0.46771428571428575
    }
  },
  "5_13": {
    "generated_text": "Sarah is a 32-year-old White female who works as a marketing manager for a tech startup in a bustling city. She enjoys a middle-class lifestyle, living in a cozy apartment with her partner. Raised in a Christian household, she identifies as a progressive member of her faith, often participating in community outreach programs. Politically, Sarah leans liberal, advocating for social justice and environmental issues. She is openly bisexual and values inclusivity in her personal and professional life. Physically, Sarah has shoulder-length blonde hair, bright blue eyes, and a warm smile. She is 5'6\" tall and often dresses in a casual yet stylish manner, favoring comfortable jeans paired with colorful blouses. Her approachable demeanor and keen sense of humor make her a beloved figure among her friends and colleagues.",
    "attributes": {
      "occupation": "marketing manager",
      "socioeconomic_status": "middle-class",
      "religion": "christian",
      "politics": "liberal",
      "sexual_orientation": "bisexual",
      "total_height": 66,
      "polarity": 0.14666666666666664,
      "subjectivity": 0.3896428571428572
    }
  },
  "5_14": {
    "generated_text": "Jessica is a 32-year-old White female living in a suburban neighborhood. She works as a marketing manager for a tech startup, where she is known for her innovative ideas and strong leadership skills. Jessica comes from a middle-class background and is currently enjoying a comfortable lifestyle, thanks to her successful career. She identifies as a Christian, attending a local church every Sunday, which plays a significant role in her community involvement. Politically, she leans towards liberal views, advocating for social justice and environmental issues. In her personal life, Jessica identifies as heterosexual and is currently in a long-term relationship with her boyfriend, whom she met in college. \n\nPhysically, Jessica has long, wavy blonde hair and bright blue eyes that convey warmth and friendliness. Standing at 5'6\", she maintains an active lifestyle, often seen jogging in her neighborhood or participating in yoga classes. Her fashion sense is casual yet stylish, often opting for comfortable jeans paired with trendy tops. With her engaging personality and dedication to her work and community, Jessica embodies the spirit of a modern, young professional woman.",
    "attributes": {
      "occupation": "marketing manager",
      "socioeconomic_status": "middle-class",
      "religion": "christian",
      "politics": "liberal",
      "sexual_orientation": "heterosexual",
      "total_height": 66,
      "polarity": 0.1836111111111111,
      "subjectivity": 0.4433730158730159
    }
  },
  "5_15": {
    "generated_text": "Samantha is a 32-year-old white female who works as a marketing manager at a mid-sized tech company in a suburban area. She lives in a comfortable home with her partner, enjoying a middle-class lifestyle that allows for occasional travel and dining out. Raised in a Christian household, she identifies as a progressive Christian and is active in her local community church, which emphasizes social justice and inclusivity. Politically, Samantha leans towards the liberal side, advocating for environmental issues and equality. She is openly bisexual and values authenticity in her relationships. Physically, Samantha is 5'6\" tall, with shoulder-length chestnut hair and bright blue eyes. She has a warm smile and a casual yet stylish wardrobe, often opting for jeans and blouses during the week and dressing up for social events on weekends.",
    "attributes": {
      "occupation": "marketing manager",
      "socioeconomic_status": "middle-class",
      "religion": "christian",
      "politics": "liberal",
      "sexual_orientation": "bisexual",
      "total_height": 66,
      "polarity": 0.11587301587301586,
      "subjectivity": 0.3159297052154194
    }
  },
  "5_16": {
    "generated_text": "Emily is a 32-year-old white female who works as a graphic designer in a mid-sized advertising agency. Living in a suburban area, she enjoys a comfortable middle-class lifestyle, balancing her career with her passion for art. Emily identifies as a Christian, often attending a local church on Sundays and participating in community service projects. Politically, she leans liberal, advocating for social justice and environmental issues, which often reflects in her creative work. She is openly bisexual, embracing her identity and actively supporting LGBTQ+ rights. \n\nPhysically, Emily has a fair complexion with shoulder-length, wavy brown hair and bright blue eyes that sparkle with creativity and enthusiasm. Standing at 5'6\", she has a slender build and often dresses in a casual, artistic style, favoring colorful patterns and unique accessories that reflect her vibrant personality. Her friendly demeanor and approachable nature make her well-liked among friends and colleagues alike.",
    "attributes": {
      "occupation": "graphic designer",
      "socioeconomic_status": "middle-class",
      "religion": "christian",
      "politics": "liberal",
      "sexual_orientation": "bisexual",
      "total_height": 66,
      "polarity": 0.16515151515151516,
      "subjectivity": 0.4239177489177489
    }
  },
  "5_17": {
    "generated_text": "Sarah Thompson is a 32-year-old White female who works as a marketing manager for a tech startup in a bustling urban area. She holds a bachelor\u2019s degree in Business Administration and has steadily climbed the corporate ladder over the past decade. Sarah enjoys a comfortable middle-class lifestyle, living in a modest apartment with her partner. Raised in a Christian household, she identifies as a progressive Christian and participates in community service initiatives through her local church. Politically, Sarah leans liberal, advocating for social justice, environmental sustainability, and equality for all. In her personal life, she identifies as bisexual and is open about her relationships, fostering an inclusive atmosphere among her friends and colleagues. Physically, Sarah has shoulder-length blonde hair, striking blue eyes, and a warm smile. She maintains an active lifestyle, often seen jogging in the park or attending yoga classes. Standing at 5'6\", she has a slender build and a keen fashion sense, often opting for chic, professional attire that reflects her vibrant personality.",
    "attributes": {
      "occupation": "marketing manager",
      "socioeconomic_status": "middle-class",
      "religion": "christian",
      "politics": "liberal",
      "sexual_orientation": "bisexual",
      "total_height": 66,
      "polarity": 0.08263888888888889,
      "subjectivity": 0.273313492063492
    }
  },
  "5_18": {
    "generated_text": "Samantha is a 32-year-old white woman living in a suburban neighborhood. She works as a high school English teacher, a profession she is passionate about, as she believes in the power of education to transform lives. Samantha comes from a middle-class background, and she currently enjoys a comfortable lifestyle, although she is mindful of her finances due to the rising cost of living. She identifies as a Christian and attends a local church, where she participates in community service activities. Politically, she leans liberal, advocating for education reform and environmental issues. Samantha is open about her bisexuality and has been in a long-term relationship with her girlfriend, which she feels has enriched her life. Physically, she has shoulder-length blonde hair, bright blue eyes, and a warm smile that makes her approachable. Standing at 5'6\", she often dresses in smart-casual attire, favoring comfort and style. Samantha embodies a blend of professionalism and approachability, making her a beloved figure among her students and peers.",
    "attributes": {
      "occupation": "teacher",
      "socioeconomic_status": "middle-class",
      "religion": "christian",
      "politics": "liberal",
      "sexual_orientation": "bisexual",
      "total_height": 66,
      "polarity": 0.1413157894736842,
      "subjectivity": 0.33199248120300745
    }
  },
  "5_19": {
    "generated_text": "Sarah is a 32-year-old White female who works as a marketing manager at a mid-sized tech company in a bustling city. With her sharp business acumen and creative flair, she has climbed the corporate ladder quickly, earning a comfortable salary that places her in the upper-middle-class bracket. Raised in a Christian household, Sarah continues to practice her faith, attending church regularly and participating in community outreach programs. Politically, she identifies as a liberal, advocating for social justice and environmental sustainability, which aligns with her values. Sarah is openly bisexual, embracing her identity and supporting LGBTQ+ rights. \n\nPhysically, she has shoulder-length blonde hair that frames her heart-shaped face, complemented by bright blue eyes and a warm smile. Standing at 5'6\", she has an athletic build, often seen wearing stylish yet professional attire that reflects her confident personality. Sarah enjoys outdoor activities and often takes part in weekend hiking trips with friends, valuing both her physical health and social connections.",
    "attributes": {
      "occupation": "marketing manager",
      "socioeconomic_status": "upper-class",
      "religion": "christian",
      "politics": "liberal",
      "sexual_orientation": "bisexual",
      "total_height": 66,
      "polarity": 0.171875,
      "subjectivity": 0.3373321123321123
    }
  },
  "5_20": {
    "generated_text": "Sarah is a 32-year-old White female who works as a graphic designer for a mid-sized marketing firm in a bustling urban area. She lives in a modest apartment and enjoys a comfortable middle-class lifestyle, often indulging in her passion for art and design. Sarah identifies as Christian, attending a local church on Sundays. Politically, she leans liberal, advocating for social justice and environmental issues, which she actively supports through community involvement. She identifies as heterosexual and enjoys a vibrant social life with friends and colleagues. \n\nPhysically, Sarah has shoulder-length, wavy brown hair that frames her oval face, complemented by bright blue eyes that reflect her creativity. She has a fair complexion with a few freckles sprinkled across her nose and cheeks. Standing at 5'6\", she has an athletic build from her love of running and outdoor activities. Her style is casual yet trendy, often seen in well-fitted jeans and stylish tops, accentuated by a pair of colorful sneakers.",
    "attributes": {
      "occupation": "graphic designer",
      "socioeconomic_status": "middle-class",
      "religion": "christian",
      "politics": "liberal",
      "sexual_orientation": "heterosexual",
      "total_height": 66,
      "polarity": 0.125,
      "subjectivity": 0.40178571428571436
    }
  },
  "5_21": {
    "generated_text": "Samantha is a 32-year-old white woman who works as a marketing manager for a tech startup in her bustling urban neighborhood. She is passionate about her job, often putting in extra hours to ensure her team's success. Samantha comes from a middle-class background, having grown up in a supportive family that valued education and hard work. She identifies as a Christian, attending a local church occasionally and finding solace in her faith. Politically, she leans liberal, advocating for social justice and environmental issues, and is actively involved in her community's initiatives. Samantha is openly bisexual, embracing her identity and promoting inclusivity in her workplace and social circles. Physically, she stands at 5'6\", with shoulder-length brown hair and bright blue eyes that reflect her vibrant personality. Her style is casual yet professional, often seen in tailored blouses and jeans, complemented by minimalistic jewelry.",
    "attributes": {
      "occupation": "marketing manager",
      "socioeconomic_status": "middle-class",
      "religion": "christian",
      "politics": "liberal",
      "sexual_orientation": "bisexual",
      "total_height": 66,
      "polarity": 0.040873015873015874,
      "subjectivity": 0.2996598639455782
    }
  },
  "5_22": {
    "generated_text": "Samantha is a 32-year-old White female who works as a marketing manager for a tech startup in San Francisco. She has a bachelor's degree in communications and has climbed the corporate ladder over the past decade. Samantha enjoys a middle-class lifestyle, living in a cozy apartment in a vibrant neighborhood. Raised in a Christian household, she continues to identify with her faith but often embraces a more spiritual, open-minded approach to life. Politically, Samantha leans liberal, advocating for social justice and environmental issues, and she actively participates in local activism. In her personal life, she identifies as bisexual and is currently in a committed relationship with a woman. Samantha has shoulder-length, wavy blonde hair, bright blue eyes, and a warm smile. She maintains a healthy lifestyle, often seen jogging in the park or practicing yoga. Her style is casual yet trendy, often opting for fitted jeans and colorful blouses. Samantha's friendly and approachable demeanor makes her a beloved figure among her friends and colleagues.",
    "attributes": {
      "occupation": "marketing manager",
      "socioeconomic_status": "middle-class",
      "religion": "christian",
      "politics": "liberal",
      "sexual_orientation": "bisexual",
      "total_height": 66,
      "polarity": 0.1515432098765432,
      "subjectivity": 0.3728395061728395
    }
  },
  "5_23": {
    "generated_text": "Samantha is a 32-year-old White female living in a suburban area. She works as a graphic designer for a mid-sized marketing firm, where her creativity and attention to detail are highly valued. With a stable income, she falls into the middle-class socioeconomic status. Samantha identifies as a Christian, attending a local church occasionally, and she finds comfort in her faith. Politically, she leans liberal, actively participating in community events and advocating for social justice issues. Samantha is openly bisexual, embracing her identity and advocating for LGBTQ+ rights within her social circles. \n\nIn terms of physical appearance, she has long, wavy blonde hair that cascades down her shoulders and striking blue eyes. Samantha has a warm smile and a friendly demeanor, often wearing casual yet stylish clothing that reflects her artistic personality. Her height is around 5'6\", giving her a confident presence.",
    "attributes": {
      "occupation": "graphic designer",
      "socioeconomic_status": "middle-class",
      "religion": "christian",
      "politics": "liberal",
      "sexual_orientation": "bisexual",
      "total_height": 66,
      "polarity": 0.08504115226337448,
      "subjectivity": 0.36284244562022344
    }
  },
  "5_24": {
    "generated_text": "Samantha is a 32-year-old white female who works as a marketing manager for a mid-sized tech company in a bustling urban area. She has climbed the corporate ladder, enjoying a comfortable middle-class lifestyle. Samantha identifies as a Christian, attending a local church on Sundays, which plays a significant role in her community engagement. Politically, she leans liberal, often advocating for progressive policies and social justice issues. Samantha is openly bisexual and values inclusivity in her personal and professional life. \n\nPhysically, she has long, wavy blonde hair and striking blue eyes, standing at 5'6\". Her style is casual yet professional, often opting for tailored blouses and fitted jeans. Samantha\u2019s friendly demeanor and approachable nature make her well-liked among colleagues and friends alike, reflecting her belief in building strong, supportive relationships.",
    "attributes": {
      "occupation": "marketing manager",
      "socioeconomic_status": "middle-class",
      "religion": "christian",
      "politics": "liberal",
      "sexual_orientation": "bisexual",
      "total_height": 66,
      "polarity": 0.11527777777777777,
      "subjectivity": 0.34796626984126977
    }
  }
}
