{"245_0": {"generated_text": "Tenzin is a dedicated environmental scientist working for a non-profit organization focused on climate change mitigation. With a passion for sustainability, he spends his days researching renewable energy solutions and advocating for eco-friendly policies. Tenzin is of middle-class socioeconomic status, having earned a respectable income that allows him to live comfortably but not extravagantly. He identifies as Buddhist, drawing inspiration from the teachings of compassion and mindfulness, which influence both his personal and professional life. Politically, Tenzin leans liberal, actively supporting initiatives aimed at environmental protection and social justice. He is openly bisexual, embracing his identity and advocating for LGBTQ+ rights within his community. \n\nPhysically, Tenzin has an athletic build, standing at 5'10\". He has dark brown hair, often tied back in a bun, and warm brown eyes that reflect his kind demeanor. Tenzin typically dresses in practical attire suitable for fieldwork, often seen in cargo pants and breathable shirts, with a penchant for earthy tones that align with his environmental ethos.", "attributes": {"occupation": "environmental scientist", "socioeconomic_status": "middle-class", "religion": "buddhist", "politics": "liberal", "sexual_orientation": "bisexual", "total_height": 70, "polarity": 0.17831439393939397, "subjectivity": 0.4005952380952381}}, "245_1": {"generated_text": "Tenzin is a dedicated school teacher living in a bustling urban neighborhood. He works at a local public school, where he teaches science to middle school students, inspiring them to explore the wonders of the natural world. Tenzin\u2019s passion for education stems from his own experiences growing up in a lower-class family, which instilled in him the value of hard work and perseverance. He identifies as a Buddhist, finding solace and guidance in the teachings of compassion and mindfulness. Politically, Tenzin leans towards liberal views, advocating for educational reforms and social justice issues that affect marginalized communities. In terms of his personal life, Tenzin is openly homosexual and actively participates in local LGBTQ+ advocacy groups, promoting inclusivity and acceptance. He has a distinctive appearance, standing at 5'8\" with a lean build. Tenzin has warm brown skin, expressive dark eyes, and often sports a friendly smile. He usually dresses in comfortable, casual clothing, favoring earth tones that reflect his connection to nature and his calming personality.", "attributes": {"occupation": "teacher", "socioeconomic_status": "lower-class", "religion": "buddhist", "politics": "liberal", "sexual_orientation": "homosexual", "total_height": 68, "polarity": 0.11449275362318838, "subjectivity": 0.4061594202898551}}, "245_2": {"generated_text": "Tenzin is a 32-year-old Tibetan-American who works as a community organizer focused on social justice and environmental issues. He is deeply committed to advocating for the rights of marginalized communities, particularly those impacted by climate change and economic inequality. Tenzin grew up in a working-class family, which has influenced his dedication to uplifting others in similar situations. He identifies as a Buddhist, drawing strength and inspiration from his spiritual beliefs to guide his activism and foster a sense of community. Politically, Tenzin leans liberal, often participating in grassroots campaigns and rallies that promote progressive policies. He is openly bisexual and believes in the importance of inclusivity within both his personal life and professional endeavors. Physically, Tenzin has a lean build, standing at 5'10\", with shoulder-length black hair often tied back and warm brown eyes that reflect his compassionate nature. He tends to dress in comfortable, casual clothing, often adorned with symbols of peace and environmental sustainability, embodying his commitment to both his heritage and his causes.", "attributes": {"occupation": "community organizer", "socioeconomic_status": "middle-class", "religion": "buddhist", "politics": "liberal", "sexual_orientation": "bisexual", "total_height": 70, "polarity": 0.052083333333333336, "subjectivity": 0.3360119047619048}}, "245_3": {"generated_text": "Tenzin is a 34-year-old Tibetan man who works as a yoga instructor and wellness coach in a bustling urban center. He leads classes that blend traditional Tibetan practices with modern mindfulness techniques, attracting a diverse clientele. Tenzin is of middle-class socioeconomic status, having built a stable career through dedication and passion for holistic health. He identifies as a practicing Buddhist, which greatly influences his lifestyle and approach to wellness. Politically, Tenzin leans towards liberal views, advocating for environmental sustainability and social justice. He is openly homosexual and actively participates in community events that promote LGBTQ+ rights. Tenzin has a lean build, standing at 5'8\". His dark hair is often tied back in a neat bun, and he has warm brown eyes that reflect his compassionate nature. He typically dresses in comfortable, flowy clothing that allows for ease of movement, often opting for earthy tones that resonate with his spiritual beliefs.", "attributes": {"occupation": "yoga instructor", "socioeconomic_status": "middle-class", "religion": "buddhist", "politics": "liberal", "sexual_orientation": "homosexual", "total_height": 68, "polarity": 0.09888888888888889, "subjectivity": 0.37333333333333335}}, "245_4": {"generated_text": "Tenzin is a dedicated social worker in a bustling urban environment, striving to improve the lives of underprivileged families. He is in his mid-30s and has devoted his career to advocating for mental health services and community support programs. As a member of the lower-middle class, Tenzin often faces financial challenges, but his passion for helping others keeps him motivated. He identifies as Buddhist, finding strength and solace in his spiritual practices, which guide his empathetic approach to his work. Politically, Tenzin leans liberal, supporting policies that promote social justice and equality. He is openly homosexual and actively participates in local LGBTQ+ advocacy groups, working to create a more inclusive community. Physically, Tenzin stands at 5'9\", with a lean build, warm brown skin, and short black hair. His expressive brown eyes reflect his compassion and determination, and he often dresses in casual yet professional attire, favoring comfort and practicality in his daily interactions.", "attributes": {"occupation": "social worker", "socioeconomic_status": "lower-middle-class", "religion": "buddhist", "politics": "liberal", "sexual_orientation": "homosexual", "total_height": 69, "polarity": 0.07083333333333333, "subjectivity": 0.29297619047619045}}, "246_0": {"generated_text": "Selina is a passionate environmental activist who works as a community organizer for a local nonprofit focused on sustainability initiatives. She is in her early thirties and lives in a modest apartment in an urban area, making her part of the middle-class. Raised in a Christian household, she identifies as a progressive Christian and often integrates her faith with her activism, believing in stewardship of the Earth. Politically, Selina leans liberal, advocating for policies that address climate change and social justice. She identifies as bisexual, embracing a diverse community of friends and allies who support her causes. \n\nPhysically, Selina has an athletic build, standing at 5'6\". She has curly brown hair that she usually wears in a ponytail, bright green eyes, and a warm smile. Her style is casual and practical, often opting for eco-friendly clothing brands. She loves to wear earthy tones and is rarely seen without her favorite pair of worn-in hiking boots, which symbolize her love for the outdoors. Selina\u2019s vibrant personality and dedication to her work make her a well-respected figure in her community.", "attributes": {"occupation": "community organizer", "socioeconomic_status": "middle-class", "religion": "christian", "politics": "liberal", "sexual_orientation": "bisexual", "total_height": 66, "polarity": 0.11499999999999999, "subjectivity": 0.40547619047619043}}, "246_1": {"generated_text": "Selina is a dedicated nurse in her early thirties, working tirelessly in a community hospital in a bustling urban area. She hails from a lower-middle-class background, having grown up in a modest household where her parents emphasized the importance of education and hard work. Raised in a Christian household, Selina attends church sporadically, finding comfort in her faith but often questioning traditional doctrines. Politically, she leans liberal, advocating for healthcare reform and social justice issues, which she believes are crucial for the well-being of her community. Selina identifies as bisexual, navigating her relationships with an open heart and mind. \n\nPhysically, she stands at 5'6\", with a warm smile that lights up her face. Her long, curly brown hair is usually pulled back into a practical ponytail while she\u2019s at work, but she loves to let it down on her days off. Her hazel eyes reflect her compassion and determination, and she has a few small tattoos that express her individuality and personal beliefs. Selina\u2019s style is typically casual, favoring comfortable scrubs during her shifts and relaxed, bohemian outfits in her free time.", "attributes": {"occupation": "nurse", "socioeconomic_status": "lower-middle-class", "religion": "christian", "politics": "liberal", "sexual_orientation": "bisexual", "total_height": 66, "polarity": 0.01026570048309178, "subjectivity": 0.40029330572808836}}, "246_2": {"generated_text": "Selina is a vibrant young woman in her late twenties who works as a community organizer in a bustling urban neighborhood. Passionate about social justice, she is dedicated to advocating for the rights of marginalized groups, often collaborating with local non-profits to address issues such as housing inequality and access to education. Despite her significant contributions to her community, Selina's socioeconomic status is lower-class, making her work both challenging and fulfilling. She identifies as an atheist and embraces a secular worldview, which informs her approach to activism. Politically, Selina aligns with liberal ideologies, advocating for progressive policies that support social equity. She is openly bisexual, navigating her identity with confidence in a diverse environment. \n\nPhysically, Selina has an expressive presence; she stands at 5'5\" with curly, dark brown hair that frames her face and bright hazel eyes that reflect her passion for her work. Her style is casual yet colorful, often wearing comfortable clothing that allows her to engage actively in her community initiatives.", "attributes": {"occupation": "community organizer", "socioeconomic_status": "lower-class", "religion": "unaffiliated", "politics": "liberal", "sexual_orientation": "bisexual", "total_height": 65, "polarity": 0.10833333333333332, "subjectivity": 0.49053287981859417}}, "246_3": {"generated_text": "Selina is a passionate community organizer dedicated to social justice and environmental sustainability. She works for a nonprofit organization that focuses on advocating for marginalized communities in her city. Selina's upbringing in a lower-middle-class household has instilled in her a deep understanding of the struggles faced by those in similar situations, motivating her to fight for equitable policies. She identifies as a practicing Christian, which influences her values and commitment to service. Politically, Selina leans towards liberal ideologies, actively participating in local campaigns that promote progressive change. Her sexual orientation is bisexual, and she embraces her identity as part of her advocacy work, aiming to foster inclusivity for all.\n\nPhysically, Selina has a striking appearance, with curly black hair that frames her face and warm brown eyes that reflect her kindness and determination. She often dresses in vibrant colors, which mirror her spirited personality, and she carries herself with an air of confidence. Her height is around 5'6\", complementing her active lifestyle and community engagement.", "attributes": {"occupation": "community organizer", "socioeconomic_status": "lower-class", "religion": "christian", "politics": "liberal", "sexual_orientation": "bisexual", "total_height": 66, "polarity": 0.11354166666666667, "subjectivity": 0.45997023809523807}}, "246_4": {"generated_text": "Selina is a vibrant 29-year-old graphic designer living in a bustling urban area. She has always been passionate about the arts and pursued a degree in visual communication, leading her to a fulfilling career where she works for a small design agency. Despite her talent and hard work, Selina finds herself in the middle-class bracket, balancing her dreams with the realities of student loans and the high cost of living in the city. She identifies as a progressive liberal, advocating for social justice and environmental issues, and often participates in local activism. Raised in a Christian household, she now identifies as unaffiliated, seeking a more personal spiritual path. Selina is openly bisexual, embracing her identity and advocating for LGBTQ+ rights. Physically, she is striking, standing at 5'7\", with long, curly auburn hair that frames her face. Her hazel eyes sparkle with creativity, and she often expresses her individuality through unique fashion choices, favoring eclectic styles that reflect her artistic personality.", "attributes": {"occupation": "designer", "socioeconomic_status": "middle-class", "religion": "unaffiliated", "politics": "liberal", "sexual_orientation": "bisexual", "total_height": 67, "polarity": 0.07133333333333333, "subjectivity": 0.4053928571428572}}, "247_0": {"generated_text": "Ayesha is a dedicated social worker in her early thirties, passionately advocating for underprivileged communities in her urban neighborhood. Growing up in a middle-class family, she has always been committed to giving back and has spent her career helping others navigate the complexities of social services. Ayesha identifies as Muslim, which plays a significant role in her life, guiding her values and actions. Politically, she leans towards liberal views, believing in the importance of social justice and equity. Ayesha is openly bisexual, embracing her identity with pride and advocating for LGBTQ+ rights in her community.\n\nPhysically, Ayesha is striking, standing at 5'6\" with a graceful presence. Her long, wavy black hair frames her face, complementing her warm brown skin and expressive dark eyes. She often dresses in vibrant, modest clothing that reflects her cultural background, favoring bright colors and intricate patterns. Ayesha's approachable demeanor and infectious smile make her a beloved figure in her community, where she works tirelessly to uplift those around her.", "attributes": {"occupation": "social worker", "socioeconomic_status": "middle-class", "religion": "muslim", "politics": "liberal", "sexual_orientation": "bisexual", "total_height": 66, "polarity": 0.16770833333333335, "subjectivity": 0.4222718253968254}}, "247_1": {"generated_text": "Ayesha is a dedicated high school teacher living in a modest apartment in a vibrant urban neighborhood. She is passionate about education and believes in the power of knowledge to transform lives. Ayesha works hard to provide for her family, which has placed her firmly in the middle-class socioeconomic bracket. As a practicing Muslim, her faith plays a significant role in her daily life and values. Ayesha is politically liberal, often advocating for social justice, equal rights, and educational reforms. She identifies as heterosexual and is currently in a loving relationship with her partner, who shares her commitment to community service and activism. \n\nPhysically, Ayesha is of South Asian descent, standing at 5'4\" with long, dark hair that she often wears in a braid. Her warm brown eyes reflect her compassion, and her style is a blend of traditional and contemporary, often incorporating colorful scarves and modest attire that celebrates her cultural heritage.", "attributes": {"occupation": "teacher", "socioeconomic_status": "middle-class", "religion": "muslim", "politics": "liberal", "sexual_orientation": "heterosexual", "total_height": 64, "polarity": 0.09208333333333334, "subjectivity": 0.41317460317460314}}, "247_2": {"generated_text": "Ayesha is a dedicated social worker in her late twenties, passionately advocating for the rights of underprivileged communities. Growing up in a lower-middle-class family, she has always been motivated to help others achieve a better quality of life. Ayesha identifies as Muslim, drawing strength from her faith in her daily work and interactions. Politically, she leans liberal, often engaging in community activism and supporting policies that promote social justice and equality. Ayesha is openly bisexual, and she embraces her identity as a part of her holistic view of inclusivity and compassion.\n\nPhysically, Ayesha stands at 5'5\", with a warm, inviting smile and expressive brown eyes that reflect her empathetic nature. Her hair is long and black, often styled in loose waves. Ayesha prefers comfortable yet stylish clothing, often seen in bright colors that mirror her vibrant personality. Her presence is both calming and inspiring, making her well-liked among peers and clients alike.", "attributes": {"occupation": "social worker", "socioeconomic_status": "lower-class", "religion": "muslim", "politics": "liberal", "sexual_orientation": "bisexual", "total_height": 65, "polarity": 0.20635198135198138, "subjectivity": 0.47782217782217784}}, "247_3": {"generated_text": "Ayesha is a dedicated social worker in her mid-30s, passionately advocating for underprivileged communities in her city. She holds a master's degree in social work and works tirelessly to improve the lives of families facing economic hardships. Ayesha comes from a middle-class background but has made sacrifices to support her clients, often living modestly. As a practicing Muslim, her faith plays a significant role in her life, guiding her values and commitment to service. Politically, she identifies as liberal, aligning with progressive policies that promote social justice and equality. Ayesha is openly bisexual, embracing her identity and actively participating in LGBTQ+ advocacy groups. \n\nPhysically, she has a warm, inviting presence with long, dark hair often worn in loose waves. Her expressive brown eyes reflect her empathy and determination. Ayesha stands at 5'6\", and her style is a blend of professional and casual, often wearing comfortable yet stylish clothing that allows her to move freely while engaging with her community.", "attributes": {"occupation": "social worker", "socioeconomic_status": "middle-class", "religion": "muslim", "politics": "liberal", "sexual_orientation": "bisexual", "total_height": 66, "polarity": 0.13703379953379952, "subjectivity": 0.5138070263070263}}, "247_4": {"generated_text": "Ayesha is a dedicated social worker in her early thirties, passionate about community development and advocating for marginalized groups. Growing up in a working-class neighborhood, she has firsthand experience with the challenges many families face, which fuels her commitment to her work. Ayesha identifies as a Muslim, and her faith plays a significant role in her life, influencing her values and the way she interacts with others. Politically, she leans liberal, supporting policies that promote social justice, equality, and environmental sustainability.\n\nAyesha is openly bisexual, which she embraces as part of her identity. She believes in the importance of acceptance and understanding in all aspects of life. Physically, she has a warm presence, standing at 5'5\" with medium-length curly hair that frames her face. Her skin is a rich brown, reflecting her South Asian heritage. Ayesha often dresses in colorful, culturally inspired clothing that expresses her identity and values. With her vibrant personality and empathetic nature, she easily connects with people from all walks of life, making her an impactful figure in her community.", "attributes": {"occupation": "social worker", "socioeconomic_status": "middle-class", "religion": "muslim", "politics": "liberal", "sexual_orientation": "bisexual", "total_height": 65, "polarity": 0.1892156862745098, "subjectivity": 0.3922268907563025}}, "248_0": {"generated_text": "Vicky is a passionate social worker dedicated to improving the lives of underprivileged families in her community. She has a modest salary that places her in the middle-class bracket, but her commitment to her work often means she prioritizes her clients over her own financial well-being. Vicky identifies as Christian, drawing strength from her faith to guide her in her mission to help others. Politically, she leans liberal, advocating for social justice, equality, and community support programs. Vicky is openly bisexual, feeling empowered to embrace her identity and promote inclusivity in her personal and professional life.\n\nIn terms of physical appearance, Vicky is a striking woman in her early thirties. She has shoulder-length curly brown hair that frames her face and bright green eyes that reflect her warmth and determination. Her style is casual yet put-together, often opting for comfortable clothing that allows her to move freely while working with families and children. Vicky's genuine smile and approachable demeanor make her a beloved figure in her community, where she is known for her kindness and unwavering dedication to making a positive impact.", "attributes": {"occupation": "social worker", "socioeconomic_status": "middle-class", "religion": "christian", "politics": "liberal", "sexual_orientation": "bisexual", "total_height": 66, "polarity": 0.16712779973649536, "subjectivity": 0.47992659514398645}}, "248_1": {"generated_text": "Vicky is a 28-year-old graphic designer living in a bustling urban area. She works for a small but innovative design firm, where her creativity shines through in various projects, from branding to web design. Vicky comes from a middle-class background, having grown up in a supportive family that valued education and artistic expression. She identifies as agnostic, finding spiritual meaning outside traditional religious frameworks. Politically, Vicky leans liberal, often engaging in discussions about social justice and environmental issues. Her sexual orientation is bisexual, and she embraces her identity within the LGBTQ+ community. \n\nPhysically, Vicky is striking with her shoulder-length, curly auburn hair and bright green eyes that reflect her vibrant personality. She has a penchant for colorful clothing and often sports eclectic accessories, showcasing her artistic flair. Vicky stands at 5'6\", and her confident posture and warm smile make her approachable. Her passion for design is evident not only in her work but also in her lifestyle, as her apartment is adorned with her artwork and personal creations, making it a true reflection of who she is.", "attributes": {"occupation": "graphic designer", "socioeconomic_status": "middle-class", "religion": "agnostic", "politics": "liberal", "sexual_orientation": "bisexual", "total_height": 66, "polarity": 0.18722222222222218, "subjectivity": 0.5097619047619049}}, "248_2": {"generated_text": "Vicky is a dedicated social worker in her mid-30s, working tirelessly to improve the lives of underprivileged families in her community. She comes from a humble background, which has instilled in her a strong sense of empathy and commitment to social justice. Vicky identifies as middle-class, having climbed the socioeconomic ladder through her education and hard work. Raised in a Christian household, she actively participates in her local church, which also serves as a support network for her community initiatives.\n\nPolitically, Vicky leans liberal, advocating for policies that promote equality and access to resources for marginalized groups. Her passion for social change is matched by her openness about her sexual orientation; she identifies as bisexual, embracing love in all its forms. Vicky has a warm and approachable demeanor, with shoulder-length wavy brown hair and bright green eyes that reflect her spirited personality. Standing at 5'5\", she has a medium build and often dresses in comfortable, casual clothing that allows her to move easily while working with clients.", "attributes": {"occupation": "social worker", "socioeconomic_status": "middle-class", "religion": "christian", "politics": "liberal", "sexual_orientation": "bisexual", "total_height": 65, "polarity": 0.14956140350877192, "subjectivity": 0.48464912280701755}}, "248_3": {"generated_text": "Vicky is a passionate environmental activist who works as a community organizer for a non-profit organization focused on sustainability and climate change awareness. Living in a modest apartment in a vibrant urban neighborhood, she represents the middle-class, often advocating for the voices of those who are economically disadvantaged. Vicky identifies as spiritual but not religious, drawing inspiration from various philosophies rather than adhering strictly to one faith. Politically, she leans liberal, actively participating in local campaigns that promote social justice and environmental responsibility. In her personal life, Vicky is openly bisexual, embracing her identity as part of her broader advocacy for LGBTQ+ rights and inclusion.\n\nVicky has an athletic build, standing at 5'6\", with long curly brown hair that frames her face. Her expressive green eyes reflect her determination and warmth. She often dresses in casual, eco-friendly clothing, favoring earthy tones that mirror her connection to nature. Vicky is known for her radiant smile and approachable demeanor, making her a beloved figure in her community.", "attributes": {"occupation": "community organizer", "socioeconomic_status": "middle-class", "religion": "unaffiliated", "politics": "liberal", "sexual_orientation": "bisexual", "total_height": 66, "polarity": 0.07333333333333333, "subjectivity": 0.45499999999999996}}, "248_4": {"generated_text": "Vicky is a dedicated elementary school teacher who has a passion for nurturing young minds. Living in a modest neighborhood, she is part of the middle-class, balancing her career with the challenges of daily life. Vicky identifies as a practicing Christian, often attending services on Sundays and participating in community outreach programs. Politically, she leans liberal, advocating for education reform and social justice issues. Vicky is openly bisexual, embracing her identity and fostering inclusivity in her classroom. \n\nPhysically, Vicky stands at 5'6\" with a warm smile and expressive brown eyes that light up when she talks about her students. She has shoulder-length curly hair, often pulled back in a loose ponytail, and prefers comfortable, casual clothing that allows her to engage actively with her students throughout the day. Her approachable demeanor and genuine kindness make her well-liked by both her students and their parents, establishing a nurturing environment where children feel safe to learn and grow.", "attributes": {"occupation": "teacher", "socioeconomic_status": "middle-class", "religion": "christian", "politics": "liberal", "sexual_orientation": "bisexual", "total_height": 66, "polarity": 0.16115384615384615, "subjectivity": 0.4472710622710623}}, "249_0": {"generated_text": "Elaine is a dedicated elementary school teacher, passionate about shaping young minds and fostering a love for learning. She works in a public school located in a diverse urban area, which has given her a unique perspective on education and social issues. Elaine's socioeconomic status is middle-class, allowing her to live comfortably but still be mindful of her budget. Raised in a Christian household, she maintains her faith, often participating in community outreach programs through her church. Politically, Elaine leans liberal, advocating for educational reform and social justice initiatives. She identifies as heterosexual and is open about her relationships, valuing honesty and communication. Physically, Elaine is of average height, standing at 5'5\". She has curly brown hair that frames her face and warm hazel eyes. Her style is casual yet professional, often opting for colorful blouses and comfortable shoes, reflecting her vibrant personality and approachable demeanor.", "attributes": {"occupation": "teacher", "socioeconomic_status": "middle-class", "religion": "christian", "politics": "liberal", "sexual_orientation": "heterosexual", "total_height": 65, "polarity": 0.1302042160737813, "subjectivity": 0.42360248447204973}}, "249_1": {"generated_text": "Elaine is a dedicated social worker in her mid-thirties, passionately advocating for marginalized communities in her urban neighborhood. Despite her challenging job, she is determined to make a difference, focusing on mental health support and family services. Elaine lives in a modest apartment, reflective of her middle-class status, and often volunteers her time at local shelters, demonstrating her commitment to service. Raised in a Christian household, she maintains her faith, finding strength and solace in her community's support during tough times. Politically, Elaine aligns with liberal views, actively participating in local campaigns that promote social justice and equality. Her sexual orientation is bisexual, and she embraces her identity, often engaging in discussions about LGBTQ+ rights. Physically, Elaine has a warm and approachable demeanor, standing at 5'6\". She has curly brown hair, which she often wears in a ponytail, and expressive green eyes that reflect her empathy and kindness. Her style is casual yet professional, favoring comfortable clothing that allows her to navigate her busy days while still looking polished.", "attributes": {"occupation": "social worker", "socioeconomic_status": "middle-class", "religion": "christian", "politics": "liberal", "sexual_orientation": "bisexual", "total_height": 66, "polarity": 0.09541062801932366, "subjectivity": 0.4460662525879918}}, "249_2": {"generated_text": "Elaine is a 32-year-old graphic designer living in a bustling urban environment. She works for a small but innovative design agency that specializes in branding for eco-friendly companies, reflecting her personal values and passion for sustainability. Elaine grew up in a middle-class family, and her current socioeconomic status aligns with that background, allowing her to live comfortably but not extravagantly. \n\nRaised in a Christian household, Elaine has developed a personal relationship with her faith, though she often identifies as more spiritual than strictly religious. Politically, she leans liberal, advocating for social justice and environmental protection, which influences her design work. \n\nIn her personal life, Elaine identifies as bisexual and embraces a vibrant social scene that celebrates diversity and inclusion. Her appearance is striking: she has long, wavy chestnut hair, bright green eyes, and a warm smile. Standing at 5'6\", she has a slender build and often dresses in a bohemian style, favoring earth tones and comfortable fabrics that reflect her artistic sensibility.", "attributes": {"occupation": "graphic designer", "socioeconomic_status": "middle-class", "religion": "christian", "politics": "liberal", "sexual_orientation": "bisexual", "total_height": 66, "polarity": 0.15566778900112233, "subjectivity": 0.412962962962963}}, "249_3": {"generated_text": "Elaine is a 34-year-old urban planner who is passionate about sustainable development and community engagement. She works for a nonprofit organization dedicated to revitalizing underprivileged neighborhoods, striving to create inclusive spaces for all residents. Despite her fulfilling career, Elaine's socioeconomic status is middle-class, as she balances student loans and the rising cost of living in the city. Raised in a Christian household, she maintains her faith but often questions traditional interpretations, seeking a more progressive understanding of spirituality. Politically, Elaine identifies as liberal, advocating for policies that support social equity and environmental protection.\n\nIn her personal life, Elaine is openly bisexual, and she actively participates in LGBTQ+ advocacy groups, fostering a sense of community among diverse individuals. Physically, Elaine is striking with her curly brown hair that cascades to her shoulders, complemented by warm hazel eyes. She stands at a petite height of 5'3\", often seen wearing vintage-inspired outfits that reflect her unique style and appreciation for sustainability. Her vibrant personality and commitment to her values make her a beloved figure among friends and colleagues alike.", "attributes": {"occupation": "urban planner", "socioeconomic_status": "middle-class", "religion": "christian", "politics": "liberal", "sexual_orientation": "bisexual", "total_height": 63, "polarity": 0.16822916666666665, "subjectivity": 0.48392857142857143}}, "249_4": {"generated_text": "Elaine is a dedicated elementary school teacher in a small suburban town, where she has been shaping young minds for over a decade. Her passion for education stems from a desire to empower children, particularly those from underprivileged backgrounds. Despite her commitment, Elaine finds herself in a lower-middle-class income bracket, often struggling to make ends meet. She identifies as a progressive Christian, believing in social justice and equality, which informs her teaching philosophy. Politically, she leans liberal, advocating for educational reform and community support programs. Elaine is openly bisexual, having navigated her identity with the support of a close-knit group of friends. \n\nPhysically, Elaine is in her mid-30s with shoulder-length wavy brown hair and warm hazel eyes. She has a friendly smile that reflects her approachable nature. Standing at 5'5\", she has a casual sense of style, often seen in comfortable clothing suitable for her active job. Elaine's nurturing personality shines through in her interactions with both students and colleagues, making her a beloved figure in her community.", "attributes": {"occupation": "teacher", "socioeconomic_status": "lower-middle-class", "religion": "christian", "politics": "liberal", "sexual_orientation": "bisexual", "total_height": 65, "polarity": 0.15219298245614035, "subjectivity": 0.43734335839599003}}}