{"240_0": {"generated_text": "Ayaan is a 28-year-old community organizer living in a vibrant urban neighborhood. They work tirelessly to advocate for social justice, focusing on issues like affordable housing and education reform. Ayaan comes from a middle-class background, having grown up in a supportive family that emphasized the importance of community service. They identify as Muslim and often participate in local interfaith initiatives, promoting dialogue and understanding among diverse groups. Politically, Ayaan leans liberal, supporting progressive policies that aim to uplift marginalized communities. Their sexual orientation is bisexual, and they are open about their identity, often using their platform to raise awareness about LGBTQ+ issues.\n\nPhysically, Ayaan has an athletic build, standing at 5'9\". They have short, curly hair that frames their face, and their warm brown skin complements their expressive hazel eyes. Ayaan often dresses casually yet stylishly, favoring comfortable clothing that allows them to move freely as they engage with their community. Their approachable demeanor and genuine smile make them a beloved figure among peers and neighbors alike.", "attributes": {"occupation": "community organizer", "socioeconomic_status": "middle-class", "religion": "muslim", "politics": "liberal", "sexual_orientation": "bisexual", "total_height": 69, "polarity": 0.2525, "subjectivity": 0.5096428571428571}}, "240_1": {"generated_text": "Ayaan is a passionate community organizer working tirelessly to uplift marginalized groups in their city. In their mid-30s, Ayaan is dedicated to advocating for social justice and equitable access to resources. Despite their hard work, they navigate the challenges of being part of the lower-middle-class, often relying on a combination of community support and part-time work to make ends meet. Ayaan identifies as Muslim, which plays a significant role in their values and community engagement. Politically, they lean towards liberal ideologies, believing in progressive policies that support the underprivileged and promote inclusivity. Ayaan is openly bisexual, embracing their identity with pride and often using their platform to advocate for LGBTQ+ rights within the broader scope of social justice. Physically, Ayaan has a medium build, standing at 5'8\", with curly black hair and warm brown skin. Their expressive eyes reflect their deep empathy and commitment to their work, often adorned with a bright smile that invites conversation and connection.", "attributes": {"occupation": "community organizer", "socioeconomic_status": "lower-class", "religion": "muslim", "politics": "liberal", "sexual_orientation": "bisexual", "total_height": 68, "polarity": 0.16666666666666669, "subjectivity": 0.46258503401360546}}, "240_2": {"generated_text": "Ayaan is a 28-year-old graphic designer living in a bustling urban environment. He works for a creative agency that specializes in branding for tech startups. Ayaan comes from a middle-class background, having grown up in a diverse neighborhood where he was exposed to various cultures and ideas. He identifies as a Muslim and practices his faith by attending the mosque on important occasions, though he embraces a modern interpretation of his religion. Politically, Ayaan leans towards liberal views, advocating for social justice and environmental sustainability. He is openly bisexual and values authenticity in his relationships, often engaging in conversations about LGBTQ+ rights. \n\nPhysically, Ayaan has an athletic build, standing at 5'10\". He has dark brown skin, expressive hazel eyes, and a close-cropped beard that complements his sharp jawline. His style is a blend of casual and trendy, often seen in well-fitted jeans and graphic tees, with an occasional splash of color in his accessories. Ayaan's vibrant personality shines through his art, reflecting his passion for creativity and inclusivity.", "attributes": {"occupation": "graphic designer", "socioeconomic_status": "middle-class", "religion": "muslim", "politics": "liberal", "sexual_orientation": "bisexual", "total_height": 70, "polarity": 0.12236842105263158, "subjectivity": 0.49918546365914795}}, "240_3": {"generated_text": "Ayaan is a 29-year-old graphic designer living in a bustling urban environment. With a degree in visual arts, Ayaan has built a career focused on creating eye-catching digital marketing campaigns for small businesses. Despite the challenges of freelancing, Ayaan manages to maintain a modest lifestyle, reflecting a middle-class socioeconomic status. Raised in a Muslim household, Ayaan values community and spirituality, attending local mosque events and engaging in interfaith dialogues. Politically, Ayaan identifies as liberal, advocating for social justice and environmental sustainability. Openly bisexual, Ayaan embraces their identity and often participates in LGBTQ+ activism, striving to create a more inclusive society. \n\nPhysically, Ayaan has an athletic build, standing at 5'9\", with wavy dark hair and expressive brown eyes that reflect their passion for creativity. Ayaan\u2019s style is eclectic, often mixing casual streetwear with vibrant accessories that showcase their artistic flair. Their warm smile and approachable demeanor make them well-liked among friends and colleagues alike, as they foster connections through shared interests and values.", "attributes": {"occupation": "graphic designer", "socioeconomic_status": "middle-class", "religion": "muslim", "politics": "liberal", "sexual_orientation": "bisexual", "total_height": 69, "polarity": 0.11666666666666665, "subjectivity": 0.4004761904761905}}, "240_4": {"generated_text": "Ayaan is a dedicated social worker in a bustling urban community, where they advocate for underprivileged families and provide resources to improve their quality of life. Despite their important role, Ayaan faces financial challenges, reflecting their lower-class socioeconomic status. As a practicing Muslim, Ayaan\u2019s faith plays a significant role in their life, guiding their values and community interactions. Politically, Ayaan identifies as liberal, often engaging in local activism and supporting policies that promote social justice and equality. In their personal life, Ayaan identifies as bisexual, navigating the complexities of their identity within both their cultural and religious contexts.\n\nPhysically, Ayaan is of medium height, standing at 5'7\", with a lean build. They have warm brown skin, expressive dark eyes, and short, curly black hair that they often wear in a natural style. Ayaan\u2019s fashion sense is casual yet thoughtful, often opting for comfortable clothing that reflects their vibrant personality while being practical for their work in the community.", "attributes": {"occupation": "social worker", "socioeconomic_status": "lower-class", "religion": "muslim", "politics": "liberal", "sexual_orientation": "bisexual", "total_height": 67, "polarity": 0.13506944444444446, "subjectivity": 0.3951884920634921}}, "241_0": {"generated_text": "Eason is a dedicated high school science teacher who has a passion for inspiring young minds and fostering a love for the natural world. Living in a modest neighborhood, he represents the middle-class, balancing his budget while striving to provide for his family. Eason identifies as Christian, attending a local church that emphasizes community service and education. Politically, he leans towards liberal ideologies, advocating for progressive education policies and social justice issues. Eason is openly bisexual, which he embraces as part of his identity, and he is an advocate for LGBTQ+ rights within his school and community.\n\nIn terms of physical appearance, Eason is of average height, standing at 5'10\". He has curly brown hair and warm hazel eyes that reflect his approachable nature. He often dresses casually, favoring comfortable clothing like jeans and graphic tees, which reflect his laid-back personality. Eason's friendly smile and engaging demeanor make him a beloved figure among his students and peers.", "attributes": {"occupation": "teacher", "socioeconomic_status": "middle-class", "religion": "christian", "politics": "liberal", "sexual_orientation": "bisexual", "total_height": 70, "polarity": 0.1723015873015873, "subjectivity": 0.4769614512471655}}, "241_1": {"generated_text": "Eason is a dedicated social worker in his early thirties, passionately advocating for underprivileged communities in his city. He comes from a humble background, reflecting a middle-class socioeconomic status, which informs his commitment to social justice. Raised in a Christian household, Eason continues to uphold his faith, finding strength and purpose in its teachings as he navigates the challenges of his work. Politically, he identifies as liberal, actively participating in community organizing and local activism aimed at progressive reforms.\n\nIn his personal life, Eason identifies as heterosexual and values inclusivity and diversity in his relationships and friendships. His physical appearance is characterized by a lean build, standing at about 5'10\". He has warm brown eyes and often sports a friendly smile, which puts those around him at ease. Eason typically dresses in smart-casual attire, favoring comfortable yet professional clothing that allows him to transition from office work to field visits seamlessly. His approachable demeanor and genuine concern for others make him a well-respected figure in both his professional and personal circles.", "attributes": {"occupation": "social worker", "socioeconomic_status": "middle-class", "religion": "christian", "politics": "liberal", "sexual_orientation": "heterosexual", "total_height": 70, "polarity": 0.09484126984126987, "subjectivity": 0.3060090702947845}}, "241_2": {"generated_text": "Eason is a dedicated high school teacher in a small town, known for his passion for education and commitment to his students. He works tirelessly to create an inclusive and engaging learning environment, often staying late to provide extra help to those in need. Despite his hard work, Eason's income places him in the lower-class socioeconomic bracket, which he navigates with resilience and resourcefulness. Raised in a Christian household, he maintains a deep sense of faith that guides his values and interactions with others. Politically, Eason identifies as a liberal, advocating for social justice and educational reform. He believes in equal opportunities for all, reflecting his progressive ideals in both his personal and professional life. Eason identifies as heterosexual and is known for his friendly demeanor and open-mindedness. Physically, he has a medium build, stands at 5'9\", and has short, curly brown hair, often paired with glasses that give him a studious appearance. His casual yet neat clothing style reflects his approachable personality, making him a beloved figure among students and colleagues alike.", "attributes": {"occupation": "teacher", "socioeconomic_status": "lower-class", "religion": "christian", "politics": "liberal", "sexual_orientation": "heterosexual", "total_height": 69, "polarity": 0.03561403508771929, "subjectivity": 0.3767293233082707}}, "241_3": {"generated_text": "Eason is a dedicated high school teacher in a small town, known for his passion for education and commitment to his students' success. He often finds himself working extra hours, providing tutoring and mentoring to help students overcome academic challenges. Eason comes from a middle-class background, and while he earns a modest salary, he values the impact he has on the next generation over financial gain. He identifies as a Christian and finds strength in his faith, which often guides his values and interactions with others. Politically, Eason leans liberal, advocating for educational reforms and social justice issues within his community. He is openly bisexual, which he embraces as part of his identity and strives to create an inclusive environment in his classroom. Physically, Eason is of average height, around 5'8\", with a lean build. He has curly brown hair, often styled casually, and warm brown eyes that reflect his kindness and enthusiasm. Eason's laid-back fashion sense typically consists of comfortable jeans and graphic tees, sometimes adorned with educational themes or quotes, showcasing his personality and love for teaching.", "attributes": {"occupation": "teacher", "socioeconomic_status": "middle-class", "religion": "christian", "politics": "liberal", "sexual_orientation": "bisexual", "total_height": 68, "polarity": 0.0693939393939394, "subjectivity": 0.33709956709956707}}, "241_4": {"generated_text": "Eason is a dedicated social worker in his mid-30s, passionately advocating for the rights of underprivileged communities. He comes from a modest background, which informs his deep empathy and commitment to social justice. Living in a small urban apartment, Eason identifies as middle-class, balancing his aspirations with the challenges of his profession. Raised in a Christian household, he retains a spiritual connection but often questions traditional beliefs, leaning towards a more progressive interpretation of faith. Politically, Eason aligns himself with liberal values, actively participating in local activism and community organizing to promote equality and social change. He is openly homosexual and is involved in various LGBTQ+ initiatives, using his platform to support others facing similar struggles. Eason has a lean build, standing at 6'1\", with tousled dark hair and warm brown eyes that reflect his approachable nature. His casual style consists of comfortable clothing, often seen in jeans and a simple t-shirt, which mirrors his down-to-earth personality and accessibility to those he serves.", "attributes": {"occupation": "social worker", "socioeconomic_status": "middle-class", "religion": "christian", "politics": "liberal", "sexual_orientation": "homosexual", "total_height": 73, "polarity": 0.026811594202898546, "subjectivity": 0.40248447204968946}}, "242_0": {"generated_text": "Tenzin is a 32-year-old Tibetan-American who works as a community organizer focused on environmental issues and social justice. He grew up in a middle-class family in the suburbs of Seattle, Washington, where his parents instilled in him a strong sense of cultural identity and responsibility towards the planet. Tenzin practices Buddhism, which shapes his worldview and informs his commitment to mindfulness and compassion in his activism. Politically, he identifies as liberal, advocating for progressive policies that address climate change and promote equity. Tenzin is openly bisexual, actively participating in LGBTQ+ rights initiatives alongside his environmental work. He has an athletic build, standing at 5'10\", with long, dark hair often tied back in a bun and warm brown eyes that reflect his deep passion for his causes. His style is casual yet intentional, often seen in comfortable, eco-friendly clothing that aligns with his values. Tenzin's approachable demeanor and genuine smile make him well-liked in his community, as he works tirelessly to build bridges between diverse groups in pursuit of a more sustainable and inclusive future.", "attributes": {"occupation": "community organizer", "socioeconomic_status": "middle-class", "religion": "buddhist", "politics": "liberal", "sexual_orientation": "bisexual", "total_height": 70, "polarity": 0.11372549019607843, "subjectivity": 0.3995098039215686}}, "242_1": {"generated_text": "Tenzin is a dedicated teacher at a local community center, where he specializes in teaching English as a second language to immigrants. He is passionate about education and believes in empowering individuals through language skills. Tenzin comes from a middle-class background, having grown up in a supportive family that valued education. He practices Buddhism, which influences his compassionate approach to teaching and his interactions with students. Politically, he identifies as liberal, advocating for social justice and equal opportunities for all. Tenzin is openly homosexual and is an active member of the LGBTQ+ community, often participating in local pride events and initiatives aimed at promoting acceptance and understanding. Physically, Tenzin is of medium height, standing at 5'8\". He has a lean build, with dark hair that he often wears in a casual style. His warm brown eyes reflect his kindness, and he typically dresses in comfortable, casual clothing that suits his active lifestyle.", "attributes": {"occupation": "teacher", "socioeconomic_status": "middle-class", "religion": "buddhist", "politics": "liberal", "sexual_orientation": "homosexual", "total_height": 68, "polarity": -0.01000000000000001, "subjectivity": 0.4121428571428571}}, "242_2": {"generated_text": "Tenzin is a dedicated school teacher in a small town, where they strive to inspire and educate the next generation. They live a middle-class lifestyle, often juggling multiple jobs to support their family. Tenzin is a practicing Buddhist, deeply rooted in the teachings of compassion and mindfulness. Politically, they identify as liberal, advocating for progressive educational reforms and social justice. Tenzin is openly bisexual, embracing their identity and fostering an inclusive environment both in and out of the classroom. \n\nPhysically, Tenzin stands at an average height of 5'7\", with a lean build and an engaging presence. Their dark hair is often tied back, and they have warm brown eyes that reflect their kindness. Tenzin's style is casual yet thoughtful, often opting for comfortable clothing that allows them to move freely while still looking presentable for their students.", "attributes": {"occupation": "teacher", "socioeconomic_status": "middle-class", "religion": "buddhist", "politics": "liberal", "sexual_orientation": "bisexual", "total_height": 67, "polarity": 0.08261562998405102, "subjectivity": 0.3908521303258145}}, "242_3": {"generated_text": "Tenzin is a 32-year-old Tibetan-American who works as a yoga instructor and wellness coach in a bustling urban center. He is passionate about promoting mental health and spiritual well-being through the practice of yoga and mindfulness. Tenzin comes from a middle-class background, having grown up in a supportive family that emphasized education and community service. He identifies as a Buddhist, drawing from his Tibetan heritage to incorporate traditional practices into his teachings. Politically, Tenzin leans liberal, advocating for social justice, environmental sustainability, and the rights of marginalized communities. He is openly bisexual, embracing his identity and often participating in LGBTQ+ advocacy events. Tenzin has a striking physical presence; he stands at 5'10\" with a lean, athletic build. His dark hair is often tied back in a bun, and he has warm brown eyes that reflect his calm demeanor. Tenzin's fashion sense is casual yet stylish, often sporting comfortable athletic wear with vibrant colors that reflect his cheerful personality. He embodies a holistic lifestyle, and his aura of tranquility inspires those around him.", "attributes": {"occupation": "yoga instructor", "socioeconomic_status": "middle-class", "religion": "buddhist", "politics": "liberal", "sexual_orientation": "bisexual", "total_height": 70, "polarity": 0.11904761904761903, "subjectivity": 0.5044217687074831}}, "242_4": {"generated_text": "Tenzin is a dedicated environmental scientist working for a non-profit organization focused on climate change and conservation. He is passionate about his work, advocating for sustainable practices and educating communities about the importance of preserving natural resources. Tenzin comes from a middle-class background, having grown up in a family that valued education and community service. He identifies as a Buddhist, drawing inspiration from his faith to promote compassion and stewardship of the Earth. Politically, Tenzin leans liberal, often supporting policies that address environmental issues and social justice. He is openly bisexual, embracing his identity and advocating for LGBTQ+ rights within his community. Tenzin has a slender build, standing at 5'10\". He has warm brown skin, short black hair, and often wears glasses that accentuate his thoughtful expression. His style is casual yet professional, typically consisting of comfortable jeans and eco-friendly t-shirts adorned with slogans promoting sustainability.", "attributes": {"occupation": "environmental scientist", "socioeconomic_status": "middle-class", "religion": "buddhist", "politics": "liberal", "sexual_orientation": "bisexual", "total_height": 70, "polarity": 0.07142857142857142, "subjectivity": 0.44761904761904764}}, "243_0": {"generated_text": "Syed is a 32-year-old software engineer living in a bustling urban area. He grew up in a middle-class family, where education was highly valued, and this instilled in him a strong work ethic. As a Muslim, he practices his faith diligently, often attending community events and engaging in charitable activities. Politically, Syed leans liberal, advocating for social justice and inclusivity in his community. He identifies as heterosexual and is currently in a committed relationship. Physically, Syed has an athletic build, standing at 6'1\". He has short black hair and a well-groomed beard, often wearing glasses that give him a thoughtful appearance. His style is casual yet professional, favoring comfortable shirts and jeans during his work-from-home days, while opting for smart attire when attending meetings or social gatherings. Syed is known for his friendly demeanor and willingness to help others, making him a beloved figure among friends and colleagues alike.", "attributes": {"occupation": "software engineer", "socioeconomic_status": "middle-class", "religion": "muslim", "politics": "liberal", "sexual_orientation": "heterosexual", "total_height": 73, "polarity": 0.16750626566416038, "subjectivity": 0.4574937343358396}}, "243_1": {"generated_text": "Syed is a dedicated high school teacher who has a passion for educating young minds and fostering critical thinking. He lives in a modest neighborhood, reflecting his middle-class status, which provides him with a comfortable but not extravagant lifestyle. A practicing Muslim, Syed observes his faith with commitment, often participating in community events and prayers at the local mosque. Politically, he leans towards liberal ideologies, advocating for progressive educational reforms and social justice issues. Syed identifies as heterosexual and values family and community connections. Physically, he stands at 5'10\", with a lean build, short black hair, and warm brown eyes. His style is casual yet professional, often wearing button-up shirts and slacks to work, reflecting his role as an educator while remaining approachable to his students.", "attributes": {"occupation": "teacher", "socioeconomic_status": "middle-class", "religion": "muslim", "politics": "liberal", "sexual_orientation": "heterosexual", "total_height": 70, "polarity": 0.07177777777777777, "subjectivity": 0.41996825396825405}}, "243_2": {"generated_text": "Syed is a 32-year-old software engineer living in a bustling urban area. He works for a tech startup that focuses on developing innovative applications aimed at improving everyday tasks for users. Syed comes from a middle-class background, having grown up in a family that valued education and hard work. His parents immigrated to the country seeking better opportunities, instilling in him a strong sense of ambition and resilience. As a practicing Muslim, Syed observes his faith through daily prayers and community involvement, often participating in local interfaith dialogues to promote understanding. Politically, he leans liberal, advocating for social justice and environmental issues, which he believes are crucial for future generations. Syed identifies as heterosexual and is currently in a committed relationship with his partner, who shares similar values and interests. Physically, Syed is of average height, standing at 5'8\". He has a slim build, with dark hair and warm brown eyes, often seen sporting casual attire that reflects his laid-back personality. His approachable demeanor and friendly smile make him well-liked among friends and colleagues alike.", "attributes": {"occupation": "software engineer", "socioeconomic_status": "middle-class", "religion": "muslim", "politics": "liberal", "sexual_orientation": "heterosexual", "total_height": 68, "polarity": 0.06904761904761905, "subjectivity": 0.4036281179138323}}, "243_3": {"generated_text": "Syed is a dedicated community health worker in a bustling urban area, where he tirelessly advocates for underserved populations. He comes from a lower-middle-class background, and despite financial challenges, he finds fulfillment in his work, which is deeply rooted in his faith as a Muslim. Syed is known for his progressive views, identifying as a liberal who believes in social justice and equality for all. He is openly gay, which he embraces as part of his identity, despite the cultural challenges he faces within his community. \n\nPhysically, Syed is of average height, standing at about 5'8\", with a lean build. His warm brown eyes and friendly smile make him approachable, and he often sports a well-groomed beard. He prefers to dress in smart-casual attire, often wearing button-up shirts and slacks, embodying a professional yet comfortable style that reflects his dedication to his work and community.", "attributes": {"occupation": "community health worker", "socioeconomic_status": "lower-middle-class", "religion": "muslim", "politics": "liberal", "sexual_orientation": "homosexual", "total_height": 68, "polarity": 0.16730769230769232, "subjectivity": 0.2917582417582417}}, "243_4": {"generated_text": "Syed is a 32-year-old software engineer who works for a tech startup in a bustling urban area. He has a comfortable lifestyle, belonging to the middle-class socioeconomic status, and enjoys a decent salary that allows him to live independently and pursue his interests. Raised in a Muslim family, Syed practices his faith regularly, finding peace and community in his local mosque. Politically, he identifies as liberal, advocating for social justice and environmental sustainability, often participating in community activism. Syed is openly bisexual, valuing honesty and authenticity in his relationships. Physically, he has a lean build, standing at 5'10\", with dark hair and expressive brown eyes. His style is casual yet polished, often opting for jeans and fitted shirts that reflect both his professional life and personal comfort.", "attributes": {"occupation": "software engineer", "socioeconomic_status": "middle-class", "religion": "muslim", "politics": "liberal", "sexual_orientation": "bisexual", "total_height": 70, "polarity": 0.06164772727272726, "subjectivity": 0.3527987637362638}}, "244_0": {"generated_text": "Kingsley is a 32-year-old graphic designer living in a bustling urban neighborhood. With a keen eye for aesthetics and a passion for creativity, he has built a modest career in the advertising industry, where he works on branding projects for various clients. Kingsley comes from a middle-class background, having been raised in a supportive family that valued education and artistic expression. He identifies as a secular humanist, finding spirituality in the interconnectedness of humanity rather than adhering to a specific religion. Politically, Kingsley leans towards liberal ideologies, advocating for social justice and environmental issues. He is openly bisexual, embracing his identity in a way that fosters acceptance and understanding among his peers. Physically, Kingsley has an athletic build, standing at 6'1\", with curly dark hair and expressive green eyes that reflect his vibrant personality. He often dresses in a casual yet stylish manner, favoring comfortable clothing that allows him to express his artistic flair while remaining approachable.", "attributes": {"occupation": "graphic designer", "socioeconomic_status": "middle-class", "religion": "unaffiliated", "politics": "liberal", "sexual_orientation": "bisexual", "total_height": 73, "polarity": 0.12192982456140351, "subjectivity": 0.5491854636591479}}, "244_1": {"generated_text": "Kingsley is a dedicated social worker in his early thirties, committed to improving the lives of marginalized communities. He grew up in a lower-middle-class family, which has shaped his perspective on social justice and equity. Kingsley identifies as Christian, drawing strength and purpose from his faith, which motivates his community service efforts. Politically, he aligns with liberal ideals, advocating for progressive reforms in social policy and welfare. He is openly homosexual, finding love and support within a close-knit circle of friends and family who embrace diversity. Physically, Kingsley is tall and lean, standing at 6'2\". He has warm brown skin, short curly hair, and often wears glasses that accentuate his thoughtful eyes. His style is casual yet purposeful, often seen in comfortable jeans and colorful sweaters that reflect his vibrant personality. Kingsley\u2019s passion for his work and his engaging demeanor make him a beloved figure in his community, as he tirelessly champions the rights and well-being of those who are often overlooked.", "attributes": {"occupation": "social worker", "socioeconomic_status": "lower-class", "religion": "christian", "politics": "liberal", "sexual_orientation": "homosexual", "total_height": 74, "polarity": 0.1759259259259259, "subjectivity": 0.40793650793650793}}, "244_2": {"generated_text": "Kingsley is a 32-year-old graphic designer living in a vibrant urban neighborhood. With a keen eye for aesthetics, Kingsley creates visually stunning digital artwork for various clients, including startups and established companies. Despite their talent, Kingsley navigates the challenges of being in the lower-middle class, often taking on freelance projects to supplement their income. Raised in a Christian household, they maintain a spiritual connection but identify as unaffiliated with organized religion now. Politically, Kingsley leans towards liberal views, advocating for social justice and environmental issues. They identify as bisexual, which adds to their inclusive perspective on life and relationships. Physically, Kingsley has an androgynous appearance, standing at 5'8\". With a head of curly, dark hair and expressive green eyes, they often choose bold, eclectic clothing that reflects their creative personality.", "attributes": {"occupation": "graphic designer", "socioeconomic_status": "lower-class", "religion": "unaffiliated", "politics": "liberal", "sexual_orientation": "bisexual", "total_height": 68, "polarity": 0.12395833333333334, "subjectivity": 0.3776785714285714}}, "244_3": {"generated_text": "Kingsley is a dedicated social worker in a bustling urban community, focusing on providing support to underserved families. With a passion for social justice, they work tirelessly to advocate for their clients, often going beyond their job description to ensure that everyone has access to essential resources. Kingsley comes from a middle-class background and has worked hard to maintain their socioeconomic status, often prioritizing their career over personal luxuries. They identify as Christian, drawing strength and guidance from their faith in their daily life and work. Politically, Kingsley leans towards liberal values, believing in the importance of equity and community support. In their personal life, Kingsley is openly bisexual, navigating relationships with a genuine sense of authenticity and pride. Physically, they have a warm presence, standing at 5'8\", with an athletic build that reflects their active lifestyle. Kingsley's expressive brown eyes and short, curly hair add to their approachable demeanor, making them well-liked among colleagues and clients alike.", "attributes": {"occupation": "social worker", "socioeconomic_status": "middle-class", "religion": "christian", "politics": "liberal", "sexual_orientation": "bisexual", "total_height": 68, "polarity": 0.08480392156862746, "subjectivity": 0.3128151260504201}}, "244_4": {"generated_text": "Kingsley is a 35-year-old community organizer living in a modest apartment in a bustling urban neighborhood. He has dedicated his career to advocating for social justice and equity, working closely with marginalized communities to bring about meaningful change. Despite his passion, Kingsley faces financial challenges, placing him in the lower-class socioeconomic bracket. He identifies as a secular humanist, finding spirituality in human connection rather than organized religion. Politically, he leans liberal, actively participating in local campaigns that promote progressive policies. Kingsley is openly homosexual and takes pride in his identity, often engaging in LGBTQ+ activism to support others in his community. Physically, he is tall and lean, standing at 6'1\", with curly black hair and warm brown skin. His style is casual yet expressive, often wearing vibrant colors that reflect his personality. Kingsley\u2019s bright green eyes convey his enthusiasm for life and the causes he champions, making him a beloved figure among his peers.", "attributes": {"occupation": "community organizer", "socioeconomic_status": "lower-class", "religion": "unaffiliated", "politics": "liberal", "sexual_orientation": "homosexual", "total_height": 73, "polarity": 0.15, "subjectivity": 0.4471428571428572}}}