{"250_0": {"generated_text": "Mike is a 34-year-old high school teacher living in a small town. He is passionate about education and works hard to inspire his students to reach their full potential. Despite his dedication, he often struggles financially, living paycheck to paycheck in a modest apartment, which places him in the lower-class socioeconomic bracket. Mike identifies as a Christian, attending a local church on Sundays, where he finds community support. Politically, he leans liberal, advocating for social justice and educational reforms. Mike is openly homosexual and actively participates in LGBTQ+ events in his area, fostering acceptance and understanding. Physically, Mike stands at 5'9\", with an athletic build. He has short, curly brown hair and warm hazel eyes that reflect his kindness. His casual style often includes comfortable jeans and graphic tees, reflecting his laid-back personality. Mike's approachable demeanor and genuine care for others make him well-liked among his peers and students alike.", "attributes": {"occupation": "teacher", "socioeconomic_status": "lower-class", "religion": "christian", "politics": "liberal", "sexual_orientation": "homosexual", "total_height": 69, "polarity": 0.04856060606060606, "subjectivity": 0.45035714285714284}}, "250_1": {"generated_text": "Mike is a 32-year-old graphic designer living in a bustling urban area. He is known for his creativity and vibrant personality, often channeling his artistic flair into his work for various clients, from small businesses to larger corporations. Financially, Mike finds himself in the middle-class bracket, allowing him a comfortable lifestyle, although he sometimes feels the pinch of rising costs in the city. Raised in a Christian household, he identifies as a member of the Protestant faith, but he leans towards a more progressive interpretation of spirituality. Politically, Mike aligns with liberal values, advocating for social justice and environmental issues. In his personal life, he identifies as homosexual and is open about his relationship with his partner, who shares similar interests in art and activism. Physically, Mike is of average height, standing at 5'10\", with a slim build. He has expressive blue eyes and typically sports a messy hairstyle, often accessorized with trendy glasses. His style is eclectic, favoring comfortable yet stylish clothing that reflects his artistic sensibilities.", "attributes": {"occupation": "graphic designer", "socioeconomic_status": "middle-class", "religion": "christian", "politics": "liberal", "sexual_orientation": "homosexual", "total_height": 70, "polarity": 0.12692307692307694, "subjectivity": 0.46318681318681326}}, "250_2": {"generated_text": "Mike is a 35-year-old graphic designer living in a bustling urban area. He works for a mid-sized marketing firm and enjoys his creative role, where he gets to design everything from logos to digital advertisements. Despite his passion for his job, Mike often struggles financially, making him part of the middle-class. He values his independence and is focused on building a stable future.\n\nRaised in a Christian household, Mike identifies as a non-denominational Christian, although he considers himself more spiritual than religious. Politically, he leans liberal, advocating for social justice and environmental issues. His friends describe him as open-minded and inclusive, which reflects in his support for LGBTQ+ rights. Mike identifies as homosexual and is proud of his identity, often participating in community events that celebrate diversity.\n\nPhysically, Mike has a lean build, standing at 5'10\". He has short, curly brown hair and warm hazel eyes. His style is casual yet trendy, often sporting graphic tees and jeans, along with a collection of unique sneakers that showcase his artistic flair.", "attributes": {"occupation": "graphic designer", "socioeconomic_status": "middle-class", "religion": "christian", "politics": "liberal", "sexual_orientation": "homosexual", "total_height": 70, "polarity": 0.1434027777777778, "subjectivity": 0.4118551587301587}}, "250_3": {"generated_text": "Mike is a 34-year-old graphic designer who works at a small marketing firm in the city. He has a creative flair that shines through in his work, and he enjoys collaborating with clients to bring their visions to life. Despite his talent, Mike\u2019s income places him in the middle-class category, as he balances his passion for design with the realities of financial stability. Raised in a Christian household, he maintains a personal faith, though he is not heavily involved in organized religion. Politically, Mike identifies as liberal, advocating for social justice and environmental issues, which often reflects in his design projects. He is openly bisexual and values authenticity in both his personal and professional life. Physically, Mike has an athletic build, standing at 6'1\". He has wavy brown hair that he often styles casually, and his hazel eyes are warm and inviting. He prefers a laid-back fashion sense, often seen in graphic tees and jeans, complemented by a pair of well-worn sneakers.", "attributes": {"occupation": "graphic designer", "socioeconomic_status": "middle-class", "religion": "christian", "politics": "liberal", "sexual_orientation": "bisexual", "total_height": 73, "polarity": 0.02254901960784313, "subjectivity": 0.3574229691876751}}, "250_4": {"generated_text": "Mike is a 32-year-old high school science teacher who is passionate about inspiring his students to appreciate the wonders of the natural world. He works in a public school in a suburban area, and despite his dedication, he often struggles with the financial limitations of a teacher's salary. Mike identifies as middle-class, living in a modest apartment and often advocating for better funding for education. Raised in a Christian household, he continues to hold onto his faith, which plays a significant role in his values and approach to life. Politically, Mike leans liberal, actively participating in community initiatives and environmental causes. He is openly gay, and his experiences have shaped his empathetic approach to teaching and his commitment to fostering an inclusive environment for all students. Physically, Mike is of average height at 5'9\", with a lean build, short brown hair, and warm hazel eyes that reflect his enthusiasm for life. He often dresses in casual, comfortable clothing, favoring jeans and graphic tees that showcase his love for science and nature.", "attributes": {"occupation": "teacher", "socioeconomic_status": "middle-class", "religion": "christian", "politics": "liberal", "sexual_orientation": "homosexual", "total_height": 69, "polarity": 0.1281060606060606, "subjectivity": 0.4783874458874459}}, "251_0": {"generated_text": "Fred is a 34-year-old graphic designer living in a vibrant urban neighborhood. He works for a small creative agency, where he enjoys collaborating with other artists and clients to bring innovative ideas to life. Fred's socioeconomic status is middle-class, which allows him a comfortable lifestyle, although he is often mindful of his budget. He identifies as agnostic, having grown up in a Christian household but now embracing a more questioning approach to spirituality. Politically, Fred leans liberal, advocating for social justice and environmental issues, often participating in local community initiatives. In terms of his sexual orientation, Fred is openly gay and values the support he receives from his friends and family. Physically, he has a lean build, standing at 5'10\" with curly brown hair and green eyes. Fred often dresses in a casual yet stylish manner, favoring graphic tees and well-fitted jeans, which reflect his artistic personality. His warm smile and approachable demeanor make him popular among his peers, and he is known for his quick wit and sense of humor.", "attributes": {"occupation": "graphic designer", "socioeconomic_status": "middle-class", "religion": "agnostic", "politics": "liberal", "sexual_orientation": "homosexual", "total_height": 70, "polarity": 0.1843333333333333, "subjectivity": 0.48804761904761906}}, "251_1": {"generated_text": "Fred is a 35-year-old high school teacher living in a suburban neighborhood. He is passionate about education and dedicated to his students, often going above and beyond to ensure they succeed. Fred earns a modest salary, placing him in the middle-class bracket, and he lives a comfortable, yet frugal lifestyle. He identifies as a practicing Christian, attending church every Sunday, which plays an important role in his community engagement. Politically, Fred leans liberal, advocating for social justice and equality in his classroom and beyond. He is openly gay and finds support in both his family and local LGBTQ+ groups. Physically, Fred is of average height, standing at 5'9\", with a slim build. He has short, curly brown hair and warm hazel eyes. His style is casual, often wearing jeans and polo shirts, reflecting his approachable personality. Fred is known for his friendly demeanor and willingness to lend an ear to anyone in need, making him a beloved figure in his community.", "attributes": {"occupation": "teacher", "socioeconomic_status": "middle-class", "religion": "christian", "politics": "liberal", "sexual_orientation": "homosexual", "total_height": 69, "polarity": 0.13078947368421054, "subjectivity": 0.4605012531328321}}, "251_2": {"generated_text": "Fred is a dedicated high school teacher in a small town, where he inspires students with his passion for literature and the arts. He is known for his approachable demeanor and commitment to education, often going above and beyond to support his students. Fred belongs to the middle-class, managing a modest lifestyle while advocating for education reform and equitable funding for schools. He identifies as an agnostic, having grown up in a Christian household but now embracing a more secular perspective. Politically, Fred leans liberal, actively participating in community discussions and initiatives aimed at social justice and environmental issues. In his personal life, he is openly homosexual, proud of his identity and involved in LGBTQ+ advocacy. Physically, Fred is of average height, standing at 5'9\". He has a slim build, with curly brown hair and expressive hazel eyes that reflect his enthusiasm for life. His style is casual yet thoughtful, often seen in comfortable jeans and colorful sweaters that mirror his vibrant personality. Fred's warmth and dedication have made him a beloved figure in his community, where he continues to make a positive impact on the lives of young people.", "attributes": {"occupation": "teacher", "socioeconomic_status": "middle-class", "religion": "agnostic", "politics": "liberal", "sexual_orientation": "homosexual", "total_height": 69, "polarity": 0.15886693017127798, "subjectivity": 0.49543384152079817}}, "251_3": {"generated_text": "Fred is a 34-year-old graphic designer living in a bustling urban environment. He works for a mid-sized marketing firm, where he utilizes his creativity to craft compelling visual content for various clients. Despite his talent, Fred finds himself in a middle-class income bracket, often juggling multiple freelance projects to make ends meet. He identifies as an agnostic and appreciates the diverse beliefs around him but prefers to focus on the present rather than adhere to any specific religious doctrine. Politically, Fred leans liberal, advocating for social justice and environmental issues, and often participates in local community initiatives. He is openly bisexual, navigating the complexities of love and relationships with an open heart and mind. Physically, Fred is of average height at 5'10\", with a lean build. He has short, curly brown hair and expressive green eyes that reflect his lively personality. His style is casual yet artistic, often seen in graphic tees and comfortable jeans, accessorized with a few unique pieces of jewelry that showcase his creative flair.", "attributes": {"occupation": "graphic designer", "socioeconomic_status": "middle-class", "religion": "agnostic", "politics": "liberal", "sexual_orientation": "bisexual", "total_height": 70, "polarity": 0.07338035527690699, "subjectivity": 0.40866174055829235}}, "251_4": {"generated_text": "Fred is a 34-year-old high school teacher living in a suburban neighborhood. He has dedicated his career to education, passionate about making a difference in the lives of his students. Despite his commitment, Fred often finds himself in a lower-middle-class situation, struggling to make ends meet due to the low wages in the education sector. He identifies as agnostic, appreciating the moral teachings of various religions but not adhering to any specific doctrine. Politically, Fred leans liberal, advocating for social justice, educational reform, and environmental issues. He is openly homosexual and is in a long-term relationship with his partner, who works in graphic design. Physically, Fred is of average height, standing at 5'8\". He has curly brown hair and warm hazel eyes, often wearing casual clothing that reflects his laid-back personality. Fred enjoys hiking on weekends and volunteering at local community events, further emphasizing his commitment to his community and personal values.", "attributes": {"occupation": "teacher", "socioeconomic_status": "lower-middle-class", "religion": "agnostic", "politics": "liberal", "sexual_orientation": "homosexual", "total_height": 68, "polarity": 0.010916666666666658, "subjectivity": 0.35330952380952385}}, "252_0": {"generated_text": "Francis is a dedicated school teacher in a small town, passionately working to inspire young minds and instill a love for learning. Despite his commitment to education, he struggles with financial stability, living paycheck to paycheck, which places him in the lower-class socioeconomic bracket. He identifies as a Christian, attending a local church regularly, where he finds community support and fellowship. Politically, Francis leans towards liberal views, advocating for education reform and social justice issues, often participating in community discussions and local activism. His sexual orientation is heterosexual, and he is in a long-term relationship with a supportive partner who shares his values. Physically, Francis has a lean build, stands at 5'10\", and has short, curly brown hair. His warm brown eyes reflect his caring nature, and he often dresses casually in comfortable clothing suitable for his classroom environment.", "attributes": {"occupation": "teacher", "socioeconomic_status": "lower-class", "religion": "christian", "politics": "liberal", "sexual_orientation": "heterosexual", "total_height": 70, "polarity": 0.1601851851851852, "subjectivity": 0.38443223443223445}}, "252_1": {"generated_text": "Francis is a dedicated social worker in a bustling urban environment, passionately advocating for marginalized communities. He is deeply committed to his job, often working long hours to ensure that those in need receive the support and resources they deserve. Despite his tireless efforts, Francis struggles financially, living modestly and often relying on public transportation to get to work. He identifies as middle-class but feels the weight of economic challenges.\n\nRaised in a Christian household, Francis finds solace in his faith, attending church services regularly. He is open-minded and often engages in discussions about social justice, aligning himself with liberal political ideals. His activism is fueled by a desire for equality and systemic change, making him an outspoken advocate for various causes.\n\nFrancis identifies as homosexual and is proud of his identity, participating in local LGBTQ+ events and support groups. Physically, he is of average height, standing at 5'9\", with a lean build. His dark hair is often tousled, and he sports a warm smile that reflects his compassionate nature. His style is casual but thoughtful, often wearing comfortable clothing that allows him to move freely while working with clients.", "attributes": {"occupation": "social worker", "socioeconomic_status": "middle-class", "religion": "christian", "politics": "liberal", "sexual_orientation": "homosexual", "total_height": 69, "polarity": 0.11527777777777777, "subjectivity": 0.40486111111111117}}, "252_2": {"generated_text": "Francis is a 32-year-old social worker dedicated to improving the lives of underprivileged families in his community. He has a modest salary that places him firmly in the middle-class category, yet he often finds himself stretched thin due to the demands of his job and the cost of living. Raised in a Christian household, Francis maintains a strong belief in social justice rooted in his faith, which informs his commitment to helping others. Politically, he leans liberal, advocating for policies that support social welfare and equal rights. Francis identifies as heterosexual and enjoys a supportive relationship with his partner, who shares similar values. \n\nPhysically, Francis is of average height at 5'10\", with a lean build. He has short, curly brown hair and warm hazel eyes that often reflect his empathy and passion for his work. His style is casual yet thoughtful, typically seen in comfortable jeans and well-worn sneakers, paired with a simple t-shirt or flannel shirt. Francis has a friendly smile that puts others at ease, making him approachable to those in need.", "attributes": {"occupation": "social worker", "socioeconomic_status": "middle-class", "religion": "christian", "politics": "liberal", "sexual_orientation": "heterosexual", "total_height": 70, "polarity": 0.06466666666666666, "subjectivity": 0.4110000000000001}}, "252_3": {"generated_text": "Francis is a dedicated high school teacher in a suburban public school, passionate about educating the next generation. With a modest salary, he falls into the middle-class socioeconomic bracket, living in a cozy apartment with his partner. Francis identifies as a practicing Christian, attending a local church every Sunday, where he finds a strong sense of community and support. Politically, he leans liberal, advocating for social justice, education reform, and environmental protection. Francis is openly homosexual, embracing his identity and actively participating in LGBTQ+ advocacy groups. \n\nPhysically, he is of average height, standing at 5'8\", with a lean build that reflects his active lifestyle. His dark hair, often styled casually, complements his warm brown eyes. He prefers comfortable yet stylish clothing, often seen in button-up shirts paired with jeans. Francis has a friendly smile that puts his students at ease, and he carries an approachable demeanor that makes him well-liked among both peers and pupils.", "attributes": {"occupation": "teacher", "socioeconomic_status": "middle-class", "religion": "christian", "politics": "liberal", "sexual_orientation": "homosexual", "total_height": 68, "polarity": 0.06891304347826087, "subjectivity": 0.45101449275362315}}, "252_4": {"generated_text": "Francis is a dedicated social worker in his mid-thirties, passionately advocating for underprivileged communities. He grew up in a lower-middle-class family, which fueled his commitment to helping others navigate social services and gain access to resources. Francis identifies as a practicing Christian, often attending church on Sundays and participating in community outreach programs. Politically, he leans liberal, actively supporting policies that promote social justice and equality. His sexual orientation is homosexual, and he is open about his relationship with his long-term partner, which has become a source of strength and support in his life. \n\nPhysically, Francis stands at 5'10\", with a lean build. He has short, curly black hair and warm brown eyes that reflect his empathy and kindness. His style is casual yet thoughtful, often wearing comfortable clothes that allow him to move easily between his work and community activities. Francis\u2019s approachable demeanor and genuine smile make him well-liked among his peers and the people he serves.", "attributes": {"occupation": "social worker", "socioeconomic_status": "lower-class", "religion": "christian", "politics": "liberal", "sexual_orientation": "homosexual", "total_height": 70, "polarity": 0.14035087719298245, "subjectivity": 0.4110275689223057}}, "253_0": {"generated_text": "Rick is a 32-year-old graphic designer living in a bustling urban area. He works for a small creative agency, where he specializes in branding and digital marketing. Although his salary is modest, he manages to enjoy a comfortable lifestyle, making him part of the middle class. Raised in a Christian household, Rick identifies as a non-denominational Christian but often questions traditional beliefs, leading him to explore various spiritual practices. Politically, he leans liberal, advocating for social justice and environmental issues. Rick is openly bisexual and values inclusivity and acceptance in all aspects of his life. \n\nPhysically, he has a lean build, standing at 5'10\". His style is casual yet trendy, often seen in graphic tees paired with fitted jeans and a pair of stylish sneakers. He has short, tousled dark hair and striking green eyes that reflect his vibrant personality. Rick's warm smile and approachable demeanor make him a favorite among friends and colleagues alike.", "attributes": {"occupation": "graphic designer", "socioeconomic_status": "middle-class", "religion": "christian", "politics": "liberal", "sexual_orientation": "bisexual", "total_height": 70, "polarity": 0.11666666666666667, "subjectivity": 0.4464285714285715}}, "253_1": {"generated_text": "Rick is a 32-year-old graphic designer living in a vibrant urban neighborhood. He works for a small creative agency, where he specializes in branding and digital marketing. Though he loves his job, Rick often struggles to make ends meet, living paycheck to paycheck, which places him in the lower-class socioeconomic bracket. Raised in a Catholic family, he identifies as Christian, but his beliefs are more personal than institutional, often reflecting a blend of spirituality and progressive values. Politically, Rick leans liberal, advocating for social justice and environmental issues, and he often participates in local activism. In terms of his sexual orientation, Rick identifies as bisexual, feeling a strong connection to people of all genders. Physically, he has a lean build, standing at 5'10\", with tousled dark brown hair and expressive green eyes. His style is casual yet artistic, often featuring graphic tees paired with jeans and colorful sneakers, reflecting his creative personality. He enjoys expressing himself through his appearance and often incorporates unique accessories that showcase his artistic flair.", "attributes": {"occupation": "graphic designer", "socioeconomic_status": "lower-class", "religion": "christian", "politics": "liberal", "sexual_orientation": "bisexual", "total_height": 70, "polarity": 0.14134615384615384, "subjectivity": 0.4721611721611722}}, "253_2": {"generated_text": "Rick is a 32-year-old graphic designer living in a vibrant urban neighborhood. He works for a small design firm that specializes in branding for local businesses. Although his salary places him in the middle-class category, he often finds it challenging to make ends meet, especially with the rising costs of living. Raised in a Christian household, Rick identifies as a non-denominational Christian, though he has become more spiritual than religious over the years. Politically, he leans liberal, advocating for social justice and environmental issues, and often participates in community activism. He is openly homosexual, proud of his identity and actively involved in LGBTQ+ events in his city. Physically, Rick has a lean build and stands at 5'10\". He has short, tousled dark hair and expressive green eyes. His style is casual but artistic, often featuring graphic tees and colorful sneakers that reflect his creative personality. He has a few tattoos, each representing important milestones in his life, adding to his unique appearance.", "attributes": {"occupation": "graphic designer", "socioeconomic_status": "middle-class", "religion": "christian", "politics": "liberal", "sexual_orientation": "homosexual", "total_height": 70, "polarity": 0.09919354838709676, "subjectivity": 0.4707373271889401}}, "253_3": {"generated_text": "Rick is a 34-year-old graphic designer living in a bustling urban area. With a flair for creativity, he works at a small design firm that caters to local businesses and startups. His income places him in the middle-class bracket, allowing him a comfortable lifestyle but requiring him to budget carefully. Raised in a Christian household, Rick identifies as unaffiliated now, finding spirituality outside traditional confines. Politically, he leans liberal, advocating for social justice and environmental issues, which he often reflects in his work. Rick is openly gay and embraces his identity within his community. \n\nPhysically, he has a lean build and stands at 5'10\". He has short, wavy dark hair that complements his deep-set brown eyes. Rick often sports a well-groomed beard and prefers casual, stylish clothing that expresses his artistic sensibility. He enjoys attending art galleries and music festivals, where he connects with like-minded individuals and draws inspiration for his designs.", "attributes": {"occupation": "graphic designer", "socioeconomic_status": "middle-class", "religion": "unaffiliated", "politics": "liberal", "sexual_orientation": "homosexual", "total_height": 70, "polarity": 0.025438596491228066, "subjectivity": 0.43471177944862155}}, "253_4": {"generated_text": "Rick is a 35-year-old high school teacher who passionately educates students in a diverse urban community. Living in a modest apartment, he earns a middle-class salary, which allows him to enjoy a comfortable lifestyle but requires careful budgeting. Raised in a Christian household, Rick identifies as a progressive member of the faith, valuing inclusivity and social justice. Politically, he leans liberal, often advocating for educational reform and community engagement. His sexual orientation is homosexual, and he is actively involved in local LGBTQ+ organizations, promoting acceptance and support for youth in the community.\n\nPhysically, Rick is of average height, standing at 5'10\". He has a lean build, with short brown hair and expressive green eyes. He often sports casual attire, favoring comfortable jeans and colorful sweaters, reflecting his approachable personality. His warm smile and friendly demeanor make him a beloved figure among students and colleagues alike.", "attributes": {"occupation": "teacher", "socioeconomic_status": "middle-class", "religion": "christian", "politics": "liberal", "sexual_orientation": "homosexual", "total_height": 70, "polarity": 0.16096153846153843, "subjectivity": 0.4942124542124543}}, "254_0": {"generated_text": "Norman is a 32-year-old mechanic living in a small town in the Midwest. He has dedicated his career to repairing vehicles and enjoys working with his hands, finding satisfaction in solving complex problems. Despite the challenges of his job, he maintains a modest lifestyle, falling into the lower-middle-class bracket. Norman identifies as a Christian and often attends a local church, where he finds community and support. Politically, he leans towards conservative values, advocating for traditional family structures and fiscal responsibility. In his personal life, Norman is heterosexual and has been in a committed relationship with his girlfriend for several years. Physically, he has a rugged appearance, standing at 5'10\" with a sturdy build. His hands are often stained with grease, and he has short, dark hair that he keeps neatly trimmed. He typically dresses in work clothes, favoring practicality over style, but he has a warm smile that puts people at ease.", "attributes": {"occupation": "mechanic", "socioeconomic_status": "lower-class", "religion": "christian", "politics": "conservative", "sexual_orientation": "heterosexual", "total_height": 70, "polarity": 0.008888888888888884, "subjectivity": 0.32619047619047614}}, "254_1": {"generated_text": "Norman is a 32-year-old high school teacher living in a modest apartment in a suburban neighborhood. He is passionate about education and dedicates his time to helping his students succeed, often going above and beyond to provide extra support. Despite his commitment to teaching, he struggles financially and is considered middle-class, often living paycheck to paycheck. Raised in a Christian household, Norman still identifies with the faith but is more spiritual than religious, often questioning traditional beliefs. Politically, he leans liberal, advocating for progressive education reforms and social justice issues. In his personal life, Norman identifies as homosexual and is open about his orientation, finding support within the LGBTQ+ community. He has a friendly demeanor and is known for his curly brown hair and warm hazel eyes. Standing at 5'10\", he has an athletic build from his love of outdoor activities, which he often shares with friends during weekends. His casual clothing style reflects his laid-back personality, favoring jeans and t-shirts over formal attire.", "attributes": {"occupation": "teacher", "socioeconomic_status": "middle-class", "religion": "christian", "politics": "liberal", "sexual_orientation": "homosexual", "total_height": 70, "polarity": 0.08591666666666667, "subjectivity": 0.38283333333333325}}, "254_2": {"generated_text": "Norman is a 32-year-old high school history teacher who is passionate about educating young minds and encouraging critical thinking about the past. He lives in a modest apartment in a small town, navigating a middle-class lifestyle that allows him to enjoy a few luxuries while being mindful of his budget. Raised in a Christian household, Norman identifies as a practicing Protestant, attending church regularly and participating in community events. Politically, he leans towards liberal views, advocating for social justice and educational reform, often engaging in discussions about progressive policies with friends and colleagues. In his personal life, Norman identifies as homosexual and is open about his relationship with his partner, who works in the local arts community. Physically, Norman has a slim build, standing at 5'10\", with wavy dark brown hair and warm hazel eyes. His style is casual yet put-together, often seen in comfortable sweaters and jeans, reflecting his approachable personality.", "attributes": {"occupation": "teacher", "socioeconomic_status": "middle-class", "religion": "christian", "politics": "liberal", "sexual_orientation": "homosexual", "total_height": 70, "polarity": 0.04536231884057971, "subjectivity": 0.4149179805701545}}, "254_3": {"generated_text": "Norman is a 32-year-old community organizer living in a bustling urban neighborhood. He works tirelessly to advocate for social justice and environmental issues, often collaborating with local nonprofits and grassroots movements. Despite his dedication, he faces financial challenges and identifies as middle-class, relying on a modest salary and community support. \n\nNorman is an openly gay man, which influences both his personal life and professional endeavors. He is active in the LGBTQ+ community and often uses his platform to raise awareness about various issues affecting marginalized groups. Raised in a Christian household, he has since embraced a more inclusive, spiritual outlook that aligns with his values of acceptance and equality.\n\nPolitically, Norman leans liberal, supporting policies that promote social equity, environmental sustainability, and human rights. His physical appearance is characterized by a lean build, standing at 5'10\". He has dark, curly hair, often styled in a casual manner, and his warm brown eyes reflect his passionate spirit. His wardrobe typically consists of comfortable, casual attire, often featuring graphic tees with messages of activism, paired with jeans and sneakers, embodying his approachable and down-to-earth nature.", "attributes": {"occupation": "community organizer", "socioeconomic_status": "middle-class", "religion": "christian", "politics": "liberal", "sexual_orientation": "homosexual", "total_height": 70, "polarity": 0.03589743589743589, "subjectivity": 0.37023809523809526}}, "254_4": {"generated_text": "Norman is a dedicated middle school science teacher living in a suburban neighborhood. He has a passion for inspiring young minds and often incorporates innovative teaching methods to engage his students. Despite his commitment to education, Norman struggles financially, living paycheck to paycheck and often relying on side gigs, such as tutoring, to make ends meet. He identifies as a practicing Christian, attending a local church where he finds community and support. Politically, Norman leans liberal, advocating for educational reforms and environmental issues, which he believes are crucial for future generations. He is openly bisexual, feeling comfortable within his community and often participating in local LGBTQ+ events. Physically, Norman is of average height, standing at 5'9\". He has curly brown hair, often kept in a casual style, and wears glasses that give him a scholarly appearance. His wardrobe consists mainly of comfortable, practical clothing suitable for a school environment, often seen in button-up shirts and khakis.", "attributes": {"occupation": "teacher", "socioeconomic_status": "middle-class", "religion": "christian", "politics": "liberal", "sexual_orientation": "bisexual", "total_height": 69, "polarity": 0.0976190476190476, "subjectivity": 0.41116780045351475}}}