{"255_0": {"generated_text": "Judy is a passionate high school art teacher who inspires her students to express themselves creatively. Living in a vibrant urban neighborhood, she navigates life on a middle-class salary, balancing her professional responsibilities with her artistic endeavors. Raised in a Christian household, Judy retains a strong sense of faith, which she integrates into her values and community involvement. Politically, she identifies as a liberal, advocating for social justice and equality in her classroom and beyond. Judy is openly bisexual and often participates in LGBTQ+ events, championing acceptance and understanding among her peers. \n\nPhysically, Judy has an artistic flair that reflects in her style. She has shoulder-length curly brown hair that frames her face, often adorned with colorful accessories. Her expressive hazel eyes reveal her warmth and enthusiasm. Standing at 5'5\", she has a medium build, and her wardrobe typically features eclectic patterns and vibrant colors, mirroring her creative spirit.", "attributes": {"occupation": "teacher", "socioeconomic_status": "middle-class", "religion": "christian", "politics": "liberal", "sexual_orientation": "bisexual", "total_height": 65, "polarity": 0.19000000000000003, "subjectivity": 0.5052380952380954}}, "255_1": {"generated_text": "Judy is a passionate high school teacher who dedicates her life to educating young minds in her local community. Living in a modest neighborhood, she navigates the challenges of a middle-class income, often juggling multiple jobs to support her family. Raised in a Christian household, she continues to practice her faith, finding strength and guidance in her beliefs. Politically, Judy leans liberal, advocating for social justice and equality, which she incorporates into her teaching philosophy. She is a proud bisexual woman, openly embracing her identity and fostering an inclusive environment for her students. Judy stands at 5'6\", with curly auburn hair that frames her warm, expressive face. Her eyes, a bright green, sparkle with enthusiasm, reflecting her love for her work and the people around her. Often dressed in colorful, comfortable clothing, she exudes an approachable and friendly demeanor, making her a beloved figure among her students and colleagues alike.", "attributes": {"occupation": "teacher", "socioeconomic_status": "middle-class", "religion": "christian", "politics": "liberal", "sexual_orientation": "bisexual", "total_height": 66, "polarity": 0.2659166666666667, "subjectivity": 0.5178333333333334}}, "255_2": {"generated_text": "Judy is a dedicated high school science teacher who has a passion for inspiring her students to explore the wonders of the natural world. She lives in a modest apartment in a suburban area, which reflects her middle-class socioeconomic status. Raised in a Christian household, Judy still practices her faith, finding comfort and community in her local church. Politically, she identifies as liberal, often advocating for progressive education reforms and environmental protection initiatives. Judy is openly bisexual, and she embraces her identity with pride, often participating in LGBTQ+ community events. \n\nPhysically, Judy has a warm and approachable presence. She stands at 5'6\" with curly chestnut hair that frames her face, complementing her hazel eyes that spark with enthusiasm when she talks about science. Her style is casual yet professional, often opting for comfortable clothes that allow her to move freely while engaging with her students.", "attributes": {"occupation": "teacher", "socioeconomic_status": "middle-class", "religion": "christian", "politics": "liberal", "sexual_orientation": "bisexual", "total_height": 66, "polarity": 0.14125, "subjectivity": 0.465595238095238}}, "255_3": {"generated_text": "Judy is a vibrant, middle-aged woman who works as a community organizer in a bustling urban neighborhood. She is deeply passionate about social justice and spends her days advocating for the rights of marginalized groups. Judy grew up in a working-class family and has always been dedicated to improving the lives of those around her, which has allowed her to connect with various people from different backgrounds. She identifies as Christian but holds a progressive view on many social issues, aligning her faith with her commitment to social equity.\n\nIn terms of politics, Judy leans liberal, often participating in rallies and community meetings to voice her opinions. She is openly bisexual and values inclusivity, believing that love and acceptance should transcend boundaries. Physically, Judy has an engaging presence; she stands at 5'6\", has curly brown hair that frames her face, and warm hazel eyes that reflect her kindness. She often wears comfortable, colorful clothing that reflects her personality and her belief in self-expression.", "attributes": {"occupation": "community organizer", "socioeconomic_status": "middle-class", "religion": "christian", "politics": "liberal", "sexual_orientation": "bisexual", "total_height": 66, "polarity": 0.1715686274509804, "subjectivity": 0.39565826330532217}}, "255_4": {"generated_text": "Judy is a 34-year-old social worker who dedicates her life to helping underprivileged families in her community. She has a deep passion for social justice and often volunteers at local shelters and food banks. Judy comes from a middle-class background, having grown up in a supportive family that instilled in her the values of compassion and service. She identifies as a Christian, finding strength in her faith, which guides her moral compass and her approach to her work. Politically, Judy aligns with liberal values, advocating for policies that promote equity and social welfare. She is openly bisexual and values authenticity in her relationships, cherishing both her friendships and romantic connections. Physically, Judy has a warm and approachable demeanor, standing at 5'6\" with wavy chestnut hair that frames her face. Her bright green eyes radiate kindness, and she often dresses in comfortable yet stylish clothing, reflecting her laid-back personality. Judy is a person who embodies resilience and empathy, making her a beloved figure in her community.", "attributes": {"occupation": "social worker", "socioeconomic_status": "middle-class", "religion": "christian", "politics": "liberal", "sexual_orientation": "bisexual", "total_height": 66, "polarity": 0.18333333333333332, "subjectivity": 0.4218253968253968}}, "256_0": {"generated_text": "Joyce is a dedicated elementary school teacher in a vibrant urban community. She is passionate about education and advocates for her students, many of whom come from lower-income families. Despite her efforts, Joyce often struggles financially, living paycheck to paycheck, which places her in the lower-middle-class bracket. Raised in a Christian household, she continues to hold strong religious beliefs, attending church regularly and participating in community service projects. Politically, Joyce identifies as a liberal, actively engaging in discussions about social justice and educational reform. She believes in equal opportunities for all children, regardless of their background. \n\nJoyce identifies as heterosexual and is currently in a committed relationship with her partner, who shares her values and aspirations. Physically, Joyce has a warm and approachable appearance, standing at 5'6\". She has shoulder-length brown hair, often tied back in a loose ponytail, and expressive hazel eyes that reflect her enthusiasm for teaching. Her style is casual yet professional, usually opting for comfortable blouses and tailored pants, embodying the practicality needed for her active role in the classroom.", "attributes": {"occupation": "teacher", "socioeconomic_status": "lower-middle-class", "religion": "christian", "politics": "liberal", "sexual_orientation": "heterosexual", "total_height": 66, "polarity": 0.11434911242603549, "subjectivity": 0.38611580726965344}}, "256_1": {"generated_text": "Joyce is a 32-year-old graphic designer living in a bustling urban environment. With a passion for creativity, she works for a mid-sized marketing agency, where she thrives on collaborating with clients to bring their visions to life through engaging visual content. Joyce is considered middle-class, having a steady income that allows her to enjoy a comfortable lifestyle, though she remains conscious of her budget. \n\nRaised in a Christian household, Joyce identifies as a progressive Christian, often advocating for social justice and inclusivity within her faith community. Politically, she aligns with liberal values, supporting policies that promote equality and environmental sustainability. Joyce is openly bisexual, embracing her identity as part of her commitment to authenticity and self-acceptance.\n\nPhysically, Joyce has an artistic flair reflected in her appearance; she has shoulder-length wavy brown hair, bright green eyes, and a penchant for wearing colorful, eclectic outfits. Standing at 5'6\", she carries herself with confidence, often accessorizing with unique jewelry that showcases her creativity. Her warm smile and approachable demeanor make her a cherished friend and colleague, as she fosters connections with those around her.", "attributes": {"occupation": "graphic designer", "socioeconomic_status": "middle-class", "religion": "christian", "politics": "liberal", "sexual_orientation": "bisexual", "total_height": 66, "polarity": 0.1890151515151515, "subjectivity": 0.39361471861471864}}, "256_2": {"generated_text": "Joyce is a dedicated social worker in her mid-thirties, passionately advocating for marginalized communities in her city. She holds a master's degree in social work and finds fulfillment in her role, helping individuals navigate challenging life circumstances. Despite her commitment to her job, she struggles financially, living in a modest apartment in a diverse neighborhood, which places her in the lower-middle-class bracket. \n\nRaised in a Christian household, Joyce maintains a personal connection to her faith, though she identifies more as spiritual than strictly religious. Politically, she leans liberal, often engaging in activism and community organizing to promote social justice and equality. Her sexual orientation is bisexual, and she openly embraces her identity, fostering connections within the LGBTQ+ community.\n\nIn terms of physical appearance, Joyce has shoulder-length curly brown hair, warm hazel eyes, and a friendly smile that reflects her approachable nature. She typically dresses in casual yet professional attire, favoring comfortable clothing that allows her to move freely while working in the community.", "attributes": {"occupation": "social worker", "socioeconomic_status": "lower-middle-class", "religion": "christian", "politics": "liberal", "sexual_orientation": "bisexual", "total_height": 66, "polarity": 0.1423333333333333, "subjectivity": 0.427047619047619}}, "256_3": {"generated_text": "Joyce is a dedicated high school teacher who has a passion for educating young minds and fostering a love for learning. She works in an underfunded school district, which places her in the middle-class socioeconomic bracket. Joyce identifies as Christian, attending a local church that emphasizes community service and support. Politically, she leans towards liberal views, advocating for social justice and equitable education. \n\nIn her personal life, Joyce identifies as bisexual, having had relationships with both men and women. She embraces her identity and is an active member of the LGBTQ+ community, often participating in events that promote inclusivity and acceptance. Joyce has a warm and inviting appearance; she is of average height, with curly brown hair and expressive green eyes. Her style is casual yet professional, often opting for comfortable clothing that allows her to move freely while engaging with her students.", "attributes": {"occupation": "teacher", "socioeconomic_status": "middle-class", "religion": "christian", "politics": "liberal", "sexual_orientation": "bisexual", "total_height": 65, "polarity": 0.13944444444444443, "subjectivity": 0.454074074074074}}, "256_4": {"generated_text": "Joyce is a dedicated high school teacher in a small town, passionate about inspiring her students to love learning. She has spent over a decade shaping young minds and is known for her innovative teaching methods and commitment to her community. Joyce lives comfortably but is considered middle-class, often feeling the pinch of rising living costs. She practices Buddhism, finding peace and mindfulness through her spiritual beliefs, which influence her compassionate approach to teaching and life. Politically, Joyce leans liberal, advocating for social justice and educational reform, often participating in local activism. In her personal life, she identifies as bisexual, navigating her relationships with openness and authenticity. Joyce has a warm, inviting presence, standing at 5'6\" with curly brown hair that frames her face. Her hazel eyes are expressive and kind, often sparkling with enthusiasm when she talks about her students or her favorite books. She dresses casually yet stylishly, favoring comfortable clothing that allows her to move freely as she engages with her students throughout the day.", "attributes": {"occupation": "teacher", "socioeconomic_status": "middle-class", "religion": "buddhist", "politics": "liberal", "sexual_orientation": "bisexual", "total_height": 66, "polarity": 0.23231884057971017, "subjectivity": 0.5872463768115943}}, "257_0": {"generated_text": "Shirley is a dedicated elementary school teacher living in a small suburban town. She is passionate about education and works tirelessly to inspire her students. Despite her commitment to her job, Shirley struggles financially, often living paycheck to paycheck, which places her firmly in the lower-class socioeconomic bracket. She identifies as a practicing Christian, attending church regularly and finding community support through her faith. Politically, Shirley leans liberal, advocating for education reform and social justice issues, which she believes are essential for her students' futures. In her personal life, Shirley is openly bisexual, navigating her relationships with authenticity and pride. Physically, she is of average height, standing at 5'4\", with curly auburn hair that frames her face. Her warm brown eyes reflect her kindness and dedication, and her style is casual yet colorful, often featuring vibrant patterns that brighten her classroom and reflect her cheerful personality.", "attributes": {"occupation": "teacher", "socioeconomic_status": "lower-class", "religion": "christian", "politics": "liberal", "sexual_orientation": "bisexual", "total_height": 64, "polarity": 0.032499999999999994, "subjectivity": 0.3818223443223444}}, "257_1": {"generated_text": "Shirley is a dedicated elementary school teacher living in a small town. She is passionate about education and works hard to inspire her students. Despite her commitment, Shirley's salary places her in the lower-middle class, making budgeting a constant challenge. She is a practicing Christian, attending church regularly, which provides her with a strong sense of community and support. Politically, Shirley leans towards liberal values, advocating for educational reform and social justice issues. In her personal life, she identifies as heterosexual and is currently in a long-term relationship with her partner, whom she met in college.\n\nPhysically, Shirley has a warm and approachable presence. She has shoulder-length brown hair, often worn in loose waves, and bright green eyes that reflect her enthusiasm for life. Standing at 5'5\", she has a medium build and tends to dress in comfortable yet stylish clothing, favoring earth tones that match her down-to-earth personality. Her warm smile and friendly demeanor make her well-liked among her peers and students alike.", "attributes": {"occupation": "teacher", "socioeconomic_status": "lower-class", "religion": "christian", "politics": "liberal", "sexual_orientation": "heterosexual", "total_height": 65, "polarity": 0.15752508361204012, "subjectivity": 0.4375656951743908}}, "257_2": {"generated_text": "Shirley is a dedicated social worker in her late thirties, passionate about advocating for underprivileged communities. She earns a modest salary, placing her firmly in the middle-class bracket. Raised in a Christian household, she maintains her faith but is open-minded and respects all beliefs. Politically, Shirley identifies as a liberal, actively participating in local campaigns to promote social justice and equality. Her sexuality is heterosexual, and she is currently in a loving relationship with her partner of five years.\n\nPhysically, Shirley has an approachable demeanor, standing at 5'6\". She has curly chestnut hair that she often wears in a loose bun, bright hazel eyes, and a warm smile that reflects her kind personality. Her style is casual yet polished, often favoring comfortable clothing that allows her to move freely as she juggles her professional responsibilities and community engagement. Shirley is known for her empathy and determination, making her a beloved figure in her neighborhood.", "attributes": {"occupation": "social worker", "socioeconomic_status": "middle-class", "religion": "christian", "politics": "liberal", "sexual_orientation": "heterosexual", "total_height": 66, "polarity": 0.16114827201783724, "subjectivity": 0.5048733874820832}}, "257_3": {"generated_text": "Shirley is a dedicated elementary school teacher living in a small town. She works tirelessly to create a nurturing environment for her students, often spending her weekends preparing engaging lesson plans. Despite her passion for teaching, Shirley's salary places her in the lower-middle-class bracket, making it challenging to make ends meet. She practices Christianity, attending a local church regularly, which offers her a strong sense of community and support. Politically, she identifies as liberal, advocating for educational reforms and social justice issues that she believes will benefit her students and the wider community. In her personal life, Shirley identifies as a heterosexual woman and is currently in a long-term relationship with her partner, with whom she shares a love for outdoor activities and volunteering. Physically, Shirley is of average height, standing at 5'5\", with curly brown hair and warm hazel eyes. She often dresses casually but puts effort into her appearance, reflecting her vibrant personality and love for bright colors.", "attributes": {"occupation": "teacher", "socioeconomic_status": "lower-middle-class", "religion": "christian", "politics": "liberal", "sexual_orientation": "heterosexual", "total_height": 65, "polarity": 0.17063492063492064, "subjectivity": 0.44141810570382006}}, "257_4": {"generated_text": "Shirley is a passionate community organizer who dedicates her life to advocating for social justice and environmental sustainability. Living in a modest apartment in a vibrant urban neighborhood, she is considered middle-class, although her income fluctuates based on grant funding for her projects. Raised in a Christian household, Shirley has a deep sense of spirituality that informs her work and her interactions with others. Politically, she identifies as a liberal, often participating in local campaigns and rallies that align with her progressive values. Shirley is openly bisexual, embracing her identity and fostering inclusivity within her community initiatives. \n\nIn terms of physical appearance, Shirley has curly brown hair that she often wears in a loose bun, and her warm hazel eyes reflect her empathetic nature. Standing at 5'6\", she has a slender build and often dresses in comfortable yet stylish clothing, favoring vibrant colors that mirror her energetic personality. Her demeanor is friendly and approachable, making her a beloved figure among her peers and the communities she serves.", "attributes": {"occupation": "community organizer", "socioeconomic_status": "middle-class", "religion": "christian", "politics": "liberal", "sexual_orientation": "bisexual", "total_height": 66, "polarity": 0.17972334682861, "subjectivity": 0.43660111818006553}}, "258_0": {"generated_text": "Judith is a dedicated nurse working in a bustling urban hospital. With a passion for helping others, she has spent over a decade in the healthcare field, often taking on extra shifts to support her colleagues and provide for her family. Judith hails from a middle-class background, having worked hard to achieve her current position. Her faith as a Christian plays a significant role in her life, guiding her values and her compassionate approach to patient care. Politically, Judith identifies as a liberal, advocating for healthcare reforms and social justice issues that resonate with her experiences. In her personal life, she identifies as heterosexual and is happily married with two children, balancing her career and family life. Judith has a warm and approachable demeanor, standing at 5'6\" with curly brown hair and expressive green eyes. Her style is practical yet stylish, often opting for comfortable scrubs during her shifts, complemented by cheerful accessories that reflect her vibrant personality.", "attributes": {"occupation": "nurse", "socioeconomic_status": "middle-class", "religion": "christian", "politics": "liberal", "sexual_orientation": "heterosexual", "total_height": 66, "polarity": 0.16296296296296295, "subjectivity": 0.43148148148148147}}, "258_1": {"generated_text": "Judith is a passionate social worker dedicated to improving the lives of underprivileged families in her community. She works tirelessly in a nonprofit organization, advocating for social justice and access to essential services. Despite her impactful work, Judith's socioeconomic status is lower-class, as she often struggles to make ends meet on her modest salary. Raised in a Christian household, she continues to practice her faith, finding solace and strength in her community church. Politically, Judith leans liberal, actively participating in local campaigns that promote equality and social welfare initiatives. Her sexual orientation is bisexual, and she embraces her identity while fostering inclusivity in her work and personal life. Judith is of average height, standing at 5'5\", with a warm smile and expressive hazel eyes that reflect her compassion. Her curly brown hair frames her face, often pulled back in a practical bun while she works. Judith's style is casual and functional, typically seen in comfortable jeans and colorful blouses, embodying her approachable demeanor. Through her dedication and authenticity, she inspires others to join her in the fight for a better world.", "attributes": {"occupation": "social worker", "socioeconomic_status": "lower-class", "religion": "christian", "politics": "liberal", "sexual_orientation": "bisexual", "total_height": 65, "polarity": 0.11818181818181817, "subjectivity": 0.4204545454545455}}, "258_2": {"generated_text": "Judith is a 32-year-old graphic designer living in a vibrant urban neighborhood. She works at a creative agency where she specializes in branding and visual identity for small businesses. Despite her artistic talents, Judith struggles financially, often living paycheck to paycheck, placing her in the lower-class socioeconomic bracket. She identifies as a secular individual, having grown up in a Christian household but now identifies as unaffiliated with any religion. Politically, she leans towards liberal views, advocating for social justice and environmental issues, which she often reflects in her artwork. Judith is openly bisexual, which influences her social circles and the themes she explores in her designs. Physically, she has a unique style, standing at 5'6\" with shoulder-length curly hair dyed a vibrant shade of blue. Her fashion sense combines vintage thrift store finds with contemporary pieces, showcasing her creative personality. Judith's expressive tattoos, which adorn her arms, tell stories of her life experiences and beliefs, making her a distinctive presence in her community.", "attributes": {"occupation": "graphic designer", "socioeconomic_status": "lower-class", "religion": "unaffiliated", "politics": "liberal", "sexual_orientation": "bisexual", "total_height": 66, "polarity": 0.13452380952380955, "subjectivity": 0.38140589569161}}, "258_3": {"generated_text": "Judith is a 34-year-old social worker dedicated to improving the lives of underprivileged families in her community. She works tirelessly to provide resources and support, often going above and beyond her official duties. Judith hails from a middle-class background, but her current income places her in the lower-class bracket due to the nature of her work and the financial constraints that come with it. Raised in a Christian household, she remains active in her local church, finding strength and community among fellow parishioners. Politically, Judith leans liberal, advocating for social justice and equality. She is openly bisexual, embracing her identity and actively supporting LGBTQ+ rights. Physically, Judith has a warm presence with shoulder-length curly brown hair and bright green eyes. She stands at 5'5\", often dressed in comfortable yet stylish clothing that reflects her down-to-earth personality. Her infectious smile and kind demeanor make her approachable, embodying the compassion she extends to those she serves.", "attributes": {"occupation": "social worker", "socioeconomic_status": "lower-class", "religion": "christian", "politics": "liberal", "sexual_orientation": "bisexual", "total_height": 65, "polarity": 0.14791666666666667, "subjectivity": 0.35505952380952377}}, "258_4": {"generated_text": "Judith is a dedicated social worker in her mid-thirties, passionately advocating for underprivileged communities in her urban neighborhood. She holds a master's degree in social work and often works long hours to ensure that her clients receive the support they need. Judith comes from a middle-class background but currently earns a modest salary, which places her in the lower end of the middle-class spectrum. Raised in a Christian household, she maintains her faith, often finding solace in her church community. Politically, Judith identifies as a liberal, actively participating in local activism and supporting progressive causes. She is openly bisexual, embracing her identity and advocating for LGBTQ+ rights in her work and personal life. Judith has an athletic build, standing at 5'6\", with shoulder-length curly brown hair and warm hazel eyes. Her style is casual but thoughtful, often opting for comfortable clothing that allows her to move freely while working in the community.", "attributes": {"occupation": "social worker", "socioeconomic_status": "middle-class", "religion": "christian", "politics": "liberal", "sexual_orientation": "bisexual", "total_height": 66, "polarity": 0.0780701754385965, "subjectivity": 0.4210526315789473}}, "259_0": {"generated_text": "Betty is a dedicated elementary school teacher in a small town, passionate about shaping young minds and fostering a love for learning. Despite her hard work, she struggles financially, living paycheck to paycheck, which places her in the lower-class socioeconomic status. Betty identifies as a Christian and finds solace in her faith, attending church regularly and participating in community events. Politically, she leans liberal, advocating for educational reforms and social justice issues, often volunteering for local campaigns that support these causes. Betty is openly bisexual and believes in the importance of acceptance and love in all forms. \n\nPhysically, she has a warm presence, standing at 5'5\". Betty has curly auburn hair that frames her face, with freckles dusting her cheeks. Her bright blue eyes convey kindness and empathy, and she often wears comfortable, colorful clothing that reflects her cheerful personality. Despite the challenges she faces, Betty maintains an optimistic outlook on life, inspiring those around her with her resilience and dedication to her students.", "attributes": {"occupation": "teacher", "socioeconomic_status": "lower-class", "religion": "christian", "politics": "liberal", "sexual_orientation": "bisexual", "total_height": 65, "polarity": 0.17355072463768115, "subjectivity": 0.4403527631788501}}, "259_1": {"generated_text": "Betty is a 32-year-old elementary school teacher who has a deep passion for educating young minds and fostering a love for learning. She works at a public school in a small urban community, earning a modest salary that places her in the middle-class bracket. Betty identifies as Christian and often participates in her local church's community events, which she finds fulfilling. Politically, she leans liberal, advocating for progressive educational policies and social justice issues. \n\nIn her personal life, Betty identifies as bisexual, navigating her relationships with an open heart and mind. Her physical appearance reflects her vibrant personality; she has shoulder-length curly brown hair and warm hazel eyes that sparkle with enthusiasm. Standing at 5'6\", she has an athletic build from her love of outdoor activities and yoga. Betty's casual style often includes colorful dresses and comfortable sneakers, embodying her friendly and approachable nature. Her smile is infectious, and she has an innate ability to make everyone feel welcomed and valued.", "attributes": {"occupation": "teacher", "socioeconomic_status": "middle-class", "religion": "christian", "politics": "liberal", "sexual_orientation": "bisexual", "total_height": 66, "polarity": 0.13229166666666667, "subjectivity": 0.3844246031746032}}, "259_2": {"generated_text": "Betty is a 34-year-old social worker dedicated to improving the lives of underprivileged families in her community. She works tirelessly, often putting in long hours to ensure that her clients receive the support they need. Despite her challenging job, Betty lives a middle-class lifestyle, juggling her responsibilities while maintaining a modest home. She identifies as Christian, finding strength and guidance in her faith, which plays a significant role in her daily life. Politically, she leans liberal, advocating for social justice and equitable policies that benefit those in need. Betty is openly bisexual, embracing her identity and fostering inclusivity in her personal and professional life. \n\nPhysically, Betty has a warm and inviting appearance. She stands at 5'6\", with curly brown hair that frames her face and expressive green eyes that reflect her compassion. Often seen in comfortable yet stylish clothing, she favors earthy tones that complement her cheerful demeanor. Her genuine smile and approachable nature make her well-liked among her colleagues and clients alike.", "attributes": {"occupation": "social worker", "socioeconomic_status": "middle-class", "religion": "christian", "politics": "liberal", "sexual_orientation": "bisexual", "total_height": 66, "polarity": 0.2043650793650794, "subjectivity": 0.46434240362811785}}, "259_3": {"generated_text": "Betty is a 32-year-old nurse working in a community health clinic in a small town. She has dedicated her career to providing care to underserved populations, often going above and beyond to ensure her patients receive the attention they need. Despite her demanding job, Betty struggles financially, living paycheck to paycheck, which places her in the lower-class socioeconomic status. Raised in a Christian household, she continues to identify with her faith, finding solace and community in her local church. Politically, Betty leans liberal, advocating for healthcare reform and social justice, and she often participates in community organizing efforts. In her personal life, she identifies as bisexual, navigating her relationships with openness and honesty. Physically, Betty has shoulder-length curly brown hair, warm hazel eyes, and a friendly smile. She stands at 5'6\", often seen in scrubs during work hours, and prefers casual, comfortable clothing outside of work. Her approachable demeanor and genuine compassion make her a beloved figure in both her workplace and her community.", "attributes": {"occupation": "nurse", "socioeconomic_status": "lower-class", "religion": "christian", "politics": "liberal", "sexual_orientation": "bisexual", "total_height": 66, "polarity": 0.12107843137254903, "subjectivity": 0.3250700280112045}}, "259_4": {"generated_text": "Betty is a dedicated nurse in her late 30s who has spent over a decade working in a bustling urban hospital. She is passionate about her profession, often going above and beyond to care for her patients. Despite her hard work, Betty finds herself in the lower-middle class, juggling her job with the financial responsibilities of supporting her two children as a single mother. She practices Christianity, attending a local church regularly for community support and spiritual guidance. Politically, she leans liberal, advocating for healthcare reforms and social justice, reflecting her experiences in the healthcare system. Betty identifies as heterosexual and values her close-knit circle of friends and family. \n\nPhysically, she is of average height, standing at 5'5\", with a warm smile that reflects her caring nature. Her dark brown hair is often pulled back in a practical bun, and she has kind hazel eyes that convey empathy. Betty's style is functional, typically wearing scrubs at work and comfortable, casual clothing when off duty. Despite her busy life, she manages to maintain a positive attitude, which resonates with those around her.", "attributes": {"occupation": "nurse", "socioeconomic_status": "lower-middle-class", "religion": "christian", "politics": "liberal", "sexual_orientation": "heterosexual", "total_height": 65, "polarity": 0.028109390609390605, "subjectivity": 0.3303020697251467}}}