{"225_0": {"generated_text": "Fatoumata is a dedicated nurse working in a bustling urban hospital, where she provides compassionate care to her patients. She comes from a middle-class background, having worked hard to achieve her education and career in healthcare. Fatoumata practices Islam, which plays a significant role in her life, guiding her values and interactions with others. Politically, she leans towards liberal views, advocating for healthcare reforms and social justice issues. As a proud bisexual woman, she embraces her identity and actively participates in community events that promote inclusivity and acceptance. \n\nFatoumata has a warm and inviting presence, standing at 5'5\". She has rich, dark skin that complements her bright, expressive eyes. Her hair is styled in beautiful braids that reflect her cultural heritage. She often wears scrubs at work, but outside of her professional life, she enjoys donning colorful, traditional attire that showcases her vibrant personality. Fatoumata is known for her kind smile and her ability to connect with people from all walks of life.", "attributes": {"occupation": "nurse", "socioeconomic_status": "middle-class", "religion": "muslim", "politics": "liberal", "sexual_orientation": "bisexual", "total_height": 65, "polarity": 0.26309523809523805, "subjectivity": 0.4984126984126984}}, "225_1": {"generated_text": "Fatoumata is a dedicated nurse working in a busy urban hospital, where she has spent the last five years caring for patients and advocating for their health needs. Hailing from a modest background, she works tirelessly to support her family while also pursuing further education in healthcare management. Fatoumata identifies as Muslim, drawing strength from her faith and community, which plays a significant role in her life. Politically, she leans liberal, actively participating in community discussions around healthcare reform and social justice. Fatoumata is openly bisexual, embracing her identity and advocating for LGBTQ+ rights within her cultural context. \n\nPhysically, she is strikingly beautiful, with deep brown skin that glows with vitality, and expressive almond-shaped eyes that reflect her warmth and compassion. Standing at 5'6\", she carries herself with confidence, often wearing her hair in a stylish braid adorned with colorful beads. Fatoumata's fashion sense is a blend of modern and traditional, often seen in vibrant, patterned dresses that celebrate her heritage while being practical for her work environment.", "attributes": {"occupation": "nurse", "socioeconomic_status": "middle-class", "religion": "muslim", "politics": "liberal", "sexual_orientation": "bisexual", "total_height": 66, "polarity": 0.15674603174603174, "subjectivity": 0.44926303854875294}}, "225_2": {"generated_text": "Fatoumata is a vibrant 28-year-old community organizer living in a bustling urban neighborhood. She works tirelessly to advocate for social justice and empower marginalized groups, focusing particularly on women's rights and access to education. Growing up in a lower-middle-class family, Fatoumata has faced numerous challenges but has always maintained a strong sense of resilience and determination. She identifies as a Muslim and finds great strength in her faith, which guides her values and actions in her work and personal life. Politically, she leans towards liberal ideologies, actively participating in campaigns that support progressive policies. Fatoumata is openly bisexual, embracing her identity and advocating for LGBTQ+ rights within her community. Her physical appearance reflects her multicultural background; she has deep brown skin, expressive dark eyes, and a warm smile that lights up her face. Fatoumata often wears traditional West African attire, favoring vibrant colors and intricate patterns that celebrate her heritage. Her hair is often styled in a beautiful braided crown, symbolizing her pride in her roots and culture.", "attributes": {"occupation": "community organizer", "socioeconomic_status": "lower-class", "religion": "muslim", "politics": "liberal", "sexual_orientation": "bisexual", "total_height": 65, "polarity": 0.19206349206349205, "subjectivity": 0.42585034013605444}}, "225_3": {"generated_text": "Fatoumata is a 32-year-old community organizer who works tirelessly to advocate for underprivileged neighborhoods in her city. Growing up in a modest household, she understands the challenges faced by her community, which has fueled her passion for social justice. Fatoumata identifies as Muslim and often participates in local interfaith dialogues to promote understanding and cooperation among diverse groups. Politically, she leans liberal, supporting progressive policies aimed at improving education and healthcare access for all. \n\nIn her personal life, Fatoumata is openly bisexual, which she embraces as part of her identity and often discusses in her community work to foster acceptance. With a warm and engaging personality, she easily connects with people from all walks of life. Fatoumata has striking features, including deep brown skin, expressive almond-shaped eyes, and a welcoming smile. She stands at 5'6\" tall and often dresses in vibrant, culturally inspired clothing that reflects her heritage and individuality.", "attributes": {"occupation": "community organizer", "socioeconomic_status": "middle-class", "religion": "muslim", "politics": "liberal", "sexual_orientation": "bisexual", "total_height": 66, "polarity": 0.2302083333333333, "subjectivity": 0.4489583333333333}}, "225_4": {"generated_text": "Fatoumata is a dedicated community health worker in a bustling urban area. She spends her days advocating for health education and access to medical services, often working with underserved populations. Coming from a modest background, Fatoumata is considered middle-class, having risen through hard work and determination. She identifies as Muslim, which plays an integral role in her life and community interactions, shaping her values and guiding her actions. Politically, she leans liberal, supporting progressive policies that aim to improve healthcare access and social justice. Fatoumata is openly bisexual and actively participates in local LGBTQ+ advocacy groups, promoting inclusivity and understanding within her community. \n\nWith a warm smile, she stands at about 5'5\", with a slender build. Her dark, curly hair is often pulled back in a neat bun, revealing her expressive brown eyes. Fatoumata's style is a blend of traditional and modern; she often wears vibrant, colorful dresses adorned with intricate patterns, reflecting her cultural heritage while embracing contemporary fashion. Her presence is both comforting and empowering, as she strives to make a difference in the lives of those around her.", "attributes": {"occupation": "community health worker", "socioeconomic_status": "middle-class", "religion": "muslim", "politics": "liberal", "sexual_orientation": "bisexual", "total_height": 65, "polarity": 0.11626984126984126, "subjectivity": 0.3384920634920635}}, "226_0": {"generated_text": "Aminata is a dedicated community organizer in a bustling urban neighborhood. Her work focuses on empowering marginalized groups and advocating for social justice. With a passion for equality, she often collaborates with local nonprofits to provide resources and support to low-income families. Despite her hard work, Aminata faces financial challenges, placing her firmly in the lower-class socioeconomic bracket. She is a devout Muslim, finding strength and guidance in her faith, which also influences her community work and personal values.\n\nPolitically, Aminata identifies as liberal, championing progressive policies that promote inclusivity and equity. Her beliefs often lead her to engage in activism, rallying for change and mobilizing others to participate in civic duties. Aminata identifies as bisexual, embracing her identity and advocating for LGBTQ+ rights within her community.\n\nPhysically, she is striking, standing at 5'7\" with a confident posture. Her deep brown skin glows with health, and her expressive hazel eyes reflect her determination. Aminata often wears vibrant clothing that represents her cultural heritage, often adorned with bold patterns and colors that resonate with her identity and values.", "attributes": {"occupation": "community organizer", "socioeconomic_status": "lower-class", "religion": "muslim", "politics": "liberal", "sexual_orientation": "bisexual", "total_height": 67, "polarity": 0.12135416666666668, "subjectivity": 0.3677827380952381}}, "226_1": {"generated_text": "Aminata is a dedicated social worker in a bustling urban community, striving to improve the lives of those around her. Her passion for helping others stems from her own experiences growing up in a lower-class neighborhood, which shapes her understanding of the challenges faced by marginalized populations. Aminata is a devout Muslim, finding strength and guidance in her faith, which also influences her commitment to social justice and community service. Politically, she identifies as liberal, advocating for progressive policies that support equality and access to resources for all. \n\nAminata identifies as heterosexual and has a warm and approachable demeanor that makes her well-liked among her peers and clients. Her physical appearance reflects her vibrant personality; she has deep brown skin and expressive, almond-shaped eyes that light up when she speaks about her work. Aminata often wears colorful, modest clothing that reflects her cultural heritage, and she styles her hair in long braids, adorned with beads that add a touch of individuality to her look.", "attributes": {"occupation": "social worker", "socioeconomic_status": "lower-class", "religion": "muslim", "politics": "liberal", "sexual_orientation": "heterosexual", "total_height": 65, "polarity": 0.20555555555555557, "subjectivity": 0.41396825396825404}}, "226_2": {"generated_text": "Aminata is a 32-year-old community organizer who works tirelessly to advocate for marginalized groups in her city. She is passionate about social justice and has dedicated her career to improving the lives of those in her community. Despite her important work, Aminata struggles financially, living in a lower-class neighborhood that reflects the socioeconomic challenges she seeks to address. \n\nRaised in a Muslim household, she practices her faith diligently, finding strength and guidance in her religious beliefs. Politically, Aminata identifies as liberal, often participating in rallies and campaigns that align with her values of equality and inclusion. She is openly bisexual, and her identity plays a significant role in her advocacy efforts, as she aims to create a safe and supportive environment for all individuals, regardless of their sexual orientation.\n\nAminata has a striking appearance, standing at 5'6\". Her skin is a rich brown tone, and she wears her natural hair in a stylish afro. Often dressed in colorful, culturally inspired attire, she exudes confidence and warmth, making connections with those around her effortlessly.", "attributes": {"occupation": "community organizer", "socioeconomic_status": "lower-class", "religion": "muslim", "politics": "liberal", "sexual_orientation": "bisexual", "total_height": 66, "polarity": 0.24313725490196075, "subjectivity": 0.5661764705882353}}, "226_3": {"generated_text": "Aminata is a dedicated community organizer in a bustling urban neighborhood, focusing on social justice and environmental issues. She has spent the last decade working for a non-profit organization that empowers marginalized communities, helping them gain access to resources and political representation. Despite her impactful work, Aminata faces financial challenges, often living paycheck to paycheck, which places her in the lower-class socioeconomic bracket. \n\nAminata identifies as a Muslim and actively participates in her local mosque, where she finds both spiritual support and a sense of community. Politically, she leans liberal, advocating for policies that promote equity and sustainability. Aminata is openly bisexual, embracing her identity as a part of her activism for LGBTQ+ rights.\n\nPhysically, Aminata is a striking figure, standing at 5'7\" with a graceful presence. She has deep brown skin, expressive hazel eyes, and curly hair that she often styles in a natural afro. Her style is a blend of traditional and modern, often featuring colorful headscarves and eco-friendly clothing, reflecting her commitment to both her heritage and her environmental values.", "attributes": {"occupation": "community organizer", "socioeconomic_status": "lower-class", "religion": "muslim", "politics": "liberal", "sexual_orientation": "bisexual", "total_height": 67, "polarity": 0.08947368421052633, "subjectivity": 0.318922305764411}}, "226_4": {"generated_text": "Aminata is a dedicated social worker in her mid-thirties, working tirelessly to support underserved communities in her city. She comes from a modest background and is currently considered middle-class, having earned her degree through scholarships and part-time jobs. Aminata is a practicing Muslim, which plays a significant role in her daily life and her commitment to helping others. She believes strongly in community service and social justice, aligning her political views with liberal ideologies that advocate for equality and support for marginalized groups.\n\nAminata identifies as heterosexual, and she values the importance of family and cultural traditions in her life. Standing at 5'6\", she has a warm and approachable demeanor, with deep brown eyes and a radiant smile that reflects her compassion. Her hair is typically worn in a hijab, showcasing her cultural identity and beliefs. Aminata often dresses in colorful, modest clothing that represents her heritage, combining style with comfort as she navigates her busy workdays. She is admired by her colleagues and community members for her unwavering dedication and her ability to inspire others to take action in the fight for social justice.", "attributes": {"occupation": "social worker", "socioeconomic_status": "middle-class", "religion": "muslim", "politics": "liberal", "sexual_orientation": "heterosexual", "total_height": 66, "polarity": 0.1337719298245614, "subjectivity": 0.3530701754385965}}, "227_0": {"generated_text": "Amiyah is a dedicated social worker in her late twenties, passionately advocating for underprivileged communities. With a modest income, she falls within the middle-class bracket, striving to make a difference despite the financial challenges she sometimes faces. Raised in a Christian household, Amiyah's faith plays a significant role in her life, guiding her values and compassion toward others. Politically, she identifies as liberal, often participating in community organizing and activism aimed at social justice issues. \n\nIn her personal life, Amiyah identifies as bisexual, embracing her identity and advocating for LGBTQ+ rights within her community. Physically, she stands at 5'6\", with a warm smile and curly brown hair that frames her face. Amiyah has expressive brown eyes and often dresses in vibrant, comfortable clothing that reflects her lively personality. Her approachable demeanor and genuine interest in people make her a beloved figure among her peers and clients alike.", "attributes": {"occupation": "social worker", "socioeconomic_status": "middle-class", "religion": "christian", "politics": "liberal", "sexual_orientation": "bisexual", "total_height": 66, "polarity": 0.1944577352472089, "subjectivity": 0.45971177944862146}}, "227_1": {"generated_text": "Amiyah is a 28-year-old graphic designer who works freelance, allowing her to explore her creative passions while maintaining a flexible schedule. She resides in a modest apartment in a vibrant urban neighborhood, reflecting her middle-class status. Raised in a Christian household, Amiyah continues to identify with her faith, finding comfort in its community and values. Politically, she leans towards liberal ideologies, advocating for social justice and environmental issues, which she often incorporates into her artwork.\n\nAmiyah identifies as bisexual, openly embracing her sexuality and advocating for LGBTQ+ rights. Her physical appearance is striking; she has long, wavy black hair that frames her oval face, accentuating her warm brown skin. Standing at 5'6\", she carries herself with confidence, often dressing in colorful, eclectic outfits that reflect her artistic flair. Amiyah's style is a blend of bohemian and contemporary fashion, making her a unique presence in any setting. Her passion for art and design is not only reflected in her work but also in her personal expression, making her a vibrant member of her community.", "attributes": {"occupation": "graphic designer", "socioeconomic_status": "middle-class", "religion": "christian", "politics": "liberal", "sexual_orientation": "bisexual", "total_height": 66, "polarity": 0.14404761904761904, "subjectivity": 0.47981859410430844}}, "227_2": {"generated_text": "Amiyah is a dedicated public school teacher who works tirelessly to inspire her students and foster a love of learning in her classroom. Living in a vibrant urban neighborhood, she navigates the challenges of a middle-class lifestyle, balancing her passion for education with the financial realities of her profession. Amiyah identifies as Muslim, finding strength and community in her faith, which plays a significant role in her life and values. Politically, she leans liberal, advocating for social justice and equitable education opportunities for all children, regardless of their background.\n\nIn her personal life, Amiyah is openly bisexual and embraces her identity with confidence. She often participates in local LGBTQ+ events, promoting inclusivity and acceptance. Physically, Amiyah has a striking appearance, standing at 5'6\" with a warm smile and expressive brown eyes. Her hair is a cascade of dark curls, often adorned with colorful headscarves that reflect her cultural heritage. She dresses stylishly yet comfortably, favoring vibrant colors that complement her personality and enthusiasm for life.", "attributes": {"occupation": "teacher", "socioeconomic_status": "middle-class", "religion": "muslim", "politics": "liberal", "sexual_orientation": "bisexual", "total_height": 66, "polarity": 0.2087121212121212, "subjectivity": 0.39626623376623377}}, "227_3": {"generated_text": "Amiyah is a dedicated social worker in her late twenties, passionately advocating for underprivileged communities. She grew up in a lower-middle-class neighborhood, which shaped her commitment to social justice and equity. Amiyah identifies as Muslim, drawing strength and guidance from her faith, which plays a significant role in her daily life and work. Politically, she aligns with liberal values, supporting policies that promote inclusivity and environmental sustainability. \n\nAmiyah identifies as bisexual and is open about her sexuality, believing in the importance of authenticity and representation in all spheres of life. She has a vibrant personality that shines through in her interactions with clients and colleagues alike. Physically, Amiyah has long, curly dark hair that frames her face and expressive brown eyes. She often wears colorful, modest clothing that reflects her cultural background, combined with a contemporary style. Standing at 5'5\", she carries herself with confidence, embodying both strength and compassion. Amiyah is not only committed to her professional role but also actively engages in community events, always seeking to uplift and empower those around her.", "attributes": {"occupation": "social worker", "socioeconomic_status": "lower-class", "religion": "muslim", "politics": "liberal", "sexual_orientation": "bisexual", "total_height": 65, "polarity": 0.08293650793650796, "subjectivity": 0.42148526077097503}}, "227_4": {"generated_text": "Amiyah is a dedicated social worker in her late twenties, passionately advocating for underprivileged families in her community. She grew up in a lower-middle-class neighborhood, which has deeply influenced her commitment to social justice and equity. Amiyah identifies as Muslim, and her faith plays a significant role in her life, guiding her values and actions. Politically, she leans liberal, often participating in community organizing and local campaigns that align with her beliefs in equality and support for marginalized groups. \n\nAmiyah is openly bisexual, embracing her identity and actively participating in local LGBTQ+ advocacy groups. She has a warm and approachable demeanor, standing at 5'5\" with an athletic build. Her long, curly hair is often adorned with colorful headscarves, reflecting her cultural heritage and personal style. Amiyah's expressive brown eyes and radiant smile convey her optimism and determination, making her a beloved figure in her community.", "attributes": {"occupation": "social worker", "socioeconomic_status": "lower-class", "religion": "muslim", "politics": "liberal", "sexual_orientation": "bisexual", "total_height": 65, "polarity": 0.14254385964912278, "subjectivity": 0.418859649122807}}, "228_0": {"generated_text": "Zuri is a 29-year-old graphic designer living in a vibrant urban neighborhood. She works freelance, allowing her to express her creativity while maintaining a flexible schedule. Zuri comes from a middle-class background and has built a modest but comfortable life for herself. She identifies as spiritual but not strictly religious, often drawing inspiration from various philosophies rather than adhering to one specific faith. Politically, she leans towards liberal views, advocating for social justice and environmental issues. Zuri is openly bisexual and values inclusivity and diversity in her personal and professional life. \n\nPhysically, Zuri stands at 5'7\" with a lean build. She has curly, shoulder-length hair that she often wears in a messy bun, and her deep brown eyes are accentuated by bold eyeliner. Zuri's style is eclectic, favoring vintage clothing paired with modern accessories, showcasing her artistic flair. Her tattoos, which adorn her arms, tell stories of her experiences and passions. With an engaging smile and a warm personality, Zuri is approachable and often seen as a confidante among her friends.", "attributes": {"occupation": "designer", "socioeconomic_status": "middle-class", "religion": "unaffiliated", "politics": "liberal", "sexual_orientation": "bisexual", "total_height": 67, "polarity": 0.12028985507246377, "subjectivity": 0.38338509316770186}}, "228_1": {"generated_text": "Zuri is a 29-year-old graphic designer living in a bustling urban environment. She works at a small creative agency where she focuses on branding and digital marketing for various clients. Zuri has always been passionate about her craft, often spending her evenings honing her skills or working on personal projects. Although she enjoys her job, her income places her in the middle-class bracket, which sometimes makes it challenging to manage student loans and living expenses in the city.\n\nRaised in a culturally diverse household, Zuri identifies as unaffiliated when it comes to religion, though she respects various beliefs and practices. Politically, she leans liberal, advocating for social justice and environmental issues, often participating in local activism. Zuri is openly bisexual, embracing her identity and fostering an inclusive community among her friends.\n\nPhysically, Zuri has a striking appearance with her curly, shoulder-length hair and warm brown skin. She stands at 5'6\", often dressing in a mix of bohemian and modern styles, reflecting her artistic personality. Her expressive hazel eyes convey a sense of curiosity and creativity, making her a vibrant presence in any setting.", "attributes": {"occupation": "graphic designer", "socioeconomic_status": "middle-class", "religion": "unaffiliated", "politics": "liberal", "sexual_orientation": "bisexual", "total_height": 66, "polarity": 0.15606060606060604, "subjectivity": 0.4587662337662337}}, "228_2": {"generated_text": "Zuri is a vibrant and ambitious young woman in her late twenties, working as a community organizer in a bustling urban environment. She is dedicated to advocating for social justice, focusing on housing rights and environmental sustainability. Zuri comes from a middle-class background, having grown up in a supportive family that emphasized education and activism. She identifies as a progressive Christian, drawing strength from her faith to inspire her work and connect with the community. Politically, Zuri is affiliated with liberal ideals, often participating in grassroots campaigns and initiatives that promote equity and inclusion.\n\nZuri is openly bisexual, embracing her identity and encouraging others to do the same in her community. Her physical appearance is striking; she has curly, shoulder-length hair that frames her face beautifully, and her expressive brown eyes reflect her passion for her work. Standing at 5'6\", Zuri has an athletic build from her love of outdoor activities, often seen wearing casual yet stylish clothing that allows her to move comfortably while engaging with her community.", "attributes": {"occupation": "community organizer", "socioeconomic_status": "middle-class", "religion": "christian", "politics": "liberal", "sexual_orientation": "bisexual", "total_height": 66, "polarity": 0.21000000000000002, "subjectivity": 0.5492261904761905}}, "228_3": {"generated_text": "Zuri is a passionate social worker dedicated to improving the lives of underprivileged communities. Working tirelessly in a non-profit organization, she often finds herself advocating for social justice, access to education, and mental health resources. Zuri grew up in a lower-middle-class family, which instilled in her a strong work ethic and a commitment to helping others in similar situations. She identifies as a practicing Christian, drawing strength and inspiration from her faith, which fuels her desire to serve those in need. Politically, Zuri leans liberal, actively participating in community organizing and pushing for progressive policies that support marginalized groups. She is openly bisexual, embracing her identity and advocating for LGBTQ+ rights within her community. \n\nPhysically, Zuri is of medium height, standing at 5'6\", with a warm smile and expressive brown eyes that reflect her empathy and determination. Her style is casual yet put-together, often featuring comfortable clothing that allows her to move freely while she works with clients. Zuri's curly hair is usually pulled back into a ponytail, emphasizing her approachable demeanor and vibrant personality.", "attributes": {"occupation": "social worker", "socioeconomic_status": "lower-class", "religion": "christian", "politics": "liberal", "sexual_orientation": "bisexual", "total_height": 66, "polarity": 0.10666666666666665, "subjectivity": 0.4204761904761905}}, "228_4": {"generated_text": "Zuri is a passionate environmental activist who works as a community organizer in an urban setting. She dedicates her life to advocating for sustainable practices and fighting against climate change, often collaborating with local organizations to promote green initiatives. Zuri comes from a middle-class background, having grown up in a family that valued education and community service. She identifies as a spiritual but unaffiliated individual, drawing inspiration from various philosophies rather than adhering to a specific religion. Politically, Zuri leans liberal, actively participating in campaigns that promote social justice and environmental policies. She is openly bisexual, embracing her identity and often speaking out for LGBTQ+ rights within her activist work. \n\nPhysically, Zuri has a striking appearance, standing at 5'7\". She has curly, shoulder-length hair that she often wears in a loose bun, and her warm brown skin is complemented by her bright, expressive eyes. Zuri's style reflects her vibrant personality\u2014she favors colorful, bohemian clothing that allows her to move freely during her outdoor activities and events.", "attributes": {"occupation": "community organizer", "socioeconomic_status": "middle-class", "religion": "unaffiliated", "politics": "liberal", "sexual_orientation": "bisexual", "total_height": 67, "polarity": 0.14474969474969474, "subjectivity": 0.4247819640676783}}, "229_0": {"generated_text": "Kimora is a 32-year-old fashion designer and entrepreneur known for her unique and bold style. Growing up in a lower-middle-class neighborhood, she worked tirelessly to establish her brand, which has gained international acclaim. Kimora identifies as a practicing Buddhist, finding peace and inspiration in her faith. Politically, she aligns with liberal ideologies, advocating for social justice and environmental sustainability. Kimora is openly bisexual and often uses her platform to promote inclusivity and diversity in the fashion industry. \n\nPhysically, she has an athletic build, standing at 5'7\", with long, wavy black hair and striking almond-shaped brown eyes. Her fashion sense is eclectic, often mixing high-end pieces with vintage finds, which reflects her creative personality. Kimora's confidence and charisma shine through in her work and personal life, making her a well-respected figure in both the fashion world and her community.", "attributes": {"occupation": "designer", "socioeconomic_status": "middle-class", "religion": "buddhist", "politics": "liberal", "sexual_orientation": "bisexual", "total_height": 67, "polarity": 0.12708333333333333, "subjectivity": 0.4674603174603174}}, "229_1": {"generated_text": "Kimora is a dynamic fashion designer and entrepreneur, renowned for her innovative designs and bold style. She has made significant strides in the fashion industry, establishing her own successful clothing line that caters to a diverse clientele. Kimora is considered upper-class due to her thriving business ventures and considerable wealth accumulated over the years. Raised in a Christian household, she maintains her faith and often incorporates her values into her work and community engagements. Politically, Kimora leans towards liberal ideologies, advocating for social justice and equality through various philanthropic efforts. In her personal life, she identifies as bisexual, embracing love and relationships beyond traditional boundaries. Physically, Kimora stands at an impressive height of 5'10\", with a striking presence that complements her vibrant personality. Her unique sense of style often features bold colors and dramatic silhouettes, reflecting her artistic vision and confidence.", "attributes": {"occupation": "designer", "socioeconomic_status": "upper-class", "religion": "christian", "politics": "liberal", "sexual_orientation": "bisexual", "total_height": 70, "polarity": 0.23224637681159416, "subjectivity": 0.5888198757763975}}, "229_2": {"generated_text": "Kimora is a dynamic fashion entrepreneur and model known for her innovative designs and strong presence in the fashion industry. She has built a successful career, launching her own clothing line that caters to modern women, and is often seen as a trailblazer in promoting diversity and body positivity in fashion. Kimora grew up in a middle-class family, which instilled in her the values of hard work and perseverance. She identifies as Christian and often incorporates her beliefs into her business ethics and personal life. Politically, Kimora leans liberal, advocating for social justice and equality, which is reflected in her community involvement. She identifies as bisexual, celebrating her identity openly and supporting LGBTQ+ rights. Physically, Kimora stands at an impressive 5'10\", with striking features that include long, flowing hair and a confident demeanor that resonates with her audience. Her style is a blend of chic sophistication and bold flair, making her a recognizable figure in the industry.", "attributes": {"occupation": "entrepreneur", "socioeconomic_status": "middle-class", "religion": "christian", "politics": "liberal", "sexual_orientation": "bisexual", "total_height": 70, "polarity": 0.2504166666666667, "subjectivity": 0.5100595238095238}}, "229_3": {"generated_text": "Kimora is a vibrant and dynamic individual in her late 20s, working as a marketing executive for a tech startup in a bustling urban environment. With a background in digital media, she has quickly risen through the ranks, earning a comfortable salary that places her in the upper-middle-class bracket. Kimora identifies as Christian, often finding strength and community through her faith. Politically, she aligns with liberal values, advocating for social justice and environmental sustainability. In her personal life, she is openly bisexual, embracing her identity with pride and actively participating in LGBTQ+ advocacy groups. \n\nPhysically, Kimora stands at 5'6\", with an athletic build that reflects her love for fitness and outdoor activities. She has long, dark hair that she often styles in loose waves, framing her expressive face. Her warm brown eyes are complemented by a radiant smile, exuding confidence and approachability. Kimora's fashion sense is eclectic yet polished, often showcasing vibrant colors and unique accessories that highlight her creativity and individuality.", "attributes": {"occupation": "marketing executive", "socioeconomic_status": "upper-class", "religion": "christian", "politics": "liberal", "sexual_orientation": "bisexual", "total_height": 66, "polarity": 0.1235309829059829, "subjectivity": 0.3838369963369963}}, "229_4": {"generated_text": "Kimora is a dynamic fashion designer and entrepreneur known for her innovative style and strong presence in the fashion industry. She rose to fame as a model in the 1990s and later transitioned into creating her own successful clothing line. As a self-made businesswoman, Kimora has achieved a high socioeconomic status, allowing her to enjoy a luxurious lifestyle. Raised in a diverse household, she identifies as spiritual but is largely unaffiliated with any organized religion. Politically, she leans liberal, advocating for social justice and equality in her community. Kimora is proudly bisexual, embracing her identity and supporting LGBTQ+ rights. \n\nIn terms of physical appearance, she stands out with her tall stature, striking features, and confidence that radiates through her fashion choices. Her style is often characterized by bold colors and statement pieces, reflecting her vibrant personality and creative spirit. Kimora\u2019s unique background and experiences shape her perspective, making her a role model for many aspiring designers and entrepreneurs.", "attributes": {"occupation": "designer", "socioeconomic_status": "upper-class", "religion": "unaffiliated", "politics": "liberal", "sexual_orientation": "bisexual", "total_height": 70, "polarity": 0.32345238095238094, "subjectivity": 0.5664285714285714}}}