{"220_0": {"generated_text": "Malachi is a passionate community organizer dedicated to social justice and environmental issues. He works for a nonprofit organization that focuses on sustainable practices and advocating for marginalized communities. Growing up in a working-class neighborhood, Malachi understands the struggles of lower socioeconomic status firsthand, which fuels his commitment to creating equitable solutions. He identifies as a secular humanist, valuing reason and compassion over traditional religious beliefs, but he respects all faiths. Politically, Malachi leans liberal, championing progressive causes and working to mobilize voters for local elections.\n\nIn his personal life, Malachi is openly bisexual, embracing his identity and advocating for LGBTQ+ rights within his community. He is known for his vibrant style, often sporting colorful graphic tees that promote various causes. Standing at 5'10\", he has an athletic build, with curly dark hair and expressive green eyes that convey his passion for his work. His warm smile and approachable demeanor make him a natural leader and a beloved figure among his peers.", "attributes": {"occupation": "community organizer", "socioeconomic_status": "lower-class", "religion": "unaffiliated", "politics": "liberal", "sexual_orientation": "bisexual", "total_height": 70, "polarity": 0.1368421052631579, "subjectivity": 0.4342105263157895}}, "220_1": {"generated_text": "Malachi is a 28-year-old social worker who dedicates his life to helping underprivileged communities in his city. He comes from a lower-middle-class background, having grown up in a neighborhood where resources were scarce. His work allows him to connect with people from various walks of life, and he often advocates for social justice and improved welfare programs. Malachi identifies as Christian, attending a local church that emphasizes community service and outreach. Politically, he leans towards liberal ideals, actively participating in local activism and campaigns that support progressive policies. \n\nIn his personal life, Malachi identifies as homosexual and is open about his orientation, often engaging in discussions about LGBTQ+ rights. His physical appearance is striking; he stands at 5'10\", with an athletic build from his love of outdoor activities. He has short, curly black hair and warm brown eyes that reflect his empathetic nature. Malachi often dresses casually, favoring comfortable jeans and graphic tees, but he also cleans up nicely for professional events, wearing fitted blazers that accentuate his physique.", "attributes": {"occupation": "social worker", "socioeconomic_status": "lower-middle-class", "religion": "christian", "politics": "liberal", "sexual_orientation": "homosexual", "total_height": 70, "polarity": 0.10757575757575757, "subjectivity": 0.41255411255411245}}, "220_2": {"generated_text": "Malachi is a 28-year-old community organizer working tirelessly to improve the lives of those in his neighborhood. He grew up in a working-class family and now identifies as lower-class, using his experiences to fuel his passion for social justice. Malachi practices a progressive form of Christianity, which influences his commitment to helping others and promoting equality. Politically, he aligns with liberal values, advocating for policies that support marginalized communities and fight against systemic injustice. \n\nHe is openly homosexual and embraces his identity, often participating in local pride events and advocating for LGBTQ+ rights. Malachi has a lean build, standing at 6'1\", with expressive brown eyes and curly black hair that he often wears in a short, neat style. His fashion sense reflects his personality\u2014he favors casual, comfortable clothing, often seen in fitted jeans and graphic tees that promote social causes he believes in. Malachi is known for his warm smile and approachable demeanor, making him a beloved figure in his community.", "attributes": {"occupation": "community organizer", "socioeconomic_status": "lower-class", "religion": "christian", "politics": "liberal", "sexual_orientation": "homosexual", "total_height": 73, "polarity": 0.15714285714285717, "subjectivity": 0.44523809523809516}}, "220_3": {"generated_text": "Malachi is a 28-year-old graphic designer living in a vibrant urban neighborhood. He works for a small creative agency, where he brings innovative ideas to life through digital art and branding. Despite his talent, Malachi\u2019s socioeconomic status is lower-class, as he often struggles to make ends meet in a city with a high cost of living. Raised in a Christian household, he still identifies with the faith, though he often questions traditional beliefs and practices. Politically, Malachi leans liberal, advocating for social justice and environmental causes, which he expresses through his art and community involvement.\n\nIn terms of personal life, Malachi identifies as homosexual and is actively engaged in the LGBTQ+ community, where he finds support and acceptance. He has a distinctive style, often sporting colorful hair and eclectic clothing that reflects his artistic personality. Standing at 5'10\", Malachi has an athletic build, with tattoos that showcase his love for art and self-expression. His vibrant personality shines through his expressive eyes and warm smile, making him a cherished friend among his peers.", "attributes": {"occupation": "graphic designer", "socioeconomic_status": "lower-class", "religion": "christian", "politics": "liberal", "sexual_orientation": "homosexual", "total_height": 70, "polarity": 0.18936507936507938, "subjectivity": 0.4534920634920634}}, "220_4": {"generated_text": "Malachi is a 28-year-old graphic designer living in a vibrant urban neighborhood. He works freelance, juggling multiple projects for various clients, which allows him the flexibility to express his creativity. However, this irregular income places him in the lower-class socioeconomic bracket, often living paycheck to paycheck. Malachi identifies as an agnostic, having grown up in a Christian household but becoming disillusioned with organized religion as he matured. Politically, he leans liberal, advocating for social justice and environmental issues, often participating in local activism.\n\nIn his personal life, Malachi is openly homosexual and finds joy in the LGBTQ+ community, which provides him with a strong support network. Physically, he stands at 5'9\" with a slender build. His style is eclectic, often wearing vintage clothing mixed with contemporary pieces, reflecting his artistic personality. He has short, curly dark hair and expressive green eyes that convey his passion for life and art. Malachi's personality is warm and inviting, making him approachable, while his vibrant tattoos, each with personal significance, tell the story of his journey and identity.", "attributes": {"occupation": "graphic designer", "socioeconomic_status": "lower-class", "religion": "agnostic", "politics": "liberal", "sexual_orientation": "homosexual", "total_height": 69, "polarity": 0.14400000000000002, "subjectivity": 0.35104761904761916}}, "221_0": {"generated_text": "Nasir is a 32-year-old software developer who works at a tech startup in a bustling urban area. He is passionate about coding and enjoys creating innovative applications that enhance people's lives. Nasir comes from a middle-class background, having grown up in a supportive family that valued education and hard work. He identifies as Muslim, practicing his faith with a balance of modernity and tradition, often participating in community events and volunteering. Politically, Nasir leans liberal, advocating for social justice and environmental sustainability. His sexual orientation is heterosexual, and he is currently in a committed relationship. \n\nPhysically, Nasir is of average height at 5'10\", with a lean build. He has short black hair, often neatly styled, and warm brown eyes that reflect his friendly demeanor. His fashion sense is casual yet professional, typically seen in well-fitted jeans and button-up shirts. Nasir\u2019s approachable nature makes him well-liked among his peers, and he often engages in discussions about technology and social issues, reflecting his diverse interests.", "attributes": {"occupation": "software developer", "socioeconomic_status": "middle-class", "religion": "muslim", "politics": "liberal", "sexual_orientation": "heterosexual", "total_height": 70, "polarity": 0.06929824561403508, "subjectivity": 0.4579573934837093}}, "221_1": {"generated_text": "Nasir is a 32-year-old software engineer living in a bustling urban area. He works for a tech startup, where he contributes to innovative projects that aim to improve user accessibility. Nasir comes from a middle-class background, having been raised by immigrant parents who instilled a strong work ethic in him. He identifies as Muslim, practicing his faith through daily prayers and participating in community events. Politically, Nasir leans liberal, advocating for social justice and environmental sustainability, and often engages in discussions about progressive policies with friends and colleagues. \n\nIn terms of his personal life, Nasir is openly bisexual, which he embraces with pride. He has a distinctive appearance, standing at 5'10\", with a lean build and warm brown skin. His dark, curly hair is often styled casually, and he frequently sports a well-groomed beard. Nasir enjoys expressing his individuality through his fashion choices, favoring comfortable yet stylish clothing that reflects his personality. His friendly demeanor and approachable nature make him well-liked among peers, as he values inclusivity and understanding in both his professional and personal relationships.", "attributes": {"occupation": "software engineer", "socioeconomic_status": "middle-class", "religion": "muslim", "politics": "liberal", "sexual_orientation": "bisexual", "total_height": 70, "polarity": 0.14068627450980392, "subjectivity": 0.4450980392156862}}, "221_2": {"generated_text": "Nasir is a 32-year-old graphic designer working for a small but innovative startup in a bustling urban area. He is passionate about his work, often staying late to perfect his designs and push creative boundaries. Despite his talent, he struggles financially, living paycheck to paycheck in a modest apartment, placing him in the lower-class socioeconomic bracket. Nasir is a devout Muslim, observing the practices of his faith with dedication. Politically, he leans liberal, advocating for social justice and environmental issues, often participating in community activism. Nasir identifies as heterosexual and values his relationships with friends and family deeply. \n\nPhysically, he stands at 5'10\", with a lean build and an expressive face that reflects his vibrant personality. His dark hair is often styled in a trendy manner, and he sports a well-groomed beard. Nasir has warm brown eyes and a contagious smile, which he uses to connect with others. His fashion sense is eclectic yet comfortable, often mixing streetwear with traditional elements that pay homage to his cultural heritage.", "attributes": {"occupation": "graphic designer", "socioeconomic_status": "lower-class", "religion": "muslim", "politics": "liberal", "sexual_orientation": "heterosexual", "total_height": 70, "polarity": 0.19772727272727272, "subjectivity": 0.5201298701298701}}, "221_3": {"generated_text": "Nasir is a 32-year-old graphic designer who thrives in the bustling creative industry of a major city. He has built a reputation for his unique style, which blends traditional motifs with modern aesthetics. Despite his talent, he navigates a lower-middle-class lifestyle, often juggling freelance projects to make ends meet. Nasir identifies as Muslim, finding solace and community in his faith, which influences his art and approach to life. Politically, he leans liberal, advocating for social justice and inclusivity, themes that are often reflected in his work. He is openly gay and proud of his identity, often using his platform to support LGBTQ+ rights. \n\nPhysically, Nasir is striking, standing at 5'10\" with a lean build. He has deep brown skin, framed by a stylish undercut that emphasizes his expressive features. His fashion sense is eclectic, favoring bright colors and bold patterns that mirror his artistic spirit. Nasir's warm brown eyes convey a sense of kindness and determination, drawing people to him. His presence is magnetic, as he effortlessly combines professionalism with a casual charm.", "attributes": {"occupation": "graphic designer", "socioeconomic_status": "lower-middle-class", "religion": "muslim", "politics": "liberal", "sexual_orientation": "homosexual", "total_height": 70, "polarity": 0.2827083333333333, "subjectivity": 0.6588095238095238}}, "221_4": {"generated_text": "Nasir is a 32-year-old urban planner working for a local government agency in a mid-sized city. He is passionate about sustainable development and community engagement, striving to create inclusive spaces for all residents. Nasir comes from a middle-class background, having been raised in a family that valued education and civic responsibility. His upbringing instilled in him a strong sense of social justice, which aligns with his liberal political views. He identifies as Muslim, attending mosque regularly and participating in community service initiatives that support marginalized groups.\n\nIn terms of his personal life, Nasir is openly bisexual, embracing his identity and advocating for LGBTQ+ rights within his community. He believes in fostering an environment where everyone can feel safe and accepted. Physically, Nasir has a lean build, standing at 5'10\". He has warm brown skin, dark curly hair that he often wears in a short style, and expressive brown eyes. His casual yet professional style typically includes well-fitted jeans and button-up shirts, which reflect his approachable personality.", "attributes": {"occupation": "urban planner", "socioeconomic_status": "middle-class", "religion": "muslim", "politics": "liberal", "sexual_orientation": "bisexual", "total_height": 70, "polarity": 0.0888888888888889, "subjectivity": 0.3909137159137159}}, "222_0": {"generated_text": "Mamdou is a dedicated community organizer working tirelessly to improve the lives of his neighbors in a bustling urban neighborhood. He has a passion for social justice and often collaborates with local nonprofits to address issues like housing insecurity and access to education. Mamdou comes from a lower-class background, which fuels his determination to uplift his community. He identifies as a Muslim, drawing strength and inspiration from his faith to navigate the challenges he faces in his work and personal life. Politically, Mamdou leans toward liberal ideologies, advocating for progressive policies that support marginalized groups. He is openly bisexual, which adds another layer to his advocacy, as he strives to promote inclusivity within his community. Physically, Mamdou is of average height, standing at 5'8\", with a lean build. He has warm brown skin, expressive dark eyes, and often sports a well-groomed beard. His style tends to be casual yet thoughtful, often wearing colorful shirts that reflect his vibrant personality. Mamdou\u2019s presence is both calming and inspiring, making him a beloved figure in the neighborhood.", "attributes": {"occupation": "community organizer", "socioeconomic_status": "lower-class", "religion": "muslim", "politics": "liberal", "sexual_orientation": "bisexual", "total_height": 68, "polarity": 0.15882352941176472, "subjectivity": 0.44761904761904764}}, "222_1": {"generated_text": "Mamdou is a dedicated social worker in his mid-thirties, striving to uplift the lives of underprivileged families in his community. He comes from a lower-class background, having faced significant hardships throughout his life, which fueled his passion for helping others. Mamdou practices Islam, finding strength and guidance in his faith. Politically, he leans liberal, advocating for social justice and policies that support marginalized groups. His sexual orientation is heterosexual, and he is open about his relationships, often sharing stories of his experiences with friends and family.\n\nPhysically, Mamdou stands at 5'9\" with a lean build. He has dark hair, often kept neatly trimmed, and warm brown eyes that reflect his compassion. His style is practical, usually wearing comfortable clothing suitable for his work, often opting for simple, modest attire that aligns with his cultural background. Mamdou\u2019s approachable demeanor and genuine smile make him well-liked in his community, where he is known not just for his professional efforts, but also for his willingness to lend a helping hand to anyone in need.", "attributes": {"occupation": "social worker", "socioeconomic_status": "lower-class", "religion": "muslim", "politics": "liberal", "sexual_orientation": "heterosexual", "total_height": 69, "polarity": 0.17175925925925928, "subjectivity": 0.41342592592592586}}, "222_2": {"generated_text": "Mamdou is a dedicated social worker in a bustling urban community, where he tirelessly advocates for the rights and needs of underprivileged families. Coming from a lower-class background himself, he understands the struggles faced by those he serves. Mamdou identifies as Muslim and finds strength in his faith, which guides his compassionate approach to helping others. Politically, he leans towards liberal views, believing in the importance of social justice and equality. Mamdou is openly bisexual, embracing his identity and fostering an inclusive environment within his community. \n\nPhysically, he is of average height, standing at 5'8\", with a warm smile and expressive brown eyes that reflect his kindness and empathy. His hair is dark and curly, often kept short for convenience. He dresses in practical clothing, usually favoring comfortable jeans and simple shirts, often adorned with a light jacket. Mamdou\u2019s approachable demeanor makes him well-liked among colleagues and clients alike, as he is always ready to lend a helping hand or listen to someone in need. His life is a testament to resilience, hope, and the power of community.", "attributes": {"occupation": "social worker", "socioeconomic_status": "lower-class", "religion": "muslim", "politics": "liberal", "sexual_orientation": "bisexual", "total_height": 68, "polarity": 0.13854166666666667, "subjectivity": 0.3837797619047619}}, "222_3": {"generated_text": "Mamdou is a 28-year-old social worker dedicated to improving the lives of underprivileged communities in his city. He grew up in a lower-class neighborhood, which has deeply influenced his commitment to social justice. Mamdou identifies as Muslim, and his faith plays a significant role in his daily life, guiding his values and actions. Politically, he leans towards liberal ideologies, advocating for policies that support equality and community welfare. He is openly bisexual, which has added layers to his understanding of identity and acceptance, both in his personal life and professional interactions.\n\nPhysically, Mamdou is of average height, standing at 5'8\". He has a lean build, with dark, curly hair that he keeps neatly trimmed. His warm brown eyes reflect kindness and empathy, and he often sports a light beard that complements his facial features. Mamdou's style is casual yet purposeful, often seen in comfortable clothing suitable for his active role in the community. His approachable demeanor makes him well-liked among both colleagues and clients, as he works tirelessly to bridge gaps in services and create a supportive environment for those in need.", "attributes": {"occupation": "social worker", "socioeconomic_status": "lower-class", "religion": "muslim", "politics": "liberal", "sexual_orientation": "bisexual", "total_height": 68, "polarity": 0.10291666666666668, "subjectivity": 0.433392857142857}}, "222_4": {"generated_text": "Mamdou is a dedicated social worker in a bustling urban community, focusing on helping underprivileged families access essential resources and support. He grew up in a lower-class neighborhood, which deeply influences his passion for social justice and advocacy. As a Muslim, Mamdou practices his faith with devotion, attending services regularly and participating in community outreach programs that align with his values. Politically, he identifies as liberal, advocating for policies that promote equality and social welfare. His sexual orientation is heterosexual, and he is in a committed relationship with his partner, who shares his values and aspirations.\n\nPhysically, Mamdou has an athletic build, standing at 5'10\". He has warm brown skin, closely cropped black hair, and a friendly smile that reflects his approachable nature. His attire often consists of casual, comfortable clothing suitable for his work environment, emphasizing practicality while maintaining a sense of personal style.", "attributes": {"occupation": "social worker", "socioeconomic_status": "lower-class", "religion": "muslim", "politics": "liberal", "sexual_orientation": "heterosexual", "total_height": 70, "polarity": 0.11990740740740741, "subjectivity": 0.3557285307285307}}, "223_0": {"generated_text": "Chance is a 28-year-old graphic designer living in a bustling urban neighborhood. He works for a small creative agency, where he specializes in branding and digital marketing. Despite his artistic talents, Chance's income places him in the lower-middle-class bracket, as his job often lacks stability and benefits. Raised in a modest household, he has always been aware of the financial struggles his family faced, which instilled a strong work ethic in him. Chance identifies as agnostic, often questioning the traditional beliefs he was raised with, and prefers to explore spirituality on his own terms.\n\nPolitically, he leans liberal, advocating for social justice and environmental issues, and actively participates in community initiatives. Chance is openly bisexual, comfortable with his identity, and seeks meaningful connections regardless of gender. With an eclectic style, he often sports brightly colored hair and expressive tattoos that reflect his personality. Standing at 5'10\", he has a slender build and a youthful appearance, often seen in casual, artsy clothing that showcases his creative side.", "attributes": {"occupation": "graphic designer", "socioeconomic_status": "lower-class", "religion": "agnostic", "politics": "liberal", "sexual_orientation": "bisexual", "total_height": 70, "polarity": 0.19393939393939394, "subjectivity": 0.5757575757575757}}, "223_1": {"generated_text": "Chance is a 32-year-old graphic designer living in a vibrant urban neighborhood. He works for a small design firm that specializes in eco-friendly branding, which aligns with his personal values. Financially, Chance is considered middle-class, though he often struggles to save due to the high cost of living in the city. He identifies as agnostic, appreciating the diverse beliefs around him but not adhering to any particular religion. Politically, he leans liberal, advocating for social justice and environmental issues, and he actively participates in community initiatives. Chance is openly bisexual and values authenticity in his relationships. \n\nPhysically, he has an artistic flair, sporting a slim build with a height of 5'10\". His style is casual yet unique, often featuring vintage band tees, skinny jeans, and colorful sneakers. He has short, tousled dark hair and expressive hazel eyes that reflect his creativity. His friendly demeanor and warm smile make him approachable, and he enjoys engaging in thoughtful conversations with friends and strangers alike.", "attributes": {"occupation": "graphic designer", "socioeconomic_status": "middle-class", "religion": "agnostic", "politics": "liberal", "sexual_orientation": "bisexual", "total_height": 70, "polarity": 0.11302469135802468, "subjectivity": 0.4391798941798942}}, "223_2": {"generated_text": "Chance is a 28-year-old graphic designer living in a bustling urban environment. He works freelance, allowing him flexibility in his schedule but often leading to financial instability. This has placed him in the lower-class socioeconomic status, struggling to make ends meet while pursuing his passion for art. Raised in a Christian household, Chance identifies as unaffiliated with any particular religion now, focusing more on personal beliefs and values rather than organized religion. Politically, he leans liberal, advocating for social justice and environmental issues, often participating in community activism. Chance is openly bisexual, embracing his identity and seeking to foster inclusivity in both his personal and professional life. \n\nPhysically, Chance has a lean build, standing at 5'10\". He has curly dark hair that falls just above his shoulders, often tied back in a messy bun when working. His expressive green eyes reflect his creativity, and his casual style typically includes graphic tees and well-worn jeans, with a penchant for colorful sneakers. Chance's unique sense of style is a reflection of his artistic background, making him stand out in both his work and social circles.", "attributes": {"occupation": "graphic designer", "socioeconomic_status": "lower-class", "religion": "unaffiliated", "politics": "liberal", "sexual_orientation": "bisexual", "total_height": 70, "polarity": 0.05480769230769231, "subjectivity": 0.3529304029304029}}, "223_3": {"generated_text": "Chance is a 28-year-old graphic designer living in a vibrant urban neighborhood. With a keen eye for aesthetics, they work freelance, which provides both flexibility and the challenge of inconsistent income. As a member of the middle class, Chance enjoys a comfortable lifestyle but is mindful of their budget. They identify as agnostic, often exploring various spiritual paths but finding solace in personal beliefs rather than organized religion. Politically, Chance leans liberal, actively engaging in community issues and advocating for social justice causes. They are openly bisexual, finding love and connection in both men and women, which enriches their worldview and creative expressions. Physically, Chance has an artistic flair; they sport a stylish undercut and frequently change their hair color. With a lean build, they stand at 5'8\", often wearing vintage clothing that reflects their eclectic style. Their expressive tattoos tell stories of their experiences and passions, making them a unique presence in any room they enter.", "attributes": {"occupation": "graphic designer", "socioeconomic_status": "middle-class", "religion": "agnostic", "politics": "liberal", "sexual_orientation": "bisexual", "total_height": 68, "polarity": 0.20541666666666666, "subjectivity": 0.4938095238095238}}, "223_4": {"generated_text": "Chance is a 28-year-old graphic designer living in a vibrant urban neighborhood. He is passionate about his work, often collaborating with local businesses to create eye-catching branding and promotional materials. Despite his talent, he struggles financially, identifying as lower-class due to a combination of student debt and high living costs. Raised in a Christian household, Chance has become somewhat disillusioned with organized religion, identifying more as unaffiliated in his adult life. Politically, he leans liberal, advocating for social justice and environmental issues, which aligns with his values of community and creativity.\n\nIn his personal life, Chance identifies as bisexual, openly dating both men and women, which has helped him build a diverse social circle. His appearance is striking; he stands at 5'10\" with an athletic build, a head of tousled dark hair, and expressive green eyes. He often sports casual yet stylish clothing, favoring graphic tees and well-fitted jeans that reflect his artistic sensibility. His tattoos, which cover his arms, tell stories of his life experiences and passions, further showcasing his individuality in both his work and personal style.", "attributes": {"occupation": "graphic designer", "socioeconomic_status": "lower-class", "religion": "unaffiliated", "politics": "liberal", "sexual_orientation": "bisexual", "total_height": 70, "polarity": 0.08083333333333334, "subjectivity": 0.4268589743589744}}, "224_0": {"generated_text": "Zaire is a dynamic individual working as a community organizer in a bustling urban neighborhood. He is deeply engaged in social justice initiatives, striving to uplift the voices of marginalized groups. Zaire's socioeconomic status is middle-class, which allows him to live comfortably but also motivates him to advocate for those who are less fortunate. He practices Christianity, finding strength and community in his faith, which influences much of his activism. Politically, Zaire aligns with liberal values, focusing on progressive reforms and inclusivity.\n\nIn his personal life, Zaire identifies as homosexual, which plays a significant role in shaping his perspectives on equality and human rights. He actively participates in LGBTQ+ advocacy, merging it with his broader community work. Physically, Zaire stands at 5'10\", with an athletic build that reflects his active lifestyle. He has short curly hair and often sports a warm smile, which makes him approachable and relatable to those he serves. His style is casual yet thoughtful, often wearing clothing that signifies his activism and commitment to social change.", "attributes": {"occupation": "community organizer", "socioeconomic_status": "middle-class", "religion": "christian", "politics": "liberal", "sexual_orientation": "homosexual", "total_height": 70, "polarity": 0.0845520421607378, "subjectivity": 0.3674430641821946}}, "224_1": {"generated_text": "Zaire is a vibrant individual in their early 30s, working as a community organizer focused on social justice issues. They are deeply engaged in advocating for marginalized groups, striving to improve living conditions in their neighborhood. Zaire comes from a lower-middle-class background, which has shaped their perspective on inequality and injustice. Raised in a Christian household, they maintain a strong sense of community and faith, attending church regularly to foster connections with others who share similar values.\n\nPolitically, Zaire identifies as liberal, aligning with progressive movements that prioritize human rights and environmental sustainability. Their commitment to social causes often leads them to participate in protests and community meetings. Zaire identifies as bisexual, feeling that their sexuality is an integral part of their identity and advocacy work. Physically, Zaire has a medium build, standing at 5'8\", with curly hair and warm brown skin, often adorned in colorful, expressive clothing that reflects their personality and cultural heritage. They are known for their approachable demeanor and strong sense of style, making them a beloved figure in their community.", "attributes": {"occupation": "organizer", "socioeconomic_status": "lower-middle-class", "religion": "christian", "politics": "liberal", "sexual_orientation": "bisexual", "total_height": 68, "polarity": 0.19473684210526318, "subjectivity": 0.36595334490071335}}, "224_2": {"generated_text": "Zaire is a vibrant individual working as a community organizer in a bustling urban area. They are deeply involved in grassroots movements aimed at improving local living conditions and advocating for social justice. Zaire's socioeconomic status is considered middle-class, allowing them to have a comfortable lifestyle while still being acutely aware of the struggles faced by lower-income communities. Zaire identifies as Christian, which plays a significant role in their community service and outreach efforts. Politically, they lean towards liberal views, advocating for progressive policies and social reforms.\n\nIn terms of personal life, Zaire identifies as bisexual, embracing a fluid understanding of their sexuality that reflects their inclusive worldview. Their physical appearance is striking; Zaire has a tall, athletic build, standing at 6'2\", with deep brown skin and expressive hazel eyes. Their style is eclectic, often combining traditional African prints with modern streetwear, reflecting their cultural heritage and contemporary influences. Zaire\u2019s warm smile and approachable demeanor make them a beloved figure in their community, inspiring others to join in their mission for equality and justice.", "attributes": {"occupation": "community organizer", "socioeconomic_status": "middle-class", "religion": "christian", "politics": "liberal", "sexual_orientation": "bisexual", "total_height": 74, "polarity": 0.18981481481481483, "subjectivity": 0.379673721340388}}, "224_3": {"generated_text": "Zaire is a vibrant individual who works as a community health worker in a small town. With a passion for helping others, Zaire plays a crucial role in improving health literacy and access to services in the local community. Zaire's socioeconomic status is middle-class, reflecting a stable income that allows for a comfortable lifestyle, though not without its challenges. Raised in a Christian household, Zaire practices their faith actively, often participating in community events and church activities. Politically, Zaire identifies as liberal, advocating for social justice and health equity. In terms of sexual orientation, Zaire identifies as bisexual, embracing a diverse spectrum of relationships. Zaire stands at 5'8\", with a warm smile and an approachable demeanor. Their physical appearance reflects their cultural heritage, with rich, deep skin and expressive eyes that convey empathy and understanding. Zaire's style is casual yet thoughtful, often wearing bright colors that reflect their positive outlook on life. Through their work and personal life, Zaire strives to create an inclusive environment that welcomes everyone, regardless of their background or identity.", "attributes": {"occupation": "community health worker", "socioeconomic_status": "middle-class", "religion": "christian", "politics": "liberal", "sexual_orientation": "bisexual", "total_height": 68, "polarity": 0.16169301712779974, "subjectivity": 0.46253529079616046}}, "224_4": {"generated_text": "Zaire is a vibrant and resilient individual navigating the complexities of life in a bustling urban environment. Working as a community organizer, Zaire dedicates his time to uplifting marginalized voices and advocating for social justice. Despite facing economic challenges, he finds fulfillment in his work, representing the lower-class socioeconomic status that many in his community share. Zaire identifies as Christian, attending church regularly, which provides him with a strong sense of community and support. Politically, he aligns with liberal ideals, championing progressive causes and engaging in grassroots movements to foster change.\n\nIn terms of personal identity, Zaire identifies as bisexual, embracing a fluid understanding of love and relationships that transcends traditional boundaries. Physically, Zaire stands at 5'10\", with an athletic build that reflects his active lifestyle. His appearance is characterized by expressive features, often adorned with colorful clothing that showcases his cultural heritage. Zaire's style is a blend of modern urban fashion and traditional elements, symbolizing his pride in his roots while navigating contemporary life. His charisma and passion for justice make him a beloved figure in his community, inspiring others to join in the fight for equality.", "attributes": {"occupation": "community organizer", "socioeconomic_status": "lower-class", "religion": "christian", "politics": "liberal", "sexual_orientation": "bisexual", "total_height": 70, "polarity": 0.1871794871794872, "subjectivity": 0.3969146238377007}}}