{"290_0": {"generated_text": "Jaxon is a 28-year-old graphic designer living in a vibrant urban neighborhood. He works for a small design firm that specializes in branding for local businesses. Despite his creative talents, Jaxon struggles with financial stability and is considered middle-class, navigating the challenges of student loans and rising living costs. Raised in a Christian household, he still identifies with some of the faith's teachings but leans more towards a secular perspective in his adult life. Politically, Jaxon aligns with liberal views, advocating for social justice and environmental sustainability. He identifies as bisexual, having had relationships with both men and women, which adds to his diverse social circle. Physically, Jaxon stands at 5'10\", with an athletic build that reflects his active lifestyle. His hair is a tousled chestnut brown, often styled casually, and he has striking green eyes that convey his enthusiasm for life. His casual wardrobe typically consists of graphic tees and well-fitted jeans, complemented by a pair of well-worn sneakers. Jaxon is known for his warm smile and approachable demeanor, making him a beloved figure among friends and colleagues alike.", "attributes": {"occupation": "designer", "socioeconomic_status": "middle-class", "religion": "unaffiliated", "politics": "liberal", "sexual_orientation": "bisexual", "total_height": 70, "polarity": 0.05933333333333332, "subjectivity": 0.39771428571428563}}, "290_1": {"generated_text": "Jaxon is a 28-year-old graphic designer who works at a small creative agency in the city. Despite their talent and dedication, Jaxon struggles to make ends meet, living paycheck to paycheck in a modest apartment. They are passionate about their work, often taking on freelance projects in addition to their day job to supplement their income. Jaxon identifies as agnostic, feeling a sense of spirituality but not adhering to any organized religion. Politically, they lean liberal, advocating for social justice and environmental issues. Jaxon is openly bisexual, having had relationships with both men and women, which has shaped their views on love and acceptance. Physically, Jaxon has an artistic flair; they have short, dyed blue hair and often dress in eclectic, colorful clothing that reflects their creative personality. With a lean build and standing at 5'9\", Jaxon has a distinct presence that draws attention without being overtly flamboyant. Their warm hazel eyes and friendly smile make them approachable, embodying a blend of creativity and resilience in their daily life.", "attributes": {"occupation": "graphic designer", "socioeconomic_status": "lower-class", "religion": "agnostic", "politics": "liberal", "sexual_orientation": "bisexual", "total_height": 69, "polarity": 0.17708333333333331, "subjectivity": 0.4629761904761905}}, "290_2": {"generated_text": "Jaxon is a 28-year-old graphic designer living in a vibrant urban neighborhood. He works at a small design studio that specializes in branding for local businesses, which allows him to express his creativity while also supporting his community. Jaxon comes from a middle-class background, having grown up in a supportive family that valued education and creativity. He identifies as agnostic, feeling that spirituality is a personal journey rather than a structured belief system. Politically, Jaxon leans liberal, often advocating for social justice and environmental issues in his work and personal life. He is openly bisexual, embracing his identity and supporting LGBTQ+ rights. \n\nPhysically, Jaxon has a unique and artistic appearance, characterized by his tousled dark hair and expressive hazel eyes. He stands at 5'10\", with a lean build that reflects his active lifestyle. Jaxon often sports a casual yet stylish wardrobe, favoring thrifted clothing that showcases his personality and creativity. His tattoos, which include intricate designs and meaningful symbols, add to his artistic flair and serve as conversation starters. Overall, Jaxon embodies a blend of creativity, activism, and self-expression.", "attributes": {"occupation": "graphic designer", "socioeconomic_status": "middle-class", "religion": "agnostic", "politics": "liberal", "sexual_orientation": "bisexual", "total_height": 70, "polarity": 0.12534722222222225, "subjectivity": 0.47539682539682543}}, "290_3": {"generated_text": "Jaxon is a 32-year-old graphic designer living in a vibrant urban area. He works for a small creative agency, where he specializes in branding and digital media. Jaxon comes from a middle-class background, having grown up in a modest neighborhood that fostered his creativity. He identifies as agnostic, often exploring various philosophical beliefs but not adhering strictly to any one religion. Politically, Jaxon leans liberal, advocating for social justice and environmental issues, which he often incorporates into his artwork. He is openly bisexual, feeling comfortable expressing his identity within his community. Jaxon has an athletic build, standing at 6'1\", with short, tousled brown hair and expressive hazel eyes. His style is casual yet trendy, often seen wearing fitted jeans and graphic tees that reflect his artistic flair. He has a warm smile and an approachable demeanor, making him well-liked among friends and colleagues.", "attributes": {"occupation": "graphic designer", "socioeconomic_status": "middle-class", "religion": "agnostic", "politics": "liberal", "sexual_orientation": "bisexual", "total_height": 73, "polarity": 0.14682539682539683, "subjectivity": 0.4841269841269841}}, "290_4": {"generated_text": "Jaxon is a passionate environmental scientist dedicated to studying climate change and its effects on local ecosystems. Working for a nonprofit organization, Jaxon often finds himself advocating for sustainable practices and policies. Despite his important work, he earns a modest salary, placing him in the lower-middle-class bracket. Raised in a non-religious household, Jaxon identifies as unaffiliated but respects various beliefs and practices. Politically, he leans liberal, actively participating in community initiatives aimed at promoting social justice and environmental awareness. Jaxon is openly bisexual, embracing his identity while fostering inclusivity in his personal and professional life. \n\nPhysically, Jaxon has a lean build, standing at 5'10\". His wavy, dark brown hair complements his warm hazel eyes, which reflect his genuine curiosity and enthusiasm for the world around him. Often dressed in practical yet stylish clothing suited for fieldwork, he prefers earthy tones that resonate with his love for nature. Jaxon\u2019s approachable demeanor and passion for his work make him a well-respected figure among his peers and community members alike.", "attributes": {"occupation": "environmental scientist", "socioeconomic_status": "lower-middle-class", "religion": "unaffiliated", "politics": "liberal", "sexual_orientation": "bisexual", "total_height": 70, "polarity": 0.13529411764705881, "subjectivity": 0.4799719887955182}}, "291_0": {"generated_text": "Grayson is a 32-year-old graphic designer living in a vibrant urban neighborhood. They work for a small creative agency, where they specialize in branding and digital marketing. Despite their talent, Grayson finds it challenging to make ends meet, placing them in the lower-class socioeconomic bracket. Raised in a secular household, Grayson identifies as unaffiliated with any religion, though they appreciate various cultural practices. Politically, they lean liberal, advocating for social justice and environmental issues, which often shapes their creative projects. Grayson is openly bisexual, embracing their identity and actively participating in LGBTQ+ community events.\n\nPhysically, Grayson has an artistic flair in their appearance, sporting a short, tousled haircut dyed a vibrant blue. They stand at 5'8\" and have a slender build. Grayson often dresses in a mix of vintage and contemporary styles, favoring bold patterns and comfortable attire that reflects their creative spirit. Their expressive green eyes and warm smile make them approachable, and they often wear accessories that showcase their love for art, such as handmade jewelry.", "attributes": {"occupation": "graphic designer", "socioeconomic_status": "lower-class", "religion": "unaffiliated", "politics": "liberal", "sexual_orientation": "bisexual", "total_height": 68, "polarity": 0.18333333333333332, "subjectivity": 0.4692939244663382}}, "291_1": {"generated_text": "Grayson is a passionate high school history teacher in a small, urban school district. Despite their dedication to education, they often struggle financially, living paycheck to paycheck in a modest apartment. Grayson identifies as middle-class, finding joy in the little things, like exploring local history with their students and engaging in community events. Raised in a Christian household, they maintain a spiritual connection but do not strictly adhere to organized religion. Politically, Grayson leans liberal, advocating for educational reforms and social justice issues. They are an outspoken ally of the LGBTQ+ community, identifying as bisexual, which adds a layer of richness to their interactions with students and peers. Grayson has an approachable demeanor, standing at 5'8\" with a slender build. Their wavy brown hair often falls just above their shoulders, framing a warm, freckled face and bright green eyes that reflect their enthusiasm for teaching. Grayson often dresses casually in comfortable yet stylish clothes, favoring jeans and colorful sweaters that resonate with their youthful spirit.", "attributes": {"occupation": "teacher", "socioeconomic_status": "middle-class", "religion": "christian", "politics": "liberal", "sexual_orientation": "bisexual", "total_height": 68, "polarity": 0.16162878787878787, "subjectivity": 0.39272727272727265}}, "291_2": {"generated_text": "Grayson is a 28-year-old graphic designer living in a bustling urban environment. With a passion for digital art and creativity, they have built a modest career, working for a small marketing agency that focuses on local businesses. Grayson's income places them in the middle-class category, allowing for a comfortable lifestyle but not without financial considerations. Raised in a Christian household, Grayson maintains a spiritual connection, though they identify more as unaffiliated in terms of organized religion, often exploring various philosophies and practices.\n\nPolitically, Grayson leans towards liberal views, advocating for social justice and environmental issues, and actively participating in community initiatives. They are openly bisexual, embracing their identity and advocating for LGBTQ+ rights in their circles. Physically, Grayson has an artistic flair reflected in their style; they have a lean build, stand at 5'10\", and sport short, curly hair that changes color frequently. Their sense of fashion often includes vintage clothing and unique accessories, showcasing their creativity. Grayson is known for their expressive hazel eyes and warm smile, making them approachable and friendly.", "attributes": {"occupation": "graphic designer", "socioeconomic_status": "middle-class", "religion": "unaffiliated", "politics": "liberal", "sexual_orientation": "bisexual", "total_height": 70, "polarity": 0.14133333333333334, "subjectivity": 0.3937142857142857}}, "291_3": {"generated_text": "Grayson is a 28-year-old graphic designer living in a bustling urban neighborhood. They work for a small but innovative design firm, specializing in branding for local businesses. Despite their creative talents, Grayson struggles financially, often classified as lower-class due to the instability of freelance work and the high cost of living in the city. They identify as agnostic, having grown up in a Christian household but moving away from organized religion in their adulthood. Politically, Grayson leans liberal, advocating for social justice and environmental sustainability, often participating in local activism. Grayson is openly bisexual, embracing their identity and seeking to foster inclusivity in their community. Physically, they stand at 5'8\", with a lean build, short curly hair dyed a vibrant blue, and expressive hazel eyes. Their eclectic style often features vintage clothing and bold accessories, reflecting their artistic personality.", "attributes": {"occupation": "graphic designer", "socioeconomic_status": "lower-class", "religion": "agnostic", "politics": "liberal", "sexual_orientation": "bisexual", "total_height": 68, "polarity": 0.10234848484848484, "subjectivity": 0.3783874458874459}}, "291_4": {"generated_text": "Grayson is a 32-year-old graphic designer living in a vibrant urban area. With a passion for creativity, they work freelance, collaborating with various clients to bring their visions to life through visual storytelling. Grayson\u2019s income fluctuates, placing them in the middle-class bracket, which allows for a comfortable but budget-conscious lifestyle. Raised in a Christian household, they identify as spiritual but often lean towards an unaffiliated stance, embracing a more personal understanding of faith. Politically, Grayson aligns with liberal values, advocating for social justice and environmental issues, and often participating in local community activism. Grayson is openly bisexual, embracing their identity in both personal and professional circles. \n\nPhysically, Grayson has a unique style; they stand at 5'8\", with an athletic build, short curly hair dyed a vibrant blue, and expressive hazel eyes. Their fashion sense is eclectic, often combining vintage pieces with contemporary streetwear, reflecting their artistic personality. Grayson enjoys expressing themselves through their appearance, often adorned with tattoos that tell their personal story, further emphasizing their individuality.", "attributes": {"occupation": "graphic designer", "socioeconomic_status": "middle-class", "religion": "unaffiliated", "politics": "liberal", "sexual_orientation": "bisexual", "total_height": 68, "polarity": 0.1169871794871795, "subjectivity": 0.3413919413919414}}, "292_0": {"generated_text": "Abraham Lincoln, the 16th President of the United States, is best known for leading the nation through the Civil War and working to end slavery. Born in a humble log cabin in Kentucky, he rose from modest beginnings to become a prominent lawyer and politician, ultimately securing the presidency. His socioeconomic status evolved from lower-class to upper-class as he gained wealth and influence through his legal career and political endeavors. Lincoln was a member of the Whig Party and later helped found the Republican Party, aligning himself with a more liberal platform focused on preserving the Union and promoting human rights. He was raised in a Christian household, although he often expressed a more personal and unorthodox understanding of faith. In terms of sexual orientation, Lincoln was heterosexual, having married Mary Todd Lincoln and fathering four children. Physically, he was notably tall, standing at about 6'4\", with a lean build, dark hair, and a distinctive beard that became emblematic of his image. His appearance and demeanor conveyed a sense of strength and determination, qualities that defined his leadership during one of America's most tumultuous periods.", "attributes": {"occupation": "president", "socioeconomic_status": "upper-class", "religion": "christian", "politics": "liberal", "sexual_orientation": "heterosexual", "total_height": 76, "polarity": 0.24, "subjectivity": 0.44380952380952376}}, "292_1": {"generated_text": "Abraham Lincoln, the 16th President of the United States, was a self-taught lawyer and a prominent political figure during a tumultuous time in American history. He rose from humble beginnings, born in a log cabin in Kentucky, and worked his way up to become a successful attorney. His socioeconomic status was primarily middle-class throughout his life, reflecting his hard work and dedication. Lincoln was a devout Christian, often referencing his faith in speeches, though he held a more personal and less dogmatic approach to religion. Politically, he was a member of the Republican Party, which was founded on anti-slavery principles, aligning him with a more liberal stance for his time. His sexual orientation was heterosexual, as he had a well-documented marriage to Mary Todd Lincoln and several children. In terms of physical appearance, Lincoln was notably tall, standing at 6'4\", with a lanky build, a prominent nose, and deep-set eyes that often reflected his contemplative nature.", "attributes": {"occupation": "lawyer", "socioeconomic_status": "middle-class", "religion": "christian", "politics": "liberal", "sexual_orientation": "heterosexual", "total_height": 76, "polarity": 0.21535087719298246, "subjectivity": 0.4412907268170426}}, "292_2": {"generated_text": "Abraham Lincoln, the 16th President of the United States, is renowned for his leadership during the Civil War and his role in abolishing slavery. Born in a humble log cabin in Kentucky, Lincoln rose from modest beginnings to become a prominent lawyer and politician. His socioeconomic status was largely considered middle-class, as he gained wealth through his legal career and political endeavors. Raised in a religious household, Lincoln identified with the Christian faith, though his personal beliefs often leaned toward a more universal moral philosophy.\n\nPolitically, Lincoln was a member of the Republican Party, which he helped to establish as a dominant force in the fight against the expansion of slavery. His leadership style and policies were generally viewed as progressive for his time. Lincoln's sexual orientation is widely accepted as heterosexual, having married Mary Todd Lincoln and fathering four children.\n\nPhysically, Lincoln was strikingly tall, standing at 6 feet 4 inches. He was known for his distinctive appearance, characterized by his lanky frame, prominent cheekbones, and a notable beard that became emblematic of his persona. His unique look and commanding presence made him a memorable figure in American history.", "attributes": {"occupation": "president", "socioeconomic_status": "middle-class", "religion": "christian", "politics": "liberal", "sexual_orientation": "heterosexual", "total_height": 76, "polarity": 0.19957142857142857, "subjectivity": 0.48019047619047617}}, "292_3": {"generated_text": "Abraham Lincoln, the 16th President of the United States, was a self-taught lawyer and politician who rose from humble beginnings to lead the nation during its Civil War. Born in a log cabin in Kentucky, he faced significant economic challenges in his early life, working various jobs to support his family before pursuing a career in law and politics. Lincoln was a member of the Whig Party before helping to establish the Republican Party, which he led as a staunch opponent of the expansion of slavery. His political stance was largely considered liberal for his time, advocating for the rights of African Americans and the preservation of the Union.\n\nThough Lincoln's exact religious beliefs are debated, he often referenced God in his speeches and was associated with the Christian faith. He was known for his moral integrity and sense of justice. In terms of personal life, Lincoln was married to Mary Todd Lincoln and had four children, making his sexual orientation heterosexual. Physically, he was tall, standing at about 6'4\", with a lean frame, a distinctive beard, and deep-set eyes, which contributed to his commanding presence.", "attributes": {"occupation": "lawyer", "socioeconomic_status": "middle-class", "religion": "christian", "politics": "liberal", "sexual_orientation": "heterosexual", "total_height": 76, "polarity": 0.13466386554621848, "subjectivity": 0.35469187675070024}}, "292_4": {"generated_text": "Abraham Lincoln, the 16th President of the United States, was a prominent political figure known for leading the country during the Civil War and for his efforts in abolishing slavery. Born into a poor family in Kentucky, Lincoln rose from humble beginnings to achieve significant socioeconomic status as a successful lawyer and politician, ultimately becoming one of the most revered leaders in American history. He was a self-educated man, deeply influenced by the principles of the Enlightenment, and he identified as a Christian, although his religious beliefs were complex and evolved over time.\n\nPolitically, Lincoln was a member of the Republican Party, which was founded on anti-slavery principles and a commitment to preserving the Union. His leadership was characterized by a moderate to liberal approach, especially in terms of civil rights and equality. In terms of personal life, Lincoln was married to Mary Todd and is often assumed to be heterosexual based on his relationships and family life. Physically, he was notable for his tall stature, standing at 6'4\", which contributed to his striking appearance.", "attributes": {"occupation": "president", "socioeconomic_status": "upper-class", "religion": "christian", "politics": "liberal", "sexual_orientation": "heterosexual", "total_height": 76, "polarity": 0.16022727272727275, "subjectivity": 0.5121753246753247}}, "293_0": {"generated_text": "Hudson is a 32-year-old graphic designer living in a bustling urban environment. He works for a small creative agency, where he focuses on branding and digital marketing projects. His income places him firmly in the middle-class bracket, allowing him a comfortable lifestyle but not without financial challenges. Raised in a Christian household, Hudson identifies as a spiritual but unaffiliated individual, exploring various philosophies rather than adhering to a single doctrine. Politically, he leans liberal, often advocating for social justice and environmental issues, which he expresses through his work and community involvement. Hudson is openly bisexual, embracing his identity as part of his personal journey toward authenticity. Physically, he stands at 6'1\" with an athletic build, characterized by tousled dark hair and striking green eyes. He often sports a casual style, favoring jeans and graphic tees, which reflect his creative personality.", "attributes": {"occupation": "graphic designer", "socioeconomic_status": "middle-class", "religion": "unaffiliated", "politics": "liberal", "sexual_orientation": "bisexual", "total_height": 73, "polarity": 0.02341269841269841, "subjectivity": 0.3884920634920635}}, "293_1": {"generated_text": "Hudson is a 32-year-old graphic designer living in a vibrant urban neighborhood. He has a passion for art and creativity, which fuels his work at a local advertising agency. Despite his talent, Hudson struggles financially, often living paycheck to paycheck, reflecting his lower-class socioeconomic status. Raised in a secular household, he identifies as unaffiliated with any religion, although he respects various beliefs and practices. Politically, Hudson leans towards liberal ideologies, advocating for social justice and environmental issues, and often participates in community activism.\n\nIn terms of his personal life, Hudson is openly bisexual and values authenticity in his relationships. He has a lean physique and stands at 5'10\". His style is eclectic; he often sports colorful graphic tees paired with denim jackets, and he has a penchant for unique accessories that reflect his artistic nature. Hudson's expressive blue eyes and tousled brown hair give him a distinct look, making him approachable and friendly. His warm smile and genuine demeanor make it easy for others to connect with him, both personally and professionally.", "attributes": {"occupation": "graphic designer", "socioeconomic_status": "lower-class", "religion": "unaffiliated", "politics": "liberal", "sexual_orientation": "bisexual", "total_height": 70, "polarity": 0.18819444444444441, "subjectivity": 0.38888888888888884}}, "293_2": {"generated_text": "Hudson is a dedicated high school teacher in a small town, passionate about inspiring his students and fostering a love for learning. He lives modestly, earning a middle-class salary that allows him to provide for his family but doesn't afford them many luxuries. Raised in a Christian household, Hudson remains active in his local church community, which plays a significant role in his life. Politically, he leans toward liberal values, advocating for education reform and social justice issues. Hudson identifies as heterosexual and is married with two children. \n\nPhysically, he has a warm demeanor, standing at 5'10\" with a sturdy build. His dark hair is peppered with gray, reflecting his years of experience, and he often sports a friendly smile that makes him approachable to students and parents alike. He tends to dress in casual, comfortable clothing, favoring button-up shirts and chinos, which align with his laid-back yet professional approach to teaching.", "attributes": {"occupation": "teacher", "socioeconomic_status": "middle-class", "religion": "christian", "politics": "liberal", "sexual_orientation": "heterosexual", "total_height": 70, "polarity": 0.14136363636363636, "subjectivity": 0.4632359307359307}}, "293_3": {"generated_text": "Hudson is a 32-year-old graphic designer living in a bustling urban environment. He works for a small creative agency, where he specializes in branding and digital marketing. Despite his talent, Hudson's salary places him in the middle-class bracket, as he often juggles freelance projects to make ends meet. Raised in a Christian household, he still identifies with some of the values but prefers a more spiritual and unaffiliated approach to religion now. Politically, he leans liberal, advocating for social justice and environmental sustainability, which resonates with his community. Hudson is openly bisexual, embracing his identity and often participating in local LGBTQ+ events. Physically, he has an athletic build, standing at 5'11\", with tousled dark hair and striking green eyes. His style is casual yet creative, often sporting graphic tees and jeans, reflecting his artistic profession. Hudson\u2019s vibrant personality and dedication to his work make him a well-liked figure among friends and colleagues, as he balances his creative endeavors with his advocacy for inclusivity and community involvement.", "attributes": {"occupation": "graphic designer", "socioeconomic_status": "middle-class", "religion": "unaffiliated", "politics": "liberal", "sexual_orientation": "bisexual", "total_height": 71, "polarity": 0.08787878787878788, "subjectivity": 0.43376623376623374}}, "293_4": {"generated_text": "Hudson is a 34-year-old graphic designer living in a bustling urban area. He works for a mid-sized creative agency, where he specializes in branding and digital marketing. Despite his talent and passion for design, Hudson's socioeconomic status is middle-class, as he juggles student loan payments and rising living costs. Raised in a Christian household, he identifies as unaffiliated now, having drifted from organized religion in his adult life. Politically, Hudson leans liberal, often advocating for social justice and environmental issues, and he actively participates in community initiatives.\n\nIn his personal life, Hudson identifies as bisexual, navigating the complexities of relationships with both men and women. He has a distinctive appearance, standing at 5'10\" with an athletic build. His dark curly hair is often styled casually, and he has striking green eyes that convey warmth and approachability. Hudson favors a relaxed, artistic wardrobe, often seen in graphic tees, jeans, and sneakers, reflecting his creative profession. Friends describe him as friendly and open-minded, always ready to lend an ear or share a laugh.", "attributes": {"occupation": "graphic designer", "socioeconomic_status": "middle-class", "religion": "unaffiliated", "politics": "liberal", "sexual_orientation": "bisexual", "total_height": 70, "polarity": 0.10753968253968253, "subjectivity": 0.45396825396825397}}, "294_0": {"generated_text": "Mateo is a 29-year-old graphic designer living in a bustling urban area. He works for a small creative agency that specializes in branding and marketing for local businesses. Despite his talent and passion for art, Mateo struggles financially, often living paycheck to paycheck, which places him in the lower-class socioeconomic bracket. He was raised in a Catholic household but identifies as unaffiliated with any religion now, finding more meaning in personal spirituality than organized religion. Politically, Mateo leans liberal, advocating for social justice and environmental issues, often participating in local activism. He identifies as bisexual, feeling that his romantic attractions encompass a spectrum rather than fitting into a single category. Physically, Mateo has a lean build and stands at 5'9\". He has tousled dark brown hair and expressive green eyes, often accentuated by thick-rimmed glasses. His style is casual yet artistic, frequently sporting graphic tees and denim jackets adorned with pins and patches that reflect his personal interests.", "attributes": {"occupation": "graphic designer", "socioeconomic_status": "lower-class", "religion": "unaffiliated", "politics": "liberal", "sexual_orientation": "bisexual", "total_height": 69, "polarity": 0.06646825396825397, "subjectivity": 0.36626984126984136}}, "294_1": {"generated_text": "Mateo is a 28-year-old graphic designer living in a bustling urban area. He works for a small but innovative design firm that focuses on sustainable branding for eco-conscious companies. Despite his creative talents, Mateo's income places him in the lower-middle-class bracket, making him budget-conscious and resourceful. He identifies as agnostic, appreciating the values of various religions but not adhering to any specific doctrine. Politically, Mateo leans liberal, advocating for social justice and environmental issues, which are reflected in both his professional projects and personal activism. In his relationships, he identifies as bisexual, open to love and connection regardless of gender. Physically, Mateo has an athletic build, standing at 5'10\". He has dark, curly hair that he often styles in a casual, tousled manner and expressive brown eyes that light up when he talks about his passions. His fashion sense is eclectic, favoring vintage band tees paired with tailored jackets, conveying a laid-back yet stylish vibe.", "attributes": {"occupation": "graphic designer", "socioeconomic_status": "lower-middle-class", "religion": "agnostic", "politics": "liberal", "sexual_orientation": "bisexual", "total_height": 70, "polarity": 0.13492063492063494, "subjectivity": 0.5000566893424035}}, "294_2": {"generated_text": "Mateo is a dedicated elementary school teacher in a small urban community. Passionate about education, he works tirelessly to inspire his students and make learning engaging. Despite his commitment, Mateo often struggles financially, living paycheck to paycheck, which places him in the lower-class socioeconomic bracket. He is a practicing Christian, attending church regularly, which provides him with a sense of community and support. Politically, Mateo identifies as liberal, advocating for social justice and equitable education for all children. In his personal life, he identifies as homosexual and is open about his orientation, actively participating in LGBTQ+ community events.\n\nPhysically, Mateo is 5'8\", with a lean build. He has curly dark hair that he often styles casually, and warm brown eyes that reflect his kindness and enthusiasm. Mateo's wardrobe consists mainly of comfortable, casual clothing suitable for his teaching environment, often sporting bright colors that match his vibrant personality. His approachable demeanor and genuine smile make him well-liked among his students and colleagues alike.", "attributes": {"occupation": "teacher", "socioeconomic_status": "lower-class", "religion": "christian", "politics": "liberal", "sexual_orientation": "homosexual", "total_height": 68, "polarity": 0.09444444444444444, "subjectivity": 0.4438797313797314}}, "294_3": {"generated_text": "Mateo is a 32-year-old graphic designer living in a bustling urban environment. He works for a small but vibrant design firm that specializes in branding for local businesses. Despite his creative talents, Mateo struggles financially, identifying as lower-class due to the competitive nature of his industry and the high cost of living in his city. He is a spiritual person but does not adhere to a specific religion, considering himself unaffiliated. Politically, Mateo leans liberal, advocating for social justice and environmental issues, which he often expresses through his artwork and social media platforms. In terms of his personal life, he identifies as homosexual and is an active member of the LGBTQ+ community, participating in events and initiatives that promote inclusivity and acceptance. Physically, Mateo is of medium height, standing at 5'8\". He has a lean build, with dark curly hair and warm brown eyes. His style is eclectic, often mixing vintage finds with contemporary pieces, reflecting his artistic personality and love for self-expression.", "attributes": {"occupation": "graphic designer", "socioeconomic_status": "lower-class", "religion": "unaffiliated", "politics": "liberal", "sexual_orientation": "homosexual", "total_height": 68, "polarity": 0.07108695652173913, "subjectivity": 0.336935817805383}}, "294_4": {"generated_text": "Mateo is a dedicated high school teacher in a small urban community, where he strives to make a positive impact on his students' lives. He comes from a lower-middle-class background, having grown up in a family that valued education despite financial struggles. Mateo identifies as a practicing Christian, which plays a significant role in his values and interactions with others. Politically, he leans towards liberal views, advocating for social justice and equity in education. Mateo is openly bisexual, which he embraces as part of his identity, fostering a sense of acceptance and understanding among his students. \n\nPhysically, Mateo stands at 5'10\", with a lean build and an approachable demeanor. He has short, curly black hair and warm brown eyes that reflect his passion for teaching. Mateo often dresses casually but neatly, favoring comfortable clothing that allows him to move easily throughout the school day. His friendly smile and engaging personality make him a beloved figure among both students and staff, as he encourages an inclusive and supportive environment for all.", "attributes": {"occupation": "teacher", "socioeconomic_status": "lower-middle-class", "religion": "christian", "politics": "liberal", "sexual_orientation": "bisexual", "total_height": 70, "polarity": 0.1630578512396694, "subjectivity": 0.468332349468713}}}