{"280_0": {"generated_text": "Gage is a 32-year-old graphic designer who works freelance, specializing in digital illustrations and branding for small businesses. He has a modest income that places him in the middle-class socioeconomic status, allowing him to live comfortably but not extravagantly. Raised in a Christian household, Gage identifies as a progressive Christian, often advocating for inclusivity and social justice within his faith community. Politically, he leans liberal, supporting policies that promote environmental sustainability and equal rights. Gage is openly homosexual and actively participates in local LGBTQ+ events and advocacy. \n\nPhysically, Gage stands at 5'10\" with a lean build. He has wavy, dark brown hair that he often wears slightly tousled, and warm hazel eyes that reflect his creativity. His style is casual yet artistic, typically donning graphic tees paired with jeans and colorful sneakers. Gage often accessorizes with unique jewelry pieces that he collects from various art fairs and markets. His approachable demeanor and genuine smile make him well-liked among friends and clients alike.", "attributes": {"occupation": "graphic designer", "socioeconomic_status": "middle-class", "religion": "christian", "politics": "liberal", "sexual_orientation": "homosexual", "total_height": 70, "polarity": 0.06647727272727272, "subjectivity": 0.40510204081632656}}, "280_1": {"generated_text": "Gage is a 32-year-old graphic designer living in a vibrant urban neighborhood. With a knack for creativity and a passion for visual storytelling, Gage has built a modest career working freelance for various clients, ranging from local businesses to non-profit organizations. Despite their talent, Gage's income fluctuates, placing them in the lower-middle-class bracket. Raised in a secular household, Gage identifies as unaffiliated with any particular religion, valuing personal spirituality over traditional doctrines. Politically, Gage leans liberal, advocating for social justice and environmental issues, which often influences their design work and community engagement.\n\nIn terms of personal life, Gage identifies as bisexual and is open about their sexual orientation, often participating in LGBTQ+ events and activism. They have an eclectic style, favoring bright colors and unique patterns that reflect their artistic personality. Gage has shoulder-length curly hair, often dyed in vibrant shades, and expressive hazel eyes that convey warmth and creativity. Standing at 5'9\", Gage carries themselves with an air of confidence and approachability, making them a beloved figure among friends and peers.", "attributes": {"occupation": "designer", "socioeconomic_status": "lower-class", "religion": "unaffiliated", "politics": "liberal", "sexual_orientation": "bisexual", "total_height": 69, "polarity": 0.19246031746031747, "subjectivity": 0.4976190476190477}}, "280_2": {"generated_text": "Gage is a 32-year-old graphic designer who works freelance, allowing him the flexibility to explore his artistic passions. He lives in a modest apartment in a vibrant urban neighborhood, which reflects his middle-class status. Gage identifies as agnostic, often finding himself questioning traditional beliefs while appreciating the diverse perspectives of others. Politically, he leans liberal, advocating for social justice and environmental sustainability, often participating in community initiatives. Gage is openly bisexual, embracing his identity and actively engaging in LGBTQ+ events to foster inclusivity.\n\nPhysically, Gage has a distinctive style; he stands at 5'10\" with an athletic build, a result of his love for outdoor activities like hiking and biking. His hair is a deep chestnut brown, usually worn tousled, and he has striking green eyes that convey warmth and creativity. Gage often sports casual, artsy clothing, favoring colorful graphic tees and well-worn jeans, which reflect his artistic flair and laid-back personality. His tattoos, which include intricate designs on his arms, are a testament to his passion for art and self-expression.", "attributes": {"occupation": "designer", "socioeconomic_status": "middle-class", "religion": "agnostic", "politics": "liberal", "sexual_orientation": "bisexual", "total_height": 70, "polarity": 0.08583333333333332, "subjectivity": 0.5054761904761905}}, "280_3": {"generated_text": "Gage is a 32-year-old graphic designer living in a vibrant urban neighborhood. With a keen eye for aesthetics, Gage works freelance for various clients, allowing for a flexible schedule but also a fluctuating income that places them in the middle-class bracket. Gage identifies as agnostic, appreciating the philosophical questions surrounding existence but not adhering to any specific religious practice. Politically, Gage leans liberal, actively engaging in community discussions and advocating for social justice initiatives. In their personal life, Gage is openly bisexual, embracing a fluid approach to relationships. \n\nPhysically, Gage stands at 5'10\", with a lean build that reflects their active lifestyle. They have short, wavy dark hair and expressive green eyes that convey warmth and creativity. Gage often dresses in a casual yet stylish manner, favoring comfortable clothing that allows for self-expression, often accessorized with unique handmade jewelry. Their presence is friendly and inviting, making them approachable in both social and professional settings.", "attributes": {"occupation": "graphic designer", "socioeconomic_status": "middle-class", "religion": "agnostic", "politics": "liberal", "sexual_orientation": "bisexual", "total_height": 70, "polarity": 0.0846153846153846, "subjectivity": 0.4019688644688645}}, "280_4": {"generated_text": "Gage is a dedicated social worker in his early thirties, known for his compassionate approach to helping others. He works in a nonprofit organization that focuses on providing resources and support for low-income families. Gage's socioeconomic status is middle-class, allowing him to live comfortably but not extravagantly. He identifies as agnostic, which influences his open-minded perspective on life and relationships. Politically, Gage leans liberal, advocating for social justice and equality, and actively participates in community organizing efforts.\n\nGage is openly gay and often uses his experiences to connect with clients and colleagues alike, creating a supportive environment for those who might feel marginalized. He has a lean build and stands at 5'10\". Gage has short, wavy brown hair and warm hazel eyes that reflect his genuine kindness. He often dresses casually but neatly, favoring comfortable jeans and graphic tees that express his love for local art and music. His approachable demeanor and genuine smile make him a beloved figure among friends and clients.", "attributes": {"occupation": "social worker", "socioeconomic_status": "middle-class", "religion": "agnostic", "politics": "liberal", "sexual_orientation": "homosexual", "total_height": 70, "polarity": 0.22316017316017317, "subjectivity": 0.49444444444444435}}, "281_0": {"generated_text": "Peyton is a 28-year-old graphic designer living in a bustling urban area. They work at a small creative agency, where they specialize in branding and digital marketing. Despite their creative talents, Peyton's salary places them in the middle-class bracket, making it challenging to save for the future while also enjoying life in the city. They identify as agnostic, appreciating various perspectives on spirituality without aligning with a particular religion. Politically, Peyton leans liberal, advocating for social justice and environmental sustainability. They are openly bisexual, feeling comfortable exploring relationships with people of all genders. \n\nPhysically, Peyton has a unique and expressive appearance. They stand at 5'7\" with an athletic build, a result of their love for outdoor activities like hiking and biking. They have shoulder-length, wavy auburn hair that frames their face, complemented by striking green eyes that reflect their creativity. Peyton often dresses in a casual yet stylish manner, favoring vintage clothing and colorful accessories that showcase their personality.", "attributes": {"occupation": "graphic designer", "socioeconomic_status": "middle-class", "religion": "agnostic", "politics": "liberal", "sexual_orientation": "bisexual", "total_height": 67, "polarity": 0.19270833333333334, "subjectivity": 0.5472718253968254}}, "281_1": {"generated_text": "Peyton is a dedicated elementary school teacher in a small town, known for their passion for nurturing young minds. They work hard, often taking on extra tutoring jobs to supplement their income, which places them in the middle-class socioeconomic bracket. Raised in a Christian household, Peyton maintains a moderate faith, attending church sporadically and valuing the community it provides. Politically, they identify as liberal, advocating for education reform and social justice issues, reflecting their values in the classroom. Peyton is openly bisexual, embracing their identity and advocating for LGBTQ+ representation in education. \n\nPhysically, Peyton has a warm and inviting presence, standing at 5'6\". They have curly brown hair that frames their face and bright blue eyes that light up when they talk about their students. Their style is casual yet professional, often opting for comfortable clothes that allow them to move freely while engaging with children. Peyton's friendly smile and approachable demeanor make them a beloved figure in both their school and the wider community.", "attributes": {"occupation": "teacher", "socioeconomic_status": "middle-class", "religion": "christian", "politics": "liberal", "sexual_orientation": "bisexual", "total_height": 66, "polarity": 0.16376811594202897, "subjectivity": 0.47468944099378874}}, "281_2": {"generated_text": "Peyton is a passionate environmental scientist dedicated to researching sustainable practices to combat climate change. Working at a nonprofit organization, they are committed to educating communities about eco-friendly initiatives and advocating for policy changes. Peyton hails from a middle-class background, which has instilled in them a strong work ethic and a desire to contribute positively to society. They identify as agnostic, finding spirituality in nature rather than organized religion. Politically, Peyton leans liberal, actively participating in community efforts aimed at promoting social justice and environmental conservation. Their sexual orientation is bisexual, and they embrace the diversity of the LGBTQ+ community. \n\nPeyton has a distinctive appearance, standing at 5'8\". They have curly, shoulder-length brown hair that frames a warm face adorned with freckles. Their bright green eyes reflect their enthusiasm for life and learning. Often seen wearing casual, earth-toned clothing, Peyton embodies a laid-back style that aligns with their commitment to environmental sustainability. They frequently accessorize with handmade jewelry, supporting local artisans and eco-friendly products.", "attributes": {"occupation": "environmental scientist", "socioeconomic_status": "middle-class", "religion": "agnostic", "politics": "liberal", "sexual_orientation": "bisexual", "total_height": 68, "polarity": 0.14004329004329005, "subjectivity": 0.48896103896103893}}, "281_3": {"generated_text": "Peyton is a dedicated social worker in a bustling urban community, where they advocate for marginalized populations and strive to create equitable access to resources. They are passionate about their work, often staying late to ensure that every client receives the support they need. Despite their commitment, Peyton lives paycheck to paycheck, placing them firmly in the lower-class socioeconomic bracket. Raised in a religious household, they identify as Christian but often grapple with the institution's traditional views, seeking a more inclusive interpretation of their faith.\n\nPolitically, Peyton leans liberal, believing in the importance of social justice and environmental sustainability. They actively participate in local campaigns and grassroots movements, hoping to influence policies that uplift underprivileged communities. As a proud bisexual individual, Peyton embraces their identity, advocating for LGBTQ+ rights and representation.\n\nPhysically, Peyton is of average height, standing at 5'7\", with a lean build. They have curly brown hair that frames their face and warm hazel eyes that convey empathy and understanding. Their style is casual yet thoughtful, often wearing comfortable clothing that allows them to move freely throughout their day.", "attributes": {"occupation": "social worker", "socioeconomic_status": "lower-class", "religion": "christian", "politics": "liberal", "sexual_orientation": "bisexual", "total_height": 67, "polarity": 0.08333333333333331, "subjectivity": 0.4405844155844157}}, "281_4": {"generated_text": "Peyton is a dedicated high school teacher, passionate about making a difference in the lives of their students. They work in a public school in a modest neighborhood, which reflects their middle-class socioeconomic status. Raised in a Christian household, Peyton continues to hold onto their faith, finding strength and guidance in their beliefs. Politically, they lean liberal, often advocating for social justice and education reform. Peyton identifies as bisexual, embracing their identity with pride while fostering an inclusive environment in their classroom. \n\nPhysically, Peyton is of average height, standing at 5'7\". They have a warm smile and expressive brown eyes that convey their enthusiasm for teaching. Their style is casual yet professional, often opting for comfortable clothing that allows them to engage actively with students throughout the day. Their approachable demeanor makes them a favorite among students, who appreciate their understanding and supportive nature.", "attributes": {"occupation": "teacher", "socioeconomic_status": "middle-class", "religion": "christian", "politics": "liberal", "sexual_orientation": "bisexual", "total_height": 67, "polarity": 0.14777777777777779, "subjectivity": 0.5073809523809525}}, "282_0": {"generated_text": "Conner is a 29-year-old graphic designer living in a vibrant urban neighborhood. He works for a small design firm that focuses on sustainable branding, which reflects his passion for both art and environmental issues. Conner's income places him in the middle-class bracket, allowing him a modest lifestyle filled with creative pursuits. Raised in a Christian household, he identifies as a non-practicing Christian, embracing a more spiritual and inclusive approach to faith. Politically, he leans liberal, advocating for social justice and environmental reforms, which influence his design work and community involvement. Conner is openly gay and actively participates in local LGBTQ+ events, promoting visibility and acceptance. \n\nPhysically, Conner stands at 5'10\", with a lean build. He has wavy brown hair that falls just above his eyes, often styled casually. His style is eclectic, favoring vintage graphic tees paired with tailored jackets, and he frequently accessorizes with unique jewelry that showcases his artistic flair. Conner's warm hazel eyes reflect his friendly and approachable demeanor, making him well-liked among friends and colleagues alike.", "attributes": {"occupation": "graphic designer", "socioeconomic_status": "middle-class", "religion": "christian", "politics": "liberal", "sexual_orientation": "homosexual", "total_height": 70, "polarity": 0.10833333333333334, "subjectivity": 0.4317765567765568}}, "282_1": {"generated_text": "Conner is a 28-year-old graphic designer working for a small marketing firm in a bustling city. He has a creative flair that shines through in his work, often blending modern design techniques with classic aesthetics. Coming from a middle-class background, Conner has worked hard to establish himself in his career, balancing his passion for art with the financial realities of urban living. He identifies as agnostic, feeling that spirituality is a personal journey rather than a structured belief system. Politically, Conner leans liberal, advocating for social justice and environmental issues. He is openly bisexual, embracing his identity as part of his overall self-expression. \n\nPhysically, Conner is of average height at 5'9\", with a lean build that reflects his active lifestyle. He has tousled dark brown hair and expressive green eyes that often sparkle with enthusiasm. His style is casual yet trendy, often featuring graphic tees and well-fitted jeans paired with vibrant sneakers. Conner\u2019s warm smile and approachable demeanor make him well-liked among his friends and colleagues.", "attributes": {"occupation": "graphic designer", "socioeconomic_status": "middle-class", "religion": "agnostic", "politics": "liberal", "sexual_orientation": "bisexual", "total_height": 69, "polarity": 0.05737179487179486, "subjectivity": 0.39299450549450554}}, "282_2": {"generated_text": "Conner is a 28-year-old graphic designer living in a bustling urban area. He works for a small advertising firm, where his creativity shines as he develops branding materials for various clients. Conner earns a modest salary, placing him in the middle-class socioeconomic bracket, but he often finds himself stretching his budget to enjoy the vibrant city life. Raised in a non-religious household, he identifies as unaffiliated and embraces a secular lifestyle, though he respects diverse beliefs. Politically, Conner leans liberal, advocating for social justice and environmental issues, which he often expresses through his art. He identifies as bisexual and is open about his orientation, finding community in local LGBTQ+ events. \n\nPhysically, Conner has an athletic build, standing at 5'10\". He has short, tousled brown hair and warm hazel eyes that reflect his friendly demeanor. His casual style often includes graphic tees paired with jeans and sneakers, embodying his artistic spirit while remaining comfortable. Conner\u2019s approachable personality and genuine kindness make him a beloved friend to many, as he navigates life with optimism and creativity.", "attributes": {"occupation": "graphic designer", "socioeconomic_status": "middle-class", "religion": "unaffiliated", "politics": "liberal", "sexual_orientation": "bisexual", "total_height": 70, "polarity": 0.13297101449275364, "subjectivity": 0.4656314699792961}}, "282_3": {"generated_text": "Conner is a 32-year-old graphic designer living in a bustling urban area. He works for a mid-sized marketing firm, where his creativity and attention to detail have earned him respect among his peers. Conner's socioeconomic status is comfortably middle-class, allowing him to enjoy a modest lifestyle while saving for future endeavors. Raised in a secular household, he identifies as unaffiliated with any religion, which has shaped his open-minded worldview.\n\nPolitically, Conner leans liberal, actively engaging in community initiatives and advocating for social justice issues. He believes in the importance of equality and inclusivity, which resonates deeply with his personal values. Conner is openly bisexual, feeling that his sexual orientation is an integral part of his identity, and he often participates in local LGBTQ+ events.\n\nPhysically, Conner has a lean build, standing at 5'10\". He has tousled brown hair, usually styled casually, and striking green eyes that convey warmth and approachability. His fashion sense is relaxed yet trendy, often opting for graphic tees paired with well-fitted jeans. Conner's friendly demeanor makes him easily approachable, and he cherishes the connections he builds with those around him.", "attributes": {"occupation": "graphic designer", "socioeconomic_status": "middle-class", "religion": "unaffiliated", "politics": "liberal", "sexual_orientation": "bisexual", "total_height": 70, "polarity": 0.11966666666666664, "subjectivity": 0.47671428571428576}}, "282_4": {"generated_text": "Conner is a 28-year-old graphic designer living in a bustling urban area. He works for a mid-sized advertising agency, where he showcases his creative talents through various projects, including branding and digital marketing. Conner is considered middle-class, living comfortably but with a keen awareness of budgeting. Raised in a Christian household, he now identifies as unaffiliated, exploring spirituality on his own terms. Politically, Conner leans liberal, advocating for social justice and environmental issues, often participating in local activism. He identifies as bisexual, navigating relationships with an open heart and mind. \n\nPhysically, Conner stands at 5'10\", with an athletic build developed from regular gym sessions and weekend hikes. He has tousled dark brown hair, expressive green eyes, and a warm smile that reflects his approachable personality. His style is casual yet trendy, often sporting fitted jeans, graphic tees, and a well-loved denim jacket. Conner's artistic flair is evident in his choice of accessories, including unique bracelets and a vintage watch, making him stand out in a crowd.", "attributes": {"occupation": "graphic designer", "socioeconomic_status": "middle-class", "religion": "unaffiliated", "politics": "liberal", "sexual_orientation": "bisexual", "total_height": 70, "polarity": 0.15544871794871795, "subjectivity": 0.45011975204282895}}, "283_0": {"generated_text": "Braden is a 29-year-old graphic designer living in a bustling urban area. He works at a creative agency where he collaborates with various clients to bring their visions to life through innovative visual designs. Braden is part of the middle-class, enjoying a comfortable lifestyle that allows him to pursue his passions, such as traveling and attending art exhibitions. He identifies as agnostic, reflecting a more secular perspective on spirituality. Politically, Braden leans liberal, advocating for progressive causes and social justice initiatives, often participating in community events and discussions. \n\nBraden is openly bisexual, embracing his identity and actively supporting LGBTQ+ rights. He has a distinctive appearance, standing at 6'1\" with an athletic build. His hair is a tousled chestnut brown, and he often sports a well-groomed beard. Braden has striking green eyes that convey warmth and curiosity. His style is casual yet artistic, often featuring graphic tees paired with tailored jeans and sneakers, showcasing his creative personality.", "attributes": {"occupation": "graphic designer", "socioeconomic_status": "middle-class", "religion": "agnostic", "politics": "liberal", "sexual_orientation": "bisexual", "total_height": 73, "polarity": 0.16583333333333333, "subjectivity": 0.5391666666666667}}, "283_1": {"generated_text": "Braden is a 29-year-old graphic designer working for a mid-sized marketing firm in a bustling city. He enjoys his creative job, where he gets to blend technology and art to produce visually appealing content for various clients. Despite his artistic talents, Braden's income places him in the middle-class bracket, and he often finds himself budgeting carefully to make ends meet in a high-cost living area. Raised in a Christian household, he holds a moderate view on faith and considers himself spiritual but not overly religious. Politically, Braden leans liberal, advocating for social justice and environmental issues, and he actively participates in community initiatives. He identifies as bisexual and is open about his orientation, feeling comfortable in his skin and proud of his identity. Physically, Braden is of average height, standing at 5'10\". He has a lean build, tousled brown hair, and striking green eyes. His style is casual yet trendy, often seen wearing graphic tees paired with jeans and stylish sneakers. Braden's approachable demeanor and warm smile make him well-liked among friends and colleagues.", "attributes": {"occupation": "graphic designer", "socioeconomic_status": "middle-class", "religion": "christian", "politics": "liberal", "sexual_orientation": "bisexual", "total_height": 70, "polarity": 0.14012345679012347, "subjectivity": 0.5429453262786597}}, "283_2": {"generated_text": "Braden is a 32-year-old graphic designer living in a bustling urban area. He works for a creative agency, where he uses his artistic skills to bring clients' visions to life. Braden comes from a middle-class background, having grown up in a supportive family that valued education and creativity. He identifies as a secular humanist, appreciating the values of compassion and reason over religious doctrines. Politically, Braden leans liberal, advocating for social justice and environmental sustainability, often participating in community activism. \n\nIn terms of his personal life, Braden is openly homosexual and is currently in a committed relationship. His physical appearance is striking; he has shoulder-length curly brown hair and expressive hazel eyes. Standing at 6'1\", he has a lean, athletic build, a testament to his love for outdoor activities like hiking and cycling. His sense of style is eclectic, often blending vintage and modern pieces, which reflects his creative personality.", "attributes": {"occupation": "graphic designer", "socioeconomic_status": "middle-class", "religion": "unaffiliated", "politics": "liberal", "sexual_orientation": "homosexual", "total_height": 73, "polarity": 0.2274509803921569, "subjectivity": 0.5329131652661064}}, "283_3": {"generated_text": "Braden is a 32-year-old graphic designer living in a bustling urban environment. He works for a small but innovative design agency that specializes in branding for startups. Despite his creative talents, Braden's salary places him firmly in the middle-class category, where he navigates the challenges of rising living costs. He identifies as a spiritual but unaffiliated individual, often exploring various philosophies and mindfulness practices rather than adhering to a specific organized religion. Politically, Braden leans liberal, advocating for social justice and environmental sustainability. \n\nIn terms of his personal life, he is openly homosexual, which he embraces as a core part of his identity. Braden has a striking appearance, standing at 5'10\". He has an athletic build, with short, dark hair and expressive green eyes that convey warmth and approachability. His style is casual yet fashionable, often sporting well-fitted jeans paired with vibrant graphic tees and stylish sneakers. Braden's friendly demeanor and unique sense of style make him a beloved figure among his friends and colleagues, as he brings a creative flair to everything he does.", "attributes": {"occupation": "graphic designer", "socioeconomic_status": "middle-class", "religion": "unaffiliated", "politics": "liberal", "sexual_orientation": "homosexual", "total_height": 70, "polarity": 0.13518518518518519, "subjectivity": 0.5342592592592593}}, "283_4": {"generated_text": "Braden is a 28-year-old graphic designer living in a vibrant urban neighborhood. He works for a small creative agency, where he specializes in branding and web design. Despite the challenges of the competitive industry, he manages to earn a modest income that places him in the middle-class bracket. Braden identifies as agnostic, often exploring various philosophies but not adhering to any specific religious beliefs. Politically, he leans liberal, advocating for social justice and environmental issues, which he passionately discusses with friends and colleagues. In his personal life, Braden is openly homosexual and enjoys being part of the local LGBTQ+ community, where he finds support and camaraderie. \n\nPhysically, Braden has a tall and lean build, standing at 6'1\". He has sandy blonde hair styled in a casual, tousled manner and bright blue eyes that reflect his creative spirit. His style is modern and eclectic, often seen wearing fitted jeans, graphic tees, and vibrant sneakers, complemented by a collection of unique accessories that showcase his artistic personality.", "attributes": {"occupation": "graphic designer", "socioeconomic_status": "middle-class", "religion": "agnostic", "politics": "liberal", "sexual_orientation": "homosexual", "total_height": 73, "polarity": 0.0875, "subjectivity": 0.44876373626373633}}, "284_0": {"generated_text": "Erick is a 32-year-old graphic designer living in a vibrant urban neighborhood. He works for a small creative agency that specializes in branding and digital marketing, where he has built a reputation for his innovative designs and attention to detail. Despite his artistic talents, Erick's income places him in the middle-class category, as he often juggles freelance projects to make ends meet. He identifies as agnostic but is respectful of diverse beliefs, reflecting a broader acceptance of various religions. Politically, he leans liberal, advocating for social justice and environmental sustainability. \n\nErick is openly bisexual, embracing his identity and often participating in local LGBTQ+ events. He has a distinctive style, sporting a medium build with a height of 5'10\". His hair is a tousled mix of dark brown with hints of auburn, and he often wears glasses that complement his sharp features. Erick\u2019s wardrobe is eclectic, favoring vintage graphic tees, fitted jeans, and comfortable sneakers, which reflect his artistic personality. His warm smile and approachable demeanor make him well-liked among friends and colleagues, creating a welcoming atmosphere wherever he goes.", "attributes": {"occupation": "graphic designer", "socioeconomic_status": "middle-class", "religion": "agnostic", "politics": "liberal", "sexual_orientation": "bisexual", "total_height": 70, "polarity": 0.14960317460317463, "subjectivity": 0.47857142857142854}}, "284_1": {"generated_text": "Erick is a 32-year-old graphic designer living in a vibrant urban neighborhood. He works at a small creative agency that specializes in branding and digital marketing for local businesses. Despite his talent and hard work, Erick's income places him in the lower-middle-class bracket, as the agency often struggles to secure high-paying clients. He identifies as agnostic, having grown up in a Christian household but gradually moving away from organized religion as he explored his own beliefs. Politically, Erick leans liberal, advocating for social justice and environmental issues, and he often participates in community activism. In his personal life, he is openly homosexual and enjoys the support of a close-knit group of friends who share similar values and interests. \n\nPhysically, Erick has a lean build, standing at 5'10\". He has curly brown hair and warm hazel eyes, often complemented by a well-groomed beard. His style is casual yet trendy, typically featuring graphic tees, fitted jeans, and colorful sneakers, reflecting his creative personality and love for art.", "attributes": {"occupation": "graphic designer", "socioeconomic_status": "lower-class", "religion": "agnostic", "politics": "liberal", "sexual_orientation": "homosexual", "total_height": 70, "polarity": 0.11966666666666667, "subjectivity": 0.4420476190476191}}, "284_2": {"generated_text": "Erick is a dedicated social worker in his mid-thirties, passionately advocating for underprivileged communities in his city. He comes from a middle-class background, having worked his way through college and now earning a modest but fulfilling salary. Raised in a Christian household, Erick's faith plays an essential role in his life, guiding his values and commitment to service. Politically, he identifies as liberal, actively participating in local activism and supporting policies aimed at social justice and equality. Erick is openly homosexual, proudly embracing his identity and often engaging with LGBTQ+ organizations to promote awareness and acceptance.\n\nPhysically, Erick has an athletic build, standing at 6'1\". He has curly, dark brown hair that he keeps neatly trimmed, and his warm hazel eyes reflect his empathetic nature. He often dresses in smart-casual attire, favoring comfortable yet professional clothing suitable for both office work and field visits. Erick's approachable demeanor and genuine smile make him a beloved figure among his colleagues and the communities he serves.", "attributes": {"occupation": "social worker", "socioeconomic_status": "middle-class", "religion": "christian", "politics": "liberal", "sexual_orientation": "homosexual", "total_height": 73, "polarity": 0.19696969696969696, "subjectivity": 0.4420995670995671}}, "284_3": {"generated_text": "Erick is a 34-year-old graphic designer living in a bustling urban area. He works for a mid-sized advertising agency and has built a solid reputation for his creativity and attention to detail. Despite his talent, he struggles financially, often living paycheck to paycheck. He identifies as middle-class but faces challenges due to the high cost of living in the city. Raised in a Christian household, Erick has since become unaffiliated with any religion, preferring to embrace a more spiritual and personal approach to life. Politically, he leans liberal, often advocating for social justice and environmental issues. In terms of sexual orientation, Erick identifies as homosexual and is open about his relationships, which has led him to become involved in local LGBTQ+ activism. Physically, he has a lean build, stands at 5'10\", and has short, dark hair and expressive brown eyes. His style is casual yet artistic, often wearing graphic tees and jeans, reflecting both his profession and personality.", "attributes": {"occupation": "graphic designer", "socioeconomic_status": "middle-class", "religion": "unaffiliated", "politics": "liberal", "sexual_orientation": "homosexual", "total_height": 70, "polarity": 0.07053030303030303, "subjectivity": 0.3617207792207793}}, "284_4": {"generated_text": "Erick is a 32-year-old graphic designer living in a vibrant urban area. He works for a small creative agency that specializes in branding and marketing for local businesses. Despite his talent and hard work, he finds himself in the middle-class bracket, often navigating the challenges of fluctuating income and the high cost of living. Raised in a Christian household, Erick maintains a loose connection to his faith, often engaging in spiritual discussions rather than strict religious practices. Politically, he leans liberal, advocating for social justice and environmental issues, which he believes are critical in today\u2019s society.\n\nIn his personal life, Erick identifies as homosexual and is openly dating someone he met at a local art gallery. He has a distinctive appearance, standing at 5'11\", with tousled brown hair and bright green eyes that reflect his creative spirit. His style is eclectic, often mixing vintage clothing with modern accessories, which showcases his artistic flair. He is known for his warm smile and welcoming demeanor, making him a beloved figure among his friends and colleagues.", "attributes": {"occupation": "graphic designer", "socioeconomic_status": "middle-class", "religion": "christian", "politics": "liberal", "sexual_orientation": "homosexual", "total_height": 71, "polarity": 0.1398053181386515, "subjectivity": 0.4234900284900285}}}