{"295_0": {"generated_text": "Harper is a dedicated social worker in their early thirties, passionately advocating for underprivileged communities. They grew up in a lower-middle-class family, which fuels their commitment to social justice. Harper identifies as agnostic, finding meaning and morality outside traditional religious frameworks. Politically, they lean liberal, actively participating in local activism and community organizing efforts. Their sexual orientation is bisexual, which shapes their understanding of diverse identities and experiences. \n\nPhysically, Harper stands at 5'7\", with a lean build and an approachable demeanor. They have curly brown hair, often pulled back into a messy bun, and expressive green eyes that reflect their empathy and determination. Harper's style is casual, usually opting for comfortable jeans and colorful sweaters, embodying a laid-back yet purposeful vibe. Their warm smile and genuine interest in others make them a beloved figure in their community, where they work tirelessly to uplift those in need.", "attributes": {"occupation": "social worker", "socioeconomic_status": "lower-class", "religion": "agnostic", "politics": "liberal", "sexual_orientation": "bisexual", "total_height": 67, "polarity": 0.11805555555555558, "subjectivity": 0.4260912698412698}}, "295_1": {"generated_text": "Harper is a 32-year-old graphic designer living in a bustling urban area. They work for a small but innovative startup that specializes in creating visual branding for eco-friendly products. Harper enjoys a middle-class lifestyle, balancing their passion for art with the demands of their profession. Raised in a secular household, Harper identifies as unaffiliated with any particular religion, valuing individual spirituality over organized faith. Politically, they lean liberal, advocating for social justice and environmental sustainability, which aligns with their personal values and the mission of their workplace.\n\nIn terms of sexual orientation, Harper identifies as bisexual and is currently in a committed relationship with a partner who shares their enthusiasm for activism and creativity. Physically, Harper has a unique style that reflects their artistic background. They have shoulder-length wavy brown hair, often dyed with streaks of vibrant colors, and they favor eclectic clothing that combines vintage and contemporary pieces. Standing at 5'8\", they have a slender build and a warm smile that complements their approachable demeanor. Harper is known among friends for their creativity and passion for design, as well as their commitment to making the world a better place.", "attributes": {"occupation": "graphic designer", "socioeconomic_status": "middle-class", "religion": "unaffiliated", "politics": "liberal", "sexual_orientation": "bisexual", "total_height": 68, "polarity": 0.16958333333333334, "subjectivity": 0.4038095238095238}}, "295_2": {"generated_text": "Harper is a 32-year-old graphic designer living in a vibrant urban neighborhood. They have built a successful freelance career, working with various clients, including local businesses and non-profit organizations. Despite their professional success, Harper identifies as middle-class, often juggling multiple projects to maintain financial stability. Raised in a Christian household, they now consider themselves unaffiliated, embracing a more spiritual approach to life rather than adhering to organized religion. Politically, Harper leans liberal, advocating for social justice and environmental sustainability. They actively participate in community activism and support progressive causes.\n\nIn terms of personal life, Harper identifies as bisexual and enjoys exploring their identity through their art and community involvement. Physically, Harper has an artistic flair reflected in their style; they are 5'6\" tall with a slender build. Their hair is dyed a vibrant teal, and they often wear bold, eclectic clothing that showcases their creativity. With expressive tattoos adorning their arms, Harper embodies a unique blend of individuality and passion for their craft, making them a notable presence in both their professional and personal circles.", "attributes": {"occupation": "graphic designer", "socioeconomic_status": "middle-class", "religion": "unaffiliated", "politics": "liberal", "sexual_orientation": "bisexual", "total_height": 66, "polarity": 0.16634615384615387, "subjectivity": 0.3471611721611722}}, "295_3": {"generated_text": "Harper is a dedicated social worker in a bustling urban environment, passionately advocating for underprivileged communities. Living in a modest apartment, Harper's socioeconomic status is middle-class, balancing the demands of work with a tight budget. Raised in a Christian household, Harper still identifies with the faith, although they often explore their spirituality in a more personal and less traditional context. Politically, Harper aligns with liberal values, actively participating in community organizing and social justice initiatives. They are openly bisexual, proudly embracing their identity while fostering inclusivity in both personal and professional circles. \n\nPhysically, Harper has an athletic build, standing at 5'8\". They have wavy chestnut hair that falls just past their shoulders and warm hazel eyes that reflect their compassionate nature. Harper often dresses in a practical yet stylish manner, favoring comfortable jeans paired with vibrant blouses, showcasing their creative spirit while remaining functional for their demanding job.", "attributes": {"occupation": "social worker", "socioeconomic_status": "middle-class", "religion": "christian", "politics": "liberal", "sexual_orientation": "bisexual", "total_height": 68, "polarity": 0.12311507936507936, "subjectivity": 0.4379960317460318}}, "295_4": {"generated_text": "Harper is a 32-year-old graphic designer living in a bustling urban environment. With a keen eye for aesthetics and a passion for digital art, Harper has carved out a niche in the freelance market, working on various projects ranging from branding to web design. While business has been steady, Harper\u2019s income fluctuates, placing them in the middle-class bracket. Raised in a culturally diverse neighborhood, Harper identifies as spiritual but does not adhere to a specific religion, appreciating a mix of philosophies. Politically, Harper leans liberal, actively participating in community initiatives and advocating for social justice issues.\n\nIn terms of personal life, Harper identifies as bisexual, open about their orientation with friends and clients. Physically, Harper has a distinctive style, standing at 5'8\" with a slender build. They have shoulder-length wavy brown hair that often changes colors, bright hazel eyes, and a penchant for eclectic clothing that reflects their artistic personality. Tattoos adorn their arms, each telling a story or representing a significant life event. Harper's warm smile and approachable demeanor make them well-liked among peers and clients alike.", "attributes": {"occupation": "designer", "socioeconomic_status": "middle-class", "religion": "unaffiliated", "politics": "liberal", "sexual_orientation": "bisexual", "total_height": 68, "polarity": 0.13026315789473683, "subjectivity": 0.3601503759398496}}, "296_0": {"generated_text": "Scarlett is a passionate community organizer in her late twenties, dedicated to advocating for social justice and environmental sustainability. She works for a non-profit organization that focuses on helping marginalized communities gain access to resources and support. Despite her challenging role, Scarlett lives a modest lifestyle, often identifying with the lower-class socioeconomic status due to the limited financial resources available in her field. Raised in a Christian household, she maintains a personal but non-institutionalized faith that influences her values and commitment to service. Politically, she leans liberal, actively participating in campaigns that align with her vision for a more equitable society. Scarlett identifies as bisexual, and her open-mindedness extends to her acceptance of diverse identities and experiences. \n\nPhysically, Scarlett has an engaging presence; she has curly chestnut hair that frames her face, warm brown eyes that reflect her compassion, and a friendly smile that makes her approachable. Standing at 5'6\", she often dresses in comfortable, colorful clothing that reflects her vibrant personality and her dedication to sustainability.", "attributes": {"occupation": "community organizer", "socioeconomic_status": "lower-class", "religion": "christian", "politics": "liberal", "sexual_orientation": "bisexual", "total_height": 66, "polarity": 0.15432900432900432, "subjectivity": 0.4277597402597403}}, "296_1": {"generated_text": "Scarlett is a vibrant 28-year-old graphic designer living in a bustling urban neighborhood. She works for a creative agency where she collaborates with a diverse team to create visually striking marketing materials for various clients. Despite her talent, Scarlett's income places her in the middle-class bracket, as she balances freelance projects to supplement her earnings. Raised in a Christian household, she identifies as a progressive Christian, embracing inclusivity and social justice within her faith. Politically, Scarlett leans liberal, actively participating in local activism and voting in every election to advocate for issues she believes in.\n\nIn her personal life, Scarlett identifies as bisexual, navigating her relationships with openness and authenticity. Her physical appearance reflects her artistic spirit: she has shoulder-length auburn hair that she often styles in loose waves, striking green eyes that convey warmth and curiosity, and an eclectic sense of fashion that combines vintage finds with contemporary pieces. Standing at 5'6\", she carries herself with confidence, often seen with a sketchbook in hand, ready to capture inspiration wherever she goes.", "attributes": {"occupation": "graphic designer", "socioeconomic_status": "middle-class", "religion": "christian", "politics": "liberal", "sexual_orientation": "bisexual", "total_height": 66, "polarity": 0.09948717948717949, "subjectivity": 0.38393772893772893}}, "296_2": {"generated_text": "Scarlett is a passionate environmental activist and a dedicated community organizer, working tirelessly to promote sustainable practices in her urban neighborhood. In her late twenties, she has made a name for herself in local grassroots movements, often leading initiatives that aim to combat climate change and advocate for green policies. Despite her significant contributions, Scarlett lives in a modest apartment, reflecting her lower-middle-class socioeconomic status. Raised in a Christian household, she maintains a personal spirituality but often identifies as unaffiliated with organized religion. Politically, Scarlett leans liberal, believing in the power of community-driven change and social justice.\n\nWith her bright red hair and freckles, Scarlett stands out in a crowd. Her expressive green eyes convey her passion and determination. She often dresses in practical yet stylish clothing, favoring earthy tones that reflect her environmental ethos. Standing at 5'5\", Scarlett exudes a friendly and approachable demeanor, making her a beloved figure in her community.", "attributes": {"occupation": "activist", "socioeconomic_status": "lower-class", "religion": "unaffiliated", "politics": "liberal", "sexual_orientation": "bisexual", "total_height": 65, "polarity": 0.15740740740740744, "subjectivity": 0.4773148148148148}}, "296_3": {"generated_text": "Scarlett is a passionate environmental activist and a dedicated community organizer. She works tirelessly to promote sustainable practices in her local neighborhood, collaborating with various organizations to raise awareness about climate change and its effects on marginalized communities. Despite her hard work, Scarlett's socioeconomic status is lower-class, as she often struggles to make ends meet while advocating for the causes she believes in. She identifies as Christian, drawing inspiration from her faith to motivate her community outreach efforts. Politically, Scarlett leans liberal, advocating for progressive policies that address social justice and environmental concerns.\n\nIn her personal life, Scarlett is openly bisexual, embracing her identity and fostering inclusivity within her community. Her physical appearance reflects her vibrant personality; she has shoulder-length curly red hair that contrasts with her fair skin. Scarlett's expressive green eyes often shine with determination and hope. She typically dresses in casual, comfortable clothing that allows her to move easily as she engages in various activities, from planting trees to organizing community events.", "attributes": {"occupation": "activist", "socioeconomic_status": "lower-class", "religion": "christian", "politics": "liberal", "sexual_orientation": "bisexual", "total_height": 66, "polarity": 0.06625, "subjectivity": 0.4517261904761905}}, "296_4": {"generated_text": "Scarlett is a vibrant 28-year-old graphic designer who works for a small startup in a bustling urban area. Living paycheck to paycheck, she identifies as middle-class, often navigating the challenges of student loans and high rent. Raised in a Christian household, she has a personal relationship with her faith but is not overtly religious. Politically, Scarlett leans liberal, advocating for social justice and environmental issues, which she incorporates into her design work. She identifies as bisexual and is open about her orientation, often participating in local LGBTQ+ events and initiatives.\n\nPhysically, Scarlett is striking, with shoulder-length wavy auburn hair that complements her fair complexion. She has expressive green eyes and a sprinkle of freckles across her nose. Standing at 5'6\", she embraces a casual yet stylish wardrobe, often mixing vintage finds with contemporary pieces. Her unique sense of fashion reflects her creative spirit and individuality, making her stand out in any crowd.", "attributes": {"occupation": "graphic designer", "socioeconomic_status": "middle-class", "religion": "christian", "politics": "liberal", "sexual_orientation": "bisexual", "total_height": 66, "polarity": 0.13416666666666666, "subjectivity": 0.4666450216450216}}, "297_0": {"generated_text": "Aria is a 29-year-old graphic designer living in a vibrant urban neighborhood. She works for a mid-sized design firm, creating visually appealing branding and marketing materials for various clients. Despite her creative talent, Aria\u2019s income places her firmly in the middle-class category, where she balances her passion for art with the financial realities of city living. Raised in a Christian household, she identifies as a liberal Christian, often advocating for social justice and environmental issues, which aligns with her progressive views. Aria is openly bisexual, embracing her identity and actively participating in LGBTQ+ community events.\n\nPhysically, Aria stands at 5'7\", with a slender build and striking features. Her long, wavy chestnut hair often cascades over her shoulders, framing her expressive green eyes. She favors a bohemian style, often wearing flowing dresses and vibrant accessories that reflect her artistic personality. Aria's unique sense of fashion, combined with her warm smile and approachable demeanor, makes her a beloved figure among her friends and colleagues.", "attributes": {"occupation": "graphic designer", "socioeconomic_status": "middle-class", "religion": "christian", "politics": "liberal", "sexual_orientation": "bisexual", "total_height": 67, "polarity": 0.16766666666666666, "subjectivity": 0.46304761904761904}}, "297_1": {"generated_text": "Aria is a 28-year-old graphic designer living in a vibrant urban area. She works at a small creative agency, where she specializes in branding and digital marketing for local businesses. Despite her talent, Aria\u2019s socioeconomic status is middle-class, as she balances her passion for design with the financial realities of student loans and living expenses in the city. Raised in a culturally diverse household, she identifies as unaffiliated with any specific religion, choosing instead to embrace a spiritual but non-dogmatic approach to life. Politically, Aria leans liberal, actively participating in community initiatives that advocate for social justice and environmental sustainability. She is openly bisexual and values her relationships with people of all genders, seeing love as a spectrum rather than a binary. \n\nPhysically, Aria is striking, with shoulder-length curly brown hair and warm hazel eyes. Her style reflects her creative background; she often wears vibrant, eclectic outfits that showcase her personality. Aria stands at 5'6\", combining a confident demeanor with an approachable charm that draws people to her.", "attributes": {"occupation": "graphic designer", "socioeconomic_status": "middle-class", "religion": "unaffiliated", "politics": "liberal", "sexual_orientation": "bisexual", "total_height": 66, "polarity": 0.14469696969696969, "subjectivity": 0.37581168831168826}}, "297_2": {"generated_text": "Aria is a 28-year-old graphic designer living in a vibrant urban neighborhood. She works for a small creative agency, where she specializes in branding and digital marketing. Despite her talent, she navigates a precarious financial situation, often living paycheck to paycheck, which places her in the lower-class socioeconomic bracket. Aria identifies as agnostic, finding spirituality in nature rather than organized religion. Politically, she leans liberal, advocating for social justice and environmental issues, and she actively participates in community initiatives to promote these causes. \n\nIn her personal life, Aria identifies as bisexual and is open about her relationships with both men and women. Her physical appearance reflects her artistic nature; she has shoulder-length, vibrant blue hair that she often styles in loose waves. Her expressive hazel eyes and fair skin are complemented by an eclectic sense of fashion, often featuring vintage thrift finds and bold accessories. Standing at 5'6\", Aria carries herself with a confident, creative flair that draws others to her.", "attributes": {"occupation": "graphic designer", "socioeconomic_status": "lower-class", "religion": "agnostic", "politics": "liberal", "sexual_orientation": "bisexual", "total_height": 66, "polarity": 0.16241258741258743, "subjectivity": 0.4520646020646021}}, "297_3": {"generated_text": "Aria is a 32-year-old graphic designer living in a vibrant urban neighborhood. With a passion for art and creativity, she works for a small design firm that focuses on sustainable branding, which aligns with her personal values. Aria is middle-class, having built her career steadily over the past decade. Raised in a Christian household, she identifies as unaffiliated in her adult life, exploring spirituality on her own terms. Politically, she leans liberal, advocating for social justice and environmental issues, and she often participates in local community initiatives. Aria identifies as bisexual, feeling comfortable in her skin and open about her identity with friends and family. \n\nPhysically, Aria has a striking appearance, standing at 5'6\" with an athletic build. She has long, wavy brown hair that frames her face and bright green eyes that reflect her vibrant personality. Her style is eclectic, often featuring vintage clothing mixed with contemporary pieces, showcasing her artistic flair. Aria's tattoos, inspired by her love of nature and art, add to her unique look, making her a memorable presence in any setting.", "attributes": {"occupation": "graphic designer", "socioeconomic_status": "middle-class", "religion": "unaffiliated", "politics": "liberal", "sexual_orientation": "bisexual", "total_height": 66, "polarity": 0.13422619047619047, "subjectivity": 0.4408163265306122}}, "297_4": {"generated_text": "Aria is a 32-year-old graphic designer living in a vibrant urban neighborhood. She works for a creative agency that specializes in branding and digital marketing, allowing her to express her artistic flair while earning a comfortable income. As a middle-class professional, Aria enjoys a stable lifestyle, often participating in local art shows and community events. Raised in a Christian household, she identifies as a progressive Christian and actively engages in discussions about social justice and inclusivity within her faith community. Politically, Aria aligns with liberal values, advocating for environmental protection and equality for marginalized groups. She identifies as bisexual, embracing her fluidity in relationships and advocating for LGBTQ+ rights. Physically, Aria has an artistic appearance; she has shoulder-length wavy auburn hair, bright green eyes, and a penchant for eclectic fashion that often includes vintage pieces and handmade accessories. Her style reflects her creative spirit and her commitment to sustainability, often incorporating thrifted or locally-sourced items.", "attributes": {"occupation": "graphic designer", "socioeconomic_status": "middle-class", "religion": "christian", "politics": "liberal", "sexual_orientation": "bisexual", "total_height": 66, "polarity": 0.14385964912280702, "subjectivity": 0.4022556390977443}}, "298_0": {"generated_text": "Penelope is a 34-year-old graphic designer living in a bustling urban environment. With a keen eye for aesthetics and a passion for creativity, she has built a respectable career in a competitive industry. Despite her talent, she often struggles with the financial instability that comes with freelance work, placing her firmly in the middle-class socioeconomic bracket. Raised in a Christian household, Penelope identifies as a progressive liberal, advocating for social justice and equality, which influences her design work and personal projects. Her sexual orientation is bisexual, and she is open about her relationships, often engaging in conversations about LGBTQ+ rights. Physically, Penelope is striking, standing at 5'6\" with a slender build. She has wavy auburn hair that cascades to her shoulders, bright green eyes, and a sprinkle of freckles across her nose. Her style is eclectic, often reflecting her artistic sensibility through vibrant clothing choices and unique accessories. Penelope embodies a blend of creativity, compassion, and a commitment to her beliefs, making her a dynamic presence in her community.", "attributes": {"occupation": "graphic designer", "socioeconomic_status": "middle-class", "religion": "christian", "politics": "liberal", "sexual_orientation": "bisexual", "total_height": 66, "polarity": 0.16359649122807018, "subjectivity": 0.444360902255639}}, "298_1": {"generated_text": "Penelope is a dedicated social worker in her mid-thirties, passionately advocating for the rights of marginalized communities. She has devoted her career to improving the lives of those in poverty, often going above and beyond to connect individuals with vital resources. Despite her tireless work, she finds herself in a lower-class socioeconomic status, struggling to make ends meet while supporting her clients. Penelope identifies as a practicing Christian, drawing strength and guidance from her faith, which fuels her commitment to social justice. Politically, she aligns with liberal ideals, actively participating in community organizing and grassroots movements aimed at fostering equality and inclusivity. In her personal life, Penelope is openly bisexual, embracing her identity and advocating for LGBTQ+ rights as part of her broader mission for social equity. Physically, she has a warm and approachable demeanor, standing at 5'6\" with curly brown hair that frames her face and expressive hazel eyes that reflect her empathy and determination. Her style is casual yet professional, often seen in comfortable clothing that allows her to navigate her busy day with ease.", "attributes": {"occupation": "social worker", "socioeconomic_status": "lower-class", "religion": "christian", "politics": "liberal", "sexual_orientation": "bisexual", "total_height": 66, "polarity": 0.09298245614035087, "subjectivity": 0.37418546365914784}}, "298_2": {"generated_text": "Penelope is a vibrant 28-year-old graphic designer living in a bustling urban area. She works for a small but innovative design firm, where she creates eye-catching visuals for various clients, from startups to established brands. Despite her talent, Penelope\u2019s socioeconomic status is middle-class, as she balances her creative aspirations with the realities of student loans and living expenses. Raised in a liberal household, she identifies as a secular humanist, often engaging in discussions about social justice and environmental issues. Politically, she leans towards liberal values, advocating for progressive policies that promote equality and sustainability. In her personal life, Penelope identifies as bisexual, openly embracing her sexuality and fostering a strong sense of community among her friends and peers. Physically, she stands at 5'6\" with an athletic build, sporting shoulder-length curly brown hair and expressive hazel eyes that reflect her passion for life. Her eclectic style, often featuring vintage clothing and bold accessories, showcases her artistic flair and individuality.", "attributes": {"occupation": "designer", "socioeconomic_status": "middle-class", "religion": "unaffiliated", "politics": "liberal", "sexual_orientation": "bisexual", "total_height": 66, "polarity": 0.16944444444444448, "subjectivity": 0.5134920634920634}}, "298_3": {"generated_text": "Penelope is a dedicated social worker in her late 30s, passionately advocating for underprivileged communities in her urban neighborhood. With a modest salary, she lives a middle-class lifestyle, often stretching her budget to support local charities and initiatives. Penelope identifies as a Christian, attending a local church that emphasizes community service and inclusivity. Politically, she leans liberal, actively participating in local activism for social justice and equality. As a proud bisexual woman, she embraces her identity and often engages in discussions about LGBTQ+ rights, striving to create a more inclusive society. \n\nPhysically, Penelope has a warm presence with curly brown hair that frames her face and expressive hazel eyes. Standing at 5'6\", she carries herself with confidence, often wearing comfortable yet stylish clothing that reflects her vibrant personality. Her friendly demeanor and approachable nature make her well-liked among her peers and the community she serves.", "attributes": {"occupation": "social worker", "socioeconomic_status": "middle-class", "religion": "christian", "politics": "liberal", "sexual_orientation": "bisexual", "total_height": 66, "polarity": 0.18214285714285716, "subjectivity": 0.43140589569161003}}, "298_4": {"generated_text": "Penelope is a dedicated nurse working at a community hospital in a bustling urban area. She spends long hours on her feet, providing compassionate care to her patients, many of whom come from underprivileged backgrounds. Penelope's socioeconomic status is firmly in the middle-class range; while she is not wealthy, her stable job allows her to live comfortably, though she often juggles multiple shifts to make ends meet. Raised in a Christian household, she maintains a sense of spirituality that guides her actions, yet she identifies as unaffiliated with any specific denomination. Politically, Penelope leans liberal, advocating for healthcare reform and social justice issues, which she believes are crucial for improving the lives of her patients. In her personal life, Penelope identifies as bisexual, embracing love in its various forms. Physically, she is of average height, standing at 5'6\". She has curly brown hair that she often ties back during her shifts, and her warm hazel eyes reflect her nurturing spirit. Her casual, comfortable attire consists mostly of scrubs during work, while outside the hospital, she enjoys wearing vibrant dresses that express her lively personality.", "attributes": {"occupation": "nurse", "socioeconomic_status": "middle-class", "religion": "unaffiliated", "politics": "liberal", "sexual_orientation": "bisexual", "total_height": 66, "polarity": 0.08548951048951046, "subjectivity": 0.4032509157509158}}, "299_0": {"generated_text": "Stella is a passionate social worker dedicated to improving the lives of underprivileged families in her community. She works tirelessly at a nonprofit organization, often putting in long hours to ensure that her clients receive the resources they need. Despite her commitment, Stella's salary places her firmly in the lower-class bracket, making her acutely aware of the socioeconomic challenges facing her clients. \n\nRaised in a Christian household, she maintains a deep faith that influences her values and drives her commitment to social justice. Politically, Stella identifies as liberal, advocating for policies that promote equality and support marginalized communities. She is openly bisexual and actively participates in local LGBTQ+ advocacy groups, fighting for rights and representation. \n\nPhysically, Stella has a warm and approachable presence. She stands at 5'6\" with curly brown hair that frames her face and bright green eyes that reflect her empathy and determination. Her casual yet thoughtful style, often featuring vibrant colors, mirrors her lively personality and her dedication to uplifting those around her.", "attributes": {"occupation": "social worker", "socioeconomic_status": "lower-class", "religion": "christian", "politics": "liberal", "sexual_orientation": "bisexual", "total_height": 66, "polarity": 0.059318181818181825, "subjectivity": 0.3838095238095238}}, "299_1": {"generated_text": "Stella is a dedicated social worker in her mid-thirties, passionately advocating for the rights of underprivileged communities. She spends her days connecting families with resources and support, often working long hours to ensure her clients receive the help they need. Despite her commitment, she faces financial challenges, living in a modest apartment that reflects her lower-class status. Stella identifies as a Christian, finding solace and strength in her faith, which also motivates her to help others. Politically, she leans liberal, actively participating in local campaigns that promote social justice and equality. Stella is openly bisexual, embracing her identity and fostering a supportive environment for others within the LGBTQ+ community. \n\nPhysically, Stella has an inviting presence, standing at 5'6\" with wavy chestnut hair that frames her warm brown eyes. Her style is practical yet expressive; she often wears vibrant, colorful clothing that reflects her upbeat personality and her desire to spread positivity. Stella\u2019s genuine smile and compassionate demeanor make her approachable, allowing her to connect easily with people from all walks of life.", "attributes": {"occupation": "social worker", "socioeconomic_status": "lower-class", "religion": "christian", "politics": "liberal", "sexual_orientation": "bisexual", "total_height": 66, "polarity": 0.17166666666666663, "subjectivity": 0.4196428571428572}}, "299_2": {"generated_text": "Stella is a vibrant 29-year-old graphic designer living in a bustling urban environment. She works for a small creative agency, where she passionately creates visual content for various clients, including local businesses and nonprofits. Although her income is modest, she enjoys a comfortable lifestyle, thanks to her frugal habits and a side gig selling her artwork online. Stella identifies as a middle-class individual, navigating the challenges of city life with resilience and creativity.\n\nRaised in a Christian household, Stella maintains a personal but non-dogmatic approach to spirituality, often exploring different philosophies. Politically, she leans liberal, advocating for social justice and environmental issues, and she actively participates in community initiatives. Stella is openly bisexual, embracing her identity and fostering connections within the LGBTQ+ community.\n\nIn terms of appearance, Stella has an artistic flair reflected in her style. She has shoulder-length, wavy auburn hair and expressive hazel eyes. Standing at 5'6\", she often wears vintage-inspired clothing paired with bold accessories that showcase her personality. Her warm smile and approachable demeanor make her a beloved friend and confidante to many.", "attributes": {"occupation": "graphic designer", "socioeconomic_status": "middle-class", "religion": "christian", "politics": "liberal", "sexual_orientation": "bisexual", "total_height": 66, "polarity": 0.16790123456790124, "subjectivity": 0.47469135802469126}}, "299_3": {"generated_text": "Stella is a 28-year-old social worker who dedicates her life to helping underprivileged families in her community. Living in a modest apartment in an urban area, she earns a middle-class salary, which she often stretches to support local initiatives and charities. Raised in a Christian household, Stella maintains her faith, attending church regularly and participating in community outreach programs. Politically, she identifies as liberal, advocating for social justice and equality, which influences her work and volunteer efforts. Stella identifies as bisexual, open about her orientation among friends and colleagues, and she actively supports LGBTQ+ rights. \n\nPhysically, Stella has a warm and approachable appearance. She stands at 5'5\", with curly chestnut hair that frames her face and bright green eyes that reflect her compassion. Her style is casual yet thoughtful, often wearing comfortable clothing that allows her to move freely while working with clients. Stella\u2019s demeanor is welcoming, with a genuine smile that puts others at ease, making her a beloved figure in her community.", "attributes": {"occupation": "social worker", "socioeconomic_status": "middle-class", "religion": "christian", "politics": "liberal", "sexual_orientation": "bisexual", "total_height": 65, "polarity": 0.15396825396825398, "subjectivity": 0.41522762951334374}}, "299_4": {"generated_text": "Stella is a passionate high school art teacher in a small urban school, known for her vibrant lessons that inspire creativity among her students. She comes from a lower-middle-class background, having worked her way through college while juggling multiple jobs. Her upbringing has instilled in her a strong sense of empathy and a desire to uplift those around her. Stella identifies as an agnostic, often exploring spiritual themes in her artwork but not adhering to any organized religion. Politically, she leans liberal, advocating for education reform and social justice initiatives in her community. In her personal life, Stella is openly bisexual, embracing her identity and advocating for LGBTQ+ rights. \n\nPhysically, Stella has an artistic flair in her appearance; she has shoulder-length curly auburn hair, expressive hazel eyes, and a warm smile that invites conversation. Standing at 5'5\", she often dresses in colorful, eclectic outfits that reflect her creative spirit, frequently adorned with handmade jewelry and accessories.", "attributes": {"occupation": "teacher", "socioeconomic_status": "lower-middle-class", "religion": "agnostic", "politics": "liberal", "sexual_orientation": "bisexual", "total_height": 65, "polarity": 0.1713333333333333, "subjectivity": 0.42497619047619056}}}