{"265_0": {"generated_text": "Tracy is a 32-year-old social worker living in a bustling urban area. Dedicated to helping others, Tracy works tirelessly to provide support and resources to underprivileged families in the community. Despite the challenges of their job, Tracy finds fulfillment in making a positive impact on the lives of those in need. Financially, Tracy is considered middle-class, managing to live comfortably but often feeling the strain of student loans and living expenses. \n\nRaised in a Christian household, Tracy still identifies with their faith, although they often question traditional interpretations. Politically, Tracy leans liberal, advocating for social justice and progressive policies that support marginalized groups. Tracy identifies as bisexual, feeling a strong connection to both male and female partners, and embraces their sexuality as part of their identity. \n\nPhysically, Tracy has a warm and approachable demeanor, standing at 5'6\". They have curly brown hair that falls just below their shoulders, and bright green eyes that reflect their passion for their work. Tracy's style is casual yet put-together, often wearing comfortable clothing that allows them to move easily throughout their busy day.", "attributes": {"occupation": "social worker", "socioeconomic_status": "middle-class", "religion": "christian", "politics": "liberal", "sexual_orientation": "bisexual", "total_height": 66, "polarity": 0.13318903318903322, "subjectivity": 0.403411667697382}}, "265_1": {"generated_text": "Tracy is a dedicated nurse working in a busy urban hospital, where they provide compassionate care to patients in need. With a strong work ethic and a passion for helping others, Tracy is often seen as a reliable figure among colleagues and patients alike. Living in a modest apartment, Tracy's socioeconomic status is middle-class, allowing for a comfortable but not extravagant lifestyle. They identify as agnostic, often exploring various philosophies and beliefs rather than adhering to a specific religion. Politically, Tracy leans liberal, advocating for social justice and healthcare reform, and actively participates in community initiatives. They are openly bisexual, embracing their identity and fostering inclusivity in their personal and professional life. Physically, Tracy has an athletic build, standing at 5'8\" with shoulder-length brown hair and warm brown eyes. Their style is practical, often opting for scrubs during work hours and casual, comfortable clothing outside of work.", "attributes": {"occupation": "nurse", "socioeconomic_status": "middle-class", "religion": "agnostic", "politics": "liberal", "sexual_orientation": "bisexual", "total_height": 68, "polarity": 0.08518518518518518, "subjectivity": 0.4158068783068783}}, "265_2": {"generated_text": "Tracy is a 32-year-old graphic designer living in a bustling urban area. They work for a small creative agency, where they specialize in branding and digital art, often collaborating with local businesses to enhance their visual identity. Despite their talent, Tracy's income places them in the middle-class bracket, where they often juggle freelance projects to make ends meet. Tracy identifies as agnostic, feeling a connection to spirituality but not aligning with any organized religion. Politically, they lean liberal, advocating for social justice and environmental issues, and often participate in community activism. In their personal life, Tracy is openly bisexual and values authentic connections, often attending LGBTQ+ events to foster a sense of community. Physically, Tracy has a unique style that reflects their artistic background: they have short, brightly dyed hair and a penchant for wearing vintage clothing. With an average height of 5'6\", their presence is often described as vibrant and approachable, characterized by their expressive tattoos that tell stories of their journey and interests.", "attributes": {"occupation": "graphic designer", "socioeconomic_status": "middle-class", "religion": "agnostic", "politics": "liberal", "sexual_orientation": "bisexual", "total_height": 66, "polarity": 0.15041666666666664, "subjectivity": 0.4246428571428572}}, "265_3": {"generated_text": "Tracy is a dedicated social worker in her early thirties, passionately advocating for underprivileged communities. She comes from a middle-class background and has worked hard to climb the professional ladder, often engaging in community outreach programs. Raised in a Christian household, Tracy maintains her faith, finding strength in her beliefs to support her clients. Politically, she leans liberal, advocating for social justice and equality, which aligns with her profession's values. Tracy identifies as bisexual, embracing her identity and often participating in LGBTQ+ advocacy events. \n\nPhysically, Tracy has an athletic build, standing at 5'6\". She has shoulder-length curly brown hair and warm hazel eyes that reflect her kindness. Tracy often wears casual, comfortable clothing, favoring earthy tones and practical shoes that allow her to move easily throughout her busy day. Her approachable demeanor and genuine smile make her well-liked among her colleagues and clients alike.", "attributes": {"occupation": "social worker", "socioeconomic_status": "middle-class", "religion": "christian", "politics": "liberal", "sexual_orientation": "bisexual", "total_height": 66, "polarity": 0.121078431372549, "subjectivity": 0.40399159663865547}}, "265_4": {"generated_text": "Tracy is a dedicated elementary school teacher in a small town, passionate about shaping young minds and fostering a love for learning. Living on a teacher's salary, Tracy is considered middle-class, often budgeting carefully to make ends meet. Raised in a Christian household, Tracy holds strong spiritual beliefs and actively participates in community church activities. Politically, Tracy leans liberal, advocating for educational reforms and social justice issues. In their personal life, Tracy identifies as bisexual, navigating a world that has become increasingly accepting but still presents challenges.\n\nPhysically, Tracy has a warm and approachable demeanor, standing at 5'6\". With shoulder-length wavy brown hair and expressive hazel eyes, Tracy often dresses in a casual yet professional style, favoring colorful blouses and comfortable shoes suitable for a busy day in the classroom. Their friendly smile and genuine interest in others make them well-liked among colleagues and students alike, creating a welcoming environment in both personal and professional settings.", "attributes": {"occupation": "teacher", "socioeconomic_status": "middle-class", "religion": "christian", "politics": "liberal", "sexual_orientation": "bisexual", "total_height": 66, "polarity": 0.16458333333333333, "subjectivity": 0.4568877551020409}}, "266_0": {"generated_text": "Stacy is a dedicated social worker in her mid-thirties, known for her passion for helping underserved communities. She works at a nonprofit organization that focuses on providing mental health services to low-income families. Despite her fulfilling job, Stacy struggles financially, making her part of the lower-class socioeconomic group. Raised in a Christian household, she continues to practice her faith, finding strength and guidance in her beliefs. Politically, Stacy identifies as liberal, advocating for social justice and equality. Her sexual orientation is bisexual, which she embraces openly within her circle of friends and colleagues. \n\nPhysically, Stacy is of average height, standing at 5'5\". She has curly chestnut hair that frames her face, complemented by warm brown eyes that reflect her compassionate nature. Stacy often dresses in a casual yet professional manner, favoring comfortable clothing that allows her to move easily while working with clients. Her warm smile and approachable demeanor make her well-liked among those she serves and her peers alike.", "attributes": {"occupation": "social worker", "socioeconomic_status": "lower-class", "religion": "christian", "politics": "liberal", "sexual_orientation": "bisexual", "total_height": 65, "polarity": 0.13235294117647056, "subjectivity": 0.365266106442577}}, "266_1": {"generated_text": "Stacy is a 32-year-old graphic designer living in a bustling urban area. She works for a mid-sized marketing agency, where she specializes in digital content creation. With a steady income, Stacy enjoys a comfortable middle-class lifestyle, allowing her to explore her passion for art and design. Raised in a Christian household, she identifies as a progressive Christian, often engaging in community service and social justice initiatives. Politically, Stacy leans liberal, advocating for environmental issues and equality rights. She is openly bisexual, embracing her identity and actively participating in LGBTQ+ events within her community.\n\nPhysically, Stacy has a vibrant presence. She stands at 5'6\" with an athletic build, thanks to her love for outdoor activities like hiking and yoga. Her long, wavy brown hair frames her face, and her hazel eyes often sparkle with enthusiasm. Stacy has a penchant for colorful clothing that reflects her artistic nature, frequently accessorizing with handmade jewelry that she collects from various local artisans. Her style is a blend of casual and chic, making her a standout in any crowd.", "attributes": {"occupation": "graphic designer", "socioeconomic_status": "middle-class", "religion": "christian", "politics": "liberal", "sexual_orientation": "bisexual", "total_height": 66, "polarity": 0.08333333333333334, "subjectivity": 0.3656314699792961}}, "266_2": {"generated_text": "Stacy is a 32-year-old graphic designer who works freelance, balancing multiple clients and projects. She lives in a modest apartment in a bustling urban neighborhood, which reflects her middle-class status. Growing up in a religious household, Stacy identifies as Christian, though she often finds herself questioning the strict doctrines she was raised with. Politically, she leans liberal, advocating for social justice and environmental sustainability, and often participates in local activism. Stacy is openly bisexual and values her relationships with both men and women, believing in love that transcends traditional boundaries.\n\nIn terms of physical appearance, Stacy has shoulder-length, wavy brown hair that she often ties up in a messy bun while working. Her green eyes are bright and expressive, often accentuated by a touch of eyeliner. She has a warm smile that reflects her approachable personality. Standing at 5'6\", she maintains a casual style, often wearing comfortable jeans and graphic tees paired with sneakers, embodying a laid-back yet creative vibe.", "attributes": {"occupation": "graphic designer", "socioeconomic_status": "middle-class", "religion": "christian", "politics": "liberal", "sexual_orientation": "bisexual", "total_height": 66, "polarity": 0.1318840579710145, "subjectivity": 0.4337474120082816}}, "266_3": {"generated_text": "Stacy is a 32-year-old graphic designer living in a vibrant urban area. She works for a small design firm that focuses on sustainable branding and eco-friendly products. Despite her creative talents, Stacy often finds herself struggling financially, making her part of the lower-class socioeconomic group. Raised in a Christian household, she has since adopted a more spiritual but unaffiliated approach to religion, seeking personal meaning rather than organized practices. Politically, Stacy leans liberal, advocating for environmental issues and social justice, and she actively participates in local community initiatives.\n\nIn terms of her sexual orientation, Stacy identifies as bisexual, which adds to her unique perspective on love and relationships. Physically, she is striking, standing at 5'6\" with an athletic build. Her long, wavy chestnut hair frames her heart-shaped face, and her bright green eyes are often accentuated by minimal makeup. Stacy's style is casual yet trendy, favoring comfortable clothing that reflects her artistic nature while also being mindful of sustainable fashion choices.", "attributes": {"occupation": "graphic designer", "socioeconomic_status": "lower-class", "religion": "unaffiliated", "politics": "liberal", "sexual_orientation": "bisexual", "total_height": 66, "polarity": 0.13125, "subjectivity": 0.4812925170068028}}, "266_4": {"generated_text": "Stacy is a dedicated nurse working in a bustling urban hospital, where she tends to patients with compassion and skill. Despite her demanding job, she often struggles to make ends meet, living in a modest apartment in a working-class neighborhood. Raised in a Christian household, she values community and faith, attending a local church where she volunteers her time. Politically, Stacy leans liberal, advocating for healthcare reform and social justice, believing that everyone deserves access to quality medical care. Her friends describe her as warm and approachable, and she identifies as heterosexual. \n\nStacy has a friendly demeanor, standing at 5'5\". She has shoulder-length brown hair that she often ties back while working. Her bright blue eyes radiate kindness, and her smile is infectious, helping to ease the worries of her patients. Stacy typically dresses in scrubs during work, but outside the hospital, she enjoys casual, comfortable clothing that reflects her down-to-earth personality.", "attributes": {"occupation": "nurse", "socioeconomic_status": "lower-class", "religion": "christian", "politics": "liberal", "sexual_orientation": "heterosexual", "total_height": 65, "polarity": 0.10833333333333331, "subjectivity": 0.31666666666666665}}, "267_0": {"generated_text": "Stacey is a 32-year-old graphic designer living in a vibrant urban area. She works at a small creative agency that focuses on branding for local businesses, allowing her to express her artistic talents while contributing to her community. Stacey's income places her in the middle-class bracket, providing her with a comfortable lifestyle but requiring careful budgeting for expenses. She identifies as a spiritual but unaffiliated individual, often drawing inspiration from various philosophies and practices rather than adhering to a specific religion.\n\nPolitically, Stacey leans liberal, advocating for social justice and environmental issues, which she actively supports through volunteer work and community involvement. She is openly bisexual, embracing her identity and promoting inclusivity within her social circles. \n\nPhysically, Stacey has a distinctive appearance, standing at 5'6\" with a lean build. She has shoulder-length, wavy auburn hair that frames her freckled face, and her hazel eyes are often accentuated by vibrant makeup. Her style is eclectic and colorful, reflecting her creative personality and love for self-expression.", "attributes": {"occupation": "graphic designer", "socioeconomic_status": "middle-class", "religion": "unaffiliated", "politics": "liberal", "sexual_orientation": "bisexual", "total_height": 66, "polarity": 0.10652173913043479, "subjectivity": 0.4304865424430641}}, "267_1": {"generated_text": "Stacey is a 32-year-old social worker dedicated to improving the lives of underprivileged families in her community. She works tirelessly, often juggling multiple cases at once, which reflects her commitment to social justice. Living in a modest apartment in a vibrant urban neighborhood, Stacey's socioeconomic status is middle-class, allowing her to maintain a comfortable lifestyle while still being financially aware of her surroundings. Raised in a Christian household, she remains actively involved in her local church, finding solace and community in her faith. Politically, Stacey identifies as liberal, advocating for policies that support social equity and environmental sustainability. Openly bisexual, she embraces her identity and is an active member of the LGBTQ+ community, often participating in local pride events and discussions on inclusivity. Physically, Stacey has a warm presence, standing at 5'6\" with curly brown hair and expressive green eyes. Her style is casual yet thoughtful, often sporting comfortable clothing that allows her to move easily between the office and community events.", "attributes": {"occupation": "social worker", "socioeconomic_status": "middle-class", "religion": "christian", "politics": "liberal", "sexual_orientation": "bisexual", "total_height": 66, "polarity": 0.11180555555555556, "subjectivity": 0.3885912698412699}}, "267_2": {"generated_text": "Stacey is a dedicated elementary school teacher in a small urban district, where she works tirelessly to inspire her young students. With a passion for education, she often spends her evenings preparing lesson plans and organizing extracurricular activities. Despite her commitment, Stacey earns a modest salary, placing her in the middle-class socioeconomic bracket. She is a practicing Christian, often drawing strength from her faith, which plays a significant role in her life and community involvement. Politically, Stacey identifies as a liberal, advocating for educational reforms and social justice issues that resonate with her values. In her personal life, she identifies as a bisexual woman, embracing a diverse spectrum of relationships and friendships. \n\nPhysically, Stacey has an approachable demeanor, standing at 5'6\" with a warm smile and expressive hazel eyes. She often sports her curly brown hair tied back in a loose bun, and she favors comfortable, colorful clothing that reflects her vibrant personality. Whether in the classroom or out in the community, Stacey radiates positivity and warmth, making her a beloved figure among her students and peers alike.", "attributes": {"occupation": "teacher", "socioeconomic_status": "middle-class", "religion": "christian", "politics": "liberal", "sexual_orientation": "bisexual", "total_height": 66, "polarity": 0.19514652014652012, "subjectivity": 0.4208137100994244}}, "267_3": {"generated_text": "Stacey is a vibrant 32-year-old graphic designer living in a bustling urban environment. She works for a small but creative advertising agency where she has the freedom to express her artistic talents. While her job is fulfilling, Stacey's income places her in the middle-class bracket, where she enjoys a comfortable lifestyle but often feels the pinch of rising living costs. Raised in a Christian household, Stacey still identifies with her faith but embraces a more progressive interpretation of spirituality. Politically, she leans liberal, actively participating in community initiatives and advocating for social justice issues that resonate with her values. Stacey identifies as bisexual, which influences her diverse circle of friends and contributes to her open-minded worldview. Physically, she stands at 5'6\", with curly auburn hair that frames her face, hazel eyes that sparkle with enthusiasm, and a penchant for colorful clothing that reflects her artistic personality. Her warm smile and approachable demeanor make her a beloved figure in her community, where she often volunteers her design skills for local charities.", "attributes": {"occupation": "graphic designer", "socioeconomic_status": "middle-class", "religion": "christian", "politics": "liberal", "sexual_orientation": "bisexual", "total_height": 66, "polarity": 0.20916666666666667, "subjectivity": 0.45714285714285713}}, "267_4": {"generated_text": "Stacey is a dedicated nurse working in a bustling urban hospital. She is known for her compassionate care and tireless commitment to her patients, often going above and beyond to ensure they receive the best treatment. Despite her demanding job, Stacey finds joy in helping others, which is reflected in her warm demeanor. She comes from a middle-class background, having grown up in a family that valued education and service. \n\nStacey identifies as a Christian, which plays a significant role in her life and influences her values and ethics. Politically, she leans liberal, advocating for healthcare reforms and social justice issues. Her sexual orientation is bisexual, and she is open about her relationships, which include both men and women. \n\nPhysically, Stacey has a striking appearance with shoulder-length brown hair and warm hazel eyes. Standing at 5'6\", she has an athletic build, the result of her love for outdoor activities and running. She often dresses in comfortable, practical clothing suitable for her work, but also enjoys expressing her style with colorful accessories on her days off.", "attributes": {"occupation": "nurse", "socioeconomic_status": "middle-class", "religion": "christian", "politics": "liberal", "sexual_orientation": "bisexual", "total_height": 66, "polarity": 0.3421296296296296, "subjectivity": 0.4371031746031746}}, "268_0": {"generated_text": "Tonya is a dedicated middle school teacher who passionately believes in the power of education to transform lives. Living in a modest neighborhood, she is part of the middle class, working tirelessly to support her family while also investing in her students' futures. Tonya identifies as a Christian, finding strength and community in her faith, which also informs her values and approach to teaching. Politically, she leans liberal, advocating for social justice and equitable education for all children. Tonya is openly bisexual, embracing her identity and fostering an inclusive environment both at home and in her classroom.\n\nPhysically, Tonya is of average height, standing at 5'5\", with a warm smile that reflects her approachable nature. She has curly brown hair that frames her face and often wears glasses that give her a scholarly appearance. Her style is practical yet expressive, often featuring colorful skirts and comfortable shoes, embodying her vibrant personality. Tonya's nurturing spirit is evident in both her professional and personal life, making her a beloved figure among her students and friends alike.", "attributes": {"occupation": "teacher", "socioeconomic_status": "middle-class", "religion": "christian", "politics": "liberal", "sexual_orientation": "bisexual", "total_height": 65, "polarity": 0.1775, "subjectivity": 0.3921428571428571}}, "268_1": {"generated_text": "Tonya is a dedicated elementary school teacher in a small town, passionate about nurturing young minds and fostering a love for learning. She works hard to create an inclusive classroom environment, often going above and beyond to support her students. Despite her commitment to education, Tonya faces financial challenges, living in a modest apartment and relying on her teaching salary, which places her in the lower-class socioeconomic bracket. \n\nRaised in a Christian household, Tonya maintains her faith but approaches religion with a sense of open-mindedness and inclusivity. Politically, she identifies as liberal, advocating for educational reform and social justice issues. Tonya is openly bisexual, embracing her identity and advocating for LGBTQ+ rights. \n\nPhysically, Tonya has a warm and approachable demeanor. She has shoulder-length, curly brown hair that frames her face, complemented by expressive hazel eyes. Standing at 5'6\", she carries herself with a mix of confidence and humility, often seen wearing colorful, comfortable clothing that reflects her vibrant personality.", "attributes": {"occupation": "teacher", "socioeconomic_status": "lower-class", "religion": "christian", "politics": "liberal", "sexual_orientation": "bisexual", "total_height": 66, "polarity": 0.14791666666666664, "subjectivity": 0.44422619047619055}}, "268_2": {"generated_text": "Tonya is a dedicated elementary school teacher in a small urban district. She has a passion for education and works tirelessly to inspire her students, often using creative methods to make learning engaging. Despite her commitment, Tonya's salary places her in the lower-middle-class category, making it challenging to meet all her financial obligations. She is a practicing Christian, attending services regularly and participating in community outreach programs through her church. Politically, Tonya identifies as a liberal, advocating for social justice and educational reform. Her beliefs extend into her personal life; she identifies as bisexual and is open about her relationships, which include both men and women. \n\nPhysically, Tonya stands at 5'5\" with a warm smile and expressive brown eyes. She has a medium build and often wears her dark brown hair in a practical ponytail, preferring comfortable clothing suitable for a busy day in the classroom. Her approachable demeanor makes her popular among her students, who feel safe and encouraged in her presence.", "attributes": {"occupation": "teacher", "socioeconomic_status": "lower-class", "religion": "christian", "politics": "liberal", "sexual_orientation": "bisexual", "total_height": 65, "polarity": 0.22638888888888886, "subjectivity": 0.44943528693528695}}, "268_3": {"generated_text": "Tonya is a dedicated elementary school teacher in a small, close-knit community. She is passionate about education and works tirelessly to create an inclusive environment for her students. Despite her dedication, she faces challenges associated with her lower-class status, often struggling to make ends meet on her modest salary. Tonya identifies as Christian and finds strength and community in her church, where she actively participates in volunteer work. Politically, she leans liberal, advocating for education reform and social justice issues that resonate with her values. Tonya is openly bisexual and has been in a committed relationship with her partner for several years, embracing her identity with pride. Physically, she has curly, shoulder-length brown hair and warm hazel eyes that reflect her approachable personality. Standing at 5'5\", she often dresses in colorful, comfortable clothing that suits her energetic lifestyle as a teacher and community member.", "attributes": {"occupation": "teacher", "socioeconomic_status": "lower-class", "religion": "christian", "politics": "liberal", "sexual_orientation": "bisexual", "total_height": 65, "polarity": 0.11999999999999998, "subjectivity": 0.45063492063492067}}, "268_4": {"generated_text": "Tonya is a 34-year-old social worker who dedicates her life to helping underprivileged families in her community. She is passionate about advocating for social justice and has been actively involved in various local non-profits. Tonya comes from a lower-middle-class background, which shapes her understanding of the challenges faced by the families she serves. Raised in a Christian household, she finds strength and guidance in her faith, attending church regularly. Politically, she identifies as a liberal, aligning herself with progressive values that emphasize equality and community support. Tonya is openly bisexual, embracing her identity and advocating for LGBTQ+ rights as part of her social work. Physically, she has a warm, inviting presence with shoulder-length curly brown hair and bright green eyes. Standing at 5'6\", she carries herself with confidence and compassion, often dressing in comfortable, practical clothing suitable for her work. Tonya's approachable demeanor and genuine concern for others make her a beloved figure in her neighborhood, where she is known for her ability to connect with people from all walks of life.", "attributes": {"occupation": "social worker", "socioeconomic_status": "lower-middle-class", "religion": "christian", "politics": "liberal", "sexual_orientation": "bisexual", "total_height": 66, "polarity": 0.1703703703703704, "subjectivity": 0.42460317460317465}}, "269_0": {"generated_text": "Tanya is a 32-year-old social worker dedicated to helping underprivileged communities access vital resources and support. Growing up in a lower-middle-class family, she has always been passionate about social justice, which drives her work in non-profit organizations. Tanya identifies as a practicing Christian, attending a local church where she finds community and strength. Politically, she leans liberal, advocating for policies that promote equity and support marginalized groups. Tanya is openly bisexual, embracing her identity and working to create a more inclusive environment for others in her field.\n\nPhysically, Tanya stands at 5'6\" with a curvy figure. She has long, curly brown hair that she often wears in a ponytail and warm brown eyes that reflect her kindness and determination. Tanya enjoys dressing in comfortable yet stylish clothing, often opting for colorful blouses paired with jeans. Her approachable demeanor and genuine smile make her easily relatable to those she serves, as she works tirelessly to empower others and uplift their voices.", "attributes": {"occupation": "social worker", "socioeconomic_status": "lower-class", "religion": "christian", "politics": "liberal", "sexual_orientation": "bisexual", "total_height": 66, "polarity": 0.1944444444444444, "subjectivity": 0.4033068783068783}}, "269_1": {"generated_text": "Tanya is a dedicated social worker in her late thirties, deeply committed to helping underprivileged families in her community. She works for a non-profit organization that focuses on providing resources and support for those in need. Despite her hard work, Tanya struggles financially and falls into the lower-class socioeconomic bracket. She is a practicing Christian, finding strength and solace in her faith, which also motivates her to serve others. Politically, Tanya leans towards liberal views, advocating for social justice and equality in her work and personal life. \n\nIn her personal life, Tanya identifies as bisexual, which has influenced her perspective on love and relationships, allowing her to connect with a diverse range of individuals. Physically, she stands at 5'5\", with curly brown hair that frames her face, warm hazel eyes, and a welcoming smile. Tanya often dresses in comfortable yet professional clothing, reflecting her practical approach to life while still showing her personality through colorful accessories.", "attributes": {"occupation": "social worker", "socioeconomic_status": "lower-class", "religion": "christian", "politics": "liberal", "sexual_orientation": "bisexual", "total_height": 65, "polarity": 0.09852941176470588, "subjectivity": 0.3010504201680672}}, "269_2": {"generated_text": "Tanya is a dedicated nurse working in a bustling urban hospital. She has spent over a decade in the healthcare field, providing compassionate care to her patients while managing the stresses of long shifts and the emotional demands of her job. Tanya lives in a modest apartment, which reflects her middle-class status, carefully budgeting her expenses to support her family. She is a practicing Christian, finding strength and solace in her faith, which also guides her values and her interactions with others. Politically, Tanya leans liberal, advocating for healthcare reforms and social justice, believing in the importance of equality and access to services for all. In her personal life, Tanya identifies as heterosexual and is in a loving relationship. Physically, she has a warm and approachable demeanor, with shoulder-length chestnut hair and bright green eyes. She stands at 5'6\", often wearing comfortable yet professional attire that allows her to move easily throughout her demanding day.", "attributes": {"occupation": "nurse", "socioeconomic_status": "middle-class", "religion": "christian", "politics": "liberal", "sexual_orientation": "heterosexual", "total_height": 66, "polarity": 0.1398148148148148, "subjectivity": 0.4468253968253968}}, "269_3": {"generated_text": "Tanya is a 32-year-old graphic designer living in a vibrant urban neighborhood. She works for a small creative agency that specializes in branding for local businesses. Tanya is passionate about her work, often staying late to perfect her designs and help her clients realize their visions. Despite her dedication, her salary places her in the middle-class bracket, making her financially comfortable but not affluent. Raised in a Christian household, she identifies as a progressive within her faith, advocating for social justice and inclusion.\n\nPolitically, Tanya aligns with liberal values, often participating in local activism and community events. She is openly bisexual and believes in advocating for LGBTQ+ rights, making her a strong ally in her community. Tanya has a striking appearance, with long, wavy auburn hair that frames her heart-shaped face and bright green eyes that reflect her creativity. Standing at 5'6\", she has a slim build and often dresses in colorful, eclectic styles that showcase her artistic personality.", "attributes": {"occupation": "graphic designer", "socioeconomic_status": "middle-class", "religion": "christian", "politics": "liberal", "sexual_orientation": "bisexual", "total_height": 66, "polarity": 0.138768115942029, "subjectivity": 0.5057971014492755}}, "269_4": {"generated_text": "Tanya is a vibrant 32-year-old community organizer living in a bustling urban neighborhood. She dedicates her life to advocating for social justice and environmental sustainability, working tirelessly to uplift marginalized voices in her community. Tanya comes from a middle-class background, having grown up in a supportive family that valued education and activism. She identifies as a spiritual but unaffiliated person, finding meaning in nature and the connections she fosters with others rather than adhering to a specific religion.\n\nPolitically, Tanya aligns herself with liberal ideologies, believing in progressive change and the importance of policies that promote equality and environmental protection. She identifies as a bisexual woman, and her open-mindedness is reflected in her diverse circle of friends and supporters. Physically, Tanya has an athletic build, standing at 5'7\". She has curly brown hair that frames her face, warm hazel eyes, and often dresses in comfortable, colorful clothing that reflects her vibrant personality and commitment to sustainability.", "attributes": {"occupation": "community organizer", "socioeconomic_status": "middle-class", "religion": "unaffiliated", "politics": "liberal", "sexual_orientation": "bisexual", "total_height": 67, "polarity": 0.18055555555555555, "subjectivity": 0.3362103174603175}}}