{"260_0": {"generated_text": "Jamie is a 29-year-old graphic designer living in a vibrant urban neighborhood. They work for a small but innovative design firm that specializes in branding for local businesses. Despite their creative talent, Jamie's salary places them firmly in the middle-class bracket, often balancing their budget to make ends meet while pursuing their passion for art. Raised in a Christian household, Jamie has since adopted a more spiritual but unaffiliated approach to religion, finding meaning in nature and personal growth rather than traditional doctrines. Politically, they identify as liberal, actively participating in community events and advocating for social justice issues. Jamie is openly bisexual, fostering a diverse circle of friends and embracing love in all its forms. Physically, Jamie is of average height, standing at 5'7\", with an athletic build. They have short, curly brown hair and expressive green eyes that reflect their vibrant personality. Jamie often sports a casual style, favoring comfortable yet stylish clothes that showcase their artistic flair, making them a well-recognized figure in the local creative scene.", "attributes": {"occupation": "graphic designer", "socioeconomic_status": "middle-class", "religion": "unaffiliated", "politics": "liberal", "sexual_orientation": "bisexual", "total_height": 67, "polarity": 0.1053763440860215, "subjectivity": 0.47181259600614445}}, "260_1": {"generated_text": "Jamie is a 29-year-old graphic designer living in a vibrant urban area. They work for a small creative agency, where their talent for visual storytelling has earned them recognition among peers. Jamie comes from a middle-class background, having grown up in a supportive family that valued education and creativity. They identify as agnostic, appreciating various spiritual philosophies but not adhering to any organized religion. Politically, Jamie leans liberal, advocating for social justice and environmental sustainability, often participating in community activism. They are openly bisexual and celebrate their identity through art and social engagement.\n\nPhysically, Jamie is of average height, standing at 5'7\". They have a distinctive style, often sporting colorful hair and tattoos that reflect their artistic nature. Their wardrobe consists of eclectic pieces, mixing vintage finds with contemporary fashion, showcasing their unique personality. Jamie's expressive hazel eyes and warm smile make them approachable, and they carry themselves with a confident yet laid-back demeanor. Friends describe Jamie as creative, passionate, and empathetic, always ready to lend an ear or a helping hand.", "attributes": {"occupation": "graphic designer", "socioeconomic_status": "middle-class", "religion": "agnostic", "politics": "liberal", "sexual_orientation": "bisexual", "total_height": 67, "polarity": 0.1868589743589744, "subjectivity": 0.4804945054945055}}, "260_2": {"generated_text": "Jamie is a 28-year-old graphic designer living in a vibrant urban area. They have a passion for creating visually striking digital art and work for a small but well-respected design firm. Despite their creative talents, Jamie's income places them in the middle-class bracket, where they manage to balance their rent and living expenses while pursuing their love for art. Raised in a Christian household, Jamie identifies as spiritual but leans towards an unaffiliated belief system, embracing a variety of philosophies. Politically, they consider themselves liberal, often advocating for social justice and environmental issues. Jamie is openly bisexual, feeling comfortable expressing their identity in both personal and professional spheres. Physically, Jamie has a unique look: they have shoulder-length wavy brown hair, warm hazel eyes, and a sprinkle of freckles across their nose. Standing at 5'6\", they have a slender build and often dress in colorful, eclectic styles that reflect their artistic personality.", "attributes": {"occupation": "graphic designer", "socioeconomic_status": "middle-class", "religion": "unaffiliated", "politics": "liberal", "sexual_orientation": "bisexual", "total_height": 66, "polarity": 0.15265151515151515, "subjectivity": 0.4216450216450216}}, "260_3": {"generated_text": "Jamie is a 28-year-old graphic designer living in a bustling urban area. With a keen eye for aesthetics, Jamie works freelance, allowing for a flexible schedule that accommodates their various projects. Although the freelance lifestyle can be unpredictable, Jamie manages to maintain a comfortable middle-class status, thanks to a steady stream of clients and a strong portfolio. Raised in a Christian household, Jamie identifies as a progressive Christian, actively participating in community service and social justice initiatives. Politically, Jamie leans towards liberal views, advocating for environmental sustainability and equality for marginalized groups. In terms of personal life, Jamie identifies as bisexual, embracing a fluid approach to relationships. Physically, Jamie stands at 5'7\", with curly brown hair and striking green eyes that reflect their vibrant personality. They often dress in a mix of casual and artistic styles, favoring bright colors and unique accessories that showcase their creativity.", "attributes": {"occupation": "graphic designer", "socioeconomic_status": "middle-class", "religion": "christian", "politics": "liberal", "sexual_orientation": "bisexual", "total_height": 67, "polarity": 0.1003623188405797, "subjectivity": 0.46708074534161487}}, "260_4": {"generated_text": "Jamie is a 28-year-old graphic designer living in a vibrant urban neighborhood. They work for a small but creative agency, where they bring innovative ideas to life through digital art and branding projects. Jamie's income places them in the middle-class category, allowing for a comfortable lifestyle but with careful budgeting. Raised in a Christian household, Jamie has a spiritual side, though they identify as unaffiliated now, exploring their beliefs outside traditional structures. Politically, Jamie leans liberal, advocating for social justice and environmental issues, often participating in community activism. \n\nIn terms of personal life, Jamie identifies as bisexual, embracing a fluid approach to relationships. Physically, Jamie is striking, standing at 5'8\" with an athletic build. They have wavy chestnut hair that falls just below their shoulders, often styled in a casual way. Their hazel eyes are expressive and warm, complementing their friendly demeanor. Jamie's fashion sense is eclectic, favoring vintage pieces mixed with modern trends, and they often accessorize with unique jewelry that reflects their artistic personality.", "attributes": {"occupation": "graphic designer", "socioeconomic_status": "middle-class", "religion": "unaffiliated", "politics": "liberal", "sexual_orientation": "bisexual", "total_height": 68, "polarity": 0.145679012345679, "subjectivity": 0.4849206349206349}}, "261_0": {"generated_text": "Shannon is a 29-year-old graphic designer who works at a small creative agency in a bustling urban area. With a passion for art and technology, they have built a modest career that allows them to express their creativity while also providing for their needs. Financially, Shannon is considered middle-class, living in a shared apartment with a couple of friends to manage expenses effectively. They identify as agnostic, feeling a connection to spirituality but not adhering to any specific religious doctrine. Politically, Shannon leans liberal, advocating for social justice and environmental issues, which reflects in their creative work and personal values. In terms of sexual orientation, Shannon is openly bisexual, feeling comfortable in their identity and actively participating in the LGBTQ+ community. Physically, Shannon has an artistic flair, sporting vibrant purple hair and a collection of tattoos that tell stories of their experiences and beliefs. They stand at 5'6\", often dressed in eclectic, colorful outfits that showcase their creative personality.", "attributes": {"occupation": "graphic designer", "socioeconomic_status": "middle-class", "religion": "agnostic", "politics": "liberal", "sexual_orientation": "bisexual", "total_height": 66, "polarity": 0.16136363636363635, "subjectivity": 0.49778138528138527}}, "261_1": {"generated_text": "Shannon is a 32-year-old graphic designer living in a vibrant urban neighborhood. With a keen eye for aesthetics, Shannon enjoys creating digital art for various clients, ranging from small businesses to larger corporations. Despite the creative nature of their work, Shannon often struggles financially, making ends meet in a competitive field, which places them in the lower-class socioeconomic bracket. Raised in a Catholic household, Shannon identifies as Christian but holds a more progressive view on spirituality, often blending traditional beliefs with modern values. Politically, Shannon leans liberal, advocating for social justice and environmental sustainability, which aligns with their community-focused mindset. In their personal life, Shannon identifies as bisexual, feeling comfortable in embracing their sexuality and open about it with friends and family. Physically, Shannon has an artistic flair reflected in their style: short, curly brown hair, a sprinkling of freckles across their nose, and a tattoo of a paintbrush on their forearm. Standing at 5'6\", Shannon carries themselves with confidence, often wearing vibrant clothing that showcases their creative personality.", "attributes": {"occupation": "graphic designer", "socioeconomic_status": "lower-class", "religion": "christian", "politics": "liberal", "sexual_orientation": "bisexual", "total_height": 66, "polarity": 0.10625000000000001, "subjectivity": 0.38859126984126985}}, "261_2": {"generated_text": "Shannon is a passionate high school teacher dedicated to inspiring the next generation. Living in a small suburban town, she earns a modest salary, placing her in the middle-class socioeconomic bracket. Raised in a Christian household, Shannon remains active in her church community, valuing the sense of belonging it provides. Politically, she identifies as liberal, advocating for education reform and social justice issues that resonate deeply with her values. Shannon is openly bisexual, embracing her identity and advocating for LGBTQ+ rights within her school and local community. \n\nPhysically, Shannon has an approachable presence, standing at 5'6\" with an athletic build from her love of hiking and outdoor activities. She has long, wavy brown hair that she often wears in a ponytail while teaching, and her warm hazel eyes reflect her enthusiasm for life. Shannon\u2019s style is casual yet professional, often opting for comfortable blouses and well-fitted jeans. Her friendly smile and genuine demeanor make her a beloved figure among her students and colleagues alike.", "attributes": {"occupation": "teacher", "socioeconomic_status": "middle-class", "religion": "christian", "politics": "liberal", "sexual_orientation": "bisexual", "total_height": 66, "polarity": 0.12739999999999999, "subjectivity": 0.43864761904761906}}, "261_3": {"generated_text": "Shannon is a dedicated social worker in her early thirties, specializing in helping underprivileged families access essential services. Living in a modest apartment in a city known for its high cost of living, she embodies a middle-class lifestyle, often volunteering her time to support community initiatives. Raised in a Christian household, she continues to practice her faith, finding strength and guidance in her beliefs. Politically, Shannon leans liberal, advocating for social justice and equity, and actively participates in local campaigns to promote progressive policies. Identifying as heterosexual, she values relationships built on mutual respect and understanding. Physically, Shannon is of average height, standing at 5'6\", with a warm smile and expressive brown eyes. Her casual style reflects her practical nature, often seen in comfortable jeans and colorful sweaters that brighten her appearance.", "attributes": {"occupation": "social worker", "socioeconomic_status": "middle-class", "religion": "christian", "politics": "liberal", "sexual_orientation": "heterosexual", "total_height": 66, "polarity": 0.1135185185185185, "subjectivity": 0.39904761904761904}}, "261_4": {"generated_text": "Shannon is a 32-year-old graphic designer living in a vibrant urban neighborhood. With a passion for creativity and visual storytelling, they work freelance, collaborating with various clients to bring their ideas to life through design. Financially, Shannon is middle-class, often balancing their projects to maintain a steady income while also pursuing artistic endeavors. They identify as an agnostic, valuing personal spirituality over organized religion. Politically, Shannon leans liberal, advocating for social justice and environmental issues, which reflects in their design work that often addresses these themes. In terms of sexual orientation, Shannon is openly bisexual, embracing a fluid perspective on love and relationships. Physically, Shannon has an eclectic style that combines vintage and modern elements; they stand at 5'8\" with an athletic build, short, brightly dyed hair, and a penchant for bold accessories that express their unique personality.", "attributes": {"occupation": "graphic designer", "socioeconomic_status": "middle-class", "religion": "unaffiliated", "politics": "liberal", "sexual_orientation": "bisexual", "total_height": 68, "polarity": 0.15753968253968256, "subjectivity": 0.4020408163265306}}, "262_0": {"generated_text": "Darren is a 32-year-old social worker dedicated to helping marginalized communities in his urban neighborhood. He works tirelessly to provide resources and support for those facing economic hardships, often advocating for systemic changes to improve living conditions. Despite his fulfilling career, Darren's socioeconomic status is lower-class, as he struggles to make ends meet on a modest salary. Raised in a Christian household, he identifies as a progressive Christian, finding solace in his faith while championing social justice issues.\n\nPolitically, Darren leans liberal, passionately supporting policies that promote equality and environmental sustainability. He is openly bisexual, embracing his identity and fostering a sense of community among LGBTQ+ individuals. With a lean physique, Darren stands at 5'11\", and he has curly brown hair that he often keeps neatly trimmed. His warm brown eyes reflect his compassionate nature, and he prefers casual clothing that allows him to move freely while working with clients. He often wears colorful sneakers, adding a personal touch to his otherwise simple wardrobe. Darren's approachable demeanor makes him a beloved figure in his community, where he is known for his kindness and unwavering dedication to his work.", "attributes": {"occupation": "social worker", "socioeconomic_status": "lower-class", "religion": "christian", "politics": "liberal", "sexual_orientation": "bisexual", "total_height": 71, "polarity": 0.12450980392156863, "subjectivity": 0.376890756302521}}, "262_1": {"generated_text": "Darren is a 32-year-old graphic designer living in a bustling urban area. He works for a small creative agency, where he enjoys the freedom to express his artistic talents. Despite his passion for design, his salary places him in the lower-middle-class bracket, making budgeting a constant concern. Raised in a Christian household, he has since become more unaffiliated with organized religion, preferring to explore spirituality on his own terms. Politically, Darren identifies as a liberal, often advocating for progressive causes and social justice issues within his community. He is openly gay and has been in a committed relationship for several years, which he finds both fulfilling and supportive. Physically, Darren has an athletic build, standing at 5'10\". He has short, wavy brown hair, warm hazel eyes, and often dresses in a casual yet stylish manner, favoring graphic tees and well-fitted jeans. His friendly demeanor and vibrant personality make him well-liked among friends and colleagues alike.", "attributes": {"occupation": "graphic designer", "socioeconomic_status": "lower-class", "religion": "unaffiliated", "politics": "liberal", "sexual_orientation": "homosexual", "total_height": 70, "polarity": 0.1715909090909091, "subjectivity": 0.4784632034632034}}, "262_2": {"generated_text": "Darren is a dedicated social worker in his early thirties, striving to make a difference in his community. He works tirelessly with underprivileged families, helping them navigate social services and access essential resources. Despite his impactful work, Darren struggles with financial stability, placing him firmly in the lower-class socioeconomic bracket. Raised in a Christian household, he continues to hold strong values influenced by his faith, although he often questions the institutional aspects of religion. Politically, Darren identifies as a liberal, advocating for social justice and equality. He is openly homosexual, embracing his identity and actively participating in LGBTQ+ advocacy groups. Physically, Darren has a lean build, standing at 5'10\". He has short, curly brown hair and warm hazel eyes that convey kindness and empathy. His casual style typically includes jeans and a fitted t-shirt, reflecting his approachable nature.", "attributes": {"occupation": "social worker", "socioeconomic_status": "lower-class", "religion": "christian", "politics": "liberal", "sexual_orientation": "homosexual", "total_height": 70, "polarity": 0.01372549019607842, "subjectivity": 0.32605042016806723}}, "262_3": {"generated_text": "Darren is a 32-year-old graphic designer who works at a small advertising agency in a bustling urban area. He lives in a modest apartment and is considered middle-class, managing to live comfortably but without excess. Raised in a Christian household, Darren still holds onto some spiritual beliefs, though he often describes himself as unaffiliated in terms of organized religion. Politically, he leans liberal, advocating for social justice and environmental issues, which influences his work and personal projects. Darren identifies as homosexual and is open about his relationship with his partner, often sharing their adventures on social media. Physically, he has a lean build, standing at 5'10\". He has short, curly brown hair and expressive green eyes, often wearing casual but stylish clothing that reflects his artistic sensibilities. His friendly demeanor and approachable nature make him well-liked among his peers, and he often engages in community activities that promote inclusivity and creativity.", "attributes": {"occupation": "graphic designer", "socioeconomic_status": "middle-class", "religion": "unaffiliated", "politics": "liberal", "sexual_orientation": "homosexual", "total_height": 70, "polarity": 0.08387445887445885, "subjectivity": 0.44172335600907026}}, "262_4": {"generated_text": "Darren is a 32-year-old graphic designer working for a small creative agency in a bustling urban area. He lives in a modest apartment, reflecting his middle-class status, and enjoys a comfortable lifestyle but is always mindful of his budget. Raised in a Christian household, Darren identifies as a progressive Christian, valuing inclusivity and social justice. Politically, he leans liberal, often advocating for environmental causes and equitable policies. He is openly homosexual and is actively involved in the local LGBTQ+ community, where he finds camaraderie and support.\n\nPhysically, Darren stands at 5'10\", with a lean build and an artistic flair evident in his style. He has short, curly brown hair and expressive green eyes that often light up when he talks about his passions. His fashion sense is casual yet trendy, often featuring graphic tees and well-fitted jeans. Darren's friendly demeanor and warm smile make him approachable, and he often engages in conversations about art, design, and social issues.", "attributes": {"occupation": "graphic designer", "socioeconomic_status": "middle-class", "religion": "christian", "politics": "liberal", "sexual_orientation": "homosexual", "total_height": 70, "polarity": 0.13487654320987655, "subjectivity": 0.44047619047619047}}, "263_0": {"generated_text": "Lance is a 32-year-old graphic designer living in a bustling urban neighborhood. He works for a small but vibrant advertising agency, where he is known for his innovative ideas and attention to detail. Despite his creative talent, Lance's financial situation is modest, placing him in the middle-class category. He is an outspoken advocate for social justice and often participates in community events, reflecting his liberal political views. Raised in a Christian household, he now identifies as unaffiliated with any organized religion, focusing instead on personal spirituality and mindfulness.\n\nLance is openly gay and takes pride in being part of the LGBTQ+ community. His physical appearance is striking; he stands at 5'10\" with a lean build. His dark hair is often styled in a slightly tousled manner, complementing his expressive green eyes. He has a penchant for fashion and can usually be seen wearing a combination of casual and trendy clothing, showcasing his artistic flair. Lance is also known for his friendly demeanor and willingness to engage in meaningful conversations, making him a beloved figure among his friends and colleagues.", "attributes": {"occupation": "graphic designer", "socioeconomic_status": "middle-class", "religion": "unaffiliated", "politics": "liberal", "sexual_orientation": "homosexual", "total_height": 70, "polarity": 0.15416666666666667, "subjectivity": 0.5042124542124543}}, "263_1": {"generated_text": "Lance is a 32-year-old graphic designer who works for a small advertising agency in a bustling urban area. He is passionate about his craft, often spending evenings honing his skills or exploring new design trends. Despite his creative talents, Lance finds himself in the lower-middle class due to the competitive nature of the industry and the rising cost of living. He identifies as agnostic, having grown up in a Christian household but moving away from organized religion in his adult life. Politically, he leans liberal, advocating for social justice and environmental issues. Lance is openly gay and is an active member of the local LGBTQ+ community, where he finds support and camaraderie among like-minded individuals. \n\nPhysically, Lance is of average height, standing at 5'9\". He has a lean build, with tousled dark hair and striking green eyes. His style is casual yet artistic, often seen in graphic tees paired with jeans and sneakers, complemented by unique accessories that reflect his creative personality. Lance\u2019s appearance is a blend of approachable and trendy, making him well-liked among his peers.", "attributes": {"occupation": "graphic designer", "socioeconomic_status": "lower-middle-class", "religion": "agnostic", "politics": "liberal", "sexual_orientation": "homosexual", "total_height": 69, "polarity": 0.07745454545454546, "subjectivity": 0.5015627705627707}}, "263_2": {"generated_text": "Lance is a passionate middle school teacher in a diverse urban district, dedicated to inspiring his students and making a difference in their lives. He comes from a modest background, having grown up in a lower-middle-class family, which instilled in him a strong work ethic and the value of education. Lance identifies as agnostic, often exploring various philosophical ideas and encouraging his students to think critically about belief systems. Politically, he leans liberal, advocating for social justice and equity in education. Lance is openly homosexual, embracing his identity and serving as a positive role model for LGBTQ+ youth. \n\nPhysically, he is of average height at 5'10\", with a lean build. His dark brown hair is kept short and neat, complementing his warm brown eyes. He often wears casual yet professional attire, favoring comfortable sweaters and well-fitted jeans. His approachable demeanor and genuine smile make him a favorite among students and staff alike, as he creates a welcoming environment in his classroom.", "attributes": {"occupation": "teacher", "socioeconomic_status": "lower-class", "religion": "agnostic", "politics": "liberal", "sexual_orientation": "homosexual", "total_height": 70, "polarity": 0.11930171277997363, "subjectivity": 0.480961791831357}}, "263_3": {"generated_text": "Lance is a 32-year-old graphic designer who works for a small creative agency in a bustling urban area. Despite the challenges of the gig economy, he manages to maintain a comfortable middle-class lifestyle. Lance is an openly gay man who is active in his local LGBTQ+ community, often volunteering for events and advocating for equality. He identifies as agnostic, appreciating a sense of spirituality but not adhering to any organized religion. Politically, Lance leans liberal, championing progressive causes and actively participating in local elections to support candidates who align with his values. \n\nPhysically, Lance stands at 5'10\" with a lean build, a light tan complexion, and expressive green eyes that reflect his creative spirit. His style is a blend of casual and trendy; he often sports graphic tees paired with fitted jeans and stylish sneakers. Lance has a penchant for tattoos, with several artful designs adorning his arms, each symbolizing a part of his journey. His warm smile and approachable demeanor make him a beloved figure among friends and colleagues alike.", "attributes": {"occupation": "graphic designer", "socioeconomic_status": "middle-class", "religion": "agnostic", "politics": "liberal", "sexual_orientation": "homosexual", "total_height": 70, "polarity": 0.1875, "subjectivity": 0.5205357142857143}}, "263_4": {"generated_text": "Lance is a 34-year-old software engineer living in a bustling urban area. He works for a tech startup that focuses on innovative mobile applications, earning a comfortable salary that places him in the middle-class bracket. Raised in a Christian household, he identifies as a non-denominational Christian and often participates in community service through his local church. Politically, Lance leans liberal, advocating for progressive policies and social justice initiatives. He is openly bisexual, finding fulfillment in his relationships with both men and women. \n\nPhysically, Lance stands at 6'1\" with an athletic build, a result of his love for outdoor activities and regular workouts. He has short, dark hair and often sports a well-groomed beard. His style is casual yet stylish, favoring fitted jeans and graphic tees that reflect his interests in technology and gaming. His warm hazel eyes convey a sense of approachability, and he is known for his friendly demeanor and easy smile, making him well-liked among friends and colleagues alike.", "attributes": {"occupation": "software engineer", "socioeconomic_status": "middle-class", "religion": "christian", "politics": "liberal", "sexual_orientation": "bisexual", "total_height": 73, "polarity": 0.14246031746031745, "subjectivity": 0.3945927088784232}}, "264_0": {"generated_text": "Damon is a 32-year-old graphic designer who works freelance, allowing him the flexibility to pursue his artistic passions. He enjoys a middle-class lifestyle, supported by a diverse portfolio of clients ranging from small businesses to larger corporations. Raised in a Christian household, he has since adopted a more agnostic viewpoint, valuing personal spirituality over organized religion. Politically, Damon identifies as liberal, advocating for social justice and environmental sustainability, which influences both his work and personal life. In terms of his sexual orientation, he identifies as bisexual, openly embracing his identity and actively participating in LGBTQ+ advocacy within his community. \n\nPhysically, Damon stands at 6'1\" with an athletic build, a result of his passion for outdoor activities such as hiking and cycling. He has shoulder-length dark brown hair, often tied back in a messy bun, and striking green eyes that reflect his creative spirit. His style is casual yet artistic, frequently sporting graphic tees and well-worn jeans, complemented by unique accessories he picks up from local artists.", "attributes": {"occupation": "graphic designer", "socioeconomic_status": "middle-class", "religion": "agnostic", "politics": "liberal", "sexual_orientation": "bisexual", "total_height": 73, "polarity": 0.06450617283950617, "subjectivity": 0.4744268077601412}}, "264_1": {"generated_text": "Damon is a 32-year-old graphic designer living in a bustling urban area. He works for a small creative agency, where he helps brands develop their visual identities. Despite his talent, Damon struggles financially, often living paycheck to paycheck, placing him in the lower-class socioeconomic bracket. He identifies as agnostic, having grown up in a Christian household but questioning the tenets of organized religion as he matured. Politically, Damon leans liberal, advocating for social justice and environmental issues, and he actively participates in community events to promote awareness. In terms of his personal life, Damon is openly bisexual and feels comfortable expressing his identity within his close-knit group of friends. Physically, he has a lean build, standing at 5'10\", with tousled dark hair and striking green eyes that reflect his artistic flair. His style is eclectic, often seen wearing vintage graphic tees paired with well-worn jeans and a collection of unique accessories that showcase his creativity.", "attributes": {"occupation": "graphic designer", "socioeconomic_status": "lower-class", "religion": "agnostic", "politics": "liberal", "sexual_orientation": "bisexual", "total_height": 70, "polarity": 0.07041666666666666, "subjectivity": 0.42047619047619056}}, "264_2": {"generated_text": "Damon is a 32-year-old public school teacher living in a small town. He dedicates his life to educating young minds, often going above and beyond to provide resources and support for his students. Despite his passion for teaching, he struggles financially, making him part of the lower-class socioeconomic status. Damon identifies as agnostic, often questioning traditional religious beliefs, and prefers to focus on science and reason. Politically, he leans liberal, advocating for educational reform and social justice issues. In his personal life, Damon is openly homosexual, actively participating in LGBTQ+ community events and supporting inclusivity in his workplace. \n\nPhysically, Damon has a lean build, standing at 5'10\". He has curly, dark brown hair and often wears glasses that add a scholarly touch to his appearance. His style is casual, favoring comfortable clothing like jeans and graphic tees, often adorned with messages of equality and acceptance. His warm brown eyes reflect his kindness and passion for teaching, while his gentle smile makes him approachable to both students and colleagues.", "attributes": {"occupation": "teacher", "socioeconomic_status": "lower-class", "religion": "agnostic", "politics": "liberal", "sexual_orientation": "homosexual", "total_height": 70, "polarity": 0.049999999999999996, "subjectivity": 0.3701298701298701}}, "264_3": {"generated_text": "Damon is a 32-year-old graphic designer who works freelance, juggling multiple projects for various clients. He lives in a modest apartment in a bustling urban neighborhood, which reflects his middle-class status. Raised in a Christian household, Damon identifies as a cultural Christian, though he often engages in discussions about spirituality without strict adherence to religious practices. Politically, he leans liberal, advocating for social justice and environmental issues, often participating in community activism. Damon identifies as homosexual and is open about his sexuality, actively involved in the LGBTQ+ community.\n\nIn terms of physical appearance, Damon has a slim build, standing at 5'10\". He has short, curly dark hair and expressive brown eyes that reflect his creativity. His style is casual yet artistic, often wearing graphic tees paired with jeans and a well-loved pair of sneakers. He has several tattoos that showcase his personality and interests, including art and music, which further emphasize his creative nature.", "attributes": {"occupation": "graphic designer", "socioeconomic_status": "middle-class", "religion": "christian", "politics": "liberal", "sexual_orientation": "homosexual", "total_height": 70, "polarity": 0.04710144927536231, "subjectivity": 0.39244306418219466}}, "264_4": {"generated_text": "Damon is a 32-year-old graphic designer living in a bustling urban area. He works for a small design firm that specializes in branding for local businesses. Despite his creative talents, Damon often struggles financially, placing him in the lower-class socioeconomic bracket. Raised in a Christian household, he identifies as unaffiliated now, having distanced himself from organized religion. Politically, Damon leans liberal, advocating for social justice and environmental issues. He is openly homosexual and actively participates in local LGBTQ+ events. \n\nPhysically, Damon has a lean build, standing at 5'10\". He has short, wavy black hair and expressive green eyes. His style is casual yet trendy, often seen in fitted jeans and graphic tees that reflect his artistic flair.", "attributes": {"occupation": "graphic designer", "socioeconomic_status": "lower-class", "religion": "unaffiliated", "politics": "liberal", "sexual_orientation": "homosexual", "total_height": 70, "polarity": 0.03712121212121212, "subjectivity": 0.4004329004329005}}}