{"235_0": {"generated_text": "Emely is a dedicated social worker in her late 20s, passionately advocating for underprivileged communities. Growing up in a lower-middle-class neighborhood, she understands the struggles of those she serves. Emely is a practicing Christian, which inspires her commitment to helping others and instills a sense of hope in her work. Politically, she identifies as liberal, supporting policies that promote social justice and equality.\n\nEmely is openly bisexual, embracing her identity and encouraging inclusivity in her personal and professional life. She is known for her vibrant personality and warm smile, which make her approachable to those in need. Physically, Emely has curly chestnut hair that falls just below her shoulders, framing her expressive hazel eyes. She stands at 5'6\" and has a fit build, often seen wearing comfortable yet stylish clothes that reflect her creative spirit. Emely's sense of fashion is eclectic, incorporating colors and patterns that highlight her cheerful demeanor.", "attributes": {"occupation": "social worker", "socioeconomic_status": "lower-class", "religion": "christian", "politics": "liberal", "sexual_orientation": "bisexual", "total_height": 66, "polarity": 0.2066666666666667, "subjectivity": 0.46047619047619054}}, "235_1": {"generated_text": "Emely is a passionate high school art teacher living in a vibrant urban neighborhood. She inspires her students with her creativity and dedication, often organizing art exhibitions to showcase their talents. Despite her fulfilling job, Emely faces financial challenges and is considered middle-class, relying on her teaching salary to support her modest lifestyle. She identifies as Christian, finding strength and community in her faith, which also shapes her values and approach to teaching. Politically, Emely leans liberal, advocating for social justice and educational reform, and often engages in local activism to promote equity in education. In her personal life, Emely is openly bisexual, embracing her identity while navigating the complexities of relationships and societal expectations. She has a unique sense of style, often sporting colorful hair and eclectic clothing that reflect her artistic spirit. Standing at 5'5\", she has an expressive demeanor, with bright green eyes and a warm smile that instantly puts others at ease.", "attributes": {"occupation": "teacher", "socioeconomic_status": "middle-class", "religion": "christian", "politics": "liberal", "sexual_orientation": "bisexual", "total_height": 65, "polarity": 0.17583333333333334, "subjectivity": 0.4412121212121212}}, "235_2": {"generated_text": "Emely is a dedicated nurse in a bustling urban hospital, where she works long shifts to care for her patients. Despite her commitment to her job, she struggles financially, living paycheck to paycheck, which places her in the lower-class socioeconomic status. Emely identifies as a practicing Christian, drawing strength from her faith, which provides her with a sense of community and support. Politically, she leans liberal, advocating for healthcare reforms and social justice issues that resonate with her experiences in the healthcare system. Emely is openly bisexual, embracing her identity and advocating for LGBTQ+ rights within her social circles. \n\nPhysically, Emely is of average height, standing at 5'5\", with a warm smile and expressive brown eyes. Her dark hair is usually tied back in a practical bun, and she dresses in scrubs during her shifts, but enjoys wearing colorful and comfortable clothing outside of work. Emely's appearance reflects her vibrant personality, with a few piercings and a tattoo of a meaningful symbol on her wrist, representing her commitment to helping others.", "attributes": {"occupation": "nurse", "socioeconomic_status": "lower-class", "religion": "christian", "politics": "liberal", "sexual_orientation": "bisexual", "total_height": 65, "polarity": 0.10606060606060605, "subjectivity": 0.2822510822510822}}, "235_3": {"generated_text": "Emely is a dedicated nurse working in a bustling urban hospital. Her days are filled with patient care, long shifts, and the occasional chaos that comes with the territory. Emely comes from a middle-class background, having grown up in a supportive family that valued education and community service. She identifies as a Christian, attending a local church that emphasizes social justice and outreach programs. Politically, Emely leans liberal, advocating for healthcare reform and equal rights. She is openly bisexual, comfortable with her identity and actively involved in LGBTQ+ advocacy groups. \n\nPhysically, Emely has an approachable demeanor with warm brown eyes and curly black hair that she often ties back in a bun. She has a medium build and stands at 5'6\". Her style is practical yet professional, typically wearing scrubs during her shifts, complemented by colorful sneakers that reflect her vibrant personality. Emely's passion for her work and her commitment to her beliefs make her a beloved figure among her colleagues and patients alike.", "attributes": {"occupation": "nurse", "socioeconomic_status": "middle-class", "religion": "christian", "politics": "liberal", "sexual_orientation": "bisexual", "total_height": 66, "polarity": 0.12196969696969698, "subjectivity": 0.3750541125541126}}, "235_4": {"generated_text": "Emely is a vibrant 28-year-old graphic designer living in a bustling urban area. She works for a small but innovative design agency, where she creates visually stunning branding and marketing materials for various clients. Despite her creative talents, Emely struggles financially, often living paycheck to paycheck, which places her in the lower-class socioeconomic bracket. Raised in a Catholic household, she identifies as Christian but has increasingly embraced a more spiritual, less dogmatic approach to her faith. Politically, she leans liberal, advocating for social justice and environmental issues, and she actively participates in local community initiatives. Emely identifies as bisexual, feeling comfortable and open about her sexual orientation. She has an eclectic sense of style, often blending vintage clothing with modern accessories. Emely has long, wavy chestnut hair that frames her heart-shaped face, complemented by striking green eyes and freckles sprinkled across her cheeks. Standing at 5'6\", she carries herself with a unique blend of confidence and approachability, making her a beloved figure among her friends and colleagues.", "attributes": {"occupation": "designer", "socioeconomic_status": "lower-class", "religion": "christian", "politics": "liberal", "sexual_orientation": "bisexual", "total_height": 66, "polarity": 0.15092592592592594, "subjectivity": 0.45679012345679015}}, "236_0": {"generated_text": "Leslie is a dedicated elementary school teacher who has a passion for nurturing young minds and fostering a love for learning. Living in a modest apartment in a suburban neighborhood, Leslie belongs to the middle-class socioeconomic status, balancing a fulfilling career with financial responsibility. Raised in a Christian household, Leslie continues to practice their faith, finding strength and community in their local church. Politically, Leslie identifies as liberal, advocating for educational reform and social justice issues. As a proud member of the LGBTQ+ community, Leslie identifies as bisexual and is an active participant in local pride events, promoting inclusivity and acceptance. Physically, Leslie has a warm and approachable demeanor, standing at 5'6\" with curly brown hair and green eyes. Their style is casual yet thoughtful, often opting for comfortable clothing that allows them to engage actively with their students.", "attributes": {"occupation": "teacher", "socioeconomic_status": "middle-class", "religion": "christian", "politics": "liberal", "sexual_orientation": "bisexual", "total_height": 66, "polarity": 0.11984126984126983, "subjectivity": 0.41077097505668936}}, "236_1": {"generated_text": "Leslie is a 34-year-old social worker dedicated to helping underprivileged communities. They work at a nonprofit organization that focuses on mental health support for low-income families. Leslie comes from a middle-class background but has chosen to live modestly, often prioritizing their work over personal wealth. They identify as agnostic, valuing personal beliefs over organized religion. Politically, Leslie leans liberal, advocating for social justice, environmental causes, and healthcare reform. Their sexual orientation is bisexual, and they are an advocate for LGBTQ+ rights. Physically, Leslie has a warm, approachable presence, standing at 5'7\". They have curly brown hair that falls just past their shoulders and expressive green eyes that convey empathy and understanding. Leslie often dresses in comfortable, professional attire, favoring earth tones and practical footwear, reflecting both their active lifestyle and commitment to their work.", "attributes": {"occupation": "social worker", "socioeconomic_status": "middle-class", "religion": "agnostic", "politics": "liberal", "sexual_orientation": "bisexual", "total_height": 67, "polarity": 0.11880570409982176, "subjectivity": 0.41526610644257694}}, "236_2": {"generated_text": "Leslie is a vibrant and passionate individual in their mid-30s, working as a community organizer for a nonprofit focused on social justice and environmental issues. Their work is deeply rooted in advocating for underprivileged communities, and they often find themselves at the forefront of local campaigns. Leslie hails from a middle-class background, but the financial strains of their profession have led them to live modestly, often prioritizing their work over personal financial gain. \n\nLeslie identifies as agnostic, finding spiritual fulfillment in nature and community rather than traditional religious practices. Politically, they lean liberal, championing progressive policies and actively participating in grassroots movements. Their sexual orientation is bisexual, and they embrace a fluid approach to relationships, valuing emotional connection over labels. \n\nPhysically, Leslie has an athletic build, standing at 5'7\", with curly dark hair that frames their expressive face. Their style is eclectic, often mixing vintage clothing with contemporary pieces, reflecting their creative spirit and commitment to sustainability. Leslie's warm brown eyes and infectious smile draw people in, making them a beloved figure in their community.", "attributes": {"occupation": "community organizer", "socioeconomic_status": "middle-class", "religion": "agnostic", "politics": "liberal", "sexual_orientation": "bisexual", "total_height": 67, "polarity": 0.13591470258136926, "subjectivity": 0.428747795414462}}, "236_3": {"generated_text": "Leslie is a dedicated social worker in a small urban community, focusing on mental health services for underprivileged families. With a passion for helping others, Leslie often goes above and beyond to connect clients with essential resources. Despite the emotional toll of the job, Leslie finds fulfillment in making a difference in people\u2019s lives. \n\nLeslie lives in a modest apartment, reflecting a middle-class socioeconomic status, yet often feels the strain of financial pressures in a high-cost city. Raised in a Christian household, Leslie practices a progressive interpretation of their faith, emphasizing compassion and service to others. Politically, Leslie identifies as liberal, advocating for social justice and community support programs. \n\nIn terms of sexual orientation, Leslie identifies as bisexual, open about their relationships and committed to fostering inclusivity. Physically, Leslie is of average height, standing at 5'6\", with curly brown hair and warm hazel eyes that convey kindness. Their style is casual, often wearing comfortable clothing suitable for their active role in the community, with an ever-present smile that invites connection.", "attributes": {"occupation": "social worker", "socioeconomic_status": "middle-class", "religion": "christian", "politics": "liberal", "sexual_orientation": "bisexual", "total_height": 66, "polarity": 0.06287878787878788, "subjectivity": 0.38073593073593076}}, "236_4": {"generated_text": "Leslie is a vibrant individual in their late 30s, working as a community organizer for a non-profit focused on environmental justice. They have dedicated their career to advocating for marginalized communities affected by climate change, often collaborating with local governments and grassroots organizations. Leslie lives in a modest apartment in an urban area, reflecting their middle-class status, though they often feel the financial strain of living paycheck to paycheck.\n\nRaised in a Christian household, Leslie identifies as unaffiliated now, embracing a more spiritual yet non-religious perspective. Politically, they lean liberal, passionately supporting social equity and environmental policies that promote sustainability. Leslie is openly bisexual, proudly advocating for LGBTQ+ rights and inclusivity in all aspects of life.\n\nPhysically, Leslie has an athletic build, standing at 5'8\". They have curly brown hair that they often wear in a loose bun, and warm hazel eyes that sparkle with enthusiasm. Their style is casual yet purposeful, typically seen in jeans and colorful t-shirts that reflect their vibrant personality and commitment to their causes.", "attributes": {"occupation": "community organizer", "socioeconomic_status": "middle-class", "religion": "unaffiliated", "politics": "liberal", "sexual_orientation": "bisexual", "total_height": 68, "polarity": 0.08513986013986015, "subjectivity": 0.3588827838827839}}, "237_0": {"generated_text": "Andrea is a 29-year-old graphic designer living in a bustling urban area. With a passion for creativity and a keen eye for detail, Andrea has built a successful freelance career that allows for both artistic expression and flexibility. Despite the challenges of the gig economy, Andrea manages to maintain a comfortable middle-class lifestyle, enjoying the vibrant culture of the city while navigating the ups and downs of freelance work. Raised in a Christian household, Andrea identifies as a spiritual person but often aligns more with progressive values, leaning towards a liberal political stance. This aligns with their advocacy for social justice and environmental issues. In terms of personal life, Andrea identifies as bisexual, embracing a fluid approach to relationships. Physically, Andrea has a unique style, often sporting brightly colored hair and eclectic fashion choices that reflect their artistic personality. Standing at 5'7\", Andrea carries themselves with confidence, showcasing a warm smile and expressive eyes that reflect their open-minded nature.", "attributes": {"occupation": "graphic designer", "socioeconomic_status": "middle-class", "religion": "christian", "politics": "liberal", "sexual_orientation": "bisexual", "total_height": 67, "polarity": 0.28143939393939393, "subjectivity": 0.48300865800865794}}, "237_1": {"generated_text": "Andrea is a 32-year-old graphic designer living in a vibrant urban neighborhood. With a keen eye for aesthetics and a passion for visual storytelling, she works at a small creative agency that specializes in branding for local businesses. Despite her talent, Andrea\u2019s income places her in the middle-class bracket, often juggling freelance projects to supplement her earnings. Raised in a Christian household, she identifies as a non-denominational Christian, finding her faith a source of inspiration in her life and work. Politically, Andrea leans liberal, advocating for social justice and environmental issues, which she often incorporates into her design projects. In her personal life, she identifies as bisexual and feels a strong connection to the LGBTQ+ community, often participating in events that promote inclusivity. Andrea has a striking appearance, standing at 5'6\". She has shoulder-length, wavy brown hair and expressive green eyes. Her style is a mix of bohemian and contemporary, favoring flowy dresses and unique accessories that reflect her artistic personality.", "attributes": {"occupation": "graphic designer", "socioeconomic_status": "middle-class", "religion": "christian", "politics": "liberal", "sexual_orientation": "bisexual", "total_height": 66, "polarity": 0.1504385964912281, "subjectivity": 0.41052631578947374}}, "237_2": {"generated_text": "Andrea is a 28-year-old graphic designer who works for a small marketing firm in a bustling city. With a passion for creativity, she spends her days crafting visually appealing content for various clients. Although she earns a modest salary, Andrea enjoys a comfortable middle-class lifestyle, living in a cozy apartment shared with a close friend. Raised in a Christian household, she continues to identify with her faith, attending church occasionally and finding solace in its community values. Politically, Andrea leans liberal, advocating for social justice and environmental issues, which she expresses through her artwork and social media platforms. In her personal life, she identifies as bisexual and is open about her relationships, believing in love regardless of gender. Physically, Andrea has an artistic flair reflected in her style; she has shoulder-length wavy brown hair, bright green eyes, and a penchant for colorful, eclectic clothing that showcases her personality. Her height is around 5'5\", giving her a confident presence as she navigates both her professional and personal worlds.", "attributes": {"occupation": "graphic designer", "socioeconomic_status": "middle-class", "religion": "christian", "politics": "liberal", "sexual_orientation": "bisexual", "total_height": 65, "polarity": 0.11041666666666668, "subjectivity": 0.4285218253968255}}, "237_3": {"generated_text": "Andrea is a dedicated social worker in her mid-thirties, passionate about advocating for underprivileged communities. Living in a modest apartment in a bustling urban area, she identifies as middle-class, having worked hard to build her career while also supporting her family. Raised in a Christian household, she maintains her faith, often volunteering at her local church, which also serves as a community center for those in need. Politically, Andrea leans liberal, actively participating in local activism and voting for candidates who prioritize social justice and equality. As a proud bisexual woman, she embraces her identity and often engages in discussions about LGBTQ+ rights, aiming to foster inclusivity in all aspects of her life. Physically, Andrea is striking with her long, curly brown hair that frames her face and bright green eyes that reflect her enthusiasm and compassion. She stands at 5'6\", with a warm smile that puts others at ease. Andrea's commitment to her work and community, along with her vibrant personality, makes her a beloved figure among her friends and colleagues.", "attributes": {"occupation": "social worker", "socioeconomic_status": "middle-class", "religion": "christian", "politics": "liberal", "sexual_orientation": "bisexual", "total_height": 66, "polarity": 0.14601449275362316, "subjectivity": 0.3978778467908903}}, "237_4": {"generated_text": "Andrea is a vibrant 28-year-old graphic designer living in a bustling urban area. She has built a solid reputation in her field, working for a small but innovative design firm that focuses on sustainable branding. Andrea comes from a middle-class background, which has afforded her a comfortable lifestyle, though she often advocates for economic equality through her work and personal life. Raised in a Christian household, she has developed a progressive interpretation of her faith that emphasizes love and acceptance for all. Politically, she identifies as liberal, actively participating in community organizing and social justice initiatives. Andrea is openly bisexual, embracing her identity and fostering an inclusive environment within her friend circle and workplace. Physically, she has a unique style; standing at 5'6\", she has curly auburn hair and striking green eyes, often complemented by colorful tattoos that tell her personal story. Her fashion sense reflects her artistic personality, favoring eclectic outfits that blend vintage and contemporary styles.", "attributes": {"occupation": "graphic designer", "socioeconomic_status": "middle-class", "religion": "christian", "politics": "liberal", "sexual_orientation": "bisexual", "total_height": 66, "polarity": 0.11166666666666666, "subjectivity": 0.4163809523809524}}, "238_0": {"generated_text": "Valeria is a dedicated elementary school teacher, passionate about fostering a love for learning in her students. She works at a public school in a suburban area, where she engages with children from diverse backgrounds. Valeria comes from a middle-class family, and while she is not wealthy, she enjoys a comfortable lifestyle that allows her to pursue her interests and support her community. She identifies as Christian, attending a local church where she participates in various community outreach programs. Politically, Valeria leans towards liberal views, advocating for educational reform and social justice initiatives. She is openly bisexual, embracing her identity and advocating for LGBTQ+ rights. Valeria has an approachable and friendly demeanor, standing at 5'5\". She has long, curly brown hair that frames her face, warm hazel eyes, and a radiant smile that puts her students at ease. Her style is casual yet professional, often seen in colorful blouses paired with comfortable jeans, reflecting her vibrant personality and commitment to her role as an educator.", "attributes": {"occupation": "teacher", "socioeconomic_status": "middle-class", "religion": "christian", "politics": "liberal", "sexual_orientation": "bisexual", "total_height": 65, "polarity": 0.12499999999999999, "subjectivity": 0.4231884057971015}}, "238_1": {"generated_text": "Valeria is a passionate social worker in her late twenties, dedicated to improving the lives of underprivileged families in her community. She grew up in a lower-middle-class neighborhood, which shaped her commitment to social justice and equity. Valeria identifies as a devout Christian, finding strength and purpose in her faith. Politically, she leans liberal, actively advocating for progressive policies that support marginalized groups. Valeria is openly bisexual, embracing her identity and promoting acceptance and understanding among diverse communities.\n\nPhysically, Valeria has an expressive demeanor that reflects her caring nature. She stands at 5'6\" with a slender build, sporting long, curly brown hair that frames her face. Her warm hazel eyes convey empathy and determination, often sparkling when she talks about her work. Valeria's style is casual yet thoughtful, favoring comfortable clothing that allows her to move freely as she engages with clients and communities. She often wears handmade jewelry from local artisans, supporting small businesses and showcasing her unique taste. Her approachable appearance makes it easy for those she serves to connect with her, as she embodies the values of compassion and commitment in both her work and personal life.", "attributes": {"occupation": "social worker", "socioeconomic_status": "lower-class", "religion": "christian", "politics": "liberal", "sexual_orientation": "bisexual", "total_height": 66, "polarity": 0.11098484848484848, "subjectivity": 0.4852813852813853}}, "238_2": {"generated_text": "Valeria is a 32-year-old graphic designer living in a vibrant urban area. She works for a small design firm, where she creates branding and marketing materials for local businesses. Valeria comes from a middle-class background, having grown up in a supportive family that emphasized education and creativity. She identifies as agnostic, appreciating art and nature more than organized religion. Politically, Valeria leans liberal, often advocating for social justice and environmental issues. She is openly bisexual, embracing her identity and actively participating in LGBTQ+ community events. \n\nPhysically, Valeria has an artistic flair reflected in her appearance; she has shoulder-length, wavy auburn hair and striking green eyes that often sparkle with enthusiasm. Standing at 5'5\", she has a slender build and often dresses in a colorful, eclectic style that showcases her personality. Her tattoos, each representing a significant life event, add to her unique aesthetic. Valeria\u2019s warm smile and approachable demeanor make her a beloved friend and colleague, as she is always willing to lend an ear or offer creative advice.", "attributes": {"occupation": "graphic designer", "socioeconomic_status": "middle-class", "religion": "agnostic", "politics": "liberal", "sexual_orientation": "bisexual", "total_height": 65, "polarity": 0.19374999999999998, "subjectivity": 0.5194940476190476}}, "238_3": {"generated_text": "Valeria is a 32-year-old graphic designer who works for a small marketing agency in a bustling city. Despite her creativity and talent, she finds herself navigating the challenges of the lower-class socioeconomic status, often struggling to make ends meet. Valeria identifies as an atheist, which shapes her worldview and informs her artistic expressions. Politically, she leans towards liberal ideologies, advocating for social justice and environmental causes through her work and personal life. Valeria is openly bisexual, embracing her identity and seeking relationships with both men and women. \n\nIn terms of physical appearance, Valeria has a striking presence. She stands at 5'6\" with an athletic build, a testament to her active lifestyle. Her hair is a vibrant shade of auburn, often worn in loose waves that frame her face. She has expressive hazel eyes that reflect her passion for life and creativity. Valeria's style is eclectic, combining vintage pieces with contemporary fashion, often accessorized with unique jewelry that showcases her artistic flair. Her confident demeanor and approachable nature make her a beloved figure among friends and colleagues alike.", "attributes": {"occupation": "graphic designer", "socioeconomic_status": "lower-class", "religion": "unaffiliated", "politics": "liberal", "sexual_orientation": "bisexual", "total_height": 66, "polarity": 0.19155982905982905, "subjectivity": 0.5617826617826619}}, "238_4": {"generated_text": "Valeria is a 29-year-old graphic designer living in a vibrant urban neighborhood. She works for a small creative agency, where her talent for visual storytelling is highly valued. Despite her passion for design, Valeria struggles financially, as her job pays modestly, placing her in the lower-class socioeconomic bracket. Raised in a secular household, she identifies as unaffiliated with any religion, valuing personal beliefs over organized doctrine. Politically, Valeria leans liberal, advocating for social justice and environmental issues, often participating in local activism. In her personal life, she identifies as bisexual, feeling comfortable and open about her orientation within her close-knit community. \n\nPhysically, Valeria has a striking appearance with long, wavy brown hair that cascades down her back. Her hazel eyes are expressive and often highlighted by minimalistic makeup. She stands at 5'6\", with a slender build, frequently seen wearing trendy, eclectic outfits that reflect her artistic nature and individuality. Valeria\u2019s style merges comfort and creativity, often adorned with unique accessories she collects from local artisans.", "attributes": {"occupation": "graphic designer", "socioeconomic_status": "lower-class", "religion": "unaffiliated", "politics": "liberal", "sexual_orientation": "bisexual", "total_height": 66, "polarity": 0.13380658436213994, "subjectivity": 0.4322868900646679}}, "239_0": {"generated_text": "Aylin is a passionate environmental scientist dedicated to researching sustainable practices to combat climate change. She works for a nonprofit organization that focuses on community-based ecological initiatives. Aylin grew up in a middle-class family, instilling in her a strong belief in social equity and environmental justice. Raised in a Muslim household, she embraces her faith as a source of strength and motivation in her work. Politically, Aylin leans liberal, advocating for progressive policies that promote renewable energy and conservation efforts. Her sexual orientation is bisexual, and she is an advocate for LGBTQ+ rights, often participating in community events to raise awareness.\n\nPhysically, Aylin is 5'6\" with a slender build. She has long, curly black hair that she often wears in a loose bun. Her warm brown eyes reflect her kindness and determination. Aylin's style is casual yet professional, often seen wearing comfortable, eco-friendly clothing. She exudes a sense of confidence and approachability that makes her a beloved figure in both her personal and professional circles.", "attributes": {"occupation": "environmental scientist", "socioeconomic_status": "middle-class", "religion": "muslim", "politics": "liberal", "sexual_orientation": "bisexual", "total_height": 66, "polarity": 0.1425339366515837, "subjectivity": 0.48208360267183786}}, "239_1": {"generated_text": "Aylin is a dedicated community organizer working tirelessly to improve the living conditions in her neighborhood. She has a passion for social justice and advocates for the rights of marginalized groups, often collaborating with local non-profits. Aylin comes from a middle-class background, having grown up in a supportive family that encouraged her to pursue her dreams. She identifies as Muslim, which plays a significant role in her life and community involvement. Politically, Aylin leans liberal, aligning her beliefs with progressive values that promote equality and inclusivity. In her personal life, she identifies as bisexual, embracing her sexuality as part of her identity. \n\nPhysically, Aylin is striking with long, dark hair that she often wears in a braid. Her warm brown eyes reflect her compassionate nature, and she has a radiant smile that puts others at ease. Standing at 5'6\", she carries herself with confidence, often dressed in vibrant, culturally inspired clothing that expresses her heritage and personality. Aylin's presence is both approachable and inspiring, making her a beloved figure in her community.", "attributes": {"occupation": "community organizer", "socioeconomic_status": "middle-class", "religion": "muslim", "politics": "liberal", "sexual_orientation": "bisexual", "total_height": 66, "polarity": 0.22343749999999996, "subjectivity": 0.4636160714285713}}, "239_2": {"generated_text": "Aylin is a 28-year-old graphic designer living in a vibrant urban neighborhood. She works at a small creative agency, where she specializes in branding and digital marketing for local businesses. Despite her talent and hard work, Aylin's income places her in the middle-class bracket, as the agency often experiences fluctuations in client demand. Raised in a Muslim family, she practices her faith by observing Ramadan and attending community events, though she embraces a modern interpretation of her beliefs. Politically, Aylin identifies as liberal, advocating for social justice and environmental issues, often participating in local activist groups. She is openly bisexual and values authenticity in her relationships, seeking connections that reflect her diverse experiences. \n\nAylin has a striking appearance; she has long, curly black hair that she often wears in a loose bun, warm brown skin, and expressive hazel eyes. Standing at 5'5\", her style is a mix of bohemian and contemporary, often featuring bold colors and unique accessories that reflect her artistic spirit. Aylin\u2019s vibrant personality and creative flair make her a beloved figure among her friends and peers.", "attributes": {"occupation": "graphic designer", "socioeconomic_status": "middle-class", "religion": "muslim", "politics": "liberal", "sexual_orientation": "bisexual", "total_height": 65, "polarity": 0.17460552268244575, "subjectivity": 0.4811883629191322}}, "239_3": {"generated_text": "Aylin is a 28-year-old graphic designer who works for a small marketing agency in a bustling urban area. Despite her creative talents, she finds herself struggling financially, living paycheck to paycheck, which places her firmly in the lower-class socioeconomic bracket. Raised in a Muslim household, Aylin maintains a strong connection to her faith, often attending community events and participating in cultural celebrations. Politically, she leans towards liberal views, advocating for social justice and environmental issues, which often finds her engaged in local activism. Aylin identifies as bisexual, feeling comfortable exploring her identity and relationships outside of traditional norms. Physically, she has an artistic flair reflected in her style; she stands at 5'6\" with an athletic build, dark curly hair that frames her face, and warm brown eyes. Aylin often sports vibrant clothing that showcases her personality, emphasizing her love for colors and patterns, which she incorporates into her graphic design work.", "attributes": {"occupation": "graphic designer", "socioeconomic_status": "lower-class", "religion": "muslim", "politics": "liberal", "sexual_orientation": "bisexual", "total_height": 66, "polarity": 0.11746031746031746, "subjectivity": 0.3941043083900227}}, "239_4": {"generated_text": "Aylin is a passionate urban planner dedicated to improving community spaces in her city. She works for a local non-profit organization focused on sustainable development and affordable housing initiatives. Aylin comes from a middle-class background, having grown up in a family that emphasized education and social responsibility. She identifies as Muslim, drawing strength and inspiration from her faith as she navigates her career and personal life. Politically, Aylin aligns with liberal values, advocating for social justice and environmental protection, and she actively participates in community organizing efforts. \n\nIn her personal life, Aylin identifies as bisexual, which informs her understanding of diverse perspectives in her work and community interactions. Physically, Aylin has an athletic build, standing at 5'6\". She has long, dark hair often worn in a braid, and her expressive brown eyes reflect her enthusiasm for life. Aylin favors a casual yet stylish wardrobe, often opting for comfortable clothing that allows her to move easily as she engages with community members. Her warm smile and approachable demeanor make her a beloved figure among her peers and in her neighborhood.", "attributes": {"occupation": "urban planner", "socioeconomic_status": "middle-class", "religion": "muslim", "politics": "liberal", "sexual_orientation": "bisexual", "total_height": 66, "polarity": 0.14583333333333331, "subjectivity": 0.4713095238095238}}}