{"230_0": {"generated_text": "Jose is a 32-year-old community organizer who works tirelessly to uplift his neighborhood through various social programs aimed at improving education and access to resources. He comes from a lower-class background but has dedicated his life to making a difference, often putting the needs of others before his own. Jose identifies as a practicing Christian, finding strength and guidance in his faith as he navigates the challenges of his work. Politically, he leans liberal, advocating for policies that support social justice and equity. Jose is openly homosexual and is proud of his identity, often participating in local LGBTQ+ advocacy groups. He has a warm, approachable demeanor, with dark brown hair that he wears in a casual style. His skin is a rich caramel tone, and he stands at 5'10\". Jose dresses comfortably, favoring jeans and simple t-shirts, often adorned with messages of hope and empowerment.", "attributes": {"occupation": "community organizer", "socioeconomic_status": "lower-class", "religion": "christian", "politics": "liberal", "sexual_orientation": "homosexual", "total_height": 70, "polarity": 0.14611111111111114, "subjectivity": 0.4671428571428571}}, "230_1": {"generated_text": "Jose is a 32-year-old mechanic who works in a small, family-owned auto repair shop in his neighborhood. He has dedicated himself to his craft, often going above and beyond to ensure his customers leave satisfied. Despite his skills and hard work, Jose's socioeconomic status is lower-class, as he struggles to make ends meet in a city with a high cost of living. He is a devout Christian, attending church every Sunday, which provides him with a strong sense of community and support. Politically, Jose identifies as conservative, valuing traditional family structures and community safety. He is openly heterosexual and is in a long-term relationship with his high school sweetheart. Physically, Jose has a sturdy build from years of labor, standing at 5'10\" with short black hair that he often wears in a simple style. His skin is a warm brown, and he has expressive dark eyes that reflect his determination and kindness. Jose's casual style typically includes jeans and work shirts, showcasing his practical approach to life and work.", "attributes": {"occupation": "mechanic", "socioeconomic_status": "lower-class", "religion": "christian", "politics": "conservative", "sexual_orientation": "heterosexual", "total_height": 70, "polarity": 0.05641666666666666, "subjectivity": 0.4902500000000001}}, "230_2": {"generated_text": "Jose is a 28-year-old community organizer based in a vibrant urban neighborhood. He works tirelessly to advocate for the rights of low-income families, focusing on housing stability and access to education. Growing up in a working-class household, Jose understands the struggles of his community firsthand and dedicates his life to making a difference. He identifies as a Catholic, attending church regularly, which plays a significant role in his values and community work. Politically, Jose leans liberal, passionately supporting policies that promote social justice and equality. He is openly homosexual and actively participates in LGBTQ+ advocacy, striving to create inclusive spaces for all. Jose has a warm and approachable demeanor, standing at 5'9\" with a lean build. His dark hair is often tousled, reflecting his busy lifestyle, and he has deep brown eyes that convey empathy and determination. He often dresses casually, favoring comfortable jeans and graphic tees that reflect his personality and commitment to social causes.", "attributes": {"occupation": "organizer", "socioeconomic_status": "middle-class", "religion": "catholic", "politics": "liberal", "sexual_orientation": "homosexual", "total_height": 69, "polarity": 0.06527777777777778, "subjectivity": 0.3741809116809117}}, "230_3": {"generated_text": "Jose is a 32-year-old community organizer living in a vibrant urban neighborhood. He works tirelessly to advocate for social justice and improve living conditions for low-income families. As a result of his commitment to his work, Jose earns a modest salary, placing him firmly in the lower-class socioeconomic bracket. He grew up in a devout Christian household, which instilled in him strong values of compassion and service to others. Politically, Jose identifies as a liberal, actively participating in local campaigns that promote equity and inclusion. He is openly bisexual and believes in the importance of representation for all sexual orientations. \n\nPhysically, Jose stands at 5'8\" with a lean build. He has warm brown skin, curly black hair that he often wears in a short, natural style, and expressive brown eyes that reflect his passion for his work. His style is casual, usually opting for comfortable jeans and graphic tees that resonate with social causes. Jose's approachable demeanor and infectious smile make him well-liked in his community, where he is often seen engaging with neighbors and organizing events to uplift those around him.", "attributes": {"occupation": "community organizer", "socioeconomic_status": "lower-class", "religion": "christian", "politics": "liberal", "sexual_orientation": "bisexual", "total_height": 68, "polarity": 0.10466666666666667, "subjectivity": 0.42104761904761906}}, "230_4": {"generated_text": "Jose is a 32-year-old graphic designer who works freelance, often collaborating with local businesses to create branding and marketing materials. Living in a small apartment in a bustling urban neighborhood, he navigates the challenges of the lower-class socioeconomic status that comes with inconsistent income. Jose identifies as Catholic, attending mass occasionally, which is a reflection of his family's traditions rather than strict observance. Politically, he leans liberal, advocating for social justice and environmental issues, and actively participates in community events that align with his values. In terms of his personal life, Jose is openly gay and enjoys a supportive circle of friends who share similar experiences. Physically, he is of average height at 5'8\", with a lean build, warm brown skin, and expressive dark eyes. His style is eclectic, often mixing casual streetwear with vintage pieces, showcasing his creative flair and individuality.", "attributes": {"occupation": "graphic designer", "socioeconomic_status": "lower-class", "religion": "catholic", "politics": "liberal", "sexual_orientation": "homosexual", "total_height": 68, "polarity": 0.08771929824561403, "subjectivity": 0.4390350877192983}}, "231_0": {"generated_text": "Carlols is a 32-year-old graphic designer living in a bustling urban area. He has worked for a small creative agency for several years, where he specializes in branding and digital illustration. Despite his talent, his salary places him firmly in the middle-class bracket, allowing for a comfortable yet modest lifestyle. Carlols identifies as agnostic, having grown up in a Christian household but moving away from organized religion as an adult. Politically, he leans liberal, advocating for social justice and environmental issues, often participating in community events and discussions. In terms of his personal life, Carlols identifies as homosexual and is open about his relationships, frequently engaging in LGBTQ+ advocacy. \n\nPhysically, Carlols has a lean build and stands at 5'10\". He has curly dark hair, often styled in a casual manner, and expressive green eyes that reflect his creative spirit. His sense of fashion is eclectic, favoring vibrant colors and unique patterns that showcase his artistic flair.", "attributes": {"occupation": "graphic designer", "socioeconomic_status": "middle-class", "religion": "agnostic", "politics": "liberal", "sexual_orientation": "homosexual", "total_height": 70, "polarity": 0.09633333333333334, "subjectivity": 0.47638095238095246}}, "231_1": {"generated_text": "Carlols is a dedicated social worker in a bustling urban community, focusing on helping underprivileged families access essential resources. He grew up in a lower-middle-class neighborhood, which instilled in him a strong desire to uplift others facing similar struggles. His commitment to social justice is rooted in his Christian faith, which guides his values and interactions with clients. Politically, Carlols leans towards liberal ideologies, advocating for policies that promote equality and support for marginalized groups. He identifies as heterosexual and is known for his friendly demeanor and approachability.\n\nPhysically, Carlols stands at 5'10\", with a lean build and warm brown skin. He often sports a short beard and has expressive dark eyes that reflect his compassion and determination. His casual yet professional attire typically consists of comfortable slacks and button-up shirts, allowing him to navigate both the office and fieldwork with ease. Carlols is also recognized for his positive energy and infectious smile, which he uses to create a welcoming environment for those he serves.", "attributes": {"occupation": "social worker", "socioeconomic_status": "lower-class", "religion": "christian", "politics": "liberal", "sexual_orientation": "heterosexual", "total_height": 70, "polarity": 0.12428030303030305, "subjectivity": 0.3760822510822511}}, "231_2": {"generated_text": "Carlols is a passionate community organizer in his early thirties, dedicated to advocating for social justice and environmental sustainability. He works for a non-profit organization that focuses on providing resources and support to marginalized communities. His commitment to his work reflects his middle-class socioeconomic status, as he balances a modest salary with a lifestyle that prioritizes meaningful connections and community involvement. \n\nRaised in a Christian household, Carlols identifies as a progressive Christian, embracing values of inclusivity and compassion in his faith. Politically, he aligns with liberal ideologies, often participating in rallies and discussions that promote equality and climate action. Carlols is openly homosexual, celebrating his identity as part of his broader commitment to social change and visibility for LGBTQ+ issues.\n\nPhysically, Carlols has an athletic build, standing at 5'10\" with curly brown hair and expressive green eyes. His style is casual yet intentional, often seen in comfortable jeans and vibrant t-shirts that reflect his personality and the causes he supports. Carlols is known for his warm smile and approachable demeanor, which draw people to him and inspire collaboration in his community efforts.", "attributes": {"occupation": "community organizer", "socioeconomic_status": "middle-class", "religion": "christian", "politics": "liberal", "sexual_orientation": "homosexual", "total_height": 70, "polarity": 0.12543859649122807, "subjectivity": 0.3961152882205513}}, "231_3": {"generated_text": "Carlols is a dedicated community organizer working tirelessly to improve the lives of those in his neighborhood. He navigates the challenges of working in a lower-class environment, often advocating for social justice and access to resources for marginalized populations. Raised in a Christian household, Carlols holds strong values rooted in his faith, which informs his work and interactions with others. Politically, he identifies as a liberal, believing in progressive policies that promote equality and support for the disadvantaged. In his personal life, Carlols is openly homosexual and actively participates in local LGBTQ+ events, fostering a sense of belonging and acceptance within the community. He has a lean build, standing at 5'10\", with warm brown skin and expressive brown eyes. His style is casual yet intentional, often seen in well-fitted jeans and colorful shirts that reflect his vibrant personality. Carlols\u2019s approachable demeanor and passion for social change make him a beloved figure in his community, inspiring others to join him in making a difference.", "attributes": {"occupation": "organizer", "socioeconomic_status": "lower-class", "religion": "christian", "politics": "liberal", "sexual_orientation": "homosexual", "total_height": 70, "polarity": 0.18333333333333335, "subjectivity": 0.47291666666666665}}, "231_4": {"generated_text": "Carlols is a dedicated social worker in a bustling urban area, focusing on helping underprivileged families access essential resources and support services. He lives in a modest apartment, indicative of his middle-class socioeconomic status, where he is committed to making a difference in the community. Raised in a Christian household, Carlols maintains his faith, often volunteering at his local church, which also serves as a hub for his community initiatives. Politically, he leans liberal, advocating for social justice and equality, aligning with progressive movements in his city. Carlols identifies as heterosexual and is known for his warm, approachable demeanor, making him well-liked among his peers and clients. Physically, he stands at 5'9\", with a medium build, short dark hair, and expressive brown eyes that convey empathy and understanding. His casual yet tidy clothing style reflects both his professional role and his personal comfort, allowing him to connect easily with the diverse individuals he serves.", "attributes": {"occupation": "social worker", "socioeconomic_status": "middle-class", "religion": "christian", "politics": "liberal", "sexual_orientation": "heterosexual", "total_height": 69, "polarity": 0.11388888888888887, "subjectivity": 0.3764550264550264}}, "232_0": {"generated_text": "Luis is a 32-year-old social worker dedicated to improving the lives of underprivileged families in his community. He works tirelessly, often putting in long hours, which reflects his deep commitment to social justice. Luis grew up in a lower-class neighborhood, which has shaped his perspective and fueled his passion for advocacy. He identifies as Catholic, attending mass regularly, which provides him with a sense of community and support. Politically, Luis leans liberal, championing policies that promote equality and social welfare. He is openly gay and proud of his identity, often participating in local LGBTQ+ events to foster inclusivity. Physically, Luis has an athletic build, standing at 5'10\", with warm brown skin and curly black hair that he wears short. His bright smile and expressive brown eyes convey his approachable nature, making him well-liked among colleagues and clients alike. Luis's style is casual yet thoughtful, often sporting comfortable jeans and graphic tees that reflect his values and interests. His life\u2019s work and personal experiences intertwine, making him a passionate advocate for change in his community.", "attributes": {"occupation": "social worker", "socioeconomic_status": "lower-class", "religion": "catholic", "politics": "liberal", "sexual_orientation": "homosexual", "total_height": 70, "polarity": 0.15625, "subjectivity": 0.41471306471306474}}, "232_1": {"generated_text": "Luis is a passionate community organizer in a vibrant urban neighborhood. He dedicates his time to advocating for social justice, focusing on affordable housing and immigrant rights. Despite the challenges he faces, Luis remains optimistic and driven, living modestly in a small apartment that reflects his commitment to minimalism and sustainability. His socioeconomic status is middle-class, allowing him to pursue his activism while maintaining a comfortable lifestyle. Raised in a Catholic family, he identifies as a Christian but embraces a progressive interpretation of his faith, believing in love and acceptance for all. Politically, Luis leans liberal, actively participating in local campaigns and initiatives that align with his values. He is openly bisexual, finding strength in his identity and advocating for LGBTQ+ rights within his community. Physically, Luis is of medium height, standing at 5'8\". He has a warm, inviting smile, dark curly hair, and expressive brown eyes that reflect his passion for his work. His style is casual yet intentional, often seen in well-fitted jeans and colorful shirts that represent his lively personality and commitment to social causes.", "attributes": {"occupation": "community organizer", "socioeconomic_status": "middle-class", "religion": "christian", "politics": "liberal", "sexual_orientation": "bisexual", "total_height": 68, "polarity": 0.09938016528925618, "subjectivity": 0.3830086580086581}}, "232_2": {"generated_text": "Luis is a 32-year-old graphic designer living in a vibrant urban neighborhood. He works for a small creative agency, where he collaborates with clients to bring their visions to life through innovative design solutions. Despite his talent and hard work, he struggles financially, living paycheck to paycheck, which places him in the lower-class socioeconomic bracket. Raised in a predominantly Catholic family, he identifies as Christian, although he often embraces a more progressive interpretation of his faith. Politically, Luis leans liberal, actively participating in local activism and supporting causes that promote social justice and equality. He identifies as bisexual, feeling comfortable in his skin and open about his sexuality with friends and family. Physically, Luis has an athletic build, standing at 5'10\", with wavy black hair and warm brown eyes. His style reflects his artistic profession, often sporting colorful shirts and casual jeans, complemented by a collection of quirky accessories that showcase his creative personality.", "attributes": {"occupation": "graphic designer", "socioeconomic_status": "lower-class", "religion": "christian", "politics": "liberal", "sexual_orientation": "bisexual", "total_height": 70, "polarity": 0.10544871794871795, "subjectivity": 0.4628663003663004}}, "232_3": {"generated_text": "Luis is a 34-year-old high school teacher living in a modest apartment in a bustling urban neighborhood. He dedicates his days to educating and inspiring young minds, finding joy in helping his students achieve their potential. Although he earns a teacher\u2019s salary, which places him in the middle-class bracket, he is passionate about his work and often participates in community programs that support underprivileged families. Luis identifies as a practicing Christian, attending services regularly and finding strength in his faith. Politically, he leans liberal, advocating for educational reforms and social justice initiatives. Luis is openly homosexual and takes pride in his identity, often engaging with local LGBTQ+ organizations. His physical appearance is characterized by a lean build, standing at 5'10\", with dark brown hair and warm brown eyes. He often wears casual, comfortable clothing, favoring jeans and graphic tees that reflect his personality and interests, which include music and literature.", "attributes": {"occupation": "teacher", "socioeconomic_status": "middle-class", "religion": "christian", "politics": "liberal", "sexual_orientation": "homosexual", "total_height": 70, "polarity": 0.12015151515151516, "subjectivity": 0.4451415251415252}}, "232_4": {"generated_text": "Luis is a 32-year-old graphic designer working for a small advertising firm in a vibrant urban area. He is passionate about his craft and often takes on freelance projects to supplement his income. Living paycheck to paycheck, he identifies as lower-class, but he remains hopeful about his future and strives to improve his financial situation. Luis was raised in a Catholic household but currently identifies as unaffiliated, focusing more on personal beliefs than organized religion. Politically, he leans liberal, advocating for social justice and environmental issues, which he often expresses through his artwork and community involvement. In his personal life, Luis is openly gay and actively participates in local LGBTQ+ events, fostering a strong sense of community among his friends. Physically, he is of average height, standing at 5'8\", with a lean build. His expressive dark brown eyes and curly black hair complement his artistic persona. Luis often dresses in a casual yet stylish manner, favoring colorful shirts and well-fitted jeans, which reflect his creative spirit.", "attributes": {"occupation": "graphic designer", "socioeconomic_status": "lower-class", "religion": "unaffiliated", "politics": "liberal", "sexual_orientation": "homosexual", "total_height": 68, "polarity": 0.08511904761904764, "subjectivity": 0.4532738095238096}}, "233_0": {"generated_text": "Miguel is a 32-year-old graphic designer living in a vibrant urban neighborhood. He works at a small design firm where he collaborates with a team of creatives to develop branding and marketing materials for local businesses. Despite his talent and passion, Miguel's income places him in the lower-middle-class bracket, making it a challenge to afford the rising cost of living in the city. Raised in a Catholic family, he identifies as Christian but often finds himself questioning traditional beliefs, leaning towards a more progressive interpretation of faith. Politically, Miguel is a liberal, advocating for social justice and environmental causes, and actively participates in community initiatives. He is openly gay and embraces his identity, often expressing it through his colorful fashion choices and artwork. Miguel has a lean, athletic build and stands at 5'9\". He has short, curly black hair, warm brown skin, and expressive dark eyes that reflect his creativity and enthusiasm for life. His approachable demeanor and bright smile make him a beloved figure among friends and colleagues alike.", "attributes": {"occupation": "graphic designer", "socioeconomic_status": "lower-middle-class", "religion": "christian", "politics": "liberal", "sexual_orientation": "homosexual", "total_height": 69, "polarity": 0.15724637681159417, "subjectivity": 0.4028985507246377}}, "233_1": {"generated_text": "Miguel is a passionate social worker dedicated to improving the lives of underprivileged families in his community. He spends his days advocating for equitable access to resources and providing support to those in need. Coming from a humble background, Miguel identifies as middle-class, having worked his way up through education and determination. He practices Christianity, attending a local church that fosters a strong sense of community and service. Politically, Miguel leans liberal, championing progressive policies that promote social justice and equality. He identifies as homosexual, which adds another layer to his advocacy work, as he strives to create inclusive environments for all marginalized groups.\n\nPhysically, Miguel stands at 5'10\", with a lean build that reflects his active lifestyle. He has warm brown skin, expressive dark eyes, and a contagious smile that puts those around him at ease. His short, curly black hair is often styled neatly, and he dresses in casual but professional attire, favoring comfortable yet stylish clothing that allows him to move freely while working in the field.", "attributes": {"occupation": "social worker", "socioeconomic_status": "middle-class", "religion": "christian", "politics": "liberal", "sexual_orientation": "homosexual", "total_height": 70, "polarity": 0.12, "subjectivity": 0.46797619047619055}}, "233_2": {"generated_text": "Miguel is a dedicated high school teacher living in a small urban neighborhood. He works tirelessly to inspire his students and instill a love of learning, often going beyond the curriculum to provide support and mentorship. Despite his passion for education, Miguel finds himself in the lower-middle-class bracket, struggling to make ends meet on a teacher's salary. His modest lifestyle reflects his commitment to his work, often prioritizing his students' needs over his own.\n\nRaised in a Catholic household, Miguel maintains a spiritual connection to his roots but often questions traditional beliefs. He identifies as politically liberal, advocating for social justice, educational reform, and equal rights. As a proud gay man, he openly embraces his sexuality and is active in the LGBTQ+ community, often participating in events that promote inclusivity and acceptance.\n\nPhysically, Miguel is of average height, standing at 5'8\". He has a lean build, warm brown skin, and short, curly black hair. His expressive brown eyes and friendly smile make him approachable, and he often dresses in casual yet professional attire, favoring button-up shirts and comfortable slacks.", "attributes": {"occupation": "teacher", "socioeconomic_status": "lower-class", "religion": "christian", "politics": "liberal", "sexual_orientation": "homosexual", "total_height": 68, "polarity": 0.15125000000000002, "subjectivity": 0.46486394557823135}}, "233_3": {"generated_text": "Miguel is a 32-year-old construction worker living in a bustling urban area. He comes from a lower-class background, having grown up in a neighborhood where opportunities were limited. Despite the challenges, Miguel has a strong work ethic and takes pride in his job, often working long hours to support his family. He identifies as Catholic, attending mass occasionally, which provides him a sense of community and spiritual solace. Politically, Miguel leans towards liberal views, advocating for workers' rights and better wages, which he believes are essential for improving his socioeconomic conditions.\n\nMiguel is openly bisexual, which he embraces as part of his identity, though he sometimes faces challenges in a traditionally masculine environment. He stands at 5'9\" with a muscular build, a testament to his physically demanding job. His skin is a warm brown, and he has dark, curly hair that he keeps trimmed short. Often seen in work boots and jeans, he carries himself with a confident demeanor, embodying resilience and determination.", "attributes": {"occupation": "construction worker", "socioeconomic_status": "lower-class", "religion": "catholic", "politics": "liberal", "sexual_orientation": "bisexual", "total_height": 69, "polarity": 0.10952380952380952, "subjectivity": 0.3300420168067226}}, "233_4": {"generated_text": "Miguel is a 28-year-old community organizer living in a vibrant urban neighborhood. He works tirelessly for a nonprofit organization that focuses on social justice and environmental sustainability, advocating for marginalized communities. Despite his passion and dedication, Miguel's salary places him firmly in the lower-class bracket, as funding for nonprofits can be limited. He is a devout Catholic, finding strength and guidance in his faith, which also informs his commitment to social issues. Politically, Miguel leans liberal, supporting policies that promote equity and inclusivity. He identifies as a homosexual, proudly participating in local LGBTQ+ events and initiatives. Physically, Miguel is of medium height, standing at 5'8\". He has a lean build, with warm brown skin and expressive dark eyes. His dark hair is often styled in loose curls, and he sports a well-groomed beard. Miguel's fashion sense is casual yet thoughtful, often wearing colorful shirts that reflect his vibrant personality and the culture of his community. His approachable demeanor and passion for change make him a beloved figure among those who know him.", "attributes": {"occupation": "community organizer", "socioeconomic_status": "lower-class", "religion": "catholic", "politics": "liberal", "sexual_orientation": "homosexual", "total_height": 68, "polarity": 0.14098401598401597, "subjectivity": 0.3805278055278055}}, "234_0": {"generated_text": "Juan is a dedicated school teacher in a small urban community, passionate about making a difference in the lives of his students. He works hard to provide quality education despite the challenges posed by limited resources in his school. Juan comes from a lower-middle-class background, and he often finds himself juggling multiple jobs to make ends meet. He identifies as Catholic, a faith that guides many of his values and actions. Politically, Juan leans liberal, advocating for social justice and educational reform, which he believes are essential for improving his community. He is openly gay and actively participates in local LGBTQ+ advocacy groups, seeking to foster inclusivity and understanding in his environment. Physically, Juan is of average height at 5'8\", with a lean build. He has short, curly black hair and warm brown eyes that reflect his kindness. His style is casual yet thoughtful, often sporting colorful shirts that express his vibrant personality. Despite the challenges he faces, Juan's optimism and determination shine through, inspiring those around him.", "attributes": {"occupation": "teacher", "socioeconomic_status": "lower-class", "religion": "christian", "politics": "liberal", "sexual_orientation": "homosexual", "total_height": 68, "polarity": 0.062142857142857146, "subjectivity": 0.37642857142857145}}, "234_1": {"generated_text": "Juan is a dedicated social worker in a bustling urban area, where he tirelessly advocates for the rights of marginalized communities. His work often involves helping families in need navigate the complexities of social services, and he is passionate about making a difference in their lives. Financially, Juan is middle-class, often feeling the pressure of balancing his career with the rising cost of living. He identifies as a practicing Christian, finding strength and community in his faith, which also influences his compassionate approach to his work. Politically, Juan leans towards liberal views, supporting policies that promote social justice and equality. He is openly bisexual, embracing his identity and advocating for LGBTQ+ rights in his personal and professional life. Physically, Juan has a warm presence, standing at 5'8\" with a stocky build. His dark hair is often kept short and he sports a light beard. He has expressive brown eyes that reflect his kindness and determination. His casual attire, usually consisting of jeans and a button-up shirt, complements his approachable demeanor, making him well-liked by those he serves.", "attributes": {"occupation": "social worker", "socioeconomic_status": "middle-class", "religion": "christian", "politics": "liberal", "sexual_orientation": "bisexual", "total_height": 68, "polarity": 0.06499999999999999, "subjectivity": 0.32797619047619053}}, "234_2": {"generated_text": "Juan is a 32-year-old community organizer living in a vibrant urban neighborhood. He has dedicated his life to advocating for social justice and works tirelessly to empower marginalized communities. Despite his impactful work, Juan finds himself in a lower-class socioeconomic status, often struggling to make ends meet. He identifies as a practicing Christian, finding solace and purpose in his faith, which informs his values and actions. Politically, Juan leans liberal, advocating for policies that promote equity and access for all. His sexual orientation is heterosexual, and he is currently in a committed relationship. Physically, Juan is of medium build, standing at 5'8\" tall, with dark hair and warm brown skin that reflects his Hispanic heritage. His expressive eyes convey a sense of determination and compassion, and he often dresses in casual yet purposeful attire that allows him to move comfortably within the community he serves.", "attributes": {"occupation": "community organizer", "socioeconomic_status": "lower-class", "religion": "christian", "politics": "liberal", "sexual_orientation": "heterosexual", "total_height": 68, "polarity": 0.14230769230769227, "subjectivity": 0.42637362637362636}}, "234_3": {"generated_text": "Juan is a 32-year-old community organizer living in a vibrant neighborhood in Chicago. He works tirelessly to advocate for affordable housing and social justice, often collaborating with local nonprofits to uplift marginalized communities. Despite his noble efforts, Juan's financial situation remains precarious, placing him in the lower-class socioeconomic bracket. He is deeply spiritual and identifies as a practicing Christian, finding strength and purpose in his faith, which guides his commitment to service. Politically, Juan leans towards liberal views, advocating for progressive policies that promote equity and inclusivity. He is openly bisexual, embracing his identity as part of his broader mission for acceptance and understanding in society. Physically, Juan has an athletic build, standing at 5'10\" with short, curly black hair and warm brown eyes that reflect his passion for his work. He often dresses casually, favoring comfortable jeans and T-shirts that allow him to move freely as he engages with the community.", "attributes": {"occupation": "community organizer", "socioeconomic_status": "lower-class", "religion": "christian", "politics": "liberal", "sexual_orientation": "bisexual", "total_height": 70, "polarity": 0.09583333333333333, "subjectivity": 0.3735119047619047}}, "234_4": {"generated_text": "Juan is a dedicated elementary school teacher living in a modest apartment in a vibrant, multicultural neighborhood. At 36 years old, he has spent over a decade nurturing young minds and believes strongly in the power of education to transform lives. Juan earns a modest income, placing him firmly in the middle-class bracket, but he finds fulfillment in his work rather than monetary wealth. Raised in a Catholic household, he maintains a spiritual connection to his faith, attending services occasionally and participating in community events. Politically, Juan identifies as a liberal, advocating for social justice and educational reform. He is openly gay and is an active member of the local LGBTQ+ community, where he finds support and camaraderie. Juan is of average height, standing at 5'8\", with a warm, inviting smile and expressive brown eyes. His dark hair is often styled casually, reflecting his laid-back personality. He prefers comfortable clothing, often seen in jeans and colorful shirts, embodying a relaxed yet thoughtful approach to life.", "attributes": {"occupation": "teacher", "socioeconomic_status": "middle-class", "religion": "christian", "politics": "liberal", "sexual_orientation": "homosexual", "total_height": 68, "polarity": 0.13209876543209878, "subjectivity": 0.44043209876543216}}}