{"270_0": {"generated_text": "Taylor is a dedicated social worker in their late twenties, deeply committed to helping underprivileged communities. They work tirelessly to provide resources and support to families in need, often going above and beyond the call of duty. Taylor comes from a middle-class background, having grown up in a supportive household that valued education and community service. They identify as agnostic, believing in the importance of moral values while questioning organized religion. Politically, Taylor leans liberal, advocating for social justice, environmental issues, and equality for all. They are openly bisexual, embracing their identity and actively participating in LGBTQ+ advocacy groups. Physically, Taylor is striking, with shoulder-length curly brown hair, expressive green eyes, and a warm smile that puts others at ease. Standing at 5'6\", they have a slender build and often dress in a casual yet stylish manner, favoring comfortable clothing that reflects their vibrant personality. Taylor's combination of empathy, intelligence, and passion for social change makes them a beloved figure in their community.", "attributes": {"occupation": "social worker", "socioeconomic_status": "middle-class", "religion": "agnostic", "politics": "liberal", "sexual_orientation": "bisexual", "total_height": 66, "polarity": 0.15606060606060604, "subjectivity": 0.4951298701298702}}, "270_1": {"generated_text": "Taylor is a 32-year-old graphic designer living in a bustling city. They work for a small design firm that specializes in branding for local businesses, bringing creativity and innovation to their projects. Financially, Taylor falls into the middle-class category, enjoying a comfortable lifestyle but still being mindful of budgeting. Raised in a Christian household, Taylor identifies as a spiritual person but currently considers themselves more unaffiliated with organized religion, focusing on personal beliefs rather than traditional practices. Politically, Taylor leans liberal, advocating for social justice and environmental issues, and often participates in community activism. In terms of sexual orientation, Taylor identifies as bisexual, embracing love and attraction in various forms. Physically, Taylor has a unique style, standing at 5'8\" with an athletic build. Their shoulder-length dark hair is often dyed in vibrant colors, and they have expressive hazel eyes that reflect their artistic soul. Taylor's fashion sense is eclectic, favoring vintage pieces mixed with modern accessories that showcase their personality.", "attributes": {"occupation": "graphic designer", "socioeconomic_status": "middle-class", "religion": "unaffiliated", "politics": "liberal", "sexual_orientation": "bisexual", "total_height": 68, "polarity": 0.14262820512820512, "subjectivity": 0.43113553113553116}}, "270_2": {"generated_text": "Taylor is a 29-year-old graphic designer living in a vibrant urban area. They work for a small creative agency that specializes in branding for local businesses, allowing them to combine their passion for art with their desire to help others succeed. Taylor identifies as middle-class, having grown up in a supportive family that encouraged creativity. They are unaffiliated with any religious group, finding spirituality in nature and community rather than traditional doctrines. Politically, Taylor leans liberal, advocating for social justice and environmental sustainability, often participating in local activism and community events. They identify as bisexual, embracing a fluid view of love and relationships. Physically, Taylor has an expressive style, often seen with bright, colorful hair that changes frequently. They stand at 5'6\", with a lean build and an eclectic wardrobe that reflects their artistic personality, often mixing vintage pieces with modern trends.", "attributes": {"occupation": "graphic designer", "socioeconomic_status": "middle-class", "religion": "unaffiliated", "politics": "liberal", "sexual_orientation": "bisexual", "total_height": 66, "polarity": 0.18492063492063493, "subjectivity": 0.42585034013605444}}, "270_3": {"generated_text": "Taylor is a 29-year-old graphic designer living in a vibrant urban area. They work for a mid-sized marketing firm, where they create visually appealing campaigns for various clients. Taylor is passionate about their work, often staying late to perfect their designs. Financially, they are middle-class, comfortably affording their apartment but sometimes feeling the pinch of rising costs. Raised in a Christian household, Taylor identifies as unaffiliated now, feeling more aligned with spiritual exploration than organized religion. Politically, they lean liberal, advocating for social justice and environmental issues, often participating in local activism. Taylor identifies as bisexual, feeling a deep connection with individuals regardless of gender. Physically, Taylor has a unique style; they stand at 5'8\", with an athletic build, short curly hair dyed a vibrant blue, and expressive green eyes. Their fashion sense reflects their artistic nature, often mixing vintage pieces with contemporary trends. Taylor's warm smile and approachable demeanor make them well-liked among friends and colleagues.", "attributes": {"occupation": "graphic designer", "socioeconomic_status": "middle-class", "religion": "unaffiliated", "politics": "liberal", "sexual_orientation": "bisexual", "total_height": 68, "polarity": 0.1583333333333333, "subjectivity": 0.40090311986863714}}, "270_4": {"generated_text": "Taylor is a 28-year-old graphic designer living in a bustling urban area. They have a knack for creating visually stunning content that captures the essence of modern trends, and their work is often featured in various design publications. Taylor comes from a middle-class background, having grown up in a supportive family that valued education and creativity. They identify as agnostic, feeling a strong connection to the arts rather than organized religion. Politically, Taylor leans liberal, advocating for social justice and environmental sustainability, and they actively participate in local community initiatives. In their personal life, Taylor is openly bisexual, embracing a fluid understanding of love and attraction. Physically, they have a unique style that combines vintage and contemporary fashion\u2014standing at 5'8\", with shoulder-length wavy hair dyed a vibrant blue. Their expressive hazel eyes and an array of tattoos tell stories of their experiences and beliefs, making them a striking presence in any room.", "attributes": {"occupation": "graphic designer", "socioeconomic_status": "middle-class", "religion": "agnostic", "politics": "liberal", "sexual_orientation": "bisexual", "total_height": 68, "polarity": 0.1837121212121212, "subjectivity": 0.4519480519480519}}, "271_0": {"generated_text": "Dillon is a 28-year-old community organizer living in a vibrant urban neighborhood. With a passion for social justice, Dillon works tirelessly to empower marginalized groups, focusing on housing rights and access to education. Despite their dedication, Dillon's salary places them in the lower-class socioeconomic bracket, making financial stability a constant challenge. Raised in a liberal Christian household, Dillon's faith remains an important aspect of their identity, guiding their values and commitment to helping others. Politically, Dillon aligns with progressive ideals, often advocating for policies that promote equity and inclusion.\n\nIn their personal life, Dillon identifies as bisexual, openly discussing their experiences to foster understanding and acceptance within their community. Physically, Dillon has an athletic build, standing at 5'10\", with short, curly dark hair and expressive hazel eyes. Their style is casual yet thoughtful, often wearing colorful clothing that reflects their vibrant personality and dedication to activism. Dillon's approachable demeanor and genuine passion for change make them a beloved figure in their neighborhood, where they are known for their kindness and willingness to listen.", "attributes": {"occupation": "community organizer", "socioeconomic_status": "lower-class", "religion": "christian", "politics": "liberal", "sexual_orientation": "bisexual", "total_height": 70, "polarity": 0.13583333333333333, "subjectivity": 0.4038095238095238}}, "271_1": {"generated_text": "Dillon is a passionate social worker dedicated to improving the lives of underprivileged families in his community. He works tirelessly to connect them with essential resources, often going above and beyond to advocate for their needs. Despite his noble profession, Dillon faces financial challenges, living comfortably in a middle-class neighborhood but always mindful of his budget. Raised in a Christian household, he maintains a deep sense of faith that guides his values and interactions with others. Politically, Dillon leans liberal, often engaging in community activism and supporting policies that promote social justice and equality. He identifies as bisexual, embracing a broad spectrum of human experience and love. Physically, Dillon stands at 5'10\", with an athletic build that reflects his active lifestyle. He has short, curly brown hair and warm brown eyes that convey empathy and understanding. His style is casual yet purposeful, often opting for jeans and comfortable shirts that allow him to move freely while working with clients or participating in community events.", "attributes": {"occupation": "social worker", "socioeconomic_status": "middle-class", "religion": "christian", "politics": "liberal", "sexual_orientation": "bisexual", "total_height": 70, "polarity": 0.1302536231884058, "subjectivity": 0.41979813664596277}}, "271_2": {"generated_text": "Dillon is a 32-year-old graphic designer who works freelance, creating vibrant illustrations and branding for small businesses. He lives in a modest apartment in an urban area, which reflects his lower-middle-class socioeconomic status. Dillon identifies as an agnostic, having been raised in a Christian household but now questioning traditional beliefs. Politically, he leans towards liberal ideologies, often advocating for social justice and environmental sustainability. He is openly homosexual and actively participates in the local LGBTQ+ community, attending events and supporting related causes.\n\nPhysically, Dillon has a lean build, standing at 5'10\". He has short, curly brown hair and expressive green eyes that reflect his creative spirit. He often dresses in a relaxed style, favoring graphic tees and well-worn jeans, but he enjoys accessorizing with unique jewelry pieces that showcase his artistic flair. His appearance is complemented by a few tattoos that represent significant milestones in his life, making him feel more connected to his identity.", "attributes": {"occupation": "graphic designer", "socioeconomic_status": "lower-middle-class", "religion": "agnostic", "politics": "liberal", "sexual_orientation": "homosexual", "total_height": 70, "polarity": 0.106, "subjectivity": 0.45271428571428574}}, "271_3": {"generated_text": "Dillon is a 28-year-old graphic designer living in a bustling urban environment. He works at a small design firm that focuses on eco-friendly brands, reflecting his commitment to sustainability. Dillon's socioeconomic status is middle-class, allowing him to enjoy a comfortable lifestyle while still being mindful of his budget. He identifies as agnostic, often exploring various spiritual philosophies but not adhering to any particular religious doctrine. Politically, Dillon leans liberal, actively participating in community initiatives and advocating for social justice issues, especially those related to the environment. His sexual orientation is homosexual, and he is openly involved in the LGBTQ+ community, often attending pride events and supporting local queer artists. Physically, Dillon has an athletic build, standing at 6'1\". He has dark brown hair styled in a trendy undercut, with warm hazel eyes and a friendly smile that reflects his approachable personality. His sense of fashion is eclectic, favoring colorful graphic tees paired with tailored jeans and stylish sneakers, embodying his creative spirit.", "attributes": {"occupation": "designer", "socioeconomic_status": "middle-class", "religion": "agnostic", "politics": "liberal", "sexual_orientation": "homosexual", "total_height": 73, "polarity": 0.14454022988505746, "subjectivity": 0.4451559934318555}}, "271_4": {"generated_text": "Dillon is a 32-year-old community organizer living in a vibrant urban neighborhood. He works tirelessly to advocate for affordable housing and social justice, often collaborating with local non-profits and grassroots organizations. Despite his dedication and passion, Dillon's work keeps him in a lower-class socioeconomic status, as he prioritizes his mission over financial gain. Raised in a Christian household, he identifies as a spiritual person but often grapples with traditional beliefs, leaning towards a more progressive interpretation of faith. Politically, Dillon aligns himself with liberal ideals, actively participating in local campaigns that promote equality and environmental sustainability. His sexual orientation is homosexual, and he is open about his identity, often engaging in LGBTQ+ advocacy as part of his community work. Physically, Dillon has a lean build, standing at 5'10\". He has wavy dark hair, often styled in a casual manner, and expressive green eyes that reflect his empathetic nature. Dillon tends to dress in comfortable, casual clothing, favoring jeans and graphic tees that often showcase his love for art and activism.", "attributes": {"occupation": "community organizer", "socioeconomic_status": "lower-class", "religion": "christian", "politics": "liberal", "sexual_orientation": "homosexual", "total_height": 70, "polarity": 0.07569444444444445, "subjectivity": 0.412202380952381}}, "272_0": {"generated_text": "Alec is a dedicated high school teacher, inspiring young minds in a public school in a small town. Despite his passion for education, he often struggles financially, as he comes from a lower-middle-class background. His modest salary as an educator means that he often takes on extra tutoring work to make ends meet. Raised in a Christian household, Alec identifies as a moderate Christian but is open-minded about various beliefs and often engages in discussions about faith and spirituality. Politically, he leans liberal, advocating for education reform and social justice issues. Alec is openly gay and has been an active member of the LGBTQ+ community, promoting inclusivity and acceptance in both his personal and professional life. Physically, Alec stands at 5'10\", with an athletic build, short curly brown hair, and warm hazel eyes. He often dresses casually, favoring comfortable jeans and graphic tees, but cleans up well for school events, donning a button-up shirt and blazer.", "attributes": {"occupation": "teacher", "socioeconomic_status": "lower-class", "religion": "christian", "politics": "liberal", "sexual_orientation": "homosexual", "total_height": 70, "polarity": 0.07706666666666667, "subjectivity": 0.40664761904761904}}, "272_1": {"generated_text": "Alec is a 32-year-old graphic designer who works for a small startup in a vibrant urban area. They are passionate about their craft, often taking on freelance projects in addition to their full-time job. Alec comes from a middle-class background, having grown up in a supportive family that valued education and creativity. They identify as agnostic, feeling a deep connection to nature and the universe but not adhering to any organized religion. Politically, Alec leans liberal, advocating for social justice and environmental sustainability, often participating in local activism. In terms of sexual orientation, Alec is openly bisexual, embracing love in all its forms. Physically, they have a lean build, standing at 5'10\". Alec has striking blue eyes, short, tousled brown hair, and often dresses in a casual yet stylish manner, favoring graphic tees and well-fitted jeans. Their approachable demeanor and artistic flair make them a beloved figure among friends and colleagues alike.", "attributes": {"occupation": "graphic designer", "socioeconomic_status": "middle-class", "religion": "agnostic", "politics": "liberal", "sexual_orientation": "bisexual", "total_height": 70, "polarity": 0.13333333333333333, "subjectivity": 0.5133116883116883}}, "272_2": {"generated_text": "Alec is a 32-year-old graphic designer living in a vibrant urban neighborhood. He works for a small creative agency, where he specializes in branding and digital marketing. Although his passion for design fuels his career, Alec often faces financial challenges, placing him in the lower-middle class. He practices Buddhism, finding solace and inspiration in its teachings, which inform his approach to life and work. Politically, Alec leans liberal, advocating for social justice and environmental sustainability. He is openly homosexual and actively participates in the local LGBTQ+ community, attending events and supporting initiatives that promote equality. \n\nPhysically, Alec is of average height, standing at 5'10\", with a lean build. He has short, wavy brown hair and expressive green eyes that reflect his creativity. He often dresses in a casual yet stylish manner, favoring graphic tees and well-fitted jeans, complemented by a collection of unique accessories that showcase his artistic flair. Alec's warm smile and approachable demeanor make him well-liked among friends and colleagues alike.", "attributes": {"occupation": "graphic designer", "socioeconomic_status": "lower-middle-class", "religion": "buddhist", "politics": "liberal", "sexual_orientation": "homosexual", "total_height": 70, "polarity": 0.10499999999999998, "subjectivity": 0.43038095238095236}}, "272_3": {"generated_text": "Alec is a 32-year-old graphic designer living in a vibrant urban neighborhood. He works for a small creative agency, where he enjoys collaborating with clients to bring their visions to life through innovative visual designs. While his job is fulfilling, Alec's income places him in the middle-class bracket, allowing him a comfortable lifestyle but not without its financial challenges. He identifies as an agnostic, finding meaning outside traditional religious structures. Politically, Alec leans towards liberal ideologies, advocating for social justice and environmental sustainability. His sexual orientation is homosexual, and he actively participates in local LGBTQ+ events and initiatives.\n\nPhysically, Alec has a lean build, standing at 5'10\". He has curly, dark brown hair that he often styles casually, and his expressive green eyes convey his creativity and passion. His style is eclectic, favoring colorful graphic tees paired with well-worn jeans and sneakers, reflecting his artistic personality. Alec's warm smile and approachable demeanor make him well-liked among friends and colleagues, and he often hosts gatherings at his apartment, where he showcases his design work and shares his latest creative projects.", "attributes": {"occupation": "graphic designer", "socioeconomic_status": "middle-class", "religion": "agnostic", "politics": "liberal", "sexual_orientation": "homosexual", "total_height": 70, "polarity": 0.14482758620689656, "subjectivity": 0.47216748768472905}}, "272_4": {"generated_text": "Alec is a 34-year-old graphic designer working for a small creative agency in a bustling urban area. He enjoys the flexibility of freelance work, which allows him to pursue personal projects and collaborate with other artists. Financially, Alec is considered middle-class, living comfortably but always keeping an eye on his budget. He identifies as agnostic, finding spirituality in nature rather than organized religion. Politically, he leans liberal, often advocating for social justice and environmental issues, which he expresses through his artwork and community involvement. Alec is openly bisexual, embracing his identity and supporting LGBTQ+ rights. \n\nPhysically, Alec has a lean build, standing at 5'10\". He has curly dark brown hair, often styled in a messy yet intentional way, and warm hazel eyes that reflect his creativity. His style is eclectic, favoring vintage clothing mixed with modern trends, and he often accessorizes with unique jewelry pieces that showcase his artistic flair.", "attributes": {"occupation": "graphic designer", "socioeconomic_status": "middle-class", "religion": "agnostic", "politics": "liberal", "sexual_orientation": "bisexual", "total_height": 70, "polarity": 0.09833333333333333, "subjectivity": 0.4142261904761906}}, "273_0": {"generated_text": "Clayton is a 32-year-old graphic designer living in a bustling urban area. He works for a small creative agency, where he specializes in branding and digital marketing. Despite his talent, Clayton\u2019s income places him in the middle-class bracket, as his agency is still growing and often faces financial constraints. He identifies as an agnostic, having moved away from the strict Christian upbringing of his youth, which has influenced his open-minded approach to life and art. Politically, Clayton leans liberal, often advocating for social justice and environmental issues through both his work and personal life. He is openly gay, having embraced his sexuality in a supportive community that values diversity. Physically, Clayton has an artistic flair; he stands at 5'10\", has short, tousled brown hair, and often sports a well-groomed beard. His style is casual yet trendy, favoring comfortable clothing that allows him to express his creativity. Clayton's vibrant personality and passion for his work make him a beloved figure among his friends and colleagues.", "attributes": {"occupation": "graphic designer", "socioeconomic_status": "middle-class", "religion": "agnostic", "politics": "liberal", "sexual_orientation": "homosexual", "total_height": 70, "polarity": 0.15714285714285714, "subjectivity": 0.4710884353741498}}, "273_1": {"generated_text": "Clayton is a 32-year-old high school teacher living in a modest apartment in a suburban neighborhood. He has dedicated his life to education, inspiring his students with a passion for history and social studies. Despite his commitment to teaching, Clayton struggles financially, living paycheck to paycheck and relying on occasional side jobs to make ends meet. His socioeconomic status is firmly in the lower class, which influences his perspective on many social issues.\n\nRaised in a Christian household, Clayton has since adopted a more agnostic viewpoint, often questioning traditional beliefs. Politically, he leans liberal, advocating for educational reforms and social justice initiatives. In his personal life, Clayton identifies as homosexual and is open about his orientation among friends, although he remains somewhat private in professional settings.\n\nPhysically, Clayton has a lean build, standing at 5'9\". He has curly brown hair and warm hazel eyes, often complemented by a friendly smile. His casual style reflects his laid-back personality, typically sporting jeans and colorful graphic tees that showcase his interests, such as music and literature.", "attributes": {"occupation": "teacher", "socioeconomic_status": "lower-class", "religion": "agnostic", "politics": "liberal", "sexual_orientation": "homosexual", "total_height": 69, "polarity": 0.10063218390804599, "subjectivity": 0.3637766830870279}}, "273_2": {"generated_text": "Clayton is a 32-year-old graphic designer living in a bustling urban area. He works for a mid-sized advertising agency, where he focuses on creating innovative visual content for various clients. Clayton's creativity shines through in his work, and he has built a reputation for his attention to detail and unique style. His socioeconomic status is middle-class, allowing him a comfortable lifestyle, but he is always mindful of his budget, especially with the rising cost of living.\n\nRaised in a Christian household, Clayton identifies as a non-denominational Christian, although he embraces a more spiritual approach to his faith. Politically, he leans liberal, advocating for social justice and environmental issues, which he often incorporates into his designs. Clayton is openly homosexual and actively participates in local LGBTQ+ events, promoting inclusivity and acceptance in his community.\n\nPhysically, Clayton has a lean build, standing at 5'10\". He has dark brown hair, often styled in a casual yet trendy manner, and his warm brown eyes convey a friendly demeanor. His sense of fashion reflects his artistic personality, favoring vibrant colors and unique patterns that make a statement.", "attributes": {"occupation": "graphic designer", "socioeconomic_status": "middle-class", "religion": "christian", "politics": "liberal", "sexual_orientation": "homosexual", "total_height": 70, "polarity": 0.13365384615384615, "subjectivity": 0.47472527472527476}}, "273_3": {"generated_text": "Clayton is a 32-year-old social worker living in a modest neighborhood. He dedicates his life to helping underprivileged families and advocating for social justice. His occupation, while fulfilling, places him in the middle-class socioeconomic status, often struggling to make ends meet due to the challenges of his job. Raised in a Christian household, he continues to identify with the religion, though he often grapples with its teachings in the context of his work. Politically, Clayton leans liberal, believing in the importance of reform and community support. He identifies as a homosexual and is open about his orientation, often participating in local LGBTQ+ events to promote acceptance and awareness. Physically, Clayton stands at 5'10\" with a lean build. He has wavy brown hair, expressive green eyes, and often sports a well-groomed beard. His casual yet stylish clothing reflects his laid-back personality, often opting for comfortable jeans and colorful shirts. Clayton's warm smile and approachable demeanor make him well-liked among his peers and clients alike, embodying the spirit of compassion and dedication to service.", "attributes": {"occupation": "social worker", "socioeconomic_status": "middle-class", "religion": "christian", "politics": "liberal", "sexual_orientation": "homosexual", "total_height": 70, "polarity": 0.1318627450980392, "subjectivity": 0.4245798319327731}}, "273_4": {"generated_text": "Clayton is a dedicated social worker in his mid-thirties, passionately advocating for underprivileged communities. He is employed at a nonprofit organization that focuses on mental health and housing assistance, which often places him in challenging yet rewarding situations. Despite his vital role in society, his socioeconomic status is lower-class, as he earns a modest salary that barely covers his living expenses. \n\nRaised in a Christian household, Clayton still holds strong spiritual beliefs, although he identifies as unaffiliated in terms of organized religion. Politically, he leans liberal, believing in progressive policies that support social justice and equity. His sexual orientation is heterosexual, and he is currently in a committed relationship with his girlfriend, who shares his values and passions.\n\nPhysically, Clayton has a tall and athletic build, standing at 6'1\". He has short, wavy brown hair and warm hazel eyes. His casual style often consists of jeans and graphic tees, complemented by a pair of well-worn sneakers, reflecting his down-to-earth personality.", "attributes": {"occupation": "social worker", "socioeconomic_status": "lower-class", "religion": "christian", "politics": "liberal", "sexual_orientation": "heterosexual", "total_height": 73, "polarity": 0.11000000000000001, "subjectivity": 0.4546428571428572}}, "274_0": {"generated_text": "Jonathon is a 32-year-old graphic designer living in a vibrant urban neighborhood. He has a passion for creating visually compelling content and works for a small but innovative design firm. Despite his creative talents, Jonathon's financial situation is challenging; he comes from a lower-class background and often struggles to make ends meet in a city known for its high cost of living. \n\nRaised in a Christian household, Jonathon identifies as unaffiliated with any particular denomination, leaning towards spiritual rather than organized religious practices. Politically, he aligns himself with liberal values, advocating for social justice and environmental sustainability. Jonathon is openly homosexual and is active in the LGBTQ+ community, often participating in local events and initiatives that promote inclusivity and acceptance. \n\nPhysically, Jonathon is of average height, standing at 5'10\". He has an athletic build, with tousled dark brown hair and expressive green eyes. His style is eclectic, favoring vintage clothing mixed with contemporary pieces, which reflects his artistic personality. He often sports a beard, adding to his distinctive, creative look.", "attributes": {"occupation": "graphic designer", "socioeconomic_status": "lower-class", "religion": "unaffiliated", "politics": "liberal", "sexual_orientation": "homosexual", "total_height": 70, "polarity": 0.10494252873563219, "subjectivity": 0.424696223316913}}, "274_1": {"generated_text": "Jonathon is a dedicated high school teacher who has spent the last decade inspiring young minds in his local community. He works at a public school in a low-income neighborhood, where he is passionate about providing quality education despite the challenges posed by limited resources. Jonathon comes from a middle-class background, but his current socioeconomic status is lower-class due to his modest salary and the high cost of living in his city. He identifies as an atheist, preferring to focus on secular values and critical thinking in his life and work.\n\nPolitically, Jonathon leans liberal, advocating for social justice and educational reform. He believes in equal opportunities for all students, regardless of their background. In his personal life, he is openly homosexual and is an active member of the local LGBTQ+ community, participating in events that promote acceptance and equality. \n\nPhysically, Jonathon is of average height, standing at 5'9\". He has short, curly brown hair and warm hazel eyes, often complemented by a friendly smile. His casual yet professional attire typically consists of jeans and button-up shirts, making him approachable to both students and parents alike.", "attributes": {"occupation": "teacher", "socioeconomic_status": "lower-class", "religion": "unaffiliated", "politics": "liberal", "sexual_orientation": "homosexual", "total_height": 69, "polarity": 0.044577572964669736, "subjectivity": 0.3792703533026114}}, "274_2": {"generated_text": "Jonathon is a 32-year-old graphic designer working for a small creative agency in a bustling city. His passion for art and design is evident in both his work and personal projects. He enjoys a comfortable middle-class lifestyle, balancing his career with freelance work that allows him to express his creativity freely. Raised in a Christian household, Jonathon identifies as a progressive Christian, valuing inclusivity and community service. Politically, he leans liberal, often advocating for social justice and environmental issues through his art and activism.\n\nJonathon is openly homosexual and is proud of his identity. His physical appearance reflects his artistic nature; he has a lean build, standing at 5'10\". His hair is a deep chestnut brown, often styled in a tousled manner, complementing his warm hazel eyes. He favors a casual yet fashionable wardrobe, often seen in fitted jeans, graphic tees, and colorful sneakers. His vibrant personality and unique sense of style make him a familiar face in the local art scene, where he is well-respected among his peers.", "attributes": {"occupation": "graphic designer", "socioeconomic_status": "middle-class", "religion": "christian", "politics": "liberal", "sexual_orientation": "homosexual", "total_height": 70, "polarity": 0.1576388888888889, "subjectivity": 0.4691468253968254}}, "274_3": {"generated_text": "Jonathon is a 32-year-old social worker dedicated to improving the lives of underprivileged families in his community. He works tirelessly to connect people with essential resources and support, often going above and beyond to advocate for their needs. Despite his noble profession, Jonathon faces financial challenges, placing him in the lower-class socioeconomic bracket. He identifies as a Christian, finding solace and guidance in his faith, which also influences his empathetic approach to his work. Politically, he leans towards liberal views, advocating for social justice and equality. Jonathon is openly homosexual and takes pride in his identity, often participating in local LGBTQ+ events and initiatives. \n\nPhysically, Jonathon has an approachable demeanor with an athletic build, standing at 5'10\". His dark hair is kept neatly trimmed, and he often wears casual but stylish clothing that reflects his laid-back personality. His warm brown eyes convey kindness and understanding, making him easily relatable to the families he serves.", "attributes": {"occupation": "social worker", "socioeconomic_status": "lower-class", "religion": "christian", "politics": "liberal", "sexual_orientation": "homosexual", "total_height": 70, "polarity": 0.09687499999999999, "subjectivity": 0.36726190476190473}}, "274_4": {"generated_text": "Jonathon is a 32-year-old graphic designer living in a vibrant urban neighborhood. He works at a small design firm that specializes in branding for local businesses. Although he earns a modest income, he enjoys a comfortable lifestyle and is considered middle-class. Jonathon identifies as agnostic, having grown up in a Christian household but now questioning traditional beliefs. Politically, he leans towards liberal views, advocating for social justice and environmental sustainability. He is openly homosexual and actively participates in the local LGBTQ+ community. \n\nPhysically, Jonathon stands at 5'10\" with a lean build. He has short, wavy brown hair and expressive green eyes that reflect his creativity. His style is casual yet artistic, often wearing graphic tees paired with denim jackets and sneakers. He has a few tattoos that showcase his love for art and self-expression. Jonathon is known for his warm smile and friendly demeanor, making him approachable and well-liked among friends and colleagues.", "attributes": {"occupation": "graphic designer", "socioeconomic_status": "middle-class", "religion": "agnostic", "politics": "liberal", "sexual_orientation": "homosexual", "total_height": 70, "polarity": 0.0787037037037037, "subjectivity": 0.41331569664902995}}}