{"275_0": {"generated_text": "Brittney is a 29-year-old graphic designer living in a vibrant urban area. She works for a small creative agency, where she has built a reputation for her innovative designs and attention to detail. Brittney is of middle-class socioeconomic status, which allows her to enjoy a comfortable lifestyle, though she often budgets carefully to manage her expenses. She identifies as spiritual but is largely unaffiliated with organized religion, finding meaning in nature and personal experiences rather than traditional doctrines. Politically, Brittney leans liberal, actively participating in community events and advocating for social justice issues. In her personal life, she identifies as bisexual and values inclusivity and diversity in her relationships. \n\nPhysically, Brittney has an athletic build, standing at 5'7\". She has shoulder-length wavy brown hair and striking green eyes that often catch the attention of those around her. Her style reflects her artistic background, favoring unique and colorful clothing that expresses her personality. Brittney\u2019s friendly demeanor and open-mindedness make her approachable, and she enjoys engaging in conversations about art, culture, and social issues.", "attributes": {"occupation": "graphic designer", "socioeconomic_status": "middle-class", "religion": "unaffiliated", "politics": "liberal", "sexual_orientation": "bisexual", "total_height": 67, "polarity": 0.14798534798534796, "subjectivity": 0.5085164835164835}}, "275_1": {"generated_text": "Brittney is a dedicated social worker in her mid-thirties, known for her passion for helping marginalized communities. Growing up in a lower-middle-class family, she has always been driven to make a difference, often working multiple jobs to support herself through college. Despite her modest financial situation, she finds fulfillment in her work and advocates for social justice. Brittney identifies as a Christian, drawing strength and inspiration from her faith in her daily life and work. Politically, she leans liberal, often participating in community organizing and advocating for progressive policies that support the underprivileged. Brittney is openly bisexual, embracing her identity and fostering an inclusive environment for her clients. \n\nPhysically, she stands at 5'6\", with an athletic build that reflects her active lifestyle. Brittney has long, curly brown hair and warm hazel eyes that convey her empathetic nature. She often dresses in casual yet professional attire, favoring comfort while maintaining a polished appearance. Her approachable demeanor and genuine smile make her a beloved figure in her community, as she works tirelessly to uplift those around her.", "attributes": {"occupation": "social worker", "socioeconomic_status": "lower-class", "religion": "christian", "politics": "liberal", "sexual_orientation": "bisexual", "total_height": 66, "polarity": 0.08796296296296295, "subjectivity": 0.3301587301587301}}, "275_2": {"generated_text": "Brittney is a vibrant 29-year-old graphic designer living in a bustling urban area. She works for a small creative agency that specializes in branding for local businesses. Brittney is passionate about her work and has built a solid reputation among her peers. While her salary places her in the middle-class bracket, she often finds herself navigating the challenges of city living, balancing her aspirations with the cost of living.\n\nRaised in a Christian household, Brittney identifies as a progressive individual who values inclusivity and social justice, often volunteering her time for causes she believes in. Politically, she aligns herself with liberal values, advocating for environmental issues and equal rights. Brittney is openly bisexual, embracing her identity and fostering a supportive community around her.\n\nPhysically, Brittney has a unique style that reflects her artistic spirit. She stands at 5'6\" with a slender build and has shoulder-length, wavy brown hair. Her expressive hazel eyes often sparkle with enthusiasm, and she has a penchant for colorful clothing that showcases her creativity.", "attributes": {"occupation": "graphic designer", "socioeconomic_status": "middle-class", "religion": "christian", "politics": "liberal", "sexual_orientation": "bisexual", "total_height": 66, "polarity": 0.13541666666666666, "subjectivity": 0.44714285714285723}}, "275_3": {"generated_text": "Brittney is a 32-year-old graphic designer living in a bustling urban area. She works for a mid-sized marketing firm, where she enjoys creating vibrant visual content that helps brands connect with their audience. Despite her creative talents, Brittney's income places her in the middle-class bracket, allowing her a comfortable lifestyle but not without its financial constraints. Raised in a Christian household, she identifies as a spiritual but unaffiliated person, finding her own path in faith. Politically, Brittney leans liberal, often advocating for social justice and environmental issues. Her sexual orientation is bisexual, and she embraces her identity with confidence. \n\nPhysically, Brittney has a distinctive look: she stands at 5'6\", has long, wavy brown hair, and often sports colorful tattoos that reflect her artistic personality. Her style is eclectic, mixing vintage finds with contemporary fashion, which showcases her creative spirit and individuality. Brittney embodies a modern, urban lifestyle, balancing her professional aspirations with a commitment to her personal values and beliefs.", "attributes": {"occupation": "graphic designer", "socioeconomic_status": "middle-class", "religion": "unaffiliated", "politics": "liberal", "sexual_orientation": "bisexual", "total_height": 66, "polarity": 0.14791666666666667, "subjectivity": 0.3698412698412699}}, "275_4": {"generated_text": "Brittney is a 28-year-old graphic designer living in a bustling urban area. She works for a small creative agency, where she specializes in branding and digital marketing. Brittney is passionate about her craft and often takes on freelance projects in her spare time, which helps her supplement her income. As a middle-class individual, she enjoys a comfortable lifestyle but is always mindful of her finances. Raised in a Christian household, Brittney identifies as a progressive Christian and often engages in community service activities through her church. Politically, she aligns with liberal values, advocating for social justice and environmental issues. Brittney identifies as bisexual and is open about her sexuality, fostering an inclusive environment among her friends and colleagues. In terms of physical appearance, she has a distinctive style; she stands at 5'6\" with shoulder-length wavy brown hair, hazel eyes, and a warm smile. Brittney often expresses her creativity through her fashion choices, frequently opting for vibrant colors and unique accessories that reflect her artistic personality.", "attributes": {"occupation": "graphic designer", "socioeconomic_status": "middle-class", "religion": "christian", "politics": "liberal", "sexual_orientation": "bisexual", "total_height": 66, "polarity": 0.12541666666666668, "subjectivity": 0.39964285714285713}}, "276_0": {"generated_text": "Whitney is a passionate environmental scientist dedicated to combating climate change through research and advocacy. She works for a non-profit organization that focuses on sustainable practices and educating communities about the importance of conservation. Whitney lives in a modest apartment in a vibrant urban neighborhood, reflecting her middle-class socioeconomic status. Raised in a Christian household, she maintains a strong sense of spirituality, although she often identifies as more spiritual than religious in her adult life. Politically, Whitney leans liberal, advocating for progressive policies that support environmental justice and social equality. In her personal life, she identifies as bisexual, embracing her diverse relationships and connections with people from various backgrounds. \n\nPhysically, Whitney has an athletic build from her love of outdoor activities, standing at 5'6\". She has shoulder-length curly brown hair, warm hazel eyes, and often dresses in practical yet stylish clothing suited for her active lifestyle. Her approachable demeanor and passionate spirit make her a beloved figure among her peers and community members.", "attributes": {"occupation": "environmental scientist", "socioeconomic_status": "middle-class", "religion": "christian", "politics": "liberal", "sexual_orientation": "bisexual", "total_height": 66, "polarity": 0.1619047619047619, "subjectivity": 0.46473922902494325}}, "276_1": {"generated_text": "Whitney is a passionate social worker dedicated to improving the lives of underprivileged families in her community. In her late twenties, she navigates the challenges of her middle-class income, often working long hours to make ends meet while striving to create impactful change. Raised in a Christian household, Whitney finds strength and guidance in her faith, which also shapes her values and commitment to service. Politically, she identifies as liberal, advocating for social justice and equity, and she often volunteers for progressive causes. Whitney is openly bisexual, feeling comfortable in her identity and supportive of LGBTQ+ rights. \n\nPhysically, Whitney has an athletic build, standing at 5'6\". She has shoulder-length curly brown hair and warm hazel eyes that reflect her kindness and determination. Her casual style often includes comfortable jeans and vibrant tops, embodying her approachable personality. Whitney\u2019s smile is infectious, and she carries an air of optimism that draws people to her, making her a beloved figure in her community.", "attributes": {"occupation": "social worker", "socioeconomic_status": "middle-class", "religion": "christian", "politics": "liberal", "sexual_orientation": "bisexual", "total_height": 66, "polarity": 0.13137254901960785, "subjectivity": 0.4838935574229692}}, "276_2": {"generated_text": "Whitney is a dedicated social worker in her early thirties, known for her compassion and commitment to helping underprivileged communities. She comes from a middle-class background, having worked hard to earn her degree and establish herself in her career. Raised in a Christian household, she maintains a personal faith that guides her values and approach to her work. Politically, Whitney identifies as liberal, advocating for social justice and equitable access to resources for all individuals, regardless of their background. In her personal life, she identifies as bisexual, having had relationships with both men and women, which she embraces as part of her identity.\n\nWhitney has an athletic build, standing at 5'6\". Her long, wavy brown hair frames her face, accentuating her warm hazel eyes. She often opts for comfortable yet stylish clothing, favoring earth tones that reflect her down-to-earth personality. Her approachable demeanor and genuine smile make her well-liked among her peers and clients alike.", "attributes": {"occupation": "social worker", "socioeconomic_status": "middle-class", "religion": "christian", "politics": "liberal", "sexual_orientation": "bisexual", "total_height": 66, "polarity": 0.14464285714285713, "subjectivity": 0.3625}}, "276_3": {"generated_text": "Whitney is a dedicated elementary school teacher in a small town, known for her passion for education and her commitment to her students. She comes from a middle-class background, having grown up in a supportive family that valued learning and community service. Whitney identifies as Christian and often participates in local church activities, which play a significant role in her life. Politically, she leans liberal, advocating for progressive education policies and community initiatives that support underprivileged families. \n\nIn terms of her sexual orientation, Whitney identifies as heterosexual and is currently in a long-term relationship with her partner, whom she often describes as her best friend. Physically, Whitney is of average height, standing at 5'5\". She has wavy chestnut hair that falls just below her shoulders and warm brown eyes that reflect her kindness. Whitney tends to dress in a casual yet professional manner, favoring comfortable clothing that allows her to move easily while engaging with her students.", "attributes": {"occupation": "teacher", "socioeconomic_status": "middle-class", "religion": "christian", "politics": "liberal", "sexual_orientation": "heterosexual", "total_height": 65, "polarity": 0.20601851851851852, "subjectivity": 0.5139550264550263}}, "276_4": {"generated_text": "Whitney is a vibrant 32-year-old graphic designer living in a bustling urban neighborhood. She has built a successful freelance career, which allows her to work with various clients, including startups and established brands. Despite her talent, Whitney navigates the challenges of being a freelancer in a competitive industry, placing her in the middle-class socioeconomic bracket. She identifies as a Christian and often attends a local church where she finds community and support. Politically, Whitney leans liberal, advocating for social justice and environmental issues, and actively participates in community initiatives. \n\nIn her personal life, Whitney identifies as bisexual, and she values authenticity and openness in her relationships. She has a warm and approachable demeanor, with shoulder-length brown hair and expressive green eyes. Whitney often dresses in a casual yet stylish manner, favoring comfortable clothes that reflect her artistic personality. Her height is 5'6\", and she has a slender build, often complemented by a bright smile that radiates positivity and creativity.", "attributes": {"occupation": "graphic designer", "socioeconomic_status": "middle-class", "religion": "christian", "politics": "liberal", "sexual_orientation": "bisexual", "total_height": 66, "polarity": 0.1875, "subjectivity": 0.48583333333333334}}, "277_0": {"generated_text": "Meghan is a 32-year-old graphic designer living in a vibrant urban area. She works at a small creative agency, where she specializes in branding and digital illustration. Meghan is passionate about her work, often staying late to perfect her projects. She comes from a middle-class background, having grown up in a supportive family that encouraged her artistic pursuits. While not particularly religious, she identifies as Christian and attends church occasionally for family gatherings and holidays. Politically, Meghan leans liberal, advocating for social justice and environmental issues. Her friends often describe her as an open-minded individual who welcomes diverse perspectives. In terms of her sexual orientation, Meghan identifies as bisexual and is currently in a committed relationship with her partner, who shares her values and interests. Physically, Meghan has an athletic build, standing at 5'7\". She has shoulder-length brown hair, often styled in loose waves, and striking green eyes that reflect her creative spirit. Her personal style is trendy yet comfortable, favoring colorful patterns and unique accessories that showcase her artistic flair.", "attributes": {"occupation": "graphic designer", "socioeconomic_status": "middle-class", "religion": "christian", "politics": "liberal", "sexual_orientation": "bisexual", "total_height": 67, "polarity": 0.17950785773366415, "subjectivity": 0.534529717594234}}, "277_1": {"generated_text": "Meghan is a 29-year-old graphic designer living in a vibrant urban neighborhood. She works at a small creative agency that specializes in branding for local businesses. Meghan enjoys her work and has built a reputation for her innovative designs and attention to detail. Financially, she is in the middle-class bracket, living comfortably but with aspirations for greater stability. Raised in a Christian household, Meghan identifies as Christian, though she practices her faith more through values than regular attendance at church. Politically, she leans liberal, often advocating for social justice and environmental issues. Meghan is openly bisexual and believes in the importance of inclusivity and representation in her work and life. Physically, she has an artistic flair; her hair is dyed a vibrant purple, and she has a penchant for eclectic fashion that reflects her creative spirit. Standing at 5'6\", she carries herself with confidence and often accessorizes with unique jewelry that she crafts herself.", "attributes": {"occupation": "graphic designer", "socioeconomic_status": "middle-class", "religion": "christian", "politics": "liberal", "sexual_orientation": "bisexual", "total_height": 66, "polarity": 0.1693181818181818, "subjectivity": 0.41605061605061605}}, "277_2": {"generated_text": "Meghan is a 32-year-old environmental scientist, dedicated to researching sustainable practices that can combat climate change. She is passionate about her work and often engages in community outreach to educate the public on environmental issues. Meghan comes from a middle-class background, having grown up in a suburban neighborhood where her parents instilled in her the value of education and social responsibility. She identifies as Christian but holds progressive views that often align with her liberal political beliefs. Meghan is an advocate for various social justice causes, including climate activism, women's rights, and LGBTQ+ rights. \n\nIn her personal life, Meghan identifies as bisexual and believes in love and acceptance for all. She has a unique physical appearance, characterized by her curly auburn hair that cascades down her shoulders and bright green eyes that reflect her vibrant personality. Standing at 5'6\", Meghan often dresses in a casual yet stylish manner, favoring comfortable, eco-friendly clothing that aligns with her values. Her warm smile and approachable demeanor make her a beloved figure in her community, where she encourages others to take part in creating a better world.", "attributes": {"occupation": "environmental scientist", "socioeconomic_status": "middle-class", "religion": "christian", "politics": "liberal", "sexual_orientation": "bisexual", "total_height": 66, "polarity": 0.16968599033816426, "subjectivity": 0.4470324361628709}}, "277_3": {"generated_text": "Meghan is a dedicated nurse working in a busy urban hospital, where she provides compassionate care to her patients. She is in her early 30s, with a warm smile and an approachable demeanor that puts those around her at ease. Coming from a middle-class background, she is financially stable but mindful of her budget, often looking for ways to save while still enjoying life. Meghan identifies as Christian, attending her local church on Sundays, which plays a significant role in her community involvement and personal values. Politically, she leans liberal, advocating for healthcare reforms and social justice issues, reflecting her experiences in the medical field. Meghan is openly bisexual, embracing her identity and supporting LGBTQ+ rights. Physically, she has shoulder-length brown hair, bright green eyes, and a fit build from her active lifestyle, often participating in community runs and yoga classes. Her style is casual yet professional, favoring scrubs during work and comfortable clothing in her off hours.", "attributes": {"occupation": "nurse", "socioeconomic_status": "middle-class", "religion": "christian", "politics": "liberal", "sexual_orientation": "bisexual", "total_height": 66, "polarity": 0.12604166666666666, "subjectivity": 0.33338293650793654}}, "277_4": {"generated_text": "Meghan is a 34-year-old graphic designer based in a vibrant urban area. With a passion for creativity and visual storytelling, she works for a mid-sized marketing firm that values innovative design. Meghan enjoys a comfortable middle-class lifestyle, thanks to her steady income and a supportive community. Raised in a Christian household, she identifies as a practicing Christian, attending services regularly and participating in church activities. Politically, Meghan leans liberal, advocating for social justice and environmental issues, often volunteering for local progressive campaigns. She identifies as heterosexual and is currently in a committed relationship. \n\nPhysically, Meghan stands at 5'6\" with a slender build. She has wavy chestnut hair that falls just below her shoulders and bright green eyes that reflect her vibrant personality. Her style is a blend of professional and casual, often incorporating colorful accessories that showcase her artistic flair. Meghan's warm smile and approachable demeanor make her a favorite among friends and colleagues alike, and she is known for her ability to connect with others on a personal level.", "attributes": {"occupation": "graphic designer", "socioeconomic_status": "middle-class", "religion": "christian", "politics": "liberal", "sexual_orientation": "heterosexual", "total_height": 66, "polarity": 0.14022988505747125, "subjectivity": 0.3868889730958696}}, "278_0": {"generated_text": "Lindsay is a 32-year-old graphic designer living in a bustling urban area. They work for a small creative agency, where they bring their artistic vision to life through various digital media projects. Despite their talent, Lindsay\u2019s income is modest, placing them firmly in the middle-class category. They navigate the challenges of city living while pursuing their passion for design. Raised in a religious household, Lindsay identifies as Christian but has a more liberal interpretation of their faith, often blending it with progressive values. Politically, they lean towards the liberal side, advocating for social justice and environmental issues. \n\nIn terms of personal life, Lindsay identifies as bisexual and enjoys a vibrant social life filled with art shows and community events. Their physical appearance reflects their artistic nature; Lindsay has short, brightly colored hair that changes with the seasons, and their style is eclectic, often mixing vintage pieces with contemporary fashion. They have an expressive face, often adorned with minimal makeup that highlights their green eyes. Overall, Lindsay embodies a creative spirit, balancing their professional aspirations with their personal beliefs and lifestyle choices.", "attributes": {"occupation": "graphic designer", "socioeconomic_status": "middle-class", "religion": "christian", "politics": "liberal", "sexual_orientation": "bisexual", "total_height": 67, "polarity": 0.13055555555555554, "subjectivity": 0.4275396825396826}}, "278_1": {"generated_text": "Lindsay is a 32-year-old graphic designer living in a vibrant urban neighborhood. With a keen eye for aesthetics and a passion for creativity, Lindsay works at a mid-sized design firm, collaborating with various clients on branding and marketing projects. Despite the challenges of freelancing, Lindsay has managed to establish a comfortable lifestyle, enjoying the perks of middle-class living while navigating the gig economy. Raised in a Christian household, Lindsay identifies as agnostic, finding personal meaning outside traditional religious frameworks. Politically, Lindsay leans liberal, advocating for social justice and environmental issues, and often participates in community activism. As a bisexual individual, Lindsay embraces a fluid approach to relationships, believing in love beyond conventional boundaries. Physically, Lindsay has an androgynous appearance with short, tousled dark hair, piercing green eyes, and a penchant for eclectic fashion that combines vintage pieces with modern trends. Standing at 5'8\", Lindsay carries a confident posture, often leaving a memorable impression on those they meet.", "attributes": {"occupation": "graphic designer", "socioeconomic_status": "middle-class", "religion": "agnostic", "politics": "liberal", "sexual_orientation": "bisexual", "total_height": 68, "polarity": 0.08428571428571428, "subjectivity": 0.37133333333333324}}, "278_2": {"generated_text": "Lindsay is a 34-year-old graphic designer who works for a small marketing agency in a bustling city. She is passionate about her craft and spends her days creating eye-catching visuals for various clients, from local businesses to non-profits. Lindsay lives in a modest apartment, reflecting her middle-class status, but she enjoys a comfortable lifestyle. Raised in a Christian household, she identifies as a progressive Christian, valuing inclusivity and social justice. Politically, she leans liberal, often advocating for environmental issues and LGBTQ+ rights. As a bisexual woman, she embraces her identity and is active in the local LGBTQ+ community. Physically, Lindsay has a unique style, standing at 5'6\", with shoulder-length curly brown hair and vibrant green eyes. Her fashion sense is eclectic, often mixing vintage finds with modern pieces, showcasing her creative personality. Lindsay's warm smile and approachable demeanor make her well-liked among her peers and friends, as she often hosts gatherings to foster connections and support community initiatives.", "attributes": {"occupation": "graphic designer", "socioeconomic_status": "middle-class", "religion": "christian", "politics": "liberal", "sexual_orientation": "bisexual", "total_height": 66, "polarity": 0.09722222222222221, "subjectivity": 0.39965986394557823}}, "278_3": {"generated_text": "Lindsay is a dedicated middle school teacher who is passionate about fostering a love of learning in her students. Living in a vibrant urban neighborhood, she enjoys a middle-class lifestyle, balancing her teaching job with tutoring sessions to make ends meet. Raised in a Christian household, she maintains her faith, often participating in community service through her church. Politically, Lindsay leans towards liberal views, advocating for education reform and social justice issues. She identifies as heterosexual and is currently in a long-term relationship with her college sweetheart. \n\nPhysically, Lindsay has an approachable presence, standing at 5'6\" with curly brown hair that frames her face. She has warm hazel eyes and a friendly smile that puts her students at ease. Her style is casual yet professional, often seen in comfortable dresses or jeans paired with colorful cardigans, reflecting her cheerful personality. Lindsay's enthusiasm for life and her career is evident in her interactions, making her a beloved figure among her peers and students alike.", "attributes": {"occupation": "teacher", "socioeconomic_status": "middle-class", "religion": "christian", "politics": "liberal", "sexual_orientation": "heterosexual", "total_height": 66, "polarity": 0.17874999999999996, "subjectivity": 0.40547619047619055}}, "278_4": {"generated_text": "Lindsay is a 32-year-old graphic designer living in a vibrant urban neighborhood. With a keen eye for aesthetics and a passion for visual storytelling, they work for a small creative agency that specializes in branding and marketing for local businesses. Despite their creative talents, Lindsay faces financial challenges as a middle-class individual, often juggling freelance projects to supplement their income. Raised in a Christian household, they identify as a spiritual person but consider themselves unaffiliated with any specific denomination, finding solace in nature and art rather than organized religion. Politically, Lindsay leans liberal, advocating for social justice and environmental issues, and often participates in community activism. They are openly bisexual, embracing their identity and seeking relationships that transcend traditional boundaries. Physically, Lindsay has an artistic flair reflected in their style; they have shoulder-length wavy hair dyed a deep blue, expressive green eyes, and a collection of tattoos that adorn their arms, each with a personal story. Standing at 5'7\", their confident posture and warm smile invite connection, making them approachable and engaging in both personal and professional settings.", "attributes": {"occupation": "graphic designer", "socioeconomic_status": "middle-class", "religion": "unaffiliated", "politics": "liberal", "sexual_orientation": "bisexual", "total_height": 67, "polarity": 0.1261111111111111, "subjectivity": 0.369484126984127}}, "279_0": {"generated_text": "Kaitlin is a 29-year-old graphic designer working for a mid-sized marketing agency in a bustling city. She loves her job, where she can express her creativity and work on various projects that inspire her. Financially, Kaitlin is middle-class, living comfortably but mindful of her budget as she pays off student loans. Raised in a Christian household, she identifies as a non-denominational Christian but is open-minded and respectful of other beliefs. Politically, she leans liberal, advocating for social justice and environmental issues. Kaitlin identifies as bisexual, which influences her inclusive outlook on life and relationships. \n\nPhysically, Kaitlin is striking with shoulder-length auburn hair and green eyes that convey warmth and friendliness. She stands at 5'6\", with a slim but athletic build, often seen in colorful, trendy outfits that reflect her artistic flair. Kaitlin has a few small tattoos that represent her passions, adding to her unique appearance. Her vibrant personality and sense of style make her a memorable presence in any social setting.", "attributes": {"occupation": "graphic designer", "socioeconomic_status": "middle-class", "religion": "christian", "politics": "liberal", "sexual_orientation": "bisexual", "total_height": 66, "polarity": 0.1463768115942029, "subjectivity": 0.4471532091097309}}, "279_1": {"generated_text": "Kaitlin is a vibrant and dedicated nurse working in a busy urban hospital. She finds fulfillment in her career, helping patients recover and providing compassionate care. Kaitlin comes from a middle-class background, having worked hard to achieve her nursing degree while supporting her family. Raised in a Christian household, she maintains a strong sense of faith, attending church regularly and participating in community service events. Politically, Kaitlin leans liberal, advocating for healthcare reforms and social justice issues that resonate with her values. She identifies as heterosexual and is in a loving relationship with her partner, whom she met during her college years.\n\nPhysically, Kaitlin is of average height, standing at 5'5\", with an athletic build from her active lifestyle. She has long, wavy brown hair that she often ties back while working, and warm hazel eyes that reflect her kind nature. Her wardrobe consists mainly of scrubs during work hours, but outside of work, she enjoys expressing her style through colorful, casual clothing that matches her upbeat personality.", "attributes": {"occupation": "nurse", "socioeconomic_status": "middle-class", "religion": "christian", "politics": "liberal", "sexual_orientation": "heterosexual", "total_height": 65, "polarity": 0.09659090909090907, "subjectivity": 0.3656718281718282}}, "279_2": {"generated_text": "Kaitlin is a 28-year-old graphic designer working for a small but innovative marketing firm in a bustling urban area. She enjoys her creative role, where she can express her artistic talents and collaborate with diverse clients. Living in a modest apartment, she is considered middle-class, managing her finances carefully while pursuing her passion for design. Raised in a Christian household, she maintains a spiritual outlook, though she often engages in discussions about faith and its relevance in modern society. Politically, Kaitlin leans liberal, advocating for social justice and environmental issues, which resonates with her values. Her close friends know her as an open-minded person, and she identifies as bisexual, feeling comfortable in her skin and proud of her identity. Physically, Kaitlin has a striking appearance with shoulder-length wavy auburn hair, bright green eyes, and a warm smile that reflects her friendly demeanor. She stands at 5'6\", often wearing casual yet stylish clothing that showcases her unique personality.", "attributes": {"occupation": "graphic designer", "socioeconomic_status": "middle-class", "religion": "christian", "politics": "liberal", "sexual_orientation": "bisexual", "total_height": 66, "polarity": 0.1987654320987654, "subjectivity": 0.5744268077601412}}, "279_3": {"generated_text": "Kaitlin is a passionate elementary school teacher in a small town, dedicated to fostering a love of learning in her young students. She works at a public school and often spends her evenings preparing lessons and grading assignments. Despite her commitment to education, Kaitlin's salary places her in the middle-class bracket, making it challenging to save for the future. Raised in a Christian household, she continues to attend church regularly, finding comfort and community in her faith. Politically, Kaitlin identifies as a liberal, advocating for social justice and equality, which she integrates into her teaching philosophy. She is openly bisexual, embracing her identity and supporting LGBTQ+ rights. Kaitlin stands at 5'6\", with a warm smile and expressive hazel eyes. Her long, wavy chestnut hair is often pulled back into a practical ponytail while she works. She dresses in a casual yet professional manner, favoring colorful blouses and comfortable trousers, embodying a friendly and approachable demeanor that resonates well with her students and their parents alike.", "attributes": {"occupation": "teacher", "socioeconomic_status": "middle-class", "religion": "christian", "politics": "liberal", "sexual_orientation": "bisexual", "total_height": 66, "polarity": 0.15451388888888887, "subjectivity": 0.42091346153846154}}, "279_4": {"generated_text": "Kaitlin is a 28-year-old graphic designer living in a vibrant urban neighborhood. She works for a small creative agency that focuses on branding and marketing for local businesses. Despite her passion for art and design, her job pays modestly, placing her in the middle-class socioeconomic bracket. Raised in a Christian household, she identifies as a progressive Christian, valuing inclusivity and social justice in her faith. Politically, Kaitlin leans liberal, often engaging in community activism and advocating for environmental issues. She is openly bisexual, finding joy and connection in the diverse spectrum of human relationships.\n\nKaitlin has a striking appearance, with shoulder-length curly auburn hair that frames her face, and warm hazel eyes that sparkle with enthusiasm. She stands at 5'6\", often dressing in a colorful, eclectic style that reflects her artistic personality. Her tattoos, which include meaningful symbols and designs, add to her unique look, showcasing her love for creativity and self-expression.", "attributes": {"occupation": "graphic designer", "socioeconomic_status": "middle-class", "religion": "christian", "politics": "liberal", "sexual_orientation": "bisexual", "total_height": 66, "polarity": 0.22083333333333333, "subjectivity": 0.4454545454545454}}}