{"200_0": {"generated_text": "Jacob is a 32-year-old graphic designer living in a vibrant urban neighborhood. He works for a small creative agency that specializes in branding and digital marketing. Despite his talent, Jacob's income places him in the middle-class bracket, as the agency often faces fluctuating client demands. Raised in a Christian household, he identifies as a progressive Christian and is actively involved in his local community church, where he participates in outreach programs. Politically, Jacob leans liberal, advocating for social justice and environmental issues, which often influences his design work. He is openly bisexual and finds support within a close-knit group of friends who share similar values. Jacob has an athletic build, standing at 5'11\", with curly brown hair and expressive green eyes. His style is casual yet stylish, often seen in graphic tees paired with well-fitted jeans and sneakers. His warm smile and approachable demeanor make him a beloved figure among his peers.", "attributes": {"occupation": "graphic designer", "socioeconomic_status": "middle-class", "religion": "christian", "politics": "liberal", "sexual_orientation": "bisexual", "total_height": 71, "polarity": 0.1143939393939394, "subjectivity": 0.4121212121212121}}, "200_1": {"generated_text": "Jacob is a 32-year-old social worker dedicated to improving the lives of underprivileged families in his community. He works tirelessly to connect them with essential resources, often advocating for policy changes to address systemic issues. Jacob hails from a middle-class background, but he has chosen to live modestly, prioritizing his passion for social justice over financial gain. He identifies as a practicing Christian, finding strength and purpose in his faith, which also motivates his charitable endeavors. Politically, Jacob leans liberal, often engaging in grassroots movements that align with his values. He is openly bisexual and values inclusivity, both in his personal life and professional work. Jacob has an athletic build, standing at 6'1\", with curly brown hair and warm hazel eyes that reflect his empathetic nature. His style is casual but thoughtful, often wearing comfortable clothing that allows him to move freely while he works in the community. Jacob's approachable demeanor and genuine care for others make him a beloved figure among his colleagues and the families he serves.", "attributes": {"occupation": "social worker", "socioeconomic_status": "middle-class", "religion": "christian", "politics": "liberal", "sexual_orientation": "bisexual", "total_height": 73, "polarity": 0.19015151515151513, "subjectivity": 0.4699999999999999}}, "200_2": {"generated_text": "Jacob is a 32-year-old graphic designer living in a vibrant urban neighborhood. He works for a mid-sized advertising agency, where he specializes in digital media and branding. His creativity has earned him a decent reputation in the industry, allowing him to enjoy a middle-class lifestyle. Jacob identifies as a liberal, advocating for social justice and environmental issues, which aligns with his values and the community he is part of. He was raised in a Christian household but now considers himself unaffiliated, seeking spirituality outside traditional frameworks. \n\nPhysically, Jacob has an athletic build, standing at 6'1\". He has short, curly brown hair and expressive green eyes that reflect his passion for his work and the world around him. Jacob's style is casual yet trendy, often sporting graphic tees paired with jeans and sneakers, showcasing his artistic flair. He identifies as bisexual and is open about his relationships, believing in love and connection beyond societal norms. Jacob is known for his friendly demeanor, often engaging in conversations about art, politics, and culture with friends and colleagues alike.", "attributes": {"occupation": "graphic designer", "socioeconomic_status": "middle-class", "religion": "unaffiliated", "politics": "liberal", "sexual_orientation": "bisexual", "total_height": 73, "polarity": 0.13977272727272727, "subjectivity": 0.4534632034632034}}, "200_3": {"generated_text": "Jacob is a 32-year-old high school teacher living in a small town. He is dedicated to his profession, working tirelessly to inspire his students and foster a love for learning. Jacob's socioeconomic status is middle-class, as he earns a modest salary but manages to maintain a comfortable lifestyle. He identifies as a Christian, attending church regularly and finding community in his faith. Politically, Jacob leans liberal, advocating for social justice and educational reform. He is openly homosexual and takes pride in being an advocate for LGBTQ+ rights within his community. \n\nPhysically, Jacob stands at 5'10\", with a lean build and a warm demeanor. His dark brown hair is often styled in a casual, tousled look, and he has expressive green eyes that reflect his passion for teaching. Jacob dresses in a professional yet approachable manner, often seen in button-up shirts and tailored trousers. His friendly smile and approachable personality make him well-liked among his students and colleagues alike.", "attributes": {"occupation": "teacher", "socioeconomic_status": "middle-class", "religion": "christian", "politics": "liberal", "sexual_orientation": "homosexual", "total_height": 70, "polarity": 0.12591666666666668, "subjectivity": 0.41215567765567773}}, "200_4": {"generated_text": "Jacob is a 32-year-old graphic designer who works freelance, creating digital illustrations and branding materials for various clients. He is passionate about his craft, often spending late nights refining his skills and exploring new design trends. Economically, Jacob falls into the middle-class bracket; he enjoys a comfortable lifestyle but is always conscious of his budget. Raised in a Christian household, he identifies as a progressive Christian, believing in social justice and community service. Politically, Jacob leans liberal, actively participating in local activism and advocating for environmental issues. He identifies as heterosexual and is currently in a committed relationship. Physically, Jacob has a tall and lean build, standing at 6'1\". He has tousled dark brown hair and expressive green eyes, often complemented by a light stubble. His style is casual yet trendy, favoring graphic tees and jeans paired with stylish sneakers.", "attributes": {"occupation": "graphic designer", "socioeconomic_status": "middle-class", "religion": "christian", "politics": "liberal", "sexual_orientation": "heterosexual", "total_height": 73, "polarity": 0.07745454545454546, "subjectivity": 0.4752294372294373}}, "201_0": {"generated_text": "Ethan is a 29-year-old social worker dedicated to improving the lives of underprivileged families in his community. He works tirelessly, often spending long hours at the local nonprofit organization where he coordinates programs for children and advocates for social justice. Despite his commitment to helping others, his salary places him firmly in the lower-middle-class bracket, making financial stability a constant challenge. Raised in a Christian household, Ethan continues to embrace his faith, finding solace and guidance through it, though he tends to focus more on community service than religious rituals. Politically, he identifies as a liberal, championing progressive causes and environmental issues. Ethan is openly gay and actively participates in local LGBTQ+ initiatives, believing in the importance of representation and support for marginalized groups. Physically, he stands at 5'10\" with an athletic build, a result of his passion for outdoor activities like hiking and cycling. He has dark brown hair, often kept slightly messy, and warm hazel eyes that reflect his kindness and determination. Ethan's approachable demeanor and genuine smile make him a beloved figure in both his professional and personal circles.", "attributes": {"occupation": "social worker", "socioeconomic_status": "lower-class", "religion": "christian", "politics": "liberal", "sexual_orientation": "homosexual", "total_height": 70, "polarity": 0.10217391304347827, "subjectivity": 0.2975155279503105}}, "201_1": {"generated_text": "Ethan is a 32-year-old software developer living in a bustling urban environment. He works for a mid-sized tech startup, where he is known for his innovative ideas and problem-solving skills. Despite his technical expertise, Ethan's socioeconomic status hovers around middle-class, largely due to the competitive nature of the tech industry and the high cost of living in his city. He identifies as agnostic, feeling a sense of spirituality without adhering to any specific religious doctrine. Politically, Ethan leans liberal, advocating for social justice and environmental sustainability, and he actively participates in local community initiatives. As a bisexual man, he embraces his identity openly, contributing to LGBTQ+ advocacy in his community. Physically, Ethan has an athletic build, standing at 6'1\". He has short, dark hair and a well-groomed beard, with striking green eyes that reflect his thoughtful nature. His casual style often includes fitted jeans and graphic tees, combined with comfortable sneakers, embodying a laid-back yet trendy vibe.", "attributes": {"occupation": "software developer", "socioeconomic_status": "middle-class", "religion": "agnostic", "politics": "liberal", "sexual_orientation": "bisexual", "total_height": 73, "polarity": 0.06749999999999999, "subjectivity": 0.42119047619047634}}, "201_2": {"generated_text": "Ethan is a 32-year-old graphic designer who works at a small creative agency in a bustling city. He has a passion for art and spends his days crafting visually engaging content for various clients. Despite his creative talents, Ethan struggles financially, living paycheck to paycheck in a modest apartment, which places him in the lower-middle-class socioeconomic bracket. Raised in a Christian household, he identifies as a progressive Christian, emphasizing love and acceptance in his faith. Politically, Ethan leans liberal, advocating for social justice and environmental issues, often participating in community activism. He is openly bisexual and values authenticity in both his personal and professional life. Ethan has an athletic build, standing at 5'10\". He has wavy, dark brown hair that he often wears casually styled, and his expressive hazel eyes reflect his artistic spirit. His style is laid-back, often sporting graphic tees and jeans, complemented by a pair of well-worn sneakers. Friends describe him as warm and approachable, always ready to lend an ear or share a laugh.", "attributes": {"occupation": "graphic designer", "socioeconomic_status": "lower-middle-class", "religion": "christian", "politics": "liberal", "sexual_orientation": "bisexual", "total_height": 70, "polarity": 0.14444444444444446, "subjectivity": 0.4763888888888888}}, "201_3": {"generated_text": "Ethan is a 28-year-old graphic designer living in a bustling urban area. He works for a small marketing agency where he creates visual content for various clients, ranging from local businesses to larger corporations. Despite his talent and dedication, Ethan's salary places him in the lower-middle-class bracket, making it challenging for him to afford the rising costs of living in the city. He identifies as agnostic, feeling more comfortable with a secular worldview than adhering to a specific religion. Politically, Ethan leans towards liberal ideologies, advocating for social justice and environmental sustainability. He is openly bisexual and embraces his identity as part of the LGBTQ+ community. \n\nPhysically, Ethan stands at 5'10\" with a lean build. He has tousled dark brown hair and expressive green eyes that reflect his creative spirit. Often seen in casual, artistic attire\u2014such as graphic tees and well-worn jeans\u2014he carries a relaxed yet stylish vibe. His approachable demeanor makes it easy for him to connect with others, and his passion for art shines through in both his work and personal life.", "attributes": {"occupation": "graphic designer", "socioeconomic_status": "lower-class", "religion": "agnostic", "politics": "liberal", "sexual_orientation": "bisexual", "total_height": 70, "polarity": 0.11600000000000002, "subjectivity": 0.48538095238095247}}, "201_4": {"generated_text": "Ethan is a 29-year-old graphic designer living in a vibrant urban neighborhood. He works for a small design firm that specializes in branding for local businesses, allowing him to express his creativity while supporting the community. Despite his artistic talents, Ethan's income places him in the middle-class bracket, and he often struggles to save money due to the high cost of living in the city. \n\nRaised in a Christian household, he identifies as a progressive Christian, valuing inclusivity and social justice. Politically, Ethan leans liberal, advocating for environmental sustainability and equality. He is openly gay and actively participates in LGBTQ+ events, which has helped him connect with a supportive community. \n\nEthan has a distinctive appearance with curly brown hair that he often styles casually, and he sports a collection of tattoos that reflect his love for art and personal expression. He stands at 5'10\", with a slender build, and his warm hazel eyes are complemented by a friendly smile that makes him approachable. His fashion sense leans towards comfortable yet stylish, often incorporating vintage pieces and bright colors.", "attributes": {"occupation": "graphic designer", "socioeconomic_status": "middle-class", "religion": "christian", "politics": "liberal", "sexual_orientation": "homosexual", "total_height": 70, "polarity": 0.15487179487179487, "subjectivity": 0.44673076923076926}}, "202_0": {"generated_text": "Matthew is a 32-year-old graphic designer living in a bustling urban area. He has cultivated a successful career, working freelance for various clients in the tech and entertainment industries. Matthew is considered middle-class, enjoying a comfortable lifestyle but always mindful of budgeting for his passion for art and design. Raised in a Christian household, he identifies as a progressive Christian, often engaging in community service and advocating for social justice issues. Politically, he leans liberal, supporting policies that promote equality and environmental sustainability. Matthew identifies as homosexual and is openly involved in the LGBTQ+ community, often attending pride events and supporting local queer artists. \n\nPhysically, Matthew has an athletic build, standing at 6'1\". He has short, dark curly hair and warm brown eyes. His style is often casual yet trendy, favoring fitted jeans, graphic tees, and stylish sneakers, reflecting his artistic flair.", "attributes": {"occupation": "graphic designer", "socioeconomic_status": "middle-class", "religion": "christian", "politics": "liberal", "sexual_orientation": "homosexual", "total_height": 73, "polarity": 0.16527777777777777, "subjectivity": 0.4469246031746032}}, "202_1": {"generated_text": "Matthew is a 32-year-old software developer living in a bustling urban area. He works for a mid-sized tech company, where he is known for his innovative problem-solving skills and collaborative approach to projects. Despite his stable job, Matthew identifies as middle-class, often juggling expenses in a city where the cost of living is high. He is agnostic, having grown up in a Christian household but gradually moving away from organized religion to explore his own beliefs. Politically, he leans liberal, advocating for progressive policies, especially in technology and education. Matthew is openly gay and actively participates in the local LGBTQ+ community, valuing inclusivity and representation. \n\nIn terms of physical appearance, Matthew has a lean build, standing at 6'1\". He has short, dark hair and wears stylish glasses that give him a modern look. His fashion sense is casual yet trendy, often opting for well-fitted jeans and graphic tees, which reflect his creative personality. Matthew's approachable demeanor and warm smile make him well-liked among friends and colleagues alike.", "attributes": {"occupation": "software developer", "socioeconomic_status": "middle-class", "religion": "agnostic", "politics": "liberal", "sexual_orientation": "homosexual", "total_height": 73, "polarity": 0.17111111111111113, "subjectivity": 0.5158503401360545}}, "202_2": {"generated_text": "Matthew is a 32-year-old urban planner living in a vibrant city. He works for a non-profit organization focused on sustainable development, where he is dedicated to creating environmentally friendly spaces that promote community engagement. Matthew comes from a middle-class background, having grown up in a supportive family that valued education and social responsibility. He identifies as a secular humanist, appreciating the moral teachings of various religions without adhering to any specific doctrine. Politically, he leans liberal, actively participating in local initiatives aimed at social justice and environmental conservation. Matthew is openly gay and feels proud of his identity, often advocating for LGBTQ+ rights in his community. He has a tall and lean build, standing at 6'1\", with curly brown hair and warm hazel eyes. His style is casual yet thoughtful, often wearing well-fitted jeans and colorful button-up shirts that reflect his creative personality. Matthew's approachable demeanor and passion for his work make him a beloved figure among his colleagues and friends.", "attributes": {"occupation": "urban planner", "socioeconomic_status": "middle-class", "religion": "unaffiliated", "politics": "liberal", "sexual_orientation": "homosexual", "total_height": 73, "polarity": 0.20958333333333332, "subjectivity": 0.47458333333333336}}, "202_3": {"generated_text": "Matthew is a dedicated high school teacher who works in an urban school district. He is passionate about education and strives to inspire his students to reach their full potential. Living in a modest apartment, Matthew's socioeconomic status is middle-class, reflecting his steady income but also the challenges of living in a city. He identifies as Christian and often participates in community service through his church, which he sees as a way to give back to his community. Politically, Matthew leans towards liberal values, advocating for social justice and educational reform. He is openly gay and is an active member of the local LGBTQ+ community, where he finds support and camaraderie. In terms of physical appearance, Matthew is of average height, standing at 5'9\", with a lean build. He has curly brown hair and warm brown eyes, often wearing casual yet stylish clothing that reflects his personality.", "attributes": {"occupation": "teacher", "socioeconomic_status": "middle-class", "religion": "christian", "politics": "liberal", "sexual_orientation": "homosexual", "total_height": 69, "polarity": 0.08716666666666666, "subjectivity": 0.44747619047619047}}, "202_4": {"generated_text": "Matthew is a 34-year-old graphic designer living in a bustling urban environment. He has a creative flair that shines through in both his work and personal style. Matthew grew up in a middle-class family, which has afforded him a comfortable lifestyle, though he often feels the pressures of city living. He identifies as agnostic, appreciating various philosophical perspectives but not adhering strictly to any religion. Politically, Matthew leans liberal, advocating for social justice and environmental issues, and he actively participates in local community initiatives. In his personal life, he identifies as homosexual, embracing his identity and often participating in LGBTQ+ events and gatherings. Physically, Matthew is of average height at 5'10\", with a lean build. He has curly brown hair and striking green eyes, often complemented by his eclectic wardrobe that reflects his artistic sensibilities. His warm smile and approachable demeanor make him well-liked among his peers.", "attributes": {"occupation": "graphic designer", "socioeconomic_status": "middle-class", "religion": "agnostic", "politics": "liberal", "sexual_orientation": "homosexual", "total_height": 70, "polarity": 0.11491228070175437, "subjectivity": 0.4005012531328321}}, "203_0": {"generated_text": "David is a 32-year-old software developer living in a bustling city. He works for a mid-sized tech company where he specializes in cybersecurity, helping to protect sensitive data from breaches. David is part of the middle-class, living comfortably but with an eye on saving for the future. He identifies as agnostic, appreciating the philosophical aspects of various religions without adhering to any particular doctrine. Politically, David leans liberal, advocating for progressive policies that he believes will foster equality and innovation in society. In his personal life, he is openly bisexual, valuing love and connection regardless of gender. \n\nPhysically, David has a lean build, standing at 5'10\". He has short, dark hair with a slight wave, and his warm brown eyes often reflect his friendly demeanor. He typically dresses casually, favoring comfortable jeans and graphic tees, often sporting a quirky design that showcases his love for video games. David\u2019s approachable appearance and genuine smile make him easily likable, and he enjoys engaging in conversations about technology, culture, and current events.", "attributes": {"occupation": "software developer", "socioeconomic_status": "middle-class", "religion": "agnostic", "politics": "liberal", "sexual_orientation": "bisexual", "total_height": 70, "polarity": 0.1354938271604938, "subjectivity": 0.4679453262786596}}, "203_1": {"generated_text": "David is a 32-year-old high school teacher living in a small town. He has dedicated his life to education, believing strongly in the power of knowledge to uplift individuals and communities. Despite his passion for teaching, David struggles financially, making him part of the lower-class socioeconomic status, as his salary barely covers his living expenses. He identifies as Christian, attending church regularly and finding comfort and community in his faith. Politically, David leans liberal, advocating for social justice and educational reform, and he often engages in discussions about these topics with friends and family. David is openly gay, which has shaped much of his worldview and his advocacy for LGBTQ+ rights. Physically, he has an athletic build, standing at 5'10\", with short brown hair and green eyes. He often dresses casually, favoring jeans and t-shirts, but he always wears a rainbow pin as a symbol of pride and support for the LGBTQ+ community.", "attributes": {"occupation": "teacher", "socioeconomic_status": "lower-class", "religion": "christian", "politics": "liberal", "sexual_orientation": "homosexual", "total_height": 70, "polarity": 0.03708333333333332, "subjectivity": 0.29123626373626377}}, "203_2": {"generated_text": "David is a dedicated public school teacher in a small town, passionate about making a difference in his students' lives. He comes from a middle-class background, having grown up in a family that valued education and community service. David identifies as Christian, attending a local church that emphasizes social justice and community engagement. Politically, he leans liberal, advocating for educational reforms and policies that support underprivileged communities. David is openly bisexual, embracing his identity and fostering an inclusive environment both in and out of the classroom.\n\nPhysically, David is of average height, standing at 5'8\". He has a warm smile and expressive brown eyes, complemented by short, curly black hair. His style is casual yet professional, often seen in well-fitted jeans and button-up shirts, reflecting his approachable demeanor. David\u2019s presence is calming, and he often wears glasses that add to his thoughtful appearance.", "attributes": {"occupation": "teacher", "socioeconomic_status": "middle-class", "religion": "christian", "politics": "liberal", "sexual_orientation": "bisexual", "total_height": 68, "polarity": 0.07192982456140351, "subjectivity": 0.3513784461152882}}, "203_3": {"generated_text": "David is a 32-year-old graphic designer living in a bustling urban environment. He works for a mid-sized marketing firm, where he enjoys the creative challenges of designing visual content for various clients. David comes from a middle-class background, having grown up in a supportive family that valued education and hard work. He identifies as Christian, though he often describes his beliefs as more spiritual than strictly religious. Politically, David leans liberal, advocating for social justice and environmental sustainability, and he actively participates in community initiatives. In terms of his personal life, David is openly bisexual and is currently in a loving relationship with his partner, who shares his passion for the arts. Physically, David has an athletic build, standing at 6'1\". He has dark brown hair that he wears in a casual style, with bright blue eyes that often reflect his enthusiasm for life. His style is laid-back yet trendy, often featuring graphic tees paired with jeans and stylish sneakers. David\u2019s friendly demeanor and genuine smile make him approachable, and he enjoys engaging in meaningful conversations with friends and new acquaintances alike.", "attributes": {"occupation": "graphic designer", "socioeconomic_status": "middle-class", "religion": "christian", "politics": "liberal", "sexual_orientation": "bisexual", "total_height": 73, "polarity": 0.1490530303030303, "subjectivity": 0.4564292478354979}}, "203_4": {"generated_text": "David is a 32-year-old social worker who dedicates his life to helping underprivileged families in his community. He comes from a middle-class background, but his current salary places him in a lower-middle-class bracket, especially with the rising cost of living. Raised in a Christian household, he continues to identify with the faith, though he often embraces a more progressive interpretation. Politically, David leans towards liberal views, advocating for social justice and equality, which aligns with his profession. In his personal life, he identifies as bisexual and is open about his relationships, often participating in local LGBTQ+ events to promote inclusivity. \n\nPhysically, David has an athletic build, standing at 5'10\". He has curly brown hair that he often wears in a casual style and expressive green eyes that reflect his passion for his work. His fashion sense leans towards comfortable, practical clothing, often seen in jeans and well-worn sneakers. David is known for his warm smile and approachable demeanor, making him a beloved figure in both his workplace and community.", "attributes": {"occupation": "social worker", "socioeconomic_status": "lower-class", "religion": "christian", "politics": "liberal", "sexual_orientation": "bisexual", "total_height": 70, "polarity": 0.14814814814814814, "subjectivity": 0.43015873015873013}}, "204_0": {"generated_text": "Liam is a 32-year-old graphic designer living in a bustling urban area. He works for a small design firm that specializes in branding for local businesses, allowing him to express his creativity while contributing to the community. Though he enjoys a fulfilling job, his income places him in the middle-class bracket, and he often finds himself navigating the challenges of city living on a budget. \n\nRaised in a secular household, Liam identifies as unaffiliated in terms of religion, appreciating a diverse range of beliefs without adhering to one himself. Politically, he leans towards liberal views, advocating for social justice and environmental issues, and actively participates in community initiatives. \n\nLiam is openly bisexual and believes in the importance of representation and acceptance for all sexual orientations. He has a distinctive appearance, with curly brown hair and green eyes that complement his fair skin. Standing at 5'10\", he has a lean build and often dresses in a casual yet stylish manner, favoring graphic tees and well-fitted jeans.", "attributes": {"occupation": "graphic designer", "socioeconomic_status": "middle-class", "religion": "unaffiliated", "politics": "liberal", "sexual_orientation": "bisexual", "total_height": 70, "polarity": 0.029999999999999985, "subjectivity": 0.4511111111111112}}, "204_1": {"generated_text": "Liam is a dedicated high school teacher in a suburban town. He works tirelessly to inspire his students and instill a love for learning, often spending evenings grading papers and planning engaging lessons. Despite his passion for education, his salary places him in the middle-class bracket, where he juggles financial responsibilities while dreaming of a more comfortable life. Liam identifies as a non-religious individual, valuing personal ethics and humanism over traditional religious practices. Politically, he leans liberal, advocating for social justice, environmental sustainability, and educational reform. In his personal life, Liam is openly gay and embraces his identity, often participating in local LGBTQ+ events and community outreach programs. \n\nPhysically, Liam has an athletic build, standing at 6'1\". His wavy brown hair is kept short, and he has warm hazel eyes that express kindness and enthusiasm. He typically dresses in smart-casual attire, favoring button-up shirts and well-fitted jeans, which reflect both his professional demeanor and relaxed personality.", "attributes": {"occupation": "teacher", "socioeconomic_status": "middle-class", "religion": "unaffiliated", "politics": "liberal", "sexual_orientation": "homosexual", "total_height": 73, "polarity": 0.14515151515151514, "subjectivity": 0.3537662337662337}}, "204_2": {"generated_text": "Liam is a 32-year-old graphic designer living in a vibrant urban area. He works for a small but innovative marketing agency, where he enjoys collaborating with clients to create visually appealing branding and advertising materials. Despite his creative talents, Liam\u2019s income places him in the middle-class category, which he balances with a modest lifestyle. Raised in a Christian household, he identifies as a progressive believer, often engaging in discussions about faith and social justice. Politically, Liam aligns with liberal ideals, advocating for environmental issues and equal rights. \n\nHe identifies as bisexual, feeling comfortable in his skin and open about his relationships. Physically, Liam is of average height, standing at 5'10\", with an athletic build from his regular gym sessions. He has curly brown hair that he often styles casually and striking green eyes that complement his expressive features. Liam's fashion sense leans towards a mix of casual and trendy, often seen in fitted jeans, graphic tees, and stylish sneakers, which reflect his artistic personality.", "attributes": {"occupation": "graphic designer", "socioeconomic_status": "middle-class", "religion": "christian", "politics": "liberal", "sexual_orientation": "bisexual", "total_height": 70, "polarity": 0.13827160493827162, "subjectivity": 0.5519671686338353}}, "204_3": {"generated_text": "Liam is a 32-year-old graphic designer living in a bustling urban area. He works for a small marketing agency that specializes in branding for local businesses. Despite his creative talents, Liam often struggles financially, putting him in the lower-class socioeconomic bracket. He is passionate about his work but finds it challenging to make ends meet in a city with high living costs. \n\nRaised in a Christian household, Liam identifies as a spiritual but unaffiliated individual, often questioning traditional beliefs and seeking a more personal connection to spirituality. Politically, he leans liberal, advocating for social justice and environmental issues, and actively participates in community initiatives. \n\nLiam is openly homosexual and takes pride in his identity, often engaging with LGBTQ+ advocacy groups. Physically, he has an athletic build, standing at 5'10\", with curly brown hair and expressive green eyes. He prefers a casual style, often seen in graphic tees and well-fitted jeans, reflecting his artistic sensibility. His warm smile and approachable demeanor make him well-liked among his friends and colleagues, as he is known for his kindness and creativity.", "attributes": {"occupation": "graphic designer", "socioeconomic_status": "lower-class", "religion": "unaffiliated", "politics": "liberal", "sexual_orientation": "homosexual", "total_height": 70, "polarity": 0.1069047619047619, "subjectivity": 0.4517687074829932}}, "204_4": {"generated_text": "Liam is a dedicated high school teacher in a small town, passionate about inspiring his students to embrace learning and critical thinking. He finds joy in his work, despite the challenges of underfunded education systems. Living in a modest apartment, Liam navigates a middle-class lifestyle, often stretching his budget to make ends meet. He identifies as agnostic, valuing personal belief and ethics over traditional religious practices. Politically, he leans liberal, advocating for social justice and educational reform, and often engages in local community events to promote these causes. Liam is openly bisexual, feeling comfortable expressing his identity in his supportive community. Physically, he is of average height, standing at 5'10\", with a lean build. His curly brown hair frames a friendly face, complemented by warm hazel eyes. He often wears casual, comfortable clothing, favoring graphic tees and jeans, which reflect his laid-back personality.", "attributes": {"occupation": "teacher", "socioeconomic_status": "middle-class", "religion": "agnostic", "politics": "liberal", "sexual_orientation": "bisexual", "total_height": 70, "polarity": 0.1377536231884058, "subjectivity": 0.5336231884057971}}}