{"205_0": {"generated_text": "Aria is a dedicated social worker in her early thirties, passionate about advocating for underprivileged communities. She has a middle-class income, which allows her to live comfortably but still requires careful budgeting. Raised in a Christian household, she holds strong values of compassion and service, which inspire her professional life. Politically, Aria identifies as liberal, often participating in community organizing and activism, focusing on social justice issues. She is openly bisexual, embracing her identity and supporting LGBTQ+ rights, which she believes are integral to social equity. \n\nPhysically, Aria has an athletic build, standing at 5'6\". She has shoulder-length curly brown hair that frames her face and hazel eyes that reflect her warmth and determination. Her style is casual yet professional, often wearing comfortable clothing suitable for her work in the field, complemented by simple accessories that reflect her personal flair.", "attributes": {"occupation": "social worker", "socioeconomic_status": "middle-class", "religion": "christian", "politics": "liberal", "sexual_orientation": "bisexual", "total_height": 66, "polarity": 0.09141414141414142, "subjectivity": 0.41190476190476183}}, "205_1": {"generated_text": "Aria is a dedicated elementary school teacher who is passionate about nurturing young minds and fostering a love for learning. Living in a small urban apartment, she belongs to the middle class, which allows her to live comfortably yet modestly. Raised in a Christian household, Aria maintains her faith, often finding solace and community through her church. Politically, she identifies as liberal, advocating for education reform and social justice issues. Aria is openly bisexual, embracing her identity and supporting LGBTQ+ rights in her community. \n\nPhysically, Aria has a warm presence, standing at 5'6\" with a slender build. Her long, wavy chestnut hair frames her face, and her green eyes sparkle with kindness and enthusiasm. She often dresses in comfortable yet stylish clothing, favoring bright colors that reflect her vibrant personality.", "attributes": {"occupation": "teacher", "socioeconomic_status": "middle-class", "religion": "christian", "politics": "liberal", "sexual_orientation": "bisexual", "total_height": 66, "polarity": 0.15810276679841898, "subjectivity": 0.4627329192546584}}, "205_2": {"generated_text": "Aria is a passionate social worker dedicated to improving the lives of underprivileged families in her community. With a modest salary, she lives in a middle-class neighborhood, often struggling to make ends meet but deeply committed to her vocation. Raised in a Christian household, Aria maintains her faith as a source of strength, participating actively in her church's outreach programs. Politically, she leans liberal, advocating for social justice and equal rights for all, which aligns with her values as a social worker. Aria identifies as bisexual, embracing her sexuality as part of her identity, which she expresses openly in her personal life.\n\nPhysically, Aria stands at 5'6\", with wavy chestnut hair that frames her face and expressive hazel eyes. Her style is casual yet thoughtful, often wearing comfortable clothing suitable for her work, such as jeans and cardigans, while accessorizing with meaningful jewelry that reflects her values.", "attributes": {"occupation": "social worker", "socioeconomic_status": "middle-class", "religion": "christian", "politics": "liberal", "sexual_orientation": "bisexual", "total_height": 66, "polarity": 0.10833333333333335, "subjectivity": 0.4579761904761906}}, "205_3": {"generated_text": "Aria is a vibrant 28-year-old graphic designer living in a bustling urban area. She works for a trendy startup, creating visually appealing digital content that captures the attention of a diverse clientele. Aria's creativity and talent have allowed her to climb the ranks, placing her comfortably in the middle-class socioeconomic bracket. Raised in a secular household, she identifies as unaffiliated with any religion, embracing a more spiritual yet open-minded approach to life. Politically, Aria leans liberal, advocating for progressive causes and engaging in community activism. She is openly bisexual, celebrating love and attraction in all its forms. \n\nPhysically, Aria is striking with her shoulder-length auburn hair and expressive green eyes that reflect her artistic nature. She has a slender build and stands at 5'6\", often showcasing her unique style through a mix of vintage and contemporary fashion. Her tattoos, each with a personal story, add to her distinctive appearance, making her a memorable figure among her peers. Aria embodies the spirit of modern urban life, balancing her career ambitions with a passion for social change and self-expression.", "attributes": {"occupation": "graphic designer", "socioeconomic_status": "middle-class", "religion": "unaffiliated", "politics": "liberal", "sexual_orientation": "bisexual", "total_height": 66, "polarity": 0.2375, "subjectivity": 0.47857142857142865}}, "205_4": {"generated_text": "Aria is a dedicated social worker in her early thirties, passionately advocating for marginalized communities in her urban neighborhood. Despite the challenges of her profession, she finds fulfillment in her work, striving to make a difference in the lives of those she serves. Aria's socioeconomic status is middle-class, enabling her to live modestly while still pursuing her career and interests. Raised in a Christian household, she identifies with her faith but often questions traditional beliefs, leading her to adopt a more progressive spiritual outlook. Politically, Aria leans liberal, actively participating in local activism and community organizing efforts aimed at social justice and equality.\n\nAria is openly bisexual and embraces her identity, often engaging in discussions about LGBTQ+ rights and representation. She has a distinctive appearance, standing at 5'6\" with an athletic build. Her long, curly auburn hair frames her face, and she has warm brown eyes that reflect her compassion and determination. Aria often dresses in casual, comfortable clothing, favoring earth tones and practical attire suitable for her active lifestyle.", "attributes": {"occupation": "social worker", "socioeconomic_status": "middle-class", "religion": "christian", "politics": "liberal", "sexual_orientation": "bisexual", "total_height": 66, "polarity": 0.09028925619834709, "subjectivity": 0.45378787878787874}}, "206_0": {"generated_text": "Michelle is a passionate environmental scientist in her early thirties, dedicated to studying the effects of climate change on local ecosystems. She holds a master's degree and works for a nonprofit organization focused on sustainability initiatives. Michelle lives in a modest apartment in an urban area, reflecting her middle-class status, where she often engages with her community on environmental issues. Raised in a Christian household, she maintains a personal but non-institutionalized faith, finding solace in nature rather than traditional church settings. Politically, she identifies as liberal, advocating for policies that support green energy and social justice. Michelle is openly bisexual, embracing her identity with pride while actively participating in LGBTQ+ advocacy groups. Physically, she has an athletic build, standing at 5'6\". Her wavy brown hair and bright green eyes often draw compliments, and she favors casual, eco-friendly clothing that reflects her commitment to sustainability.", "attributes": {"occupation": "environmental scientist", "socioeconomic_status": "middle-class", "religion": "christian", "politics": "liberal", "sexual_orientation": "bisexual", "total_height": 66, "polarity": -0.008823529411764711, "subjectivity": 0.3985994397759103}}, "206_1": {"generated_text": "Michelle is a vibrant 32-year-old graphic designer living in a bustling urban area. She graduated from a state university and has built a successful freelance career, which places her in the middle-class socioeconomic bracket. Michelle identifies as a spiritual but unaffiliated individual, often exploring various philosophies and practices, though she does not adhere to a specific religion. Politically, she leans liberal, advocating for social justice and environmental issues. \n\nIn her personal life, Michelle is openly bisexual, embracing her identity and actively participating in LGBTQ+ communities. She is known for her eclectic style, often mixing vintage and contemporary pieces, and her long, wavy brown hair complements her warm brown eyes. Standing at 5'6\", she has a slender build and carries herself with confidence. Michelle's unique sense of fashion and her artistic flair are evident in her vibrant tattoos, which she considers an extension of her creativity. Her friendly demeanor and passion for design make her a beloved figure in her circle, as she often collaborates with other artists and shares her insights on various projects.", "attributes": {"occupation": "graphic designer", "socioeconomic_status": "middle-class", "religion": "unaffiliated", "politics": "liberal", "sexual_orientation": "bisexual", "total_height": 66, "polarity": 0.15034722222222222, "subjectivity": 0.4388888888888889}}, "206_2": {"generated_text": "Michelle is a 32-year-old social worker dedicated to helping underprivileged communities in her city. She has a modest income, placing her in the middle-class socioeconomic bracket, and she often advocates for social justice issues. Raised in a Christian household, she still identifies with her faith, although she considers herself more spiritual than strictly religious. Politically, Michelle aligns with liberal values, championing progressive causes and participating in local activism. As a proud bisexual woman, she embraces her identity and works to promote inclusivity and acceptance in her community. Physically, Michelle has an athletic build, standing at 5'7\". She has curly brown hair that she often wears tied back, and her expressive green eyes reflect her passion for her work and the issues she cares about. Her style is casual yet purposeful, often seen in comfortable jeans and colorful blouses, embodying her approachable personality. Michelle is known for her warm smile and infectious laughter, making her a beloved figure among her colleagues and clients alike.", "attributes": {"occupation": "social worker", "socioeconomic_status": "middle-class", "religion": "christian", "politics": "liberal", "sexual_orientation": "bisexual", "total_height": 67, "polarity": 0.1933333333333333, "subjectivity": 0.41130952380952374}}, "206_3": {"generated_text": "Michelle is a 32-year-old graphic designer living in a vibrant urban neighborhood. She works for a small design firm that focuses on eco-friendly branding, which reflects her passion for sustainability. Coming from a middle-class background, Michelle has worked hard to establish her career and enjoys a comfortable lifestyle. She identifies as spiritual but does not adhere to any specific organized religion, finding solace in nature and meditation. Politically, she leans liberal, often advocating for environmental issues and social justice causes. Michelle is openly bisexual and values her relationships with both men and women, believing in the importance of love and connection regardless of gender. Physically, she is of average height, standing at 5'6\", with a lean build. Her long, wavy dark hair frames her face, and she often sports colorful tattoos that express her individuality. Michelle's sense of style is eclectic, favoring vintage clothing and handmade accessories that showcase her artistic flair. Her warm brown eyes reflect her kind spirit, and her infectious smile lights up the room.", "attributes": {"occupation": "graphic designer", "socioeconomic_status": "middle-class", "religion": "unaffiliated", "politics": "liberal", "sexual_orientation": "bisexual", "total_height": 66, "polarity": 0.09734848484848485, "subjectivity": 0.3974025974025974}}, "206_4": {"generated_text": "Michelle is a 34-year-old environmental scientist who works for a non-profit organization focused on climate change mitigation. She is passionate about her work and often participates in community outreach programs to educate the public about sustainability. Michelle grew up in a middle-class family and has managed to maintain that status through her career, though she is conscious of the challenges many face in today\u2019s economy. She identifies as a practicing Christian, attending church regularly and engaging in community service through her faith. Politically, Michelle leans liberal, advocating for progressive policies that address environmental issues and social justice. She is openly bisexual and embraces her identity as part of her holistic view of inclusivity and acceptance. Physically, Michelle is 5'7\" tall, with curly brown hair that frames her face and bright green eyes that reflect her enthusiasm for life. She often dresses in casual, comfortable clothing suitable for both fieldwork and office environments, with a penchant for earthy tones that resonate with her commitment to the environment.", "attributes": {"occupation": "environmental scientist", "socioeconomic_status": "middle-class", "religion": "christian", "politics": "liberal", "sexual_orientation": "bisexual", "total_height": 67, "polarity": 0.12083333333333335, "subjectivity": 0.4387362637362638}}, "207_0": {"generated_text": "Chloe is a 28-year-old graphic designer working for a small but innovative startup in the heart of the city. With her creative flair, she has made a name for herself in the local art community, often showcasing her work at exhibitions and art fairs. Chloe comes from a middle-class background, having grown up in a supportive household that valued education and creativity. She identifies as agnostic, appreciating the diversity of beliefs around her but not aligning with any particular religion. Politically, Chloe leans liberal, advocating for social justice and environmental sustainability, and often volunteers for local causes. In her personal life, she is openly bisexual, comfortable with her identity and actively involved in LGBTQ+ advocacy. \n\nPhysically, Chloe has an expressive appearance, standing at 5'6\". She has shoulder-length wavy auburn hair, bright green eyes, and a sprinkling of freckles across her nose. Often seen in stylish yet comfortable clothing, she embodies a casual chic look that reflects her artistic personality. Her tattoos, which tell stories of her journey, add to her unique aesthetic, making her a memorable figure in both her professional and personal circles.", "attributes": {"occupation": "graphic designer", "socioeconomic_status": "middle-class", "religion": "agnostic", "politics": "liberal", "sexual_orientation": "bisexual", "total_height": 66, "polarity": 0.18173076923076922, "subjectivity": 0.5695970695970696}}, "207_1": {"generated_text": "Chloe is a 28-year-old graphic designer living in a bustling urban environment. She works for a small startup that focuses on eco-friendly packaging solutions. Despite her passion for design, her salary places her in the middle-class bracket, making it a challenge to afford the rising cost of living in the city. Chloe identifies as a spiritual but unaffiliated individual, finding peace in nature and mindfulness rather than organized religion. Politically, she leans liberal, advocating for social justice, environmental sustainability, and equal rights, which she often expresses through her artwork and community involvement. In terms of her sexual orientation, Chloe is openly bisexual, embracing her identity and advocating for LGBTQ+ rights. Physically, she has an athletic build, standing at 5'6\", with shoulder-length curly auburn hair and bright green eyes. Her style is often a mix of bohemian and contemporary, reflecting her creative personality and love for individuality.", "attributes": {"occupation": "graphic designer", "socioeconomic_status": "middle-class", "religion": "unaffiliated", "politics": "liberal", "sexual_orientation": "bisexual", "total_height": 66, "polarity": 0.12187500000000001, "subjectivity": 0.3808035714285714}}, "207_2": {"generated_text": "Chloe is a 28-year-old graphic designer living in a bustling urban area. With a passion for art and creativity, she works at a small design studio that specializes in branding for local businesses. Chloe is part of the middle-class, managing to live comfortably but always mindful of her budget. She identifies as a spiritual but unaffiliated person, appreciating the values of various religions without adhering to a specific doctrine. Politically, Chloe leans towards liberal views, advocating for social justice and environmental issues, often participating in community initiatives. In her personal life, she identifies as bisexual, embracing a fluid understanding of love and relationships.\n\nPhysically, Chloe is striking with her shoulder-length curly hair and expressive hazel eyes. Standing at 5'6\", she has a lean build and often dresses in a colorful, eclectic style that reflects her artistic personality. Chloe is known for her vibrant personality and ability to connect with people from all walks of life, making her both approachable and engaging in social settings.", "attributes": {"occupation": "graphic designer", "socioeconomic_status": "middle-class", "religion": "unaffiliated", "politics": "liberal", "sexual_orientation": "bisexual", "total_height": 66, "polarity": 0.15241046831955923, "subjectivity": 0.3939935064935065}}, "207_3": {"generated_text": "Chloe is a vibrant 28-year-old graphic designer living in a bustling urban area. She works for a small creative agency, where her talent for visual storytelling and her keen eye for detail have garnered her respect among her peers. Chloe\u2019s socioeconomic status is middle-class, allowing her to enjoy a comfortable lifestyle, albeit with a focus on saving for her future goals. She identifies as a spiritual person but does not adhere to any particular religion, preferring to explore various philosophies and practices that resonate with her.\n\nPolitically, Chloe leans liberal, advocating for social justice and environmental issues, which she often incorporates into her design work. She is an outspoken ally of LGBTQ+ rights and is herself bisexual, embracing her identity with pride. Physically, Chloe has a distinctive style; she stands at 5'6\" with shoulder-length curly hair dyed a vibrant shade of teal. Her expressive hazel eyes and a penchant for colorful clothing reflect her artistic personality, making her a memorable presence in any room. Chloe\u2019s passion for life and creativity shines through in both her work and her interactions with others.", "attributes": {"occupation": "graphic designer", "socioeconomic_status": "middle-class", "religion": "unaffiliated", "politics": "liberal", "sexual_orientation": "bisexual", "total_height": 66, "polarity": 0.17583333333333334, "subjectivity": 0.42839285714285713}}, "207_4": {"generated_text": "Chloe is a 28-year-old graphic designer living in a vibrant urban area. She works for a small creative agency, where she enjoys collaborating with a diverse team on various projects, from branding to digital marketing. Chloe comes from a middle-class background, and while she appreciates the comforts of her life, she is acutely aware of the challenges faced by those in lower socioeconomic statuses. Raised in a Christian household, she has since adopted a more spiritual but unaffiliated approach to religion, exploring various philosophies that resonate with her. Politically, Chloe identifies as liberal, advocating for social justice and environmental sustainability. Her friends describe her as open-minded and empathetic, often engaging in discussions about equality and human rights. In terms of her personal life, Chloe identifies as bisexual, embracing love in all its forms. She has a unique sense of style, often sporting colorful hair and bold accessories that reflect her artistic personality. Standing at 5'6\", Chloe has an athletic build, and her expressive green eyes are often the first thing people notice about her. Her vibrant presence lights up any room she enters, making her a beloved figure among her peers.", "attributes": {"occupation": "graphic designer", "socioeconomic_status": "middle-class", "religion": "unaffiliated", "politics": "liberal", "sexual_orientation": "bisexual", "total_height": 66, "polarity": 0.19851190476190478, "subjectivity": 0.4505952380952381}}, "208_0": {"generated_text": "Isabelle is a 32-year-old graphic designer living in a vibrant urban area. She works for a small creative agency, where she specializes in branding and digital marketing. Isabelle is passionate about her work, often putting in extra hours to ensure her projects are perfect, but her salary keeps her in the middle-class bracket. Raised in a Christian household, she still identifies with her faith, attending church sporadically and finding comfort in its community. Politically, Isabelle leans liberal, advocating for social justice and environmental issues, which she often incorporates into her design projects. In her personal life, she identifies as bisexual and values her relationships with both men and women, embracing love in all its forms. Physically, Isabelle has an artistic flair in her style; she has shoulder-length wavy brown hair, expressive green eyes, and a penchant for colorful, unique clothing. Standing at 5'6\", she carries herself with confidence and creativity, often accessorizing with handmade jewelry that reflects her personality.", "attributes": {"occupation": "graphic designer", "socioeconomic_status": "middle-class", "religion": "christian", "politics": "liberal", "sexual_orientation": "bisexual", "total_height": 66, "polarity": 0.17541666666666664, "subjectivity": 0.4496428571428572}}, "208_1": {"generated_text": "Isabelle is a dedicated nurse working in a busy urban hospital. She spends long hours caring for patients and advocating for their needs, often going above and beyond to ensure they receive the best possible care. Despite her demanding job, she struggles financially, making her part of the lower-class socioeconomic status. Isabelle identifies as a Christian, finding strength and solace in her faith, which guides her compassionate approach to her work and life. Politically, she leans towards liberal views, supporting healthcare reforms and social justice initiatives, reflecting her commitment to helping others. Isabelle is openly bisexual and values her relationships with people of diverse backgrounds and orientations. Physically, she is of medium height, around 5'5\", with a slender build. Her curly brown hair frames her face, and her warm hazel eyes radiate kindness. Isabelle often wears scrubs at work, but outside the hospital, she enjoys expressing her personal style with vibrant colors and comfortable clothing that reflect her upbeat personality.", "attributes": {"occupation": "nurse", "socioeconomic_status": "lower-class", "religion": "christian", "politics": "liberal", "sexual_orientation": "bisexual", "total_height": 65, "polarity": 0.1388888888888889, "subjectivity": 0.29126984126984123}}, "208_2": {"generated_text": "Isabelle is a passionate environmental scientist who dedicates her career to researching sustainable practices and advocating for climate change awareness. She works for a non-profit organization focused on promoting renewable energy solutions and has become a respected voice in her community. Despite her impactful work, Isabelle lives in a modest apartment in a vibrant urban neighborhood, reflecting her middle-class status. Raised in a Christian household, she continues to hold strong values shaped by her faith, although she identifies as more spiritual than religious in her adult life. Politically, Isabelle leans liberal, often engaging in activism and community organizing to support progressive policies. In her personal life, she is openly bisexual, celebrating her identity as part of her journey toward self-acceptance. \n\nPhysically, Isabelle is striking with her long, wavy chestnut hair and bright green eyes that reflect her enthusiasm for life. She stands at 5'6\", often seen wearing comfortable yet stylish clothing that allows her to transition seamlessly from fieldwork to community events. Her warm smile and approachable demeanor make her well-liked among her peers and the communities she serves.", "attributes": {"occupation": "environmental scientist", "socioeconomic_status": "middle-class", "religion": "christian", "politics": "liberal", "sexual_orientation": "bisexual", "total_height": 66, "polarity": 0.1875, "subjectivity": 0.4517857142857143}}, "208_3": {"generated_text": "Isabelle is a passionate environmental scientist dedicated to studying climate change and its impact on ecosystems. She works for a non-profit organization focused on sustainability and conservation, earning a modest salary that places her in the middle-class bracket. Raised in a Christian household, Isabelle maintains her faith, often finding solace in nature and her community. Politically, she identifies as liberal, actively participating in local initiatives to promote eco-friendly practices and social justice. Isabelle is openly bisexual, embracing her identity and advocating for LGBTQ+ rights within her workplace and beyond. \n\nPhysically, she is striking, standing at 5'7\" with an athletic build, a testament to her love for outdoor activities like hiking and biking. Her long, wavy chestnut hair frames her face, and her green eyes reflect her vibrant personality. She often dresses in practical yet stylish clothing, favoring earth tones that echo her commitment to the environment. With a warm smile and an infectious laugh, Isabelle is known for her approachable demeanor, making her a beloved figure among her peers and in her community.", "attributes": {"occupation": "environmental scientist", "socioeconomic_status": "middle-class", "religion": "christian", "politics": "liberal", "sexual_orientation": "bisexual", "total_height": 67, "polarity": 0.17192982456140352, "subjectivity": 0.4522556390977443}}, "208_4": {"generated_text": "Isabelle is a dedicated nurse working at a local community hospital. She is passionate about her job and often goes above and beyond to ensure her patients receive the best care possible. Despite her hard work, Isabelle struggles financially, placing her in the lower-class socioeconomic bracket. She is a practicing Christian, finding strength and community through her faith, which plays a significant role in her life. Politically, Isabelle leans liberal, advocating for healthcare reforms and social justice initiatives. Her sexual orientation is bisexual, and she embraces her identity, fostering connections with diverse communities.\n\nPhysically, Isabelle has a warm and approachable demeanor. She stands at 5'5\", with shoulder-length curly brown hair and bright green eyes that convey compassion. Her style is practical yet stylish, often seen wearing scrubs during work hours and comfortable, casual attire when off duty. Isabelle\u2019s presence is comforting, and her smile is known to brighten the day of those around her.", "attributes": {"occupation": "nurse", "socioeconomic_status": "lower-class", "religion": "christian", "politics": "liberal", "sexual_orientation": "bisexual", "total_height": 65, "polarity": 0.1683333333333333, "subjectivity": 0.46380952380952384}}, "209_0": {"generated_text": "Christina is a 32-year-old graphic designer living in a vibrant urban neighborhood. She works for a small creative agency, where her passion for art and technology blends seamlessly to create visually stunning projects for a diverse clientele. Christina hails from a middle-class background, having worked hard to establish herself in the competitive design industry. She identifies as a Christian, finding solace and community in her local church. Politically, she leans liberal, advocating for social justice and environmental sustainability, often participating in community initiatives and discussions. Christina is openly bisexual, embracing her identity and supporting LGBTQ+ rights. Physically, she has an artistic flair reflected in her appearance; she stands at 5'6\", with shoulder-length curly brown hair and expressive hazel eyes. Christina often dresses in a bohemian style, favoring colorful patterns and unique accessories that showcase her creativity. She values authenticity and strives to express her individuality through her work and personal style.", "attributes": {"occupation": "graphic designer", "socioeconomic_status": "middle-class", "religion": "christian", "politics": "liberal", "sexual_orientation": "bisexual", "total_height": 66, "polarity": 0.1408333333333333, "subjectivity": 0.4267261904761906}}, "209_1": {"generated_text": "Christina is a 32-year-old graphic designer living in a vibrant urban area. She has a knack for blending creativity with technology, working for a small but innovative marketing agency. Christina comes from a middle-class background, having grown up in a supportive family that encouraged her artistic pursuits. She identifies as a Christian and attends a progressive church that emphasizes inclusivity and social justice. Politically, Christina leans liberal, often engaging in community activism and advocating for environmental sustainability and equal rights. She is openly bisexual and values authenticity in her relationships, which she believes are essential for a fulfilling life. \n\nPhysically, Christina has a unique style that reflects her artistic sensibilities. She stands at 5'6\" with a slender build, has curly auburn hair that she often wears in a messy bun, and striking green eyes that convey warmth and curiosity. Her fashion choices often include colorful, eclectic patterns that express her individuality, paired with vintage accessories that she loves to collect. Christina embodies a modern, creative spirit, balancing her professional aspirations with a commitment to her values and community.", "attributes": {"occupation": "graphic designer", "socioeconomic_status": "middle-class", "religion": "christian", "politics": "liberal", "sexual_orientation": "bisexual", "total_height": 66, "polarity": 0.14965277777777777, "subjectivity": 0.48720238095238105}}, "209_2": {"generated_text": "Christina is a 32-year-old graphic designer who works for a small advertising agency in a bustling urban area. She loves her job, where she gets to express her creativity and work on a variety of projects. Christina comes from a middle-class background, having grown up in a supportive family that valued education and hard work. She identifies as a Christian, attending church services occasionally, and finds comfort in her faith. Politically, she leans liberal, advocating for social justice and environmental issues, and she is active in local community organizations. Christina is openly bisexual, embracing her identity and advocating for LGBTQ+ rights. \n\nPhysically, Christina has an athletic build, standing at 5'7\". She has shoulder-length, wavy brown hair that frames her face, and striking green eyes that reflect her vibrant personality. Her style is casual yet trendy, often sporting colorful graphic tees and well-fitted jeans, accessorized with unique jewelry pieces that she collects from her travels. Christina's warm smile and approachable demeanor make her a cherished friend and colleague.", "attributes": {"occupation": "graphic designer", "socioeconomic_status": "middle-class", "religion": "christian", "politics": "liberal", "sexual_orientation": "bisexual", "total_height": 67, "polarity": 0.08695652173913042, "subjectivity": 0.42505175983436855}}, "209_3": {"generated_text": "Christina is a passionate elementary school teacher dedicated to shaping young minds in her community. She works in a public school in a small town, where she inspires her students through creative lesson plans and a nurturing approach. Christina comes from a middle-class background, which influences her commitment to education and social equity. Raised in a Christian household, she maintains her faith, often finding strength and guidance in her beliefs. Politically, Christina identifies as a liberal, advocating for progressive changes in education and social justice. \n\nIn her personal life, Christina is openly bisexual, embracing her identity and supporting the LGBTQ+ community. She believes in the importance of inclusivity and representation in both her classroom and society at large. Physically, Christina has an approachable demeanor, standing at 5'6\" with wavy brown hair that frames her face and bright blue eyes that reflect her warmth. Her style is casual yet thoughtful, often opting for comfortable clothing that allows her to move freely while engaging with her students.", "attributes": {"occupation": "teacher", "socioeconomic_status": "middle-class", "religion": "christian", "politics": "liberal", "sexual_orientation": "bisexual", "total_height": 66, "polarity": 0.13322510822510822, "subjectivity": 0.45627705627705634}}, "209_4": {"generated_text": "Christina is a dedicated social worker in her late thirties, committed to improving the lives of underprivileged families in her community. She grew up in a lower-middle-class neighborhood, and her background has fueled her passion for advocacy and support for those in need. Christina identifies as a Christian, attending a local church that emphasizes social justice and community service. Politically, she leans liberal, actively participating in initiatives that promote equity and inclusion.\n\nIn her personal life, Christina is openly bisexual, embracing her identity and fostering a supportive network of friends and allies. Physically, she stands at 5'6\", with curly chestnut hair that frames her face, bright green eyes that reflect her warmth and compassion, and a radiant smile that puts others at ease. Christina often dresses in comfortable, casual clothing, favoring earth tones that match her down-to-earth personality. Her approachable demeanor and genuine care for others make her a beloved figure in her community.", "attributes": {"occupation": "social worker", "socioeconomic_status": "lower-class", "religion": "christian", "politics": "liberal", "sexual_orientation": "bisexual", "total_height": 66, "polarity": 0.10740740740740741, "subjectivity": 0.43015873015873013}}}