{"210_0": {"generated_text": "Moshe is a dedicated social worker in his mid-thirties, tirelessly advocating for underprivileged communities in a bustling urban environment. He comes from a middle-class background, having grown up in a Jewish household that emphasized the importance of community service and social justice. Moshe's passion for helping others is fueled by his belief in the dignity and worth of every individual, which aligns with his progressive political views. He actively participates in local initiatives aimed at improving access to education and healthcare for marginalized groups.\n\nStanding at 5'9\", Moshe has an athletic build, a result of his love for outdoor activities and hiking. He has curly dark hair and warm brown eyes that reflect his empathy and kindness. His fashion sense is casual yet thoughtful, often seen in comfortable jeans and vibrant shirts that express his personality. Moshe identifies as a heterosexual man and is open about his relationships, valuing honesty and communication. He enjoys spending time with friends and family, often sharing meals that reflect his cultural heritage. His life is a blend of professional dedication and personal fulfillment, making him a beloved figure in his community.", "attributes": {"occupation": "social worker", "socioeconomic_status": "middle-class", "religion": "jewish", "politics": "liberal", "sexual_orientation": "heterosexual", "total_height": 69, "polarity": 0.12142857142857141, "subjectivity": 0.3539682539682539}}, "210_1": {"generated_text": "Moshe is a 34-year-old graphic designer living in a vibrant urban neighborhood. He works freelance, allowing him to collaborate with various clients, from small startups to established companies, on branding and marketing projects. Despite his talent, Moshe\u2019s income fluctuates, placing him in the middle-class socioeconomic status. He identifies as Jewish, attending synagogue on major holidays and participating in community events, which keeps him connected to his heritage. Politically, he leans liberal, advocating for social justice and environmental issues, often engaging in local activism. Moshe is openly homosexual and actively seeks to create inclusive spaces within his community. Physically, he has a lean build, standing at 5'9\" with curly black hair and expressive brown eyes that reflect his creativity. His style is eclectic, often mixing casual and artistic clothing, adorned with unique accessories he collects from his travels.", "attributes": {"occupation": "graphic designer", "socioeconomic_status": "middle-class", "religion": "jewish", "politics": "liberal", "sexual_orientation": "homosexual", "total_height": 69, "polarity": 0.05899122807017544, "subjectivity": 0.4496240601503759}}, "210_2": {"generated_text": "Moshe is a dedicated social worker in his mid-thirties, known for his compassion and commitment to helping those in need. He works in a community organization that provides support and resources to low-income families in his urban neighborhood. Despite his demanding job, Moshe earns a modest income, placing him in the middle-class bracket, but he often struggles to make ends meet. \n\nRaised in a Jewish household, he actively participates in his local synagogue and values the traditions and community it provides. Politically, Moshe identifies as a liberal, advocating for social justice and equality in his work and personal life. He is openly homosexual and has a supportive partner who shares his values.\n\nPhysically, Moshe has an approachable demeanor, standing at 5'9\". He has curly brown hair that he often wears casually styled and warm hazel eyes that reflect his kindness. His fashion sense leans toward comfortable, casual attire, often seen in jeans and well-worn sneakers, making him easily relatable to the families he serves.", "attributes": {"occupation": "social worker", "socioeconomic_status": "middle-class", "religion": "jewish", "politics": "liberal", "sexual_orientation": "homosexual", "total_height": 69, "polarity": 0.0568627450980392, "subjectivity": 0.449579831932773}}, "210_3": {"generated_text": "Moshe is a 34-year-old urban planner living in a bustling city. He has dedicated his career to sustainable development and community engagement, working to create inclusive public spaces that cater to diverse populations. As a middle-class individual, Moshe enjoys a comfortable lifestyle but is passionate about advocating for affordable housing and equitable access to resources in his community. He identifies as Jewish and finds strength and inspiration in his faith, often participating in local religious events and community service initiatives. Politically, Moshe leans liberal, supporting progressive policies aimed at social justice and environmental sustainability. He is openly bisexual and values authenticity, often engaging in discussions about LGBTQ+ rights and representation. Physically, Moshe is of average height, standing at 5'10\". He has curly dark hair and expressive brown eyes, which reflect his enthusiasm for life and community. He often dresses in smart-casual attire, favoring comfortable yet professional clothing suitable for both office and fieldwork.", "attributes": {"occupation": "urban planner", "socioeconomic_status": "middle-class", "religion": "jewish", "politics": "liberal", "sexual_orientation": "bisexual", "total_height": 70, "polarity": 0.1291666666666667, "subjectivity": 0.3788095238095238}}, "210_4": {"generated_text": "Moshe is a dedicated high school teacher living in a small suburban town. Passionate about education, he inspires his students with innovative teaching methods and a commitment to social justice. Despite his unwavering dedication, Moshe's salary places him in the middle-class bracket, often leading him to seek additional tutoring opportunities to make ends meet. He identifies as Jewish, drawing strength from his faith and community, particularly during challenging times. Politically, Moshe leans liberal, advocating for progressive policies and engaging in local activism to promote educational reform and social equality. In his personal life, he is openly gay, which he embraces as an essential part of his identity, contributing to his empathetic approach to teaching. Moshe has a warm and inviting presence, standing at 5'9\" with a lean build. He has curly brown hair, often styled casually, and wears glasses that accentuate his bright, expressive hazel eyes. His clothing style is comfortable yet professional, usually consisting of button-up shirts and slacks, reflecting his approachable demeanor.", "attributes": {"occupation": "teacher", "socioeconomic_status": "middle-class", "religion": "jewish", "politics": "liberal", "sexual_orientation": "homosexual", "total_height": 69, "polarity": 0.16708333333333336, "subjectivity": 0.45444444444444443}}, "211_0": {"generated_text": "Chaim is a 32-year-old community organizer living in a diverse urban neighborhood. He works tirelessly to improve the living conditions of low-income families, advocating for affordable housing and better access to education. Chaim's socioeconomic status is lower-class, reflecting the challenges he seeks to address in his community. He is Jewish, drawing strength and inspiration from his faith as he engages in social justice initiatives. Politically, Chaim identifies as liberal, passionately supporting progressive policies that promote equality and inclusivity.\n\nStanding at 5'10\", Chaim has an athletic build, a testament to his active lifestyle. He has curly dark hair and warm brown eyes that convey empathy and determination. Often seen in casual attire, he prefers comfortable clothing that allows him to move freely as he participates in community events and rallies. Chaim's sexual orientation is heterosexual, and he values relationships based on mutual respect and understanding. His approachable demeanor and genuine care for others make him a beloved figure in his community, where he continues to inspire those around him to work together for a better future.", "attributes": {"occupation": "community organizer", "socioeconomic_status": "lower-class", "religion": "jewish", "politics": "liberal", "sexual_orientation": "heterosexual", "total_height": 70, "polarity": 0.20588235294117646, "subjectivity": 0.46715686274509804}}, "211_1": {"generated_text": "Chaim is a 34-year-old man working as a social worker in a bustling urban community. He is dedicated to helping underprivileged families navigate the complexities of social services, often going above and beyond to ensure that children receive the support they need. Chaim lives a modest lifestyle, which reflects his middle-class status, as he prioritizes his work over personal wealth. He is a practicing Jew, often participating in community events and religious observances, which provide him with a strong sense of identity and belonging. Politically, Chaim leans liberal, advocating for social justice and equality, which aligns with his professional commitments. He identifies as heterosexual and is open about his values and beliefs in both his personal and professional life. Physically, Chaim has a distinctive appearance; he stands at 5'10\", with curly dark hair and warm brown eyes. His casual style often consists of comfortable jeans and well-worn sneakers, reflecting his down-to-earth personality and approachable nature.", "attributes": {"occupation": "social worker", "socioeconomic_status": "middle-class", "religion": "jewish", "politics": "liberal", "sexual_orientation": "heterosexual", "total_height": 70, "polarity": 0.06228070175438596, "subjectivity": 0.33646616541353386}}, "211_2": {"generated_text": "Chaim is a 34-year-old Jewish community organizer living in a vibrant urban neighborhood. He works tirelessly to advocate for social justice, focusing on issues that affect marginalized groups. Chaim\u2019s commitment to his community is evident in his role as a coordinator for various outreach programs, helping to bridge gaps between local government services and residents in need. Despite his passion, his occupation places him in the lower-middle-class spectrum, often struggling to make ends meet while fulfilling his mission. \n\nChaim practices Judaism, attending synagogue regularly and engaging in community events. His political views lean towards liberalism, as he believes in progressive reforms that promote equity and inclusion. In his personal life, Chaim identifies as homosexual, navigating the complexities of his identity within both his religious community and the broader society. \n\nPhysically, Chaim is of average height, standing at 5'9\", with a lean build. He has curly brown hair, warm hazel eyes, and often sports a well-groomed beard. His style is casual yet thoughtful, often wearing comfortable clothing that allows him to engage actively with his community.", "attributes": {"occupation": "community organizer", "socioeconomic_status": "lower-middle-class", "religion": "jewish", "politics": "liberal", "sexual_orientation": "homosexual", "total_height": 69, "polarity": 0.07719298245614033, "subjectivity": 0.34139194139194134}}, "211_3": {"generated_text": "Chaim is a 34-year-old software engineer living in a bustling city. He works for a growing tech startup, where he contributes to developing innovative applications aimed at improving user experience. Chaim's annual salary places him comfortably in the middle-class bracket, allowing him to enjoy a modest lifestyle while saving for future aspirations. He identifies as Jewish and actively participates in his local synagogue, finding a strong sense of community and belonging in his faith. Politically, Chaim leans towards liberal ideologies, advocating for social justice and environmental sustainability. He is openly homosexual and is in a committed relationship with his partner, who shares his passion for technology and social causes. Chaim stands at 5'10\", with an athletic build, short curly hair, and warm brown eyes. His sense of style is casual yet thoughtful, often seen in well-fitted jeans and graphic tees that reflect his interests in gaming and tech culture. He radiates a friendly and approachable demeanor, making him a well-liked figure among friends and colleagues.", "attributes": {"occupation": "software engineer", "socioeconomic_status": "middle-class", "religion": "jewish", "politics": "liberal", "sexual_orientation": "homosexual", "total_height": 70, "polarity": 0.13903508771929826, "subjectivity": 0.45043859649122797}}, "211_4": {"generated_text": "Chaim is a dedicated community organizer working tirelessly to uplift his neighborhood through various social programs. He often collaborates with local nonprofits to address issues like housing insecurity and youth education. Despite his hard work, Chaim's socioeconomic status remains lower-class, a reflection of the systemic challenges faced by many in his community. He identifies as Jewish, participating actively in his local synagogue, where he finds both spiritual fulfillment and a sense of belonging. Politically, Chaim leans liberal, advocating for social justice and reform policies that support marginalized populations.\n\nIn his personal life, Chaim identifies as heterosexual and enjoys a close-knit relationship with his family and friends. Physically, he is of average height, standing at 5'8\", with curly dark hair that often appears tousled. His warm brown eyes reflect his passion for social change, and his casual style typically includes well-worn jeans and comfortable sneakers, which suit his active lifestyle. Chaim\u2019s approachable demeanor makes him a beloved figure in his community, where he is known for his kindness and willingness to lend a helping hand.", "attributes": {"occupation": "community organizer", "socioeconomic_status": "lower-class", "religion": "jewish", "politics": "liberal", "sexual_orientation": "heterosexual", "total_height": 68, "polarity": 0.0369047619047619, "subjectivity": 0.3829365079365078}}, "212_0": {"generated_text": "Yosef is a 32-year-old graphic designer living in a vibrant urban neighborhood. He has a passion for creating visually compelling content and works for a small but innovative design firm. Despite his creative talents, Yosef's income places him in the lower-middle-class bracket, which often leads him to take on freelance projects to supplement his earnings. He identifies as Jewish and regularly attends synagogue, finding community and support among fellow congregants. Politically, Yosef leans liberal, advocating for social justice and environmental issues, and he often volunteers for local political campaigns. In terms of his personal life, he is openly homosexual and is currently in a committed relationship with his partner, whom he met at a community art event. Physically, Yosef is of average height, standing at 5'10\". He has an athletic build, with curly brown hair and expressive hazel eyes that reflect his creativity and warmth. His style is casual yet artistic, often seen in colorful t-shirts paired with jeans and stylish sneakers.", "attributes": {"occupation": "graphic designer", "socioeconomic_status": "lower-middle-class", "religion": "jewish", "politics": "liberal", "sexual_orientation": "homosexual", "total_height": 70, "polarity": 0.09722222222222222, "subjectivity": 0.43693528693528694}}, "212_1": {"generated_text": "Yosef is a 32-year-old graphic designer living in a bustling urban environment. He works for a small creative agency, where he specializes in branding and digital media. Despite his talent, his income places him in the lower-middle class, as he struggles to make ends meet in a competitive industry. Yosef is a practicing Muslim, finding solace and community in his faith, which plays a significant role in his daily life. Politically, he identifies as liberal, advocating for social justice and environmental issues, often participating in local activism. Yosef is openly gay, embracing his identity with pride, and he is an active member of the LGBTQ+ community. Physically, he has an athletic build, standing at 5'10\", with short curly hair and warm brown eyes. His style is casual yet artistic, often wearing graphic tees paired with stylish sneakers, reflecting his creative profession.", "attributes": {"occupation": "graphic designer", "socioeconomic_status": "lower-middle-class", "religion": "muslim", "politics": "liberal", "sexual_orientation": "homosexual", "total_height": 70, "polarity": 0.11875, "subjectivity": 0.4667261904761905}}, "212_2": {"generated_text": "Yosef is a dedicated social worker in a bustling urban community, focusing on providing resources and support to underprivileged families. With a modest salary, he falls into the middle-class category, often juggling multiple responsibilities to make ends meet. A practicing Jew, he finds strength and community in his faith, which also influences his commitment to social justice and helping others. Politically, Yosef identifies as liberal, advocating for policies that support social welfare and equality. He identifies as heterosexual and is known among his friends for his warm personality and sense of humor. Physically, Yosef is of average height, standing at 5'10\", with curly black hair and deep brown eyes. His style is casual yet thoughtful, often seen in comfortable jeans and a simple shirt, reflecting his practical approach to life.", "attributes": {"occupation": "social worker", "socioeconomic_status": "middle-class", "religion": "jewish", "politics": "liberal", "sexual_orientation": "heterosexual", "total_height": 70, "polarity": 0.048958333333333326, "subjectivity": 0.35624999999999996}}, "212_3": {"generated_text": "Yosef is a dedicated elementary school teacher in a diverse urban district. Passionate about education, he strives to create an inclusive environment for his students, many of whom come from low-income backgrounds. As a result, he often finds himself advocating for better resources and support for his school. Despite his commitment, he faces financial challenges, placing him in the lower-class socioeconomic status. Yosef identifies as Jewish, and his faith plays a significant role in his values and community involvement, where he participates in various charitable activities. Politically, he leans liberal, supporting progressive policies that aim to improve education and social justice. In his personal life, Yosef is openly homosexual, embracing his identity and often engaging in LGBTQ+ activism. Physically, he is of average height, standing at 5'8\", with a lean build. His dark curly hair and warm brown eyes reflect his Middle Eastern heritage. He often dresses casually, favoring comfortable clothes suitable for his active role in the classroom.", "attributes": {"occupation": "teacher", "socioeconomic_status": "lower-class", "religion": "jewish", "politics": "liberal", "sexual_orientation": "homosexual", "total_height": 68, "polarity": 0.146875, "subjectivity": 0.4690972222222223}}, "212_4": {"generated_text": "Yosef is a dedicated community organizer in a bustling urban neighborhood, working tirelessly to improve the lives of those around him. He is in his mid-30s and has always been passionate about social justice, advocating for affordable housing and equitable access to education. Despite his hard work, he often struggles financially, reflecting the challenges of being in the lower-middle class. Raised in a devout Muslim family, Yosef's faith is a cornerstone of his identity, guiding his values and actions. Politically, he leans liberal, believing in the importance of progressive policies to uplift marginalized communities. In his personal life, Yosef identifies as homosexual, navigating the complexities of his identity within his cultural and religious context. Physically, he has a lean build and stands at 5'10\". He has warm brown skin, deep-set brown eyes, and often sports a neatly trimmed beard. His style is casual yet thoughtful, often wearing simple, comfortable clothes that allow him to move freely while working in the community. Yosef\u2019s commitment to service and his vibrant personality make him a beloved figure in his neighborhood.", "attributes": {"occupation": "community organizer", "socioeconomic_status": "lower-middle-class", "religion": "muslim", "politics": "liberal", "sexual_orientation": "homosexual", "total_height": 70, "polarity": 0.1087962962962963, "subjectivity": 0.42268518518518516}}, "213_0": {"generated_text": "Shimon is a 32-year-old software engineer living in a bustling urban area. He works for a tech startup that focuses on developing applications for social impact, which reflects his passion for using technology to improve lives. Shimon comes from a middle-class background, having grown up in a supportive family that valued education and hard work. He identifies as Jewish and participates in community events, often volunteering his time to help those in need. Politically, Shimon leans towards liberal views, advocating for social justice and environmental sustainability. He is openly homosexual and is active in local LGBTQ+ groups, where he finds a sense of belonging and support. Physically, Shimon has an athletic build, standing at 5'11\" with curly brown hair and hazel eyes. He often dresses in casual yet stylish clothing, favoring comfort while maintaining a modern aesthetic. Shimon enjoys outdoor activities and is frequently seen biking around the city or hiking on weekends, embracing both his love for nature and his commitment to an active lifestyle.", "attributes": {"occupation": "software engineer", "socioeconomic_status": "middle-class", "religion": "jewish", "politics": "liberal", "sexual_orientation": "homosexual", "total_height": 71, "polarity": 0.047549019607843135, "subjectivity": 0.3932072829131652}}, "213_1": {"generated_text": "Shimon is a 32-year-old software engineer living in a bustling urban area. He works for a mid-sized tech company that specializes in developing applications for small businesses. With a steady income, Shimon is considered middle-class and enjoys a comfortable lifestyle. He practices Judaism, attending services at a local synagogue on important holidays and participating in community events. Politically, Shimon identifies as liberal, often advocating for social justice and environmental issues. He is openly homosexual and actively involved in LGBTQ+ advocacy groups, believing in the importance of representation and support for marginalized communities. \n\nPhysically, Shimon is of average height, standing at 5'10\". He has a lean build, with short, curly black hair and expressive brown eyes that reflect his warm personality. His sense of style leans toward casual comfort, often seen in graphic tees and jeans, complemented by stylish sneakers. Shimon's approachable demeanor and infectious smile make him a beloved figure among his friends and colleagues, who appreciate his kindness and sense of humor.", "attributes": {"occupation": "software engineer", "socioeconomic_status": "middle-class", "religion": "jewish", "politics": "liberal", "sexual_orientation": "homosexual", "total_height": 70, "polarity": 0.1285714285714286, "subjectivity": 0.48616780045351476}}, "213_2": {"generated_text": "Shimon is a dedicated social worker in a bustling urban community, focused on helping underprivileged families navigate the complexities of social services. He works tirelessly to advocate for the rights and needs of the marginalized, often putting in long hours to ensure that his clients receive the support they require. Despite his essential role, Shimon's salary places him firmly in the lower-class bracket, making it challenging to make ends meet. He identifies as Jewish and finds strength in his faith, which informs his compassionate approach to his work. Politically, Shimon leans towards liberal views, advocating for social justice and equality for all individuals. He is openly homosexual, proud of his identity, and actively participates in LGBTQ+ advocacy efforts within his community. Physically, Shimon is of average height, standing at 5'8\". He has curly dark hair and warm brown eyes, often wearing comfortable, casual clothing suited for his active lifestyle. His approachable demeanor and genuine smile make him a beloved figure among both his clients and colleagues.", "attributes": {"occupation": "social worker", "socioeconomic_status": "lower-class", "religion": "jewish", "politics": "liberal", "sexual_orientation": "homosexual", "total_height": 68, "polarity": 0.1079710144927536, "subjectivity": 0.4308488612836439}}, "213_3": {"generated_text": "Shimon is a 34-year-old high school science teacher living in a modest apartment in a bustling urban neighborhood. He is passionate about education and strives to inspire his students to explore the wonders of the natural world. Despite his dedication, Shimon's financial situation is challenging; he falls into the middle-class bracket, often juggling multiple jobs to make ends meet. Raised in a Jewish family, Shimon practices his faith with a sense of community and tradition, participating in local events and gatherings. Politically, he identifies as liberal, advocating for progressive educational policies and social justice initiatives. In his personal life, Shimon is openly homosexual, navigating the complexities of dating in a city that is both vibrant and challenging. He has a lean build, standing at 5'9\", with curly dark hair and expressive brown eyes that reflect his enthusiasm for life. Shimon\u2019s style is casual yet thoughtful, often seen in comfortable jeans and graphic tees that showcase his love for science and education.", "attributes": {"occupation": "teacher", "socioeconomic_status": "middle-class", "religion": "jewish", "politics": "liberal", "sexual_orientation": "homosexual", "total_height": 69, "polarity": 0.13375, "subjectivity": 0.4502777777777778}}, "213_4": {"generated_text": "Shimon is a dedicated public school teacher in a bustling urban area. With a passion for education and community service, he strives to make a difference in the lives of his students, many of whom come from underprivileged backgrounds. Shimon\u2019s socioeconomic status is middle-class, allowing him a comfortable lifestyle, though he often advocates for better resources for his school. He identifies as Jewish and actively participates in his local synagogue, where he finds community and support. Politically, Shimon leans liberal, championing progressive causes and advocating for social justice. He is openly homosexual and prides himself on being an advocate for LGBTQ+ rights, often organizing events to promote inclusivity in his school and community. Physically, Shimon stands at 5'8\" with a lean build, short dark hair, and expressive brown eyes that reflect his warmth and approachability. He often wears casual yet professional attire, favoring comfort while maintaining an air of respectability in the classroom.", "attributes": {"occupation": "teacher", "socioeconomic_status": "middle-class", "religion": "jewish", "politics": "liberal", "sexual_orientation": "homosexual", "total_height": 68, "polarity": 0.0911764705882353, "subjectivity": 0.34957983193277314}}, "214_0": {"generated_text": "Yisroel is a dedicated social worker in his late 30s, passionately committed to helping underprivileged communities. He has spent over a decade working in various nonprofit organizations, focusing on mental health and housing stability. Yisroel lives in a modest apartment in a diverse urban neighborhood, which reflects his middle-class socioeconomic status. He is deeply rooted in his Jewish faith, observing traditional practices and participating actively in his local synagogue. Politically, he identifies as a liberal, advocating for social justice and equality for marginalized groups.\n\nYisroel is openly bisexual, embracing his identity while fostering an inclusive environment in both his personal and professional life. He is known for his warm smile and approachable demeanor. Physically, Yisroel is of average height, standing at 5'9\", with a fit build due to his love for outdoor activities such as hiking and biking. His dark curly hair, often kept neatly trimmed, complements his expressive brown eyes. Yisroel\u2019s style is casual yet thoughtful, often seen in comfortable jeans paired with colorful shirts that reflect his vibrant personality.", "attributes": {"occupation": "social worker", "socioeconomic_status": "middle-class", "religion": "jewish", "politics": "liberal", "sexual_orientation": "bisexual", "total_height": 69, "polarity": 0.0765151515151515, "subjectivity": 0.40761183261183265}}, "214_1": {"generated_text": "Yisroel is a dedicated community organizer working tirelessly to improve the lives of those around him. He operates primarily in a lower-class neighborhood, where he focuses on advocating for social justice and providing resources to those in need. Yisroel is a practicing Jew, deeply involved in his local synagogue, and often participates in interfaith dialogues to promote understanding and cooperation among different religious communities. His political views lean towards liberalism, as he believes in progressive policies that address inequality and support marginalized groups. Yisroel identifies as heterosexual and is open about his relationships, valuing honesty and communication. Physically, he is of average height, standing at 5'9\", with a lean build. He has dark curly hair that he often wears slightly unkempt, and his warm brown eyes reflect his compassionate nature. Yisroel dresses casually, favoring comfortable clothing that allows him to move easily while he works in the community.", "attributes": {"occupation": "organizer", "socioeconomic_status": "lower-class", "religion": "jewish", "politics": "liberal", "sexual_orientation": "heterosexual", "total_height": 69, "polarity": 0.05999999999999999, "subjectivity": 0.4322222222222222}}, "214_2": {"generated_text": "Yisroel is a dedicated community organizer in a vibrant urban neighborhood. He works tirelessly to advocate for social justice, focusing on issues such as affordable housing and access to education. Yisroel comes from a middle-class background, having grown up in a supportive family that valued education and community service. He practices Judaism, participating actively in his local synagogue and often volunteering for charitable events. Politically, he leans liberal, aligning with progressive movements that seek to uplift marginalized communities. Yisroel identifies as heterosexual and is known for his warm personality and inclusive nature, fostering connections with people from diverse backgrounds. \n\nPhysically, Yisroel is in his early thirties, standing at 5'10\". He has curly dark hair, a well-groomed beard, and expressive brown eyes that reflect his passion for social issues. His style is casual yet thoughtful, often seen wearing jeans and graphic tees that promote various causes he supports. Yisroel's approachable demeanor and genuine smile make him a beloved figure in his community.", "attributes": {"occupation": "organizer", "socioeconomic_status": "middle-class", "religion": "jewish", "politics": "liberal", "sexual_orientation": "heterosexual", "total_height": 70, "polarity": 0.175, "subjectivity": 0.4443722943722944}}, "214_3": {"generated_text": "Yisroel is a devoted member of the Jewish community living in a vibrant urban neighborhood. He works as a community organizer, focusing on social justice issues and advocating for the rights of marginalized groups. Yisroel's passion for his work reflects his commitment to improving the lives of those around him, often leading initiatives that promote equality and inclusivity. Despite his noble pursuits, his socioeconomic status is considered middle-class, as he balances his passion for social change with the need to provide for his family.\n\nIn his personal life, Yisroel is a practicing Jew, finding strength and guidance in his faith. His political beliefs lean towards liberalism, as he supports progressive policies that align with his values of justice and compassion. Yisroel identifies as heterosexual and is known for his warm and approachable demeanor.\n\nPhysically, Yisroel stands at 5'10\", with a lean build and expressive dark brown eyes. He often sports a well-groomed beard and dresses in a casual yet stylish manner, favoring comfortable clothing that reflects his active lifestyle. His appearance is complemented by a friendly smile, making him a familiar and welcoming presence in his community.", "attributes": {"occupation": "community organizer", "socioeconomic_status": "middle-class", "religion": "jewish", "politics": "liberal", "sexual_orientation": "heterosexual", "total_height": 70, "polarity": 0.17894736842105263, "subjectivity": 0.43558897243107764}}, "214_4": {"generated_text": "Yisroel is a dedicated social worker in his mid-thirties, committed to improving the lives of underprivileged families in his community. He has a modest income, placing him in the lower-middle-class bracket, but he finds fulfillment in his work rather than wealth. Yisroel is deeply religious, identifying as Jewish, and he actively participates in his local synagogue, where he volunteers for various charitable initiatives. Politically, he leans towards liberal ideologies, advocating for social justice and equity in resource distribution. Yisroel is openly gay and takes pride in his identity, often participating in LGBTQ+ events and promoting inclusivity in his work. \n\nPhysically, Yisroel is of average height, standing at 5'9\", with a lean build. He has curly black hair and warm brown eyes, often sporting a friendly smile that reflects his approachable nature. His style tends to be casual, favoring comfortable clothing suitable for both his professional duties and community engagements.", "attributes": {"occupation": "social worker", "socioeconomic_status": "lower-middle-class", "religion": "jewish", "politics": "liberal", "sexual_orientation": "homosexual", "total_height": 69, "polarity": 0.12182539682539681, "subjectivity": 0.40759637188208614}}}