{"215_0": {"generated_text": "Chaya is a dedicated social worker in her mid-thirties, passionately advocating for underprivileged communities in her city. Growing up in a lower-middle-class family, she understands the challenges faced by those she serves and is committed to making a difference. Chaya identifies as Jewish and finds strength and community in her faith, participating actively in her local synagogue. Politically, she leans liberal, believing in social justice and equality for all, which aligns with her professional values. Chaya is openly bisexual and embraces her identity as part of her holistic approach to social work, promoting inclusivity and acceptance. \n\nPhysically, she has an expressive presence with curly brown hair that frames her face and bright green eyes that reflect her warmth and empathy. Standing at 5'6\", she carries herself with a mix of confidence and approachability, often dressed in comfortable yet professional attire that allows her to connect with clients easily. Chaya\u2019s passion for her work and her commitment to her values shine through in her interactions, making her a respected figure in her community.", "attributes": {"occupation": "social worker", "socioeconomic_status": "lower-class", "religion": "jewish", "politics": "liberal", "sexual_orientation": "bisexual", "total_height": 66, "polarity": 0.1323529411764706, "subjectivity": 0.3721288515406162}}, "215_1": {"generated_text": "Chaya is a passionate community organizer in her late twenties, dedicated to advocating for social justice and environmental sustainability. Living in a vibrant urban neighborhood, she comes from a middle-class background, having grown up in a supportive family that valued education and activism. Chaya identifies as Hindu, celebrating her faith through community service and cultural events. Politically, she leans liberal, actively participating in grassroots campaigns and promoting progressive policies that address inequality and climate change. Her sexual orientation is bisexual, and she is open about her relationships, contributing to her belief in inclusivity and acceptance. \n\nPhysically, Chaya has a striking presence with long, wavy black hair and warm brown skin. She stands at 5'6\", often seen in colorful, bohemian attire that reflects her artistic personality. Her expressive brown eyes convey her passion for the causes she champions, and her confident demeanor makes her a natural leader in her community.", "attributes": {"occupation": "organizer", "socioeconomic_status": "middle-class", "religion": "hindu", "politics": "liberal", "sexual_orientation": "bisexual", "total_height": 66, "polarity": 0.17777777777777776, "subjectivity": 0.5329931972789117}}, "215_2": {"generated_text": "Chaya is a vibrant 28-year-old graphic designer living in a bustling urban environment. She works for a small but creative agency that specializes in branding for eco-friendly companies, reflecting her passion for sustainability. Chaya comes from a middle-class background, having grown up in a supportive family that prioritized education and creativity. She identifies as Jewish and often participates in community events that celebrate her heritage. Politically, Chaya leans liberal, advocating for social justice and environmental issues. In her personal life, she is openly bisexual, embracing her identity with pride and often engaging in advocacy for LGBTQ+ rights.\n\nPhysically, Chaya has an artistic flair in her appearance, often sporting brightly colored hair and unique clothing that she designs herself. She stands at 5'6\", with a slender build and expressive features that reflect her dynamic personality. Her style is a blend of bohemian and contemporary, often accessorized with handmade jewelry that tells a story of her travels and experiences.", "attributes": {"occupation": "graphic designer", "socioeconomic_status": "middle-class", "religion": "jewish", "politics": "liberal", "sexual_orientation": "bisexual", "total_height": 66, "polarity": 0.19605263157894737, "subjectivity": 0.4776942355889724}}, "215_3": {"generated_text": "Chaya is a vibrant and dedicated social worker in her mid-thirties, passionately advocating for underprivileged communities in her urban neighborhood. She comes from a middle-class background, having grown up in a supportive family that emphasized the importance of education and social justice. Chaya identifies as Jewish, participating actively in her local synagogue and community events that foster inclusivity and support for various causes. Politically, she leans liberal, often engaging in discussions about systemic reform and equality, and she volunteers for various progressive campaigns. Chaya is openly bisexual, embracing her identity with pride and advocating for LGBTQ+ rights within her community.\n\nPhysically, Chaya stands at 5'6\", with curly brown hair that frames her face and expressive hazel eyes. Her style is casual yet colorful, often reflecting her vibrant personality through her choice of clothing. She has an infectious smile that can easily light up a room, and her warm demeanor makes her approachable to those she serves.", "attributes": {"occupation": "social worker", "socioeconomic_status": "middle-class", "religion": "jewish", "politics": "liberal", "sexual_orientation": "bisexual", "total_height": 66, "polarity": 0.13712121212121212, "subjectivity": 0.42543290043290044}}, "215_4": {"generated_text": "Chaya is a dedicated social worker in her late 30s, passionately advocating for the underprivileged in her community. Living in a modest apartment, she has a middle-class socioeconomic status, which she balances carefully with her responsibilities and her commitment to helping others. Raised in a Jewish household, she maintains her cultural traditions and attends synagogue regularly, finding strength and support in her faith. Politically, Chaya identifies as liberal, often participating in local campaigns that aim to enhance social justice and equality. In her personal life, she identifies as bisexual, embracing her identity and supporting LGBTQ+ rights through her work and community involvement. Physically, Chaya has a warm, approachable demeanor, with shoulder-length curly brown hair and expressive hazel eyes. Standing at 5'6\", she often dresses in a casual yet professional style, favoring comfortable clothing that allows her to move freely while working in various community settings.", "attributes": {"occupation": "social worker", "socioeconomic_status": "middle-class", "religion": "jewish", "politics": "liberal", "sexual_orientation": "bisexual", "total_height": 66, "polarity": 0.08888888888888889, "subjectivity": 0.43427524856096283}}, "216_0": {"generated_text": "Rivka is a dedicated social worker in a bustling urban environment, passionately advocating for underprivileged communities. With a modest salary that places her in the middle-class bracket, she navigates life with a sense of purpose and resilience. Raised in a Jewish household, Rivka embraces her faith as a guiding principle, often participating in community events and celebrations. Politically, she identifies as liberal, believing in social justice and equal rights for all, which influences her work and activism. \n\nRivka identifies as bisexual, a part of her identity that she embraces openly with friends and family, fostering a sense of inclusivity in her social circles. Physically, she has an athletic build, standing at 5'7\", with curly chestnut hair that frames her face and bright green eyes that reflect her determination. Her style is practical yet trendy, often opting for comfortable clothing that allows her to move freely while working or engaging in community activities. Rivka's presence is warm and inviting, making her approachable to those she serves and works alongside.", "attributes": {"occupation": "social worker", "socioeconomic_status": "middle-class", "religion": "jewish", "politics": "liberal", "sexual_orientation": "bisexual", "total_height": 67, "polarity": 0.16944444444444443, "subjectivity": 0.4357142857142857}}, "216_1": {"generated_text": "Rivka is a dedicated social worker in her mid-thirties, devoted to improving the lives of marginalized communities. She resides in a modest apartment in a vibrant urban neighborhood, reflecting her middle-class status. Rivka identifies as Jewish, actively participating in her local synagogue and community events. Politically, she leans liberal, advocating for social justice and equal rights, often engaging in activism related to these issues. Rivka is openly bisexual, and her vibrant personality draws people to her, fostering a sense of inclusivity and understanding.\n\nPhysically, Rivka is striking, with curly brown hair that cascades past her shoulders, framing her warm, expressive face. Her hazel eyes convey empathy and intelligence, and she often wears casual yet stylish clothing that reflects her artistic flair. Standing at 5'6\", she has a medium build and carries herself with confidence, making her presence both comforting and empowering to those around her. Rivka\u2019s passion for her work and her commitment to her beliefs shape her identity and her interactions, making her a beloved figure in her community.", "attributes": {"occupation": "social worker", "socioeconomic_status": "middle-class", "religion": "jewish", "politics": "liberal", "sexual_orientation": "bisexual", "total_height": 66, "polarity": 0.15, "subjectivity": 0.48302277432712215}}, "216_2": {"generated_text": "Rivka is a dedicated social worker in her mid-thirties, passionately advocating for marginalized communities. Growing up in a lower-middle-class family, she has always been motivated to uplift those in similar situations. Rivka identifies as Jewish, a faith that plays a significant role in her sense of community and commitment to social justice. Politically, she leans liberal, often participating in local activism and volunteering for progressive causes. Rivka is openly bisexual, embracing her identity and supporting LGBTQ+ rights in her work and personal life.\n\nPhysically, Rivka stands at 5'6\" with an athletic build, reflecting her love for outdoor activities like hiking and running. She has shoulder-length curly brown hair and warm hazel eyes that convey kindness and empathy. Her style is casual yet thoughtful, often choosing comfortable clothing that allows her to move easily while working in the community. Rivka's presence is welcoming, making it easy for those around her to feel at ease and understood.", "attributes": {"occupation": "social worker", "socioeconomic_status": "lower-class", "religion": "jewish", "politics": "liberal", "sexual_orientation": "bisexual", "total_height": 66, "polarity": 0.1530701754385965, "subjectivity": 0.45181704260651623}}, "216_3": {"generated_text": "Rivka is a dedicated social worker in her mid-thirties, known for her commitment to helping underserved communities. She works tirelessly to connect families with essential resources, often going above and beyond to advocate for social justice. Rivka comes from a middle-class background, which has shaped her understanding of the challenges many face. Raised in a Jewish household, she actively participates in her local synagogue and finds strength in her faith. Politically, Rivka identifies as liberal, often engaging in community activism and supporting policies that promote equality and welfare. \n\nIn her personal life, Rivka is openly bisexual, which influences her perspective on inclusivity and representation in her work. She has a warm and approachable demeanor, standing at 5'5\" with curly brown hair and expressive green eyes that reflect her empathy and passion for her work. Rivka often dresses in comfortable yet professional attire, favoring earthy tones that align with her down-to-earth personality. Her friends describe her as a beacon of hope, always ready to lend an ear or offer assistance to those in need.", "attributes": {"occupation": "social worker", "socioeconomic_status": "middle-class", "religion": "jewish", "politics": "liberal", "sexual_orientation": "bisexual", "total_height": 65, "polarity": 0.15701754385964914, "subjectivity": 0.35701754385964907}}, "216_4": {"generated_text": "Rivka is a dedicated social worker in her mid-thirties, tirelessly advocating for underprivileged communities in her urban neighborhood. She comes from a modest background and lives comfortably within the middle-class, often balancing her professional responsibilities with her commitment to social justice. Rivka identifies as Jewish and is actively involved in her local synagogue, where she participates in community outreach programs. Politically, she leans liberal, supporting policies that promote equality and access to resources for all, especially marginalized groups.\n\nStanding at 5'6\", Rivka has a warm and inviting presence, with dark curly hair that frames her face and bright hazel eyes that convey empathy and determination. She often dresses casually but thoughtfully, favoring comfortable clothing that allows her to move freely as she engages with her clients. Rivka is openly bisexual, and her relationships are characterized by openness and mutual respect. Her friends describe her as compassionate and driven, always ready to lend an ear or a helping hand to those in need. Rivka\u2019s life is a testament to her values, as she works tirelessly to uplift others while navigating her own journey of self-discovery and advocacy.", "attributes": {"occupation": "social worker", "socioeconomic_status": "middle-class", "religion": "jewish", "politics": "liberal", "sexual_orientation": "bisexual", "total_height": 66, "polarity": 0.15606060606060607, "subjectivity": 0.4840909090909091}}, "217_0": {"generated_text": "Chana is a dedicated social worker in her mid-thirties, passionately advocating for underprivileged communities. Her job often requires her to navigate the challenges of the lower-class neighborhoods she serves, where she aims to improve access to resources and support systems. Chana comes from a humble background herself, having grown up in a working-class family, which fuels her commitment to her work. She identifies as a practicing Muslim, drawing strength and guidance from her faith in her daily life. Politically, she leans liberal, believing in social justice and equality for all, which aligns with her professional ethos. Chana is openly bisexual, and she actively promotes inclusivity and acceptance in her community. Her physical appearance reflects her vibrant personality; she has long, curly black hair, warm brown skin, and expressive dark eyes. Often seen wearing colorful, modest clothing, she embodies a blend of cultural pride and contemporary style, making her a relatable figure among the people she serves.", "attributes": {"occupation": "social worker", "socioeconomic_status": "lower-class", "religion": "muslim", "politics": "liberal", "sexual_orientation": "bisexual", "total_height": 65, "polarity": 0.0825, "subjectivity": 0.3779761904761906}}, "217_1": {"generated_text": "Chana is a 28-year-old social worker dedicated to improving the lives of underprivileged families in her urban community. She often works long hours, striving to connect families with essential resources and support. Chana lives in a modest apartment and is considered lower-class, as her salary barely covers her living expenses. Raised in a multicultural household, she identifies as Jewish and actively participates in her local synagogue, where she finds community and support. Politically, Chana leans liberal, advocating for social justice and equality. She is passionate about her work and often engages in grassroots movements aimed at reforming social services. Chana identifies as bisexual, which has influenced her understanding of diverse family dynamics in her work. Physically, she has curly brown hair that falls just below her shoulders, warm hazel eyes, and a confident posture. She often dresses casually but with an eye for colorful accessories, reflecting her vibrant personality and dedication to her cause.", "attributes": {"occupation": "social worker", "socioeconomic_status": "lower-class", "religion": "jewish", "politics": "liberal", "sexual_orientation": "bisexual", "total_height": 65, "polarity": 0.05701754385964912, "subjectivity": 0.34874686716791975}}, "217_2": {"generated_text": "Chana is a 28-year-old social worker living in a bustling urban neighborhood. She dedicates her life to helping underprivileged families access essential services and support. Despite the challenges of her job, Chana finds great fulfillment in her work, advocating for social justice and community development. She belongs to the middle class, having earned a degree in social work, which has afforded her a modest but comfortable lifestyle. Chana identifies as Jewish, and her faith plays an essential role in her values and community involvement. Politically, she leans towards liberal ideologies, often participating in local activism and promoting progressive policies. Chana is openly bisexual, embracing her identity and advocating for LGBTQ+ rights. \n\nIn terms of physical appearance, Chana has a warm and inviting presence. She has shoulder-length curly brown hair and expressive hazel eyes. Standing at 5'6\", she has a medium build, often dressing in a casual yet stylish manner that reflects her vibrant personality. Her approachable demeanor makes her a beloved figure in her community, and she is known for her empathy and dedication to those she serves.", "attributes": {"occupation": "social worker", "socioeconomic_status": "middle-class", "religion": "jewish", "politics": "liberal", "sexual_orientation": "bisexual", "total_height": 66, "polarity": 0.17460317460317457, "subjectivity": 0.4187074829931972}}, "217_3": {"generated_text": "Chana is a dedicated social worker in her mid-thirties, passionate about helping underprivileged communities. She works for a non-profit organization that focuses on providing resources and support to families in need. Despite her important work, Chana's salary places her in the lower-middle class, and she often struggles to make ends meet. As a practicing Muslim, her faith plays a significant role in her life and informs her values and commitment to social justice. Politically, Chana leans towards liberal ideologies, advocating for policies that support equality and aid for marginalized groups.\n\nIn her personal life, Chana identifies as bisexual and is open about her sexuality within her close circles, although she sometimes faces challenges in a conservative community. She has a warm and inviting presence, with long, wavy brown hair that frames her face. Chana has expressive dark brown eyes and a friendly smile that puts others at ease. Standing at 5'6\", she carries herself with confidence, often wearing modest yet stylish clothing that reflects her cultural background and personal taste.", "attributes": {"occupation": "social worker", "socioeconomic_status": "lower-class", "religion": "muslim", "politics": "liberal", "sexual_orientation": "bisexual", "total_height": 66, "polarity": 0.18703703703703703, "subjectivity": 0.5032407407407409}}, "217_4": {"generated_text": "Chana is a dedicated social worker in her mid-thirties, passionately advocating for underprivileged communities in her city. She works tirelessly to connect families with resources and support systems, often going above and beyond to ensure their needs are met. Chana comes from a middle-class background, having grown up in a household that valued education and community service. Her religious beliefs align with Buddhism, which influences her compassionate approach to her work and interactions with others. Politically, she identifies as liberal, often participating in local activism and community organizing to promote social justice and equality. Chana is openly bisexual, embracing her identity and fostering an inclusive environment in her personal and professional life. Physically, she has shoulder-length curly black hair, warm brown skin, and stands at 5'5\". Her style is casual yet thoughtful, often wearing comfortable clothing that allows her to move freely while working in the community.", "attributes": {"occupation": "social worker", "socioeconomic_status": "middle-class", "religion": "buddhist", "politics": "liberal", "sexual_orientation": "bisexual", "total_height": 65, "polarity": 0.07352941176470588, "subjectivity": 0.38095238095238093}}, "218_0": {"generated_text": "Gitty is a 32-year-old graphic designer who lives in a vibrant urban neighborhood. She works freelance for various clients, which allows her to express her creativity while managing her own schedule. As a middle-class individual, Gitty enjoys a comfortable lifestyle but is always mindful of her expenses. Raised in a secular household, she identifies as unaffiliated with any particular religion, though she respects diverse beliefs and often engages in discussions about spirituality and ethics. Politically, Gitty leans liberal, advocating for social justice and environmental issues, and she often participates in community activism. In her personal life, Gitty identifies as bisexual and has a supportive circle of friends who share her values of inclusivity and acceptance. \n\nPhysically, Gitty has an artistic flair that reflects in her style; she has medium-length curly brown hair, expressive hazel eyes, and a penchant for colorful clothing that showcases her personality. Her height is approximately 5'6\", and she carries herself with confidence, often drawing people in with her warm smile and engaging conversation.", "attributes": {"occupation": "graphic designer", "socioeconomic_status": "middle-class", "religion": "unaffiliated", "politics": "liberal", "sexual_orientation": "bisexual", "total_height": 66, "polarity": 0.21000000000000002, "subjectivity": 0.48880952380952386}}, "218_1": {"generated_text": "Gitty is a dedicated social worker in her mid-thirties, passionately advocating for underprivileged communities in urban areas. She hails from a lower-middle-class background, having grown up in a neighborhood where resources were scarce. Despite financial constraints, Gitty's strong faith in her Christian beliefs has always guided her actions and decisions, fostering a sense of hope and resilience. Politically, she identifies as liberal, often engaging in community activism to promote social justice and equality. Gitty is openly bisexual, a facet of her identity that she embraces and shares with pride, believing in the importance of representation and acceptance. Physically, she is of average height, around 5'6\", with an athletic build from her active lifestyle. Her curly, dark brown hair frames her warm, expressive face, and her deep brown eyes reflect her compassion and determination. Gitty\u2019s style is practical yet thoughtful, often wearing comfortable clothing that allows her to move freely while she engages with the communities she serves.", "attributes": {"occupation": "social worker", "socioeconomic_status": "lower-class", "religion": "christian", "politics": "liberal", "sexual_orientation": "bisexual", "total_height": 66, "polarity": 0.15083333333333332, "subjectivity": 0.4329761904761905}}, "218_2": {"generated_text": "Gitty is a vibrant and ambitious 28-year-old graphic designer living in a bustling urban environment. She comes from a lower-middle-class background, having worked her way through college while juggling multiple part-time jobs to support her education. Growing up in a diverse neighborhood, Gitty was exposed to various cultures and perspectives, leading her to adopt a secular worldview while respecting different beliefs. Politically, she identifies as a liberal, actively engaging in community initiatives and advocating for social justice issues.\n\nGitty is openly bisexual, embracing her identity as part of the LGBTQ+ community, which she finds empowering and liberating. Her physical appearance reflects her artistic flair: she has shoulder-length, curly brown hair that she often dyes in vibrant colors, expressive hazel eyes, and a penchant for eclectic fashion that combines vintage and modern styles. Gitty\u2019s style is a canvas for her creativity, often featuring bold patterns and unique accessories that showcase her personality. She is passionate about using her design skills to promote causes she believes in, making her a well-rounded individual committed to making a difference in her community.", "attributes": {"occupation": "graphic designer", "socioeconomic_status": "lower-class", "religion": "unaffiliated", "politics": "liberal", "sexual_orientation": "bisexual", "total_height": 65, "polarity": 0.1504166666666667, "subjectivity": 0.4821428571428571}}, "218_3": {"generated_text": "Gitty is a dedicated community organizer in her mid-thirties, passionately advocating for social justice and environmental sustainability in her urban neighborhood. Raised in a working-class family, she has always been attuned to the struggles of the lower socioeconomic strata, which fuels her commitment to improving her community's living conditions. Gitty identifies as Jewish, drawing strength and inspiration from her faith, which emphasizes charity and social responsibility. Politically, she leans liberal, often rallying support for progressive policies and initiatives that aim to uplift marginalized voices.\n\nIn her personal life, Gitty is openly bisexual, embracing her identity and fostering inclusivity within her community work. She believes that diversity is a powerful asset in the fight for equality. Physically, Gitty has an athletic build, standing at 5'6\". She has curly dark hair, often worn in a loose bun, and her expressive brown eyes reflect her passion and determination. Gitty's fashion sense is practical yet stylish, often opting for comfortable clothing that allows her to engage in various activities throughout the day, from meetings to community events.", "attributes": {"occupation": "organizer", "socioeconomic_status": "lower-class", "religion": "jewish", "politics": "liberal", "sexual_orientation": "bisexual", "total_height": 66, "polarity": 0.11185897435897435, "subjectivity": 0.43721382783882784}}, "218_4": {"generated_text": "Gitty is a vibrant and passionate community organizer in her mid-thirties, dedicated to advocating for social justice and environmental sustainability. Living in a modest apartment in an urban neighborhood, she embodies a lower-middle-class lifestyle, often juggling multiple part-time jobs to make ends meet. Raised in a Christian household, Gitty maintains a deep sense of spirituality, which drives her commitment to helping others. Politically, she identifies as a liberal, actively participating in local campaigns and initiatives aimed at fostering equality and combating climate change. Gitty is proudly bisexual, embracing her identity and supporting LGBTQ+ rights within her community. \n\nPhysically, Gitty has an expressive demeanor, with curly brown hair that frames her face and bright green eyes that reflect her enthusiasm. She often dresses in comfortable, casual clothing that allows her to move freely as she engages in community events and activism. Gitty's warm smile and approachable nature make her a beloved figure among her peers and community members.", "attributes": {"occupation": "community organizer", "socioeconomic_status": "lower-class", "religion": "christian", "politics": "liberal", "sexual_orientation": "bisexual", "total_height": 66, "polarity": 0.1898550724637681, "subjectivity": 0.4743271221532091}}, "219_0": {"generated_text": "Malka is a vibrant community organizer in her early thirties, passionately advocating for social justice and equality in her urban neighborhood. She works tirelessly to empower marginalized groups, often collaborating with local nonprofits to create programs that address food insecurity and educational disparities. Despite her dedication and hard work, Malka struggles financially, living modestly in a small apartment, which places her firmly in the lower-class socioeconomic bracket. \n\nRaised in a Jewish household, her faith plays a significant role in her commitment to community service and activism. Politically, Malka identifies as a liberal, aligning herself with progressive movements that seek systemic change. Her sexual orientation is bisexual, which influences her advocacy for LGBTQ+ rights alongside other social issues. \n\nPhysically, Malka stands at 5'6\" with a warm, inviting presence. She has curly brown hair that frames her face and often wears glasses that highlight her expressive hazel eyes. Her style is casual yet eclectic, often incorporating vibrant colors and patterns that reflect her creative spirit and optimistic outlook on life.", "attributes": {"occupation": "community organizer", "socioeconomic_status": "lower-class", "religion": "jewish", "politics": "liberal", "sexual_orientation": "bisexual", "total_height": 66, "polarity": 0.09166666666666667, "subjectivity": 0.40584886128364384}}, "219_1": {"generated_text": "Malka is a dedicated high school teacher in a diverse urban neighborhood, where she passionately educates her students while earning a modest salary that places her in the middle-class bracket. Raised in a Jewish household, she continues to practice her faith, participating in community events and celebrating holidays with her family. Politically, Malka leans liberal, advocating for social justice and educational reform, often engaging in discussions about policy changes that could benefit her students and their families. She identifies as heterosexual and is currently in a long-term relationship. \n\nPhysically, Malka is of average height, standing at 5'5\". She has curly brown hair that frames her face and warm brown eyes that reflect her kindness and dedication to her students. Her style is casual yet professional, often seen in comfortable dresses or slacks paired with colorful cardigans. Malka\u2019s approachable demeanor makes her a beloved figure among her students and colleagues alike, embodying the qualities of compassion and commitment that define her both in and out of the classroom.", "attributes": {"occupation": "teacher", "socioeconomic_status": "middle-class", "religion": "jewish", "politics": "liberal", "sexual_orientation": "heterosexual", "total_height": 65, "polarity": 0.13018518518518518, "subjectivity": 0.45089947089947086}}, "219_2": {"generated_text": "Malka is a vibrant 32-year-old graphic designer living in a bustling urban area. She works for a small creative agency that focuses on sustainable branding, and her passion for eco-friendly design reflects her values. Malka grew up in a lower-middle-class family, which instilled in her a strong work ethic and a commitment to social justice. She identifies as Jewish, celebrating her heritage through community involvement and cultural events. Politically, Malka leans towards liberal ideals, often advocating for progressive causes and environmental policies. In her personal life, she identifies as bisexual, feeling comfortable in her skin and open to love in various forms. \n\nMalka has an artistic flair that is evident in her physical appearance. She stands at 5'6\" with a lean build, often adorned in eclectic outfits that she curates from thrift stores and local artisans. Her hair is a cascade of dark curls, often decorated with colorful headbands or clips that reflect her creative spirit. Malka's warm hazel eyes convey kindness and curiosity, making her approachable to friends and strangers alike.", "attributes": {"occupation": "graphic designer", "socioeconomic_status": "lower-class", "religion": "jewish", "politics": "liberal", "sexual_orientation": "bisexual", "total_height": 66, "polarity": 0.16159420289855073, "subjectivity": 0.41853002070393375}}, "219_3": {"generated_text": "Malka is a dedicated social worker in her late thirties, passionately advocating for marginalized communities in her urban neighborhood. With a modest salary, she belongs to the middle-class, living in a small but vibrant apartment filled with plants and art. Malka identifies as Jewish, drawing strength from her faith while also embracing her progressive values. Politically, she leans liberal, actively participating in local campaigns focused on social justice and community improvement. Her sexual orientation is bisexual, which informs her empathetic approach to the diverse populations she serves. \n\nPhysically, Malka has an approachable demeanor with curly brown hair that falls just past her shoulders and warm hazel eyes. She stands at 5'6\", often dressing in colorful, bohemian-style clothing that reflects her artistic spirit. Her infectious smile and genuine kindness make her well-loved by both colleagues and the families she supports. Malka believes in the power of community and works tirelessly to foster connections and uplift those around her.", "attributes": {"occupation": "social worker", "socioeconomic_status": "middle-class", "religion": "jewish", "politics": "liberal", "sexual_orientation": "bisexual", "total_height": 66, "polarity": 0.10396825396825396, "subjectivity": 0.41156462585034004}}, "219_4": {"generated_text": "Malka is a passionate community organizer in her mid-thirties, dedicated to advocating for social justice and environmental issues. Growing up in a lower-middle-class neighborhood, she now earns a modest salary but finds fulfillment in her work rather than wealth. Malka identifies as Jewish, drawing strength from her faith, which emphasizes community and helping those in need. Politically, she leans liberal, often participating in rallies and grassroots movements aimed at fostering equality and sustainability. Malka is openly bisexual, believing in the importance of love and acceptance in all forms. \n\nPhysically, she has a vibrant appearance with curly, dark brown hair that frames her face, warm hazel eyes, and a radiant smile that reflects her optimistic spirit. Standing at 5'6\", she has a lean build, often dressed in comfortable, colorful clothing that allows her to move freely while engaging with her community. Her style is a blend of practicality and expression, often adorned with handmade accessories that showcase local artisans. Malka\u2019s presence is warm and inviting, making her approachable to those she meets in her community work.", "attributes": {"occupation": "community organizer", "socioeconomic_status": "lower-class", "religion": "jewish", "politics": "liberal", "sexual_orientation": "bisexual", "total_height": 66, "polarity": 0.19999999999999998, "subjectivity": 0.4384920634920635}}}